{
  "type": "Feature",
  "properties": {
    "iso:country":"GB",
    "sg:address":"Oakley Road",
    "sg:city":"Rushden",
    "sg:classifiers":[
        {
            "category":"Education",
            "subcategory":"Library",
            "type":"Public Place"
        }
    ],
    "sg:phone":"+44 1933 353226",
    "sg:postcode":"NN10 9XA",
    "sg:province":"Bedfordshire",
    "sg:tags":[
        "reproduction",
        "furniture"
    ],
    "wof:name":"G B D Reproduction Furniture Ltd.",
    "wof:placetype":"venue"
},
  "geometry": {"coordinates":[-0.6100940108,52.2940444946],"type":"Point"}
}