{
  "type": "Feature",
  "properties": {
    "iso:country":"GB",
    "sg:address":"Cooksland House, Seighford",
    "sg:city":"Stafford",
    "sg:classifiers":[
        {
            "category":"Farming",
            "subcategory":"Farm",
            "type":"Manufacturing & Wholesale Goods"
        }
    ],
    "sg:phone":"+44 1785 282248",
    "sg:postcode":"ST18 9PP",
    "sg:province":"Staffordshire",
    "sg:tags":[
        "mixed",
        "crop"
    ],
    "wof:name":"Major Richard C Eld",
    "wof:placetype":"venue"
},
  "geometry": {"coordinates":[-2.164635,52.816013],"type":"Point"}
}