{
  "type": "Feature",
  "properties": {
    "iso:country":"GB",
    "sg:address":"5 Metcalf Close, Sweet Briar Industrial Estate",
    "sg:city":"Norwich",
    "sg:classifiers":[
        {
            "category":"Building & Trades",
            "subcategory":"Construction",
            "type":"Services"
        }
    ],
    "sg:phone":"+44 1603 417472",
    "sg:postcode":"NR3 2BP",
    "sg:province":"Norfolk",
    "sg:tags":[
        "contractor",
        "pool",
        "swimming"
    ],
    "wof:name":"Newson Swimming Pools",
    "wof:placetype":"venue"
},
  "geometry": {"coordinates":[1.2635920048,52.6453361511],"type":"Point"}
}