{
  "type": "Feature",
  "properties": {
    "iso:country":"GB",
    "sg:address":"22 Buchan St",
    "sg:city":"Macduff",
    "sg:classifiers":[
        {
            "category":"Military Area",
            "subcategory":"Air Force Base",
            "type":"Public Place"
        }
    ],
    "sg:postcode":"AB44 1TD",
    "sg:province":"Aberdeenshire",
    "sg:tags":[
        "taxi",
        "hire",
        "private"
    ],
    "wof:name":"Learmonth,Alan,",
    "wof:placetype":"venue"
},
  "geometry": {"coordinates":[-2.488086,57.669991],"type":"Point"}
}