{
  "type": "Feature",
  "properties": {
    "addr:full":"234-236 Werrington Road Stoke-on-trent Staffordshire ST2 9AW",
    "addr:postcode":"234-236;st2 9aw",
    "addr:street":"Werrington Road",
    "iso:country":"GB",
    "sg:address":"234-236 Werrington Road",
    "sg:city":"Stoke-on-trent",
    "sg:classifiers":[
        {
            "category":"Fast Food",
            "type":"Food & Drink"
        }
    ],
    "sg:phone":"+44 1782 206282",
    "sg:postcode":"ST2 9AW",
    "sg:province":"Staffordshire",
    "sg:tags":[
        "away",
        "take"
    ],
    "wof:name":"Bucknall Fish Bar & Kebab House",
    "wof:placetype":"venue"
},
  "geometry": {"coordinates":[-2.1403989792,53.0253257751],"type":"Point"}
}