{
  "type": "Feature",
  "properties": {
    "iso:country":"GB",
    "sg:address":"Unit 4 Chiltern Business Centre, Garsington Rd",
    "sg:city":"Oxford",
    "sg:classifiers":[
        {
            "category":"Autos & Motor Vehicles",
            "subcategory":"Auto Supplies",
            "type":"Retail Goods"
        }
    ],
    "sg:postcode":"OX4 6NG",
    "sg:province":"Oxfordshire",
    "sg:tags":[
        "windscreen"
    ],
    "wof:name":"Autoglass Ltd",
    "wof:placetype":"venue"
},
  "geometry": {"coordinates":[-1.20956,51.733559],"type":"Point"}
}