{
  "type": "Feature",
  "properties": {
    "iso:country":"GB",
    "sg:address":"St Lukes Road",
    "sg:city":"Torquay",
    "sg:classifiers":[
        {
            "category":"Professional",
            "subcategory":"Testing Lab",
            "type":"Services"
        }
    ],
    "sg:postcode":"TQ2 5NX",
    "sg:province":"Devon",
    "sg:tags":[
        "mot"
    ],
    "wof:name":"St Lukes Motors",
    "wof:placetype":"venue"
},
  "geometry": {"coordinates":[-3.5329289436,50.4663696289],"type":"Point"}
}