{
  "type": "Feature",
  "properties": {
    "addr:full":"Cherry Tree Farm, Northampton Lane, Dunchurch Rugby Warwickshire CV22 6QJ",
    "addr:postcode":"cv22 6qj",
    "addr:street":"Northampton Lane",
    "iso:country":"GB",
    "sg:address":"Cherry Tree Farm, Northampton Lane, Dunchurch",
    "sg:city":"Rugby",
    "sg:classifiers":[
        {
            "category":"Farming",
            "subcategory":"Livestock Farm",
            "type":"Manufacturing & Wholesale Goods"
        }
    ],
    "sg:phone":"+44 1788 817863",
    "sg:postcode":"CV22 6QJ",
    "sg:province":"Warwickshire",
    "sg:tags":[
        "others"
    ],
    "wof:name":"R Carlton",
    "wof:placetype":"venue"
},
  "geometry": {"coordinates":[-1.290391,52.336746],"type":"Point"}
}