{
  "type": "Feature",
  "properties": {
    "addr:full":"3 The Drive Hove East Sussex BN3 3JE",
    "addr:housenumber":"3",
    "addr:postcode":"bn3 3je",
    "addr:street":"The Drive",
    "iso:country":"GB",
    "sg:address":"3 The Drive",
    "sg:city":"Hove",
    "sg:classifiers":[
        {
            "category":"Professional",
            "subcategory":"Lawyer & Legal Services",
            "type":"Services"
        }
    ],
    "sg:phone":"+44 1273 747470",
    "sg:postcode":"BN3 3JE",
    "sg:province":"East Sussex",
    "sg:tags":[
        "solicitor"
    ],
    "wof:name":"Pitcher Mills",
    "wof:placetype":"venue"
},
  "geometry": {"coordinates":[-0.1681150049,50.8278274536],"type":"Point"}
}