{
  "type": "Feature",
  "properties": {
    "iso:country":"GB",
    "sg:address":"Gerston Business Park, Greyfriars Lane, Storrington",
    "sg:city":"Pulborough",
    "sg:classifiers":[
        {
            "category":"Retail",
            "subcategory":"Auto Repair",
            "type":"Services"
        }
    ],
    "sg:phone":"+44 1903 741388",
    "sg:postcode":"RH20 4HE",
    "sg:province":"West Sussex",
    "sg:tags":[
        "body",
        "car"
    ],
    "wof:name":"A R C",
    "wof:placetype":"venue"
},
  "geometry": {"coordinates":[-0.4538590014,50.9178009033],"type":"Point"}
}