{
  "type": "Feature",
  "properties": {
    "iso:country":"GB",
    "sg:address":"70-78 The Broadway",
    "sg:city":"Colindale",
    "sg:classifiers":[
        {
            "category":"Professional",
            "subcategory":"Business Services",
            "type":"Services"
        }
    ],
    "sg:phone":"+44 20 8202 3787",
    "sg:postcode":"NW9 7BT",
    "sg:province":"Greater London",
    "sg:tags":[
        "accomodation"
    ],
    "wof:name":"Sutherland House",
    "wof:placetype":"venue"
},
  "geometry": {"coordinates":[-0.244924,51.615692],"type":"Point"}
}