{
  "type": "Feature",
  "properties": {
    "addr:full":"28 Cedar Close Walton-on-the-naze Essex CO14 8NJ",
    "addr:housenumber":"28",
    "addr:postcode":"co14 8nj",
    "addr:street":"Cedar Close",
    "iso:country":"GB",
    "sg:address":"28 Cedar Close",
    "sg:city":"Walton-on-the-naze",
    "sg:classifiers":[
        {
            "category":"Military Area",
            "subcategory":"Air Force Base",
            "type":"Public Place"
        }
    ],
    "sg:postcode":"CO14 8NJ",
    "sg:province":"Essex",
    "sg:tags":[
        "taxi",
        "hire",
        "private"
    ],
    "wof:name":"Keith Long",
    "wof:placetype":"venue"
},
  "geometry": {"coordinates":[1.2540899515,51.8432273865],"type":"Point"}
}