{
  "type": "Feature",
  "properties": {
    "addr:full":"37 Mansfield Road Sheffield Derbyshire S12 2AG",
    "addr:housenumber":"37",
    "addr:postcode":"s12 2ag",
    "addr:street":"Mansfield Road",
    "iso:country":"GB",
    "sg:address":"37 Mansfield Road",
    "sg:city":"Sheffield",
    "sg:classifiers":[
        {
            "category":"Personal",
            "subcategory":"Beauty Salon",
            "type":"Services"
        },
        {
            "category":"Personal",
            "subcategory":"Barber",
            "type":"Services"
        }
    ],
    "sg:phone":"+44 114 239 0966",
    "sg:postcode":"S12 2AG",
    "sg:province":"Derbyshire",
    "sg:tags":[
        "unisex",
        "hairdresser"
    ],
    "wof:name":"Hot Locks",
    "wof:placetype":"venue"
},
  "geometry": {"coordinates":[-1.4205470085,53.3588371277],"type":"Point"}
}