{
  "type": "Feature",
  "properties": {
    "addr:full":"Unit 2, Jackson Pl, Wilton Rd Indstl Est, Humberston Grimsby Lincolnshire DN36 4AS",
    "addr:housenumber":"unit 2",
    "addr:postcode":"dn36 4as",
    "addr:street":"Jackson Pl Wilton Rd",
    "iso:country":"GB",
    "sg:address":"Unit 2, Jackson Pl, Wilton Rd Indstl Est, Humberston",
    "sg:city":"Grimsby",
    "sg:classifiers":[
        {
            "category":"Manufacturing",
            "subcategory":"Electronics",
            "type":"Manufacturing & Wholesale Goods"
        }
    ],
    "sg:postcode":"DN36 4AS",
    "sg:province":"Lincolnshire",
    "sg:tags":[
        "control",
        "component",
        "-",
        "electronic"
    ],
    "wof:name":"Research Incorporation Ltd",
    "wof:placetype":"venue"
},
  "geometry": {"coordinates":[-0.0431240015,53.5349121094],"type":"Point"}
}