{
  "type": "Feature",
  "properties": {
    "addr:full":"10 Styles Way Beckenham Kent BR3 3AJ",
    "addr:housenumber":"10",
    "addr:postcode":"br3 3aj",
    "addr:street":"Styles Way",
    "iso:country":"GB",
    "sg:address":"10 Styles Way",
    "sg:city":"Beckenham",
    "sg:classifiers":[
        {
            "category":"Building & Trades",
            "subcategory":"Plumbing",
            "type":"Services"
        }
    ],
    "sg:postcode":"BR3 3AJ",
    "sg:province":"Kent",
    "sg:tags":[
        "heating"
    ],
    "wof:name":"1A Abbey Plumbing",
    "wof:placetype":"venue"
},
  "geometry": {"coordinates":[-0.012559,51.394756],"type":"Point"}
}