{
  "type": "Feature",
  "properties": {
    "iso:country":"GB",
    "sg:address":"Burghley House, Stable Block",
    "sg:city":"Stamford",
    "sg:classifiers":[
        {
            "category":"Professional",
            "subcategory":"Art Services",
            "type":"Services"
        }
    ],
    "sg:phone":"+44 1780 762155",
    "sg:postcode":"PE9 3JY",
    "sg:province":"Cambridgeshire",
    "sg:tags":[
        "picture",
        "restoration",
        "cleaning"
    ],
    "wof:name":"Burghley Fine Art Conservation Ltd.",
    "wof:placetype":"venue"
},
  "geometry": {"coordinates":[-0.4802899957,52.6520843506],"type":"Point"}
}