{
  "type": "Feature",
  "properties": {
    "addr:full":"3 Lambolle Place London Greater London NW3 4PD",
    "addr:housenumber":"3",
    "addr:postcode":"nw3 4pd",
    "addr:street":"Lambolle Place",
    "iso:country":"GB",
    "sg:address":"3 Lambolle Place",
    "sg:city":"London",
    "sg:classifiers":[
        {
            "category":"Retail",
            "subcategory":"Auto Repair",
            "type":"Services"
        }
    ],
    "sg:phone":"+44 20 7435 2541",
    "sg:postcode":"NW3 4PD",
    "sg:province":"Greater London",
    "sg:tags":[
        "engine",
        "car",
        "specialist"
    ],
    "wof:name":"Belsize Motors",
    "wof:placetype":"venue"
},
  "geometry": {"coordinates":[-0.165544,51.545868],"type":"Point"}
}