{
  "type": "Feature",
  "properties": {
    "addr:full":"42 Kenneth Street Inverness Highland IV3 5DH",
    "addr:housenumber":"42",
    "addr:postcode":"iv3 5dh",
    "addr:street":"Kenneth Street",
    "iso:country":"GB",
    "sg:address":"42 Kenneth Street",
    "sg:city":"Inverness",
    "sg:classifiers":[
        {
            "category":"Professional",
            "subcategory":"Lawyer & Legal Services",
            "type":"Services"
        },
        {
            "category":"Organizations",
            "subcategory":"Community Association",
            "type":"Services"
        }
    ],
    "sg:phone":"+44 1224 643174",
    "sg:postcode":"IV3 5DH",
    "sg:province":"Highland",
    "sg:tags":[
        "associations",
        "counselling",
        "advice",
        "co-operatives",
        "trust",
        "housing",
        "societies"
    ],
    "wof:name":"MARRIAGE CARE",
    "wof:placetype":"venue"
},
  "geometry": {"coordinates":[-4.2323851585,57.4772262573],"type":"Point"}
}