{
  "type": "Feature",
  "properties": {
    "addr:full":"34 Warkworth Avenue Whitley Bay Northumberland NE26 3PS",
    "addr:housenumber":"34",
    "addr:postcode":"ne26 3ps",
    "addr:street":"Warkworth Avenue",
    "iso:country":"GB",
    "sg:address":"34 Warkworth Avenue",
    "sg:city":"Whitley Bay",
    "sg:classifiers":[
        {
            "category":"Professional",
            "subcategory":"Detective & Security Services",
            "type":"Services"
        }
    ],
    "sg:phone":"+44 191 291 3080",
    "sg:postcode":"NE26 3PS",
    "sg:province":"Northumberland",
    "sg:tags":[
        "car"
    ],
    "wof:name":"Car Pro Security",
    "wof:placetype":"venue"
},
  "geometry": {"coordinates":[-1.4521739483,55.0447235107],"type":"Point"}
}