{
  "type": "Feature",
  "properties": {
    "iso:country":"GB",
    "sg:address":"16 Allen Street",
    "sg:city":"Chester-le-street",
    "sg:classifiers":[
        {
            "category":"Professional",
            "subcategory":"Printing & Photocopies",
            "type":"Services"
        }
    ],
    "sg:phone":"+44 191 387 4184",
    "sg:postcode":"DH3 3JG",
    "sg:province":"Durham",
    "sg:tags":[
        "computer",
        "tag",
        "label"
    ],
    "wof:name":"Lettering Systems Unlimited",
    "wof:placetype":"venue"
},
  "geometry": {"coordinates":[-1.575838,54.849785],"type":"Point"}
}