{
  "type": "Feature",
  "properties": {
    "iso:country":"GB",
    "sg:address":"54 Granada Rd",
    "sg:city":"Southsea",
    "sg:classifiers":[
        {
            "category":"Travel",
            "subcategory":"Hotels & Motels",
            "type":"Entertainment"
        }
    ],
    "sg:postcode":"PO4 0RJ",
    "sg:province":"Hampshire",
    "wof:name":"Austin,Raymond,",
    "wof:placetype":"venue"
},
  "geometry": {"coordinates":[-1.075038,50.780643],"type":"Point"}
}