{
  "type": "Feature",
  "properties": {
    "addr:full":"41 High Street Halstead Essex CO9 2AA",
    "addr:housenumber":"41",
    "addr:postcode":"co9 2aa",
    "addr:street":"High Street",
    "iso:country":"GB",
    "sg:address":"41 High Street",
    "sg:city":"Halstead",
    "sg:classifiers":[
        {
            "category":"Food & Beverages",
            "subcategory":"Specialty",
            "type":"Retail Goods"
        },
        {
            "category":"Food & Beverages",
            "subcategory":"Supermarket",
            "type":"Retail Goods"
        }
    ],
    "sg:phone":"+44 1787 478513",
    "sg:postcode":"CO9 2AA",
    "sg:province":"Essex",
    "sg:tags":[
        "product",
        "health"
    ],
    "wof:name":"Pilgrims Natural",
    "wof:placetype":"venue"
},
  "geometry": {"coordinates":[0.637134,51.944584],"type":"Point"}
}