{
  "type": "Feature",
  "properties": {
    "addr:full":"36 Wallsend Road North Shields Tyne and Wear NE29 7BJ",
    "addr:housenumber":"36",
    "addr:postcode":"ne29 7bj",
    "addr:street":"Wallsend Road",
    "iso:country":"GB",
    "sg:address":"36 Wallsend Road",
    "sg:city":"North Shields",
    "sg:classifiers":[
        {
            "category":"Shopping",
            "subcategory":"Pharmacy",
            "type":"Retail Goods"
        }
    ],
    "sg:phone":"+44 191 257 2566",
    "sg:postcode":"NE29 7BJ",
    "sg:province":"Tyne and Wear",
    "sg:tags":[
        "pharmacist",
        "chemist"
    ],
    "wof:name":"Beldon Chemists",
    "wof:placetype":"venue"
},
  "geometry": {"coordinates":[-1.4690010548,55.0058097839],"type":"Point"}
}