{
  "type": "Feature",
  "properties": {
    "iso:country":"GB",
    "sg:address":"8 Durweston Street",
    "sg:city":"London",
    "sg:classifiers":[
        {
            "category":"Organizations",
            "subcategory":"Membership Organization",
            "type":"Services"
        }
    ],
    "sg:postcode":"W1H 1PH",
    "sg:province":"Greater London",
    "sg:tags":[
        "club"
    ],
    "wof:name":"Willifield Managements Limited",
    "wof:placetype":"venue"
},
  "geometry": {"coordinates":[-0.159898,51.520317],"type":"Point"}
}