{
  "type": "Feature",
  "properties": {
    "iso:country":"GB",
    "sg:address":"1 South Parade, High Street, Merstham",
    "sg:city":"Redhill",
    "sg:classifiers":[
        {
            "category":"Shopping",
            "subcategory":"News",
            "type":"Retail Goods"
        }
    ],
    "sg:phone":"+44 1737 643824",
    "sg:postcode":"RH1 3AZ",
    "sg:province":"Surrey",
    "sg:tags":[
        "newsagent"
    ],
    "wof:name":"Ronald & Gillian Styles",
    "wof:placetype":"venue"
},
  "geometry": {"coordinates":[-0.152545,51.264359],"type":"Point"}
}