{
  "type": "Feature",
  "properties": {
    "iso:country":"GB",
    "sg:address":"Henblas Street",
    "sg:city":"Wrexham",
    "sg:classifiers":[
        {
            "category":"Organizations",
            "subcategory":"Membership Organization",
            "type":"Services"
        }
    ],
    "sg:phone":"+44 1978 350171",
    "sg:postcode":"LL13 8AD",
    "sg:province":"Wrexham",
    "sg:tags":[
        "club"
    ],
    "wof:name":"Wrexham Snooker Club",
    "wof:placetype":"venue"
},
  "geometry": {"coordinates":[-2.991863966,53.0457954407],"type":"Point"}
}