{
  "type": "Feature",
  "properties": {
    "addr:full":"180 King St Castle Douglas Dumfries and Galloway DG7 1DA",
    "addr:housenumber":"180",
    "addr:postcode":"dg7 1da",
    "addr:street":"King St",
    "iso:country":"GB",
    "sg:address":"180 King St",
    "sg:city":"Castle Douglas",
    "sg:classifiers":[
        {
            "category":"Personal",
            "subcategory":"Beauty Salon",
            "type":"Services"
        }
    ],
    "sg:phone":"+44 1556 502154",
    "sg:postcode":"DG7 1DA",
    "sg:province":"Dumfries and Galloway",
    "sg:tags":[
        "unisex",
        "hairdresser"
    ],
    "wof:name":"Dorothy's Hairdressers",
    "wof:placetype":"venue"
},
  "geometry": {"coordinates":[-3.9315509796,54.9396896362],"type":"Point"}
}