{
  "type": "Feature",
  "properties": {
    "addr:full":"41a Whitworth Road Rochdale Lancashire OL12 0RA",
    "addr:housenumber":"41a",
    "addr:postcode":"ol12 0ra",
    "addr:street":"Whitworth Road",
    "iso:country":"GB",
    "sg:address":"41a Whitworth Road",
    "sg:city":"Rochdale",
    "sg:classifiers":[
        {
            "category":"Fast Food",
            "type":"Food & Drink"
        }
    ],
    "sg:postcode":"OL12 0RA",
    "sg:province":"Lancashire",
    "sg:tags":[
        "away",
        "take"
    ],
    "wof:name":"Raj Mahal",
    "wof:placetype":"venue"
},
  "geometry": {"coordinates":[-2.155688,53.622894],"type":"Point"}
}