{
  "type": "Feature",
  "properties": {
    "addr:full":"132 Sandhurst Road, Edmonton London Greater London N9 8BG",
    "addr:housenumber":"132",
    "addr:postcode":"n9 8bg",
    "addr:street":"Sandhurst Road Edmonton",
    "iso:country":"GB",
    "sg:address":"132 Sandhurst Road, Edmonton",
    "sg:city":"London",
    "sg:classifiers":[
        {
            "category":"Professional",
            "subcategory":"Management & Consulting",
            "type":"Services"
        }
    ],
    "sg:postcode":"N9 8BG",
    "sg:province":"Greater London",
    "sg:tags":[
        "consultant",
        "business"
    ],
    "wof:name":"Sandhurst Consultants Ltd",
    "wof:placetype":"venue"
},
  "geometry": {"coordinates":[-0.041385,51.638454],"type":"Point"}
}