{
  "type": "Feature",
  "properties": {
    "addr:full":"164 London Road North Lowestoft Suffolk NR32 1HB",
    "addr:housenumber":"164",
    "addr:postcode":"nr32 1hb",
    "addr:street":"London Road North",
    "iso:country":"GB",
    "sg:address":"164 London Road North",
    "sg:city":"Lowestoft",
    "sg:classifiers":[
        {
            "category":"Shopping",
            "subcategory":"Clothing, Apparel, & Fashions",
            "type":"Retail Goods"
        }
    ],
    "sg:phone":"+44 1502 582584",
    "sg:postcode":"NR32 1HB",
    "sg:province":"Suffolk",
    "sg:tags":[
        "menswear"
    ],
    "wof:name":"Sawdust Clothing",
    "wof:placetype":"venue"
},
  "geometry": {"coordinates":[1.7547739744,52.478263855],"type":"Point"}
}