{
  "type": "Feature",
  "properties": {
    "addr:full":"Chelford Rd, Henbury Macclesfield Cheshire SK11 9PG",
    "addr:postcode":"sk11 9pg",
    "addr:street":"Chelford Rd",
    "iso:country":"GB",
    "sg:address":"Chelford Rd, Henbury",
    "sg:city":"Macclesfield",
    "sg:classifiers":[
        {
            "category":"Arts & Performance",
            "subcategory":"Art Gallery",
            "type":"Entertainment"
        }
    ],
    "sg:phone":"+44 1625 425392",
    "sg:postcode":"SK11 9PG",
    "sg:province":"Cheshire",
    "wof:name":"Geldart Galleries",
    "wof:placetype":"venue"
},
  "geometry": {"coordinates":[-2.2840850353,53.271270752],"type":"Point"}
}