{
  "type": "Feature",
  "properties": {
    "addr:full":"Saxon House, 44-52 Oxford Road Reading Berkshire RG1 7LA",
    "addr:housenumber":"44-52",
    "addr:postcode":"rg1 7la",
    "addr:street":"Oxford Road",
    "iso:country":"GB",
    "sg:address":"Saxon House, 44-52 Oxford Road",
    "sg:city":"Reading",
    "sg:classifiers":[
        {
            "category":"Home & Garden",
            "subcategory":"Furniture",
            "type":"Retail Goods"
        }
    ],
    "sg:phone":"+44 118 958 1356",
    "sg:postcode":"RG1 7LA",
    "sg:province":"Berkshire",
    "wof:name":"Beadle & Crome (Reading) Ltd.",
    "wof:placetype":"venue"
},
  "geometry": {"coordinates":[-0.9773880243,51.4553833008],"type":"Point"}
}