{
  "type": "Feature",
  "properties": {
    "addr:full":"103 Avelon Road Rainham Essex RM13 7DJ",
    "addr:housenumber":"103",
    "addr:postcode":"rm13 7dj",
    "addr:street":"Avelon Road",
    "iso:country":"GB",
    "sg:address":"103 Avelon Road",
    "sg:city":"Rainham",
    "sg:classifiers":[
        {
            "category":"Building & Trades",
            "subcategory":"Construction",
            "type":"Services"
        }
    ],
    "sg:postcode":"RM13 7DJ",
    "sg:province":"Essex",
    "sg:tags":[
        "builder"
    ],
    "wof:name":"L Lunesi",
    "wof:placetype":"venue"
},
  "geometry": {"coordinates":[0.1981939971,51.5345916748],"type":"Point"}
}