{
  "type": "Feature",
  "properties": {
    "addr:full":"27 Longedge Lane, Wingerworth Chesterfield Derbyshire S42 6PB",
    "addr:housenumber":"27",
    "addr:postcode":"s42 6pb",
    "addr:street":"Longedge Lane",
    "iso:country":"GB",
    "sg:address":"27 Longedge Lane, Wingerworth",
    "sg:city":"Chesterfield",
    "sg:classifiers":[
        {
            "category":"Organizations",
            "subcategory":"Community Association",
            "type":"Services"
        }
    ],
    "sg:phone":"+44 1246 221856",
    "sg:postcode":"S42 6PB",
    "sg:province":"Derbyshire",
    "sg:tags":[
        "relation",
        "public"
    ],
    "wof:name":"L J R Public Relations",
    "wof:placetype":"venue"
},
  "geometry": {"coordinates":[-1.427257,53.209068],"type":"Point"}
}