{
  "type": "Feature",
  "properties": {
    "iso:country":"GB",
    "sg:address":"Oak Hill Road, Stapleford Abbotts",
    "sg:city":"Romford",
    "sg:classifiers":[
        {
            "category":"Shopping",
            "subcategory":"Department Store",
            "type":"Retail Goods"
        }
    ],
    "sg:phone":"+44 1708 762940",
    "sg:postcode":"RM4 1JL",
    "sg:province":"Essex",
    "wof:name":"The Village Shoppe",
    "wof:placetype":"venue"
},
  "geometry": {"coordinates":[0.18966,51.624969],"type":"Point"}
}