{
  "type": "Feature",
  "properties": {
    "iso:country":"GB",
    "sg:address":"52 Station Road, Heaton Mersey",
    "sg:city":"Stockport",
    "sg:classifiers":[
        {
            "category":"Professional",
            "subcategory":"Printing & Photocopies",
            "type":"Services"
        }
    ],
    "sg:phone":"+44 161 443 1653",
    "sg:postcode":"SK4 3QT",
    "sg:province":"Cheshire",
    "sg:tags":[
        "duplicating",
        "copying"
    ],
    "wof:name":"Polyester Graphics Ltd.",
    "wof:placetype":"venue"
},
  "geometry": {"coordinates":[-2.201899,53.409538],"type":"Point"}
}