{
  "type": "Feature",
  "properties": {
    "addr:full":"Huttock End Lane Bacup Lancashire OL13 8LD",
    "addr:postcode":"ol13 8ld",
    "addr:street":"End Lane",
    "iso:country":"GB",
    "sg:address":"Huttock End Lane",
    "sg:city":"Bacup",
    "sg:classifiers":[
        {
            "category":"Organizations",
            "subcategory":"Community Association",
            "type":"Services"
        },
        {
            "category":"Organizations",
            "subcategory":"Membership Organization",
            "type":"Services"
        }
    ],
    "sg:phone":"+44 1706 873461",
    "sg:postcode":"OL13 8LD",
    "sg:province":"Lancashire",
    "sg:tags":[
        "club",
        "social"
    ],
    "wof:name":"Rosemount Working Mens Club",
    "wof:placetype":"venue"
},
  "geometry": {"coordinates":[-2.2193980217,53.6944618225],"type":"Point"}
}