{
  "type": "Feature",
  "properties": {
    "iso:country":"GB",
    "sg:address":"12 Vauxhall Gro",
    "sg:city":"London",
    "sg:classifiers":[
        {
            "category":"Communications",
            "subcategory":"Film & Video Production",
            "type":"Services"
        }
    ],
    "sg:phone":"+44 20 7735 9099",
    "sg:postcode":"SW8 1SY",
    "sg:province":"Greater London",
    "sg:tags":[
        "illustrator",
        "artist"
    ],
    "wof:name":"Acme Arts Ltd",
    "wof:placetype":"venue"
},
  "geometry": {"coordinates":[-0.120407,51.484657],"type":"Point"}
}