{
  "type": "Feature",
  "properties": {
    "addr:full":"12 Vauxhall Gro London Greater London SW8 1SY",
    "addr:housenumber":"12",
    "addr:postcode":"sw8 1sy",
    "addr:street":"Vauxhall Gro",
    "iso:country":"GB",
    "sg:address":"12 Vauxhall Gro",
    "sg:city":"London",
    "sg:classifiers":[
        {
            "category":"Communications",
            "subcategory":"Film & Video Production",
            "type":"Services"
        }
    ],
    "sg:phone":"+44 20 7735 9099",
    "sg:postcode":"SW8 1SY",
    "sg:province":"Greater London",
    "sg:tags":[
        "illustrator",
        "artist"
    ],
    "wof:name":"Acme Arts Ltd",
    "wof:placetype":"venue"
},
  "geometry": {"coordinates":[-0.120407,51.484657],"type":"Point"}
}