{
  "type": "Feature",
  "properties": {
    "addr:full":"The Workshop, Elmhaven Marina Rochester Kent ME2 1AQ",
    "addr:postcode":"me2 1aq",
    "iso:country":"GB",
    "sg:address":"The Workshop, Elmhaven Marina",
    "sg:city":"Rochester",
    "sg:classifiers":[
        {
            "category":"Conference Center",
            "type":"Public Place"
        }
    ],
    "sg:postcode":"ME2 1AQ",
    "sg:province":"Kent",
    "wof:name":"Insight",
    "wof:placetype":"venue"
},
  "geometry": {"coordinates":[0.4887830019,51.3963699341],"type":"Point"}
}