{
  "type": "Feature",
  "properties": {
    "iso:country":"GB",
    "sg:address":"81 Henderson Street",
    "sg:city":"Stirling",
    "sg:classifiers":[
        {
            "category":"Professional",
            "subcategory":"Management & Consulting",
            "type":"Services"
        }
    ],
    "sg:postcode":"FK9 4HG",
    "sg:province":"Clackmannanshire",
    "sg:tags":[
        "consultant",
        "business"
    ],
    "wof:name":"E S P",
    "wof:placetype":"venue"
},
  "geometry": {"coordinates":[-3.943849,56.154221],"type":"Point"}
}