{
  "type": "Feature",
  "properties": {
    "iso:country":"GB",
    "sg:address":"39 Market Street",
    "sg:city":"Ulverston",
    "sg:classifiers":[
        {
            "category":"Retail",
            "subcategory":"Photofinishing",
            "type":"Services"
        }
    ],
    "sg:phone":"+44 1229 583050",
    "sg:postcode":"LA12 7LR",
    "sg:province":"Cumbria",
    "sg:tags":[
        "photographic",
        "processor"
    ],
    "wof:name":"Ulverston Photo Express",
    "wof:placetype":"venue"
},
  "geometry": {"coordinates":[-3.094551,54.196041],"type":"Point"}
}