{
  "type": "Feature",
  "properties": {
    "addr:full":"Barbot Hall Indsl Estate, Mangham Road Rotherham South Yorkshire S61 4RS",
    "addr:postcode":"s61 4rs",
    "addr:street":"Mangham Road",
    "iso:country":"GB",
    "sg:address":"Barbot Hall Indsl Estate, Mangham Road",
    "sg:city":"Rotherham",
    "sg:classifiers":[
        {
            "category":"Home & Garden",
            "subcategory":"Carpets & Floor Coverings",
            "type":"Retail Goods"
        }
    ],
    "sg:phone":"+44 1709 362448",
    "sg:postcode":"S61 4RS",
    "sg:province":"South Yorkshire",
    "sg:tags":[
        "rubber",
        "plastic"
    ],
    "wof:name":"Titan Plastech Ltd.",
    "wof:placetype":"venue"
},
  "geometry": {"coordinates":[-1.361814,53.447239],"type":"Point"}
}