{
  "type": "Feature",
  "properties": {
    "addr:full":"40 Beech Tree Road, Holmer Green High Wycombe Buckinghamshire HP15 6UT",
    "addr:housenumber":"40",
    "addr:postcode":"hp15 6ut",
    "addr:street":"Beech Tree Road",
    "iso:country":"GB",
    "sg:address":"40 Beech Tree Road, Holmer Green",
    "sg:city":"High Wycombe",
    "sg:classifiers":[
        {
            "category":"Autos & Motor Vehicles",
            "subcategory":"Auto Supplies",
            "type":"Retail Goods"
        }
    ],
    "sg:postcode":"HP15 6UT",
    "sg:province":"Buckinghamshire",
    "sg:tags":[
        "machine",
        "laundry",
        "washing"
    ],
    "wof:name":"Glinton Slade Ltd.",
    "wof:placetype":"venue"
},
  "geometry": {"coordinates":[-0.696993,51.667892],"type":"Point"}
}