{
  "type": "Feature",
  "properties": {
    "iso:country":"GB",
    "sg:address":"11 Alfred Rd",
    "sg:city":"Farnham",
    "sg:classifiers":[
        {
            "category":"Professional",
            "subcategory":"Computer Services",
            "type":"Services"
        }
    ],
    "sg:phone":"+44 1252 715659",
    "sg:postcode":"GU9 8ND",
    "sg:province":"Surrey",
    "sg:tags":[
        "system",
        "software"
    ],
    "wof:name":"Pendulum Projects Ltd",
    "wof:placetype":"venue"
},
  "geometry": {"coordinates":[-0.791014,51.210571],"type":"Point"}
}