{
  "type": "Feature",
  "properties": {
    "addr:full":"177 Unthank Rd Norwich Norfolk NR2 2PQ",
    "addr:housenumber":"177",
    "addr:postcode":"nr2 2pq",
    "addr:street":"Unthank Rd",
    "iso:country":"GB",
    "sg:address":"177 Unthank Rd",
    "sg:city":"Norwich",
    "sg:classifiers":[
        {
            "category":"Health Services",
            "subcategory":"Dentist",
            "type":"Services"
        }
    ],
    "sg:phone":"+44 1603 250010",
    "sg:postcode":"NR2 2PQ",
    "sg:province":"Norfolk",
    "sg:tags":[
        "technician",
        "dental"
    ],
    "wof:name":"Neil Coleman",
    "wof:placetype":"venue"
},
  "geometry": {"coordinates":[1.274711,52.622559],"type":"Point"}
}