{
  "type": "Feature",
  "properties": {
    "addr:full":"32 Newgate St Walton On The Naze Essex CO14 8AL",
    "addr:housenumber":"32",
    "addr:postcode":"co14 8al",
    "addr:street":"Newgate St",
    "iso:country":"GB",
    "sg:address":"32 Newgate St",
    "sg:city":"Walton On The Naze",
    "sg:classifiers":[
        {
            "category":"Fast Food",
            "type":"Food & Drink"
        }
    ],
    "sg:phone":"+44 1255 677315",
    "sg:postcode":"CO14 8AL",
    "sg:province":"Essex",
    "sg:tags":[
        "away",
        "take"
    ],
    "wof:name":"Sun Wah",
    "wof:placetype":"venue"
},
  "geometry": {"coordinates":[1.271418,51.848911],"type":"Point"}
}