{
  "type": "Feature",
  "properties": {
    "iso:country":"GB",
    "sg:address":"6 Francis Street, Raunds",
    "sg:city":"Wellingborough",
    "sg:classifiers":[
        {
            "category":"Communications",
            "subcategory":"Film & Video Production",
            "type":"Services"
        }
    ],
    "sg:postcode":"NN9 6DH",
    "sg:province":"Northamptonshire",
    "sg:tags":[
        "illustrator",
        "artist"
    ],
    "wof:name":"Niko Design",
    "wof:placetype":"venue"
},
  "geometry": {"coordinates":[-0.551427,52.336853],"type":"Point"}
}