{
  "type": "Feature",
  "properties": {
    "iso:country":"GB",
    "sg:address":"49 High Street, Kingswood",
    "sg:city":"Bristol",
    "sg:classifiers":[
        {
            "category":"Professional",
            "subcategory":"Employment Agencies",
            "type":"Services"
        }
    ],
    "sg:phone":"+44 117 947 5986",
    "sg:postcode":"BS15 4AA",
    "sg:province":"City of Bristol",
    "sg:tags":[
        "consultant"
    ],
    "wof:name":"Kingswood Training Services",
    "wof:placetype":"venue"
},
  "geometry": {"coordinates":[-2.504022,51.462513],"type":"Point"}
}