{
  "type": "Feature",
  "properties": {
    "iso:country":"GB",
    "sg:address":"353 Green Lane",
    "sg:city":"Ilford",
    "sg:classifiers":[
        {
            "category":"Real Estate",
            "subcategory":"Real Estate Agent",
            "type":"Services"
        }
    ],
    "sg:phone":"+44 20 8597 7372",
    "sg:postcode":"IG3 9TH",
    "sg:province":"Essex",
    "wof:name":"Sandra Davidson",
    "wof:placetype":"venue"
},
  "geometry": {"coordinates":[0.099444,51.561031],"type":"Point"}
}