{
  "type": "Feature",
  "properties": {
    "addr:full":"24 Hesketh Meadow Lane, Lowton Warrington Cheshire WA3 2AJ",
    "addr:housenumber":"24",
    "addr:postcode":"wa3 2aj",
    "addr:street":"Hesketh Meadow Lane",
    "iso:country":"GB",
    "sg:address":"24 Hesketh Meadow Lane, Lowton",
    "sg:city":"Warrington",
    "sg:classifiers":[
        {
            "category":"Education",
            "subcategory":"Music School",
            "type":"Public Place"
        }
    ],
    "sg:postcode":"WA3 2AJ",
    "sg:province":"Cheshire",
    "sg:tags":[
        "conservatory"
    ],
    "wof:name":"Hesketh Conservatories",
    "wof:placetype":"venue"
},
  "geometry": {"coordinates":[-2.5582840443,53.4737586975],"type":"Point"}
}