{
  "type": "Feature",
  "properties": {
    "iso:country":"GB",
    "sg:address":"Lloyds Bank Chanbers, 310-312 Chiswick High Rd",
    "sg:city":"London",
    "sg:classifiers":[
        {
            "category":"Travel",
            "subcategory":"Travel Agent",
            "type":"Entertainment"
        }
    ],
    "sg:postcode":"W4 1NR",
    "sg:province":"Greater London",
    "wof:name":"Pharoah Travel Ltd",
    "wof:placetype":"venue"
},
  "geometry": {"coordinates":[-0.2610299885,51.4925384521],"type":"Point"}
}