{
  "type": "Feature",
  "properties": {
    "iso:country":"GB",
    "sg:address":"Unit 9, Prince Consort Industrial Estate",
    "sg:city":"Hebburn",
    "sg:classifiers":[
        {
            "category":"Manufacturing",
            "subcategory":"Metals",
            "type":"Manufacturing & Wholesale Goods"
        },
        {
            "category":"Building & Trades",
            "subcategory":"Construction",
            "type":"Services"
        }
    ],
    "sg:phone":"+44 191 430 0835",
    "sg:postcode":"NE31 1EH",
    "sg:province":"Tyne and Wear",
    "sg:tags":[
        "fabricator",
        "aluminium",
        "window",
        "replacement"
    ],
    "wof:name":"Wright Aluminium Systems Ltd",
    "wof:placetype":"venue"
},
  "geometry": {"coordinates":[-1.529461,54.978992],"type":"Point"}
}