{
  "type": "Feature",
  "properties": {
    "addr:full":"1 Ferndale Road, Binley Woods Coventry Warwickshire CV3 2BG",
    "addr:housenumber":"1",
    "addr:postcode":"cv3 2bg",
    "addr:street":"Ferndale Road",
    "iso:country":"GB",
    "sg:address":"1 Ferndale Road, Binley Woods",
    "sg:city":"Coventry",
    "sg:classifiers":[
        {
            "category":"Building & Trades",
            "subcategory":"Cleaning & Sanitation",
            "type":"Services"
        }
    ],
    "sg:phone":"+44 24 7654 2795",
    "sg:postcode":"CV3 2BG",
    "sg:province":"Warwickshire",
    "sg:tags":[
        "cleaner",
        "window"
    ],
    "wof:name":"Floods",
    "wof:placetype":"venue"
},
  "geometry": {"coordinates":[-1.412776,52.392857],"type":"Point"}
}