{
  "type": "Feature",
  "properties": {
    "iso:country":"GB",
    "sg:address":"Hulley Road, Hurdsfield",
    "sg:city":"Macclesfield",
    "sg:classifiers":[
        {
            "category":"Professional",
            "subcategory":"Engineering",
            "type":"Services"
        }
    ],
    "sg:phone":"+44 1625 505300",
    "sg:postcode":"SK10 2SG",
    "sg:province":"Cheshire",
    "wof:name":"Bodycote International Plc",
    "wof:placetype":"venue"
},
  "geometry": {"coordinates":[-2.111404,53.269844],"type":"Point"}
}