{
  "type": "Feature",
  "properties": {
    "addr:full":"Mayfair West End Hampshire W1X 1FH",
    "iso:country":"GB",
    "sg:address":"Mayfair",
    "sg:city":"West End",
    "sg:classifiers":[
        {
            "category":"Personal",
            "type":"Services"
        }
    ],
    "sg:phone":"+44 20 7287 6740",
    "sg:postcode":"W1X 1FH",
    "sg:province":"Hampshire",
    "sg:tags":[
        "tailor"
    ],
    "wof:name":"40 Saville Row",
    "wof:placetype":"venue"
},
  "geometry": {"coordinates":[-0.13899,51.50758],"type":"Point"}
}