{
  "type": "Feature",
  "properties": {
    "addr:full":"178 Southchurch Boulevard Southend On Sea Essex SS2 4UX",
    "addr:housenumber":"178",
    "addr:postcode":"ss2 4ux",
    "addr:street":"Southchurch Boulevard Southend",
    "iso:country":"GB",
    "sg:address":"178 Southchurch Boulevard",
    "sg:city":"Southend On Sea",
    "sg:classifiers":[
        {
            "category":"Building & Trades",
            "subcategory":"Construction",
            "type":"Services"
        }
    ],
    "sg:phone":"+44 1702 585957",
    "sg:postcode":"SS2 4UX",
    "sg:province":"Essex",
    "sg:tags":[
        "flooring"
    ],
    "wof:name":"Tri-Contracting Services Ltd",
    "wof:placetype":"venue"
},
  "geometry": {"coordinates":[0.7527419925,51.5434455872],"type":"Point"}
}