{
  "type": "Feature",
  "properties": {
    "addr:full":"Waterside Ho, Falmouth Rd Penryn Cornwall TR10 8BE",
    "addr:postcode":"tr10 8be",
    "addr:street":"Falmouth Rd",
    "iso:country":"GB",
    "sg:address":"Waterside Ho, Falmouth Rd",
    "sg:city":"Penryn",
    "sg:classifiers":[
        {
            "category":"Shopping",
            "subcategory":"Stationery & Office Supplies",
            "type":"Retail Goods"
        }
    ],
    "sg:phone":"+44 1326 375657",
    "sg:postcode":"TR10 8BE",
    "sg:province":"Cornwall",
    "sg:tags":[
        "equipment"
    ],
    "wof:name":"Phoenix Business Equipment (Cornwall) Lt",
    "wof:placetype":"venue"
},
  "geometry": {"coordinates":[-5.104809,50.168575],"type":"Point"}
}