{
  "type": "Feature",
  "properties": {
    "iso:country":"GB",
    "sg:address":"15 Leamore Lane, Bloxwich",
    "sg:city":"Walsall",
    "sg:classifiers":[
        {
            "category":"Restaurant",
            "type":"Food & Drink"
        }
    ],
    "sg:phone":"+44 1922 400191",
    "sg:postcode":"WS3 2BJ",
    "sg:province":"Staffordshire",
    "sg:tags":[
        "indian"
    ],
    "wof:name":"Leamore Balti Ho",
    "wof:placetype":"venue"
},
  "geometry": {"coordinates":[-1.995391,52.60767],"type":"Point"}
}