{
  "type": "Feature",
  "properties": {
    "addr:full":"40 Caroline Street Bridgend Bridgend CF31 1DQ",
    "addr:housenumber":"40",
    "addr:postcode":"cf31 1dq",
    "addr:street":"Caroline Street",
    "iso:country":"GB",
    "sg:address":"40 Caroline Street",
    "sg:city":"Bridgend",
    "sg:classifiers":[
        {
            "category":"Shopping",
            "subcategory":"Jewelry",
            "type":"Retail Goods"
        },
        {
            "category":"Shopping",
            "subcategory":"Comic Books",
            "type":"Retail Goods"
        }
    ],
    "sg:phone":"+44 1656 663655",
    "sg:postcode":"CF31 1DQ",
    "sg:province":"Bridgend",
    "sg:tags":[
        "jeweller",
        "sale",
        "jewellery"
    ],
    "wof:name":"Celtic Jewellers Ltd",
    "wof:placetype":"venue"
},
  "geometry": {"coordinates":[-3.5779159069,51.5059394836],"type":"Point"}
}