{
  "type": "Feature",
  "properties": {
    "iso:country":"GB",
    "sg:address":"63 Coronation Road, Crosby",
    "sg:city":"Liverpool",
    "sg:classifiers":[
        {
            "category":"Personal",
            "subcategory":"Beauty Salon",
            "type":"Services"
        }
    ],
    "sg:phone":"+44 151 924 9990",
    "sg:postcode":"L23 5RE",
    "sg:province":"Merseyside",
    "sg:tags":[
        "unisex",
        "hairdresser"
    ],
    "wof:name":"Andrew David Salons",
    "wof:placetype":"venue"
},
  "geometry": {"coordinates":[-3.0280249119,53.490562439],"type":"Point"}
}