{
  "type": "Feature",
  "properties": {
    "addr:full":"77 Myddleton Road London Greater London N22 8LZ",
    "addr:housenumber":"77",
    "addr:postcode":"n22 8lz",
    "addr:street":"Myddleton Road",
    "iso:country":"GB",
    "sg:address":"77 Myddleton Road",
    "sg:city":"London",
    "sg:classifiers":[
        {
            "category":"Food & Beverages",
            "subcategory":"Fruits & Vegetables",
            "type":"Retail Goods"
        }
    ],
    "sg:phone":"+44 20 8889 7520",
    "sg:postcode":"N22 8LZ",
    "sg:province":"Greater London",
    "sg:tags":[
        "greengrocer"
    ],
    "wof:name":"Redsea Supermarket",
    "wof:placetype":"venue"
},
  "geometry": {"coordinates":[-0.116651997,51.6062698364],"type":"Point"}
}