{
  "type": "Feature",
  "properties": {
    "addr:full":"Brewers Garage Oxford Oxfordshire OX44 9NY",
    "addr:postcode":"ox44 9ny",
    "iso:country":"GB",
    "sg:address":"Brewers Garage",
    "sg:city":"Oxford",
    "sg:classifiers":[
        {
            "category":"Autos & Motor Vehicles",
            "subcategory":"Automobile Sales",
            "type":"Retail Goods"
        }
    ],
    "sg:phone":"+44 1865 341341",
    "sg:postcode":"OX44 9NY",
    "sg:province":"Oxfordshire",
    "sg:tags":[
        "car"
    ],
    "wof:name":"Oxford Trade Centre",
    "wof:placetype":"venue"
},
  "geometry": {"coordinates":[-1.16229,51.717918],"type":"Point"}
}