{
  "type": "Feature",
  "properties": {
    "addr:full":"3b Athena Avenue, Elgin Industrial Estate Swindon Wiltshire SN2 8HF",
    "addr:housenumber":"3b;estate",
    "addr:postcode":"sn2 8hf",
    "addr:street":"Athena Avenue;Industrial",
    "iso:country":"GB",
    "sg:address":"3b Athena Avenue, Elgin Industrial Estate",
    "sg:city":"Swindon",
    "sg:classifiers":[
        {
            "category":"Professional",
            "subcategory":"Computer Services",
            "type":"Services"
        }
    ],
    "sg:phone":"+44 1793 428700",
    "sg:postcode":"SN2 8HF",
    "sg:province":"Wiltshire",
    "sg:tags":[
        "consultant"
    ],
    "wof:name":"Thamesdown Software Fulfilment Ltd.",
    "wof:placetype":"venue"
},
  "geometry": {"coordinates":[-1.769829,51.576485],"type":"Point"}
}