{
  "type": "Feature",
  "properties": {
    "iso:country":"GB",
    "sg:address":"8th Floor, Corinthian House, 17 Lansdowne Road",
    "sg:city":"Croydon",
    "sg:classifiers":[
        {
            "category":"Professional",
            "subcategory":"Engineering",
            "type":"Services"
        },
        {
            "category":"Real Estate",
            "subcategory":"Architect",
            "type":"Services"
        }
    ],
    "sg:phone":"+44 20 8604 8999",
    "sg:postcode":"CR0 2BX",
    "sg:province":"Surrey",
    "sg:tags":[
        "design",
        "engineer"
    ],
    "wof:name":"Sir Frederick Snow & Partners Ltd",
    "wof:placetype":"venue"
},
  "geometry": {"coordinates":[-0.0965330005,51.3765678406],"type":"Point"}
}