{
  "type": "Feature",
  "properties": {
    "addr:full":"Ramsgate Stockton-on-tees Durham TS18 1BT",
    "addr:postcode":"ts18 1bt",
    "addr:street":"Ramsgate",
    "iso:country":"GB",
    "sg:address":"Ramsgate",
    "sg:city":"Stockton-on-tees",
    "sg:classifiers":[
        {
            "category":"Professional",
            "subcategory":"Employment Agencies",
            "type":"Services"
        }
    ],
    "sg:phone":"+44 1642 616112",
    "sg:postcode":"TS18 1BT",
    "sg:province":"Durham",
    "sg:tags":[
        "consultant"
    ],
    "wof:name":"Drake International Ltd.",
    "wof:placetype":"venue"
},
  "geometry": {"coordinates":[-1.3147790432,54.5631752014],"type":"Point"}
}