{
  "type": "Feature",
  "properties": {
    "addr:full":"Unit 7 Clayton Grn, Centre Sheep Hill La, Clayton-le-woods Chorley Lancashire PR6 7TL",
    "addr:housenumber":"unit 7",
    "addr:postcode":"pr6 7tl",
    "addr:street":"Clayton Grn Centre Sheep Hill La Clayton-Le-Woods",
    "iso:country":"GB",
    "sg:address":"Unit 7 Clayton Grn, Centre Sheep Hill La, Clayton-le-woods",
    "sg:city":"Chorley",
    "sg:classifiers":[
        {
            "category":"Farming",
            "subcategory":"Livestock Farm",
            "type":"Manufacturing & Wholesale Goods"
        }
    ],
    "sg:postcode":"PR6 7TL",
    "sg:province":"Lancashire",
    "sg:tags":[
        "breeder"
    ],
    "wof:name":"Roots & Fruits",
    "wof:placetype":"venue"
},
  "geometry": {"coordinates":[-2.6464240551,53.7044906616],"type":"Point"}
}