{
  "type": "Feature",
  "properties": {
    "addr:full":"Tarran Industrial Estate, Moreton Wirral Merseyside CH46 4TU",
    "addr:postcode":"ch46 4tu",
    "addr:street":"Estate",
    "iso:country":"GB",
    "sg:address":"Tarran Industrial Estate, Moreton",
    "sg:city":"Wirral",
    "sg:classifiers":[
        {
            "category":"Military Area",
            "subcategory":"Air Force Base",
            "type":"Public Place"
        }
    ],
    "sg:phone":"+44 151 606 0808",
    "sg:postcode":"CH46 4TU",
    "sg:province":"Merseyside",
    "sg:tags":[
        "water",
        "treatment"
    ],
    "wof:name":"Feedwater Ltd.",
    "wof:placetype":"venue"
},
  "geometry": {"coordinates":[-3.11822,53.409309],"type":"Point"}
}