{
  "type": "Feature",
  "properties": {
    "addr:full":"Severn Rd Sheffield South Yorkshire S10 2SU",
    "addr:postcode":"s10 2su",
    "addr:street":"Severn Rd",
    "iso:country":"GB",
    "sg:address":"Severn Rd",
    "sg:city":"Sheffield",
    "sg:classifiers":[
        {
            "category":"Organizations",
            "subcategory":"Non-profit Organization",
            "type":"Services"
        }
    ],
    "sg:phone":"+44 114 266 6141",
    "sg:postcode":"S10 2SU",
    "sg:province":"South Yorkshire",
    "sg:tags":[
        "organisation",
        "voluntary",
        "charity"
    ],
    "wof:name":"Muslim Women & Youth Help Line",
    "wof:placetype":"venue"
},
  "geometry": {"coordinates":[-1.495614,53.379742],"type":"Point"}
}