{
  "type": "Feature",
  "properties": {
    "iso:country":"GB",
    "sg:address":"Haughton Down, Salisbury Road",
    "sg:city":"Stockbridge",
    "sg:classifiers":[
        {
            "category":"Building & Trades",
            "subcategory":"Plumbing",
            "type":"Services"
        }
    ],
    "sg:postcode":"SO20 6JR",
    "sg:province":"Hampshire",
    "sg:tags":[
        "heating"
    ],
    "wof:name":"Hampshire Flexitanks Ltd.",
    "wof:placetype":"venue"
},
  "geometry": {"coordinates":[-1.4941020012,51.1142807007],"type":"Point"}
}