{
  "type": "Feature",
  "properties": {
    "addr:full":"123 Buckingham Place Road London Greater London SW1W 9DZ",
    "addr:housenumber":"123",
    "addr:postcode":"sw1w 9dz",
    "addr:street":"Buckingham Place Road",
    "iso:country":"GB",
    "sg:address":"123 Buckingham Place Road",
    "sg:city":"London",
    "sg:classifiers":[
        {
            "category":"Professional",
            "subcategory":"Employment Agencies",
            "type":"Services"
        }
    ],
    "sg:phone":"+44 20 7312 3120",
    "sg:postcode":"SW1W 9DZ",
    "sg:province":"Greater London",
    "sg:tags":[
        "consultant"
    ],
    "wof:name":"K F I (U K) Ltd.",
    "wof:placetype":"venue"
},
  "geometry": {"coordinates":[-0.1465,51.49305],"type":"Point"}
}