{
  "type": "Feature",
  "properties": {
    "iso:country":"GB",
    "sg:address":"10 Wayfield Rd, Shirley",
    "sg:city":"Solihull",
    "sg:classifiers":[
        {
            "category":"Professional",
            "subcategory":"Management & Consulting",
            "type":"Services"
        }
    ],
    "sg:phone":"+44 121 745 5241",
    "sg:postcode":"B90 3HF",
    "sg:province":"West Midlands",
    "sg:tags":[
        "consultant",
        "business"
    ],
    "wof:name":"Jean Pousson & Associates",
    "wof:placetype":"venue"
},
  "geometry": {"coordinates":[-1.8218410015,52.4098358154],"type":"Point"}
}