{
  "type": "Feature",
  "properties": {
    "iso:country":"GB",
    "sg:address":"145 Bournemouth Road, Parkstone",
    "sg:city":"Poole",
    "sg:classifiers":[
        {
            "category":"Travel",
            "subcategory":"Hotels & Motels",
            "type":"Entertainment"
        }
    ],
    "sg:phone":"+44 1202 732207",
    "sg:postcode":"BH14 9HT",
    "sg:province":"Dorset",
    "sg:tags":[
        "house",
        "guest"
    ],
    "wof:name":"Marric Hotel",
    "wof:placetype":"venue"
},
  "geometry": {"coordinates":[-1.935798049,50.724822998],"type":"Point"}
}