{
  "type": "Feature",
  "properties": {
    "addr:full":"12 Osborn Road Farnham Surrey GU9 9QT",
    "addr:housenumber":"12",
    "addr:postcode":"gu9 9qt",
    "addr:street":"Osborn Road",
    "iso:country":"GB",
    "sg:address":"12 Osborn Road",
    "sg:city":"Farnham",
    "sg:classifiers":[
        {
            "category":"Building & Trades",
            "subcategory":"Plumbing",
            "type":"Services"
        }
    ],
    "sg:phone":"+44 1252 722751",
    "sg:postcode":"GU9 9QT",
    "sg:province":"Surrey",
    "sg:tags":[
        "heating"
    ],
    "wof:name":"L B C Parratt",
    "wof:placetype":"venue"
},
  "geometry": {"coordinates":[-0.7853680253,51.2219085693],"type":"Point"}
}