{
  "type": "Feature",
  "properties": {
    "addr:full":"2a Byrne Rd Wolverhampton West Midlands WV2 3DP",
    "addr:housenumber":"2a",
    "addr:postcode":"wv2 3dp",
    "addr:street":"Byrne Rd",
    "iso:country":"GB",
    "sg:address":"2a Byrne Rd",
    "sg:city":"Wolverhampton",
    "sg:classifiers":[
        {
            "category":"Retail",
            "subcategory":"Storage",
            "type":"Services"
        }
    ],
    "sg:phone":"+44 1902 459387",
    "sg:postcode":"WV2 3DP",
    "sg:province":"West Midlands",
    "sg:tags":[
        "household",
        "removal"
    ],
    "wof:name":"G & S Removals",
    "wof:placetype":"venue"
},
  "geometry": {"coordinates":[-2.124512,52.571812],"type":"Point"}
}