{
  "type": "Feature",
  "properties": {
    "addr:full":"275 Chesterfield Road North, Pleasley Mansfield Derbyshire NG19 7QX",
    "addr:housenumber":"275",
    "addr:postcode":"ng19 7qx",
    "addr:street":"Chesterfield Road North",
    "iso:country":"GB",
    "sg:address":"275 Chesterfield Road North, Pleasley",
    "sg:city":"Mansfield",
    "sg:classifiers":[
        {
            "category":"Shopping",
            "subcategory":"News",
            "type":"Retail Goods"
        }
    ],
    "sg:phone":"+44 1623 811262",
    "sg:postcode":"NG19 7QX",
    "sg:province":"Derbyshire",
    "sg:tags":[
        "newsagent"
    ],
    "wof:name":"Mac's",
    "wof:placetype":"venue"
},
  "geometry": {"coordinates":[-1.232154,53.165031],"type":"Point"}
}