{
  "type": "Feature",
  "properties": {
    "iso:country":"GB",
    "sg:address":"Monrovia, Egloskerry",
    "sg:city":"Launceston",
    "sg:classifiers":[
        {
            "category":"Professional",
            "subcategory":"Management & Consulting",
            "type":"Services"
        }
    ],
    "sg:phone":"+44 1566 785759",
    "sg:postcode":"PL15 8RU",
    "sg:province":"Cornwall",
    "sg:tags":[
        "conservation"
    ],
    "wof:name":"BTCV",
    "wof:placetype":"venue"
},
  "geometry": {"coordinates":[-4.363344,50.636707],"type":"Point"}
}