{
  "type": "Feature",
  "properties": {
    "iso:country":"GB",
    "sg:address":"7 Naes",
    "sg:city":"Pwllheli",
    "sg:classifiers":[
        {
            "category":"Organizations",
            "subcategory":"Membership Organization",
            "type":"Services"
        }
    ],
    "sg:phone":"+44 1758 612797",
    "sg:postcode":"LL53 5HA",
    "sg:province":"Gwynedd",
    "sg:tags":[
        "club"
    ],
    "wof:name":"Conservative Club",
    "wof:placetype":"venue"
},
  "geometry": {"coordinates":[-4.4200091362,52.8873596191],"type":"Point"}
}