{
  "type": "Feature",
  "properties": {
    "addr:full":"2 Hele Gardens Plymouth Devon PL7 1JU",
    "addr:housenumber":"2",
    "addr:postcode":"pl7 1ju",
    "addr:street":"Hele Gardens",
    "iso:country":"GB",
    "sg:address":"2 Hele Gardens",
    "sg:city":"Plymouth",
    "sg:classifiers":[
        {
            "category":"Home & Garden",
            "subcategory":"Hardware",
            "type":"Retail Goods"
        }
    ],
    "sg:phone":"+44 1752 347331",
    "sg:postcode":"PL7 1JU",
    "sg:province":"Devon",
    "sg:tags":[
        "retailer",
        "diy"
    ],
    "wof:name":"Second Image Signs & Graphics",
    "wof:placetype":"venue"
},
  "geometry": {"coordinates":[-4.0425219536,50.3828659058],"type":"Point"}
}