{
  "type": "Feature",
  "properties": {
    "iso:country":"GB",
    "sg:address":"9 St Andrews Churchyard",
    "sg:city":"Penrith",
    "sg:classifiers":[
        {
            "category":"Banks & Credit Unions",
            "subcategory":"Financial Services",
            "type":"Services"
        }
    ],
    "sg:phone":"+44 1768 892748",
    "sg:postcode":"CA11 7YE",
    "sg:province":"Cumbria",
    "sg:tags":[
        "consultant"
    ],
    "wof:name":"Ian Logan Financial Services",
    "wof:placetype":"venue"
},
  "geometry": {"coordinates":[-2.757469,54.664303],"type":"Point"}
}