{
  "type": "Feature",
  "properties": {
    "addr:full":"Unit 15 Leicester Leicestershire LE5 3ED",
    "addr:housenumber":"unit 15",
    "addr:postcode":"le5 3ed",
    "iso:country":"GB",
    "sg:address":"Unit 15",
    "sg:city":"Leicester",
    "sg:classifiers":[
        {
            "category":"Professional",
            "type":"Services"
        }
    ],
    "sg:postcode":"LE5 3ED",
    "sg:province":"Leicestershire",
    "sg:tags":[
        "shopfitters"
    ],
    "wof:name":"Image Display & Interiors",
    "wof:placetype":"venue"
},
  "geometry": {"coordinates":[-1.1133999825,52.6378593445],"type":"Point"}
}