{
  "type": "Feature",
  "properties": {
    "addr:full":"15 Pinewood Drive, Dalgety Bay Dunfermline Fife KY11 9SP",
    "addr:housenumber":"15",
    "addr:postcode":"ky11 9sp",
    "addr:street":"Pinewood Drive Dalgety Bay",
    "iso:country":"GB",
    "sg:address":"15 Pinewood Drive, Dalgety Bay",
    "sg:city":"Dunfermline",
    "sg:classifiers":[
        {
            "category":"Professional",
            "subcategory":"Art Services",
            "type":"Services"
        }
    ],
    "sg:phone":"+44 1383 820566",
    "sg:postcode":"KY11 9SP",
    "sg:province":"Fife",
    "sg:tags":[
        "photographer"
    ],
    "wof:name":"Bill Roberton",
    "wof:placetype":"venue"
},
  "geometry": {"coordinates":[-3.354667,56.03371],"type":"Point"}
}