{
  "type": "Feature",
  "properties": {
    "iso:country":"GB",
    "sg:address":"173 Malden Road",
    "sg:city":"London",
    "sg:classifiers":[
        {
            "category":"Home & Garden",
            "subcategory":"Furniture",
            "type":"Retail Goods"
        }
    ],
    "sg:postcode":"NW5 4HT",
    "sg:province":"Greater London",
    "wof:name":"Holders Fine Furniture",
    "wof:placetype":"venue"
},
  "geometry": {"coordinates":[-0.1560900062,51.5506858826],"type":"Point"}
}