{
  "type": "Feature",
  "properties": {
    "addr:full":"6 Albany Street Edinburgh City of Edinburgh EH1 3QB",
    "addr:housenumber":"6",
    "addr:postcode":"eh1 3qb",
    "addr:street":"Albany Street",
    "iso:country":"GB",
    "sg:address":"6 Albany Street",
    "sg:city":"Edinburgh",
    "sg:classifiers":[
        {
            "category":"Professional",
            "subcategory":"Management & Consulting",
            "type":"Services"
        },
        {
            "category":"Professional",
            "subcategory":"Computer Services",
            "type":"Services"
        }
    ],
    "sg:postcode":"EH1 3QB",
    "sg:province":"City of Edinburgh",
    "sg:tags":[
        "development",
        "consultant",
        "business",
        "software"
    ],
    "wof:name":"CYBERFIELD CONSULTING LTD.",
    "wof:placetype":"venue"
},
  "geometry": {"coordinates":[-3.190686,55.957623],"type":"Point"}
}