{
  "type": "Feature",
  "properties": {
    "addr:full":"Unit 54 21 Steward Street Whitechapel Greater London E1 6AJ",
    "addr:housenumber":"unit;21",
    "addr:postcode":"e1 6aj",
    "addr:street":"Steward Street",
    "iso:country":"GB",
    "sg:address":"Unit 54 21 Steward Street",
    "sg:city":"Whitechapel",
    "sg:classifiers":[
        {
            "category":"Utilities",
            "type":"Services"
        }
    ],
    "sg:phone":"+44 20 7375 3549",
    "sg:postcode":"E1 6AJ",
    "sg:province":"Greater London",
    "sg:tags":[
        "internet"
    ],
    "wof:name":"Flagrant",
    "wof:placetype":"venue"
},
  "geometry": {"coordinates":[-0.07713,51.519611],"type":"Point"}
}