{
  "type": "Feature",
  "properties": {
    "iso:country":"GB",
    "sg:address":"56 Lee Lane, Horwich",
    "sg:city":"Bolton",
    "sg:classifiers":[
        {
            "category":"Organizations",
            "subcategory":"Non-profit Organization",
            "type":"Services"
        }
    ],
    "sg:postcode":"BL6 7AE",
    "sg:province":"Lancashire",
    "sg:tags":[
        "charitable",
        "organisation",
        "voluntary",
        "charity"
    ],
    "wof:name":"The Childrens Society",
    "wof:placetype":"venue"
},
  "geometry": {"coordinates":[-2.5465838909,53.6001167297],"type":"Point"}
}