{
  "type": "Feature",
  "properties": {
    "addr:full":"5a Market Street, Denton Manchester Greater Manchester M34 2JL",
    "addr:housenumber":"5a",
    "addr:postcode":"m34 2jl",
    "addr:street":"Market Street",
    "iso:country":"GB",
    "sg:address":"5a Market Street, Denton",
    "sg:city":"Manchester",
    "sg:classifiers":[
        {
            "category":"Home & Garden",
            "subcategory":"Home Furnishings",
            "type":"Retail Goods"
        }
    ],
    "sg:phone":"+44 161 336 2263",
    "sg:postcode":"M34 2JL",
    "sg:province":"Greater Manchester",
    "sg:tags":[
        "blind",
        "manufacture",
        "fitting",
        "curtain"
    ],
    "wof:name":"The Curtain Cabin",
    "wof:placetype":"venue"
},
  "geometry": {"coordinates":[-2.114379,53.455921],"type":"Point"}
}