{
  "type": "Feature",
  "properties": {
    "addr:full":"253 Brook Street, Broughty Ferry Dundee Angus DD5 2AG",
    "addr:housenumber":"253",
    "addr:postcode":"dd5 2ag",
    "addr:street":"Brook Street",
    "iso:country":"GB",
    "sg:address":"253 Brook Street, Broughty Ferry",
    "sg:city":"Dundee",
    "sg:classifiers":[
        {
            "category":"Shopping",
            "subcategory":"Clothing, Apparel, & Fashions",
            "type":"Retail Goods"
        }
    ],
    "sg:phone":"+44 1382 731707",
    "sg:postcode":"DD5 2AG",
    "sg:province":"Angus",
    "sg:tags":[
        "shop"
    ],
    "wof:name":"The Turret",
    "wof:placetype":"venue"
},
  "geometry": {"coordinates":[-2.873793,56.467281],"type":"Point"}
}