{
  "type": "Feature",
  "properties": {
    "iso:country":"GB",
    "sg:address":"103 Sundridge Drive",
    "sg:city":"Chatham",
    "sg:classifiers":[
        {
            "category":"Building & Trades",
            "subcategory":"Cleaning & Sanitation",
            "type":"Services"
        }
    ],
    "sg:phone":"+44 1634 686377",
    "sg:postcode":"ME5 8JE",
    "sg:province":"Kent",
    "sg:tags":[
        "commercial"
    ],
    "wof:name":"A A Cleaning Services",
    "wof:placetype":"venue"
},
  "geometry": {"coordinates":[0.531359,51.342922],"type":"Point"}
}