{
  "type": "Feature",
  "properties": {
    "addr:full":"64 Days Lane Sidcup Kent DA15 8JX",
    "addr:housenumber":"64",
    "addr:postcode":"da15 8jx",
    "addr:street":"Days Lane",
    "iso:country":"GB",
    "sg:address":"64 Days Lane",
    "sg:city":"Sidcup",
    "sg:classifiers":[
        {
            "category":"Place Of Worship",
            "type":"Public Place"
        }
    ],
    "sg:phone":"+44 20 8302 5356",
    "sg:postcode":"DA15 8JX",
    "sg:province":"Kent",
    "wof:name":"Holy Redeemer Church",
    "wof:placetype":"venue"
},
  "geometry": {"coordinates":[0.090388,51.44373703],"type":"Point"}
}