{
  "type": "Feature",
  "properties": {
    "addr:full":"Hickings Lane, Stapleford Nottingham Nottinghamshire NG9 8PJ",
    "addr:postcode":"ng9 8pj",
    "addr:street":"Hickings Lane",
    "iso:country":"GB",
    "sg:address":"Hickings Lane, Stapleford",
    "sg:city":"Nottingham",
    "sg:classifiers":[
        {
            "category":"Real Estate",
            "subcategory":"Real Estate Services",
            "type":"Services"
        },
        {
            "category":"Building & Trades",
            "subcategory":"Equipment Rental",
            "type":"Services"
        }
    ],
    "sg:phone":"+44 115 922 3333",
    "sg:postcode":"NG9 8PJ",
    "sg:province":"Nottinghamshire",
    "sg:tags":[
        "hire",
        "leasing",
        "plant",
        "machinery"
    ],
    "wof:name":"Sinbad Plant Ltd",
    "wof:placetype":"venue"
},
  "geometry": {"coordinates":[-1.2734980583,52.929725647],"type":"Point"}
}