{
  "type": "Feature",
  "properties": {
    "addr:full":"175 Manor Road Chigwell Essex IG7 5QB",
    "addr:housenumber":"175",
    "addr:postcode":"ig7 5qb",
    "addr:street":"Manor Road",
    "iso:country":"GB",
    "sg:address":"175 Manor Road",
    "sg:city":"Chigwell",
    "sg:classifiers":[
        {
            "category":"Real Estate",
            "subcategory":"Real Estate Agent",
            "type":"Services"
        }
    ],
    "sg:phone":"+44 20 8257 9988",
    "sg:postcode":"IG7 5QB",
    "sg:province":"Essex",
    "wof:name":"Cawleys",
    "wof:placetype":"venue"
},
  "geometry": {"coordinates":[0.091031,51.61306],"type":"Point"}
}