{
  "type": "Feature",
  "properties": {
    "addr:full":"Ashmore Lake Way Willenhall West Midlands WV13 1HJ",
    "addr:postcode":"wv13 1hj",
    "addr:street":"Ashmore Lake Way",
    "iso:country":"GB",
    "sg:address":"Ashmore Lake Way",
    "sg:city":"Willenhall",
    "sg:classifiers":[
        {
            "category":"Manufacturing",
            "subcategory":"Metals",
            "type":"Manufacturing & Wholesale Goods"
        }
    ],
    "sg:phone":"+44 1902 607336",
    "sg:postcode":"WV13 1HJ",
    "sg:province":"West Midlands",
    "sg:tags":[
        "steel",
        "stockholder"
    ],
    "wof:name":"W & J Smith (Metal Stockists) Ltd.",
    "wof:placetype":"venue"
},
  "geometry": {"coordinates":[-2.047911,52.595196],"type":"Point"}
}