{
  "type": "Feature",
  "properties": {
    "iso:country":"GB",
    "sg:address":"109-111 High St",
    "sg:city":"Harwich",
    "sg:classifiers":[
        {
            "category":"Shopping",
            "subcategory":"Department Store",
            "type":"Retail Goods"
        }
    ],
    "sg:postcode":"CO12 3AP",
    "sg:province":"Essex",
    "wof:name":"Thrower,P J,",
    "wof:placetype":"venue"
},
  "geometry": {"coordinates":[1.285515,51.938747],"type":"Point"}
}