{
  "type": "Feature",
  "properties": {
    "addr:full":"31 Lidget Street, Lindley Huddersfield West Yorkshire HD3 3JB",
    "addr:housenumber":"31",
    "addr:postcode":"hd3 3jb",
    "addr:street":"Lidget Street;West",
    "iso:country":"GB",
    "sg:address":"31 Lidget Street, Lindley",
    "sg:city":"Huddersfield",
    "sg:classifiers":[
        {
            "category":"Health Services",
            "subcategory":"Podiatrist",
            "type":"Services"
        }
    ],
    "sg:phone":"+44 1274 851314",
    "sg:postcode":"HD3 3JB",
    "sg:province":"West Yorkshire",
    "sg:tags":[
        "podiatrists",
        "chiropodist"
    ],
    "wof:name":"John Cunniffe",
    "wof:placetype":"venue"
},
  "geometry": {"coordinates":[-1.8231559992,53.6599197388],"type":"Point"}
}