{
  "type": "Feature",
  "properties": {
    "addr:full":"35 Kirkgate Otley North Yorkshire LS21 3HN",
    "addr:housenumber":"35",
    "addr:postcode":"ls21 3hn",
    "addr:street":"Kirkgate",
    "iso:country":"GB",
    "sg:address":"35 Kirkgate",
    "sg:city":"Otley",
    "sg:classifiers":[
        {
            "category":"Shopping",
            "subcategory":"Pharmacy",
            "type":"Retail Goods"
        }
    ],
    "sg:phone":"+44 1943 462014",
    "sg:postcode":"LS21 3HN",
    "sg:province":"North Yorkshire",
    "sg:tags":[
        "pharmacist",
        "chemist"
    ],
    "wof:name":"Mainprize & Wood",
    "wof:placetype":"venue"
},
  "geometry": {"coordinates":[-1.694347,53.904827],"type":"Point"}
}