{
  "type": "Feature",
  "properties": {
    "iso:country":"GB",
    "sg:address":"1 Milford St",
    "sg:city":"Liverpool",
    "sg:classifiers":[
        {
            "category":"Wholesale",
            "subcategory":"Scrap",
            "type":"Manufacturing & Wholesale Goods"
        }
    ],
    "sg:phone":"+44 151 207 0060",
    "sg:postcode":"L5 9ZE",
    "sg:province":"Merseyside",
    "sg:tags":[
        "breaker",
        "dismantlers"
    ],
    "wof:name":"Euro Salvage",
    "wof:placetype":"venue"
},
  "geometry": {"coordinates":[-2.994939,53.426731],"type":"Point"}
}