{
  "type": "Feature",
  "properties": {
    "iso:country":"GB",
    "sg:address":"5 Gordon Terrace, London Road, Brimscombe",
    "sg:city":"Stroud",
    "sg:classifiers":[
        {
            "category":"Fast Food",
            "type":"Food & Drink"
        },
        {
            "category":"Food & Beverages",
            "subcategory":"Groceries & Convenience Stores",
            "type":"Retail Goods"
        }
    ],
    "sg:phone":"+44 1453 885856",
    "sg:postcode":"GL5 2QE",
    "sg:province":"Gloucestershire",
    "sg:tags":[
        "shop",
        "fish",
        "take",
        "chip",
        "away"
    ],
    "wof:name":"Brimscombe Takeaway",
    "wof:placetype":"venue"
},
  "geometry": {"coordinates":[-2.1810429096,51.7192459106],"type":"Point"}
}