{
  "type": "Feature",
  "properties": {
    "addr:full":"26a Rear Of High Street Swadlincote Derbyshire DE11 8HY",
    "addr:housenumber":"26a rear of",
    "addr:postcode":"de11 8hy",
    "addr:street":"High Street",
    "iso:country":"GB",
    "sg:address":"26a Rear Of High Street",
    "sg:city":"Swadlincote",
    "sg:classifiers":[
        {
            "category":"Sports & Exercise",
            "subcategory":"Gym",
            "type":"Entertainment"
        }
    ],
    "sg:phone":"+44 1283 212782",
    "sg:postcode":"DE11 8HY",
    "sg:province":"Derbyshire",
    "sg:tags":[
        "fitness",
        "health",
        "centre"
    ],
    "wof:name":"Zeus Gym",
    "wof:placetype":"venue"
},
  "geometry": {"coordinates":[-1.552209,52.774094],"type":"Point"}
}