{
  "type": "Feature",
  "properties": {
    "iso:country":"GB",
    "sg:address":"The Venture, Royston Rd",
    "sg:city":"Royston",
    "sg:classifiers":[
        {
            "category":"Building & Trades",
            "subcategory":"Construction",
            "type":"Services"
        }
    ],
    "sg:phone":"+44 1763 852372",
    "sg:postcode":"SG8 0RG",
    "sg:province":"Bedfordshire",
    "sg:tags":[
        "builder"
    ],
    "wof:name":"Stephens J A",
    "wof:placetype":"venue"
},
  "geometry": {"coordinates":[-0.079094,52.128361],"type":"Point"}
}