{
  "type": "Feature",
  "properties": {
    "addr:full":"Croydon Street, Queensbury Bradford West Yorkshire BD13 2QH",
    "addr:postcode":"bd13 2qh",
    "addr:street":"Croydon Street;Bradford West",
    "iso:country":"GB",
    "sg:address":"Croydon Street, Queensbury",
    "sg:city":"Bradford",
    "sg:classifiers":[
        {
            "category":"Professional",
            "subcategory":"Testing Lab",
            "type":"Services"
        }
    ],
    "sg:phone":"+44 1274 883730",
    "sg:postcode":"BD13 2QH",
    "sg:province":"West Yorkshire",
    "sg:tags":[
        "mot"
    ],
    "wof:name":"Q 1 M O T Station",
    "wof:placetype":"venue"
},
  "geometry": {"coordinates":[-1.8459240198,53.7682495117],"type":"Point"}
}