{
  "type": "Feature",
  "properties": {
    "iso:country":"GB",
    "sg:address":"6a Spring Lane",
    "sg:city":"Eastleigh",
    "sg:classifiers":[
        {
            "category":"Food & Beverages",
            "subcategory":"Groceries & Convenience Stores",
            "type":"Retail Goods"
        }
    ],
    "sg:phone":"+44 23 8064 1132",
    "sg:postcode":"SO50 6LS",
    "sg:province":"Hampshire",
    "wof:name":"News Market",
    "wof:placetype":"venue"
},
  "geometry": {"coordinates":[-1.3367609978,50.9707260132],"type":"Point"}
}