{
  "type": "Feature",
  "properties": {
    "addr:full":"Curzon Ho, Curzon Rd Bournemouth Dorset BH1 4PR",
    "addr:postcode":"bh1 4pr",
    "addr:street":"Curzon Rd",
    "iso:country":"GB",
    "sg:address":"Curzon Ho, Curzon Rd",
    "sg:city":"Bournemouth",
    "sg:classifiers":[
        {
            "category":"Professional",
            "subcategory":"Engineering",
            "type":"Services"
        }
    ],
    "sg:phone":"+44 1202 399919",
    "sg:postcode":"BH1 4PR",
    "sg:province":"Dorset",
    "sg:tags":[
        "consulting",
        "engineer"
    ],
    "wof:name":"M & E Designs",
    "wof:placetype":"venue"
},
  "geometry": {"coordinates":[-1.8482090235,50.7329788208],"type":"Point"}
}