{
  "type": "Feature",
  "properties": {
    "addr:full":"Rectory School, Hanworth Road Hampton Greater London TW12 3HB",
    "addr:postcode":"tw12 3hb",
    "addr:street":"Hanworth Road",
    "iso:country":"GB",
    "sg:address":"Rectory School, Hanworth Road",
    "sg:city":"Hampton",
    "sg:classifiers":[
        {
            "category":"Education",
            "subcategory":"Dance Studio",
            "type":"Public Place"
        }
    ],
    "sg:postcode":"TW12 3HB",
    "sg:province":"Greater London",
    "sg:tags":[
        "school",
        "dancing"
    ],
    "wof:name":"Burge School of Dancing",
    "wof:placetype":"venue"
},
  "geometry": {"coordinates":[-0.373679,51.417568],"type":"Point"}
}