{
  "type": "Feature",
  "properties": {
    "addr:full":"Wellgate Rotherham South Yorkshire S60 1AA",
    "addr:postcode":"s60 1aa",
    "addr:street":"Wellgate",
    "iso:country":"GB",
    "sg:address":"Wellgate",
    "sg:city":"Rotherham",
    "sg:classifiers":[
        {
            "category":"Parking",
            "type":"Transportation"
        },
        {
            "category":"Government",
            "subcategory":"Office",
            "type":"Public Place"
        }
    ],
    "sg:phone":"+44 1709 839956",
    "sg:postcode":"S60 1AA",
    "sg:province":"South Yorkshire",
    "sg:tags":[
        "park",
        "car",
        "local"
    ],
    "wof:name":"Wellgate Multi Storey Car Park",
    "wof:placetype":"venue"
},
  "geometry": {"coordinates":[-1.354243,53.429874],"type":"Point"}
}