{
  "type": "Feature",
  "properties": {
    "iso:country":"GB",
    "sg:address":"Highland Region, Dalgrambich Cottage, Croy",
    "sg:city":"Inverness",
    "sg:classifiers":[
        {
            "category":"Professional",
            "subcategory":"Business Services",
            "type":"Services"
        }
    ],
    "sg:phone":"+44 1667 493608",
    "sg:postcode":"IV1 2PR",
    "sg:province":"Highland",
    "sg:tags":[
        "trade"
    ],
    "wof:name":"Scottish Lands Owners Federation",
    "wof:placetype":"venue"
},
  "geometry": {"coordinates":[-4.0080199242,57.520778656],"type":"Point"}
}