{
  "type": "Feature",
  "properties": {
    "addr:full":"D E C House, 145 Cardiff Road Reading Berkshire RG1 8JF",
    "addr:housenumber":"145",
    "addr:postcode":"rg1 8jf",
    "addr:street":"Cardiff Road",
    "iso:country":"GB",
    "sg:address":"D E C House, 145 Cardiff Road",
    "sg:city":"Reading",
    "sg:classifiers":[
        {
            "category":"Professional",
            "subcategory":"Art Services",
            "type":"Services"
        }
    ],
    "sg:phone":"+44 7860 437274",
    "sg:postcode":"RG1 8JF",
    "sg:province":"Berkshire",
    "sg:tags":[
        "graphic",
        "designer"
    ],
    "wof:name":"J C Graphic",
    "wof:placetype":"venue"
},
  "geometry": {"coordinates":[-0.983442,51.461212],"type":"Point"}
}