{
  "type": "Feature",
  "properties": {
    "addr:full":"29 Ayr Street Troon South Ayrshire KA10 6EB",
    "addr:housenumber":"29",
    "addr:postcode":"ka10 6eb",
    "addr:street":"Ayr Street",
    "iso:country":"GB",
    "sg:address":"29 Ayr Street",
    "sg:city":"Troon",
    "sg:classifiers":[
        {
            "category":"Professional",
            "subcategory":"Lawyer & Legal Services",
            "type":"Services"
        }
    ],
    "sg:phone":"+44 1292 314922",
    "sg:postcode":"KA10 6EB",
    "sg:province":"South Ayrshire",
    "sg:tags":[
        "solicitor"
    ],
    "wof:name":"Waddell & Mackintosh",
    "wof:placetype":"venue"
},
  "geometry": {"coordinates":[-4.6631,55.543461],"type":"Point"}
}