{
  "type": "Feature",
  "properties": {
    "iso:country":"GB",
    "sg:address":"Lake Street",
    "sg:city":"Bolton",
    "sg:classifiers":[
        {
            "category":"Food & Beverages",
            "subcategory":"Bakery",
            "type":"Retail Goods"
        }
    ],
    "sg:postcode":"BL3 6NE",
    "sg:province":"Lancashire",
    "sg:tags":[
        "confectionery"
    ],
    "wof:name":"Franco's Bakery Foods Ltd.",
    "wof:placetype":"venue"
},
  "geometry": {"coordinates":[-2.4302990437,53.5690002441],"type":"Point"}
}