{
  "type": "Feature",
  "properties": {
    "iso:country":"GB",
    "sg:address":"Lushill Farm, Hannington, Highworth",
    "sg:city":"Swindon",
    "sg:classifiers":[
        {
            "category":"Farming",
            "subcategory":"Livestock Farm",
            "type":"Manufacturing & Wholesale Goods"
        }
    ],
    "sg:phone":"+44 1285 810374",
    "sg:postcode":"SN6 7TA",
    "sg:province":"Gloucestershire",
    "sg:tags":[
        "others"
    ],
    "wof:name":"Captain Frederick G Barker",
    "wof:placetype":"venue"
},
  "geometry": {"coordinates":[-1.7480920553,51.6374015808],"type":"Point"}
}