{
  "type": "Feature",
  "properties": {
    "addr:full":"Shave Farm, Donyatt Ilminster Somerset TA19 0SA",
    "addr:postcode":"ta19 0sa",
    "iso:country":"GB",
    "sg:address":"Shave Farm, Donyatt",
    "sg:city":"Ilminster",
    "sg:classifiers":[
        {
            "category":"Farming",
            "subcategory":"Livestock Farm",
            "type":"Manufacturing & Wholesale Goods"
        }
    ],
    "sg:phone":"+44 1460 52317",
    "sg:postcode":"TA19 0SA",
    "sg:province":"Somerset",
    "sg:tags":[
        "others"
    ],
    "wof:name":"Gordon Sutton & Son",
    "wof:placetype":"venue"
},
  "geometry": {"coordinates":[-2.9470829964,50.9240951538],"type":"Point"}
}