{
  "type": "Feature",
  "properties": {
    "iso:country":"GB",
    "sg:address":"1 Poplars Avenue",
    "sg:city":"Hatfield",
    "sg:classifiers":[
        {
            "category":"Manufacturing",
            "subcategory":"Furniture",
            "type":"Manufacturing & Wholesale Goods"
        }
    ],
    "sg:phone":"+44 1707 262547",
    "sg:postcode":"AL10 9RY",
    "sg:province":"Hertfordshire",
    "sg:tags":[
        "polishing",
        "french"
    ],
    "wof:name":"Oaker Restoration",
    "wof:placetype":"venue"
},
  "geometry": {"coordinates":[-0.253493011,51.7589874268],"type":"Point"}
}