{
  "type": "Feature",
  "properties": {
    "iso:country":"GB",
    "sg:address":"39 Ponthaugh, Sherburn Park Est",
    "sg:city":"Rowlands Gill",
    "sg:classifiers":[
        {
            "category":"Building & Trades",
            "subcategory":"Plumbing",
            "type":"Services"
        }
    ],
    "sg:phone":"+44 1207 543904",
    "sg:postcode":"NE39 1AF",
    "sg:province":"Durham",
    "sg:tags":[
        "heating"
    ],
    "wof:name":"Ductinstal Services Ltd",
    "wof:placetype":"venue"
},
  "geometry": {"coordinates":[-1.7397099733,54.9293289185],"type":"Point"}
}