{
  "type": "Feature",
  "properties": {
    "iso:country":"GB",
    "sg:address":"11 Warland Rd",
    "sg:city":"Sevenoaks",
    "sg:classifiers":[
        {
            "category":"Utilities",
            "subcategory":"Fuel Oil & Lpg",
            "type":"Services"
        }
    ],
    "sg:phone":"+44 1474 852112",
    "sg:postcode":"TN15 6LD",
    "sg:province":"Kent",
    "sg:tags":[
        "coal",
        "smokeless"
    ],
    "wof:name":"Cray Fuels Ltd",
    "wof:placetype":"venue"
},
  "geometry": {"coordinates":[0.265757,51.344254],"type":"Point"}
}