{
  "type": "Feature",
  "properties": {
    "addr:full":"17 Lawrence Road, Ramsey Huntingdon Cambridgeshire PE26 1UY",
    "addr:housenumber":"17",
    "addr:postcode":"pe26 1uy",
    "addr:street":"Lawrence Road",
    "iso:country":"GB",
    "sg:address":"17 Lawrence Road, Ramsey",
    "sg:city":"Huntingdon",
    "sg:classifiers":[
        {
            "category":"Professional",
            "type":"Services"
        },
        {
            "category":"Conference Center",
            "type":"Public Place"
        }
    ],
    "sg:postcode":"PE26 1UY",
    "sg:province":"Cambridgeshire",
    "sg:tags":[
        "related"
    ],
    "wof:name":"ACCOMMODATING TRAVEL SERVICES LTD",
    "wof:placetype":"venue"
},
  "geometry": {"coordinates":[-0.0980819985,52.4503631592],"type":"Point"}
}