{
  "type": "Feature",
  "properties": {
    "addr:full":"Unit 36 Walkers Road, North Moons Moat Redditch Warwickshire B98 9HD",
    "addr:housenumber":"unit 36",
    "addr:postcode":"b98 9hd",
    "addr:street":"Walkers Road North Moons",
    "iso:country":"GB",
    "sg:address":"Unit 36 Walkers Road, North Moons Moat",
    "sg:city":"Redditch",
    "sg:classifiers":[
        {
            "category":"Professional",
            "subcategory":"Computer Services",
            "type":"Services"
        }
    ],
    "sg:postcode":"B98 9HD",
    "sg:province":"Warwickshire",
    "sg:tags":[
        "system",
        "software"
    ],
    "wof:name":"Latham Finishers Ltd",
    "wof:placetype":"venue"
},
  "geometry": {"coordinates":[-1.895059,52.315647],"type":"Point"}
}