{
  "type": "Feature",
  "properties": {
    "addr:full":"Arden House, 121-123 Main Street Bingley West Yorkshire BD16 2ND",
    "addr:housenumber":"121-123",
    "addr:postcode":"bd16 2nd",
    "addr:street":"Main Street",
    "iso:country":"GB",
    "sg:address":"Arden House, 121-123 Main Street",
    "sg:city":"Bingley",
    "sg:classifiers":[
        {
            "category":"Real Estate",
            "subcategory":"Real Estate Agent",
            "type":"Services"
        }
    ],
    "sg:phone":"+44 1274 568240",
    "sg:postcode":"BD16 2ND",
    "sg:province":"West Yorkshire",
    "wof:name":"Halifax Property Services",
    "wof:placetype":"venue"
},
  "geometry": {"coordinates":[-1.8379859924,53.8479881287],"type":"Point"}
}