{
  "type": "Feature",
  "properties": {
    "addr:full":"28 Atlantic Rd, Brixton London Greater London SW9 8JA",
    "addr:housenumber":"28",
    "addr:postcode":"sw9 8ja",
    "addr:street":"Atlantic Rd",
    "iso:country":"GB",
    "sg:address":"28 Atlantic Rd, Brixton",
    "sg:city":"London",
    "sg:classifiers":[
        {
            "category":"Shopping",
            "subcategory":"Pharmacy",
            "type":"Retail Goods"
        }
    ],
    "sg:postcode":"SW9 8JA",
    "sg:province":"Greater London",
    "sg:tags":[
        "toiletry"
    ],
    "wof:name":"Mayo Trading Co Ltd",
    "wof:placetype":"venue"
},
  "geometry": {"coordinates":[-0.1131900027,51.4625282288],"type":"Point"}
}