{
  "type": "Feature",
  "properties": {
    "addr:full":"25 Beaconsfield Road New Malden Surrey KT3 3HY",
    "addr:housenumber":"25",
    "addr:postcode":"kt3 3hy",
    "addr:street":"Beaconsfield Road",
    "iso:country":"GB",
    "sg:address":"25 Beaconsfield Road",
    "sg:city":"New Malden",
    "sg:classifiers":[
        {
            "category":"Building & Trades",
            "subcategory":"Construction",
            "type":"Services"
        }
    ],
    "sg:postcode":"KT3 3HY",
    "sg:province":"Surrey",
    "sg:tags":[
        "builder"
    ],
    "wof:name":"Mace Builders",
    "wof:placetype":"venue"
},
  "geometry": {"coordinates":[-0.2643649876,51.4074325562],"type":"Point"}
}