{
  "type": "Feature",
  "properties": {
    "addr:full":"28 Sandells Avenue Ashford Greater London TW15 1AL",
    "addr:housenumber":"28",
    "addr:postcode":"tw15 1al",
    "addr:street":"Sandells Avenue",
    "iso:country":"GB",
    "sg:address":"28 Sandells Avenue",
    "sg:city":"Ashford",
    "sg:classifiers":[
        {
            "category":"Building & Trades",
            "subcategory":"Construction",
            "type":"Services"
        }
    ],
    "sg:postcode":"TW15 1AL",
    "sg:province":"Greater London",
    "sg:tags":[
        "builder"
    ],
    "wof:name":"Terry Hathaway",
    "wof:placetype":"venue"
},
  "geometry": {"coordinates":[-0.442431,51.431141],"type":"Point"}
}