{
  "type": "Feature",
  "properties": {
    "iso:country":"GB",
    "sg:address":"Unit 2a-2b",
    "sg:city":"Chelmsford",
    "sg:classifiers":[
        {
            "category":"Autos & Motor Vehicles",
            "subcategory":"Fuel & Gas Station",
            "type":"Retail Goods"
        },
        {
            "category":"Professional",
            "subcategory":"Printing & Photocopies",
            "type":"Services"
        }
    ],
    "sg:phone":"+44 1245 352016",
    "sg:postcode":"CM2 9TB",
    "sg:province":"Essex",
    "sg:tags":[
        "engraving",
        "engine",
        "sale"
    ],
    "wof:name":"Clearcut Engraving",
    "wof:placetype":"venue"
},
  "geometry": {"coordinates":[0.4757,51.722511],"type":"Point"}
}