{
  "type": "Feature",
  "properties": {
    "iso:country":"GB",
    "sg:address":"Dunster Road, Chelmsley Wood",
    "sg:city":"Birmingham",
    "sg:classifiers":[
        {
            "category":"Building & Trades",
            "subcategory":"Plumbing",
            "type":"Services"
        }
    ],
    "sg:phone":"+44 121 788 3366",
    "sg:postcode":"B37 7UU",
    "sg:province":"West Midlands",
    "sg:tags":[
        "heating"
    ],
    "wof:name":"Vaillant Ltd.",
    "wof:placetype":"venue"
},
  "geometry": {"coordinates":[-1.729871,52.480473],"type":"Point"}
}