{
  "type": "Feature",
  "properties": {
    "addr:full":"341 High Street Hayes Greater London UB3 5DQ",
    "addr:housenumber":"341",
    "addr:postcode":"ub3 5dq",
    "addr:street":"High Street",
    "iso:country":"GB",
    "sg:address":"341 High Street",
    "sg:city":"Hayes",
    "sg:classifiers":[
        {
            "category":"Parking",
            "type":"Transportation"
        }
    ],
    "sg:postcode":"UB3 5DQ",
    "sg:province":"Greater London",
    "sg:tags":[
        "car",
        "park"
    ],
    "wof:name":"Stor-A-Car",
    "wof:placetype":"venue"
},
  "geometry": {"coordinates":[-0.4349319935,51.4860534668],"type":"Point"}
}