{
  "type": "Feature",
  "properties": {
    "addr:full":"New Park House, 51 Preston New Road Blackburn Lancashire BB2 6AE",
    "addr:housenumber":"51",
    "addr:postcode":"bb2 6ae",
    "addr:street":"Preston New Road",
    "iso:country":"GB",
    "sg:address":"New Park House, 51 Preston New Road",
    "sg:city":"Blackburn",
    "sg:classifiers":[
        {
            "category":"Professional",
            "subcategory":"Accounting & Tax Preparation",
            "type":"Services"
        }
    ],
    "sg:phone":"+44 1254 699225",
    "sg:postcode":"BB2 6AE",
    "sg:province":"Lancashire",
    "sg:tags":[
        "accountant"
    ],
    "wof:name":"Shaws",
    "wof:placetype":"venue"
},
  "geometry": {"coordinates":[-2.489023,53.751717],"type":"Point"}
}