{
  "type": "Feature",
  "properties": {
    "addr:full":"Main Street, Parton Whitehaven Cumbria CA28 6NY",
    "addr:postcode":"ca28 6ny",
    "addr:street":"Main Street;Whitehaven",
    "iso:country":"GB",
    "sg:address":"Main Street, Parton",
    "sg:city":"Whitehaven",
    "sg:classifiers":[
        {
            "category":"Bars & Pubs",
            "type":"Food & Drink"
        },
        {
            "category":"Community Center",
            "subcategory":"Social",
            "type":"Public Place"
        }
    ],
    "sg:phone":"+44 1946 694427",
    "sg:postcode":"CA28 6NY",
    "sg:province":"Cumbria",
    "sg:tags":[
        "pubs",
        "house",
        "inn",
        "activity"
    ],
    "wof:name":"Lowther Arms",
    "wof:placetype":"venue"
},
  "geometry": {"coordinates":[-3.581193924,54.5671882629],"type":"Point"}
}