{
  "type": "Feature",
  "properties": {
    "addr:full":"17 Highclere Drive Hemel Hempstead Hertfordshire HP3 8BY",
    "addr:housenumber":"17",
    "addr:postcode":"hp3 8by",
    "addr:street":"Highclere Drive",
    "iso:country":"GB",
    "sg:address":"17 Highclere Drive",
    "sg:city":"Hemel Hempstead",
    "sg:classifiers":[
        {
            "category":"Recreation",
            "subcategory":"Fishing",
            "type":"Entertainment"
        }
    ],
    "sg:postcode":"HP3 8BY",
    "sg:province":"Hertfordshire",
    "sg:tags":[
        "angling"
    ],
    "wof:name":"Angling Club",
    "wof:placetype":"venue"
},
  "geometry": {"coordinates":[-0.442558,51.737301],"type":"Point"}
}