{
  "type": "Feature",
  "properties": {
    "iso:country":"GB",
    "sg:address":"A5 Bamford Village Precint, Norden Road",
    "sg:city":"Rochdale",
    "sg:classifiers":[
        {
            "category":"Retail",
            "subcategory":"Laundry & Dry Cleaning",
            "type":"Services"
        }
    ],
    "sg:postcode":"OL11 5QY",
    "sg:province":"Lancashire",
    "sg:tags":[
        "alteration"
    ],
    "wof:name":"Bamford Dry Cleaners",
    "wof:placetype":"venue"
},
  "geometry": {"coordinates":[-2.2079,53.614441],"type":"Point"}
}