{
  "type": "Feature",
  "properties": {
    "iso:country":"GB",
    "sg:address":"40 West Dean",
    "sg:city":"Salisbury",
    "sg:classifiers":[
        {
            "category":"Home & Garden",
            "subcategory":"Building Materials",
            "type":"Retail Goods"
        }
    ],
    "sg:phone":"+44 1794 884990",
    "sg:postcode":"SP5 1HP",
    "sg:province":"Dorset",
    "sg:tags":[
        "gate",
        "door",
        "barrier"
    ],
    "wof:name":"Acoustic Materials Technology Ltd",
    "wof:placetype":"venue"
},
  "geometry": {"coordinates":[-1.66171,51.034382],"type":"Point"}
}