{
  "type": "Feature",
  "properties": {
    "addr:full":"7 St Botolphs Street Colchester Essex CO2 7DU",
    "addr:housenumber":"7",
    "addr:postcode":"co2 7du",
    "addr:street":"St Botolphs Street",
    "iso:country":"GB",
    "sg:address":"7 St Botolphs Street",
    "sg:city":"Colchester",
    "sg:classifiers":[
        {
            "category":"Professional",
            "subcategory":"Lawyer & Legal Services",
            "type":"Services"
        }
    ],
    "sg:phone":"+44 1206 560864",
    "sg:postcode":"CO2 7DU",
    "sg:province":"Essex",
    "sg:tags":[
        "advice",
        "counselling"
    ],
    "wof:name":"Shelter Housing Aid Centre",
    "wof:placetype":"venue"
},
  "geometry": {"coordinates":[0.9031890035,51.887512207],"type":"Point"}
}