{
  "type": "Feature",
  "properties": {
    "iso:country":"GB",
    "sg:address":"Apex Works, Charles St",
    "sg:city":"Huddersfield",
    "sg:classifiers":[
        {
            "category":"Professional",
            "type":"Services"
        }
    ],
    "sg:phone":"+44 1484 460550",
    "sg:postcode":"HD4 5RR",
    "sg:province":"West Yorkshire",
    "sg:tags":[
        "exhibition"
    ],
    "wof:name":"Solstice Exhibitions",
    "wof:placetype":"venue"
},
  "geometry": {"coordinates":[-1.81209,53.638401],"type":"Point"}
}