{
  "type": "Feature",
  "properties": {
    "iso:country":"GB",
    "sg:address":"Laurel Green",
    "sg:city":"Cwmbran",
    "sg:classifiers":[
        {
            "category":"Government",
            "subcategory":"Office",
            "type":"Public Place"
        }
    ],
    "sg:phone":"+44 1633 483533",
    "sg:postcode":"NP44 5TL",
    "sg:province":"Monmouthshire",
    "sg:tags":[
        "local"
    ],
    "wof:name":"Laurel Green Sheltered Housing",
    "wof:placetype":"venue"
},
  "geometry": {"coordinates":[-3.042529,51.662941],"type":"Point"}
}