{
  "type": "Feature",
  "properties": {
    "addr:full":"24 Courtney Road Croydon Surrey CR0 4LS",
    "addr:housenumber":"24",
    "addr:postcode":"cr0 4ls",
    "addr:street":"Courtney Road",
    "iso:country":"GB",
    "sg:address":"24 Courtney Road",
    "sg:city":"Croydon",
    "sg:classifiers":[
        {
            "category":"Building & Trades",
            "subcategory":"Plumbing",
            "type":"Services"
        }
    ],
    "sg:phone":"+44 20 8688 2706",
    "sg:postcode":"CR0 4LS",
    "sg:province":"Surrey",
    "sg:tags":[
        "heating"
    ],
    "wof:name":"A Watkins Plumbing",
    "wof:placetype":"venue"
},
  "geometry": {"coordinates":[-0.1145600006,51.3705406189],"type":"Point"}
}