{
  "type": "Feature",
  "properties": {
    "addr:full":"186 Tulse Hill London Greater London SW2 3BU",
    "addr:housenumber":"186",
    "addr:postcode":"sw2 3bu",
    "addr:street":"Tulse Hill",
    "iso:country":"GB",
    "sg:address":"186 Tulse Hill",
    "sg:city":"London",
    "sg:classifiers":[
        {
            "category":"Taxi",
            "type":"Transportation"
        }
    ],
    "sg:postcode":"SW2 3BU",
    "sg:province":"Greater London",
    "sg:tags":[
        "mini",
        "cab"
    ],
    "wof:name":"Tulse Hill Cars",
    "wof:placetype":"venue"
},
  "geometry": {"coordinates":[-0.107483,51.441139],"type":"Point"}
}