{
  "type": "Feature",
  "properties": {
    "addr:full":"50 The Blvd Lytham St Annes Lancashire FY8 1EL",
    "addr:housenumber":"50",
    "addr:postcode":"fy8 1el",
    "addr:street":"The Blvd;St",
    "iso:country":"GB",
    "sg:address":"50 The Blvd",
    "sg:city":"Lytham St Annes",
    "sg:classifiers":[
        {
            "category":"Food & Beverages",
            "subcategory":"Liquor & Beverages",
            "type":"Retail Goods"
        }
    ],
    "sg:postcode":"FY8 1EL",
    "sg:province":"Lancashire",
    "sg:tags":[
        "beer",
        "spirit",
        "wines"
    ],
    "wof:name":"Ronald Brown",
    "wof:placetype":"venue"
},
  "geometry": {"coordinates":[-3.015159,53.743084],"type":"Point"}
}