{
  "type": "Feature",
  "properties": {
    "iso:country":"GB",
    "sg:address":"The Melody, Henthorne St",
    "sg:city":"Blackpool",
    "sg:classifiers":[
        {
            "category":"Education",
            "subcategory":"Dance Studio",
            "type":"Public Place"
        }
    ],
    "sg:phone":"+44 1253 393736",
    "sg:postcode":"FY1 3RH",
    "sg:province":"Lancashire",
    "sg:tags":[
        "school",
        "dancing"
    ],
    "wof:name":"Rayners School Of Dancing",
    "wof:placetype":"venue"
},
  "geometry": {"coordinates":[-3.050718,53.809101],"type":"Point"}
}