{
  "type": "Feature",
  "properties": {
    "addr:full":"Orford Green Warrington Cheshire WA2 8PB",
    "addr:postcode":"wa2 8pb",
    "addr:street":"Orford Green",
    "iso:country":"GB",
    "sg:address":"Orford Green",
    "sg:city":"Warrington",
    "sg:classifiers":[
        {
            "category":"Autos & Motor Vehicles",
            "subcategory":"Fuel & Gas Station",
            "type":"Retail Goods"
        }
    ],
    "sg:postcode":"WA2 8PB",
    "sg:province":"Cheshire",
    "sg:tags":[
        "petrol",
        "filling"
    ],
    "wof:name":"Orford Green Service Station",
    "wof:placetype":"venue"
},
  "geometry": {"coordinates":[-2.5771439075,53.4066772461],"type":"Point"}
}