{
  "type": "Feature",
  "properties": {
    "addr:full":"Hilton Of Aldie, Fossoway Kinross Clackmannanshire KY13 0QJ",
    "addr:postcode":"ky13 0qj",
    "iso:country":"GB",
    "sg:address":"Hilton Of Aldie, Fossoway",
    "sg:city":"Kinross",
    "sg:classifiers":[
        {
            "category":"Farming",
            "subcategory":"Farm",
            "type":"Manufacturing & Wholesale Goods"
        }
    ],
    "sg:postcode":"KY13 0QJ",
    "sg:province":"Clackmannanshire",
    "sg:tags":[
        "mixed",
        "crop"
    ],
    "wof:name":"Aldie Associates Ltd.",
    "wof:placetype":"venue"
},
  "geometry": {"coordinates":[-3.5660290718,56.2003440857],"type":"Point"}
}