{
  "type": "Feature",
  "properties": {
    "addr:full":"436 Coventry Road, Small Heath Birmingham West Midlands B10 0UG",
    "addr:housenumber":"436",
    "addr:postcode":"b10 0ug",
    "addr:street":"Coventry Road",
    "iso:country":"GB",
    "sg:address":"436 Coventry Road, Small Heath",
    "sg:city":"Birmingham",
    "sg:classifiers":[
        {
            "category":"Shopping",
            "subcategory":"Books",
            "type":"Retail Goods"
        }
    ],
    "sg:phone":"+44 121 753 1889",
    "sg:postcode":"B10 0UG",
    "sg:province":"West Midlands",
    "sg:tags":[
        "bookseller",
        "retailer"
    ],
    "wof:name":"Al Hidaayah Publishing & Distribution Ltd.",
    "wof:placetype":"venue"
},
  "geometry": {"coordinates":[-1.860306,52.470592],"type":"Point"}
}