{
  "type": "Feature",
  "properties": {
    "iso:country":"GB",
    "sg:address":"Oakley Barn, Gamblesby Penrith",
    "sg:city":"Penrith",
    "sg:classifiers":[
        {
            "category":"Shopping",
            "subcategory":"Musical Instruments",
            "type":"Retail Goods"
        }
    ],
    "sg:phone":"+44 1768 881934",
    "sg:postcode":"CA10 1HR",
    "sg:province":"Cumbria",
    "wof:name":"Oakley Sound Systems",
    "wof:placetype":"venue"
},
  "geometry": {"coordinates":[-2.607501,54.747902],"type":"Point"}
}