{
  "type": "Feature",
  "properties": {
    "iso:country":"GB",
    "sg:address":"34 Arundel Gardens",
    "sg:city":"Edgware",
    "sg:classifiers":[
        {
            "category":"Building & Trades",
            "subcategory":"Cleaning & Sanitation",
            "type":"Services"
        }
    ],
    "sg:phone":"+44 20 8906 4551",
    "sg:postcode":"HA8 0RL",
    "sg:province":"Greater London",
    "sg:tags":[
        "cleaner",
        "window"
    ],
    "wof:name":"M Anderson",
    "wof:placetype":"venue"
},
  "geometry": {"coordinates":[-0.25671,51.60667],"type":"Point"}
}