{
  "type": "Feature",
  "properties": {
    "addr:full":"1 Woodbourne Close Fareham Hampshire PO15 5QG",
    "addr:housenumber":"1",
    "addr:postcode":"po15 5qg",
    "addr:street":"Woodbourne Close",
    "iso:country":"GB",
    "sg:address":"1 Woodbourne Close",
    "sg:city":"Fareham",
    "sg:classifiers":[
        {
            "category":"Professional",
            "subcategory":"Secretarial Services",
            "type":"Services"
        },
        {
            "category":"Communications",
            "type":"Services"
        }
    ],
    "sg:phone":"+44 20 7951 4346",
    "sg:postcode":"PO15 5QG",
    "sg:province":"Hampshire",
    "sg:tags":[
        "data",
        "network"
    ],
    "wof:name":"Britaniascience Uk Ltd.",
    "wof:placetype":"venue"
},
  "geometry": {"coordinates":[-1.211801,50.85191],"type":"Point"}
}