{
  "type": "Feature",
  "properties": {
    "addr:full":"16 Severn Street Welshpool Shropshire SY21 7AD",
    "addr:housenumber":"16",
    "addr:postcode":"sy21 7ad",
    "addr:street":"Severn Street",
    "iso:country":"GB",
    "sg:address":"16 Severn Street",
    "sg:city":"Welshpool",
    "sg:classifiers":[
        {
            "category":"Manufacturing",
            "subcategory":"Signs",
            "type":"Manufacturing & Wholesale Goods"
        }
    ],
    "sg:phone":"+44 1938 552541",
    "sg:postcode":"SY21 7AD",
    "sg:province":"Shropshire",
    "sg:tags":[
        "nameplate"
    ],
    "wof:name":"Mid Wales Display",
    "wof:placetype":"venue"
},
  "geometry": {"coordinates":[-3.145089,52.658585],"type":"Point"}
}