{
  "type": "Feature",
  "properties": {
    "iso:country":"GB",
    "sg:address":"7 Park Grange Croft",
    "sg:city":"Sheffield",
    "sg:classifiers":[
        {
            "category":"Social Services",
            "subcategory":"Job Training",
            "type":"Services"
        }
    ],
    "sg:phone":"+44 114 275 8851",
    "sg:postcode":"S2 3QJ",
    "sg:province":"South Yorkshire",
    "sg:tags":[
        "translator",
        "interpreter"
    ],
    "wof:name":"Ayropa International",
    "wof:placetype":"venue"
},
  "geometry": {"coordinates":[-1.458321,53.370609],"type":"Point"}
}