{
  "type": "Feature",
  "properties": {
    "iso:country":"GB",
    "sg:address":"Richmond House, 24 Richmond Road",
    "sg:city":"Solihull",
    "sg:classifiers":[
        {
            "category":"Banks & Credit Unions",
            "subcategory":"Financial Services",
            "type":"Services"
        }
    ],
    "sg:phone":"+44 121 764 4747",
    "sg:postcode":"B92 7RP",
    "sg:province":"West Midlands",
    "sg:tags":[
        "adviser",
        "independent",
        "consultant"
    ],
    "wof:name":"A S J Financial Services Ltd.",
    "wof:placetype":"venue"
},
  "geometry": {"coordinates":[-1.804414,52.440334],"type":"Point"}
}