{
  "type": "Feature",
  "properties": {
    "iso:country":"GB",
    "sg:address":"New House Farm",
    "sg:city":"Newcastle",
    "sg:classifiers":[
        {
            "category":"Building & Trades",
            "subcategory":"Construction",
            "type":"Services"
        }
    ],
    "sg:phone":"+44 1782 680221",
    "sg:postcode":"ST5 5HY",
    "sg:province":"Staffordshire",
    "sg:tags":[
        "roofing"
    ],
    "wof:name":"Buckley Building Contractors",
    "wof:placetype":"venue"
},
  "geometry": {"coordinates":[-2.293019,52.975277],"type":"Point"}
}