{
  "type": "Feature",
  "properties": {
    "iso:country":"GB",
    "sg:address":"75 Victoria Drive",
    "sg:city":"Bognor Regis",
    "sg:classifiers":[
        {
            "category":"Health Services",
            "subcategory":"Nursing And Care Facility",
            "type":"Services"
        },
        {
            "category":"Organizations",
            "subcategory":"Community Association",
            "type":"Services"
        }
    ],
    "sg:phone":"+44 1243 829156",
    "sg:postcode":"PO21 2TD",
    "sg:province":"West Sussex",
    "sg:tags":[
        "co-operatives",
        "residential",
        "housing",
        "trust",
        "society"
    ],
    "sg:website":"http://www.echg.org.uk",
    "wof:name":"English Churches Housing Group Ltd.",
    "wof:placetype":"venue"
},
  "geometry": {"coordinates":[-0.6824989915,50.7836799622],"type":"Point"}
}