{
  "type": "Feature",
  "properties": {
    "addr:full":"Pasture Lane, Hathern Loughborough Leicestershire LE12 5LJ",
    "addr:postcode":"le12 5lj",
    "addr:street":"Pasture Lane",
    "iso:country":"GB",
    "sg:address":"Pasture Lane, Hathern",
    "sg:city":"Loughborough",
    "sg:classifiers":[
        {
            "category":"Education",
            "subcategory":"School",
            "type":"Public Place"
        }
    ],
    "sg:phone":"+44 1509 842569",
    "sg:postcode":"LE12 5LJ",
    "sg:province":"Leicestershire",
    "sg:tags":[
        "local",
        "authority"
    ],
    "wof:name":"Hathern C Of E Primary School",
    "wof:placetype":"venue"
},
  "geometry": {"coordinates":[-1.252029,52.79739],"type":"Point"}
}