{
  "type": "Feature",
  "properties": {
    "addr:full":"5 Monyash Close Ilkeston Derbyshire DE7 8PR",
    "addr:housenumber":"5",
    "addr:postcode":"de7 8pr",
    "addr:street":"Monyash Close",
    "iso:country":"GB",
    "sg:address":"5 Monyash Close",
    "sg:city":"Ilkeston",
    "sg:classifiers":[
        {
            "category":"Social Services",
            "subcategory":"Adult Care",
            "type":"Services"
        },
        {
            "category":"Government",
            "subcategory":"Office",
            "type":"Public Place"
        }
    ],
    "sg:phone":"+44 115 932 6249",
    "sg:postcode":"DE7 8PR",
    "sg:province":"Derbyshire",
    "sg:tags":[
        "housing",
        "local",
        "sheltered"
    ],
    "wof:name":"Monyash Close Sheltered Housing",
    "wof:placetype":"venue"
},
  "geometry": {"coordinates":[-1.3133579493,52.9866790771],"type":"Point"}
}