{
  "type": "Feature",
  "properties": {
    "addr:full":"Unit 5 Coulson Street Industrial Estate Spennymoor Durham DL16 7RF",
    "addr:housenumber":"unit 5",
    "addr:postcode":"estate;dl16 7rf",
    "addr:street":"Coulson Street Industrial",
    "iso:country":"GB",
    "sg:address":"Unit 5 Coulson Street Industrial Estate",
    "sg:city":"Spennymoor",
    "sg:classifiers":[
        {
            "category":"Home & Garden",
            "subcategory":"Hardware",
            "type":"Retail Goods"
        }
    ],
    "sg:phone":"+44 1388 812658",
    "sg:postcode":"DL16 7RF",
    "sg:province":"Durham",
    "sg:tags":[
        "paint",
        "coating"
    ],
    "wof:name":"M B K Service Coating",
    "wof:placetype":"venue"
},
  "geometry": {"coordinates":[-1.588591,54.6982],"type":"Point"}
}