{
  "type": "Feature",
  "properties": {
    "iso:country":"GB",
    "sg:address":"Unit 3j, Barlow Way",
    "sg:city":"Rainham",
    "sg:classifiers":[
        {
            "category":"Building & Trades",
            "subcategory":"Cleaning & Sanitation",
            "type":"Services"
        }
    ],
    "sg:phone":"+44 1708 526761",
    "sg:postcode":"RM13 8BT",
    "sg:province":"Essex",
    "sg:tags":[
        "repair",
        "lift",
        "-"
    ],
    "wof:name":"Independent Lift Services Ltd.",
    "wof:placetype":"venue"
},
  "geometry": {"coordinates":[0.1751350015,51.5124816895],"type":"Point"}
}