{
  "type": "Feature",
  "properties": {
    "addr:full":"Stonehouse Farm, Tanyard Lane, Danehill Haywards Heath East Sussex RH17 7JH",
    "addr:postcode":"rh17 7jh",
    "addr:street":"Tanyard Lane",
    "iso:country":"GB",
    "sg:address":"Stonehouse Farm, Tanyard Lane, Danehill",
    "sg:city":"Haywards Heath",
    "sg:classifiers":[
        {
            "category":"Building & Trades",
            "subcategory":"Equipment Rental",
            "type":"Services"
        }
    ],
    "sg:postcode":"RH17 7JH",
    "sg:province":"East Sussex",
    "sg:tags":[
        "plant",
        "machinery"
    ],
    "wof:name":"Hirequip",
    "wof:placetype":"venue"
},
  "geometry": {"coordinates":[-0.001074,51.0313110352],"type":"Point"}
}