{
  "type": "Feature",
  "properties": {
    "addr:full":"150 Falcon Rd London Greater London SW11 2LW",
    "addr:housenumber":"150",
    "addr:postcode":"sw11 2lw",
    "addr:street":"Falcon Rd",
    "iso:country":"GB",
    "sg:address":"150 Falcon Rd",
    "sg:city":"London",
    "sg:classifiers":[
        {
            "category":"Shopping",
            "subcategory":"Florist",
            "type":"Retail Goods"
        }
    ],
    "sg:postcode":"SW11 2LW",
    "sg:province":"Greater London",
    "wof:name":"Ritchie,Peter,",
    "wof:placetype":"venue"
},
  "geometry": {"coordinates":[-0.168109,51.464138],"type":"Point"}
}