{
  "type": "Feature",
  "properties": {
    "addr:full":"Temple Court House, Church Street Romsey Hampshire SO51 8JH",
    "addr:postcode":"so51 8jh",
    "addr:street":"Temple;Church Street",
    "iso:country":"GB",
    "sg:address":"Temple Court House, Church Street",
    "sg:city":"Romsey",
    "sg:classifiers":[
        {
            "category":"Banks & Credit Unions",
            "subcategory":"Financial Services",
            "type":"Services"
        }
    ],
    "sg:phone":"+44 1794 830808",
    "sg:postcode":"SO51 8JH",
    "sg:province":"Hampshire",
    "sg:tags":[
        "adviser"
    ],
    "wof:name":"Temple Court (U K) Ltd.",
    "wof:placetype":"venue"
},
  "geometry": {"coordinates":[-1.500231,50.990852],"type":"Point"}
}