{
  "type": "Feature",
  "properties": {
    "iso:country":"GB",
    "sg:address":"5 Lechlade Road",
    "sg:city":"Faringdon",
    "sg:classifiers":[
        {
            "category":"Professional",
            "subcategory":"Engineering",
            "type":"Services"
        },
        {
            "category":"Farming",
            "subcategory":"Livestock Farm",
            "type":"Manufacturing & Wholesale Goods"
        }
    ],
    "sg:phone":"+44 1367 240224",
    "sg:postcode":"SN7 8AL",
    "sg:province":"Oxfordshire",
    "sg:tags":[
        "others"
    ],
    "wof:name":"Tetronics Ltd.",
    "wof:placetype":"venue"
},
  "geometry": {"coordinates":[-1.589272,51.658146],"type":"Point"}
}