{
  "type": "Feature",
  "properties": {
    "addr:full":"23 High Street Bridgnorth Shropshire WV16 4DB",
    "addr:housenumber":"23",
    "addr:postcode":"wv16 4db",
    "addr:street":"High Street",
    "iso:country":"GB",
    "sg:address":"23 High Street",
    "sg:city":"Bridgnorth",
    "sg:classifiers":[
        {
            "category":"Shopping",
            "subcategory":"Shoes",
            "type":"Retail Goods"
        }
    ],
    "sg:postcode":"WV16 4DB",
    "sg:province":"Shropshire",
    "sg:tags":[
        "shop"
    ],
    "wof:name":"van Twist F A Ltd.",
    "wof:placetype":"venue"
},
  "geometry": {"coordinates":[-2.420154,52.535652],"type":"Point"}
}