{
  "type": "Feature",
  "properties": {
    "iso:country":"GB",
    "sg:address":"Unit 15, Armstrong Close",
    "sg:city":"St. Leonards On Sea",
    "sg:classifiers":[
        {
            "category":"Farming",
            "subcategory":"Farm",
            "type":"Manufacturing & Wholesale Goods"
        }
    ],
    "sg:phone":"+44 1424 853055",
    "sg:postcode":"TN38 9ST",
    "sg:province":"East Sussex",
    "sg:tags":[
        "agricultural"
    ],
    "wof:name":"Philip G Turner",
    "wof:placetype":"venue"
},
  "geometry": {"coordinates":[0.532001,50.876408],"type":"Point"}
}