{
  "type": "Feature",
  "properties": {
    "iso:country":"GB",
    "sg:address":"24 Monks Park Avenue",
    "sg:city":"Bristol",
    "sg:classifiers":[
        {
            "category":"Health Services",
            "subcategory":"Doctor",
            "type":"Services"
        }
    ],
    "sg:phone":"+44 117 969 3106",
    "sg:postcode":"BS7 0UE",
    "sg:province":"City of Bristol",
    "sg:tags":[
        "practitioners"
    ],
    "wof:name":"Avon Health",
    "wof:placetype":"venue"
},
  "geometry": {"coordinates":[-2.58345294,51.4976119995],"type":"Point"}
}