{
  "type": "Feature",
  "properties": {
    "addr:full":"Fiarwinds Green Lane, Whitfield Dover Kent CT16 3ER",
    "addr:postcode":"ct16 3er",
    "addr:street":"Green Lane;Dover",
    "iso:country":"GB",
    "sg:address":"Fiarwinds Green Lane, Whitfield",
    "sg:city":"Dover",
    "sg:classifiers":[
        {
            "category":"Retail",
            "subcategory":"Driving School",
            "type":"Services"
        }
    ],
    "sg:phone":"+44 1304 821759",
    "sg:postcode":"CT16 3ER",
    "sg:province":"Kent",
    "wof:name":"Acorn Driving School",
    "wof:placetype":"venue"
},
  "geometry": {"coordinates":[1.2807600498,51.1590118408],"type":"Point"}
}