{
  "type": "Feature",
  "properties": {
    "addr:full":"103 Bure Lane Christchurch Dorset BH23 4DN",
    "addr:housenumber":"103",
    "addr:postcode":"bh23 4dn",
    "addr:street":"Bure Lane",
    "iso:country":"GB",
    "sg:address":"103 Bure Lane",
    "sg:city":"Christchurch",
    "sg:classifiers":[
        {
            "category":"Shopping",
            "subcategory":"Department Store",
            "type":"Retail Goods"
        }
    ],
    "sg:phone":"+44 1425 272940",
    "sg:postcode":"BH23 4DN",
    "sg:province":"Dorset",
    "wof:name":"Bure Stores",
    "wof:placetype":"venue"
},
  "geometry": {"coordinates":[-1.734,50.735283],"type":"Point"}
}