{
  "type": "Feature",
  "properties": {
    "addr:full":"9 Fountains Close Feltham Greater London TW13 5PA",
    "addr:housenumber":"9",
    "addr:postcode":"tw13 5pa",
    "addr:street":"Fountains Close",
    "iso:country":"GB",
    "sg:address":"9 Fountains Close",
    "sg:city":"Feltham",
    "sg:classifiers":[
        {
            "category":"Building & Trades",
            "subcategory":"Construction",
            "type":"Services"
        }
    ],
    "sg:postcode":"TW13 5PA",
    "sg:province":"Greater London",
    "sg:tags":[
        "builder"
    ],
    "wof:name":"C J Builders",
    "wof:placetype":"venue"
},
  "geometry": {"coordinates":[-0.3770940006,51.4399986267],"type":"Point"}
}