{
  "type": "Feature",
  "properties": {
    "addr:full":"45 Stonegate York North Yorkshire YO1 8AW",
    "addr:housenumber":"45",
    "addr:postcode":"yo1 8aw",
    "addr:street":"Stonegate",
    "iso:country":"GB",
    "sg:address":"45 Stonegate",
    "sg:city":"York",
    "sg:classifiers":[
        {
            "category":"Shopping",
            "subcategory":"Jewelry",
            "type":"Retail Goods"
        },
        {
            "category":"Shopping",
            "subcategory":"Comic Books",
            "type":"Retail Goods"
        }
    ],
    "sg:phone":"+44 1904 623862",
    "sg:postcode":"YO1 8AW",
    "sg:province":"North Yorkshire",
    "sg:tags":[
        "jeweller",
        "sale",
        "jewellery"
    ],
    "wof:name":"Barbara Cattle",
    "wof:placetype":"venue"
},
  "geometry": {"coordinates":[-1.082968,53.961014],"type":"Point"}
}