{
  "type": "Feature",
  "properties": {
    "addr:full":"36a High Street Newcastle Staffordshire ST5 0HE",
    "addr:housenumber":"36a",
    "addr:postcode":"st5 0he",
    "addr:street":"High Street",
    "iso:country":"GB",
    "sg:address":"36a High Street",
    "sg:city":"Newcastle",
    "sg:classifiers":[
        {
            "category":"Cafe",
            "type":"Food & Drink"
        }
    ],
    "sg:postcode":"ST5 0HE",
    "sg:province":"Staffordshire",
    "sg:tags":[
        "tea",
        "room"
    ],
    "wof:name":"Cosy Kitchen Cafe & Take Away",
    "wof:placetype":"venue"
},
  "geometry": {"coordinates":[-2.218725,53.032135],"type":"Point"}
}