{
  "type": "Feature",
  "properties": {
    "iso:country":"GB",
    "sg:address":"Maes-y-deri",
    "sg:city":"Aberdare",
    "sg:classifiers":[
        {
            "category":"Education",
            "subcategory":"School",
            "type":"Public Place"
        }
    ],
    "sg:phone":"+44 1685 882577",
    "sg:postcode":"CF44 6AJ",
    "sg:province":"Neath Port Talbot",
    "sg:tags":[
        "local",
        "authority"
    ],
    "wof:name":"Oaklands County Primary School",
    "wof:placetype":"venue"
},
  "geometry": {"coordinates":[-3.426113,51.696957],"type":"Point"}
}