{
  "type": "Feature",
  "properties": {
    "addr:full":"5 Laburnum Close, North Baddesley Southampton Hampshire SO52 9JT",
    "addr:housenumber":"5",
    "addr:postcode":"so52 9jt",
    "addr:street":"Laburnum Close",
    "iso:country":"GB",
    "sg:address":"5 Laburnum Close, North Baddesley",
    "sg:city":"Southampton",
    "sg:classifiers":[
        {
            "category":"Retail",
            "subcategory":"Repair Shop",
            "type":"Services"
        }
    ],
    "sg:phone":"+44 23 8073 5201",
    "sg:postcode":"SO52 9JT",
    "sg:province":"Hampshire",
    "sg:tags":[
        "maintenance"
    ],
    "wof:name":"House Repairs",
    "wof:placetype":"venue"
},
  "geometry": {"coordinates":[-1.4410040379,50.9786453247],"type":"Point"}
}