{
  "type": "Feature",
  "properties": {
    "iso:country":"GB",
    "sg:address":"1 Penketh Place, Pimbo Industrial Estate",
    "sg:city":"Skelmersdale",
    "sg:classifiers":[
        {
            "category":"Home & Garden",
            "subcategory":"Hardware",
            "type":"Retail Goods"
        }
    ],
    "sg:phone":"+44 1695 720535",
    "sg:postcode":"WN8 9QX",
    "sg:province":"Lancashire",
    "sg:tags":[
        "component",
        "electronic"
    ],
    "wof:name":"L E M U K Ltd.",
    "wof:placetype":"venue"
},
  "geometry": {"coordinates":[-2.769431,53.533123],"type":"Point"}
}