{
  "type": "Feature",
  "properties": {
    "addr:full":"487 New Chester Rd, Bromborough Wirral Cheshire CH62 3LB",
    "addr:housenumber":"487",
    "addr:postcode":"ch62 3lb",
    "addr:street":"New Chester Rd",
    "iso:country":"GB",
    "sg:address":"487 New Chester Rd, Bromborough",
    "sg:city":"Wirral",
    "sg:classifiers":[
        {
            "category":"Professional",
            "subcategory":"Accounting & Tax Preparation",
            "type":"Services"
        }
    ],
    "sg:phone":"+44 151 334 3685",
    "sg:postcode":"CH62 3LB",
    "sg:province":"Cheshire",
    "sg:tags":[
        "accountant"
    ],
    "wof:name":"R.M Phelan",
    "wof:placetype":"venue"
},
  "geometry": {"coordinates":[-2.9855189323,53.3459587097],"type":"Point"}
}