{
  "type": "Feature",
  "properties": {
    "addr:full":"Unit 10 Redditch Warwickshire B98 9PA",
    "addr:housenumber":"unit 10",
    "addr:postcode":"b98 9pa",
    "iso:country":"GB",
    "sg:address":"Unit 10",
    "sg:city":"Redditch",
    "sg:classifiers":[
        {
            "category":"Communications",
            "type":"Services"
        }
    ],
    "sg:phone":"+44 1527 528822",
    "sg:postcode":"B98 9PA",
    "sg:province":"Warwickshire",
    "sg:tags":[
        "system",
        "music",
        "public",
        "address"
    ],
    "wof:name":"S S E Hire Ltd.",
    "wof:placetype":"venue"
},
  "geometry": {"coordinates":[-1.892979,52.318451],"type":"Point"}
}