{
  "type": "Feature",
  "properties": {
    "iso:country":"GB",
    "sg:address":"Darnall Rd",
    "sg:city":"Sheffield",
    "sg:classifiers":[
        {
            "category":"Community Center",
            "type":"Public Place"
        }
    ],
    "sg:phone":"+44 114 244 1475",
    "sg:postcode":"S9 5AF",
    "sg:province":"South Yorkshire",
    "sg:tags":[
        "centre"
    ],
    "wof:name":"Star Works Community Centre",
    "wof:placetype":"venue"
},
  "geometry": {"coordinates":[-1.410154,53.387859],"type":"Point"}
}