{
  "type": "Feature",
  "properties": {
    "addr:full":"10 New Kingsway, Weston Coyney Stoke-on-trent Staffordshire ST3 6NA",
    "addr:housenumber":"10",
    "addr:postcode":"staffordshire st3 6na",
    "addr:street":"New Kingsway",
    "iso:country":"GB",
    "sg:address":"10 New Kingsway, Weston Coyney",
    "sg:city":"Stoke-on-trent",
    "sg:classifiers":[
        {
            "category":"Personal",
            "subcategory":"Beauty Salon",
            "type":"Services"
        }
    ],
    "sg:phone":"+44 1782 313115",
    "sg:postcode":"ST3 6NA",
    "sg:province":"Staffordshire",
    "sg:tags":[
        "unisex",
        "hairdresser"
    ],
    "wof:name":"New Look",
    "wof:placetype":"venue"
},
  "geometry": {"coordinates":[-2.098697,52.989613],"type":"Point"}
}