{
  "type": "Feature",
  "properties": {
    "addr:full":"15 Rye Walk Ingatestone Essex CM4 9AL",
    "addr:housenumber":"15",
    "addr:postcode":"cm4 9al",
    "addr:street":"Rye Walk",
    "iso:country":"GB",
    "sg:address":"15 Rye Walk",
    "sg:city":"Ingatestone",
    "sg:classifiers":[
        {
            "category":"Health Services",
            "subcategory":"Podiatrist",
            "type":"Services"
        }
    ],
    "sg:phone":"+44 1277 352606",
    "sg:postcode":"CM4 9AL",
    "sg:province":"Essex",
    "sg:tags":[
        "podiatrists",
        "chiropodist"
    ],
    "wof:name":"Jeanne Powell",
    "wof:placetype":"venue"
},
  "geometry": {"coordinates":[0.3729659915,51.6626663208],"type":"Point"}
}