{
  "type": "Feature",
  "properties": {
    "iso:country":"GB",
    "sg:address":"22 Sandy View, Beckington",
    "sg:city":"Frome",
    "sg:classifiers":[
        {
            "category":"Building & Trades",
            "subcategory":"Plumbing",
            "type":"Services"
        },
        {
            "category":"Building & Trades",
            "subcategory":"Construction",
            "type":"Services"
        }
    ],
    "sg:phone":"+44 7778 116964",
    "sg:postcode":"BA11 6TR",
    "sg:province":"Somerset",
    "sg:tags":[
        "plumber",
        "builder"
    ],
    "wof:name":"D F Services",
    "wof:placetype":"venue"
},
  "geometry": {"coordinates":[-2.281978,51.265579],"type":"Point"}
}