{
  "type": "Feature",
  "properties": {
    "addr:full":"The Rectory, High Street Llantwit Major The Vale of Glamorgan CF61 1SS",
    "addr:postcode":"cf61 1ss",
    "addr:street":"High Street;Vale",
    "iso:country":"GB",
    "sg:address":"The Rectory, High Street",
    "sg:city":"Llantwit Major",
    "sg:classifiers":[
        {
            "category":"Place Of Worship",
            "type":"Public Place"
        }
    ],
    "sg:phone":"+44 1446 795551",
    "sg:postcode":"CF61 1SS",
    "sg:province":"The Vale of Glamorgan",
    "wof:name":"The Rectorial Benefice of Llantwit Major",
    "wof:placetype":"venue"
},
  "geometry": {"coordinates":[-3.488492,51.41016],"type":"Point"}
}