{
  "type": "Feature",
  "properties": {
    "addr:full":"8 9 Finedon Sidings Industrial, Estate, Furnace Lane Finedon Wellingborough Northamptonshire NN9 5NY",
    "addr:housenumber":"9",
    "addr:postcode":"nn9 5ny",
    "addr:street":"Sidings Industrial Estate Furnace Lane",
    "iso:country":"GB",
    "sg:address":"8 9 Finedon Sidings Industrial, Estate, Furnace Lane Finedon",
    "sg:city":"Wellingborough",
    "sg:classifiers":[
        {
            "category":"Manufacturing",
            "subcategory":"Rubber & Plastics",
            "type":"Manufacturing & Wholesale Goods"
        }
    ],
    "sg:phone":"+44 1536 723488",
    "sg:postcode":"NN9 5NY",
    "sg:province":"Northamptonshire",
    "sg:tags":[
        "injection",
        "moulding"
    ],
    "wof:name":"Fenton Precision Engineers (Finedon) Ltd.",
    "wof:placetype":"venue"
},
  "geometry": {"coordinates":[-0.6492760181,52.3401908875],"type":"Point"}
}