{
  "type": "Feature",
  "properties": {
    "addr:full":"5 Christchurch Rd Hornsey Greater London N8 9QL",
    "addr:housenumber":"5",
    "addr:postcode":"n8 9ql",
    "addr:street":"Christchurch Rd",
    "iso:country":"GB",
    "sg:address":"5 Christchurch Rd",
    "sg:city":"Hornsey",
    "sg:classifiers":[
        {
            "category":"Shopping",
            "subcategory":"Books",
            "type":"Retail Goods"
        }
    ],
    "sg:phone":"+44 20 8340 2900",
    "sg:postcode":"N8 9QL",
    "sg:province":"Greater London",
    "wof:name":"European Journal of Herbal Medicine",
    "wof:placetype":"venue"
},
  "geometry": {"coordinates":[-0.125544,51.576515],"type":"Point"}
}