{
  "type": "Feature",
  "properties": {
    "iso:country":"GB",
    "sg:address":"23 Walworth Enterprise Centre, Duke Close West Way",
    "sg:city":"Andover",
    "sg:classifiers":[
        {
            "category":"Banks & Credit Unions",
            "subcategory":"Investment Brokerage",
            "type":"Services"
        }
    ],
    "sg:phone":"+44 1264 335969",
    "sg:postcode":"SP10 5AP",
    "sg:province":"Hampshire",
    "wof:name":"Home Investment Services Ltd.",
    "wof:placetype":"venue"
},
  "geometry": {"coordinates":[-1.4767789841,51.2064933777],"type":"Point"}
}