{
  "type": "Feature",
  "properties": {
    "addr:full":"Barn Farm, Stanley Pontlarge Cheltenham Gloucestershire GL54 5HD",
    "addr:postcode":"gl54 5hd",
    "addr:street":"Stanley",
    "iso:country":"GB",
    "sg:address":"Barn Farm, Stanley Pontlarge",
    "sg:city":"Cheltenham",
    "sg:classifiers":[
        {
            "category":"Real Estate",
            "subcategory":"Real Estate Services",
            "type":"Services"
        },
        {
            "category":"Building & Trades",
            "subcategory":"Equipment Rental",
            "type":"Services"
        }
    ],
    "sg:phone":"+44 1242 620064",
    "sg:postcode":"GL54 5HD",
    "sg:province":"Gloucestershire",
    "sg:tags":[
        "hire",
        "leasing",
        "plant",
        "machinery"
    ],
    "wof:name":"R J CLARKE",
    "wof:placetype":"venue"
},
  "geometry": {"coordinates":[-2.00262,51.970539],"type":"Point"}
}