{
  "type": "Feature",
  "properties": {
    "addr:full":"11-13 Scot Lane Doncaster South Yorkshire DN1 1EW",
    "addr:housenumber":"11-13",
    "addr:postcode":"dn1 1ew",
    "addr:street":"Scot Lane",
    "iso:country":"GB",
    "sg:address":"11-13 Scot Lane",
    "sg:city":"Doncaster",
    "sg:classifiers":[
        {
            "category":"Home & Garden",
            "subcategory":"Furniture",
            "type":"Retail Goods"
        }
    ],
    "sg:phone":"+44 1302 341647",
    "sg:postcode":"DN1 1EW",
    "sg:province":"South Yorkshire",
    "wof:name":"Pine & Pieces",
    "wof:placetype":"venue"
},
  "geometry": {"coordinates":[-1.13351,53.523579],"type":"Point"}
}