{
  "type": "Feature",
  "properties": {
    "iso:country":"GB",
    "sg:address":"10 Bentley Mill Lane",
    "sg:city":"Walsall",
    "sg:classifiers":[
        {
            "category":"Building & Trades",
            "subcategory":"Construction",
            "type":"Services"
        }
    ],
    "sg:phone":"+44 1922 623727",
    "sg:postcode":"WS2 0BT",
    "sg:province":"West Midlands",
    "sg:tags":[
        "joiner",
        "carpenter"
    ],
    "wof:name":"J Vincent",
    "wof:placetype":"venue"
},
  "geometry": {"coordinates":[-2.0177109241,52.5835533142],"type":"Point"}
}