{
  "type": "Feature",
  "properties": {
    "addr:full":"6 Manor Park Bristol City of Bristol BS6 7HH",
    "addr:housenumber":"6",
    "addr:postcode":"bs6 7hh",
    "addr:street":"Manor Park",
    "iso:country":"GB",
    "sg:address":"6 Manor Park",
    "sg:city":"Bristol",
    "sg:classifiers":[
        {
            "category":"Professional",
            "type":"Services"
        }
    ],
    "sg:phone":"+44 117 951 9896",
    "sg:postcode":"BS6 7HH",
    "sg:province":"City of Bristol",
    "sg:tags":[
        "caterer"
    ],
    "wof:name":"Swallows Catering Services",
    "wof:placetype":"venue"
},
  "geometry": {"coordinates":[-2.604279,51.479149],"type":"Point"}
}