{
  "type": "Feature",
  "properties": {
    "addr:full":"134 Hertford Road Enfield Greater London EN3 5AX",
    "addr:housenumber":"134",
    "addr:postcode":"en3 5ax",
    "addr:street":"Hertford Road",
    "iso:country":"GB",
    "sg:address":"134 Hertford Road",
    "sg:city":"Enfield",
    "sg:classifiers":[
        {
            "category":"Personal",
            "subcategory":"Beauty Salon",
            "type":"Services"
        }
    ],
    "sg:phone":"+44 20 8804 4298",
    "sg:postcode":"EN3 5AX",
    "sg:province":"Greater London",
    "sg:tags":[
        "unisex",
        "hairdresser"
    ],
    "wof:name":"Heales Hair Gallery",
    "wof:placetype":"venue"
},
  "geometry": {"coordinates":[-0.0482480004,51.6552772522],"type":"Point"}
}