{
  "type": "Feature",
  "properties": {
    "addr:full":"Higher Syke House, Goosnargh Preston Lancashire PR3 2EN",
    "addr:postcode":"pr3 2en",
    "iso:country":"GB",
    "sg:address":"Higher Syke House, Goosnargh",
    "sg:city":"Preston",
    "sg:classifiers":[
        {
            "category":"Farming",
            "subcategory":"Livestock Farm",
            "type":"Manufacturing & Wholesale Goods"
        },
        {
            "category":"Farming",
            "subcategory":"Farm",
            "type":"Manufacturing & Wholesale Goods"
        }
    ],
    "sg:postcode":"PR3 2EN",
    "sg:province":"Lancashire",
    "sg:tags":[
        "mixed",
        "crop",
        "others"
    ],
    "wof:name":"Steven David Hardman",
    "wof:placetype":"venue"
},
  "geometry": {"coordinates":[-2.681129,53.826515],"type":"Point"}
}