{
  "type": "Feature",
  "properties": {
    "iso:country":"GB",
    "sg:address":"136 Cromwell Road",
    "sg:city":"Whitstable",
    "sg:classifiers":[
        {
            "category":"Professional",
            "subcategory":"Detective & Security Services",
            "type":"Services"
        }
    ],
    "sg:phone":"+44 1227 772500",
    "sg:postcode":"CT5 1NQ",
    "sg:province":"Kent",
    "wof:name":"Sabre Security Services",
    "wof:placetype":"venue"
},
  "geometry": {"coordinates":[1.03051,51.359444],"type":"Point"}
}