{
  "type": "Feature",
  "properties": {
    "iso:country":"GB",
    "sg:address":"6c Church Road, Bebington",
    "sg:city":"Wirral",
    "sg:classifiers":[
        {
            "category":"Food & Beverages",
            "subcategory":"Meat & Fish",
            "type":"Retail Goods"
        }
    ],
    "sg:phone":"+44 151 645 2081",
    "sg:postcode":"CH63 7PH",
    "sg:province":"Merseyside",
    "sg:tags":[
        "chip"
    ],
    "wof:name":"Mario's",
    "wof:placetype":"venue"
},
  "geometry": {"coordinates":[-3.003296,53.350067],"type":"Point"}
}