{
  "type": "Feature",
  "properties": {
    "addr:full":"15 Fulmar Ct Leeds West Yorkshire LS10 3HB",
    "addr:housenumber":"15",
    "addr:postcode":"ls10 3hb",
    "addr:street":"Fulmar Ct",
    "iso:country":"GB",
    "sg:address":"15 Fulmar Ct",
    "sg:city":"Leeds",
    "sg:classifiers":[
        {
            "category":"Banks & Credit Unions",
            "subcategory":"Investment Brokerage",
            "type":"Services"
        }
    ],
    "sg:phone":"+44 113 277 7713",
    "sg:postcode":"LS10 3HB",
    "sg:province":"West Yorkshire",
    "sg:tags":[
        "pension"
    ],
    "wof:name":"M B Barton Pension Advisors",
    "wof:placetype":"venue"
},
  "geometry": {"coordinates":[-1.535998,53.750084],"type":"Point"}
}