{
  "type": "Feature",
  "properties": {
    "iso:country":"GB",
    "sg:address":"24 Homefield Road",
    "sg:city":"Walton-on-thames",
    "sg:classifiers":[
        {
            "category":"Retail",
            "subcategory":"Auto Repair",
            "type":"Services"
        }
    ],
    "sg:postcode":"KT12 3RD",
    "sg:province":"Surrey",
    "sg:tags":[
        "engine",
        "car",
        "specialist"
    ],
    "wof:name":"Power 4 Peanuts",
    "wof:placetype":"venue"
},
  "geometry": {"coordinates":[-0.384379,51.387287],"type":"Point"}
}