{
  "type": "Feature",
  "properties": {
    "addr:full":"37 Sun St Moorgate Greater London EC2M 2PL",
    "addr:housenumber":"37",
    "addr:postcode":"ec2m 2pl",
    "addr:street":"Sun St",
    "iso:country":"GB",
    "sg:address":"37 Sun St",
    "sg:city":"Moorgate",
    "sg:classifiers":[
        {
            "category":"Professional",
            "subcategory":"Employment Agencies",
            "type":"Services"
        }
    ],
    "sg:phone":"+44 20 7523 3820",
    "sg:postcode":"EC2M 2PL",
    "sg:province":"Greater London",
    "sg:tags":[
        "consultant"
    ],
    "wof:name":"Zarak Non Executive",
    "wof:placetype":"venue"
},
  "geometry": {"coordinates":[-0.0834409967,51.5200080872],"type":"Point"}
}