{
  "type": "Feature",
  "properties": {
    "addr:full":"54 Gordon St Glasgow Glasgow City G1 3PU",
    "addr:housenumber":"54",
    "addr:postcode":"g1 3pu",
    "addr:street":"Gordon St",
    "iso:country":"GB",
    "sg:address":"54 Gordon St",
    "sg:city":"Glasgow",
    "sg:classifiers":[
        {
            "category":"Banks & Credit Unions",
            "subcategory":"Financial Services",
            "type":"Services"
        }
    ],
    "sg:phone":"+44 141 221 5437",
    "sg:postcode":"G1 3PU",
    "sg:province":"Glasgow City",
    "sg:tags":[
        "consultant"
    ],
    "wof:name":"Davidson Trust Ltd",
    "wof:placetype":"venue"
},
  "geometry": {"coordinates":[-4.2569689751,55.8605690002],"type":"Point"}
}