{
  "type": "Feature",
  "properties": {
    "addr:full":"10 Sleapcross Gardens, Colney Heath St Albans Hertfordshire AL4 0RX",
    "addr:housenumber":"10",
    "addr:postcode":"al4 0rx",
    "addr:street":"Sleapcross Gardens",
    "iso:country":"GB",
    "sg:address":"10 Sleapcross Gardens, Colney Heath",
    "sg:city":"St Albans",
    "sg:classifiers":[
        {
            "category":"Home & Garden",
            "subcategory":"Carpets & Floor Coverings",
            "type":"Retail Goods"
        }
    ],
    "sg:postcode":"AL4 0RX",
    "sg:province":"Hertfordshire",
    "sg:tags":[
        "cleaner",
        "upholstery"
    ],
    "wof:name":"Everall Dry Carpet Cleaning",
    "wof:placetype":"venue"
},
  "geometry": {"coordinates":[-0.263447,51.745144],"type":"Point"}
}