{
  "type": "Feature",
  "properties": {
    "iso:country":"GB",
    "sg:address":"16 Gressenhall Rd",
    "sg:city":"Wandsworth",
    "sg:classifiers":[
        {
            "category":"Place Of Worship",
            "type":"Public Place"
        },
        {
            "category":"Organizations",
            "subcategory":"Membership Organization",
            "type":"Services"
        }
    ],
    "sg:phone":"+44 20 8870 1999",
    "sg:postcode":"SW18 5QL",
    "sg:province":"Greater London",
    "sg:tags":[
        "club"
    ],
    "wof:name":"Ahmadiyya Muslim Association",
    "wof:placetype":"venue"
},
  "geometry": {"coordinates":[-0.207433,51.45158],"type":"Point"}
}