{
  "type": "Feature",
  "properties": {
    "addr:full":"Barnaway, Petrockstow Okehampton Devon EX20 3QJ",
    "addr:postcode":"ex20 3qj",
    "addr:street":"Petrockstow",
    "iso:country":"GB",
    "sg:address":"Barnaway, Petrockstow",
    "sg:city":"Okehampton",
    "sg:classifiers":[
        {
            "category":"Building & Trades",
            "subcategory":"Landscaping Services",
            "type":"Services"
        }
    ],
    "sg:phone":"+44 1409 231148",
    "sg:postcode":"EX20 3QJ",
    "sg:province":"Devon",
    "sg:tags":[
        "forestry",
        "surgeon",
        "tree"
    ],
    "wof:name":"Petrock Timber",
    "wof:placetype":"venue"
},
  "geometry": {"coordinates":[-4.1153140068,50.86561203],"type":"Point"}
}