{
  "type": "Feature",
  "properties": {
    "iso:country":"GB",
    "sg:address":"21 Market Street",
    "sg:city":"Sandwich",
    "sg:classifiers":[
        {
            "category":"Travel",
            "subcategory":"Travel Agent",
            "type":"Entertainment"
        }
    ],
    "sg:phone":"+44 1304 612424",
    "sg:postcode":"CT13 9DA",
    "sg:province":"Kent",
    "sg:tags":[
        "agency",
        "activity"
    ],
    "wof:name":"Racing International Ltd.",
    "wof:placetype":"venue"
},
  "geometry": {"coordinates":[1.339855,51.27541],"type":"Point"}
}