{
  "type": "Feature",
  "properties": {
    "addr:full":"275 Broadway North Walsall West Midlands WS1 2PS",
    "addr:housenumber":"275",
    "addr:postcode":"ws1 2ps",
    "addr:street":"Broadway North",
    "iso:country":"GB",
    "sg:address":"275 Broadway North",
    "sg:city":"Walsall",
    "sg:classifiers":[
        {
            "category":"Communications",
            "type":"Services"
        }
    ],
    "sg:phone":"+44 1922 643822",
    "sg:postcode":"WS1 2PS",
    "sg:province":"West Midlands",
    "sg:tags":[
        "audio-visual"
    ],
    "wof:name":"Chris Moxey Media Services",
    "wof:placetype":"venue"
},
  "geometry": {"coordinates":[-1.96257,52.574009],"type":"Point"}
}