{
  "type": "Feature",
  "properties": {
    "addr:full":"Yew Tree Farm, The Ridgeway, Bloxham Banbury Oxfordshire OX15 4EL",
    "addr:postcode":"ox15 4el",
    "addr:street":"Yew;The",
    "iso:country":"GB",
    "sg:address":"Yew Tree Farm, The Ridgeway, Bloxham",
    "sg:city":"Banbury",
    "sg:classifiers":[
        {
            "category":"Real Estate",
            "subcategory":"Real Estate Services",
            "type":"Services"
        },
        {
            "category":"Sports & Exercise",
            "subcategory":"Stables",
            "type":"Entertainment"
        }
    ],
    "sg:phone":"+44 1295 721133",
    "sg:postcode":"OX15 4EL",
    "sg:province":"Oxfordshire",
    "sg:tags":[
        "management",
        "education",
        "equestrian"
    ],
    "wof:name":"K J & J Stanley",
    "wof:placetype":"venue"
},
  "geometry": {"coordinates":[-1.3757590055,52.016834259],"type":"Point"}
}