{
  "type": "Feature",
  "properties": {
    "iso:country":"GB",
    "sg:address":"6 Erskine Rd",
    "sg:city":"Hampstead",
    "sg:classifiers":[
        {
            "category":"Professional",
            "subcategory":"Art Services",
            "type":"Services"
        }
    ],
    "sg:phone":"+44 20 7722 5500",
    "sg:postcode":"NW3 3AJ",
    "sg:province":"Greater London",
    "sg:tags":[
        "consultant",
        "design"
    ],
    "wof:name":"Ergo",
    "wof:placetype":"venue"
},
  "geometry": {"coordinates":[-0.157691,51.541996],"type":"Point"}
}