{
  "type": "Feature",
  "properties": {
    "addr:full":"Houndsfield Primary School, Ripon Road London Greater London N9 7RE",
    "addr:postcode":"n9 7re",
    "addr:street":"Ripon Road",
    "iso:country":"GB",
    "sg:address":"Houndsfield Primary School, Ripon Road",
    "sg:city":"London",
    "sg:classifiers":[
        {
            "category":"Education",
            "subcategory":"School",
            "type":"Public Place"
        }
    ],
    "sg:phone":"+44 20 8805 2634",
    "sg:postcode":"N9 7RE",
    "sg:province":"Greater London",
    "sg:tags":[
        "local",
        "authority"
    ],
    "wof:name":"Houndsfield Language Unit",
    "wof:placetype":"venue"
},
  "geometry": {"coordinates":[-0.05452,51.634838],"type":"Point"}
}