{
  "type": "Feature",
  "properties": {
    "addr:full":"Anchor Brewhouse, 50 Shad Thames London Greater London SE1 2YB",
    "addr:housenumber":"50",
    "addr:postcode":"se1 2yb",
    "addr:street":"Shad Thames",
    "iso:country":"GB",
    "sg:address":"Anchor Brewhouse, 50 Shad Thames",
    "sg:city":"London",
    "sg:classifiers":[
        {
            "category":"Professional",
            "subcategory":"Engineering",
            "type":"Services"
        }
    ],
    "sg:postcode":"SE1 2YB",
    "sg:province":"Greater London",
    "sg:tags":[
        "engineer",
        "mechanical"
    ],
    "wof:name":"Gathershaw Limited",
    "wof:placetype":"venue"
},
  "geometry": {"coordinates":[-0.0750399977,51.5040016174],"type":"Point"}
}