{
  "type": "Feature",
  "properties": {
    "iso:country":"GB",
    "sg:address":"Suite 2d",
    "sg:city":"Gloucester",
    "sg:classifiers":[
        {
            "category":"Professional",
            "subcategory":"Printing & Photocopies",
            "type":"Services"
        }
    ],
    "sg:postcode":"GL2 5RG",
    "sg:province":"Gloucestershire",
    "sg:tags":[
        "duplicating",
        "copying"
    ],
    "wof:name":"Clarity Copiers (Gloucester) & Co",
    "wof:placetype":"venue"
},
  "geometry": {"coordinates":[-2.265299,51.847462],"type":"Point"}
}