{
  "type": "Feature",
  "properties": {
    "addr:full":"6-6a Brougham Place, Tollcross Edinburgh City of Edinburgh EH3 9HW",
    "addr:housenumber":"6-6a",
    "addr:postcode":"eh3 9hw",
    "addr:street":"Brougham Place Tollcross",
    "iso:country":"GB",
    "sg:address":"6-6a Brougham Place, Tollcross",
    "sg:city":"Edinburgh",
    "sg:classifiers":[
        {
            "category":"Restaurant",
            "type":"Food & Drink"
        }
    ],
    "sg:phone":"+44 131 229 3839",
    "sg:postcode":"EH3 9HW",
    "sg:province":"City of Edinburgh",
    "sg:tags":[
        "indian"
    ],
    "wof:name":"Bombay Bicycle Club",
    "wof:placetype":"venue"
},
  "geometry": {"coordinates":[-3.201126,55.94273],"type":"Point"}
}