{
  "type": "Feature",
  "properties": {
    "addr:full":"Bridge Farm, Hooke Beaminster Dorset DT8 3PD",
    "addr:housenumber":"beaminster",
    "addr:postcode":"dt8 3pd",
    "addr:street":"Bridge",
    "iso:country":"GB",
    "sg:address":"Bridge Farm, Hooke",
    "sg:city":"Beaminster",
    "sg:classifiers":[
        {
            "category":"Farming",
            "subcategory":"Livestock Farm",
            "type":"Manufacturing & Wholesale Goods"
        },
        {
            "category":"Farming",
            "subcategory":"Farm",
            "type":"Manufacturing & Wholesale Goods"
        }
    ],
    "sg:phone":"+44 1308 862619",
    "sg:postcode":"DT8 3PD",
    "sg:province":"Dorset",
    "sg:tags":[
        "mixed",
        "crop",
        "others"
    ],
    "wof:name":"Bernard C Wallbridge",
    "wof:placetype":"venue"
},
  "geometry": {"coordinates":[-2.7388939857,50.8090057373],"type":"Point"}
}