{
  "type": "Feature",
  "properties": {
    "iso:country":"GB",
    "sg:address":"84 Frederick Avenue, Peasedown St John",
    "sg:city":"Bath",
    "sg:classifiers":[
        {
            "category":"Building & Trades",
            "subcategory":"Plumbing",
            "type":"Services"
        }
    ],
    "sg:postcode":"BA2 8JA",
    "sg:province":"Somerset",
    "sg:tags":[
        "plumber",
        "heating"
    ],
    "wof:name":"DAVID GRAY HEATING & PLUMBING SERVICES",
    "wof:placetype":"venue"
},
  "geometry": {"coordinates":[-2.42871,51.313026],"type":"Point"}
}