{
  "type": "Feature",
  "properties": {
    "addr:full":"149 The Sycamores, Milton Cambridge Cambridgeshire CB4 6ZH",
    "addr:housenumber":"149",
    "addr:postcode":"cb4 6zh",
    "addr:street":"The Sycamores",
    "iso:country":"GB",
    "sg:address":"149 The Sycamores, Milton",
    "sg:city":"Cambridge",
    "sg:classifiers":[
        {
            "category":"Professional",
            "subcategory":"Computer Services",
            "type":"Services"
        }
    ],
    "sg:phone":"+44 1223 508896",
    "sg:postcode":"CB4 6ZH",
    "sg:province":"Cambridgeshire",
    "sg:tags":[
        "system",
        "software"
    ],
    "wof:name":"P S I Soft Ltd",
    "wof:placetype":"venue"
},
  "geometry": {"coordinates":[0.1527239978,52.2427864075],"type":"Point"}
}