{
  "type": "Feature",
  "properties": {
    "iso:country":"GB",
    "sg:address":"43 Broadlands Avenue",
    "sg:city":"Chesham",
    "sg:classifiers":[
        {
            "category":"Utilities",
            "type":"Services"
        }
    ],
    "sg:phone":"+44 1494 794797",
    "sg:postcode":"HP5 1AL",
    "sg:province":"Buckinghamshire",
    "sg:tags":[
        "internet"
    ],
    "sg:website":"http://www.soundlinks.com",
    "wof:name":"Soundlinks Ltd",
    "wof:placetype":"venue"
},
  "geometry": {"coordinates":[-0.606742,51.709869],"type":"Point"}
}