{
  "type": "Feature",
  "properties": {
    "addr:full":"128-128a Hoe Street, Walthamstow London Greater London E17 4QR",
    "addr:housenumber":"128-128a",
    "addr:postcode":"e17 4qr",
    "addr:street":"Hoe Street",
    "iso:country":"GB",
    "sg:address":"128-128a Hoe Street, Walthamstow",
    "sg:city":"London",
    "sg:classifiers":[
        {
            "category":"Professional",
            "subcategory":"Art Services",
            "type":"Services"
        }
    ],
    "sg:phone":"+44 20 8520 1370",
    "sg:postcode":"E17 4QR",
    "sg:province":"Greater London",
    "sg:tags":[
        "photographer"
    ],
    "wof:name":"Forest Photographic Co",
    "wof:placetype":"venue"
},
  "geometry": {"coordinates":[-0.0209459998,51.5877113342],"type":"Point"}
}