{
  "type": "Feature",
  "properties": {
    "iso:country":"GB",
    "sg:address":"Lowesby Hall, Lowesby Road, Lowesby",
    "sg:city":"Leicester",
    "sg:classifiers":[
        {
            "category":"Farming",
            "subcategory":"Farm",
            "type":"Manufacturing & Wholesale Goods"
        }
    ],
    "sg:phone":"+44 116 259 5635",
    "sg:postcode":"LE7 9DD",
    "sg:province":"Leicestershire",
    "sg:tags":[
        "mixed",
        "crop"
    ],
    "wof:name":"Lowesby Farm Estates",
    "wof:placetype":"venue"
},
  "geometry": {"coordinates":[-0.92835,52.662003],"type":"Point"}
}