{
  "type": "Feature",
  "properties": {
    "iso:country":"GB",
    "sg:address":"41 Lincoln Rd",
    "sg:city":"Northwood",
    "sg:classifiers":[
        {
            "category":"Building & Trades",
            "subcategory":"Construction",
            "type":"Services"
        }
    ],
    "sg:phone":"+44 1923 841777",
    "sg:postcode":"HA6 1LB",
    "sg:province":"Greater London",
    "sg:tags":[
        "surfacing",
        "road"
    ],
    "wof:name":"Abco Line Marking Co",
    "wof:placetype":"venue"
},
  "geometry": {"coordinates":[-0.416485,51.597244],"type":"Point"}
}