{
  "type": "Feature",
  "properties": {
    "iso:country":"GB",
    "sg:address":"8 Ladysmith Road",
    "sg:city":"Enfield",
    "sg:classifiers":[
        {
            "category":"Professional",
            "subcategory":"Computer Services",
            "type":"Services"
        }
    ],
    "sg:phone":"+44 20 8351 5111",
    "sg:postcode":"EN1 3AA",
    "sg:province":"Greater London",
    "sg:tags":[
        "consultant"
    ],
    "wof:name":"Toucan Computing Ltd.",
    "wof:placetype":"venue"
},
  "geometry": {"coordinates":[-0.073346,51.65263],"type":"Point"}
}