{
  "type": "Feature",
  "properties": {
    "addr:full":"127 George Road, Erdington Birmingham West Midlands B23 7SH",
    "addr:housenumber":"127",
    "addr:postcode":"b23 7sh",
    "addr:street":"George Road",
    "iso:country":"GB",
    "sg:address":"127 George Road, Erdington",
    "sg:city":"Birmingham",
    "sg:classifiers":[
        {
            "category":"Sports & Exercise",
            "subcategory":"Gym",
            "type":"Entertainment"
        }
    ],
    "sg:phone":"+44 121 382 3345",
    "sg:postcode":"B23 7SH",
    "sg:province":"West Midlands",
    "sg:tags":[
        "club",
        "fitness",
        "health",
        "centre"
    ],
    "wof:name":"Spartan Health Club",
    "wof:placetype":"venue"
},
  "geometry": {"coordinates":[-1.8612610102,52.5172080994],"type":"Point"}
}