{
  "type": "Feature",
  "properties": {
    "iso:country":"GB",
    "sg:address":"38 Fidlas Avenue",
    "sg:city":"Cardiff",
    "sg:classifiers":[
        {
            "category":"Home & Garden",
            "subcategory":"Household Appliances",
            "type":"Retail Goods"
        },
        {
            "category":"Retail",
            "subcategory":"Repair Shop",
            "type":"Services"
        },
        {
            "category":"Shopping",
            "subcategory":"Computers & Home Electronics",
            "type":"Retail Goods"
        }
    ],
    "sg:phone":"+44 29 2074 7492",
    "sg:postcode":"CF14 0NY",
    "sg:province":"Cardiff",
    "sg:tags":[
        "television",
        "aerial",
        "video",
        "servicing",
        "maintenance",
        "radio",
        "electrical"
    ],
    "wof:name":"T V Tec",
    "wof:placetype":"venue"
},
  "geometry": {"coordinates":[-3.178779,51.522717],"type":"Point"}
}