{
  "type": "Feature",
  "properties": {
    "iso:country":"GB",
    "sg:address":"76-78 Manor Road, Keyworth",
    "sg:city":"Nottingham",
    "sg:classifiers":[
        {
            "category":"Food & Beverages",
            "subcategory":"Supermarket",
            "type":"Retail Goods"
        },
        {
            "category":"Food & Beverages",
            "subcategory":"Groceries & Convenience Stores",
            "type":"Retail Goods"
        }
    ],
    "sg:phone":"+44 115 937 2436",
    "sg:postcode":"NG12 5GL",
    "sg:province":"Nottinghamshire",
    "wof:name":"Patel Food Stores",
    "wof:placetype":"venue"
},
  "geometry": {"coordinates":[-1.092772,52.874466],"type":"Point"}
}