{
  "type": "Feature",
  "properties": {
    "iso:country":"GB",
    "sg:address":"19 Treloggan La",
    "sg:city":"Newquay",
    "sg:classifiers":[
        {
            "category":"Retail",
            "subcategory":"Driving School",
            "type":"Services"
        }
    ],
    "sg:phone":"+44 1637 871092",
    "sg:postcode":"TR7 2JN",
    "sg:province":"Cornwall",
    "wof:name":"Able",
    "wof:placetype":"venue"
},
  "geometry": {"coordinates":[-5.067559,50.406708],"type":"Point"}
}