{
  "type": "Feature",
  "properties": {
    "addr:full":"St Lukes Street Gloucester Gloucestershire GL1 5RE",
    "addr:postcode":"gl1 5re",
    "addr:street":"St Lukes Street",
    "iso:country":"GB",
    "sg:address":"St Lukes Street",
    "sg:city":"Gloucester",
    "sg:classifiers":[
        {
            "category":"Building & Trades",
            "subcategory":"Construction",
            "type":"Services"
        }
    ],
    "sg:phone":"+44 1452 308030",
    "sg:postcode":"GL1 5RE",
    "sg:province":"Gloucestershire",
    "sg:tags":[
        "valve"
    ],
    "wof:name":"Severn Glocon Ltd.",
    "wof:placetype":"venue"
},
  "geometry": {"coordinates":[-2.2508890629,51.8593902588],"type":"Point"}
}