{
  "type": "Feature",
  "properties": {
    "iso:country":"GB",
    "sg:address":"Uned 1 Parc, Gwyddoniaeth",
    "sg:city":"Aberystwyth",
    "sg:classifiers":[
        {
            "category":"Education",
            "subcategory":"Library",
            "type":"Public Place"
        }
    ],
    "sg:phone":"+44 1970 626007",
    "sg:postcode":"SY23 3AH",
    "sg:province":"Ceredigion",
    "sg:tags":[
        "book"
    ],
    "wof:name":"Archif Ffilm Cymru",
    "wof:placetype":"venue"
},
  "geometry": {"coordinates":[-4.0625500679,52.4118690491],"type":"Point"}
}