{
  "type": "Feature",
  "properties": {
    "iso:country":"GB",
    "sg:address":"56 Ford Rd",
    "sg:city":"Wirral",
    "sg:classifiers":[
        {
            "category":"Place Of Worship",
            "type":"Public Place"
        }
    ],
    "sg:phone":"+44 151 677 1233",
    "sg:postcode":"CH49 0TG",
    "sg:province":"Merseyside",
    "wof:name":"United Reformed Church",
    "wof:placetype":"venue"
},
  "geometry": {"coordinates":[-3.092505,53.384361],"type":"Point"}
}