{
  "type": "Feature",
  "properties": {
    "iso:country":"GB",
    "sg:address":"Sapphire Dr",
    "sg:city":"Cannock",
    "sg:classifiers":[
        {
            "category":"Manufacturing",
            "subcategory":"Petroleum Products",
            "type":"Manufacturing & Wholesale Goods"
        }
    ],
    "sg:phone":"+44 1543 459100",
    "sg:postcode":"WS11 2FY",
    "sg:province":"Staffordshire",
    "sg:tags":[
        "double",
        "glazing"
    ],
    "wof:name":"Windows & Doors By Heritage",
    "wof:placetype":"venue"
},
  "geometry": {"coordinates":[-1.99553895,52.6979217529],"type":"Point"}
}