{
  "type": "Feature",
  "properties": {
    "addr:full":"27 Old Dumbarton Road Glasgow Glasgow City G3 8RD",
    "addr:housenumber":"27",
    "addr:postcode":"g3 8rd",
    "addr:street":"Old Dumbarton Road",
    "iso:country":"GB",
    "sg:address":"27 Old Dumbarton Road",
    "sg:city":"Glasgow",
    "sg:classifiers":[
        {
            "category":"Deli",
            "type":"Food & Drink"
        }
    ],
    "sg:phone":"+44 141 576 5031",
    "sg:postcode":"G3 8RD",
    "sg:province":"Glasgow City",
    "sg:tags":[
        "delicatessen"
    ],
    "wof:name":"Andreas Greek Deli",
    "wof:placetype":"venue"
},
  "geometry": {"coordinates":[-4.2916221619,55.8669319153],"type":"Point"}
}