{
  "type": "Feature",
  "properties": {
    "addr:full":"Woodhurst, Cattlegate Road, Crews Hill Enfield Greater London EN2 8AU",
    "addr:postcode":"en2 8au",
    "addr:street":"Cattlegate Road",
    "iso:country":"GB",
    "sg:address":"Woodhurst, Cattlegate Road, Crews Hill",
    "sg:city":"Enfield",
    "sg:classifiers":[
        {
            "category":"Building & Trades",
            "subcategory":"Construction",
            "type":"Services"
        }
    ],
    "sg:phone":"+44 1707 876515",
    "sg:postcode":"EN2 8AU",
    "sg:province":"Greater London",
    "sg:tags":[
        "builder",
        "guttering"
    ],
    "wof:name":"Calder Group",
    "wof:placetype":"venue"
},
  "geometry": {"coordinates":[-0.1203270033,51.691204071],"type":"Point"}
}