{
  "type": "Feature",
  "properties": {
    "addr:full":"10 Boughton Road Rugby Warwickshire CV21 1BJ",
    "addr:housenumber":"10",
    "addr:postcode":"cv21 1bj",
    "addr:street":"Boughton Road",
    "iso:country":"GB",
    "sg:address":"10 Boughton Road",
    "sg:city":"Rugby",
    "sg:classifiers":[
        {
            "category":"Fast Food",
            "type":"Food & Drink"
        }
    ],
    "sg:phone":"+44 1788 547722",
    "sg:postcode":"CV21 1BJ",
    "sg:province":"Warwickshire",
    "sg:tags":[
        "delivery"
    ],
    "wof:name":"Pizza The Action",
    "wof:placetype":"venue"
},
  "geometry": {"coordinates":[-1.247462,52.383224],"type":"Point"}
}