{
  "type": "Feature",
  "properties": {
    "iso:country":"GB",
    "sg:address":"Brookfold La, Harwood",
    "sg:city":"Bolton",
    "sg:classifiers":[
        {
            "category":"Utilities",
            "subcategory":"Refuse",
            "type":"Services"
        }
    ],
    "sg:postcode":"BL2 4LT",
    "sg:province":"Lancashire",
    "sg:tags":[
        "skip",
        "hire"
    ],
    "wof:name":"Southerns Environmental",
    "wof:placetype":"venue"
},
  "geometry": {"coordinates":[-2.3854339123,53.6018753052],"type":"Point"}
}