{
  "type": "Feature",
  "properties": {
    "iso:country":"GB",
    "sg:address":"60 Leigh Rd, Atherton",
    "sg:city":"Manchester",
    "sg:classifiers":[
        {
            "category":"Home & Garden",
            "subcategory":"Home Furnishings",
            "type":"Retail Goods"
        }
    ],
    "sg:phone":"+44 1942 887257",
    "sg:postcode":"M46 0NA",
    "sg:province":"Greater Manchester",
    "sg:tags":[
        "blind",
        "curtain",
        "fitting"
    ],
    "wof:name":"Choose at Home Blinds",
    "wof:placetype":"venue"
},
  "geometry": {"coordinates":[-2.5004920959,53.5215797424],"type":"Point"}
}