{
  "type": "Feature",
  "properties": {
    "addr:full":"2 Adelaide Street St Albans Hertfordshire AL3 5BH",
    "addr:housenumber":"2",
    "addr:postcode":"al3 5bh",
    "addr:street":"Adelaide Street",
    "iso:country":"GB",
    "sg:address":"2 Adelaide Street",
    "sg:city":"St Albans",
    "sg:classifiers":[
        {
            "category":"Professional",
            "subcategory":"Employment Agencies",
            "type":"Services"
        }
    ],
    "sg:phone":"+44 845 389 2324",
    "sg:postcode":"AL3 5BH",
    "sg:province":"Hertfordshire",
    "sg:tags":[
        "consultant",
        "recruitment"
    ],
    "wof:name":"Davison Bird & Associates Ltd.",
    "wof:placetype":"venue"
},
  "geometry": {"coordinates":[-0.337319,51.754761],"type":"Point"}
}