{
  "type": "Feature",
  "properties": {
    "addr:full":"Newlands Avenue, Brackla Industrial Estate Bridgend Bridgend CF31 2DA",
    "addr:postcode":"cf31 2da",
    "addr:street":"Newlands Avenue;Industrial Estate",
    "iso:country":"GB",
    "sg:address":"Newlands Avenue, Brackla Industrial Estate",
    "sg:city":"Bridgend",
    "sg:classifiers":[
        {
            "category":"Social Services",
            "subcategory":"Job Training",
            "type":"Services"
        },
        {
            "category":"Autos & Motor Vehicles",
            "subcategory":"Auto Supplies",
            "type":"Retail Goods"
        }
    ],
    "sg:phone":"+44 1656 660433",
    "sg:postcode":"CF31 2DA",
    "sg:province":"Bridgend",
    "sg:tags":[
        "clutch",
        "engineering",
        "replacement",
        "brake",
        "marine"
    ],
    "wof:name":"Clarkson Engineering Co. Ltd.",
    "wof:placetype":"venue"
},
  "geometry": {"coordinates":[-3.5643401146,51.5190925598],"type":"Point"}
}