{
  "type": "Feature",
  "properties": {
    "iso:country":"GB",
    "sg:address":"86 Fishers Lane, Pensby",
    "sg:city":"Wirral",
    "sg:classifiers":[
        {
            "category":"Health Services",
            "subcategory":"Chiropractor",
            "type":"Services"
        }
    ],
    "sg:postcode":"CH61 5XG",
    "sg:province":"Merseyside",
    "wof:name":"Deirdre Concannon",
    "wof:placetype":"venue"
},
  "geometry": {"coordinates":[-3.1046080589,53.345287323],"type":"Point"}
}