{
  "type": "Feature",
  "properties": {
    "iso:country":"GB",
    "sg:address":"Unit 13 Longbeck Estate, Marske By The Sea",
    "sg:city":"Redcar",
    "sg:classifiers":[
        {
            "category":"Autos & Motor Vehicles",
            "subcategory":"Motorcycle Sales",
            "type":"Retail Goods"
        }
    ],
    "sg:phone":"+44 1642 476100",
    "sg:postcode":"TS11 6HR",
    "sg:province":"North Yorkshire",
    "wof:name":"Mikes Bikes",
    "wof:placetype":"venue"
},
  "geometry": {"coordinates":[-1.029604,54.589569],"type":"Point"}
}