{
  "type": "Feature",
  "properties": {
    "iso:country":"GB",
    "sg:address":"Springfield, Burrelton",
    "sg:city":"Blairgowrie",
    "sg:classifiers":[
        {
            "category":"Food & Beverages",
            "subcategory":"Groceries & Convenience Stores",
            "type":"Retail Goods"
        }
    ],
    "sg:phone":"+44 1828 670343",
    "sg:postcode":"PH13 9PJ",
    "sg:province":"Angus",
    "sg:tags":[
        "merchant",
        "potato"
    ],
    "wof:name":"Greenvale Ap Ltd.",
    "wof:placetype":"venue"
},
  "geometry": {"coordinates":[-3.302469,56.516033],"type":"Point"}
}