{
  "type": "Feature",
  "properties": {
    "addr:full":"13 St Johns Road Harrow Greater London HA1 2BA",
    "addr:housenumber":"13",
    "addr:postcode":"ha1 2ba",
    "addr:street":"St Johns Road",
    "iso:country":"GB",
    "sg:address":"13 St Johns Road",
    "sg:city":"Harrow",
    "sg:classifiers":[
        {
            "category":"Banks & Credit Unions",
            "subcategory":"Bank",
            "type":"Services"
        }
    ],
    "sg:phone":"+44 1895 216400",
    "sg:postcode":"HA1 2BA",
    "sg:province":"Greater London",
    "wof:name":"Barclays Bank Plc",
    "wof:placetype":"venue"
},
  "geometry": {"coordinates":[-0.330482,51.580486],"type":"Point"}
}