{
  "type": "Feature",
  "properties": {
    "addr:full":"Graystale Farm, Polmaise Stirling Falkirk FK7 9PX",
    "addr:postcode":"fk7 9px",
    "addr:street":"Polmaise",
    "iso:country":"GB",
    "sg:address":"Graystale Farm, Polmaise",
    "sg:city":"Stirling",
    "sg:classifiers":[
        {
            "category":"Farming",
            "subcategory":"Livestock Farm",
            "type":"Manufacturing & Wholesale Goods"
        },
        {
            "category":"Farming",
            "subcategory":"Farm",
            "type":"Manufacturing & Wholesale Goods"
        }
    ],
    "sg:phone":"+44 1786 473939",
    "sg:postcode":"FK7 9PX",
    "sg:province":"Falkirk",
    "sg:tags":[
        "mixed",
        "crop"
    ],
    "wof:name":"J H Gilvear & Sons",
    "wof:placetype":"venue"
},
  "geometry": {"coordinates":[-3.9478240013,56.0979614258],"type":"Point"}
}