{
  "type": "Feature",
  "properties": {
    "addr:full":"131 Shakespeare Crescent, Eccles Manchester Greater Manchester M30 0PE",
    "addr:housenumber":"131",
    "addr:postcode":"m30 0pe",
    "addr:street":"Shakespeare Crescent",
    "iso:country":"GB",
    "sg:address":"131 Shakespeare Crescent, Eccles",
    "sg:city":"Manchester",
    "sg:classifiers":[
        {
            "category":"Personal",
            "type":"Services"
        },
        {
            "category":"Retail",
            "subcategory":"Auto Repair",
            "type":"Services"
        }
    ],
    "sg:phone":"+44 161 787 7440",
    "sg:postcode":"M30 0PE",
    "sg:province":"Greater Manchester",
    "sg:tags":[
        "garage",
        "related",
        "wedding"
    ],
    "wof:name":"Shakespeare Motor Co",
    "wof:placetype":"venue"
},
  "geometry": {"coordinates":[-2.3531160355,53.4829521179],"type":"Point"}
}