{
  "type": "Feature",
  "properties": {
    "addr:full":"Baldock Road Letchworth Hertfordshire SG6 2ER",
    "addr:postcode":"sg6 2er",
    "addr:street":"Baldock Road",
    "iso:country":"GB",
    "sg:address":"Baldock Road",
    "sg:city":"Letchworth",
    "sg:classifiers":[
        {
            "category":"Community Center",
            "type":"Public Place"
        },
        {
            "category":"Government",
            "subcategory":"Office",
            "type":"Public Place"
        }
    ],
    "sg:phone":"+44 1462 679311",
    "sg:postcode":"SG6 2ER",
    "sg:province":"Hertfordshire",
    "sg:tags":[
        "recreation",
        "local",
        "leisure",
        "centre"
    ],
    "wof:name":"North Hertfordshire Leisure Centre",
    "wof:placetype":"venue"
},
  "geometry": {"coordinates":[-0.2095640004,51.9771003723],"type":"Point"}
}