{
  "type": "Feature",
  "properties": {
    "addr:full":"25-27 High Street, Carcroft Doncaster North Yorkshire DN6 8DN",
    "addr:housenumber":"25-27",
    "addr:postcode":"dn6 8dn",
    "addr:street":"High Street",
    "iso:country":"GB",
    "sg:address":"25-27 High Street, Carcroft",
    "sg:city":"Doncaster",
    "sg:classifiers":[
        {
            "category":"Home & Garden",
            "subcategory":"Carpets & Floor Coverings",
            "type":"Retail Goods"
        }
    ],
    "sg:phone":"+44 1302 721588",
    "sg:postcode":"DN6 8DN",
    "sg:province":"North Yorkshire",
    "sg:tags":[
        "carpets",
        "rug",
        "matting"
    ],
    "wof:name":"Mr Heywood's Carpets Ltd.",
    "wof:placetype":"venue"
},
  "geometry": {"coordinates":[-1.1809699535,53.582901001],"type":"Point"}
}