{
  "type": "Feature",
  "properties": {
    "addr:full":"Shireoaks Road, Shireoaks Worksop Nottinghamshire S81 8LX",
    "addr:postcode":"s81 8lx",
    "addr:street":"Shireoaks Road",
    "iso:country":"GB",
    "sg:address":"Shireoaks Road, Shireoaks",
    "sg:city":"Worksop",
    "sg:classifiers":[
        {
            "category":"Social Services",
            "subcategory":"Retirement Home",
            "type":"Services"
        }
    ],
    "sg:phone":"+44 1909 482960",
    "sg:postcode":"S81 8LX",
    "sg:province":"Nottinghamshire",
    "sg:tags":[
        "residential",
        "care"
    ],
    "wof:name":"Newton House",
    "wof:placetype":"venue"
},
  "geometry": {"coordinates":[-1.1656479836,53.3201408386],"type":"Point"}
}