{
  "type": "Feature",
  "properties": {
    "iso:country":"GB",
    "sg:address":"Halifax Rd",
    "sg:city":"Brighouse",
    "sg:classifiers":[
        {
            "category":"Education",
            "subcategory":"Library",
            "type":"Public Place"
        }
    ],
    "sg:phone":"+44 1484 718639",
    "sg:postcode":"HD6 2AF",
    "sg:province":"West Yorkshire",
    "sg:tags":[
        "book"
    ],
    "wof:name":"Mobile Library",
    "wof:placetype":"venue"
},
  "geometry": {"coordinates":[-1.7924640179,53.7088317871],"type":"Point"}
}