{
  "type": "Feature",
  "properties": {
    "addr:full":"1 Beldams, Needingworth Huntingdon Cambridgeshire PE17 3TY",
    "addr:housenumber":"1",
    "addr:postcode":"pe17 3ty",
    "addr:street":"Beldams Needingworth Huntingdon",
    "iso:country":"GB",
    "sg:address":"1 Beldams, Needingworth",
    "sg:city":"Huntingdon",
    "sg:classifiers":[
        {
            "category":"Personal",
            "type":"Services"
        }
    ],
    "sg:phone":"+44 1480 468773",
    "sg:postcode":"PE17 3TY",
    "sg:province":"Cambridgeshire",
    "sg:tags":[
        "consultant",
        "fitness"
    ],
    "wof:name":"Workout 1404 Exercise The",
    "wof:placetype":"venue"
},
  "geometry": {"coordinates":[-0.0304000005,52.3305702209],"type":"Point"}
}