{
  "type": "Feature",
  "properties": {
    "iso:country":"GB",
    "sg:address":"38 Saltergate",
    "sg:city":"Chesterfield",
    "sg:classifiers":[
        {
            "category":"Place Of Worship",
            "type":"Public Place"
        }
    ],
    "sg:phone":"+44 1246 277390",
    "sg:postcode":"S40 1UH",
    "sg:province":"Derbyshire",
    "wof:name":"Central Methodist Church",
    "wof:placetype":"venue"
},
  "geometry": {"coordinates":[-1.428734,53.237312],"type":"Point"}
}