{
  "type": "Feature",
  "properties": {
    "addr:full":"Station Road, Rhuddlan Rhyl Conwy LL18 5UA",
    "addr:postcode":"ll18 5ua",
    "addr:street":"Station Road",
    "iso:country":"GB",
    "sg:address":"Station Road, Rhuddlan",
    "sg:city":"Rhyl",
    "sg:classifiers":[
        {
            "category":"Retail",
            "subcategory":"Auto Repair",
            "type":"Services"
        }
    ],
    "sg:phone":"+44 1745 590220",
    "sg:postcode":"LL18 5UA",
    "sg:province":"Conwy",
    "sg:tags":[
        "modification",
        "garage"
    ],
    "wof:name":"Gittins Garage (Rhuddlan) Ltd.",
    "wof:placetype":"venue"
},
  "geometry": {"coordinates":[-3.472384,53.311581],"type":"Point"}
}