{
  "type": "Feature",
  "properties": {
    "addr:full":"88 Stoke Newington, Church Street London Greater London N16 0AP",
    "addr:housenumber":"88",
    "addr:postcode":"n16 0ap",
    "addr:street":"Stoke Newington Church Street",
    "iso:country":"GB",
    "sg:address":"88 Stoke Newington, Church Street",
    "sg:city":"London",
    "sg:classifiers":[
        {
            "category":"Shopping",
            "subcategory":"Hobbies, Toys, & Games",
            "type":"Retail Goods"
        }
    ],
    "sg:phone":"+44 20 7923 7873",
    "sg:postcode":"N16 0AP",
    "sg:province":"Greater London",
    "sg:tags":[
        "shop",
        "toy"
    ],
    "wof:name":"Route 73 Kids",
    "wof:placetype":"venue"
},
  "geometry": {"coordinates":[-0.0780590028,51.5622940063],"type":"Point"}
}