{
  "type": "Feature",
  "properties": {
    "addr:full":"Unit4, Minton Enterprise Park, Oaks Drive Newmarket Cambridgeshire CB8 7YY",
    "addr:postcode":"cb8 7yy",
    "addr:street":"Park Oaks Drive",
    "iso:country":"GB",
    "sg:address":"Unit4, Minton Enterprise Park, Oaks Drive",
    "sg:city":"Newmarket",
    "sg:classifiers":[
        {
            "category":"Wholesale",
            "subcategory":"Medical Equipment & Supplies",
            "type":"Manufacturing & Wholesale Goods"
        },
        {
            "category":"Health Services",
            "subcategory":"Nursing And Care Facility",
            "type":"Services"
        }
    ],
    "sg:phone":"+44 1638 663338",
    "sg:postcode":"CB8 7YY",
    "sg:province":"Cambridgeshire",
    "sg:tags":[
        "aid",
        "hospital",
        "first"
    ],
    "wof:name":"Nitritex Ltd",
    "wof:placetype":"venue"
},
  "geometry": {"coordinates":[0.399165988,52.2498168945],"type":"Point"}
}