{
  "type": "Feature",
  "properties": {
    "iso:country":"GB",
    "sg:address":"125 Church Street, Kimberworth",
    "sg:city":"Rotherham",
    "sg:classifiers":[
        {
            "category":"Food & Beverages",
            "subcategory":"Candy",
            "type":"Retail Goods"
        },
        {
            "category":"Government",
            "subcategory":"Post Office",
            "type":"Public Place"
        }
    ],
    "sg:phone":"+44 1709 554996",
    "sg:postcode":"S61 1HA",
    "sg:province":"South Yorkshire",
    "sg:tags":[
        "confectioner"
    ],
    "wof:name":"Kimberworth Post Office",
    "wof:placetype":"venue"
},
  "geometry": {"coordinates":[-1.3929760456,53.4336280823],"type":"Point"}
}