{
  "type": "Feature",
  "properties": {
    "iso:country":"GB",
    "sg:address":"1 New Bedford Road",
    "sg:city":"Luton",
    "sg:classifiers":[
        {
            "category":"Manufacturing",
            "subcategory":"Jewelry",
            "type":"Manufacturing & Wholesale Goods"
        }
    ],
    "sg:phone":"+44 1582 654333",
    "sg:postcode":"LU1 1SA",
    "sg:province":"Bedfordshire",
    "sg:tags":[
        "repair",
        "jewellery"
    ],
    "wof:name":"L Warren",
    "wof:placetype":"venue"
},
  "geometry": {"coordinates":[-0.418349,51.881302],"type":"Point"}
}