{
  "type": "Feature",
  "properties": {
    "iso:country":"GB",
    "sg:address":"24 Addington Close",
    "sg:city":"Devizes",
    "sg:classifiers":[
        {
            "category":"Home & Garden",
            "subcategory":"Household Appliances",
            "type":"Retail Goods"
        }
    ],
    "sg:phone":"+44 1380 724083",
    "sg:postcode":"SN10 5BE",
    "sg:province":"Wiltshire",
    "sg:tags":[
        "domestic",
        "centre"
    ],
    "wof:name":"Devizes Domestic Appliances",
    "wof:placetype":"venue"
},
  "geometry": {"coordinates":[-1.986107,51.343304],"type":"Point"}
}