{
  "type": "Feature",
  "properties": {
    "addr:full":"7 Grosvenor Road Tunbridge Wells Kent TN1 2AH",
    "addr:housenumber":"7",
    "addr:postcode":"tn1 2ah",
    "addr:street":"Grosvenor Road",
    "iso:country":"GB",
    "sg:address":"7 Grosvenor Road",
    "sg:city":"Tunbridge Wells",
    "sg:classifiers":[
        {
            "category":"Cafe",
            "type":"Food & Drink"
        }
    ],
    "sg:phone":"+44 1892 522642",
    "sg:postcode":"TN1 2AH",
    "sg:province":"Kent",
    "sg:tags":[
        "tea",
        "room"
    ],
    "wof:name":"D'Ambrosao Milk Bar",
    "wof:placetype":"venue"
},
  "geometry": {"coordinates":[0.263379,51.134693],"type":"Point"}
}