{
  "type": "Feature",
  "properties": {
    "iso:country":"GB",
    "sg:address":"7 Oakwood Street",
    "sg:city":"Sunderland",
    "sg:classifiers":[
        {
            "category":"Professional",
            "type":"Services"
        },
        {
            "category":"Wholesale",
            "subcategory":"Furniture",
            "type":"Manufacturing & Wholesale Goods"
        }
    ],
    "sg:postcode":"SR2 7LT",
    "sg:province":"Tyne and Wear",
    "sg:tags":[
        "shop",
        "fitting",
        "display",
        "maker"
    ],
    "wof:name":"React Products",
    "wof:placetype":"venue"
},
  "geometry": {"coordinates":[-1.3961859941,54.9001083374],"type":"Point"}
}