{
  "type": "Feature",
  "properties": {
    "addr:full":"1a Upper Wimpole St West End Hampshire W1M 7TD",
    "addr:housenumber":"1a",
    "addr:postcode":"w1m 7td",
    "addr:street":"Upper Wimpole St",
    "iso:country":"GB",
    "sg:address":"1a Upper Wimpole St",
    "sg:city":"West End",
    "sg:classifiers":[
        {
            "category":"Health Services",
            "subcategory":"Dentist",
            "type":"Services"
        }
    ],
    "sg:phone":"+44 20 7486 9949",
    "sg:postcode":"W1M 7TD",
    "sg:province":"Hampshire",
    "wof:name":"Mr C Fickling",
    "wof:placetype":"venue"
},
  "geometry": {"coordinates":[-0.1490429938,51.5205078125],"type":"Point"}
}