{
  "type": "Feature",
  "properties": {
    "addr:full":"4 Hamble Court, Chandlers Ford Eastleigh Hampshire SO53 2NN",
    "addr:housenumber":"4",
    "addr:postcode":"so53 2nn",
    "addr:street":"Hamble Court",
    "iso:country":"GB",
    "sg:address":"4 Hamble Court, Chandlers Ford",
    "sg:city":"Eastleigh",
    "sg:classifiers":[
        {
            "category":"Professional",
            "subcategory":"Engineering",
            "type":"Services"
        }
    ],
    "sg:phone":"+44 23 8027 1220",
    "sg:postcode":"SO53 2NN",
    "sg:province":"Hampshire",
    "sg:tags":[
        "contractor",
        "electrical",
        "engineer"
    ],
    "wof:name":"J T Electrical",
    "wof:placetype":"venue"
},
  "geometry": {"coordinates":[-1.3778140545,50.9807090759],"type":"Point"}
}