{
  "type": "Feature",
  "properties": {
    "iso:country":"GB",
    "sg:address":"Ocean Villa, Sutton Road, Trusthorpe",
    "sg:city":"Lincoln",
    "sg:classifiers":[
        {
            "category":"Shopping",
            "subcategory":"Clothing, Apparel, & Fashions",
            "type":"Retail Goods"
        },
        {
            "category":"Wholesale",
            "subcategory":"Electrical",
            "type":"Manufacturing & Wholesale Goods"
        }
    ],
    "sg:postcode":"LN12 2PD",
    "sg:province":"Lincolnshire",
    "sg:tags":[
        "equipment",
        "clothing",
        "fabric",
        "refrigeration"
    ],
    "wof:name":"A C Refrigeration Sales and Service",
    "wof:placetype":"venue"
},
  "geometry": {"coordinates":[0.271194011,53.3256111145],"type":"Point"}
}