{
  "type": "Feature",
  "properties": {
    "addr:full":"39a Station Road, Desborough Kettering Northamptonshire NN14 2RL",
    "addr:housenumber":"39a",
    "addr:postcode":"nn14 2rl",
    "addr:street":"Station Road",
    "iso:country":"GB",
    "sg:address":"39a Station Road, Desborough",
    "sg:city":"Kettering",
    "sg:classifiers":[
        {
            "category":"Shopping",
            "subcategory":"Used Merchandise",
            "type":"Retail Goods"
        }
    ],
    "sg:postcode":"NN14 2RL",
    "sg:province":"Northamptonshire",
    "sg:tags":[
        "shop",
        "second-hand"
    ],
    "wof:name":"Gallery Sales",
    "wof:placetype":"venue"
},
  "geometry": {"coordinates":[-0.819184,52.443005],"type":"Point"}
}