{
  "type": "Feature",
  "properties": {
    "iso:country":"GB",
    "sg:address":"94a St Michaels Trading Estate",
    "sg:city":"Bridport",
    "sg:classifiers":[
        {
            "category":"Shopping",
            "subcategory":"Department Store",
            "type":"Retail Goods"
        }
    ],
    "sg:postcode":"DT6 3RR",
    "sg:province":"Dorset",
    "wof:name":"David Symonds",
    "wof:placetype":"venue"
},
  "geometry": {"coordinates":[-2.7625091076,50.7329177856],"type":"Point"}
}