{
  "type": "Feature",
  "properties": {
    "iso:country":"GB",
    "sg:address":"4 Langley Quay",
    "sg:city":"Slough",
    "sg:classifiers":[
        {
            "category":"Wholesale",
            "subcategory":"Chemicals & Plastics",
            "type":"Manufacturing & Wholesale Goods"
        }
    ],
    "sg:phone":"+44 1753 603000",
    "sg:postcode":"SL3 6EH",
    "sg:province":"Berkshire",
    "sg:tags":[
        "product",
        "allied"
    ],
    "wof:name":"Uniroyal Chemical  Ltd",
    "wof:placetype":"venue"
},
  "geometry": {"coordinates":[-0.543399,51.50898],"type":"Point"}
}