{
  "type": "Feature",
  "properties": {
    "iso:country":"GB",
    "sg:address":"14-18 Kew Foot Road",
    "sg:city":"Richmond",
    "sg:classifiers":[
        {
            "category":"Autos & Motor Vehicles",
            "subcategory":"Auto Supplies",
            "type":"Retail Goods"
        }
    ],
    "sg:phone":"+44 20 8940 2045",
    "sg:postcode":"TW9 2SS",
    "sg:province":"Greater London",
    "sg:tags":[
        "part",
        "motorcycle",
        "accessory"
    ],
    "wof:name":"Harwoods of Richmond Ltd.",
    "wof:placetype":"venue"
},
  "geometry": {"coordinates":[-0.302213,51.465633],"type":"Point"}
}