{
  "type": "Feature",
  "properties": {
    "iso:country":"GB",
    "sg:address":"Duke St",
    "sg:city":"Barrow In Furness",
    "sg:classifiers":[
        {
            "category":"Organizations",
            "subcategory":"Membership Organization",
            "type":"Services"
        }
    ],
    "sg:phone":"+44 1229 825316",
    "sg:postcode":"LA14 1RU",
    "sg:province":"Cumbria",
    "sg:tags":[
        "club"
    ],
    "wof:name":"Cascade Palace",
    "wof:placetype":"venue"
},
  "geometry": {"coordinates":[-3.235644,54.11676],"type":"Point"}
}