{
  "type": "Feature",
  "properties": {
    "addr:full":"43 Crossgates Shopping Centre Leeds West Yorkshire LS15 8EU",
    "addr:postcode":"ls15 8eu",
    "addr:street":"Crossgates Shopping Centre Leeds West",
    "iso:country":"GB",
    "sg:address":"43 Crossgates Shopping Centre",
    "sg:city":"Leeds",
    "sg:classifiers":[
        {
            "category":"Personal",
            "subcategory":"Barber",
            "type":"Services"
        }
    ],
    "sg:phone":"+44 113 264 0197",
    "sg:postcode":"LS15 8EU",
    "sg:province":"West Yorkshire",
    "sg:tags":[
        "men's",
        "hairdresser"
    ],
    "wof:name":"Terry'S Barbers Shop",
    "wof:placetype":"venue"
},
  "geometry": {"coordinates":[-1.452225,53.80637],"type":"Point"}
}