{
  "type": "Feature",
  "properties": {
    "addr:full":"13-15 Market St Aberdeen Aberdeen City AB11 5PY",
    "addr:housenumber":"13-15",
    "addr:postcode":"ab11 5py",
    "addr:street":"Market St",
    "iso:country":"GB",
    "sg:address":"13-15 Market St",
    "sg:city":"Aberdeen",
    "sg:classifiers":[
        {
            "category":"Brewery",
            "type":"Food & Drink"
        }
    ],
    "sg:postcode":"AB11 5PY",
    "sg:province":"Aberdeen City",
    "sg:tags":[
        "brewer"
    ],
    "wof:name":"Scottish Brewers Ltd",
    "wof:placetype":"venue"
},
  "geometry": {"coordinates":[-2.096828,57.146587],"type":"Point"}
}