{
  "type": "Feature",
  "properties": {
    "addr:full":"Middle Farm, Thimbleby Northallerton North Yorkshire DL6 3PY",
    "addr:postcode":"dl6 3py",
    "addr:street":"Middle",
    "iso:country":"GB",
    "sg:address":"Middle Farm, Thimbleby",
    "sg:city":"Northallerton",
    "sg:classifiers":[
        {
            "category":"Farming",
            "subcategory":"Dairy Farm",
            "type":"Manufacturing & Wholesale Goods"
        }
    ],
    "sg:phone":"+44 1609 883364",
    "sg:postcode":"DL6 3PY",
    "sg:province":"North Yorkshire",
    "wof:name":"J & Son Shepherd",
    "wof:placetype":"venue"
},
  "geometry": {"coordinates":[-1.308686,54.352757],"type":"Point"}
}