{
  "type": "Feature",
  "properties": {
    "addr:full":"3 Manston Way Hornchurch Essex RM12 5PJ",
    "addr:housenumber":"3",
    "addr:postcode":"rm12 5pj",
    "addr:street":"Manston Way",
    "iso:country":"GB",
    "sg:address":"3 Manston Way",
    "sg:city":"Hornchurch",
    "sg:classifiers":[
        {
            "category":"Building & Trades",
            "subcategory":"Construction",
            "type":"Services"
        }
    ],
    "sg:postcode":"RM12 5PJ",
    "sg:province":"Essex",
    "sg:tags":[
        "roofing"
    ],
    "wof:name":"R Sims Cladding & Roofing Services",
    "wof:placetype":"venue"
},
  "geometry": {"coordinates":[0.203942,51.54018],"type":"Point"}
}