{
  "type": "Feature",
  "properties": {
    "addr:full":"13 Alresford Road, Middleton Manchester Greater Manchester M24 1WU",
    "addr:housenumber":"13",
    "addr:postcode":"m24 1wu",
    "addr:street":"Alresford Road",
    "iso:country":"GB",
    "sg:address":"13 Alresford Road, Middleton",
    "sg:city":"Manchester",
    "sg:classifiers":[
        {
            "category":"Professional",
            "type":"Services"
        }
    ],
    "sg:phone":"+44 161 643 5077",
    "sg:postcode":"M24 1WU",
    "sg:province":"Greater Manchester",
    "sg:tags":[
        "entertainer"
    ],
    "wof:name":"Dan Dan the Magic Man",
    "wof:placetype":"venue"
},
  "geometry": {"coordinates":[-2.200419,53.53384],"type":"Point"}
}