{
  "type": "Feature",
  "properties": {
    "addr:full":"Stanshawes Court Drive, Yate Bristol Gloucestershire BS37 4EA",
    "addr:postcode":"bs37 4ea",
    "addr:street":"Court Drive",
    "iso:country":"GB",
    "sg:address":"Stanshawes Court Drive, Yate",
    "sg:city":"Bristol",
    "sg:classifiers":[
        {
            "category":"Building & Trades",
            "subcategory":"Construction",
            "type":"Services"
        }
    ],
    "sg:phone":"+44 1454 323862",
    "sg:postcode":"BS37 4EA",
    "sg:province":"Gloucestershire",
    "sg:tags":[
        "surfacing",
        "road"
    ],
    "wof:name":"Premier Markings",
    "wof:placetype":"venue"
},
  "geometry": {"coordinates":[-2.41297,51.535168],"type":"Point"}
}