{
  "type": "Feature",
  "properties": {
    "addr:full":"Edge Lane, Henley-in-arden Solihull Warwickshire B95 5DT",
    "addr:postcode":"b95 5dt",
    "addr:street":"Edge Lane",
    "iso:country":"GB",
    "sg:address":"Edge Lane, Henley-in-arden",
    "sg:city":"Solihull",
    "sg:classifiers":[
        {
            "category":"Professional",
            "subcategory":"Engineering",
            "type":"Services"
        }
    ],
    "sg:phone":"+44 1564 792651",
    "sg:postcode":"B95 5DT",
    "sg:province":"Warwickshire",
    "wof:name":"Southern Jig & Tool Co. (Hollywood) Ltd.",
    "wof:placetype":"venue"
},
  "geometry": {"coordinates":[-1.7627509832,52.3087463379],"type":"Point"}
}