{
  "type": "Feature",
  "properties": {
    "iso:country":"GB",
    "sg:address":"19 Willoughby Road, Langley",
    "sg:city":"Slough",
    "sg:classifiers":[
        {
            "category":"Building & Trades",
            "subcategory":"Construction",
            "type":"Services"
        }
    ],
    "sg:phone":"+44 1753 543947",
    "sg:postcode":"SL3 8JH",
    "sg:province":"Berkshire",
    "sg:tags":[
        "dry",
        "lining",
        "plasterers",
        "screeders"
    ],
    "wof:name":"Slough Plastering Co. Ltd.",
    "wof:placetype":"venue"
},
  "geometry": {"coordinates":[-0.540825,51.503227],"type":"Point"}
}