{
  "type": "Feature",
  "properties": {
    "iso:country":"GB",
    "sg:address":"1 Hoegate Street",
    "sg:city":"Plymouth",
    "sg:classifiers":[
        {
            "category":"Organizations",
            "subcategory":"Non-profit Organization",
            "type":"Services"
        }
    ],
    "sg:phone":"+44 1752 256020",
    "sg:postcode":"PL1 2JB",
    "sg:province":"Devon",
    "sg:tags":[
        "organisation",
        "voluntary",
        "charity"
    ],
    "wof:name":"Plymouth Age Concern",
    "wof:placetype":"venue"
},
  "geometry": {"coordinates":[-4.138509,50.368179],"type":"Point"}
}