{
  "type": "Feature",
  "properties": {
    "iso:country":"GB",
    "sg:address":"19 Cilmaengwyn Road, Pontardawe",
    "sg:city":"Swansea",
    "sg:classifiers":[
        {
            "category":"Professional",
            "subcategory":"Computer Services",
            "type":"Services"
        }
    ],
    "sg:phone":"+44 7976 817795",
    "sg:postcode":"SA8 4QL",
    "sg:province":"Neath Port Talbot",
    "sg:tags":[
        "system",
        "software"
    ],
    "wof:name":"Corryn Cyf",
    "wof:placetype":"venue"
},
  "geometry": {"coordinates":[-3.819783,51.741844],"type":"Point"}
}