{
  "type": "Feature",
  "properties": {
    "addr:full":"Ashbourne Close, Backworth Newcastle Upon Tyne Northumberland NE27 0JU",
    "addr:postcode":"ne27 0ju",
    "addr:street":"Ashbourne Close",
    "iso:country":"GB",
    "sg:address":"Ashbourne Close, Backworth",
    "sg:city":"Newcastle Upon Tyne",
    "sg:classifiers":[
        {
            "category":"Social Services",
            "subcategory":"Adult Care",
            "type":"Services"
        },
        {
            "category":"Social Services",
            "subcategory":"Retirement Home",
            "type":"Services"
        }
    ],
    "sg:phone":"+44 191 200 8313",
    "sg:postcode":"NE27 0JU",
    "sg:province":"Northumberland",
    "sg:tags":[
        "housing",
        "sheltered",
        "accommodation"
    ],
    "wof:name":"Eccles Court",
    "wof:placetype":"venue"
},
  "geometry": {"coordinates":[-1.52722,55.0439],"type":"Point"}
}