{
  "type": "Feature",
  "properties": {
    "addr:full":"Castleton Health Centre, 2 Elizabeth St Rochdale Lancashire OL11 3HY",
    "addr:housenumber":"2",
    "addr:postcode":"ol11 3hy",
    "addr:street":"Elizabeth St",
    "iso:country":"GB",
    "sg:address":"Castleton Health Centre, 2 Elizabeth St",
    "sg:city":"Rochdale",
    "sg:classifiers":[
        {
            "category":"Health Services",
            "subcategory":"Doctor",
            "type":"Services"
        }
    ],
    "sg:phone":"+44 1706 658905",
    "sg:postcode":"OL11 3HY",
    "sg:province":"Lancashire",
    "sg:tags":[
        "practitioners"
    ],
    "wof:name":"Worsell, K E",
    "wof:placetype":"venue"
},
  "geometry": {"coordinates":[-2.1823,53.597031],"type":"Point"}
}