{
  "type": "Feature",
  "properties": {
    "addr:full":"58 Davies St West End Hampshire W1Y 1LB",
    "addr:housenumber":"58",
    "addr:postcode":"w1y 1lb",
    "addr:street":"Davies St",
    "iso:country":"GB",
    "sg:address":"58 Davies St",
    "sg:city":"West End",
    "sg:classifiers":[
        {
            "category":"Manufacturing",
            "subcategory":"Jewelry",
            "type":"Manufacturing & Wholesale Goods"
        }
    ],
    "sg:phone":"+44 20 7495 1743",
    "sg:postcode":"W1Y 1LB",
    "sg:province":"Hampshire",
    "sg:tags":[
        "precious",
        "stone"
    ],
    "wof:name":"C Cavey & Associates",
    "wof:placetype":"venue"
},
  "geometry": {"coordinates":[-0.1483809948,51.5132331848],"type":"Point"}
}