{
  "type": "Feature",
  "properties": {
    "addr:full":"14 Slaidburn Avenue Rossendale Lancashire BB4 8JS",
    "addr:housenumber":"14",
    "addr:postcode":"bb4 8js",
    "addr:street":"Slaidburn Avenue",
    "iso:country":"GB",
    "sg:address":"14 Slaidburn Avenue",
    "sg:city":"Rossendale",
    "sg:classifiers":[
        {
            "category":"Personal",
            "subcategory":"Tanning Parlor",
            "type":"Services"
        }
    ],
    "sg:postcode":"BB4 8JS",
    "sg:province":"Lancashire",
    "sg:tags":[
        "sunbeds"
    ],
    "wof:name":"Q T Sunbed Hire",
    "wof:placetype":"venue"
},
  "geometry": {"coordinates":[-2.2870149612,53.7116851807],"type":"Point"}
}