{
  "type": "Feature",
  "properties": {
    "iso:country":"GB",
    "sg:address":"3 Bramble Close, Wickersley",
    "sg:city":"Rotherham",
    "sg:classifiers":[
        {
            "category":"Professional",
            "subcategory":"Management & Consulting",
            "type":"Services"
        }
    ],
    "sg:phone":"+44 1709 531868",
    "sg:postcode":"S66 1FH",
    "sg:province":"South Yorkshire",
    "sg:tags":[
        "environmental",
        "consultant"
    ],
    "wof:name":"Ecology Uk Ltd.",
    "wof:placetype":"venue"
},
  "geometry": {"coordinates":[-1.282744,53.416027],"type":"Point"}
}