{
  "type": "Feature",
  "properties": {
    "addr:full":"Eskdale Grn Holmrook Cumbria CA19 1TS",
    "addr:postcode":"ca19 1ts",
    "addr:street":"Eskdale Grn",
    "iso:country":"GB",
    "sg:address":"Eskdale Grn",
    "sg:city":"Holmrook",
    "sg:classifiers":[
        {
            "category":"Bars & Pubs",
            "type":"Food & Drink"
        }
    ],
    "sg:postcode":"CA19 1TS",
    "sg:province":"Cumbria",
    "sg:tags":[
        "pubs",
        "inn"
    ],
    "wof:name":"King George Iv Inn",
    "wof:placetype":"venue"
},
  "geometry": {"coordinates":[-3.419796,54.385403],"type":"Point"}
}