{
  "type": "Feature",
  "properties": {
    "iso:country":"GB",
    "sg:address":"Dewi Road",
    "sg:city":"Tregaron",
    "sg:classifiers":[
        {
            "category":"Health Services",
            "subcategory":"Hospital",
            "type":"Services"
        }
    ],
    "sg:phone":"+44 1974 298203",
    "sg:postcode":"SY25 6JP",
    "sg:province":"Ceredigion",
    "wof:name":"Tregaron Community Hospital",
    "wof:placetype":"venue"
},
  "geometry": {"coordinates":[-3.933591,52.219215],"type":"Point"}
}