{
  "type": "Feature",
  "properties": {
    "addr:full":"1-7 Garman Road London Greater London N17 0UR",
    "addr:housenumber":"1-7",
    "addr:postcode":"n17 0ur",
    "addr:street":"Garman Road",
    "iso:country":"GB",
    "sg:address":"1-7 Garman Road",
    "sg:city":"London",
    "sg:classifiers":[
        {
            "category":"Ice Cream",
            "type":"Food & Drink"
        }
    ],
    "sg:phone":"+44 20 8365 0000",
    "sg:postcode":"N17 0UR",
    "sg:province":"Greater London",
    "sg:tags":[
        "distributor",
        "mnfr",
        "manufacturer"
    ],
    "wof:name":"Snowcrest Ltd.",
    "wof:placetype":"venue"
},
  "geometry": {"coordinates":[-0.051289,51.602352],"type":"Point"}
}