{
  "type": "Feature",
  "properties": {
    "addr:full":"35a Wilson Road, Huyton Liverpool Merseyside L36 6AE",
    "addr:housenumber":"35a",
    "addr:postcode":"l36 6ae",
    "addr:street":"Wilson Road",
    "iso:country":"GB",
    "sg:address":"35a Wilson Road, Huyton",
    "sg:city":"Liverpool",
    "sg:classifiers":[
        {
            "category":"Building & Trades",
            "subcategory":"Construction",
            "type":"Services"
        }
    ],
    "sg:phone":"+44 151 489 4499",
    "sg:postcode":"L36 6AE",
    "sg:province":"Merseyside",
    "sg:tags":[
        "equipment"
    ],
    "wof:name":"Haze (U K) Ltd.",
    "wof:placetype":"venue"
},
  "geometry": {"coordinates":[-2.825839,53.406986],"type":"Point"}
}