{
  "type": "Feature",
  "properties": {
    "iso:country":"GB",
    "sg:address":"14 Crescenta Walk",
    "sg:city":"Bognor Regis",
    "sg:classifiers":[
        {
            "category":"Retail",
            "subcategory":"Driving School",
            "type":"Services"
        }
    ],
    "sg:phone":"+44 1243 830109",
    "sg:postcode":"PO21 2XS",
    "sg:province":"West Sussex",
    "wof:name":"Aldwick Driving School",
    "wof:placetype":"venue"
},
  "geometry": {"coordinates":[-0.69157,50.785912],"type":"Point"}
}