{
  "type": "Feature",
  "properties": {
    "iso:country":"GB",
    "sg:address":"Hagg Wood, Thongsbridge",
    "sg:city":"Huddersfield",
    "sg:classifiers":[
        {
            "category":"Manufacturing",
            "subcategory":"Building Materials",
            "type":"Manufacturing & Wholesale Goods"
        }
    ],
    "sg:phone":"+44 1484 663547",
    "sg:postcode":"HD7 2RW",
    "sg:province":"West Yorkshire",
    "sg:tags":[
        "stonemason"
    ],
    "wof:name":"Schweidler Construction",
    "wof:placetype":"venue"
},
  "geometry": {"coordinates":[-1.78268,53.64695],"type":"Point"}
}