{
  "type": "Feature",
  "properties": {
    "addr:full":"24 City Arcade Coventry West Midlands CV1 3HW",
    "addr:housenumber":"24",
    "addr:postcode":"cv1 3hw",
    "addr:street":"City Arcade",
    "iso:country":"GB",
    "sg:address":"24 City Arcade",
    "sg:city":"Coventry",
    "sg:classifiers":[
        {
            "category":"Shopping",
            "subcategory":"Department Store",
            "type":"Retail Goods"
        },
        {
            "category":"Shopping",
            "subcategory":"Gifts & Souvenirs",
            "type":"Retail Goods"
        }
    ],
    "sg:postcode":"CV1 3HW",
    "sg:province":"West Midlands",
    "sg:tags":[
        "poster",
        "card"
    ],
    "wof:name":"Karen Neale",
    "wof:placetype":"venue"
},
  "geometry": {"coordinates":[-1.515199,52.406212],"type":"Point"}
}