{
  "type": "Feature",
  "properties": {
    "iso:country":"GB",
    "sg:address":"Clint Rise, Clint Banks, Ripley",
    "sg:city":"Harrogate",
    "sg:classifiers":[
        {
            "category":"Building & Trades",
            "subcategory":"Equipment Rental",
            "type":"Services"
        }
    ],
    "sg:phone":"+44 1423 770731",
    "sg:postcode":"HG3 3DW",
    "sg:province":"North Yorkshire",
    "sg:tags":[
        "plant",
        "machinery"
    ],
    "wof:name":"P & R Plant Hire Ltd.",
    "wof:placetype":"venue"
},
  "geometry": {"coordinates":[-1.609376,54.034405],"type":"Point"}
}