{
  "type": "Feature",
  "properties": {
    "addr:full":"Unit 3 Slater Avenue, Ashbourne Road Derby Derbyshire DE1 1GT",
    "addr:housenumber":"unit 3",
    "addr:postcode":"de1 1gt",
    "addr:street":"Slater Avenue Ashbourne Road",
    "iso:country":"GB",
    "sg:address":"Unit 3 Slater Avenue, Ashbourne Road",
    "sg:city":"Derby",
    "sg:classifiers":[
        {
            "category":"Sports & Exercise",
            "subcategory":"Golf",
            "type":"Entertainment"
        }
    ],
    "sg:phone":"+44 1332 294459",
    "sg:postcode":"DE1 1GT",
    "sg:province":"Derbyshire",
    "sg:tags":[
        "equipment"
    ],
    "wof:name":"Golf Profile Ltd.",
    "wof:placetype":"venue"
},
  "geometry": {"coordinates":[-1.4934899807,52.9248695374],"type":"Point"}
}