{
  "type": "Feature",
  "properties": {
    "iso:country":"GB",
    "sg:address":"6 Parsonage Court, Parsonage Crescent",
    "sg:city":"Sheffield",
    "sg:classifiers":[
        {
            "category":"Organizations",
            "subcategory":"Membership Organization",
            "type":"Services"
        }
    ],
    "sg:postcode":"S6 5BU",
    "sg:province":"South Yorkshire",
    "sg:tags":[
        "club"
    ],
    "wof:name":"Parsonage Crescent Management Ltd",
    "wof:placetype":"venue"
},
  "geometry": {"coordinates":[-1.503566,53.395035],"type":"Point"}
}