{
  "type": "Feature",
  "properties": {
    "addr:full":"Unit 6 Trojan Centre, Stewarts Rd, Finedon Road Indstl Est Wellingborough Northamptonshire NN8 4ST",
    "addr:housenumber":"unit 6",
    "addr:postcode":"nn8 4st",
    "addr:street":"Stewarts Rd Finedon Road Indstl Est",
    "iso:country":"GB",
    "sg:address":"Unit 6 Trojan Centre, Stewarts Rd, Finedon Road Indstl Est",
    "sg:city":"Wellingborough",
    "sg:classifiers":[
        {
            "category":"Manufacturing",
            "subcategory":"Rubber & Plastics",
            "type":"Manufacturing & Wholesale Goods"
        }
    ],
    "sg:postcode":"NN8 4ST",
    "sg:province":"Northamptonshire",
    "sg:tags":[
        "product"
    ],
    "wof:name":"Fairnington,Matthew J,",
    "wof:placetype":"venue"
},
  "geometry": {"coordinates":[-0.6962959766,52.3024215698],"type":"Point"}
}