{
  "type": "Feature",
  "properties": {
    "addr:full":"Byne Hill Caravan Park, Mill Road Girvan South Ayrshire KA26 0HT",
    "addr:postcode":"ka26 0ht",
    "addr:street":"Byne;Mill Road",
    "iso:country":"GB",
    "sg:address":"Byne Hill Caravan Park, Mill Road",
    "sg:city":"Girvan",
    "sg:classifiers":[
        {
            "category":"Recreation",
            "subcategory":"Boat Charter",
            "type":"Entertainment"
        },
        {
            "category":"Wholesale",
            "subcategory":"Scrap",
            "type":"Manufacturing & Wholesale Goods"
        },
        {
            "category":"Government",
            "subcategory":"Department Of Motor Vehicles",
            "type":"Public Place"
        }
    ],
    "sg:phone":"+44 1465 712403",
    "sg:postcode":"KA26 0HT",
    "sg:province":"South Ayrshire",
    "sg:tags":[
        "salvage",
        "excursion"
    ],
    "wof:name":"Speed Lift Auto Salvage",
    "wof:placetype":"venue"
},
  "geometry": {"coordinates":[-4.8455591202,55.237033844],"type":"Point"}
}