{
  "type": "Feature",
  "properties": {
    "iso:country":"GB",
    "sg:address":"8 St Martins",
    "sg:city":"Marlborough",
    "sg:classifiers":[
        {
            "category":"Communications",
            "subcategory":"Film & Video Production",
            "type":"Services"
        }
    ],
    "sg:postcode":"SN8 1AR",
    "sg:province":"Berkshire",
    "sg:tags":[
        "illustrator",
        "artist"
    ],
    "wof:name":"Bajazzo Gallery",
    "wof:placetype":"venue"
},
  "geometry": {"coordinates":[-1.727241993,51.4230003357],"type":"Point"}
}