{
  "type": "Feature",
  "properties": {
    "addr:full":"Lurke Street Bedford Bedfordshire MK40 3HZ",
    "addr:postcode":"mk40 3hz",
    "addr:street":"Lurke Street",
    "iso:country":"GB",
    "sg:address":"Lurke Street",
    "sg:city":"Bedford",
    "sg:classifiers":[
        {
            "category":"Parking",
            "type":"Transportation"
        }
    ],
    "sg:phone":"+44 1234 351430",
    "sg:postcode":"MK40 3HZ",
    "sg:province":"Bedfordshire",
    "sg:tags":[
        "car",
        "park"
    ],
    "wof:name":"Lurke Street Multi Storey Car Park",
    "wof:placetype":"venue"
},
  "geometry": {"coordinates":[-0.466184,52.138145],"type":"Point"}
}