{
  "type": "Feature",
  "properties": {
    "addr:full":"P O Box 41, Mcmullen Road Darlington Durham DL1 1YS",
    "addr:housenumber":"box 41",
    "addr:postcode":"dl1 1ys",
    "addr:street":"P O;Mcmullen Road",
    "iso:country":"GB",
    "sg:address":"P O Box 41, Mcmullen Road",
    "sg:city":"Darlington",
    "sg:classifiers":[
        {
            "category":"Manufacturing",
            "subcategory":"Tobacco Products",
            "type":"Manufacturing & Wholesale Goods"
        },
        {
            "category":"Wholesale",
            "subcategory":"Machinery & Supplies",
            "type":"Manufacturing & Wholesale Goods"
        }
    ],
    "sg:phone":"+44 1325 460666",
    "sg:postcode":"DL1 1YS",
    "sg:province":"Durham",
    "sg:tags":[
        "industrial",
        "commercial"
    ],
    "wof:name":"British American Tabbacco",
    "wof:placetype":"venue"
},
  "geometry": {"coordinates":[-1.548894,54.524502],"type":"Point"}
}