{
  "type": "Feature",
  "properties": {
    "addr:full":"Victoria Square, Victoria St Austell Cornwall PL26 8LQ",
    "addr:postcode":"pl26 8lq",
    "addr:street":"Victoria Square Victoria",
    "iso:country":"GB",
    "sg:address":"Victoria Square, Victoria",
    "sg:city":"St Austell",
    "sg:classifiers":[
        {
            "category":"Real Estate",
            "subcategory":"Developer",
            "type":"Services"
        }
    ],
    "sg:phone":"+44 1726 890444",
    "sg:postcode":"PL26 8LQ",
    "sg:province":"Cornwall",
    "sg:tags":[
        "property"
    ],
    "wof:name":"Land & Property Ltd.",
    "wof:placetype":"venue"
},
  "geometry": {"coordinates":[-4.831546,50.415367],"type":"Point"}
}