{
  "type": "Feature",
  "properties": {
    "addr:full":"2 Chalfont Rd Lower Edmonton Greater London N9 9LW",
    "addr:housenumber":"2",
    "addr:postcode":"n9 9lw",
    "addr:street":"Chalfont Rd",
    "iso:country":"GB",
    "sg:address":"2 Chalfont Rd",
    "sg:city":"Lower Edmonton",
    "sg:classifiers":[
        {
            "category":"Health Services",
            "subcategory":"Doctor",
            "type":"Services"
        }
    ],
    "sg:phone":"+44 20 8807 9886",
    "sg:postcode":"N9 9LW",
    "sg:province":"Greater London",
    "sg:tags":[
        "practitioners"
    ],
    "wof:name":"S.H Yu",
    "wof:placetype":"venue"
},
  "geometry": {"coordinates":[-0.0662460029,51.622303009],"type":"Point"}
}