{
  "type": "Feature",
  "properties": {
    "addr:full":"Clocktower Workspace, 4 Shearling Way Holloway Greater London N7 9TH",
    "addr:housenumber":"4",
    "addr:postcode":"n7 9th",
    "addr:street":"Shearling Way",
    "iso:country":"GB",
    "sg:address":"Clocktower Workspace, 4 Shearling Way",
    "sg:city":"Holloway",
    "sg:classifiers":[
        {
            "category":"Manufacturing",
            "subcategory":"Textiles",
            "type":"Manufacturing & Wholesale Goods"
        }
    ],
    "sg:phone":"+44 20 7609 3310",
    "sg:postcode":"N7 9TH",
    "sg:province":"Greater London",
    "sg:tags":[
        "designer"
    ],
    "wof:name":"Loubi Ltd",
    "wof:placetype":"venue"
},
  "geometry": {"coordinates":[-0.1220199987,51.5480918884],"type":"Point"}
}