{
  "type": "Feature",
  "properties": {
    "addr:full":"2 Kiln Cottages, Stanford Road Faringdon Oxfordshire SN7 8EP",
    "addr:housenumber":"2",
    "addr:postcode":"sn7 8ep",
    "addr:street":"Kiln Cottages Stanford Road",
    "iso:country":"GB",
    "sg:address":"2 Kiln Cottages, Stanford Road",
    "sg:city":"Faringdon",
    "sg:classifiers":[
        {
            "category":"Building & Trades",
            "subcategory":"Construction",
            "type":"Services"
        }
    ],
    "sg:phone":"+44 1367 241373",
    "sg:postcode":"SN7 8EP",
    "sg:province":"Oxfordshire",
    "sg:tags":[
        "joiner",
        "carpenter"
    ],
    "wof:name":"Leonard George Church",
    "wof:placetype":"venue"
},
  "geometry": {"coordinates":[-1.5098179579,51.6424217224],"type":"Point"}
}