{
  "type": "Feature",
  "properties": {
    "addr:full":"105 New City Road Glasgow Glasgow City G4 9JX",
    "addr:housenumber":"105",
    "addr:postcode":"g4 9jx",
    "addr:street":"New City Road",
    "iso:country":"GB",
    "sg:address":"105 New City Road",
    "sg:city":"Glasgow",
    "sg:classifiers":[
        {
            "category":"Farming",
            "subcategory":"Nursery",
            "type":"Manufacturing & Wholesale Goods"
        },
        {
            "category":"Education",
            "subcategory":"Preschool",
            "type":"Public Place"
        }
    ],
    "sg:phone":"+44 141 353 2626",
    "sg:postcode":"G4 9JX",
    "sg:province":"Glasgow City",
    "sg:tags":[
        "school",
        "creche"
    ],
    "wof:name":"A Small World Private Day Nursery",
    "wof:placetype":"venue"
},
  "geometry": {"coordinates":[-4.2627038956,55.8690834045],"type":"Point"}
}