{
  "type": "Feature",
  "properties": {
    "iso:country":"GB",
    "sg:address":"Westfield Rd, Tockwith",
    "sg:city":"York",
    "sg:classifiers":[
        {
            "category":"Bars & Pubs",
            "type":"Food & Drink"
        }
    ],
    "sg:postcode":"YO26 7PY",
    "sg:province":"North Yorkshire",
    "sg:tags":[
        "pubs",
        "inn"
    ],
    "wof:name":"Ray,J M,",
    "wof:placetype":"venue"
},
  "geometry": {"coordinates":[-1.2836040258,53.9649772644],"type":"Point"}
}