{
  "type": "Feature",
  "properties": {
    "iso:country":"GB",
    "sg:address":"68a Green Lane",
    "sg:city":"Northwood",
    "sg:classifiers":[
        {
            "category":"Shopping",
            "subcategory":"Jewelry",
            "type":"Retail Goods"
        },
        {
            "category":"Shopping",
            "subcategory":"Comic Books",
            "type":"Retail Goods"
        }
    ],
    "sg:phone":"+44 1923 826328",
    "sg:postcode":"HA6 2XS",
    "sg:province":"Greater London",
    "sg:tags":[
        "jeweller",
        "sale",
        "jewellery"
    ],
    "wof:name":"Estamira Jewels",
    "wof:placetype":"venue"
},
  "geometry": {"coordinates":[-0.425659,51.611858],"type":"Point"}
}