{
  "type": "Feature",
  "properties": {
    "addr:full":"Surry Ho, 114 Tilt Rd Cobham Surrey KT11 3JH",
    "addr:housenumber":"114",
    "addr:postcode":"kt11 3jh",
    "addr:street":"Tilt Rd",
    "iso:country":"GB",
    "sg:address":"Surry Ho, 114 Tilt Rd",
    "sg:city":"Cobham",
    "sg:classifiers":[
        {
            "category":"Shopping",
            "subcategory":"Books",
            "type":"Retail Goods"
        }
    ],
    "sg:postcode":"KT11 3JH",
    "sg:province":"Surrey",
    "wof:name":"Go Virtual Ltd",
    "wof:placetype":"venue"
},
  "geometry": {"coordinates":[-0.410454,51.328117],"type":"Point"}
}