{
  "type": "Feature",
  "properties": {
    "iso:country":"GB",
    "sg:address":"2 Croydon Road",
    "sg:city":"London",
    "sg:classifiers":[
        {
            "category":"Health Services",
            "subcategory":"Nursing And Care Facility",
            "type":"Services"
        }
    ],
    "sg:phone":"+44 20 8778 5319",
    "sg:postcode":"SE20 7AF",
    "sg:province":"Greater London",
    "sg:tags":[
        "agency"
    ],
    "wof:name":"Beckenham & Penge Private Nursing Agency Ltd.",
    "wof:placetype":"venue"
},
  "geometry": {"coordinates":[-0.051896,51.413826],"type":"Point"}
}