{
  "type": "Feature",
  "properties": {
    "addr:full":"Unit 1 Taylor Lane, Denton Manchester Greater Manchester M34 3NQ",
    "addr:housenumber":"unit 1",
    "addr:postcode":"m34 3nq",
    "addr:street":"Taylor Lane",
    "iso:country":"GB",
    "sg:address":"Unit 1 Taylor Lane, Denton",
    "sg:city":"Manchester",
    "sg:classifiers":[
        {
            "category":"Home & Garden",
            "subcategory":"Home Furnishings",
            "type":"Retail Goods"
        }
    ],
    "sg:phone":"+44 161 320 0882",
    "sg:postcode":"M34 3NQ",
    "sg:province":"Greater Manchester",
    "sg:tags":[
        "furnishers",
        "planner",
        "bedroom"
    ],
    "wof:name":"Crown Bedroom Furniture",
    "wof:placetype":"venue"
},
  "geometry": {"coordinates":[-2.124964,53.46014],"type":"Point"}
}