{
  "type": "Feature",
  "properties": {
    "addr:full":"57/59 Hatfield Road Potters Bar Greater London EN6 1HS",
    "addr:housenumber":"57 / 59",
    "addr:postcode":"en6 1hs",
    "addr:street":"Hatfield Road",
    "iso:country":"GB",
    "sg:address":"57/59 Hatfield Road",
    "sg:city":"Potters Bar",
    "sg:classifiers":[
        {
            "category":"Building & Trades",
            "subcategory":"Construction",
            "type":"Services"
        }
    ],
    "sg:postcode":"EN6 1HS",
    "sg:province":"Greater London",
    "sg:tags":[
        "builder"
    ],
    "wof:name":"Buckley Construction Ltd",
    "wof:placetype":"venue"
},
  "geometry": {"coordinates":[-0.175246,51.70142],"type":"Point"}
}