{
  "type": "Feature",
  "properties": {
    "addr:full":"60 Clerkenwell Road London Greater London EC1M 5PX",
    "addr:housenumber":"60",
    "addr:postcode":"ec1m 5px",
    "addr:street":"Clerkenwell Road",
    "iso:country":"GB",
    "sg:address":"60 Clerkenwell Road",
    "sg:city":"London",
    "sg:classifiers":[
        {
            "category":"Retail",
            "subcategory":"Repair Shop",
            "type":"Services"
        }
    ],
    "sg:phone":"+44 20 7253 4925",
    "sg:postcode":"EC1M 5PX",
    "sg:province":"Greater London",
    "sg:tags":[
        "clocks",
        "watch"
    ],
    "wof:name":"Watch Service Centre",
    "wof:placetype":"venue"
},
  "geometry": {"coordinates":[-0.1010579988,51.5228042603],"type":"Point"}
}