{
  "type": "Feature",
  "properties": {
    "iso:country":"GB",
    "sg:address":"121 Park Road",
    "sg:city":"Peterborough",
    "sg:classifiers":[
        {
            "category":"Professional",
            "subcategory":"Accounting & Tax Preparation",
            "type":"Services"
        }
    ],
    "sg:phone":"+44 1733 555454",
    "sg:postcode":"PE1 2TR",
    "sg:province":"Cambridgeshire",
    "sg:tags":[
        "accountant"
    ],
    "wof:name":"Styles & Co.",
    "wof:placetype":"venue"
},
  "geometry": {"coordinates":[-0.240001,52.579704],"type":"Point"}
}