{
  "type": "Feature",
  "properties": {
    "iso:country":"GB",
    "sg:address":"Bakewell Close",
    "sg:city":"Walsall",
    "sg:classifiers":[
        {
            "category":"Education",
            "subcategory":"School",
            "type":"Public Place"
        },
        {
            "category":"Government",
            "subcategory":"Office",
            "type":"Public Place"
        }
    ],
    "sg:phone":"+44 1922 710479",
    "sg:postcode":"WS3 3QH",
    "sg:province":"Staffordshire",
    "sg:tags":[
        "local",
        "authority"
    ],
    "wof:name":"Lower Farm Junior Mixed & Infant School",
    "wof:placetype":"venue"
},
  "geometry": {"coordinates":[-1.998726,52.628735],"type":"Point"}
}