{
  "type": "Feature",
  "properties": {
    "iso:country":"GB",
    "sg:address":"2nd Floor Taylor Building, 62-64 Bromham Road",
    "sg:city":"Bedford",
    "sg:classifiers":[
        {
            "category":"Home & Garden",
            "subcategory":"Hardware",
            "type":"Retail Goods"
        }
    ],
    "sg:phone":"+44 1234 327013",
    "sg:postcode":"MK40 2QG",
    "sg:province":"Bedfordshire",
    "sg:tags":[
        "equipment",
        "wire",
        "cable"
    ],
    "wof:name":"The Rochester Corp",
    "wof:placetype":"venue"
},
  "geometry": {"coordinates":[-0.464958,52.138973],"type":"Point"}
}