{
  "type": "Feature",
  "properties": {
    "iso:country":"GB",
    "sg:address":"53 Fulford Drive",
    "sg:city":"Northampton",
    "sg:classifiers":[
        {
            "category":"Professional",
            "subcategory":"Engineering",
            "type":"Services"
        }
    ],
    "sg:phone":"+44 1604 718680",
    "sg:postcode":"NN2 7NU",
    "sg:province":"Northamptonshire",
    "sg:tags":[
        "contractor",
        "electrical",
        "engineer"
    ],
    "wof:name":"Coyle Electrics",
    "wof:placetype":"venue"
},
  "geometry": {"coordinates":[-0.879588,52.263489],"type":"Point"}
}