{
  "type": "Feature",
  "properties": {
    "iso:country":"GB",
    "sg:address":"312 Haslucks Green Road, Shirley",
    "sg:city":"Solihull",
    "sg:classifiers":[
        {
            "category":"Autos & Motor Vehicles",
            "subcategory":"Automobile Sales",
            "type":"Retail Goods"
        }
    ],
    "sg:phone":"+44 121 745 5254",
    "sg:postcode":"B90 2NE",
    "sg:province":"West Midlands",
    "sg:tags":[
        "commercial"
    ],
    "wof:name":"O'Neills of Shirley Ltd.",
    "wof:placetype":"venue"
},
  "geometry": {"coordinates":[-1.8435679674,52.4049453735],"type":"Point"}
}