{
  "type": "Feature",
  "properties": {
    "addr:full":"17 Millingford Industrial Estate, Bridge Street, Golborne Warrington Cheshire WA3 3QE",
    "addr:housenumber":"17",
    "addr:postcode":"wa3 3qe",
    "addr:street":"Millingford Industrial Estate Bridge Street",
    "iso:country":"GB",
    "sg:address":"17 Millingford Industrial Estate, Bridge Street, Golborne",
    "sg:city":"Warrington",
    "sg:classifiers":[
        {
            "category":"Cafe",
            "type":"Food & Drink"
        }
    ],
    "sg:phone":"+44 1942 722164",
    "sg:postcode":"WA3 3QE",
    "sg:province":"Cheshire",
    "sg:tags":[
        "tea",
        "room"
    ],
    "wof:name":"Sue's Snack Bar",
    "wof:placetype":"venue"
},
  "geometry": {"coordinates":[-2.5974640846,53.4734802246],"type":"Point"}
}