{
  "type": "Feature",
  "properties": {
    "iso:country":"GB",
    "sg:address":"Woodmancote, Bracknell Road",
    "sg:city":"Crowthorne",
    "sg:classifiers":[
        {
            "category":"Health Services",
            "subcategory":"Nursing And Care Facility",
            "type":"Services"
        }
    ],
    "sg:phone":"+44 1344 773464",
    "sg:postcode":"RG45 6SX",
    "sg:province":"Berkshire",
    "sg:tags":[
        "home"
    ],
    "wof:name":"Crowthorne Old Age to Teens Society",
    "wof:placetype":"venue"
},
  "geometry": {"coordinates":[-0.801989,51.369949],"type":"Point"}
}