{
  "type": "Feature",
  "properties": {
    "addr:full":"131 Abbey Road, West Hampstead London Greater London NW6 4SL",
    "addr:housenumber":"131",
    "addr:postcode":"nw6 4sl",
    "addr:street":"Abbey Road",
    "iso:country":"GB",
    "sg:address":"131 Abbey Road, West Hampstead",
    "sg:city":"London",
    "sg:classifiers":[
        {
            "category":"Shopping",
            "subcategory":"Musical Instruments",
            "type":"Retail Goods"
        }
    ],
    "sg:phone":"+44 20 7624 8895",
    "sg:postcode":"NW6 4SL",
    "sg:province":"Greater London",
    "wof:name":"Hampstead Piano Services",
    "wof:placetype":"venue"
},
  "geometry": {"coordinates":[-0.1881300062,51.5401306152],"type":"Point"}
}