{
  "type": "Feature",
  "properties": {
    "addr:full":"45 Plungington Road, Plungington Preston Lancashire PR1 7EP",
    "addr:housenumber":"45",
    "addr:postcode":"pr1 7ep",
    "addr:street":"Plungington Road Plungington",
    "iso:country":"GB",
    "sg:address":"45 Plungington Road, Plungington",
    "sg:city":"Preston",
    "sg:classifiers":[
        {
            "category":"Professional",
            "subcategory":"Accounting & Tax Preparation",
            "type":"Services"
        }
    ],
    "sg:phone":"+44 1772 828202",
    "sg:postcode":"PR1 7EP",
    "sg:province":"Lancashire",
    "sg:tags":[
        "accountant"
    ],
    "wof:name":"Gemsons Accountants & Tax Advisors",
    "wof:placetype":"venue"
},
  "geometry": {"coordinates":[-2.7106170654,53.7688484192],"type":"Point"}
}