{
  "type": "Feature",
  "properties": {
    "addr:full":"33 High Street, Bodicote Banbury Oxfordshire OX15 4BS",
    "addr:housenumber":"33",
    "addr:postcode":"ox15 4bs",
    "addr:street":"High Street",
    "iso:country":"GB",
    "sg:address":"33 High Street, Bodicote",
    "sg:city":"Banbury",
    "sg:classifiers":[
        {
            "category":"Home & Garden",
            "subcategory":"Furniture",
            "type":"Retail Goods"
        }
    ],
    "sg:phone":"+44 1295 251262",
    "sg:postcode":"OX15 4BS",
    "sg:province":"Oxfordshire",
    "wof:name":"Chloe Interiors",
    "wof:placetype":"venue"
},
  "geometry": {"coordinates":[-1.330919981,52.0378456116],"type":"Point"}
}