{
  "type": "Feature",
  "properties": {
    "addr:full":"Gupworthy Farm, Withycombe Minehead Somerset TA24 6QJ",
    "addr:housenumber":"withycombe minehead",
    "addr:postcode":"ta24 6qj",
    "iso:country":"GB",
    "sg:address":"Gupworthy Farm, Withycombe",
    "sg:city":"Minehead",
    "sg:classifiers":[
        {
            "category":"Home & Garden",
            "subcategory":"Garden Supply",
            "type":"Retail Goods"
        }
    ],
    "sg:phone":"+44 1643 821586",
    "sg:postcode":"TA24 6QJ",
    "sg:province":"Somerset",
    "sg:tags":[
        "turfing"
    ],
    "wof:name":"West Somerset Turf R J & J I Waldron",
    "wof:placetype":"venue"
},
  "geometry": {"coordinates":[-3.408808,51.162579],"type":"Point"}
}