{
  "type": "Feature",
  "properties": {
    "iso:country":"GB",
    "sg:address":"72 Watling Street",
    "sg:city":"London",
    "sg:classifiers":[
        {
            "category":"Personal",
            "type":"Services"
        }
    ],
    "sg:phone":"+44 20 7248 2165",
    "sg:postcode":"EC4M 9BJ",
    "sg:province":"Greater London",
    "sg:tags":[
        "tailor"
    ],
    "wof:name":"D Brake & Son",
    "wof:placetype":"venue"
},
  "geometry": {"coordinates":[-0.093712002,51.5130996704],"type":"Point"}
}