{
  "type": "Feature",
  "properties": {
    "iso:country":"GB",
    "sg:address":"Central Practice, Garth Road, Huntington",
    "sg:city":"York",
    "sg:classifiers":[
        {
            "category":"Health Services",
            "subcategory":"Doctor",
            "type":"Services"
        }
    ],
    "sg:phone":"+44 1904 768841",
    "sg:postcode":"YO32 9QJ",
    "sg:province":"North Yorkshire",
    "sg:tags":[
        "practitioners"
    ],
    "wof:name":"P R Burnett",
    "wof:placetype":"venue"
},
  "geometry": {"coordinates":[-1.068378,53.988235],"type":"Point"}
}