{
  "type": "Feature",
  "properties": {
    "addr:full":"129 Guildford Street Chertsey Surrey KT16 9AL",
    "addr:housenumber":"129",
    "addr:postcode":"kt16 9al",
    "addr:street":"Guildford Street",
    "iso:country":"GB",
    "sg:address":"129 Guildford Street",
    "sg:city":"Chertsey",
    "sg:classifiers":[
        {
            "category":"Health Services",
            "subcategory":"Optometrist",
            "type":"Services"
        }
    ],
    "sg:phone":"+44 1932 563250",
    "sg:postcode":"KT16 9AL",
    "sg:province":"Surrey",
    "sg:tags":[
        "optician"
    ],
    "wof:name":"Chris Boyde Opticians",
    "wof:placetype":"venue"
},
  "geometry": {"coordinates":[-0.5039730072,51.3920593262],"type":"Point"}
}