{
  "type": "Feature",
  "properties": {
    "addr:full":"13 Birch Green Gro Stoke-on-trent Staffordshire ST1 6RD",
    "addr:housenumber":"13",
    "addr:postcode":"staffordshire st1 6rd",
    "addr:street":"Birch",
    "iso:country":"GB",
    "sg:address":"13 Birch Green Gro",
    "sg:city":"Stoke-on-trent",
    "sg:classifiers":[
        {
            "category":"Building & Trades",
            "subcategory":"Construction",
            "type":"Services"
        }
    ],
    "sg:postcode":"ST1 6RD",
    "sg:province":"Staffordshire",
    "sg:tags":[
        "dry",
        "lining",
        "plasterers",
        "screeders"
    ],
    "wof:name":"Alan Littleton",
    "wof:placetype":"venue"
},
  "geometry": {"coordinates":[-2.1630680561,53.038433075],"type":"Point"}
}