{
  "type": "Feature",
  "properties": {
    "addr:full":"19 Fawkham Rd Longfield Kent DA3 7QP",
    "addr:housenumber":"19",
    "addr:postcode":"da3 7qp",
    "addr:street":"Fawkham Rd",
    "iso:country":"GB",
    "sg:address":"19 Fawkham Rd",
    "sg:city":"Longfield",
    "sg:classifiers":[
        {
            "category":"Professional",
            "subcategory":"Management & Consulting",
            "type":"Services"
        }
    ],
    "sg:phone":"+44 1474 702259",
    "sg:postcode":"DA3 7QP",
    "sg:province":"Kent",
    "sg:tags":[
        "consultant",
        "business"
    ],
    "wof:name":"Antelope Consultants Ltd",
    "wof:placetype":"venue"
},
  "geometry": {"coordinates":[0.2960300148,51.3987007141],"type":"Point"}
}