{
  "type": "Feature",
  "properties": {
    "iso:country":"GB",
    "sg:address":"250 Barking Road",
    "sg:city":"London",
    "sg:classifiers":[
        {
            "category":"Restaurant",
            "type":"Food & Drink"
        }
    ],
    "sg:phone":"+44 20 8472 8799",
    "sg:postcode":"E6 3BB",
    "sg:province":"Greater London",
    "sg:tags":[
        "-",
        "italian"
    ],
    "wof:name":"La Vignia Ristorante",
    "wof:placetype":"venue"
},
  "geometry": {"coordinates":[0.049902,51.532185],"type":"Point"}
}