{
  "type": "Feature",
  "properties": {
    "addr:full":"138-144 Windmillhill Street Motherwell North Lanarkshire ML1 1TA",
    "addr:housenumber":"138-144",
    "addr:postcode":"ml1 1ta",
    "addr:street":"Windmillhill Street",
    "iso:country":"GB",
    "sg:address":"138-144 Windmillhill Street",
    "sg:city":"Motherwell",
    "sg:classifiers":[
        {
            "category":"Health Services",
            "subcategory":"Doctor",
            "type":"Services"
        }
    ],
    "sg:phone":"+44 1698 265193",
    "sg:postcode":"ML1 1TA",
    "sg:province":"North Lanarkshire",
    "sg:tags":[
        "practitioners"
    ],
    "wof:name":"Sturgeon McGill & McKenzie",
    "wof:placetype":"venue"
},
  "geometry": {"coordinates":[-3.983589,55.785347],"type":"Point"}
}