{
  "type": "Feature",
  "properties": {
    "iso:country":"GB",
    "sg:address":"4 Gold St",
    "sg:city":"Saffron Walden",
    "sg:classifiers":[
        {
            "category":"Shopping",
            "subcategory":"Stationery & Office Supplies",
            "type":"Retail Goods"
        }
    ],
    "sg:phone":"+44 1799 526087",
    "sg:postcode":"CB10 1EJ",
    "sg:province":"Cambridgeshire",
    "sg:tags":[
        "item",
        "promotional"
    ],
    "wof:name":"Creative House",
    "wof:placetype":"venue"
},
  "geometry": {"coordinates":[0.2400220037,52.0226364136],"type":"Point"}
}