{
  "type": "Feature",
  "properties": {
    "addr:full":"28a Kings Road, Ealing London Greater London W5 2SD",
    "addr:housenumber":"28a",
    "addr:postcode":"w5 2sd",
    "addr:street":"Kings Road",
    "iso:country":"GB",
    "sg:address":"28a Kings Road, Ealing",
    "sg:city":"London",
    "sg:classifiers":[
        {
            "category":"Professional",
            "subcategory":"Engineering",
            "type":"Services"
        }
    ],
    "sg:phone":"+44 20 8997 3215",
    "sg:postcode":"W5 2SD",
    "sg:province":"Greater London",
    "sg:tags":[
        "consulting",
        "engineer"
    ],
    "wof:name":"A.N.McAvoy Limited",
    "wof:placetype":"venue"
},
  "geometry": {"coordinates":[-0.301515013,51.5204200745],"type":"Point"}
}