{
  "type": "Feature",
  "properties": {
    "iso:country":"GB",
    "sg:address":"38 High Street",
    "sg:city":"Eccleshall",
    "sg:classifiers":[
        {
            "category":"Travel",
            "subcategory":"Travel Agent",
            "type":"Entertainment"
        }
    ],
    "sg:phone":"+44 1785 851166",
    "sg:postcode":"ST21 6BZ",
    "sg:province":"Staffordshire",
    "wof:name":"Global Executive Travel",
    "wof:placetype":"venue"
},
  "geometry": {"coordinates":[-2.27688,52.87534],"type":"Point"}
}