{
  "type": "Feature",
  "properties": {
    "addr:full":"Old Milverton Hall, Old Milverton La Leamington Spa Warwickshire CV32 5BE",
    "addr:housenumber":"old milverton hall old",
    "addr:postcode":"cv32 5be",
    "addr:street":"Milverton La",
    "iso:country":"GB",
    "sg:address":"Old Milverton Hall, Old Milverton La",
    "sg:city":"Leamington Spa",
    "sg:classifiers":[
        {
            "category":"Personal",
            "type":"Services"
        }
    ],
    "sg:phone":"+44 1926 316355",
    "sg:postcode":"CV32 5BE",
    "sg:province":"Warwickshire",
    "sg:tags":[
        "consultant",
        "fitness"
    ],
    "wof:name":"Jean's Fitness Scene",
    "wof:placetype":"venue"
},
  "geometry": {"coordinates":[-1.5353239775,52.2891387939],"type":"Point"}
}