{
  "type": "Feature",
  "properties": {
    "iso:country":"GB",
    "sg:address":"147 Eastbank Street",
    "sg:city":"Southport",
    "sg:classifiers":[
        {
            "category":"Retail",
            "subcategory":"Driving School",
            "type":"Services"
        }
    ],
    "sg:postcode":"PR8 1EE",
    "sg:province":"Lancashire",
    "wof:name":"Keiths",
    "wof:placetype":"venue"
},
  "geometry": {"coordinates":[-3.00198102,53.6430969238],"type":"Point"}
}