{
  "type": "Feature",
  "properties": {
    "addr:full":"61 Admiral St, Dingle Liverpool Merseyside L8 8BN",
    "addr:housenumber":"61",
    "addr:postcode":"l8 8bn",
    "addr:street":"Admiral St",
    "iso:country":"GB",
    "sg:address":"61 Admiral St, Dingle",
    "sg:city":"Liverpool",
    "sg:classifiers":[
        {
            "category":"Building & Trades",
            "subcategory":"Construction",
            "type":"Services"
        },
        {
            "category":"Home & Garden",
            "subcategory":"Carpets & Floor Coverings",
            "type":"Retail Goods"
        }
    ],
    "sg:phone":"+44 151 727 8300",
    "sg:postcode":"L8 8BN",
    "sg:province":"Merseyside",
    "sg:tags":[
        "carpets",
        "rug",
        "flooring",
        "matting"
    ],
    "wof:name":"Admiral Carpets",
    "wof:placetype":"venue"
},
  "geometry": {"coordinates":[-2.9624240398,53.387638092],"type":"Point"}
}