{
  "type": "Feature",
  "properties": {
    "iso:country":"GB",
    "sg:address":"58 Bryant Avenue",
    "sg:city":"Slough",
    "sg:classifiers":[
        {
            "category":"Arts & Performance",
            "subcategory":"Music",
            "type":"Entertainment"
        }
    ],
    "sg:postcode":"SL2 1LG",
    "sg:province":"Berkshire",
    "sg:tags":[
        "mobile",
        "disco"
    ],
    "wof:name":"J & R Discos",
    "wof:placetype":"venue"
},
  "geometry": {"coordinates":[-0.6019150019,51.5267105103],"type":"Point"}
}