{
  "type": "Feature",
  "properties": {
    "addr:full":"1 Commercial Ope Plymouth Devon PL4 0LL",
    "addr:housenumber":"1",
    "addr:postcode":"pl4 0ll",
    "iso:country":"GB",
    "sg:address":"1 Commercial Ope",
    "sg:city":"Plymouth",
    "sg:classifiers":[
        {
            "category":"Manufacturing",
            "subcategory":"Metals",
            "type":"Manufacturing & Wholesale Goods"
        },
        {
            "category":"Wholesale",
            "subcategory":"Metals & Minerals",
            "type":"Manufacturing & Wholesale Goods"
        }
    ],
    "sg:phone":"+44 1752 664148",
    "sg:postcode":"PL4 0LL",
    "sg:province":"Devon",
    "sg:tags":[
        "fabricator",
        "work",
        "sheet"
    ],
    "wof:name":"Cotech Fabrications",
    "wof:placetype":"venue"
},
  "geometry": {"coordinates":[-4.1270909309,50.3667030334],"type":"Point"}
}