{
  "type": "Feature",
  "properties": {
    "iso:country":"GB",
    "sg:address":"Friend Boyden & Co, Pembroke House, 11 Northlands Pavement",
    "sg:city":"Basildon",
    "sg:classifiers":[
        {
            "category":"Shopping",
            "subcategory":"Florist",
            "type":"Retail Goods"
        }
    ],
    "sg:phone":"+44 1268 711511",
    "sg:postcode":"SS13 3DX",
    "sg:province":"Essex",
    "wof:name":"Crowsheath Carp Angling & Breeding Farm Ltd.",
    "wof:placetype":"venue"
},
  "geometry": {"coordinates":[0.50408,51.566261],"type":"Point"}
}