{
  "type": "Feature",
  "properties": {
    "addr:full":"3 The Birtles Civic Centre, Wythenshawe Manchester Greater Manchester M22 5RE",
    "addr:housenumber":"3",
    "addr:postcode":"m22 5re",
    "addr:street":"The",
    "iso:country":"GB",
    "sg:address":"3 The Birtles Civic Centre, Wythenshawe",
    "sg:city":"Manchester",
    "sg:classifiers":[
        {
            "category":"Personal",
            "subcategory":"Beauty Salon",
            "type":"Services"
        }
    ],
    "sg:phone":"+44 161 437 7151",
    "sg:postcode":"M22 5RE",
    "sg:province":"Greater Manchester",
    "wof:name":"Beach Bodies",
    "wof:placetype":"venue"
},
  "geometry": {"coordinates":[-2.26214,53.380329],"type":"Point"}
}