{
  "type": "Feature",
  "properties": {
    "addr:full":"High House Farm, Mendlesham Grn Stowmarket Suffolk IP14 5RQ",
    "addr:postcode":"ip14 5rq",
    "addr:street":"High House;Mendlesham Grn",
    "iso:country":"GB",
    "sg:address":"High House Farm, Mendlesham Grn",
    "sg:city":"Stowmarket",
    "sg:classifiers":[
        {
            "category":"Sports & Exercise",
            "subcategory":"Stables",
            "type":"Entertainment"
        }
    ],
    "sg:phone":"+44 1449 766716",
    "sg:postcode":"IP14 5RQ",
    "sg:province":"Suffolk",
    "sg:tags":[
        "equestrian",
        "centre",
        "livery",
        "schools",
        "riding",
        "education"
    ],
    "wof:name":"High House Riding Centre",
    "wof:placetype":"venue"
},
  "geometry": {"coordinates":[1.082645,52.2505],"type":"Point"}
}