{
  "type": "Feature",
  "properties": {
    "addr:full":"Springfield Road Stornoway Eilean Siar HS1 2PZ",
    "addr:postcode":"hs1 2pz",
    "addr:street":"Springfield Road",
    "iso:country":"GB",
    "sg:address":"Springfield Road",
    "sg:city":"Stornoway",
    "sg:classifiers":[
        {
            "category":"Professional",
            "type":"Services"
        },
        {
            "category":"Education",
            "subcategory":"School",
            "type":"Public Place"
        }
    ],
    "sg:phone":"+44 1851 705286",
    "sg:postcode":"HS1 2PZ",
    "sg:province":"Eilean Siar",
    "sg:tags":[
        "local",
        "authority",
        "caterer"
    ],
    "wof:name":"Nicolson Institute Canteen",
    "wof:placetype":"venue"
},
  "geometry": {"coordinates":[-6.369964,58.21402],"type":"Point"}
}