{
  "type": "Feature",
  "properties": {
    "addr:full":"25 Evesham Walk Redditch Warwickshire B97 4ET",
    "addr:housenumber":"25",
    "addr:postcode":"b97 4et",
    "addr:street":"Evesham Walk",
    "iso:country":"GB",
    "sg:address":"25 Evesham Walk",
    "sg:city":"Redditch",
    "sg:classifiers":[
        {
            "category":"Sports & Exercise",
            "subcategory":"Sports Center",
            "type":"Entertainment"
        }
    ],
    "sg:phone":"+44 1527 591319",
    "sg:postcode":"B97 4ET",
    "sg:province":"Warwickshire",
    "sg:tags":[
        "shop",
        "good"
    ],
    "wof:name":"Gilesports",
    "wof:placetype":"venue"
},
  "geometry": {"coordinates":[-1.9457410574,52.2946243286],"type":"Point"}
}