{
  "type": "Feature",
  "properties": {
    "iso:country":"GB",
    "sg:address":"190 Sandringham Road, Intake",
    "sg:city":"Doncaster",
    "sg:classifiers":[
        {
            "category":"Fast Food",
            "type":"Food & Drink"
        }
    ],
    "sg:phone":"+44 1302 323063",
    "sg:postcode":"DN2 5JE",
    "sg:province":"South Yorkshire",
    "sg:tags":[
        "away",
        "meal",
        "outlet",
        "take"
    ],
    "wof:name":"Goldfish Bowl",
    "wof:placetype":"venue"
},
  "geometry": {"coordinates":[-1.102214,53.529808],"type":"Point"}
}