{
  "type": "Feature",
  "properties": {
    "addr:full":"138 Charles St Leicester Leicestershire LE1 1LB",
    "addr:housenumber":"138",
    "addr:postcode":"le1 1lb",
    "addr:street":"Charles St",
    "iso:country":"GB",
    "sg:address":"138 Charles St",
    "sg:city":"Leicester",
    "sg:classifiers":[
        {
            "category":"Professional",
            "type":"Services"
        }
    ],
    "sg:phone":"+44 116 253 0491",
    "sg:postcode":"LE1 1LB",
    "sg:province":"Leicestershire",
    "sg:tags":[
        "entertainer"
    ],
    "wof:name":"Leicester Caribbean Carnival",
    "wof:placetype":"venue"
},
  "geometry": {"coordinates":[-1.1276550293,52.6336898804],"type":"Point"}
}