{
  "type": "Feature",
  "properties": {
    "iso:country":"GB",
    "sg:address":"5 Furnace Parade",
    "sg:city":"Crawley",
    "sg:classifiers":[
        {
            "category":"Utilities",
            "type":"Services"
        }
    ],
    "sg:phone":"+44 131 336 2244",
    "sg:postcode":"RH10 6NX",
    "sg:province":"Surrey",
    "sg:tags":[
        "internet"
    ],
    "wof:name":"K 2 Ltd.",
    "wof:placetype":"venue"
},
  "geometry": {"coordinates":[-0.1685930043,51.1074867249],"type":"Point"}
}