{
  "type": "Feature",
  "properties": {
    "addr:full":"Marlborough Ho, 159 High St Harrow Greater London HA3 5DX",
    "addr:housenumber":"159",
    "addr:postcode":"ha3 5dx",
    "addr:street":"High St",
    "iso:country":"GB",
    "sg:address":"Marlborough Ho, 159 High St",
    "sg:city":"Harrow",
    "sg:classifiers":[
        {
            "category":"Government",
            "subcategory":"Post Office",
            "type":"Public Place"
        }
    ],
    "sg:phone":"+44 20 8861 2366",
    "sg:postcode":"HA3 5DX",
    "sg:province":"Greater London",
    "sg:tags":[
        "messenger",
        "courier"
    ],
    "wof:name":"Speed Couriers",
    "wof:placetype":"venue"
},
  "geometry": {"coordinates":[-0.33726,51.598129],"type":"Point"}
}