{
  "type": "Feature",
  "properties": {
    "iso:country":"GB",
    "sg:address":"26 Highgrove Hill, Great Holm",
    "sg:city":"Milton Keynes",
    "sg:classifiers":[
        {
            "category":"Professional",
            "subcategory":"Management & Consulting",
            "type":"Services"
        }
    ],
    "sg:phone":"+44 1908 565121",
    "sg:postcode":"MK8 9AG",
    "sg:province":"Buckinghamshire",
    "sg:tags":[
        "consultant",
        "business"
    ],
    "wof:name":"Teamtalk Consulting Ltd.",
    "wof:placetype":"venue"
},
  "geometry": {"coordinates":[-0.79426,52.033073],"type":"Point"}
}