{
  "type": "Feature",
  "properties": {
    "addr:full":"53 Royce Close Andover Hampshire SP10 3TS",
    "addr:housenumber":"53",
    "addr:postcode":"sp10 3ts",
    "addr:street":"Royce Close",
    "iso:country":"GB",
    "sg:address":"53 Royce Close",
    "sg:city":"Andover",
    "sg:classifiers":[
        {
            "category":"Professional",
            "type":"Services"
        }
    ],
    "sg:phone":"+44 1264 334134",
    "sg:postcode":"SP10 3TS",
    "sg:province":"Hampshire",
    "sg:tags":[
        "specialist",
        "coating"
    ],
    "wof:name":"I C P (Coatings) Ltd.",
    "wof:placetype":"venue"
},
  "geometry": {"coordinates":[-1.5151679516,51.2133827209],"type":"Point"}
}