{
  "type": "Feature",
  "properties": {
    "iso:country":"GB",
    "sg:address":"46-48 Long St",
    "sg:city":"Manchester",
    "sg:classifiers":[
        {
            "category":"Retail",
            "subcategory":"Auto Rental",
            "type":"Services"
        }
    ],
    "sg:phone":"+44 161 655 3555",
    "sg:postcode":"M24 6UQ",
    "sg:province":"Greater Manchester",
    "sg:tags":[
        "car",
        "hire",
        "truck"
    ],
    "wof:name":"Advantage Vehicle Leasing & Finance",
    "wof:placetype":"venue"
},
  "geometry": {"coordinates":[-2.196462,53.551731],"type":"Point"}
}