{
  "type": "Feature",
  "properties": {
    "addr:full":"83 Kilburn High Road London Greater London NW6 6JE",
    "addr:housenumber":"83",
    "addr:postcode":"nw6 6je",
    "addr:street":"Kilburn High Road",
    "iso:country":"GB",
    "sg:address":"83 Kilburn High Road",
    "sg:city":"London",
    "sg:classifiers":[
        {
            "category":"Banks & Credit Unions",
            "subcategory":"Bank",
            "type":"Services"
        }
    ],
    "sg:phone":"+44 20 8301 7312",
    "sg:postcode":"NW6 6JE",
    "sg:province":"Greater London",
    "wof:name":"Woolwich Ltd.",
    "wof:placetype":"venue"
},
  "geometry": {"coordinates":[-0.192438,51.537201],"type":"Point"}
}