{
  "type": "Feature",
  "properties": {
    "iso:country":"GB",
    "sg:address":"Church House, 46 High Street",
    "sg:city":"Billericay",
    "sg:classifiers":[
        {
            "category":"Professional",
            "subcategory":"Employment Agencies",
            "type":"Services"
        }
    ],
    "sg:phone":"+44 1268 573939",
    "sg:postcode":"CM12 9BS",
    "sg:province":"Essex",
    "sg:tags":[
        "consultant"
    ],
    "wof:name":"M Associates",
    "wof:placetype":"venue"
},
  "geometry": {"coordinates":[0.418368,51.62672],"type":"Point"}
}