{
  "type": "Feature",
  "properties": {
    "iso:country":"GB",
    "sg:address":"6 Effingham Road, Long Ditton",
    "sg:city":"Surbiton",
    "sg:classifiers":[
        {
            "category":"Professional",
            "subcategory":"Accounting & Tax Preparation",
            "type":"Services"
        }
    ],
    "sg:phone":"+44 20 8398 0138",
    "sg:postcode":"KT6 5JY",
    "sg:province":"Surrey",
    "sg:tags":[
        "accountant"
    ],
    "wof:name":"Da Costa Peter & Co",
    "wof:placetype":"venue"
},
  "geometry": {"coordinates":[-0.3172650039,51.38804245],"type":"Point"}
}