{
  "type": "Feature",
  "properties": {
    "iso:country":"GB",
    "sg:address":"21 Delamere St",
    "sg:city":"Ashton-under-lyne",
    "sg:classifiers":[
        {
            "category":"Home & Garden",
            "subcategory":"Home Furnishings",
            "type":"Retail Goods"
        }
    ],
    "sg:postcode":"OL6 7LZ",
    "sg:province":"Greater Manchester",
    "sg:tags":[
        "furnishers",
        "planner",
        "kitchen"
    ],
    "wof:name":"Avanti Kitchens & Bedrooms",
    "wof:placetype":"venue"
},
  "geometry": {"coordinates":[-2.0946619511,53.4874801636],"type":"Point"}
}