{
  "type": "Feature",
  "properties": {
    "addr:full":"23 Middlegate Hartlepool Durham TS24 0JD",
    "addr:housenumber":"23",
    "addr:postcode":"ts24 0jd",
    "addr:street":"Middlegate Hartlepool",
    "iso:country":"GB",
    "sg:address":"23 Middlegate",
    "sg:city":"Hartlepool",
    "sg:classifiers":[
        {
            "category":"Place Of Worship",
            "type":"Public Place"
        }
    ],
    "sg:phone":"+44 1429 266080",
    "sg:postcode":"TS24 0JD",
    "sg:province":"Durham",
    "wof:name":"St. Marys R C Church",
    "wof:placetype":"venue"
},
  "geometry": {"coordinates":[-1.182932,54.696007],"type":"Point"}
}