{
  "type": "Feature",
  "properties": {
    "iso:country":"GB",
    "sg:address":"Town Fields",
    "sg:city":"Doncaster",
    "sg:classifiers":[
        {
            "category":"Organizations",
            "subcategory":"Non-profit Organization",
            "type":"Services"
        }
    ],
    "sg:phone":"+44 1302 326397",
    "sg:postcode":"DN1 2JQ",
    "sg:province":"South Yorkshire",
    "sg:tags":[
        "organisation",
        "voluntary",
        "charity"
    ],
    "wof:name":"Clark Memorial Hall The",
    "wof:placetype":"venue"
},
  "geometry": {"coordinates":[-1.122192,53.524204],"type":"Point"}
}