{
  "type": "Feature",
  "properties": {
    "addr:full":"63 Askew Road, Sheppards Bush London Greater London W12 9AH",
    "addr:housenumber":"63",
    "addr:postcode":"w12 9ah",
    "addr:street":"Askew Road",
    "iso:country":"GB",
    "sg:address":"63 Askew Road, Sheppards Bush",
    "sg:city":"London",
    "sg:classifiers":[
        {
            "category":"Restaurant",
            "type":"Food & Drink"
        }
    ],
    "sg:phone":"+44 20 8743 1289",
    "sg:postcode":"W12 9AH",
    "sg:province":"Greater London",
    "wof:name":"la Copita",
    "wof:placetype":"venue"
},
  "geometry": {"coordinates":[-0.243475005,51.5043792725],"type":"Point"}
}