{
  "type": "Feature",
  "properties": {
    "iso:country":"GB",
    "sg:address":"77 Thorpe Drive, Waterthorpe",
    "sg:city":"Sheffield",
    "sg:classifiers":[
        {
            "category":"Building & Trades",
            "subcategory":"Construction",
            "type":"Services"
        }
    ],
    "sg:phone":"+44 114 279 7874",
    "sg:postcode":"S20 7HU",
    "sg:province":"South Yorkshire",
    "sg:tags":[
        "roofing"
    ],
    "wof:name":"Compass Roofing Co.",
    "wof:placetype":"venue"
},
  "geometry": {"coordinates":[-1.3509060144,53.3372612],"type":"Point"}
}