{
  "type": "Feature",
  "properties": {
    "addr:full":"75 Cato Street, Nechells Birmingham West Midlands B7 4TS",
    "addr:housenumber":"75",
    "addr:postcode":"b7 4ts",
    "addr:street":"Cato Street",
    "iso:country":"GB",
    "sg:address":"75 Cato Street, Nechells",
    "sg:city":"Birmingham",
    "sg:classifiers":[
        {
            "category":"Wholesale",
            "subcategory":"Metals & Minerals",
            "type":"Manufacturing & Wholesale Goods"
        }
    ],
    "sg:phone":"+44 121 359 8181",
    "sg:postcode":"B7 4TS",
    "sg:province":"West Midlands",
    "sg:tags":[
        "aluminium",
        "stockholder"
    ],
    "wof:name":"Villamead Ltd.",
    "wof:placetype":"venue"
},
  "geometry": {"coordinates":[-1.868895,52.49118],"type":"Point"}
}