{
  "type": "Feature",
  "properties": {
    "addr:full":"The Cottage, The Street, Effingham Leatherhead Surrey KT24 5LQ",
    "addr:postcode":"kt24 5lq",
    "addr:street":"The Street",
    "iso:country":"GB",
    "sg:address":"The Cottage, The Street, Effingham",
    "sg:city":"Leatherhead",
    "sg:classifiers":[
        {
            "category":"Building & Trades",
            "subcategory":"Pest Control",
            "type":"Services"
        }
    ],
    "sg:postcode":"KT24 5LQ",
    "sg:province":"Surrey",
    "sg:tags":[
        "vermin"
    ],
    "wof:name":"Carpenter,Michael J,",
    "wof:placetype":"venue"
},
  "geometry": {"coordinates":[-0.4004240036,51.2722206116],"type":"Point"}
}