{
  "type": "Feature",
  "properties": {
    "addr:full":"3 Crawley Hatch Harlow Essex CM20 3HL",
    "addr:housenumber":"3",
    "addr:postcode":"cm20 3hl",
    "addr:street":"Crawley",
    "iso:country":"GB",
    "sg:address":"3 Crawley Hatch",
    "sg:city":"Harlow",
    "sg:classifiers":[
        {
            "category":"Cafe",
            "type":"Food & Drink"
        }
    ],
    "sg:phone":"+44 1279 438989",
    "sg:postcode":"CM20 3HL",
    "sg:province":"Essex",
    "sg:tags":[
        "tea",
        "room"
    ],
    "wof:name":"Little Piggies Pantry",
    "wof:placetype":"venue"
},
  "geometry": {"coordinates":[0.1147200018,51.7725296021],"type":"Point"}
}