{
  "type": "Feature",
  "properties": {
    "iso:country":"GB",
    "sg:address":"Mallards, Church Road",
    "sg:city":"Chelmsford",
    "sg:classifiers":[
        {
            "category":"Retail",
            "subcategory":"Repair Shop",
            "type":"Services"
        }
    ],
    "sg:postcode":"CM2 8UQ",
    "sg:province":"Essex",
    "sg:tags":[
        "maintenance"
    ],
    "wof:name":"Paul E Irvine",
    "wof:placetype":"venue"
},
  "geometry": {"coordinates":[0.4659979939,51.7103233337],"type":"Point"}
}