{
  "type": "Feature",
  "properties": {
    "iso:country":"GB",
    "sg:address":"Ashbourne Road, Spath",
    "sg:city":"Uttoxeter",
    "sg:classifiers":[
        {
            "category":"Home & Garden",
            "subcategory":"Garden Supply",
            "type":"Retail Goods"
        }
    ],
    "sg:phone":"+44 1889 563377",
    "sg:postcode":"ST14 5AD",
    "sg:province":"Derbyshire",
    "sg:tags":[
        "nursery",
        "centre"
    ],
    "wof:name":"Heldon Nursery",
    "wof:placetype":"venue"
},
  "geometry": {"coordinates":[-1.873359,52.913555],"type":"Point"}
}