{
  "type": "Feature",
  "properties": {
    "addr:full":"Easington Rd Hartlepool Durham TS24 8JZ",
    "addr:postcode":"ts24 8jz",
    "addr:street":"Easington Rd",
    "iso:country":"GB",
    "sg:address":"Easington Rd",
    "sg:city":"Hartlepool",
    "sg:classifiers":[
        {
            "category":"Organizations",
            "subcategory":"Membership Organization",
            "type":"Services"
        }
    ],
    "sg:postcode":"TS24 8JZ",
    "sg:province":"Durham",
    "sg:tags":[
        "club"
    ],
    "wof:name":"Iona Social Centre",
    "wof:placetype":"venue"
},
  "geometry": {"coordinates":[-1.2285939455,54.699886322],"type":"Point"}
}