{
  "type": "Feature",
  "properties": {
    "iso:country":"GB",
    "sg:address":"15a Codicote Rd",
    "sg:city":"Welwyn",
    "sg:classifiers":[
        {
            "category":"Health Services",
            "subcategory":"Doctor",
            "type":"Services"
        },
        {
            "category":"Health Services",
            "subcategory":"Health Practitioner",
            "type":"Services"
        }
    ],
    "sg:phone":"+44 1438 716838",
    "sg:postcode":"AL6 9NE",
    "sg:province":"Hertfordshire",
    "sg:tags":[
        "physiotherapist",
        "practitioners"
    ],
    "wof:name":"Sperre-Dansie B Mrs",
    "wof:placetype":"venue"
},
  "geometry": {"coordinates":[-0.22009,51.838169],"type":"Point"}
}