{
  "type": "Feature",
  "properties": {
    "addr:full":"66 West Gate Mansfield Nottinghamshire NG18 1RR",
    "addr:housenumber":"66",
    "addr:postcode":"ng18 1rr",
    "addr:street":"West Gate",
    "iso:country":"GB",
    "sg:address":"66 West Gate",
    "sg:city":"Mansfield",
    "sg:classifiers":[
        {
            "category":"Real Estate",
            "subcategory":"Real Estate Agent",
            "type":"Services"
        }
    ],
    "sg:phone":"+44 1623 654454",
    "sg:postcode":"NG18 1RR",
    "sg:province":"Nottinghamshire",
    "wof:name":"Gascoignes",
    "wof:placetype":"venue"
},
  "geometry": {"coordinates":[-1.1988990307,53.1464004517],"type":"Point"}
}