{
  "type": "Feature",
  "properties": {
    "addr:full":"155 Glencoe Rd Chatham Kent ME4 5QF",
    "addr:housenumber":"155",
    "addr:postcode":"me4 5qf",
    "addr:street":"Glencoe Rd",
    "iso:country":"GB",
    "sg:address":"155 Glencoe Rd",
    "sg:city":"Chatham",
    "sg:classifiers":[
        {
            "category":"Professional",
            "subcategory":"Detective & Security Services",
            "type":"Services"
        }
    ],
    "sg:phone":"+44 1892 547211",
    "sg:postcode":"ME4 5QF",
    "sg:province":"Kent",
    "sg:tags":[
        "locksmith"
    ],
    "wof:name":"Permclose Door & Shutter Services Ltd",
    "wof:placetype":"venue"
},
  "geometry": {"coordinates":[0.532399,51.372677],"type":"Point"}
}