{
  "type": "Feature",
  "properties": {
    "addr:full":"5 Heather Ridge Arcade Camberley Berkshire GU15 1AX",
    "addr:housenumber":"5",
    "addr:postcode":"gu15 1ax",
    "addr:street":"Heather Ridge Arcade",
    "iso:country":"GB",
    "sg:address":"5 Heather Ridge Arcade",
    "sg:city":"Camberley",
    "sg:classifiers":[
        {
            "category":"Fast Food",
            "type":"Food & Drink"
        },
        {
            "category":"Restaurant",
            "type":"Food & Drink"
        }
    ],
    "sg:phone":"+44 1276 692333",
    "sg:postcode":"GU15 1AX",
    "sg:province":"Berkshire",
    "sg:tags":[
        "away",
        "take"
    ],
    "wof:name":"Korai",
    "wof:placetype":"venue"
},
  "geometry": {"coordinates":[-0.7342299819,51.3362159729],"type":"Point"}
}