{
  "type": "Feature",
  "properties": {
    "addr:full":"Folletts Farm, Dunwear Bridgwater Somerset TA6 5HH",
    "addr:postcode":"ta6 5hh",
    "addr:street":"Dunwear",
    "iso:country":"GB",
    "sg:address":"Folletts Farm, Dunwear",
    "sg:city":"Bridgwater",
    "sg:classifiers":[
        {
            "category":"Farming",
            "subcategory":"Farm",
            "type":"Manufacturing & Wholesale Goods"
        }
    ],
    "sg:phone":"+44 1278 424297",
    "sg:postcode":"TA6 5HH",
    "sg:province":"Somerset",
    "sg:tags":[
        "mixed",
        "crop"
    ],
    "wof:name":"L R House",
    "wof:placetype":"venue"
},
  "geometry": {"coordinates":[-3.0138239861,51.1275558472],"type":"Point"}
}