{
  "type": "Feature",
  "properties": {
    "addr:full":"Clough Street, Hanley Stoke-on-trent Staffordshire ST1 4BA",
    "addr:postcode":"staffordshire st1 4ba",
    "addr:street":"Clough Street",
    "iso:country":"GB",
    "sg:address":"Clough Street, Hanley",
    "sg:city":"Stoke-on-trent",
    "sg:classifiers":[
        {
            "category":"Wholesale",
            "subcategory":"Scrap",
            "type":"Manufacturing & Wholesale Goods"
        }
    ],
    "sg:postcode":"ST1 4BA",
    "sg:province":"Staffordshire",
    "sg:tags":[
        "waste",
        "metal"
    ],
    "wof:name":"George Poole",
    "wof:placetype":"venue"
},
  "geometry": {"coordinates":[-2.179764,53.024479],"type":"Point"}
}