{
  "type": "Feature",
  "properties": {
    "iso:country":"GB",
    "sg:address":"15 Mill Street",
    "sg:city":"Congleton",
    "sg:classifiers":[
        {
            "category":"Food & Beverages",
            "subcategory":"Fruits & Vegetables",
            "type":"Retail Goods"
        }
    ],
    "sg:phone":"+44 1260 273249",
    "sg:postcode":"CW12 1AB",
    "sg:province":"Cheshire",
    "sg:tags":[
        "greengrocer"
    ],
    "wof:name":"R J & J Moore",
    "wof:placetype":"venue"
},
  "geometry": {"coordinates":[-2.214159,53.164261],"type":"Point"}
}