{
  "type": "Feature",
  "properties": {
    "addr:full":"7 Burghead Close, College Town Sandhurst Berkshire GU47 0XL",
    "addr:housenumber":"7",
    "addr:postcode":"gu47 0xl",
    "addr:street":"Burghead Close",
    "iso:country":"GB",
    "sg:address":"7 Burghead Close, College Town",
    "sg:city":"Sandhurst",
    "sg:classifiers":[
        {
            "category":"Shopping",
            "subcategory":"Pharmacy",
            "type":"Retail Goods"
        }
    ],
    "sg:postcode":"GU47 0XL",
    "sg:province":"Berkshire",
    "sg:tags":[
        "medicine",
        "therapy"
    ],
    "wof:name":"Energy Wise Feng Shui Ltd",
    "wof:placetype":"venue"
},
  "geometry": {"coordinates":[-0.786374,51.349941],"type":"Point"}
}