{
  "type": "Feature",
  "properties": {
    "addr:full":"129 Maidenway Road Paignton Devon TQ3 2PZ",
    "addr:housenumber":"129",
    "addr:postcode":"tq3 2pz",
    "addr:street":"Maidenway Road",
    "iso:country":"GB",
    "sg:address":"129 Maidenway Road",
    "sg:city":"Paignton",
    "sg:classifiers":[
        {
            "category":"Building & Trades",
            "subcategory":"Construction",
            "type":"Services"
        }
    ],
    "sg:postcode":"TQ3 2PZ",
    "sg:province":"Devon",
    "sg:tags":[
        "builder"
    ],
    "wof:name":"K A O'Neill",
    "wof:placetype":"venue"
},
  "geometry": {"coordinates":[-3.580552,50.444496],"type":"Point"}
}