{
  "type": "Feature",
  "properties": {
    "iso:country":"GB",
    "sg:address":"Blackshaw Nursery, St Georges Hospital",
    "sg:city":"London",
    "sg:classifiers":[
        {
            "category":"Farming",
            "subcategory":"Nursery",
            "type":"Manufacturing & Wholesale Goods"
        }
    ],
    "sg:phone":"+44 20 8672 4789",
    "sg:postcode":"SW17 0QT",
    "sg:province":"Greater London",
    "sg:tags":[
        "creche"
    ],
    "wof:name":"Blackshaw Nursery",
    "wof:placetype":"venue"
},
  "geometry": {"coordinates":[-0.17573,51.42667],"type":"Point"}
}