{
  "type": "Feature",
  "properties": {
    "iso:country":"GB",
    "sg:address":"512 London Road",
    "sg:city":"Thornton Heath",
    "sg:classifiers":[
        {
            "category":"Fast Food",
            "type":"Food & Drink"
        }
    ],
    "sg:phone":"+44 20 8684 5855",
    "sg:postcode":"CR7 7HQ",
    "sg:province":"Surrey",
    "sg:tags":[
        "away",
        "take"
    ],
    "wof:name":"Hungwon Restaurant",
    "wof:placetype":"venue"
},
  "geometry": {"coordinates":[-0.114492,51.39468],"type":"Point"}
}