{
  "type": "Feature",
  "properties": {
    "iso:country":"GB",
    "sg:address":"Chestnuts Farm, Langton Grn",
    "sg:city":"Eye",
    "sg:classifiers":[
        {
            "category":"Professional",
            "subcategory":"Accounting & Tax Preparation",
            "type":"Services"
        }
    ],
    "sg:phone":"+44 1379 871117",
    "sg:postcode":"IP23 7HN",
    "sg:province":"Suffolk",
    "sg:tags":[
        "herb",
        "spice"
    ],
    "wof:name":"Frozen Herbs Ltd.",
    "wof:placetype":"venue"
},
  "geometry": {"coordinates":[1.145876,52.322071],"type":"Point"}
}