{
  "type": "Feature",
  "properties": {
    "iso:country":"GB",
    "sg:address":"69 Norman Road",
    "sg:city":"St Leonards-on-sea",
    "sg:classifiers":[
        {
            "category":"Social Services",
            "subcategory":"Adult Care",
            "type":"Services"
        }
    ],
    "sg:postcode":"TN38 0EG",
    "sg:province":"East Sussex",
    "sg:tags":[
        "day",
        "centre"
    ],
    "wof:name":"Shellgate Day Centre",
    "wof:placetype":"venue"
},
  "geometry": {"coordinates":[0.558814,50.85207],"type":"Point"}
}