{
  "type": "Feature",
  "properties": {
    "addr:full":"221 Northolt Road Harrow Greater London HA2 8HN",
    "addr:housenumber":"221",
    "addr:postcode":"ha2 8hn",
    "addr:street":"Northolt Road",
    "iso:country":"GB",
    "sg:address":"221 Northolt Road",
    "sg:city":"Harrow",
    "sg:classifiers":[
        {
            "category":"Shopping",
            "subcategory":"Shoes",
            "type":"Retail Goods"
        }
    ],
    "sg:phone":"+44 20 8422 6886",
    "sg:postcode":"HA2 8HN",
    "sg:province":"Greater London",
    "wof:name":"Head of Shoe Repair",
    "wof:placetype":"venue"
},
  "geometry": {"coordinates":[-0.3524430096,51.5649414062],"type":"Point"}
}