{
  "type": "Feature",
  "properties": {
    "iso:country":"GB",
    "sg:address":"P O Box 42",
    "sg:city":"Peterborough",
    "sg:classifiers":[
        {
            "category":"Organizations",
            "subcategory":"Non-profit Organization",
            "type":"Services"
        }
    ],
    "sg:phone":"+44 1733 52400",
    "sg:postcode":"PE1 1BN",
    "sg:province":"Cambridgeshire",
    "sg:tags":[
        "organisation",
        "voluntary",
        "charity"
    ],
    "wof:name":"Anglian Water Trust Fund",
    "wof:placetype":"venue"
},
  "geometry": {"coordinates":[-0.25395,52.582539],"type":"Point"}
}