{
  "type": "Feature",
  "properties": {
    "iso:country":"GB",
    "sg:address":"5 Chevet Croft, Sandal",
    "sg:city":"Wakefield",
    "sg:classifiers":[
        {
            "category":"Retail",
            "subcategory":"Driving School",
            "type":"Services"
        }
    ],
    "sg:postcode":"WF2 6QR",
    "sg:province":"West Yorkshire",
    "wof:name":"Whiteways Industries Ltd",
    "wof:placetype":"venue"
},
  "geometry": {"coordinates":[-1.483042,53.651855],"type":"Point"}
}