{
  "type": "Feature",
  "properties": {
    "addr:full":"5 Chevet Croft, Sandal Wakefield West Yorkshire WF2 6QR",
    "addr:housenumber":"5",
    "addr:postcode":"wf2 6qr",
    "addr:street":"Chevet Croft;West",
    "iso:country":"GB",
    "sg:address":"5 Chevet Croft, Sandal",
    "sg:city":"Wakefield",
    "sg:classifiers":[
        {
            "category":"Retail",
            "subcategory":"Driving School",
            "type":"Services"
        }
    ],
    "sg:postcode":"WF2 6QR",
    "sg:province":"West Yorkshire",
    "wof:name":"Whiteways Industries Ltd",
    "wof:placetype":"venue"
},
  "geometry": {"coordinates":[-1.483042,53.651855],"type":"Point"}
}