{
  "type": "Feature",
  "properties": {
    "iso:country":"GB",
    "sg:address":"Longage Hill, Lyminge",
    "sg:city":"Folkestone",
    "sg:classifiers":[
        {
            "category":"Arena",
            "subcategory":"Sports Club",
            "type":"Entertainment"
        }
    ],
    "sg:phone":"+44 1303 863251",
    "sg:postcode":"CT18 8HB",
    "sg:province":"Kent",
    "wof:name":"Sibton Park Cricket Club",
    "wof:placetype":"venue"
},
  "geometry": {"coordinates":[1.0902,51.129047],"type":"Point"}
}