{
  "type": "Feature",
  "properties": {
    "addr:full":"Jordan House, 47 Brunswick Place London Greater London N1 6EB",
    "addr:housenumber":"47",
    "addr:postcode":"n1 6eb",
    "addr:street":"Brunswick Place",
    "iso:country":"GB",
    "sg:address":"Jordan House, 47 Brunswick Place",
    "sg:city":"London",
    "sg:classifiers":[
        {
            "category":"Wholesale",
            "subcategory":"Books, Periodicals, & Newspapers",
            "type":"Manufacturing & Wholesale Goods"
        }
    ],
    "sg:phone":"+44 20 7750 5000",
    "sg:postcode":"N1 6EB",
    "sg:province":"Greater London",
    "sg:tags":[
        "publishing"
    ],
    "wof:name":"Hanson Cooke Ltd.",
    "wof:placetype":"venue"
},
  "geometry": {"coordinates":[-0.085536,51.527401],"type":"Point"}
}