{
  "type": "Feature",
  "properties": {
    "iso:country":"GB",
    "sg:address":"Taw Garage, Victoria Road",
    "sg:city":"Barnstaple",
    "sg:classifiers":[
        {
            "category":"Retail",
            "subcategory":"Auto Rental",
            "type":"Services"
        }
    ],
    "sg:phone":"+44 1271 372809",
    "sg:postcode":"EX32 8NP",
    "sg:province":"Devon",
    "sg:tags":[
        "car"
    ],
    "wof:name":"Ford Rent-A-Car",
    "wof:placetype":"venue"
},
  "geometry": {"coordinates":[-4.056222,51.078323],"type":"Point"}
}