{
  "type": "Feature",
  "properties": {
    "addr:full":"54 Crystal Road Blackpool Lancashire FY1 6BS",
    "addr:housenumber":"54",
    "addr:postcode":"fy1 6bs",
    "addr:street":"Crystal Road",
    "iso:country":"GB",
    "sg:address":"54 Crystal Road",
    "sg:city":"Blackpool",
    "sg:classifiers":[
        {
            "category":"Travel",
            "subcategory":"Hotels & Motels",
            "type":"Entertainment"
        }
    ],
    "sg:phone":"+44 1253 346205",
    "sg:postcode":"FY1 6BS",
    "sg:province":"Lancashire",
    "sg:tags":[
        "house",
        "guest"
    ],
    "wof:name":"Lansdowne House Hotel",
    "wof:placetype":"venue"
},
  "geometry": {"coordinates":[-3.051978,53.80246],"type":"Point"}
}