{
  "type": "Feature",
  "properties": {
    "iso:country":"GB",
    "sg:address":"Unit L 207 Strathmartine Road",
    "sg:city":"Dundee",
    "sg:classifiers":[
        {
            "category":"Wholesale",
            "subcategory":"Machinery & Supplies",
            "type":"Manufacturing & Wholesale Goods"
        }
    ],
    "sg:phone":"+44 1634 299100",
    "sg:postcode":"DD3 8PH",
    "sg:province":"Dundee City",
    "sg:tags":[
        "equipment",
        "handling",
        "lifting"
    ],
    "wof:name":"Wam Scotland",
    "wof:placetype":"venue"
},
  "geometry": {"coordinates":[-2.98411,56.478611],"type":"Point"}
}