{
  "type": "Feature",
  "properties": {
    "iso:country":"GB",
    "sg:address":"67 Chingford Mount Road",
    "sg:city":"London",
    "sg:classifiers":[
        {
            "category":"Retail",
            "subcategory":"Laundry & Dry Cleaning",
            "type":"Services"
        }
    ],
    "sg:phone":"+44 20 8527 7201",
    "sg:postcode":"E4 8LU",
    "sg:province":"Greater London",
    "sg:tags":[
        "alteration"
    ],
    "wof:name":"C & A Dry Cleaners",
    "wof:placetype":"venue"
},
  "geometry": {"coordinates":[-0.0182140004,51.6105690002],"type":"Point"}
}