{
  "type": "Feature",
  "properties": {
    "iso:country":"GB",
    "sg:address":"101b Bradwell Road, Bradville",
    "sg:city":"Milton Keynes",
    "sg:classifiers":[
        {
            "category":"Bars & Pubs",
            "type":"Food & Drink"
        }
    ],
    "sg:phone":"+44 1908 312987",
    "sg:postcode":"MK13 7AW",
    "sg:province":"Buckinghamshire",
    "sg:tags":[
        "pubs",
        "inn"
    ],
    "wof:name":"Halleys",
    "wof:placetype":"venue"
},
  "geometry": {"coordinates":[-0.785253,52.059307],"type":"Point"}
}