{
  "type": "Feature",
  "properties": {
    "addr:full":"4 Unity Street Bristol City of Bristol BS1 5HH",
    "addr:housenumber":"4",
    "addr:postcode":"bs1 5hh",
    "addr:street":"Unity Street",
    "iso:country":"GB",
    "sg:address":"4 Unity Street",
    "sg:city":"Bristol",
    "sg:classifiers":[
        {
            "category":"Professional",
            "subcategory":"Employment Agencies",
            "type":"Services"
        }
    ],
    "sg:phone":"+44 117 904 1250",
    "sg:postcode":"BS1 5HH",
    "sg:province":"City of Bristol",
    "sg:tags":[
        "consultant"
    ],
    "wof:name":"Morson All Trades",
    "wof:placetype":"venue"
},
  "geometry": {"coordinates":[-2.600723,51.453438],"type":"Point"}
}