{
  "type": "Feature",
  "properties": {
    "addr:full":"124 Ash Road Aldershot Hampshire GU12 4EY",
    "addr:housenumber":"124",
    "addr:postcode":"gu12 4ey",
    "addr:street":"Ash Road",
    "iso:country":"GB",
    "sg:address":"124 Ash Road",
    "sg:city":"Aldershot",
    "sg:classifiers":[
        {
            "category":"Professional",
            "subcategory":"Computer Services",
            "type":"Services"
        }
    ],
    "sg:postcode":"GU12 4EY",
    "sg:province":"Hampshire",
    "sg:tags":[
        "system",
        "software"
    ],
    "wof:name":"Londiberg Ltd",
    "wof:placetype":"venue"
},
  "geometry": {"coordinates":[-0.7449659705,51.241897583],"type":"Point"}
}