{
  "type": "Feature",
  "properties": {
    "addr:full":"1 Lower Bar Newport Shropshire TF10 7JB",
    "addr:housenumber":"1",
    "addr:postcode":"tf10 7jb",
    "addr:street":"Lower Bar",
    "iso:country":"GB",
    "sg:address":"1 Lower Bar",
    "sg:city":"Newport",
    "sg:classifiers":[
        {
            "category":"Shopping",
            "subcategory":"Thrift Store",
            "type":"Retail Goods"
        }
    ],
    "sg:phone":"+44 1952 814318",
    "sg:postcode":"TF10 7JB",
    "sg:province":"Shropshire",
    "sg:tags":[
        "shop",
        "charity"
    ],
    "wof:name":"Hospice Shop Shropshire & Mid Wales",
    "wof:placetype":"venue"
},
  "geometry": {"coordinates":[-2.380966,52.770287],"type":"Point"}
}