{
  "type": "Feature",
  "properties": {
    "addr:full":"2 Commerce Rd Brentford Greater London TW8 8LR",
    "addr:housenumber":"2",
    "addr:postcode":"tw8 8lr",
    "addr:street":"Commerce Rd",
    "iso:country":"GB",
    "sg:address":"2 Commerce Rd",
    "sg:city":"Brentford",
    "sg:classifiers":[
        {
            "category":"Building & Trades",
            "subcategory":"Electrical",
            "type":"Services"
        }
    ],
    "sg:phone":"+44 20 8560 9652",
    "sg:postcode":"TW8 8LR",
    "sg:province":"Greater London",
    "sg:tags":[
        "consultant",
        "lighting"
    ],
    "wof:name":"T M B Associates Production Supplies & Services",
    "wof:placetype":"venue"
},
  "geometry": {"coordinates":[-0.3146930039,51.4842529297],"type":"Point"}
}