{
  "type": "Feature",
  "properties": {
    "addr:full":"Unit 1, Manse Lane Burntisland Fife KY3 0BJ",
    "addr:housenumber":"unit 1",
    "addr:postcode":"ky3 0bj",
    "addr:street":"Manse Lane",
    "iso:country":"GB",
    "sg:address":"Unit 1, Manse Lane",
    "sg:city":"Burntisland",
    "sg:classifiers":[
        {
            "category":"Manufacturing",
            "subcategory":"Metals",
            "type":"Manufacturing & Wholesale Goods"
        }
    ],
    "sg:phone":"+44 1592 874283",
    "sg:postcode":"KY3 0BJ",
    "sg:province":"Fife",
    "sg:tags":[
        "blacksmith",
        "forgemasters"
    ],
    "wof:name":"D Laing Blacksmiths & Fabricators",
    "wof:placetype":"venue"
},
  "geometry": {"coordinates":[-3.230491,56.061592],"type":"Point"}
}