{
  "type": "Feature",
  "properties": {
    "addr:full":"White Bear Marina, Park Road, Adlington Chorley Lancashire PR7 4HZ",
    "addr:postcode":"pr7 4hz",
    "addr:street":"Park Road",
    "iso:country":"GB",
    "sg:address":"White Bear Marina, Park Road, Adlington",
    "sg:city":"Chorley",
    "sg:classifiers":[
        {
            "category":"Cafe",
            "type":"Food & Drink"
        }
    ],
    "sg:phone":"+44 1257 474454",
    "sg:postcode":"PR7 4HZ",
    "sg:province":"Lancashire",
    "sg:tags":[
        "tea",
        "room"
    ],
    "wof:name":"Mariners Coffee Shop",
    "wof:placetype":"venue"
},
  "geometry": {"coordinates":[-2.6090700626,53.6119194031],"type":"Point"}
}