{
  "type": "Feature",
  "properties": {
    "addr:full":"Shelah Rd Halesowen West Midlands B63 3XL",
    "addr:postcode":"b63 3xl",
    "addr:street":"Shelah Rd",
    "iso:country":"GB",
    "sg:address":"Shelah Rd",
    "sg:city":"Halesowen",
    "sg:classifiers":[
        {
            "category":"Autos & Motor Vehicles",
            "subcategory":"Auto Supplies",
            "type":"Retail Goods"
        }
    ],
    "sg:phone":"+44 121 550 5757",
    "sg:postcode":"B63 3XL",
    "sg:province":"West Midlands",
    "sg:tags":[
        "transmission",
        "equipment",
        "power"
    ],
    "wof:name":"Hayley Transmissions",
    "wof:placetype":"venue"
},
  "geometry": {"coordinates":[-2.0574769974,52.4613342285],"type":"Point"}
}