{
  "type": "Feature",
  "properties": {
    "iso:country":"GB",
    "sg:address":"15 Kings Parade, Ditchling Road",
    "sg:city":"Brighton",
    "sg:classifiers":[
        {
            "category":"Fast Food",
            "type":"Food & Drink"
        }
    ],
    "sg:phone":"+44 1273 559684",
    "sg:postcode":"BN1 6JT",
    "sg:province":"East Sussex",
    "sg:tags":[
        "away",
        "take"
    ],
    "wof:name":"Canton Take-Away",
    "wof:placetype":"venue"
},
  "geometry": {"coordinates":[-0.13514,50.84444],"type":"Point"}
}