{
  "type": "Feature",
  "properties": {
    "iso:country":"GB",
    "sg:address":"220 Great West Road",
    "sg:city":"Hounslow",
    "sg:classifiers":[
        {
            "category":"Real Estate",
            "subcategory":"Real Estate Operator",
            "type":"Services"
        }
    ],
    "sg:phone":"+44 20 8814 2020",
    "sg:postcode":"TW5 9AW",
    "sg:province":"Greater London",
    "sg:tags":[
        "letting",
        "agent"
    ],
    "wof:name":"Network Letting Services",
    "wof:placetype":"venue"
},
  "geometry": {"coordinates":[-0.384805,51.476521],"type":"Point"}
}