{
  "type": "Feature",
  "properties": {
    "addr:full":"2a Gt. Shaw St Preston Lancashire PR1 2HH",
    "addr:housenumber":"2a",
    "addr:postcode":"pr1 2hh",
    "addr:street":"Gt. Shaw St",
    "iso:country":"GB",
    "sg:address":"2a Gt. Shaw St",
    "sg:city":"Preston",
    "sg:classifiers":[
        {
            "category":"Retail",
            "subcategory":"Auto Repair",
            "type":"Services"
        }
    ],
    "sg:postcode":"PR1 2HH",
    "sg:province":"Lancashire",
    "sg:tags":[
        "electrician"
    ],
    "wof:name":"Burns,Alan,",
    "wof:placetype":"venue"
},
  "geometry": {"coordinates":[-2.704068,53.761871],"type":"Point"}
}