{
  "type": "Feature",
  "properties": {
    "iso:country":"GB",
    "sg:address":"School Road, Kenfig Hill",
    "sg:city":"Bridgend",
    "sg:classifiers":[
        {
            "category":"Social Services",
            "subcategory":"Retirement Home",
            "type":"Services"
        }
    ],
    "sg:phone":"+44 1656 742790",
    "sg:postcode":"CF33 6DT",
    "sg:province":"Bridgend",
    "sg:tags":[
        "residential",
        "care"
    ],
    "wof:name":"Glyn Cynffig",
    "wof:placetype":"venue"
},
  "geometry": {"coordinates":[-3.673969,51.53421],"type":"Point"}
}