{
  "type": "Feature",
  "properties": {
    "iso:country":"GB",
    "sg:address":"12 Harberton Close",
    "sg:city":"Paignton",
    "sg:classifiers":[
        {
            "category":"Professional",
            "subcategory":"Management & Consulting",
            "type":"Services"
        }
    ],
    "sg:postcode":"TQ4 7EA",
    "sg:province":"Devon",
    "sg:tags":[
        "fire",
        "consultant",
        "protection"
    ],
    "wof:name":"Head-on Fire & Safety",
    "wof:placetype":"venue"
},
  "geometry": {"coordinates":[-3.586962,50.421692],"type":"Point"}
}