{
  "type": "Feature",
  "properties": {
    "addr:full":"21 Wellington Street, Greenbank Plymouth Devon PL4 8NB",
    "addr:housenumber":"21",
    "addr:postcode":"pl4 8nb",
    "addr:street":"Wellington Street",
    "iso:country":"GB",
    "sg:address":"21 Wellington Street, Greenbank",
    "sg:city":"Plymouth",
    "sg:classifiers":[
        {
            "category":"Bars & Pubs",
            "type":"Food & Drink"
        }
    ],
    "sg:postcode":"PL4 8NB",
    "sg:province":"Devon",
    "sg:tags":[
        "pubs",
        "inn"
    ],
    "wof:name":"D Oakman",
    "wof:placetype":"venue"
},
  "geometry": {"coordinates":[-4.1336970329,50.3766021729],"type":"Point"}
}