{
  "type": "Feature",
  "properties": {
    "iso:country":"GB",
    "sg:address":"Garreg Farm, Fachallt Road, Whitford",
    "sg:city":"Holywell",
    "sg:classifiers":[
        {
            "category":"Farming",
            "subcategory":"Livestock Farm",
            "type":"Manufacturing & Wholesale Goods"
        }
    ],
    "sg:phone":"+44 1745 560305",
    "sg:postcode":"CH8 9AL",
    "sg:province":"Denbighshire",
    "sg:tags":[
        "others"
    ],
    "wof:name":"W J Davies & Co.",
    "wof:placetype":"venue"
},
  "geometry": {"coordinates":[-3.225195,53.274548],"type":"Point"}
}