{
  "type": "Feature",
  "properties": {
    "iso:country":"GB",
    "sg:address":"19d Hunters Rd, Weldon North Ind Est",
    "sg:city":"Corby",
    "sg:classifiers":[
        {
            "category":"Train Station",
            "subcategory":"Rail",
            "type":"Transportation"
        }
    ],
    "sg:phone":"+44 1536 204233",
    "sg:postcode":"NN17 5JE",
    "sg:province":"Northamptonshire",
    "sg:tags":[
        "caravan"
    ],
    "wof:name":"Nooteboom Trailers G.B",
    "wof:placetype":"venue"
},
  "geometry": {"coordinates":[-0.6551039815,52.5028152466],"type":"Point"}
}