{
  "type": "Feature",
  "properties": {
    "iso:country":"GB",
    "sg:address":"57 Acacia Road",
    "sg:city":"Hampton",
    "sg:classifiers":[
        {
            "category":"Shopping",
            "subcategory":"Stationery & Office Supplies",
            "type":"Retail Goods"
        }
    ],
    "sg:phone":"+44 20 8979 6965",
    "sg:postcode":"TW12 3DP",
    "sg:province":"Greater London",
    "sg:tags":[
        "equipment",
        "printing",
        "mech"
    ],
    "wof:name":"Graphic Enterprises",
    "wof:placetype":"venue"
},
  "geometry": {"coordinates":[-0.3708640039,51.4256706238],"type":"Point"}
}