{
  "type": "Feature",
  "properties": {
    "iso:country":"GB",
    "sg:address":"26 Lower Teddington Road, Hampton Wick",
    "sg:city":"Kingston-upon-thames",
    "sg:classifiers":[
        {
            "category":"Social Services",
            "subcategory":"Retirement Home",
            "type":"Services"
        }
    ],
    "sg:phone":"+44 20 8977 4137",
    "sg:postcode":"KT1 4HJ",
    "sg:province":"Greater London",
    "sg:tags":[
        "residential",
        "care"
    ],
    "wof:name":"Moiravale",
    "wof:placetype":"venue"
},
  "geometry": {"coordinates":[-0.3095650077,51.4161109924],"type":"Point"}
}