{
  "type": "Feature",
  "properties": {
    "iso:country":"GB",
    "sg:address":"39 Melbourne St",
    "sg:city":"Stalybridge",
    "sg:classifiers":[
        {
            "category":"Shopping",
            "subcategory":"Shoes",
            "type":"Retail Goods"
        }
    ],
    "sg:postcode":"SK15 2JJ",
    "sg:province":"Greater Manchester",
    "sg:tags":[
        "shop"
    ],
    "wof:name":"Nixon,A,",
    "wof:placetype":"venue"
},
  "geometry": {"coordinates":[-2.057524,53.482834],"type":"Point"}
}