{
  "type": "Feature",
  "properties": {
    "iso:country":"GB",
    "sg:address":"Levolux House, 24 Eastville Close, Eastern Avenue",
    "sg:city":"Gloucester",
    "sg:classifiers":[
        {
            "category":"Home & Garden",
            "subcategory":"Home Furnishings",
            "type":"Retail Goods"
        },
        {
            "category":"Building & Trades",
            "subcategory":"Landfill",
            "type":"Services"
        }
    ],
    "sg:phone":"+44 1452 500007",
    "sg:postcode":"GL4 3SJ",
    "sg:province":"Gloucestershire",
    "sg:tags":[
        "blind",
        "awning",
        "canopy",
        "blinds"
    ],
    "sg:website":"http://www.levolux.co.uk",
    "wof:name":"Levolux A T Ltd",
    "wof:placetype":"venue"
},
  "geometry": {"coordinates":[-2.2235279083,51.8581123352],"type":"Point"}
}