{
  "type": "Feature",
  "properties": {
    "addr:full":"St. Andrews Rd Northampton Northamptonshire NN1 2SD",
    "addr:postcode":"nn1 2sd",
    "addr:street":"St. Andrews Rd",
    "iso:country":"GB",
    "sg:address":"St. Andrews Rd",
    "sg:city":"Northampton",
    "sg:classifiers":[
        {
            "category":"Cafe",
            "type":"Food & Drink"
        }
    ],
    "sg:phone":"+44 1604 636099",
    "sg:postcode":"NN1 2SD",
    "sg:province":"Northamptonshire",
    "sg:tags":[
        "tea",
        "room"
    ],
    "wof:name":"Super Sausage Cafeteria & Motel",
    "wof:placetype":"venue"
},
  "geometry": {"coordinates":[-0.9039430022,52.2455177307],"type":"Point"}
}