{
  "type": "Feature",
  "properties": {
    "iso:country":"GB",
    "sg:address":"Ackergill Street",
    "sg:city":"Wick",
    "sg:classifiers":[
        {
            "category":"Education",
            "subcategory":"School",
            "type":"Public Place"
        },
        {
            "category":"Government",
            "subcategory":"Office",
            "type":"Public Place"
        }
    ],
    "sg:phone":"+44 1955 602873",
    "sg:postcode":"KW1 4DT",
    "sg:province":"Highland",
    "sg:tags":[
        "local",
        "authority"
    ],
    "wof:name":"North Primary School",
    "wof:placetype":"venue"
},
  "geometry": {"coordinates":[-3.089499,58.448124],"type":"Point"}
}