{
  "type": "Feature",
  "properties": {
    "addr:full":"New Farm Office, Elms Farm, Grove Road Wantage Berkshire OX12 7PD",
    "addr:postcode":"ox12 7pd",
    "addr:street":"Elms Farm Grove Road",
    "iso:country":"GB",
    "sg:address":"New Farm Office, Elms Farm, Grove Road",
    "sg:city":"Wantage",
    "sg:classifiers":[
        {
            "category":"Farming",
            "subcategory":"Dairy Farm",
            "type":"Manufacturing & Wholesale Goods"
        }
    ],
    "sg:postcode":"OX12 7PD",
    "sg:province":"Berkshire",
    "wof:name":"Kingsgrove Farms",
    "wof:placetype":"venue"
},
  "geometry": {"coordinates":[-1.423639,51.591747],"type":"Point"}
}