{
  "type": "Feature",
  "properties": {
    "addr:full":"23 Water Street Edinburgh City of Edinburgh EH6 6SU",
    "addr:housenumber":"23",
    "addr:postcode":"eh6 6su",
    "addr:street":"Water Street",
    "iso:country":"GB",
    "sg:address":"23 Water Street",
    "sg:city":"Edinburgh",
    "sg:classifiers":[
        {
            "category":"Shopping",
            "subcategory":"Stationery & Office Supplies",
            "type":"Retail Goods"
        },
        {
            "category":"Community Center",
            "subcategory":"Social",
            "type":"Public Place"
        },
        {
            "category":"Military Area",
            "subcategory":"Air Force Base",
            "type":"Public Place"
        }
    ],
    "sg:phone":"+44 131 555 4466",
    "sg:postcode":"EH6 6SU",
    "sg:province":"City of Edinburgh",
    "sg:tags":[
        "case",
        "item",
        "manufacturer",
        "promotional"
    ],
    "wof:name":"Justin Case Co",
    "wof:placetype":"venue"
},
  "geometry": {"coordinates":[-3.1694231033,55.9754257202],"type":"Point"}
}