{
  "type": "Feature",
  "properties": {
    "addr:full":"44 Terrace Road Walton-on-thames Surrey KT12 2SD",
    "addr:housenumber":"44",
    "addr:postcode":"kt12 2sd",
    "addr:street":"Terrace Road",
    "iso:country":"GB",
    "sg:address":"44 Terrace Road",
    "sg:city":"Walton-on-thames",
    "sg:classifiers":[
        {
            "category":"Professional",
            "subcategory":"Computer Services",
            "type":"Services"
        }
    ],
    "sg:postcode":"KT12 2SD",
    "sg:province":"Surrey",
    "sg:tags":[
        "consultant"
    ],
    "wof:name":"Rennison Commercial",
    "wof:placetype":"venue"
},
  "geometry": {"coordinates":[-0.4123870134,51.3911895752],"type":"Point"}
}