{
  "type": "Feature",
  "properties": {
    "addr:full":"32 Reybridge, Lacock Chippenham Wiltshire SN15 2PF",
    "addr:housenumber":"32",
    "addr:postcode":"sn15 2pf",
    "addr:street":"Reybridge Lacock",
    "iso:country":"GB",
    "sg:address":"32 Reybridge, Lacock",
    "sg:city":"Chippenham",
    "sg:classifiers":[
        {
            "category":"Farming",
            "subcategory":"Livestock Farm",
            "type":"Manufacturing & Wholesale Goods"
        }
    ],
    "sg:phone":"+44 1249 730517",
    "sg:postcode":"SN15 2PF",
    "sg:province":"Wiltshire",
    "sg:tags":[
        "others"
    ],
    "wof:name":"A W Doel & Sons Ltd.",
    "wof:placetype":"venue"
},
  "geometry": {"coordinates":[-2.1194300652,51.4604415894],"type":"Point"}
}