{
  "type": "Feature",
  "properties": {
    "iso:country":"GB",
    "sg:address":"Wishing Well House, 5a Snowdon Drive",
    "sg:city":"Wrexham",
    "sg:classifiers":[
        {
            "category":"Professional",
            "subcategory":"Computer Services",
            "type":"Services"
        }
    ],
    "sg:phone":"+44 1978 846563",
    "sg:postcode":"LL14 2TF",
    "sg:province":"Wrexham",
    "sg:tags":[
        "consultant"
    ],
    "wof:name":"Spider Rider Web Page Design",
    "wof:placetype":"venue"
},
  "geometry": {"coordinates":[-3.03708601,53.0076942444],"type":"Point"}
}