{
  "type": "Feature",
  "properties": {
    "addr:full":"Church Rd, Thornton In Craven Skipton Lancashire BD23 3TN",
    "addr:postcode":"bd23 3tn",
    "addr:street":"Church Rd",
    "iso:country":"GB",
    "sg:address":"Church Rd, Thornton In Craven",
    "sg:city":"Skipton",
    "sg:classifiers":[
        {
            "category":"Organizations",
            "subcategory":"Non-profit Organization",
            "type":"Services"
        }
    ],
    "sg:phone":"+44 1282 844699",
    "sg:postcode":"BD23 3TN",
    "sg:province":"Lancashire",
    "sg:tags":[
        "organisation",
        "voluntary",
        "charity"
    ],
    "wof:name":"Cromwells Homecare",
    "wof:placetype":"venue"
},
  "geometry": {"coordinates":[-2.150309,53.931133],"type":"Point"}
}