{
  "type": "Feature",
  "properties": {
    "iso:country":"GB",
    "sg:address":"Acacia Road",
    "sg:city":"Oldham",
    "sg:classifiers":[
        {
            "category":"Bars & Pubs",
            "type":"Food & Drink"
        }
    ],
    "sg:phone":"+44 161 652 8497",
    "sg:postcode":"OL8 3NN",
    "sg:province":"Lancashire",
    "sg:tags":[
        "pubs",
        "inn"
    ],
    "wof:name":"The Greengate Inn",
    "wof:placetype":"venue"
},
  "geometry": {"coordinates":[-2.125872,53.516685],"type":"Point"}
}