{
  "type": "Feature",
  "properties": {
    "addr:full":"132 Wickham Rd Croydon Surrey CR0 8BE",
    "addr:housenumber":"132",
    "addr:postcode":"cr0 8be",
    "addr:street":"Wickham Rd",
    "iso:country":"GB",
    "sg:address":"132 Wickham Rd",
    "sg:city":"Croydon",
    "sg:classifiers":[
        {
            "category":"Health Services",
            "subcategory":"Dentist",
            "type":"Services"
        }
    ],
    "sg:phone":"+44 20 8655 1118",
    "sg:postcode":"CR0 8BE",
    "sg:province":"Surrey",
    "wof:name":"M A Jamil",
    "wof:placetype":"venue"
},
  "geometry": {"coordinates":[-0.051396,51.374161],"type":"Point"}
}