{
  "type": "Feature",
  "properties": {
    "iso:country":"GB",
    "sg:address":"132 Wickham Rd",
    "sg:city":"Croydon",
    "sg:classifiers":[
        {
            "category":"Health Services",
            "subcategory":"Dentist",
            "type":"Services"
        }
    ],
    "sg:phone":"+44 20 8655 1118",
    "sg:postcode":"CR0 8BE",
    "sg:province":"Surrey",
    "wof:name":"M A Jamil",
    "wof:placetype":"venue"
},
  "geometry": {"coordinates":[-0.051396,51.374161],"type":"Point"}
}