{
  "type": "Feature",
  "properties": {
    "addr:full":"31 Broadfield Gardens Worcester Worcestershire WR4 0DP",
    "addr:housenumber":"31",
    "addr:postcode":"wr4 0dp",
    "addr:street":"Broadfield Gardens",
    "iso:country":"GB",
    "sg:address":"31 Broadfield Gardens",
    "sg:city":"Worcester",
    "sg:classifiers":[
        {
            "category":"Building & Trades",
            "subcategory":"Plumbing",
            "type":"Services"
        }
    ],
    "sg:postcode":"WR4 0DP",
    "sg:province":"Worcestershire",
    "sg:tags":[
        "heating"
    ],
    "wof:name":"John Evans",
    "wof:placetype":"venue"
},
  "geometry": {"coordinates":[-2.178879,52.207554],"type":"Point"}
}