{
  "type": "Feature",
  "properties": {
    "iso:country":"GB",
    "sg:address":"Brimar Buildings, Hele Business Park",
    "sg:city":"Ilfracombe",
    "sg:classifiers":[
        {
            "category":"Professional",
            "subcategory":"Engineering",
            "type":"Services"
        }
    ],
    "sg:phone":"+44 1271 867447",
    "sg:postcode":"EX34 9RA",
    "sg:province":"Devon",
    "sg:tags":[
        "precision",
        "engineer"
    ],
    "wof:name":"Brimar Technique",
    "wof:placetype":"venue"
},
  "geometry": {"coordinates":[-4.1235542297,51.2081604004],"type":"Point"}
}