{
  "type": "Feature",
  "properties": {
    "addr:full":"2nd Floor, Boston House Richmond Greater London TW9 1QE",
    "addr:housenumber":"2nd floor boston house",
    "addr:postcode":"tw9 1qe",
    "iso:country":"GB",
    "sg:address":"2nd Floor, Boston House",
    "sg:city":"Richmond",
    "sg:classifiers":[
        {
            "category":"Banks & Credit Unions",
            "subcategory":"Financial Services",
            "type":"Services"
        }
    ],
    "sg:phone":"+44 20 8332 9955",
    "sg:postcode":"TW9 1QE",
    "sg:province":"Greater London",
    "sg:tags":[
        "consultant"
    ],
    "wof:name":"Factors & Discounters Association Ltd.",
    "wof:placetype":"venue"
},
  "geometry": {"coordinates":[-0.300726,51.461319],"type":"Point"}
}