{
  "type": "Feature",
  "properties": {
    "addr:full":"Po Box 446 Aylesbury Buckinghamshire HP21 7AJ",
    "addr:housenumber":"po",
    "addr:postcode":"hp21 7aj",
    "addr:street":"Box 446",
    "iso:country":"GB",
    "sg:address":"Po Box 446",
    "sg:city":"Aylesbury",
    "sg:classifiers":[
        {
            "category":"Shopping",
            "subcategory":"Computers & Home Electronics",
            "type":"Retail Goods"
        }
    ],
    "sg:phone":"+44 1296 338747",
    "sg:postcode":"HP21 7AJ",
    "sg:province":"Buckinghamshire",
    "sg:tags":[
        "equipment",
        "radio"
    ],
    "wof:name":"Tardis Communication Systems Ltd.",
    "wof:placetype":"venue"
},
  "geometry": {"coordinates":[-0.7783100009,51.8100013733],"type":"Point"}
}