{
  "type": "Feature",
  "properties": {
    "addr:full":"33 Rowan Road London Greater London SW16 5JF",
    "addr:housenumber":"33",
    "addr:postcode":"sw16 5jf",
    "addr:street":"Rowan Road",
    "iso:country":"GB",
    "sg:address":"33 Rowan Road",
    "sg:city":"London",
    "sg:classifiers":[
        {
            "category":"Professional",
            "type":"Services"
        }
    ],
    "sg:postcode":"SW16 5JF",
    "sg:province":"Greater London",
    "sg:tags":[
        "interior",
        "furnishers",
        "designer"
    ],
    "wof:name":"Adrian Hewitt",
    "wof:placetype":"venue"
},
  "geometry": {"coordinates":[-0.1420029998,51.4090042114],"type":"Point"}
}