{
  "type": "Feature",
  "properties": {
    "addr:full":"65 Hammonds Ridge Burgess Hill East Sussex RH15 9QW",
    "addr:housenumber":"65",
    "addr:postcode":"rh15 9qw",
    "addr:street":"Hammonds Ridge",
    "iso:country":"GB",
    "sg:address":"65 Hammonds Ridge",
    "sg:city":"Burgess Hill",
    "sg:classifiers":[
        {
            "category":"Wholesale",
            "subcategory":"Vending Machines",
            "type":"Manufacturing & Wholesale Goods"
        }
    ],
    "sg:phone":"+44 1444 246029",
    "sg:postcode":"RH15 9QW",
    "sg:province":"East Sussex",
    "sg:tags":[
        "sale"
    ],
    "wof:name":"Hoiles Enterprises Ltd.",
    "wof:placetype":"venue"
},
  "geometry": {"coordinates":[-0.1475739926,50.9491462708],"type":"Point"}
}