{
  "type": "Feature",
  "properties": {
    "addr:full":"Marine Terrace Margate Kent CT9 1XJ",
    "addr:postcode":"ct9 1xj",
    "addr:street":"Marine Terrace Margate",
    "iso:country":"GB",
    "sg:address":"Marine Terrace",
    "sg:city":"Margate",
    "sg:classifiers":[
        {
            "category":"Recreation",
            "subcategory":"Amusement Park",
            "type":"Entertainment"
        }
    ],
    "sg:phone":"+44 1843 296160",
    "sg:postcode":"CT9 1XJ",
    "sg:province":"Kent",
    "sg:tags":[
        "arcade"
    ],
    "wof:name":"Flamingo Amusement Arcade",
    "wof:placetype":"venue"
},
  "geometry": {"coordinates":[1.37558496,51.3867301941],"type":"Point"}
}