{
  "type": "Feature",
  "properties": {
    "addr:full":"Unit 16 Maun Valley Industrial Estate Sutton-in-ashfield Nottinghamshire NG17 2JD",
    "addr:housenumber":"unit 16",
    "addr:postcode":"ng17 2jd",
    "addr:street":"Maun Valley Industrial Estate",
    "iso:country":"GB",
    "sg:address":"Unit 16 Maun Valley Industrial Estate",
    "sg:city":"Sutton-in-ashfield",
    "sg:classifiers":[
        {
            "category":"Home & Garden",
            "subcategory":"Kitchen Supply",
            "type":"Retail Goods"
        }
    ],
    "sg:postcode":"NG17 2JD",
    "sg:province":"Nottinghamshire",
    "sg:tags":[
        "equipment",
        "brewer"
    ],
    "wof:name":"Midlands Dispense",
    "wof:placetype":"venue"
},
  "geometry": {"coordinates":[-1.2388809919,53.1219139099],"type":"Point"}
}