{
  "type": "Feature",
  "properties": {
    "iso:country":"GB",
    "sg:address":"Croston Ash, Green Lane, Ockham",
    "sg:city":"Woking",
    "sg:classifiers":[
        {
            "category":"Building & Trades",
            "subcategory":"Construction",
            "type":"Services"
        }
    ],
    "sg:phone":"+44 1483 282823",
    "sg:postcode":"GU23 6PQ",
    "sg:province":"Surrey",
    "sg:tags":[
        "builder"
    ],
    "wof:name":"Goodmacs",
    "wof:placetype":"venue"
},
  "geometry": {"coordinates":[-0.462024,51.298393],"type":"Point"}
}