{
  "type": "Feature",
  "properties": {
    "iso:country":"GB",
    "sg:address":"The Gables, High Rd, Fobbing",
    "sg:city":"Stanford Le Hope",
    "sg:classifiers":[
        {
            "category":"Sports & Exercise",
            "subcategory":"Swimming Pool",
            "type":"Entertainment"
        }
    ],
    "sg:phone":"+44 1375 671843",
    "sg:postcode":"SS17 9HT",
    "sg:province":"Essex",
    "sg:tags":[
        "diver"
    ],
    "wof:name":"Adventures in Scuba",
    "wof:placetype":"venue"
},
  "geometry": {"coordinates":[0.4736959934,51.5288276672],"type":"Point"}
}