{
  "type": "Feature",
  "properties": {
    "iso:country":"GB",
    "sg:address":"Manor Road",
    "sg:city":"Hayling Island",
    "sg:classifiers":[
        {
            "category":"Travel",
            "subcategory":"Hotels & Motels",
            "type":"Entertainment"
        },
        {
            "category":"Community Center",
            "type":"Public Place"
        }
    ],
    "sg:phone":"+44 23 9246 6131",
    "sg:postcode":"PO11 0QR",
    "sg:province":"Hampshire",
    "sg:tags":[
        "recreation",
        "leisure",
        "centre"
    ],
    "sg:website":"http://www.newtownhouse.co.uk",
    "wof:name":"Newtown House Hotel",
    "wof:placetype":"venue"
},
  "geometry": {"coordinates":[-0.985454,50.796612],"type":"Point"}
}