{
  "type": "Feature",
  "properties": {
    "addr:full":"Unit 8 Onslow Clo Basingstoke Hampshire RG24 8PL",
    "addr:housenumber":"unit 8",
    "addr:postcode":"rg24 8pl",
    "addr:street":"Onslow Clo",
    "iso:country":"GB",
    "sg:address":"Unit 8 Onslow Clo",
    "sg:city":"Basingstoke",
    "sg:classifiers":[
        {
            "category":"Retail",
            "subcategory":"Auto Rental",
            "type":"Services"
        }
    ],
    "sg:phone":"+44 1256 352111",
    "sg:postcode":"RG24 8PL",
    "sg:province":"Hampshire",
    "sg:tags":[
        "car"
    ],
    "wof:name":"Europcar",
    "wof:placetype":"venue"
},
  "geometry": {"coordinates":[-1.063814044,51.2839126587],"type":"Point"}
}