{
  "type": "Feature",
  "properties": {
    "addr:full":"79 Rooley Heights Sowerby Bridge West Yorkshire HX6 1HR",
    "addr:housenumber":"79",
    "addr:postcode":"hx6 1hr",
    "addr:street":"Rooley Heights;West",
    "iso:country":"GB",
    "sg:address":"79 Rooley Heights",
    "sg:city":"Sowerby Bridge",
    "sg:classifiers":[
        {
            "category":"Building & Trades",
            "subcategory":"Construction",
            "type":"Services"
        }
    ],
    "sg:postcode":"HX6 1HR",
    "sg:province":"West Yorkshire",
    "sg:tags":[
        "roofing",
        "monumental",
        "mason"
    ],
    "wof:name":"C Brealey & J Fawcett Monumental Masons",
    "wof:placetype":"venue"
},
  "geometry": {"coordinates":[-1.9416099787,53.7050323486],"type":"Point"}
}