{
  "type": "Feature",
  "properties": {
    "iso:country":"GB",
    "sg:address":"92 Queen Street",
    "sg:city":"Cardiff",
    "sg:classifiers":[
        {
            "category":"Travel",
            "subcategory":"Travel Agent",
            "type":"Entertainment"
        }
    ],
    "sg:phone":"+44 29 2034 7450",
    "sg:postcode":"CF10 2XN",
    "sg:province":"Cardiff",
    "wof:name":"Going Places",
    "wof:placetype":"venue"
},
  "geometry": {"coordinates":[-3.1781740189,51.4816932678],"type":"Point"}
}