{
  "type": "Feature",
  "properties": {
    "addr:full":"87 Carpenters Lane, Hadlow Tonbridge Kent TN11 0ER",
    "addr:housenumber":"87",
    "addr:postcode":"tn11 0er",
    "addr:street":"Carpenters Lane",
    "iso:country":"GB",
    "sg:address":"87 Carpenters Lane, Hadlow",
    "sg:city":"Tonbridge",
    "sg:classifiers":[
        {
            "category":"Bars & Pubs",
            "type":"Food & Drink"
        }
    ],
    "sg:phone":"+44 1732 850242",
    "sg:postcode":"TN11 0ER",
    "sg:province":"Kent",
    "sg:tags":[
        "pubs",
        "inn"
    ],
    "wof:name":"The Rose & Crown",
    "wof:placetype":"venue"
},
  "geometry": {"coordinates":[0.332628,51.230957],"type":"Point"}
}