{
  "type": "Feature",
  "properties": {
    "iso:country":"GB",
    "sg:address":"63 Commercial Rd, Parkstone",
    "sg:city":"Poole",
    "sg:classifiers":[
        {
            "category":"Government",
            "subcategory":"Police Station",
            "type":"Public Place"
        },
        {
            "category":"Government",
            "subcategory":"Office",
            "type":"Public Place"
        }
    ],
    "sg:phone":"+44 1202 724000",
    "sg:postcode":"BH14 0JB",
    "sg:province":"Dorset",
    "sg:tags":[
        "support",
        "local"
    ],
    "wof:name":"The Probation Service",
    "wof:placetype":"venue"
},
  "geometry": {"coordinates":[-1.955019,50.7234],"type":"Point"}
}