{
  "type": "Feature",
  "properties": {
    "addr:full":"7a Ilsham Road, Wellswood Torquay Devon TQ1 2JG",
    "addr:housenumber":"7a",
    "addr:postcode":"tq1 2jg",
    "addr:street":"Ilsham Road",
    "iso:country":"GB",
    "sg:address":"7a Ilsham Road, Wellswood",
    "sg:city":"Torquay",
    "sg:classifiers":[
        {
            "category":"Taxi",
            "type":"Transportation"
        },
        {
            "category":"Military Area",
            "subcategory":"Air Force Base",
            "type":"Public Place"
        }
    ],
    "sg:postcode":"TQ1 2JG",
    "sg:province":"Devon",
    "sg:tags":[
        "mini",
        "hire",
        "private",
        "cab"
    ],
    "wof:name":"Central Taxis Ltd",
    "wof:placetype":"venue"
},
  "geometry": {"coordinates":[-3.5070109367,50.4666900635],"type":"Point"}
}