{
  "type": "Feature",
  "properties": {
    "addr:full":"Four Shells, Queen Katherine Road Lymington Hampshire SO41 3RY",
    "addr:postcode":"so41 3ry",
    "addr:street":"Queen Katherine Road",
    "iso:country":"GB",
    "sg:address":"Four Shells, Queen Katherine Road",
    "sg:city":"Lymington",
    "sg:classifiers":[
        {
            "category":"Building & Trades",
            "subcategory":"Equipment Rental",
            "type":"Services"
        }
    ],
    "sg:phone":"+44 1590 676710",
    "sg:postcode":"SO41 3RY",
    "sg:province":"Hampshire",
    "sg:tags":[
        "plant",
        "machinery"
    ],
    "wof:name":"Dunford Construction Ltd.",
    "wof:placetype":"venue"
},
  "geometry": {"coordinates":[-1.538911,50.758938],"type":"Point"}
}