{
  "type": "Feature",
  "properties": {
    "iso:country":"GB",
    "sg:address":"120 High Street, Yatton",
    "sg:city":"Bristol",
    "sg:classifiers":[
        {
            "category":"Shopping",
            "subcategory":"Antiques",
            "type":"Retail Goods"
        }
    ],
    "sg:postcode":"BS49 4DH",
    "sg:province":"Somerset",
    "wof:name":"Glenville Antiques",
    "wof:placetype":"venue"
},
  "geometry": {"coordinates":[-2.8241939545,51.3888282776],"type":"Point"}
}