{
  "type": "Feature",
  "properties": {
    "addr:full":"4a Station Square, Flitwick Bedford Bedfordshire MK45 1DP",
    "addr:housenumber":"4a",
    "addr:postcode":"mk45 1dp",
    "addr:street":"Station Square",
    "iso:country":"GB",
    "sg:address":"4a Station Square, Flitwick",
    "sg:city":"Bedford",
    "sg:classifiers":[
        {
            "category":"Utilities",
            "type":"Services"
        }
    ],
    "sg:postcode":"MK45 1DP",
    "sg:province":"Bedfordshire",
    "sg:tags":[
        "internet"
    ],
    "wof:name":"Properties Direct Ltd",
    "wof:placetype":"venue"
},
  "geometry": {"coordinates":[-0.494118005,52.0034790039],"type":"Point"}
}