{
  "type": "Feature",
  "properties": {
    "iso:country":"GB",
    "sg:address":"49 Moorgate",
    "sg:city":"Retford",
    "sg:classifiers":[
        {
            "category":"Shopping",
            "subcategory":"Computers & Home Electronics",
            "type":"Retail Goods"
        }
    ],
    "sg:phone":"+44 1777 711112",
    "sg:postcode":"DN22 6RN",
    "sg:province":"Nottinghamshire",
    "wof:name":"Oak Computer Services",
    "wof:placetype":"venue"
},
  "geometry": {"coordinates":[-0.9393619895,53.3263092041],"type":"Point"}
}