{
  "type": "Feature",
  "properties": {
    "addr:full":"17 Bank Street Kirriemuir Angus DD8 4BE",
    "addr:housenumber":"17",
    "addr:postcode":"dd8 4be",
    "addr:street":"Bank Street",
    "iso:country":"GB",
    "sg:address":"17 Bank Street",
    "sg:city":"Kirriemuir",
    "sg:classifiers":[
        {
            "category":"Organizations",
            "subcategory":"Religious Organization",
            "type":"Services"
        }
    ],
    "sg:phone":"+44 1575 574040",
    "sg:postcode":"DD8 4BE",
    "sg:province":"Angus",
    "sg:tags":[
        "organisation",
        "place",
        "worship"
    ],
    "wof:name":"Crucible Christian Centre",
    "wof:placetype":"venue"
},
  "geometry": {"coordinates":[-3.002892971,56.673538208],"type":"Point"}
}