{
  "type": "Feature",
  "properties": {
    "addr:full":"793 Harrow Road Wembley Greater London HA0 2LP",
    "addr:housenumber":"793",
    "addr:postcode":"ha0 2lp",
    "addr:street":"Harrow Road",
    "iso:country":"GB",
    "sg:address":"793 Harrow Road",
    "sg:city":"Wembley",
    "sg:classifiers":[
        {
            "category":"Real Estate",
            "subcategory":"Real Estate Agent",
            "type":"Services"
        }
    ],
    "sg:phone":"+44 20 8904 4400",
    "sg:postcode":"HA0 2LP",
    "sg:province":"Greater London",
    "wof:name":"Robert Berry & Co. Ltd.",
    "wof:placetype":"venue"
},
  "geometry": {"coordinates":[-0.3173789978,51.5559158325],"type":"Point"}
}