{
  "type": "Feature",
  "properties": {
    "iso:country":"GB",
    "sg:address":"250 Earlsdon Avenue North",
    "sg:city":"Coventry",
    "sg:classifiers":[
        {
            "category":"Building & Trades",
            "subcategory":"Cleaning & Sanitation",
            "type":"Services"
        },
        {
            "category":"Retail",
            "subcategory":"Event Space",
            "type":"Services"
        }
    ],
    "sg:phone":"+44 24 7671 1616",
    "sg:postcode":"CV5 6GX",
    "sg:province":"West Midlands",
    "sg:tags":[
        "exhibition",
        "fair",
        "organiser"
    ],
    "wof:name":"All-Sorted Event Management",
    "wof:placetype":"venue"
},
  "geometry": {"coordinates":[-1.5342680216,52.4036216736],"type":"Point"}
}