{
  "type": "Feature",
  "properties": {
    "addr:full":"71 Brighton Road Surbiton Surrey KT6 5NF",
    "addr:housenumber":"71",
    "addr:postcode":"kt6 5nf",
    "addr:street":"Brighton Road",
    "iso:country":"GB",
    "sg:address":"71 Brighton Road",
    "sg:city":"Surbiton",
    "sg:classifiers":[
        {
            "category":"Fast Food",
            "type":"Food & Drink"
        }
    ],
    "sg:phone":"+44 20 8390 1700",
    "sg:postcode":"KT6 5NF",
    "sg:province":"Surrey",
    "sg:tags":[
        "away",
        "take"
    ],
    "wof:name":"K Wong",
    "wof:placetype":"venue"
},
  "geometry": {"coordinates":[-0.3115009964,51.3920707703],"type":"Point"}
}