{
  "type": "Feature",
  "properties": {
    "addr:full":"8 French Gardens, Blackwater Camberley Hampshire GU17 9DP",
    "addr:housenumber":"8",
    "addr:postcode":"gu17 9dp",
    "addr:street":"French Gardens Blackwater",
    "iso:country":"GB",
    "sg:address":"8 French Gardens, Blackwater",
    "sg:city":"Camberley",
    "sg:classifiers":[
        {
            "category":"Utilities",
            "subcategory":"Telephone",
            "type":"Services"
        }
    ],
    "sg:phone":"+44 1276 31458",
    "sg:postcode":"GU17 9DP",
    "sg:province":"Hampshire",
    "sg:tags":[
        "telecommunication"
    ],
    "wof:name":"Ian Blackford Telecommunications",
    "wof:placetype":"venue"
},
  "geometry": {"coordinates":[-0.7819870114,51.3288803101],"type":"Point"}
}