{
  "type": "Feature",
  "properties": {
    "iso:country":"GB",
    "sg:address":"Warwick House, St James Road",
    "sg:city":"Brackley",
    "sg:classifiers":[
        {
            "category":"Manufacturing",
            "subcategory":"Tools & Machinery",
            "type":"Manufacturing & Wholesale Goods"
        }
    ],
    "sg:phone":"+44 1280 705482",
    "sg:postcode":"NN13 7XY",
    "sg:province":"Buckinghamshire",
    "wof:name":"Starragheckert Uk Ltd.",
    "wof:placetype":"venue"
},
  "geometry": {"coordinates":[-1.1482260227,52.0235710144],"type":"Point"}
}