{
  "type": "Feature",
  "properties": {
    "addr:full":"60 Herbert Road, Plumstead London Greater London SE18 3SH",
    "addr:housenumber":"60",
    "addr:postcode":"se18 3sh",
    "addr:street":"Herbert Road",
    "iso:country":"GB",
    "sg:address":"60 Herbert Road, Plumstead",
    "sg:city":"London",
    "sg:classifiers":[
        {
            "category":"Shopping",
            "subcategory":"Pharmacy",
            "type":"Retail Goods"
        }
    ],
    "sg:phone":"+44 20 8854 1064",
    "sg:postcode":"SE18 3SH",
    "sg:province":"Greater London",
    "sg:tags":[
        "pharmacist",
        "chemist"
    ],
    "wof:name":"Herbert Pharmacy",
    "wof:placetype":"venue"
},
  "geometry": {"coordinates":[0.06922,51.480221],"type":"Point"}
}