{
  "type": "Feature",
  "properties": {
    "iso:country":"GB",
    "sg:address":"Unit 9 Cam Sq, Wilbury Way",
    "sg:city":"Hitchin",
    "sg:classifiers":[
        {
            "category":"Professional",
            "subcategory":"Printing & Photocopies",
            "type":"Services"
        }
    ],
    "sg:phone":"+44 1462 421252",
    "sg:postcode":"SG4 0TZ",
    "sg:province":"Hertfordshire",
    "sg:tags":[
        "printer"
    ],
    "wof:name":"Kall-Kwik Printing",
    "wof:placetype":"venue"
},
  "geometry": {"coordinates":[-0.2650310099,51.9655456543],"type":"Point"}
}