{
  "type": "Feature",
  "properties": {
    "iso:country":"GB",
    "sg:address":"Unit 15, Laws Yard, Willow Walk",
    "sg:city":"Spalding",
    "sg:classifiers":[
        {
            "category":"Retail",
            "subcategory":"Storage",
            "type":"Services"
        }
    ],
    "sg:postcode":"PE11 1UW",
    "sg:province":"Lincolnshire",
    "sg:tags":[
        "household",
        "removal"
    ],
    "wof:name":"Peace of Mind",
    "wof:placetype":"venue"
},
  "geometry": {"coordinates":[-0.168619,52.794609],"type":"Point"}
}