{
  "type": "Feature",
  "properties": {
    "addr:full":"47 Meadow Walk Whitstable Kent CT5 4PW",
    "addr:housenumber":"47",
    "addr:postcode":"ct5 4pw",
    "addr:street":"Meadow Walk Whitstable",
    "iso:country":"GB",
    "sg:address":"47 Meadow Walk",
    "sg:city":"Whitstable",
    "sg:classifiers":[
        {
            "category":"Building & Trades",
            "subcategory":"Construction",
            "type":"Services"
        }
    ],
    "sg:phone":"+44 1227 275735",
    "sg:postcode":"CT5 4PW",
    "sg:province":"Kent",
    "sg:tags":[
        "joiner",
        "carpenter"
    ],
    "wof:name":"S Harris",
    "wof:placetype":"venue"
},
  "geometry": {"coordinates":[1.0185710192,51.3452835083],"type":"Point"}
}