{
  "type": "Feature",
  "properties": {
    "iso:country":"GB",
    "sg:address":"341 Barking Road, East Ham",
    "sg:city":"London",
    "sg:classifiers":[
        {
            "category":"Retail",
            "subcategory":"Laundry & Dry Cleaning",
            "type":"Services"
        }
    ],
    "sg:phone":"+44 20 8472 9444",
    "sg:postcode":"E6 1AL",
    "sg:province":"Greater London",
    "sg:tags":[
        "alteration"
    ],
    "wof:name":"The Golden Dry Cleaners",
    "wof:placetype":"venue"
},
  "geometry": {"coordinates":[0.052621,51.532887],"type":"Point"}
}