{
  "type": "Feature",
  "properties": {
    "iso:country":"GB",
    "sg:address":"Chesterfield Rd",
    "sg:city":"Chesterfield",
    "sg:classifiers":[
        {
            "category":"Place Of Worship",
            "type":"Public Place"
        }
    ],
    "sg:phone":"+44 1246 472310",
    "sg:postcode":"S43 3QF",
    "sg:province":"Derbyshire",
    "wof:name":"St Joseph's R C Church",
    "wof:placetype":"venue"
},
  "geometry": {"coordinates":[-1.356789,53.265881],"type":"Point"}
}