{
  "type": "Feature",
  "properties": {
    "addr:full":"154 Barry Road Barry The Vale of Glamorgan CF63 1BD",
    "addr:housenumber":"154",
    "addr:postcode":"cf63 1bd",
    "addr:street":"Barry Road;Vale",
    "iso:country":"GB",
    "sg:address":"154 Barry Road",
    "sg:city":"Barry",
    "sg:classifiers":[
        {
            "category":"Restaurant",
            "type":"Food & Drink"
        },
        {
            "category":"Food & Beverages",
            "subcategory":"Meat & Fish",
            "type":"Retail Goods"
        }
    ],
    "sg:phone":"+44 1446 744383",
    "sg:postcode":"CF63 1BD",
    "sg:province":"The Vale of Glamorgan",
    "sg:tags":[
        "chip"
    ],
    "wof:name":"Lau's Fish Bar",
    "wof:placetype":"venue"
},
  "geometry": {"coordinates":[-3.2634971142,51.412322998],"type":"Point"}
}