{
  "type": "Feature",
  "properties": {
    "iso:country":"GB",
    "sg:address":"217 Chanterlands Avenue",
    "sg:city":"Hull",
    "sg:classifiers":[
        {
            "category":"Personal",
            "subcategory":"Beauty Salon",
            "type":"Services"
        }
    ],
    "sg:phone":"+44 1482 443257",
    "sg:postcode":"HU5 3TP",
    "sg:province":"East Riding of Yorkshire",
    "sg:tags":[
        "unisex",
        "hairdresser"
    ],
    "wof:name":"Clippers Hull Ltd.",
    "wof:placetype":"venue"
},
  "geometry": {"coordinates":[-0.374487,53.7575],"type":"Point"}
}