{
  "type": "Feature",
  "properties": {
    "iso:country":"GB",
    "sg:address":"20 River Street",
    "sg:city":"Truro",
    "sg:classifiers":[
        {
            "category":"Cafe",
            "type":"Food & Drink"
        }
    ],
    "sg:phone":"+44 1872 242468",
    "sg:postcode":"TR1 2SQ",
    "sg:province":"Cornwall",
    "sg:tags":[
        "tea",
        "room"
    ],
    "wof:name":"The County Cafe & Outsales",
    "wof:placetype":"venue"
},
  "geometry": {"coordinates":[-5.055127,50.263405],"type":"Point"}
}