{
  "type": "Feature",
  "properties": {
    "iso:country":"GB",
    "sg:address":"Unit 19 Borers Yard, Borers Arms Road, Copthorne",
    "sg:city":"Crawley",
    "sg:classifiers":[
        {
            "category":"Real Estate",
            "subcategory":"Architect",
            "type":"Services"
        }
    ],
    "sg:phone":"+44 1342 716455",
    "sg:postcode":"RH10 3LH",
    "sg:province":"Surrey",
    "sg:tags":[
        "architectural"
    ],
    "wof:name":"Guide Line Building Services Ltd",
    "wof:placetype":"venue"
},
  "geometry": {"coordinates":[-0.111629,51.139404],"type":"Point"}
}