{
  "type": "Feature",
  "properties": {
    "addr:full":"1 Bartleet Road Redditch Warwickshire B98 0DQ",
    "addr:housenumber":"1",
    "addr:postcode":"b98 0dq",
    "addr:street":"Bartleet Road",
    "iso:country":"GB",
    "sg:address":"1 Bartleet Road",
    "sg:city":"Redditch",
    "sg:classifiers":[
        {
            "category":"Professional",
            "subcategory":"Engineering",
            "type":"Services"
        }
    ],
    "sg:phone":"+44 1527 502242",
    "sg:postcode":"B98 0DQ",
    "sg:province":"Warwickshire",
    "sg:tags":[
        "hydraulic",
        "engineer"
    ],
    "wof:name":"Cyltech Developments",
    "wof:placetype":"venue"
},
  "geometry": {"coordinates":[-1.89906,52.287819],"type":"Point"}
}