{
  "type": "Feature",
  "properties": {
    "addr:full":"235a High St North, East Ham East Ham Greater London E6 1JG",
    "addr:housenumber":"235a",
    "addr:postcode":"e6 1jg",
    "addr:street":"High St North;Ham",
    "iso:country":"GB",
    "sg:address":"235a High St North, East Ham",
    "sg:city":"East Ham",
    "sg:classifiers":[
        {
            "category":"Communications",
            "type":"Services"
        }
    ],
    "sg:phone":"+44 20 8470 1068",
    "sg:postcode":"E6 1JG",
    "sg:province":"Greater London",
    "sg:tags":[
        "broadcasting"
    ],
    "wof:name":"Trans Asia Ltd",
    "wof:placetype":"venue"
},
  "geometry": {"coordinates":[0.0506470017,51.5400276184],"type":"Point"}
}