{
  "type": "Feature",
  "properties": {
    "addr:full":"109 Main Street, Ratho Newbridge City of Edinburgh EH28 8RS",
    "addr:housenumber":"109",
    "addr:postcode":"eh28 8rs",
    "addr:street":"Main Street",
    "iso:country":"GB",
    "sg:address":"109 Main Street, Ratho",
    "sg:city":"Newbridge",
    "sg:classifiers":[
        {
            "category":"Building & Trades",
            "subcategory":"Plumbing",
            "type":"Services"
        }
    ],
    "sg:phone":"+44 131 333 1518",
    "sg:postcode":"EH28 8RS",
    "sg:province":"City of Edinburgh",
    "sg:tags":[
        "heating"
    ],
    "wof:name":"Colin Bain Plumbing",
    "wof:placetype":"venue"
},
  "geometry": {"coordinates":[-3.3791339397,55.9220962524],"type":"Point"}
}