{
  "type": "Feature",
  "properties": {
    "addr:full":"365 St. John St Clerkenwell Greater London EC1V 4LB",
    "addr:housenumber":"365",
    "addr:postcode":"ec1v 4lb",
    "addr:street":"St. John St",
    "iso:country":"GB",
    "sg:address":"365 St. John St",
    "sg:city":"Clerkenwell",
    "sg:classifiers":[
        {
            "category":"Manufacturing",
            "subcategory":"Apparel",
            "type":"Manufacturing & Wholesale Goods"
        }
    ],
    "sg:phone":"+44 20 7833 8255",
    "sg:postcode":"EC1V 4LB",
    "sg:province":"Greater London",
    "sg:tags":[
        "garment",
        "designer"
    ],
    "wof:name":"Debbie Bliss",
    "wof:placetype":"venue"
},
  "geometry": {"coordinates":[-0.105169,51.529678],"type":"Point"}
}