{
  "type": "Feature",
  "properties": {
    "addr:full":"Hawks Rd Hailsham East Sussex BN27 1NP",
    "addr:postcode":"bn27 1np",
    "addr:street":"Hawks Rd",
    "iso:country":"GB",
    "sg:address":"Hawks Rd",
    "sg:city":"Hailsham",
    "sg:classifiers":[
        {
            "category":"Social Services",
            "subcategory":"Child Care",
            "type":"Services"
        }
    ],
    "sg:phone":"+44 1323 843771",
    "sg:postcode":"BN27 1NP",
    "sg:province":"East Sussex",
    "sg:tags":[
        "children's",
        "home"
    ],
    "wof:name":"Lansdowne Childrens Centre",
    "wof:placetype":"venue"
},
  "geometry": {"coordinates":[0.2550379932,50.8783111572],"type":"Point"}
}