{
  "type": "Feature",
  "properties": {
    "addr:full":"Barnhorn Road Bexhill-on-sea East Sussex TN39 4QR",
    "addr:postcode":"tn39 4qr",
    "addr:street":"Barnhorn Road",
    "iso:country":"GB",
    "sg:address":"Barnhorn Road",
    "sg:city":"Bexhill-on-sea",
    "sg:classifiers":[
        {
            "category":"Health Services",
            "subcategory":"Nursing And Care Facility",
            "type":"Services"
        },
        {
            "category":"Retail",
            "subcategory":"Auto Repair",
            "type":"Services"
        }
    ],
    "sg:postcode":"TN39 4QR",
    "sg:province":"East Sussex",
    "sg:tags":[
        "modification",
        "residential",
        "garage"
    ],
    "wof:name":"Barnhorn Service Centre",
    "wof:placetype":"venue"
},
  "geometry": {"coordinates":[0.432695,50.845123],"type":"Point"}
}