{
  "type": "Feature",
  "properties": {
    "addr:full":"23 Clysbarton Court, Bramhall Stockport Cheshire SK7 3NP",
    "addr:housenumber":"23",
    "addr:postcode":"sk7 3np",
    "addr:street":"Clysbarton Court",
    "iso:country":"GB",
    "sg:address":"23 Clysbarton Court, Bramhall",
    "sg:city":"Stockport",
    "sg:classifiers":[
        {
            "category":"Home & Garden",
            "subcategory":"Household Appliances",
            "type":"Retail Goods"
        }
    ],
    "sg:postcode":"SK7 3NP",
    "sg:province":"Cheshire",
    "sg:tags":[
        "electrical"
    ],
    "wof:name":"Pickups Home Maintenance",
    "wof:placetype":"venue"
},
  "geometry": {"coordinates":[-2.171724,53.373775],"type":"Point"}
}