{
  "type": "Feature",
  "properties": {
    "addr:full":"Edenfield Avenue Hornsea East Riding of Yorkshire HU18 1UL",
    "addr:postcode":"hu18 1ul",
    "addr:street":"Edenfield Avenue",
    "iso:country":"GB",
    "sg:address":"Edenfield Avenue",
    "sg:city":"Hornsea",
    "sg:classifiers":[
        {
            "category":"Building & Trades",
            "subcategory":"Construction",
            "type":"Services"
        }
    ],
    "sg:phone":"+44 1964 533616",
    "sg:postcode":"HU18 1UL",
    "sg:province":"East Riding of Yorkshire",
    "sg:tags":[
        "builder"
    ],
    "wof:name":"James Malcom Osborne",
    "wof:placetype":"venue"
},
  "geometry": {"coordinates":[-0.170224,53.901154],"type":"Point"}
}