{
  "type": "Feature",
  "properties": {
    "addr:full":"Ryeground Ho, 6b Ryeground La Liverpool Lancashire L37 7EQ",
    "addr:housenumber":"6b",
    "addr:postcode":"l37 7eq",
    "addr:street":"Ryeground La Liverpool",
    "iso:country":"GB",
    "sg:address":"Ryeground Ho, 6b Ryeground La",
    "sg:city":"Liverpool",
    "sg:classifiers":[
        {
            "category":"Real Estate",
            "subcategory":"Real Estate Operator",
            "type":"Services"
        }
    ],
    "sg:phone":"+44 1704 878477",
    "sg:postcode":"L37 7EQ",
    "sg:province":"Lancashire",
    "sg:tags":[
        "letting",
        "agent"
    ],
    "wof:name":"Ryeground Properties",
    "wof:placetype":"venue"
},
  "geometry": {"coordinates":[-3.0575299263,53.5646286011],"type":"Point"}
}