{
  "type": "Feature",
  "properties": {
    "iso:country":"GB",
    "sg:address":"109 Langworthy Road",
    "sg:city":"Salford",
    "sg:classifiers":[
        {
            "category":"Shopping",
            "subcategory":"Pharmacy",
            "type":"Retail Goods"
        }
    ],
    "sg:phone":"+44 161 736 1205",
    "sg:postcode":"M6 5PH",
    "sg:province":"Greater Manchester",
    "sg:tags":[
        "pharmacist",
        "chemist"
    ],
    "wof:name":"C S  Fletcher (Salford) Ltd.",
    "wof:placetype":"venue"
},
  "geometry": {"coordinates":[-2.294929,53.484081],"type":"Point"}
}