{
  "type": "Feature",
  "properties": {
    "addr:full":"Woodside Farm, Octon Driffield East Riding of Yorkshire YO25 3BL",
    "addr:postcode":"yo25 3bl",
    "addr:street":"Octon",
    "iso:country":"GB",
    "sg:address":"Woodside Farm, Octon",
    "sg:city":"Driffield",
    "sg:classifiers":[
        {
            "category":"Manufacturing",
            "subcategory":"Buildings",
            "type":"Manufacturing & Wholesale Goods"
        }
    ],
    "sg:phone":"+44 1377 267434",
    "sg:postcode":"YO25 3BL",
    "sg:province":"East Riding of Yorkshire",
    "sg:tags":[
        "portable"
    ],
    "wof:name":"Farmer Cabins Ltd",
    "wof:placetype":"venue"
},
  "geometry": {"coordinates":[-0.4177379906,54.1115074158],"type":"Point"}
}