{
  "type": "Feature",
  "properties": {
    "addr:full":"Firgrove Rd Bordon Hampshire GU35 9EQ",
    "addr:postcode":"gu35 9eq",
    "addr:street":"Firgrove Rd",
    "iso:country":"GB",
    "sg:address":"Firgrove Rd",
    "sg:city":"Bordon",
    "sg:classifiers":[
        {
            "category":"Retail",
            "subcategory":"Auto Rental",
            "type":"Services"
        }
    ],
    "sg:phone":"+44 1420 472437",
    "sg:postcode":"GU35 9EQ",
    "sg:province":"Hampshire",
    "sg:tags":[
        "truck",
        "hire",
        "van"
    ],
    "wof:name":"Alpha Self Drive",
    "wof:placetype":"venue"
},
  "geometry": {"coordinates":[-0.8651139736,51.1088562012],"type":"Point"}
}