{
  "type": "Feature",
  "properties": {
    "addr:full":"6 Lower Mill Street Kidderminster Staffordshire DY11 6UU",
    "addr:housenumber":"6",
    "addr:postcode":"dy11 6uu",
    "addr:street":"Lower Mill Street",
    "iso:country":"GB",
    "sg:address":"6 Lower Mill Street",
    "sg:city":"Kidderminster",
    "sg:classifiers":[
        {
            "category":"Insurance",
            "subcategory":"Insurance Agent",
            "type":"Services"
        }
    ],
    "sg:phone":"+44 1562 741054",
    "sg:postcode":"DY11 6UU",
    "sg:province":"Staffordshire",
    "sg:website":"http://www.swinton.co.uk",
    "wof:name":"Swinton",
    "wof:placetype":"venue"
},
  "geometry": {"coordinates":[-2.250791,52.388256],"type":"Point"}
}