{
  "type": "Feature",
  "properties": {
    "iso:country":"GB",
    "sg:address":"278 Rishton Lane",
    "sg:city":"Bolton",
    "sg:classifiers":[
        {
            "category":"Building & Trades",
            "subcategory":"Construction",
            "type":"Services"
        }
    ],
    "sg:phone":"+44 1204 432990",
    "sg:postcode":"BL3 2EN",
    "sg:province":"Lancashire",
    "sg:tags":[
        "glazier"
    ],
    "wof:name":"Fastglaze",
    "wof:placetype":"venue"
},
  "geometry": {"coordinates":[-2.4286301136,53.5598487854],"type":"Point"}
}