{
  "type": "Feature",
  "properties": {
    "iso:country":"GB",
    "sg:address":"19 St Bernards Road",
    "sg:city":"Slough",
    "sg:classifiers":[
        {
            "category":"Professional",
            "subcategory":"Engineering",
            "type":"Services"
        }
    ],
    "sg:postcode":"SL3 7NT",
    "sg:province":"Berkshire",
    "sg:tags":[
        "contractor",
        "electrical",
        "engineer"
    ],
    "wof:name":"P J Electrics",
    "wof:placetype":"venue"
},
  "geometry": {"coordinates":[-0.5737100244,51.5030593872],"type":"Point"}
}