{
  "type": "Feature",
  "properties": {
    "addr:full":"Candwr Farm, Ponthir Newport Monmouthshire NP18 1HU",
    "addr:postcode":"np18 1hu",
    "iso:country":"GB",
    "sg:address":"Candwr Farm, Ponthir",
    "sg:city":"Newport",
    "sg:classifiers":[
        {
            "category":"Manufacturing",
            "subcategory":"Food",
            "type":"Manufacturing & Wholesale Goods"
        }
    ],
    "sg:phone":"+44 1633 421601",
    "sg:postcode":"NP18 1HU",
    "sg:province":"Monmouthshire",
    "sg:tags":[
        "miller",
        "mill"
    ],
    "wof:name":"On Farm Feeds",
    "wof:placetype":"venue"
},
  "geometry": {"coordinates":[-2.97201,51.629665],"type":"Point"}
}