{
  "type": "Feature",
  "properties": {
    "addr:full":"146 Cross Street, Sale Manchester Cheshire M33 7AQ",
    "addr:housenumber":"146",
    "addr:postcode":"m33 7aq",
    "addr:street":"Cross Street",
    "iso:country":"GB",
    "sg:address":"146 Cross Street, Sale",
    "sg:city":"Manchester",
    "sg:classifiers":[
        {
            "category":"Home & Garden",
            "subcategory":"Home Furnishings",
            "type":"Retail Goods"
        },
        {
            "category":"Home & Garden",
            "subcategory":"Kitchen Supply",
            "type":"Retail Goods"
        }
    ],
    "sg:phone":"+44 161 905 1553",
    "sg:postcode":"M33 7AQ",
    "sg:province":"Cheshire",
    "sg:tags":[
        "furnishers",
        "ware",
        "planner"
    ],
    "wof:name":"Di Lusso Kitchens Ltd.",
    "wof:placetype":"venue"
},
  "geometry": {"coordinates":[-2.3198060989,53.4303703308],"type":"Point"}
}