{
  "type": "Feature",
  "properties": {
    "addr:full":"8 Eastmoor Rd Newport Newport NP19 4NX",
    "addr:housenumber":"8",
    "addr:postcode":"np19 4nx",
    "addr:street":"Eastmoor Rd",
    "iso:country":"GB",
    "sg:address":"8 Eastmoor Rd",
    "sg:city":"Newport",
    "sg:classifiers":[
        {
            "category":"Building & Trades",
            "subcategory":"Construction",
            "type":"Services"
        }
    ],
    "sg:phone":"+44 1633 273557",
    "sg:postcode":"NP19 4NX",
    "sg:province":"Newport",
    "sg:tags":[
        "roofing"
    ],
    "wof:name":"D Truelove",
    "wof:placetype":"venue"
},
  "geometry": {"coordinates":[-2.951305,51.579544],"type":"Point"}
}