{
  "type": "Feature",
  "properties": {
    "addr:full":"12 Badminton Road, Downend Bristol City of Bristol BS16 6BQ",
    "addr:housenumber":"12",
    "addr:postcode":"bs16 6bq",
    "addr:street":"Badminton Road",
    "iso:country":"GB",
    "sg:address":"12 Badminton Road, Downend",
    "sg:city":"Bristol",
    "sg:classifiers":[
        {
            "category":"Real Estate",
            "subcategory":"Real Estate Agent",
            "type":"Services"
        }
    ],
    "sg:phone":"+44 117 970 2244",
    "sg:postcode":"BS16 6BQ",
    "sg:province":"City of Bristol",
    "wof:name":"Andrews Estate Agents Ltd.",
    "wof:placetype":"venue"
},
  "geometry": {"coordinates":[-2.5029881001,51.4889526367],"type":"Point"}
}