{
  "type": "Feature",
  "properties": {
    "addr:full":"10 Stratfield Road, Summertown Oxford Oxfordshire OX2 7BQ",
    "addr:housenumber":"10",
    "addr:postcode":"ox2 7bq",
    "addr:street":"Stratfield Road",
    "iso:country":"GB",
    "sg:address":"10 Stratfield Road, Summertown",
    "sg:city":"Oxford",
    "sg:classifiers":[
        {
            "category":"Organizations",
            "subcategory":"Membership Organization",
            "type":"Services"
        }
    ],
    "sg:postcode":"OX2 7BQ",
    "sg:province":"Oxfordshire",
    "sg:tags":[
        "club"
    ],
    "wof:name":"Modes Users Association",
    "wof:placetype":"venue"
},
  "geometry": {"coordinates":[-1.265977025,51.776599884],"type":"Point"}
}