{
  "type": "Feature",
  "properties": {
    "addr:full":"33a Market Road Great Yarmouth Norfolk NR30 1PB",
    "addr:housenumber":"33a",
    "addr:postcode":"nr30 1pb",
    "addr:street":"Market Road",
    "iso:country":"GB",
    "sg:address":"33a Market Road",
    "sg:city":"Great Yarmouth",
    "sg:classifiers":[
        {
            "category":"Shopping",
            "subcategory":"Clothing, Apparel, & Fashions",
            "type":"Retail Goods"
        }
    ],
    "sg:postcode":"NR30 1PB",
    "sg:province":"Norfolk",
    "sg:tags":[
        "menswear"
    ],
    "wof:name":"Stephen D Barrow",
    "wof:placetype":"venue"
},
  "geometry": {"coordinates":[1.726847,52.608635],"type":"Point"}
}