{
  "type": "Feature",
  "properties": {
    "iso:country":"GB",
    "sg:address":"5 Dickens Rd",
    "sg:city":"Broadstairs",
    "sg:classifiers":[
        {
            "category":"Building & Trades",
            "subcategory":"Construction",
            "type":"Services"
        }
    ],
    "sg:phone":"+44 1843 601670",
    "sg:postcode":"CT10 1DX",
    "sg:province":"Kent",
    "sg:tags":[
        "builder"
    ],
    "wof:name":"Emes Building Services",
    "wof:placetype":"venue"
},
  "geometry": {"coordinates":[1.4435850382,51.3620986938],"type":"Point"}
}