{
  "type": "Feature",
  "properties": {
    "addr:full":"26 Dunstall St Scunthorpe Lincolnshire DN15 6LD",
    "addr:housenumber":"26",
    "addr:postcode":"dn15 6ld",
    "addr:street":"Dunstall St",
    "iso:country":"GB",
    "sg:address":"26 Dunstall St",
    "sg:city":"Scunthorpe",
    "sg:classifiers":[
        {
            "category":"Arts & Performance",
            "subcategory":"Art Gallery",
            "type":"Entertainment"
        }
    ],
    "sg:phone":"+44 1724 271820",
    "sg:postcode":"DN15 6LD",
    "sg:province":"Lincolnshire",
    "wof:name":"Impressions",
    "wof:placetype":"venue"
},
  "geometry": {"coordinates":[-0.6530370116,53.5902481079],"type":"Point"}
}