{
  "type": "Feature",
  "properties": {
    "addr:full":"27 Chancery Lane London Greater London WC2A 1PA",
    "addr:housenumber":"27",
    "addr:postcode":"wc2a 1pa",
    "addr:street":"Chancery Lane",
    "iso:country":"GB",
    "sg:address":"27 Chancery Lane",
    "sg:city":"London",
    "sg:classifiers":[
        {
            "category":"Professional",
            "subcategory":"Lawyer & Legal Services",
            "type":"Services"
        }
    ],
    "sg:phone":"+44 20 7440 4400",
    "sg:postcode":"WC2A 1PA",
    "sg:province":"Greater London",
    "sg:tags":[
        "solicitor"
    ],
    "wof:name":"Maxwell Batley Ltd.",
    "wof:placetype":"venue"
},
  "geometry": {"coordinates":[-0.1111489981,51.5141906738],"type":"Point"}
}