{
  "type": "Feature",
  "properties": {
    "iso:country":"GB",
    "sg:address":"522 Victoria Road",
    "sg:city":"Ruislip",
    "sg:classifiers":[
        {
            "category":"Retail",
            "subcategory":"Laundry & Dry Cleaning",
            "type":"Services"
        }
    ],
    "sg:phone":"+44 20 8845 4252",
    "sg:postcode":"HA4 0HD",
    "sg:province":"Greater London",
    "sg:tags":[
        "cleaner",
        "alteration"
    ],
    "wof:name":"Xl Cleaners",
    "wof:placetype":"venue"
},
  "geometry": {"coordinates":[-0.397152,51.558266],"type":"Point"}
}