{
  "type": "Feature",
  "properties": {
    "addr:full":"1 New Road Chatteris Cambridgeshire PE16 6BJ",
    "addr:housenumber":"1",
    "addr:postcode":"pe16 6bj",
    "addr:street":"New Road",
    "iso:country":"GB",
    "sg:address":"1 New Road",
    "sg:city":"Chatteris",
    "sg:classifiers":[
        {
            "category":"Autos & Motor Vehicles",
            "subcategory":"Automobile Sales",
            "type":"Retail Goods"
        }
    ],
    "sg:phone":"+44 1354 692634",
    "sg:postcode":"PE16 6BJ",
    "sg:province":"Cambridgeshire",
    "sg:tags":[
        "car"
    ],
    "wof:name":"Philip Chatteris",
    "wof:placetype":"venue"
},
  "geometry": {"coordinates":[0.0486700013,52.4563903809],"type":"Point"}
}