{
  "type": "Feature",
  "properties": {
    "addr:full":"36/2 Kings Rd, Rosyth Dunfermline Fife KY11 2SP",
    "addr:housenumber":"36 / 2",
    "addr:postcode":"ky11 2sp",
    "addr:street":"Kings Rd",
    "iso:country":"GB",
    "sg:address":"36/2 Kings Rd, Rosyth",
    "sg:city":"Dunfermline",
    "sg:classifiers":[
        {
            "category":"Professional",
            "subcategory":"Accounting & Tax Preparation",
            "type":"Services"
        }
    ],
    "sg:phone":"+44 1383 418818",
    "sg:postcode":"KY11 2SP",
    "sg:province":"Fife",
    "sg:tags":[
        "accountant",
        "activity"
    ],
    "wof:name":"D Brown & Co",
    "wof:placetype":"venue"
},
  "geometry": {"coordinates":[-3.4280080795,56.0432739258],"type":"Point"}
}