{
  "type": "Feature",
  "properties": {
    "addr:full":"Tees Offshore Base, Dockside Road, Southbank Middlesbrough North Yorkshire TS6 6UZ",
    "addr:postcode":"ts6 6uz",
    "addr:street":"Dockside Road",
    "iso:country":"GB",
    "sg:address":"Tees Offshore Base, Dockside Road, Southbank",
    "sg:city":"Middlesbrough",
    "sg:classifiers":[
        {
            "category":"Manufacturing",
            "subcategory":"Metals",
            "type":"Manufacturing & Wholesale Goods"
        }
    ],
    "sg:phone":"+44 1642 457011",
    "sg:postcode":"TS6 6UZ",
    "sg:province":"North Yorkshire",
    "sg:tags":[
        "heat",
        "-",
        "treatment"
    ],
    "wof:name":"Beatyheat Ltd.",
    "wof:placetype":"venue"
},
  "geometry": {"coordinates":[-1.1811900139,54.5882797241],"type":"Point"}
}