{
  "type": "Feature",
  "properties": {
    "addr:full":"1 Pecks House Farm Cotts, Newbiggin Lane Newcastle-upon-tyne Tyne and Wear NE5 1NA",
    "addr:housenumber":"1",
    "addr:postcode":"ne5 1na",
    "addr:street":"Pecks House Farm;Newbiggin Lane",
    "iso:country":"GB",
    "sg:address":"1 Pecks House Farm Cotts, Newbiggin Lane",
    "sg:city":"Newcastle-upon-tyne",
    "sg:classifiers":[
        {
            "category":"Military Area",
            "subcategory":"Air Force Base",
            "type":"Public Place"
        }
    ],
    "sg:postcode":"NE5 1NA",
    "sg:province":"Tyne and Wear",
    "sg:tags":[
        "taxi",
        "hire",
        "private"
    ],
    "wof:name":"Airport Taxis & Minibuses",
    "wof:placetype":"venue"
},
  "geometry": {"coordinates":[-1.68587,55.01033],"type":"Point"}
}