{
  "type": "Feature",
  "properties": {
    "addr:full":"1 Polgarth Penzance Cornwall TR18 5QX",
    "addr:housenumber":"1",
    "addr:postcode":"tr18 5qx",
    "addr:street":"Polgarth",
    "iso:country":"GB",
    "sg:address":"1 Polgarth",
    "sg:city":"Penzance",
    "sg:classifiers":[
        {
            "category":"Farming",
            "subcategory":"Fish & Marine Products",
            "type":"Manufacturing & Wholesale Goods"
        }
    ],
    "sg:phone":"+44 1736 361781",
    "sg:postcode":"TR18 5QX",
    "sg:province":"Cornwall",
    "sg:tags":[
        "fishmonger"
    ],
    "wof:name":"M & R Crab Processors",
    "wof:placetype":"venue"
},
  "geometry": {"coordinates":[-5.5584058762,50.1088409424],"type":"Point"}
}