{
  "type": "Feature",
  "properties": {
    "addr:full":"18 Ashford Rise Belper Derbyshire DE56 1TJ",
    "addr:housenumber":"18",
    "addr:postcode":"de56 1tj",
    "addr:street":"Ashford Rise",
    "iso:country":"GB",
    "sg:address":"18 Ashford Rise",
    "sg:city":"Belper",
    "sg:classifiers":[
        {
            "category":"Building & Trades",
            "subcategory":"Construction",
            "type":"Services"
        }
    ],
    "sg:phone":"+44 1773 824113",
    "sg:postcode":"DE56 1TJ",
    "sg:province":"Derbyshire",
    "sg:tags":[
        "builder"
    ],
    "wof:name":"Wilcon Homes Northern",
    "wof:placetype":"venue"
},
  "geometry": {"coordinates":[-1.4641269445,53.0347747803],"type":"Point"}
}