{
  "type": "Feature",
  "properties": {
    "addr:full":"16 Spencer Street Carlisle Cumbria CA1 1BG",
    "addr:housenumber":"16",
    "addr:postcode":"ca1 1bg",
    "addr:street":"Spencer Street",
    "iso:country":"GB",
    "sg:address":"16 Spencer Street",
    "sg:city":"Carlisle",
    "sg:classifiers":[
        {
            "category":"Professional",
            "subcategory":"Employment Agencies",
            "type":"Services"
        },
        {
            "category":"Government",
            "subcategory":"Post Office",
            "type":"Public Place"
        }
    ],
    "sg:postcode":"CA1 1BG",
    "sg:province":"Cumbria",
    "sg:tags":[
        "consultant",
        "serviced",
        "facility"
    ],
    "wof:name":"Carlisle Office Services",
    "wof:placetype":"venue"
},
  "geometry": {"coordinates":[-2.930884,54.894672],"type":"Point"}
}