{
  "type": "Feature",
  "properties": {
    "addr:full":"Holme Bottom Farm Harrogate North Yorkshire HG3 3BH",
    "addr:postcode":"hg3 3bh",
    "addr:street":"Holme",
    "iso:country":"GB",
    "sg:address":"Holme Bottom Farm",
    "sg:city":"Harrogate",
    "sg:classifiers":[
        {
            "category":"Farming",
            "subcategory":"Farm",
            "type":"Manufacturing & Wholesale Goods"
        }
    ],
    "sg:phone":"+44 1423 771661",
    "sg:postcode":"HG3 3BH",
    "sg:province":"North Yorkshire",
    "sg:tags":[
        "mixed",
        "crop"
    ],
    "wof:name":"D S Cockshott",
    "wof:placetype":"venue"
},
  "geometry": {"coordinates":[-1.53624,54.032001],"type":"Point"}
}