{
  "type": "Feature",
  "properties": {
    "addr:full":"1st Floor A Wing, South Court, Sharston Road Manchester Greater Manchester M22 4SN",
    "addr:postcode":"m22 4sn",
    "addr:street":"South Court Sharston Road",
    "iso:country":"GB",
    "sg:address":"1st Floor A Wing, South Court, Sharston Road",
    "sg:city":"Manchester",
    "sg:classifiers":[
        {
            "category":"Manufacturing",
            "subcategory":"Chemicals & Compounds",
            "type":"Manufacturing & Wholesale Goods"
        },
        {
            "category":"Wholesale",
            "subcategory":"Chemicals & Plastics",
            "type":"Manufacturing & Wholesale Goods"
        }
    ],
    "sg:phone":"+44 161 998 1991",
    "sg:postcode":"M22 4SN",
    "sg:province":"Greater Manchester",
    "sg:tags":[
        "product",
        "allied"
    ],
    "wof:name":"3 V (U K) Ltd.",
    "wof:placetype":"venue"
},
  "geometry": {"coordinates":[-2.2571389675,53.3969688416],"type":"Point"}
}