{
  "type": "Feature",
  "properties": {
    "addr:full":"Restoration Ho Stafford Rd Wallington Surrey SM6 9AP",
    "addr:postcode":"sm6 9ap",
    "addr:street":"Stafford Rd",
    "iso:country":"GB",
    "sg:address":"Restoration Ho Stafford Rd",
    "sg:city":"Wallington",
    "sg:classifiers":[
        {
            "category":"Utilities",
            "subcategory":"Natural Gas",
            "type":"Services"
        }
    ],
    "sg:phone":"+44 20 8669 9900",
    "sg:postcode":"SM6 9AP",
    "sg:province":"Surrey",
    "sg:tags":[
        "consultant",
        "air conditioning"
    ],
    "wof:name":"Conduct Services",
    "wof:placetype":"venue"
},
  "geometry": {"coordinates":[-0.149898,51.360123],"type":"Point"}
}