{
  "type": "Feature",
  "properties": {
    "addr:full":"West Wing Dipple Medical Centre, Wickford Avenue Pitsea Basildon Essex SS13 3HQ",
    "addr:postcode":"ss13 3hq",
    "addr:street":"Wickford Avenue",
    "iso:country":"GB",
    "sg:address":"West Wing Dipple Medical Centre, Wickford Avenue Pitsea",
    "sg:city":"Basildon",
    "sg:classifiers":[
        {
            "category":"Health Services",
            "subcategory":"Doctor",
            "type":"Services"
        }
    ],
    "sg:phone":"+44 1268 555225",
    "sg:postcode":"SS13 3HQ",
    "sg:province":"Essex",
    "sg:tags":[
        "practitioners"
    ],
    "wof:name":"Bell R J Reade P F Sims M A Dr S",
    "wof:placetype":"venue"
},
  "geometry": {"coordinates":[0.5033299923,51.5647583008],"type":"Point"}
}