{
  "type": "Feature",
  "properties": {
    "iso:country":"GB",
    "sg:address":"83 Stanmore Road",
    "sg:city":"Birmingham",
    "sg:classifiers":[
        {
            "category":"Farming",
            "subcategory":"Nursery",
            "type":"Manufacturing & Wholesale Goods"
        },
        {
            "category":"Social Services",
            "subcategory":"Child Care",
            "type":"Services"
        }
    ],
    "sg:phone":"+44 121 429 1480",
    "sg:postcode":"B16 9SU",
    "sg:province":"West Midlands",
    "sg:tags":[
        "creche"
    ],
    "wof:name":"Stanmore Day Nursery",
    "wof:placetype":"venue"
},
  "geometry": {"coordinates":[-1.95169,52.476551],"type":"Point"}
}