{
  "type": "Feature",
  "properties": {
    "iso:country":"GB",
    "sg:address":"37 St Johns Street",
    "sg:city":"Devizes",
    "sg:classifiers":[
        {
            "category":"Shopping",
            "subcategory":"Clothing, Apparel, & Fashions",
            "type":"Retail Goods"
        }
    ],
    "sg:phone":"+44 1380 722216",
    "sg:postcode":"SN10 1BL",
    "sg:province":"Wiltshire",
    "sg:tags":[
        "shop"
    ],
    "wof:name":"Beales (Bath) Ltd.",
    "wof:placetype":"venue"
},
  "geometry": {"coordinates":[-1.9953839779,51.3517799377],"type":"Point"}
}