{
  "type": "Feature",
  "properties": {
    "addr:full":"Homestead Farm Woodnesborough Road Sandwich Kent CT13 0NA",
    "addr:postcode":"ct13 0na",
    "addr:street":"Woodnesborough Road Sandwich",
    "iso:country":"GB",
    "sg:address":"Homestead Farm Woodnesborough Road",
    "sg:city":"Sandwich",
    "sg:classifiers":[
        {
            "category":"Wholesale",
            "subcategory":"Fruits & Vegetables",
            "type":"Manufacturing & Wholesale Goods"
        }
    ],
    "sg:postcode":"CT13 0NA",
    "sg:province":"Kent",
    "wof:name":"Langmead Morgan",
    "wof:placetype":"venue"
},
  "geometry": {"coordinates":[1.3343299627,51.273765564],"type":"Point"}
}