{
  "type": "Feature",
  "properties": {
    "addr:full":"36 Swanley Centre Swanley Kent BR8 7TL",
    "addr:housenumber":"36",
    "addr:postcode":"br8 7tl",
    "addr:street":"Swanley Centre",
    "iso:country":"GB",
    "sg:address":"36 Swanley Centre",
    "sg:city":"Swanley",
    "sg:classifiers":[
        {
            "category":"Shopping",
            "subcategory":"Mobile Phones",
            "type":"Retail Goods"
        }
    ],
    "sg:phone":"+44 1322 662303",
    "sg:postcode":"BR8 7TL",
    "sg:province":"Kent",
    "wof:name":"I H Electrical Co. Ltd.",
    "wof:placetype":"venue"
},
  "geometry": {"coordinates":[0.1793379933,51.3981323242],"type":"Point"}
}