{
  "type": "Feature",
  "properties": {
    "iso:country":"GB",
    "sg:address":"27 Chapelfields, Ardingly Rd, Cuckfield",
    "sg:city":"Haywards Heath",
    "sg:classifiers":[
        {
            "category":"Health Services",
            "subcategory":"Health Practitioner",
            "type":"Services"
        },
        {
            "category":"Shopping",
            "subcategory":"Pharmacy",
            "type":"Retail Goods"
        }
    ],
    "sg:phone":"+44 1444 417198",
    "sg:postcode":"RH17 5JR",
    "sg:province":"East Sussex",
    "sg:tags":[
        "medicine",
        "medical",
        "therapy",
        "treatment",
        "alternative"
    ],
    "wof:name":"Triangle Healing Trust",
    "wof:placetype":"venue"
},
  "geometry": {"coordinates":[-0.1406289935,51.0108146667],"type":"Point"}
}