{
  "type": "Feature",
  "properties": {
    "addr:full":"763 Wandsworth Rd South Lambeth Greater London SW8 3JG",
    "addr:housenumber":"763",
    "addr:postcode":"sw8 3jg",
    "addr:street":"Wandsworth Rd",
    "iso:country":"GB",
    "sg:address":"763 Wandsworth Rd",
    "sg:city":"South Lambeth",
    "sg:classifiers":[
        {
            "category":"Home & Garden",
            "subcategory":"Household Appliances",
            "type":"Retail Goods"
        }
    ],
    "sg:phone":"+44 20 7627 8585",
    "sg:postcode":"SW8 3JG",
    "sg:province":"Greater London",
    "sg:tags":[
        "electrical"
    ],
    "wof:name":"A M C Refrigeration",
    "wof:placetype":"venue"
},
  "geometry": {"coordinates":[-0.1466919929,51.4670829773],"type":"Point"}
}