{
  "type": "Feature",
  "properties": {
    "addr:full":"Sheepbridge Site, Dunston Rd Chesterfield Derbyshire S41 9QD",
    "addr:postcode":"s41 9qd",
    "addr:street":"Dunston Rd",
    "iso:country":"GB",
    "sg:address":"Sheepbridge Site, Dunston Rd",
    "sg:city":"Chesterfield",
    "sg:classifiers":[
        {
            "category":"Utilities",
            "subcategory":"Fuel Oil & Lpg",
            "type":"Services"
        }
    ],
    "sg:phone":"+44 1246 222036",
    "sg:postcode":"S41 9QD",
    "sg:province":"Derbyshire",
    "wof:name":"G.S Hepworth",
    "wof:placetype":"venue"
},
  "geometry": {"coordinates":[-1.4438290596,53.268283844],"type":"Point"}
}