{
  "type": "Feature",
  "properties": {
    "iso:country":"GB",
    "sg:address":"6 Riley Road, Telford Way Industrial Estate",
    "sg:city":"Kettering",
    "sg:classifiers":[
        {
            "category":"Real Estate",
            "subcategory":"Surveying",
            "type":"Services"
        }
    ],
    "sg:phone":"+44 1536 483400",
    "sg:postcode":"NN16 8NN",
    "sg:province":"Northamptonshire",
    "sg:tags":[
        "surveyor",
        "valuer"
    ],
    "wof:name":"Budworth Brown Ltd",
    "wof:placetype":"venue"
},
  "geometry": {"coordinates":[-0.744849,52.410023],"type":"Point"}
}