{
  "type": "Feature",
  "properties": {
    "iso:country":"GB",
    "sg:address":"24 Railway Terrace",
    "sg:city":"Derby",
    "sg:classifiers":[
        {
            "category":"Bars & Pubs",
            "type":"Food & Drink"
        }
    ],
    "sg:phone":"+44 1332 341274",
    "sg:postcode":"DE1 2RU",
    "sg:province":"Derbyshire",
    "sg:tags":[
        "pubs",
        "inn"
    ],
    "wof:name":"The Merry Widows",
    "wof:placetype":"venue"
},
  "geometry": {"coordinates":[-1.46410501,52.9164085388],"type":"Point"}
}