{
  "type": "Feature",
  "properties": {
    "addr:full":"Long Lane, Tuxford Newark Nottinghamshire NG22 0LS",
    "addr:postcode":"ng22 0ls",
    "addr:street":"Long Lane",
    "iso:country":"GB",
    "sg:address":"Long Lane, Tuxford",
    "sg:city":"Newark",
    "sg:classifiers":[
        {
            "category":"Freight",
            "type":"Transportation"
        }
    ],
    "sg:phone":"+44 1777 870100",
    "sg:postcode":"NG22 0LS",
    "sg:province":"Nottinghamshire",
    "sg:tags":[
        "haulage",
        "road"
    ],
    "wof:name":"Caricare",
    "wof:placetype":"venue"
},
  "geometry": {"coordinates":[-0.901314,53.231091],"type":"Point"}
}