{
  "type": "Feature",
  "properties": {
    "addr:full":"1 Cromwell Road London Greater London SW7 2HR",
    "addr:housenumber":"1",
    "addr:postcode":"sw7 2hr",
    "addr:street":"Cromwell Road",
    "iso:country":"GB",
    "sg:address":"1 Cromwell Road",
    "sg:city":"London",
    "sg:classifiers":[
        {
            "category":"Government",
            "subcategory":"Embassy",
            "type":"Public Place"
        }
    ],
    "sg:phone":"+44 20 7584 4206",
    "sg:postcode":"SW7 2HR",
    "sg:province":"Greater London",
    "sg:tags":[
        "consulate"
    ],
    "wof:name":"Venezuelan Embassy",
    "wof:placetype":"venue"
},
  "geometry": {"coordinates":[-0.174622,51.494858],"type":"Point"}
}