{
  "type": "Feature",
  "properties": {
    "addr:full":"Barley Hall, 2 Coffee Yard York North Yorkshire YO1 8AR",
    "addr:housenumber":"2",
    "addr:postcode":"yo1 8ar",
    "addr:street":"Coffee Yard",
    "iso:country":"GB",
    "sg:address":"Barley Hall, 2 Coffee Yard",
    "sg:city":"York",
    "sg:classifiers":[
        {
            "category":"Landmark",
            "subcategory":"Tourist Attraction",
            "type":"Public Place"
        }
    ],
    "sg:phone":"+44 1904 610275",
    "sg:postcode":"YO1 8AR",
    "sg:province":"North Yorkshire",
    "sg:tags":[
        "interest"
    ],
    "wof:name":"The Barley Hall Trust Ltd.",
    "wof:placetype":"venue"
},
  "geometry": {"coordinates":[-1.08281,53.960892],"type":"Point"}
}