{
  "type": "Feature",
  "properties": {
    "iso:country":"GB",
    "sg:address":"269 Watford Road",
    "sg:city":"Harrow",
    "sg:classifiers":[
        {
            "category":"Building & Trades",
            "subcategory":"Landscaping Services",
            "type":"Services"
        }
    ],
    "sg:phone":"+44 20 8423 0208",
    "sg:postcode":"HA1 3TS",
    "sg:province":"Greater London",
    "sg:tags":[
        "pond",
        "aquarium"
    ],
    "wof:name":"Harrow Koi Co",
    "wof:placetype":"venue"
},
  "geometry": {"coordinates":[-0.324661,51.572739],"type":"Point"}
}