{
  "type": "Feature",
  "properties": {
    "iso:country":"GB",
    "sg:address":"2 Kinsall Green, Wilnecote",
    "sg:city":"Tamworth",
    "sg:classifiers":[
        {
            "category":"Building & Trades",
            "subcategory":"Construction",
            "type":"Services"
        }
    ],
    "sg:phone":"+44 1827 260600",
    "sg:postcode":"B77 5PX",
    "sg:province":"Staffordshire",
    "sg:tags":[
        "builder"
    ],
    "wof:name":"Redrow Homes (Midlands) Ltd.",
    "wof:placetype":"venue"
},
  "geometry": {"coordinates":[-1.642839,52.605225],"type":"Point"}
}