{
  "type": "Feature",
  "properties": {
    "addr:full":"12 Union Street Ryde Isle of Wight PO33 2DU",
    "addr:housenumber":"12",
    "addr:postcode":"po33 2du",
    "addr:street":"Union Street",
    "iso:country":"GB",
    "sg:address":"12 Union Street",
    "sg:city":"Ryde",
    "sg:classifiers":[
        {
            "category":"Restaurant",
            "type":"Food & Drink"
        }
    ],
    "sg:phone":"+44 1983 613018",
    "sg:postcode":"PO33 2DU",
    "sg:province":"Isle of Wight",
    "wof:name":"Thumbs Up",
    "wof:placetype":"venue"
},
  "geometry": {"coordinates":[-1.161458,50.731686],"type":"Point"}
}