{
  "type": "Feature",
  "properties": {
    "addr:full":"74 Coventry St, Southam Leamington Spa Warwickshire CV33 0EA",
    "addr:housenumber":"74",
    "addr:postcode":"cv33 0ea",
    "addr:street":"Coventry St",
    "iso:country":"GB",
    "sg:address":"74 Coventry St, Southam",
    "sg:city":"Leamington Spa",
    "sg:classifiers":[
        {
            "category":"Professional",
            "subcategory":"Accounting & Tax Preparation",
            "type":"Services"
        }
    ],
    "sg:phone":"+44 1926 813320",
    "sg:postcode":"CV33 0EA",
    "sg:province":"Warwickshire",
    "sg:tags":[
        "accountant"
    ],
    "wof:name":"Alan Bradley Chartered Accountants",
    "wof:placetype":"venue"
},
  "geometry": {"coordinates":[-1.3845499754,52.2508888245],"type":"Point"}
}