{
  "type": "Feature",
  "properties": {
    "iso:country":"GB",
    "sg:address":"Woodbine Cottage, Low Street, Gringley On The Hill",
    "sg:city":"Doncaster",
    "sg:classifiers":[
        {
            "category":"Building & Trades",
            "subcategory":"Construction",
            "type":"Services"
        }
    ],
    "sg:phone":"+44 1777 817630",
    "sg:postcode":"DN10 4RZ",
    "sg:province":"Lincolnshire",
    "sg:tags":[
        "builder"
    ],
    "wof:name":"Ronald Albert Arkless",
    "wof:placetype":"venue"
},
  "geometry": {"coordinates":[-0.886663,53.409229],"type":"Point"}
}