{
  "type": "Feature",
  "properties": {
    "iso:country":"GB",
    "sg:address":"31 Brookside",
    "sg:city":"Hinckley",
    "sg:classifiers":[
        {
            "category":"Cinema",
            "subcategory":"Movie Rental",
            "type":"Entertainment"
        }
    ],
    "sg:phone":"+44 1455 634131",
    "sg:postcode":"LE10 2TG",
    "sg:province":"Leicestershire",
    "sg:tags":[
        "video",
        "library"
    ],
    "wof:name":"Select Games",
    "wof:placetype":"venue"
},
  "geometry": {"coordinates":[-1.371103,52.533318],"type":"Point"}
}