{
  "type": "Feature",
  "properties": {
    "iso:country":"GB",
    "sg:address":"John Radcliffe Hospital, Headley Way, Headington",
    "sg:city":"Oxford",
    "sg:classifiers":[
        {
            "category":"Health Services",
            "subcategory":"Hospital",
            "type":"Services"
        },
        {
            "category":"Education",
            "subcategory":"University",
            "type":"Public Place"
        }
    ],
    "sg:phone":"+44 1865 222443",
    "sg:postcode":"OX3 9DS",
    "sg:province":"Oxfordshire",
    "sg:tags":[
        "activties"
    ],
    "sg:website":"http://www.imm.ox.ac.uk",
    "wof:name":"Wetherall Institute Of Molecular Medicine",
    "wof:placetype":"venue"
},
  "geometry": {"coordinates":[-1.2183790207,51.7578353882],"type":"Point"}
}