{
  "type": "Feature",
  "properties": {
    "addr:full":"Wirksworth Health Centre, St. Johns St Matlock Derbyshire DE4 4DR",
    "addr:postcode":"de4 4dr",
    "addr:street":"Centre;St",
    "iso:country":"GB",
    "sg:address":"Wirksworth Health Centre, St. Johns St",
    "sg:city":"Matlock",
    "sg:classifiers":[
        {
            "category":"Health Services",
            "subcategory":"Doctor",
            "type":"Services"
        }
    ],
    "sg:phone":"+44 1629 822178",
    "sg:postcode":"DE4 4DR",
    "sg:province":"Derbyshire",
    "sg:tags":[
        "practitioners"
    ],
    "wof:name":"Lindop, A",
    "wof:placetype":"venue"
},
  "geometry": {"coordinates":[-1.570915,53.090565],"type":"Point"}
}