{
  "type": "Feature",
  "properties": {
    "iso:country":"GB",
    "sg:address":"Tithebarn Street",
    "sg:city":"Preston",
    "sg:classifiers":[
        {
            "category":"Parking",
            "type":"Transportation"
        }
    ],
    "sg:phone":"+44 1772 887755",
    "sg:postcode":"PR1 1YT",
    "sg:province":"Lancashire",
    "sg:tags":[
        "car",
        "park"
    ],
    "wof:name":"Bus Station and Car Parks",
    "wof:placetype":"venue"
},
  "geometry": {"coordinates":[-2.6973190308,53.7616539001],"type":"Point"}
}