{
  "type": "Feature",
  "properties": {
    "iso:country":"GB",
    "sg:address":"4-6 Cheapside",
    "sg:city":"Barnsley",
    "sg:classifiers":[
        {
            "category":"Shopping",
            "subcategory":"Comic Books",
            "type":"Retail Goods"
        }
    ],
    "sg:phone":"+44 1226 771085",
    "sg:postcode":"S70 1RR",
    "sg:province":"South Yorkshire",
    "sg:tags":[
        "jeweller",
        "sale",
        "jewellery"
    ],
    "wof:name":"Ernest Jones Ltd",
    "wof:placetype":"venue"
},
  "geometry": {"coordinates":[-1.4799040556,53.5522193909],"type":"Point"}
}