{
  "type": "Feature",
  "properties": {
    "addr:full":"Lowbridge Farm, Rushock Droitwich Worcestershire WR9 0NN",
    "addr:postcode":"wr9 0nn",
    "iso:country":"GB",
    "sg:address":"Lowbridge Farm, Rushock",
    "sg:city":"Droitwich",
    "sg:classifiers":[
        {
            "category":"Farming",
            "subcategory":"Livestock Farm",
            "type":"Manufacturing & Wholesale Goods"
        }
    ],
    "sg:postcode":"WR9 0NN",
    "sg:province":"Worcestershire",
    "sg:tags":[
        "others"
    ],
    "wof:name":"Wilson & Sons",
    "wof:placetype":"venue"
},
  "geometry": {"coordinates":[-2.172187,52.338905],"type":"Point"}
}