{
  "type": "Feature",
  "properties": {
    "iso:country":"GB",
    "sg:address":"44 Pk St",
    "sg:city":"Brighouse",
    "sg:classifiers":[
        {
            "category":"Home & Garden",
            "subcategory":"Home Furnishings",
            "type":"Retail Goods"
        }
    ],
    "sg:postcode":"HD6 1JL",
    "sg:province":"West Yorkshire",
    "sg:tags":[
        "wall",
        "wallpaper",
        "covering"
    ],
    "wof:name":"Brighouse Colour Centre",
    "wof:placetype":"venue"
},
  "geometry": {"coordinates":[-1.773737,53.702194],"type":"Point"}
}