{
  "type": "Feature",
  "properties": {
    "addr:full":"Rear Of 33 Kingston Road Staines Berkshire TW18 4LH",
    "addr:housenumber":"rear of 33",
    "addr:postcode":"tw18 4lh",
    "addr:street":"Kingston Road",
    "iso:country":"GB",
    "sg:address":"Rear Of 33 Kingston Road",
    "sg:city":"Staines",
    "sg:classifiers":[
        {
            "category":"Health Services",
            "subcategory":"Dentist",
            "type":"Services"
        }
    ],
    "sg:phone":"+44 1784 455034",
    "sg:postcode":"TW18 4LH",
    "sg:province":"Berkshire",
    "sg:tags":[
        "technician",
        "dental"
    ],
    "wof:name":"Portmore Dental Laboratory",
    "wof:placetype":"venue"
},
  "geometry": {"coordinates":[-0.5066040158,51.4351615906],"type":"Point"}
}