{
  "type": "Feature",
  "properties": {
    "addr:full":"3-13 Chelsea Harbour Design Centre, Chelsea Harbour London Greater London SW10 0XE",
    "addr:housenumber":"3-13",
    "addr:postcode":"sw10 0xe",
    "iso:country":"GB",
    "sg:address":"3-13 Chelsea Harbour Design Centre, Chelsea Harbour",
    "sg:city":"London",
    "sg:classifiers":[
        {
            "category":"Wholesale",
            "subcategory":"Home Furnishings",
            "type":"Manufacturing & Wholesale Goods"
        }
    ],
    "sg:phone":"+44 20 7349 8835",
    "sg:postcode":"SW10 0XE",
    "sg:province":"Greater London",
    "sg:tags":[
        "wsale",
        "rug",
        "carpet"
    ],
    "wof:name":"Carpet Design Studio Ltd.",
    "wof:placetype":"venue"
},
  "geometry": {"coordinates":[-0.1831250042,51.4756774902],"type":"Point"}
}