{
  "type": "Feature",
  "properties": {
    "addr:full":"Simonswood House, Newton Gardens Liverpool Merseyside L32 8RN",
    "addr:postcode":"l32 8rn",
    "addr:street":"Newton Gardens",
    "iso:country":"GB",
    "sg:address":"Simonswood House, Newton Gardens",
    "sg:city":"Liverpool",
    "sg:classifiers":[
        {
            "category":"Government",
            "subcategory":"Post Office",
            "type":"Public Place"
        }
    ],
    "sg:phone":"+44 151 722 3344",
    "sg:postcode":"L32 8RN",
    "sg:province":"Merseyside",
    "wof:name":"Kirkby Post Office",
    "wof:placetype":"venue"
},
  "geometry": {"coordinates":[-2.886419,53.481216],"type":"Point"}
}