{
  "type": "Feature",
  "properties": {
    "iso:country":"GB",
    "sg:address":"11 Derwent Avenue, North Ferriby",
    "sg:city":"Hull",
    "sg:classifiers":[
        {
            "category":"Professional",
            "subcategory":"Engineering",
            "type":"Services"
        }
    ],
    "sg:postcode":"HU14 3DZ",
    "sg:province":"East Riding of Yorkshire",
    "sg:tags":[
        "contractor",
        "electrical",
        "engineer"
    ],
    "wof:name":"P G Electrical Services",
    "wof:placetype":"venue"
},
  "geometry": {"coordinates":[-0.510609,53.715328],"type":"Point"}
}