{
  "type": "Feature",
  "properties": {
    "addr:full":"5 Barton Close North Shields Tyne and Wear NE30 2TG",
    "addr:housenumber":"5",
    "addr:postcode":"ne30 2tg",
    "addr:street":"Barton Close",
    "iso:country":"GB",
    "sg:address":"5 Barton Close",
    "sg:city":"North Shields",
    "sg:classifiers":[
        {
            "category":"Professional",
            "subcategory":"Art Services",
            "type":"Services"
        }
    ],
    "sg:phone":"+44 191 272 8876",
    "sg:postcode":"NE30 2TG",
    "sg:province":"Tyne and Wear",
    "sg:tags":[
        "graphic",
        "designer"
    ],
    "wof:name":"John Spoors Associates",
    "wof:placetype":"venue"
},
  "geometry": {"coordinates":[-1.443395,55.024563],"type":"Point"}
}