{
  "type": "Feature",
  "properties": {
    "iso:country":"GB",
    "sg:address":"45 Lunsford Lane, Larkfield",
    "sg:city":"Aylesford",
    "sg:classifiers":[
        {
            "category":"Professional",
            "subcategory":"Business Services",
            "type":"Services"
        }
    ],
    "sg:phone":"+44 1732 840657",
    "sg:postcode":"ME20 6HN",
    "sg:province":"Kent",
    "sg:tags":[
        "shop",
        "cleaning"
    ],
    "wof:name":"V.I.P Cleaning",
    "wof:placetype":"venue"
},
  "geometry": {"coordinates":[0.431046,51.299805],"type":"Point"}
}