{
  "type": "Feature",
  "properties": {
    "addr:full":"36/37 Fore Street Newquay Cornwall TR7 1HD",
    "addr:housenumber":"36 / 37",
    "addr:postcode":"tr7 1hd",
    "addr:street":"Fore Street",
    "iso:country":"GB",
    "sg:address":"36/37 Fore Street",
    "sg:city":"Newquay",
    "sg:classifiers":[
        {
            "category":"Wholesale",
            "subcategory":"Office Equipment",
            "type":"Manufacturing & Wholesale Goods"
        },
        {
            "category":"Shopping",
            "subcategory":"Bicycles & Sporting Goods",
            "type":"Retail Goods"
        }
    ],
    "sg:phone":"+44 1637 872341",
    "sg:postcode":"TR7 1HD",
    "sg:province":"Cornwall",
    "sg:tags":[
        "hire",
        "outdoor",
        "leisure",
        "activity"
    ],
    "wof:name":"Sunny Days",
    "wof:placetype":"venue"
},
  "geometry": {"coordinates":[-5.087095,50.415016],"type":"Point"}
}