{
  "type": "Feature",
  "properties": {
    "iso:country":"GB",
    "sg:address":"1 New Mill Street",
    "sg:city":"Dudley",
    "sg:classifiers":[
        {
            "category":"Building & Trades",
            "subcategory":"Plumbing",
            "type":"Services"
        }
    ],
    "sg:phone":"+44 1384 255172",
    "sg:postcode":"DY2 8PB",
    "sg:province":"West Midlands",
    "sg:tags":[
        "merchant",
        "plumbers'"
    ],
    "wof:name":"C J Smith Handyman Warehouse",
    "wof:placetype":"venue"
},
  "geometry": {"coordinates":[-2.083418,52.50906],"type":"Point"}
}