{
  "type": "Feature",
  "properties": {
    "iso:country":"GB",
    "sg:address":"Unit 42 Farriers Way Industrial Estate, Netherton",
    "sg:city":"Bootle",
    "sg:classifiers":[
        {
            "category":"Freight",
            "type":"Transportation"
        }
    ],
    "sg:phone":"+44 151 521 1662",
    "sg:postcode":"L30 4XL",
    "sg:province":"Merseyside",
    "sg:tags":[
        "forwarders"
    ],
    "wof:name":"Glenn Freight Services Ltd.",
    "wof:placetype":"venue"
},
  "geometry": {"coordinates":[-2.9698269367,53.4734230042],"type":"Point"}
}