{
  "type": "Feature",
  "properties": {
    "addr:full":"5 St Nicholas Close, Dersingham King's Lynn Norfolk PE31 6LT",
    "addr:housenumber":"5",
    "addr:postcode":"pe31 6lt",
    "addr:street":"St Nicholas Close;Lynn",
    "iso:country":"GB",
    "sg:address":"5 St Nicholas Close, Dersingham",
    "sg:city":"King's Lynn",
    "sg:classifiers":[
        {
            "category":"Professional",
            "subcategory":"Detective & Security Services",
            "type":"Services"
        }
    ],
    "sg:postcode":"PE31 6LT",
    "sg:province":"Norfolk",
    "sg:tags":[
        "alarm",
        "burglar",
        "system"
    ],
    "wof:name":"Shield Security Systems",
    "wof:placetype":"venue"
},
  "geometry": {"coordinates":[0.50852,52.8442],"type":"Point"}
}