{
  "type": "Feature",
  "properties": {
    "iso:country":"GB",
    "sg:address":"11 Orchard Close, Wenvoe",
    "sg:city":"Cardiff",
    "sg:classifiers":[
        {
            "category":"Professional",
            "subcategory":"Management & Consulting",
            "type":"Services"
        }
    ],
    "sg:postcode":"CF5 6BW",
    "sg:province":"Cardiff",
    "sg:tags":[
        "consultant",
        "business"
    ],
    "wof:name":"Anning Associates Ltd",
    "wof:placetype":"venue"
},
  "geometry": {"coordinates":[-3.267342,51.449268],"type":"Point"}
}