{
  "type": "Feature",
  "properties": {
    "addr:full":"1 South Lake Pde, Kingfisher Dr Reading Berkshire RG5 3SJ",
    "addr:housenumber":"1",
    "addr:postcode":"rg5 3sj",
    "addr:street":"South Lake;Kingfisher Dr",
    "iso:country":"GB",
    "sg:address":"1 South Lake Pde, Kingfisher Dr",
    "sg:city":"Reading",
    "sg:classifiers":[
        {
            "category":"Personal",
            "subcategory":"Beauty Salon",
            "type":"Services"
        }
    ],
    "sg:phone":"+44 118 926 0798",
    "sg:postcode":"RG5 3SJ",
    "sg:province":"Berkshire",
    "sg:tags":[
        "unisex",
        "hairdresser"
    ],
    "wof:name":"Flair's Unisex Salon",
    "wof:placetype":"venue"
},
  "geometry": {"coordinates":[-0.901363,51.446438],"type":"Point"}
}