{
  "type": "Feature",
  "properties": {
    "addr:full":"Junction Road, Norton Stockton-on-tees Durham TS20 1SU",
    "addr:postcode":"ts20 1su",
    "addr:street":"Junction Road",
    "iso:country":"GB",
    "sg:address":"Junction Road, Norton",
    "sg:city":"Stockton-on-tees",
    "sg:classifiers":[
        {
            "category":"Bars & Pubs",
            "type":"Food & Drink"
        }
    ],
    "sg:phone":"+44 1642 612452",
    "sg:postcode":"TS20 1SU",
    "sg:province":"Durham",
    "sg:tags":[
        "pubs",
        "inn"
    ],
    "wof:name":"Harpers",
    "wof:placetype":"venue"
},
  "geometry": {"coordinates":[-1.313929,54.592335],"type":"Point"}
}