{
  "type": "Feature",
  "properties": {
    "addr:full":"School House, The Butts Alston Cumbria CA9 3JQ",
    "addr:postcode":"ca9 3jq",
    "addr:street":"School;The Butts",
    "iso:country":"GB",
    "sg:address":"School House, The Butts",
    "sg:city":"Alston",
    "sg:classifiers":[
        {
            "category":"Retail",
            "subcategory":"Repair Shop",
            "type":"Services"
        },
        {
            "category":"Manufacturing",
            "subcategory":"Furniture",
            "type":"Manufacturing & Wholesale Goods"
        }
    ],
    "sg:phone":"+44 1434 381604",
    "sg:postcode":"CA9 3JQ",
    "sg:province":"Cumbria",
    "sg:tags":[
        "mnfr",
        "upholstering",
        "upholsterer"
    ],
    "wof:name":"J R Paine",
    "wof:placetype":"venue"
},
  "geometry": {"coordinates":[-2.438751936,54.8123817444],"type":"Point"}
}