{
  "type": "Feature",
  "properties": {
    "iso:country":"GB",
    "sg:address":"51 The Park, Great Bookham",
    "sg:city":"Leatherhead",
    "sg:classifiers":[
        {
            "category":"Home & Garden",
            "subcategory":"Household Appliances",
            "type":"Retail Goods"
        }
    ],
    "sg:postcode":"KT23 3LN",
    "sg:province":"Surrey",
    "sg:tags":[
        "electrical"
    ],
    "wof:name":"Dytchley Ltd.",
    "wof:placetype":"venue"
},
  "geometry": {"coordinates":[-0.37584,51.28685],"type":"Point"}
}