{
  "type": "Feature",
  "properties": {
    "addr:full":"41 Peel Road Bootle Merseyside L20 4RL",
    "addr:housenumber":"41",
    "addr:postcode":"l20 4rl",
    "addr:street":"Peel Road",
    "iso:country":"GB",
    "sg:address":"41 Peel Road",
    "sg:city":"Bootle",
    "sg:classifiers":[
        {
            "category":"Shopping",
            "subcategory":"Department Store",
            "type":"Retail Goods"
        },
        {
            "category":"Food & Beverages",
            "subcategory":"Groceries & Convenience Stores",
            "type":"Retail Goods"
        }
    ],
    "sg:phone":"+44 151 922 5768",
    "sg:postcode":"L20 4RL",
    "sg:province":"Merseyside",
    "wof:name":"Mo's Mini Market",
    "wof:placetype":"venue"
},
  "geometry": {"coordinates":[-3.0056080818,53.4580192566],"type":"Point"}
}