{
  "type": "Feature",
  "properties": {
    "iso:country":"GB",
    "sg:address":"Grampian House, 144 Deansgate",
    "sg:city":"Manchester",
    "sg:classifiers":[
        {
            "category":"Insurance",
            "subcategory":"Insurance Agent",
            "type":"Services"
        }
    ],
    "sg:postcode":"M3 3EE",
    "sg:province":"Greater Manchester",
    "wof:name":"Salford Properties Ltd.",
    "wof:placetype":"venue"
},
  "geometry": {"coordinates":[-2.2485289574,53.4800796509],"type":"Point"}
}