{
  "type": "Feature",
  "properties": {
    "iso:country":"GB",
    "sg:address":"Gownfold Farm, Kirdford",
    "sg:city":"Billingshurst",
    "sg:classifiers":[
        {
            "category":"Farming",
            "subcategory":"Livestock Farm",
            "type":"Manufacturing & Wholesale Goods"
        }
    ],
    "sg:phone":"+44 1403 820286",
    "sg:postcode":"RH14 0LW",
    "sg:province":"West Sussex",
    "sg:tags":[
        "others"
    ],
    "wof:name":"John Treadwell",
    "wof:placetype":"venue"
},
  "geometry": {"coordinates":[-0.552624,51.032429],"type":"Point"}
}