{
  "type": "Feature",
  "properties": {
    "addr:full":"Bod Gynda Farm Brynteg Isle of Anglesey LL78 7JJ",
    "addr:postcode":"ll78 7jj",
    "iso:country":"GB",
    "sg:address":"Bod Gynda Farm",
    "sg:city":"Brynteg",
    "sg:classifiers":[
        {
            "category":"Farming",
            "subcategory":"Livestock Farm",
            "type":"Manufacturing & Wholesale Goods"
        },
        {
            "category":"Farming",
            "subcategory":"Farm",
            "type":"Manufacturing & Wholesale Goods"
        }
    ],
    "sg:phone":"+44 1248 852385",
    "sg:postcode":"LL78 7JJ",
    "sg:province":"Isle of Anglesey",
    "sg:tags":[
        "mixed",
        "crop",
        "others"
    ],
    "wof:name":"Robert Morgan & Sons",
    "wof:placetype":"venue"
},
  "geometry": {"coordinates":[-4.2594590187,53.319606781],"type":"Point"}
}