{
  "type": "Feature",
  "properties": {
    "addr:full":"Unit 5 Elphinstone Road Tranent East Lothian EH33 2LG",
    "addr:housenumber":"unit 5",
    "addr:postcode":"eh33 2lg",
    "addr:street":"Elphinstone Road",
    "iso:country":"GB",
    "sg:address":"Unit 5 Elphinstone Road",
    "sg:city":"Tranent",
    "sg:classifiers":[
        {
            "category":"Building & Trades",
            "subcategory":"Construction",
            "type":"Services"
        }
    ],
    "sg:phone":"+44 1875 615000",
    "sg:postcode":"EH33 2LG",
    "sg:province":"East Lothian",
    "sg:tags":[
        "builder"
    ],
    "wof:name":"Dunedin Waugh",
    "wof:placetype":"venue"
},
  "geometry": {"coordinates":[-2.962545,55.941975],"type":"Point"}
}