{
  "type": "Feature",
  "properties": {
    "iso:country":"GB",
    "sg:address":"Kite Close",
    "sg:city":"Waterlooville",
    "sg:classifiers":[
        {
            "category":"Organizations",
            "subcategory":"Religious Organization",
            "type":"Services"
        }
    ],
    "sg:phone":"+44 23 9225 5288",
    "sg:postcode":"PO8 9UJ",
    "sg:province":"Hampshire",
    "sg:tags":[
        "organisation",
        "place",
        "worship"
    ],
    "wof:name":"Living Waters Fellowship",
    "wof:placetype":"venue"
},
  "geometry": {"coordinates":[-1.0302590132,50.9013786316],"type":"Point"}
}