{
  "type": "Feature",
  "properties": {
    "iso:country":"GB",
    "sg:address":"Bromley Business Centre",
    "sg:city":"Bromley",
    "sg:classifiers":[
        {
            "category":"Building & Trades",
            "subcategory":"Construction",
            "type":"Services"
        }
    ],
    "sg:phone":"+44 20 8313 9992",
    "sg:postcode":"BR1 1QW",
    "sg:province":"Kent",
    "sg:tags":[
        "conversion",
        "loft"
    ],
    "wof:name":"Metropolitan Home Improvements",
    "wof:placetype":"venue"
},
  "geometry": {"coordinates":[0.014928,51.4057006836],"type":"Point"}
}