{
  "type": "Feature",
  "properties": {
    "addr:full":"8-10 Northway Scarborough North Yorkshire YO11 1JL",
    "addr:housenumber":"8-10",
    "addr:postcode":"yo11 1jl",
    "addr:street":"Northway",
    "iso:country":"GB",
    "sg:address":"8-10 Northway",
    "sg:city":"Scarborough",
    "sg:classifiers":[
        {
            "category":"Personal",
            "subcategory":"Beauty Salon",
            "type":"Services"
        },
        {
            "category":"Personal",
            "subcategory":"Barber",
            "type":"Services"
        }
    ],
    "sg:phone":"+44 1723 371750",
    "sg:postcode":"YO11 1JL",
    "sg:province":"North Yorkshire",
    "sg:tags":[
        "unisex",
        "hairdresser"
    ],
    "wof:name":"Jones Hairstylist",
    "wof:placetype":"venue"
},
  "geometry": {"coordinates":[-0.4057599902,54.2805633545],"type":"Point"}
}