{
  "type": "Feature",
  "properties": {
    "addr:full":"Loggerheads, Ruthin Road Mold Denbighshire CH7 5LH",
    "addr:postcode":"ch7 5lh",
    "addr:street":"Ruthin Road",
    "iso:country":"GB",
    "sg:address":"Loggerheads, Ruthin Road",
    "sg:city":"Mold",
    "sg:classifiers":[
        {
            "category":"Government",
            "subcategory":"Office",
            "type":"Public Place"
        },
        {
            "category":"Landmark",
            "subcategory":"Tourist Attraction",
            "type":"Public Place"
        }
    ],
    "sg:phone":"+44 1352 810614",
    "sg:postcode":"CH7 5LH",
    "sg:province":"Denbighshire",
    "sg:tags":[
        "local",
        "interest"
    ],
    "wof:name":"Loggerheads Country Park",
    "wof:placetype":"venue"
},
  "geometry": {"coordinates":[-3.139984,53.163868],"type":"Point"}
}