{
  "type": "Feature",
  "properties": {
    "iso:country":"GB",
    "sg:address":"15 Churchill Crescent",
    "sg:city":"Farnborough",
    "sg:classifiers":[
        {
            "category":"Shopping",
            "subcategory":"Pharmacy",
            "type":"Retail Goods"
        }
    ],
    "sg:phone":"+44 1252 543781",
    "sg:postcode":"GU14 8EL",
    "sg:province":"Hampshire",
    "sg:tags":[
        "pharmacist",
        "chemist"
    ],
    "wof:name":"Churchill Pharmacy",
    "wof:placetype":"venue"
},
  "geometry": {"coordinates":[-0.7575259805,51.3102455139],"type":"Point"}
}