{
  "type": "Feature",
  "properties": {
    "iso:country":"GB",
    "sg:address":"Ellwood House, The Roe",
    "sg:city":"St Asaph",
    "sg:classifiers":[
        {
            "category":"Retail",
            "subcategory":"Veterinary Services",
            "type":"Services"
        }
    ],
    "sg:phone":"+44 1745 584680",
    "sg:postcode":"LL17 0LT",
    "sg:province":"Conwy",
    "sg:tags":[
        "surgeon",
        "activity"
    ],
    "wof:name":"W T Pritchard",
    "wof:placetype":"venue"
},
  "geometry": {"coordinates":[-3.455794,53.267296],"type":"Point"}
}