{
  "type": "Feature",
  "properties": {
    "addr:full":"Arvon Avenue Llandudno Conwy LL30 2DY",
    "addr:postcode":"ll30 2dy",
    "addr:street":"Arvon Avenue",
    "iso:country":"GB",
    "sg:address":"Arvon Avenue",
    "sg:city":"Llandudno",
    "sg:classifiers":[
        {
            "category":"Travel",
            "subcategory":"Hotels & Motels",
            "type":"Entertainment"
        }
    ],
    "sg:phone":"+44 1492 877056",
    "sg:postcode":"LL30 2DY",
    "sg:province":"Conwy",
    "sg:tags":[
        "house",
        "guest"
    ],
    "wof:name":"RIVIERA PRIVATE HOTEL",
    "wof:placetype":"venue"
},
  "geometry": {"coordinates":[-3.8342559338,53.3255844116],"type":"Point"}
}