{
  "type": "Feature",
  "properties": {
    "iso:country":"GB",
    "sg:address":"10 Arkwright Gate",
    "sg:city":"Andover",
    "sg:classifiers":[
        {
            "category":"Professional",
            "subcategory":"Engineering",
            "type":"Services"
        }
    ],
    "sg:phone":"+44 1264 324231",
    "sg:postcode":"SP10 3SB",
    "sg:province":"Hampshire",
    "sg:tags":[
        "precision",
        "engineer"
    ],
    "wof:name":"F G Precision Ltd.",
    "wof:placetype":"venue"
},
  "geometry": {"coordinates":[-1.517629,51.217834],"type":"Point"}
}