{
  "type": "Feature",
  "properties": {
    "addr:full":"Keeper's Cottage, Thorley Lane, Hale Barns Altrincham Cheshire WA15 8UQ",
    "addr:postcode":"wa15 8uq",
    "addr:street":"Thorley Lane",
    "iso:country":"GB",
    "sg:address":"Keeper's Cottage, Thorley Lane, Hale Barns",
    "sg:city":"Altrincham",
    "sg:classifiers":[
        {
            "category":"Building & Trades",
            "subcategory":"Construction",
            "type":"Services"
        }
    ],
    "sg:phone":"+44 161 980 7210",
    "sg:postcode":"WA15 8UQ",
    "sg:province":"Cheshire",
    "sg:tags":[
        "builder"
    ],
    "wof:name":"J & J Drinkwater",
    "wof:placetype":"venue"
},
  "geometry": {"coordinates":[-2.28874,53.372231],"type":"Point"}
}