{
  "type": "Feature",
  "properties": {
    "addr:full":"1 The Spinney, Horton Road Ringwood Dorset BH24 2EH",
    "addr:housenumber":"1",
    "addr:postcode":"bh24 2eh",
    "addr:street":"The Spinney Horton Road",
    "iso:country":"GB",
    "sg:address":"1 The Spinney, Horton Road",
    "sg:city":"Ringwood",
    "sg:classifiers":[
        {
            "category":"Professional",
            "subcategory":"Computer Services",
            "type":"Services"
        }
    ],
    "sg:phone":"+44 7768 565627",
    "sg:postcode":"BH24 2EH",
    "sg:province":"Dorset",
    "sg:tags":[
        "system",
        "software"
    ],
    "wof:name":"Pagedean Ltd.",
    "wof:placetype":"venue"
},
  "geometry": {"coordinates":[-1.8469120264,50.8315734863],"type":"Point"}
}