{
  "type": "Feature",
  "properties": {
    "iso:country":"GB",
    "sg:address":"60 Overlinks Dr",
    "sg:city":"Salford",
    "sg:classifiers":[
        {
            "category":"Retail",
            "subcategory":"Auto Repair",
            "type":"Services"
        }
    ],
    "sg:phone":"+44 161 743 1300",
    "sg:postcode":"M6 7PF",
    "sg:province":"Greater Manchester",
    "sg:tags":[
        "modification",
        "garage"
    ],
    "wof:name":"R Booth",
    "wof:placetype":"venue"
},
  "geometry": {"coordinates":[-2.3208799362,53.500202179],"type":"Point"}
}