{
  "type": "Feature",
  "properties": {
    "addr:full":"Po Box 2 Bacup Lancashire OL13 0DT",
    "addr:housenumber":"po;2",
    "addr:postcode":"ol13 0dt",
    "addr:street":"Box",
    "iso:country":"GB",
    "sg:address":"Po Box 2",
    "sg:city":"Bacup",
    "sg:classifiers":[
        {
            "category":"Professional",
            "subcategory":"Engineering",
            "type":"Services"
        }
    ],
    "sg:phone":"+44 1706 878669",
    "sg:postcode":"OL13 0DT",
    "sg:province":"Lancashire",
    "wof:name":"Waterfoot Knives Ltd.",
    "wof:placetype":"venue"
},
  "geometry": {"coordinates":[-2.231204,53.69183],"type":"Point"}
}