{
  "type": "Feature",
  "properties": {
    "iso:country":"GB",
    "sg:address":"4-6 Horsemarket",
    "sg:city":"Darlington",
    "sg:classifiers":[
        {
            "category":"Professional",
            "subcategory":"Employment Agencies",
            "type":"Services"
        }
    ],
    "sg:phone":"+44 1325 481026",
    "sg:postcode":"DL1 5QQ",
    "sg:province":"Durham",
    "sg:tags":[
        "consultant"
    ],
    "wof:name":"Liz Dargue Staffing (Darlington) Ltd.",
    "wof:placetype":"venue"
},
  "geometry": {"coordinates":[-1.548894,54.524502],"type":"Point"}
}