{
  "type": "Feature",
  "properties": {
    "addr:full":"Lyme Stadium, Loomer Road Newcastle Staffordshire ST5 7LB",
    "addr:postcode":"st5 7lb",
    "addr:street":"Loomer Road",
    "iso:country":"GB",
    "sg:address":"Lyme Stadium, Loomer Road",
    "sg:city":"Newcastle",
    "sg:classifiers":[
        {
            "category":"Sports & Exercise",
            "subcategory":"Race Track",
            "type":"Entertainment"
        }
    ],
    "sg:postcode":"ST5 7LB",
    "sg:province":"Staffordshire",
    "sg:tags":[
        "motor"
    ],
    "wof:name":"Stokeway Speedway",
    "wof:placetype":"venue"
},
  "geometry": {"coordinates":[-2.250459,53.034897],"type":"Point"}
}