{
  "type": "Feature",
  "properties": {
    "addr:full":"1 The Stiles Ormskirk Lancashire L39 3QG",
    "addr:housenumber":"1",
    "addr:postcode":"l39 3qg",
    "addr:street":"The Stiles Ormskirk",
    "iso:country":"GB",
    "sg:address":"1 The Stiles",
    "sg:city":"Ormskirk",
    "sg:classifiers":[
        {
            "category":"Arts & Performance",
            "subcategory":"Theater",
            "type":"Entertainment"
        }
    ],
    "sg:phone":"+44 1695 570258",
    "sg:postcode":"L39 3QG",
    "sg:province":"Lancashire",
    "sg:tags":[
        "theatrical",
        "agency"
    ],
    "wof:name":"Positive Management",
    "wof:placetype":"venue"
},
  "geometry": {"coordinates":[-2.885941,53.568867],"type":"Point"}
}