{
  "type": "Feature",
  "properties": {
    "iso:country":"GB",
    "sg:address":"18 Kingswood Road",
    "sg:city":"Colchester",
    "sg:classifiers":[
        {
            "category":"Shopping",
            "subcategory":"Hobbies, Toys, & Games",
            "type":"Retail Goods"
        },
        {
            "category":"Professional",
            "subcategory":"Art Services",
            "type":"Services"
        }
    ],
    "sg:postcode":"CO4 5JX",
    "sg:province":"Essex",
    "sg:tags":[
        "model",
        "toy",
        "maker"
    ],
    "wof:name":"Vernacular Miniatures",
    "wof:placetype":"venue"
},
  "geometry": {"coordinates":[0.90367,51.911098],"type":"Point"}
}