{
  "type": "Feature",
  "properties": {
    "iso:country":"GB",
    "sg:address":"Leadenhall Farm, Holbeach St Marks, Holbeach",
    "sg:city":"Spalding",
    "sg:classifiers":[
        {
            "category":"Farming",
            "subcategory":"Livestock Farm",
            "type":"Manufacturing & Wholesale Goods"
        }
    ],
    "sg:postcode":"PE12 8HB",
    "sg:province":"Cambridgeshire",
    "sg:tags":[
        "others"
    ],
    "wof:name":"J Ward & Son (Farms)",
    "wof:placetype":"venue"
},
  "geometry": {"coordinates":[0.01215,52.87373],"type":"Point"}
}