{
  "type": "Feature",
  "properties": {
    "iso:country":"GB",
    "sg:address":"Pen Isa Dre, Trofarth",
    "sg:city":"Abergele",
    "sg:classifiers":[
        {
            "category":"Farming",
            "subcategory":"Livestock Farm",
            "type":"Manufacturing & Wholesale Goods"
        }
    ],
    "sg:phone":"+44 1745 860517",
    "sg:postcode":"LL22 8BD",
    "sg:province":"Conwy",
    "sg:tags":[
        "others"
    ],
    "wof:name":"P P & M E Thomas",
    "wof:placetype":"venue"
},
  "geometry": {"coordinates":[-3.717229,53.23056],"type":"Point"}
}