{
  "type": "Feature",
  "properties": {
    "addr:full":"214-216 Kensington High Street London Greater London W8 7RG",
    "addr:housenumber":"214-216",
    "addr:postcode":"w8 7rg",
    "addr:street":"Kensington High Street",
    "iso:country":"GB",
    "sg:address":"214-216 Kensington High Street",
    "sg:city":"London",
    "sg:classifiers":[
        {
            "category":"Communications",
            "subcategory":"Film & Video Production",
            "type":"Services"
        },
        {
            "category":"Shopping",
            "subcategory":"Party Supplies",
            "type":"Retail Goods"
        }
    ],
    "sg:phone":"+44 20 7937 6500",
    "sg:postcode":"W8 7RG",
    "sg:province":"Greater London",
    "sg:tags":[
        "product",
        "novelty"
    ],
    "wof:name":"Non Stop Party Shop Ltd",
    "wof:placetype":"venue"
},
  "geometry": {"coordinates":[-0.1979469955,51.4994277954],"type":"Point"}
}