{
  "type": "Feature",
  "properties": {
    "addr:full":"Meres Visitor Centre, Mereside Ellesmere Shropshire SY12 0PA",
    "addr:postcode":"sy12 0pa",
    "addr:street":"Mereside;Shropshire",
    "iso:country":"GB",
    "sg:address":"Meres Visitor Centre, Mereside",
    "sg:city":"Ellesmere",
    "sg:classifiers":[
        {
            "category":"Landmark",
            "subcategory":"Tourist Information",
            "type":"Public Place"
        }
    ],
    "sg:phone":"+44 1691 622981",
    "sg:postcode":"SY12 0PA",
    "sg:province":"Shropshire",
    "wof:name":"Tourist Information Centre",
    "wof:placetype":"venue"
},
  "geometry": {"coordinates":[-2.8967549801,52.9076843262],"type":"Point"}
}