{
  "type": "Feature",
  "properties": {
    "addr:full":"Unit 23 Norris Way Industrial Estate, Norris Way Rushden Bedfordshire NN10 6BP",
    "addr:housenumber":"unit 23;estate",
    "addr:postcode":"nn10 6bp",
    "addr:street":"Norris Way Industrial;Norris Way",
    "iso:country":"GB",
    "sg:address":"Unit 23 Norris Way Industrial Estate, Norris Way",
    "sg:city":"Rushden",
    "sg:classifiers":[
        {
            "category":"Retail",
            "subcategory":"Auto Repair",
            "type":"Services"
        }
    ],
    "sg:phone":"+44 1933 410402",
    "sg:postcode":"NN10 6BP",
    "sg:province":"Bedfordshire",
    "sg:tags":[
        "bodybuilder",
        "repairer"
    ],
    "wof:name":"Michael A Harding",
    "wof:placetype":"venue"
},
  "geometry": {"coordinates":[-0.620637,52.298176],"type":"Point"}
}