{
  "type": "Feature",
  "properties": {
    "iso:country":"GB",
    "sg:address":"12 Regent Court, Stotfold",
    "sg:city":"Hitchin",
    "sg:classifiers":[
        {
            "category":"Shopping",
            "subcategory":"Computers & Home Electronics",
            "type":"Retail Goods"
        }
    ],
    "sg:phone":"+44 1462 730180",
    "sg:postcode":"SG5 4AJ",
    "sg:province":"Bedfordshire",
    "sg:tags":[
        "aerial",
        "television",
        "radio"
    ],
    "wof:name":"Anthony Matthews",
    "wof:placetype":"venue"
},
  "geometry": {"coordinates":[-0.226221,52.021973],"type":"Point"}
}