{
  "type": "Feature",
  "properties": {
    "addr:full":"106 Auckland Road Potters Bar Greater London EN6 3HE",
    "addr:housenumber":"106",
    "addr:postcode":"en6 3he",
    "addr:street":"Auckland Road",
    "iso:country":"GB",
    "sg:address":"106 Auckland Road",
    "sg:city":"Potters Bar",
    "sg:classifiers":[
        {
            "category":"Professional",
            "subcategory":"Detective & Security Services",
            "type":"Services"
        }
    ],
    "sg:phone":"+44 1707 647861",
    "sg:postcode":"EN6 3HE",
    "sg:province":"Greater London",
    "sg:tags":[
        "agency"
    ],
    "wof:name":"Akers Investigation Bureau Ltd.",
    "wof:placetype":"venue"
},
  "geometry": {"coordinates":[-0.204637,51.696289],"type":"Point"}
}