{
  "type": "Feature",
  "properties": {
    "iso:country":"GB",
    "sg:address":"Blockley",
    "sg:city":"Moreton-in-marsh",
    "sg:classifiers":[
        {
            "category":"Home & Garden",
            "subcategory":"Building Materials",
            "type":"Retail Goods"
        }
    ],
    "sg:phone":"+44 1386 700551",
    "sg:postcode":"GL56 9LH",
    "sg:province":"Gloucestershire",
    "sg:tags":[
        "brick"
    ],
    "wof:name":"Northcot Brick Ltd.",
    "wof:placetype":"venue"
},
  "geometry": {"coordinates":[-1.758819,52.013359],"type":"Point"}
}