{
  "type": "Feature",
  "properties": {
    "iso:country":"GB",
    "sg:address":"Main Street, Anwick",
    "sg:city":"Sleaford",
    "sg:classifiers":[
        {
            "category":"Food & Beverages",
            "subcategory":"Supermarket",
            "type":"Retail Goods"
        }
    ],
    "sg:phone":"+44 1526 832661",
    "sg:postcode":"NG34 9SL",
    "sg:province":"Lincolnshire",
    "sg:tags":[
        "frozen"
    ],
    "wof:name":"G W Padley Holdings Ltd.",
    "wof:placetype":"venue"
},
  "geometry": {"coordinates":[-0.328904,53.013882],"type":"Point"}
}