{
  "type": "Feature",
  "properties": {
    "addr:full":"22 Marshall Street, Crossgates Leeds West Yorkshire LS15 8DY",
    "addr:housenumber":"22",
    "addr:postcode":"ls15 8dy",
    "addr:street":"Marshall Street",
    "iso:country":"GB",
    "sg:address":"22 Marshall Street, Crossgates",
    "sg:city":"Leeds",
    "sg:classifiers":[
        {
            "category":"Building & Trades",
            "subcategory":"Plumbing",
            "type":"Services"
        }
    ],
    "sg:postcode":"LS15 8DY",
    "sg:province":"West Yorkshire",
    "sg:tags":[
        "heating"
    ],
    "wof:name":"Ace Plumbers",
    "wof:placetype":"venue"
},
  "geometry": {"coordinates":[-1.448845,53.806664],"type":"Point"}
}