{
  "type": "Feature",
  "properties": {
    "iso:country":"GB",
    "sg:address":"4 Portland Street",
    "sg:city":"Newark",
    "sg:classifiers":[
        {
            "category":"Shopping",
            "subcategory":"Used Merchandise",
            "type":"Retail Goods"
        }
    ],
    "sg:postcode":"NG24 4XG",
    "sg:province":"Nottinghamshire",
    "sg:tags":[
        "shop",
        "second-hand"
    ],
    "wof:name":"Robert Roe",
    "wof:placetype":"venue"
},
  "geometry": {"coordinates":[-0.8108350039,53.0741882324],"type":"Point"}
}