{
  "type": "Feature",
  "properties": {
    "iso:country":"GB",
    "sg:address":"4 Francis St",
    "sg:city":"Dundee",
    "sg:classifiers":[
        {
            "category":"Manufacturing",
            "subcategory":"Building Materials",
            "type":"Manufacturing & Wholesale Goods"
        }
    ],
    "sg:phone":"+44 1382 825555",
    "sg:postcode":"DD3 8HH",
    "sg:province":"Dundee City",
    "sg:tags":[
        "tarmac",
        "asphalt"
    ],
    "wof:name":"Jet Kleen Scotland",
    "wof:placetype":"venue"
},
  "geometry": {"coordinates":[-2.98201,56.476048],"type":"Point"}
}