{
  "type": "Feature",
  "properties": {
    "iso:country":"GB",
    "sg:address":"Halifax Way, Pockrington Industrial Estate, Pockrington",
    "sg:city":"York",
    "sg:classifiers":[
        {
            "category":"Manufacturing",
            "subcategory":"Chemicals & Compounds",
            "type":"Manufacturing & Wholesale Goods"
        }
    ],
    "sg:phone":"+44 1759 305568",
    "sg:postcode":"YO42 1NT",
    "sg:province":"East Riding of Yorkshire",
    "sg:tags":[
        "mnfrs",
        "explosive",
        "engineer"
    ],
    "wof:name":"Explosive Developments Ltd.",
    "wof:placetype":"venue"
},
  "geometry": {"coordinates":[-0.806236,53.925297],"type":"Point"}
}