{
  "type": "Feature",
  "properties": {
    "iso:country":"GB",
    "sg:address":"134 Worplesdon Rd",
    "sg:city":"Guildford",
    "sg:classifiers":[
        {
            "category":"Building & Trades",
            "subcategory":"Construction",
            "type":"Services"
        }
    ],
    "sg:phone":"+44 1483 823558",
    "sg:postcode":"GU2 9RX",
    "sg:province":"Surrey",
    "sg:tags":[
        "decorator",
        "painter"
    ],
    "wof:name":"Guildford & Antiques Paint Stripping",
    "wof:placetype":"venue"
},
  "geometry": {"coordinates":[-0.592312,51.253674],"type":"Point"}
}