{
  "type": "Feature",
  "properties": {
    "addr:full":"Bridgewater Lodge, Golf Club Road, Little Gaddesden Berkhamsted Bedfordshire HP4 1LY",
    "addr:postcode":"hp4 1ly",
    "addr:street":"Club Road",
    "iso:country":"GB",
    "sg:address":"Bridgewater Lodge, Golf Club Road, Little Gaddesden",
    "sg:city":"Berkhamsted",
    "sg:classifiers":[
        {
            "category":"Professional",
            "subcategory":"Management & Consulting",
            "type":"Services"
        }
    ],
    "sg:phone":"+44 1442 843114",
    "sg:postcode":"HP4 1LY",
    "sg:province":"Bedfordshire",
    "sg:tags":[
        "consultant",
        "business"
    ],
    "wof:name":"John Mocatta",
    "wof:placetype":"venue"
},
  "geometry": {"coordinates":[-0.562148,51.81213],"type":"Point"}
}