{
  "type": "Feature",
  "properties": {
    "iso:country":"GB",
    "sg:address":"438 High Road, Leighton",
    "sg:city":"London",
    "sg:classifiers":[
        {
            "category":"Building & Trades",
            "subcategory":"Construction",
            "type":"Services"
        },
        {
            "category":"Manufacturing",
            "subcategory":"Building Materials",
            "type":"Manufacturing & Wholesale Goods"
        }
    ],
    "sg:phone":"+44 20 8539 9648",
    "sg:postcode":"E10 5EL",
    "sg:province":"Greater London",
    "sg:tags":[
        "merchant",
        "builder"
    ],
    "wof:name":"Brown The Builder",
    "wof:placetype":"venue"
},
  "geometry": {"coordinates":[-0.01108,51.563728],"type":"Point"}
}