{
  "type": "Feature",
  "properties": {
    "addr:full":"Tulip Tree Day Centre, Castle Road Kidderminster Staffordshire DY11 6TH",
    "addr:postcode":"dy11 6th",
    "addr:street":"Tulip;Castle Road",
    "iso:country":"GB",
    "sg:address":"Tulip Tree Day Centre, Castle Road",
    "sg:city":"Kidderminster",
    "sg:classifiers":[
        {
            "category":"Organizations",
            "subcategory":"Non-profit Organization",
            "type":"Services"
        }
    ],
    "sg:phone":"+44 1562 827010",
    "sg:postcode":"DY11 6TH",
    "sg:province":"Staffordshire",
    "sg:tags":[
        "organisation",
        "voluntary",
        "charity"
    ],
    "wof:name":"W R V S",
    "wof:placetype":"venue"
},
  "geometry": {"coordinates":[-2.24965,52.383781],"type":"Point"}
}