{
  "type": "Feature",
  "properties": {
    "addr:full":"Pitcairlie By Auchtermuchty Cupar Fife KY14 6EU",
    "addr:postcode":"ky14 6eu",
    "addr:street":"Cupar",
    "iso:country":"GB",
    "sg:address":"Pitcairlie By Auchtermuchty",
    "sg:city":"Cupar",
    "sg:classifiers":[
        {
            "category":"Professional",
            "subcategory":"Art Services",
            "type":"Services"
        }
    ],
    "sg:postcode":"KY14 6EU",
    "sg:province":"Fife",
    "sg:tags":[
        "photographer"
    ],
    "wof:name":"Allison,David,",
    "wof:placetype":"venue"
},
  "geometry": {"coordinates":[-3.23305,56.321339],"type":"Point"}
}