{
  "type": "Feature",
  "properties": {
    "addr:full":"Schivas Croft, St Catherines Inverurie Aberdeenshire AB51 8TN",
    "addr:postcode":"ab51 8tn",
    "addr:street":"Schivas Croft",
    "iso:country":"GB",
    "sg:address":"Schivas Croft, St Catherines",
    "sg:city":"Inverurie",
    "sg:classifiers":[
        {
            "category":"Building & Trades",
            "subcategory":"Landscaping Services",
            "type":"Services"
        }
    ],
    "sg:phone":"+44 1651 806498",
    "sg:postcode":"AB51 8TN",
    "sg:province":"Aberdeenshire",
    "sg:tags":[
        "horticultural",
        "consultant"
    ],
    "wof:name":"Ken Malcolm Equipment",
    "wof:placetype":"venue"
},
  "geometry": {"coordinates":[-2.2749300003,57.3908882141],"type":"Point"}
}