{
  "type": "Feature",
  "properties": {
    "iso:country":"GB",
    "sg:address":"Oak Road, Cumbernauld",
    "sg:city":"Glasgow",
    "sg:classifiers":[
        {
            "category":"Education",
            "subcategory":"School",
            "type":"Public Place"
        },
        {
            "category":"Government",
            "subcategory":"Office",
            "type":"Public Place"
        }
    ],
    "sg:phone":"+44 1236 720556",
    "sg:postcode":"G67 3LQ",
    "sg:province":"Falkirk",
    "sg:tags":[
        "local",
        "authority"
    ],
    "wof:name":"St Lucy's Primary School",
    "wof:placetype":"venue"
},
  "geometry": {"coordinates":[-3.9492940903,55.9600601196],"type":"Point"}
}