{
  "type": "Feature",
  "properties": {
    "iso:country":"GB",
    "sg:address":"105 Hawthorn Road",
    "sg:city":"Ashington",
    "sg:classifiers":[
        {
            "category":"Food & Beverages",
            "subcategory":"Liquor & Beverages",
            "type":"Retail Goods"
        }
    ],
    "sg:postcode":"NE63 0SP",
    "sg:province":"Northumberland",
    "sg:tags":[
        "beer",
        "spirit",
        "wines"
    ],
    "wof:name":"Cellar 5",
    "wof:placetype":"venue"
},
  "geometry": {"coordinates":[-1.558169,55.1759],"type":"Point"}
}