{
  "type": "Feature",
  "properties": {
    "addr:full":"164 Buxton Road Macclesfield Cheshire SK10 1NG",
    "addr:housenumber":"164",
    "addr:postcode":"sk10 1ng",
    "addr:street":"Buxton Road",
    "iso:country":"GB",
    "sg:address":"164 Buxton Road",
    "sg:city":"Macclesfield",
    "sg:classifiers":[
        {
            "category":"Government",
            "subcategory":"Post Office",
            "type":"Public Place"
        }
    ],
    "sg:phone":"+44 1625 423285",
    "sg:postcode":"SK10 1NG",
    "sg:province":"Cheshire",
    "wof:name":"Buxton Road Post Office",
    "wof:placetype":"venue"
},
  "geometry": {"coordinates":[-2.115606,53.258839],"type":"Point"}
}