{
  "type": "Feature",
  "properties": {
    "addr:full":"Old Gatehouse Road Dawlish Devon EX7 0DG",
    "addr:postcode":"ex7 0dg",
    "addr:street":"Old Gatehouse Road",
    "iso:country":"GB",
    "sg:address":"Old Gatehouse Road",
    "sg:city":"Dawlish",
    "sg:classifiers":[
        {
            "category":"Health Services",
            "subcategory":"Nursing And Care Facility",
            "type":"Services"
        }
    ],
    "sg:postcode":"EX7 0DG",
    "sg:province":"Devon",
    "sg:tags":[
        "home"
    ],
    "wof:name":"Treston Court Hotel",
    "wof:placetype":"venue"
},
  "geometry": {"coordinates":[-3.466576,50.58419],"type":"Point"}
}