{
  "type": "Feature",
  "properties": {
    "addr:full":"Penteinon, Cwm Cou Newcastle Emlyn Carmarthenshire SA38 9PR",
    "addr:postcode":"sa38 9pr",
    "addr:street":"Cwm",
    "iso:country":"GB",
    "sg:address":"Penteinon, Cwm Cou",
    "sg:city":"Newcastle Emlyn",
    "sg:classifiers":[
        {
            "category":"Farming",
            "subcategory":"Livestock Farm",
            "type":"Manufacturing & Wholesale Goods"
        }
    ],
    "sg:phone":"+44 1239 710466",
    "sg:postcode":"SA38 9PR",
    "sg:province":"Carmarthenshire",
    "sg:tags":[
        "others"
    ],
    "wof:name":"J.S James",
    "wof:placetype":"venue"
},
  "geometry": {"coordinates":[-4.467984,52.035919],"type":"Point"}
}