{
  "type": "Feature",
  "properties": {
    "iso:country":"GB",
    "sg:address":"191 Station Lane",
    "sg:city":"Hornchurch",
    "sg:classifiers":[
        {
            "category":"Personal",
            "subcategory":"Beauty Salon",
            "type":"Services"
        }
    ],
    "sg:phone":"+44 1708 442535",
    "sg:postcode":"RM12 6LL",
    "sg:province":"Essex",
    "sg:tags":[
        "lady",
        "hairdresser"
    ],
    "wof:name":"Elizabeth Ann",
    "wof:placetype":"venue"
},
  "geometry": {"coordinates":[0.219787,51.554707],"type":"Point"}
}