{
  "type": "Feature",
  "properties": {
    "iso:country":"GB",
    "sg:address":"74-76 Princes Street",
    "sg:city":"Ardrossan",
    "sg:classifiers":[
        {
            "category":"Professional",
            "subcategory":"Lawyer & Legal Services",
            "type":"Services"
        }
    ],
    "sg:phone":"+44 1294 464131",
    "sg:postcode":"KA22 8DF",
    "sg:province":"North Ayrshire",
    "sg:tags":[
        "solicitor"
    ],
    "wof:name":"James Campbell & Co",
    "wof:placetype":"venue"
},
  "geometry": {"coordinates":[-4.813533,55.63958],"type":"Point"}
}