{
  "type": "Feature",
  "properties": {
    "addr:full":"Growland Farm, Munderfield Bromyard Herefordshire HR7 4JS",
    "addr:postcode":"hr7 4js",
    "addr:street":"Munderfield",
    "iso:country":"GB",
    "sg:address":"Growland Farm, Munderfield",
    "sg:city":"Bromyard",
    "sg:classifiers":[
        {
            "category":"Real Estate",
            "subcategory":"Developer",
            "type":"Services"
        }
    ],
    "sg:phone":"+44 1885 490365",
    "sg:postcode":"HR7 4JS",
    "sg:province":"Herefordshire",
    "sg:tags":[
        "property"
    ],
    "wof:name":"Rocrest Ltd.",
    "wof:placetype":"venue"
},
  "geometry": {"coordinates":[-2.510399,52.189098],"type":"Point"}
}