{
  "type": "Feature",
  "properties": {
    "addr:full":"Tigh Na Beinne Croft Road, Lochcarron Strathcarron Highland IV54 8YA",
    "addr:postcode":"iv54 8ya",
    "addr:street":"Croft Road;Strathcarron",
    "iso:country":"GB",
    "sg:address":"Tigh Na Beinne Croft Road, Lochcarron",
    "sg:city":"Strathcarron",
    "sg:classifiers":[
        {
            "category":"Professional",
            "subcategory":"Art Services",
            "type":"Services"
        }
    ],
    "sg:postcode":"IV54 8YA",
    "sg:province":"Highland",
    "sg:tags":[
        "photographer"
    ],
    "wof:name":"Alex Ingram",
    "wof:placetype":"venue"
},
  "geometry": {"coordinates":[-5.428674,57.423656],"type":"Point"}
}