{
  "type": "Feature",
  "properties": {
    "addr:full":"38 The Drive, Dovercourt Harwich Essex CO12 3SU",
    "addr:housenumber":"38",
    "addr:postcode":"co12 3su",
    "addr:street":"The Drive",
    "iso:country":"GB",
    "sg:address":"38 The Drive, Dovercourt",
    "sg:city":"Harwich",
    "sg:classifiers":[
        {
            "category":"Professional",
            "subcategory":"Engineering",
            "type":"Services"
        }
    ],
    "sg:postcode":"CO12 3SU",
    "sg:province":"Essex",
    "sg:tags":[
        "contractor",
        "electrical",
        "engineer"
    ],
    "wof:name":"John D Anderson",
    "wof:placetype":"venue"
},
  "geometry": {"coordinates":[1.2696290016,51.9293861389],"type":"Point"}
}