{
  "type": "Feature",
  "properties": {
    "addr:full":"41 Howard Business Park, Howard Clo Waltham Abbey Essex EN9 1XE",
    "addr:housenumber":"41",
    "addr:postcode":"en9 1xe",
    "addr:street":"Howard Business Park Howard Clo;Abbey",
    "iso:country":"GB",
    "sg:address":"41 Howard Business Park, Howard Clo",
    "sg:city":"Waltham Abbey",
    "sg:classifiers":[
        {
            "category":"Professional",
            "subcategory":"Management & Consulting",
            "type":"Services"
        }
    ],
    "sg:phone":"+44 1992 787550",
    "sg:postcode":"EN9 1XE",
    "sg:province":"Essex",
    "sg:tags":[
        "consultant",
        "business"
    ],
    "wof:name":"Performance Resources",
    "wof:placetype":"venue"
},
  "geometry": {"coordinates":[0.00149,51.68642],"type":"Point"}
}