{
  "type": "Feature",
  "properties": {
    "iso:country":"GB",
    "sg:address":"40 Warwick Road",
    "sg:city":"Stockport",
    "sg:classifiers":[
        {
            "category":"Building & Trades",
            "subcategory":"Plumbing",
            "type":"Services"
        }
    ],
    "sg:postcode":"SK4 4HE",
    "sg:province":"Cheshire",
    "sg:tags":[
        "central",
        "heating"
    ],
    "wof:name":"Barlow,Robert J,",
    "wof:placetype":"venue"
},
  "geometry": {"coordinates":[-2.179289,53.419506],"type":"Point"}
}