{
  "type": "Feature",
  "properties": {
    "iso:country":"GB",
    "sg:address":"2 St Georges Road",
    "sg:city":"Glasgow",
    "sg:classifiers":[
        {
            "category":"Bars & Pubs",
            "subcategory":"Wine Bar",
            "type":"Food & Drink"
        }
    ],
    "sg:phone":"+44 141 332 7000",
    "sg:postcode":"G3 6UJ",
    "sg:province":"Glasgow City",
    "wof:name":"Drist Wood",
    "wof:placetype":"venue"
},
  "geometry": {"coordinates":[-4.2680888176,55.8710403442],"type":"Point"}
}