{
  "type": "Feature",
  "properties": {
    "addr:full":"Old St. Peters School, Reardon St Whitechapel Devon E1W2QH",
    "addr:postcode":"e1w2qh",
    "addr:street":"Reardon St",
    "iso:country":"GB",
    "sg:address":"Old St. Peters School, Reardon St",
    "sg:city":"Whitechapel",
    "sg:classifiers":[
        {
            "category":"Community Center",
            "type":"Public Place"
        }
    ],
    "sg:phone":"+44 20 7709 9096",
    "sg:postcode":"E1W2QH",
    "sg:province":"Devon",
    "sg:tags":[
        "centre"
    ],
    "wof:name":"St. Peters Community Centre",
    "wof:placetype":"venue"
},
  "geometry": {"coordinates":[-0.05958,51.505539],"type":"Point"}
}