{
  "type": "Feature",
  "properties": {
    "addr:full":"40 Icknield Close, Wendover Aylesbury Buckinghamshire HP22 6HG",
    "addr:housenumber":"40",
    "addr:postcode":"hp22 6hg",
    "addr:street":"Icknield Close",
    "iso:country":"GB",
    "sg:address":"40 Icknield Close, Wendover",
    "sg:city":"Aylesbury",
    "sg:classifiers":[
        {
            "category":"Professional",
            "subcategory":"Printing & Photocopies",
            "type":"Services"
        }
    ],
    "sg:postcode":"HP22 6HG",
    "sg:province":"Buckinghamshire",
    "sg:tags":[
        "plate",
        "lithographic",
        "maker"
    ],
    "wof:name":"R Ward (Tynedale Graphics)",
    "wof:placetype":"venue"
},
  "geometry": {"coordinates":[-0.7386509776,51.7650413513],"type":"Point"}
}