{
  "type": "Feature",
  "properties": {
    "iso:country":"GB",
    "sg:address":"139 Upper Wickham Lane",
    "sg:city":"Welling",
    "sg:classifiers":[
        {
            "category":"Professional",
            "subcategory":"Management & Consulting",
            "type":"Services"
        },
        {
            "category":"Personal",
            "type":"Services"
        }
    ],
    "sg:phone":"+44 20 8854 2261",
    "sg:postcode":"DA16 3AL",
    "sg:province":"Kent",
    "sg:tags":[
        "consultant",
        "beauty",
        "specialist"
    ],
    "wof:name":"Beauty Room At My Fair Lady",
    "wof:placetype":"venue"
},
  "geometry": {"coordinates":[0.110684,51.4674530029],"type":"Point"}
}