{
  "type": "Feature",
  "properties": {
    "iso:country":"GB",
    "sg:address":"Doncaster Rd",
    "sg:city":"Barnsley",
    "sg:classifiers":[
        {
            "category":"Banks & Credit Unions",
            "subcategory":"Investment Brokerage",
            "type":"Services"
        }
    ],
    "sg:phone":"+44 1226 786466",
    "sg:postcode":"S71 5AP",
    "sg:province":"South Yorkshire",
    "sg:tags":[
        "contractor"
    ],
    "wof:name":"Platts Harris Agricultural Group Ltd",
    "wof:placetype":"venue"
},
  "geometry": {"coordinates":[-1.415144,53.546703],"type":"Point"}
}