{
  "type": "Feature",
  "properties": {
    "addr:full":"3 Warner Street Accrington Lancashire BB5 1HN",
    "addr:housenumber":"3",
    "addr:postcode":"bb5 1hn",
    "addr:street":"Warner Street",
    "iso:country":"GB",
    "sg:address":"3 Warner Street",
    "sg:city":"Accrington",
    "sg:classifiers":[
        {
            "category":"Shopping",
            "subcategory":"Clothing, Apparel, & Fashions",
            "type":"Retail Goods"
        }
    ],
    "sg:phone":"+44 1254 394495",
    "sg:postcode":"BB5 1HN",
    "sg:province":"Lancashire",
    "sg:tags":[
        "shop"
    ],
    "wof:name":"Something Special",
    "wof:placetype":"venue"
},
  "geometry": {"coordinates":[-2.36166,53.752052],"type":"Point"}
}