{
  "type": "Feature",
  "properties": {
    "iso:country":"GB",
    "sg:address":"Lowe Cottage Farm, The Lowe, Wem",
    "sg:city":"Shrewsbury",
    "sg:classifiers":[
        {
            "category":"Utilities",
            "subcategory":"Refuse",
            "type":"Services"
        }
    ],
    "sg:phone":"+44 1743 361155",
    "sg:postcode":"SY4 5UE",
    "sg:province":"Shropshire",
    "sg:tags":[
        "skip",
        "hire"
    ],
    "wof:name":"Peter Griffiths Skip Hire",
    "wof:placetype":"venue"
},
  "geometry": {"coordinates":[-2.733865,52.862679],"type":"Point"}
}