{
  "type": "Feature",
  "properties": {
    "iso:country":"GB",
    "sg:address":"125 High Street, Wolstanton",
    "sg:city":"Newcastle",
    "sg:classifiers":[
        {
            "category":"Government",
            "subcategory":"Post Office",
            "type":"Public Place"
        }
    ],
    "sg:postcode":"ST5 0EP",
    "sg:province":"Staffordshire",
    "wof:name":"Wolstanton Sub Post Office",
    "wof:placetype":"venue"
},
  "geometry": {"coordinates":[-2.2175590992,53.0317115784],"type":"Point"}
}