{
  "type": "Feature",
  "properties": {
    "addr:full":"7 Dark Gate Carmarthen Carmarthenshire SA31 1PT",
    "addr:housenumber":"7",
    "addr:postcode":"sa31 1pt",
    "addr:street":"Dark Gate",
    "iso:country":"GB",
    "sg:address":"7 Dark Gate",
    "sg:city":"Carmarthen",
    "sg:classifiers":[
        {
            "category":"Shopping",
            "subcategory":"Comic Books",
            "type":"Retail Goods"
        }
    ],
    "sg:postcode":"SA31 1PT",
    "sg:province":"Carmarthenshire",
    "sg:tags":[
        "jeweller"
    ],
    "wof:name":"Burgess Jewellers",
    "wof:placetype":"venue"
},
  "geometry": {"coordinates":[-4.3085680008,51.8563423157],"type":"Point"}
}