{
  "type": "Feature",
  "properties": {
    "addr:full":"25a Rusty Well Park Yeovil Somerset BA20 2NA",
    "addr:housenumber":"25a",
    "addr:postcode":"ba20 2na",
    "addr:street":"Rusty Well Park",
    "iso:country":"GB",
    "sg:address":"25a Rusty Well Park",
    "sg:city":"Yeovil",
    "sg:classifiers":[
        {
            "category":"Manufacturing",
            "subcategory":"Buildings",
            "type":"Manufacturing & Wholesale Goods"
        }
    ],
    "sg:postcode":"BA20 2NA",
    "sg:province":"Somerset",
    "sg:tags":[
        "mobile",
        "home"
    ],
    "wof:name":"Rusty Well Park Ltd.",
    "wof:placetype":"venue"
},
  "geometry": {"coordinates":[-2.643366,50.935139],"type":"Point"}
}