{
  "type": "Feature",
  "properties": {
    "addr:full":"21 Norwood Road London Greater London SE24 9AA",
    "addr:housenumber":"21",
    "addr:postcode":"se24 9aa",
    "addr:street":"Norwood Road",
    "iso:country":"GB",
    "sg:address":"21 Norwood Road",
    "sg:city":"London",
    "sg:classifiers":[
        {
            "category":"Communications",
            "type":"Services"
        }
    ],
    "sg:postcode":"SE24 9AA",
    "sg:province":"Greater London",
    "sg:tags":[
        "tv",
        "video",
        "radio"
    ],
    "wof:name":"Channels",
    "wof:placetype":"venue"
},
  "geometry": {"coordinates":[-0.10111,51.451908],"type":"Point"}
}