{
  "type": "Feature",
  "properties": {
    "addr:full":"Waterford Road Ipswich Suffolk IP1 5NW",
    "addr:postcode":"ip1 5nw",
    "addr:street":"Waterford Road",
    "iso:country":"GB",
    "sg:address":"Waterford Road",
    "sg:city":"Ipswich",
    "sg:classifiers":[
        {
            "category":"Education",
            "subcategory":"School",
            "type":"Public Place"
        }
    ],
    "sg:phone":"+44 1473 741438",
    "sg:postcode":"IP1 5NW",
    "sg:province":"Suffolk",
    "sg:tags":[
        "local",
        "authority"
    ],
    "wof:name":"Whitehouse Community Infants School",
    "wof:placetype":"venue"
},
  "geometry": {"coordinates":[1.121716,52.079208],"type":"Point"}
}