{
  "type": "Feature",
  "properties": {
    "iso:country":"GB",
    "sg:address":"Plumtree Rd Ind Est, Plumtree Rd, Bircotes",
    "sg:city":"Doncaster",
    "sg:classifiers":[
        {
            "category":"Professional",
            "subcategory":"Detective & Security Services",
            "type":"Services"
        }
    ],
    "sg:phone":"+44 1302 711044",
    "sg:postcode":"DN11 8EW",
    "sg:province":"South Yorkshire",
    "sg:tags":[
        "video",
        "cctv"
    ],
    "wof:name":"Impact Asset Protection Ltd",
    "wof:placetype":"venue"
},
  "geometry": {"coordinates":[-1.0494940281,53.4264717102],"type":"Point"}
}