{
  "type": "Feature",
  "properties": {
    "addr:full":"89 Rosebank Av Hornchurch Essex RM12 5QU",
    "addr:housenumber":"89",
    "addr:postcode":"rm12 5qu",
    "addr:street":"Rosebank Av Hornchurch",
    "iso:country":"GB",
    "sg:address":"89 Rosebank Av",
    "sg:city":"Hornchurch",
    "sg:classifiers":[
        {
            "category":"Retail",
            "subcategory":"Auto Repair",
            "type":"Services"
        }
    ],
    "sg:phone":"+44 1708 444267",
    "sg:postcode":"RM12 5QU",
    "sg:province":"Essex",
    "sg:tags":[
        "modification",
        "garage"
    ],
    "wof:name":"I D Carter",
    "wof:placetype":"venue"
},
  "geometry": {"coordinates":[0.2087000012,51.5471878052],"type":"Point"}
}