{
  "type": "Feature",
  "properties": {
    "iso:country":"GB",
    "sg:address":"10 Gottfried Mews, Fortess Road",
    "sg:city":"London",
    "sg:classifiers":[
        {
            "category":"Freight",
            "type":"Transportation"
        }
    ],
    "sg:phone":"+44 20 7482 1863",
    "sg:postcode":"NW5 2HN",
    "sg:province":"Greater London",
    "sg:tags":[
        "overseas",
        "shipping",
        "removal"
    ],
    "wof:name":"Shifting Gear Ltd.",
    "wof:placetype":"venue"
},
  "geometry": {"coordinates":[-0.1389340013,51.5556983948],"type":"Point"}
}