{
  "type": "Feature",
  "properties": {
    "addr:full":"366 Lanark Rd West Currie City of Edinburgh EH14 5RR",
    "addr:housenumber":"366",
    "addr:postcode":"eh14 5rr",
    "addr:street":"Lanark Rd West",
    "iso:country":"GB",
    "sg:address":"366 Lanark Rd West",
    "sg:city":"Currie",
    "sg:classifiers":[
        {
            "category":"Retail",
            "subcategory":"Driving School",
            "type":"Services"
        }
    ],
    "sg:postcode":"EH14 5RR",
    "sg:province":"City of Edinburgh",
    "wof:name":"Macgee,Julie,",
    "wof:placetype":"venue"
},
  "geometry": {"coordinates":[-3.321162,55.892853],"type":"Point"}
}