{
  "type": "Feature",
  "properties": {
    "addr:full":"4 Kingston Place, Kingsmuir Forfar Angus DD8 2RG",
    "addr:housenumber":"4",
    "addr:postcode":"dd8 2rg",
    "addr:street":"Kingston Place",
    "iso:country":"GB",
    "sg:address":"4 Kingston Place, Kingsmuir",
    "sg:city":"Forfar",
    "sg:classifiers":[
        {
            "category":"Building & Trades",
            "subcategory":"Construction",
            "type":"Services"
        }
    ],
    "sg:phone":"+44 1307 466952",
    "sg:postcode":"DD8 2RG",
    "sg:province":"Angus",
    "sg:tags":[
        "builder",
        "joiner",
        "carpenter"
    ],
    "wof:name":"Thomson & Douglas Ltd",
    "wof:placetype":"venue"
},
  "geometry": {"coordinates":[-2.8531908989,56.6322784424],"type":"Point"}
}