{
  "type": "Feature",
  "properties": {
    "addr:full":"46 Denbigh Drive Fareham Hampshire PO16 7PN",
    "addr:housenumber":"46",
    "addr:postcode":"po16 7pn",
    "addr:street":"Denbigh Drive",
    "iso:country":"GB",
    "sg:address":"46 Denbigh Drive",
    "sg:city":"Fareham",
    "sg:classifiers":[
        {
            "category":"Building & Trades",
            "subcategory":"Construction",
            "type":"Services"
        }
    ],
    "sg:phone":"+44 1329 232465",
    "sg:postcode":"PO16 7PN",
    "sg:province":"Hampshire",
    "sg:tags":[
        "tiling",
        "contractor"
    ],
    "wof:name":"P S Tiling",
    "wof:placetype":"venue"
},
  "geometry": {"coordinates":[-1.1915210485,50.8574638367],"type":"Point"}
}