{
  "type": "Feature",
  "properties": {
    "addr:full":"9 Sherston Close, Nailsea Bristol Somerset BS48 2TR",
    "addr:housenumber":"9",
    "addr:postcode":"bs48 2tr",
    "addr:street":"Sherston Close",
    "iso:country":"GB",
    "sg:address":"9 Sherston Close, Nailsea",
    "sg:city":"Bristol",
    "sg:classifiers":[
        {
            "category":"Building & Trades",
            "subcategory":"Landscaping Services",
            "type":"Services"
        }
    ],
    "sg:phone":"+44 1275 851605",
    "sg:postcode":"BS48 2TR",
    "sg:province":"Somerset",
    "sg:tags":[
        "gardening"
    ],
    "wof:name":"Evans Maintenance Services",
    "wof:placetype":"venue"
},
  "geometry": {"coordinates":[-2.745587,51.429722],"type":"Point"}
}