{
  "type": "Feature",
  "properties": {
    "iso:country":"GB",
    "sg:address":"Pocklington Ind Est, The Airfield, Pocklington",
    "sg:city":"York",
    "sg:classifiers":[
        {
            "category":"Brewery",
            "type":"Food & Drink"
        }
    ],
    "sg:phone":"+44 1759 306750",
    "sg:postcode":"YO42 1NR",
    "sg:province":"East Riding of Yorkshire",
    "sg:tags":[
        "brewer"
    ],
    "wof:name":"Beer Lines York",
    "wof:placetype":"venue"
},
  "geometry": {"coordinates":[-0.785503,53.98563],"type":"Point"}
}