{
  "type": "Feature",
  "properties": {
    "iso:country":"GB",
    "sg:address":"Stane Street, Five Oaks",
    "sg:city":"Billingshurst",
    "sg:classifiers":[
        {
            "category":"Bars & Pubs",
            "type":"Food & Drink"
        }
    ],
    "sg:phone":"+44 1403 782679",
    "sg:postcode":"RH14 9AJ",
    "sg:province":"West Sussex",
    "sg:tags":[
        "pubs",
        "inn"
    ],
    "wof:name":"B Cooper-johnstone",
    "wof:placetype":"venue"
},
  "geometry": {"coordinates":[-0.452428,51.021183],"type":"Point"}
}