{
  "type": "Feature",
  "properties": {
    "addr:full":"62 Tantallon Road, Wandsworth London Greater London SW12 8DH",
    "addr:housenumber":"62",
    "addr:postcode":"sw12 8dh",
    "addr:street":"Tantallon Road",
    "iso:country":"GB",
    "sg:address":"62 Tantallon Road, Wandsworth",
    "sg:city":"London",
    "sg:classifiers":[
        {
            "category":"Building & Trades",
            "subcategory":"Plumbing",
            "type":"Services"
        }
    ],
    "sg:phone":"+44 20 8675 6226",
    "sg:postcode":"SW12 8DH",
    "sg:province":"Greater London",
    "sg:tags":[
        "heating"
    ],
    "wof:name":"Arnica Mechanical Services Ltd.",
    "wof:placetype":"venue"
},
  "geometry": {"coordinates":[-0.1581739932,51.4452018738],"type":"Point"}
}