{
  "type": "Feature",
  "properties": {
    "iso:country":"GB",
    "sg:address":"St Helens Street",
    "sg:city":"Corbridge",
    "sg:classifiers":[
        {
            "category":"Food & Beverages",
            "subcategory":"Supermarket",
            "type":"Retail Goods"
        }
    ],
    "sg:phone":"+44 1434 632013",
    "sg:postcode":"NE45 5BE",
    "sg:province":"Northumberland",
    "wof:name":"North Eastern & Cumbrian Co-Op Food Stores",
    "wof:placetype":"venue"
},
  "geometry": {"coordinates":[-2.018655,54.975487],"type":"Point"}
}