{
  "type": "Feature",
  "properties": {
    "addr:full":"44 High St Brierley Hill West Midlands DY5 2AA",
    "addr:housenumber":"44",
    "addr:postcode":"dy5 2aa",
    "addr:street":"High St",
    "iso:country":"GB",
    "sg:address":"44 High St",
    "sg:city":"Brierley Hill",
    "sg:classifiers":[
        {
            "category":"Restaurant",
            "type":"Food & Drink"
        }
    ],
    "sg:phone":"+44 1384 412757",
    "sg:postcode":"DY5 2AA",
    "sg:province":"West Midlands",
    "sg:tags":[
        "indian"
    ],
    "wof:name":"Tim Tandoori",
    "wof:placetype":"venue"
},
  "geometry": {"coordinates":[-2.104087,52.472553],"type":"Point"}
}