{
  "type": "Feature",
  "properties": {
    "iso:country":"GB",
    "sg:address":"53 Old Christchurch Road",
    "sg:city":"Bournemouth",
    "sg:classifiers":[
        {
            "category":"Shopping",
            "subcategory":"Shoes",
            "type":"Retail Goods"
        }
    ],
    "sg:phone":"+44 1202 291946",
    "sg:postcode":"BH1 1DJ",
    "sg:province":"Dorset",
    "sg:tags":[
        "shop"
    ],
    "wof:name":"Faith Shoes",
    "wof:placetype":"venue"
},
  "geometry": {"coordinates":[-1.876798,50.720928],"type":"Point"}
}