{
  "type": "Feature",
  "properties": {
    "iso:country":"GB",
    "sg:address":"560 Brighton Road",
    "sg:city":"South Croydon",
    "sg:classifiers":[
        {
            "category":"Building & Trades",
            "subcategory":"Construction",
            "type":"Services"
        }
    ],
    "sg:postcode":"CR2 6AW",
    "sg:province":"Surrey",
    "sg:tags":[
        "builder"
    ],
    "wof:name":"Fairhope Ltd",
    "wof:placetype":"venue"
},
  "geometry": {"coordinates":[-0.1035130024,51.3463478088],"type":"Point"}
}