{
  "type": "Feature",
  "properties": {
    "addr:full":"65 Padstow Road Birmingham West Midlands B24 0NH",
    "addr:housenumber":"65",
    "addr:postcode":"b24 0nh",
    "addr:street":"Padstow Road",
    "iso:country":"GB",
    "sg:address":"65 Padstow Road",
    "sg:city":"Birmingham",
    "sg:classifiers":[
        {
            "category":"Professional",
            "subcategory":"Art Services",
            "type":"Services"
        },
        {
            "category":"Building & Trades",
            "subcategory":"Construction",
            "type":"Services"
        }
    ],
    "sg:phone":"+44 121 350 0355",
    "sg:postcode":"B24 0NH",
    "sg:province":"West Midlands",
    "sg:tags":[
        "decorator",
        "painter"
    ],
    "wof:name":"Lawrence Leigh",
    "wof:placetype":"venue"
},
  "geometry": {"coordinates":[-1.8117599487,52.5236320496],"type":"Point"}
}