{
  "type": "Feature",
  "properties": {
    "iso:country":"GB",
    "sg:address":"Goodrest Farm, Bromsgrove Road, Hunnington",
    "sg:city":"Halesowen",
    "sg:classifiers":[
        {
            "category":"Farming",
            "subcategory":"Livestock Farm",
            "type":"Manufacturing & Wholesale Goods"
        }
    ],
    "sg:phone":"+44 121 550 1223",
    "sg:postcode":"B62 0JN",
    "sg:province":"West Midlands",
    "sg:tags":[
        "others"
    ],
    "wof:name":"J & C F Cherry",
    "wof:placetype":"venue"
},
  "geometry": {"coordinates":[-2.0524089336,52.4281044006],"type":"Point"}
}