{
  "type": "Feature",
  "properties": {
    "iso:country":"GB",
    "sg:address":"Unit M, Wirral Business Centre, Dock Road",
    "sg:city":"Wallasey",
    "sg:classifiers":[
        {
            "category":"Building & Trades",
            "subcategory":"Construction",
            "type":"Services"
        }
    ],
    "sg:phone":"+44 151 630 0800",
    "sg:postcode":"CH41 1JW",
    "sg:province":"Merseyside",
    "sg:tags":[
        "builder"
    ],
    "wof:name":"Moreton Alarm Supplies",
    "wof:placetype":"venue"
},
  "geometry": {"coordinates":[-3.03665,53.406151],"type":"Point"}
}