{
  "type": "Feature",
  "properties": {
    "addr:full":"St Albans Road Barnet Hertfordshire EN5 4RE",
    "addr:postcode":"en5 4re",
    "addr:street":"St Albans Road",
    "iso:country":"GB",
    "sg:address":"St Albans Road",
    "sg:city":"Barnet",
    "sg:classifiers":[
        {
            "category":"Retail",
            "subcategory":"Auto Repair",
            "type":"Services"
        }
    ],
    "sg:postcode":"EN5 4RE",
    "sg:province":"Hertfordshire",
    "sg:tags":[
        "modification",
        "garage"
    ],
    "wof:name":"Star Garage",
    "wof:placetype":"venue"
},
  "geometry": {"coordinates":[-0.2055339962,51.6594390869],"type":"Point"}
}