{
  "type": "Feature",
  "properties": {
    "addr:full":"Stoney Park Farm, Consall Stoke-on-trent Staffordshire ST9 0AD",
    "addr:postcode":"staffordshire st9 0ad",
    "addr:street":"Stoney Park Farm",
    "iso:country":"GB",
    "sg:address":"Stoney Park Farm, Consall",
    "sg:city":"Stoke-on-trent",
    "sg:classifiers":[
        {
            "category":"Freight",
            "type":"Transportation"
        }
    ],
    "sg:phone":"+44 1782 550009",
    "sg:postcode":"ST9 0AD",
    "sg:province":"Staffordshire",
    "sg:tags":[
        "haulage",
        "road"
    ],
    "wof:name":"G A & C Y Carr",
    "wof:placetype":"venue"
},
  "geometry": {"coordinates":[-2.0333099365,53.0368995667],"type":"Point"}
}