{
  "type": "Feature",
  "properties": {
    "iso:country":"GB",
    "sg:address":"Oxney Industrial Estate, Oxney Road",
    "sg:city":"Peterborough",
    "sg:classifiers":[
        {
            "category":"Building & Trades",
            "subcategory":"Construction",
            "type":"Services"
        }
    ],
    "sg:phone":"+44 1733 566774",
    "sg:postcode":"PE1 5YW",
    "sg:province":"Cambridgeshire",
    "sg:tags":[
        "demolition",
        "contractor"
    ],
    "wof:name":"Spriggs Reclaim Centre",
    "wof:placetype":"venue"
},
  "geometry": {"coordinates":[-0.199849993,52.5886993408],"type":"Point"}
}