{
  "type": "Feature",
  "properties": {
    "addr:full":"45 Cowper Rd Dover Kent CT17 0PJ",
    "addr:housenumber":"45",
    "addr:postcode":"ct17 0pj",
    "addr:street":"Cowper Rd",
    "iso:country":"GB",
    "sg:address":"45 Cowper Rd",
    "sg:city":"Dover",
    "sg:classifiers":[
        {
            "category":"Retail",
            "subcategory":"Repair Shop",
            "type":"Services"
        }
    ],
    "sg:phone":"+44 1304 826386",
    "sg:postcode":"CT17 0PJ",
    "sg:province":"Kent",
    "sg:tags":[
        "maintenance"
    ],
    "wof:name":"R Potts",
    "wof:placetype":"venue"
},
  "geometry": {"coordinates":[1.2727359533,51.1395072937],"type":"Point"}
}