{
  "type": "Feature",
  "properties": {
    "iso:country":"GB",
    "sg:address":"22 Mill Street",
    "sg:city":"Stafford",
    "sg:classifiers":[
        {
            "category":"Travel",
            "subcategory":"Travel Agent",
            "type":"Entertainment"
        }
    ],
    "sg:phone":"+44 1785 222522",
    "sg:postcode":"ST16 2AL",
    "sg:province":"Staffordshire",
    "wof:name":"Hourds Marketing Ltd.",
    "wof:placetype":"venue"
},
  "geometry": {"coordinates":[-2.118199,52.805248],"type":"Point"}
}