{
  "type": "Feature",
  "properties": {
    "iso:country":"GB",
    "sg:address":"39 Nelson Street",
    "sg:city":"Buckingham",
    "sg:classifiers":[
        {
            "category":"Fast Food",
            "type":"Food & Drink"
        }
    ],
    "sg:phone":"+44 1280 812184",
    "sg:postcode":"MK18 1DA",
    "sg:province":"Buckinghamshire",
    "sg:tags":[
        "away",
        "take"
    ],
    "wof:name":"Buckingham Tandoori Indian Takeaway",
    "wof:placetype":"venue"
},
  "geometry": {"coordinates":[-0.990397,51.997761],"type":"Point"}
}