{
  "type": "Feature",
  "properties": {
    "iso:country":"GB",
    "sg:address":"14 Main Street, Kirkby Lonsdale",
    "sg:city":"Carnforth",
    "sg:classifiers":[
        {
            "category":"Shopping",
            "subcategory":"Antiques",
            "type":"Retail Goods"
        }
    ],
    "sg:phone":"+44 15242 72409",
    "sg:postcode":"LA6 2AE",
    "sg:province":"Cumbria",
    "wof:name":"Architus",
    "wof:placetype":"venue"
},
  "geometry": {"coordinates":[-2.5966830254,54.2008552551],"type":"Point"}
}