{
  "type": "Feature",
  "properties": {
    "iso:country":"GB",
    "sg:address":"Dean Street",
    "sg:city":"Crediton",
    "sg:classifiers":[
        {
            "category":"Bars & Pubs",
            "type":"Food & Drink"
        }
    ],
    "sg:postcode":"EX17 3EW",
    "sg:province":"Devon",
    "sg:tags":[
        "pubs",
        "inn"
    ],
    "wof:name":"Plymouth Inn",
    "wof:placetype":"venue"
},
  "geometry": {"coordinates":[-3.6521849632,50.7874526978],"type":"Point"}
}