{
  "type": "Feature",
  "properties": {
    "iso:country":"GB",
    "sg:address":"Nursteed Road, Devizes",
    "sg:city":"Pewsey",
    "sg:classifiers":[
        {
            "category":"Sports & Exercise",
            "subcategory":"Athletic Track",
            "type":"Entertainment"
        }
    ],
    "sg:phone":"+44 1380 728000",
    "sg:postcode":"SN10 3DY",
    "sg:province":"Wiltshire",
    "sg:tags":[
        "wholesale",
        "cd",
        "tape",
        "record"
    ],
    "wof:name":"Discovery Records",
    "wof:placetype":"venue"
},
  "geometry": {"coordinates":[-1.972559,51.343071],"type":"Point"}
}