{
  "type": "Feature",
  "properties": {
    "addr:full":"405 New Hythe Lane, Larkfield Aylesford Kent ME20 6SA",
    "addr:housenumber":"405",
    "addr:postcode":"me20 6sa",
    "addr:street":"New Hythe Lane",
    "iso:country":"GB",
    "sg:address":"405 New Hythe Lane, Larkfield",
    "sg:city":"Aylesford",
    "sg:classifiers":[
        {
            "category":"Home & Garden",
            "subcategory":"Building Materials",
            "type":"Retail Goods"
        }
    ],
    "sg:postcode":"ME20 6SA",
    "sg:province":"Kent",
    "sg:tags":[
        "ready",
        "mixed",
        "concrete"
    ],
    "wof:name":"Peter Dove",
    "wof:placetype":"venue"
},
  "geometry": {"coordinates":[0.4426900148,51.3046112061],"type":"Point"}
}