{
  "type": "Feature",
  "properties": {
    "addr:full":"100b Manford Way Chigwell Essex IG7 4DF",
    "addr:housenumber":"100b",
    "addr:postcode":"ig7 4df",
    "addr:street":"Manford Way",
    "iso:country":"GB",
    "sg:address":"100b Manford Way",
    "sg:city":"Chigwell",
    "sg:classifiers":[
        {
            "category":"Government",
            "subcategory":"City Hall",
            "type":"Public Place"
        }
    ],
    "sg:phone":"+44 20 8500 4311",
    "sg:postcode":"IG7 4DF",
    "sg:province":"Essex",
    "wof:name":"Hainault Forest Community Centre",
    "wof:placetype":"venue"
},
  "geometry": {"coordinates":[0.1043339968,51.6081237793],"type":"Point"}
}