{
  "type": "Feature",
  "properties": {
    "iso:country":"GB",
    "sg:address":"Unit 1c Hawkslaw Trading Estate, Riverside Road",
    "sg:city":"Leven",
    "sg:classifiers":[
        {
            "category":"Manufacturing",
            "subcategory":"Signs",
            "type":"Manufacturing & Wholesale Goods"
        }
    ],
    "sg:phone":"+44 1333 424774",
    "sg:postcode":"KY8 4LT",
    "sg:province":"Fife",
    "sg:tags":[
        "nameplate"
    ],
    "wof:name":"Colin Cruickshank",
    "wof:placetype":"venue"
},
  "geometry": {"coordinates":[-2.998787,56.194401],"type":"Point"}
}