{
  "type": "Feature",
  "properties": {
    "addr:full":"4 Queens Street, Morley Leeds West Yorkshire LS27 9BJ",
    "addr:housenumber":"4",
    "addr:postcode":"ls27 9bj",
    "addr:street":"Queens Street",
    "iso:country":"GB",
    "sg:address":"4 Queens Street, Morley",
    "sg:city":"Leeds",
    "sg:classifiers":[
        {
            "category":"Building & Trades",
            "subcategory":"Construction",
            "type":"Services"
        }
    ],
    "sg:postcode":"LS27 9BJ",
    "sg:province":"West Yorkshire",
    "sg:tags":[
        "glass",
        "replacement"
    ],
    "wof:name":"Day Night 24 Ltd.",
    "wof:placetype":"venue"
},
  "geometry": {"coordinates":[-1.604728,53.743805],"type":"Point"}
}