{
  "type": "Feature",
  "properties": {
    "addr:full":"22 Dickens Close, Galley Common Nuneaton Leicestershire CV10 9SQ",
    "addr:housenumber":"22",
    "addr:postcode":"cv10 9sq",
    "addr:street":"Dickens Close Galley Common",
    "iso:country":"GB",
    "sg:address":"22 Dickens Close, Galley Common",
    "sg:city":"Nuneaton",
    "sg:classifiers":[
        {
            "category":"Professional",
            "subcategory":"Detective & Security Services",
            "type":"Services"
        }
    ],
    "sg:postcode":"CV10 9SQ",
    "sg:province":"Leicestershire",
    "wof:name":"Meridian Security Services",
    "wof:placetype":"venue"
},
  "geometry": {"coordinates":[-1.52289,52.523666],"type":"Point"}
}