{
  "type": "Feature",
  "properties": {
    "addr:full":"52 Connaught Rd Norwich Norfolk NR2 3BP",
    "addr:housenumber":"52",
    "addr:postcode":"nr2 3bp",
    "addr:street":"Connaught Rd",
    "iso:country":"GB",
    "sg:address":"52 Connaught Rd",
    "sg:city":"Norwich",
    "sg:classifiers":[
        {
            "category":"Professional",
            "subcategory":"Engineering",
            "type":"Services"
        }
    ],
    "sg:phone":"+44 1603 766424",
    "sg:postcode":"NR2 3BP",
    "sg:province":"Norfolk",
    "sg:tags":[
        "contractor",
        "electrical",
        "engineer"
    ],
    "wof:name":"Castle Electrical",
    "wof:placetype":"venue"
},
  "geometry": {"coordinates":[1.273641,52.632969],"type":"Point"}
}