{
  "type": "Feature",
  "properties": {
    "addr:full":"Transcript Mill Glenrothes Fife KY7 6QP",
    "addr:postcode":"ky7 6qp",
    "addr:street":"Transcript Mill",
    "iso:country":"GB",
    "sg:address":"Transcript Mill",
    "sg:city":"Glenrothes",
    "sg:classifiers":[
        {
            "category":"Manufacturing",
            "subcategory":"Paper Products",
            "type":"Manufacturing & Wholesale Goods"
        }
    ],
    "sg:phone":"+44 1592 754331",
    "sg:postcode":"KY7 6QP",
    "sg:province":"Fife",
    "sg:tags":[
        "mill",
        "pulp"
    ],
    "wof:name":"Sappi Europe Transcript Mill",
    "wof:placetype":"venue"
},
  "geometry": {"coordinates":[-3.1737439632,56.1972084045],"type":"Point"}
}