{
  "type": "Feature",
  "properties": {
    "addr:full":"3 Fortescue Road, Radstock Bath Somerset BA3 3PH",
    "addr:housenumber":"3",
    "addr:postcode":"ba3 3ph",
    "addr:street":"Fortescue Road",
    "iso:country":"GB",
    "sg:address":"3 Fortescue Road, Radstock",
    "sg:city":"Bath",
    "sg:classifiers":[
        {
            "category":"Shopping",
            "subcategory":"Florist",
            "type":"Retail Goods"
        }
    ],
    "sg:phone":"+44 1761 433241",
    "sg:postcode":"BA3 3PH",
    "sg:province":"Somerset",
    "wof:name":"Rebecca's Flower Shop",
    "wof:placetype":"venue"
},
  "geometry": {"coordinates":[-2.447419,51.291935],"type":"Point"}
}