{
  "type": "Feature",
  "properties": {
    "addr:full":"46 Windmill Rd Bedford Bedfordshire MK45 1AU",
    "addr:housenumber":"46",
    "addr:postcode":"mk45 1au",
    "addr:street":"Windmill Rd",
    "iso:country":"GB",
    "sg:address":"46 Windmill Rd",
    "sg:city":"Bedford",
    "sg:classifiers":[
        {
            "category":"Building & Trades",
            "subcategory":"Cleaning & Sanitation",
            "type":"Services"
        }
    ],
    "sg:phone":"+44 1525 712800",
    "sg:postcode":"MK45 1AU",
    "sg:province":"Bedfordshire",
    "sg:tags":[
        "commercial"
    ],
    "wof:name":"Whitehall Cleaning Services",
    "wof:placetype":"venue"
},
  "geometry": {"coordinates":[-0.502989,52.008652],"type":"Point"}
}