{
  "type": "Feature",
  "properties": {
    "addr:full":"Unit 3, West Devon Business Park Tavistock Devon PL19 9DP",
    "addr:housenumber":"unit 3",
    "addr:postcode":"pl19 9dp",
    "addr:street":"West;Park",
    "iso:country":"GB",
    "sg:address":"Unit 3, West Devon Business Park",
    "sg:city":"Tavistock",
    "sg:classifiers":[
        {
            "category":"Sports & Exercise",
            "subcategory":"Playing Field",
            "type":"Entertainment"
        }
    ],
    "sg:postcode":"PL19 9DP",
    "sg:province":"Devon",
    "sg:tags":[
        "sanitary",
        "hygiene",
        "appliance"
    ],
    "wof:name":"Tiles & Bathrooms Plus",
    "wof:placetype":"venue"
},
  "geometry": {"coordinates":[-4.1482372284,50.5381774902],"type":"Point"}
}