{
  "type": "Feature",
  "properties": {
    "iso:country":"GB",
    "sg:address":"Bencroft Gardens, Bremhill",
    "sg:city":"Calne",
    "sg:classifiers":[
        {
            "category":"Home & Garden",
            "subcategory":"Garden Supply",
            "type":"Retail Goods"
        }
    ],
    "sg:postcode":"SN11 9LH",
    "sg:province":"Wiltshire",
    "sg:tags":[
        "nursery",
        "centre"
    ],
    "wof:name":"Roger Hayward",
    "wof:placetype":"venue"
},
  "geometry": {"coordinates":[-2.0307838917,51.4569320679],"type":"Point"}
}