{
  "type": "Feature",
  "properties": {
    "iso:country":"GB",
    "sg:address":"103 Footshill Rd, Hanham",
    "sg:city":"Bristol",
    "sg:classifiers":[
        {
            "category":"Building & Trades",
            "subcategory":"Construction",
            "type":"Services"
        }
    ],
    "sg:phone":"+44 117 961 1871",
    "sg:postcode":"BS15 8HB",
    "sg:province":"City of Bristol",
    "sg:tags":[
        "builder"
    ],
    "wof:name":"L & N Lear",
    "wof:placetype":"venue"
},
  "geometry": {"coordinates":[-2.5149700642,51.4528503418],"type":"Point"}
}