{
  "type": "Feature",
  "properties": {
    "addr:full":"23a Preston Street Faversham Kent ME13 8NZ",
    "addr:housenumber":"23a",
    "addr:postcode":"me13 8nz",
    "addr:street":"Preston Street",
    "iso:country":"GB",
    "sg:address":"23a Preston Street",
    "sg:city":"Faversham",
    "sg:classifiers":[
        {
            "category":"Building & Trades",
            "subcategory":"Cleaning & Sanitation",
            "type":"Services"
        }
    ],
    "sg:phone":"+44 1795 590609",
    "sg:postcode":"ME13 8NZ",
    "sg:province":"Kent",
    "sg:tags":[
        "commercial"
    ],
    "wof:name":"Service Master C S Canterbury",
    "wof:placetype":"venue"
},
  "geometry": {"coordinates":[0.891193,51.313667],"type":"Point"}
}