{
  "type": "Feature",
  "properties": {
    "iso:country":"GB",
    "sg:address":"Barnsley Road, Ackworth",
    "sg:city":"Pontefract",
    "sg:classifiers":[
        {
            "category":"Health Services",
            "subcategory":"Doctor",
            "type":"Services"
        },
        {
            "category":"Health Services",
            "subcategory":"Clinic",
            "type":"Services"
        },
        {
            "category":"Home & Garden",
            "subcategory":"Home Furnishings",
            "type":"Retail Goods"
        }
    ],
    "sg:phone":"+44 1977 611023",
    "sg:postcode":"WF7 7HZ",
    "sg:province":"West Yorkshire",
    "sg:tags":[
        "nh",
        "furnishers",
        "planner",
        "practitioners",
        "kitchen"
    ],
    "wof:name":"College Lane Surgery",
    "wof:placetype":"venue"
},
  "geometry": {"coordinates":[-1.332687,53.648544],"type":"Point"}
}