{
  "type": "Feature",
  "properties": {
    "addr:full":"Sandringham, Guildford Road Woking Surrey GU22 7QL",
    "addr:postcode":"gu22 7ql",
    "addr:street":"Guildford Road",
    "iso:country":"GB",
    "sg:address":"Sandringham, Guildford Road",
    "sg:city":"Woking",
    "sg:classifiers":[
        {
            "category":"Professional",
            "subcategory":"Accounting & Tax Preparation",
            "type":"Services"
        }
    ],
    "sg:phone":"+44 1483 755000",
    "sg:postcode":"GU22 7QL",
    "sg:province":"Surrey",
    "sg:tags":[
        "accountant",
        "chartered"
    ],
    "wof:name":"Menzies Chartered Accountants",
    "wof:placetype":"venue"
},
  "geometry": {"coordinates":[-0.5594,51.315208],"type":"Point"}
}