{
  "type": "Feature",
  "properties": {
    "addr:full":"Vicarage Farm, Shotwick Village Road Chester Cheshire CH1 6HX",
    "addr:postcode":"ch1 6hx",
    "addr:street":"Village Road",
    "iso:country":"GB",
    "sg:address":"Vicarage Farm, Shotwick Village Road",
    "sg:city":"Chester",
    "sg:classifiers":[
        {
            "category":"Farming",
            "subcategory":"Dairy Farm",
            "type":"Manufacturing & Wholesale Goods"
        }
    ],
    "sg:postcode":"CH1 6HX",
    "sg:province":"Cheshire",
    "wof:name":"R H & C E Jones",
    "wof:placetype":"venue"
},
  "geometry": {"coordinates":[-2.9936840534,53.2397193909],"type":"Point"}
}