{
  "type": "Feature",
  "properties": {
    "iso:country":"GB",
    "sg:address":"27 Sopers Lane, Broadstone",
    "sg:city":"Poole",
    "sg:classifiers":[
        {
            "category":"Retail",
            "subcategory":"Repair Shop",
            "type":"Services"
        }
    ],
    "sg:postcode":"BH17 7EW",
    "sg:province":"Dorset",
    "sg:tags":[
        "upholsterer"
    ],
    "wof:name":"Alan K Ridout",
    "wof:placetype":"venue"
},
  "geometry": {"coordinates":[-1.98709,50.746891],"type":"Point"}
}