{
  "type": "Feature",
  "properties": {
    "iso:country":"GB",
    "sg:address":"10a Meer Street",
    "sg:city":"Stratford-upon-avon",
    "sg:classifiers":[
        {
            "category":"Home & Garden",
            "subcategory":"Home Furnishings",
            "type":"Retail Goods"
        }
    ],
    "sg:phone":"+44 1789 205517",
    "sg:postcode":"CV37 6QB",
    "sg:province":"Warwickshire",
    "sg:tags":[
        "furnishers",
        "planner",
        "kitchen"
    ],
    "wof:name":"Harvey Jones Kitchens",
    "wof:placetype":"venue"
},
  "geometry": {"coordinates":[-1.707929,52.193256],"type":"Point"}
}