{
  "type": "Feature",
  "properties": {
    "iso:country":"GB",
    "sg:address":"20 Westgate",
    "sg:city":"Chichester",
    "sg:classifiers":[
        {
            "category":"Health Services",
            "subcategory":"Health Practitioner",
            "type":"Services"
        }
    ],
    "sg:phone":"+44 1243 783040",
    "sg:postcode":"PO19 3EU",
    "sg:province":"West Sussex",
    "sg:tags":[
        "physiotherapist"
    ],
    "wof:name":"Griffiths Physiotherapy & Sports Injury Clinic",
    "wof:placetype":"venue"
},
  "geometry": {"coordinates":[-0.785134,50.837132],"type":"Point"}
}