{
  "type": "Feature",
  "properties": {
    "iso:country":"GB",
    "sg:address":"Units D & E, Shipley Wharf, Wharf Street",
    "sg:city":"Shipley",
    "sg:classifiers":[
        {
            "category":"Professional",
            "subcategory":"Engineering",
            "type":"Services"
        }
    ],
    "sg:phone":"+44 1274 531862",
    "sg:postcode":"BD17 7DW",
    "sg:province":"West Yorkshire",
    "sg:tags":[
        "design",
        "engineer"
    ],
    "wof:name":"Miko Oilfield Supplies Ltd.",
    "wof:placetype":"venue"
},
  "geometry": {"coordinates":[-1.7768800259,53.8355102539],"type":"Point"}
}