{
  "type": "Feature",
  "properties": {
    "addr:full":"8 Westgate Road, Belton Doncaster Lincolnshire DN9 1QG",
    "addr:housenumber":"8",
    "addr:postcode":"dn9 1qg",
    "addr:street":"Westgate Road",
    "iso:country":"GB",
    "sg:address":"8 Westgate Road, Belton",
    "sg:city":"Doncaster",
    "sg:classifiers":[
        {
            "category":"Organizations",
            "subcategory":"Professional Association",
            "type":"Services"
        }
    ],
    "sg:phone":"+44 1427 875187",
    "sg:postcode":"DN9 1QG",
    "sg:province":"Lincolnshire",
    "sg:tags":[
        "tech",
        "system",
        "automation"
    ],
    "wof:name":"L C Automation",
    "wof:placetype":"venue"
},
  "geometry": {"coordinates":[-0.8182089925,53.5569076538],"type":"Point"}
}