{
  "type": "Feature",
  "properties": {
    "addr:full":"65 Boutport Street Barnstaple Devon EX31 1HG",
    "addr:housenumber":"65",
    "addr:postcode":"ex31 1hg",
    "addr:street":"Boutport Street",
    "iso:country":"GB",
    "sg:address":"65 Boutport Street",
    "sg:city":"Barnstaple",
    "sg:classifiers":[
        {
            "category":"Shopping",
            "subcategory":"Books",
            "type":"Retail Goods"
        },
        {
            "category":"Shopping",
            "subcategory":"News",
            "type":"Retail Goods"
        }
    ],
    "sg:phone":"+44 1271 325867",
    "sg:postcode":"EX31 1HG",
    "sg:province":"Devon",
    "sg:tags":[
        "bookseller",
        "newsagent"
    ],
    "wof:name":"Doves",
    "wof:placetype":"venue"
},
  "geometry": {"coordinates":[-4.06102705,51.0828857422],"type":"Point"}
}