{
  "type": "Feature",
  "properties": {
    "addr:full":"194 Union St London Greater London SE1 0LH",
    "addr:housenumber":"194",
    "addr:postcode":"se1 0lh",
    "addr:street":"Union St",
    "iso:country":"GB",
    "sg:address":"194 Union St",
    "sg:city":"London",
    "sg:classifiers":[
        {
            "category":"Professional",
            "subcategory":"Management & Consulting",
            "type":"Services"
        }
    ],
    "sg:postcode":"SE1 0LH",
    "sg:province":"Greater London",
    "sg:tags":[
        "marketing",
        "consultant"
    ],
    "wof:name":"Contact Consultants",
    "wof:placetype":"venue"
},
  "geometry": {"coordinates":[-0.09893,51.503792],"type":"Point"}
}