{
  "type": "Feature",
  "properties": {
    "addr:full":"Telegraph Garage, 305 New Chester Rd, Little Sutton Ellesmere Port Cheshire CH66 1QQ",
    "addr:housenumber":"305",
    "addr:postcode":"ch66 1qq",
    "addr:street":"New Chester Rd",
    "iso:country":"GB",
    "sg:address":"Telegraph Garage, 305 New Chester Rd, Little Sutton",
    "sg:city":"Ellesmere Port",
    "sg:classifiers":[
        {
            "category":"Autos & Motor Vehicles",
            "subcategory":"Automobile Sales",
            "type":"Retail Goods"
        }
    ],
    "sg:phone":"+44 151 339 4506",
    "sg:postcode":"CH66 1QQ",
    "sg:province":"Cheshire",
    "sg:tags":[
        "commercial"
    ],
    "wof:name":"Red Lion Car Sales",
    "wof:placetype":"venue"
},
  "geometry": {"coordinates":[-2.9472100735,53.286190033],"type":"Point"}
}