{
  "type": "Feature",
  "properties": {
    "iso:country":"GB",
    "sg:address":"210 New Hall Lane",
    "sg:city":"Preston",
    "sg:classifiers":[
        {
            "category":"Cinema",
            "subcategory":"Movie Rental",
            "type":"Entertainment"
        }
    ],
    "sg:phone":"+44 1772 793287",
    "sg:postcode":"PR1 4SS",
    "sg:province":"Lancashire",
    "sg:tags":[
        "video",
        "library"
    ],
    "wof:name":"Star Sound & Vision",
    "wof:placetype":"venue"
},
  "geometry": {"coordinates":[-2.675746,53.763302],"type":"Point"}
}