{
  "type": "Feature",
  "properties": {
    "addr:full":"170 New Bond St London Greater London W1S 4RB",
    "addr:housenumber":"170",
    "addr:postcode":"w1s 4rb",
    "addr:street":"New Bond St",
    "iso:country":"GB",
    "sg:address":"170 New Bond St",
    "sg:city":"London",
    "sg:classifiers":[
        {
            "category":"Manufacturing",
            "subcategory":"Apparel",
            "type":"Manufacturing & Wholesale Goods"
        }
    ],
    "sg:postcode":"W1S 4RB",
    "sg:province":"Greater London",
    "sg:tags":[
        "garment",
        "designer"
    ],
    "wof:name":"Carmal Enterprises Ltd",
    "wof:placetype":"venue"
},
  "geometry": {"coordinates":[-0.1421409994,51.5098724365],"type":"Point"}
}