{
  "type": "Feature",
  "properties": {
    "iso:country":"GB",
    "sg:address":"24 St Phillip's Road",
    "sg:city":"Swindon",
    "sg:classifiers":[
        {
            "category":"Professional",
            "type":"Services"
        }
    ],
    "sg:postcode":"SN2 7QH",
    "sg:province":"Wiltshire",
    "sg:tags":[
        "reflexologists"
    ],
    "wof:name":"Beverly Brett",
    "wof:placetype":"venue"
},
  "geometry": {"coordinates":[-1.765938,51.557201],"type":"Point"}
}