{
  "type": "Feature",
  "properties": {
    "addr:full":"12 Green Lane Industrial Estate, Green Lane Letchworth Hertfordshire SG6 1HP",
    "addr:housenumber":"12",
    "addr:postcode":"sg6 1hp",
    "addr:street":"Green Lane Industrial Estate Green Lane",
    "iso:country":"GB",
    "sg:address":"12 Green Lane Industrial Estate, Green Lane",
    "sg:city":"Letchworth",
    "sg:classifiers":[
        {
            "category":"Professional",
            "subcategory":"Printing & Photocopies",
            "type":"Services"
        }
    ],
    "sg:phone":"+44 1462 686707",
    "sg:postcode":"SG6 1HP",
    "sg:province":"Hertfordshire",
    "sg:tags":[
        "process",
        "screen",
        "printer"
    ],
    "wof:name":"Dyprint",
    "wof:placetype":"venue"
},
  "geometry": {"coordinates":[-0.211218,51.990589],"type":"Point"}
}