{
  "type": "Feature",
  "properties": {
    "addr:full":"2a Randolph Place Edinburgh City of Edinburgh EH3 7TQ",
    "addr:housenumber":"2a",
    "addr:postcode":"eh3 7tq",
    "addr:street":"Randolph Place Edinburgh",
    "iso:country":"GB",
    "sg:address":"2a Randolph Place",
    "sg:city":"Edinburgh",
    "sg:classifiers":[
        {
            "category":"Personal",
            "type":"Services"
        }
    ],
    "sg:phone":"+44 131 226 1668",
    "sg:postcode":"EH3 7TQ",
    "sg:province":"City of Edinburgh",
    "sg:tags":[
        "slimming",
        "product"
    ],
    "wof:name":"Total Image Lifestyle Weight Control Programme",
    "wof:placetype":"venue"
},
  "geometry": {"coordinates":[-3.209782,55.951477],"type":"Point"}
}