{
  "type": "Feature",
  "properties": {
    "addr:full":"Belasis Business Centre, Coxwold Way, Belasis Hall Technology Park Billingham Durham TS23 4EA",
    "addr:postcode":"ts23 4ea",
    "addr:street":"Coxwold Way",
    "iso:country":"GB",
    "sg:address":"Belasis Business Centre, Coxwold Way, Belasis Hall Technology Park",
    "sg:city":"Billingham",
    "sg:classifiers":[
        {
            "category":"Professional",
            "subcategory":"Engineering",
            "type":"Services"
        }
    ],
    "sg:phone":"+44 1642 345640",
    "sg:postcode":"TS23 4EA",
    "sg:province":"Durham",
    "sg:tags":[
        "consulting",
        "engineer"
    ],
    "wof:name":"McLellan & Partners",
    "wof:placetype":"venue"
},
  "geometry": {"coordinates":[-1.2936450243,54.6068572998],"type":"Point"}
}