{
  "type": "Feature",
  "properties": {
    "iso:country":"GB",
    "sg:address":"46 Plassey Street",
    "sg:city":"Penarth",
    "sg:classifiers":[
        {
            "category":"Food & Beverages",
            "subcategory":"Specialty",
            "type":"Retail Goods"
        }
    ],
    "sg:postcode":"CF64 1EL",
    "sg:province":"The Vale of Glamorgan",
    "sg:tags":[
        "vegetarian"
    ],
    "wof:name":"Tomlins",
    "wof:placetype":"venue"
},
  "geometry": {"coordinates":[-3.177774,51.440887],"type":"Point"}
}