{
  "type": "Feature",
  "properties": {
    "addr:full":"13 Hillcrest Way, Buckingham Industrial Estate Buckingham Buckinghamshire MK18 1HJ",
    "addr:housenumber":"13",
    "addr:postcode":"mk18 1hj",
    "addr:street":"Hillcrest Way;Industrial Estate",
    "iso:country":"GB",
    "sg:address":"13 Hillcrest Way, Buckingham Industrial Estate",
    "sg:city":"Buckingham",
    "sg:classifiers":[
        {
            "category":"Wholesale",
            "subcategory":"Construction Materials",
            "type":"Manufacturing & Wholesale Goods"
        }
    ],
    "sg:phone":"+44 1280 823023",
    "sg:postcode":"MK18 1HJ",
    "sg:province":"Buckinghamshire",
    "sg:tags":[
        "merchant",
        "glass"
    ],
    "wof:name":"Buckingham Glass",
    "wof:placetype":"venue"
},
  "geometry": {"coordinates":[-0.981943,51.98621],"type":"Point"}
}