{
  "type": "Feature",
  "properties": {
    "iso:country":"GB",
    "sg:address":"Crab Lane, Bobbington",
    "sg:city":"Stourbridge",
    "sg:classifiers":[
        {
            "category":"Home & Garden",
            "subcategory":"Garden Supply",
            "type":"Retail Goods"
        }
    ],
    "sg:phone":"+44 1384 221543",
    "sg:postcode":"DY7 5DZ",
    "sg:province":"Shropshire",
    "sg:tags":[
        "nursery",
        "centre"
    ],
    "wof:name":"Haven Nurseries Ltd.",
    "wof:placetype":"venue"
},
  "geometry": {"coordinates":[-2.283994,52.511806],"type":"Point"}
}