{
  "type": "Feature",
  "properties": {
    "addr:full":"25 Lampits Hill Stanford-le-hope Essex SS17 9AA",
    "addr:housenumber":"25",
    "addr:postcode":"ss17 9aa",
    "addr:street":"Lampits Hill Stanford-Le-Hope",
    "iso:country":"GB",
    "sg:address":"25 Lampits Hill",
    "sg:city":"Stanford-le-hope",
    "sg:classifiers":[
        {
            "category":"Shopping",
            "subcategory":"Baby Store",
            "type":"Retail Goods"
        }
    ],
    "sg:postcode":"SS17 9AA",
    "sg:province":"Essex",
    "sg:tags":[
        "babywear",
        "childrens"
    ],
    "wof:name":"Lyneye",
    "wof:placetype":"venue"
},
  "geometry": {"coordinates":[0.455332,51.531612],"type":"Point"}
}