{
  "type": "Feature",
  "properties": {
    "iso:country":"GB",
    "sg:address":"Hedge End, Thanet Way, St. Nicholas At Wade",
    "sg:city":"Birchington",
    "sg:classifiers":[
        {
            "category":"Manufacturing",
            "subcategory":"Buildings",
            "type":"Manufacturing & Wholesale Goods"
        }
    ],
    "sg:phone":"+44 1843 845649",
    "sg:postcode":"CT7 0NB",
    "sg:province":"Kent",
    "sg:tags":[
        "sectional"
    ],
    "wof:name":"Pinelodge Construction Ltd",
    "wof:placetype":"venue"
},
  "geometry": {"coordinates":[1.308942,51.374016],"type":"Point"}
}