{
  "type": "Feature",
  "properties": {
    "addr:full":"85 East St Newton Abbot Devon TQ12 2JR",
    "addr:housenumber":"85",
    "addr:postcode":"tq12 2jr",
    "addr:street":"East St",
    "iso:country":"GB",
    "sg:address":"85 East St",
    "sg:city":"Newton Abbot",
    "sg:classifiers":[
        {
            "category":"Manufacturing",
            "subcategory":"Signs",
            "type":"Manufacturing & Wholesale Goods"
        }
    ],
    "sg:phone":"+44 1626 364228",
    "sg:postcode":"TQ12 2JR",
    "sg:province":"Devon",
    "sg:tags":[
        "commercial",
        "maker"
    ],
    "wof:name":"Abbot Signs",
    "wof:placetype":"venue"
},
  "geometry": {"coordinates":[-3.608289,50.528912],"type":"Point"}
}