{
  "type": "Feature",
  "properties": {
    "addr:full":"45 Totnes Road Paignton Devon TQ4 5LA",
    "addr:housenumber":"45",
    "addr:postcode":"tq4 5la",
    "addr:street":"Totnes Road",
    "iso:country":"GB",
    "sg:address":"45 Totnes Road",
    "sg:city":"Paignton",
    "sg:classifiers":[
        {
            "category":"Autos & Motor Vehicles",
            "subcategory":"Automobile Sales",
            "type":"Retail Goods"
        }
    ],
    "sg:phone":"+44 1803 554484",
    "sg:postcode":"TQ4 5LA",
    "sg:province":"Devon",
    "sg:tags":[
        "car"
    ],
    "wof:name":"Torbay Motors Ltd.",
    "wof:placetype":"venue"
},
  "geometry": {"coordinates":[-3.571408,50.433285],"type":"Point"}
}