{
  "type": "Feature",
  "properties": {
    "iso:country":"GB",
    "sg:address":"52 St Giles Street",
    "sg:city":"Norwich",
    "sg:classifiers":[
        {
            "category":"Restaurant",
            "type":"Food & Drink"
        }
    ],
    "sg:phone":"+44 1603 617199",
    "sg:postcode":"NR2 1LW",
    "sg:province":"Norfolk",
    "wof:name":"Andreas Villia",
    "wof:placetype":"venue"
},
  "geometry": {"coordinates":[1.2890939713,52.629196167],"type":"Point"}
}