{
  "type": "Feature",
  "properties": {
    "iso:country":"GB",
    "sg:address":"13 Athersley Managed Workshops, Wingfield Road",
    "sg:city":"Barnsley",
    "sg:classifiers":[
        {
            "category":"Communications",
            "subcategory":"Film & Video Production",
            "type":"Services"
        }
    ],
    "sg:phone":"+44 1226 284483",
    "sg:postcode":"S71 3PN",
    "sg:province":"South Yorkshire",
    "sg:tags":[
        "microfilming"
    ],
    "wof:name":"New Systems",
    "wof:placetype":"venue"
},
  "geometry": {"coordinates":[-1.465282,53.573841],"type":"Point"}
}