{
  "type": "Feature",
  "properties": {
    "addr:full":"Holt Hill, Beoley Redditch Warwickshire B98 9AT",
    "addr:postcode":"b98 9at",
    "addr:street":"Holt Hill",
    "iso:country":"GB",
    "sg:address":"Holt Hill, Beoley",
    "sg:city":"Redditch",
    "sg:classifiers":[
        {
            "category":"Bars & Pubs",
            "type":"Food & Drink"
        }
    ],
    "sg:phone":"+44 1527 67227",
    "sg:postcode":"B98 9AT",
    "sg:province":"Warwickshire",
    "sg:tags":[
        "pubs",
        "inn"
    ],
    "wof:name":"Whitbread Group Plc",
    "wof:placetype":"venue"
},
  "geometry": {"coordinates":[-1.906234026,52.3238983154],"type":"Point"}
}