{
  "type": "Feature",
  "properties": {
    "addr:full":"8 Surrey Gro Bradford West Yorkshire BD5 7EJ",
    "addr:housenumber":"8",
    "addr:postcode":"bd5 7ej",
    "addr:street":"Surrey Gro Bradford West",
    "iso:country":"GB",
    "sg:address":"8 Surrey Gro",
    "sg:city":"Bradford",
    "sg:classifiers":[
        {
            "category":"Health Services",
            "subcategory":"Health Practitioner",
            "type":"Services"
        }
    ],
    "sg:phone":"+44 1274 394822",
    "sg:postcode":"BD5 7EJ",
    "sg:province":"West Yorkshire",
    "sg:tags":[
        "psychotherapist"
    ],
    "wof:name":"Cairns Personal Counselling Service (The)",
    "wof:placetype":"venue"
},
  "geometry": {"coordinates":[-1.75177598,53.7813873291],"type":"Point"}
}