{
  "type": "Feature",
  "properties": {
    "addr:full":"Randells Hotel, Keighley Road Skipton Lancashire BD23 2TA",
    "addr:postcode":"bd23 2ta",
    "addr:street":"Keighley Road",
    "iso:country":"GB",
    "sg:address":"Randells Hotel, Keighley Road",
    "sg:city":"Skipton",
    "sg:classifiers":[
        {
            "category":"Personal",
            "subcategory":"Beauty Salon",
            "type":"Services"
        }
    ],
    "sg:phone":"+44 1756 796848",
    "sg:postcode":"BD23 2TA",
    "sg:province":"Lancashire",
    "sg:tags":[
        "unisex",
        "hairdresser"
    ],
    "wof:name":"Melanie Topp",
    "wof:placetype":"venue"
},
  "geometry": {"coordinates":[-2.0185139179,53.9602012634],"type":"Point"}
}