{
  "type": "Feature",
  "properties": {
    "addr:full":"38 Park Road Chorley Lancashire PR7 1QU",
    "addr:housenumber":"38",
    "addr:postcode":"pr7 1qu",
    "addr:street":"Park Road",
    "iso:country":"GB",
    "sg:address":"38 Park Road",
    "sg:city":"Chorley",
    "sg:classifiers":[
        {
            "category":"Health Services",
            "subcategory":"Dentist",
            "type":"Services"
        }
    ],
    "sg:phone":"+44 1257 262152",
    "sg:postcode":"PR7 1QU",
    "sg:province":"Lancashire",
    "wof:name":"Reeves Dental Practice",
    "wof:placetype":"venue"
},
  "geometry": {"coordinates":[-2.6312420368,53.6583976746],"type":"Point"}
}