{
  "type": "Feature",
  "properties": {
    "addr:full":"221 East Park Road Leicester Leicestershire LE5 5AZ",
    "addr:housenumber":"221",
    "addr:postcode":"le5 5az",
    "addr:street":"East Park Road",
    "iso:country":"GB",
    "sg:address":"221 East Park Road",
    "sg:city":"Leicester",
    "sg:classifiers":[
        {
            "category":"Health Services",
            "subcategory":"Optometrist",
            "type":"Services"
        },
        {
            "category":"Shopping",
            "subcategory":"Optician",
            "type":"Retail Goods"
        }
    ],
    "sg:phone":"+44 116 254 2330",
    "sg:postcode":"LE5 5AZ",
    "sg:province":"Leicestershire",
    "sg:tags":[
        "ophthalmic"
    ],
    "wof:name":"Vision Aid Centre",
    "wof:placetype":"venue"
},
  "geometry": {"coordinates":[-1.1076509953,52.629322052],"type":"Point"}
}