{
  "type": "Feature",
  "properties": {
    "addr:full":"Brook Cottage, Chelmsford Road, Barnston Dunmow Essex CM6 1LW",
    "addr:postcode":"cm6 1lw",
    "addr:street":"Chelmsford Road",
    "iso:country":"GB",
    "sg:address":"Brook Cottage, Chelmsford Road, Barnston",
    "sg:city":"Dunmow",
    "sg:classifiers":[
        {
            "category":"Retail",
            "subcategory":"Auto Repair",
            "type":"Services"
        }
    ],
    "sg:postcode":"CM6 1LW",
    "sg:province":"Essex",
    "sg:tags":[
        "garage"
    ],
    "wof:name":"T J Hockley",
    "wof:placetype":"venue"
},
  "geometry": {"coordinates":[0.364977,51.870613],"type":"Point"}
}