{
  "type": "Feature",
  "properties": {
    "addr:full":"170 Main Street, Rutherglen Glasgow Glasgow City G73 2HW",
    "addr:housenumber":"170",
    "addr:postcode":"g73 2hw",
    "addr:street":"Main Street",
    "iso:country":"GB",
    "sg:address":"170 Main Street, Rutherglen",
    "sg:city":"Glasgow",
    "sg:classifiers":[
        {
            "category":"Shopping",
            "subcategory":"Shoes",
            "type":"Retail Goods"
        }
    ],
    "sg:phone":"+44 141 643 1996",
    "sg:postcode":"G73 2HW",
    "sg:province":"Glasgow City",
    "sg:tags":[
        "shop"
    ],
    "wof:name":"Feet & Co",
    "wof:placetype":"venue"
},
  "geometry": {"coordinates":[-4.2132720947,55.8283233643],"type":"Point"}
}