{
  "type": "Feature",
  "properties": {
    "iso:country":"GB",
    "sg:address":"Prestwood",
    "sg:city":"Stourbridge",
    "sg:classifiers":[
        {
            "category":"Health Services",
            "subcategory":"Nursing And Care Facility",
            "type":"Services"
        }
    ],
    "sg:phone":"+44 1384 877440",
    "sg:postcode":"DY7 5AL",
    "sg:province":"Shropshire",
    "sg:tags":[
        "home"
    ],
    "wof:name":"Prestwood Nursing Home & Coach House",
    "wof:placetype":"venue"
},
  "geometry": {"coordinates":[-2.190358,52.468052],"type":"Point"}
}