{
  "type": "Feature",
  "properties": {
    "addr:full":"1b Nightingales Corner, Little Chalfont Amersham Buckinghamshire HP7 9PY",
    "addr:housenumber":"1b",
    "addr:postcode":"hp7 9py",
    "addr:street":"Nightingales Corner",
    "iso:country":"GB",
    "sg:address":"1b Nightingales Corner, Little Chalfont",
    "sg:city":"Amersham",
    "sg:classifiers":[
        {
            "category":"Professional",
            "subcategory":"Lawyer & Legal Services",
            "type":"Services"
        }
    ],
    "sg:phone":"+44 1727 832830",
    "sg:postcode":"HP7 9PY",
    "sg:province":"Buckinghamshire",
    "sg:tags":[
        "solicitor"
    ],
    "wof:name":"Peters & Co.",
    "wof:placetype":"venue"
},
  "geometry": {"coordinates":[-0.5666720271,51.6673812866],"type":"Point"}
}