{
  "type": "Feature",
  "properties": {
    "addr:full":"34-36 Elm Rd Leigh On Sea Essex SS9 1SN",
    "addr:housenumber":"34-36",
    "addr:postcode":"ss9 1sn",
    "addr:street":"Elm Rd",
    "iso:country":"GB",
    "sg:address":"34-36 Elm Rd",
    "sg:city":"Leigh On Sea",
    "sg:classifiers":[
        {
            "category":"Restaurant",
            "type":"Food & Drink"
        }
    ],
    "sg:phone":"+44 1702 711141",
    "sg:postcode":"SS9 1SN",
    "sg:province":"Essex",
    "wof:name":"Rococo Mobile",
    "wof:placetype":"venue"
},
  "geometry": {"coordinates":[0.6544560194,51.5420379639],"type":"Point"}
}