{
  "type": "Feature",
  "properties": {
    "iso:country":"GB",
    "sg:address":"2 Court Road",
    "sg:city":"Bridgend",
    "sg:classifiers":[
        {
            "category":"Real Estate",
            "subcategory":"Developer",
            "type":"Services"
        }
    ],
    "sg:phone":"+44 1656 661178",
    "sg:postcode":"CF31 1BN",
    "sg:province":"Bridgend",
    "sg:tags":[
        "property"
    ],
    "wof:name":"la'pec Properties (Bridgend) Ltd.",
    "wof:placetype":"venue"
},
  "geometry": {"coordinates":[-3.5764451027,51.5059051514],"type":"Point"}
}