{
  "type": "Feature",
  "properties": {
    "iso:country":"GB",
    "sg:address":"2 Woodford Road",
    "sg:city":"Watford",
    "sg:classifiers":[
        {
            "category":"Bars & Pubs",
            "type":"Food & Drink"
        },
        {
            "category":"Travel",
            "subcategory":"Hotels & Motels",
            "type":"Entertainment"
        }
    ],
    "sg:phone":"+44 1923 253091",
    "sg:postcode":"WD17 1PA",
    "sg:province":"Hertfordshire",
    "sg:tags":[
        "pubs",
        "inn"
    ],
    "wof:name":"Wellington Arms Hotel",
    "wof:placetype":"venue"
},
  "geometry": {"coordinates":[-0.394457,51.661625],"type":"Point"}
}