{
  "type": "Feature",
  "properties": {
    "iso:country":"GB",
    "sg:address":"31 Horsforth Avenue",
    "sg:city":"Bridlington",
    "sg:classifiers":[
        {
            "category":"Travel",
            "subcategory":"Hotels & Motels",
            "type":"Entertainment"
        }
    ],
    "sg:postcode":"YO15 3DG",
    "sg:province":"East Riding of Yorkshire",
    "wof:name":"Abbey Court",
    "wof:placetype":"venue"
},
  "geometry": {"coordinates":[-0.19915,54.079041],"type":"Point"}
}