{
  "type": "Feature",
  "properties": {
    "iso:country":"GB",
    "sg:address":"Memory Lane",
    "sg:city":"Leicester",
    "sg:classifiers":[
        {
            "category":"Autos & Motor Vehicles",
            "subcategory":"Automobile Sales",
            "type":"Retail Goods"
        }
    ],
    "sg:phone":"+44 116 253 6214",
    "sg:postcode":"LE1 3UL",
    "sg:province":"Leicestershire",
    "sg:tags":[
        "car"
    ],
    "wof:name":"Sunbeam Supreme",
    "wof:placetype":"venue"
},
  "geometry": {"coordinates":[-1.128449,52.642986],"type":"Point"}
}