{
  "type": "Feature",
  "properties": {
    "addr:full":"Sallyvonteen Touchie Farm Kinross Clackmannanshire KY13 0RS",
    "addr:postcode":"ky13 0rs",
    "iso:country":"GB",
    "sg:address":"Sallyvonteen Touchie Farm",
    "sg:city":"Kinross",
    "sg:classifiers":[
        {
            "category":"Farming",
            "subcategory":"Livestock Farm",
            "type":"Manufacturing & Wholesale Goods"
        }
    ],
    "sg:postcode":"KY13 0RS",
    "sg:province":"Clackmannanshire",
    "sg:tags":[
        "others"
    ],
    "wof:name":"A B Dawson",
    "wof:placetype":"venue"
},
  "geometry": {"coordinates":[-3.4255139828,56.2113265991],"type":"Point"}
}