{
  "type": "Feature",
  "properties": {
    "iso:country":"GB",
    "sg:address":"1 Linden Road",
    "sg:city":"Bognor Regis",
    "sg:classifiers":[
        {
            "category":"Fast Food",
            "type":"Food & Drink"
        },
        {
            "category":"Food & Beverages",
            "subcategory":"Meat & Fish",
            "type":"Retail Goods"
        }
    ],
    "sg:phone":"+44 1243 865610",
    "sg:postcode":"PO21 2AL",
    "sg:province":"West Sussex",
    "sg:tags":[
        "shop",
        "chip"
    ],
    "wof:name":"Linden Fisheries",
    "wof:placetype":"venue"
},
  "geometry": {"coordinates":[-0.676966,50.78632],"type":"Point"}
}