{
  "type": "Feature",
  "properties": {
    "addr:full":"The Granary, Jericho Farm, Cassington Oxford Oxfordshire OX29 4EB",
    "addr:postcode":"ox29 4eb",
    "iso:country":"GB",
    "sg:address":"The Granary, Jericho Farm, Cassington",
    "sg:city":"Oxford",
    "sg:classifiers":[
        {
            "category":"Professional",
            "subcategory":"Management & Consulting",
            "type":"Services"
        }
    ],
    "sg:phone":"+44 1865 880024",
    "sg:postcode":"OX29 4EB",
    "sg:province":"Oxfordshire",
    "sg:tags":[
        "marketing",
        "consultant"
    ],
    "wof:name":"Dakota Marketing Services Ltd",
    "wof:placetype":"venue"
},
  "geometry": {"coordinates":[-1.350479,51.78965],"type":"Point"}
}