{
  "type": "Feature",
  "properties": {
    "addr:full":"31 Webster Avenue Scunthorpe Lincolnshire DN15 7DX",
    "addr:housenumber":"31",
    "addr:postcode":"dn15 7dx",
    "addr:street":"Webster Avenue",
    "iso:country":"GB",
    "sg:address":"31 Webster Avenue",
    "sg:city":"Scunthorpe",
    "sg:classifiers":[
        {
            "category":"Banks & Credit Unions",
            "subcategory":"Financial Services",
            "type":"Services"
        }
    ],
    "sg:phone":"+44 1724 856700",
    "sg:postcode":"DN15 7DX",
    "sg:province":"Lincolnshire",
    "sg:tags":[
        "adviser"
    ],
    "wof:name":"D N P Hornsby Independent Financial Management",
    "wof:placetype":"venue"
},
  "geometry": {"coordinates":[-0.66653198,53.5887374878],"type":"Point"}
}