{
  "type": "Feature",
  "properties": {
    "iso:country":"GB",
    "sg:address":"10 Victoria Rd",
    "sg:city":"Sidmouth",
    "sg:classifiers":[
        {
            "category":"Place Of Worship",
            "type":"Public Place"
        }
    ],
    "sg:phone":"+44 1395 513384",
    "sg:postcode":"EX10 8TZ",
    "sg:province":"Devon",
    "wof:name":"Sidmouth Methodist Church",
    "wof:placetype":"venue"
},
  "geometry": {"coordinates":[-3.239752,50.684376],"type":"Point"}
}