{
  "type": "Feature",
  "properties": {
    "iso:country":"GB",
    "sg:address":"The Warehouse, 12 Ravensbury Terrace",
    "sg:city":"Wandsworth",
    "sg:classifiers":[
        {
            "category":"Professional",
            "subcategory":"Management & Consulting",
            "type":"Services"
        }
    ],
    "sg:phone":"+44 20 8944 7808",
    "sg:postcode":"SW18 4RL",
    "sg:province":"Greater London",
    "sg:tags":[
        "consultant",
        "business"
    ],
    "wof:name":"Lynn Carter Business Development",
    "wof:placetype":"venue"
},
  "geometry": {"coordinates":[-0.1944790035,51.4568710327],"type":"Point"}
}