{
  "type": "Feature",
  "properties": {
    "addr:full":"The Railway Gates, Norwood Road March Cambridgeshire PE15 8QH",
    "addr:postcode":"pe15 8qh",
    "addr:street":"Norwood Road",
    "iso:country":"GB",
    "sg:address":"The Railway Gates, Norwood Road",
    "sg:city":"March",
    "sg:classifiers":[
        {
            "category":"Manufacturing",
            "subcategory":"Building Materials",
            "type":"Manufacturing & Wholesale Goods"
        }
    ],
    "sg:phone":"+44 1354 656000",
    "sg:postcode":"PE15 8QH",
    "sg:province":"Cambridgeshire",
    "sg:tags":[
        "merchant",
        "builder"
    ],
    "wof:name":"Plastic Pipe Supplies Ltd",
    "wof:placetype":"venue"
},
  "geometry": {"coordinates":[0.088905,52.551254],"type":"Point"}
}