{
  "type": "Feature",
  "properties": {
    "addr:full":"5 Smithills Hall Clo Bury Lancashire BL0 9FF",
    "addr:housenumber":"5",
    "addr:postcode":"bl0 9ff",
    "addr:street":"Smithills Hall Clo",
    "iso:country":"GB",
    "sg:address":"5 Smithills Hall Clo",
    "sg:city":"Bury",
    "sg:classifiers":[
        {
            "category":"Professional",
            "type":"Services"
        }
    ],
    "sg:phone":"+44 1706 821803",
    "sg:postcode":"BL0 9FF",
    "sg:province":"Lancashire",
    "sg:tags":[
        "entertainer"
    ],
    "wof:name":"Clara Clowns Puppet Parties",
    "wof:placetype":"venue"
},
  "geometry": {"coordinates":[-2.3190391064,53.64037323],"type":"Point"}
}