{
  "type": "Feature",
  "properties": {
    "addr:full":"The Courtyard, Chester Rd Wrexham Wrexham LL12 0HH",
    "addr:postcode":"ll12 0hh",
    "addr:street":"Chester Rd",
    "iso:country":"GB",
    "sg:address":"The Courtyard, Chester Rd",
    "sg:city":"Wrexham",
    "sg:classifiers":[
        {
            "category":"Professional",
            "subcategory":"Management & Consulting",
            "type":"Services"
        }
    ],
    "sg:phone":"+44 1244 571541",
    "sg:postcode":"LL12 0HH",
    "sg:province":"Wrexham",
    "sg:tags":[
        "consultant",
        "business"
    ],
    "wof:name":"Finanacial Management For Business",
    "wof:placetype":"venue"
},
  "geometry": {"coordinates":[-2.9498300552,53.1046600342],"type":"Point"}
}