{
  "type": "Feature",
  "properties": {
    "iso:country":"GB",
    "sg:address":"12 Dukes Road, Cambuslang",
    "sg:city":"Glasgow",
    "sg:classifiers":[
        {
            "category":"Organizations",
            "subcategory":"Community Association",
            "type":"Services"
        }
    ],
    "sg:phone":"+44 141 641 5068",
    "sg:postcode":"G72 7BA",
    "sg:province":"South Lanarkshire",
    "sg:tags":[
        "society",
        "housing"
    ],
    "wof:name":"Wellshot & Silverbanks Tennants Co-Operative",
    "wof:placetype":"venue"
},
  "geometry": {"coordinates":[-4.184375,55.821362],"type":"Point"}
}