{
  "type": "Feature",
  "properties": {
    "addr:full":"Probation Centre, 27 Argyle St Newport Newport NP20 5NE",
    "addr:housenumber":"27",
    "addr:postcode":"np20 5ne",
    "addr:street":"Argyle St",
    "iso:country":"GB",
    "sg:address":"Probation Centre, 27 Argyle St",
    "sg:city":"Newport",
    "sg:classifiers":[
        {
            "category":"Government",
            "subcategory":"Police Station",
            "type":"Public Place"
        }
    ],
    "sg:phone":"+44 1633 821394",
    "sg:postcode":"NP20 5NE",
    "sg:province":"Newport",
    "sg:tags":[
        "support"
    ],
    "wof:name":"The Probation Service",
    "wof:placetype":"venue"
},
  "geometry": {"coordinates":[-2.99589,51.598911],"type":"Point"}
}