{
  "type": "Feature",
  "properties": {
    "addr:full":"20 Crouch End Hill London Greater London N8 8AA",
    "addr:housenumber":"20",
    "addr:postcode":"n8 8aa",
    "addr:street":"Crouch",
    "iso:country":"GB",
    "sg:address":"20 Crouch End Hill",
    "sg:city":"London",
    "sg:classifiers":[
        {
            "category":"Food & Beverages",
            "subcategory":"Meat & Fish",
            "type":"Retail Goods"
        }
    ],
    "sg:phone":"+44 20 8342 8181",
    "sg:postcode":"N8 8AA",
    "sg:province":"Greater London",
    "sg:tags":[
        "butcher"
    ],
    "wof:name":"la Bottega Ltd.",
    "wof:placetype":"venue"
},
  "geometry": {"coordinates":[-0.12461,51.57785],"type":"Point"}
}