{
  "type": "Feature",
  "properties": {
    "addr:full":"35 Celia Heights Bodmin Cornwall PL31 1EH",
    "addr:housenumber":"35",
    "addr:postcode":"pl31 1eh",
    "addr:street":"Celia Heights",
    "iso:country":"GB",
    "sg:address":"35 Celia Heights",
    "sg:city":"Bodmin",
    "sg:classifiers":[
        {
            "category":"Taxi",
            "type":"Transportation"
        }
    ],
    "sg:phone":"+44 1208 77340",
    "sg:postcode":"PL31 1EH",
    "sg:province":"Cornwall",
    "sg:tags":[
        "mini",
        "cab"
    ],
    "wof:name":"Bodmin Station Taxi",
    "wof:placetype":"venue"
},
  "geometry": {"coordinates":[-4.7089109421,50.4620819092],"type":"Point"}
}