{
  "type": "Feature",
  "properties": {
    "iso:country":"GB",
    "sg:address":"Norwich Close",
    "sg:city":"Lichfield",
    "sg:classifiers":[
        {
            "category":"Shopping",
            "subcategory":"Pharmacy",
            "type":"Retail Goods"
        }
    ],
    "sg:phone":"+44 1543 257536",
    "sg:postcode":"WS13 7SJ",
    "sg:province":"Staffordshire",
    "sg:tags":[
        "medicine",
        "therapy"
    ],
    "wof:name":"Bowen Technique By Cherie Niven",
    "wof:placetype":"venue"
},
  "geometry": {"coordinates":[-1.821479,52.699863],"type":"Point"}
}