{
  "type": "Feature",
  "properties": {
    "iso:country":"GB",
    "sg:address":"136 Marsh Lane",
    "sg:city":"Stanmore",
    "sg:classifiers":[
        {
            "category":"Health Services",
            "subcategory":"Doctor",
            "type":"Services"
        },
        {
            "category":"Health Services",
            "subcategory":"Dentist",
            "type":"Services"
        }
    ],
    "sg:phone":"+44 20 8954 2010",
    "sg:postcode":"HA7 4HP",
    "sg:province":"Greater London",
    "wof:name":"PETER RABIN",
    "wof:placetype":"venue"
},
  "geometry": {"coordinates":[-0.3054400086,51.6130065918],"type":"Point"}
}