{
  "type": "Feature",
  "properties": {
    "iso:country":"GB",
    "sg:address":"1 Gay Meadows, Stockton On The Forest",
    "sg:city":"York",
    "sg:classifiers":[
        {
            "category":"Professional",
            "subcategory":"Engineering",
            "type":"Services"
        }
    ],
    "sg:phone":"+44 1904 400144",
    "sg:postcode":"YO32 9UJ",
    "sg:province":"North Yorkshire",
    "sg:tags":[
        "contractor",
        "electrical",
        "engineer"
    ],
    "wof:name":"Simpson & Wood",
    "wof:placetype":"venue"
},
  "geometry": {"coordinates":[-1.0025670528,53.9922676086],"type":"Point"}
}