{
  "type": "Feature",
  "properties": {
    "addr:full":"89 Derby Road, Risley Derby Derbyshire DE72 3SY",
    "addr:housenumber":"89",
    "addr:postcode":"de72 3sy",
    "addr:street":"Derby Road",
    "iso:country":"GB",
    "sg:address":"89 Derby Road, Risley",
    "sg:city":"Derby",
    "sg:classifiers":[
        {
            "category":"Education",
            "subcategory":"Special Training",
            "type":"Public Place"
        }
    ],
    "sg:phone":"+44 115 916 0311",
    "sg:postcode":"DE72 3SY",
    "sg:province":"Derbyshire",
    "sg:tags":[
        "product",
        "centre"
    ],
    "wof:name":"Dale Carnegie Training",
    "wof:placetype":"venue"
},
  "geometry": {"coordinates":[-1.313305,52.916641],"type":"Point"}
}