{
  "type": "Feature",
  "properties": {
    "addr:full":"23 Rangeway Avenue Blackpool Lancashire FY4 2DJ",
    "addr:housenumber":"23",
    "addr:postcode":"fy4 2dj",
    "addr:street":"Rangeway Avenue",
    "iso:country":"GB",
    "sg:address":"23 Rangeway Avenue",
    "sg:city":"Blackpool",
    "sg:classifiers":[
        {
            "category":"Home & Garden",
            "subcategory":"Building Materials",
            "type":"Retail Goods"
        }
    ],
    "sg:postcode":"FY4 2DJ",
    "sg:province":"Lancashire",
    "sg:tags":[
        "insulation",
        "installers"
    ],
    "wof:name":"Winglaw Ltd",
    "wof:placetype":"venue"
},
  "geometry": {"coordinates":[-3.044166,53.791744],"type":"Point"}
}