{
  "type": "Feature",
  "properties": {
    "addr:full":"18 Lambolle Place London Greater London NW3 4PG",
    "addr:housenumber":"18",
    "addr:postcode":"nw3 4pg",
    "addr:street":"Lambolle Place",
    "iso:country":"GB",
    "sg:address":"18 Lambolle Place",
    "sg:city":"London",
    "sg:classifiers":[
        {
            "category":"Health Services",
            "subcategory":"Health Practitioner",
            "type":"Services"
        }
    ],
    "sg:phone":"+44 20 7483 3568",
    "sg:postcode":"NW3 4PG",
    "sg:province":"Greater London",
    "sg:tags":[
        "acupuncture"
    ],
    "wof:name":"Janine Norris",
    "wof:placetype":"venue"
},
  "geometry": {"coordinates":[-0.164954,51.546192],"type":"Point"}
}