{
  "type": "Feature",
  "properties": {
    "addr:full":"Gas Lane Swindon Gloucestershire SN6 6BY",
    "addr:postcode":"sn6 6by",
    "addr:street":"Gas Lane",
    "iso:country":"GB",
    "sg:address":"Gas Lane",
    "sg:city":"Swindon",
    "sg:classifiers":[
        {
            "category":"Manufacturing",
            "subcategory":"Wood Products",
            "type":"Manufacturing & Wholesale Goods"
        }
    ],
    "sg:postcode":"SN6 6BY",
    "sg:province":"Gloucestershire",
    "sg:tags":[
        "maker",
        "cabinet"
    ],
    "wof:name":"Cricklade Craft Workshop",
    "wof:placetype":"venue"
},
  "geometry": {"coordinates":[-1.8565969467,51.6425666809],"type":"Point"}
}