{
  "type": "Feature",
  "properties": {
    "iso:country":"GB",
    "sg:address":"Laurel Farm, Stone Street, Spexhall",
    "sg:city":"Halesworth",
    "sg:classifiers":[
        {
            "category":"Farming",
            "subcategory":"Farm",
            "type":"Manufacturing & Wholesale Goods"
        }
    ],
    "sg:postcode":"IP19 0RN",
    "sg:province":"Suffolk",
    "sg:tags":[
        "mixed",
        "crop"
    ],
    "wof:name":"M O & P Gardner",
    "wof:placetype":"venue"
},
  "geometry": {"coordinates":[1.492938,52.367741],"type":"Point"}
}