{
  "type": "Feature",
  "properties": {
    "addr:full":"25 Hill Top Rise, Grenoside Sheffield South Yorkshire S35 8PD",
    "addr:housenumber":"25",
    "addr:postcode":"s35 8pd",
    "addr:street":"Hill Top Rise",
    "iso:country":"GB",
    "sg:address":"25 Hill Top Rise, Grenoside",
    "sg:city":"Sheffield",
    "sg:classifiers":[
        {
            "category":"Professional",
            "subcategory":"Management & Consulting",
            "type":"Services"
        }
    ],
    "sg:phone":"+44 114 257 8282",
    "sg:postcode":"S35 8PD",
    "sg:province":"South Yorkshire",
    "sg:tags":[
        "consultant",
        "business"
    ],
    "wof:name":"McL Consultancy Ltd.",
    "wof:placetype":"venue"
},
  "geometry": {"coordinates":[-1.490593,53.437061],"type":"Point"}
}