{
  "type": "Feature",
  "properties": {
    "addr:full":"21 Warminster Road Sheffield Derbyshire S8 9BJ",
    "addr:housenumber":"21",
    "addr:postcode":"s8 9bj",
    "addr:street":"Warminster Road",
    "iso:country":"GB",
    "sg:address":"21 Warminster Road",
    "sg:city":"Sheffield",
    "sg:classifiers":[
        {
            "category":"Insurance",
            "subcategory":"Insurance Agent",
            "type":"Services"
        }
    ],
    "sg:phone":"+44 114 255 0303",
    "sg:postcode":"S8 9BJ",
    "sg:province":"Derbyshire",
    "wof:name":"The Scottish Amicable Life Assurance Society",
    "wof:placetype":"venue"
},
  "geometry": {"coordinates":[-1.470543,53.350311],"type":"Point"}
}