{
  "type": "Feature",
  "properties": {
    "iso:country":"GB",
    "sg:address":"40 Albert Square",
    "sg:city":"Rugby",
    "sg:classifiers":[
        {
            "category":"Bars & Pubs",
            "type":"Food & Drink"
        },
        {
            "category":"Community Center",
            "subcategory":"Social",
            "type":"Public Place"
        }
    ],
    "sg:phone":"+44 1788 544789",
    "sg:postcode":"CV21 2SH",
    "sg:province":"Warwickshire",
    "sg:tags":[
        "pubs",
        "house",
        "inn",
        "activity"
    ],
    "wof:name":"SEVEN STARS",
    "wof:placetype":"venue"
},
  "geometry": {"coordinates":[-1.2580369711,52.3747215271],"type":"Point"}
}