{
  "type": "Feature",
  "properties": {
    "addr:full":"37 Manor Road Wallington Surrey SM6 0BW",
    "addr:housenumber":"37",
    "addr:postcode":"sm6 0bw",
    "addr:street":"Manor Road",
    "iso:country":"GB",
    "sg:address":"37 Manor Road",
    "sg:city":"Wallington",
    "sg:classifiers":[
        {
            "category":"Professional",
            "subcategory":"Engineering",
            "type":"Services"
        },
        {
            "category":"Shopping",
            "subcategory":"Beauty & Cosmetics",
            "type":"Retail Goods"
        }
    ],
    "sg:phone":"+44 20 8773 0475",
    "sg:postcode":"SM6 0BW",
    "sg:province":"Surrey",
    "sg:tags":[
        "supply",
        "contractor",
        "equipment",
        "electrical",
        "hairdressing",
        "engineer"
    ],
    "wof:name":"Vanguard Hair Dryer Service",
    "wof:placetype":"venue"
},
  "geometry": {"coordinates":[-0.1523929983,51.3657798767],"type":"Point"}
}