{
  "type": "Feature",
  "properties": {
    "iso:country":"GB",
    "sg:address":"14 Pine Grove, Woburn Sands",
    "sg:city":"Milton Keynes",
    "sg:classifiers":[
        {
            "category":"Health Services",
            "subcategory":"Health Practitioner",
            "type":"Services"
        }
    ],
    "sg:phone":"+44 1908 584454",
    "sg:postcode":"MK17 8PX",
    "sg:province":"Bedfordshire",
    "sg:tags":[
        "hypnotherapists"
    ],
    "wof:name":"Dr F.Z Nazir M.B.B.S. M.N.C.H.Acc",
    "wof:placetype":"venue"
},
  "geometry": {"coordinates":[-0.727749,52.005856],"type":"Point"}
}