{
  "type": "Feature",
  "properties": {
    "addr:full":"103a Dundas Street Edinburgh City of Edinburgh EH3 6SD",
    "addr:housenumber":"103a",
    "addr:postcode":"eh3 6sd",
    "addr:street":"Dundas Street",
    "iso:country":"GB",
    "sg:address":"103a Dundas Street",
    "sg:city":"Edinburgh",
    "sg:classifiers":[
        {
            "category":"Building & Trades",
            "subcategory":"Construction",
            "type":"Services"
        }
    ],
    "sg:phone":"+44 131 557 2728",
    "sg:postcode":"EH3 6SD",
    "sg:province":"City of Edinburgh",
    "sg:tags":[
        "decorator",
        "painter"
    ],
    "wof:name":"Dobie & Son Ltd.",
    "wof:placetype":"venue"
},
  "geometry": {"coordinates":[-3.200195,55.959225],"type":"Point"}
}