{
  "type": "Feature",
  "properties": {
    "iso:country":"GB",
    "sg:address":"Parc Cynog Farm, Pendine",
    "sg:city":"Carmarthen",
    "sg:classifiers":[
        {
            "category":"Farming",
            "subcategory":"Livestock Farm",
            "type":"Manufacturing & Wholesale Goods"
        }
    ],
    "sg:postcode":"SA33 4PY",
    "sg:province":"Carmarthenshire",
    "sg:tags":[
        "others"
    ],
    "wof:name":"Denzel I Evans",
    "wof:placetype":"venue"
},
  "geometry": {"coordinates":[-4.53077,51.765919],"type":"Point"}
}