{
  "type": "Feature",
  "properties": {
    "addr:full":"Unit 8 Bonlea Trading Estate, Thornaby Stockton-on-tees Durham TS17 7AQ",
    "addr:housenumber":"unit 8",
    "addr:postcode":"ts17 7aq",
    "addr:street":"Trading Estate",
    "iso:country":"GB",
    "sg:address":"Unit 8 Bonlea Trading Estate, Thornaby",
    "sg:city":"Stockton-on-tees",
    "sg:classifiers":[
        {
            "category":"Building & Trades",
            "subcategory":"Cleaning & Sanitation",
            "type":"Services"
        }
    ],
    "sg:phone":"+44 1642 618566",
    "sg:postcode":"TS17 7AQ",
    "sg:province":"Durham",
    "sg:tags":[
        "commercial"
    ],
    "wof:name":"Wischem",
    "wof:placetype":"venue"
},
  "geometry": {"coordinates":[-1.296614,54.557217],"type":"Point"}
}