{
  "type": "Feature",
  "properties": {
    "addr:full":"31 Clerkenwell Clo Clerkenwell Greater London EC1R 0AT",
    "addr:housenumber":"31",
    "addr:postcode":"ec1r 0at",
    "addr:street":"Clerkenwell Clo",
    "iso:country":"GB",
    "sg:address":"31 Clerkenwell Clo",
    "sg:city":"Clerkenwell",
    "sg:classifiers":[
        {
            "category":"Professional",
            "subcategory":"Art Services",
            "type":"Services"
        }
    ],
    "sg:phone":"+44 20 7490 8880",
    "sg:postcode":"EC1R 0AT",
    "sg:province":"Greater London",
    "sg:tags":[
        "graphic",
        "designer"
    ],
    "wof:name":"L Roberts",
    "wof:placetype":"venue"
},
  "geometry": {"coordinates":[-0.106765,51.524712],"type":"Point"}
}