{
  "type": "Feature",
  "properties": {
    "addr:full":"Port Eynon Swansea Swansea SA3 1NN",
    "addr:postcode":"sa3 1nn",
    "iso:country":"GB",
    "sg:address":"Port Eynon",
    "sg:city":"Swansea",
    "sg:classifiers":[
        {
            "category":"Bars & Pubs",
            "type":"Food & Drink"
        }
    ],
    "sg:postcode":"SA3 1NN",
    "sg:province":"Swansea",
    "sg:tags":[
        "pubs",
        "inn"
    ],
    "wof:name":"The Ship Inn",
    "wof:placetype":"venue"
},
  "geometry": {"coordinates":[-4.2128100395,51.5462913513],"type":"Point"}
}