{
  "type": "Feature",
  "properties": {
    "addr:full":"13 Glamis Drive Stone Staffordshire ST15 8SP",
    "addr:housenumber":"13",
    "addr:postcode":"st15 8sp",
    "addr:street":"Glamis Drive",
    "iso:country":"GB",
    "sg:address":"13 Glamis Drive",
    "sg:city":"Stone",
    "sg:classifiers":[
        {
            "category":"Professional",
            "subcategory":"Management & Consulting",
            "type":"Services"
        }
    ],
    "sg:phone":"+44 1785 816444",
    "sg:postcode":"ST15 8SP",
    "sg:province":"Staffordshire",
    "sg:tags":[
        "consultant",
        "promotion",
        "sale"
    ],
    "wof:name":"Ccb Marketing & Promotion Ltd.",
    "wof:placetype":"venue"
},
  "geometry": {"coordinates":[-2.12893,52.889141],"type":"Point"}
}