{
  "type": "Feature",
  "properties": {
    "iso:country":"GB",
    "sg:address":"137-139 Broom Lane, Levenshulme",
    "sg:city":"Manchester",
    "sg:classifiers":[
        {
            "category":"Building & Trades",
            "subcategory":"Construction",
            "type":"Services"
        }
    ],
    "sg:postcode":"M19 3LH",
    "sg:province":"Greater Manchester",
    "sg:tags":[
        "builder"
    ],
    "wof:name":"Sutton Builders",
    "wof:placetype":"venue"
},
  "geometry": {"coordinates":[-2.183653,53.442802],"type":"Point"}
}