{
  "type": "Feature",
  "properties": {
    "addr:full":"2 Oak Court, 67-72 Bethel Road Sevenoaks Kent TN13 3UE",
    "addr:housenumber":"2;67-72",
    "addr:postcode":"tn13 3ue",
    "addr:street":"Oak Court;Bethel Road",
    "iso:country":"GB",
    "sg:address":"2 Oak Court, 67-72 Bethel Road",
    "sg:city":"Sevenoaks",
    "sg:classifiers":[
        {
            "category":"Home & Garden",
            "subcategory":"Kitchen Supply",
            "type":"Retail Goods"
        }
    ],
    "sg:phone":"+44 1732 742000",
    "sg:postcode":"TN13 3UE",
    "sg:province":"Kent",
    "sg:tags":[
        "equipment",
        "catering"
    ],
    "wof:name":"Into Design Ltd.",
    "wof:placetype":"venue"
},
  "geometry": {"coordinates":[0.1929389983,51.270198822],"type":"Point"}
}