{
  "type": "Feature",
  "properties": {
    "addr:full":"17 Gough Square London Greater London EC4A 3DE",
    "addr:housenumber":"17",
    "addr:postcode":"ec4a 3de",
    "addr:street":"Gough Square",
    "iso:country":"GB",
    "sg:address":"17 Gough Square",
    "sg:city":"London",
    "sg:classifiers":[
        {
            "category":"Museum",
            "subcategory":"Art Museum",
            "type":"Entertainment"
        }
    ],
    "sg:phone":"+44 20 7353 3745",
    "sg:postcode":"EC4A 3DE",
    "sg:province":"Greater London",
    "sg:tags":[
        "gallery"
    ],
    "wof:name":"Dr Johnson's House",
    "wof:placetype":"venue"
},
  "geometry": {"coordinates":[-0.1072689965,51.5151290894],"type":"Point"}
}