{
  "type": "Feature",
  "properties": {
    "addr:full":"85 Castle Lane West Bournemouth Dorset BH9 3LH",
    "addr:housenumber":"85",
    "addr:postcode":"bh9 3lh",
    "addr:street":"Castle Lane West",
    "iso:country":"GB",
    "sg:address":"85 Castle Lane West",
    "sg:city":"Bournemouth",
    "sg:classifiers":[
        {
            "category":"Shopping",
            "subcategory":"Mobile Phones",
            "type":"Retail Goods"
        }
    ],
    "sg:phone":"+44 1202 527772",
    "sg:postcode":"BH9 3LH",
    "sg:province":"Dorset",
    "wof:name":"In Touch Cellular",
    "wof:placetype":"venue"
},
  "geometry": {"coordinates":[-1.8682039976,50.7589530945],"type":"Point"}
}