{
  "type": "Feature",
  "properties": {
    "addr:full":"17 Haseldine Road, London Colney St Albans Hertfordshire AL2 1RR",
    "addr:housenumber":"17",
    "addr:postcode":"al2 1rr",
    "addr:street":"Haseldine Road",
    "iso:country":"GB",
    "sg:address":"17 Haseldine Road, London Colney",
    "sg:city":"St Albans",
    "sg:classifiers":[
        {
            "category":"Food & Beverages",
            "subcategory":"Liquor & Beverages",
            "type":"Retail Goods"
        }
    ],
    "sg:phone":"+44 1727 823343",
    "sg:postcode":"AL2 1RR",
    "sg:province":"Hertfordshire",
    "sg:tags":[
        "beer",
        "spirit",
        "wines"
    ],
    "wof:name":"Unwins Ltd.",
    "wof:placetype":"venue"
},
  "geometry": {"coordinates":[-0.2976309955,51.7228660583],"type":"Point"}
}