{
  "type": "Feature",
  "properties": {
    "addr:full":"82 Offington Drive, Offington Worthing West Sussex BN14 9PS",
    "addr:housenumber":"82",
    "addr:postcode":"bn14 9ps",
    "addr:street":"Offington Drive",
    "iso:country":"GB",
    "sg:address":"82 Offington Drive, Offington",
    "sg:city":"Worthing",
    "sg:classifiers":[
        {
            "category":"Building & Trades",
            "subcategory":"Construction",
            "type":"Services"
        }
    ],
    "sg:postcode":"BN14 9PS",
    "sg:province":"West Sussex",
    "sg:tags":[
        "glazier",
        "decorator",
        "painter"
    ],
    "wof:name":"Taplin & Son",
    "wof:placetype":"venue"
},
  "geometry": {"coordinates":[-0.385729,50.835308],"type":"Point"}
}