{
  "type": "Feature",
  "properties": {
    "addr:full":"27/29 High Street, Puddlestown Dorchester Dorset DT2 8RT",
    "addr:housenumber":"27 / 29",
    "addr:postcode":"dt2 8rt",
    "addr:street":"High Street;Dorchester",
    "iso:country":"GB",
    "sg:address":"27/29 High Street, Puddlestown",
    "sg:city":"Dorchester",
    "sg:classifiers":[
        {
            "category":"Shopping",
            "subcategory":"Department Store",
            "type":"Retail Goods"
        },
        {
            "category":"Food & Beverages",
            "subcategory":"Groceries & Convenience Stores",
            "type":"Retail Goods"
        },
        {
            "category":"Food & Beverages",
            "subcategory":"Meat & Fish",
            "type":"Retail Goods"
        }
    ],
    "sg:phone":"+44 1305 848235",
    "sg:postcode":"DT2 8RT",
    "sg:province":"Dorset",
    "sg:tags":[
        "butcher"
    ],
    "wof:name":"R & O BALL & SON",
    "wof:placetype":"venue"
},
  "geometry": {"coordinates":[-2.346454,50.748177],"type":"Point"}
}