{
  "type": "Feature",
  "properties": {
    "iso:country":"GB",
    "sg:address":"Thornbera Road",
    "sg:city":"Bishops Stortford",
    "sg:classifiers":[
        {
            "category":"Building & Trades",
            "subcategory":"Construction",
            "type":"Services"
        }
    ],
    "sg:phone":"+44 1279 833343",
    "sg:postcode":"CM23 3NL",
    "sg:province":"Essex",
    "sg:tags":[
        "roofing"
    ],
    "wof:name":"G Tierney Roofing",
    "wof:placetype":"venue"
},
  "geometry": {"coordinates":[0.15623,51.85767],"type":"Point"}
}