{
  "type": "Feature",
  "properties": {
    "addr:full":"40 Croft Road, Charlton Kings Cheltenham Gloucestershire GL53 8LA",
    "addr:housenumber":"40",
    "addr:postcode":"gl53 8la",
    "addr:street":"Croft Road",
    "iso:country":"GB",
    "sg:address":"40 Croft Road, Charlton Kings",
    "sg:city":"Cheltenham",
    "sg:classifiers":[
        {
            "category":"Retail",
            "subcategory":"Repair Shop",
            "type":"Services"
        }
    ],
    "sg:postcode":"GL53 8LA",
    "sg:province":"Gloucestershire",
    "sg:tags":[
        "maintenance"
    ],
    "wof:name":"Terry Miller Building & Maintenance",
    "wof:placetype":"venue"
},
  "geometry": {"coordinates":[-2.0518410206,51.8801078796],"type":"Point"}
}