{
  "type": "Feature",
  "properties": {
    "addr:full":"Shale Street Bilston West Midlands WV14 0LR",
    "addr:postcode":"wv14 0lr",
    "addr:street":"Shale Street",
    "iso:country":"GB",
    "sg:address":"Shale Street",
    "sg:city":"Bilston",
    "sg:classifiers":[
        {
            "category":"Manufacturing",
            "subcategory":"Metals",
            "type":"Manufacturing & Wholesale Goods"
        }
    ],
    "sg:phone":"+44 1902 402132",
    "sg:postcode":"WV14 0LR",
    "sg:province":"West Midlands",
    "sg:tags":[
        "foundry"
    ],
    "wof:name":"Formcast Ltd.",
    "wof:placetype":"venue"
},
  "geometry": {"coordinates":[-2.0816791058,52.5664558411],"type":"Point"}
}