{
  "type": "Feature",
  "properties": {
    "iso:country":"GB",
    "sg:address":"23 Broadstone Street",
    "sg:city":"Todmorden",
    "sg:classifiers":[
        {
            "category":"Place Of Worship",
            "type":"Public Place"
        }
    ],
    "sg:phone":"+44 1706 815517",
    "sg:postcode":"OL14 8AL",
    "sg:province":"Lancashire",
    "wof:name":"Vale Baptist Church",
    "wof:placetype":"venue"
},
  "geometry": {"coordinates":[-2.0834898949,53.7175827026],"type":"Point"}
}