{
  "type": "Feature",
  "properties": {
    "iso:country":"GB",
    "sg:address":"114 Draycott Rd",
    "sg:city":"Nottingham",
    "sg:classifiers":[
        {
            "category":"Professional",
            "subcategory":"Management & Consulting",
            "type":"Services"
        }
    ],
    "sg:phone":"+44 115 946 5050",
    "sg:postcode":"NG10 3BZ",
    "sg:province":"Derbyshire",
    "sg:tags":[
        "consultant",
        "business"
    ],
    "wof:name":"Real Learning",
    "wof:placetype":"venue"
},
  "geometry": {"coordinates":[-1.301338,52.882725],"type":"Point"}
}