{
  "type": "Feature",
  "properties": {
    "addr:full":"Glanllyn, Dwyran Llanfairpwllgwyngyll Isle of Anglesey LL61 6YU",
    "addr:postcode":"ll61 6yu",
    "addr:street":"Llanfairpwllgwyngyll",
    "iso:country":"GB",
    "sg:address":"Glanllyn, Dwyran",
    "sg:city":"Llanfairpwllgwyngyll",
    "sg:classifiers":[
        {
            "category":"Recreation",
            "subcategory":"Dog Park",
            "type":"Entertainment"
        },
        {
            "category":"Retail",
            "subcategory":"Animal Services",
            "type":"Services"
        }
    ],
    "sg:postcode":"LL61 6YU",
    "sg:province":"Isle of Anglesey",
    "sg:tags":[
        "training"
    ],
    "wof:name":"K 9 Phoenix Dog Training",
    "wof:placetype":"venue"
},
  "geometry": {"coordinates":[-4.3246240616,53.1667938232],"type":"Point"}
}