{
  "type": "Feature",
  "properties": {
    "addr:full":"The Shipyard, Upper Brents Faversham Kent ME13 7DZ",
    "addr:postcode":"me13 7dz",
    "addr:street":"Upper Brents Faversham",
    "iso:country":"GB",
    "sg:address":"The Shipyard, Upper Brents",
    "sg:city":"Faversham",
    "sg:classifiers":[
        {
            "category":"Building & Trades",
            "subcategory":"Construction",
            "type":"Services"
        }
    ],
    "sg:phone":"+44 1795 531564",
    "sg:postcode":"ME13 7DZ",
    "sg:province":"Kent",
    "sg:tags":[
        "ceiling",
        "contractor"
    ],
    "wof:name":"G J Reardon",
    "wof:placetype":"venue"
},
  "geometry": {"coordinates":[0.8933100104,51.3211708069],"type":"Point"}
}