{
  "type": "Feature",
  "properties": {
    "addr:full":"6 Grove Corner, Bookham Leatherhead Surrey KT23 4LP",
    "addr:housenumber":"6",
    "addr:postcode":"kt23 4lp",
    "addr:street":"Grove Corner",
    "iso:country":"GB",
    "sg:address":"6 Grove Corner, Bookham",
    "sg:city":"Leatherhead",
    "sg:classifiers":[
        {
            "category":"Farming",
            "subcategory":"Fish & Marine Products",
            "type":"Manufacturing & Wholesale Goods"
        },
        {
            "category":"Food & Beverages",
            "subcategory":"Meat & Fish",
            "type":"Retail Goods"
        }
    ],
    "sg:phone":"+44 1372 452980",
    "sg:postcode":"KT23 4LP",
    "sg:province":"Surrey",
    "sg:tags":[
        "fishmonger",
        "related"
    ],
    "wof:name":"Ron Fowler & Sons",
    "wof:placetype":"venue"
},
  "geometry": {"coordinates":[-0.3729479909,51.2766075134],"type":"Point"}
}