{
  "type": "Feature",
  "properties": {
    "addr:full":"68 Sandon Rd Southport Lancashire PR8 4QD",
    "addr:housenumber":"68",
    "addr:postcode":"pr8 4qd",
    "addr:street":"Sandon Rd",
    "iso:country":"GB",
    "sg:address":"68 Sandon Rd",
    "sg:city":"Southport",
    "sg:classifiers":[
        {
            "category":"Professional",
            "subcategory":"Engineering",
            "type":"Services"
        }
    ],
    "sg:phone":"+44 1704 564601",
    "sg:postcode":"PR8 4QD",
    "sg:province":"Lancashire",
    "sg:tags":[
        "consulting",
        "engineer"
    ],
    "wof:name":"Stagg-Blackman & Partners",
    "wof:placetype":"venue"
},
  "geometry": {"coordinates":[-3.022294,53.620205],"type":"Point"}
}