{
  "type": "Feature",
  "properties": {
    "addr:full":"Brixton Farm, Cross Inn, Laugharne Carmarthen Carmarthenshire SA33 4QT",
    "addr:postcode":"sa33 4qt",
    "iso:country":"GB",
    "sg:address":"Brixton Farm, Cross Inn, Laugharne",
    "sg:city":"Carmarthen",
    "sg:classifiers":[
        {
            "category":"Farming",
            "subcategory":"Livestock Farm",
            "type":"Manufacturing & Wholesale Goods"
        }
    ],
    "sg:phone":"+44 1994 427212",
    "sg:postcode":"SA33 4QT",
    "sg:province":"Carmarthenshire",
    "sg:tags":[
        "others"
    ],
    "wof:name":"Thomas & Derek John",
    "wof:placetype":"venue"
},
  "geometry": {"coordinates":[-4.462729,51.771809],"type":"Point"}
}