{
  "type": "Feature",
  "properties": {
    "iso:country":"GB",
    "sg:address":"45 Chestnut Avenue",
    "sg:city":"West Wickham",
    "sg:classifiers":[
        {
            "category":"Home & Garden",
            "subcategory":"Hardware",
            "type":"Retail Goods"
        }
    ],
    "sg:phone":"+44 20 8462 0275",
    "sg:postcode":"BR4 9ET",
    "sg:province":"Kent",
    "sg:tags":[
        "equipment",
        "welding"
    ],
    "wof:name":"Alec Leggett Welding Equipment Repairs",
    "wof:placetype":"venue"
},
  "geometry": {"coordinates":[0.002321,51.365295],"type":"Point"}
}