{
  "type": "Feature",
  "properties": {
    "addr:full":"8a Chequer Road Doncaster South Yorkshire DN1 2AF",
    "addr:housenumber":"8a",
    "addr:postcode":"dn1 2af",
    "addr:street":"Chequer Road",
    "iso:country":"GB",
    "sg:address":"8a Chequer Road",
    "sg:city":"Doncaster",
    "sg:classifiers":[
        {
            "category":"Education",
            "subcategory":"University",
            "type":"Public Place"
        }
    ],
    "sg:phone":"+44 1302 812125",
    "sg:postcode":"DN1 2AF",
    "sg:province":"South Yorkshire",
    "sg:tags":[
        "higher"
    ],
    "wof:name":"Doncaster Students Union",
    "wof:placetype":"venue"
},
  "geometry": {"coordinates":[-1.127165,53.519749],"type":"Point"}
}