{
  "type": "Feature",
  "properties": {
    "addr:full":"198 Barnett Wood Lane Ashtead Surrey KT21 2DB",
    "addr:housenumber":"198",
    "addr:postcode":"kt21 2db",
    "addr:street":"Barnett Wood Lane",
    "iso:country":"GB",
    "sg:address":"198 Barnett Wood Lane",
    "sg:city":"Ashtead",
    "sg:classifiers":[
        {
            "category":"Manufacturing",
            "subcategory":"Buildings",
            "type":"Manufacturing & Wholesale Goods"
        }
    ],
    "sg:phone":"+44 1372 279977",
    "sg:postcode":"KT21 2DB",
    "sg:province":"Surrey",
    "sg:tags":[
        "system",
        "air conditioning"
    ],
    "wof:name":"Delta Automotive Air Conditioning Ltd",
    "wof:placetype":"venue"
},
  "geometry": {"coordinates":[-0.310555011,51.3134727478],"type":"Point"}
}