{
  "type": "Feature",
  "properties": {
    "addr:full":"Glachnagoire Beauly Highland IV4 7JQ",
    "addr:postcode":"iv4 7jq",
    "addr:street":"Beauly",
    "iso:country":"GB",
    "sg:address":"Glachnagoire",
    "sg:city":"Beauly",
    "sg:classifiers":[
        {
            "category":"Retail",
            "subcategory":"Animal Services",
            "type":"Services"
        }
    ],
    "sg:phone":"+44 1463 741275",
    "sg:postcode":"IV4 7JQ",
    "sg:province":"Highland",
    "sg:tags":[
        "breeder",
        "livestock"
    ],
    "wof:name":"G Ferguson",
    "wof:placetype":"venue"
},
  "geometry": {"coordinates":[-4.460757,57.482918],"type":"Point"}
}