{
  "type": "Feature",
  "properties": {
    "addr:full":"48 Dale Street Bacup Lancashire OL13 8BA",
    "addr:housenumber":"48",
    "addr:postcode":"ol13 8ba",
    "addr:street":"Dale Street",
    "iso:country":"GB",
    "sg:address":"48 Dale Street",
    "sg:city":"Bacup",
    "sg:classifiers":[
        {
            "category":"Professional",
            "subcategory":"Engineering",
            "type":"Services"
        },
        {
            "category":"Home & Garden",
            "subcategory":"Household Appliances",
            "type":"Retail Goods"
        }
    ],
    "sg:phone":"+44 1706 876576",
    "sg:postcode":"OL13 8BA",
    "sg:province":"Lancashire",
    "sg:tags":[
        "gas",
        "engineer"
    ],
    "wof:name":"David Lord",
    "wof:placetype":"venue"
},
  "geometry": {"coordinates":[-2.2037110329,53.7042045593],"type":"Point"}
}