{
  "type": "Feature",
  "properties": {
    "addr:full":"Unit 1c, Faraday Road, Littleport Ely Cambridgeshire CB6 1PE",
    "addr:housenumber":"unit 1c",
    "addr:postcode":"cb6 1pe",
    "addr:street":"Faraday Road",
    "iso:country":"GB",
    "sg:address":"Unit 1c, Faraday Road, Littleport",
    "sg:city":"Ely",
    "sg:classifiers":[
        {
            "category":"Manufacturing",
            "subcategory":"Buildings",
            "type":"Manufacturing & Wholesale Goods"
        }
    ],
    "sg:postcode":"CB6 1PE",
    "sg:province":"Cambridgeshire",
    "sg:tags":[
        "portable"
    ],
    "wof:name":"Littleport Timber Buildings",
    "wof:placetype":"venue"
},
  "geometry": {"coordinates":[0.3020560145,52.4593582153],"type":"Point"}
}