{
  "type": "Feature",
  "properties": {
    "iso:country":"GB",
    "sg:address":"77 St Martins Lane",
    "sg:city":"London",
    "sg:classifiers":[
        {
            "category":"Real Estate",
            "subcategory":"Architect",
            "type":"Services"
        }
    ],
    "sg:phone":"+44 20 7240 7766",
    "sg:postcode":"WC2N 4AA",
    "sg:province":"Greater London",
    "wof:name":"Scott Brownrigg Ltd.",
    "wof:placetype":"venue"
},
  "geometry": {"coordinates":[-0.12757,51.51144],"type":"Point"}
}