{
  "type": "Feature",
  "properties": {
    "addr:full":"6 Park Parade, Gunnersbury Avenue London Greater London W3 9BD",
    "addr:housenumber":"6",
    "addr:postcode":"w3 9bd",
    "addr:street":"Park Parade Gunnersbury Avenue",
    "iso:country":"GB",
    "sg:address":"6 Park Parade, Gunnersbury Avenue",
    "sg:city":"London",
    "sg:classifiers":[
        {
            "category":"Shopping",
            "subcategory":"News",
            "type":"Retail Goods"
        }
    ],
    "sg:phone":"+44 20 8992 0054",
    "sg:postcode":"W3 9BD",
    "sg:province":"Greater London",
    "sg:tags":[
        "newsagent"
    ],
    "wof:name":"Rama News",
    "wof:placetype":"venue"
},
  "geometry": {"coordinates":[-0.28517,51.501381],"type":"Point"}
}