{
  "type": "Feature",
  "properties": {
    "iso:country":"GB",
    "sg:address":"96c Whiteladies Road, Clifton",
    "sg:city":"Bristol",
    "sg:classifiers":[
        {
            "category":"Home & Garden",
            "subcategory":"Carpets & Floor Coverings",
            "type":"Retail Goods"
        }
    ],
    "sg:phone":"+44 117 974 4556",
    "sg:postcode":"BS8 2QX",
    "sg:province":"City of Bristol",
    "sg:tags":[
        "carpets",
        "rug",
        "matting"
    ],
    "wof:name":"Richard Snow Carpets",
    "wof:placetype":"venue"
},
  "geometry": {"coordinates":[-2.6123869419,51.4671325684],"type":"Point"}
}