{
  "type": "Feature",
  "properties": {
    "addr:full":"4 Ellingham Road, Adeyfield Hemel Hempstead Hertfordshire HP2 5LE",
    "addr:housenumber":"4",
    "addr:postcode":"hp2 5le",
    "addr:street":"Ellingham Road Adeyfield Hemel Hempstead",
    "iso:country":"GB",
    "sg:address":"4 Ellingham Road, Adeyfield",
    "sg:city":"Hemel Hempstead",
    "sg:classifiers":[
        {
            "category":"Shopping",
            "subcategory":"Computers & Home Electronics",
            "type":"Retail Goods"
        }
    ],
    "sg:postcode":"HP2 5LE",
    "sg:province":"Hertfordshire",
    "sg:tags":[
        "aerial",
        "television",
        "radio"
    ],
    "wof:name":"Dacorum Aerials",
    "wof:placetype":"venue"
},
  "geometry": {"coordinates":[-0.455155,51.759895],"type":"Point"}
}