{
  "type": "Feature",
  "properties": {
    "iso:country":"GB",
    "sg:address":"14 Main St",
    "sg:city":"Pembroke",
    "sg:classifiers":[
        {
            "category":"Shopping",
            "subcategory":"Hobbies, Toys, & Games",
            "type":"Retail Goods"
        }
    ],
    "sg:phone":"+44 1646 685888",
    "sg:postcode":"SA71 4NP",
    "sg:province":"Pembrokeshire",
    "sg:tags":[
        "shop",
        "toy"
    ],
    "wof:name":"Haggars Toys & Gift Shop",
    "wof:placetype":"venue"
},
  "geometry": {"coordinates":[-4.9174609184,51.6761627197],"type":"Point"}
}