{
  "type": "Feature",
  "properties": {
    "addr:full":"9 Southfield Road, Downley High Wycombe Buckinghamshire HP13 5JZ",
    "addr:housenumber":"9",
    "addr:postcode":"hp13 5jz",
    "addr:street":"Southfield Road",
    "iso:country":"GB",
    "sg:address":"9 Southfield Road, Downley",
    "sg:city":"High Wycombe",
    "sg:classifiers":[
        {
            "category":"Building & Trades",
            "subcategory":"Construction",
            "type":"Services"
        }
    ],
    "sg:phone":"+44 1494 510172",
    "sg:postcode":"HP13 5JZ",
    "sg:province":"Buckinghamshire",
    "sg:tags":[
        "builder"
    ],
    "wof:name":"John Ian Pearson",
    "wof:placetype":"venue"
},
  "geometry": {"coordinates":[-0.778094,51.640499],"type":"Point"}
}