{
  "type": "Feature",
  "properties": {
    "addr:full":"60 Oldmill Road, Uddingston Glasgow Glasgow City G71 7PF",
    "addr:housenumber":"60",
    "addr:postcode":"g71 7pf",
    "addr:street":"Oldmill Road",
    "iso:country":"GB",
    "sg:address":"60 Oldmill Road, Uddingston",
    "sg:city":"Glasgow",
    "sg:classifiers":[
        {
            "category":"Bars & Pubs",
            "type":"Food & Drink"
        }
    ],
    "sg:phone":"+44 1698 812678",
    "sg:postcode":"G71 7PF",
    "sg:province":"Glasgow City",
    "sg:tags":[
        "pubs",
        "inn"
    ],
    "wof:name":"Rowantree Inn",
    "wof:placetype":"venue"
},
  "geometry": {"coordinates":[-4.080857,55.819904],"type":"Point"}
}