{
  "type": "Feature",
  "properties": {
    "iso:country":"GB",
    "sg:address":"27 Head Street",
    "sg:city":"Colchester",
    "sg:classifiers":[
        {
            "category":"Shopping",
            "subcategory":"Clothing, Apparel, & Fashions",
            "type":"Retail Goods"
        }
    ],
    "sg:postcode":"CO1 1NH",
    "sg:province":"Essex",
    "sg:tags":[
        "menswear"
    ],
    "wof:name":"Navy & Army Stores",
    "wof:placetype":"venue"
},
  "geometry": {"coordinates":[0.89607,51.888496],"type":"Point"}
}