{
  "type": "Feature",
  "properties": {
    "addr:full":"2 Main Road, Wybunbury Nantwich Cheshire CW5 7NA",
    "addr:housenumber":"2",
    "addr:postcode":"cw5 7na",
    "addr:street":"Main Road",
    "iso:country":"GB",
    "sg:address":"2 Main Road, Wybunbury",
    "sg:city":"Nantwich",
    "sg:classifiers":[
        {
            "category":"Bars & Pubs",
            "type":"Food & Drink"
        }
    ],
    "sg:phone":"+44 1270 841280",
    "sg:postcode":"CW5 7NA",
    "sg:province":"Cheshire",
    "sg:tags":[
        "pubs",
        "house",
        "inn",
        "public",
        "activity"
    ],
    "sg:website":"http://www.swaninnwybunbury.co.uk",
    "wof:name":"Swan Inn",
    "wof:placetype":"venue"
},
  "geometry": {"coordinates":[-2.448901,53.044853],"type":"Point"}
}