{
  "type": "Feature",
  "properties": {
    "iso:country":"GB",
    "sg:address":"39 Bath Rd",
    "sg:city":"Swindon",
    "sg:classifiers":[
        {
            "category":"Professional",
            "subcategory":"Lawyer & Legal Services",
            "type":"Services"
        }
    ],
    "sg:phone":"+44 1793 619933",
    "sg:postcode":"SN1 4AS",
    "sg:province":"Wiltshire",
    "sg:tags":[
        "advice",
        "counselling"
    ],
    "wof:name":"Cruse Bereavement Care",
    "wof:placetype":"venue"
},
  "geometry": {"coordinates":[-1.779108,51.552433],"type":"Point"}
}