{
  "type": "Feature",
  "properties": {
    "iso:country":"GB",
    "sg:address":"Wetherby Rd, Boroughbridge",
    "sg:city":"York",
    "sg:classifiers":[
        {
            "category":"Building & Trades",
            "subcategory":"Construction",
            "type":"Services"
        },
        {
            "category":"Community Center",
            "type":"Public Place"
        },
        {
            "category":"Government",
            "subcategory":"Office",
            "type":"Public Place"
        }
    ],
    "sg:phone":"+44 1423 323505",
    "sg:postcode":"YO51 9JX",
    "sg:province":"North Yorkshire",
    "sg:tags":[
        "recreation",
        "glazier",
        "local",
        "leisure",
        "centre"
    ],
    "wof:name":"Council of the Borough of Harrogate",
    "wof:placetype":"venue"
},
  "geometry": {"coordinates":[-1.395457983,54.0976524353],"type":"Point"}
}