{
  "type": "Feature",
  "properties": {
    "addr:full":"The Hay Barn, Devitts Green Lane, Arley Coventry Warwickshire CV7 8GF",
    "addr:postcode":"cv7 8gf",
    "addr:street":"Green Lane",
    "iso:country":"GB",
    "sg:address":"The Hay Barn, Devitts Green Lane, Arley",
    "sg:city":"Coventry",
    "sg:classifiers":[
        {
            "category":"Freight",
            "type":"Transportation"
        }
    ],
    "sg:phone":"+44 1675 481328",
    "sg:postcode":"CV7 8GF",
    "sg:province":"Warwickshire",
    "sg:tags":[
        "haulage",
        "road"
    ],
    "wof:name":"J W & J A Swift",
    "wof:placetype":"venue"
},
  "geometry": {"coordinates":[-1.5985790491,52.5107002258],"type":"Point"}
}