{
  "type": "Feature",
  "properties": {
    "addr:full":"49a Market Parade Havant Hampshire PO9 1PY",
    "addr:housenumber":"49a",
    "addr:postcode":"po9 1py",
    "addr:street":"Market Parade",
    "iso:country":"GB",
    "sg:address":"49a Market Parade",
    "sg:city":"Havant",
    "sg:classifiers":[
        {
            "category":"Banks & Credit Unions",
            "subcategory":"Bureau De Change",
            "type":"Services"
        }
    ],
    "sg:postcode":"PO9 1PY",
    "sg:province":"Hampshire",
    "sg:tags":[
        "town",
        "consultant",
        "planning"
    ],
    "wof:name":"Planning Solutions Ltd.",
    "wof:placetype":"venue"
},
  "geometry": {"coordinates":[-0.982384,50.853436],"type":"Point"}
}