{
  "type": "Feature",
  "properties": {
    "iso:country":"GB",
    "sg:address":"The Old School",
    "sg:city":"St Ives",
    "sg:classifiers":[
        {
            "category":"Community Center",
            "subcategory":"Youth",
            "type":"Public Place"
        }
    ],
    "sg:phone":"+44 1736 795122",
    "sg:postcode":"TR26 1NT",
    "sg:province":"Cornwall",
    "sg:tags":[
        "organisation",
        "centre"
    ],
    "wof:name":"Creazen An Enys Island Centre",
    "wof:placetype":"venue"
},
  "geometry": {"coordinates":[-5.48574,50.210361],"type":"Point"}
}