{
  "type": "Feature",
  "properties": {
    "addr:full":"87 Worthing Avenue Gosport Hampshire PO12 4DB",
    "addr:housenumber":"87",
    "addr:postcode":"po12 4db",
    "addr:street":"Worthing Avenue",
    "iso:country":"GB",
    "sg:address":"87 Worthing Avenue",
    "sg:city":"Gosport",
    "sg:classifiers":[
        {
            "category":"Building & Trades",
            "subcategory":"Construction",
            "type":"Services"
        }
    ],
    "sg:postcode":"PO12 4DB",
    "sg:province":"Hampshire",
    "sg:tags":[
        "builder"
    ],
    "wof:name":"A A Hensman",
    "wof:placetype":"venue"
},
  "geometry": {"coordinates":[-1.1445490122,50.8106689453],"type":"Point"}
}