{
  "type": "Feature",
  "properties": {
    "iso:country":"GB",
    "sg:address":"Unit 14 Bartlett Park, Lynx Trading Estate",
    "sg:city":"Yeovil",
    "sg:classifiers":[
        {
            "category":"Communications",
            "subcategory":"Film & Video Production",
            "type":"Services"
        }
    ],
    "sg:phone":"+44 1935 471440",
    "sg:postcode":"BA20 2PT",
    "sg:province":"Somerset",
    "sg:tags":[
        "microfilming"
    ],
    "wof:name":"Line Scan Ltd.",
    "wof:placetype":"venue"
},
  "geometry": {"coordinates":[-2.656294,50.933861],"type":"Point"}
}