{
  "type": "Feature",
  "properties": {
    "iso:country":"GB",
    "sg:address":"Le Roy Cottage, Northbrook Avenue",
    "sg:city":"Winchester",
    "sg:classifiers":[
        {
            "category":"Building & Trades",
            "subcategory":"Construction",
            "type":"Services"
        }
    ],
    "sg:postcode":"SO23 0JW",
    "sg:province":"Hampshire",
    "sg:tags":[
        "builder"
    ],
    "wof:name":"D Bull",
    "wof:placetype":"venue"
},
  "geometry": {"coordinates":[-1.316809,51.063068],"type":"Point"}
}