{
  "type": "Feature",
  "properties": {
    "iso:country":"GB",
    "sg:address":"7 Brooklyn Villas, Goudhurst Road, Marden",
    "sg:city":"Tonbridge",
    "sg:classifiers":[
        {
            "category":"Banks & Credit Unions",
            "subcategory":"Atm",
            "type":"Services"
        }
    ],
    "sg:phone":"+44 1622 832599",
    "sg:postcode":"TN12 9JR",
    "sg:province":"Kent",
    "sg:tags":[
        "carburettor"
    ],
    "wof:name":"Hales Distribution",
    "wof:placetype":"venue"
},
  "geometry": {"coordinates":[0.489726007,51.176322937],"type":"Point"}
}