{
  "type": "Feature",
  "properties": {
    "addr:full":"15 The Chase, Shann Park Keighley North Yorkshire BD20 6HU",
    "addr:housenumber":"15",
    "addr:postcode":"bd20 6hu",
    "addr:street":"The Chase Shann Park",
    "iso:country":"GB",
    "sg:address":"15 The Chase, Shann Park",
    "sg:city":"Keighley",
    "sg:classifiers":[
        {
            "category":"Personal",
            "subcategory":"Tanning Parlor",
            "type":"Services"
        }
    ],
    "sg:phone":"+44 1535 600792",
    "sg:postcode":"BD20 6HU",
    "sg:province":"North Yorkshire",
    "sg:tags":[
        "sunbeds"
    ],
    "wof:name":"Sun-Hire",
    "wof:placetype":"venue"
},
  "geometry": {"coordinates":[-1.9265830517,53.8730506897],"type":"Point"}
}