{
  "type": "Feature",
  "properties": {
    "iso:country":"GB",
    "sg:address":"47 North Cross Road",
    "sg:city":"London",
    "sg:classifiers":[
        {
            "category":"Food & Beverages",
            "subcategory":"Fruits & Vegetables",
            "type":"Retail Goods"
        }
    ],
    "sg:phone":"+44 20 8693 7169",
    "sg:postcode":"SE22 9ET",
    "sg:province":"Greater London",
    "sg:tags":[
        "greengrocer"
    ],
    "wof:name":"Pretty Traditional",
    "wof:placetype":"venue"
},
  "geometry": {"coordinates":[-0.073736,51.457569],"type":"Point"}
}