{
  "type": "Feature",
  "properties": {
    "addr:full":"Abbey Hill Industrial Estate, Abbey Hill Yeovil Somerset BA21 3AR",
    "addr:housenumber":"estate",
    "addr:postcode":"ba21 3ar",
    "addr:street":"Hill Industrial;Hill",
    "iso:country":"GB",
    "sg:address":"Abbey Hill Industrial Estate, Abbey Hill",
    "sg:city":"Yeovil",
    "sg:classifiers":[
        {
            "category":"Retail",
            "subcategory":"Auto Repair",
            "type":"Services"
        }
    ],
    "sg:phone":"+44 1935 427700",
    "sg:postcode":"BA21 3AR",
    "sg:province":"Somerset",
    "sg:tags":[
        "body",
        "car"
    ],
    "wof:name":"Hoopers Panel & Paint Craft",
    "wof:placetype":"venue"
},
  "geometry": {"coordinates":[-2.66359,50.950001],"type":"Point"}
}