{
  "type": "Feature",
  "properties": {
    "iso:country":"GB",
    "sg:address":"Middlegate",
    "sg:city":"Newcastle Upon Tyne",
    "sg:classifiers":[
        {
            "category":"Place Of Worship",
            "type":"Public Place"
        }
    ],
    "sg:phone":"+44 191 267 4558",
    "sg:postcode":"NE5 1AU",
    "sg:province":"Tyne and Wear",
    "wof:name":"West Denton United Reformed Church",
    "wof:placetype":"venue"
},
  "geometry": {"coordinates":[-1.71027,54.992722],"type":"Point"}
}