{
  "type": "Feature",
  "properties": {
    "addr:full":", Llanystumdwy Criccieth Gwynedd LL52 0SP",
    "addr:postcode":"ll52 0sp",
    "addr:street":"Criccieth",
    "iso:country":"GB",
    "sg:address":", Llanystumdwy",
    "sg:city":"Criccieth",
    "sg:classifiers":[
        {
            "category":"Education",
            "subcategory":"School",
            "type":"Public Place"
        }
    ],
    "sg:phone":"+44 1766 522961",
    "sg:postcode":"LL52 0SP",
    "sg:province":"Gwynedd",
    "sg:tags":[
        "local",
        "authority"
    ],
    "wof:name":"Ysgol Llanystumdwy",
    "wof:placetype":"venue"
},
  "geometry": {"coordinates":[-4.229499,52.920139],"type":"Point"}
}