{
  "type": "Feature",
  "properties": {
    "addr:full":"75 Wellington Road Newport Isle of Wight PO30 5PX",
    "addr:housenumber":"75",
    "addr:postcode":"po30 5px",
    "addr:street":"Wellington Road",
    "iso:country":"GB",
    "sg:address":"75 Wellington Road",
    "sg:city":"Newport",
    "sg:classifiers":[
        {
            "category":"Shopping",
            "subcategory":"News",
            "type":"Retail Goods"
        }
    ],
    "sg:phone":"+44 1983 528366",
    "sg:postcode":"PO30 5PX",
    "sg:province":"Isle of Wight",
    "sg:tags":[
        "newsagent"
    ],
    "wof:name":"True Wight News",
    "wof:placetype":"venue"
},
  "geometry": {"coordinates":[-1.3128880262,50.696685791],"type":"Point"}
}