{
  "type": "Feature",
  "properties": {
    "addr:full":"C/o Crossway West Paddock, Leyland Preston Lancashire PR5 1HR",
    "addr:postcode":"pr5 1hr",
    "addr:street":"C / O Crossway West;Leyland",
    "iso:country":"GB",
    "sg:address":"C/o Crossway West Paddock, Leyland",
    "sg:city":"Preston",
    "sg:classifiers":[
        {
            "category":"Social Services",
            "type":"Services"
        }
    ],
    "sg:phone":"+44 1772 423611",
    "sg:postcode":"PR5 1HR",
    "sg:province":"Lancashire",
    "wof:name":"South Ribble Supported Housing",
    "wof:placetype":"venue"
},
  "geometry": {"coordinates":[-2.6934900284,53.6953392029],"type":"Point"}
}