{
  "type": "Feature",
  "properties": {
    "addr:full":"18 Woolley Drive Bradford-on-avon Wiltshire BA15 1AU",
    "addr:housenumber":"18",
    "addr:postcode":"ba15 1au",
    "addr:street":"Woolley Drive",
    "iso:country":"GB",
    "sg:address":"18 Woolley Drive",
    "sg:city":"Bradford-on-avon",
    "sg:classifiers":[
        {
            "category":"Military Area",
            "subcategory":"Air Force Base",
            "type":"Public Place"
        }
    ],
    "sg:postcode":"BA15 1AU",
    "sg:province":"Wiltshire",
    "sg:tags":[
        "water",
        "treatment"
    ],
    "wof:name":"A G Kent Alloys",
    "wof:placetype":"venue"
},
  "geometry": {"coordinates":[-2.2427899837,51.3508262634],"type":"Point"}
}