{
  "type": "Feature",
  "properties": {
    "addr:full":"59 George St West End Greater London W1H 5PH",
    "addr:housenumber":"59",
    "addr:postcode":"w1h 5ph",
    "addr:street":"George St",
    "iso:country":"GB",
    "sg:address":"59 George St",
    "sg:city":"West End",
    "sg:classifiers":[
        {
            "category":"Professional",
            "subcategory":"Management & Consulting",
            "type":"Services"
        }
    ],
    "sg:phone":"+44 20 7935 3001",
    "sg:postcode":"W1H 5PH",
    "sg:province":"Greater London",
    "sg:tags":[
        "consultant",
        "specialist"
    ],
    "wof:name":"Etrily Williams",
    "wof:placetype":"venue"
},
  "geometry": {"coordinates":[-0.16398,51.516491],"type":"Point"}
}