{
  "type": "Feature",
  "properties": {
    "iso:country":"GB",
    "sg:address":"13 Church St",
    "sg:city":"Houghton Le Spring",
    "sg:classifiers":[
        {
            "category":"Health Services",
            "subcategory":"Dentist",
            "type":"Services"
        }
    ],
    "sg:phone":"+44 191 584 3247",
    "sg:postcode":"DH4 4DN",
    "sg:province":"Durham",
    "wof:name":"G.W Maw",
    "wof:placetype":"venue"
},
  "geometry": {"coordinates":[-1.467989,54.841801],"type":"Point"}
}