{
  "type": "Feature",
  "properties": {
    "addr:full":"65-67 Ashbourne Rd Derby Derbyshire DE22 3FS",
    "addr:housenumber":"65-67",
    "addr:postcode":"de22 3fs",
    "addr:street":"Ashbourne Rd",
    "iso:country":"GB",
    "sg:address":"65-67 Ashbourne Rd",
    "sg:city":"Derby",
    "sg:classifiers":[
        {
            "category":"Health Services",
            "subcategory":"Clinic",
            "type":"Services"
        }
    ],
    "sg:phone":"+44 1332 292416",
    "sg:postcode":"DE22 3FS",
    "sg:province":"Derbyshire",
    "sg:tags":[
        "nh"
    ],
    "wof:name":"Elms Clinic",
    "wof:placetype":"venue"
},
  "geometry": {"coordinates":[-1.540767,52.937229],"type":"Point"}
}