{
  "type": "Feature",
  "properties": {
    "addr:full":"721 Lincoln Road Peterborough Cambridgeshire PE1 3HD",
    "addr:housenumber":"721",
    "addr:postcode":"pe1 3hd",
    "addr:street":"Lincoln Road",
    "iso:country":"GB",
    "sg:address":"721 Lincoln Road",
    "sg:city":"Peterborough",
    "sg:classifiers":[
        {
            "category":"Recreation",
            "subcategory":"Fishing",
            "type":"Entertainment"
        }
    ],
    "sg:postcode":"PE1 3HD",
    "sg:province":"Cambridgeshire",
    "sg:tags":[
        "angling"
    ],
    "wof:name":"P.D'S Fishing Tackle",
    "wof:placetype":"venue"
},
  "geometry": {"coordinates":[-0.2579959929,52.5948295593],"type":"Point"}
}