{
  "type": "Feature",
  "properties": {
    "addr:full":"106 Handsworth Rd Sheffield South Yorkshire S9 4AE",
    "addr:housenumber":"106",
    "addr:postcode":"s9 4ae",
    "addr:street":"Handsworth Rd",
    "iso:country":"GB",
    "sg:address":"106 Handsworth Rd",
    "sg:city":"Sheffield",
    "sg:classifiers":[
        {
            "category":"Organizations",
            "subcategory":"Professional Association",
            "type":"Services"
        }
    ],
    "sg:phone":"+44 114 261 0305",
    "sg:postcode":"S9 4AE",
    "sg:province":"South Yorkshire",
    "sg:tags":[
        "specialist",
        "calendar"
    ],
    "wof:name":"Carma Print & Promotions",
    "wof:placetype":"venue"
},
  "geometry": {"coordinates":[-1.397995,53.379219],"type":"Point"}
}