{
  "type": "Feature",
  "properties": {
    "addr:full":"14 Vulcan Way Sandhurst Berkshire GU47 9DB",
    "addr:housenumber":"14",
    "addr:postcode":"gu47 9db",
    "addr:street":"Vulcan Way",
    "iso:country":"GB",
    "sg:address":"14 Vulcan Way",
    "sg:city":"Sandhurst",
    "sg:classifiers":[
        {
            "category":"Autos & Motor Vehicles",
            "subcategory":"Automobile Sales",
            "type":"Retail Goods"
        }
    ],
    "sg:phone":"+44 1252 870030",
    "sg:postcode":"GU47 9DB",
    "sg:province":"Berkshire",
    "sg:tags":[
        "commercial"
    ],
    "wof:name":"Aurora Car Imports",
    "wof:placetype":"venue"
},
  "geometry": {"coordinates":[-0.802235,51.344261],"type":"Point"}
}