{
  "type": "Feature",
  "properties": {
    "iso:country":"GB",
    "sg:address":"Red Mine Close, Holditch Industrial Estate",
    "sg:city":"Newcastle",
    "sg:classifiers":[
        {
            "category":"Wholesale",
            "subcategory":"Chemicals & Plastics",
            "type":"Manufacturing & Wholesale Goods"
        }
    ],
    "sg:phone":"+44 1782 614973",
    "sg:postcode":"ST5 9HZ",
    "sg:province":"Staffordshire",
    "sg:tags":[
        "product",
        "allied"
    ],
    "wof:name":"W A Stewart & Co. Ltd.",
    "wof:placetype":"venue"
},
  "geometry": {"coordinates":[-2.2408950329,53.029460907],"type":"Point"}
}