{
  "type": "Feature",
  "properties": {
    "iso:country":"GB",
    "sg:address":"27 Manor Rd",
    "sg:city":"Goole",
    "sg:classifiers":[
        {
            "category":"Taxi",
            "type":"Transportation"
        }
    ],
    "sg:postcode":"DN14 5SD",
    "sg:province":"East Riding of Yorkshire",
    "sg:tags":[
        "mini",
        "cab"
    ],
    "wof:name":"Beadle,Nigel Thomas,",
    "wof:placetype":"venue"
},
  "geometry": {"coordinates":[-0.872799,53.692101],"type":"Point"}
}