{
  "type": "Feature",
  "properties": {
    "addr:full":"1 Chapel Street Welshpool Shropshire SY21 7LQ",
    "addr:housenumber":"1",
    "addr:postcode":"sy21 7lq",
    "addr:street":"Chapel Street",
    "iso:country":"GB",
    "sg:address":"1 Chapel Street",
    "sg:city":"Welshpool",
    "sg:classifiers":[
        {
            "category":"Military Area",
            "subcategory":"Air Force Base",
            "type":"Public Place"
        }
    ],
    "sg:postcode":"SY21 7LQ",
    "sg:province":"Shropshire",
    "sg:tags":[
        "taxi",
        "hire",
        "private"
    ],
    "wof:name":"Mount Taxis",
    "wof:placetype":"venue"
},
  "geometry": {"coordinates":[-3.152693,52.660801],"type":"Point"}
}