{
  "type": "Feature",
  "properties": {
    "iso:country":"GB",
    "sg:address":"364 West Bromwich Road",
    "sg:city":"Walsall",
    "sg:classifiers":[
        {
            "category":"Professional",
            "subcategory":"Engineering",
            "type":"Services"
        }
    ],
    "sg:phone":"+44 1922 649373",
    "sg:postcode":"WS5 4NU",
    "sg:province":"West Midlands",
    "sg:tags":[
        "contractor",
        "electrical",
        "engineer"
    ],
    "wof:name":"B B S Electrical & Security",
    "wof:placetype":"venue"
},
  "geometry": {"coordinates":[-1.977699,52.563976],"type":"Point"}
}