{
  "type": "Feature",
  "properties": {
    "addr:full":"2nd Floor 2 Meridians Cross, Ocean Village Southampton Hampshire SO14 3TJ",
    "addr:housenumber":"2nd floor 2",
    "addr:postcode":"so14 3tj",
    "addr:street":"Meridians Cross Ocean Village",
    "iso:country":"GB",
    "sg:address":"2nd Floor 2 Meridians Cross, Ocean Village",
    "sg:city":"Southampton",
    "sg:classifiers":[
        {
            "category":"Banks & Credit Unions",
            "subcategory":"Bank",
            "type":"Services"
        }
    ],
    "sg:postcode":"SO14 3TJ",
    "sg:province":"Hampshire",
    "sg:tags":[
        "broker",
        "mortgage"
    ],
    "wof:name":"Charcol,John,",
    "wof:placetype":"venue"
},
  "geometry": {"coordinates":[-1.39505,50.89566],"type":"Point"}
}