{
  "type": "Feature",
  "properties": {
    "addr:full":"Kirkton, Crudie Turriff Aberdeenshire AB53 5QB",
    "addr:postcode":"ab53 5qb",
    "iso:country":"GB",
    "sg:address":"Kirkton, Crudie",
    "sg:city":"Turriff",
    "sg:classifiers":[
        {
            "category":"Retail",
            "subcategory":"Animal Services",
            "type":"Services"
        }
    ],
    "sg:phone":"+44 1888 551685",
    "sg:postcode":"AB53 5QB",
    "sg:province":"Aberdeenshire",
    "sg:tags":[
        "box",
        "horse",
        "transporting"
    ],
    "wof:name":"Kirkton Horse Transport",
    "wof:placetype":"venue"
},
  "geometry": {"coordinates":[-2.344694,57.606529],"type":"Point"}
}