{
  "type": "Feature",
  "properties": {
    "iso:country":"GB",
    "sg:address":"Guildhall Buildings, Stephenson Street",
    "sg:city":"Birmingham",
    "sg:classifiers":[
        {
            "category":"Professional",
            "subcategory":"Business Services",
            "type":"Services"
        }
    ],
    "sg:phone":"+44 121 643 4117",
    "sg:postcode":"B2 4BH",
    "sg:province":"West Midlands",
    "sg:tags":[
        "fashion",
        "agent"
    ],
    "wof:name":"Stephen Chance Agency",
    "wof:placetype":"venue"
},
  "geometry": {"coordinates":[-1.9003,52.478661],"type":"Point"}
}