{
  "type": "Feature",
  "properties": {
    "iso:country":"GB",
    "sg:address":"Sterling Ho, 67 Lawrence Rd",
    "sg:city":"Seven Sisters",
    "sg:classifiers":[
        {
            "category":"Shopping",
            "subcategory":"Clothing, Apparel, & Fashions",
            "type":"Retail Goods"
        }
    ],
    "sg:phone":"+44 20 8800 0093",
    "sg:postcode":"N15 4EY",
    "sg:province":"Greater London",
    "sg:tags":[
        "clothing",
        "fabric"
    ],
    "wof:name":"Rosella Ltd",
    "wof:placetype":"venue"
},
  "geometry": {"coordinates":[-0.08008,51.58688],"type":"Point"}
}