{
  "type": "Feature",
  "properties": {
    "addr:full":"34b New Rd Ammanford Carmarthenshire SA18 1UN",
    "addr:housenumber":"34b",
    "addr:postcode":"sa18 1un",
    "addr:street":"New Rd",
    "iso:country":"GB",
    "sg:address":"34b New Rd",
    "sg:city":"Ammanford",
    "sg:classifiers":[
        {
            "category":"Building & Trades",
            "subcategory":"Equipment Rental",
            "type":"Services"
        }
    ],
    "sg:phone":"+44 7836 381502",
    "sg:postcode":"SA18 1UN",
    "sg:province":"Carmarthenshire",
    "sg:tags":[
        "plant",
        "machinery"
    ],
    "wof:name":"Maerdy Plant Hire",
    "wof:placetype":"venue"
},
  "geometry": {"coordinates":[-3.873389,51.793182],"type":"Point"}
}