{
  "type": "Feature",
  "properties": {
    "addr:full":"355-357 London Road Sheffield South Yorkshire S2 4NB",
    "addr:housenumber":"355-357",
    "addr:postcode":"s2 4nb",
    "addr:street":"London Road",
    "iso:country":"GB",
    "sg:address":"355-357 London Road",
    "sg:city":"Sheffield",
    "sg:classifiers":[
        {
            "category":"Transit Center",
            "subcategory":"Freight",
            "type":"Transportation"
        }
    ],
    "sg:postcode":"S2 4NB",
    "sg:province":"South Yorkshire",
    "sg:tags":[
        "piano",
        "accessory"
    ],
    "wof:name":"Allan C King",
    "wof:placetype":"venue"
},
  "geometry": {"coordinates":[-1.472485,53.36504],"type":"Point"}
}