{
  "type": "Feature",
  "properties": {
    "iso:country":"GB",
    "sg:address":"31b Clifton Road",
    "sg:city":"Rugby",
    "sg:classifiers":[
        {
            "category":"Food & Beverages",
            "subcategory":"Supermarket",
            "type":"Retail Goods"
        }
    ],
    "sg:phone":"+44 1788 572406",
    "sg:postcode":"CV21 3PY",
    "sg:province":"Warwickshire",
    "wof:name":"Kwik Save Stores Ltd.",
    "wof:placetype":"venue"
},
  "geometry": {"coordinates":[-1.25637,52.372002],"type":"Point"}
}