{
  "type": "Feature",
  "properties": {
    "addr:full":"40 Hanway Street London Greater London W1T 1US",
    "addr:housenumber":"40",
    "addr:postcode":"w1t 1us",
    "addr:street":"Hanway Street",
    "iso:country":"GB",
    "sg:address":"40 Hanway Street",
    "sg:city":"London",
    "sg:classifiers":[
        {
            "category":"Shopping",
            "subcategory":"Comic Books",
            "type":"Retail Goods"
        }
    ],
    "sg:phone":"+44 20 7631 0519",
    "sg:postcode":"W1T 1US",
    "sg:province":"Greater London",
    "sg:tags":[
        "jeweller"
    ],
    "wof:name":"The Oxford Jewellers",
    "wof:placetype":"venue"
},
  "geometry": {"coordinates":[-0.131724,51.5167160034],"type":"Point"}
}