{
  "type": "Feature",
  "properties": {
    "addr:full":"55 Kingston Road Wimbledon Greater London SW19 1JW",
    "addr:housenumber":"55",
    "addr:postcode":"sw19 1jw",
    "addr:street":"Kingston Road",
    "iso:country":"GB",
    "sg:address":"55 Kingston Road",
    "sg:city":"Wimbledon",
    "sg:classifiers":[
        {
            "category":"Retail",
            "subcategory":"Auto Repair",
            "type":"Services"
        }
    ],
    "sg:phone":"+44 20 8542 8489",
    "sg:postcode":"SW19 1JW",
    "sg:province":"Greater London",
    "sg:tags":[
        "modification",
        "garage"
    ],
    "wof:name":"J Oates",
    "wof:placetype":"venue"
},
  "geometry": {"coordinates":[-0.1953220069,51.4154815674],"type":"Point"}
}