{
  "type": "Feature",
  "properties": {
    "addr:full":"25 London Road King's Lynn Norfolk PE30 5QA",
    "addr:housenumber":"25",
    "addr:postcode":"pe30 5qa",
    "addr:street":"London Road",
    "iso:country":"GB",
    "sg:address":"25 London Road",
    "sg:city":"King's Lynn",
    "sg:classifiers":[
        {
            "category":"Retail",
            "subcategory":"Veterinary Services",
            "type":"Services"
        }
    ],
    "sg:phone":"+44 1553 773168",
    "sg:postcode":"PE30 5QA",
    "sg:province":"Norfolk",
    "sg:tags":[
        "surgeon"
    ],
    "wof:name":"The London Road Veterinary Clinic",
    "wof:placetype":"venue"
},
  "geometry": {"coordinates":[0.4024989903,52.7485580444],"type":"Point"}
}