{
  "type": "Feature",
  "properties": {
    "addr:full":"Ranase, Dudmoor Lane Christchurch Dorset BH23 6BQ",
    "addr:postcode":"bh23 6bq",
    "addr:street":"Dudmoor Lane",
    "iso:country":"GB",
    "sg:address":"Ranase, Dudmoor Lane",
    "sg:city":"Christchurch",
    "sg:classifiers":[
        {
            "category":"Building & Trades",
            "subcategory":"Construction",
            "type":"Services"
        },
        {
            "category":"Building & Trades",
            "subcategory":"Electrical",
            "type":"Services"
        }
    ],
    "sg:phone":"+44 1202 475710",
    "sg:postcode":"BH23 6BQ",
    "sg:province":"Dorset",
    "sg:tags":[
        "electrician",
        "decorator",
        "painter",
        "contractor"
    ],
    "wof:name":"R Clifford-Smith",
    "wof:placetype":"venue"
},
  "geometry": {"coordinates":[-1.79239,50.75856],"type":"Point"}
}