{
  "type": "Feature",
  "properties": {
    "iso:country":"GB",
    "sg:address":"The Rectory, East End Rd",
    "sg:city":"Southminster",
    "sg:classifiers":[
        {
            "category":"Place Of Worship",
            "type":"Public Place"
        }
    ],
    "sg:phone":"+44 1621 776203",
    "sg:postcode":"CM0 7PX",
    "sg:province":"Essex",
    "wof:name":"St Peters Chapel",
    "wof:placetype":"venue"
},
  "geometry": {"coordinates":[0.82919,51.662418],"type":"Point"}
}