{
  "type": "Feature",
  "properties": {
    "iso:country":"GB",
    "sg:address":"18 Hobart Crescent, Willen Park",
    "sg:city":"Milton Keynes",
    "sg:classifiers":[
        {
            "category":"Professional",
            "subcategory":"Business Services",
            "type":"Services"
        }
    ],
    "sg:postcode":"MK15 9HH",
    "sg:province":"Buckinghamshire",
    "sg:tags":[
        "shop",
        "cleaning"
    ],
    "wof:name":"J L Cleaning",
    "wof:placetype":"venue"
},
  "geometry": {"coordinates":[-0.737114,52.060024],"type":"Point"}
}