{
  "type": "Feature",
  "properties": {
    "addr:full":"Mcintosh House, Millender Walk London Greater London SE16 2SB",
    "addr:postcode":"se16 2sb",
    "addr:street":"Millender Walk",
    "iso:country":"GB",
    "sg:address":"Mcintosh House, Millender Walk",
    "sg:city":"London",
    "sg:classifiers":[
        {
            "category":"Building & Trades",
            "subcategory":"Plumbing",
            "type":"Services"
        }
    ],
    "sg:phone":"+44 20 7231 3944",
    "sg:postcode":"SE16 2SB",
    "sg:province":"Greater London",
    "sg:tags":[
        "central",
        "heating"
    ],
    "wof:name":"Seaflame Co. Ltd.",
    "wof:placetype":"venue"
},
  "geometry": {"coordinates":[-0.0516880006,51.4900512695],"type":"Point"}
}