{
  "type": "Feature",
  "properties": {
    "iso:country":"GB",
    "sg:address":"62 Priory St",
    "sg:city":"Tonbridge",
    "sg:classifiers":[
        {
            "category":"Food & Beverages",
            "subcategory":"Bakery",
            "type":"Retail Goods"
        }
    ],
    "sg:phone":"+44 1732 357485",
    "sg:postcode":"TN9 2AW",
    "sg:province":"Kent",
    "sg:tags":[
        "baker"
    ],
    "wof:name":"B & D Bakery Ltd",
    "wof:placetype":"venue"
},
  "geometry": {"coordinates":[0.273108989,51.1893501282],"type":"Point"}
}