{
  "type": "Feature",
  "properties": {
    "iso:country":"GB",
    "sg:address":"Newtech Square, Deeside Park",
    "sg:city":"Deeside",
    "sg:classifiers":[
        {
            "category":"Home & Garden",
            "subcategory":"Kitchen Supply",
            "type":"Retail Goods"
        }
    ],
    "sg:phone":"+44 1244 280081",
    "sg:postcode":"CH5 2NT",
    "sg:province":"Flintshire",
    "sg:tags":[
        "catering"
    ],
    "wof:name":"The National Catering Butcher Ltd",
    "wof:placetype":"venue"
},
  "geometry": {"coordinates":[-3.0059928894,53.2269935608],"type":"Point"}
}