{
  "type": "Feature",
  "properties": {
    "addr:full":"Quadron House, Mendip Road Weston-super-mare Somerset BS23 3HB",
    "addr:postcode":"bs23 3hb",
    "addr:street":"Mendip Road",
    "iso:country":"GB",
    "sg:address":"Quadron House, Mendip Road",
    "sg:city":"Weston-super-mare",
    "sg:classifiers":[
        {
            "category":"Building & Trades",
            "subcategory":"Cleaning & Sanitation",
            "type":"Services"
        }
    ],
    "sg:phone":"+44 1934 614444",
    "sg:postcode":"BS23 3HB",
    "sg:province":"Somerset",
    "sg:tags":[
        "facility"
    ],
    "wof:name":"Quadron Services Ltd.",
    "wof:placetype":"venue"
},
  "geometry": {"coordinates":[-2.9618339539,51.346786499],"type":"Point"}
}