{
  "type": "Feature",
  "properties": {
    "addr:full":"83-85 Saffron Hill London Greater London EC1N 8RT",
    "addr:housenumber":"83-85",
    "addr:postcode":"ec1n 8rt",
    "addr:street":"Saffron Hill",
    "iso:country":"GB",
    "sg:address":"83-85 Saffron Hill",
    "sg:city":"London",
    "sg:classifiers":[
        {
            "category":"Shopping",
            "subcategory":"Books",
            "type":"Retail Goods"
        }
    ],
    "sg:phone":"+44 20 7430 2800",
    "sg:postcode":"EC1N 8RT",
    "sg:province":"Greater London",
    "wof:name":"Usborne Publishing Ltd.",
    "wof:placetype":"venue"
},
  "geometry": {"coordinates":[-0.107543,51.521263],"type":"Point"}
}