{
  "type": "Feature",
  "properties": {
    "iso:country":"GB",
    "sg:address":"10a-10b High Street",
    "sg:city":"Horley",
    "sg:classifiers":[
        {
            "category":"Home & Garden",
            "subcategory":"Kitchen Supply",
            "type":"Retail Goods"
        }
    ],
    "sg:phone":"+44 1293 820930",
    "sg:postcode":"RH6 7AY",
    "sg:province":"Surrey",
    "sg:tags":[
        "equipment",
        "catering"
    ],
    "wof:name":"M & G Catering Equipment",
    "wof:placetype":"venue"
},
  "geometry": {"coordinates":[-0.163138,51.171822],"type":"Point"}
}