{
  "type": "Feature",
  "properties": {
    "addr:full":"47 Wellingborough Road, Earls Barton Northampton Northamptonshire NN6 0JS",
    "addr:housenumber":"47",
    "addr:postcode":"nn6 0js",
    "addr:street":"Wellingborough Road",
    "iso:country":"GB",
    "sg:address":"47 Wellingborough Road, Earls Barton",
    "sg:city":"Northampton",
    "sg:classifiers":[
        {
            "category":"Personal",
            "subcategory":"Beauty Salon",
            "type":"Services"
        }
    ],
    "sg:phone":"+44 1604 812982",
    "sg:postcode":"NN6 0JS",
    "sg:province":"Northamptonshire",
    "sg:tags":[
        "unisex",
        "hairdresser"
    ],
    "wof:name":"Bizzy Sizzors",
    "wof:placetype":"venue"
},
  "geometry": {"coordinates":[-0.7470859885,52.2690925598],"type":"Point"}
}