{
  "type": "Feature",
  "properties": {
    "iso:country":"GB",
    "sg:address":"Unit 6 Acorn Business Centre, Lees Road",
    "sg:city":"Liverpool",
    "sg:classifiers":[
        {
            "category":"Shopping",
            "subcategory":"Discount & Variety Stores",
            "type":"Retail Goods"
        }
    ],
    "sg:phone":"+44 151 546 4005",
    "sg:postcode":"L33 7SA",
    "sg:province":"Lancashire",
    "sg:tags":[
        "cleaning",
        "supply"
    ],
    "wof:name":"North West Wiper Co",
    "wof:placetype":"venue"
},
  "geometry": {"coordinates":[-2.863469,53.480675],"type":"Point"}
}