{
  "type": "Feature",
  "properties": {
    "addr:full":"75 Belvedere View Galston East Ayrshire KA4 8QD",
    "addr:housenumber":"75",
    "addr:postcode":"ka4 8qd",
    "addr:street":"Belvedere View Galston East",
    "iso:country":"GB",
    "sg:address":"75 Belvedere View",
    "sg:city":"Galston",
    "sg:classifiers":[
        {
            "category":"Professional",
            "subcategory":"Art Services",
            "type":"Services"
        },
        {
            "category":"Building & Trades",
            "subcategory":"Construction",
            "type":"Services"
        }
    ],
    "sg:phone":"+44 1563 821841",
    "sg:postcode":"KA4 8QD",
    "sg:province":"East Ayrshire",
    "sg:tags":[
        "glazier",
        "decorator",
        "painter"
    ],
    "wof:name":"I Morrison",
    "wof:placetype":"venue"
},
  "geometry": {"coordinates":[-4.3695459366,55.5989151001],"type":"Point"}
}