{
  "type": "Feature",
  "properties": {
    "addr:full":"The Galleries, 37 Market Street Wigan Lancashire WN1 1JL",
    "addr:housenumber":"37",
    "addr:postcode":"wn1 1jl",
    "addr:street":"Market Street",
    "iso:country":"GB",
    "sg:address":"The Galleries, 37 Market Street",
    "sg:city":"Wigan",
    "sg:classifiers":[
        {
            "category":"Shopping",
            "subcategory":"Pharmacy",
            "type":"Retail Goods"
        }
    ],
    "sg:phone":"+44 1942 242788",
    "sg:postcode":"WN1 1JL",
    "sg:province":"Lancashire",
    "sg:tags":[
        "pharmacist",
        "chemist"
    ],
    "wof:name":"Boots the Chemist",
    "wof:placetype":"venue"
},
  "geometry": {"coordinates":[-2.6335320473,53.5441551208],"type":"Point"}
}