{
  "type": "Feature",
  "properties": {
    "iso:country":"GB",
    "sg:address":"10 Kings Bench Wk, Temple",
    "sg:city":"London",
    "sg:classifiers":[
        {
            "category":"Professional",
            "subcategory":"Lawyer & Legal Services",
            "type":"Services"
        }
    ],
    "sg:phone":"+44 20 7353 2501",
    "sg:postcode":"EC4Y 7EB",
    "sg:province":"Greater London",
    "sg:tags":[
        "barrister"
    ],
    "wof:name":"James Shaw",
    "wof:placetype":"venue"
},
  "geometry": {"coordinates":[-0.1086879969,51.5119819641],"type":"Point"}
}