{
  "type": "Feature",
  "properties": {
    "addr:full":"4 Pound Lane Tomatin Devon EX3 0NA",
    "addr:housenumber":"4",
    "addr:postcode":"ex3 0na",
    "addr:street":"Pound Lane",
    "iso:country":"GB",
    "sg:address":"4 Pound Lane",
    "sg:city":"Tomatin",
    "sg:classifiers":[
        {
            "category":"Real Estate",
            "subcategory":"Architect",
            "type":"Services"
        }
    ],
    "sg:phone":"+44 20 8668 6011",
    "sg:postcode":"EX3 0NA",
    "sg:province":"Devon",
    "wof:name":"Gundry Dyer Greenway",
    "wof:placetype":"venue"
},
  "geometry": {"coordinates":[-3.46647,50.68755],"type":"Point"}
}