{
  "type": "Feature",
  "properties": {
    "addr:full":"6 Strathord Place, Moodiesburn Glasgow East Dunbartonshire G69 0NA",
    "addr:housenumber":"6",
    "addr:postcode":"g69 0na",
    "addr:street":"Strathord Place",
    "iso:country":"GB",
    "sg:address":"6 Strathord Place, Moodiesburn",
    "sg:city":"Glasgow",
    "sg:classifiers":[
        {
            "category":"Organizations",
            "subcategory":"Non-profit Organization",
            "type":"Services"
        }
    ],
    "sg:postcode":"G69 0NA",
    "sg:province":"East Dunbartonshire",
    "sg:tags":[
        "organisation",
        "voluntary",
        "charity"
    ],
    "wof:name":"Cat Advisory & Rescue Service",
    "wof:placetype":"venue"
},
  "geometry": {"coordinates":[-4.0800008774,55.9190826416],"type":"Point"}
}