{
  "type": "Feature",
  "properties": {
    "iso:country":"GB",
    "sg:address":"3 Bray Road, Stoke D'abernon",
    "sg:city":"Cobham",
    "sg:classifiers":[
        {
            "category":"Personal",
            "subcategory":"Beauty Salon",
            "type":"Services"
        }
    ],
    "sg:phone":"+44 1932 863476",
    "sg:postcode":"KT11 3HZ",
    "sg:province":"Surrey",
    "sg:tags":[
        "unisex",
        "lady",
        "hairdresser"
    ],
    "wof:name":"Raymond Hedley",
    "wof:placetype":"venue"
},
  "geometry": {"coordinates":[-0.389332,51.319042],"type":"Point"}
}