{
  "type": "Feature",
  "properties": {
    "iso:country":"GB",
    "sg:address":"1st Floor 15-17 Oldgate",
    "sg:city":"Morpeth",
    "sg:classifiers":[
        {
            "category":"Personal",
            "type":"Services"
        }
    ],
    "sg:postcode":"NE61 1LX",
    "sg:province":"Northumberland",
    "sg:tags":[
        "dressmaker"
    ],
    "wof:name":"Ellens Simply Sewing",
    "wof:placetype":"venue"
},
  "geometry": {"coordinates":[-1.6927089691,55.1675949097],"type":"Point"}
}