{
  "type": "Feature",
  "properties": {
    "iso:country":"GB",
    "sg:address":"Birbeck Road",
    "sg:city":"Sidcup",
    "sg:classifiers":[
        {
            "category":"Manufacturing",
            "subcategory":"Metals",
            "type":"Manufacturing & Wholesale Goods"
        },
        {
            "category":"Professional",
            "subcategory":"Engineering",
            "type":"Services"
        }
    ],
    "sg:phone":"+44 20 8300 5111",
    "sg:postcode":"DA14 4DB",
    "sg:province":"Kent",
    "sg:tags":[
        "fabricator"
    ],
    "wof:name":"Warren Engineering Ltd",
    "wof:placetype":"venue"
},
  "geometry": {"coordinates":[0.1060300022,51.4310798645],"type":"Point"}
}