{
  "type": "Feature",
  "properties": {
    "iso:country":"GB",
    "sg:address":"20 Rothes Drive",
    "sg:city":"Glasgow",
    "sg:classifiers":[
        {
            "category":"Food & Beverages",
            "subcategory":"Supermarket",
            "type":"Retail Goods"
        }
    ],
    "sg:phone":"+44 141 946 0467",
    "sg:postcode":"G23 5EZ",
    "sg:province":"Glasgow City",
    "sg:website":"http://www.asda.co.uk",
    "wof:name":"Asda Stores Ltd.",
    "wof:placetype":"venue"
},
  "geometry": {"coordinates":[-4.29761,55.902317],"type":"Point"}
}