{
  "type": "Feature",
  "properties": {
    "addr:full":"1 The Timbers Fareham Hampshire PO15 5NB",
    "addr:housenumber":"1",
    "addr:postcode":"po15 5nb",
    "addr:street":"The",
    "iso:country":"GB",
    "sg:address":"1 The Timbers",
    "sg:city":"Fareham",
    "sg:classifiers":[
        {
            "category":"Professional",
            "subcategory":"Management & Consulting",
            "type":"Services"
        }
    ],
    "sg:postcode":"PO15 5NB",
    "sg:province":"Hampshire",
    "sg:tags":[
        "consultant",
        "business"
    ],
    "wof:name":"McMillan Associates",
    "wof:placetype":"venue"
},
  "geometry": {"coordinates":[-1.216091,50.851734],"type":"Point"}
}