{
  "type": "Feature",
  "properties": {
    "iso:country":"GB",
    "sg:address":"2 Lilac Grove, Beeston",
    "sg:city":"Nottingham",
    "sg:classifiers":[
        {
            "category":"Health Services",
            "subcategory":"Nursing And Care Facility",
            "type":"Services"
        }
    ],
    "sg:phone":"+44 115 925 2319",
    "sg:postcode":"NG9 1PA",
    "sg:province":"Nottinghamshire",
    "sg:tags":[
        "home"
    ],
    "wof:name":"Lilac Residential Care Home",
    "wof:placetype":"venue"
},
  "geometry": {"coordinates":[-1.2036219835,52.9218063354],"type":"Point"}
}