{
  "type": "Feature",
  "properties": {
    "addr:full":"Lower Holditch Axminster Devon EX13 7AX",
    "addr:postcode":"ex13 7ax",
    "addr:street":"Lower Holditch",
    "iso:country":"GB",
    "sg:address":"Lower Holditch",
    "sg:city":"Axminster",
    "sg:classifiers":[
        {
            "category":"Farming",
            "subcategory":"Livestock Farm",
            "type":"Manufacturing & Wholesale Goods"
        }
    ],
    "sg:postcode":"EX13 7AX",
    "sg:province":"Devon",
    "sg:tags":[
        "others"
    ],
    "wof:name":"Captain P E I Bailey",
    "wof:placetype":"venue"
},
  "geometry": {"coordinates":[-2.9414319992,50.8182487488],"type":"Point"}
}