{
  "type": "Feature",
  "properties": {
    "addr:full":"22 Bristol Arcade Sleaford Lincolnshire NG34 7ST",
    "addr:housenumber":"22",
    "addr:postcode":"ng34 7st",
    "addr:street":"Bristol Arcade",
    "iso:country":"GB",
    "sg:address":"22 Bristol Arcade",
    "sg:city":"Sleaford",
    "sg:classifiers":[
        {
            "category":"Farming",
            "subcategory":"Livestock Farm",
            "type":"Manufacturing & Wholesale Goods"
        }
    ],
    "sg:phone":"+44 1529 415306",
    "sg:postcode":"NG34 7ST",
    "sg:province":"Lincolnshire",
    "sg:tags":[
        "breeder"
    ],
    "wof:name":"Tudor Flowers",
    "wof:placetype":"venue"
},
  "geometry": {"coordinates":[-0.42022,53.001671],"type":"Point"}
}