{
  "type": "Feature",
  "properties": {
    "addr:full":"117 The Gro London Greater London E15 1EN",
    "addr:housenumber":"117",
    "addr:postcode":"e15 1en",
    "addr:street":"The Gro",
    "iso:country":"GB",
    "sg:address":"117 The Gro",
    "sg:city":"London",
    "sg:classifiers":[
        {
            "category":"Food & Beverages",
            "subcategory":"Candy",
            "type":"Retail Goods"
        }
    ],
    "sg:postcode":"E15 1EN",
    "sg:province":"Greater London",
    "sg:tags":[
        "confectioner"
    ],
    "wof:name":"S C Patel",
    "wof:placetype":"venue"
},
  "geometry": {"coordinates":[0.0046299999,51.5450706482],"type":"Point"}
}