{
  "type": "Feature",
  "properties": {
    "addr:full":"Unit 1, Oakwood, 205 Old Oak Common Lane London Greater London W3 7DX",
    "addr:housenumber":"unit 1;205",
    "addr:postcode":"w3 7dx",
    "addr:street":"Oakwood;Old Oak Common Lane",
    "iso:country":"GB",
    "sg:address":"Unit 1, Oakwood, 205 Old Oak Common Lane",
    "sg:city":"London",
    "sg:classifiers":[
        {
            "category":"Freight",
            "type":"Transportation"
        }
    ],
    "sg:phone":"+44 1932 788597",
    "sg:postcode":"W3 7DX",
    "sg:province":"Greater London",
    "sg:tags":[
        "haulage",
        "road"
    ],
    "wof:name":"Taylor Transport (London) Ltd.",
    "wof:placetype":"venue"
},
  "geometry": {"coordinates":[-0.25139,51.521389],"type":"Point"}
}