{
  "type": "Feature",
  "properties": {
    "iso:country":"GB",
    "sg:address":"160 Inderwick Rd",
    "sg:city":"Hornsey",
    "sg:classifiers":[
        {
            "category":"Professional",
            "subcategory":"Lawyer & Legal Services",
            "type":"Services"
        }
    ],
    "sg:phone":"+44 20 8341 7167",
    "sg:postcode":"N8 9JT",
    "sg:province":"Greater London",
    "sg:tags":[
        "advice",
        "counselling"
    ],
    "wof:name":"Community Hygiene Concern Help Line",
    "wof:placetype":"venue"
},
  "geometry": {"coordinates":[-0.116684,51.582813],"type":"Point"}
}