{
  "type": "Feature",
  "properties": {
    "iso:country":"GB",
    "sg:address":"39 Clarendon Street",
    "sg:city":"Cambridge",
    "sg:classifiers":[
        {
            "category":"Government",
            "subcategory":"Post Office",
            "type":"Public Place"
        }
    ],
    "sg:postcode":"CB1 1JX",
    "sg:province":"Cambridgeshire",
    "sg:tags":[
        "organisation",
        "soc",
        "research"
    ],
    "wof:name":"Cemorc Ltd.",
    "wof:placetype":"venue"
},
  "geometry": {"coordinates":[0.127313,52.204414],"type":"Point"}
}