{
  "type": "Feature",
  "properties": {
    "iso:country":"GB",
    "sg:address":"Holmgate Road, Clay Cross",
    "sg:city":"Chesterfield",
    "sg:classifiers":[
        {
            "category":"Education",
            "subcategory":"Library",
            "type":"Public Place"
        },
        {
            "category":"Government",
            "subcategory":"Office",
            "type":"Public Place"
        }
    ],
    "sg:phone":"+44 1246 862592",
    "sg:postcode":"S45 9PH",
    "sg:province":"Derbyshire",
    "sg:tags":[
        "book",
        "local"
    ],
    "wof:name":"Clay Cross Library",
    "wof:placetype":"venue"
},
  "geometry": {"coordinates":[-1.4157170057,53.1657905579],"type":"Point"}
}