{
  "type": "Feature",
  "properties": {
    "iso:country":"GB",
    "sg:address":"12 Great Preston Road",
    "sg:city":"Ryde",
    "sg:classifiers":[
        {
            "category":"Building & Trades",
            "subcategory":"Landscaping Services",
            "type":"Services"
        }
    ],
    "sg:phone":"+44 1983 566632",
    "sg:postcode":"PO33 1DR",
    "sg:province":"Isle of Wight",
    "sg:tags":[
        "gardening"
    ],
    "wof:name":"Ian Harding",
    "wof:placetype":"venue"
},
  "geometry": {"coordinates":[-1.150043,50.721458],"type":"Point"}
}