{
  "type": "Feature",
  "properties": {
    "addr:full":"Wanbourne Lane, Nettlebed Henley-on-thames Berkshire RG9 5AJ",
    "addr:postcode":"rg9 5aj",
    "addr:street":"Wanbourne Lane",
    "iso:country":"GB",
    "sg:address":"Wanbourne Lane, Nettlebed",
    "sg:city":"Henley-on-thames",
    "sg:classifiers":[
        {
            "category":"Health Services",
            "subcategory":"Doctor",
            "type":"Services"
        }
    ],
    "sg:phone":"+44 1491 641204",
    "sg:postcode":"RG9 5AJ",
    "sg:province":"Berkshire",
    "sg:tags":[
        "practitioners"
    ],
    "wof:name":"The Surgery",
    "wof:placetype":"venue"
},
  "geometry": {"coordinates":[-0.991999,51.576988],"type":"Point"}
}