{
  "type": "Feature",
  "properties": {
    "iso:country":"GB",
    "sg:address":"13 Clinton Crescent",
    "sg:city":"St Leonards-on-sea",
    "sg:classifiers":[
        {
            "category":"Shopping",
            "subcategory":"Computers & Home Electronics",
            "type":"Retail Goods"
        }
    ],
    "sg:phone":"+44 1424 714902",
    "sg:postcode":"TN38 0RN",
    "sg:province":"East Sussex",
    "wof:name":"Phoenix Systems",
    "wof:placetype":"venue"
},
  "geometry": {"coordinates":[0.552653,50.862202],"type":"Point"}
}