{
  "type": "Feature",
  "properties": {
    "iso:country":"GB",
    "sg:address":"Moor Allerton Centre",
    "sg:city":"Leeds",
    "sg:classifiers":[
        {
            "category":"Education",
            "subcategory":"Library",
            "type":"Public Place"
        }
    ],
    "sg:phone":"+44 113 214 5624",
    "sg:postcode":"LS17 5NY",
    "sg:province":"North Yorkshire",
    "sg:tags":[
        "book"
    ],
    "wof:name":"Moor Allerton Library",
    "wof:placetype":"venue"
},
  "geometry": {"coordinates":[-1.549536,53.84539],"type":"Point"}
}