{
  "type": "Feature",
  "properties": {
    "addr:full":"62 Harrogate Road Leeds West Yorkshire LS7 4LA",
    "addr:housenumber":"62",
    "addr:postcode":"ls7 4la",
    "addr:street":"Harrogate Road",
    "iso:country":"GB",
    "sg:address":"62 Harrogate Road",
    "sg:city":"Leeds",
    "sg:classifiers":[
        {
            "category":"Personal",
            "subcategory":"Beauty Salon",
            "type":"Services"
        }
    ],
    "sg:postcode":"LS7 4LA",
    "sg:province":"West Yorkshire",
    "sg:tags":[
        "unisex",
        "hairdresser"
    ],
    "wof:name":"Gino & Corrado",
    "wof:placetype":"venue"
},
  "geometry": {"coordinates":[-1.536054,53.827065],"type":"Point"}
}