{
  "type": "Feature",
  "properties": {
    "addr:full":"71 Kemble Street Prescot Merseyside L34 5SF",
    "addr:housenumber":"71",
    "addr:postcode":"l34 5sf",
    "addr:street":"Kemble Street",
    "iso:country":"GB",
    "sg:address":"71 Kemble Street",
    "sg:city":"Prescot",
    "sg:classifiers":[
        {
            "category":"Banks & Credit Unions",
            "subcategory":"Financial Services",
            "type":"Services"
        }
    ],
    "sg:phone":"+44 151 493 1999",
    "sg:postcode":"L34 5SF",
    "sg:province":"Merseyside",
    "sg:tags":[
        "consultant"
    ],
    "wof:name":"Abacus Financial Services",
    "wof:placetype":"venue"
},
  "geometry": {"coordinates":[-2.80133,53.427876],"type":"Point"}
}