{
  "type": "Feature",
  "properties": {
    "iso:country":"GB",
    "sg:address":"47-48 St Mary Street",
    "sg:city":"Cardiff",
    "sg:classifiers":[
        {
            "category":"Shopping",
            "subcategory":"Clothing, Apparel, & Fashions",
            "type":"Retail Goods"
        }
    ],
    "sg:postcode":"CF10 1FA",
    "sg:province":"Cardiff",
    "sg:tags":[
        "shop"
    ],
    "wof:name":"Keith & Dennis Glaister",
    "wof:placetype":"venue"
},
  "geometry": {"coordinates":[-3.177989,51.478401],"type":"Point"}
}