{
  "type": "Feature",
  "properties": {
    "addr:full":"Unit 29, Ford House Road Industrial Estate, Steel Drive Wolverhampton Staffordshire WV10 9XE",
    "addr:housenumber":"unit 29 ford",
    "addr:postcode":"wv10 9xe",
    "addr:street":"House Road Industrial Estate Steel Drive",
    "iso:country":"GB",
    "sg:address":"Unit 29, Ford House Road Industrial Estate, Steel Drive",
    "sg:city":"Wolverhampton",
    "sg:classifiers":[
        {
            "category":"Personal",
            "subcategory":"Skin Care",
            "type":"Services"
        }
    ],
    "sg:phone":"+44 1902 787900",
    "sg:postcode":"WV10 9XE",
    "sg:province":"Staffordshire",
    "sg:tags":[
        "leather",
        "merchant"
    ],
    "wof:name":"William Hudson & Sons (Wolverhampton) Ltd.",
    "wof:placetype":"venue"
},
  "geometry": {"coordinates":[-2.123992,52.618488],"type":"Point"}
}