{
  "type": "Feature",
  "properties": {
    "iso:country":"GB",
    "sg:address":"Winsu Avenue",
    "sg:city":"Paignton",
    "sg:classifiers":[
        {
            "category":"Professional",
            "subcategory":"Engineering",
            "type":"Services"
        }
    ],
    "sg:postcode":"TQ3 1QF",
    "sg:province":"Devon",
    "sg:tags":[
        "contractor",
        "electrical",
        "engineer"
    ],
    "wof:name":"Russell Hodge",
    "wof:placetype":"venue"
},
  "geometry": {"coordinates":[-3.571111,50.445724],"type":"Point"}
}