{
  "type": "Feature",
  "properties": {
    "iso:country":"GB",
    "sg:address":"Highfield House, 1 Highfield Terrace",
    "sg:city":"Leamington Spa",
    "sg:classifiers":[
        {
            "category":"Real Estate",
            "subcategory":"Architect",
            "type":"Services"
        }
    ],
    "sg:phone":"+44 1926 336820",
    "sg:postcode":"CV32 6EE",
    "sg:province":"Warwickshire",
    "wof:name":"Brian R  Bassett Ltd.",
    "wof:placetype":"venue"
},
  "geometry": {"coordinates":[-1.5525089502,52.2911109924],"type":"Point"}
}