{
  "type": "Feature",
  "properties": {
    "addr:full":"3 Vernon Street Liverpool Merseyside L2 2AZ",
    "addr:housenumber":"3",
    "addr:postcode":"l2 2az",
    "addr:street":"Vernon Street",
    "iso:country":"GB",
    "sg:address":"3 Vernon Street",
    "sg:city":"Liverpool",
    "sg:classifiers":[
        {
            "category":"Professional",
            "type":"Services"
        }
    ],
    "sg:phone":"+44 151 652 9885",
    "sg:postcode":"L2 2AZ",
    "sg:province":"Merseyside",
    "sg:tags":[
        "shopfitters"
    ],
    "wof:name":"Precise Construction Ltd.",
    "wof:placetype":"venue"
},
  "geometry": {"coordinates":[-2.988006,53.408665],"type":"Point"}
}