{
  "type": "Feature",
  "properties": {
    "iso:country":"GB",
    "sg:address":"11 Marborough Road",
    "sg:city":"Swindon",
    "sg:classifiers":[
        {
            "category":"Retail",
            "subcategory":"Auto Rental",
            "type":"Services"
        },
        {
            "category":"Autos & Motor Vehicles",
            "subcategory":"Automobile Sales",
            "type":"Retail Goods"
        },
        {
            "category":"Banks & Credit Unions",
            "subcategory":"Bank",
            "type":"Services"
        }
    ],
    "sg:phone":"+44 1793 644996",
    "sg:postcode":"SN3 1QT",
    "sg:province":"Wiltshire",
    "sg:tags":[
        "car",
        "commercial",
        "broker",
        "mortgage"
    ],
    "wof:name":"DAVID PEARCE",
    "wof:placetype":"venue"
},
  "geometry": {"coordinates":[-1.7723519802,51.5496330261],"type":"Point"}
}