{
  "type": "Feature",
  "properties": {
    "iso:country":"GB",
    "sg:address":"Station Road",
    "sg:city":"South Queensferry",
    "sg:classifiers":[
        {
            "category":"Education",
            "subcategory":"School",
            "type":"Public Place"
        }
    ],
    "sg:phone":"+44 131 331 1895",
    "sg:postcode":"EH30 9JY",
    "sg:province":"City of Edinburgh",
    "sg:tags":[
        "local",
        "authority"
    ],
    "wof:name":"St Margaret's R C Primary School",
    "wof:placetype":"venue"
},
  "geometry": {"coordinates":[-3.381069,55.986694],"type":"Point"}
}