{
  "type": "Feature",
  "properties": {
    "iso:country":"GB",
    "sg:address":"21 Hillersdon Avenue",
    "sg:city":"Edgware",
    "sg:classifiers":[
        {
            "category":"Professional",
            "subcategory":"Accounting & Tax Preparation",
            "type":"Services"
        }
    ],
    "sg:phone":"+44 20 8905 3334",
    "sg:postcode":"HA8 7SG",
    "sg:province":"Greater London",
    "sg:tags":[
        "accountant"
    ],
    "wof:name":"A U Chauhan & Co",
    "wof:placetype":"venue"
},
  "geometry": {"coordinates":[-0.286581,51.617519],"type":"Point"}
}