{
  "type": "Feature",
  "properties": {
    "addr:full":"Spelmonden Farm, Spelmonden Road, Goudhurst Cranbrook Kent TN17 1HE",
    "addr:postcode":"tn17 1he",
    "addr:street":"Spelmonden Road",
    "iso:country":"GB",
    "sg:address":"Spelmonden Farm, Spelmonden Road, Goudhurst",
    "sg:city":"Cranbrook",
    "sg:classifiers":[
        {
            "category":"Farming",
            "subcategory":"Livestock Farm",
            "type":"Manufacturing & Wholesale Goods"
        }
    ],
    "sg:phone":"+44 1580 211400",
    "sg:postcode":"TN17 1HE",
    "sg:province":"Kent",
    "sg:tags":[
        "others"
    ],
    "wof:name":"Spelmonden Estate Co Ltd",
    "wof:placetype":"venue"
},
  "geometry": {"coordinates":[0.458639,51.112839],"type":"Point"}
}