{
  "type": "Feature",
  "properties": {
    "addr:full":"110 Clarendon Road London Greater London W11 2HR",
    "addr:housenumber":"110",
    "addr:postcode":"w11 2hr",
    "addr:street":"Clarendon Road",
    "iso:country":"GB",
    "sg:address":"110 Clarendon Road",
    "sg:city":"London",
    "sg:classifiers":[
        {
            "category":"Professional",
            "type":"Services"
        },
        {
            "category":"Communications",
            "subcategory":"Film & Video Production",
            "type":"Services"
        }
    ],
    "sg:phone":"+44 20 7221 7799",
    "sg:postcode":"W11 2HR",
    "sg:province":"Greater London",
    "sg:tags":[
        "entertainer",
        "studio"
    ],
    "wof:name":"The Flying Music Co. Ltd.",
    "wof:placetype":"venue"
},
  "geometry": {"coordinates":[-0.211326,51.513077],"type":"Point"}
}