{
  "type": "Feature",
  "properties": {
    "addr:full":"9b Church Street Troon South Ayrshire KA10 6AU",
    "addr:housenumber":"9b",
    "addr:postcode":"ka10 6au",
    "addr:street":"Church Street",
    "iso:country":"GB",
    "sg:address":"9b Church Street",
    "sg:city":"Troon",
    "sg:classifiers":[
        {
            "category":"Shopping",
            "subcategory":"Shoes",
            "type":"Retail Goods"
        }
    ],
    "sg:phone":"+44 1292 315871",
    "sg:postcode":"KA10 6AU",
    "sg:province":"South Ayrshire",
    "sg:tags":[
        "shop",
        "retailer",
        "footwear"
    ],
    "wof:name":"de Beaufort Footwear",
    "wof:placetype":"venue"
},
  "geometry": {"coordinates":[-4.661102,55.544197],"type":"Point"}
}