{
  "type": "Feature",
  "properties": {
    "addr:full":"29 Wigston Street, Countesthorpe Leicester Leicestershire LE8 5RP",
    "addr:housenumber":"29",
    "addr:postcode":"le8 5rp",
    "addr:street":"Wigston Street",
    "iso:country":"GB",
    "sg:address":"29 Wigston Street, Countesthorpe",
    "sg:city":"Leicester",
    "sg:classifiers":[
        {
            "category":"Shopping",
            "subcategory":"Stationery & Office Supplies",
            "type":"Retail Goods"
        }
    ],
    "sg:phone":"+44 116 277 2262",
    "sg:postcode":"LE8 5RP",
    "sg:province":"Leicestershire",
    "sg:tags":[
        "equipment",
        "school"
    ],
    "wof:name":"Edu Playtoys",
    "wof:placetype":"venue"
},
  "geometry": {"coordinates":[-1.135627,52.55492],"type":"Point"}
}