{
  "type": "Feature",
  "properties": {
    "addr:full":"4 Park Close, Penwortham Residential Park Preston Lancashire PR1 9YA",
    "addr:housenumber":"4",
    "addr:postcode":"pr1 9ya",
    "addr:street":"Park Close;Residential Park",
    "iso:country":"GB",
    "sg:address":"4 Park Close, Penwortham Residential Park",
    "sg:city":"Preston",
    "sg:classifiers":[
        {
            "category":"Military Area",
            "subcategory":"Air Force Base",
            "type":"Public Place"
        }
    ],
    "sg:phone":"+44 1772 747667",
    "sg:postcode":"PR1 9YA",
    "sg:province":"Lancashire",
    "sg:tags":[
        "taxi",
        "hire",
        "private"
    ],
    "wof:name":"Peters Taxi",
    "wof:placetype":"venue"
},
  "geometry": {"coordinates":[-2.7095220089,53.7392044067],"type":"Point"}
}