{
  "type": "Feature",
  "properties": {
    "iso:country":"GB",
    "sg:address":"6 Fullwood Crescent, Holly Hall",
    "sg:city":"Dudley",
    "sg:classifiers":[
        {
            "category":"Shopping",
            "subcategory":"Party Supplies",
            "type":"Retail Goods"
        }
    ],
    "sg:phone":"+44 1384 824660",
    "sg:postcode":"DY2 0SQ",
    "sg:province":"West Midlands",
    "sg:tags":[
        "inflatables",
        "bouncy",
        "castle"
    ],
    "wof:name":"J's Bouncing Castles",
    "wof:placetype":"venue"
},
  "geometry": {"coordinates":[-2.112298,52.494759],"type":"Point"}
}