{
  "type": "Feature",
  "properties": {
    "addr:full":"Bouchers Hall, Kelvedon Road, Messing Colchester Essex CO5 9TW",
    "addr:postcode":"co5 9tw",
    "addr:street":"Kelvedon Road Messing Colchester",
    "iso:country":"GB",
    "sg:address":"Bouchers Hall, Kelvedon Road, Messing",
    "sg:city":"Colchester",
    "sg:classifiers":[
        {
            "category":"Farming",
            "subcategory":"Livestock Farm",
            "type":"Manufacturing & Wholesale Goods"
        }
    ],
    "sg:phone":"+44 1621 815565",
    "sg:postcode":"CO5 9TW",
    "sg:province":"Essex",
    "sg:tags":[
        "others"
    ],
    "wof:name":"Norman S Campbell",
    "wof:placetype":"venue"
},
  "geometry": {"coordinates":[0.7051849961,51.8399734497],"type":"Point"}
}