{
  "type": "Feature",
  "properties": {
    "addr:full":"687 High Road, Tottenham London Greater London N17 8AD",
    "addr:housenumber":"687",
    "addr:postcode":"n17 8ad",
    "addr:street":"High Road",
    "iso:country":"GB",
    "sg:address":"687 High Road, Tottenham",
    "sg:city":"London",
    "sg:classifiers":[
        {
            "category":"Taxi",
            "type":"Transportation"
        }
    ],
    "sg:postcode":"N17 8AD",
    "sg:province":"Greater London",
    "sg:tags":[
        "mini",
        "cab"
    ],
    "wof:name":"G T Car Service",
    "wof:placetype":"venue"
},
  "geometry": {"coordinates":[-0.068087,51.600677],"type":"Point"}
}