{
  "type": "Feature",
  "properties": {
    "iso:country":"GB",
    "sg:address":"1 Ebble Cottage, Homington",
    "sg:city":"Salisbury",
    "sg:classifiers":[
        {
            "category":"Health Services",
            "subcategory":"Clinic",
            "type":"Services"
        }
    ],
    "sg:postcode":"SP5 4NJ",
    "sg:province":"Dorset",
    "sg:tags":[
        "aromatherapy"
    ],
    "wof:name":"Natural Fragrances",
    "wof:placetype":"venue"
},
  "geometry": {"coordinates":[-1.823969,51.033329],"type":"Point"}
}