{
  "type": "Feature",
  "properties": {
    "addr:full":"11 High Street, Winchcombe Cheltenham Gloucestershire GL54 5LJ",
    "addr:housenumber":"11",
    "addr:postcode":"gl54 5lj",
    "addr:street":"High Street",
    "iso:country":"GB",
    "sg:address":"11 High Street, Winchcombe",
    "sg:city":"Cheltenham",
    "sg:classifiers":[
        {
            "category":"Shopping",
            "subcategory":"Pharmacy",
            "type":"Retail Goods"
        }
    ],
    "sg:phone":"+44 1242 602305",
    "sg:postcode":"GL54 5LJ",
    "sg:province":"Gloucestershire",
    "sg:tags":[
        "pharmacist",
        "chemist"
    ],
    "wof:name":"Lloyds Pharmacy",
    "wof:placetype":"venue"
},
  "geometry": {"coordinates":[-1.963978,51.953468],"type":"Point"}
}