{
  "type": "Feature",
  "properties": {
    "iso:country":"GB",
    "sg:address":"Lamplight, Casterton Lane, Tinwell",
    "sg:city":"Stamford",
    "sg:classifiers":[
        {
            "category":"Communications",
            "type":"Services"
        }
    ],
    "sg:postcode":"PE9 3UQ",
    "sg:province":"Cambridgeshire",
    "sg:tags":[
        "system",
        "music",
        "public",
        "address"
    ],
    "wof:name":"Pauley Bob Public Address & Disco Equipment Hire",
    "wof:placetype":"venue"
},
  "geometry": {"coordinates":[-0.5173839927,52.6460952759],"type":"Point"}
}