{
  "type": "Feature",
  "properties": {
    "addr:full":"32 Manor Rd Taunton Somerset TA1 5BD",
    "addr:housenumber":"32",
    "addr:postcode":"ta1 5bd",
    "addr:street":"Manor Rd",
    "iso:country":"GB",
    "sg:address":"32 Manor Rd",
    "sg:city":"Taunton",
    "sg:classifiers":[
        {
            "category":"Building & Trades",
            "subcategory":"Construction",
            "type":"Services"
        }
    ],
    "sg:phone":"+44 1823 253111",
    "sg:postcode":"TA1 5BD",
    "sg:province":"Somerset",
    "sg:tags":[
        "builder"
    ],
    "sg:website":"http://www.netline.co.uk",
    "wof:name":"Chartwell Building Contractors",
    "wof:placetype":"venue"
},
  "geometry": {"coordinates":[-3.1151120663,51.0136451721],"type":"Point"}
}