{
  "type": "Feature",
  "properties": {
    "addr:full":"Gwerneithig, Twyn-y-sherriff Usk Monmouthshire NP15 2HT",
    "addr:postcode":"np15 2ht",
    "iso:country":"GB",
    "sg:address":"Gwerneithig, Twyn-y-sherriff",
    "sg:city":"Usk",
    "sg:classifiers":[
        {
            "category":"Farming",
            "subcategory":"Livestock Farm",
            "type":"Manufacturing & Wholesale Goods"
        }
    ],
    "sg:phone":"+44 1291 690763",
    "sg:postcode":"NP15 2HT",
    "sg:province":"Monmouthshire",
    "sg:tags":[
        "others"
    ],
    "wof:name":"J Cullimore",
    "wof:placetype":"venue"
},
  "geometry": {"coordinates":[-2.902848959,51.7037353516],"type":"Point"}
}