{
  "type": "Feature",
  "properties": {
    "addr:full":"311 Littleton Road Salford Greater Manchester M7 3TA",
    "addr:housenumber":"311",
    "addr:postcode":"m7 3ta",
    "addr:street":"Littleton Road",
    "iso:country":"GB",
    "sg:address":"311 Littleton Road",
    "sg:city":"Salford",
    "sg:classifiers":[
        {
            "category":"Health Services",
            "subcategory":"Dentist",
            "type":"Services"
        }
    ],
    "sg:phone":"+44 161 708 9644",
    "sg:postcode":"M7 3TA",
    "sg:province":"Greater Manchester",
    "wof:name":"COLIN MITCHELL",
    "wof:placetype":"venue"
},
  "geometry": {"coordinates":[-2.280108,53.504097],"type":"Point"}
}