{
  "type": "Feature",
  "properties": {
    "iso:country":"GB",
    "sg:address":"Dogmore Lane, Rushton",
    "sg:city":"Tarporley",
    "sg:classifiers":[
        {
            "category":"Autos & Motor Vehicles",
            "subcategory":"Automobile Sales",
            "type":"Retail Goods"
        }
    ],
    "sg:phone":"+44 1829 760315",
    "sg:postcode":"CW6 9BB",
    "sg:province":"Cheshire",
    "sg:tags":[
        "car",
        "commercial"
    ],
    "wof:name":"David E Starkey",
    "wof:placetype":"venue"
},
  "geometry": {"coordinates":[-2.6245601177,53.1709098816],"type":"Point"}
}