{
  "type": "Feature",
  "properties": {
    "addr:full":"Unit 11 Westland Ct Leeds West Yorkshire LS11 5ST",
    "addr:housenumber":"unit 11",
    "addr:postcode":"ls11 5st",
    "addr:street":"Westland Ct",
    "iso:country":"GB",
    "sg:address":"Unit 11 Westland Ct",
    "sg:city":"Leeds",
    "sg:classifiers":[
        {
            "category":"Manufacturing",
            "subcategory":"Metals",
            "type":"Manufacturing & Wholesale Goods"
        }
    ],
    "sg:phone":"+44 113 277 6787",
    "sg:postcode":"LS11 5ST",
    "sg:province":"West Yorkshire",
    "sg:tags":[
        "work",
        "sheet"
    ],
    "wof:name":"Excel Fabrication Services",
    "wof:placetype":"venue"
},
  "geometry": {"coordinates":[-1.550754,53.764977],"type":"Point"}
}