{
  "type": "Feature",
  "properties": {
    "addr:full":"6 Kinnaird Clo Bromley Kent BR1 4HJ",
    "addr:housenumber":"6",
    "addr:postcode":"br1 4hj",
    "addr:street":"Kinnaird Clo",
    "iso:country":"GB",
    "sg:address":"6 Kinnaird Clo",
    "sg:city":"Bromley",
    "sg:classifiers":[
        {
            "category":"Building & Trades",
            "subcategory":"Construction",
            "type":"Services"
        }
    ],
    "sg:phone":"+44 20 8249 0512",
    "sg:postcode":"BR1 4HJ",
    "sg:province":"Kent",
    "sg:tags":[
        "glass",
        "replacement"
    ],
    "wof:name":"B & B Glaziers",
    "wof:placetype":"venue"
},
  "geometry": {"coordinates":[0.008991,51.417286],"type":"Point"}
}