{
  "type": "Feature",
  "properties": {
    "addr:full":"Middle Street, Potterhanworth Lincoln Lincolnshire LN4 2DR",
    "addr:postcode":"ln4 2dr",
    "addr:street":"Middle Street",
    "iso:country":"GB",
    "sg:address":"Middle Street, Potterhanworth",
    "sg:city":"Lincoln",
    "sg:classifiers":[
        {
            "category":"Government",
            "subcategory":"Post Office",
            "type":"Public Place"
        }
    ],
    "sg:postcode":"LN4 2DR",
    "sg:province":"Lincolnshire",
    "wof:name":"Potterhanworth Post Office",
    "wof:placetype":"venue"
},
  "geometry": {"coordinates":[-0.4230909944,53.1835212708],"type":"Point"}
}