{
  "type": "Feature",
  "properties": {
    "addr:full":"15 Market Place, Chapel En Le Frith High Peak Cheshire SK23 0EN",
    "addr:housenumber":"15",
    "addr:postcode":"sk23 0en",
    "addr:street":"Market Place Chapel",
    "iso:country":"GB",
    "sg:address":"15 Market Place, Chapel En Le Frith",
    "sg:city":"High Peak",
    "sg:classifiers":[
        {
            "category":"Personal",
            "subcategory":"Beauty Salon",
            "type":"Services"
        }
    ],
    "sg:phone":"+44 1298 812174",
    "sg:postcode":"SK23 0EN",
    "sg:province":"Cheshire",
    "sg:tags":[
        "unisex",
        "hairdresser"
    ],
    "wof:name":"Cobbles",
    "wof:placetype":"venue"
},
  "geometry": {"coordinates":[-1.9156149626,53.3236541748],"type":"Point"}
}