{
  "type": "Feature",
  "properties": {
    "iso:country":"GB",
    "sg:address":"40 Bowling Green Lane",
    "sg:city":"London",
    "sg:classifiers":[
        {
            "category":"Freight",
            "type":"Transportation"
        }
    ],
    "sg:phone":"+44 20 7837 3759",
    "sg:postcode":"EC1R 0NE",
    "sg:province":"Greater London",
    "sg:tags":[
        "shipping"
    ],
    "wof:name":"Harwin Shipping Agency Ltd.",
    "wof:placetype":"venue"
},
  "geometry": {"coordinates":[-0.107356,51.524761],"type":"Point"}
}