{
  "type": "Feature",
  "properties": {
    "addr:full":"167 Barkby Road, Queniborough Leicester Leicestershire LE7 3FE",
    "addr:housenumber":"167",
    "addr:postcode":"le7 3fe",
    "addr:street":"Barkby Road",
    "iso:country":"GB",
    "sg:address":"167 Barkby Road, Queniborough",
    "sg:city":"Leicester",
    "sg:classifiers":[
        {
            "category":"Shopping",
            "subcategory":"Tobacco",
            "type":"Retail Goods"
        }
    ],
    "sg:phone":"+44 116 260 6929",
    "sg:postcode":"LE7 3FE",
    "sg:province":"Leicestershire",
    "sg:tags":[
        "confectioner",
        "tobacconist"
    ],
    "wof:name":"Ramon Allured",
    "wof:placetype":"venue"
},
  "geometry": {"coordinates":[-1.0544329882,52.6970367432],"type":"Point"}
}