{
  "type": "Feature",
  "properties": {
    "addr:full":"High Street, Hogsthorpe Skegness Lincolnshire PE24 5PP",
    "addr:postcode":"pe24 5pp",
    "addr:street":"High Street",
    "iso:country":"GB",
    "sg:address":"High Street, Hogsthorpe",
    "sg:city":"Skegness",
    "sg:classifiers":[
        {
            "category":"Bars & Pubs",
            "type":"Food & Drink"
        },
        {
            "category":"Community Center",
            "subcategory":"Social",
            "type":"Public Place"
        }
    ],
    "sg:phone":"+44 1754 872217",
    "sg:postcode":"PE24 5PP",
    "sg:province":"Lincolnshire",
    "sg:tags":[
        "pubs",
        "house",
        "inn",
        "activity"
    ],
    "wof:name":"Saracens Head",
    "wof:placetype":"venue"
},
  "geometry": {"coordinates":[0.243945,53.161991],"type":"Point"}
}