{
  "type": "Feature",
  "properties": {
    "addr:full":"Brae Of Gadgirth, Sundrum Ayr East Ayrshire KA6 5LB",
    "addr:postcode":"ka6 5lb",
    "addr:street":"Sundrum;East",
    "iso:country":"GB",
    "sg:address":"Brae Of Gadgirth, Sundrum",
    "sg:city":"Ayr",
    "sg:classifiers":[
        {
            "category":"Transit Center",
            "subcategory":"Passenger",
            "type":"Transportation"
        },
        {
            "category":"Retail",
            "subcategory":"Pet Boarding",
            "type":"Services"
        }
    ],
    "sg:phone":"+44 1292 591247",
    "sg:postcode":"KA6 5LB",
    "sg:province":"East Ayrshire",
    "sg:tags":[
        "kennel",
        "catteries"
    ],
    "wof:name":"The Country Kennels & Cattery",
    "wof:placetype":"venue"
},
  "geometry": {"coordinates":[-4.5267138481,55.4525299072],"type":"Point"}
}