{
  "type": "Feature",
  "properties": {
    "addr:full":"Unit 4, 1 Wood Street Calne Wiltshire SN11 0BZ",
    "addr:housenumber":"unit;1",
    "addr:postcode":"sn11 0bz",
    "addr:street":"Wood Street",
    "iso:country":"GB",
    "sg:address":"Unit 4, 1 Wood Street",
    "sg:city":"Calne",
    "sg:classifiers":[
        {
            "category":"Restaurant",
            "type":"Food & Drink"
        }
    ],
    "sg:phone":"+44 1249 814124",
    "sg:postcode":"SN11 0BZ",
    "sg:province":"Wiltshire",
    "sg:tags":[
        "indian"
    ],
    "wof:name":"Joy Balti House",
    "wof:placetype":"venue"
},
  "geometry": {"coordinates":[-2.0049331188,51.4318656921],"type":"Point"}
}