{
  "type": "Feature",
  "properties": {
    "addr:full":"145 Sandy Lane South Wallington Surrey SM6 9NP",
    "addr:housenumber":"145",
    "addr:postcode":"sm6 9np",
    "addr:street":"Sandy Lane South",
    "iso:country":"GB",
    "sg:address":"145 Sandy Lane South",
    "sg:city":"Wallington",
    "sg:classifiers":[
        {
            "category":"Travel",
            "subcategory":"Travel Agent",
            "type":"Entertainment"
        }
    ],
    "sg:phone":"+44 20 8669 8607",
    "sg:postcode":"SM6 9NP",
    "sg:province":"Surrey",
    "wof:name":"Flight Centre",
    "wof:placetype":"venue"
},
  "geometry": {"coordinates":[-0.1456689984,51.3486709595],"type":"Point"}
}