{
  "type": "Feature",
  "properties": {
    "addr:full":"38 Kenpas Highway Coventry Warwickshire CV3 6BP",
    "addr:housenumber":"38",
    "addr:postcode":"cv3 6bp",
    "addr:street":"Kenpas Highway",
    "iso:country":"GB",
    "sg:address":"38 Kenpas Highway",
    "sg:city":"Coventry",
    "sg:classifiers":[
        {
            "category":"Shopping",
            "subcategory":"News",
            "type":"Retail Goods"
        }
    ],
    "sg:phone":"+44 24 7641 8833",
    "sg:postcode":"CV3 6BP",
    "sg:province":"Warwickshire",
    "sg:tags":[
        "newsagent"
    ],
    "wof:name":"Morgam News Ltd.",
    "wof:placetype":"venue"
},
  "geometry": {"coordinates":[-1.53194,52.384972],"type":"Point"}
}