{
  "type": "Feature",
  "properties": {
    "iso:country":"GB",
    "sg:address":"121-123 Broughton Road",
    "sg:city":"Edinburgh",
    "sg:classifiers":[
        {
            "category":"Shopping",
            "subcategory":"Department Store",
            "type":"Retail Goods"
        }
    ],
    "sg:phone":"+44 131 556 6197",
    "sg:postcode":"EH7 4JF",
    "sg:province":"City of Edinburgh",
    "wof:name":"You & Us Convenience Store",
    "wof:placetype":"venue"
},
  "geometry": {"coordinates":[-3.191688,55.964874],"type":"Point"}
}