{
  "type": "Feature",
  "properties": {
    "iso:country":"GB",
    "sg:address":"Park Gate, Castle Hedingham",
    "sg:city":"Halstead",
    "sg:classifiers":[
        {
            "category":"Farming",
            "subcategory":"Livestock Farm",
            "type":"Manufacturing & Wholesale Goods"
        }
    ],
    "sg:phone":"+44 1787 460580",
    "sg:postcode":"CO9 3AG",
    "sg:province":"Essex",
    "sg:tags":[
        "others"
    ],
    "wof:name":"J M Ruffel",
    "wof:placetype":"venue"
},
  "geometry": {"coordinates":[0.589204,51.977261],"type":"Point"}
}