{
  "type": "Feature",
  "properties": {
    "addr:full":"14 Whitehall Rd, Drighlington Bradford West Yorkshire BD11 1NE",
    "addr:housenumber":"14",
    "addr:postcode":"bd11 1ne",
    "addr:street":"Whitehall Rd",
    "iso:country":"GB",
    "sg:address":"14 Whitehall Rd, Drighlington",
    "sg:city":"Bradford",
    "sg:classifiers":[
        {
            "category":"Autos & Motor Vehicles",
            "subcategory":"Automobile Sales",
            "type":"Retail Goods"
        }
    ],
    "sg:phone":"+44 113 287 9326",
    "sg:postcode":"BD11 1NE",
    "sg:province":"West Yorkshire",
    "sg:tags":[
        "commercial"
    ],
    "wof:name":"Team Cars",
    "wof:placetype":"venue"
},
  "geometry": {"coordinates":[-1.6459729671,53.765247345],"type":"Point"}
}