{
  "type": "Feature",
  "properties": {
    "addr:full":"8 Market Avenue Plymouth Devon PL1 1PQ",
    "addr:housenumber":"8",
    "addr:postcode":"pl1 1pq",
    "addr:street":"Market Avenue",
    "iso:country":"GB",
    "sg:address":"8 Market Avenue",
    "sg:city":"Plymouth",
    "sg:classifiers":[
        {
            "category":"Food & Beverages",
            "subcategory":"Meat & Fish",
            "type":"Retail Goods"
        }
    ],
    "sg:phone":"+44 1752 664087",
    "sg:postcode":"PL1 1PQ",
    "sg:province":"Devon",
    "sg:tags":[
        "butcher"
    ],
    "wof:name":"Martins Butchers",
    "wof:placetype":"venue"
},
  "geometry": {"coordinates":[-4.1470680237,50.3714942932],"type":"Point"}
}