{
  "type": "Feature",
  "properties": {
    "addr:full":"Moat House Works Alcester Warwickshire B49 5QF",
    "addr:postcode":"b49 5qf",
    "addr:street":"Moat",
    "iso:country":"GB",
    "sg:address":"Moat House Works",
    "sg:city":"Alcester",
    "sg:classifiers":[
        {
            "category":"Professional",
            "subcategory":"Printing & Photocopies",
            "type":"Services"
        }
    ],
    "sg:phone":"+44 1789 762519",
    "sg:postcode":"B49 5QF",
    "sg:province":"Warwickshire",
    "sg:tags":[
        "printer"
    ],
    "wof:name":"Mostyn Printers & Publishers Ltd.",
    "wof:placetype":"venue"
},
  "geometry": {"coordinates":[-1.8836590052,52.2178993225],"type":"Point"}
}