{
  "type": "Feature",
  "properties": {
    "addr:full":"Fairoaks, The Murch Dinas Powys The Vale of Glamorgan CF64 4QU",
    "addr:postcode":"cf64 4qu",
    "addr:street":"Vale",
    "iso:country":"GB",
    "sg:address":"Fairoaks, The Murch",
    "sg:city":"Dinas Powys",
    "sg:classifiers":[
        {
            "category":"Education",
            "subcategory":"Library",
            "type":"Public Place"
        },
        {
            "category":"Government",
            "subcategory":"Office",
            "type":"Public Place"
        }
    ],
    "sg:phone":"+44 29 2051 2556",
    "sg:postcode":"CF64 4QU",
    "sg:province":"The Vale of Glamorgan",
    "sg:tags":[
        "book",
        "local"
    ],
    "wof:name":"Dinas Powys Library",
    "wof:placetype":"venue"
},
  "geometry": {"coordinates":[-3.215659,51.433521],"type":"Point"}
}