{
  "type": "Feature",
  "properties": {
    "addr:full":"Housing Neighbourhood Office, 1 Ringwood Rd Bradford West Yorkshire BD5 9LB",
    "addr:housenumber":"1",
    "addr:postcode":"bd5 9lb",
    "addr:street":"Ringwood Rd",
    "iso:country":"GB",
    "sg:address":"Housing Neighbourhood Office, 1 Ringwood Rd",
    "sg:city":"Bradford",
    "sg:classifiers":[
        {
            "category":"Government",
            "subcategory":"Office",
            "type":"Public Place"
        }
    ],
    "sg:phone":"+44 1274 502336",
    "sg:postcode":"BD5 9LB",
    "sg:province":"West Yorkshire",
    "sg:tags":[
        "local"
    ],
    "wof:name":"Bradford Metropolitan District Council",
    "wof:placetype":"venue"
},
  "geometry": {"coordinates":[-1.77077,53.780529],"type":"Point"}
}