{
  "type": "Feature",
  "properties": {
    "iso:country":"GB",
    "sg:address":"45 High Street",
    "sg:city":"Oakham",
    "sg:classifiers":[
        {
            "category":"Real Estate",
            "subcategory":"Surveying",
            "type":"Services"
        }
    ],
    "sg:phone":"+44 1572 757777",
    "sg:postcode":"LE15 6AJ",
    "sg:province":"Leicestershire",
    "sg:tags":[
        "surveyor",
        "valuer"
    ],
    "wof:name":"Ruddle Merz Ltd",
    "wof:placetype":"venue"
},
  "geometry": {"coordinates":[-0.731028,52.670174],"type":"Point"}
}