{
  "type": "Feature",
  "properties": {
    "addr:full":"Unit 63 Murdock Road, Manton Industrial Estate Bedford Bedfordshire MK41 7PL",
    "addr:housenumber":"unit 63",
    "addr:postcode":"mk41 7pl",
    "addr:street":"Murdock Road;Industrial Estate",
    "iso:country":"GB",
    "sg:address":"Unit 63 Murdock Road, Manton Industrial Estate",
    "sg:city":"Bedford",
    "sg:classifiers":[
        {
            "category":"Professional",
            "subcategory":"Business Services",
            "type":"Services"
        }
    ],
    "sg:phone":"+44 1234 273388",
    "sg:postcode":"MK41 7PL",
    "sg:province":"Bedfordshire",
    "sg:tags":[
        "import",
        "export",
        "agent"
    ],
    "wof:name":"Rejel Automotive",
    "wof:placetype":"venue"
},
  "geometry": {"coordinates":[-0.473625,52.154575],"type":"Point"}
}