{
  "type": "Feature",
  "properties": {
    "addr:full":"Civic Centre, Paris Street Exeter Devon EX1 1JN",
    "addr:postcode":"ex1 1jn",
    "addr:street":"Paris Street",
    "iso:country":"GB",
    "sg:address":"Civic Centre, Paris Street",
    "sg:city":"Exeter",
    "sg:classifiers":[
        {
            "category":"Government",
            "subcategory":"Office",
            "type":"Public Place"
        }
    ],
    "sg:phone":"+44 1392 277888",
    "sg:postcode":"EX1 1JN",
    "sg:province":"Devon",
    "sg:tags":[
        "local"
    ],
    "sg:website":"http://www.exeter.gov.uk",
    "wof:name":"Exeter City Council",
    "wof:placetype":"venue"
},
  "geometry": {"coordinates":[-3.5316441059,50.7199058533],"type":"Point"}
}