{
  "type": "Feature",
  "properties": {
    "addr:full":"Acton Lane Sudbury Essex CO10 1QN",
    "addr:postcode":"co10 1qn",
    "addr:street":"Acton Lane",
    "iso:country":"GB",
    "sg:address":"Acton Lane",
    "sg:city":"Sudbury",
    "sg:classifiers":[
        {
            "category":"Health Services",
            "subcategory":"Nursing And Care Facility",
            "type":"Services"
        },
        {
            "category":"Social Services",
            "subcategory":"Retirement Home",
            "type":"Services"
        },
        {
            "category":"Government",
            "subcategory":"Office",
            "type":"Public Place"
        }
    ],
    "sg:phone":"+44 1787 373542",
    "sg:postcode":"CO10 1QN",
    "sg:province":"Essex",
    "sg:tags":[
        "residential",
        "local"
    ],
    "wof:name":"Hazell Court",
    "wof:placetype":"venue"
},
  "geometry": {"coordinates":[0.736635983,52.0448036194],"type":"Point"}
}