{
  "type": "Feature",
  "properties": {
    "addr:full":"Haverfordwest Castle, Castle Street Haverfordwest Pembrokeshire SA61 2EF",
    "addr:postcode":"sa61 2ef",
    "addr:street":"Castle Street",
    "iso:country":"GB",
    "sg:address":"Haverfordwest Castle, Castle Street",
    "sg:city":"Haverfordwest",
    "sg:classifiers":[
        {
            "category":"Landmark",
            "subcategory":"Tourist Attraction",
            "type":"Public Place"
        }
    ],
    "sg:phone":"+44 1437 763087",
    "sg:postcode":"SA61 2EF",
    "sg:province":"Pembrokeshire",
    "sg:tags":[
        "interest"
    ],
    "wof:name":"Haverfordwest Town Museum",
    "wof:placetype":"venue"
},
  "geometry": {"coordinates":[-4.97735,51.798763],"type":"Point"}
}