{
  "type": "Feature",
  "properties": {
    "iso:country":"GB",
    "sg:address":"91 Legrams Lane",
    "sg:city":"Bradford",
    "sg:classifiers":[
        {
            "category":"Wholesale",
            "subcategory":"Non-durable Goods",
            "type":"Manufacturing & Wholesale Goods"
        }
    ],
    "sg:phone":"+44 1274 740555",
    "sg:postcode":"BD7 2AA",
    "sg:province":"West Yorkshire",
    "sg:tags":[
        "carry",
        "cash"
    ],
    "wof:name":"T B (Halifax) Ltd.",
    "wof:placetype":"venue"
},
  "geometry": {"coordinates":[-1.7768980265,53.7916221619],"type":"Point"}
}