{
  "type": "Feature",
  "properties": {
    "iso:country":"GB",
    "sg:address":"107 High Street, Horsell",
    "sg:city":"Woking",
    "sg:classifiers":[
        {
            "category":"Food & Beverages",
            "subcategory":"Meat & Fish",
            "type":"Retail Goods"
        }
    ],
    "sg:phone":"+44 1483 764722",
    "sg:postcode":"GU21 4SY",
    "sg:province":"Surrey",
    "sg:tags":[
        "butcher"
    ],
    "wof:name":"JENNERS BUTCHERS",
    "wof:placetype":"venue"
},
  "geometry": {"coordinates":[-0.574035,51.32394],"type":"Point"}
}