{
  "type": "Feature",
  "properties": {
    "iso:country":"GB",
    "sg:address":"459 Maidstone Road",
    "sg:city":"Gillingham",
    "sg:classifiers":[
        {
            "category":"Building & Trades",
            "subcategory":"Construction",
            "type":"Services"
        }
    ],
    "sg:phone":"+44 1634 360235",
    "sg:postcode":"ME8 0NN",
    "sg:province":"Kent",
    "sg:tags":[
        "roofing",
        "guttering",
        "contracting"
    ],
    "wof:name":"May's Roofing",
    "wof:placetype":"venue"
},
  "geometry": {"coordinates":[0.588949,51.347561],"type":"Point"}
}