{
  "type": "Feature",
  "properties": {
    "addr:full":"George Street Chorley Lancashire PR7 2BE",
    "addr:postcode":"pr7 2be",
    "addr:street":"George Street",
    "iso:country":"GB",
    "sg:address":"George Street",
    "sg:city":"Chorley",
    "sg:classifiers":[
        {
            "category":"Professional",
            "subcategory":"Engineering",
            "type":"Services"
        }
    ],
    "sg:phone":"+44 1257 274723",
    "sg:postcode":"PR7 2BE",
    "sg:province":"Lancashire",
    "sg:tags":[
        "engineer",
        "mechanical"
    ],
    "wof:name":"Alan Gordon Engineering Co. Ltd.",
    "wof:placetype":"venue"
},
  "geometry": {"coordinates":[-2.6309,53.650478],"type":"Point"}
}