{
  "type": "Feature",
  "properties": {
    "iso:country":"GB",
    "sg:address":"Barn Garth",
    "sg:city":"Kendal",
    "sg:classifiers":[
        {
            "category":"Communications",
            "type":"Services"
        }
    ],
    "sg:phone":"+44 15395 68505",
    "sg:postcode":"LA8 8AJ",
    "sg:province":"Cumbria",
    "sg:tags":[
        "data",
        "network"
    ],
    "wof:name":"Axess It",
    "wof:placetype":"venue"
},
  "geometry": {"coordinates":[-2.810659,54.29829],"type":"Point"}
}