{
  "type": "Feature",
  "properties": {
    "iso:country":"GB",
    "sg:address":"121 Osmaston Road",
    "sg:city":"Derby",
    "sg:classifiers":[
        {
            "category":"Health Services",
            "subcategory":"Clinic",
            "type":"Services"
        }
    ],
    "sg:phone":"+44 1332 366717",
    "sg:postcode":"DE1 2GA",
    "sg:province":"Derbyshire",
    "sg:tags":[
        "nh"
    ],
    "wof:name":"Community Nursing Services",
    "wof:placetype":"venue"
},
  "geometry": {"coordinates":[-1.4731940031,52.916179657],"type":"Point"}
}