{
  "type": "Feature",
  "properties": {
    "iso:country":"GB",
    "sg:address":"790 Borough Rd",
    "sg:city":"Birkenhead",
    "sg:classifiers":[
        {
            "category":"Home & Garden",
            "subcategory":"Carpets & Floor Coverings",
            "type":"Retail Goods"
        }
    ],
    "sg:phone":"+44 151 609 0134",
    "sg:postcode":"L42 9JG",
    "sg:province":"Merseyside",
    "sg:tags":[
        "carpets",
        "rug",
        "matting"
    ],
    "wof:name":"Bogan's Carpets",
    "wof:placetype":"venue"
},
  "geometry": {"coordinates":[-3.0326030254,53.3751907349],"type":"Point"}
}