{
  "type": "Feature",
  "properties": {
    "iso:country":"GB",
    "sg:address":"Unit 4, 27 Lisle Avenue",
    "sg:city":"Kidderminster",
    "sg:classifiers":[
        {
            "category":"Home & Garden",
            "subcategory":"Home Furnishings",
            "type":"Retail Goods"
        }
    ],
    "sg:phone":"+44 1562 825033",
    "sg:postcode":"DY11 7DF",
    "sg:province":"Staffordshire",
    "sg:tags":[
        "furnishers",
        "planner",
        "bedroom"
    ],
    "wof:name":"Woodrobes Ltd.",
    "wof:placetype":"venue"
},
  "geometry": {"coordinates":[-2.254965,52.373196],"type":"Point"}
}