{
  "type": "Feature",
  "properties": {
    "addr:full":"Somerset Nuffield Hospital, Staplegrove Elm Taunton Somerset TA2 6AN",
    "addr:postcode":"ta2 6an",
    "addr:street":"Elm",
    "iso:country":"GB",
    "sg:address":"Somerset Nuffield Hospital, Staplegrove Elm",
    "sg:city":"Taunton",
    "sg:classifiers":[
        {
            "category":"Health Services",
            "subcategory":"Hospital",
            "type":"Services"
        }
    ],
    "sg:phone":"+44 1823 661606",
    "sg:postcode":"TA2 6AN",
    "sg:province":"Somerset",
    "wof:name":"Staplegrove Anaesthetic Group",
    "wof:placetype":"venue"
},
  "geometry": {"coordinates":[-3.1269140244,51.0300064087],"type":"Point"}
}