{
  "type": "Feature",
  "properties": {
    "iso:country":"GB",
    "sg:address":"Banamex House, 3 Creed Court, 5 Ludgate Hill",
    "sg:city":"London",
    "sg:classifiers":[
        {
            "category":"Banks & Credit Unions",
            "subcategory":"Bank",
            "type":"Services"
        }
    ],
    "sg:phone":"+44 20 7369 2900",
    "sg:postcode":"EC4M 7AA",
    "sg:province":"Greater London",
    "wof:name":"Banamex Investment Ltd.",
    "wof:placetype":"venue"
},
  "geometry": {"coordinates":[-0.1010200009,51.513710022],"type":"Point"}
}