{
  "type": "Feature",
  "properties": {
    "addr:full":"7 Mill Ho, Lichfield St Tamworth Staffordshire B78 3QB",
    "addr:housenumber":"7",
    "addr:postcode":"b78 3qb",
    "addr:street":"Mill Ho Lichfield St",
    "iso:country":"GB",
    "sg:address":"7 Mill Ho, Lichfield St",
    "sg:city":"Tamworth",
    "sg:classifiers":[
        {
            "category":"Professional",
            "subcategory":"Computer Services",
            "type":"Services"
        }
    ],
    "sg:postcode":"B78 3QB",
    "sg:province":"Staffordshire",
    "sg:tags":[
        "system",
        "software"
    ],
    "wof:name":"Data Exchange Services Ltd",
    "wof:placetype":"venue"
},
  "geometry": {"coordinates":[-1.701779,52.615002],"type":"Point"}
}