{
  "type": "Feature",
  "properties": {
    "iso:country":"GB",
    "sg:address":"Arthington Lane, Pool In Wharfedale",
    "sg:city":"Otley",
    "sg:classifiers":[
        {
            "category":"Education",
            "subcategory":"School",
            "type":"Public Place"
        }
    ],
    "sg:phone":"+44 113 284 3151",
    "sg:postcode":"LS21 1LG",
    "sg:province":"North Yorkshire",
    "sg:tags":[
        "local",
        "authority"
    ],
    "wof:name":"Pool C Of E Primary School",
    "wof:placetype":"venue"
},
  "geometry": {"coordinates":[-1.580389,53.898201],"type":"Point"}
}