{
  "type": "Feature",
  "properties": {
    "iso:country":"GB",
    "sg:address":"26 St Andrews St",
    "sg:city":"Dundee",
    "sg:classifiers":[
        {
            "category":"Professional",
            "subcategory":"Engineering",
            "type":"Services"
        }
    ],
    "sg:phone":"+44 1382 224213",
    "sg:postcode":"DD1 2EZ",
    "sg:province":"Dundee City",
    "sg:tags":[
        "contractor",
        "electrical",
        "engineer"
    ],
    "wof:name":"Lockhart & Maxwell's (Dundee) Ltd",
    "wof:placetype":"venue"
},
  "geometry": {"coordinates":[-2.966816,56.463688],"type":"Point"}
}