{
  "type": "Feature",
  "properties": {
    "iso:country":"GB",
    "sg:address":"Lotus Complex, Paignton Road, Stoke Gabriel",
    "sg:city":"Totnes",
    "sg:classifiers":[
        {
            "category":"Professional",
            "subcategory":"Management & Consulting",
            "type":"Services"
        }
    ],
    "sg:phone":"+44 1803 782567",
    "sg:postcode":"TQ9 6SL",
    "sg:province":"Devon",
    "sg:tags":[
        "consultant",
        "business"
    ],
    "wof:name":"In Focus Learning Ltd.",
    "wof:placetype":"venue"
},
  "geometry": {"coordinates":[-3.688093,50.434147],"type":"Point"}
}