{
  "type": "Feature",
  "properties": {
    "addr:full":"Drayton Fields Farm, Braunston Road Daventry Northamptonshire NN11 5NP",
    "addr:postcode":"nn11 5np",
    "addr:street":"Drayton Fields;Braunston Road",
    "iso:country":"GB",
    "sg:address":"Drayton Fields Farm, Braunston Road",
    "sg:city":"Daventry",
    "sg:classifiers":[
        {
            "category":"Farming",
            "subcategory":"Dairy Farm",
            "type":"Manufacturing & Wholesale Goods"
        }
    ],
    "sg:phone":"+44 1327 702729",
    "sg:postcode":"NN11 5NP",
    "sg:province":"Northamptonshire",
    "wof:name":"B & L Whitfield & Son",
    "wof:placetype":"venue"
},
  "geometry": {"coordinates":[-1.1622389555,52.260433197],"type":"Point"}
}