{
  "type": "Feature",
  "properties": {
    "iso:country":"GB",
    "sg:address":"52 The Strand",
    "sg:city":"Stoke-on-trent",
    "sg:classifiers":[
        {
            "category":"Shopping",
            "subcategory":"Comic Books",
            "type":"Retail Goods"
        }
    ],
    "sg:phone":"+44 1782 313505",
    "sg:postcode":"ST3 2JW",
    "sg:province":"Staffordshire",
    "sg:tags":[
        "jeweller"
    ],
    "wof:name":"Wm Williamson Ltd.",
    "wof:placetype":"venue"
},
  "geometry": {"coordinates":[-2.136988,52.98761],"type":"Point"}
}