{
  "type": "Feature",
  "properties": {
    "addr:full":"21 Victoria Square, Clifton Bristol City of Bristol BS8 4ES",
    "addr:housenumber":"21",
    "addr:postcode":"bs8 4es",
    "addr:street":"Victoria Square",
    "iso:country":"GB",
    "sg:address":"21 Victoria Square, Clifton",
    "sg:city":"Bristol",
    "sg:classifiers":[
        {
            "category":"Building & Trades",
            "subcategory":"Construction",
            "type":"Services"
        }
    ],
    "sg:postcode":"BS8 4ES",
    "sg:province":"City of Bristol",
    "sg:tags":[
        "builder"
    ],
    "wof:name":"N H General Builder",
    "wof:placetype":"venue"
},
  "geometry": {"coordinates":[-2.6170780659,51.4549942017],"type":"Point"}
}