{
  "type": "Feature",
  "properties": {
    "iso:country":"GB",
    "sg:address":"Richmond, Brighton Place",
    "sg:city":"Peterculter",
    "sg:classifiers":[
        {
            "category":"Sports & Exercise",
            "subcategory":"Tennis Court",
            "type":"Entertainment"
        }
    ],
    "sg:phone":"+44 1224 732568",
    "sg:postcode":"AB14 0UP",
    "sg:province":"Aberdeen City",
    "sg:tags":[
        "breakdown",
        "recovery"
    ],
    "wof:name":"Richmond Garage",
    "wof:placetype":"venue"
},
  "geometry": {"coordinates":[-2.2641038895,57.0961494446],"type":"Point"}
}