{
  "type": "Feature",
  "properties": {
    "addr:full":"Cyntwell Avenue Cardiff Cardiff CF5 5QN",
    "addr:postcode":"cf5 5qn",
    "addr:street":"Avenue Cardiff",
    "iso:country":"GB",
    "sg:address":"Cyntwell Avenue",
    "sg:city":"Cardiff",
    "sg:classifiers":[
        {
            "category":"Education",
            "subcategory":"School",
            "type":"Public Place"
        }
    ],
    "sg:phone":"+44 29 2059 1585",
    "sg:postcode":"CF5 5QN",
    "sg:province":"Cardiff",
    "sg:tags":[
        "local",
        "authority"
    ],
    "wof:name":"CWRT Yr Ala County Junior School",
    "wof:placetype":"venue"
},
  "geometry": {"coordinates":[-3.2570290565,51.4715881348],"type":"Point"}
}