{
  "type": "Feature",
  "properties": {
    "addr:full":"Peel Ho, 3 Barttelot Rd Horsham West Sussex RH12 1DE",
    "addr:housenumber":"3",
    "addr:postcode":"rh12 1de",
    "addr:street":"Peel;Barttelot Rd",
    "iso:country":"GB",
    "sg:address":"Peel Ho, 3 Barttelot Rd",
    "sg:city":"Horsham",
    "sg:classifiers":[
        {
            "category":"Professional",
            "subcategory":"Business Services",
            "type":"Services"
        }
    ],
    "sg:phone":"+44 1403 266366",
    "sg:postcode":"RH12 1DE",
    "sg:province":"West Sussex",
    "sg:tags":[
        "registrar"
    ],
    "wof:name":"Documents Direct Ltd",
    "wof:placetype":"venue"
},
  "geometry": {"coordinates":[-0.3291069865,51.0651817322],"type":"Point"}
}