{
  "type": "Feature",
  "properties": {
    "iso:country":"GB",
    "sg:address":"Prentice Road",
    "sg:city":"Stowmarket",
    "sg:classifiers":[
        {
            "category":"Manufacturing",
            "subcategory":"Tools & Machinery",
            "type":"Manufacturing & Wholesale Goods"
        },
        {
            "category":"Home & Garden",
            "subcategory":"Hardware",
            "type":"Retail Goods"
        }
    ],
    "sg:phone":"+44 1449 771443",
    "sg:postcode":"IP14 1RD",
    "sg:province":"Suffolk",
    "sg:tags":[
        "machine",
        "equipment",
        "welding",
        "manufacturer"
    ],
    "wof:name":"Sifbronze Ltd.",
    "wof:placetype":"venue"
},
  "geometry": {"coordinates":[0.999823,52.188694],"type":"Point"}
}