{
  "type": "Feature",
  "properties": {
    "iso:country":"GB",
    "sg:address":"41 Wolverwood Lane",
    "sg:city":"Plymouth",
    "sg:classifiers":[
        {
            "category":"Building & Trades",
            "subcategory":"Construction",
            "type":"Services"
        }
    ],
    "sg:phone":"+44 1752 337695",
    "sg:postcode":"PL7 1PD",
    "sg:province":"Devon",
    "sg:tags":[
        "joiner",
        "carpenter"
    ],
    "wof:name":"R Brewer",
    "wof:placetype":"venue"
},
  "geometry": {"coordinates":[-4.041552,50.379414],"type":"Point"}
}