{
  "type": "Feature",
  "properties": {
    "iso:country":"GB",
    "sg:address":"Eccleston Paddocks, Paddock Road",
    "sg:city":"Chester",
    "sg:classifiers":[
        {
            "category":"Real Estate",
            "subcategory":"Developer",
            "type":"Services"
        }
    ],
    "sg:phone":"+44 1244 675311",
    "sg:postcode":"CH4 9HP",
    "sg:province":"Cheshire",
    "sg:tags":[
        "property"
    ],
    "wof:name":"Linenhall Chester Ltd.",
    "wof:placetype":"venue"
},
  "geometry": {"coordinates":[-2.907134,53.162411],"type":"Point"}
}