{
  "type": "Feature",
  "properties": {
    "addr:full":"6 Market Walk Saffron Walden Cambridgeshire CB10 1JZ",
    "addr:housenumber":"6",
    "addr:postcode":"cb10 1jz",
    "addr:street":"Market Walk",
    "iso:country":"GB",
    "sg:address":"6 Market Walk",
    "sg:city":"Saffron Walden",
    "sg:classifiers":[
        {
            "category":"Shopping",
            "subcategory":"Thrift Store",
            "type":"Retail Goods"
        }
    ],
    "sg:phone":"+44 1799 526768",
    "sg:postcode":"CB10 1JZ",
    "sg:province":"Cambridgeshire",
    "sg:tags":[
        "shop",
        "charity"
    ],
    "wof:name":"Home Farm Trust",
    "wof:placetype":"venue"
},
  "geometry": {"coordinates":[0.241147995,52.0231208801],"type":"Point"}
}