{
  "type": "Feature",
  "properties": {
    "iso:country":"GB",
    "sg:address":"21-23 Sagar St",
    "sg:city":"Castleford",
    "sg:classifiers":[
        {
            "category":"Sports & Exercise",
            "subcategory":"Gym",
            "type":"Entertainment"
        }
    ],
    "sg:postcode":"WF10 1AG",
    "sg:province":"West Yorkshire",
    "sg:tags":[
        "fitness",
        "health",
        "centre"
    ],
    "wof:name":"Proud,Edith Anne,",
    "wof:placetype":"venue"
},
  "geometry": {"coordinates":[-1.351223,53.726608],"type":"Point"}
}