{
  "type": "Feature",
  "properties": {
    "addr:full":"Bold Gate Lodge Camborne Cornwall TR14 0NQ",
    "addr:postcode":"tr14 0nq",
    "addr:street":"Bold Gate",
    "iso:country":"GB",
    "sg:address":"Bold Gate Lodge",
    "sg:city":"Camborne",
    "sg:classifiers":[
        {
            "category":"Professional",
            "subcategory":"Computer Services",
            "type":"Services"
        }
    ],
    "sg:postcode":"TR14 0NQ",
    "sg:province":"Cornwall",
    "sg:tags":[
        "system",
        "software"
    ],
    "wof:name":"Ball Gate Systems",
    "wof:placetype":"venue"
},
  "geometry": {"coordinates":[-5.3279099464,50.1703300476],"type":"Point"}
}