{
  "type": "Feature",
  "properties": {
    "addr:full":"1 Tower Hill Terrace London Greater London EC3N 4EE",
    "addr:housenumber":"1",
    "addr:postcode":"ec3n 4ee",
    "addr:street":"Tower Hill Terrace",
    "iso:country":"GB",
    "sg:address":"1 Tower Hill Terrace",
    "sg:city":"London",
    "sg:classifiers":[
        {
            "category":"Fast Food",
            "type":"Food & Drink"
        }
    ],
    "sg:phone":"+44 20 7481 9805",
    "sg:postcode":"EC3N 4EE",
    "sg:province":"Greater London",
    "sg:tags":[
        "away",
        "take"
    ],
    "wof:name":"K F C",
    "wof:placetype":"venue"
},
  "geometry": {"coordinates":[-0.0788540021,51.5089683533],"type":"Point"}
}