{
  "type": "Feature",
  "properties": {
    "addr:full":"9 Main Rd Tamworth Staffordshire B79 0DP",
    "addr:housenumber":"9",
    "addr:postcode":"b79 0dp",
    "addr:street":"Main Rd",
    "iso:country":"GB",
    "sg:address":"9 Main Rd",
    "sg:city":"Tamworth",
    "sg:classifiers":[
        {
            "category":"Food & Beverages",
            "subcategory":"Supermarket",
            "type":"Retail Goods"
        }
    ],
    "sg:postcode":"B79 0DP",
    "sg:province":"Staffordshire",
    "wof:name":"Boyes,Robert,",
    "wof:placetype":"venue"
},
  "geometry": {"coordinates":[-1.6021000147,52.6570167542],"type":"Point"}
}