{
  "type": "Feature",
  "properties": {
    "iso:country":"GB",
    "sg:address":"2 Ruskin Close, Selsey",
    "sg:city":"Chichester",
    "sg:classifiers":[
        {
            "category":"Banks & Credit Unions",
            "subcategory":"Investment Brokerage",
            "type":"Services"
        },
        {
            "category":"Train Station",
            "subcategory":"Light Rail",
            "type":"Transportation"
        }
    ],
    "sg:phone":"+44 1243 604048",
    "sg:postcode":"PO20 0TE",
    "sg:province":"West Sussex",
    "sg:tags":[
        "personnel",
        "firework",
        "display",
        "stockist"
    ],
    "wof:name":"Selstar Fireworks",
    "wof:placetype":"venue"
},
  "geometry": {"coordinates":[-0.777004,50.730991],"type":"Point"}
}