{
  "type": "Feature",
  "properties": {
    "iso:country":"GB",
    "sg:address":"98 Maldon Road",
    "sg:city":"Chelmsford",
    "sg:classifiers":[
        {
            "category":"Professional",
            "subcategory":"Business Services",
            "type":"Services"
        }
    ],
    "sg:phone":"+44 1245 477406",
    "sg:postcode":"CM2 7DH",
    "sg:province":"Essex",
    "sg:tags":[
        "import",
        "export",
        "agent"
    ],
    "wof:name":"Chelmer Imports",
    "wof:placetype":"venue"
},
  "geometry": {"coordinates":[0.5098119974,51.7198486328],"type":"Point"}
}