{
  "type": "Feature",
  "properties": {
    "iso:country":"GB",
    "sg:address":"Countrywide House, Knights Way, Battlefield Enterprise Park",
    "sg:city":"Shrewsbury",
    "sg:classifiers":[
        {
            "category":"Utilities",
            "subcategory":"Refuse",
            "type":"Services"
        }
    ],
    "sg:phone":"+44 845 230 5566",
    "sg:postcode":"SY1 3AB",
    "sg:province":"Shropshire",
    "sg:tags":[
        "disposal",
        "waste"
    ],
    "wof:name":"Countrywide Waste Management Ltd.",
    "wof:placetype":"venue"
},
  "geometry": {"coordinates":[-2.744713,52.744888],"type":"Point"}
}