{
  "type": "Feature",
  "properties": {
    "addr:full":"100 Carlisle Rd Airdrie North Lanarkshire ML6 8RA",
    "addr:housenumber":"100",
    "addr:postcode":"ml6 8ra",
    "addr:street":"Carlisle Rd",
    "iso:country":"GB",
    "sg:address":"100 Carlisle Rd",
    "sg:city":"Airdrie",
    "sg:classifiers":[
        {
            "category":"Building & Trades",
            "subcategory":"Construction",
            "type":"Services"
        }
    ],
    "sg:phone":"+44 1236 752812",
    "sg:postcode":"ML6 8RA",
    "sg:province":"North Lanarkshire",
    "sg:tags":[
        "roofing"
    ],
    "wof:name":"A C B Construction",
    "wof:placetype":"venue"
},
  "geometry": {"coordinates":[-3.964140892,55.8603973389],"type":"Point"}
}