{
  "type": "Feature",
  "properties": {
    "addr:full":"Doncaster Rd Worksop Nottinghamshire S81 9RJ",
    "addr:postcode":"s81 9rj",
    "addr:street":"Doncaster Rd",
    "iso:country":"GB",
    "sg:address":"Doncaster Rd",
    "sg:city":"Worksop",
    "sg:classifiers":[
        {
            "category":"Organizations",
            "subcategory":"Membership Organization",
            "type":"Services"
        }
    ],
    "sg:phone":"+44 1909 730343",
    "sg:postcode":"S81 9RJ",
    "sg:province":"Nottinghamshire",
    "sg:tags":[
        "club"
    ],
    "wof:name":"Smokeys Country Music Club",
    "wof:placetype":"venue"
},
  "geometry": {"coordinates":[-1.1130189896,53.357673645],"type":"Point"}
}