{
  "type": "Feature",
  "properties": {
    "iso:country":"GB",
    "sg:address":"25a Maryland Square",
    "sg:city":"London",
    "sg:classifiers":[
        {
            "category":"Professional",
            "subcategory":"Management & Consulting",
            "type":"Services"
        }
    ],
    "sg:postcode":"E15 1HF",
    "sg:province":"Greater London",
    "sg:tags":[
        "consultant",
        "business"
    ],
    "wof:name":"Seaward Ltd",
    "wof:placetype":"venue"
},
  "geometry": {"coordinates":[0.00822,51.548119],"type":"Point"}
}