{
  "type": "Feature",
  "properties": {
    "iso:country":"GB",
    "sg:address":"8 Doncaster Road",
    "sg:city":"Scunthorpe",
    "sg:classifiers":[
        {
            "category":"Professional",
            "type":"Services"
        },
        {
            "category":"Real Estate",
            "subcategory":"Real Estate Agent",
            "type":"Services"
        }
    ],
    "sg:phone":"+44 1724 858855",
    "sg:postcode":"DN15 7RB",
    "sg:province":"Lincolnshire",
    "sg:tags":[
        "valuer",
        "auctioneer"
    ],
    "wof:name":"Canter & Francis",
    "wof:placetype":"venue"
},
  "geometry": {"coordinates":[-0.655931,53.591007],"type":"Point"}
}