{
  "type": "Feature",
  "properties": {
    "addr:full":"The Lindens, Heightington Bewdley Shropshire DY12 2XN",
    "addr:postcode":"dy12 2xn",
    "addr:street":"Heightington",
    "iso:country":"GB",
    "sg:address":"The Lindens, Heightington",
    "sg:city":"Bewdley",
    "sg:classifiers":[
        {
            "category":"Professional",
            "subcategory":"Management & Consulting",
            "type":"Services"
        }
    ],
    "sg:phone":"+44 1299 827181",
    "sg:postcode":"DY12 2XN",
    "sg:province":"Shropshire",
    "sg:tags":[
        "marketing",
        "consultant"
    ],
    "wof:name":"Castlegate Marketing Ltd.",
    "wof:placetype":"venue"
},
  "geometry": {"coordinates":[-2.314779,52.376019],"type":"Point"}
}