{
  "type": "Feature",
  "properties": {
    "addr:full":"Fire Station, Lees Rd Oldham Lancashire OL4 1JN",
    "addr:postcode":"ol4 1jn",
    "addr:street":"Lees Rd",
    "iso:country":"GB",
    "sg:address":"Fire Station, Lees Rd",
    "sg:city":"Oldham",
    "sg:classifiers":[
        {
            "category":"Government",
            "subcategory":"Fire Station",
            "type":"Public Place"
        }
    ],
    "sg:phone":"+44 161 609 8210",
    "sg:postcode":"OL4 1JN",
    "sg:province":"Lancashire",
    "wof:name":"Greater Manchester County FireService",
    "wof:placetype":"venue"
},
  "geometry": {"coordinates":[-2.0947299004,53.5420799255],"type":"Point"}
}