{
  "type": "Feature",
  "properties": {
    "iso:country":"GB",
    "sg:address":"Dixon Road, Knowsley Industrial Park",
    "sg:city":"Liverpool",
    "sg:classifiers":[
        {
            "category":"Wholesale",
            "subcategory":"Office Equipment",
            "type":"Manufacturing & Wholesale Goods"
        },
        {
            "category":"Shopping",
            "subcategory":"Stationery & Office Supplies",
            "type":"Retail Goods"
        }
    ],
    "sg:phone":"+44 151 547 1791",
    "sg:postcode":"L33 7XF",
    "sg:province":"Lancashire",
    "sg:tags":[
        "manufacturer"
    ],
    "sg:website":"http://www.dams.com",
    "wof:name":"Dams International Ltd.",
    "wof:placetype":"venue"
},
  "geometry": {"coordinates":[-2.8644940853,53.4754066467],"type":"Point"}
}