{
  "type": "Feature",
  "properties": {
    "addr:full":"96 Dedworth Road Windsor Berkshire SL4 5AY",
    "addr:housenumber":"96",
    "addr:postcode":"sl4 5ay",
    "addr:street":"Dedworth Road",
    "iso:country":"GB",
    "sg:address":"96 Dedworth Road",
    "sg:city":"Windsor",
    "sg:classifiers":[
        {
            "category":"Food & Beverages",
            "subcategory":"Liquor & Beverages",
            "type":"Retail Goods"
        }
    ],
    "sg:phone":"+44 1753 866275",
    "sg:postcode":"SL4 5AY",
    "sg:province":"Berkshire",
    "sg:tags":[
        "beer",
        "spirit",
        "wines"
    ],
    "wof:name":"Thresher",
    "wof:placetype":"venue"
},
  "geometry": {"coordinates":[-0.6359300017,51.4786567688],"type":"Point"}
}