{
  "type": "Feature",
  "properties": {
    "iso:country":"GB",
    "sg:address":"36 Milton Road",
    "sg:city":"Ware",
    "sg:classifiers":[
        {
            "category":"Professional",
            "subcategory":"Management & Consulting",
            "type":"Services"
        }
    ],
    "sg:postcode":"SG12 0PZ",
    "sg:province":"Hertfordshire",
    "sg:tags":[
        "consultant",
        "business"
    ],
    "wof:name":"Coastnorth Ltd",
    "wof:placetype":"venue"
},
  "geometry": {"coordinates":[-0.03266,51.816414],"type":"Point"}
}