{
  "type": "Feature",
  "properties": {
    "addr:full":"57-59 Broadwater Road Worthing West Sussex BN14 8AH",
    "addr:housenumber":"57-59",
    "addr:postcode":"bn14 8ah",
    "addr:street":"Broadwater Road",
    "iso:country":"GB",
    "sg:address":"57-59 Broadwater Road",
    "sg:city":"Worthing",
    "sg:classifiers":[
        {
            "category":"Shopping",
            "subcategory":"Antiques",
            "type":"Retail Goods"
        }
    ],
    "sg:phone":"+44 1903 202059",
    "sg:postcode":"BN14 8AH",
    "sg:province":"West Sussex",
    "wof:name":"Wilsons Antiques Worthing",
    "wof:placetype":"venue"
},
  "geometry": {"coordinates":[-0.373598,50.824444],"type":"Point"}
}