{
  "type": "Feature",
  "properties": {
    "iso:country":"GB",
    "sg:address":"90 Clapham Rd",
    "sg:city":"Bedford",
    "sg:classifiers":[
        {
            "category":"Food & Beverages",
            "subcategory":"Supermarket",
            "type":"Retail Goods"
        }
    ],
    "sg:phone":"+44 1234 363150",
    "sg:postcode":"MK41 7PJ",
    "sg:province":"Bedfordshire",
    "wof:name":"J Sainsbury PLC",
    "wof:placetype":"venue"
},
  "geometry": {"coordinates":[-0.484423,52.146919],"type":"Point"}
}