{
  "type": "Feature",
  "properties": {
    "iso:country":"GB",
    "sg:address":"20 Edgwick Road",
    "sg:city":"Coventry",
    "sg:classifiers":[
        {
            "category":"Retail",
            "subcategory":"Auto Repair",
            "type":"Services"
        }
    ],
    "sg:phone":"+44 24 7666 8011",
    "sg:postcode":"CV6 5FQ",
    "sg:province":"Warwickshire",
    "sg:tags":[
        "modification",
        "garage",
        "related"
    ],
    "wof:name":"Vehicle Service Centre",
    "wof:placetype":"venue"
},
  "geometry": {"coordinates":[-1.491959,52.427505],"type":"Point"}
}