{
  "type": "Feature",
  "properties": {
    "iso:country":"GB",
    "sg:address":"33-35 Commercial Road",
    "sg:city":"London",
    "sg:classifiers":[
        {
            "category":"Shopping",
            "subcategory":"Crafts & Fabrics",
            "type":"Retail Goods"
        }
    ],
    "sg:postcode":"E1 1LD",
    "sg:province":"Greater London",
    "sg:tags":[
        "supplier"
    ],
    "wof:name":"Woodland Fashions Ltd.",
    "wof:placetype":"venue"
},
  "geometry": {"coordinates":[-0.0659139976,51.5150146484],"type":"Point"}
}