{
  "type": "Feature",
  "properties": {
    "iso:country":"GB",
    "sg:address":"133 New Rd",
    "sg:city":"Ayr",
    "sg:classifiers":[
        {
            "category":"Recreation",
            "subcategory":"Gun Range",
            "type":"Entertainment"
        }
    ],
    "sg:phone":"+44 1292 619883",
    "sg:postcode":"KA8 8DD",
    "sg:province":"South Ayrshire",
    "sg:tags":[
        "operator",
        "tour"
    ],
    "wof:name":"Scotia Sports Travel",
    "wof:placetype":"venue"
},
  "geometry": {"coordinates":[-4.6267,55.47179],"type":"Point"}
}