{
  "type": "Feature",
  "properties": {
    "addr:full":"43 Pyle Rd, Pyle Bridgend Bridgend CF33 6PG",
    "addr:housenumber":"43",
    "addr:postcode":"cf33 6pg",
    "addr:street":"Pyle Rd",
    "iso:country":"GB",
    "sg:address":"43 Pyle Rd, Pyle",
    "sg:city":"Bridgend",
    "sg:classifiers":[
        {
            "category":"Professional",
            "subcategory":"Employment Agencies",
            "type":"Services"
        }
    ],
    "sg:postcode":"CF33 6PG",
    "sg:province":"Bridgend",
    "sg:tags":[
        "consultant"
    ],
    "wof:name":"Accents Ltd",
    "wof:placetype":"venue"
},
  "geometry": {"coordinates":[-3.6933178902,51.528591156],"type":"Point"}
}