{
  "type": "Feature",
  "properties": {
    "iso:country":"GB",
    "sg:address":"Regency Ho, Kings Pl",
    "sg:city":"Buckhurst Hill",
    "sg:classifiers":[
        {
            "category":"Building & Trades",
            "subcategory":"Construction",
            "type":"Services"
        }
    ],
    "sg:phone":"+44 20 8559 1075",
    "sg:postcode":"IG9 5EB",
    "sg:province":"Essex",
    "sg:tags":[
        "builder"
    ],
    "wof:name":"Applied Decoration Services Ltd",
    "wof:placetype":"venue"
},
  "geometry": {"coordinates":[0.030989,51.624306],"type":"Point"}
}