{
  "type": "Feature",
  "properties": {
    "iso:country":"GB",
    "sg:address":"5 St James Street",
    "sg:city":"South Petherton",
    "sg:classifiers":[
        {
            "category":"Home & Garden",
            "subcategory":"Carpets & Floor Coverings",
            "type":"Retail Goods"
        }
    ],
    "sg:phone":"+44 1460 241161",
    "sg:postcode":"TA13 5BS",
    "sg:province":"Somerset",
    "sg:tags":[
        "carpets",
        "rug",
        "matting"
    ],
    "wof:name":"K D Carpets",
    "wof:placetype":"venue"
},
  "geometry": {"coordinates":[-2.809847,50.949791],"type":"Point"}
}