{
  "type": "Feature",
  "properties": {
    "iso:country":"GB",
    "sg:address":"Resersh House Business Center",
    "sg:city":"London",
    "sg:classifiers":[
        {
            "category":"Travel",
            "subcategory":"Travel Agent",
            "type":"Entertainment"
        }
    ],
    "sg:phone":"+44 20 8989 0331",
    "sg:postcode":"SW7 3DP",
    "sg:province":"Greater London",
    "wof:name":"Tyche Tours Ltd.",
    "wof:placetype":"venue"
},
  "geometry": {"coordinates":[-0.17602,51.49411],"type":"Point"}
}