{
  "type": "Feature",
  "properties": {
    "addr:full":"Smithfield Street Llanidloes Powys SY18 6EJ",
    "addr:postcode":"sy18 6ej",
    "addr:street":"Smithfield Street",
    "iso:country":"GB",
    "sg:address":"Smithfield Street",
    "sg:city":"Llanidloes",
    "sg:classifiers":[
        {
            "category":"Arena",
            "subcategory":"Sports Club",
            "type":"Entertainment"
        }
    ],
    "sg:phone":"+44 1686 413254",
    "sg:postcode":"SY18 6EJ",
    "sg:province":"Powys",
    "wof:name":"Llanidloes Rugby Club",
    "wof:placetype":"venue"
},
  "geometry": {"coordinates":[-3.5411748886,52.4470672607],"type":"Point"}
}