{
  "type": "Feature",
  "properties": {
    "iso:country":"GB",
    "sg:address":"Meliden Road, Rhuddlan",
    "sg:city":"Rhyl",
    "sg:classifiers":[
        {
            "category":"Education",
            "subcategory":"Special Training",
            "type":"Public Place"
        },
        {
            "category":"Government",
            "subcategory":"Office",
            "type":"Public Place"
        }
    ],
    "sg:phone":"+44 1745 590242",
    "sg:postcode":"LL18 6LG",
    "sg:province":"Conwy",
    "sg:tags":[
        "school",
        "local"
    ],
    "wof:name":"Tir Morfa Junior & Infant Special School",
    "wof:placetype":"venue"
},
  "geometry": {"coordinates":[-3.472384,53.311581],"type":"Point"}
}