{
  "type": "Feature",
  "properties": {
    "addr:full":"8 Jocelyn Road, First Floor Flat Richmond Greater London TW9 2TH",
    "addr:housenumber":"8",
    "addr:postcode":"tw9 2th",
    "addr:street":"Jocelyn Road First Floor Flat",
    "iso:country":"GB",
    "sg:address":"8 Jocelyn Road, First Floor Flat",
    "sg:city":"Richmond",
    "sg:classifiers":[
        {
            "category":"Communications",
            "type":"Services"
        }
    ],
    "sg:postcode":"TW9 2TH",
    "sg:province":"Greater London",
    "sg:tags":[
        "data",
        "network"
    ],
    "wof:name":"Lendata Solutions Ltd.",
    "wof:placetype":"venue"
},
  "geometry": {"coordinates":[-0.2978410125,51.4668083191],"type":"Point"}
}