{
  "type": "Feature",
  "properties": {
    "addr:full":"Ongar Rd Brentwood Essex CM15 9DP",
    "addr:postcode":"cm15 9dp",
    "addr:street":"Ongar Rd",
    "iso:country":"GB",
    "sg:address":"Ongar Rd",
    "sg:city":"Brentwood",
    "sg:classifiers":[
        {
            "category":"Building & Trades",
            "subcategory":"Construction",
            "type":"Services"
        }
    ],
    "sg:phone":"+44 1277 848411",
    "sg:postcode":"CM15 9DP",
    "sg:province":"Essex",
    "sg:tags":[
        "joinery"
    ],
    "wof:name":"Chelmer Fencing & Landscapes",
    "wof:placetype":"venue"
},
  "geometry": {"coordinates":[0.2943,51.628159],"type":"Point"}
}