{
  "type": "Feature",
  "properties": {
    "addr:full":"25 Naseby Rise, Manor Fields Newbury Berkshire RG14 2SF",
    "addr:housenumber":"25",
    "addr:postcode":"rg14 2sf",
    "addr:street":"Naseby Rise Manor;Newbury",
    "iso:country":"GB",
    "sg:address":"25 Naseby Rise, Manor Fields",
    "sg:city":"Newbury",
    "sg:classifiers":[
        {
            "category":"Professional",
            "subcategory":"Computer Services",
            "type":"Services"
        }
    ],
    "sg:phone":"+44 1635 523662",
    "sg:postcode":"RG14 2SF",
    "sg:province":"Berkshire",
    "sg:tags":[
        "system",
        "software"
    ],
    "wof:name":"It Works (Uk) Ltd.",
    "wof:placetype":"venue"
},
  "geometry": {"coordinates":[-1.3010799885,51.4111976624],"type":"Point"}
}