{
  "type": "Feature",
  "properties": {
    "iso:country":"GB",
    "sg:address":"123 Tickleford Drive",
    "sg:city":"Southampton",
    "sg:classifiers":[
        {
            "category":"Food & Beverages",
            "subcategory":"Groceries & Convenience Stores",
            "type":"Retail Goods"
        }
    ],
    "sg:phone":"+44 23 8032 2730",
    "sg:postcode":"SO19 9QP",
    "sg:province":"Hampshire",
    "wof:name":"Clements",
    "wof:placetype":"venue"
},
  "geometry": {"coordinates":[-1.3596589565,50.8861618042],"type":"Point"}
}