{
  "type": "Feature",
  "properties": {
    "iso:country":"GB",
    "sg:address":"Albion Court, 18-20 Frederick Street",
    "sg:city":"Birmingham",
    "sg:classifiers":[
        {
            "category":"Shopping",
            "subcategory":"Computers & Home Electronics",
            "type":"Retail Goods"
        }
    ],
    "sg:phone":"+44 121 693 9666",
    "sg:postcode":"B1 3HE",
    "sg:province":"West Midlands",
    "sg:tags":[
        "consumables"
    ],
    "wof:name":"Port - P Ltd.",
    "wof:placetype":"venue"
},
  "geometry": {"coordinates":[-1.911512,52.485107],"type":"Point"}
}