{
  "type": "Feature",
  "properties": {
    "iso:country":"GB",
    "sg:address":"49 Klea Avenue",
    "sg:city":"London",
    "sg:classifiers":[
        {
            "category":"Health Services",
            "subcategory":"Health Practitioner",
            "type":"Services"
        }
    ],
    "sg:postcode":"SW4 9HG",
    "sg:province":"Greater London",
    "sg:tags":[
        "hypnotherapists"
    ],
    "wof:name":"Keith Bibby",
    "wof:placetype":"venue"
},
  "geometry": {"coordinates":[-0.141347,51.454376],"type":"Point"}
}