{
  "type": "Feature",
  "properties": {
    "addr:full":"2 Abingdon Way Nuneaton Leicestershire CV11 6DX",
    "addr:housenumber":"2",
    "addr:postcode":"cv11 6dx",
    "addr:street":"Abingdon Way",
    "iso:country":"GB",
    "sg:address":"2 Abingdon Way",
    "sg:city":"Nuneaton",
    "sg:classifiers":[
        {
            "category":"Building & Trades",
            "subcategory":"Construction",
            "type":"Services"
        }
    ],
    "sg:phone":"+44 24 7637 5611",
    "sg:postcode":"CV11 6DX",
    "sg:province":"Leicestershire",
    "sg:tags":[
        "builder"
    ],
    "wof:name":"Prestige Home Improvements",
    "wof:placetype":"venue"
},
  "geometry": {"coordinates":[-1.446856,52.537193],"type":"Point"}
}