{
  "type": "Feature",
  "properties": {
    "addr:full":"Vicarage Street Luton Bedfordshire LU1 3HZ",
    "addr:postcode":"lu1 3hz",
    "addr:street":"Vicarage Street",
    "iso:country":"GB",
    "sg:address":"Vicarage Street",
    "sg:city":"Luton",
    "sg:classifiers":[
        {
            "category":"Place Of Worship",
            "type":"Public Place"
        }
    ],
    "sg:phone":"+44 1582 400294",
    "sg:postcode":"LU1 3HZ",
    "sg:province":"Bedfordshire",
    "wof:name":"The Salvation Army",
    "wof:placetype":"venue"
},
  "geometry": {"coordinates":[-0.4094139934,51.8774490356],"type":"Point"}
}