{
  "type": "Feature",
  "properties": {
    "addr:full":"Britco Works, 25 Orgreave Crescent, Dore House Industrial Estate Sheffield South Yorkshire S13 9NQ",
    "addr:housenumber":"25",
    "addr:postcode":"s13 9nq",
    "addr:street":"Orgreave Crescent Dore House Industrial Estate",
    "iso:country":"GB",
    "sg:address":"Britco Works, 25 Orgreave Crescent, Dore House Industrial Estate",
    "sg:city":"Sheffield",
    "sg:classifiers":[
        {
            "category":"Professional",
            "subcategory":"Engineering",
            "type":"Services"
        }
    ],
    "sg:phone":"+44 1483 746146",
    "sg:postcode":"S13 9NQ",
    "sg:province":"South Yorkshire",
    "wof:name":"James Walker Britco Ltd.",
    "wof:placetype":"venue"
},
  "geometry": {"coordinates":[-1.4645440578,53.3831100464],"type":"Point"}
}