{
  "type": "Feature",
  "properties": {
    "iso:country":"GB",
    "sg:address":"15 Vine Pl",
    "sg:city":"Sunderland",
    "sg:classifiers":[
        {
            "category":"Fast Food",
            "type":"Food & Drink"
        }
    ],
    "sg:phone":"+44 191 514 2840",
    "sg:postcode":"SR1 3NE",
    "sg:province":"Tyne and Wear",
    "sg:tags":[
        "away",
        "take"
    ],
    "wof:name":"Kebab Corner",
    "wof:placetype":"venue"
},
  "geometry": {"coordinates":[-1.386726,54.903866],"type":"Point"}
}