{
  "type": "Feature",
  "properties": {
    "addr:full":"528 Manchester Road Sheffield South Yorkshire S36 2DW",
    "addr:housenumber":"528",
    "addr:postcode":"s36 2dw",
    "addr:street":"Manchester Road",
    "iso:country":"GB",
    "sg:address":"528 Manchester Road",
    "sg:city":"Sheffield",
    "sg:classifiers":[
        {
            "category":"Food & Beverages",
            "subcategory":"Fruits & Vegetables",
            "type":"Retail Goods"
        }
    ],
    "sg:postcode":"S36 2DW",
    "sg:province":"South Yorkshire",
    "sg:tags":[
        "greengrocer"
    ],
    "wof:name":"Richard Walkers Fruit & Veg",
    "wof:placetype":"venue"
},
  "geometry": {"coordinates":[-1.6185990572,53.4912261963],"type":"Point"}
}