{
  "type": "Feature",
  "properties": {
    "iso:country":"GB",
    "sg:address":"17 Wood Street",
    "sg:city":"Cardiff",
    "sg:classifiers":[
        {
            "category":"Utilities",
            "subcategory":"Electric",
            "type":"Services"
        }
    ],
    "sg:phone":"+44 29 2023 5069",
    "sg:postcode":"CF1 1EN",
    "sg:province":"Cardiff",
    "sg:tags":[
        "electricity"
    ],
    "wof:name":"Swalec Gas Ltd.",
    "wof:placetype":"venue"
},
  "geometry": {"coordinates":[-3.182799,51.476101],"type":"Point"}
}