{
  "type": "Feature",
  "properties": {
    "iso:country":"GB",
    "sg:address":"74-76 Courtfield Gardens",
    "sg:city":"London",
    "sg:classifiers":[
        {
            "category":"Travel",
            "subcategory":"Hotels & Motels",
            "type":"Entertainment"
        }
    ],
    "sg:phone":"+44 20 7373 8594",
    "sg:postcode":"SW5 0NL",
    "sg:province":"Greater London",
    "wof:name":"Regent Court Hotel",
    "wof:placetype":"venue"
},
  "geometry": {"coordinates":[-0.1873369962,51.4928741455],"type":"Point"}
}