{
  "type": "Feature",
  "properties": {
    "addr:full":"7 Woodbury Drove, Crossways Dorchester Dorset DT2 8XT",
    "addr:housenumber":"7;crossways",
    "addr:postcode":"dt2 8xt",
    "addr:street":"Woodbury Drove",
    "iso:country":"GB",
    "sg:address":"7 Woodbury Drove, Crossways",
    "sg:city":"Dorchester",
    "sg:classifiers":[
        {
            "category":"Building & Trades",
            "subcategory":"Construction",
            "type":"Services"
        },
        {
            "category":"Sports & Exercise",
            "subcategory":"Playing Field",
            "type":"Entertainment"
        }
    ],
    "sg:phone":"+44 1305 854843",
    "sg:postcode":"DT2 8XT",
    "sg:province":"Dorset",
    "sg:tags":[
        "conservation",
        "builder",
        "thatching",
        "craft",
        "related"
    ],
    "wof:name":"D J Trevett Thatching",
    "wof:placetype":"venue"
},
  "geometry": {"coordinates":[-2.3287539482,50.6934585571],"type":"Point"}
}