{
  "type": "Feature",
  "properties": {
    "iso:country":"GB",
    "sg:address":"113-123 Upper Richmond Road",
    "sg:city":"London",
    "sg:classifiers":[
        {
            "category":"Utilities",
            "type":"Services"
        }
    ],
    "sg:postcode":"SW15 2TL",
    "sg:province":"Greater London",
    "sg:tags":[
        "connection",
        "provider",
        "internet"
    ],
    "wof:name":"Global Internet Ltd",
    "wof:placetype":"venue"
},
  "geometry": {"coordinates":[-0.2135230005,51.4599189758],"type":"Point"}
}