{
  "type": "Feature",
  "properties": {
    "iso:country":"GB",
    "sg:address":"Unit C Long Mead Industrial Estate, Blenheim Road",
    "sg:city":"Epsom",
    "sg:classifiers":[
        {
            "category":"Professional",
            "subcategory":"Detective & Security Services",
            "type":"Services"
        }
    ],
    "sg:postcode":"KT19 9QQ",
    "sg:province":"Surrey",
    "sg:tags":[
        "alarm",
        "burglar",
        "system"
    ],
    "wof:name":"Realisations Electronics Ltd.",
    "wof:placetype":"venue"
},
  "geometry": {"coordinates":[-0.271106,51.333008],"type":"Point"}
}