{
  "type": "Feature",
  "properties": {
    "iso:country":"GB",
    "sg:address":"Unit 16, Rudolf Place Indstl Est, Miles St",
    "sg:city":"London",
    "sg:classifiers":[
        {
            "category":"Building & Trades",
            "subcategory":"Cleaning & Sanitation",
            "type":"Services"
        }
    ],
    "sg:phone":"+44 20 7793 9996",
    "sg:postcode":"SW8 1RP",
    "sg:province":"Greater London",
    "sg:tags":[
        "repair",
        "lift",
        "-"
    ],
    "wof:name":"Lifts Direct Ltd",
    "wof:placetype":"venue"
},
  "geometry": {"coordinates":[-0.124154,51.483124],"type":"Point"}
}