{
  "type": "Feature",
  "properties": {
    "addr:full":"1 Ambler Street Castleford West Yorkshire WF10 4EB",
    "addr:housenumber":"1",
    "addr:postcode":"wf10 4eb",
    "addr:street":"Ambler Street",
    "iso:country":"GB",
    "sg:address":"1 Ambler Street",
    "sg:city":"Castleford",
    "sg:classifiers":[
        {
            "category":"Personal",
            "subcategory":"Beauty Salon",
            "type":"Services"
        }
    ],
    "sg:phone":"+44 1977 554377",
    "sg:postcode":"WF10 4EB",
    "sg:province":"West Yorkshire",
    "sg:tags":[
        "lady",
        "hairdresser"
    ],
    "wof:name":"Jills",
    "wof:placetype":"venue"
},
  "geometry": {"coordinates":[-1.347161,53.723042],"type":"Point"}
}