{
  "type": "Feature",
  "properties": {
    "iso:country":"GB",
    "sg:address":"20 College Road, Ash Vale",
    "sg:city":"Aldershot",
    "sg:classifiers":[
        {
            "category":"Home & Garden",
            "subcategory":"Carpets & Floor Coverings",
            "type":"Retail Goods"
        }
    ],
    "sg:phone":"+44 1252 315672",
    "sg:postcode":"GU12 5BZ",
    "sg:province":"Hampshire",
    "sg:tags":[
        "carpets",
        "rug",
        "matting"
    ],
    "wof:name":"G Baxter",
    "wof:placetype":"venue"
},
  "geometry": {"coordinates":[-0.717506,51.254189],"type":"Point"}
}