{
  "type": "Feature",
  "properties": {
    "iso:country":"GB",
    "sg:address":"Church Road",
    "sg:city":"Norwich",
    "sg:classifiers":[
        {
            "category":"Bars & Pubs",
            "type":"Food & Drink"
        }
    ],
    "sg:phone":"+44 1508 489438",
    "sg:postcode":"NR16 1BH",
    "sg:province":"Norfolk",
    "sg:tags":[
        "pubs",
        "inn"
    ],
    "wof:name":"The Bird in Hand",
    "wof:placetype":"venue"
},
  "geometry": {"coordinates":[1.1144720316,52.4850158691],"type":"Point"}
}