{
  "type": "Feature",
  "properties": {
    "addr:full":"South Suffolk Branch, Wadhurst Road Ipswich Suffolk IP3 8RS",
    "addr:postcode":"ip3 8rs",
    "addr:street":"South Suffolk Branch Wadhurst Road",
    "iso:country":"GB",
    "sg:address":"South Suffolk Branch, Wadhurst Road",
    "sg:city":"Ipswich",
    "sg:classifiers":[
        {
            "category":"Organizations",
            "subcategory":"Non-profit Organization",
            "type":"Services"
        }
    ],
    "sg:phone":"+44 1473 724506",
    "sg:postcode":"IP3 8RS",
    "sg:province":"Suffolk",
    "sg:tags":[
        "charitable",
        "organisation",
        "voluntary",
        "charity"
    ],
    "wof:name":"Multiple Sclerosis Society of Great Britain & Northern Ireland",
    "wof:placetype":"venue"
},
  "geometry": {"coordinates":[1.2058,52.042969],"type":"Point"}
}