{
  "type": "Feature",
  "properties": {
    "addr:full":"10 Pendeen Rd Glasgow Glasgow City G33 4TU",
    "addr:housenumber":"10",
    "addr:postcode":"g33 4tu",
    "addr:street":"Pendeen Rd",
    "iso:country":"GB",
    "sg:address":"10 Pendeen Rd",
    "sg:city":"Glasgow",
    "sg:classifiers":[
        {
            "category":"Food & Beverages",
            "subcategory":"Supermarket",
            "type":"Retail Goods"
        }
    ],
    "sg:postcode":"G33 4TU",
    "sg:province":"Glasgow City",
    "wof:name":"Bell,Lorraine,",
    "wof:placetype":"venue"
},
  "geometry": {"coordinates":[-4.13248,55.85751],"type":"Point"}
}