{
  "type": "Feature",
  "properties": {
    "iso:country":"GB",
    "sg:address":"63 Elm Gro, Southsea",
    "sg:city":"Portsmouth",
    "sg:classifiers":[
        {
            "category":"Home & Garden",
            "subcategory":"Household Appliances",
            "type":"Retail Goods"
        }
    ],
    "sg:phone":"+44 23 9275 6316",
    "sg:postcode":"PO5 1JF",
    "sg:province":"Hampshire",
    "sg:tags":[
        "electrical"
    ],
    "wof:name":"M D P Holdings",
    "wof:placetype":"venue"
},
  "geometry": {"coordinates":[-1.0877360106,50.7902565002],"type":"Point"}
}