{
  "type": "Feature",
  "properties": {
    "iso:country":"GB",
    "sg:address":"Rodney House, Castle Gate",
    "sg:city":"Nottingham",
    "sg:classifiers":[
        {
            "category":"Professional",
            "subcategory":"Accounting & Tax Preparation",
            "type":"Services"
        }
    ],
    "sg:phone":"+44 115 948 0788",
    "sg:postcode":"NG1 7AW",
    "sg:province":"Nottinghamshire",
    "sg:tags":[
        "accountant"
    ],
    "wof:name":"B M J Publishing Group Ltd.",
    "wof:placetype":"venue"
},
  "geometry": {"coordinates":[-1.150782,52.951073],"type":"Point"}
}