{
  "type": "Feature",
  "properties": {
    "addr:full":"21-29 Sandringham Road Thornton Heath Surrey CR7 7AX",
    "addr:housenumber":"21-29",
    "addr:postcode":"cr7 7ax",
    "addr:street":"Sandringham Road",
    "iso:country":"GB",
    "sg:address":"21-29 Sandringham Road",
    "sg:city":"Thornton Heath",
    "sg:classifiers":[
        {
            "category":"Bakery",
            "type":"Food & Drink"
        }
    ],
    "sg:postcode":"CR7 7AX",
    "sg:province":"Surrey",
    "sg:tags":[
        "cake",
        "maker"
    ],
    "wof:name":"Coughlans Bakeries Ltd.",
    "wof:placetype":"venue"
},
  "geometry": {"coordinates":[-0.0975989997,51.3930435181],"type":"Point"}
}