{
  "type": "Feature",
  "properties": {
    "iso:country":"GB",
    "sg:address":"Stanley House, 57-59 Broadway",
    "sg:city":"Peterborough",
    "sg:classifiers":[
        {
            "category":"Professional",
            "subcategory":"Computer Services",
            "type":"Services"
        }
    ],
    "sg:phone":"+44 1733 892525",
    "sg:postcode":"PE1 1SY",
    "sg:province":"Cambridgeshire",
    "sg:tags":[
        "system",
        "software"
    ],
    "wof:name":"Media Broadcast Systems Ltd.",
    "wof:placetype":"venue"
},
  "geometry": {"coordinates":[-0.241784,52.574841],"type":"Point"}
}