{
  "type": "Feature",
  "properties": {
    "addr:full":"Barrier Bank, Cowbit Spalding Cambridgeshire PE12 6AL",
    "addr:housenumber":"cowbit",
    "addr:postcode":"pe12 6al",
    "addr:street":"Spalding",
    "iso:country":"GB",
    "sg:address":"Barrier Bank, Cowbit",
    "sg:city":"Spalding",
    "sg:classifiers":[
        {
            "category":"Education",
            "subcategory":"School",
            "type":"Public Place"
        },
        {
            "category":"Government",
            "subcategory":"Office",
            "type":"Public Place"
        }
    ],
    "sg:phone":"+44 1406 380369",
    "sg:postcode":"PE12 6AL",
    "sg:province":"Cambridgeshire",
    "sg:tags":[
        "local",
        "authority"
    ],
    "wof:name":"Cowbit C of E Endowed Primary School",
    "wof:placetype":"venue"
},
  "geometry": {"coordinates":[-0.1340419948,52.7437553406],"type":"Point"}
}