{
  "type": "Feature",
  "properties": {
    "iso:country":"GB",
    "sg:address":"12 Appold Street",
    "sg:city":"London",
    "sg:classifiers":[
        {
            "category":"Real Estate",
            "subcategory":"Developer",
            "type":"Services"
        }
    ],
    "sg:postcode":"EC2A 2AW",
    "sg:province":"Greater London",
    "sg:tags":[
        "property"
    ],
    "wof:name":"Chase Midland Vct Ltd",
    "wof:placetype":"venue"
},
  "geometry": {"coordinates":[-0.081809,51.520878],"type":"Point"}
}