{
  "type": "Feature",
  "properties": {
    "iso:country":"GB",
    "sg:address":"20 Bridge St",
    "sg:city":"Winchester",
    "sg:classifiers":[
        {
            "category":"Place Of Worship",
            "type":"Public Place"
        }
    ],
    "sg:phone":"+44 1962 863217",
    "sg:postcode":"SO23 9BH",
    "sg:province":"Hampshire",
    "wof:name":"Vineyard Christian Fellowship",
    "wof:placetype":"venue"
},
  "geometry": {"coordinates":[-1.30734,51.060833],"type":"Point"}
}