{
  "type": "Feature",
  "properties": {
    "iso:country":"GB",
    "sg:address":"10 Wentworth Street",
    "sg:city":"London",
    "sg:classifiers":[
        {
            "category":"Shopping",
            "subcategory":"Clothing, Apparel, & Fashions",
            "type":"Retail Goods"
        }
    ],
    "sg:phone":"+44 20 7247 1527",
    "sg:postcode":"E1 7TF",
    "sg:province":"Greater London",
    "sg:tags":[
        "shop"
    ],
    "wof:name":"Shades Of London",
    "wof:placetype":"venue"
},
  "geometry": {"coordinates":[0.0430000015,51.5503845215],"type":"Point"}
}