{
  "type": "Feature",
  "properties": {
    "addr:full":"East St Newquay Cornwall TR7 1DB",
    "addr:postcode":"tr7 1db",
    "addr:street":"East St",
    "iso:country":"GB",
    "sg:address":"East St",
    "sg:city":"Newquay",
    "sg:classifiers":[
        {
            "category":"Bars & Pubs",
            "subcategory":"Nightclub",
            "type":"Food & Drink"
        }
    ],
    "sg:phone":"+44 1637 872255",
    "sg:postcode":"TR7 1DB",
    "sg:province":"Cornwall",
    "sg:tags":[
        "club",
        "night"
    ],
    "wof:name":"Berties Nightclub",
    "wof:placetype":"venue"
},
  "geometry": {"coordinates":[-5.079404,50.41415],"type":"Point"}
}