{
  "type": "Feature",
  "properties": {
    "iso:country":"GB",
    "sg:address":"Golf Links Road, Westward House",
    "sg:city":"Bideford",
    "sg:classifiers":[
        {
            "category":"Fast Food",
            "type":"Food & Drink"
        }
    ],
    "sg:phone":"+44 1237 474543",
    "sg:postcode":"EX39 1LH",
    "sg:province":"Devon",
    "sg:tags":[
        "away",
        "take"
    ],
    "wof:name":"Sunshine Leisure Takeaway",
    "wof:placetype":"venue"
},
  "geometry": {"coordinates":[-4.220808,51.044331],"type":"Point"}
}