{
  "type": "Feature",
  "properties": {
    "addr:full":"11 Riverdale Drive London Greater London SW18 4UR",
    "addr:housenumber":"11",
    "addr:postcode":"sw18 4ur",
    "addr:street":"Riverdale Drive",
    "iso:country":"GB",
    "sg:address":"11 Riverdale Drive",
    "sg:city":"London",
    "sg:classifiers":[
        {
            "category":"Banks & Credit Unions",
            "subcategory":"Financial Services",
            "type":"Services"
        }
    ],
    "sg:postcode":"SW18 4UR",
    "sg:province":"Greater London",
    "sg:tags":[
        "consultant"
    ],
    "wof:name":"1/2 Cut Financial Securities Ltd",
    "wof:placetype":"venue"
},
  "geometry": {"coordinates":[-0.1925349981,51.4431838989],"type":"Point"}
}