{
  "type": "Feature",
  "properties": {
    "addr:full":"1 Percy Terrace, Penshaw Houghton-le-spring Durham DH4 7PG",
    "addr:housenumber":"1",
    "addr:postcode":"dh4 7pg",
    "addr:street":"Percy Terrace",
    "iso:country":"GB",
    "sg:address":"1 Percy Terrace, Penshaw",
    "sg:city":"Houghton-le-spring",
    "sg:classifiers":[
        {
            "category":"Food & Beverages",
            "subcategory":"Supermarket",
            "type":"Retail Goods"
        }
    ],
    "sg:phone":"+44 191 385 3226",
    "sg:postcode":"DH4 7PG",
    "sg:province":"Durham",
    "wof:name":"North Eastern Co-Operative",
    "wof:placetype":"venue"
},
  "geometry": {"coordinates":[-1.501019,54.87571],"type":"Point"}
}