{
  "type": "Feature",
  "properties": {
    "iso:country":"GB",
    "sg:address":"Coldhams Lane",
    "sg:city":"Cambridge",
    "sg:classifiers":[
        {
            "category":"Social Services",
            "subcategory":"Job Training",
            "type":"Services"
        }
    ],
    "sg:phone":"+44 1223 431011",
    "sg:postcode":"CB1 3EP",
    "sg:province":"Cambridgeshire",
    "sg:tags":[
        "translator",
        "interpreter"
    ],
    "wof:name":"Cambridge Translation Bureau",
    "wof:placetype":"venue"
},
  "geometry": {"coordinates":[0.14333,52.208416],"type":"Point"}
}