{
  "type": "Feature",
  "properties": {
    "iso:country":"GB",
    "sg:address":"73 Clifton Street",
    "sg:city":"Lytham St Annes",
    "sg:classifiers":[
        {
            "category":"Food & Beverages",
            "subcategory":"Bakery",
            "type":"Retail Goods"
        }
    ],
    "sg:phone":"+44 1253 738408",
    "sg:postcode":"FY8 5ER",
    "sg:province":"Lancashire",
    "sg:tags":[
        "baker"
    ],
    "wof:name":"Hampsons",
    "wof:placetype":"venue"
},
  "geometry": {"coordinates":[-2.9612269402,53.7373352051],"type":"Point"}
}