{
  "type": "Feature",
  "properties": {
    "iso:country":"GB",
    "sg:address":"50 Snowdon Close",
    "sg:city":"Kidderminster",
    "sg:classifiers":[
        {
            "category":"Retail",
            "subcategory":"Driving School",
            "type":"Services"
        }
    ],
    "sg:phone":"+44 1562 822724",
    "sg:postcode":"DY11 5JH",
    "sg:province":"Staffordshire",
    "wof:name":"Shakespeare Driving School",
    "wof:placetype":"venue"
},
  "geometry": {"coordinates":[-2.263684,52.402946],"type":"Point"}
}