{
  "type": "Feature",
  "properties": {
    "addr:full":"Barrack Road Christchurch Dorset BH23 2BD",
    "addr:postcode":"bh23 2bd",
    "addr:street":"Barrack Road",
    "iso:country":"GB",
    "sg:address":"Barrack Road",
    "sg:city":"Christchurch",
    "sg:classifiers":[
        {
            "category":"Shopping",
            "subcategory":"Pets & Pet Supplies",
            "type":"Retail Goods"
        }
    ],
    "sg:phone":"+44 1202 490644",
    "sg:postcode":"BH23 2BD",
    "sg:province":"Dorset",
    "wof:name":"Pet Smart",
    "wof:placetype":"venue"
},
  "geometry": {"coordinates":[-1.8010480404,50.7427940369],"type":"Point"}
}