{
  "type": "Feature",
  "properties": {
    "addr:full":"286-288 Heathway Dagenham Essex RM10 8QS",
    "addr:housenumber":"286-288",
    "addr:postcode":"rm10 8qs",
    "addr:street":"Heathway",
    "iso:country":"GB",
    "sg:address":"286-288 Heathway",
    "sg:city":"Dagenham",
    "sg:classifiers":[
        {
            "category":"Organizations",
            "subcategory":"Non-profit Organization",
            "type":"Services"
        }
    ],
    "sg:phone":"+44 20 8593 7830",
    "sg:postcode":"RM10 8QS",
    "sg:province":"Essex",
    "sg:tags":[
        "organisation",
        "voluntary",
        "charity"
    ],
    "wof:name":"Barnardo's",
    "wof:placetype":"venue"
},
  "geometry": {"coordinates":[0.148064,51.542652],"type":"Point"}
}