{
  "type": "Feature",
  "properties": {
    "addr:full":"8 The Parade Kidlington Buckinghamshire OX5 1EE",
    "addr:housenumber":"8",
    "addr:postcode":"ox5 1ee",
    "addr:street":"The Parade",
    "iso:country":"GB",
    "sg:address":"8 The Parade",
    "sg:city":"Kidlington",
    "sg:classifiers":[
        {
            "category":"Personal",
            "subcategory":"Beauty Salon",
            "type":"Services"
        },
        {
            "category":"Personal",
            "subcategory":"Barber",
            "type":"Services"
        }
    ],
    "sg:phone":"+44 1865 375858",
    "sg:postcode":"OX5 1EE",
    "sg:province":"Buckinghamshire",
    "sg:tags":[
        "unisex",
        "hairdresser"
    ],
    "wof:name":"The Hair Gallery",
    "wof:placetype":"venue"
},
  "geometry": {"coordinates":[-1.295621,51.821449],"type":"Point"}
}