{
  "type": "Feature",
  "properties": {
    "addr:full":"3-5 Standishgate Wigan Lancashire WN1 1UE",
    "addr:housenumber":"3-5",
    "addr:postcode":"wn1 1ue",
    "addr:street":"Standishgate Wigan",
    "iso:country":"GB",
    "sg:address":"3-5 Standishgate",
    "sg:city":"Wigan",
    "sg:classifiers":[
        {
            "category":"Shopping",
            "subcategory":"Clothing, Apparel, & Fashions",
            "type":"Retail Goods"
        }
    ],
    "sg:phone":"+44 1942 245078",
    "sg:postcode":"WN1 1UE",
    "sg:province":"Lancashire",
    "sg:tags":[
        "menswear"
    ],
    "wof:name":"Burton Menswear",
    "wof:placetype":"venue"
},
  "geometry": {"coordinates":[-2.6307020187,53.5469474792],"type":"Point"}
}