{
  "type": "Feature",
  "properties": {
    "iso:country":"GB",
    "sg:address":"Town Quay, Pier Rd",
    "sg:city":"Littlehampton",
    "sg:classifiers":[
        {
            "category":"Autos & Motor Vehicles",
            "subcategory":"Boat Sales",
            "type":"Retail Goods"
        }
    ],
    "sg:phone":"+44 1903 713104",
    "sg:postcode":"BN17 5LR",
    "sg:province":"West Sussex",
    "sg:tags":[
        "repair",
        "builder"
    ],
    "wof:name":"A Powell",
    "wof:placetype":"venue"
},
  "geometry": {"coordinates":[-0.538959,50.82103],"type":"Point"}
}