{
  "type": "Feature",
  "properties": {
    "addr:full":"East Castle Street Alloa Clackmannanshire FK10 1BB",
    "addr:postcode":"fk10 1bb",
    "addr:street":"East Castle Street",
    "iso:country":"GB",
    "sg:address":"East Castle Street",
    "sg:city":"Alloa",
    "sg:classifiers":[
        {
            "category":"Social Services",
            "subcategory":"Adult Care",
            "type":"Services"
        },
        {
            "category":"Government",
            "subcategory":"Office",
            "type":"Public Place"
        }
    ],
    "sg:phone":"+44 1259 218722",
    "sg:postcode":"FK10 1BB",
    "sg:province":"Clackmannanshire",
    "sg:tags":[
        "local",
        "day",
        "centre"
    ],
    "wof:name":"Alloa Family Centre",
    "wof:placetype":"venue"
},
  "geometry": {"coordinates":[-3.7889640331,56.1106834412],"type":"Point"}
}