{
  "type": "Feature",
  "properties": {
    "addr:full":"Unit 48a Darlaston Central Trading, Estate, Salisbury Street Wednesbury West Midlands WS10 8BQ",
    "addr:housenumber":"unit 48a;estate",
    "addr:postcode":"ws10 8bq",
    "addr:street":"Trading;Salisbury Street",
    "iso:country":"GB",
    "sg:address":"Unit 48a Darlaston Central Trading, Estate, Salisbury Street",
    "sg:city":"Wednesbury",
    "sg:classifiers":[
        {
            "category":"Professional",
            "subcategory":"Engineering",
            "type":"Services"
        }
    ],
    "sg:phone":"+44 121 568 7077",
    "sg:postcode":"WS10 8BQ",
    "sg:province":"West Midlands",
    "sg:tags":[
        "contractor",
        "electrical",
        "engineer"
    ],
    "wof:name":"Property Protection Services Ltd.",
    "wof:placetype":"venue"
},
  "geometry": {"coordinates":[-2.0192539692,52.5527305603],"type":"Point"}
}