{
  "type": "Feature",
  "properties": {
    "iso:country":"GB",
    "sg:address":"58 West Street",
    "sg:city":"Horsham",
    "sg:classifiers":[
        {
            "category":"Personal",
            "subcategory":"Beauty Salon",
            "type":"Services"
        }
    ],
    "sg:phone":"+44 1403 256644",
    "sg:postcode":"RH12 1PL",
    "sg:province":"West Sussex",
    "sg:tags":[
        "unisex",
        "hairdresser"
    ],
    "wof:name":"Toni & Guy",
    "wof:placetype":"venue"
},
  "geometry": {"coordinates":[-0.3296279907,51.0627212524],"type":"Point"}
}