{
  "type": "Feature",
  "properties": {
    "iso:country":"GB",
    "sg:address":"48 Thorn Park",
    "sg:city":"St Austell",
    "sg:classifiers":[
        {
            "category":"Building & Trades",
            "subcategory":"Construction",
            "type":"Services"
        }
    ],
    "sg:phone":"+44 1726 67059",
    "sg:postcode":"PL25 4DP",
    "sg:province":"Cornwall",
    "sg:tags":[
        "joiner",
        "carpenter"
    ],
    "wof:name":"M Ford",
    "wof:placetype":"venue"
},
  "geometry": {"coordinates":[-4.7806940079,50.346786499],"type":"Point"}
}