{
  "type": "Feature",
  "properties": {
    "iso:country":"GB",
    "sg:address":"51 High Street",
    "sg:city":"Epping",
    "sg:classifiers":[
        {
            "category":"Shopping",
            "subcategory":"News",
            "type":"Retail Goods"
        }
    ],
    "sg:phone":"+44 1992 572046",
    "sg:postcode":"CM16 4BA",
    "sg:province":"Essex",
    "sg:tags":[
        "newsagent"
    ],
    "wof:name":"R L Patel",
    "wof:placetype":"venue"
},
  "geometry": {"coordinates":[0.107176,51.696445],"type":"Point"}
}