{
  "type": "Feature",
  "properties": {
    "addr:full":"Rear Of Sheffield Derbyshire S8 0RS",
    "addr:housenumber":"rear of",
    "addr:postcode":"s8 0rs",
    "iso:country":"GB",
    "sg:address":"Rear Of",
    "sg:city":"Sheffield",
    "sg:classifiers":[
        {
            "category":"Retail",
            "subcategory":"Auto Repair",
            "type":"Services"
        }
    ],
    "sg:postcode":"S8 0RS",
    "sg:province":"Derbyshire",
    "sg:tags":[
        "modification",
        "garage"
    ],
    "wof:name":"Smithywood Garage",
    "wof:placetype":"venue"
},
  "geometry": {"coordinates":[-1.4811700583,53.3543891907],"type":"Point"}
}