{
  "type": "Feature",
  "properties": {
    "addr:full":"72-74 High Street Brentwood Essex CM14 4AN",
    "addr:housenumber":"72-74",
    "addr:postcode":"cm14 4an",
    "addr:street":"High Street",
    "iso:country":"GB",
    "sg:address":"72-74 High Street",
    "sg:city":"Brentwood",
    "sg:classifiers":[
        {
            "category":"Shopping",
            "subcategory":"Thrift Store",
            "type":"Retail Goods"
        }
    ],
    "sg:phone":"+44 1277 217609",
    "sg:postcode":"CM14 4AN",
    "sg:province":"Essex",
    "sg:tags":[
        "shop",
        "charity"
    ],
    "wof:name":"Salvationarmy Trading Co. Ltd.",
    "wof:placetype":"venue"
},
  "geometry": {"coordinates":[0.300833,51.619843],"type":"Point"}
}