{
  "type": "Feature",
  "properties": {
    "addr:full":"466 Bath Road Slough Berkshire SL1 6BB",
    "addr:housenumber":"466",
    "addr:postcode":"sl1 6bb",
    "addr:street":"Bath Road",
    "iso:country":"GB",
    "sg:address":"466 Bath Road",
    "sg:city":"Slough",
    "sg:classifiers":[
        {
            "category":"Shopping",
            "type":"Retail Goods"
        }
    ],
    "sg:phone":"+44 1753 671668",
    "sg:postcode":"SL1 6BB",
    "sg:province":"Berkshire",
    "sg:tags":[
        "part",
        "accessory"
    ],
    "wof:name":"Body Shop Supplies",
    "wof:placetype":"venue"
},
  "geometry": {"coordinates":[-0.649462,51.520302],"type":"Point"}
}