{
  "type": "Feature",
  "properties": {
    "addr:full":"13 Reading Avenue, St Nicholas Park Estate Nuneaton Leicestershire CV11 6HE",
    "addr:housenumber":"13",
    "addr:postcode":"cv11 6he",
    "addr:street":"Reading Avenue St Nicholas Park Estate",
    "iso:country":"GB",
    "sg:address":"13 Reading Avenue, St Nicholas Park Estate",
    "sg:city":"Nuneaton",
    "sg:classifiers":[
        {
            "category":"Building & Trades",
            "subcategory":"Construction",
            "type":"Services"
        }
    ],
    "sg:phone":"+44 24 7634 7638",
    "sg:postcode":"CV11 6HE",
    "sg:province":"Leicestershire",
    "sg:tags":[
        "builder"
    ],
    "wof:name":"T Brown & Son",
    "wof:placetype":"venue"
},
  "geometry": {"coordinates":[-1.443898,52.537659],"type":"Point"}
}