{
  "type": "Feature",
  "properties": {
    "iso:country":"GB",
    "sg:address":"Old Police Ho, Park Pl, Ashton Keynes",
    "sg:city":"Swindon",
    "sg:classifiers":[
        {
            "category":"Professional",
            "subcategory":"Management & Consulting",
            "type":"Services"
        }
    ],
    "sg:phone":"+44 1285 861547",
    "sg:postcode":"SN6 6NT",
    "sg:province":"Gloucestershire",
    "sg:tags":[
        "consultant",
        "business"
    ],
    "wof:name":"Viewstar Consultants Ltd",
    "wof:placetype":"venue"
},
  "geometry": {"coordinates":[-1.940819,51.641937],"type":"Point"}
}