{
  "type": "Feature",
  "properties": {
    "addr:full":"157 Woodgrange Dr Southend-on-sea Essex SS1 2SF",
    "addr:housenumber":"157",
    "addr:postcode":"ss1 2sf",
    "addr:street":"Woodgrange Dr Southend-On-Sea",
    "iso:country":"GB",
    "sg:address":"157 Woodgrange Dr",
    "sg:city":"Southend-on-sea",
    "sg:classifiers":[
        {
            "category":"Shopping",
            "subcategory":"Florist",
            "type":"Retail Goods"
        }
    ],
    "sg:postcode":"SS1 2SF",
    "sg:province":"Essex",
    "wof:name":"Childs,Angeline,",
    "wof:placetype":"venue"
},
  "geometry": {"coordinates":[0.731641,51.535534],"type":"Point"}
}