{
  "type": "Feature",
  "properties": {
    "addr:full":"Shopping Centre Ringwood Dorset BH24 1AW",
    "addr:postcode":"bh24 1aw",
    "addr:street":"Shopping",
    "iso:country":"GB",
    "sg:address":"Shopping Centre",
    "sg:city":"Ringwood",
    "sg:classifiers":[
        {
            "category":"Shopping",
            "subcategory":"Hobbies, Toys, & Games",
            "type":"Retail Goods"
        }
    ],
    "sg:postcode":"BH24 1AW",
    "sg:province":"Dorset",
    "sg:tags":[
        "computer"
    ],
    "wof:name":"Tony Barrass",
    "wof:placetype":"venue"
},
  "geometry": {"coordinates":[-1.7929890156,50.8463287354],"type":"Point"}
}