{
  "type": "Feature",
  "properties": {
    "addr:full":"Symons Avenue Chatham Kent ME4 5UP",
    "addr:postcode":"me4 5up",
    "addr:street":"Symons Avenue",
    "iso:country":"GB",
    "sg:address":"Symons Avenue",
    "sg:city":"Chatham",
    "sg:classifiers":[
        {
            "category":"Education",
            "subcategory":"School",
            "type":"Public Place"
        }
    ],
    "sg:phone":"+44 1634 409521",
    "sg:postcode":"ME4 5UP",
    "sg:province":"Kent",
    "sg:tags":[
        "local",
        "authority"
    ],
    "wof:name":"Glencoe County Infants School",
    "wof:placetype":"venue"
},
  "geometry": {"coordinates":[0.526048,51.373131],"type":"Point"}
}