{
  "type": "Feature",
  "properties": {
    "addr:full":"62 Bedford Place Southampton Hampshire SO15 2DS",
    "addr:housenumber":"62",
    "addr:postcode":"so15 2ds",
    "addr:street":"Bedford Place",
    "iso:country":"GB",
    "sg:address":"62 Bedford Place",
    "sg:city":"Southampton",
    "sg:classifiers":[
        {
            "category":"Personal",
            "subcategory":"Beauty Salon",
            "type":"Services"
        }
    ],
    "sg:phone":"+44 23 8022 6964",
    "sg:postcode":"SO15 2DS",
    "sg:province":"Hampshire",
    "sg:tags":[
        "unisex",
        "hairdresser"
    ],
    "wof:name":"Heath & Sinclair Ltd.",
    "wof:placetype":"venue"
},
  "geometry": {"coordinates":[-1.40651,50.913364],"type":"Point"}
}