{
  "type": "Feature",
  "properties": {
    "addr:full":"Shelford Lodge Farm, Shelford Road, Radcliffe On Trent Nottingham Nottinghamshire NG12 1EA",
    "addr:postcode":"ng12 1ea",
    "addr:street":"Shelford Road",
    "iso:country":"GB",
    "sg:address":"Shelford Lodge Farm, Shelford Road, Radcliffe On Trent",
    "sg:city":"Nottingham",
    "sg:classifiers":[
        {
            "category":"Farming",
            "subcategory":"Livestock Farm",
            "type":"Manufacturing & Wholesale Goods"
        }
    ],
    "sg:postcode":"NG12 1EA",
    "sg:province":"Nottinghamshire",
    "sg:tags":[
        "others"
    ],
    "wof:name":"Malcolm P Wilson",
    "wof:placetype":"venue"
},
  "geometry": {"coordinates":[-1.0138640404,52.9734382629],"type":"Point"}
}