{
  "type": "Feature",
  "properties": {
    "addr:full":"85 West Street Tavistock Devon PL19 8AQ",
    "addr:housenumber":"85",
    "addr:postcode":"pl19 8aq",
    "addr:street":"West Street",
    "iso:country":"GB",
    "sg:address":"85 West Street",
    "sg:city":"Tavistock",
    "sg:classifiers":[
        {
            "category":"Shopping",
            "subcategory":"Mobile Phones",
            "type":"Retail Goods"
        }
    ],
    "sg:phone":"+44 1822 615755",
    "sg:postcode":"PL19 8AQ",
    "sg:province":"Devon",
    "wof:name":"Jag Communications (Plymouth) Ltd.",
    "wof:placetype":"venue"
},
  "geometry": {"coordinates":[-4.145921,50.549919],"type":"Point"}
}