{
  "type": "Feature",
  "properties": {
    "addr:full":"4 Dukes Gate, Acton Lane London Greater London W4 5DX",
    "addr:housenumber":"4",
    "addr:postcode":"w4 5dx",
    "addr:street":"Dukes Gate Acton Lane",
    "iso:country":"GB",
    "sg:address":"4 Dukes Gate, Acton Lane",
    "sg:city":"London",
    "sg:classifiers":[
        {
            "category":"Coffee & Tea",
            "type":"Food & Drink"
        }
    ],
    "sg:phone":"+44 20 8740 3820",
    "sg:postcode":"W4 5DX",
    "sg:province":"Greater London",
    "wof:name":"B B L Coffee Ltd.",
    "wof:placetype":"venue"
},
  "geometry": {"coordinates":[-0.268059,51.493752],"type":"Point"}
}