{
  "type": "Feature",
  "properties": {
    "addr:full":"112 The Chandlery, 50 Westminster Bridge Road London Greater London SE1 7QY",
    "addr:housenumber":"112;50",
    "addr:postcode":"se1 7qy",
    "addr:street":"The Chandlery;Westminster Bridge Road",
    "iso:country":"GB",
    "sg:address":"112 The Chandlery, 50 Westminster Bridge Road",
    "sg:city":"London",
    "sg:classifiers":[
        {
            "category":"Professional",
            "subcategory":"Business Services",
            "type":"Services"
        }
    ],
    "sg:phone":"+44 20 7721 7680",
    "sg:postcode":"SE1 7QY",
    "sg:province":"Greater London",
    "sg:tags":[
        "assessment",
        "quality"
    ],
    "wof:name":"Russell Square Quality Associates Ltd.",
    "wof:placetype":"venue"
},
  "geometry": {"coordinates":[-0.108529,51.498283],"type":"Point"}
}