{
  "type": "Feature",
  "properties": {
    "iso:country":"GB",
    "sg:address":"Unit 4, Cumberland Business Park, 17 Cumberland Avenue",
    "sg:city":"London",
    "sg:classifiers":[
        {
            "category":"Food & Beverages",
            "subcategory":"Bakery",
            "type":"Retail Goods"
        },
        {
            "category":"Shopping",
            "subcategory":"Pharmacy",
            "type":"Retail Goods"
        }
    ],
    "sg:phone":"+44 20 8961 9743",
    "sg:postcode":"NW10 7RT",
    "sg:province":"Greater London",
    "sg:tags":[
        "medical",
        "confectionery"
    ],
    "wof:name":"Tar Ltd.",
    "wof:placetype":"venue"
},
  "geometry": {"coordinates":[-0.277669,51.530605],"type":"Point"}
}