{
  "type": "Feature",
  "properties": {
    "addr:full":"Unit 28 Carylon Road Industrial Atherstone Leicestershire CV9 1JH",
    "addr:housenumber":"unit 28",
    "addr:postcode":"cv9 1jh",
    "addr:street":"Carylon Road Industrial Atherstone Leicestershire",
    "iso:country":"GB",
    "sg:address":"Unit 28 Carylon Road Industrial",
    "sg:city":"Atherstone",
    "sg:classifiers":[
        {
            "category":"Home & Garden",
            "subcategory":"Building Materials",
            "type":"Retail Goods"
        }
    ],
    "sg:postcode":"CV9 1JH",
    "sg:province":"Leicestershire",
    "sg:tags":[
        "furnishers",
        "bathroom",
        "planner"
    ],
    "wof:name":"Decorative Bathroom Systems Ltd.",
    "wof:placetype":"venue"
},
  "geometry": {"coordinates":[-1.5419590473,52.5759353638],"type":"Point"}
}