{
  "type": "Feature",
  "properties": {
    "addr:full":"147a Richmond Road Crewe Cheshire CW1 4AX",
    "addr:housenumber":"147a",
    "addr:postcode":"cw1 4ax",
    "addr:street":"Richmond Road",
    "iso:country":"GB",
    "sg:address":"147a Richmond Road",
    "sg:city":"Crewe",
    "sg:classifiers":[
        {
            "category":"Wholesale",
            "subcategory":"Vending Machines",
            "type":"Manufacturing & Wholesale Goods"
        }
    ],
    "sg:phone":"+44 1270 587700",
    "sg:postcode":"CW1 4AX",
    "sg:province":"Cheshire",
    "wof:name":"Brupac Drinks & Machine Co. Ltd.",
    "wof:placetype":"venue"
},
  "geometry": {"coordinates":[-2.4297809601,53.1021232605],"type":"Point"}
}