{
  "type": "Feature",
  "properties": {
    "iso:country":"GB",
    "sg:address":"5 Bramcote Road",
    "sg:city":"Liverpool",
    "sg:classifiers":[
        {
            "category":"Real Estate",
            "subcategory":"Real Estate Services",
            "type":"Services"
        },
        {
            "category":"Building & Trades",
            "subcategory":"Construction",
            "type":"Services"
        }
    ],
    "sg:phone":"+44 151 547 4639",
    "sg:postcode":"L33 9UY",
    "sg:province":"Lancashire",
    "sg:tags":[
        "joiner",
        "carpenter"
    ],
    "wof:name":"Jackson Joinery Services",
    "wof:placetype":"venue"
},
  "geometry": {"coordinates":[-2.876177,53.49242],"type":"Point"}
}