{
  "type": "Feature",
  "properties": {
    "addr:full":"Blendon Station, 510 Blackfen Road Sidcup Kent DA15 9NT",
    "addr:housenumber":"510",
    "addr:postcode":"da15 9nt",
    "addr:street":"Blackfen Road",
    "iso:country":"GB",
    "sg:address":"Blendon Station, 510 Blackfen Road",
    "sg:city":"Sidcup",
    "sg:classifiers":[
        {
            "category":"Autos & Motor Vehicles",
            "subcategory":"Fuel & Gas Station",
            "type":"Retail Goods"
        }
    ],
    "sg:phone":"+44 20 8298 7290",
    "sg:postcode":"DA15 9NT",
    "sg:province":"Kent",
    "sg:tags":[
        "hr",
        "petrol"
    ],
    "wof:name":"Shell Blendon",
    "wof:placetype":"venue"
},
  "geometry": {"coordinates":[0.1182300001,51.4478492737],"type":"Point"}
}