{
  "type": "Feature",
  "properties": {
    "addr:full":"58 Rudston Rd Liverpool Merseyside L16 4PH",
    "addr:housenumber":"58",
    "addr:postcode":"l16 4ph",
    "addr:street":"Rudston Rd",
    "iso:country":"GB",
    "sg:address":"58 Rudston Rd",
    "sg:city":"Liverpool",
    "sg:classifiers":[
        {
            "category":"Shopping",
            "subcategory":"Party Supplies",
            "type":"Retail Goods"
        }
    ],
    "sg:postcode":"L16 4PH",
    "sg:province":"Merseyside",
    "sg:tags":[
        "inflatables",
        "bouncy",
        "castle"
    ],
    "wof:name":"Kirkbride,Lynne,",
    "wof:placetype":"venue"
},
  "geometry": {"coordinates":[-2.89538908,53.398235321],"type":"Point"}
}