{
  "type": "Feature",
  "properties": {
    "addr:full":"Castle Building, Womanby Street Cardiff Cardiff CF10 1BR",
    "addr:postcode":"cf10 1br",
    "addr:street":"Womanby Street",
    "iso:country":"GB",
    "sg:address":"Castle Building, Womanby Street",
    "sg:city":"Cardiff",
    "sg:classifiers":[
        {
            "category":"Professional",
            "subcategory":"Management & Consulting",
            "type":"Services"
        }
    ],
    "sg:postcode":"CF10 1BR",
    "sg:province":"Cardiff",
    "sg:tags":[
        "consultant",
        "business"
    ],
    "wof:name":"Eres Economic Development Partnership Ltd.",
    "wof:placetype":"venue"
},
  "geometry": {"coordinates":[-3.180717,51.481022],"type":"Point"}
}