{
  "type": "Feature",
  "properties": {
    "addr:full":"Unit 62 Trostre Road Industrial Estate Llanelli Carmarthenshire SA14 9UU",
    "addr:housenumber":"unit 62",
    "addr:postcode":"sa14 9uu",
    "addr:street":"Trostre Road Industrial Estate",
    "iso:country":"GB",
    "sg:address":"Unit 62 Trostre Road Industrial Estate",
    "sg:city":"Llanelli",
    "sg:classifiers":[
        {
            "category":"Food & Beverages",
            "subcategory":"Bakery",
            "type":"Retail Goods"
        }
    ],
    "sg:phone":"+44 1554 758285",
    "sg:postcode":"SA14 9UU",
    "sg:province":"Carmarthenshire",
    "sg:tags":[
        "confectionery"
    ],
    "wof:name":"David Jenkins",
    "wof:placetype":"venue"
},
  "geometry": {"coordinates":[-4.143394,51.672375],"type":"Point"}
}