{
  "type": "Feature",
  "properties": {
    "iso:country":"GB",
    "sg:address":"Sinope Street",
    "sg:city":"Gloucester",
    "sg:classifiers":[
        {
            "category":"Social Services",
            "subcategory":"Adult Care",
            "type":"Services"
        },
        {
            "category":"Government",
            "subcategory":"Office",
            "type":"Public Place"
        }
    ],
    "sg:phone":"+44 1452 417593",
    "sg:postcode":"GL1 4AW",
    "sg:province":"Gloucestershire",
    "sg:tags":[
        "local",
        "day",
        "centre"
    ],
    "wof:name":"Widden Family Centre",
    "wof:placetype":"venue"
},
  "geometry": {"coordinates":[-2.23531,51.862007],"type":"Point"}
}