{
  "type": "Feature",
  "properties": {
    "iso:country":"GB",
    "sg:address":"45 High Street",
    "sg:city":"Burton-on-trent",
    "sg:classifiers":[
        {
            "category":"Professional",
            "subcategory":"Lawyer & Legal Services",
            "type":"Services"
        }
    ],
    "sg:phone":"+44 1283 548282",
    "sg:postcode":"DE14 1JP",
    "sg:province":"Derbyshire",
    "sg:tags":[
        "solicitor"
    ],
    "wof:name":"Drewry & Newbold",
    "wof:placetype":"venue"
},
  "geometry": {"coordinates":[-1.629528,52.803398],"type":"Point"}
}