{
  "type": "Feature",
  "properties": {
    "addr:full":"Unit 3 North St Workshops, North St Stoke-sub-hamdon Somerset TA14 6QR",
    "addr:housenumber":"unit 3",
    "addr:postcode":"ta14 6qr",
    "addr:street":"North St;North St",
    "iso:country":"GB",
    "sg:address":"Unit 3 North St Workshops, North St",
    "sg:city":"Stoke-sub-hamdon",
    "sg:classifiers":[
        {
            "category":"Organizations",
            "subcategory":"Non-profit Organization",
            "type":"Services"
        }
    ],
    "sg:phone":"+44 1935 825775",
    "sg:postcode":"TA14 6QR",
    "sg:province":"Somerset",
    "sg:tags":[
        "organisation",
        "voluntary",
        "charity"
    ],
    "wof:name":"Macmillan Cancer Relief",
    "wof:placetype":"venue"
},
  "geometry": {"coordinates":[-2.7507278919,50.9597244263],"type":"Point"}
}