{
  "type": "Feature",
  "properties": {
    "iso:country":"GB",
    "sg:address":"Swettenham",
    "sg:city":"Congleton",
    "sg:classifiers":[
        {
            "category":"Organizations",
            "subcategory":"Membership Organization",
            "type":"Services"
        }
    ],
    "sg:phone":"+44 1477 571376",
    "sg:postcode":"CW12 2LA",
    "sg:province":"Cheshire",
    "sg:tags":[
        "club",
        "social"
    ],
    "wof:name":"Swettenham Club",
    "wof:placetype":"venue"
},
  "geometry": {"coordinates":[-2.28445,53.200691],"type":"Point"}
}