{
  "type": "Feature",
  "properties": {
    "iso:country":"GB",
    "sg:address":"45 High Street",
    "sg:city":"Ross-on-wye",
    "sg:classifiers":[
        {
            "category":"Cafe",
            "type":"Food & Drink"
        }
    ],
    "sg:phone":"+44 1989 562217",
    "sg:postcode":"HR9 5HG",
    "sg:province":"Gloucestershire",
    "sg:tags":[
        "tea",
        "room"
    ],
    "wof:name":"The Priory Coffee Shop",
    "wof:placetype":"venue"
},
  "geometry": {"coordinates":[-2.585057,51.914227],"type":"Point"}
}