{
  "type": "Feature",
  "properties": {
    "iso:country":"GB",
    "sg:address":"5 College Court",
    "sg:city":"Gloucester",
    "sg:classifiers":[
        {
            "category":"Shopping",
            "subcategory":"Florist",
            "type":"Retail Goods"
        }
    ],
    "sg:phone":"+44 1452 300767",
    "sg:postcode":"GL1 2NJ",
    "sg:province":"Gloucestershire",
    "wof:name":"The Living Room",
    "wof:placetype":"venue"
},
  "geometry": {"coordinates":[-2.2481129169,51.8667182922],"type":"Point"}
}