{
  "type": "Feature",
  "properties": {
    "addr:full":"10b Pethericks Mill Indslt Estate Bude Cornwall EX23 8QN",
    "addr:housenumber":"10b",
    "addr:postcode":"ex23 8qn",
    "addr:street":"Pethericks Mill Indslt Estate",
    "iso:country":"GB",
    "sg:address":"10b Pethericks Mill Indslt Estate",
    "sg:city":"Bude",
    "sg:classifiers":[
        {
            "category":"Wholesale",
            "subcategory":"Machinery & Supplies",
            "type":"Manufacturing & Wholesale Goods"
        }
    ],
    "sg:phone":"+44 1288 354454",
    "sg:postcode":"EX23 8QN",
    "sg:province":"Cornwall",
    "sg:tags":[
        "plant"
    ],
    "wof:name":"L J L  Repair Parts Ltd.",
    "wof:placetype":"venue"
},
  "geometry": {"coordinates":[-4.5444779396,50.8283615112],"type":"Point"}
}