{
  "type": "Feature",
  "properties": {
    "iso:country":"GB",
    "sg:address":"8 Jury Street, Warwick",
    "sg:city":"Warwick",
    "sg:postcode":"CV34 4EW",
    "sg:province":"Warwickshire",
    "wof:name":"Uniprize Machine Tools Ltd.",
    "wof:placetype":"venue"
},
  "geometry": {"coordinates":[-1.5867340565,52.2814102173],"type":"Point"}
}