{
  "type": "Feature",
  "properties": {
    "iso:country":"GB",
    "sg:address":"Stocksfield Hall Farm",
    "sg:city":"Stocksfield",
    "sg:classifiers":[
        {
            "category":"Professional",
            "subcategory":"Management & Consulting",
            "type":"Services"
        }
    ],
    "sg:phone":"+44 1661 844712",
    "sg:postcode":"NE43 7TN",
    "sg:province":"Northumberland",
    "sg:tags":[
        "project"
    ],
    "wof:name":"J P M Consultants",
    "wof:placetype":"venue"
},
  "geometry": {"coordinates":[-1.9158940315,54.946685791],"type":"Point"}
}