{
  "type": "Feature",
  "properties": {
    "addr:full":"16 High Street, Otford Sevenoaks Kent TN14 5PQ",
    "addr:housenumber":"16",
    "addr:postcode":"tn14 5pq",
    "addr:street":"High Street",
    "iso:country":"GB",
    "sg:address":"16 High Street, Otford",
    "sg:city":"Sevenoaks",
    "sg:classifiers":[
        {
            "category":"Shopping",
            "subcategory":"Antiques",
            "type":"Retail Goods"
        }
    ],
    "sg:phone":"+44 1959 522778",
    "sg:postcode":"TN14 5PQ",
    "sg:province":"Kent",
    "wof:name":"Mandarin Gallery",
    "wof:placetype":"venue"
},
  "geometry": {"coordinates":[0.1893489957,51.3130836487],"type":"Point"}
}