{
  "type": "Feature",
  "properties": {
    "addr:full":"2a Replingham Road London Greater London SW18 5LS",
    "addr:housenumber":"2a",
    "addr:postcode":"sw18 5ls",
    "addr:street":"Replingham Road",
    "iso:country":"GB",
    "sg:address":"2a Replingham Road",
    "sg:city":"London",
    "sg:classifiers":[
        {
            "category":"Real Estate",
            "subcategory":"Real Estate Agent",
            "type":"Services"
        }
    ],
    "sg:phone":"+44 20 8874 6686",
    "sg:postcode":"SW18 5LS",
    "sg:province":"Greater London",
    "wof:name":"Bells Estate Agents",
    "wof:placetype":"venue"
},
  "geometry": {"coordinates":[-0.206419,51.444706],"type":"Point"}
}