{
  "type": "Feature",
  "properties": {
    "iso:country":"GB",
    "sg:address":"14-16 Lidget Hill",
    "sg:city":"Pudsey",
    "sg:classifiers":[
        {
            "category":"Restaurant",
            "type":"Food & Drink"
        }
    ],
    "sg:phone":"+44 113 255 5568",
    "sg:postcode":"LS28 7DR",
    "sg:province":"West Yorkshire",
    "sg:tags":[
        "chinese"
    ],
    "wof:name":"Dragon Inn",
    "wof:placetype":"venue"
},
  "geometry": {"coordinates":[-1.663526,53.797237],"type":"Point"}
}