{
  "type": "Feature",
  "properties": {
    "iso:country":"GB",
    "sg:address":"10f-11f The Waters Edge",
    "sg:city":"Birmingham",
    "sg:classifiers":[
        {
            "category":"Real Estate",
            "subcategory":"Developer",
            "type":"Services"
        },
        {
            "category":"Real Estate",
            "subcategory":"Real Estate Agent",
            "type":"Services"
        }
    ],
    "sg:phone":"+44 121 643 7799",
    "sg:postcode":"B1 2HL",
    "sg:province":"West Midlands",
    "sg:tags":[
        "property"
    ],
    "wof:name":"Argent Estates Ltd.",
    "wof:placetype":"venue"
},
  "geometry": {"coordinates":[-1.9122489691,52.4782295227],"type":"Point"}
}