{
  "type": "Feature",
  "properties": {
    "addr:full":"1 Larch Gro, Sedgley Dudley Staffordshire DY3 1TL",
    "addr:housenumber":"1",
    "addr:postcode":"dy3 1tl",
    "addr:street":"Larch Gro",
    "iso:country":"GB",
    "sg:address":"1 Larch Gro, Sedgley",
    "sg:city":"Dudley",
    "sg:classifiers":[
        {
            "category":"Professional",
            "subcategory":"Engineering",
            "type":"Services"
        }
    ],
    "sg:postcode":"DY3 1TL",
    "sg:province":"Staffordshire",
    "sg:tags":[
        "civil",
        "engineer"
    ],
    "wof:name":"Sedgley Asphalt & Paving Ltd",
    "wof:placetype":"venue"
},
  "geometry": {"coordinates":[-2.117363,52.535126],"type":"Point"}
}