{
  "type": "Feature",
  "properties": {
    "iso:country":"GB",
    "sg:address":"128 Green La",
    "sg:city":"Birmingham",
    "sg:classifiers":[
        {
            "category":"Professional",
            "subcategory":"Engineering",
            "type":"Services"
        }
    ],
    "sg:phone":"+44 121 749 7566",
    "sg:postcode":"B36 0BX",
    "sg:province":"West Midlands",
    "sg:tags":[
        "contractor",
        "electrical",
        "engineer"
    ],
    "wof:name":"Amlec Electrical Services",
    "wof:placetype":"venue"
},
  "geometry": {"coordinates":[-1.760065,52.506874],"type":"Point"}
}