{
  "type": "Feature",
  "properties": {
    "iso:country":"GB",
    "sg:address":"Ravensfield",
    "sg:city":"Basildon",
    "sg:classifiers":[
        {
            "category":"Social Services",
            "subcategory":"Adult Care",
            "type":"Services"
        },
        {
            "category":"Government",
            "subcategory":"Office",
            "type":"Public Place"
        }
    ],
    "sg:phone":"+44 1268 554221",
    "sg:postcode":"SS14 1UH",
    "sg:province":"Essex",
    "sg:tags":[
        "housing",
        "local",
        "sheltered"
    ],
    "wof:name":"Ravensfield Court Sheltered Housing",
    "wof:placetype":"venue"
},
  "geometry": {"coordinates":[0.49154,51.571182],"type":"Point"}
}