{
  "type": "Feature",
  "properties": {
    "iso:country":"GB",
    "sg:address":"23 Broad St",
    "sg:city":"Newent",
    "sg:classifiers":[
        {
            "category":"Home & Garden",
            "subcategory":"Household Appliances",
            "type":"Retail Goods"
        }
    ],
    "sg:phone":"+44 1531 822460",
    "sg:postcode":"GL18 1AQ",
    "sg:province":"Gloucestershire",
    "sg:tags":[
        "electrical",
        "domestic"
    ],
    "wof:name":"Newent Pine",
    "wof:placetype":"venue"
},
  "geometry": {"coordinates":[-2.405092001,51.9304885864],"type":"Point"}
}