{
  "type": "Feature",
  "properties": {
    "addr:full":"6 The Maltings, Weavering Maidstone Kent ME14 5UF",
    "addr:housenumber":"6",
    "addr:postcode":"me14 5uf",
    "addr:street":"The Maltings",
    "iso:country":"GB",
    "sg:address":"6 The Maltings, Weavering",
    "sg:city":"Maidstone",
    "sg:classifiers":[
        {
            "category":"Shopping",
            "subcategory":"Hobbies, Toys, & Games",
            "type":"Retail Goods"
        }
    ],
    "sg:postcode":"ME14 5UF",
    "sg:province":"Kent",
    "sg:tags":[
        "house",
        "dolls'",
        "doll"
    ],
    "wof:name":"Kent Garden Costume Dolls",
    "wof:placetype":"venue"
},
  "geometry": {"coordinates":[0.55752,51.274261],"type":"Point"}
}