{
  "type": "Feature",
  "properties": {
    "addr:full":"Unit 5 The Cuckoo Bridge Retail Dumfries Dumfries and Galloway DG2 9BF",
    "addr:housenumber":"unit 5",
    "addr:postcode":"dg2 9bf",
    "addr:street":"The Cuckoo Bridge",
    "iso:country":"GB",
    "sg:address":"Unit 5 The Cuckoo Bridge Retail",
    "sg:city":"Dumfries",
    "sg:classifiers":[
        {
            "category":"Home & Garden",
            "subcategory":"Furniture",
            "type":"Retail Goods"
        }
    ],
    "sg:phone":"+44 1387 264784",
    "sg:postcode":"DG2 9BF",
    "sg:province":"Dumfries and Galloway",
    "wof:name":"D P Furniture Express",
    "wof:placetype":"venue"
},
  "geometry": {"coordinates":[-3.6257300377,55.076499939],"type":"Point"}
}