{
  "type": "Feature",
  "properties": {
    "addr:full":"Unit 21, 31 Rushworth Street London Greater London SE1 0RB",
    "addr:housenumber":"unit;31",
    "addr:postcode":"se1 0rb",
    "addr:street":"Rushworth Street",
    "iso:country":"GB",
    "sg:address":"Unit 21, 31 Rushworth Street",
    "sg:city":"London",
    "sg:classifiers":[
        {
            "category":"Communications",
            "type":"Services"
        }
    ],
    "sg:phone":"+44 20 7803 4111",
    "sg:postcode":"SE1 0RB",
    "sg:province":"Greater London",
    "sg:tags":[
        "telecommunication"
    ],
    "wof:name":"District Maintenance Ltd.",
    "wof:placetype":"venue"
},
  "geometry": {"coordinates":[-0.102369003,51.5014610291],"type":"Point"}
}