{
  "type": "Feature",
  "properties": {
    "iso:country":"GB",
    "sg:address":"15 Fore Street",
    "sg:city":"Fowey",
    "sg:classifiers":[
        {
            "category":"Food & Beverages",
            "subcategory":"Candy",
            "type":"Retail Goods"
        }
    ],
    "sg:postcode":"PL23 1AH",
    "sg:province":"Cornwall",
    "sg:tags":[
        "confectioner"
    ],
    "wof:name":"Middleton's",
    "wof:placetype":"venue"
},
  "geometry": {"coordinates":[-4.634812,50.335873],"type":"Point"}
}