{
  "type": "Feature",
  "properties": {
    "iso:country":"GB",
    "sg:address":"16a West Street, Portchester",
    "sg:city":"Fareham",
    "sg:classifiers":[
        {
            "category":"Shopping",
            "subcategory":"Florist",
            "type":"Retail Goods"
        }
    ],
    "sg:phone":"+44 23 9237 2720",
    "sg:postcode":"PO16 9UZ",
    "sg:province":"Hampshire",
    "wof:name":"The Flower Studio",
    "wof:placetype":"venue"
},
  "geometry": {"coordinates":[-1.127939,50.846069],"type":"Point"}
}