{
  "type": "Feature",
  "properties": {
    "iso:country":"GB",
    "sg:address":"Bingley Rd",
    "sg:city":"Hoddesdon",
    "sg:classifiers":[
        {
            "category":"Home & Garden",
            "subcategory":"Household Appliances",
            "type":"Retail Goods"
        }
    ],
    "sg:phone":"+44 1992 446688",
    "sg:postcode":"EN11 0NX",
    "sg:province":"Essex",
    "sg:tags":[
        "refrigeration",
        "air conditioning"
    ],
    "wof:name":"Denco Ltd",
    "wof:placetype":"venue"
},
  "geometry": {"coordinates":[0.000113,51.760059],"type":"Point"}
}