{
  "type": "Feature",
  "properties": {
    "iso:country":"GB",
    "sg:address":"22-24 Carters Green",
    "sg:city":"West Bromwich",
    "sg:classifiers":[
        {
            "category":"Professional",
            "subcategory":"Computer Services",
            "type":"Services"
        }
    ],
    "sg:phone":"+44 121 525 2526",
    "sg:postcode":"B70 9LW",
    "sg:province":"West Midlands",
    "sg:tags":[
        "system",
        "software"
    ],
    "wof:name":"C-green Systems",
    "wof:placetype":"venue"
},
  "geometry": {"coordinates":[-2.0041539669,52.5239944458],"type":"Point"}
}