{
  "type": "Feature",
  "properties": {
    "addr:full":"Unit 2 Pym St Centre Leeds West Yorkshire LS10 1PG",
    "addr:housenumber":"unit 2",
    "addr:postcode":"ls10 1pg",
    "addr:street":"Pym St",
    "iso:country":"GB",
    "sg:address":"Unit 2 Pym St Centre",
    "sg:city":"Leeds",
    "sg:classifiers":[
        {
            "category":"Retail",
            "subcategory":"Repair Shop",
            "type":"Services"
        }
    ],
    "sg:phone":"+44 113 244 5353",
    "sg:postcode":"LS10 1PG",
    "sg:province":"West Yorkshire",
    "sg:tags":[
        "maintenance"
    ],
    "wof:name":"Inspace Property Services Ltd.",
    "wof:placetype":"venue"
},
  "geometry": {"coordinates":[-1.5311150551,53.7857284546],"type":"Point"}
}