{
  "type": "Feature",
  "properties": {
    "addr:full":"42 Church Road Southport Lancashire PR9 8ET",
    "addr:housenumber":"42",
    "addr:postcode":"pr9 8et",
    "addr:street":"Church Road",
    "iso:country":"GB",
    "sg:address":"42 Church Road",
    "sg:city":"Southport",
    "sg:classifiers":[
        {
            "category":"Food & Beverages",
            "subcategory":"Supermarket",
            "type":"Retail Goods"
        },
        {
            "category":"Food & Beverages",
            "subcategory":"Groceries & Convenience Stores",
            "type":"Retail Goods"
        }
    ],
    "sg:phone":"+44 1704 227070",
    "sg:postcode":"PR9 8ET",
    "sg:province":"Lancashire",
    "wof:name":"United Co-Operatives",
    "wof:placetype":"venue"
},
  "geometry": {"coordinates":[-2.9219110012,53.6816368103],"type":"Point"}
}