{
  "type": "Feature",
  "properties": {
    "iso:country":"GB",
    "sg:address":"Church Road",
    "sg:city":"Basildon",
    "sg:classifiers":[
        {
            "category":"Social Services",
            "type":"Services"
        },
        {
            "category":"Government",
            "subcategory":"Office",
            "type":"Public Place"
        }
    ],
    "sg:phone":"+44 1268 521898",
    "sg:postcode":"SS14 2EX",
    "sg:province":"Essex",
    "sg:tags":[
        "local"
    ],
    "wof:name":"Willowbrook Family Centre",
    "wof:placetype":"venue"
},
  "geometry": {"coordinates":[0.472365,51.580231],"type":"Point"}
}