{
  "type": "Feature",
  "properties": {
    "iso:country":"GB",
    "sg:address":"106 Ashdown Ho, London Gatwick Airport",
    "sg:city":"Gatwick",
    "sg:classifiers":[
        {
            "category":"Bus Charters",
            "type":"Transportation"
        }
    ],
    "sg:phone":"+44 1293 507099",
    "sg:postcode":"RH6 0JH",
    "sg:province":"Surrey",
    "sg:tags":[
        "coach"
    ],
    "wof:name":"Speedlink Airport Services",
    "wof:placetype":"venue"
},
  "geometry": {"coordinates":[-0.172354,51.161774],"type":"Point"}
}