{
  "type": "Feature",
  "properties": {
    "addr:full":"17 Lexby Rd Southampton Hampshire SO40 9HB",
    "addr:housenumber":"17",
    "addr:postcode":"so40 9hb",
    "addr:street":"Lexby Rd",
    "iso:country":"GB",
    "sg:address":"17 Lexby Rd",
    "sg:city":"Southampton",
    "sg:classifiers":[
        {
            "category":"Building & Trades",
            "subcategory":"Landscaping Services",
            "type":"Services"
        }
    ],
    "sg:phone":"+44 23 8066 0605",
    "sg:postcode":"SO40 9HB",
    "sg:province":"Hampshire",
    "sg:tags":[
        "gardening"
    ],
    "wof:name":"Sherred & Cooper",
    "wof:placetype":"venue"
},
  "geometry": {"coordinates":[-1.483072,50.911705],"type":"Point"}
}