{
  "type": "Feature",
  "properties": {
    "addr:full":"Marlborough House Faringdon Oxfordshire SN7 7JQ",
    "addr:postcode":"sn7 7jq",
    "addr:street":"Faringdon",
    "iso:country":"GB",
    "sg:address":"Marlborough House",
    "sg:city":"Faringdon",
    "sg:classifiers":[
        {
            "category":"Building & Trades",
            "subcategory":"Construction",
            "type":"Services"
        }
    ],
    "sg:phone":"+44 1367 240105",
    "sg:postcode":"SN7 7JQ",
    "sg:province":"Oxfordshire",
    "sg:tags":[
        "builder"
    ],
    "wof:name":"Russell Spinage Ltd.",
    "wof:placetype":"venue"
},
  "geometry": {"coordinates":[-1.586654,51.65617],"type":"Point"}
}