{
  "type": "Feature",
  "properties": {
    "iso:country":"GB",
    "sg:address":"573 Cheetham Hill Road",
    "sg:city":"Manchester",
    "sg:classifiers":[
        {
            "category":"Food & Beverages",
            "subcategory":"Groceries & Convenience Stores",
            "type":"Retail Goods"
        }
    ],
    "sg:phone":"+44 161 740 8362",
    "sg:postcode":"M8 7JE",
    "sg:province":"Greater Manchester",
    "wof:name":"Ihjaz Khaliq & K Hedayatt",
    "wof:placetype":"venue"
},
  "geometry": {"coordinates":[-2.244717,53.511307],"type":"Point"}
}