{
  "type": "Feature",
  "properties": {
    "addr:full":"24a Lichfield Street Tamworth Staffordshire B79 7QE",
    "addr:housenumber":"24a",
    "addr:postcode":"b79 7qe",
    "addr:street":"Lichfield Street",
    "iso:country":"GB",
    "sg:address":"24a Lichfield Street",
    "sg:city":"Tamworth",
    "sg:classifiers":[
        {
            "category":"Health Services",
            "subcategory":"Dentist",
            "type":"Services"
        }
    ],
    "sg:phone":"+44 1827 64307",
    "sg:postcode":"B79 7QE",
    "sg:province":"Staffordshire",
    "wof:name":"Brickett & Brotherton",
    "wof:placetype":"venue"
},
  "geometry": {"coordinates":[-1.7046289444,52.6341781616],"type":"Point"}
}