{
  "type": "Feature",
  "properties": {
    "addr:full":"Kingfisher Ho, 7 High Green Cambridge Cambridgeshire CB2 5EG",
    "addr:housenumber":"7",
    "addr:postcode":"cb2 5eg",
    "addr:street":"High Green",
    "iso:country":"GB",
    "sg:address":"Kingfisher Ho, 7 High Green",
    "sg:city":"Cambridge",
    "sg:classifiers":[
        {
            "category":"Arena",
            "subcategory":"Sports Club",
            "type":"Entertainment"
        }
    ],
    "sg:phone":"+44 1223 847379",
    "sg:postcode":"CB2 5EG",
    "sg:province":"Cambridgeshire",
    "wof:name":"Cambridge Newmarket Polo Club",
    "wof:placetype":"venue"
},
  "geometry": {"coordinates":[0.13562,52.1516],"type":"Point"}
}