{
  "type": "Feature",
  "properties": {
    "addr:full":"15 Downing Crescent Scunthorpe Lincolnshire DN16 3LS",
    "addr:housenumber":"15",
    "addr:postcode":"dn16 3ls",
    "addr:street":"Downing Crescent",
    "iso:country":"GB",
    "sg:address":"15 Downing Crescent",
    "sg:city":"Scunthorpe",
    "sg:classifiers":[
        {
            "category":"Banks & Credit Unions",
            "subcategory":"Bureau De Change",
            "type":"Services"
        }
    ],
    "sg:phone":"+44 1724 860541",
    "sg:postcode":"DN16 3LS",
    "sg:province":"Lincolnshire",
    "sg:tags":[
        "town",
        "consultant",
        "planning"
    ],
    "wof:name":"Enfortec Associates",
    "wof:placetype":"venue"
},
  "geometry": {"coordinates":[-0.653509,53.556267],"type":"Point"}
}