{
  "type": "Feature",
  "properties": {
    "iso:country":"GB",
    "sg:address":"26 Dulais Road",
    "sg:city":"Swansea",
    "sg:classifiers":[
        {
            "category":"Food & Beverages",
            "subcategory":"Meat & Fish",
            "type":"Retail Goods"
        }
    ],
    "sg:phone":"+44 1792 882328",
    "sg:postcode":"SA4 8RH",
    "sg:province":"Carmarthenshire",
    "sg:tags":[
        "chip"
    ],
    "wof:name":"Wilsons Fish Bar",
    "wof:placetype":"venue"
},
  "geometry": {"coordinates":[-4.0379757881,51.7148895264],"type":"Point"}
}