{
  "type": "Feature",
  "properties": {
    "iso:country":"GB",
    "sg:address":"10 Eastwood Clo",
    "sg:city":"South Woodford",
    "sg:classifiers":[
        {
            "category":"Shopping",
            "subcategory":"Pharmacy",
            "type":"Retail Goods"
        }
    ],
    "sg:phone":"+44 20 8532 9595",
    "sg:postcode":"E18 1BX",
    "sg:province":"Greater London",
    "sg:tags":[
        "medical"
    ],
    "wof:name":"Body Clock Health Care",
    "wof:placetype":"venue"
},
  "geometry": {"coordinates":[0.0262650009,51.5934715271],"type":"Point"}
}