{
  "type": "Feature",
  "properties": {
    "iso:country":"GB",
    "sg:address":"Ashby Road Central, Shepsted",
    "sg:city":"Loughborough",
    "sg:classifiers":[
        {
            "category":"Autos & Motor Vehicles",
            "subcategory":"Automobile Sales",
            "type":"Retail Goods"
        }
    ],
    "sg:phone":"+44 1509 502121",
    "sg:postcode":"LE12 9EP",
    "sg:province":"Leicestershire",
    "sg:tags":[
        "commercial"
    ],
    "wof:name":"Lex Commercials Ltd.",
    "wof:placetype":"venue"
},
  "geometry": {"coordinates":[-1.3348139524,52.761806488],"type":"Point"}
}