{
  "type": "Feature",
  "properties": {
    "addr:full":"4 Market Square Horsham West Sussex RH12 1EU",
    "addr:housenumber":"4",
    "addr:postcode":"rh12 1eu",
    "addr:street":"Market Square",
    "iso:country":"GB",
    "sg:address":"4 Market Square",
    "sg:city":"Horsham",
    "sg:classifiers":[
        {
            "category":"Shopping",
            "subcategory":"Clothing, Apparel, & Fashions",
            "type":"Retail Goods"
        }
    ],
    "sg:phone":"+44 1403 254773",
    "sg:postcode":"RH12 1EU",
    "sg:province":"West Sussex",
    "sg:tags":[
        "shop"
    ],
    "wof:name":"Lady Fayre",
    "wof:placetype":"venue"
},
  "geometry": {"coordinates":[-0.328966,51.061352],"type":"Point"}
}