{
  "type": "Feature",
  "properties": {
    "iso:country":"GB",
    "sg:address":"2nd Floor",
    "sg:city":"London",
    "sg:classifiers":[
        {
            "category":"Banks & Credit Unions",
            "subcategory":"Bank",
            "type":"Services"
        }
    ],
    "sg:phone":"+44 20 7577 2187",
    "sg:postcode":"EC2M 2SX",
    "sg:province":"Greater London",
    "wof:name":"The Bank of Tokyo-Mitsubishi Ltd.",
    "wof:placetype":"venue"
},
  "geometry": {"coordinates":[-0.084517,51.516514],"type":"Point"}
}