{
  "type": "Feature",
  "properties": {
    "addr:full":"18 Sandgate Rd Folkestone Kent CT20 1DP",
    "addr:housenumber":"18",
    "addr:postcode":"ct20 1dp",
    "addr:street":"Sandgate Rd",
    "iso:country":"GB",
    "sg:address":"18 Sandgate Rd",
    "sg:city":"Folkestone",
    "sg:classifiers":[
        {
            "category":"Food & Beverages",
            "subcategory":"Bakery",
            "type":"Retail Goods"
        }
    ],
    "sg:phone":"+44 1303 259847",
    "sg:postcode":"CT20 1DP",
    "sg:province":"Kent",
    "sg:tags":[
        "baker"
    ],
    "wof:name":"Clarks Bakery",
    "wof:placetype":"venue"
},
  "geometry": {"coordinates":[1.153538,51.075951],"type":"Point"}
}