{
  "type": "Feature",
  "properties": {
    "addr:full":"23 High St Sheffield Derbyshire S31 0TT",
    "addr:housenumber":"23",
    "addr:postcode":"s31 0tt",
    "addr:street":"High St",
    "iso:country":"GB",
    "sg:address":"23 High St",
    "sg:city":"Sheffield",
    "sg:classifiers":[
        {
            "category":"Food & Beverages",
            "subcategory":"Fruits & Vegetables",
            "type":"Retail Goods"
        }
    ],
    "sg:phone":"+44 114 287 6646",
    "sg:postcode":"S31 0TT",
    "sg:province":"Derbyshire",
    "sg:tags":[
        "greengrocer"
    ],
    "wof:name":"K Tiler",
    "wof:placetype":"venue"
},
  "geometry": {"coordinates":[-1.4667420387,53.3829650879],"type":"Point"}
}