{
  "type": "Feature",
  "properties": {
    "addr:full":"Trimpley Lane, Shatterford Bewdley Shropshire DY12 1RE",
    "addr:postcode":"dy12 1re",
    "addr:street":"Trimpley Lane",
    "iso:country":"GB",
    "sg:address":"Trimpley Lane, Shatterford",
    "sg:city":"Bewdley",
    "sg:classifiers":[
        {
            "category":"Organizations",
            "subcategory":"Non-profit Organization",
            "type":"Services"
        }
    ],
    "sg:phone":"+44 1299 861561",
    "sg:postcode":"DY12 1RE",
    "sg:province":"Shropshire",
    "sg:tags":[
        "organisation",
        "voluntary",
        "charity"
    ],
    "wof:name":"Anthroposophical Medical Trust",
    "wof:placetype":"venue"
},
  "geometry": {"coordinates":[-2.308338,52.427879],"type":"Point"}
}