{
  "type": "Feature",
  "properties": {
    "addr:full":"96-98 Windsor Rd Torquay Devon TQ1 1SU",
    "addr:housenumber":"96-98",
    "addr:postcode":"tq1 1su",
    "addr:street":"Windsor Rd",
    "iso:country":"GB",
    "sg:address":"96-98 Windsor Rd",
    "sg:city":"Torquay",
    "sg:classifiers":[
        {
            "category":"Social Services",
            "subcategory":"Retirement Home",
            "type":"Services"
        }
    ],
    "sg:phone":"+44 1803 323301",
    "sg:postcode":"TQ1 1SU",
    "sg:province":"Devon",
    "sg:tags":[
        "residential",
        "care"
    ],
    "wof:name":"Redvers",
    "wof:placetype":"venue"
},
  "geometry": {"coordinates":[-3.520979,50.474529],"type":"Point"}
}