{
  "type": "Feature",
  "properties": {
    "addr:full":"298 High St Croydon Surrey CR0 1NG",
    "addr:housenumber":"298",
    "addr:postcode":"cr0 1ng",
    "addr:street":"High St",
    "iso:country":"GB",
    "sg:address":"298 High St",
    "sg:city":"Croydon",
    "sg:classifiers":[
        {
            "category":"Government",
            "subcategory":"Post Office",
            "type":"Public Place"
        }
    ],
    "sg:phone":"+44 20 8686 8127",
    "sg:postcode":"CR0 1NG",
    "sg:province":"Surrey",
    "wof:name":"Sub Post Office The",
    "wof:placetype":"venue"
},
  "geometry": {"coordinates":[-0.0994969979,51.3681945801],"type":"Point"}
}