{
  "type": "Feature",
  "properties": {
    "addr:full":"Milton Damerel Holsworthy Cornwall EX22 7LL",
    "addr:housenumber":"damerel",
    "addr:postcode":"ex22 7ll",
    "iso:country":"GB",
    "sg:address":"Milton Damerel",
    "sg:city":"Holsworthy",
    "sg:classifiers":[
        {
            "category":"Travel",
            "subcategory":"Hotels & Motels",
            "type":"Entertainment"
        }
    ],
    "sg:phone":"+44 1409 261481",
    "sg:postcode":"EX22 7LL",
    "sg:province":"Cornwall",
    "wof:name":"Woodford Bridge Hotel & Country Club",
    "wof:placetype":"venue"
},
  "geometry": {"coordinates":[-4.3349227905,50.8490638733],"type":"Point"}
}