{
  "type": "Feature",
  "properties": {
    "iso:country":"GB",
    "sg:address":"6a Main Street",
    "sg:city":"Bonnybridge",
    "sg:classifiers":[
        {
            "category":"Personal",
            "subcategory":"Beauty Salon",
            "type":"Services"
        },
        {
            "category":"Personal",
            "subcategory":"Barber",
            "type":"Services"
        }
    ],
    "sg:phone":"+44 1324 815877",
    "sg:postcode":"FK4 1BT",
    "sg:province":"Falkirk",
    "sg:tags":[
        "unisex",
        "hairdresser"
    ],
    "wof:name":"Profile Hairdressing",
    "wof:placetype":"venue"
},
  "geometry": {"coordinates":[-3.885616,56.00148],"type":"Point"}
}