{
  "type": "Feature",
  "properties": {
    "addr:full":"House Of Expressions Building, Forward Drive Harrow Greater London HA3 8NT",
    "addr:postcode":"ha3 8nt",
    "addr:street":"Forward Drive",
    "iso:country":"GB",
    "sg:address":"House Of Expressions Building, Forward Drive",
    "sg:city":"Harrow",
    "sg:classifiers":[
        {
            "category":"Shopping",
            "subcategory":"Clothing, Apparel, & Fashions",
            "type":"Retail Goods"
        }
    ],
    "sg:phone":"+44 20 8909 2713",
    "sg:postcode":"HA3 8NT",
    "sg:province":"Greater London",
    "sg:tags":[
        "staff",
        "wear",
        "uniform"
    ],
    "wof:name":"House of Embroidery Ltd.",
    "wof:placetype":"venue"
},
  "geometry": {"coordinates":[-0.3279399872,51.5902900696],"type":"Point"}
}