{
  "type": "Feature",
  "properties": {
    "addr:full":"Unit 11 Regents Walk, Newerne Street Lydney Gloucestershire GL15 5RF",
    "addr:housenumber":"unit 11",
    "addr:postcode":"gl15 5rf",
    "addr:street":"Regents Walk Newerne Street",
    "iso:country":"GB",
    "sg:address":"Unit 11 Regents Walk, Newerne Street",
    "sg:city":"Lydney",
    "sg:classifiers":[
        {
            "category":"Building & Trades",
            "subcategory":"Construction",
            "type":"Services"
        }
    ],
    "sg:phone":"+44 1594 844665",
    "sg:postcode":"GL15 5RF",
    "sg:province":"Gloucestershire",
    "sg:tags":[
        "builder"
    ],
    "wof:name":"F W Johnson Ltd.",
    "wof:placetype":"venue"
},
  "geometry": {"coordinates":[-2.535819,51.724491],"type":"Point"}
}