{
  "type": "Feature",
  "properties": {
    "addr:full":"2 Green La Belper Derbyshire DE56 1BZ",
    "addr:housenumber":"2",
    "addr:postcode":"de56 1bz",
    "addr:street":"Green La Belper",
    "iso:country":"GB",
    "sg:address":"2 Green La",
    "sg:city":"Belper",
    "sg:classifiers":[
        {
            "category":"Health Services",
            "subcategory":"Doctor",
            "type":"Services"
        }
    ],
    "sg:phone":"+44 1773 823521",
    "sg:postcode":"DE56 1BZ",
    "sg:province":"Derbyshire",
    "sg:tags":[
        "practitioners"
    ],
    "wof:name":"Fairweather, J E",
    "wof:placetype":"venue"
},
  "geometry": {"coordinates":[-1.4798469543,53.0235214233],"type":"Point"}
}