{
  "type": "Feature",
  "properties": {
    "addr:full":"Icknield Square, Ladywood Birmingham West Midlands B16 0PP",
    "addr:postcode":"b16 0pp",
    "addr:street":"Icknield Square",
    "iso:country":"GB",
    "sg:address":"Icknield Square, Ladywood",
    "sg:city":"Birmingham",
    "sg:classifiers":[
        {
            "category":"Autos & Motor Vehicles",
            "subcategory":"Auto Supplies",
            "type":"Retail Goods"
        }
    ],
    "sg:phone":"+44 121 454 4567",
    "sg:postcode":"B16 0PP",
    "sg:province":"West Midlands",
    "sg:tags":[
        "electric"
    ],
    "wof:name":"Peebles Field Services",
    "wof:placetype":"venue"
},
  "geometry": {"coordinates":[-1.9269069433,52.4816093445],"type":"Point"}
}