{
  "type": "Feature",
  "properties": {
    "addr:full":"264 Radford Road, Hyson Grn Nottingham Nottinghamshire NG7 5GN",
    "addr:housenumber":"264",
    "addr:postcode":"ng7 5gn",
    "addr:street":"Radford Road Hyson Grn",
    "iso:country":"GB",
    "sg:address":"264 Radford Road, Hyson Grn",
    "sg:city":"Nottingham",
    "sg:classifiers":[
        {
            "category":"Shopping",
            "subcategory":"Florist",
            "type":"Retail Goods"
        }
    ],
    "sg:postcode":"NG7 5GN",
    "sg:province":"Nottinghamshire",
    "wof:name":"Karen's Flower Kabin",
    "wof:placetype":"venue"
},
  "geometry": {"coordinates":[-1.1728689671,52.9686775208],"type":"Point"}
}