{
  "type": "Feature",
  "properties": {
    "addr:full":"1034 Yardley Wood Road Birmingham West Midlands B14 4BW",
    "addr:housenumber":"1034",
    "addr:postcode":"b14 4bw",
    "addr:street":"Yardley Wood Road",
    "iso:country":"GB",
    "sg:address":"1034 Yardley Wood Road",
    "sg:city":"Birmingham",
    "sg:classifiers":[
        {
            "category":"Food & Beverages",
            "subcategory":"Meat & Fish",
            "type":"Retail Goods"
        }
    ],
    "sg:postcode":"B14 4BW",
    "sg:province":"West Midlands",
    "sg:tags":[
        "butcher"
    ],
    "wof:name":"R Neal Meats",
    "wof:placetype":"venue"
},
  "geometry": {"coordinates":[-1.869924,52.41465],"type":"Point"}
}