{
  "type": "Feature",
  "properties": {
    "iso:country":"GB",
    "sg:address":"113 Weybourne Rd",
    "sg:city":"Farnham",
    "sg:classifiers":[
        {
            "category":"Autos & Motor Vehicles",
            "subcategory":"Motorcycle Sales",
            "type":"Retail Goods"
        }
    ],
    "sg:postcode":"GU9 9EZ",
    "sg:province":"Surrey",
    "sg:tags":[
        "chauffeur",
        "driven",
        "car"
    ],
    "wof:name":"Creagh,Frederick,",
    "wof:placetype":"venue"
},
  "geometry": {"coordinates":[-0.772015,51.238216],"type":"Point"}
}