{
  "type": "Feature",
  "properties": {
    "addr:full":"Hollygrove Barn Wigpool, Stenders Mitcheldean Gloucestershire GL17 0JE",
    "addr:postcode":"gl17 0je",
    "addr:street":"Wigpool",
    "iso:country":"GB",
    "sg:address":"Hollygrove Barn Wigpool, Stenders",
    "sg:city":"Mitcheldean",
    "sg:classifiers":[
        {
            "category":"Manufacturing",
            "subcategory":"Lumber",
            "type":"Manufacturing & Wholesale Goods"
        }
    ],
    "sg:postcode":"GL17 0JE",
    "sg:province":"Gloucestershire",
    "sg:tags":[
        "importer",
        "merchants",
        "agent",
        "timber"
    ],
    "wof:name":"Roger Jim Reed",
    "wof:placetype":"venue"
},
  "geometry": {"coordinates":[-2.4890880585,51.8653831482],"type":"Point"}
}