{
  "type": "Feature",
  "properties": {
    "addr:full":"51 Yew Tree Rd, Witley Godalming Surrey GU8 5RQ",
    "addr:housenumber":"51",
    "addr:postcode":"gu8 5rq",
    "addr:street":"Yew Tree Rd",
    "iso:country":"GB",
    "sg:address":"51 Yew Tree Rd, Witley",
    "sg:city":"Godalming",
    "sg:classifiers":[
        {
            "category":"Real Estate",
            "subcategory":"Surveying",
            "type":"Services"
        }
    ],
    "sg:phone":"+44 1483 421191",
    "sg:postcode":"GU8 5RQ",
    "sg:province":"Surrey",
    "sg:tags":[
        "surveyor",
        "quantity"
    ],
    "wof:name":"Howard George Associates",
    "wof:placetype":"venue"
},
  "geometry": {"coordinates":[-0.657806,51.159367],"type":"Point"}
}