{
  "type": "Feature",
  "properties": {
    "addr:full":"91 Northfield Road Coventry West Midlands CV1 2BQ",
    "addr:housenumber":"91",
    "addr:postcode":"cv1 2bq",
    "addr:street":"Northfield Road",
    "iso:country":"GB",
    "sg:address":"91 Northfield Road",
    "sg:city":"Coventry",
    "sg:classifiers":[
        {
            "category":"Cinema",
            "subcategory":"Movie Rental",
            "type":"Entertainment"
        }
    ],
    "sg:phone":"+44 24 7625 6972",
    "sg:postcode":"CV1 2BQ",
    "sg:province":"West Midlands",
    "sg:tags":[
        "video",
        "library"
    ],
    "wof:name":"Lumiere Group",
    "wof:placetype":"venue"
},
  "geometry": {"coordinates":[-1.4941999912,52.4042167664],"type":"Point"}
}