{
  "type": "Feature",
  "properties": {
    "iso:country":"GB",
    "sg:address":"103 High Street",
    "sg:city":"Broadstairs",
    "sg:classifiers":[
        {
            "category":"Professional",
            "subcategory":"Lawyer & Legal Services",
            "type":"Services"
        }
    ],
    "sg:postcode":"CT10 1JS",
    "sg:province":"Kent",
    "sg:tags":[
        "solicitor"
    ],
    "wof:name":"Barnes Marsland (Solicitors) Ltd.",
    "wof:placetype":"venue"
},
  "geometry": {"coordinates":[1.435869,51.359642],"type":"Point"}
}