{
  "type": "Feature",
  "properties": {
    "iso:country":"GB",
    "sg:address":"39 The Pines, Laindon",
    "sg:city":"Basildon",
    "sg:classifiers":[
        {
            "category":"Communications",
            "type":"Services"
        }
    ],
    "sg:phone":"+44 1268 459200",
    "sg:postcode":"SS15 4DW",
    "sg:province":"Essex",
    "sg:tags":[
        "data",
        "network"
    ],
    "wof:name":"Majestic Data Services Ltd.",
    "wof:placetype":"venue"
},
  "geometry": {"coordinates":[0.4293,51.585598],"type":"Point"}
}