{
  "type": "Feature",
  "properties": {
    "iso:country":"GB",
    "sg:address":"East Main Street, Whitburn",
    "sg:city":"Bathgate",
    "sg:classifiers":[
        {
            "category":"Travel",
            "subcategory":"Hotels & Motels",
            "type":"Entertainment"
        }
    ],
    "sg:phone":"+44 1501 740818",
    "sg:postcode":"EH47 0JU",
    "sg:province":"North Lanarkshire",
    "wof:name":"Hilcroft Hotel",
    "wof:placetype":"venue"
},
  "geometry": {"coordinates":[-3.689629,55.86607],"type":"Point"}
}