{
  "type": "Feature",
  "properties": {
    "iso:country":"GB",
    "sg:address":"57-58 Dock Street",
    "sg:city":"Dundee",
    "sg:classifiers":[
        {
            "category":"Bars & Pubs",
            "subcategory":"Wine Bar",
            "type":"Food & Drink"
        }
    ],
    "sg:phone":"+44 1382 227728",
    "sg:postcode":"DD1 3DU",
    "sg:province":"Dundee City",
    "wof:name":"A G B's",
    "wof:placetype":"venue"
},
  "geometry": {"coordinates":[-2.965264,56.461281],"type":"Point"}
}