{
  "type": "Feature",
  "properties": {
    "addr:full":"Unit 25 Chalwyn Indstl Est, St. Clements Rd Poole Dorset BH15 3PE",
    "addr:housenumber":"unit 25",
    "addr:postcode":"bh15 3pe",
    "addr:street":"Indstl Est St. Clements Rd",
    "iso:country":"GB",
    "sg:address":"Unit 25 Chalwyn Indstl Est, St. Clements Rd",
    "sg:city":"Poole",
    "sg:classifiers":[
        {
            "category":"Manufacturing",
            "subcategory":"Rubber & Plastics",
            "type":"Manufacturing & Wholesale Goods"
        }
    ],
    "sg:postcode":"BH15 3PE",
    "sg:province":"Dorset",
    "sg:tags":[
        "product"
    ],
    "wof:name":"Bournemouth & Poole Windows",
    "wof:placetype":"venue"
},
  "geometry": {"coordinates":[-1.986739,50.714485],"type":"Point"}
}