{
  "type": "Feature",
  "properties": {
    "addr:full":"1 Navigator Court Stockton-on-tees Durham TS18 3TQ",
    "addr:housenumber":"1",
    "addr:postcode":"ts18 3tq",
    "addr:street":"Navigator Court",
    "iso:country":"GB",
    "sg:address":"1 Navigator Court",
    "sg:city":"Stockton-on-tees",
    "sg:classifiers":[
        {
            "category":"Autos & Motor Vehicles",
            "subcategory":"Automobile Sales",
            "type":"Retail Goods"
        }
    ],
    "sg:phone":"+44 1642 607788",
    "sg:postcode":"TS18 3TQ",
    "sg:province":"Durham",
    "sg:tags":[
        "car"
    ],
    "wof:name":"G T C",
    "wof:placetype":"venue"
},
  "geometry": {"coordinates":[-1.3204749823,54.5479888916],"type":"Point"}
}