{
  "type": "Feature",
  "properties": {
    "addr:full":"88 Trevino Drive Leicester Leicestershire LE4 7PH",
    "addr:housenumber":"88",
    "addr:postcode":"le4 7ph",
    "addr:street":"Trevino Drive",
    "iso:country":"GB",
    "sg:address":"88 Trevino Drive",
    "sg:city":"Leicester",
    "sg:classifiers":[
        {
            "category":"Manufacturing",
            "subcategory":"Textiles",
            "type":"Manufacturing & Wholesale Goods"
        }
    ],
    "sg:phone":"+44 116 224 6661",
    "sg:postcode":"LE4 7PH",
    "sg:province":"Leicestershire",
    "sg:tags":[
        "knitwear"
    ],
    "wof:name":"Jersey Knit Ltd.",
    "wof:placetype":"venue"
},
  "geometry": {"coordinates":[-1.0936939716,52.6659088135],"type":"Point"}
}