{
  "type": "Feature",
  "properties": {
    "iso:country":"GB",
    "sg:address":"125 Argyll Street",
    "sg:city":"Dunoon",
    "sg:classifiers":[
        {
            "category":"Shopping",
            "subcategory":"Jewelry",
            "type":"Retail Goods"
        },
        {
            "category":"Shopping",
            "subcategory":"Comic Books",
            "type":"Retail Goods"
        }
    ],
    "sg:phone":"+44 1369 706672",
    "sg:postcode":"PA23 7DD",
    "sg:province":"Argyll and Bute",
    "sg:tags":[
        "jeweller",
        "sale",
        "jewellery"
    ],
    "wof:name":"The Curiosity Shoppe",
    "wof:placetype":"venue"
},
  "geometry": {"coordinates":[-4.926568,55.949497],"type":"Point"}
}