{
  "type": "Feature",
  "properties": {
    "iso:country":"GB",
    "sg:address":"100 St Mary Street",
    "sg:city":"Weymouth",
    "sg:classifiers":[
        {
            "category":"Banks & Credit Unions",
            "subcategory":"Bank",
            "type":"Services"
        },
        {
            "category":"Banks & Credit Unions",
            "subcategory":"Financial Services",
            "type":"Services"
        }
    ],
    "sg:phone":"+44 1305 773424",
    "sg:postcode":"DT4 8NY",
    "sg:province":"Dorset",
    "sg:tags":[
        "building",
        "society"
    ],
    "wof:name":"WOOLWICH BUILDING SOCIETY",
    "wof:placetype":"venue"
},
  "geometry": {"coordinates":[-2.454092,50.61097],"type":"Point"}
}