{
  "type": "Feature",
  "properties": {
    "iso:country":"GB",
    "sg:address":"Stoke Mill, Mill Road, Sharnbrook",
    "sg:city":"Bedford",
    "sg:classifiers":[
        {
            "category":"Restaurant",
            "type":"Food & Drink"
        }
    ],
    "sg:phone":"+44 1234 781678",
    "sg:postcode":"MK44 1NP",
    "sg:province":"Bedfordshire",
    "wof:name":"Mill House Restaurant",
    "wof:placetype":"venue"
},
  "geometry": {"coordinates":[-0.544024,52.225994],"type":"Point"}
}