{
  "type": "Feature",
  "properties": {
    "addr:full":"60 Stoke Poges Lane Slough Berkshire SL1 3PD",
    "addr:housenumber":"60",
    "addr:postcode":"sl1 3pd",
    "addr:street":"Stoke Poges Lane",
    "iso:country":"GB",
    "sg:address":"60 Stoke Poges Lane",
    "sg:city":"Slough",
    "sg:classifiers":[
        {
            "category":"Health Services",
            "subcategory":"Doctor",
            "type":"Services"
        }
    ],
    "sg:phone":"+44 1753 535356",
    "sg:postcode":"SL1 3PD",
    "sg:province":"Berkshire",
    "sg:tags":[
        "practitioners"
    ],
    "wof:name":"Dr Satya Chaudhry",
    "wof:placetype":"venue"
},
  "geometry": {"coordinates":[-0.599893,51.518032],"type":"Point"}
}