{
  "type": "Feature",
  "properties": {
    "iso:country":"GB",
    "sg:address":"70 East End Road, Charlton Kings",
    "sg:city":"Cheltenham",
    "sg:classifiers":[
        {
            "category":"Professional",
            "subcategory":"Engineering",
            "type":"Services"
        }
    ],
    "sg:phone":"+44 1242 515587",
    "sg:postcode":"GL53 8QL",
    "sg:province":"Gloucestershire",
    "sg:tags":[
        "contractor",
        "electrical",
        "engineer"
    ],
    "wof:name":"N L Sherwood",
    "wof:placetype":"venue"
},
  "geometry": {"coordinates":[-2.0404169559,51.8823814392],"type":"Point"}
}