{
  "type": "Feature",
  "properties": {
    "addr:full":"138 Westgate Southwell Nottinghamshire NG25 0LT",
    "addr:housenumber":"138",
    "addr:postcode":"ng25 0lt",
    "addr:street":"Westgate Southwell",
    "iso:country":"GB",
    "sg:address":"138 Westgate",
    "sg:city":"Southwell",
    "sg:classifiers":[
        {
            "category":"Health Services",
            "subcategory":"Podiatrist",
            "type":"Services"
        }
    ],
    "sg:postcode":"NG25 0LT",
    "sg:province":"Nottinghamshire",
    "sg:tags":[
        "podiatrists",
        "chiropodist"
    ],
    "wof:name":"Arthur Wood",
    "wof:placetype":"venue"
},
  "geometry": {"coordinates":[-0.964784,53.075359],"type":"Point"}
}