{
  "type": "Feature",
  "properties": {
    "iso:country":"GB",
    "sg:address":"Hedleys, Hinton St Mary",
    "sg:city":"Sturminster Newton",
    "sg:classifiers":[
        {
            "category":"Building & Trades",
            "subcategory":"Landscaping Services",
            "type":"Services"
        }
    ],
    "sg:postcode":"DT10 1NA",
    "sg:province":"Dorset",
    "sg:tags":[
        "landscape",
        "contractor"
    ],
    "wof:name":"B J Plant Hire",
    "wof:placetype":"venue"
},
  "geometry": {"coordinates":[-2.305149,50.926624],"type":"Point"}
}