{
  "type": "Feature",
  "properties": {
    "addr:full":"40 High Street, Burringham Scunthorpe Lincolnshire DN17 3LY",
    "addr:housenumber":"40",
    "addr:postcode":"dn17 3ly",
    "addr:street":"High Street",
    "iso:country":"GB",
    "sg:address":"40 High Street, Burringham",
    "sg:city":"Scunthorpe",
    "sg:classifiers":[
        {
            "category":"Professional",
            "subcategory":"Engineering",
            "type":"Services"
        }
    ],
    "sg:postcode":"DN17 3LY",
    "sg:province":"Lincolnshire",
    "wof:name":"Spencers of Burringham",
    "wof:placetype":"venue"
},
  "geometry": {"coordinates":[-0.7370870113,53.5756874084],"type":"Point"}
}