{
  "type": "Feature",
  "properties": {
    "addr:full":"Rectory Farm, The Folly, Cold Ashton Chippenham Gloucestershire SN14 8JR",
    "addr:postcode":"sn14 8jr",
    "addr:street":"Rectory;The;Cold Ashton",
    "iso:country":"GB",
    "sg:address":"Rectory Farm, The Folly, Cold Ashton",
    "sg:city":"Chippenham",
    "sg:classifiers":[
        {
            "category":"Communications",
            "subcategory":"Film & Video Production",
            "type":"Services"
        }
    ],
    "sg:postcode":"SN14 8JR",
    "sg:province":"Gloucestershire",
    "sg:tags":[
        "recording",
        "studio"
    ],
    "wof:name":"Koh-San Recording Studios",
    "wof:placetype":"venue"
},
  "geometry": {"coordinates":[-2.360883,51.451927],"type":"Point"}
}