{
  "type": "Feature",
  "properties": {
    "addr:full":"71 Main Street Bingley West Yorkshire BD16 2JA",
    "addr:housenumber":"71",
    "addr:postcode":"bd16 2ja",
    "addr:street":"Main Street",
    "iso:country":"GB",
    "sg:address":"71 Main Street",
    "sg:city":"Bingley",
    "sg:classifiers":[
        {
            "category":"Shopping",
            "subcategory":"Jewelry",
            "type":"Retail Goods"
        },
        {
            "category":"Shopping",
            "subcategory":"Comic Books",
            "type":"Retail Goods"
        }
    ],
    "sg:phone":"+44 1274 562801",
    "sg:postcode":"BD16 2JA",
    "sg:province":"West Yorkshire",
    "sg:tags":[
        "jeweller",
        "sale",
        "jewellery"
    ],
    "wof:name":"Bingley Jewellery",
    "wof:placetype":"venue"
},
  "geometry": {"coordinates":[-1.8387999535,53.8493881226],"type":"Point"}
}