{
  "type": "Feature",
  "properties": {
    "iso:country":"GB",
    "sg:address":"Courthouse St",
    "sg:city":"Pontypridd",
    "sg:classifiers":[
        {
            "category":"Government",
            "subcategory":"Office",
            "type":"Public Place"
        }
    ],
    "sg:phone":"+44 1443 486510",
    "sg:postcode":"CF37 1JR",
    "sg:province":"Caerphilly",
    "sg:tags":[
        "central"
    ],
    "wof:name":"Probation Service",
    "wof:placetype":"venue"
},
  "geometry": {"coordinates":[-3.330959,51.597549],"type":"Point"}
}