{
  "type": "Feature",
  "properties": {
    "iso:country":"GB",
    "sg:address":"37 Oakham Close",
    "sg:city":"Redditch",
    "sg:classifiers":[
        {
            "category":"Retail",
            "subcategory":"Driving School",
            "type":"Services"
        }
    ],
    "sg:phone":"+44 1527 402362",
    "sg:postcode":"B98 7YG",
    "sg:province":"Warwickshire",
    "wof:name":"Classic School Of Motoring",
    "wof:placetype":"venue"
},
  "geometry": {"coordinates":[-1.92602,52.277779],"type":"Point"}
}