{
  "type": "Feature",
  "properties": {
    "addr:full":"Cottage Close, Poolsbrook Chesterfield Derbyshire S43 3LF",
    "addr:postcode":"s43 3lf",
    "addr:street":"Cottage Close",
    "iso:country":"GB",
    "sg:address":"Cottage Close, Poolsbrook",
    "sg:city":"Chesterfield",
    "sg:classifiers":[
        {
            "category":"Education",
            "subcategory":"School",
            "type":"Public Place"
        }
    ],
    "sg:phone":"+44 1246 472540",
    "sg:postcode":"S43 3LF",
    "sg:province":"Derbyshire",
    "sg:tags":[
        "local",
        "authority"
    ],
    "wof:name":"Poolsbrook Primary School",
    "wof:placetype":"venue"
},
  "geometry": {"coordinates":[-1.3371750116,53.2586402893],"type":"Point"}
}