{
  "type": "Feature",
  "properties": {
    "addr:full":"39 Earls Hall Avenue Southend-on-sea Essex SS2 6PB",
    "addr:housenumber":"39",
    "addr:postcode":"ss2 6pb",
    "addr:street":"Earls Hall Avenue",
    "iso:country":"GB",
    "sg:address":"39 Earls Hall Avenue",
    "sg:city":"Southend-on-sea",
    "sg:classifiers":[
        {
            "category":"Building & Trades",
            "subcategory":"Construction",
            "type":"Services"
        }
    ],
    "sg:postcode":"SS2 6PB",
    "sg:province":"Essex",
    "sg:tags":[
        "builder"
    ],
    "wof:name":"Smith & Barker",
    "wof:placetype":"venue"
},
  "geometry": {"coordinates":[0.698055,51.5546],"type":"Point"}
}