{
  "type": "Feature",
  "properties": {
    "iso:country":"GB",
    "sg:address":"136 Cornwall Street",
    "sg:city":"Plymouth",
    "sg:classifiers":[
        {
            "category":"Shopping",
            "subcategory":"Books",
            "type":"Retail Goods"
        }
    ],
    "sg:phone":"+44 1752 660374",
    "sg:postcode":"PL1 1NJ",
    "sg:province":"Devon",
    "sg:tags":[
        "bookseller"
    ],
    "wof:name":"Bonus Books",
    "wof:placetype":"venue"
},
  "geometry": {"coordinates":[-4.1463909149,50.3724441528],"type":"Point"}
}