{
  "type": "Feature",
  "properties": {
    "addr:full":"28 Fountain St, Nailsworth Stroud Gloucestershire GL6 0BL",
    "addr:housenumber":"28",
    "addr:postcode":"gl6 0bl",
    "addr:street":"Fountain St",
    "iso:country":"GB",
    "sg:address":"28 Fountain St, Nailsworth",
    "sg:city":"Stroud",
    "sg:classifiers":[
        {
            "category":"Communications",
            "type":"Services"
        }
    ],
    "sg:phone":"+44 1453 833318",
    "sg:postcode":"GL6 0BL",
    "sg:province":"Gloucestershire",
    "sg:tags":[
        "telecommunication"
    ],
    "wof:name":"The Orange Phone Shop",
    "wof:placetype":"venue"
},
  "geometry": {"coordinates":[-2.21849,51.694603],"type":"Point"}
}