{
  "type": "Feature",
  "properties": {
    "iso:country":"GB",
    "sg:address":"Hill House, 56 Western Road",
    "sg:city":"Hove",
    "sg:classifiers":[
        {
            "category":"Home & Garden",
            "subcategory":"Home Furnishings",
            "type":"Retail Goods"
        }
    ],
    "sg:phone":"+44 1273 323136",
    "sg:postcode":"BN3 1JD",
    "sg:province":"East Sussex",
    "sg:tags":[
        "mantelpiece",
        "fireplace"
    ],
    "wof:name":"Sussex Fireplace Centre",
    "wof:placetype":"venue"
},
  "geometry": {"coordinates":[-0.161152,50.825962],"type":"Point"}
}