{
  "type": "Feature",
  "properties": {
    "addr:full":"Building 200 Chertsey Road Sunbury-on-thames Surrey TW16 7XA",
    "addr:housenumber":"200",
    "addr:postcode":"tw16 7xa",
    "addr:street":"Chertsey Road",
    "iso:country":"GB",
    "sg:address":"Building 200 Chertsey Road",
    "sg:city":"Sunbury-on-thames",
    "sg:classifiers":[
        {
            "category":"Train Station",
            "subcategory":"Light Rail",
            "type":"Transportation"
        }
    ],
    "sg:phone":"+44 1932 779543",
    "sg:postcode":"TW16 7XA",
    "sg:province":"Surrey",
    "sg:tags":[
        "equipment",
        "energy",
        "solar"
    ],
    "wof:name":"B P Solar Holdings Ltd.",
    "wof:placetype":"venue"
},
  "geometry": {"coordinates":[-0.430494,51.427307],"type":"Point"}
}