{
  "type": "Feature",
  "properties": {
    "addr:full":"22 Fairfax Ct Yarm North Yorkshire TS15 9QZ",
    "addr:housenumber":"22",
    "addr:postcode":"ts15 9qz",
    "addr:street":"Fairfax Ct",
    "iso:country":"GB",
    "sg:address":"22 Fairfax Ct",
    "sg:city":"Yarm",
    "sg:classifiers":[
        {
            "category":"Shopping",
            "subcategory":"Gifts & Souvenirs",
            "type":"Retail Goods"
        }
    ],
    "sg:phone":"+44 1642 649600",
    "sg:postcode":"TS15 9QZ",
    "sg:province":"North Yorkshire",
    "sg:tags":[
        "poster",
        "card"
    ],
    "wof:name":"Verses",
    "wof:placetype":"venue"
},
  "geometry": {"coordinates":[-1.3538470268,54.5084648132],"type":"Point"}
}