{
  "type": "Feature",
  "properties": {
    "addr:full":"1 High Street Delabole Cornwall PL33 9AD",
    "addr:housenumber":"1",
    "addr:postcode":"pl33 9ad",
    "addr:street":"High Street",
    "iso:country":"GB",
    "sg:address":"1 High Street",
    "sg:city":"Delabole",
    "sg:classifiers":[
        {
            "category":"Food & Beverages",
            "subcategory":"Meat & Fish",
            "type":"Retail Goods"
        }
    ],
    "sg:phone":"+44 1840 212232",
    "sg:postcode":"PL33 9AD",
    "sg:province":"Cornwall",
    "sg:tags":[
        "chip"
    ],
    "wof:name":"A Doidge & N Saulsbury",
    "wof:placetype":"venue"
},
  "geometry": {"coordinates":[-4.727338,50.627457],"type":"Point"}
}