{
  "type": "Feature",
  "properties": {
    "iso:country":"GB",
    "sg:address":"68 Stratford Rd",
    "sg:city":"Solihull",
    "sg:classifiers":[
        {
            "category":"Shopping",
            "subcategory":"Bicycles & Sporting Goods",
            "type":"Retail Goods"
        }
    ],
    "sg:phone":"+44 121 744 1526",
    "sg:postcode":"B90 3LP",
    "sg:province":"West Midlands",
    "sg:tags":[
        "equipment",
        "leisure"
    ],
    "wof:name":"Comdean Ltd",
    "wof:placetype":"venue"
},
  "geometry": {"coordinates":[-1.8302639723,52.4163284302],"type":"Point"}
}