{
  "type": "Feature",
  "properties": {
    "iso:country":"GB",
    "sg:address":"Maespwll, Talgarreg",
    "sg:city":"Llandysul",
    "sg:classifiers":[
        {
            "category":"Personal",
            "subcategory":"Adult",
            "type":"Services"
        }
    ],
    "sg:phone":"+44 1545 590385",
    "sg:postcode":"SA44 4HB",
    "sg:province":"Carmarthenshire",
    "sg:tags":[
        "equestrian"
    ],
    "wof:name":"Paul A  Rail",
    "wof:placetype":"venue"
},
  "geometry": {"coordinates":[-4.307817,52.044479],"type":"Point"}
}