{
  "type": "Feature",
  "properties": {
    "addr:full":"Unit 8, Satellite Industrial Park, Neachells Lane Wolverhampton Staffordshire WV11 3PQ",
    "addr:housenumber":"unit 8",
    "addr:postcode":"wv11 3pq",
    "addr:street":"Industrial Park Neachells Lane",
    "iso:country":"GB",
    "sg:address":"Unit 8, Satellite Industrial Park, Neachells Lane",
    "sg:city":"Wolverhampton",
    "sg:classifiers":[
        {
            "category":"Government",
            "subcategory":"Post Office",
            "type":"Public Place"
        }
    ],
    "sg:phone":"+44 7712 107856",
    "sg:postcode":"WV11 3PQ",
    "sg:province":"Staffordshire",
    "sg:tags":[
        "cutting"
    ],
    "wof:name":"Mercia Tube Cutting Ltd.",
    "wof:placetype":"venue"
},
  "geometry": {"coordinates":[-2.121669054,52.5886497498],"type":"Point"}
}