{
  "type": "Feature",
  "properties": {
    "addr:full":"Hayre Building, Ulverscroft Road Leicester Leicestershire LE4 6BY",
    "addr:postcode":"le4 6by",
    "addr:street":"Ulverscroft Road",
    "iso:country":"GB",
    "sg:address":"Hayre Building, Ulverscroft Road",
    "sg:city":"Leicester",
    "sg:classifiers":[
        {
            "category":"Manufacturing",
            "subcategory":"Lumber",
            "type":"Manufacturing & Wholesale Goods"
        }
    ],
    "sg:phone":"+44 116 251 1185",
    "sg:postcode":"LE4 6BY",
    "sg:province":"Leicestershire",
    "sg:tags":[
        "merchant",
        "merchants",
        "importer",
        "agent",
        "timber"
    ],
    "wof:name":"Shires Timber Co. Ltd.",
    "wof:placetype":"venue"
},
  "geometry": {"coordinates":[-1.116236,52.645702],"type":"Point"}
}