{
  "type": "Feature",
  "properties": {
    "addr:full":"13 Battle Hill Hexham Northumberland NE46 1BA",
    "addr:housenumber":"13",
    "addr:postcode":"ne46 1ba",
    "addr:street":"Battle Hill",
    "iso:country":"GB",
    "sg:address":"13 Battle Hill",
    "sg:city":"Hexham",
    "sg:classifiers":[
        {
            "category":"Communications",
            "type":"Services"
        }
    ],
    "sg:postcode":"NE46 1BA",
    "sg:province":"Northumberland",
    "sg:tags":[
        "tv",
        "video",
        "radio"
    ],
    "wof:name":"J S Penney",
    "wof:placetype":"venue"
},
  "geometry": {"coordinates":[-2.1027350426,54.9700202942],"type":"Point"}
}