{
  "type": "Feature",
  "properties": {
    "iso:country":"GB",
    "sg:address":"Lambs Lane South",
    "sg:city":"Rainham",
    "sg:classifiers":[
        {
            "category":"Education",
            "subcategory":"University",
            "type":"Public Place"
        }
    ],
    "sg:postcode":"RM13 9XD",
    "sg:province":"Essex",
    "sg:tags":[
        "adult"
    ],
    "wof:name":"Century Youth House",
    "wof:placetype":"venue"
},
  "geometry": {"coordinates":[0.206933,51.516647],"type":"Point"}
}