{
  "type": "Feature",
  "properties": {
    "iso:country":"GB",
    "sg:address":"68 Princes Street",
    "sg:city":"Thurso",
    "sg:classifiers":[
        {
            "category":"Communications",
            "type":"Services"
        }
    ],
    "sg:postcode":"KW14 7DH",
    "sg:province":"Highland",
    "sg:tags":[
        "tv",
        "video",
        "radio"
    ],
    "wof:name":"Bain & Gibson",
    "wof:placetype":"venue"
},
  "geometry": {"coordinates":[-3.521474,58.594761],"type":"Point"}
}