{
  "type": "Feature",
  "properties": {
    "addr:full":"156 Cowbridge Road East Cardiff Cardiff CF1 9ND",
    "addr:housenumber":"156",
    "addr:postcode":"cf1 9nd",
    "addr:street":"Cowbridge Road East",
    "iso:country":"GB",
    "sg:address":"156 Cowbridge Road East",
    "sg:city":"Cardiff",
    "sg:classifiers":[
        {
            "category":"Retail",
            "subcategory":"Laundry & Dry Cleaning",
            "type":"Services"
        }
    ],
    "sg:phone":"+44 29 2037 3636",
    "sg:postcode":"CF1 9ND",
    "sg:province":"Cardiff",
    "sg:tags":[
        "alteration"
    ],
    "wof:name":"Johnsons The Cleaners",
    "wof:placetype":"venue"
},
  "geometry": {"coordinates":[-3.2005898952,51.4814987183],"type":"Point"}
}