{
  "type": "Feature",
  "properties": {
    "iso:country":"GB",
    "sg:address":"38 Brown Street",
    "sg:city":"Dundee",
    "sg:classifiers":[
        {
            "category":"Government",
            "subcategory":"Fire Station",
            "type":"Public Place"
        }
    ],
    "sg:phone":"+44 1382 322410",
    "sg:postcode":"DD1 5DT",
    "sg:province":"Dundee City",
    "sg:tags":[
        "security"
    ],
    "wof:name":"Pubvend Ltd.",
    "wof:placetype":"venue"
},
  "geometry": {"coordinates":[-2.980949,56.463097],"type":"Point"}
}