{
  "type": "Feature",
  "properties": {
    "addr:full":"11 Mount Ephrain Road London Greater London SW16 1NQ",
    "addr:housenumber":"11",
    "addr:postcode":"sw16 1nq",
    "addr:street":"Mount Ephrain Road",
    "iso:country":"GB",
    "sg:address":"11 Mount Ephrain Road",
    "sg:city":"London",
    "sg:classifiers":[
        {
            "category":"Professional",
            "subcategory":"Employment Agencies",
            "type":"Services"
        },
        {
            "category":"Professional",
            "subcategory":"Computer Services",
            "type":"Services"
        }
    ],
    "sg:phone":"+44 20 8835 9981",
    "sg:postcode":"SW16 1NQ",
    "sg:province":"Greater London",
    "sg:tags":[
        "consultant",
        "system",
        "software"
    ],
    "wof:name":"Smart Networks Ltd.",
    "wof:placetype":"venue"
},
  "geometry": {"coordinates":[-0.1290740073,51.435634613],"type":"Point"}
}