{
  "type": "Feature",
  "properties": {
    "addr:full":"3 Caldecottt House, Lancaster Rd Rugby Warwickshire CV21 2QN",
    "addr:housenumber":"3;house",
    "addr:postcode":"cv21 2qn",
    "addr:street":"Lancaster Rd",
    "iso:country":"GB",
    "sg:address":"3 Caldecottt House, Lancaster Rd",
    "sg:city":"Rugby",
    "sg:classifiers":[
        {
            "category":"Organizations",
            "subcategory":"Non-profit Organization",
            "type":"Services"
        }
    ],
    "sg:phone":"+44 1788 561113",
    "sg:postcode":"CV21 2QN",
    "sg:province":"Warwickshire",
    "sg:tags":[
        "organisation",
        "voluntary",
        "charity"
    ],
    "wof:name":"W.R.V.S.Meals On Wheels",
    "wof:placetype":"venue"
},
  "geometry": {"coordinates":[-1.2642899752,52.3781585693],"type":"Point"}
}