{
  "type": "Feature",
  "properties": {
    "addr:full":"Llanberis Farm, Crawley Down Rd East Grinstead East Sussex RH19 2PS",
    "addr:postcode":"rh19 2ps",
    "addr:street":"Llanberis;Crawley Down Rd",
    "iso:country":"GB",
    "sg:address":"Llanberis Farm, Crawley Down Rd",
    "sg:city":"East Grinstead",
    "sg:classifiers":[
        {
            "category":"Building & Trades",
            "subcategory":"Construction",
            "type":"Services"
        }
    ],
    "sg:phone":"+44 1342 321007",
    "sg:postcode":"RH19 2PS",
    "sg:province":"East Sussex",
    "sg:tags":[
        "builder"
    ],
    "wof:name":"Mike Of All Trades",
    "wof:placetype":"venue"
},
  "geometry": {"coordinates":[-0.007568,51.123981],"type":"Point"}
}