{
  "type": "Feature",
  "properties": {
    "addr:full":"Unit 3 Litchard Industrial Estate Bridgend Bridgend CF31 2AL",
    "addr:housenumber":"unit 3",
    "addr:postcode":"cf31 2al",
    "addr:street":"Litchard Industrial Estate",
    "iso:country":"GB",
    "sg:address":"Unit 3 Litchard Industrial Estate",
    "sg:city":"Bridgend",
    "sg:classifiers":[
        {
            "category":"Autos & Motor Vehicles",
            "subcategory":"Auto Supplies",
            "type":"Retail Goods"
        },
        {
            "category":"Building & Trades",
            "subcategory":"Construction",
            "type":"Services"
        }
    ],
    "sg:phone":"+44 1656 667000",
    "sg:postcode":"CF31 2AL",
    "sg:province":"Bridgend",
    "sg:tags":[
        "paint",
        "household",
        "component",
        "spraying"
    ],
    "wof:name":"J S Hussey & Co",
    "wof:placetype":"venue"
},
  "geometry": {"coordinates":[-3.5782630444,51.5088348389],"type":"Point"}
}