{
  "type": "Feature",
  "properties": {
    "addr:full":"New Writtle Street Chelmsford Essex CM2 0RZ",
    "addr:postcode":"cm2 0rz",
    "addr:street":"Writtle Street",
    "iso:country":"GB",
    "sg:address":"New Writtle Street",
    "sg:city":"Chelmsford",
    "sg:classifiers":[
        {
            "category":"Bars & Pubs",
            "type":"Food & Drink"
        }
    ],
    "sg:phone":"+44 1245 600002",
    "sg:postcode":"CM2 0RZ",
    "sg:province":"Essex",
    "sg:tags":[
        "pubs",
        "inn"
    ],
    "wof:name":"T D Ridley & Sons (Brewers) Ltd.",
    "wof:placetype":"venue"
},
  "geometry": {"coordinates":[0.471037,51.729534],"type":"Point"}
}