{
  "type": "Feature",
  "properties": {
    "addr:full":"87-88 Northgate Canterbury Kent CT1 1BA",
    "addr:housenumber":"87-88",
    "addr:postcode":"ct1 1ba",
    "addr:street":"Northgate",
    "iso:country":"GB",
    "sg:address":"87-88 Northgate",
    "sg:city":"Canterbury",
    "sg:classifiers":[
        {
            "category":"Food & Beverages",
            "subcategory":"Bakery",
            "type":"Retail Goods"
        }
    ],
    "sg:postcode":"CT1 1BA",
    "sg:province":"Kent",
    "sg:tags":[
        "pizza"
    ],
    "wof:name":"The Pizza Place",
    "wof:placetype":"venue"
},
  "geometry": {"coordinates":[1.0844490528,51.2827911377],"type":"Point"}
}