{
  "type": "Feature",
  "properties": {
    "iso:country":"GB",
    "sg:address":"25 Retreat Road",
    "sg:city":"Richmond",
    "sg:classifiers":[
        {
            "category":"Professional",
            "subcategory":"Business Services",
            "type":"Services"
        }
    ],
    "sg:postcode":"TW9 1NN",
    "sg:province":"Greater London",
    "sg:tags":[
        "holding"
    ],
    "wof:name":"Binia Holdings Ltd",
    "wof:placetype":"venue"
},
  "geometry": {"coordinates":[-0.308245,51.459595],"type":"Point"}
}