{
  "type": "Feature",
  "properties": {
    "addr:full":"17 Bexhill Rd, Opp M F I St Leonards On Sea East Sussex TN38 0AH",
    "addr:housenumber":"17",
    "addr:postcode":"tn38 0ah",
    "addr:street":"Bexhill Rd Opp M;I",
    "iso:country":"GB",
    "sg:address":"17 Bexhill Rd, Opp M F I",
    "sg:city":"St Leonards On Sea",
    "sg:classifiers":[
        {
            "category":"Cafe",
            "type":"Food & Drink"
        }
    ],
    "sg:phone":"+44 1424 426176",
    "sg:postcode":"TN38 0AH",
    "sg:province":"East Sussex",
    "sg:tags":[
        "tea",
        "room"
    ],
    "wof:name":"Teaspoons",
    "wof:placetype":"venue"
},
  "geometry": {"coordinates":[0.53763,50.851154],"type":"Point"}
}