{
  "type": "Feature",
  "properties": {
    "iso:country":"GB",
    "sg:address":"45 Frant Road",
    "sg:city":"Thornton Heath",
    "sg:classifiers":[
        {
            "category":"Retail",
            "subcategory":"Storage",
            "type":"Services"
        }
    ],
    "sg:phone":"+44 20 8684 0608",
    "sg:postcode":"CR7 7JZ",
    "sg:province":"Surrey",
    "sg:tags":[
        "household",
        "activity",
        "domestic",
        "removal"
    ],
    "wof:name":"Donovan's Removals",
    "wof:placetype":"venue"
},
  "geometry": {"coordinates":[-0.107289,51.391014],"type":"Point"}
}