{
  "type": "Feature",
  "properties": {
    "addr:full":"Unit 1 Gateside Indust Est Lanark South Lanarkshire ML11 0JR",
    "addr:housenumber":"unit 1",
    "addr:postcode":"ml11 0jr",
    "addr:street":"Indust Est",
    "iso:country":"GB",
    "sg:address":"Unit 1 Gateside Indust Est",
    "sg:city":"Lanark",
    "sg:classifiers":[
        {
            "category":"Personal",
            "type":"Services"
        }
    ],
    "sg:phone":"+44 1555 895559",
    "sg:postcode":"ML11 0JR",
    "sg:province":"South Lanarkshire",
    "sg:tags":[
        "wedding"
    ],
    "wof:name":"Bride Print",
    "wof:placetype":"venue"
},
  "geometry": {"coordinates":[-3.8865880966,55.6375961304],"type":"Point"}
}