{
  "type": "Feature",
  "properties": {
    "iso:country":"GB",
    "sg:address":"141b Liverpool Rd, Longton",
    "sg:city":"Preston",
    "sg:classifiers":[
        {
            "category":"Health Services",
            "subcategory":"Chiropractor",
            "type":"Services"
        }
    ],
    "sg:phone":"+44 1772 616505",
    "sg:postcode":"PR4 5AB",
    "sg:province":"Lancashire",
    "wof:name":"GB Holistic Clinic",
    "wof:placetype":"venue"
},
  "geometry": {"coordinates":[-2.764959,53.732891],"type":"Point"}
}