{
  "type": "Feature",
  "properties": {
    "addr:full":"Packman Road, Wath Upon Dearne Rotherham South Yorkshire S63 6AQ",
    "addr:postcode":"s63 6aq",
    "addr:street":"Packman Road",
    "iso:country":"GB",
    "sg:address":"Packman Road, Wath Upon Dearne",
    "sg:city":"Rotherham",
    "sg:classifiers":[
        {
            "category":"Autos & Motor Vehicles",
            "subcategory":"Automobile Sales",
            "type":"Retail Goods"
        }
    ],
    "sg:phone":"+44 1709 760006",
    "sg:postcode":"S63 6AQ",
    "sg:province":"South Yorkshire",
    "sg:tags":[
        "car"
    ],
    "wof:name":"Genesis Car Sales",
    "wof:placetype":"venue"
},
  "geometry": {"coordinates":[-1.3712610006,53.5023498535],"type":"Point"}
}