{
  "type": "Feature",
  "properties": {
    "addr:full":"15-17 Egginton Street Leicester Leicestershire LE5 5BD",
    "addr:housenumber":"15-17",
    "addr:postcode":"le5 5bd",
    "addr:street":"Egginton Street",
    "iso:country":"GB",
    "sg:address":"15-17 Egginton Street",
    "sg:city":"Leicester",
    "sg:classifiers":[
        {
            "category":"Food & Beverages",
            "subcategory":"Supermarket",
            "type":"Retail Goods"
        }
    ],
    "sg:phone":"+44 116 254 3687",
    "sg:postcode":"LE5 5BD",
    "sg:province":"Leicestershire",
    "wof:name":"Central Supermarket",
    "wof:placetype":"venue"
},
  "geometry": {"coordinates":[-1.109099,52.629799],"type":"Point"}
}