{
  "type": "Feature",
  "properties": {
    "iso:country":"GB",
    "sg:address":"108 High Street, North Shore",
    "sg:city":"Blackpool",
    "sg:classifiers":[
        {
            "category":"Travel",
            "subcategory":"Hotels & Motels",
            "type":"Entertainment"
        }
    ],
    "sg:phone":"+44 1253 622836",
    "sg:postcode":"FY1 2DL",
    "sg:province":"Lancashire",
    "sg:tags":[
        "house",
        "guest"
    ],
    "wof:name":"Karena Guest House",
    "wof:placetype":"venue"
},
  "geometry": {"coordinates":[-3.052318,53.824512],"type":"Point"}
}