{
  "type": "Feature",
  "properties": {
    "iso:country":"GB",
    "sg:address":"16 Windsor Gardens",
    "sg:city":"Braintree",
    "sg:classifiers":[
        {
            "category":"Professional",
            "subcategory":"Engineering",
            "type":"Services"
        }
    ],
    "sg:phone":"+44 1376 322277",
    "sg:postcode":"CM7 9LD",
    "sg:province":"Essex",
    "sg:tags":[
        "contractor",
        "electrical",
        "engineer"
    ],
    "wof:name":"P J Crisp",
    "wof:placetype":"venue"
},
  "geometry": {"coordinates":[0.5645160079,51.8826408386],"type":"Point"}
}