{
  "type": "Feature",
  "properties": {
    "addr:full":"Unit 45, Ealing Bdwy London Greater London W5 5JY",
    "addr:housenumber":"unit 45",
    "addr:postcode":"w5 5jy",
    "iso:country":"GB",
    "sg:address":"Unit 45, Ealing Bdwy",
    "sg:city":"London",
    "sg:classifiers":[
        {
            "category":"Shopping",
            "subcategory":"Music",
            "type":"Retail Goods"
        }
    ],
    "sg:phone":"+44 20 8567 1137",
    "sg:postcode":"W5 5JY",
    "sg:province":"Greater London",
    "sg:tags":[
        "record",
        "tape",
        "cd"
    ],
    "wof:name":"Our Price",
    "wof:placetype":"venue"
},
  "geometry": {"coordinates":[-0.3055199981,51.5106468201],"type":"Point"}
}