{
  "type": "Feature",
  "properties": {
    "iso:country":"GB",
    "sg:address":"Unit 1b, Castle Trading Estate, Porchester",
    "sg:city":"Fareham",
    "sg:classifiers":[
        {
            "category":"Retail",
            "subcategory":"Auto Repair",
            "type":"Services"
        }
    ],
    "sg:phone":"+44 23 9237 2279",
    "sg:postcode":"PO16 9SE",
    "sg:province":"Hampshire",
    "sg:tags":[
        "modification",
        "garage"
    ],
    "wof:name":"Kwik-fit Tyre & Exhaust Centre",
    "wof:placetype":"venue"
},
  "geometry": {"coordinates":[-1.118999,50.845795],"type":"Point"}
}