{
  "type": "Feature",
  "properties": {
    "addr:full":"Parciau, Llanndaniel Gaerwen Isle of Anglesey LL60 6HB",
    "addr:postcode":"ll60 6hb",
    "addr:street":"Gaerwen",
    "iso:country":"GB",
    "sg:address":"Parciau, Llanndaniel",
    "sg:city":"Gaerwen",
    "sg:classifiers":[
        {
            "category":"Organizations",
            "subcategory":"Labor Organization",
            "type":"Services"
        },
        {
            "category":"Utilities",
            "subcategory":"Fuel Oil & Lpg",
            "type":"Services"
        },
        {
            "category":"Shopping",
            "subcategory":"Discount & Variety Stores",
            "type":"Retail Goods"
        }
    ],
    "sg:phone":"+44 1248 421333",
    "sg:postcode":"LL60 6HB",
    "sg:province":"Isle of Anglesey",
    "sg:tags":[
        "coal",
        "cleaning",
        "smokeless",
        "supply"
    ],
    "wof:name":"George Jones & Son",
    "wof:placetype":"venue"
},
  "geometry": {"coordinates":[-4.2764987946,53.2228240967],"type":"Point"}
}