{
  "type": "Feature",
  "properties": {
    "addr:full":"Unit 3, Queens Walk Maidenhead Berkshire SL6 1LL",
    "addr:housenumber":"unit 3",
    "addr:postcode":"sl6 1ll",
    "addr:street":"Queens Walk",
    "iso:country":"GB",
    "sg:address":"Unit 3, Queens Walk",
    "sg:city":"Maidenhead",
    "sg:classifiers":[
        {
            "category":"Shopping",
            "subcategory":"Gifts & Souvenirs",
            "type":"Retail Goods"
        }
    ],
    "sg:phone":"+44 1628 771735",
    "sg:postcode":"SL6 1LL",
    "sg:province":"Berkshire",
    "sg:tags":[
        "poster",
        "card"
    ],
    "wof:name":"Birthdays",
    "wof:placetype":"venue"
},
  "geometry": {"coordinates":[-0.7202060223,51.522518158],"type":"Point"}
}