{
  "type": "Feature",
  "properties": {
    "iso:country":"GB",
    "sg:address":"19 Winchcomb Road",
    "sg:city":"Norwich",
    "sg:classifiers":[
        {
            "category":"Building & Trades",
            "subcategory":"Plumbing",
            "type":"Services"
        }
    ],
    "sg:phone":"+44 1603 624001",
    "sg:postcode":"NR2 3UF",
    "sg:province":"Norfolk",
    "sg:tags":[
        "plumber",
        "heating"
    ],
    "wof:name":"C J Allman",
    "wof:placetype":"venue"
},
  "geometry": {"coordinates":[1.261647,52.635807],"type":"Point"}
}