{
  "type": "Feature",
  "properties": {
    "addr:full":"29 St. Margarets Rd, Ward End Birmingham West Midlands B8 2BA",
    "addr:housenumber":"29",
    "addr:postcode":"b8 2ba",
    "addr:street":"St. Margarets Rd",
    "iso:country":"GB",
    "sg:address":"29 St. Margarets Rd, Ward End",
    "sg:city":"Birmingham",
    "sg:classifiers":[
        {
            "category":"Food & Beverages",
            "subcategory":"Groceries & Convenience Stores",
            "type":"Retail Goods"
        }
    ],
    "sg:phone":"+44 121 327 5741",
    "sg:postcode":"B8 2BA",
    "sg:province":"West Midlands",
    "wof:name":"Sajad Food Store",
    "wof:placetype":"venue"
},
  "geometry": {"coordinates":[-1.833646,52.49464],"type":"Point"}
}