{
  "type": "Feature",
  "properties": {
    "iso:country":"GB",
    "sg:address":"Ironstone Rd, Chase Terrace",
    "sg:city":"Burntwood",
    "sg:classifiers":[
        {
            "category":"Bars & Pubs",
            "type":"Food & Drink"
        }
    ],
    "sg:phone":"+44 1543 279030",
    "sg:postcode":"WS7 8LY",
    "sg:province":"Staffordshire",
    "sg:tags":[
        "pubs",
        "inn"
    ],
    "wof:name":"The Victoria Inn",
    "wof:placetype":"venue"
},
  "geometry": {"coordinates":[-1.942447,52.689266],"type":"Point"}
}