{
  "type": "Feature",
  "properties": {
    "iso:country":"GB",
    "sg:address":"37 Perry St",
    "sg:city":"Darwen",
    "sg:classifiers":[
        {
            "category":"Health Services",
            "subcategory":"Doctor",
            "type":"Services"
        }
    ],
    "sg:phone":"+44 1254 760309",
    "sg:postcode":"BB3 3DG",
    "sg:province":"Lancashire",
    "sg:tags":[
        "practitioners"
    ],
    "wof:name":"Derar, I M",
    "wof:placetype":"venue"
},
  "geometry": {"coordinates":[-2.462903,53.699547],"type":"Point"}
}