{
  "type": "Feature",
  "properties": {
    "iso:country":"GB",
    "sg:address":"6-7 Medwin Walk",
    "sg:city":"Horsham",
    "sg:classifiers":[
        {
            "category":"Home & Garden",
            "subcategory":"Home Furnishings",
            "type":"Retail Goods"
        }
    ],
    "sg:phone":"+44 1403 266630",
    "sg:postcode":"RH12 1AG",
    "sg:province":"West Sussex",
    "sg:tags":[
        "furnishers",
        "planner",
        "kitchen"
    ],
    "wof:name":"In-toto Kitchens & Bathrooms",
    "wof:placetype":"venue"
},
  "geometry": {"coordinates":[-0.327711,51.063923],"type":"Point"}
}