{
  "type": "Feature",
  "properties": {
    "addr:full":"363 Bath Road, Arnos Vale Bristol City of Bristol BS4 3EW",
    "addr:housenumber":"363",
    "addr:postcode":"bs4 3ew",
    "addr:street":"Bath Road",
    "iso:country":"GB",
    "sg:address":"363 Bath Road, Arnos Vale",
    "sg:city":"Bristol",
    "sg:classifiers":[
        {
            "category":"Shopping",
            "subcategory":"Pharmacy",
            "type":"Retail Goods"
        }
    ],
    "sg:phone":"+44 117 977 4659",
    "sg:postcode":"BS4 3EW",
    "sg:province":"City of Bristol",
    "sg:tags":[
        "medicine",
        "therapy"
    ],
    "wof:name":"Diamonds Massage Studio",
    "wof:placetype":"venue"
},
  "geometry": {"coordinates":[-2.5639920235,51.4424095154],"type":"Point"}
}