{
  "type": "Feature",
  "properties": {
    "addr:full":"40-41 Western International Market, Hayes Road Southall Greater London UB2 5XA",
    "addr:housenumber":"40-41",
    "addr:postcode":"ub2 5xa",
    "addr:street":"Western;Hayes Road",
    "iso:country":"GB",
    "sg:address":"40-41 Western International Market, Hayes Road",
    "sg:city":"Southall",
    "sg:classifiers":[
        {
            "category":"Wholesale",
            "subcategory":"Fruits & Vegetables",
            "type":"Manufacturing & Wholesale Goods"
        }
    ],
    "sg:phone":"+44 20 8561 3366",
    "sg:postcode":"UB2 5XA",
    "sg:province":"Greater London",
    "wof:name":"M McDade (Western) Ltd.",
    "wof:placetype":"venue"
},
  "geometry": {"coordinates":[-0.40422,51.49617],"type":"Point"}
}