{
  "type": "Feature",
  "properties": {
    "iso:country":"GB",
    "sg:address":"Dental Surgery, 22 Old Woking Rd",
    "sg:city":"West Byfleet",
    "sg:classifiers":[
        {
            "category":"Health Services",
            "subcategory":"Dentist",
            "type":"Services"
        }
    ],
    "sg:phone":"+44 1932 343675",
    "sg:postcode":"KT14 6HP",
    "sg:province":"Surrey",
    "wof:name":"S W Wilkinson",
    "wof:placetype":"venue"
},
  "geometry": {"coordinates":[-0.496921,51.338421],"type":"Point"}
}