{
  "type": "Feature",
  "properties": {
    "addr:full":"73 Ber Street Norwich Norfolk NR1 3AD",
    "addr:housenumber":"73",
    "addr:postcode":"nr1 3ad",
    "addr:street":"Ber Street",
    "iso:country":"GB",
    "sg:address":"73 Ber Street",
    "sg:city":"Norwich",
    "sg:classifiers":[
        {
            "category":"Organizations",
            "subcategory":"Non-profit Organization",
            "type":"Services"
        }
    ],
    "sg:postcode":"NR1 3AD",
    "sg:province":"Norfolk",
    "sg:tags":[
        "organisation",
        "voluntary",
        "charity"
    ],
    "wof:name":"Mind",
    "wof:placetype":"venue"
},
  "geometry": {"coordinates":[1.2974699736,52.6241264343],"type":"Point"}
}