{
  "type": "Feature",
  "properties": {
    "iso:country":"GB",
    "sg:address":"Unit 3d, Harpings Rd, National Ave",
    "sg:city":"Hull",
    "sg:classifiers":[
        {
            "category":"Manufacturing",
            "subcategory":"Building Materials",
            "type":"Manufacturing & Wholesale Goods"
        }
    ],
    "sg:phone":"+44 1482 492255",
    "sg:postcode":"HU5 4JF",
    "sg:province":"East Riding of Yorkshire",
    "sg:tags":[
        "merchant",
        "builder"
    ],
    "wof:name":"Building Construction Products Ltd",
    "wof:placetype":"venue"
},
  "geometry": {"coordinates":[-0.381164,53.755779],"type":"Point"}
}