{
  "type": "Feature",
  "properties": {
    "addr:full":"Temple House London Greater London SW14 8LS",
    "addr:postcode":"sw14 8ls",
    "iso:country":"GB",
    "sg:address":"Temple House",
    "sg:city":"London",
    "sg:classifiers":[
        {
            "category":"Building & Trades",
            "subcategory":"Construction",
            "type":"Services"
        }
    ],
    "sg:postcode":"SW14 8LS",
    "sg:province":"Greater London",
    "sg:tags":[
        "builder"
    ],
    "wof:name":"Bradwell Meads Ltd.",
    "wof:placetype":"venue"
},
  "geometry": {"coordinates":[-0.2659089863,51.4648246765],"type":"Point"}
}