{
  "type": "Feature",
  "properties": {
    "addr:full":"Dunnington Court Farm, Broomland, Dunnington Alcester Warwickshire B49 5NU",
    "addr:postcode":"b49 5nu",
    "addr:street":"Dunnington Court;Broomland",
    "iso:country":"GB",
    "sg:address":"Dunnington Court Farm, Broomland, Dunnington",
    "sg:city":"Alcester",
    "sg:classifiers":[
        {
            "category":"Farming",
            "subcategory":"Livestock Farm",
            "type":"Manufacturing & Wholesale Goods"
        }
    ],
    "sg:phone":"+44 1789 772451",
    "sg:postcode":"B49 5NU",
    "sg:province":"Warwickshire",
    "sg:tags":[
        "others"
    ],
    "wof:name":"Bomford",
    "wof:placetype":"venue"
},
  "geometry": {"coordinates":[-1.9017879963,52.1811332703],"type":"Point"}
}