{
  "type": "Feature",
  "properties": {
    "addr:full":"27-29 Willow St Oswestry Shropshire SY11 1AQ",
    "addr:housenumber":"27-29",
    "addr:postcode":"sy11 1aq",
    "addr:street":"Willow St",
    "iso:country":"GB",
    "sg:address":"27-29 Willow St",
    "sg:city":"Oswestry",
    "sg:classifiers":[
        {
            "category":"Education",
            "subcategory":"Special Training",
            "type":"Public Place"
        }
    ],
    "sg:phone":"+44 1691 656000",
    "sg:postcode":"SY11 1AQ",
    "sg:province":"Shropshire",
    "sg:tags":[
        "product",
        "centre"
    ],
    "wof:name":"New Careers Training Shropshire",
    "wof:placetype":"venue"
},
  "geometry": {"coordinates":[-3.05693,52.859894],"type":"Point"}
}