{
  "type": "Feature",
  "properties": {
    "addr:full":"Unit 4 Lion Works, 543 Wallisdown Road Poole Dorset BH12 5AD",
    "addr:housenumber":"unit 4;543",
    "addr:postcode":"bh12 5ad",
    "addr:street":"Lion Works;Wallisdown Road",
    "iso:country":"GB",
    "sg:address":"Unit 4 Lion Works, 543 Wallisdown Road",
    "sg:city":"Poole",
    "sg:classifiers":[
        {
            "category":"Wholesale",
            "subcategory":"Scrap",
            "type":"Manufacturing & Wholesale Goods"
        }
    ],
    "sg:postcode":"BH12 5AD",
    "sg:province":"Dorset",
    "sg:tags":[
        "waste",
        "metal"
    ],
    "wof:name":"Perrys Recycling",
    "wof:placetype":"venue"
},
  "geometry": {"coordinates":[-1.9279299974,50.7518997192],"type":"Point"}
}