{
  "type": "Feature",
  "properties": {
    "iso:country":"GB",
    "sg:address":"16 Carlton Crescent",
    "sg:city":"Sutton",
    "sg:classifiers":[
        {
            "category":"Professional",
            "subcategory":"Computer Services",
            "type":"Services"
        }
    ],
    "sg:postcode":"SM3 9TS",
    "sg:province":"Surrey",
    "sg:tags":[
        "system",
        "software"
    ],
    "wof:name":"Cymon Ltd",
    "wof:placetype":"venue"
},
  "geometry": {"coordinates":[-0.217365,51.369331],"type":"Point"}
}