{
  "type": "Feature",
  "properties": {
    "addr:full":"23 Alan Rd Padstow Cornwall PL28 8DS",
    "addr:housenumber":"23",
    "addr:postcode":"pl28 8ds",
    "addr:street":"Alan Rd",
    "iso:country":"GB",
    "sg:address":"23 Alan Rd",
    "sg:city":"Padstow",
    "sg:classifiers":[
        {
            "category":"Home & Garden",
            "subcategory":"Home Furnishings",
            "type":"Retail Goods"
        }
    ],
    "sg:postcode":"PL28 8DS",
    "sg:province":"Cornwall",
    "sg:tags":[
        "furnishers",
        "planner",
        "kitchen"
    ],
    "wof:name":"Heywood,Paul,International Ltd",
    "wof:placetype":"venue"
},
  "geometry": {"coordinates":[-4.939125,50.536404],"type":"Point"}
}