{
  "type": "Feature",
  "properties": {
    "addr:full":"Alan House, 48 Bootham York North Yorkshire YO30 7WZ",
    "addr:housenumber":"48",
    "addr:postcode":"yo30 7wz",
    "addr:street":"Bootham",
    "iso:country":"GB",
    "sg:address":"Alan House, 48 Bootham",
    "sg:city":"York",
    "sg:classifiers":[
        {
            "category":"Real Estate",
            "subcategory":"Surveying",
            "type":"Services"
        },
        {
            "category":"Real Estate",
            "subcategory":"Real Estate Agent",
            "type":"Services"
        }
    ],
    "sg:phone":"+44 1904 756300",
    "sg:postcode":"YO30 7WZ",
    "sg:province":"North Yorkshire",
    "sg:tags":[
        "surveyor",
        "land"
    ],
    "wof:name":"Smiths Gore",
    "wof:placetype":"venue"
},
  "geometry": {"coordinates":[-1.087661,53.963943],"type":"Point"}
}