{
  "type": "Feature",
  "properties": {
    "iso:country":"GB",
    "sg:address":"Bryn Gwennol, Sunny Bank, Quakers Yard",
    "sg:city":"Treharris",
    "sg:classifiers":[
        {
            "category":"Professional",
            "subcategory":"Employment Agencies",
            "type":"Services"
        }
    ],
    "sg:phone":"+44 1443 410716",
    "sg:postcode":"CF46 5BA",
    "sg:province":"Caerphilly",
    "sg:tags":[
        "consultant"
    ],
    "wof:name":"David Thomas",
    "wof:placetype":"venue"
},
  "geometry": {"coordinates":[-3.30647,51.664886],"type":"Point"}
}