{
  "type": "Feature",
  "properties": {
    "iso:country":"GB",
    "sg:address":"13 Marlborough Road, Upper Holloway",
    "sg:city":"London",
    "sg:classifiers":[
        {
            "category":"Professional",
            "subcategory":"Art Services",
            "type":"Services"
        },
        {
            "category":"Building & Trades",
            "subcategory":"Construction",
            "type":"Services"
        }
    ],
    "sg:phone":"+44 20 7263 1497",
    "sg:postcode":"N19 4NA",
    "sg:province":"Greater London",
    "sg:tags":[
        "decorator",
        "painter"
    ],
    "wof:name":"Gareth Mathias",
    "wof:placetype":"venue"
},
  "geometry": {"coordinates":[-0.1277469993,51.5638618469],"type":"Point"}
}