{
  "type": "Feature",
  "properties": {
    "iso:country":"GB",
    "sg:address":"Glenfoot Farm",
    "sg:city":"Tillicoultry",
    "sg:classifiers":[
        {
            "category":"Farming",
            "subcategory":"Livestock Farm",
            "type":"Manufacturing & Wholesale Goods"
        }
    ],
    "sg:phone":"+44 1259 750631",
    "sg:postcode":"FK13 6BT",
    "sg:province":"Clackmannanshire",
    "sg:tags":[
        "others"
    ],
    "wof:name":"R Marshall & Partner",
    "wof:placetype":"venue"
},
  "geometry": {"coordinates":[-3.7459690571,56.1513290405],"type":"Point"}
}