{
  "type": "Feature",
  "properties": {
    "iso:country":"GB",
    "sg:address":"Unit 6, 33 Ebury Road, Sherwood Rise",
    "sg:city":"Nottingham",
    "sg:classifiers":[
        {
            "category":"Manufacturing",
            "subcategory":"Textiles",
            "type":"Manufacturing & Wholesale Goods"
        }
    ],
    "sg:phone":"+44 115 960 6247",
    "sg:postcode":"NG5 1BB",
    "sg:province":"Nottinghamshire",
    "sg:tags":[
        "merchant",
        "agent"
    ],
    "wof:name":"J S Distributors (Nottingham) Ltd.",
    "wof:placetype":"venue"
},
  "geometry": {"coordinates":[-1.156352,52.973305],"type":"Point"}
}