{
  "type": "Feature",
  "properties": {
    "addr:full":"60 St Marys Street Wallingford Oxfordshire OX10 0EL",
    "addr:housenumber":"60",
    "addr:postcode":"ox10 0el",
    "addr:street":"St Marys Street",
    "iso:country":"GB",
    "sg:address":"60 St Marys Street",
    "sg:city":"Wallingford",
    "sg:classifiers":[
        {
            "category":"Health Services",
            "subcategory":"Optometrist",
            "type":"Services"
        }
    ],
    "sg:phone":"+44 1491 835466",
    "sg:postcode":"OX10 0EL",
    "sg:province":"Oxfordshire",
    "sg:tags":[
        "optician"
    ],
    "wof:name":"Hubbard's Opticians",
    "wof:placetype":"venue"
},
  "geometry": {"coordinates":[-1.124519,51.599895],"type":"Point"}
}