{
  "type": "Feature",
  "properties": {
    "addr:full":"Larch Farm, Stawell Bridgwater Somerset TA7 9AN",
    "addr:postcode":"ta7 9an",
    "addr:street":"Stawell",
    "iso:country":"GB",
    "sg:address":"Larch Farm, Stawell",
    "sg:city":"Bridgwater",
    "sg:classifiers":[
        {
            "category":"Real Estate",
            "subcategory":"Real Estate Agent",
            "type":"Services"
        }
    ],
    "sg:postcode":"TA7 9AN",
    "sg:province":"Somerset",
    "wof:name":"Larchfield Estates Ltd.",
    "wof:placetype":"venue"
},
  "geometry": {"coordinates":[-2.905559,51.140324],"type":"Point"}
}