{
  "type": "Feature",
  "properties": {
    "addr:full":"7 Fettercairn Gardens, Bishopbriggs Glasgow East Dunbartonshire G64 1AY",
    "addr:housenumber":"7",
    "addr:postcode":"g64 1ay",
    "addr:street":"Fettercairn Gardens",
    "iso:country":"GB",
    "sg:address":"7 Fettercairn Gardens, Bishopbriggs",
    "sg:city":"Glasgow",
    "sg:classifiers":[
        {
            "category":"Professional",
            "subcategory":"Detective & Security Services",
            "type":"Services"
        }
    ],
    "sg:postcode":"G64 1AY",
    "sg:province":"East Dunbartonshire",
    "sg:tags":[
        "alarm",
        "burglar",
        "system"
    ],
    "wof:name":"Advanced Alarm Systems",
    "wof:placetype":"venue"
},
  "geometry": {"coordinates":[-4.2052850723,55.9036407471],"type":"Point"}
}