{
  "type": "Feature",
  "properties": {
    "addr:full":"Bond House, Goodwood Road London Greater London SE14 6BL",
    "addr:postcode":"se14 6bl",
    "addr:street":"Goodwood Road",
    "iso:country":"GB",
    "sg:address":"Bond House, Goodwood Road",
    "sg:city":"London",
    "sg:classifiers":[
        {
            "category":"Home & Garden",
            "subcategory":"Kitchen Supply",
            "type":"Retail Goods"
        }
    ],
    "sg:phone":"+44 20 8691 5831",
    "sg:postcode":"SE14 6BL",
    "sg:province":"Greater London",
    "sg:tags":[
        "bar",
        "accessory"
    ],
    "wof:name":"Grey Simmonds Ltd.",
    "wof:placetype":"venue"
},
  "geometry": {"coordinates":[-0.03999,51.476761],"type":"Point"}
}