{
  "type": "Feature",
  "properties": {
    "addr:full":"16 Stoneleigh Park Avenue Croydon Surrey CR0 7SL",
    "addr:housenumber":"16",
    "addr:postcode":"cr0 7sl",
    "addr:street":"Stoneleigh Park Avenue",
    "iso:country":"GB",
    "sg:address":"16 Stoneleigh Park Avenue",
    "sg:city":"Croydon",
    "sg:classifiers":[
        {
            "category":"Insurance",
            "subcategory":"Insurance Agent",
            "type":"Services"
        }
    ],
    "sg:phone":"+44 20 8662 0314",
    "sg:postcode":"CR0 7SL",
    "sg:province":"Surrey",
    "wof:name":"I B A Insurance Services Ltd.",
    "wof:placetype":"venue"
},
  "geometry": {"coordinates":[-0.047644,51.389416],"type":"Point"}
}