{
  "type": "Feature",
  "properties": {
    "addr:full":"51 Stamford New Road Altrincham Cheshire WA14 1DS",
    "addr:housenumber":"51",
    "addr:postcode":"wa14 1ds",
    "addr:street":"Stamford New Road",
    "iso:country":"GB",
    "sg:address":"51 Stamford New Road",
    "sg:city":"Altrincham",
    "sg:classifiers":[
        {
            "category":"Home & Garden",
            "subcategory":"Kitchen Supply",
            "type":"Retail Goods"
        }
    ],
    "sg:phone":"+44 161 740 2400",
    "sg:postcode":"WA14 1DS",
    "sg:province":"Cheshire",
    "sg:tags":[
        "glassware",
        "china"
    ],
    "wof:name":"Allweis",
    "wof:placetype":"venue"
},
  "geometry": {"coordinates":[-2.3506469727,53.3857040405],"type":"Point"}
}