{
  "type": "Feature",
  "properties": {
    "addr:full":"100 Belmont Road Erith Kent DA8 1LD",
    "addr:housenumber":"100",
    "addr:postcode":"da8 1ld",
    "addr:street":"Belmont Road",
    "iso:country":"GB",
    "sg:address":"100 Belmont Road",
    "sg:city":"Erith",
    "sg:classifiers":[
        {
            "category":"Real Estate",
            "subcategory":"Surveying",
            "type":"Services"
        }
    ],
    "sg:postcode":"DA8 1LD",
    "sg:province":"Kent",
    "sg:tags":[
        "building",
        "surveyor"
    ],
    "wof:name":"Thames-Side Building & Safety Consultancy",
    "wof:placetype":"venue"
},
  "geometry": {"coordinates":[0.1535580009,51.4714241028],"type":"Point"}
}