{
  "type": "Feature",
  "properties": {
    "addr:full":"Worksop Road Sheffield South Yorkshire S9 3TH",
    "addr:postcode":"s9 3th",
    "addr:street":"Worksop Road",
    "iso:country":"GB",
    "sg:address":"Worksop Road",
    "sg:city":"Sheffield",
    "sg:classifiers":[
        {
            "category":"Building & Trades",
            "subcategory":"Equipment Rental",
            "type":"Services"
        }
    ],
    "sg:phone":"+44 114 243 1121",
    "sg:postcode":"S9 3TH",
    "sg:province":"South Yorkshire",
    "sg:tags":[
        "plant",
        "machinery"
    ],
    "wof:name":"Ashtead Plant Hire Co",
    "wof:placetype":"venue"
},
  "geometry": {"coordinates":[-1.429989,53.395329],"type":"Point"}
}