{
  "type": "Feature",
  "properties": {
    "iso:country":"GB",
    "sg:address":"The Rowan Centre, North Street",
    "sg:city":"Atherstone",
    "sg:classifiers":[
        {
            "category":"Social Services",
            "subcategory":"Adult Care",
            "type":"Services"
        }
    ],
    "sg:phone":"+44 1827 718972",
    "sg:postcode":"CV9 1JN",
    "sg:province":"Leicestershire",
    "sg:tags":[
        "day",
        "centre"
    ],
    "wof:name":"The Rowan Organisation",
    "wof:placetype":"venue"
},
  "geometry": {"coordinates":[-1.5419590473,52.5759353638],"type":"Point"}
}