{
  "type": "Feature",
  "properties": {
    "addr:full":"13-15 Pier Street Aberystwyth Ceredigion SY23 2LJ",
    "addr:housenumber":"13-15",
    "addr:postcode":"sy23 2lj",
    "addr:street":"Pier Street",
    "iso:country":"GB",
    "sg:address":"13-15 Pier Street",
    "sg:city":"Aberystwyth",
    "sg:classifiers":[
        {
            "category":"Restaurant",
            "type":"Food & Drink"
        }
    ],
    "sg:phone":"+44 1970 617417",
    "sg:postcode":"SY23 2LJ",
    "sg:province":"Ceredigion",
    "wof:name":"Home Cafe & Restaurant",
    "wof:placetype":"venue"
},
  "geometry": {"coordinates":[-4.0871691704,52.4154396057],"type":"Point"}
}