{
  "type": "Feature",
  "properties": {
    "addr:full":"23 Maundeville Crescent Christchurch Dorset BH23 2EW",
    "addr:housenumber":"23",
    "addr:postcode":"bh23 2ew",
    "addr:street":"Maundeville Crescent",
    "iso:country":"GB",
    "sg:address":"23 Maundeville Crescent",
    "sg:city":"Christchurch",
    "sg:classifiers":[
        {
            "category":"Professional",
            "subcategory":"Management & Consulting",
            "type":"Services"
        }
    ],
    "sg:phone":"+44 1202 480084",
    "sg:postcode":"BH23 2EW",
    "sg:province":"Dorset",
    "sg:tags":[
        "project"
    ],
    "wof:name":"Searle Consultancy Ltd.",
    "wof:placetype":"venue"
},
  "geometry": {"coordinates":[-1.8026419878,50.7414550781],"type":"Point"}
}