{
  "type": "Feature",
  "properties": {
    "iso:country":"GB",
    "sg:address":"65 Clerk Street",
    "sg:city":"Edinburgh",
    "sg:classifiers":[
        {
            "category":"Personal",
            "subcategory":"Beauty Salon",
            "type":"Services"
        },
        {
            "category":"Personal",
            "subcategory":"Barber",
            "type":"Services"
        }
    ],
    "sg:phone":"+44 131 668 3868",
    "sg:postcode":"EH8 9JQ",
    "sg:province":"City of Edinburgh",
    "sg:tags":[
        "unisex",
        "hairdresser"
    ],
    "wof:name":"Gordon Black Hairdressing",
    "wof:placetype":"venue"
},
  "geometry": {"coordinates":[-3.182024,55.941772],"type":"Point"}
}