{
  "type": "Feature",
  "properties": {
    "addr:full":"Martins Gate, Breton Side Plymouth Devon PL4 0AT",
    "addr:postcode":"pl4 0at",
    "addr:street":"Martins Gate Breton Side",
    "iso:country":"GB",
    "sg:address":"Martins Gate, Breton Side",
    "sg:city":"Plymouth",
    "sg:classifiers":[
        {
            "category":"Education",
            "subcategory":"School",
            "type":"Public Place"
        },
        {
            "category":"Government",
            "subcategory":"Office",
            "type":"Public Place"
        }
    ],
    "sg:phone":"+44 1752 229351",
    "sg:postcode":"PL4 0AT",
    "sg:province":"Devon",
    "sg:tags":[
        "local",
        "authority"
    ],
    "wof:name":"Martins Gate Pupil Referral Unit",
    "wof:placetype":"venue"
},
  "geometry": {"coordinates":[-4.134659,50.370411],"type":"Point"}
}