{
  "type": "Feature",
  "properties": {
    "iso:country":"GB",
    "sg:address":"Neath Rd",
    "sg:city":"Neath",
    "sg:classifiers":[
        {
            "category":"Place Of Worship",
            "type":"Public Place"
        }
    ],
    "sg:phone":"+44 1639 812200",
    "sg:postcode":"SA11 2SL",
    "sg:province":"Neath Port Talbot",
    "wof:name":"St Clement Church In Wales",
    "wof:placetype":"venue"
},
  "geometry": {"coordinates":[-3.817364,51.638409],"type":"Point"}
}