{
  "type": "Feature",
  "properties": {
    "addr:full":"522 Kents Hill Road North Benfleet Essex SS7 4AA",
    "addr:housenumber":"522",
    "addr:postcode":"ss7 4aa",
    "addr:street":"Kents Hill Road North Benfleet",
    "iso:country":"GB",
    "sg:address":"522 Kents Hill Road North",
    "sg:city":"Benfleet",
    "sg:classifiers":[
        {
            "category":"Retail",
            "subcategory":"Repair Shop",
            "type":"Services"
        }
    ],
    "sg:phone":"+44 1268 753736",
    "sg:postcode":"SS7 4AA",
    "sg:province":"Essex",
    "sg:tags":[
        "maintenance"
    ],
    "wof:name":"S H Taylor & Son",
    "wof:placetype":"venue"
},
  "geometry": {"coordinates":[0.5649809837,51.5707244873],"type":"Point"}
}