{
  "type": "Feature",
  "properties": {
    "iso:country":"GB",
    "sg:address":"The Street, Sedlescombe",
    "sg:city":"Battle",
    "sg:classifiers":[
        {
            "category":"Retail",
            "subcategory":"Repair Shop",
            "type":"Services"
        }
    ],
    "sg:phone":"+44 1424 870621",
    "sg:postcode":"TN33 0QJ",
    "sg:province":"East Sussex",
    "sg:tags":[
        "radio",
        "television",
        "video"
    ],
    "wof:name":"Expert Service",
    "wof:placetype":"venue"
},
  "geometry": {"coordinates":[0.53241,50.935558],"type":"Point"}
}