{
  "type": "Feature",
  "properties": {
    "iso:country":"GB",
    "sg:address":"10 Birch Grove, Martlesham Heath",
    "sg:city":"Ipswich",
    "sg:classifiers":[
        {
            "category":"Professional",
            "type":"Services"
        },
        {
            "category":"Social Services",
            "subcategory":"Job Training",
            "type":"Services"
        }
    ],
    "sg:phone":"+44 1473 610042",
    "sg:postcode":"IP5 3TD",
    "sg:province":"Suffolk",
    "sg:tags":[
        "translator",
        "interpreter",
        "translation",
        "activity"
    ],
    "wof:name":"Europa Translations",
    "wof:placetype":"venue"
},
  "geometry": {"coordinates":[1.2745039463,52.055229187],"type":"Point"}
}