{
  "type": "Feature",
  "properties": {
    "iso:country":"GB",
    "sg:address":"Kings Park, 5th Avenue Team Valley",
    "sg:city":"Gateshead",
    "sg:classifiers":[
        {
            "category":"Manufacturing",
            "subcategory":"Tools & Machinery",
            "type":"Manufacturing & Wholesale Goods"
        }
    ],
    "sg:phone":"+44 191 497 7180",
    "sg:postcode":"NE11 9AB",
    "sg:province":"Tyne and Wear",
    "sg:tags":[
        "design",
        "maker"
    ],
    "wof:name":"Amsys Rapid Prototyping & Tooling Ltd.",
    "wof:placetype":"venue"
},
  "geometry": {"coordinates":[-1.640650034,54.9518814087],"type":"Point"}
}