{
  "type": "Feature",
  "properties": {
    "iso:country":"GB",
    "sg:address":"37 Morpeth Avenue",
    "sg:city":"South Shields",
    "sg:classifiers":[
        {
            "category":"Bus Charters",
            "type":"Transportation"
        }
    ],
    "sg:phone":"+44 191 455 4295",
    "sg:postcode":"NE34 0SF",
    "sg:province":"Tyne and Wear",
    "sg:tags":[
        "hire",
        "coach"
    ],
    "wof:name":"Campbells Coaches",
    "wof:placetype":"venue"
},
  "geometry": {"coordinates":[-1.422586,54.982841],"type":"Point"}
}