{
  "type": "Feature",
  "properties": {
    "addr:full":"Darlowes Green, Eastern Esplanade Southend-on-sea Essex SS1 2ES",
    "addr:postcode":"ss1 2es",
    "addr:street":"Eastern Esplanade",
    "iso:country":"GB",
    "sg:address":"Darlowes Green, Eastern Esplanade",
    "sg:city":"Southend-on-sea",
    "sg:classifiers":[
        {
            "category":"Sports & Exercise",
            "subcategory":"Golf",
            "type":"Entertainment"
        }
    ],
    "sg:phone":"+44 1702 466540",
    "sg:postcode":"SS1 2ES",
    "sg:province":"Essex",
    "sg:tags":[
        "club",
        "course"
    ],
    "wof:name":"Arnold Palmer",
    "wof:placetype":"venue"
},
  "geometry": {"coordinates":[0.7280399799,51.5314407349],"type":"Point"}
}