{
  "type": "Feature",
  "properties": {
    "addr:full":"18 Paisley Avenue, Black Brook St Helens Lancashire WA11 9QN",
    "addr:housenumber":"18",
    "addr:postcode":"wa11 9qn",
    "addr:street":"Paisley Avenue Black Brook",
    "iso:country":"GB",
    "sg:address":"18 Paisley Avenue, Black Brook",
    "sg:city":"St Helens",
    "sg:classifiers":[
        {
            "category":"Arts & Performance",
            "subcategory":"Music",
            "type":"Entertainment"
        }
    ],
    "sg:phone":"+44 1744 818828",
    "sg:postcode":"WA11 9QN",
    "sg:province":"Lancashire",
    "sg:tags":[
        "mobile",
        "disco"
    ],
    "wof:name":"Daves Disco",
    "wof:placetype":"venue"
},
  "geometry": {"coordinates":[-2.706995,53.466076],"type":"Point"}
}