{
  "type": "Feature",
  "properties": {
    "iso:country":"GB",
    "sg:address":"Ham Wharf House, Ham",
    "sg:city":"Taunton",
    "sg:classifiers":[
        {
            "category":"Professional",
            "subcategory":"Management & Consulting",
            "type":"Services"
        }
    ],
    "sg:phone":"+44 1823 442178",
    "sg:postcode":"TA3 5NZ",
    "sg:province":"Devon",
    "sg:tags":[
        "consultant",
        "business"
    ],
    "wof:name":"Derek Johnson Ltd.",
    "wof:placetype":"venue"
},
  "geometry": {"coordinates":[-3.032546,51.020325],"type":"Point"}
}