{
  "type": "Feature",
  "properties": {
    "iso:country":"GB",
    "sg:address":"Hethersgill",
    "sg:city":"Carlisle",
    "sg:classifiers":[
        {
            "category":"Bars & Pubs",
            "type":"Food & Drink"
        }
    ],
    "sg:phone":"+44 1228 675318",
    "sg:postcode":"CA6 6EH",
    "sg:province":"Cumbria",
    "sg:tags":[
        "pubs",
        "inn"
    ],
    "wof:name":"The Black Lion",
    "wof:placetype":"venue"
},
  "geometry": {"coordinates":[-2.81736,54.996521],"type":"Point"}
}