{
  "type": "Feature",
  "properties": {
    "iso:country":"GB",
    "sg:address":"Dilston Close",
    "sg:city":"Washington",
    "sg:classifiers":[
        {
            "category":"Education",
            "subcategory":"School",
            "type":"Public Place"
        },
        {
            "category":"Government",
            "subcategory":"Office",
            "type":"Public Place"
        }
    ],
    "sg:phone":"+44 191 219 3777",
    "sg:postcode":"NE38 0LN",
    "sg:province":"Durham",
    "sg:tags":[
        "local",
        "authority"
    ],
    "wof:name":"Oxclose Community School",
    "wof:placetype":"venue"
},
  "geometry": {"coordinates":[-1.542641,54.895741],"type":"Point"}
}