{
  "type": "Feature",
  "properties": {
    "iso:country":"GB",
    "sg:address":"South Parade, Thorne",
    "sg:city":"Doncaster",
    "sg:classifiers":[
        {
            "category":"Professional",
            "subcategory":"Lawyer & Legal Services",
            "type":"Services"
        }
    ],
    "sg:phone":"+44 1405 813108",
    "sg:postcode":"DN8 5DX",
    "sg:province":"East Riding of Yorkshire",
    "sg:tags":[
        "solicitor"
    ],
    "wof:name":"Kenyon Son & Craddock",
    "wof:placetype":"venue"
},
  "geometry": {"coordinates":[-0.961637,53.611591],"type":"Point"}
}