{
  "type": "Feature",
  "properties": {
    "iso:country":"GB",
    "sg:address":"110 Princess Rd, Maybury Woking",
    "sg:city":"Woking",
    "sg:classifiers":[
        {
            "category":"Organizations",
            "subcategory":"Non-profit Organization",
            "type":"Services"
        }
    ],
    "sg:phone":"+44 1483 889467",
    "sg:postcode":"GU22 8ES",
    "sg:province":"Surrey",
    "sg:tags":[
        "organisation",
        "voluntary",
        "charity"
    ],
    "wof:name":"Foundation for Disaster Relief",
    "wof:placetype":"venue"
},
  "geometry": {"coordinates":[-0.537254,51.325161],"type":"Point"}
}