{
  "type": "Feature",
  "properties": {
    "iso:country":"GB",
    "sg:address":"1 Udall Street",
    "sg:city":"London",
    "sg:classifiers":[
        {
            "category":"Arena",
            "subcategory":"Bull Ring",
            "type":"Entertainment"
        }
    ],
    "sg:phone":"+44 20 7499 3411",
    "sg:postcode":"SW1P 2PR",
    "sg:province":"Greater London",
    "sg:tags":[
        "rating",
        "surveyor"
    ],
    "wof:name":"Bisset Moffatt & Hill",
    "wof:placetype":"venue"
},
  "geometry": {"coordinates":[-0.13658,51.492481],"type":"Point"}
}