{
  "type": "Feature",
  "properties": {
    "iso:country":"GB",
    "sg:address":"37 Frognal Court, Finchley Road",
    "sg:city":"London",
    "sg:classifiers":[
        {
            "category":"Banks & Credit Unions",
            "subcategory":"Financial Services",
            "type":"Services"
        }
    ],
    "sg:postcode":"NW3 5HG",
    "sg:province":"Greater London",
    "sg:tags":[
        "consultant"
    ],
    "wof:name":"Kingmaker Investments Ltd",
    "wof:placetype":"venue"
},
  "geometry": {"coordinates":[-0.180547,51.549072],"type":"Point"}
}