{
  "type": "Feature",
  "properties": {
    "addr:full":"69 The Street Ashtead Surrey KT21 1AA",
    "addr:housenumber":"69",
    "addr:postcode":"kt21 1aa",
    "addr:street":"The Street",
    "iso:country":"GB",
    "sg:address":"69 The Street",
    "sg:city":"Ashtead",
    "sg:classifiers":[
        {
            "category":"Personal",
            "subcategory":"Beauty Salon",
            "type":"Services"
        },
        {
            "category":"Personal",
            "subcategory":"Barber",
            "type":"Services"
        }
    ],
    "sg:phone":"+44 1372 275500",
    "sg:postcode":"KT21 1AA",
    "sg:province":"Surrey",
    "sg:tags":[
        "unisex",
        "lady",
        "hairdresser"
    ],
    "wof:name":"Hair Technique",
    "wof:placetype":"venue"
},
  "geometry": {"coordinates":[-0.2979770005,51.3103675842],"type":"Point"}
}