{
  "type": "Feature",
  "properties": {
    "addr:full":"Rear Of Crouch Engineering, Station Road Burnham On Crouch Essex CM0 8HQ",
    "addr:housenumber":"rear of crouch engineering",
    "addr:postcode":"cm0 8hq",
    "addr:street":"Station Road",
    "iso:country":"GB",
    "sg:address":"Rear Of Crouch Engineering, Station Road",
    "sg:city":"Burnham On Crouch",
    "sg:classifiers":[
        {
            "category":"Autos & Motor Vehicles",
            "subcategory":"Automobile Sales",
            "type":"Retail Goods"
        }
    ],
    "sg:phone":"+44 1621 785537",
    "sg:postcode":"CM0 8HQ",
    "sg:province":"Essex",
    "sg:tags":[
        "car"
    ],
    "wof:name":"B Dennerley",
    "wof:placetype":"venue"
},
  "geometry": {"coordinates":[0.8154270053,51.6318397522],"type":"Point"}
}