{
  "type": "Feature",
  "properties": {
    "iso:country":"GB",
    "sg:address":"37 Halesowen Road, Netherton",
    "sg:city":"Dudley",
    "sg:classifiers":[
        {
            "category":"Professional",
            "subcategory":"Printing & Photocopies",
            "type":"Services"
        }
    ],
    "sg:phone":"+44 1384 231464",
    "sg:postcode":"DY2 9QD",
    "sg:province":"West Midlands",
    "sg:tags":[
        "trophy"
    ],
    "wof:name":"D G Trophies",
    "wof:placetype":"venue"
},
  "geometry": {"coordinates":[-2.0808670521,52.4886398315],"type":"Point"}
}