{
  "type": "Feature",
  "properties": {
    "addr:full":"1 Park Road Dukinfield Greater Manchester SK16 5LX",
    "addr:housenumber":"1",
    "addr:postcode":"sk16 5lx",
    "addr:street":"Park Road",
    "iso:country":"GB",
    "sg:address":"1 Park Road",
    "sg:city":"Dukinfield",
    "sg:classifiers":[
        {
            "category":"Bars & Pubs",
            "type":"Food & Drink"
        }
    ],
    "sg:postcode":"SK16 5LX",
    "sg:province":"Greater Manchester",
    "sg:tags":[
        "pubs",
        "inn"
    ],
    "wof:name":"Tame Valley Hotel",
    "wof:placetype":"venue"
},
  "geometry": {"coordinates":[-2.0829930305,53.481803894],"type":"Point"}
}