{
  "type": "Feature",
  "properties": {
    "iso:country":"GB",
    "sg:address":"P O Box 696",
    "sg:city":"Brentwood",
    "sg:classifiers":[
        {
            "category":"Arena",
            "subcategory":"Sports Club",
            "type":"Entertainment"
        }
    ],
    "sg:phone":"+44 1277 262800",
    "sg:postcode":"CM14 4RL",
    "sg:province":"Essex",
    "wof:name":"Kazen Kai",
    "wof:placetype":"venue"
},
  "geometry": {"coordinates":[0.2949000001,51.6178588867],"type":"Point"}
}