{
  "type": "Feature",
  "properties": {
    "iso:country":"GB",
    "sg:address":"24 The Brickfields",
    "sg:city":"Ware",
    "sg:classifiers":[
        {
            "category":"Personal",
            "type":"Services"
        }
    ],
    "sg:postcode":"SG12 0AZ",
    "sg:province":"Hertfordshire",
    "sg:tags":[
        "wedding"
    ],
    "wof:name":"Flowers Forever",
    "wof:placetype":"venue"
},
  "geometry": {"coordinates":[-0.0482189991,51.8139038086],"type":"Point"}
}