{
  "type": "Feature",
  "properties": {
    "addr:full":"29 Pendle Court, Astley Bridge Bolton Lancashire BL1 6PY",
    "addr:housenumber":"29",
    "addr:postcode":"bl1 6py",
    "addr:street":"Pendle Court",
    "iso:country":"GB",
    "sg:address":"29 Pendle Court, Astley Bridge",
    "sg:city":"Bolton",
    "sg:classifiers":[
        {
            "category":"Autos & Motor Vehicles",
            "subcategory":"Auto Supplies",
            "type":"Retail Goods"
        }
    ],
    "sg:phone":"+44 1204 592288",
    "sg:postcode":"BL1 6PY",
    "sg:province":"Lancashire",
    "sg:tags":[
        "windscreen"
    ],
    "wof:name":"Award Windscreens",
    "wof:placetype":"venue"
},
  "geometry": {"coordinates":[-2.440819025,53.5984306335],"type":"Point"}
}