{
  "type": "Feature",
  "properties": {
    "addr:full":"56 Union St Torquay Devon TQ2 5PS",
    "addr:housenumber":"56",
    "addr:postcode":"tq2 5ps",
    "addr:street":"Union St",
    "iso:country":"GB",
    "sg:address":"56 Union St",
    "sg:city":"Torquay",
    "sg:classifiers":[
        {
            "category":"Retail",
            "subcategory":"Laundry & Dry Cleaning",
            "type":"Services"
        }
    ],
    "sg:phone":"+44 1803 298501",
    "sg:postcode":"TQ2 5PS",
    "sg:province":"Devon",
    "sg:tags":[
        "alteration"
    ],
    "wof:name":"Kneels Ltd",
    "wof:placetype":"venue"
},
  "geometry": {"coordinates":[-3.529621,50.466484],"type":"Point"}
}