{
  "type": "Feature",
  "properties": {
    "addr:full":"24 Pinner Hill Rd Pinner Greater London HA5 3SB",
    "addr:housenumber":"24",
    "addr:postcode":"ha5 3sb",
    "addr:street":"Pinner Hill Rd",
    "iso:country":"GB",
    "sg:address":"24 Pinner Hill Rd",
    "sg:city":"Pinner",
    "sg:classifiers":[
        {
            "category":"Professional",
            "subcategory":"Employment Agencies",
            "type":"Services"
        }
    ],
    "sg:phone":"+44 20 8429 2251",
    "sg:postcode":"HA5 3SB",
    "sg:province":"Greater London",
    "sg:tags":[
        "consultant"
    ],
    "wof:name":"Alpha Link Recruitment Consultants",
    "wof:placetype":"venue"
},
  "geometry": {"coordinates":[-0.395312,51.59996],"type":"Point"}
}