{
  "type": "Feature",
  "properties": {
    "iso:country":"GB",
    "sg:address":"Unit 1 Midland Rd",
    "sg:city":"Wednesbury",
    "sg:classifiers":[
        {
            "category":"Wholesale",
            "subcategory":"Metals & Minerals",
            "type":"Manufacturing & Wholesale Goods"
        }
    ],
    "sg:phone":"+44 121 568 8010",
    "sg:postcode":"WS10 8HX",
    "sg:province":"West Midlands",
    "sg:tags":[
        "aluminium",
        "stockholder"
    ],
    "wof:name":"Birmingham Non Ferrous Metals",
    "wof:placetype":"venue"
},
  "geometry": {"coordinates":[-2.039264,52.57655],"type":"Point"}
}