{
  "type": "Feature",
  "properties": {
    "addr:full":"Solent View, Southlands School, Vicars Hill Lymington Hampshire SO41 5QB",
    "addr:postcode":"so41 5qb",
    "addr:street":"Solent View;Vicars Hill",
    "iso:country":"GB",
    "sg:address":"Solent View, Southlands School, Vicars Hill",
    "sg:city":"Lymington",
    "sg:classifiers":[
        {
            "category":"Education",
            "subcategory":"Special Training",
            "type":"Public Place"
        }
    ],
    "sg:phone":"+44 1590 677986",
    "sg:postcode":"SO41 5QB",
    "sg:province":"Hampshire",
    "sg:tags":[
        "school"
    ],
    "wof:name":"Solent View School The",
    "wof:placetype":"venue"
},
  "geometry": {"coordinates":[-1.538910985,50.7589378357],"type":"Point"}
}