{
  "type": "Feature",
  "properties": {
    "iso:country":"GB",
    "sg:address":"82-84 York Road, Bedminster",
    "sg:city":"Bristol",
    "sg:classifiers":[
        {
            "category":"Professional",
            "subcategory":"Computer Services",
            "type":"Services"
        }
    ],
    "sg:postcode":"BS3 4AL",
    "sg:province":"City of Bristol",
    "sg:tags":[
        "system",
        "software"
    ],
    "wof:name":"Maindisc Computer Services",
    "wof:placetype":"venue"
},
  "geometry": {"coordinates":[-2.5885739326,51.4446868896],"type":"Point"}
}