{
  "type": "Feature",
  "properties": {
    "iso:country":"GB",
    "sg:address":"Collins Green, School Rd",
    "sg:city":"Colchester",
    "sg:classifiers":[
        {
            "category":"Building & Trades",
            "subcategory":"Plumbing",
            "type":"Services"
        }
    ],
    "sg:phone":"+44 1621 815546",
    "sg:postcode":"CO5 9TH",
    "sg:province":"Essex",
    "sg:tags":[
        "heating"
    ],
    "wof:name":"I G Bennett",
    "wof:placetype":"venue"
},
  "geometry": {"coordinates":[0.7498099804,51.8336296082],"type":"Point"}
}