{
  "type": "Feature",
  "properties": {
    "iso:country":"GB",
    "sg:address":"10 East Grinstead Road",
    "sg:city":"Lingfield",
    "sg:classifiers":[
        {
            "category":"Food & Beverages",
            "subcategory":"Supermarket",
            "type":"Retail Goods"
        }
    ],
    "sg:phone":"+44 1342 833415",
    "sg:postcode":"RH7 6EP",
    "sg:province":"Surrey",
    "wof:name":"Costcutter",
    "wof:placetype":"venue"
},
  "geometry": {"coordinates":[-0.0185,51.173927],"type":"Point"}
}