{
  "type": "Feature",
  "properties": {
    "addr:full":"7 Princess Street Aberystwyth Ceredigion SY23 1DX",
    "addr:housenumber":"7",
    "addr:postcode":"sy23 1dx",
    "addr:street":"Princess Street",
    "iso:country":"GB",
    "sg:address":"7 Princess Street",
    "sg:city":"Aberystwyth",
    "sg:classifiers":[
        {
            "category":"Shopping",
            "subcategory":"Books",
            "type":"Retail Goods"
        }
    ],
    "sg:phone":"+44 1970 639479",
    "sg:postcode":"SY23 1DX",
    "sg:province":"Ceredigion",
    "sg:tags":[
        "bookseller",
        "retailer"
    ],
    "wof:name":"Ystwyth Books",
    "wof:placetype":"venue"
},
  "geometry": {"coordinates":[-4.0862622261,52.4137268066],"type":"Point"}
}