{
  "type": "Feature",
  "properties": {
    "addr:full":"60 Front Street Consett Durham DH8 5AL",
    "addr:housenumber":"60",
    "addr:postcode":"dh8 5al",
    "addr:street":"Front Street",
    "iso:country":"GB",
    "sg:address":"60 Front Street",
    "sg:city":"Consett",
    "sg:classifiers":[
        {
            "category":"Food & Beverages",
            "subcategory":"Meat & Fish",
            "type":"Retail Goods"
        }
    ],
    "sg:phone":"+44 1207 502017",
    "sg:postcode":"DH8 5AL",
    "sg:province":"Durham",
    "sg:tags":[
        "butcher"
    ],
    "wof:name":"J E Thackeray & Sons",
    "wof:placetype":"venue"
},
  "geometry": {"coordinates":[-1.830575943,54.8518486023],"type":"Point"}
}