{
  "type": "Feature",
  "properties": {
    "iso:country":"GB",
    "sg:address":"87 Fleet Road",
    "sg:city":"Fleet",
    "sg:classifiers":[
        {
            "category":"Freight",
            "type":"Transportation"
        }
    ],
    "sg:postcode":"GU51 3PJ",
    "sg:province":"Hampshire",
    "sg:tags":[
        "forwarders"
    ],
    "wof:name":"C M C Shipping Ltd.",
    "wof:placetype":"venue"
},
  "geometry": {"coordinates":[-0.836211,51.286076],"type":"Point"}
}