{
  "type": "Feature",
  "properties": {
    "addr:full":"25a Dudley St Wolverhampton West Midlands WV1 3EY",
    "addr:housenumber":"25a",
    "addr:postcode":"wv1 3ey",
    "addr:street":"Dudley St",
    "iso:country":"GB",
    "sg:address":"25a Dudley St",
    "sg:city":"Wolverhampton",
    "sg:classifiers":[
        {
            "category":"Shopping",
            "subcategory":"Shoes",
            "type":"Retail Goods"
        }
    ],
    "sg:phone":"+44 1902 712581",
    "sg:postcode":"WV1 3EY",
    "sg:province":"West Midlands",
    "sg:tags":[
        "shop"
    ],
    "wof:name":"Shoefayre Ltd",
    "wof:placetype":"venue"
},
  "geometry": {"coordinates":[-2.127117,52.584599],"type":"Point"}
}