{
  "type": "Feature",
  "properties": {
    "addr:full":"3 Lawrence Drive Uxbridge Greater London UB10 8RN",
    "addr:housenumber":"3",
    "addr:postcode":"ub10 8rn",
    "addr:street":"Lawrence Drive",
    "iso:country":"GB",
    "sg:address":"3 Lawrence Drive",
    "sg:city":"Uxbridge",
    "sg:classifiers":[
        {
            "category":"Wholesale",
            "subcategory":"Meat",
            "type":"Manufacturing & Wholesale Goods"
        }
    ],
    "sg:phone":"+44 1895 639624",
    "sg:postcode":"UB10 8RN",
    "sg:province":"Greater London",
    "sg:tags":[
        "wholesaler",
        "-"
    ],
    "wof:name":"J H Nelson (Meat Wholesalers) Ltd.",
    "wof:placetype":"venue"
},
  "geometry": {"coordinates":[-0.4373939931,51.5611495972],"type":"Point"}
}