{
  "type": "Feature",
  "properties": {
    "addr:full":"1 Thorkhill Gardens Thames Ditton Surrey KT7 0UP",
    "addr:housenumber":"1",
    "addr:postcode":"kt7 0up",
    "addr:street":"Thorkhill Gardens;Ditton",
    "iso:country":"GB",
    "sg:address":"1 Thorkhill Gardens",
    "sg:city":"Thames Ditton",
    "sg:classifiers":[
        {
            "category":"Building & Trades",
            "subcategory":"Construction",
            "type":"Services"
        }
    ],
    "sg:phone":"+44 20 8398 9861",
    "sg:postcode":"KT7 0UP",
    "sg:province":"Surrey",
    "sg:tags":[
        "joiner",
        "carpenter"
    ],
    "wof:name":"Alexander Associates Building Specialists",
    "wof:placetype":"venue"
},
  "geometry": {"coordinates":[-0.3267700076,51.3846969604],"type":"Point"}
}