{
  "type": "Feature",
  "properties": {
    "iso:country":"GB",
    "sg:address":"4 Park Terrace",
    "sg:city":"Glasgow",
    "sg:classifiers":[
        {
            "category":"Communications",
            "type":"Services"
        }
    ],
    "sg:phone":"+44 141 332 6300",
    "sg:postcode":"G3 6BY",
    "sg:province":"Glasgow City",
    "sg:tags":[
        "telecommunication"
    ],
    "wof:name":"Ecosse Telecommunications Ltd.",
    "wof:placetype":"venue"
},
  "geometry": {"coordinates":[-4.280115,55.869705],"type":"Point"}
}