{
  "type": "Feature",
  "properties": {
    "addr:full":"London Road Bicester Oxfordshire OX6 0JL",
    "addr:postcode":"ox6 0jl",
    "addr:street":"London Road",
    "iso:country":"GB",
    "sg:address":"London Road",
    "sg:city":"Bicester",
    "sg:classifiers":[
        {
            "category":"Autos & Motor Vehicles",
            "subcategory":"Automobile Sales",
            "type":"Retail Goods"
        }
    ],
    "sg:phone":"+44 1869 244000",
    "sg:postcode":"OX6 0JL",
    "sg:province":"Oxfordshire",
    "sg:tags":[
        "car"
    ],
    "wof:name":"City Motors (Oxford) Ltd.",
    "wof:placetype":"venue"
},
  "geometry": {"coordinates":[-1.1496709585,51.8963012695],"type":"Point"}
}