{
  "type": "Feature",
  "properties": {
    "addr:full":"Market Place, Chapel En Le Frith High Peak Cheshire SK23 0EN",
    "addr:postcode":"sk23 0en",
    "addr:street":"Market Place Chapel",
    "iso:country":"GB",
    "sg:address":"Market Place, Chapel En Le Frith",
    "sg:city":"High Peak",
    "sg:classifiers":[
        {
            "category":"Travel",
            "subcategory":"Hotels & Motels",
            "type":"Entertainment"
        },
        {
            "category":"Community Center",
            "subcategory":"Social",
            "type":"Public Place"
        }
    ],
    "sg:phone":"+44 1298 812105",
    "sg:postcode":"SK23 0EN",
    "sg:province":"Cheshire",
    "sg:tags":[
        "house",
        "activity"
    ],
    "wof:name":"KINGS ARMS HOTEL",
    "wof:placetype":"venue"
},
  "geometry": {"coordinates":[-1.9170930386,53.3228492737],"type":"Point"}
}