{
  "type": "Feature",
  "properties": {
    "iso:country":"GB",
    "sg:address":"8 Millers Meadow, Rainow",
    "sg:city":"Macclesfield",
    "sg:classifiers":[
        {
            "category":"Professional",
            "subcategory":"Management & Consulting",
            "type":"Services"
        }
    ],
    "sg:phone":"+44 1625 573763",
    "sg:postcode":"SK10 5UE",
    "sg:province":"Cheshire",
    "sg:tags":[
        "consultant",
        "energy",
        "conservation"
    ],
    "wof:name":"Miltec System Design",
    "wof:placetype":"venue"
},
  "geometry": {"coordinates":[-2.0742809772,53.2828216553],"type":"Point"}
}