{
  "type": "Feature",
  "properties": {
    "iso:country":"GB",
    "sg:address":"127 Heathfield, Pound Hill,",
    "sg:city":"Crawley",
    "sg:classifiers":[
        {
            "category":"Building & Trades",
            "subcategory":"Construction",
            "type":"Services"
        }
    ],
    "sg:postcode":"RH10 3UU",
    "sg:province":"Surrey",
    "sg:tags":[
        "builder"
    ],
    "wof:name":"D B Enterprises",
    "wof:placetype":"venue"
},
  "geometry": {"coordinates":[-0.126364,51.13345],"type":"Point"}
}