{
  "type": "Feature",
  "properties": {
    "addr:full":"21 Briar Road Romford Essex RM3 8AH",
    "addr:housenumber":"21",
    "addr:postcode":"rm3 8ah",
    "addr:street":"Briar Road",
    "iso:country":"GB",
    "sg:address":"21 Briar Road",
    "sg:city":"Romford",
    "sg:classifiers":[
        {
            "category":"Food & Beverages",
            "subcategory":"Bakery",
            "type":"Retail Goods"
        }
    ],
    "sg:phone":"+44 1708 371341",
    "sg:postcode":"RM3 8AH",
    "sg:province":"Essex",
    "sg:tags":[
        "baker"
    ],
    "wof:name":"Cosson & Son",
    "wof:placetype":"venue"
},
  "geometry": {"coordinates":[0.2133679986,51.6003837585],"type":"Point"}
}