{
  "type": "Feature",
  "properties": {
    "iso:country":"GB",
    "sg:address":"Petitor Crescent, Deedmore Road",
    "sg:city":"Coventry",
    "sg:classifiers":[
        {
            "category":"Education",
            "subcategory":"Special Training",
            "type":"Public Place"
        },
        {
            "category":"Government",
            "subcategory":"Office",
            "type":"Public Place"
        }
    ],
    "sg:phone":"+44 24 7661 2271",
    "sg:postcode":"CV2 1EW",
    "sg:province":"Warwickshire",
    "sg:tags":[
        "school",
        "local"
    ],
    "wof:name":"Deedmore Special School",
    "wof:placetype":"venue"
},
  "geometry": {"coordinates":[-1.466921,52.435345],"type":"Point"}
}