{
  "type": "Feature",
  "properties": {
    "addr:full":"Highbury Exeter Devon EX4 2AP",
    "addr:postcode":"ex4 2ap",
    "addr:street":"Highbury",
    "iso:country":"GB",
    "sg:address":"Highbury",
    "sg:city":"Exeter",
    "sg:classifiers":[
        {
            "category":"Building & Trades",
            "subcategory":"Construction",
            "type":"Services"
        }
    ],
    "sg:postcode":"EX4 2AP",
    "sg:province":"Devon",
    "sg:tags":[
        "decorator",
        "painter"
    ],
    "wof:name":"Lion Decorating",
    "wof:placetype":"venue"
},
  "geometry": {"coordinates":[-3.567556,50.727592],"type":"Point"}
}