{
  "type": "Feature",
  "properties": {
    "addr:full":"3rd Floor, 231 The Vale London Greater London W3 7QS",
    "addr:housenumber":"3rd floor 231",
    "addr:postcode":"w3 7qs",
    "addr:street":"The Vale",
    "iso:country":"GB",
    "sg:address":"3rd Floor, 231 The Vale",
    "sg:city":"London",
    "sg:classifiers":[
        {
            "category":"Manufacturing",
            "subcategory":"Furniture",
            "type":"Manufacturing & Wholesale Goods"
        }
    ],
    "sg:phone":"+44 20 8749 7670",
    "sg:postcode":"W3 7QS",
    "sg:province":"Greater London",
    "sg:tags":[
        "design"
    ],
    "wof:name":"Ben Brooks",
    "wof:placetype":"venue"
},
  "geometry": {"coordinates":[-0.2607829869,51.5062942505],"type":"Point"}
}