{
  "type": "Feature",
  "properties": {
    "addr:full":"The Courtyard, Frogmoor High Wycombe Buckinghamshire HP13 5DJ",
    "addr:postcode":"hp13 5dj",
    "iso:country":"GB",
    "sg:address":"The Courtyard, Frogmoor",
    "sg:city":"High Wycombe",
    "sg:classifiers":[
        {
            "category":"Shopping",
            "subcategory":"Computers & Home Electronics",
            "type":"Retail Goods"
        }
    ],
    "sg:phone":"+44 1494 510000",
    "sg:postcode":"HP13 5DJ",
    "sg:province":"Buckinghamshire",
    "wof:name":"Cornwell Parker 1995 Ltd",
    "wof:placetype":"venue"
},
  "geometry": {"coordinates":[-0.7477890253,51.628944397],"type":"Point"}
}