{
  "type": "Feature",
  "properties": {
    "addr:full":"1-5 Martyrs Avenue, Langley Grn Crawley West Sussex RH11 7RX",
    "addr:postcode":"rh11 7rx",
    "addr:street":"1-5 Martyrs Avenue;Grn",
    "iso:country":"GB",
    "sg:address":"1-5 Martyrs Avenue, Langley Grn",
    "sg:city":"Crawley",
    "sg:classifiers":[
        {
            "category":"Professional",
            "subcategory":"Engineering",
            "type":"Services"
        }
    ],
    "sg:phone":"+44 1293 525260",
    "sg:postcode":"RH11 7RX",
    "sg:province":"West Sussex",
    "sg:tags":[
        "precision",
        "engineer"
    ],
    "wof:name":"Broadbridge Precision Engineering Ltd.",
    "wof:placetype":"venue"
},
  "geometry": {"coordinates":[-0.188241,51.131046],"type":"Point"}
}