{
  "type": "Feature",
  "properties": {
    "addr:full":"244 Merton Road London Greater London SW18 5JQ",
    "addr:housenumber":"244",
    "addr:postcode":"sw18 5jq",
    "addr:street":"Merton Road",
    "iso:country":"GB",
    "sg:address":"244 Merton Road",
    "sg:city":"London",
    "sg:classifiers":[
        {
            "category":"Education",
            "subcategory":"Music School",
            "type":"Public Place"
        }
    ],
    "sg:phone":"+44 20 8871 0154",
    "sg:postcode":"SW18 5JQ",
    "sg:province":"Greater London",
    "sg:tags":[
        "teacher"
    ],
    "wof:name":"David Piano Keyboard Tuition",
    "wof:placetype":"venue"
},
  "geometry": {"coordinates":[-0.199653,51.448704],"type":"Point"}
}