{
  "type": "Feature",
  "properties": {
    "addr:full":"53 Maple Rd Penge Greater London SE20 8LA",
    "addr:housenumber":"53",
    "addr:postcode":"se20 8la",
    "addr:street":"Maple Rd",
    "iso:country":"GB",
    "sg:address":"53 Maple Rd",
    "sg:city":"Penge",
    "sg:classifiers":[
        {
            "category":"Food & Beverages",
            "subcategory":"Meat & Fish",
            "type":"Retail Goods"
        }
    ],
    "sg:phone":"+44 20 8778 5545",
    "sg:postcode":"SE20 8LA",
    "sg:province":"Greater London",
    "sg:tags":[
        "chip"
    ],
    "wof:name":"Ossie's Plaice",
    "wof:placetype":"venue"
},
  "geometry": {"coordinates":[-0.058993,51.411644],"type":"Point"}
}