{
  "type": "Feature",
  "properties": {
    "iso:country":"GB",
    "sg:address":"Dintonia, Lower Road, Quidhampton",
    "sg:city":"Salisbury",
    "sg:classifiers":[
        {
            "category":"Communications",
            "type":"Services"
        }
    ],
    "sg:phone":"+44 1722 743080",
    "sg:postcode":"SP2 9AT",
    "sg:province":"Wiltshire",
    "sg:tags":[
        "audio-visual"
    ],
    "wof:name":"Stephen Wagstaff",
    "wof:placetype":"venue"
},
  "geometry": {"coordinates":[-1.846062,51.078514],"type":"Point"}
}