{
  "type": "Feature",
  "properties": {
    "addr:full":"29 The Dell, Plympton Plymouth Devon PL7 4PS",
    "addr:housenumber":"29",
    "addr:postcode":"pl7 4ps",
    "addr:street":"The Dell",
    "iso:country":"GB",
    "sg:address":"29 The Dell, Plympton",
    "sg:city":"Plymouth",
    "sg:classifiers":[
        {
            "category":"Banks & Credit Unions",
            "subcategory":"Financial Services",
            "type":"Services"
        }
    ],
    "sg:phone":"+44 1752 345500",
    "sg:postcode":"PL7 4PS",
    "sg:province":"Devon",
    "sg:tags":[
        "claim",
        "assessor"
    ],
    "wof:name":"Milligan (Assessors) Ltd.",
    "wof:placetype":"venue"
},
  "geometry": {"coordinates":[-4.0708141327,50.393371582],"type":"Point"}
}