{
  "type": "Feature",
  "properties": {
    "addr:full":"Stall 3 Brighton Open Market, Francis Street Brighton East Sussex BN1 4JT",
    "addr:housenumber":"stall 3 brighton",
    "addr:postcode":"bn1 4jt",
    "addr:street":"Francis Street",
    "iso:country":"GB",
    "sg:address":"Stall 3 Brighton Open Market, Francis Street",
    "sg:city":"Brighton",
    "sg:classifiers":[
        {
            "category":"Farming",
            "subcategory":"Farm",
            "type":"Manufacturing & Wholesale Goods"
        }
    ],
    "sg:phone":"+44 1273 683027",
    "sg:postcode":"BN1 4JT",
    "sg:province":"East Sussex",
    "sg:tags":[
        "egg",
        "producer"
    ],
    "wof:name":"The Egg Shop",
    "wof:placetype":"venue"
},
  "geometry": {"coordinates":[-0.135739997,50.831161499],"type":"Point"}
}