{
  "type": "Feature",
  "properties": {
    "addr:full":"96-98 Merritt Road, Greatstone New Romney Kent TN28 8SZ",
    "addr:housenumber":"96-98",
    "addr:postcode":"tn28 8sz",
    "addr:street":"Merritt Road",
    "iso:country":"GB",
    "sg:address":"96-98 Merritt Road, Greatstone",
    "sg:city":"New Romney",
    "sg:classifiers":[
        {
            "category":"Shopping",
            "subcategory":"Computers & Home Electronics",
            "type":"Retail Goods"
        },
        {
            "category":"Professional",
            "subcategory":"Computer Services",
            "type":"Services"
        }
    ],
    "sg:phone":"+44 1797 366333",
    "sg:postcode":"TN28 8SZ",
    "sg:province":"Kent",
    "sg:tags":[
        "system",
        "software"
    ],
    "wof:name":"Comtec Computers Ltd.",
    "wof:placetype":"venue"
},
  "geometry": {"coordinates":[0.962038,50.965092],"type":"Point"}
}