{
  "type": "Feature",
  "properties": {
    "iso:country":"GB",
    "sg:address":"New Farm, Moor Road, Fordham",
    "sg:city":"Ely",
    "sg:classifiers":[
        {
            "category":"Farming",
            "subcategory":"Livestock Farm",
            "type":"Manufacturing & Wholesale Goods"
        }
    ],
    "sg:phone":"+44 1638 720346",
    "sg:postcode":"CB7 5LX",
    "sg:province":"Cambridgeshire",
    "sg:tags":[
        "others"
    ],
    "wof:name":"Philip Frederick Boon",
    "wof:placetype":"venue"
},
  "geometry": {"coordinates":[0.384086,52.311432],"type":"Point"}
}