{
  "type": "Feature",
  "properties": {
    "addr:full":"14 Dover Close Rushden Bedfordshire NN10 0RQ",
    "addr:housenumber":"14",
    "addr:postcode":"nn10 0rq",
    "addr:street":"Dover Close",
    "iso:country":"GB",
    "sg:address":"14 Dover Close",
    "sg:city":"Rushden",
    "sg:classifiers":[
        {
            "category":"Wholesale",
            "subcategory":"Office Equipment",
            "type":"Manufacturing & Wholesale Goods"
        },
        {
            "category":"Government",
            "subcategory":"Post Office",
            "type":"Public Place"
        }
    ],
    "sg:phone":"+44 1933 411452",
    "sg:postcode":"NN10 0RQ",
    "sg:province":"Bedfordshire",
    "sg:tags":[
        "register",
        "cash",
        "accessory"
    ],
    "wof:name":"Ensign Cash Registers",
    "wof:placetype":"venue"
},
  "geometry": {"coordinates":[-0.583608,52.284756],"type":"Point"}
}