{
  "type": "Feature",
  "properties": {
    "iso:country":"GB",
    "sg:address":"3 Bourton Close, Tilehurst",
    "sg:city":"Reading",
    "sg:classifiers":[
        {
            "category":"Professional",
            "subcategory":"Engineering",
            "type":"Services"
        }
    ],
    "sg:phone":"+44 118 942 2281",
    "sg:postcode":"RG30 4LB",
    "sg:province":"Berkshire",
    "sg:tags":[
        "contractor",
        "electrical",
        "engineer"
    ],
    "wof:name":"G G Hatter",
    "wof:placetype":"venue"
},
  "geometry": {"coordinates":[-1.0267150402,51.45495224],"type":"Point"}
}