{
  "type": "Feature",
  "properties": {
    "iso:country":"GB",
    "sg:address":"Hill Farm, Holme Hale",
    "sg:city":"Thetford",
    "sg:classifiers":[
        {
            "category":"Farming",
            "subcategory":"Crops",
            "type":"Manufacturing & Wholesale Goods"
        },
        {
            "category":"Farming",
            "subcategory":"Livestock Farm",
            "type":"Manufacturing & Wholesale Goods"
        }
    ],
    "sg:phone":"+44 1760 441071",
    "sg:postcode":"IP25 7EF",
    "sg:province":"Norfolk",
    "sg:tags":[
        "arable",
        "others"
    ],
    "wof:name":"Brooke Bros Farmers",
    "wof:placetype":"venue"
},
  "geometry": {"coordinates":[0.823984,52.603981],"type":"Point"}
}