{
  "type": "Feature",
  "properties": {
    "iso:country":"GB",
    "sg:address":"27-28 Windmill Street",
    "sg:city":"Gravesend",
    "sg:classifiers":[
        {
            "category":"Real Estate",
            "subcategory":"Real Estate Agent",
            "type":"Services"
        }
    ],
    "sg:phone":"+44 1474 332981",
    "sg:postcode":"DA12 1AX",
    "sg:province":"Kent",
    "wof:name":"Walker Croft & Jarvis",
    "wof:placetype":"venue"
},
  "geometry": {"coordinates":[0.369312,51.440472],"type":"Point"}
}