{
  "type": "Feature",
  "properties": {
    "iso:country":"GB",
    "sg:address":"Coleham Depot, Betton St",
    "sg:city":"Shrewsbury",
    "sg:classifiers":[
        {
            "category":"Train Station",
            "subcategory":"Rail",
            "type":"Transportation"
        }
    ],
    "sg:phone":"+44 1743 241978",
    "sg:postcode":"SY3 7LJ",
    "sg:province":"Shropshire",
    "sg:tags":[
        "railway"
    ],
    "wof:name":"Bridge Examiners GTRM",
    "wof:placetype":"venue"
},
  "geometry": {"coordinates":[-2.746609,52.70657],"type":"Point"}
}