{
  "type": "Feature",
  "properties": {
    "addr:full":"40 Byne Road London Greater London SE26 5JE",
    "addr:housenumber":"40",
    "addr:postcode":"se26 5je",
    "addr:street":"Byne Road",
    "iso:country":"GB",
    "sg:address":"40 Byne Road",
    "sg:city":"London",
    "sg:classifiers":[
        {
            "category":"Manufacturing",
            "subcategory":"Printing",
            "type":"Manufacturing & Wholesale Goods"
        }
    ],
    "sg:postcode":"SE26 5JE",
    "sg:province":"Greater London",
    "sg:tags":[
        "bookbinder"
    ],
    "wof:name":"W J Holder & Sons",
    "wof:placetype":"venue"
},
  "geometry": {"coordinates":[-0.0543260016,51.4218406677],"type":"Point"}
}