{
  "type": "Feature",
  "properties": {
    "iso:country":"GB",
    "sg:address":"56 Albion St",
    "sg:city":"London",
    "sg:classifiers":[
        {
            "category":"Bars & Pubs",
            "type":"Food & Drink"
        }
    ],
    "sg:postcode":"SE16 7JQ",
    "sg:province":"Greater London",
    "sg:tags":[
        "pubs",
        "inn"
    ],
    "wof:name":"Little Crown",
    "wof:placetype":"venue"
},
  "geometry": {"coordinates":[-0.05357,51.49918],"type":"Point"}
}