{
  "type": "Feature",
  "properties": {
    "addr:full":"187 Camden High St Camden Greater London NW1 7JY",
    "addr:housenumber":"187",
    "addr:postcode":"nw1 7jy",
    "addr:street":"Camden High St",
    "iso:country":"GB",
    "sg:address":"187 Camden High St",
    "sg:city":"Camden",
    "sg:classifiers":[
        {
            "category":"Sports & Exercise",
            "subcategory":"Sports Center",
            "type":"Entertainment"
        }
    ],
    "sg:phone":"+44 20 7267 6622",
    "sg:postcode":"NW1 7JY",
    "sg:province":"Greater London",
    "sg:tags":[
        "shop",
        "good"
    ],
    "wof:name":"Super Sport",
    "wof:placetype":"venue"
},
  "geometry": {"coordinates":[-0.143015,51.539696],"type":"Point"}
}