{
  "type": "Feature",
  "properties": {
    "iso:country":"GB",
    "sg:address":"Scotland Farm, Carburton",
    "sg:city":"Worksop",
    "sg:classifiers":[
        {
            "category":"Freight",
            "type":"Transportation"
        }
    ],
    "sg:phone":"+44 1909 475500",
    "sg:postcode":"S80 3BL",
    "sg:province":"Nottinghamshire",
    "sg:tags":[
        "haulage",
        "road"
    ],
    "wof:name":"Worksop Industrial Tippers Ltd.",
    "wof:placetype":"venue"
},
  "geometry": {"coordinates":[-1.084104,53.25222],"type":"Point"}
}