{
  "type": "Feature",
  "properties": {
    "addr:full":"St John Ambulance Head Quarters, Heanton Street Braunton Devon EX33 2JS",
    "addr:postcode":"ex33 2js",
    "addr:street":"Heanton Street",
    "iso:country":"GB",
    "sg:address":"St John Ambulance Head Quarters, Heanton Street",
    "sg:city":"Braunton",
    "sg:classifiers":[
        {
            "category":"Organizations",
            "subcategory":"Non-profit Organization",
            "type":"Services"
        }
    ],
    "sg:phone":"+44 1271 815983",
    "sg:postcode":"EX33 2JS",
    "sg:province":"Devon",
    "sg:tags":[
        "charitable",
        "organisation",
        "voluntary",
        "charity"
    ],
    "wof:name":"St John Ambulance",
    "wof:placetype":"venue"
},
  "geometry": {"coordinates":[-4.1616492271,51.1098175049],"type":"Point"}
}