{
  "type": "Feature",
  "properties": {
    "iso:country":"GB",
    "sg:address":"14 Bulganak Road",
    "sg:city":"Thornton Heath",
    "sg:classifiers":[
        {
            "category":"Shopping",
            "subcategory":"Pharmacy",
            "type":"Retail Goods"
        }
    ],
    "sg:postcode":"CR7 8JA",
    "sg:province":"Surrey",
    "sg:tags":[
        "medicine",
        "therapy"
    ],
    "wof:name":"Savida Bhandari",
    "wof:placetype":"venue"
},
  "geometry": {"coordinates":[-0.1007419974,51.3999328613],"type":"Point"}
}