{
  "type": "Feature",
  "properties": {
    "addr:full":"Unit 4 Parsons Hall, High Street, Industrial Estate Wellingborough Bedfordshire NN29 7AB",
    "addr:housenumber":"unit 4;hall",
    "addr:postcode":"estate;nn29 7ab",
    "addr:street":"Parsons;High Street Industrial",
    "iso:country":"GB",
    "sg:address":"Unit 4 Parsons Hall, High Street, Industrial Estate",
    "sg:city":"Wellingborough",
    "sg:classifiers":[
        {
            "category":"Military Area",
            "subcategory":"Air Force Base",
            "type":"Public Place"
        }
    ],
    "sg:phone":"+44 1933 410066",
    "sg:postcode":"NN29 7AB",
    "sg:province":"Bedfordshire",
    "sg:tags":[
        "water",
        "treatment"
    ],
    "wof:name":"Beacon Water Treatment Ltd.",
    "wof:placetype":"venue"
},
  "geometry": {"coordinates":[-0.64313,52.286861],"type":"Point"}
}