{
  "type": "Feature",
  "properties": {
    "iso:country":"GB",
    "sg:address":"478 Cricklade Road",
    "sg:city":"Swindon",
    "sg:classifiers":[
        {
            "category":"Health Services",
            "subcategory":"Doctor",
            "type":"Services"
        }
    ],
    "sg:phone":"+44 1793 725113",
    "sg:postcode":"SN2 7BG",
    "sg:province":"Wiltshire",
    "sg:tags":[
        "practitioners"
    ],
    "wof:name":"Crossroads Surgery",
    "wof:placetype":"venue"
},
  "geometry": {"coordinates":[-1.7749370337,51.5841903687],"type":"Point"}
}