{
  "type": "Feature",
  "properties": {
    "addr:full":"496a Katherine Rd Forest Gate Greater London E7 8DP",
    "addr:housenumber":"496a",
    "addr:postcode":"e7 8dp",
    "addr:street":"Katherine Rd;Gate",
    "iso:country":"GB",
    "sg:address":"496a Katherine Rd",
    "sg:city":"Forest Gate",
    "sg:classifiers":[
        {
            "category":"Retail",
            "subcategory":"Auto Repair",
            "type":"Services"
        }
    ],
    "sg:phone":"+44 20 8470 9111",
    "sg:postcode":"E7 8DP",
    "sg:province":"Greater London",
    "sg:tags":[
        "modification",
        "garage"
    ],
    "wof:name":"Prestige Car Specialists",
    "wof:placetype":"venue"
},
  "geometry": {"coordinates":[0.036723,51.545753],"type":"Point"}
}