{
  "type": "Feature",
  "properties": {
    "addr:full":"101 St Mary Street Weymouth Dorset DT4 8NY",
    "addr:housenumber":"101",
    "addr:postcode":"dt4 8ny",
    "addr:street":"St Mary Street",
    "iso:country":"GB",
    "sg:address":"101 St Mary Street",
    "sg:city":"Weymouth",
    "sg:classifiers":[
        {
            "category":"Health Services",
            "subcategory":"Optometrist",
            "type":"Services"
        }
    ],
    "sg:phone":"+44 1305 784914",
    "sg:postcode":"DT4 8NY",
    "sg:province":"Dorset",
    "sg:tags":[
        "optician"
    ],
    "wof:name":"Batemans (Opticians)",
    "wof:placetype":"venue"
},
  "geometry": {"coordinates":[-2.454084,50.611034],"type":"Point"}
}