{
  "type": "Feature",
  "properties": {
    "iso:country":"GB",
    "sg:address":"Pinkerton Road",
    "sg:city":"Basingstoke",
    "sg:classifiers":[
        {
            "category":"Education",
            "subcategory":"School",
            "type":"Public Place"
        }
    ],
    "sg:phone":"+44 1256 322554",
    "sg:postcode":"RG22 6RT",
    "sg:province":"Hampshire",
    "sg:tags":[
        "local",
        "authority"
    ],
    "wof:name":"Park View County Infant School",
    "wof:placetype":"venue"
},
  "geometry": {"coordinates":[-1.113978982,51.2560882568],"type":"Point"}
}