{
  "type": "Feature",
  "properties": {
    "addr:full":"34 Porthleven Crescent, Astley Manchester Greater Manchester M29 7FZ",
    "addr:housenumber":"34",
    "addr:postcode":"m29 7fz",
    "addr:street":"Porthleven Crescent",
    "iso:country":"GB",
    "sg:address":"34 Porthleven Crescent, Astley",
    "sg:city":"Manchester",
    "sg:classifiers":[
        {
            "category":"Education",
            "subcategory":"Music School",
            "type":"Public Place"
        }
    ],
    "sg:postcode":"M29 7FZ",
    "sg:province":"Greater Manchester",
    "sg:tags":[
        "teacher"
    ],
    "wof:name":"Drum Studios",
    "wof:placetype":"venue"
},
  "geometry": {"coordinates":[-2.4510290623,53.5110397339],"type":"Point"}
}