{
  "type": "Feature",
  "properties": {
    "addr:full":"49 Leymoor Road Huddersfield West Yorkshire HD3 4SW",
    "addr:housenumber":"49",
    "addr:postcode":"hd3 4sw",
    "addr:street":"Leymoor Road",
    "iso:country":"GB",
    "sg:address":"49 Leymoor Road",
    "sg:city":"Huddersfield",
    "sg:classifiers":[
        {
            "category":"Personal",
            "subcategory":"Beauty Salon",
            "type":"Services"
        }
    ],
    "sg:postcode":"HD3 4SW",
    "sg:province":"West Yorkshire",
    "sg:tags":[
        "unisex",
        "hairdresser"
    ],
    "wof:name":"Cutting Cabin",
    "wof:placetype":"venue"
},
  "geometry": {"coordinates":[-1.841265,53.645428],"type":"Point"}
}