{
  "type": "Feature",
  "properties": {
    "iso:country":"GB",
    "sg:address":"16 Raeden Court",
    "sg:city":"Aberdeen",
    "sg:classifiers":[
        {
            "category":"Organizations",
            "subcategory":"Community Association",
            "type":"Services"
        }
    ],
    "sg:phone":"+44 1224 326964",
    "sg:postcode":"AB15 5PF",
    "sg:province":"Aberdeen City",
    "sg:tags":[
        "co-operatives",
        "society",
        "housing",
        "trust"
    ],
    "wof:name":"Margaret Blackwood Housing Association",
    "wof:placetype":"venue"
},
  "geometry": {"coordinates":[-2.1452219486,57.1508827209],"type":"Point"}
}