{
  "type": "Feature",
  "properties": {
    "iso:country":"GB",
    "sg:address":"New Elvaston Quarry, Thulston",
    "sg:city":"Derby",
    "sg:classifiers":[
        {
            "category":"Home & Garden",
            "subcategory":"Garden Supply",
            "type":"Retail Goods"
        }
    ],
    "sg:phone":"+44 1332 799300",
    "sg:postcode":"DE72 3FF",
    "sg:province":"Derbyshire",
    "sg:tags":[
        "sand",
        "gravel"
    ],
    "wof:name":"Tarmac Quarry Products (Eastern) Ltd.",
    "wof:placetype":"venue"
},
  "geometry": {"coordinates":[-1.3930490017,52.8837394714],"type":"Point"}
}