{
  "type": "Feature",
  "properties": {
    "addr:full":"6 Birchwood Parade, Birchwood Drive Dartford Kent DA2 7NJ",
    "addr:housenumber":"6",
    "addr:postcode":"da2 7nj",
    "addr:street":"Birchwood Parade Birchwood Drive",
    "iso:country":"GB",
    "sg:address":"6 Birchwood Parade, Birchwood Drive",
    "sg:city":"Dartford",
    "sg:classifiers":[
        {
            "category":"Shopping",
            "subcategory":"News",
            "type":"Retail Goods"
        }
    ],
    "sg:phone":"+44 1322 551437",
    "sg:postcode":"DA2 7NJ",
    "sg:province":"Kent",
    "sg:tags":[
        "newsagent"
    ],
    "wof:name":"Martin The Newsagent Ltd",
    "wof:placetype":"venue"
},
  "geometry": {"coordinates":[0.180038,51.427273],"type":"Point"}
}