{
  "type": "Feature",
  "properties": {
    "addr:full":"Care Management, 7 Castle St Huntly Aberdeenshire AB54 8BP",
    "addr:housenumber":"7",
    "addr:postcode":"ab54 8bp",
    "addr:street":"Castle St",
    "iso:country":"GB",
    "sg:address":"Care Management, 7 Castle St",
    "sg:city":"Huntly",
    "sg:classifiers":[
        {
            "category":"Government",
            "subcategory":"Office",
            "type":"Public Place"
        }
    ],
    "sg:phone":"+44 1466 794878",
    "sg:postcode":"AB54 8BP",
    "sg:province":"Aberdeenshire",
    "sg:tags":[
        "local"
    ],
    "wof:name":"Aberdeenshire Council",
    "wof:placetype":"venue"
},
  "geometry": {"coordinates":[-2.7863690853,57.446308136],"type":"Point"}
}