{
  "type": "Feature",
  "properties": {
    "addr:full":"184 Bruntsfield Place Edinburgh City of Edinburgh EH10 4DF",
    "addr:housenumber":"184",
    "addr:postcode":"eh10 4df",
    "addr:street":"Bruntsfield Place Edinburgh",
    "iso:country":"GB",
    "sg:address":"184 Bruntsfield Place",
    "sg:city":"Edinburgh",
    "sg:classifiers":[
        {
            "category":"Cafe",
            "type":"Food & Drink"
        }
    ],
    "sg:phone":"+44 131 228 1188",
    "sg:postcode":"EH10 4DF",
    "sg:province":"City of Edinburgh",
    "sg:tags":[
        "tea",
        "room"
    ],
    "wof:name":"La Grande Cafetiere",
    "wof:placetype":"venue"
},
  "geometry": {"coordinates":[-3.20986,55.936024],"type":"Point"}
}