{
  "type": "Feature",
  "properties": {
    "iso:country":"GB",
    "sg:address":"193 Sparrows Herne",
    "sg:city":"Bushey",
    "sg:classifiers":[
        {
            "category":"Real Estate",
            "subcategory":"Developer",
            "type":"Services"
        }
    ],
    "sg:postcode":"WD2 1EE",
    "sg:province":"Hertfordshire",
    "sg:tags":[
        "property"
    ],
    "wof:name":"Propwell Limited",
    "wof:placetype":"venue"
},
  "geometry": {"coordinates":[-0.3630700111,51.6443405151],"type":"Point"}
}