{
  "type": "Feature",
  "properties": {
    "iso:country":"GB",
    "sg:address":"56 High Street",
    "sg:city":"Lymington",
    "sg:classifiers":[
        {
            "category":"Shopping",
            "subcategory":"Crafts & Fabrics",
            "type":"Retail Goods"
        }
    ],
    "sg:phone":"+44 1590 673254",
    "sg:postcode":"SO41 9AH",
    "sg:province":"Hampshire",
    "sg:tags":[
        "shop"
    ],
    "wof:name":"Leigh's",
    "wof:placetype":"venue"
},
  "geometry": {"coordinates":[-1.544464,50.757549],"type":"Point"}
}