{
  "type": "Feature",
  "properties": {
    "iso:country":"GB",
    "sg:address":"Hermitage St",
    "sg:city":"London",
    "sg:classifiers":[
        {
            "category":"Parking",
            "type":"Transportation"
        }
    ],
    "sg:phone":"+44 20 7402 2933",
    "sg:postcode":"W2 1JP",
    "sg:province":"Greater London",
    "sg:tags":[
        "car",
        "park"
    ],
    "wof:name":"Chambers,David,",
    "wof:placetype":"venue"
},
  "geometry": {"coordinates":[-0.176319,51.519829],"type":"Point"}
}