{
  "type": "Feature",
  "properties": {
    "addr:full":"16 Grafton Pl Chelmsford Essex CM2 6TG",
    "addr:housenumber":"16",
    "addr:postcode":"cm2 6tg",
    "addr:street":"Grafton Pl",
    "iso:country":"GB",
    "sg:address":"16 Grafton Pl",
    "sg:city":"Chelmsford",
    "sg:classifiers":[
        {
            "category":"Shopping",
            "type":"Retail Goods"
        }
    ],
    "sg:phone":"+44 1245 451726",
    "sg:postcode":"CM2 6TG",
    "sg:province":"Essex",
    "sg:tags":[
        "part",
        "accessory"
    ],
    "wof:name":"Anglia Motor Parts Ltd",
    "wof:placetype":"venue"
},
  "geometry": {"coordinates":[0.5055029988,51.7410545349],"type":"Point"}
}