{
  "type": "Feature",
  "properties": {
    "iso:country":"GB",
    "sg:address":"64 Eaton Valley Rd",
    "sg:city":"Luton",
    "sg:classifiers":[
        {
            "category":"Building & Trades",
            "subcategory":"Cleaning & Sanitation",
            "type":"Services"
        }
    ],
    "sg:postcode":"LU2 0SW",
    "sg:province":"Bedfordshire",
    "sg:tags":[
        "commercial"
    ],
    "wof:name":"Evans,Anthony,",
    "wof:placetype":"venue"
},
  "geometry": {"coordinates":[-0.389927,51.884911],"type":"Point"}
}