{
  "type": "Feature",
  "properties": {
    "addr:full":"The Old Coach House, Ripon Rd Harrogate North Yorkshire HG1 2JJ",
    "addr:postcode":"hg1 2jj",
    "addr:street":"Ripon Rd",
    "iso:country":"GB",
    "sg:address":"The Old Coach House, Ripon Rd",
    "sg:city":"Harrogate",
    "sg:classifiers":[
        {
            "category":"Home & Garden",
            "subcategory":"Household Appliances",
            "type":"Retail Goods"
        }
    ],
    "sg:phone":"+44 1423 544050",
    "sg:postcode":"HG1 2JJ",
    "sg:province":"North Yorkshire",
    "sg:tags":[
        "cleaner",
        "vacuum"
    ],
    "wof:name":"North Yorkshire Homecare Systems",
    "wof:placetype":"venue"
},
  "geometry": {"coordinates":[-1.549175,54.004322],"type":"Point"}
}