{
  "type": "Feature",
  "properties": {
    "addr:full":"College Lane Tamworth Staffordshire B79 7LP",
    "addr:postcode":"b79 7lp",
    "addr:street":"College Lane",
    "iso:country":"GB",
    "sg:address":"College Lane",
    "sg:city":"Tamworth",
    "sg:classifiers":[
        {
            "category":"Home & Garden",
            "subcategory":"Carpets & Floor Coverings",
            "type":"Retail Goods"
        }
    ],
    "sg:postcode":"B79 7LP",
    "sg:province":"Staffordshire",
    "sg:tags":[
        "carpets",
        "rug",
        "matting"
    ],
    "wof:name":"Michael Devlin",
    "wof:placetype":"venue"
},
  "geometry": {"coordinates":[-1.69404,52.63348],"type":"Point"}
}