{
  "type": "Feature",
  "properties": {
    "addr:full":"120 Halifax Road, Brierfield Nelson Lancashire BB9 5BQ",
    "addr:housenumber":"120",
    "addr:postcode":"bb9 5bq",
    "addr:street":"Halifax Road",
    "iso:country":"GB",
    "sg:address":"120 Halifax Road, Brierfield",
    "sg:city":"Nelson",
    "sg:classifiers":[
        {
            "category":"Building & Trades",
            "subcategory":"Construction",
            "type":"Services"
        }
    ],
    "sg:phone":"+44 1282 691266",
    "sg:postcode":"BB9 5BQ",
    "sg:province":"Lancashire",
    "sg:tags":[
        "roofing"
    ],
    "wof:name":"Ken Smith Roofing Ltd.",
    "wof:placetype":"venue"
},
  "geometry": {"coordinates":[-2.2266490459,53.8243865967],"type":"Point"}
}