{
  "type": "Feature",
  "properties": {
    "iso:country":"GB",
    "sg:address":"92 Hendrecafn Road, Penygraig",
    "sg:city":"Tonypandy",
    "sg:classifiers":[
        {
            "category":"Personal",
            "subcategory":"Beauty Salon",
            "type":"Services"
        }
    ],
    "sg:phone":"+44 1443 436424",
    "sg:postcode":"CF40 1HA",
    "sg:province":"Rhondda, Cynon, Taff",
    "sg:tags":[
        "unisex",
        "hairdresser"
    ],
    "wof:name":"Guys & Dolls",
    "wof:placetype":"venue"
},
  "geometry": {"coordinates":[-3.450754,51.616058],"type":"Point"}
}