{
  "type": "Feature",
  "properties": {
    "iso:country":"GB",
    "sg:address":"11/15 Dixisfield",
    "sg:city":"Exeter",
    "sg:classifiers":[
        {
            "category":"Organizations",
            "subcategory":"Non-profit Organization",
            "type":"Services"
        }
    ],
    "sg:phone":"+44 1392 425550",
    "sg:postcode":"EX11 1QA",
    "sg:province":"Devon",
    "sg:tags":[
        "organisation",
        "voluntary",
        "charity"
    ],
    "wof:name":"Pre-School Learning Alliance",
    "wof:placetype":"venue"
},
  "geometry": {"coordinates":[-3.292299,50.745731],"type":"Point"}
}