{
  "type": "Feature",
  "properties": {
    "addr:full":"4 Smith Road Widnes Cheshire WA8 7AU",
    "addr:housenumber":"4",
    "addr:postcode":"wa8 7au",
    "addr:street":"Smith Road",
    "iso:country":"GB",
    "sg:address":"4 Smith Road",
    "sg:city":"Widnes",
    "sg:classifiers":[
        {
            "category":"Building & Trades",
            "subcategory":"Plumbing",
            "type":"Services"
        }
    ],
    "sg:phone":"+44 151 420 7958",
    "sg:postcode":"WA8 7AU",
    "sg:province":"Cheshire",
    "sg:tags":[
        "heating"
    ],
    "wof:name":"Premier Plumbing & Joinery",
    "wof:placetype":"venue"
},
  "geometry": {"coordinates":[-2.7399439812,53.3620948792],"type":"Point"}
}