{
  "type": "Feature",
  "properties": {
    "addr:full":"3 Moat Street Bridgnorth Shropshire WV16 4EP",
    "addr:housenumber":"3",
    "addr:postcode":"wv16 4ep",
    "addr:street":"Moat Street",
    "iso:country":"GB",
    "sg:address":"3 Moat Street",
    "sg:city":"Bridgnorth",
    "sg:classifiers":[
        {
            "category":"Personal",
            "subcategory":"Beauty Salon",
            "type":"Services"
        }
    ],
    "sg:phone":"+44 1746 765251",
    "sg:postcode":"WV16 4EP",
    "sg:province":"Shropshire",
    "sg:tags":[
        "unisex",
        "hairdresser"
    ],
    "wof:name":"Reflections Hair Studio",
    "wof:placetype":"venue"
},
  "geometry": {"coordinates":[-2.419975,52.537125],"type":"Point"}
}