{
  "type": "Feature",
  "properties": {
    "iso:country":"GB",
    "sg:address":"Unit 1 The Mills, Station Road",
    "sg:city":"Newton Abbot",
    "sg:classifiers":[
        {
            "category":"Home & Garden",
            "subcategory":"Furniture",
            "type":"Retail Goods"
        }
    ],
    "sg:phone":"+44 1626 833806",
    "sg:postcode":"TQ13 9JG",
    "sg:province":"Devon",
    "wof:name":"M & S Pine",
    "wof:placetype":"venue"
},
  "geometry": {"coordinates":[-3.73068,50.601292],"type":"Point"}
}