{
  "type": "Feature",
  "properties": {
    "addr:full":"Unit 1 The Mills, Station Road Newton Abbot Devon TQ13 9JG",
    "addr:housenumber":"unit 1 the mills",
    "addr:postcode":"tq13 9jg",
    "addr:street":"Station Road",
    "iso:country":"GB",
    "sg:address":"Unit 1 The Mills, Station Road",
    "sg:city":"Newton Abbot",
    "sg:classifiers":[
        {
            "category":"Home & Garden",
            "subcategory":"Furniture",
            "type":"Retail Goods"
        }
    ],
    "sg:phone":"+44 1626 833806",
    "sg:postcode":"TQ13 9JG",
    "sg:province":"Devon",
    "wof:name":"M & S Pine",
    "wof:placetype":"venue"
},
  "geometry": {"coordinates":[-3.73068,50.601292],"type":"Point"}
}