{
  "type": "Feature",
  "properties": {
    "iso:country":"GB",
    "sg:address":"38 Shafto St",
    "sg:city":"Newcastle Upon Tyne",
    "sg:classifiers":[
        {
            "category":"Shopping",
            "subcategory":"Baby Store",
            "type":"Retail Goods"
        }
    ],
    "sg:phone":"+44 191 275 3480",
    "sg:postcode":"NE15 6AX",
    "sg:province":"Northumberland",
    "sg:tags":[
        "babywear",
        "childrens"
    ],
    "wof:name":"Kutekids",
    "wof:placetype":"venue"
},
  "geometry": {"coordinates":[-1.6884050369,54.9707336426],"type":"Point"}
}