{
  "type": "Feature",
  "properties": {
    "addr:full":"5 Waterloo Road Hinckley Leicestershire LE10 0QJ",
    "addr:housenumber":"5",
    "addr:postcode":"le10 0qj",
    "addr:street":"Waterloo Road",
    "iso:country":"GB",
    "sg:address":"5 Waterloo Road",
    "sg:city":"Hinckley",
    "sg:classifiers":[
        {
            "category":"Retail",
            "subcategory":"Laundry & Dry Cleaning",
            "type":"Services"
        }
    ],
    "sg:phone":"+44 1455 890748",
    "sg:postcode":"LE10 0QJ",
    "sg:province":"Leicestershire",
    "sg:tags":[
        "launderette"
    ],
    "wof:name":"The Soap Suds Launderette",
    "wof:placetype":"venue"
},
  "geometry": {"coordinates":[-1.374726,52.538849],"type":"Point"}
}