{
  "type": "Feature",
  "properties": {
    "addr:full":"46 Kingshill Avenue St Albans Hertfordshire AL4 9QB",
    "addr:housenumber":"46",
    "addr:postcode":"al4 9qb",
    "addr:street":"Kingshill Avenue",
    "iso:country":"GB",
    "sg:address":"46 Kingshill Avenue",
    "sg:city":"St Albans",
    "sg:classifiers":[
        {
            "category":"Manufacturing",
            "subcategory":"Printing",
            "type":"Manufacturing & Wholesale Goods"
        }
    ],
    "sg:postcode":"AL4 9QB",
    "sg:province":"Hertfordshire",
    "sg:tags":[
        "bookbinder"
    ],
    "wof:name":"David Bryan Hand Bookbinders",
    "wof:placetype":"venue"
},
  "geometry": {"coordinates":[-0.310146,51.766422],"type":"Point"}
}