{
  "type": "Feature",
  "properties": {
    "addr:full":"22 Bridge Street, Usk Monmouth Monmouthshire NP15 1BG",
    "addr:housenumber":"22",
    "addr:postcode":"np15 1bg",
    "addr:street":"Bridge Street",
    "iso:country":"GB",
    "sg:address":"22 Bridge Street, Usk",
    "sg:city":"Monmouth",
    "sg:classifiers":[
        {
            "category":"Shopping",
            "subcategory":"Department Store",
            "type":"Retail Goods"
        },
        {
            "category":"Home & Garden",
            "subcategory":"Home Furnishings",
            "type":"Retail Goods"
        }
    ],
    "sg:phone":"+44 1291 672048",
    "sg:postcode":"NP15 1BG",
    "sg:province":"Monmouthshire",
    "sg:tags":[
        "wall",
        "wallpaper",
        "covering"
    ],
    "wof:name":"H & R Paint Wallpaper Garden Centre",
    "wof:placetype":"venue"
},
  "geometry": {"coordinates":[-2.90488,51.702721],"type":"Point"}
}