{
  "type": "Feature",
  "properties": {
    "iso:country":"GB",
    "sg:address":"Rhosymedre Junior School, Special Unit, Park Rd",
    "sg:city":"Wrexham",
    "sg:classifiers":[
        {
            "category":"Government",
            "subcategory":"Office",
            "type":"Public Place"
        }
    ],
    "sg:phone":"+44 1978 810115",
    "sg:postcode":"LL14 3EG",
    "sg:province":"Wrexham",
    "sg:tags":[
        "local"
    ],
    "wof:name":"Wrexham County Borough Council",
    "wof:placetype":"venue"
},
  "geometry": {"coordinates":[-3.0609500408,52.9785995483],"type":"Point"}
}