{
  "type": "Feature",
  "properties": {
    "iso:country":"GB",
    "sg:address":"High Road, Chilwell",
    "sg:city":"Nottingham",
    "sg:classifiers":[
        {
            "category":"Social Services",
            "subcategory":"Job Training",
            "type":"Services"
        },
        {
            "category":"Education",
            "subcategory":"University",
            "type":"Public Place"
        },
        {
            "category":"Education",
            "subcategory":"School",
            "type":"Public Place"
        }
    ],
    "sg:phone":"+44 115 917 5252",
    "sg:postcode":"NG9 4AH",
    "sg:province":"Nottinghamshire",
    "sg:tags":[
        "college",
        "higher"
    ],
    "wof:name":"BROXTOWE COLLEGE",
    "wof:placetype":"venue"
},
  "geometry": {"coordinates":[-1.221179,52.922218],"type":"Point"}
}