{
  "type": "Feature",
  "properties": {
    "iso:country":"GB",
    "sg:address":"Unit 15a, 168 New Rd",
    "sg:city":"Rainham",
    "sg:classifiers":[
        {
            "category":"Freight",
            "type":"Transportation"
        }
    ],
    "sg:phone":"+44 1708 559030",
    "sg:postcode":"RM13 8RS",
    "sg:province":"Essex",
    "sg:tags":[
        "haulage",
        "road"
    ],
    "wof:name":"Cargo Masters Ltd",
    "wof:placetype":"venue"
},
  "geometry": {"coordinates":[0.177333,51.523594],"type":"Point"}
}