{
  "type": "Feature",
  "properties": {
    "addr:full":"Garnett House, Burneside Kendal Cumbria LA9 5SF",
    "addr:postcode":"la9 5sf",
    "addr:street":"Burneside Kendal",
    "iso:country":"GB",
    "sg:address":"Garnett House, Burneside",
    "sg:city":"Kendal",
    "sg:classifiers":[
        {
            "category":"Travel",
            "subcategory":"Hotels & Motels",
            "type":"Entertainment"
        }
    ],
    "sg:postcode":"LA9 5SF",
    "sg:province":"Cumbria",
    "sg:tags":[
        "house",
        "guest"
    ],
    "wof:name":"Sylvia Beaty",
    "wof:placetype":"venue"
},
  "geometry": {"coordinates":[-2.748749,54.337509],"type":"Point"}
}