{
  "type": "Feature",
  "properties": {
    "addr:full":"15 Church Road, Newick Lewes East Sussex BN8 4JU",
    "addr:housenumber":"15",
    "addr:postcode":"bn8 4ju",
    "addr:street":"Church Road",
    "iso:country":"GB",
    "sg:address":"15 Church Road, Newick",
    "sg:city":"Lewes",
    "sg:classifiers":[
        {
            "category":"Autos & Motor Vehicles",
            "subcategory":"Automobile Sales",
            "type":"Retail Goods"
        },
        {
            "category":"Retail",
            "subcategory":"Auto Repair",
            "type":"Services"
        }
    ],
    "sg:phone":"+44 1825 722233",
    "sg:postcode":"BN8 4JU",
    "sg:province":"East Sussex",
    "sg:tags":[
        "modification",
        "garage",
        "car"
    ],
    "wof:name":"The Newick Motor Co Ltd",
    "wof:placetype":"venue"
},
  "geometry": {"coordinates":[0.020373,50.97221],"type":"Point"}
}