{
  "type": "Feature",
  "properties": {
    "addr:full":"50 Wellington Street Batley West Yorkshire WF17 5HU",
    "addr:housenumber":"50",
    "addr:postcode":"wf17 5hu",
    "addr:street":"Wellington Street",
    "iso:country":"GB",
    "sg:address":"50 Wellington Street",
    "sg:city":"Batley",
    "sg:classifiers":[
        {
            "category":"Professional",
            "type":"Services"
        }
    ],
    "sg:phone":"+44 1924 423523",
    "sg:postcode":"WF17 5HU",
    "sg:province":"West Yorkshire",
    "sg:tags":[
        "caterer"
    ],
    "wof:name":"Spicy Land",
    "wof:placetype":"venue"
},
  "geometry": {"coordinates":[-1.629537,53.71241],"type":"Point"}
}