{
  "type": "Feature",
  "properties": {
    "iso:country":"GB",
    "sg:address":"61 New City Road",
    "sg:city":"London",
    "sg:classifiers":[
        {
            "category":"Building & Trades",
            "subcategory":"Construction",
            "type":"Services"
        }
    ],
    "sg:phone":"+44 20 8471 0884",
    "sg:postcode":"E13 9LN",
    "sg:province":"Greater London",
    "sg:tags":[
        "builder"
    ],
    "wof:name":"T E B (Builders) Ltd.",
    "wof:placetype":"venue"
},
  "geometry": {"coordinates":[0.03515,51.527187],"type":"Point"}
}