{
  "type": "Feature",
  "properties": {
    "addr:full":"61 New City Road London Greater London E13 9LN",
    "addr:housenumber":"61",
    "addr:postcode":"e13 9ln",
    "addr:street":"New City Road",
    "iso:country":"GB",
    "sg:address":"61 New City Road",
    "sg:city":"London",
    "sg:classifiers":[
        {
            "category":"Building & Trades",
            "subcategory":"Construction",
            "type":"Services"
        }
    ],
    "sg:phone":"+44 20 8471 0884",
    "sg:postcode":"E13 9LN",
    "sg:province":"Greater London",
    "sg:tags":[
        "builder"
    ],
    "wof:name":"T E B (Builders) Ltd.",
    "wof:placetype":"venue"
},
  "geometry": {"coordinates":[0.03515,51.527187],"type":"Point"}
}