{
  "type": "Feature",
  "properties": {
    "addr:full":"Unit 3, Abbey Mead Industrial Park, Brooker Road Waltham Abbey Essex EN9 1HU",
    "addr:housenumber":"unit 3",
    "addr:postcode":"en9 1hu",
    "addr:street":"Abbey Mead Industrial Park Brooker Road",
    "iso:country":"GB",
    "sg:address":"Unit 3, Abbey Mead Industrial Park, Brooker Road",
    "sg:city":"Waltham Abbey",
    "sg:classifiers":[
        {
            "category":"Professional",
            "subcategory":"Management & Consulting",
            "type":"Services"
        }
    ],
    "sg:phone":"+44 1992 761666",
    "sg:postcode":"EN9 1HU",
    "sg:province":"Essex",
    "sg:tags":[
        "fire",
        "consultant",
        "protection"
    ],
    "wof:name":"McCartney Fire Protection",
    "wof:placetype":"venue"
},
  "geometry": {"coordinates":[0.00149,51.68642],"type":"Point"}
}