{
  "type": "Feature",
  "properties": {
    "addr:full":"Fairways, Edinburgh Road, Carnwath Lanark South Lanarkshire ML11 8HS",
    "addr:postcode":"ml11 8hs",
    "addr:street":"Edinburgh Road",
    "iso:country":"GB",
    "sg:address":"Fairways, Edinburgh Road, Carnwath",
    "sg:city":"Lanark",
    "sg:classifiers":[
        {
            "category":"Professional",
            "subcategory":"Engineering",
            "type":"Services"
        }
    ],
    "sg:phone":"+44 1506 418028",
    "sg:postcode":"ML11 8HS",
    "sg:province":"South Lanarkshire",
    "sg:tags":[
        "contractor",
        "electrical",
        "engineer"
    ],
    "wof:name":"Ormiston Electrics",
    "wof:placetype":"venue"
},
  "geometry": {"coordinates":[-3.6246130466,55.7005653381],"type":"Point"}
}