{
  "type": "Feature",
  "properties": {
    "iso:country":"GB",
    "sg:address":"54 Dovehouse Hill",
    "sg:city":"Luton",
    "sg:classifiers":[
        {
            "category":"Organizations",
            "subcategory":"Non-profit Organization",
            "type":"Services"
        }
    ],
    "sg:phone":"+44 1582 730664",
    "sg:postcode":"LU2 9ES",
    "sg:province":"Bedfordshire",
    "sg:tags":[
        "organisation",
        "voluntary",
        "charity"
    ],
    "wof:name":"Arthritis Care",
    "wof:placetype":"venue"
},
  "geometry": {"coordinates":[-0.388906,51.888927],"type":"Point"}
}