{
  "type": "Feature",
  "properties": {
    "addr:full":"155 Chorley New Road, Horwich Bolton Lancashire BL6 5QE",
    "addr:housenumber":"155",
    "addr:postcode":"bl6 5qe",
    "addr:street":"Chorley New Road",
    "iso:country":"GB",
    "sg:address":"155 Chorley New Road, Horwich",
    "sg:city":"Bolton",
    "sg:classifiers":[
        {
            "category":"Fast Food",
            "type":"Food & Drink"
        }
    ],
    "sg:phone":"+44 1204 468940",
    "sg:postcode":"BL6 5QE",
    "sg:province":"Lancashire",
    "sg:tags":[
        "away",
        "take"
    ],
    "wof:name":"The Golden Harvest",
    "wof:placetype":"venue"
},
  "geometry": {"coordinates":[-2.550235,53.598251],"type":"Point"}
}