{
  "type": "Feature",
  "properties": {
    "iso:country":"GB",
    "sg:address":"59 Birch Avenue, Chapeltown",
    "sg:city":"Sheffield",
    "sg:classifiers":[
        {
            "category":"Retail",
            "subcategory":"Repair Shop",
            "type":"Services"
        }
    ],
    "sg:postcode":"S35 1RQ",
    "sg:province":"South Yorkshire",
    "sg:tags":[
        "maintenance"
    ],
    "wof:name":"A W Builders",
    "wof:placetype":"venue"
},
  "geometry": {"coordinates":[-1.471802,53.460716],"type":"Point"}
}