{
  "type": "Feature",
  "properties": {
    "addr:full":"137 Victoria Road Ferndown Dorset BH22 9HX",
    "addr:housenumber":"137",
    "addr:postcode":"bh22 9hx",
    "addr:street":"Victoria Road",
    "iso:country":"GB",
    "sg:address":"137 Victoria Road",
    "sg:city":"Ferndown",
    "sg:classifiers":[
        {
            "category":"Utilities",
            "subcategory":"Telephone",
            "type":"Services"
        },
        {
            "category":"Communications",
            "type":"Services"
        },
        {
            "category":"Utilities",
            "subcategory":"Cable",
            "type":"Services"
        }
    ],
    "sg:phone":"+44 1202 863200",
    "sg:postcode":"BH22 9HX",
    "sg:province":"Dorset",
    "sg:tags":[
        "telecom",
        "equipment",
        "telecommunication",
        "system"
    ],
    "wof:name":"Bistech Plc",
    "wof:placetype":"venue"
},
  "geometry": {"coordinates":[-1.891201973,50.8041648865],"type":"Point"}
}