{
  "type": "Feature",
  "properties": {
    "iso:country":"GB",
    "sg:address":"77 Norton Road, Stockton",
    "sg:city":"Stockton-on-tees",
    "sg:classifiers":[
        {
            "category":"Wholesale",
            "subcategory":"Computers",
            "type":"Manufacturing & Wholesale Goods"
        },
        {
            "category":"Professional",
            "subcategory":"Computer Services",
            "type":"Services"
        }
    ],
    "sg:phone":"+44 1642 612784",
    "sg:postcode":"TS18 2DA",
    "sg:province":"Durham",
    "sg:tags":[
        "supplier",
        "consumables",
        "system",
        "software"
    ],
    "wof:name":"Thersby Group",
    "wof:placetype":"venue"
},
  "geometry": {"coordinates":[-1.312288,54.570271],"type":"Point"}
}