{
  "type": "Feature",
  "properties": {
    "addr:full":"30 Spedan Close London Greater London NW3 7XF",
    "addr:housenumber":"30",
    "addr:postcode":"nw3 7xf",
    "addr:street":"Spedan Close",
    "iso:country":"GB",
    "sg:address":"30 Spedan Close",
    "sg:city":"London",
    "sg:classifiers":[
        {
            "category":"Professional",
            "subcategory":"Employment Agencies",
            "type":"Services"
        }
    ],
    "sg:phone":"+44 20 7431 5698",
    "sg:postcode":"NW3 7XF",
    "sg:province":"Greater London",
    "sg:tags":[
        "modelling"
    ],
    "wof:name":"Movie Mites",
    "wof:placetype":"venue"
},
  "geometry": {"coordinates":[-0.182649,51.55954],"type":"Point"}
}