{
  "type": "Feature",
  "properties": {
    "iso:country":"GB",
    "sg:address":"The Mill House, Crewe Green Road",
    "sg:city":"Crewe",
    "sg:classifiers":[
        {
            "category":"Home & Garden",
            "subcategory":"Home Furnishings",
            "type":"Retail Goods"
        }
    ],
    "sg:phone":"+44 1270 215200",
    "sg:postcode":"CW1 5NW",
    "sg:province":"Cheshire",
    "sg:tags":[
        "racking",
        "shelving",
        "diy"
    ],
    "wof:name":"Active Supply & Design (C D M) Ltd.",
    "wof:placetype":"venue"
},
  "geometry": {"coordinates":[-2.420349,53.092884],"type":"Point"}
}