{
  "type": "Feature",
  "properties": {
    "addr:full":"5 Humber Place, Horbury Wakefield West Yorkshire WF4 6JE",
    "addr:housenumber":"5",
    "addr:postcode":"wf4 6je",
    "addr:street":"Humber Place;West",
    "iso:country":"GB",
    "sg:address":"5 Humber Place, Horbury",
    "sg:city":"Wakefield",
    "sg:classifiers":[
        {
            "category":"Professional",
            "subcategory":"Art Services",
            "type":"Services"
        }
    ],
    "sg:phone":"+44 1924 264725",
    "sg:postcode":"WF4 6JE",
    "sg:province":"West Yorkshire",
    "sg:tags":[
        "photographer"
    ],
    "wof:name":"Photoneg",
    "wof:placetype":"venue"
},
  "geometry": {"coordinates":[-1.5586739779,53.6621017456],"type":"Point"}
}