{
  "type": "Feature",
  "properties": {
    "addr:full":"6 Greyfriars Clo Darlington Durham DL3 8UA",
    "addr:housenumber":"6;clo",
    "addr:postcode":"dl3 8ua",
    "addr:street":"Greyfriars",
    "iso:country":"GB",
    "sg:address":"6 Greyfriars Clo",
    "sg:city":"Darlington",
    "sg:classifiers":[
        {
            "category":"Building & Trades",
            "subcategory":"Construction",
            "type":"Services"
        }
    ],
    "sg:phone":"+44 1325 486091",
    "sg:postcode":"DL3 8UA",
    "sg:province":"Durham",
    "sg:tags":[
        "builder"
    ],
    "wof:name":"Paul Scott",
    "wof:placetype":"venue"
},
  "geometry": {"coordinates":[-1.6004090309,54.5240097046],"type":"Point"}
}