{
  "type": "Feature",
  "properties": {
    "iso:country":"GB",
    "sg:address":"100-102 Bradshawgate",
    "sg:city":"Bolton",
    "sg:classifiers":[
        {
            "category":"Real Estate",
            "subcategory":"Surveying",
            "type":"Services"
        }
    ],
    "sg:postcode":"BL1 1QJ",
    "sg:province":"Lancashire",
    "sg:tags":[
        "surveyor",
        "valuer"
    ],
    "wof:name":"Joseph Jackson & Sons",
    "wof:placetype":"venue"
},
  "geometry": {"coordinates":[-2.4258921146,53.5767402649],"type":"Point"}
}