{
  "type": "Feature",
  "properties": {
    "iso:country":"GB",
    "sg:address":"171 North Street",
    "sg:city":"Glasgow",
    "sg:classifiers":[
        {
            "category":"Restaurant",
            "type":"Food & Drink"
        }
    ],
    "sg:postcode":"G3 7DA",
    "sg:province":"Glasgow City",
    "sg:tags":[
        "indian"
    ],
    "wof:name":"Cafe India",
    "wof:placetype":"venue"
},
  "geometry": {"coordinates":[-4.2717847824,55.8651390076],"type":"Point"}
}