{
  "type": "Feature",
  "properties": {
    "iso:country":"GB",
    "sg:address":"Grafton Mews, High Street",
    "sg:city":"Chipping Campden",
    "sg:classifiers":[
        {
            "category":"Food & Beverages",
            "subcategory":"Fruits & Vegetables",
            "type":"Retail Goods"
        }
    ],
    "sg:phone":"+44 1386 840577",
    "sg:postcode":"GL55 6AT",
    "sg:province":"Gloucestershire",
    "sg:tags":[
        "greengrocer"
    ],
    "wof:name":"Campden Fruit & Vegetables",
    "wof:placetype":"venue"
},
  "geometry": {"coordinates":[-1.779454,52.051388],"type":"Point"}
}