{
  "type": "Feature",
  "properties": {
    "iso:country":"GB",
    "sg:address":"151 Coronation Road, Southville",
    "sg:city":"Bristol",
    "sg:classifiers":[
        {
            "category":"Health Services",
            "subcategory":"Dentist",
            "type":"Services"
        }
    ],
    "sg:phone":"+44 117 966 3697",
    "sg:postcode":"BS3 1RE",
    "sg:province":"City of Bristol",
    "wof:name":"Coronation Road Dental Surgery",
    "wof:placetype":"venue"
},
  "geometry": {"coordinates":[-2.6073200703,51.4460639954],"type":"Point"}
}