{
  "type": "Feature",
  "properties": {
    "addr:full":"67 Stockwell Head Hinckley Leicestershire LE10 1RD",
    "addr:housenumber":"67",
    "addr:postcode":"le10 1rd",
    "addr:street":"Stockwell Head",
    "iso:country":"GB",
    "sg:address":"67 Stockwell Head",
    "sg:city":"Hinckley",
    "sg:classifiers":[
        {
            "category":"Professional",
            "subcategory":"Business Services",
            "type":"Services"
        }
    ],
    "sg:phone":"+44 1455 631977",
    "sg:postcode":"LE10 1RD",
    "sg:province":"Leicestershire",
    "sg:tags":[
        "tile",
        "stockist"
    ],
    "wof:name":"Hinckley Tile Services",
    "wof:placetype":"venue"
},
  "geometry": {"coordinates":[-1.3699959517,52.5424156189],"type":"Point"}
}