{
  "type": "Feature",
  "properties": {
    "iso:country":"GB",
    "sg:address":"Chester Rd, Walton",
    "sg:city":"Warrington",
    "sg:classifiers":[
        {
            "category":"Bars & Pubs",
            "type":"Food & Drink"
        }
    ],
    "sg:phone":"+44 1925 261680",
    "sg:postcode":"WA4 6EG",
    "sg:province":"Cheshire",
    "sg:tags":[
        "pubs",
        "inn"
    ],
    "wof:name":"Stag Inn",
    "wof:placetype":"venue"
},
  "geometry": {"coordinates":[-2.5955789089,53.3692588806],"type":"Point"}
}