{
  "type": "Feature",
  "properties": {
    "addr:full":"Mountain Farm Black Moss Road, Blacko Nelson Lancashire BB9 6LE",
    "addr:postcode":"bb9 6le",
    "addr:street":"Black Moss Road",
    "iso:country":"GB",
    "sg:address":"Mountain Farm Black Moss Road, Blacko",
    "sg:city":"Nelson",
    "sg:classifiers":[
        {
            "category":"Farming",
            "subcategory":"Farm",
            "type":"Manufacturing & Wholesale Goods"
        }
    ],
    "sg:postcode":"BB9 6LE",
    "sg:province":"Lancashire",
    "sg:tags":[
        "mixed",
        "crop"
    ],
    "wof:name":"Edward J Duerden",
    "wof:placetype":"venue"
},
  "geometry": {"coordinates":[-2.214138031,53.8668251038],"type":"Point"}
}