{
  "type": "Feature",
  "properties": {
    "iso:country":"GB",
    "sg:address":"4 Roman Courts",
    "sg:city":"Cambridge",
    "sg:classifiers":[
        {
            "category":"Social Services",
            "subcategory":"Adult Care",
            "type":"Services"
        },
        {
            "category":"Government",
            "subcategory":"Office",
            "type":"Public Place"
        }
    ],
    "sg:phone":"+44 1223 312649",
    "sg:postcode":"CB4 2TS",
    "sg:province":"Cambridgeshire",
    "sg:tags":[
        "housing",
        "local",
        "sheltered"
    ],
    "wof:name":"Roman Court Sheltered Housing",
    "wof:placetype":"venue"
},
  "geometry": {"coordinates":[0.1278540045,52.2333946228],"type":"Point"}
}