{
  "type": "Feature",
  "properties": {
    "iso:country":"GB",
    "sg:address":"1 Currie Street",
    "sg:city":"Glasgow",
    "sg:classifiers":[
        {
            "category":"Health Services",
            "subcategory":"Nursing And Care Facility",
            "type":"Services"
        }
    ],
    "sg:phone":"+44 141 945 1523",
    "sg:postcode":"G20 9EW",
    "sg:province":"Glasgow City",
    "sg:tags":[
        "home"
    ],
    "wof:name":"Wyndford Locks Nursing Home",
    "wof:placetype":"venue"
},
  "geometry": {"coordinates":[-4.279775,55.888634],"type":"Point"}
}