{
  "type": "Feature",
  "properties": {
    "addr:full":"Unit 23 Hatton Craft Centre Warwick Warwickshire CV35 8XA",
    "addr:housenumber":"unit 23;craft",
    "addr:postcode":"cv35 8xa",
    "addr:street":"Hatton;Centre",
    "iso:country":"GB",
    "sg:address":"Unit 23 Hatton Craft Centre",
    "sg:city":"Warwick",
    "sg:classifiers":[
        {
            "category":"Home & Garden",
            "subcategory":"Kitchen Supply",
            "type":"Retail Goods"
        }
    ],
    "sg:phone":"+44 1926 842789",
    "sg:postcode":"CV35 8XA",
    "sg:province":"Warwickshire",
    "sg:tags":[
        "glassware",
        "china"
    ],
    "wof:name":"Maid of China",
    "wof:placetype":"venue"
},
  "geometry": {"coordinates":[-1.662364,52.290173],"type":"Point"}
}