{
  "type": "Feature",
  "properties": {
    "iso:country":"GB",
    "sg:address":"116 Whiteladies Road, Clifton",
    "sg:city":"Bristol",
    "sg:classifiers":[
        {
            "category":"Food & Beverages",
            "subcategory":"Liquor & Beverages",
            "type":"Retail Goods"
        }
    ],
    "sg:phone":"+44 117 946 6104",
    "sg:postcode":"BS8 2RP",
    "sg:province":"City of Bristol",
    "sg:tags":[
        "beer",
        "spirit",
        "wines"
    ],
    "wof:name":"Victoria Wine",
    "wof:placetype":"venue"
},
  "geometry": {"coordinates":[-2.6138730049,51.46849823],"type":"Point"}
}