{
  "type": "Feature",
  "properties": {
    "addr:full":"Dolwen Bach, Llangernyw Abergele Conwy LL22 8RR",
    "addr:postcode":"ll22 8rr",
    "iso:country":"GB",
    "sg:address":"Dolwen Bach, Llangernyw",
    "sg:city":"Abergele",
    "sg:classifiers":[
        {
            "category":"Farming",
            "subcategory":"Livestock Farm",
            "type":"Manufacturing & Wholesale Goods"
        },
        {
            "category":"Farming",
            "subcategory":"Farm",
            "type":"Manufacturing & Wholesale Goods"
        }
    ],
    "sg:phone":"+44 1745 860686",
    "sg:postcode":"LL22 8RR",
    "sg:province":"Conwy",
    "sg:tags":[
        "mixed",
        "crop"
    ],
    "wof:name":"D G & C A Williams",
    "wof:placetype":"venue"
},
  "geometry": {"coordinates":[-3.6695940495,53.25573349],"type":"Point"}
}