{
  "type": "Feature",
  "properties": {
    "addr:full":"6-8 Upr Promenade Colwyn Bay Conwy LL28 4BS",
    "addr:housenumber":"6-8",
    "addr:postcode":"ll28 4bs",
    "addr:street":"Upr Promenade",
    "iso:country":"GB",
    "sg:address":"6-8 Upr Promenade",
    "sg:city":"Colwyn Bay",
    "sg:classifiers":[
        {
            "category":"Travel",
            "subcategory":"Hotels & Motels",
            "type":"Entertainment"
        }
    ],
    "sg:postcode":"LL28 4BS",
    "sg:province":"Conwy",
    "sg:tags":[
        "house",
        "guest"
    ],
    "wof:name":"Anchor Hotel",
    "wof:placetype":"venue"
},
  "geometry": {"coordinates":[-3.7335460186,53.299747467],"type":"Point"}
}