{
  "type": "Feature",
  "properties": {
    "iso:country":"GB",
    "sg:address":"Dudley Clo",
    "sg:city":"Hemel Hempstead",
    "sg:classifiers":[
        {
            "category":"Government",
            "subcategory":"Office",
            "type":"Public Place"
        }
    ],
    "sg:phone":"+44 1442 833515",
    "sg:postcode":"HP3 0LR",
    "sg:province":"Hertfordshire",
    "sg:tags":[
        "local"
    ],
    "wof:name":"Dudley House Sheltered Housing",
    "wof:placetype":"venue"
},
  "geometry": {"coordinates":[-0.53266,51.725986],"type":"Point"}
}