{
  "type": "Feature",
  "properties": {
    "iso:country":"GB",
    "sg:address":"5-7 Leytonstone Road",
    "sg:city":"London",
    "sg:classifiers":[
        {
            "category":"Restaurant",
            "type":"Food & Drink"
        }
    ],
    "sg:phone":"+44 20 8534 2066",
    "sg:postcode":"E15 1JA",
    "sg:province":"Greater London",
    "wof:name":"M A Khan",
    "wof:placetype":"venue"
},
  "geometry": {"coordinates":[0.004592,51.546028],"type":"Point"}
}