{
  "type": "Feature",
  "properties": {
    "addr:full":"118 Hillmorton Road Rugby Warwickshire CV22 5AL",
    "addr:housenumber":"118",
    "addr:postcode":"cv22 5al",
    "addr:street":"Hillmorton Road",
    "iso:country":"GB",
    "sg:address":"118 Hillmorton Road",
    "sg:city":"Rugby",
    "sg:classifiers":[
        {
            "category":"Fast Food",
            "type":"Food & Drink"
        }
    ],
    "sg:phone":"+44 1788 547186",
    "sg:postcode":"CV22 5AL",
    "sg:province":"Warwickshire",
    "sg:tags":[
        "away",
        "take"
    ],
    "wof:name":"Rugby House",
    "wof:placetype":"venue"
},
  "geometry": {"coordinates":[-1.245232,52.366711],"type":"Point"}
}