{
  "type": "Feature",
  "properties": {
    "addr:full":"Montgomerie Street Girvan South Ayrshire KA26 9HE",
    "addr:postcode":"ka26 9he",
    "addr:street":"Montgomerie Street",
    "iso:country":"GB",
    "sg:address":"Montgomerie Street",
    "sg:city":"Girvan",
    "sg:classifiers":[
        {
            "category":"Place Of Worship",
            "type":"Public Place"
        }
    ],
    "sg:phone":"+44 1465 712672",
    "sg:postcode":"KA26 9HE",
    "sg:province":"South Ayrshire",
    "wof:name":"Girvan North Parish Church",
    "wof:placetype":"venue"
},
  "geometry": {"coordinates":[-4.8525891304,55.2459602356],"type":"Point"}
}