{
  "type": "Feature",
  "properties": {
    "iso:country":"GB",
    "sg:address":"137 Parkdale Road, Carlton",
    "sg:city":"Nottingham",
    "sg:classifiers":[
        {
            "category":"Building & Trades",
            "subcategory":"Construction",
            "type":"Services"
        }
    ],
    "sg:phone":"+44 115 987 3809",
    "sg:postcode":"NG4 1BW",
    "sg:province":"Nottinghamshire",
    "sg:tags":[
        "decorator",
        "painter"
    ],
    "wof:name":"Reginald J Albery",
    "wof:placetype":"venue"
},
  "geometry": {"coordinates":[-1.101502,52.962128],"type":"Point"}
}