{
  "type": "Feature",
  "properties": {
    "addr:full":"Old Telephone Exchange, Watling Street Leighton Buzzard Bedfordshire LU7 9LP",
    "addr:postcode":"lu7 9lp",
    "addr:street":"Watling Street",
    "iso:country":"GB",
    "sg:address":"Old Telephone Exchange, Watling Street",
    "sg:city":"Leighton Buzzard",
    "sg:classifiers":[
        {
            "category":"Building & Trades",
            "subcategory":"Construction",
            "type":"Services"
        }
    ],
    "sg:phone":"+44 1525 210128",
    "sg:postcode":"LU7 9LP",
    "sg:province":"Bedfordshire",
    "sg:tags":[
        "joiner",
        "carpenter"
    ],
    "wof:name":"John Woollison",
    "wof:placetype":"venue"
},
  "geometry": {"coordinates":[-0.663909,51.917351],"type":"Point"}
}