{
  "type": "Feature",
  "properties": {
    "iso:country":"GB",
    "sg:address":"Briar Close Business Park, Briar Close",
    "sg:city":"Evesham",
    "sg:classifiers":[
        {
            "category":"Communications",
            "subcategory":"Newspaper",
            "type":"Services"
        }
    ],
    "sg:phone":"+44 1386 442555",
    "sg:postcode":"WR11 4JT",
    "sg:province":"Gloucestershire",
    "sg:tags":[
        "magazine"
    ],
    "wof:name":"Evesham Journal",
    "wof:placetype":"venue"
},
  "geometry": {"coordinates":[-1.9489790201,52.097038269],"type":"Point"}
}