{
  "type": "Feature",
  "properties": {
    "iso:country":"GB",
    "sg:address":"38 Wimblington Rd",
    "sg:city":"March",
    "sg:classifiers":[
        {
            "category":"Freight",
            "type":"Transportation"
        }
    ],
    "sg:postcode":"PE15 9QN",
    "sg:province":"Cambridgeshire",
    "sg:tags":[
        "haulage",
        "road"
    ],
    "wof:name":"Mitcham,John L,",
    "wof:placetype":"venue"
},
  "geometry": {"coordinates":[0.087731,52.532906],"type":"Point"}
}