{
  "type": "Feature",
  "properties": {
    "addr:full":"Unit 7 The Steadings Maisemore Ct Gloucester Gloucestershire GL2 8EY",
    "addr:housenumber":"unit 7",
    "addr:postcode":"gl2 8ey",
    "addr:street":"The;Maisemore Ct",
    "iso:country":"GB",
    "sg:address":"Unit 7 The Steadings Maisemore Ct",
    "sg:city":"Gloucester",
    "sg:classifiers":[
        {
            "category":"Professional",
            "subcategory":"Engineering",
            "type":"Services"
        }
    ],
    "sg:phone":"+44 1452 307280",
    "sg:postcode":"GL2 8EY",
    "sg:province":"Gloucestershire",
    "sg:tags":[
        "engineer",
        "mechanical"
    ],
    "wof:name":"G E A Gallay Systens Ltd",
    "wof:placetype":"venue"
},
  "geometry": {"coordinates":[-2.2716701031,51.8930397034],"type":"Point"}
}