{
  "type": "Feature",
  "properties": {
    "addr:full":"9 Central Business Centre, Great Central Way London Greater London NW10 0UR",
    "addr:housenumber":"9",
    "addr:postcode":"nw10 0ur",
    "addr:street":"Central Business Centre Great Central Way",
    "iso:country":"GB",
    "sg:address":"9 Central Business Centre, Great Central Way",
    "sg:city":"London",
    "sg:classifiers":[
        {
            "category":"Restaurant",
            "type":"Food & Drink"
        }
    ],
    "sg:phone":"+44 20 8830 2424",
    "sg:postcode":"NW10 0UR",
    "sg:province":"Greater London",
    "wof:name":"Spudulike Group Ltd.",
    "wof:placetype":"venue"
},
  "geometry": {"coordinates":[-0.25266,51.55365],"type":"Point"}
}