{
  "type": "Feature",
  "properties": {
    "iso:country":"GB",
    "sg:address":"2 Mill Parade, Mill Lane, Storrington",
    "sg:city":"Pulborough",
    "sg:classifiers":[
        {
            "category":"Personal",
            "subcategory":"Beauty Salon",
            "type":"Services"
        },
        {
            "category":"Personal",
            "subcategory":"Barber",
            "type":"Services"
        }
    ],
    "sg:phone":"+44 1903 742865",
    "sg:postcode":"RH20 4NF",
    "sg:province":"West Sussex",
    "sg:tags":[
        "unisex",
        "hairdresser"
    ],
    "wof:name":"Headline 2",
    "wof:placetype":"venue"
},
  "geometry": {"coordinates":[-0.4538590014,50.9178009033],"type":"Point"}
}