{
  "type": "Feature",
  "properties": {
    "addr:full":"Heald House, Heald Street, Garston Liverpool Merseyside L19 2LY",
    "addr:postcode":"l19 2ly",
    "addr:street":"Heald Street",
    "iso:country":"GB",
    "sg:address":"Heald House, Heald Street, Garston",
    "sg:city":"Liverpool",
    "sg:classifiers":[
        {
            "category":"Home & Garden",
            "subcategory":"Carpets & Floor Coverings",
            "type":"Retail Goods"
        }
    ],
    "sg:postcode":"L19 2LY",
    "sg:province":"Merseyside",
    "sg:tags":[
        "wall",
        "tie",
        "replacement"
    ],
    "wof:name":"Wall Tie Installers Federation",
    "wof:placetype":"venue"
},
  "geometry": {"coordinates":[-2.899514,53.355213],"type":"Point"}
}