{
  "type": "Feature",
  "properties": {
    "iso:country":"GB",
    "sg:address":"Pier Cottage",
    "sg:city":"Coniston",
    "sg:classifiers":[
        {
            "category":"Landmark",
            "subcategory":"Tourist Attraction",
            "type":"Public Place"
        }
    ],
    "sg:phone":"+44 15394 41288",
    "sg:postcode":"LA21 8AJ",
    "sg:province":"Cumbria",
    "sg:tags":[
        "interest"
    ],
    "wof:name":"National Trust (The)",
    "wof:placetype":"venue"
},
  "geometry": {"coordinates":[-3.075541,54.370098],"type":"Point"}
}