{
  "type": "Feature",
  "properties": {
    "iso:country":"GB",
    "sg:address":"Draycot Yard, Ladysmith Rd",
    "sg:city":"Swindon",
    "sg:classifiers":[
        {
            "category":"Sports & Exercise",
            "subcategory":"Stables",
            "type":"Entertainment"
        }
    ],
    "sg:phone":"+44 1793 741433",
    "sg:postcode":"SN4 0SY",
    "sg:province":"Wiltshire",
    "sg:tags":[
        "education",
        "equestrian"
    ],
    "wof:name":"Cowley Bros Ltd",
    "wof:placetype":"venue"
},
  "geometry": {"coordinates":[-1.735489,51.513165],"type":"Point"}
}