{
  "type": "Feature",
  "properties": {
    "addr:full":"71, Troutbeck, Albany Street Camden Greater London NW1 4EJ",
    "addr:housenumber":"71",
    "addr:postcode":"nw1 4ej",
    "addr:street":"Troutbeck Albany Street",
    "iso:country":"GB",
    "sg:address":"71, Troutbeck, Albany Street",
    "sg:city":"Camden",
    "sg:classifiers":[
        {
            "category":"Health Services",
            "subcategory":"Dentist",
            "type":"Services"
        }
    ],
    "sg:phone":"+44 20 7419 4848",
    "sg:postcode":"NW1 4EJ",
    "sg:province":"Greater London",
    "sg:tags":[
        "technician",
        "instrument",
        "dental"
    ],
    "wof:name":"Dental Lab",
    "wof:placetype":"venue"
},
  "geometry": {"coordinates":[-0.1439999938,51.5278587341],"type":"Point"}
}