{
  "type": "Feature",
  "properties": {
    "addr:full":"Maplan House, Main Street Glasgow Glasgow City G73 3AE",
    "addr:postcode":"g73 3ae",
    "addr:street":"Main Street",
    "iso:country":"GB",
    "sg:address":"Maplan House, Main Street",
    "sg:city":"Glasgow",
    "sg:classifiers":[
        {
            "category":"Manufacturing",
            "subcategory":"Petroleum Products",
            "type":"Manufacturing & Wholesale Goods"
        }
    ],
    "sg:phone":"+44 1292 671333",
    "sg:postcode":"G73 3AE",
    "sg:province":"Glasgow City",
    "sg:tags":[
        "double",
        "glazing"
    ],
    "wof:name":"Carrick Windows (Ayrshire) Ltd.",
    "wof:placetype":"venue"
},
  "geometry": {"coordinates":[-4.209458828,55.8285140991],"type":"Point"}
}