{
  "type": "Feature",
  "properties": {
    "iso:country":"GB",
    "sg:address":"67 Manor Road, St Helen Auckland",
    "sg:city":"Bishop Auckland",
    "sg:classifiers":[
        {
            "category":"Bars & Pubs",
            "type":"Food & Drink"
        }
    ],
    "sg:phone":"+44 1388 605437",
    "sg:postcode":"DL14 9ER",
    "sg:province":"Durham",
    "sg:tags":[
        "pubs",
        "inn"
    ],
    "wof:name":"The Wheatsheaf Inn",
    "wof:placetype":"venue"
},
  "geometry": {"coordinates":[-1.759209,54.619839],"type":"Point"}
}