{
  "type": "Feature",
  "properties": {
    "addr:full":"162a Bishopthorpe Road York North Yorkshire YO23 1LF",
    "addr:housenumber":"162a",
    "addr:postcode":"yo23 1lf",
    "addr:street":"Bishopthorpe Road",
    "iso:country":"GB",
    "sg:address":"162a Bishopthorpe Road",
    "sg:city":"York",
    "sg:classifiers":[
        {
            "category":"Food & Beverages",
            "subcategory":"Groceries & Convenience Stores",
            "type":"Retail Goods"
        }
    ],
    "sg:phone":"+44 1904 673556",
    "sg:postcode":"YO23 1LF",
    "sg:province":"North Yorkshire",
    "wof:name":"Pat's Place",
    "wof:placetype":"venue"
},
  "geometry": {"coordinates":[-1.085691,53.946308],"type":"Point"}
}