{
  "type": "Feature",
  "properties": {
    "iso:country":"GB",
    "sg:address":"45 Pinfold Hill",
    "sg:city":"Lichfield",
    "sg:classifiers":[
        {
            "category":"Organizations",
            "subcategory":"Non-profit Organization",
            "type":"Services"
        }
    ],
    "sg:phone":"+44 1543 480011",
    "sg:postcode":"WS14 0JN",
    "sg:province":"Staffordshire",
    "sg:tags":[
        "organisation",
        "voluntary",
        "charity"
    ],
    "wof:name":"M E Midlands",
    "wof:placetype":"venue"
},
  "geometry": {"coordinates":[-1.8364360332,52.6416053772],"type":"Point"}
}