{
  "type": "Feature",
  "properties": {
    "addr:full":"Lake Road, Bowness-On-Windermere Windermere Cumbria LA23 3AP",
    "addr:postcode":"la23 3ap",
    "addr:street":"Lake Road",
    "iso:country":"GB",
    "sg:address":"Lake Road, Bowness-On-Windermere",
    "sg:city":"Windermere",
    "sg:classifiers":[
        {
            "category":"Home & Garden",
            "subcategory":"Household Appliances",
            "type":"Retail Goods"
        },
        {
            "category":"Retail",
            "subcategory":"Event Space",
            "type":"Services"
        }
    ],
    "sg:phone":"+44 15394 42323",
    "sg:postcode":"LA23 3AP",
    "sg:province":"Cumbria",
    "sg:tags":[
        "electrical",
        "product",
        "domestic",
        "sales"
    ],
    "wof:name":"Lakeland Electric",
    "wof:placetype":"venue"
},
  "geometry": {"coordinates":[-2.9161539078,54.3670310974],"type":"Point"}
}