{
  "type": "Feature",
  "properties": {
    "iso:country":"GB",
    "sg:address":"187 Market Street",
    "sg:city":"Hyde",
    "sg:classifiers":[
        {
            "category":"Retail",
            "subcategory":"Storage",
            "type":"Services"
        }
    ],
    "sg:phone":"+44 161 366 5553",
    "sg:postcode":"SK14 1HF",
    "sg:province":"Cheshire",
    "sg:tags":[
        "household",
        "removal"
    ],
    "wof:name":"Atherton Allsorts",
    "wof:placetype":"venue"
},
  "geometry": {"coordinates":[-2.0759410858,53.4478378296],"type":"Point"}
}