{
  "type": "Feature",
  "properties": {
    "addr:full":"13 Thesiger Road Abingdon Oxfordshire OX14 2DX",
    "addr:housenumber":"13",
    "addr:postcode":"ox14 2dx",
    "addr:street":"Thesiger Road",
    "iso:country":"GB",
    "sg:address":"13 Thesiger Road",
    "sg:city":"Abingdon",
    "sg:classifiers":[
        {
            "category":"Building & Trades",
            "subcategory":"Cleaning & Sanitation",
            "type":"Services"
        }
    ],
    "sg:phone":"+44 1235 526892",
    "sg:postcode":"OX14 2DX",
    "sg:province":"Oxfordshire",
    "sg:tags":[
        "contracting",
        "commercial"
    ],
    "wof:name":"C F S Cleaning Service",
    "wof:placetype":"venue"
},
  "geometry": {"coordinates":[-1.2800960541,51.6752586365],"type":"Point"}
}