{
  "type": "Feature",
  "properties": {
    "iso:country":"GB",
    "sg:address":"8 Common Nook, Ince",
    "sg:city":"Wigan",
    "sg:classifiers":[
        {
            "category":"Transit Center",
            "subcategory":"Passenger",
            "type":"Transportation"
        }
    ],
    "sg:phone":"+44 1942 242215",
    "sg:postcode":"WN2 2TA",
    "sg:province":"Lancashire",
    "sg:tags":[
        "boarding",
        "kennel",
        "catteries"
    ],
    "wof:name":"Amberswood Boarding Kennels",
    "wof:placetype":"venue"
},
  "geometry": {"coordinates":[-2.590619,53.545891],"type":"Point"}
}