{
  "type": "Feature",
  "properties": {
    "iso:country":"GB",
    "sg:address":"Gatting Way, Off Pk Rd",
    "sg:city":"Uxbridge",
    "sg:classifiers":[
        {
            "category":"Personal",
            "subcategory":"Sauna",
            "type":"Services"
        }
    ],
    "sg:postcode":"UB8 1NR",
    "sg:province":"Buckinghamshire",
    "wof:name":"Uxbridge Sauna",
    "wof:placetype":"venue"
},
  "geometry": {"coordinates":[-0.470214,51.551842],"type":"Point"}
}