{
  "type": "Feature",
  "properties": {
    "iso:country":"GB",
    "sg:address":"Newcombe House Notting Hill",
    "sg:city":"London",
    "sg:classifiers":[
        {
            "category":"Professional",
            "subcategory":"Computer Services",
            "type":"Services"
        }
    ],
    "sg:postcode":"W11 3LQ",
    "sg:tags":[
        "journalism",
        "news",
        "photography",
        "social-media"
    ],
    "sg:website":"http://www.demotix.com",
    "wof:name":"Demotix",
    "wof:placetype":"venue"
},
  "geometry": {"coordinates":[-0.1243129,51.5105777],"type":"Point"}
}