{
  "type": "Feature",
  "properties": {
    "addr:full":"Cargo Fleet Base Normanby Wharf, Dockside Rd Middlesbrough North Yorkshire TS3 8AT",
    "addr:postcode":"ts3 8at",
    "addr:street":"Normanby Wharf Dockside Rd",
    "iso:country":"GB",
    "sg:address":"Cargo Fleet Base Normanby Wharf, Dockside Rd",
    "sg:city":"Middlesbrough",
    "sg:classifiers":[
        {
            "category":"Professional",
            "subcategory":"Detective & Security Services",
            "type":"Services"
        }
    ],
    "sg:postcode":"TS3 8AT",
    "sg:province":"North Yorkshire",
    "wof:name":"Saunders,David,",
    "wof:placetype":"venue"
},
  "geometry": {"coordinates":[-1.2016400099,54.5797805786],"type":"Point"}
}