{
  "type": "Feature",
  "properties": {
    "iso:country":"GB",
    "sg:address":"40 Church Street, Woodlesford",
    "sg:city":"Leeds",
    "sg:classifiers":[
        {
            "category":"Bars & Pubs",
            "type":"Food & Drink"
        }
    ],
    "sg:phone":"+44 113 282 2205",
    "sg:postcode":"LS26 8RD",
    "sg:province":"West Yorkshire",
    "sg:tags":[
        "pubs",
        "house",
        "inn",
        "public",
        "activity"
    ],
    "wof:name":"The White Hart",
    "wof:placetype":"venue"
},
  "geometry": {"coordinates":[-1.422798,53.77103],"type":"Point"}
}