{
  "type": "Feature",
  "properties": {
    "iso:country":"GB",
    "sg:address":"Allen House, The Maltings",
    "sg:city":"Sawbridgeworth",
    "sg:classifiers":[
        {
            "category":"Autos & Motor Vehicles",
            "subcategory":"Auto Supplies",
            "type":"Retail Goods"
        }
    ],
    "sg:postcode":"CM21 9JX",
    "sg:province":"Essex",
    "sg:tags":[
        "electric"
    ],
    "wof:name":"Zicon Electronics Ltd.",
    "wof:placetype":"venue"
},
  "geometry": {"coordinates":[0.147223,51.812527],"type":"Point"}
}