{
  "type": "Feature",
  "properties": {
    "addr:full":"Stoney Garth, Moss Road, Moss Doncaster North Yorkshire DN6 0HL",
    "addr:postcode":"dn6 0hl",
    "addr:street":"Stoney Garth Moss Road",
    "iso:country":"GB",
    "sg:address":"Stoney Garth, Moss Road, Moss",
    "sg:city":"Doncaster",
    "sg:classifiers":[
        {
            "category":"Landmark",
            "subcategory":"Tourist Information",
            "type":"Public Place"
        }
    ],
    "sg:postcode":"DN6 0HL",
    "sg:province":"North Yorkshire",
    "sg:tags":[
        "tour",
        "guide",
        "sightseeing"
    ],
    "wof:name":"Howdens Coaches",
    "wof:placetype":"venue"
},
  "geometry": {"coordinates":[-1.098443985,53.6219062805],"type":"Point"}
}