{
  "type": "Feature",
  "properties": {
    "addr:full":"12-15 Hanger Grn, Ealing London Greater London W5 3AY",
    "addr:housenumber":"12-15",
    "addr:postcode":"w5 3ay",
    "addr:street":"Hanger Grn",
    "iso:country":"GB",
    "sg:address":"12-15 Hanger Grn, Ealing",
    "sg:city":"London",
    "sg:classifiers":[
        {
            "category":"Professional",
            "subcategory":"Accounting & Tax Preparation",
            "type":"Services"
        }
    ],
    "sg:phone":"+44 20 8354 9000",
    "sg:postcode":"W5 3AY",
    "sg:province":"Greater London",
    "sg:tags":[
        "accountant"
    ],
    "wof:name":"Stern & Co. Ltd.",
    "wof:placetype":"venue"
},
  "geometry": {"coordinates":[-0.28487,51.526588],"type":"Point"}
}