{
  "type": "Feature",
  "properties": {
    "iso:country":"GB",
    "sg:address":"7 Effingham Cres",
    "sg:city":"Dover",
    "sg:classifiers":[
        {
            "category":"Autos & Motor Vehicles",
            "subcategory":"Automobile Sales",
            "type":"Retail Goods"
        }
    ],
    "sg:postcode":"CT17 9RH",
    "sg:province":"Kent",
    "sg:tags":[
        "car"
    ],
    "wof:name":"Reid,A,",
    "wof:placetype":"venue"
},
  "geometry": {"coordinates":[1.30896,51.12772],"type":"Point"}
}