{
  "type": "Feature",
  "properties": {
    "iso:country":"GB",
    "sg:address":"Unit 2 Park Road, Hartwell",
    "sg:city":"Northampton",
    "sg:classifiers":[
        {
            "category":"Freight",
            "type":"Transportation"
        }
    ],
    "sg:postcode":"NN7 2HP",
    "sg:province":"Buckinghamshire",
    "sg:tags":[
        "haulage",
        "road"
    ],
    "wof:name":"Stordel Services",
    "wof:placetype":"venue"
},
  "geometry": {"coordinates":[-0.85409,52.145782],"type":"Point"}
}