{
  "type": "Feature",
  "properties": {
    "addr:full":"7 Harley Villas, Harlesdon London Greater London NW10 8BD",
    "addr:housenumber":"7",
    "addr:postcode":"nw10 8bd",
    "addr:street":"Harley Villas",
    "iso:country":"GB",
    "sg:address":"7 Harley Villas, Harlesdon",
    "sg:city":"London",
    "sg:classifiers":[
        {
            "category":"Building & Trades",
            "subcategory":"Construction",
            "type":"Services"
        }
    ],
    "sg:postcode":"NW10 8BD",
    "sg:province":"Greater London",
    "sg:tags":[
        "builder"
    ],
    "wof:name":"Backpack Construction Ltd",
    "wof:placetype":"venue"
},
  "geometry": {"coordinates":[-0.2494679987,51.5338096619],"type":"Point"}
}