{
  "type": "Feature",
  "properties": {
    "addr:full":"7 Market Pl Hayle Cornwall TR27 4EA",
    "addr:housenumber":"7",
    "addr:postcode":"tr27 4ea",
    "addr:street":"Market Pl",
    "iso:country":"GB",
    "sg:address":"7 Market Pl",
    "sg:city":"Hayle",
    "sg:classifiers":[
        {
            "category":"Cinema",
            "subcategory":"Movie Rental",
            "type":"Entertainment"
        }
    ],
    "sg:phone":"+44 1736 753941",
    "sg:postcode":"TR27 4EA",
    "sg:province":"Cornwall",
    "sg:tags":[
        "video",
        "library"
    ],
    "wof:name":"Penwith Video Library",
    "wof:placetype":"venue"
},
  "geometry": {"coordinates":[-5.40846,50.191151],"type":"Point"}
}