{
  "type": "Feature",
  "properties": {
    "addr:full":"Middale, Longsleddale Kendal Cumbria LA8 9BD",
    "addr:postcode":"la8 9bd",
    "iso:country":"GB",
    "sg:address":"Middale, Longsleddale",
    "sg:city":"Kendal",
    "sg:classifiers":[
        {
            "category":"Home & Garden",
            "subcategory":"Garden Supply",
            "type":"Retail Goods"
        },
        {
            "category":"Farming",
            "subcategory":"Farm",
            "type":"Manufacturing & Wholesale Goods"
        }
    ],
    "sg:postcode":"LA8 9BD",
    "sg:province":"Cumbria",
    "sg:tags":[
        "mixed",
        "bulb",
        "crop",
        "grower"
    ],
    "wof:name":"John A Bennett",
    "wof:placetype":"venue"
},
  "geometry": {"coordinates":[-2.77887,54.427719],"type":"Point"}
}