{
  "type": "Feature",
  "properties": {
    "addr:full":"Unit 40-43, Hardengreen Industrial Estate Dalkeith City of Edinburgh EH22 3NU",
    "addr:housenumber":"unit 40-43",
    "addr:postcode":"eh22 3nu",
    "addr:street":"Hardengreen Industrial Estate",
    "iso:country":"GB",
    "sg:address":"Unit 40-43, Hardengreen Industrial Estate",
    "sg:city":"Dalkeith",
    "sg:classifiers":[
        {
            "category":"Insurance",
            "subcategory":"Insurance Agent",
            "type":"Services"
        }
    ],
    "sg:phone":"+44 131 454 0321",
    "sg:postcode":"EH22 3NU",
    "sg:province":"City of Edinburgh",
    "wof:name":"Tribune Risk & Insurance Services Ltd.",
    "wof:placetype":"venue"
},
  "geometry": {"coordinates":[-3.0837199688,55.8839645386],"type":"Point"}
}