{
  "type": "Feature",
  "properties": {
    "iso:country":"GB",
    "sg:address":"10a Bank Street",
    "sg:city":"Newquay",
    "sg:classifiers":[
        {
            "category":"Personal",
            "subcategory":"Beauty Salon",
            "type":"Services"
        }
    ],
    "sg:phone":"+44 1637 872441",
    "sg:postcode":"TR7 1JF",
    "sg:province":"Cornwall",
    "sg:tags":[
        "unisex",
        "hairdresser"
    ],
    "wof:name":"Renee Hair Design",
    "wof:placetype":"venue"
},
  "geometry": {"coordinates":[-5.086484,50.413349],"type":"Point"}
}