{
  "type": "Feature",
  "properties": {
    "addr:full":"P O Box 95 Loughborough Leicestershire LE11 5ZJ",
    "addr:housenumber":"box 95",
    "addr:postcode":"le11 5zj",
    "addr:street":"P O",
    "iso:country":"GB",
    "sg:address":"P O Box 95",
    "sg:city":"Loughborough",
    "sg:classifiers":[
        {
            "category":"Professional",
            "type":"Services"
        }
    ],
    "sg:phone":"+44 1509 646553",
    "sg:postcode":"LE11 5ZJ",
    "sg:province":"Leicestershire",
    "sg:tags":[
        "exhibition"
    ],
    "wof:name":"Dishley Exhibitions Ltd.",
    "wof:placetype":"venue"
},
  "geometry": {"coordinates":[-1.2234740257,52.7685241699],"type":"Point"}
}