{
  "type": "Feature",
  "properties": {
    "addr:full":"Brunel Drive Newark Nottinghamshire NG24 2EQ",
    "addr:postcode":"ng24 2eq",
    "addr:street":"Brunel Drive",
    "iso:country":"GB",
    "sg:address":"Brunel Drive",
    "sg:city":"Newark",
    "sg:classifiers":[
        {
            "category":"Professional",
            "subcategory":"Engineering",
            "type":"Services"
        }
    ],
    "sg:phone":"+44 1636 676694",
    "sg:postcode":"NG24 2EQ",
    "sg:province":"Nottinghamshire",
    "wof:name":"Greenberry Bros (Engineering) Ltd.",
    "wof:placetype":"venue"
},
  "geometry": {"coordinates":[-0.7868390083,53.0882263184],"type":"Point"}
}