{
  "type": "Feature",
  "properties": {
    "addr:full":"28 Beach Road West Felixstowe Suffolk IP11 2BL",
    "addr:housenumber":"28",
    "addr:postcode":"ip11 2bl",
    "addr:street":"Beach Road West",
    "iso:country":"GB",
    "sg:address":"28 Beach Road West",
    "sg:city":"Felixstowe",
    "sg:classifiers":[
        {
            "category":"Place Of Worship",
            "type":"Public Place"
        }
    ],
    "sg:phone":"+44 1394 286671",
    "sg:postcode":"IP11 2BL",
    "sg:province":"Suffolk",
    "wof:name":"Temple of Light Christian Spiritualist Church",
    "wof:placetype":"venue"
},
  "geometry": {"coordinates":[1.3407239914,51.9562721252],"type":"Point"}
}