{
  "type": "Feature",
  "properties": {
    "iso:country":"GB",
    "sg:address":"Ty Bryn, 50 Forest View",
    "sg:city":"Mountain Ash",
    "sg:classifiers":[
        {
            "category":"Communications",
            "type":"Services"
        }
    ],
    "sg:postcode":"CF45 3DU",
    "sg:province":"Rhondda, Cynon, Taff",
    "sg:tags":[
        "tv",
        "video",
        "radio"
    ],
    "wof:name":"Stuart Lewis Systems",
    "wof:placetype":"venue"
},
  "geometry": {"coordinates":[-3.378964,51.684399],"type":"Point"}
}