{
  "type": "Feature",
  "properties": {
    "addr:full":"7 St James Road Southampton Hampshire SO15 5FB",
    "addr:housenumber":"7",
    "addr:postcode":"so15 5fb",
    "addr:street":"St James Road",
    "iso:country":"GB",
    "sg:address":"7 St James Road",
    "sg:city":"Southampton",
    "sg:classifiers":[
        {
            "category":"Shopping",
            "subcategory":"Discount & Variety Stores",
            "type":"Retail Goods"
        }
    ],
    "sg:phone":"+44 23 8077 1546",
    "sg:postcode":"SO15 5FB",
    "sg:province":"Hampshire",
    "sg:tags":[
        "shop",
        "model"
    ],
    "wof:name":"Footplate Model Railways",
    "wof:placetype":"venue"
},
  "geometry": {"coordinates":[-1.429954,50.92799],"type":"Point"}
}