{
  "type": "Feature",
  "properties": {
    "iso:country":"GB",
    "sg:address":"16 Plas Newydd",
    "sg:city":"Cardiff",
    "sg:classifiers":[
        {
            "category":"Shopping",
            "subcategory":"News",
            "type":"Retail Goods"
        }
    ],
    "sg:phone":"+44 29 2052 0477",
    "sg:postcode":"CF4 1NR",
    "sg:province":"Cardiff",
    "sg:tags":[
        "newsagent"
    ],
    "wof:name":"A & J News",
    "wof:placetype":"venue"
},
  "geometry": {"coordinates":[-3.166737,51.491394],"type":"Point"}
}