{
  "type": "Feature",
  "properties": {
    "addr:full":"138 Gloucester Road, Bishopston Bristol City of Bristol BS7 8NT",
    "addr:housenumber":"138",
    "addr:postcode":"bs7 8nt",
    "addr:street":"Gloucester Road",
    "iso:country":"GB",
    "sg:address":"138 Gloucester Road, Bishopston",
    "sg:city":"Bristol",
    "sg:classifiers":[
        {
            "category":"Autos & Motor Vehicles",
            "subcategory":"Automobile Sales",
            "type":"Retail Goods"
        }
    ],
    "sg:phone":"+44 117 975 4304",
    "sg:postcode":"BS7 8NT",
    "sg:province":"City of Bristol",
    "sg:tags":[
        "car"
    ],
    "wof:name":"Automart",
    "wof:placetype":"venue"
},
  "geometry": {"coordinates":[-2.590443,51.476978],"type":"Point"}
}