{
  "type": "Feature",
  "properties": {
    "addr:full":"Pioneer Wks, Marsh La, Taplow Maidenhead Berkshire SL6 0DF",
    "addr:postcode":"sl6 0df",
    "addr:street":"Marsh La Taplow",
    "iso:country":"GB",
    "sg:address":"Pioneer Wks, Marsh La, Taplow",
    "sg:city":"Maidenhead",
    "sg:classifiers":[
        {
            "category":"Building & Trades",
            "subcategory":"Construction",
            "type":"Services"
        }
    ],
    "sg:phone":"+44 1628 674636",
    "sg:postcode":"SL6 0DF",
    "sg:province":"Berkshire",
    "sg:tags":[
        "platform",
        "work",
        "scaffolding"
    ],
    "wof:name":"Generation Building Equipment Ltd",
    "wof:placetype":"venue"
},
  "geometry": {"coordinates":[-0.687149,51.532169],"type":"Point"}
}