{
  "type": "Feature",
  "properties": {
    "addr:full":"6 Radford Street Stone Staffordshire ST15 8DA",
    "addr:housenumber":"6",
    "addr:postcode":"st15 8da",
    "addr:street":"Radford Street",
    "iso:country":"GB",
    "sg:address":"6 Radford Street",
    "sg:city":"Stone",
    "sg:classifiers":[
        {
            "category":"Professional",
            "subcategory":"Business Services",
            "type":"Services"
        }
    ],
    "sg:phone":"+44 500 401289",
    "sg:postcode":"ST15 8DA",
    "sg:province":"Staffordshire",
    "sg:tags":[
        "import",
        "export",
        "agent"
    ],
    "wof:name":"Total Communications",
    "wof:placetype":"venue"
},
  "geometry": {"coordinates":[-2.148489,52.904533],"type":"Point"}
}