{
  "type": "Feature",
  "properties": {
    "addr:full":"1 Manse Road, Coylton Ayr East Ayrshire KA6 6LD",
    "addr:housenumber":"1",
    "addr:postcode":"ayr;ka6 6ld",
    "addr:street":"Manse Road",
    "iso:country":"GB",
    "sg:address":"1 Manse Road, Coylton",
    "sg:city":"Ayr",
    "sg:classifiers":[
        {
            "category":"Professional",
            "subcategory":"Engineering",
            "type":"Services"
        }
    ],
    "sg:phone":"+44 1292 570286",
    "sg:postcode":"KA6 6LD",
    "sg:province":"East Ayrshire",
    "sg:tags":[
        "contractor",
        "electrical",
        "engineer"
    ],
    "wof:name":"Kyleview Electrical Contractor",
    "wof:placetype":"venue"
},
  "geometry": {"coordinates":[-4.4942998886,55.4464988708],"type":"Point"}
}