{
  "type": "Feature",
  "properties": {
    "iso:country":"GB",
    "sg:address":"229 Queens Ct, Harris St",
    "sg:city":"Middlesbrough",
    "sg:classifiers":[
        {
            "category":"Freight",
            "type":"Transportation"
        }
    ],
    "sg:postcode":"TS1 5EF",
    "sg:province":"North Yorkshire",
    "sg:tags":[
        "haulage",
        "road"
    ],
    "wof:name":"Simpson,Chris,",
    "wof:placetype":"venue"
},
  "geometry": {"coordinates":[-1.236569,54.572971],"type":"Point"}
}