{
  "type": "Feature",
  "properties": {
    "addr:full":"239 Ruchill Street Glasgow Glasgow City G20 9QU",
    "addr:housenumber":"239",
    "addr:postcode":"g20 9qu",
    "addr:street":"Ruchill Street",
    "iso:country":"GB",
    "sg:address":"239 Ruchill Street",
    "sg:city":"Glasgow",
    "sg:classifiers":[
        {
            "category":"Community Center",
            "type":"Public Place"
        }
    ],
    "sg:phone":"+44 141 948 0340",
    "sg:postcode":"G20 9QU",
    "sg:province":"Glasgow City",
    "sg:tags":[
        "recreation",
        "leisure",
        "centre"
    ],
    "wof:name":"The Terraces Gym & Health Club",
    "wof:placetype":"venue"
},
  "geometry": {"coordinates":[-4.2766718864,55.8877944946],"type":"Point"}
}