{
  "type": "Feature",
  "properties": {
    "addr:full":"45 Wisbech Road March Cambridgeshire PE15 8ED",
    "addr:housenumber":"45",
    "addr:postcode":"pe15 8ed",
    "addr:street":"Wisbech Road",
    "iso:country":"GB",
    "sg:address":"45 Wisbech Road",
    "sg:city":"March",
    "sg:classifiers":[
        {
            "category":"Retail",
            "subcategory":"Repair Shop",
            "type":"Services"
        },
        {
            "category":"Manufacturing",
            "subcategory":"Furniture",
            "type":"Manufacturing & Wholesale Goods"
        }
    ],
    "sg:phone":"+44 1354 652967",
    "sg:postcode":"PE15 8ED",
    "sg:province":"Cambridgeshire",
    "sg:tags":[
        "mnfr",
        "upholstering",
        "upholsterer"
    ],
    "wof:name":"M C Upholsterers",
    "wof:placetype":"venue"
},
  "geometry": {"coordinates":[0.078025,52.554844],"type":"Point"}
}