{
  "type": "Feature",
  "properties": {
    "addr:full":"91 Duke Street Liverpool Merseyside L1 5AA",
    "addr:housenumber":"91",
    "addr:postcode":"l1 5aa",
    "addr:street":"Duke Street",
    "iso:country":"GB",
    "sg:address":"91 Duke Street",
    "sg:city":"Liverpool",
    "sg:classifiers":[
        {
            "category":"Banks & Credit Unions",
            "subcategory":"Investment Brokerage",
            "type":"Services"
        }
    ],
    "sg:phone":"+44 151 707 1707",
    "sg:postcode":"L1 5AA",
    "sg:province":"Merseyside",
    "sg:tags":[
        "stockbroker"
    ],
    "wof:name":"Blankstone Sington Ltd.",
    "wof:placetype":"venue"
},
  "geometry": {"coordinates":[-2.982949,53.40202],"type":"Point"}
}