{
  "type": "Feature",
  "properties": {
    "iso:country":"GB",
    "sg:address":"Unit 23, Western Rd",
    "sg:city":"Birmingham",
    "sg:classifiers":[
        {
            "category":"Retail",
            "subcategory":"Auto Repair",
            "type":"Services"
        }
    ],
    "sg:phone":"+44 121 551 4231",
    "sg:postcode":"B18 7QD",
    "sg:province":"West Midlands",
    "sg:tags":[
        "car",
        "specialist",
        "customizing"
    ],
    "wof:name":"P M Tyres",
    "wof:placetype":"venue"
},
  "geometry": {"coordinates":[-1.9280680418,52.4885406494],"type":"Point"}
}