{
  "type": "Feature",
  "properties": {
    "iso:country":"GB",
    "sg:address":"23 Market Pl",
    "sg:city":"Heywood",
    "sg:classifiers":[
        {
            "category":"Shopping",
            "subcategory":"Baby Store",
            "type":"Retail Goods"
        }
    ],
    "sg:phone":"+44 1706 626064",
    "sg:postcode":"OL10 1LA",
    "sg:province":"Lancashire",
    "sg:tags":[
        "babywear",
        "childrens"
    ],
    "wof:name":"Scrambles",
    "wof:placetype":"venue"
},
  "geometry": {"coordinates":[-2.220221,53.593521],"type":"Point"}
}