{
  "type": "Feature",
  "properties": {
    "addr:full":"70 High St, Holme On Spalding Moor York East Riding of Yorkshire YO43 4AA",
    "addr:housenumber":"70",
    "addr:postcode":"yo43 4aa",
    "addr:street":"High St;Moor",
    "iso:country":"GB",
    "sg:address":"70 High St, Holme On Spalding Moor",
    "sg:city":"York",
    "sg:classifiers":[
        {
            "category":"Food & Beverages",
            "subcategory":"Supermarket",
            "type":"Retail Goods"
        }
    ],
    "sg:phone":"+44 1430 860255",
    "sg:postcode":"YO43 4AA",
    "sg:province":"East Riding of Yorkshire",
    "wof:name":"Cost Cutters",
    "wof:placetype":"venue"
},
  "geometry": {"coordinates":[-0.7681519985,53.8363456726],"type":"Point"}
}