{
  "type": "Feature",
  "properties": {
    "iso:country":"GB",
    "sg:address":"St Johns Place",
    "sg:city":"Darlington",
    "sg:classifiers":[
        {
            "category":"Bars & Pubs",
            "type":"Food & Drink"
        }
    ],
    "sg:phone":"+44 1325 465516",
    "sg:postcode":"DL1 4AB",
    "sg:province":"Durham",
    "sg:tags":[
        "pubs",
        "inn"
    ],
    "wof:name":"Grey Horse Inn",
    "wof:placetype":"venue"
},
  "geometry": {"coordinates":[-1.544355,54.52301],"type":"Point"}
}