{
  "type": "Feature",
  "properties": {
    "addr:full":"266 Bury New Rd Salford Greater Manchester M7 2YJ",
    "addr:housenumber":"266",
    "addr:postcode":"m7 2yj",
    "addr:street":"Bury New Rd",
    "iso:country":"GB",
    "sg:address":"266 Bury New Rd",
    "sg:city":"Salford",
    "sg:classifiers":[
        {
            "category":"Retail",
            "subcategory":"Auto Rental",
            "type":"Services"
        }
    ],
    "sg:phone":"+44 161 708 9400",
    "sg:postcode":"M7 2YJ",
    "sg:province":"Greater Manchester",
    "sg:tags":[
        "car",
        "hire",
        "truck"
    ],
    "wof:name":"Bluepoint Leasing",
    "wof:placetype":"venue"
},
  "geometry": {"coordinates":[-2.2561750412,53.5003623962],"type":"Point"}
}