{
  "type": "Feature",
  "properties": {
    "addr:full":"Dovercourt, Manor Road Hayling Island Hampshire PO11 0QX",
    "addr:postcode":"po11 0qx",
    "addr:street":"Manor Road",
    "iso:country":"GB",
    "sg:address":"Dovercourt, Manor Road",
    "sg:city":"Hayling Island",
    "sg:classifiers":[
        {
            "category":"Recreation",
            "subcategory":"Campground",
            "type":"Entertainment"
        }
    ],
    "sg:phone":"+44 23 9246 4695",
    "sg:postcode":"PO11 0QX",
    "sg:province":"Hampshire",
    "sg:tags":[
        "operator",
        "site",
        "camping"
    ],
    "wof:name":"The Oven Camp Site",
    "wof:placetype":"venue"
},
  "geometry": {"coordinates":[-0.985454,50.796612],"type":"Point"}
}