{
  "type": "Feature",
  "properties": {
    "addr:full":"The Parkway Centre, Longbridge Road, Trafford Park Manchester Cheshire M17 1SN",
    "addr:postcode":"m17 1sn",
    "addr:street":"The Parkway;Longbridge Road",
    "iso:country":"GB",
    "sg:address":"The Parkway Centre, Longbridge Road, Trafford Park",
    "sg:city":"Manchester",
    "sg:classifiers":[
        {
            "category":"Home & Garden",
            "subcategory":"Kitchen Supply",
            "type":"Retail Goods"
        }
    ],
    "sg:phone":"+44 161 886 6500",
    "sg:postcode":"M17 1SN",
    "sg:province":"Cheshire",
    "sg:tags":[
        "catering"
    ],
    "wof:name":"A C S Catering Supplies",
    "wof:placetype":"venue"
},
  "geometry": {"coordinates":[-2.3083589077,53.4681396484],"type":"Point"}
}