{
  "type": "Feature",
  "properties": {
    "addr:full":"Forrestfield Street Glasgow East Dunbartonshire G21 2LE",
    "addr:postcode":"g21 2le",
    "addr:street":"Forrestfield Street",
    "iso:country":"GB",
    "sg:address":"Forrestfield Street",
    "sg:city":"Glasgow",
    "sg:classifiers":[
        {
            "category":"Community Center",
            "type":"Public Place"
        }
    ],
    "sg:phone":"+44 141 552 3218",
    "sg:postcode":"G21 2LE",
    "sg:province":"East Dunbartonshire",
    "sg:tags":[
        "recreation",
        "leisure",
        "centre"
    ],
    "wof:name":"Roystonhill Recreation Centre",
    "wof:placetype":"venue"
},
  "geometry": {"coordinates":[-4.221614,55.868454],"type":"Point"}
}