{
  "type": "Feature",
  "properties": {
    "addr:full":"37 Mafeking Avenue Brentford Greater London TW8 0NJ",
    "addr:housenumber":"37",
    "addr:postcode":"tw8 0nj",
    "addr:street":"Mafeking Avenue",
    "iso:country":"GB",
    "sg:address":"37 Mafeking Avenue",
    "sg:city":"Brentford",
    "sg:classifiers":[
        {
            "category":"Retail",
            "subcategory":"Auto Repair",
            "type":"Services"
        }
    ],
    "sg:postcode":"TW8 0NJ",
    "sg:province":"Greater London",
    "sg:tags":[
        "modification",
        "garage"
    ],
    "wof:name":"Bob's Bodyshop Ltd",
    "wof:placetype":"venue"
},
  "geometry": {"coordinates":[-0.301034,51.487148],"type":"Point"}
}