{
  "type": "Feature",
  "properties": {
    "addr:full":"Downs Ct 29 The Downs Altrincham Cheshire WA14 2QD",
    "addr:housenumber":"29",
    "addr:postcode":"wa14 2qd",
    "addr:street":"Downs Ct;The Downs",
    "iso:country":"GB",
    "sg:address":"Downs Ct 29 The Downs",
    "sg:city":"Altrincham",
    "sg:classifiers":[
        {
            "category":"Professional",
            "subcategory":"Lawyer & Legal Services",
            "type":"Services"
        }
    ],
    "sg:phone":"+44 161 941 5008",
    "sg:postcode":"WA14 2QD",
    "sg:province":"Cheshire",
    "sg:tags":[
        "practitioner",
        "insolvency"
    ],
    "wof:name":"Marlborough Consulting",
    "wof:placetype":"venue"
},
  "geometry": {"coordinates":[-2.349209,53.386726],"type":"Point"}
}