{
  "type": "Feature",
  "properties": {
    "addr:full":"81 High Street Honiton Devon EX14 1PG",
    "addr:housenumber":"81",
    "addr:postcode":"ex14 1pg",
    "addr:street":"High Street",
    "iso:country":"GB",
    "sg:address":"81 High Street",
    "sg:city":"Honiton",
    "sg:classifiers":[
        {
            "category":"Shopping",
            "subcategory":"Crafts & Fabrics",
            "type":"Retail Goods"
        }
    ],
    "sg:postcode":"EX14 1PG",
    "sg:province":"Devon",
    "sg:tags":[
        "material",
        "art"
    ],
    "wof:name":"The Art & Hobbies Shop",
    "wof:placetype":"venue"
},
  "geometry": {"coordinates":[-3.1878540516,50.800163269],"type":"Point"}
}