{
  "type": "Feature",
  "properties": {
    "addr:full":"199a High St Falkirk Falkirk FK1 1DU",
    "addr:housenumber":"199a",
    "addr:postcode":"fk1 1du",
    "addr:street":"High St",
    "iso:country":"GB",
    "sg:address":"199a High St",
    "sg:city":"Falkirk",
    "sg:classifiers":[
        {
            "category":"Sports & Exercise",
            "subcategory":"Sports Center",
            "type":"Entertainment"
        }
    ],
    "sg:phone":"+44 1324 610066",
    "sg:postcode":"FK1 1DU",
    "sg:province":"Falkirk",
    "sg:tags":[
        "shop",
        "good"
    ],
    "wof:name":"Select Skates",
    "wof:placetype":"venue"
},
  "geometry": {"coordinates":[-3.7806239128,55.9986495972],"type":"Point"}
}