{
  "type": "Feature",
  "properties": {
    "iso:country":"GB",
    "sg:address":"Unit 1, Devonshire Court",
    "sg:city":"Feltham",
    "sg:classifiers":[
        {
            "category":"Professional",
            "subcategory":"Business Services",
            "type":"Services"
        }
    ],
    "sg:phone":"+44 20 8890 0555",
    "sg:postcode":"TW13 7LU",
    "sg:province":"Greater London",
    "sg:tags":[
        "shop",
        "cleaning"
    ],
    "wof:name":"Dall Cleaning Services",
    "wof:placetype":"venue"
},
  "geometry": {"coordinates":[-0.407806,51.444672],"type":"Point"}
}