{
  "type": "Feature",
  "properties": {
    "iso:country":"GB",
    "sg:address":"45 Princess Street",
    "sg:city":"Cannock",
    "sg:classifiers":[
        {
            "category":"Health Services",
            "subcategory":"Doctor",
            "type":"Services"
        }
    ],
    "sg:phone":"+44 1543 571650",
    "sg:postcode":"WS11 5JT",
    "sg:province":"Staffordshire",
    "sg:tags":[
        "practitioners"
    ],
    "wof:name":"Chadsmore Medical Practice",
    "wof:placetype":"venue"
},
  "geometry": {"coordinates":[-2.023011,52.707703],"type":"Point"}
}