{
  "type": "Feature",
  "properties": {
    "iso:country":"GB",
    "sg:address":"101 Calley Down Crescent, New Addington",
    "sg:city":"Croydon",
    "sg:classifiers":[
        {
            "category":"Personal",
            "subcategory":"Beauty Salon",
            "type":"Services"
        }
    ],
    "sg:phone":"+44 1689 843471",
    "sg:postcode":"CR0 0EQ",
    "sg:province":"Surrey",
    "sg:tags":[
        "unisex",
        "hairdresser"
    ],
    "wof:name":"Exclusive Hairdressing",
    "wof:placetype":"venue"
},
  "geometry": {"coordinates":[-0.0065270001,51.3443756104],"type":"Point"}
}