{
  "type": "Feature",
  "properties": {
    "addr:full":"Lower Bowden Farm, Bowden Templecombe Somerset BA8 0PQ",
    "addr:housenumber":"bowden templecombe",
    "addr:postcode":"ba8 0pq",
    "addr:street":"Somerset",
    "iso:country":"GB",
    "sg:address":"Lower Bowden Farm, Bowden",
    "sg:city":"Templecombe",
    "sg:classifiers":[
        {
            "category":"Farming",
            "subcategory":"Farm",
            "type":"Manufacturing & Wholesale Goods"
        }
    ],
    "sg:postcode":"BA8 0PQ",
    "sg:province":"Somerset",
    "sg:tags":[
        "mixed",
        "crop"
    ],
    "wof:name":"Bowden Farms",
    "wof:placetype":"venue"
},
  "geometry": {"coordinates":[-2.415287,51.001381],"type":"Point"}
}