{
  "type": "Feature",
  "properties": {
    "addr:full":"16 Wyebank Way, Tutshill Chepstow Gloucestershire NP16 7DN",
    "addr:housenumber":"16",
    "addr:postcode":"np16 7dn",
    "addr:street":"Wyebank Way",
    "iso:country":"GB",
    "sg:address":"16 Wyebank Way, Tutshill",
    "sg:city":"Chepstow",
    "sg:classifiers":[
        {
            "category":"Building & Trades",
            "subcategory":"Cleaning & Sanitation",
            "type":"Services"
        }
    ],
    "sg:phone":"+44 1291 622211",
    "sg:postcode":"NP16 7DN",
    "sg:province":"Gloucestershire",
    "sg:tags":[
        "commercial"
    ],
    "wof:name":"National Cleaning Services",
    "wof:placetype":"venue"
},
  "geometry": {"coordinates":[-2.664433,51.638218],"type":"Point"}
}