{
  "type": "Feature",
  "properties": {
    "iso:country":"GB",
    "sg:address":"Mercury Works, Leysfield Road",
    "sg:city":"London",
    "sg:classifiers":[
        {
            "category":"Retail",
            "subcategory":"Auto Repair",
            "type":"Services"
        }
    ],
    "sg:postcode":"W12 9JF",
    "sg:province":"Greater London",
    "sg:tags":[
        "body",
        "car"
    ],
    "wof:name":"F & M Autos",
    "wof:placetype":"venue"
},
  "geometry": {"coordinates":[-0.23762,51.500851],"type":"Point"}
}