{
  "type": "Feature",
  "properties": {
    "addr:full":"Suite 2 Highgate Greater London N6 4AE",
    "addr:housenumber":"suite 2",
    "addr:postcode":"n6 4ae",
    "addr:street":"Highgate",
    "iso:country":"GB",
    "sg:address":"Suite 2",
    "sg:city":"Highgate",
    "sg:classifiers":[
        {
            "category":"Real Estate",
            "subcategory":"Real Estate Operator",
            "type":"Services"
        }
    ],
    "sg:phone":"+44 20 8340 8273",
    "sg:postcode":"N6 4AE",
    "sg:province":"Greater London",
    "sg:tags":[
        "letting",
        "agent"
    ],
    "wof:name":"Mendoza Residential",
    "wof:placetype":"venue"
},
  "geometry": {"coordinates":[-0.152404,51.572556],"type":"Point"}
}