{
  "type": "Feature",
  "properties": {
    "addr:full":"Unit 6-10, Fendrod Business Park Swansea Swansea SA6 8QP",
    "addr:housenumber":"6-10",
    "addr:postcode":"sa6 8qp",
    "addr:street":"Fendrod Business Park",
    "iso:country":"GB",
    "sg:address":"Unit 6-10, Fendrod Business Park",
    "sg:city":"Swansea",
    "sg:classifiers":[
        {
            "category":"Shopping",
            "subcategory":"Gifts & Souvenirs",
            "type":"Retail Goods"
        },
        {
            "category":"Sports & Exercise",
            "subcategory":"Golf",
            "type":"Entertainment"
        }
    ],
    "sg:phone":"+44 1792 411777",
    "sg:postcode":"SA6 8QP",
    "sg:province":"Swansea",
    "sg:tags":[
        "greeting",
        "card"
    ],
    "wof:name":"The Card Co",
    "wof:placetype":"venue"
},
  "geometry": {"coordinates":[-3.9115190506,51.6605148315],"type":"Point"}
}