{
  "type": "Feature",
  "properties": {
    "iso:country":"GB",
    "sg:address":"Glaneinon Yard, Glanduar",
    "sg:city":"Llanybydder",
    "sg:classifiers":[
        {
            "category":"Autos & Motor Vehicles",
            "subcategory":"Automobile Sales",
            "type":"Retail Goods"
        }
    ],
    "sg:phone":"+44 1570 480544",
    "sg:postcode":"SA40 9RA",
    "sg:province":"Carmarthenshire",
    "sg:tags":[
        "commercial"
    ],
    "wof:name":"Foundry Commercials Ltd.",
    "wof:placetype":"venue"
},
  "geometry": {"coordinates":[-4.158361,52.073936],"type":"Point"}
}