{
  "type": "Feature",
  "properties": {
    "iso:country":"GB",
    "sg:address":"1 Braidcraft Place",
    "sg:city":"Glasgow",
    "sg:classifiers":[
        {
            "category":"Banks & Credit Unions",
            "subcategory":"Bank",
            "type":"Services"
        }
    ],
    "sg:phone":"+44 141 882 1692",
    "sg:postcode":"G53 5EU",
    "sg:province":"East Renfrewshire",
    "wof:name":"Lloyds T S B Bank Plc",
    "wof:placetype":"venue"
},
  "geometry": {"coordinates":[-4.34428,55.824776],"type":"Point"}
}