{
  "type": "Feature",
  "properties": {
    "iso:country":"GB",
    "sg:address":"Fern Bank, Quarry Hill",
    "sg:city":"Sowerby Bridge",
    "sg:classifiers":[
        {
            "category":"Manufacturing",
            "subcategory":"Building Materials",
            "type":"Manufacturing & Wholesale Goods"
        }
    ],
    "sg:phone":"+44 1422 832013",
    "sg:postcode":"HX6 3BG",
    "sg:province":"West Yorkshire",
    "sg:tags":[
        "tarmac",
        "asphalt"
    ],
    "wof:name":"T & T Plant Ltd",
    "wof:placetype":"venue"
},
  "geometry": {"coordinates":[-1.913934,53.706539],"type":"Point"}
}