{
  "type": "Feature",
  "properties": {
    "addr:full":"Cardiff Road Pwllheli Gwynedd LL53 5BY",
    "addr:postcode":"ll53 5by",
    "addr:street":"Cardiff Road",
    "iso:country":"GB",
    "sg:address":"Cardiff Road",
    "sg:city":"Pwllheli",
    "sg:classifiers":[
        {
            "category":"Shopping",
            "subcategory":"Stationery & Office Supplies",
            "type":"Retail Goods"
        }
    ],
    "sg:phone":"+44 1758 614364",
    "sg:postcode":"LL53 5BY",
    "sg:province":"Gwynedd",
    "wof:name":"Copi Stationers",
    "wof:placetype":"venue"
},
  "geometry": {"coordinates":[-4.419724,52.887699],"type":"Point"}
}