{
  "type": "Feature",
  "properties": {
    "addr:full":"132 Parliament Road Middlesbrough North Yorkshire TS1 4JQ",
    "addr:housenumber":"132",
    "addr:postcode":"ts1 4jq",
    "addr:street":"Parliament Road",
    "iso:country":"GB",
    "sg:address":"132 Parliament Road",
    "sg:city":"Middlesbrough",
    "sg:classifiers":[
        {
            "category":"Home & Garden",
            "subcategory":"Household Appliances",
            "type":"Retail Goods"
        },
        {
            "category":"Retail",
            "subcategory":"Laundry & Dry Cleaning",
            "type":"Services"
        }
    ],
    "sg:phone":"+44 1642 210331",
    "sg:postcode":"TS1 4JQ",
    "sg:province":"North Yorkshire",
    "sg:tags":[
        "launderette",
        "electrical"
    ],
    "wof:name":"The Stanland Group Ltd.",
    "wof:placetype":"venue"
},
  "geometry": {"coordinates":[-1.2470550537,54.5687522888],"type":"Point"}
}