{
  "type": "Feature",
  "properties": {
    "iso:country":"GB",
    "sg:address":"4 Learmonth Grove",
    "sg:city":"Edinburgh",
    "sg:classifiers":[
        {
            "category":"Building & Trades",
            "subcategory":"Construction",
            "type":"Services"
        }
    ],
    "sg:phone":"+44 131 332 4740",
    "sg:postcode":"EH4 1BP",
    "sg:province":"City of Edinburgh",
    "sg:tags":[
        "roofing",
        "contracting"
    ],
    "wof:name":"Peter Long",
    "wof:placetype":"venue"
},
  "geometry": {"coordinates":[-3.219918,55.957245],"type":"Point"}
}