{
  "type": "Feature",
  "properties": {
    "addr:full":"89-91 Bayham Street London Greater London NW1 0AG",
    "addr:housenumber":"89-91",
    "addr:postcode":"nw1 0ag",
    "addr:street":"Bayham Street",
    "iso:country":"GB",
    "sg:address":"89-91 Bayham Street",
    "sg:city":"London",
    "sg:classifiers":[
        {
            "category":"Real Estate",
            "subcategory":"Architect",
            "type":"Services"
        }
    ],
    "sg:phone":"+44 20 7428 9393",
    "sg:postcode":"NW1 0AG",
    "sg:province":"Greater London",
    "wof:name":"Wright & Wright",
    "wof:placetype":"venue"
},
  "geometry": {"coordinates":[-0.1403550059,51.5377922058],"type":"Point"}
}