{
  "type": "Feature",
  "properties": {
    "addr:full":"St Machars Ho, Kilbarchan Rd Bridge Of Weir Inverclyde PA11 3ET",
    "addr:postcode":"pa11 3et",
    "addr:street":"Kilbarchan Rd",
    "iso:country":"GB",
    "sg:address":"St Machars Ho, Kilbarchan Rd",
    "sg:city":"Bridge Of Weir",
    "sg:classifiers":[
        {
            "category":"Health Services",
            "subcategory":"Doctor",
            "type":"Services"
        }
    ],
    "sg:phone":"+44 1505 612482",
    "sg:postcode":"PA11 3ET",
    "sg:province":"Inverclyde",
    "sg:tags":[
        "practitioners"
    ],
    "wof:name":"G O'Kane Dr",
    "wof:placetype":"venue"
},
  "geometry": {"coordinates":[-4.5697689056,55.8555450439],"type":"Point"}
}