{
  "type": "Feature",
  "properties": {
    "addr:full":"Unit 3c, Formal Industrial Estate, Treswithian Camborne Cornwall TR14 0PY",
    "addr:housenumber":"unit",
    "addr:postcode":"tr14 0py",
    "addr:street":"Formal Industrial",
    "iso:country":"GB",
    "sg:address":"Unit 3c, Formal Industrial Estate, Treswithian",
    "sg:city":"Camborne",
    "sg:classifiers":[
        {
            "category":"Utilities",
            "subcategory":"Telephone",
            "type":"Services"
        },
        {
            "category":"Communications",
            "type":"Services"
        }
    ],
    "sg:phone":"+44 1209 716360",
    "sg:postcode":"TR14 0PY",
    "sg:province":"Cornwall",
    "sg:tags":[
        "tv",
        "video",
        "radio",
        "telecommunication"
    ],
    "wof:name":"Teletronics Ltd.",
    "wof:placetype":"venue"
},
  "geometry": {"coordinates":[-5.31531,50.21759],"type":"Point"}
}