{
  "type": "Feature",
  "properties": {
    "addr:full":"2 Woodvale Road, Woodgate Birmingham West Midlands B32 4LA",
    "addr:housenumber":"2",
    "addr:postcode":"b32 4la",
    "addr:street":"Woodvale Road Woodgate",
    "iso:country":"GB",
    "sg:address":"2 Woodvale Road, Woodgate",
    "sg:city":"Birmingham",
    "sg:classifiers":[
        {
            "category":"Building & Trades",
            "subcategory":"Construction",
            "type":"Services"
        }
    ],
    "sg:postcode":"B32 4LA",
    "sg:province":"West Midlands",
    "sg:tags":[
        "roofing"
    ],
    "wof:name":"Weathertight Roofing Services",
    "wof:placetype":"venue"
},
  "geometry": {"coordinates":[-2.0098869801,52.4388542175],"type":"Point"}
}