{
  "type": "Feature",
  "properties": {
    "addr:full":"1 Station Road Oakham Leicestershire LE15 6QT",
    "addr:housenumber":"1",
    "addr:postcode":"le15 6qt",
    "addr:street":"Station Road",
    "iso:country":"GB",
    "sg:address":"1 Station Road",
    "sg:city":"Oakham",
    "sg:classifiers":[
        {
            "category":"Bars & Pubs",
            "type":"Food & Drink"
        },
        {
            "category":"Community Center",
            "subcategory":"Social",
            "type":"Public Place"
        }
    ],
    "sg:phone":"+44 1572 722225",
    "sg:postcode":"LE15 6QT",
    "sg:province":"Leicestershire",
    "sg:tags":[
        "pubs",
        "house",
        "inn",
        "activity"
    ],
    "wof:name":"The Odd House Tavern",
    "wof:placetype":"venue"
},
  "geometry": {"coordinates":[-0.726006,52.672604],"type":"Point"}
}