{
  "type": "Feature",
  "properties": {
    "addr:full":"Green Farm, Allensmore Hereford Herefordshire HR2 9AH",
    "addr:housenumber":"allensmore",
    "addr:postcode":"hr2 9ah",
    "iso:country":"GB",
    "sg:address":"Green Farm, Allensmore",
    "sg:city":"Hereford",
    "sg:classifiers":[
        {
            "category":"Farming",
            "subcategory":"Crops",
            "type":"Manufacturing & Wholesale Goods"
        },
        {
            "category":"Food & Beverages",
            "subcategory":"Groceries & Convenience Stores",
            "type":"Retail Goods"
        }
    ],
    "sg:phone":"+44 1432 277251",
    "sg:postcode":"HR2 9AH",
    "sg:province":"Herefordshire",
    "sg:tags":[
        "merchant",
        "arable",
        "potato"
    ],
    "wof:name":"G D Owens & Sons",
    "wof:placetype":"venue"
},
  "geometry": {"coordinates":[-2.778119,52.020119],"type":"Point"}
}