{
  "type": "Feature",
  "properties": {
    "addr:full":"29 Whitworth Rd Gosport Hampshire PO12 3NJ",
    "addr:housenumber":"29",
    "addr:postcode":"po12 3nj",
    "addr:street":"Whitworth Rd",
    "iso:country":"GB",
    "sg:address":"29 Whitworth Rd",
    "sg:city":"Gosport",
    "sg:classifiers":[
        {
            "category":"Home & Garden",
            "subcategory":"Household Appliances",
            "type":"Retail Goods"
        }
    ],
    "sg:phone":"+44 23 9252 2725",
    "sg:postcode":"PO12 3NJ",
    "sg:province":"Hampshire",
    "sg:tags":[
        "electrical"
    ],
    "wof:name":"Wilkins Refrigeration",
    "wof:placetype":"venue"
},
  "geometry": {"coordinates":[-1.143151,50.798233],"type":"Point"}
}