{
  "type": "Feature",
  "properties": {
    "iso:country":"GB",
    "sg:address":"New Moon Service Station, Farnham Road",
    "sg:city":"Farnham",
    "sg:classifiers":[
        {
            "category":"Autos & Motor Vehicles",
            "subcategory":"Automobile Sales",
            "type":"Retail Goods"
        }
    ],
    "sg:phone":"+44 1420 22080",
    "sg:postcode":"GU10 4LA",
    "sg:province":"Hampshire",
    "sg:tags":[
        "car"
    ],
    "wof:name":"Dalton & Blaber Car Sales",
    "wof:placetype":"venue"
},
  "geometry": {"coordinates":[-0.8352299929,51.1875305176],"type":"Point"}
}