{
  "type": "Feature",
  "properties": {
    "addr:full":"10 Castle Street Hastings East Sussex TN34 3DY",
    "addr:housenumber":"10",
    "addr:postcode":"tn34 3dy",
    "addr:street":"Castle Street",
    "iso:country":"GB",
    "sg:address":"10 Castle Street",
    "sg:city":"Hastings",
    "sg:classifiers":[
        {
            "category":"Shopping",
            "subcategory":"Bicycles & Sporting Goods",
            "type":"Retail Goods"
        }
    ],
    "sg:postcode":"TN34 3DY",
    "sg:province":"East Sussex",
    "sg:tags":[
        "dance",
        "balletwear"
    ],
    "wof:name":"Jason Pierce",
    "wof:placetype":"venue"
},
  "geometry": {"coordinates":[0.5826129913,50.8552856445],"type":"Point"}
}