{
  "type": "Feature",
  "properties": {
    "iso:country":"GB",
    "sg:address":"68a Humberston Avenue, Humberston",
    "sg:city":"Grimsby",
    "sg:classifiers":[
        {
            "category":"Social Services",
            "subcategory":"Retirement Home",
            "type":"Services"
        }
    ],
    "sg:phone":"+44 1472 816183",
    "sg:postcode":"DN36 4SU",
    "sg:province":"Lincolnshire",
    "sg:tags":[
        "residential",
        "care"
    ],
    "wof:name":"Clover Lodge Rest Home",
    "wof:placetype":"venue"
},
  "geometry": {"coordinates":[-0.0447160006,53.5257301331],"type":"Point"}
}