{
  "type": "Feature",
  "properties": {
    "addr:full":"Unit 2 Tramway Business Park, Ludgershall Road, Brill Aylesbury Buckinghamshire HP18 9TY",
    "addr:housenumber":"unit 2",
    "addr:postcode":"hp18 9ty",
    "addr:street":"Tramway Business Park Ludgershall Road",
    "iso:country":"GB",
    "sg:address":"Unit 2 Tramway Business Park, Ludgershall Road, Brill",
    "sg:city":"Aylesbury",
    "sg:classifiers":[
        {
            "category":"Food & Beverages",
            "subcategory":"Specialty",
            "type":"Retail Goods"
        }
    ],
    "sg:phone":"+44 1844 238808",
    "sg:postcode":"HP18 9TY",
    "sg:province":"Buckinghamshire",
    "sg:tags":[
        "dietetic",
        "homogenised"
    ],
    "wof:name":"A C Lacey",
    "wof:placetype":"venue"
},
  "geometry": {"coordinates":[-1.0517090559,51.8203697205],"type":"Point"}
}