{
  "type": "Feature",
  "properties": {
    "iso:country":"GB",
    "sg:address":"The Old Raglan To Abergavenny Road, Llanvihangel Gobion",
    "sg:city":"Abergavenny",
    "sg:classifiers":[
        {
            "category":"Travel",
            "subcategory":"Hotels & Motels",
            "type":"Entertainment"
        }
    ],
    "sg:phone":"+44 1873 840678",
    "sg:postcode":"NP7 9BA",
    "sg:province":"Herefordshire",
    "sg:website":"http://www.llch.co.uk",
    "wof:name":"Llansantffraed Court Hotel",
    "wof:placetype":"venue"
},
  "geometry": {"coordinates":[-2.947059,51.777744],"type":"Point"}
}