{
  "type": "Feature",
  "properties": {
    "iso:country":"GB",
    "sg:address":"1 Meadow Road",
    "sg:city":"Loughton",
    "sg:classifiers":[
        {
            "category":"Health Services",
            "subcategory":"Health Practitioner",
            "type":"Services"
        }
    ],
    "sg:phone":"+44 20 8508 3925",
    "sg:postcode":"IG10 4HY",
    "sg:province":"Essex",
    "sg:tags":[
        "psychotherapist"
    ],
    "wof:name":"Michael Moore",
    "wof:placetype":"venue"
},
  "geometry": {"coordinates":[0.050901,51.643185],"type":"Point"}
}