{
  "type": "Feature",
  "properties": {
    "addr:full":"15 Brenkley Way, Blezard Business Park, Wideopen Newcastle-upon-tyne Northumberland NE13 6DS",
    "addr:housenumber":"15",
    "addr:postcode":"ne13 6ds",
    "addr:street":"Brenkley Way Blezard Business Park",
    "iso:country":"GB",
    "sg:address":"15 Brenkley Way, Blezard Business Park, Wideopen",
    "sg:city":"Newcastle-upon-tyne",
    "sg:classifiers":[
        {
            "category":"Banks & Credit Unions",
            "subcategory":"Financial Services",
            "type":"Services"
        }
    ],
    "sg:postcode":"NE13 6DS",
    "sg:province":"Northumberland",
    "sg:tags":[
        "adviser",
        "consultant"
    ],
    "wof:name":"Financial Independents Ltd",
    "wof:placetype":"venue"
},
  "geometry": {"coordinates":[-1.630739,55.060715],"type":"Point"}
}