{
  "type": "Feature",
  "properties": {
    "addr:full":"50-54 The Centre Feltham Greater London TW13 4AU",
    "addr:housenumber":"50-54",
    "addr:postcode":"tw13 4au",
    "addr:street":"The Centre",
    "iso:country":"GB",
    "sg:address":"50-54 The Centre",
    "sg:city":"Feltham",
    "sg:classifiers":[
        {
            "category":"Shopping",
            "subcategory":"Clothing, Apparel, & Fashions",
            "type":"Retail Goods"
        }
    ],
    "sg:phone":"+44 20 8751 3847",
    "sg:postcode":"TW13 4AU",
    "sg:province":"Greater London",
    "sg:tags":[
        "shop"
    ],
    "wof:name":"Peacocks Stores",
    "wof:placetype":"venue"
},
  "geometry": {"coordinates":[-0.411626,51.444958],"type":"Point"}
}