{
  "type": "Feature",
  "properties": {
    "iso:country":"GB",
    "sg:address":"1185 Bristol Road South",
    "sg:city":"Birmingham",
    "sg:classifiers":[
        {
            "category":"Home & Garden",
            "subcategory":"Home Furnishings",
            "type":"Retail Goods"
        }
    ],
    "sg:phone":"+44 121 475 3183",
    "sg:postcode":"B31 2SL",
    "sg:province":"West Midlands",
    "sg:tags":[
        "mantelpiece",
        "fireplace"
    ],
    "wof:name":"G & V Decorative Plasterwork",
    "wof:placetype":"venue"
},
  "geometry": {"coordinates":[-1.979613,52.404598],"type":"Point"}
}