{
  "type": "Feature",
  "properties": {
    "iso:country":"GB",
    "sg:address":"Ellesmere Road, Forest Town",
    "sg:city":"Mansfield",
    "sg:classifiers":[
        {
            "category":"Farming",
            "subcategory":"Nursery",
            "type":"Manufacturing & Wholesale Goods"
        }
    ],
    "sg:postcode":"NG19 0EQ",
    "sg:province":"Derbyshire",
    "sg:tags":[
        "creche"
    ],
    "wof:name":"Ellesmere House",
    "wof:placetype":"venue"
},
  "geometry": {"coordinates":[-1.166749,53.152504],"type":"Point"}
}