{
  "type": "Feature",
  "properties": {
    "iso:country":"GB",
    "sg:address":"4 Waverley Lane",
    "sg:city":"Aberdeen",
    "sg:classifiers":[
        {
            "category":"Real Estate",
            "subcategory":"Surveying",
            "type":"Services"
        }
    ],
    "sg:phone":"+44 1224 648004",
    "sg:postcode":"AB10 1XG",
    "sg:province":"Aberdeen City",
    "sg:tags":[
        "surveyor",
        "quantity"
    ],
    "wof:name":"Morgan Munro Ltd.",
    "wof:placetype":"venue"
},
  "geometry": {"coordinates":[-2.115281105,57.1446876526],"type":"Point"}
}