{
  "type": "Feature",
  "properties": {
    "iso:country":"GB",
    "sg:address":"Burnley Road, Brierfield",
    "sg:city":"Nelson",
    "sg:classifiers":[
        {
            "category":"Bars & Pubs",
            "type":"Food & Drink"
        }
    ],
    "sg:phone":"+44 1282 615720",
    "sg:postcode":"BB9 5HY",
    "sg:province":"Lancashire",
    "sg:tags":[
        "pubs",
        "inn"
    ],
    "wof:name":"The Wigglesworth Arms Hotel",
    "wof:placetype":"venue"
},
  "geometry": {"coordinates":[-2.234284,53.823605],"type":"Point"}
}