{
  "type": "Feature",
  "properties": {
    "iso:country":"GB",
    "sg:address":"46 Bond Street",
    "sg:city":"Bristol",
    "sg:classifiers":[
        {
            "category":"Sports & Exercise",
            "subcategory":"Sports Center",
            "type":"Entertainment"
        }
    ],
    "sg:phone":"+44 117 929 4666",
    "sg:postcode":"BS1 3LZ",
    "sg:province":"City of Bristol",
    "sg:tags":[
        "shop",
        "good"
    ],
    "wof:name":"Greedy Guts",
    "wof:placetype":"venue"
},
  "geometry": {"coordinates":[-2.5875489712,51.4592132568],"type":"Point"}
}