{
  "type": "Feature",
  "properties": {
    "addr:full":"Church Bank, Tattenhall Chester Cheshire CH3 9QE",
    "addr:postcode":"ch3 9qe",
    "iso:country":"GB",
    "sg:address":"Church Bank, Tattenhall",
    "sg:city":"Chester",
    "sg:classifiers":[
        {
            "category":"Shopping",
            "subcategory":"Florist",
            "type":"Retail Goods"
        }
    ],
    "sg:postcode":"CH3 9QE",
    "sg:province":"Cheshire",
    "wof:name":"Village Greens",
    "wof:placetype":"venue"
},
  "geometry": {"coordinates":[-2.7728788853,53.1191558838],"type":"Point"}
}