{
  "type": "Feature",
  "properties": {
    "addr:full":"542 Portswood Road Southampton Hampshire SO17 3SP",
    "addr:housenumber":"542",
    "addr:postcode":"so17 3sp",
    "addr:street":"Portswood Road",
    "iso:country":"GB",
    "sg:address":"542 Portswood Road",
    "sg:city":"Southampton",
    "sg:classifiers":[
        {
            "category":"Retail",
            "subcategory":"Auto Rental",
            "type":"Services"
        }
    ],
    "sg:postcode":"SO17 3SP",
    "sg:province":"Hampshire",
    "sg:tags":[
        "car"
    ],
    "wof:name":"Global Self Drive",
    "wof:placetype":"venue"
},
  "geometry": {"coordinates":[-1.385422945,50.9307441711],"type":"Point"}
}