{
  "type": "Feature",
  "properties": {
    "addr:full":"18 St Marys Street Shrewsbury Shropshire SY1 1ED",
    "addr:housenumber":"18",
    "addr:postcode":"sy1 1ed",
    "addr:street":"St Marys Street",
    "iso:country":"GB",
    "sg:address":"18 St Marys Street",
    "sg:city":"Shrewsbury",
    "sg:classifiers":[
        {
            "category":"Shopping",
            "subcategory":"Comic Books",
            "type":"Retail Goods"
        }
    ],
    "sg:postcode":"SY1 1ED",
    "sg:province":"Shropshire",
    "sg:tags":[
        "jeweller"
    ],
    "wof:name":"The Little Gem",
    "wof:placetype":"venue"
},
  "geometry": {"coordinates":[-2.751982,52.708225],"type":"Point"}
}