{
  "type": "Feature",
  "properties": {
    "iso:country":"GB",
    "sg:address":"6 Ridge Grove",
    "sg:city":"Stourbridge",
    "sg:classifiers":[
        {
            "category":"Professional",
            "subcategory":"Computer Services",
            "type":"Services"
        }
    ],
    "sg:phone":"+44 1384 896199",
    "sg:postcode":"DY9 7PX",
    "sg:province":"West Midlands",
    "sg:tags":[
        "system",
        "software"
    ],
    "wof:name":"Harp Shareware",
    "wof:placetype":"venue"
},
  "geometry": {"coordinates":[-2.1321980953,52.455745697],"type":"Point"}
}