{
  "type": "Feature",
  "properties": {
    "addr:full":"Peterley Road, Horspath Industrial Estate Oxford Oxfordshire OX4 2TZ",
    "addr:postcode":"ox4 2tz",
    "addr:street":"Peterley Road;Industrial Estate",
    "iso:country":"GB",
    "sg:address":"Peterley Road, Horspath Industrial Estate",
    "sg:city":"Oxford",
    "sg:classifiers":[
        {
            "category":"Autos & Motor Vehicles",
            "subcategory":"Automobile Sales",
            "type":"Retail Goods"
        }
    ],
    "sg:postcode":"OX4 2TZ",
    "sg:province":"Oxfordshire",
    "sg:tags":[
        "car",
        "truck"
    ],
    "wof:name":"Palmer & Phillips",
    "wof:placetype":"venue"
},
  "geometry": {"coordinates":[-1.195782,51.738831],"type":"Point"}
}