{
  "type": "Feature",
  "properties": {
    "addr:full":"17 Hickling Close Leigh-on-sea Essex SS9 4SX",
    "addr:housenumber":"17",
    "addr:postcode":"ss9 4sx",
    "addr:street":"Hickling Close",
    "iso:country":"GB",
    "sg:address":"17 Hickling Close",
    "sg:city":"Leigh-on-sea",
    "sg:classifiers":[
        {
            "category":"Government",
            "subcategory":"Post Office",
            "type":"Public Place"
        }
    ],
    "sg:postcode":"SS9 4SX",
    "sg:province":"Essex",
    "sg:tags":[
        "messenger",
        "courier"
    ],
    "wof:name":"Webb Contract Deliveries",
    "wof:placetype":"venue"
},
  "geometry": {"coordinates":[0.635091,51.56678],"type":"Point"}
}