{
  "type": "Feature",
  "properties": {
    "iso:country":"GB",
    "sg:address":"75 Stratford Road",
    "sg:city":"Milford Haven",
    "sg:classifiers":[
        {
            "category":"Ice Cream",
            "type":"Food & Drink"
        }
    ],
    "sg:phone":"+44 1646 692722",
    "sg:postcode":"SA73 2JD",
    "sg:province":"Pembrokeshire",
    "sg:tags":[
        "mnfr"
    ],
    "wof:name":"Rabaiotti's Ice Cream Factory",
    "wof:placetype":"venue"
},
  "geometry": {"coordinates":[-5.031255,51.713886],"type":"Point"}
}