{
  "type": "Feature",
  "properties": {
    "iso:country":"GB",
    "sg:address":"18 King Harold Road",
    "sg:city":"Colchester",
    "sg:classifiers":[
        {
            "category":"Building & Trades",
            "subcategory":"Construction",
            "type":"Services"
        }
    ],
    "sg:phone":"+44 1206 44981",
    "sg:postcode":"CO3 4SB",
    "sg:province":"Essex",
    "sg:tags":[
        "builder"
    ],
    "wof:name":"Richard J Sexton",
    "wof:placetype":"venue"
},
  "geometry": {"coordinates":[0.8654789925,51.8757362366],"type":"Point"}
}