{
  "type": "Feature",
  "properties": {
    "addr:full":"4 1high Street Broadstairs Kent CT10 1GR",
    "addr:postcode":"ct10 1gr",
    "addr:street":"1High Street",
    "iso:country":"GB",
    "sg:address":"4 1high Street",
    "sg:city":"Broadstairs",
    "sg:classifiers":[
        {
            "category":"Shopping",
            "subcategory":"Stationery & Office Supplies",
            "type":"Retail Goods"
        }
    ],
    "sg:postcode":"CT10 1GR",
    "sg:province":"Kent",
    "wof:name":"Kat Stationers",
    "wof:placetype":"venue"
},
  "geometry": {"coordinates":[1.44106,51.358604],"type":"Point"}
}