{
  "type": "Feature",
  "properties": {
    "iso:country":"GB",
    "sg:address":"87 Ringwood Road, Totton",
    "sg:city":"Southampton",
    "sg:classifiers":[
        {
            "category":"Manufacturing",
            "subcategory":"Rubber & Plastics",
            "type":"Manufacturing & Wholesale Goods"
        }
    ],
    "sg:postcode":"SO40 8DX",
    "sg:province":"Hampshire",
    "sg:tags":[
        "product",
        "foam"
    ],
    "wof:name":"The Upholstery Shop",
    "wof:placetype":"venue"
},
  "geometry": {"coordinates":[-1.492936,50.917282],"type":"Point"}
}