{
  "type": "Feature",
  "properties": {
    "addr:full":"Lower Greenhills Farm, Ipstones Edge, Ipstones Stoke-on-trent Staffordshire ST10 2LP",
    "addr:housenumber":"ipstones",
    "addr:postcode":"st10 2lp",
    "addr:street":"Lower Greenhills",
    "iso:country":"GB",
    "sg:address":"Lower Greenhills Farm, Ipstones Edge, Ipstones",
    "sg:city":"Stoke-on-trent",
    "sg:classifiers":[
        {
            "category":"Building & Trades",
            "subcategory":"Construction",
            "type":"Services"
        }
    ],
    "sg:phone":"+44 1538 266908",
    "sg:postcode":"ST10 2LP",
    "sg:province":"Staffordshire",
    "sg:tags":[
        "builder"
    ],
    "wof:name":"P Hurst",
    "wof:placetype":"venue"
},
  "geometry": {"coordinates":[-1.969696,53.046928],"type":"Point"}
}