{
  "type": "Feature",
  "properties": {
    "iso:country":"GB",
    "sg:address":"265 Melton Road",
    "sg:city":"Leicester",
    "sg:classifiers":[
        {
            "category":"Shopping",
            "subcategory":"Clothing, Apparel, & Fashions",
            "type":"Retail Goods"
        }
    ],
    "sg:postcode":"LE4 6QN",
    "sg:province":"Leicestershire",
    "sg:tags":[
        "clothing",
        "fabric"
    ],
    "wof:name":"Exek Clothing",
    "wof:placetype":"venue"
},
  "geometry": {"coordinates":[-1.116509,52.657478],"type":"Point"}
}