{
  "type": "Feature",
  "properties": {
    "iso:country":"GB",
    "sg:address":"Tudor House, 13-15 Chester Street",
    "sg:city":"Mold",
    "sg:classifiers":[
        {
            "category":"Real Estate",
            "subcategory":"Real Estate Agent",
            "type":"Services"
        }
    ],
    "sg:phone":"+44 1352 758088",
    "sg:postcode":"CH7 1EG",
    "sg:province":"Denbighshire",
    "wof:name":"Molyneux",
    "wof:placetype":"venue"
},
  "geometry": {"coordinates":[-3.138173,53.168125],"type":"Point"}
}