{
  "type": "Feature",
  "properties": {
    "addr:full":"Unit 40 Hobbs Industrial Estate Lingfield Surrey RH7 6HN",
    "addr:housenumber":"unit 40;estate",
    "addr:postcode":"rh7 6hn",
    "addr:street":"Hobbs Industrial",
    "iso:country":"GB",
    "sg:address":"Unit 40 Hobbs Industrial Estate",
    "sg:city":"Lingfield",
    "sg:classifiers":[
        {
            "category":"Retail",
            "subcategory":"Auto Repair",
            "type":"Services"
        }
    ],
    "sg:phone":"+44 1293 822883",
    "sg:postcode":"RH7 6HN",
    "sg:province":"Surrey",
    "sg:tags":[
        "modification",
        "garage"
    ],
    "wof:name":"J W Smith Auto Service",
    "wof:placetype":"venue"
},
  "geometry": {"coordinates":[-0.051229,51.15514],"type":"Point"}
}