{
  "type": "Feature",
  "properties": {
    "addr:full":"65 Hailey Place Cranleigh Surrey GU6 7EQ",
    "addr:housenumber":"65",
    "addr:postcode":"gu6 7eq",
    "addr:street":"Hailey Place",
    "iso:country":"GB",
    "sg:address":"65 Hailey Place",
    "sg:city":"Cranleigh",
    "sg:classifiers":[
        {
            "category":"Health Services",
            "subcategory":"Podiatrist",
            "type":"Services"
        }
    ],
    "sg:postcode":"GU6 7EQ",
    "sg:province":"Surrey",
    "sg:tags":[
        "podiatrists",
        "chiropodist"
    ],
    "wof:name":"Gavin N M Morrison",
    "wof:placetype":"venue"
},
  "geometry": {"coordinates":[-0.47264,51.14576],"type":"Point"}
}