{
  "type": "Feature",
  "properties": {
    "iso:country":"GB",
    "sg:address":"64 Little Ealing La",
    "sg:city":"Ealing",
    "sg:classifiers":[
        {
            "category":"Organizations",
            "subcategory":"Religious Organization",
            "type":"Services"
        }
    ],
    "sg:phone":"+44 20 8567 5245",
    "sg:postcode":"W5 4XF",
    "sg:province":"Greater London",
    "sg:tags":[
        "organisation"
    ],
    "wof:name":"Lourdesmount Centre",
    "wof:placetype":"venue"
},
  "geometry": {"coordinates":[-0.309051007,51.4979286194],"type":"Point"}
}