{
  "type": "Feature",
  "properties": {
    "iso:country":"GB",
    "sg:address":"Pims House, Mildmay Avenue, Islington",
    "sg:city":"London",
    "sg:classifiers":[
        {
            "category":"Organizations",
            "subcategory":"Community Association",
            "type":"Services"
        }
    ],
    "sg:phone":"+44 20 7226 1000",
    "sg:postcode":"N1 4RS",
    "sg:province":"Greater London",
    "sg:tags":[
        "relation",
        "public"
    ],
    "wof:name":"P I M S U K Ltd.",
    "wof:placetype":"venue"
},
  "geometry": {"coordinates":[-0.08607,51.548061],"type":"Point"}
}