{
  "type": "Feature",
  "properties": {
    "addr:full":"350 Scotland Street Glasgow Glasgow City G5 8QF",
    "addr:housenumber":"350",
    "addr:postcode":"g5 8qf",
    "addr:street":"Scotland Street",
    "iso:country":"GB",
    "sg:address":"350 Scotland Street",
    "sg:city":"Glasgow",
    "sg:classifiers":[
        {
            "category":"Farming",
            "subcategory":"Fish & Marine Products",
            "type":"Manufacturing & Wholesale Goods"
        },
        {
            "category":"Food & Beverages",
            "subcategory":"Meat & Fish",
            "type":"Retail Goods"
        }
    ],
    "sg:phone":"+44 141 429 1609",
    "sg:postcode":"G5 8QF",
    "sg:province":"Glasgow City",
    "sg:tags":[
        "fishmonger",
        "butcher"
    ],
    "wof:name":"James McKechnie & Son",
    "wof:placetype":"venue"
},
  "geometry": {"coordinates":[-4.27326,55.850029],"type":"Point"}
}