{
  "type": "Feature",
  "properties": {
    "addr:full":"High St Kingswinford Staffordshire DY6 8AW",
    "addr:postcode":"dy6 8aw",
    "addr:street":"High St",
    "iso:country":"GB",
    "sg:address":"High St",
    "sg:city":"Kingswinford",
    "sg:classifiers":[
        {
            "category":"Utilities",
            "subcategory":"Electric",
            "type":"Services"
        }
    ],
    "sg:phone":"+44 845 735 3637",
    "sg:postcode":"DY6 8AW",
    "sg:province":"Staffordshire",
    "sg:tags":[
        "electricity"
    ],
    "wof:name":"MEB Midlands Electricity",
    "wof:placetype":"venue"
},
  "geometry": {"coordinates":[-2.1593840122,52.5002975464],"type":"Point"}
}