{
  "type": "Feature",
  "properties": {
    "addr:full":"Unit 3a, Buckley Road Industrial Estate Rochdale Lancashire OL12 9EF",
    "addr:housenumber":"unit 3a;estate",
    "addr:postcode":"ol12 9ef",
    "addr:street":"Buckley Road Industrial",
    "iso:country":"GB",
    "sg:address":"Unit 3a, Buckley Road Industrial Estate",
    "sg:city":"Rochdale",
    "sg:classifiers":[
        {
            "category":"Manufacturing",
            "subcategory":"Tools & Machinery",
            "type":"Manufacturing & Wholesale Goods"
        }
    ],
    "sg:phone":"+44 1706 710359",
    "sg:postcode":"OL12 9EF",
    "sg:province":"Lancashire",
    "wof:name":"Hirschmann U K Ltd.",
    "wof:placetype":"venue"
},
  "geometry": {"coordinates":[-2.145464,53.6287],"type":"Point"}
}