{
  "type": "Feature",
  "properties": {
    "addr:full":"The Basket Loft Tolcarne Place, Newlyn Penzance Cornwall TR18 5PR",
    "addr:postcode":"tr18 5pr",
    "addr:street":"Place",
    "iso:country":"GB",
    "sg:address":"The Basket Loft Tolcarne Place, Newlyn",
    "sg:city":"Penzance",
    "sg:classifiers":[
        {
            "category":"Building & Trades",
            "subcategory":"Construction",
            "type":"Services"
        }
    ],
    "sg:phone":"+44 1736 369479",
    "sg:postcode":"TR18 5PR",
    "sg:province":"Cornwall",
    "sg:tags":[
        "builder"
    ],
    "wof:name":"B.S Podd",
    "wof:placetype":"venue"
},
  "geometry": {"coordinates":[-5.552408,50.101761],"type":"Point"}
}