{
  "type": "Feature",
  "properties": {
    "addr:full":"Warwick Road, Knowle Solihull Warwickshire B93 9LW",
    "addr:postcode":"b93 9lw",
    "addr:street":"Warwick Road",
    "iso:country":"GB",
    "sg:address":"Warwick Road, Knowle",
    "sg:city":"Solihull",
    "sg:classifiers":[
        {
            "category":"Bars & Pubs",
            "type":"Food & Drink"
        }
    ],
    "sg:phone":"+44 1564 772655",
    "sg:postcode":"B93 9LW",
    "sg:province":"Warwickshire",
    "sg:tags":[
        "pubs",
        "inn"
    ],
    "wof:name":"Black Boy",
    "wof:placetype":"venue"
},
  "geometry": {"coordinates":[-1.750101,52.402195],"type":"Point"}
}