{
  "type": "Feature",
  "properties": {
    "addr:full":"Wet La Exeter Devon EX6 7NQ",
    "addr:postcode":"ex6 7nq",
    "addr:street":"Wet La Exeter",
    "iso:country":"GB",
    "sg:address":"Wet La",
    "sg:city":"Exeter",
    "sg:classifiers":[
        {
            "category":"Food & Beverages",
            "subcategory":"Meat & Fish",
            "type":"Retail Goods"
        }
    ],
    "sg:phone":"+44 1647 252243",
    "sg:postcode":"EX6 7NQ",
    "sg:province":"Devon",
    "sg:tags":[
        "butcher"
    ],
    "wof:name":"Maid Marion Store",
    "wof:placetype":"venue"
},
  "geometry": {"coordinates":[-3.6530559063,50.6540870667],"type":"Point"}
}