{
  "type": "Feature",
  "properties": {
    "addr:full":"Unit 17 Bethel Square Brecon Powys LD3 7JP",
    "addr:housenumber":"unit 17",
    "addr:postcode":"ld3 7jp",
    "addr:street":"Square",
    "iso:country":"GB",
    "sg:address":"Unit 17 Bethel Square",
    "sg:city":"Brecon",
    "sg:classifiers":[
        {
            "category":"Shopping",
            "subcategory":"Gifts & Souvenirs",
            "type":"Retail Goods"
        }
    ],
    "sg:phone":"+44 1874 622202",
    "sg:postcode":"LD3 7JP",
    "sg:province":"Powys",
    "sg:tags":[
        "shop",
        "poster",
        "card"
    ],
    "wof:name":"Lancedown Ltd.",
    "wof:placetype":"venue"
},
  "geometry": {"coordinates":[-3.3911418915,51.9497413635],"type":"Point"}
}