{
  "type": "Feature",
  "properties": {
    "iso:country":"GB",
    "sg:address":"Bakeham Lane",
    "sg:city":"Egham",
    "sg:classifiers":[
        {
            "category":"Professional",
            "subcategory":"Computer Services",
            "type":"Services"
        }
    ],
    "sg:postcode":"TW20 9TY",
    "sg:province":"Surrey",
    "sg:tags":[
        "information"
    ],
    "wof:name":"International Mycological Institute",
    "wof:placetype":"venue"
},
  "geometry": {"coordinates":[-0.569143,51.423008],"type":"Point"}
}