{
  "type": "Feature",
  "properties": {
    "iso:country":"GB",
    "sg:address":"Llysnewydd, Llandre",
    "sg:city":"Bow Street",
    "sg:classifiers":[
        {
            "category":"Building & Trades",
            "subcategory":"Landscaping Services",
            "type":"Services"
        }
    ],
    "sg:phone":"+44 1970 828318",
    "sg:postcode":"SY24 5BS",
    "sg:province":"Ceredigion",
    "sg:tags":[
        "horticultural",
        "consultant"
    ],
    "wof:name":"A Owen",
    "wof:placetype":"venue"
},
  "geometry": {"coordinates":[-4.027775,52.442253],"type":"Point"}
}