{
  "type": "Feature",
  "properties": {
    "addr:full":"75 Bournbrook Road Birmingham West Midlands B29 7BX",
    "addr:housenumber":"75",
    "addr:postcode":"b29 7bx",
    "addr:street":"Bournbrook Road",
    "iso:country":"GB",
    "sg:address":"75 Bournbrook Road",
    "sg:city":"Birmingham",
    "sg:classifiers":[
        {
            "category":"Building & Trades",
            "subcategory":"Plumbing",
            "type":"Services"
        }
    ],
    "sg:postcode":"B29 7BX",
    "sg:province":"West Midlands",
    "sg:tags":[
        "heating"
    ],
    "wof:name":"1 A",
    "wof:placetype":"venue"
},
  "geometry": {"coordinates":[-1.926954031,52.4437980652],"type":"Point"}
}