{
  "type": "Feature",
  "properties": {
    "addr:full":"Stanley Ind Est, Station Rd, West Hallam Ilkeston Derbyshire DE7 6HB",
    "addr:postcode":"de7 6hb",
    "addr:street":"Station Rd",
    "iso:country":"GB",
    "sg:address":"Stanley Ind Est, Station Rd, West Hallam",
    "sg:city":"Ilkeston",
    "sg:classifiers":[
        {
            "category":"Autos & Motor Vehicles",
            "subcategory":"Automobile Sales",
            "type":"Retail Goods"
        }
    ],
    "sg:phone":"+44 115 932 0272",
    "sg:postcode":"DE7 6HB",
    "sg:province":"Derbyshire",
    "sg:tags":[
        "commercial"
    ],
    "wof:name":"Stanley Motors",
    "wof:placetype":"venue"
},
  "geometry": {"coordinates":[-1.3589890003,52.9667549133],"type":"Point"}
}