{
  "type": "Feature",
  "properties": {
    "addr:full":"Uppincott Farm, Shobrooke Crediton Devon EX17 1BE",
    "addr:postcode":"ex17 1be",
    "iso:country":"GB",
    "sg:address":"Uppincott Farm, Shobrooke",
    "sg:city":"Crediton",
    "sg:classifiers":[
        {
            "category":"Farming",
            "subcategory":"Farm",
            "type":"Manufacturing & Wholesale Goods"
        }
    ],
    "sg:postcode":"EX17 1BE",
    "sg:province":"Devon",
    "sg:tags":[
        "mixed",
        "crop"
    ],
    "wof:name":"A V & N Lee",
    "wof:placetype":"venue"
},
  "geometry": {"coordinates":[-3.617874,50.798553],"type":"Point"}
}