{
  "type": "Feature",
  "properties": {
    "addr:full":"Elliott House Birmingham West Midlands B29 6LS",
    "addr:postcode":"b29 6ls",
    "iso:country":"GB",
    "sg:address":"Elliott House",
    "sg:city":"Birmingham",
    "sg:classifiers":[
        {
            "category":"Professional",
            "subcategory":"Employment Agencies",
            "type":"Services"
        }
    ],
    "sg:postcode":"B29 6LS",
    "sg:province":"West Midlands",
    "sg:tags":[
        "consultant"
    ],
    "wof:name":"T A Distributors",
    "wof:placetype":"venue"
},
  "geometry": {"coordinates":[-1.9379650354,52.4405593872],"type":"Point"}
}