{
  "type": "Feature",
  "properties": {
    "addr:full":"Stay Farm Thirsk North Yorkshire YO7 2JT",
    "addr:housenumber":"thirsk",
    "addr:postcode":"yo7 2jt",
    "iso:country":"GB",
    "sg:address":"Stay Farm",
    "sg:city":"Thirsk",
    "sg:classifiers":[
        {
            "category":"Wholesale",
            "subcategory":"Construction Materials",
            "type":"Manufacturing & Wholesale Goods"
        }
    ],
    "sg:phone":"+44 1845 537242",
    "sg:postcode":"YO7 2JT",
    "sg:province":"North Yorkshire",
    "sg:tags":[
        "sawdust",
        "sawmills",
        "shaving"
    ],
    "wof:name":"Kepwick Estate Office",
    "wof:placetype":"venue"
},
  "geometry": {"coordinates":[-1.275072,54.246204],"type":"Point"}
}