{
  "type": "Feature",
  "properties": {
    "addr:full":"243a High Street Peterborough Cambridgeshire PE2 9EH",
    "addr:housenumber":"243a",
    "addr:postcode":"pe2 9eh",
    "addr:street":"High Street",
    "iso:country":"GB",
    "sg:address":"243a High Street",
    "sg:city":"Peterborough",
    "sg:classifiers":[
        {
            "category":"Organizations",
            "subcategory":"Community Association",
            "type":"Services"
        },
        {
            "category":"Organizations",
            "subcategory":"Membership Organization",
            "type":"Services"
        }
    ],
    "sg:phone":"+44 1733 344415",
    "sg:postcode":"PE2 9EH",
    "sg:province":"Cambridgeshire",
    "sg:tags":[
        "club",
        "social"
    ],
    "wof:name":"FLETTON WOODSTON & STANGROUND EX-SERVICE & WORKING MENS CLUB LTD",
    "wof:placetype":"venue"
},
  "geometry": {"coordinates":[-0.2486439943,52.5578155518],"type":"Point"}
}