{
  "type": "Feature",
  "properties": {
    "addr:full":"140 Nicolson Street Edinburgh City of Edinburgh EH8 9EH",
    "addr:housenumber":"140",
    "addr:postcode":"eh8 9eh",
    "addr:street":"Nicolson Street",
    "iso:country":"GB",
    "sg:address":"140 Nicolson Street",
    "sg:city":"Edinburgh",
    "sg:classifiers":[
        {
            "category":"Restaurant",
            "type":"Food & Drink"
        }
    ],
    "sg:phone":"+44 131 662 4185",
    "sg:postcode":"EH8 9EH",
    "sg:province":"City of Edinburgh",
    "wof:name":"de Niro's",
    "wof:placetype":"venue"
},
  "geometry": {"coordinates":[-3.1834139824,55.9442024231],"type":"Point"}
}