{
  "type": "Feature",
  "properties": {
    "addr:full":"31-33 High Street, Burton Latimer Kettering Northamptonshire NN15 5LB",
    "addr:housenumber":"31-33",
    "addr:postcode":"nn15 5lb",
    "addr:street":"High Street",
    "iso:country":"GB",
    "sg:address":"31-33 High Street, Burton Latimer",
    "sg:city":"Kettering",
    "sg:classifiers":[
        {
            "category":"Restaurant",
            "type":"Food & Drink"
        }
    ],
    "sg:phone":"+44 1536 722900",
    "sg:postcode":"NN15 5LB",
    "sg:province":"Northamptonshire",
    "wof:name":"Kushboo",
    "wof:placetype":"venue"
},
  "geometry": {"coordinates":[-0.6781079769,52.364730835],"type":"Point"}
}