{
  "type": "Feature",
  "properties": {
    "addr:full":"160 Station App, Epsom Rd Croydon Surrey CR0 4NA",
    "addr:housenumber":"160;app",
    "addr:postcode":"cr0 4na",
    "addr:street":"Station;Epsom Rd",
    "iso:country":"GB",
    "sg:address":"160 Station App, Epsom Rd",
    "sg:city":"Croydon",
    "sg:classifiers":[
        {
            "category":"Shopping",
            "type":"Retail Goods"
        }
    ],
    "sg:postcode":"CR0 4NA",
    "sg:province":"Surrey",
    "sg:tags":[
        "part",
        "accessory"
    ],
    "wof:name":"Waddon Car Spares",
    "wof:placetype":"venue"
},
  "geometry": {"coordinates":[-0.1144800037,51.368938446],"type":"Point"}
}