{
  "type": "Feature",
  "properties": {
    "iso:country":"GB",
    "sg:address":"224a High Street",
    "sg:city":"Beckenham",
    "sg:classifiers":[
        {
            "category":"Personal",
            "subcategory":"Beauty Salon",
            "type":"Services"
        }
    ],
    "sg:phone":"+44 20 8650 7386",
    "sg:postcode":"BR3 1EN",
    "sg:province":"Kent",
    "sg:tags":[
        "lady",
        "hairdresser"
    ],
    "wof:name":"Gigante Marketing Ltd.",
    "wof:placetype":"venue"
},
  "geometry": {"coordinates":[-0.028834,51.406548],"type":"Point"}
}