{
  "type": "Feature",
  "properties": {
    "iso:country":"GB",
    "sg:address":"247 Main Road, Walters Ash",
    "sg:city":"High Wycombe",
    "sg:classifiers":[
        {
            "category":"Shopping",
            "subcategory":"Department Store",
            "type":"Retail Goods"
        },
        {
            "category":"Food & Beverages",
            "subcategory":"Groceries & Convenience Stores",
            "type":"Retail Goods"
        }
    ],
    "sg:postcode":"HP14 4TH",
    "sg:province":"Buckinghamshire",
    "wof:name":"THE COUNTRY STORE",
    "wof:placetype":"venue"
},
  "geometry": {"coordinates":[-0.788827,51.673698],"type":"Point"}
}