{
  "type": "Feature",
  "properties": {
    "iso:country":"GB",
    "sg:address":"2 Stratford Avenue",
    "sg:city":"Uxbridge",
    "sg:classifiers":[
        {
            "category":"Professional",
            "subcategory":"Engineering",
            "type":"Services"
        }
    ],
    "sg:phone":"+44 1895 236494",
    "sg:postcode":"UB10 0JW",
    "sg:province":"Greater London",
    "sg:tags":[
        "civil",
        "engineer"
    ],
    "wof:name":"Bridgehill Construction Ltd.",
    "wof:placetype":"venue"
},
  "geometry": {"coordinates":[-0.463772,51.536491],"type":"Point"}
}