{
  "type": "Feature",
  "properties": {
    "addr:full":"605 Henley Road Coventry Warwickshire CV2 2FZ",
    "addr:housenumber":"605",
    "addr:postcode":"cv2 2fz",
    "addr:street":"Henley Road",
    "iso:country":"GB",
    "sg:address":"605 Henley Road",
    "sg:city":"Coventry",
    "sg:classifiers":[
        {
            "category":"Social Services",
            "subcategory":"Retirement Home",
            "type":"Services"
        }
    ],
    "sg:phone":"+44 24 7662 1723",
    "sg:postcode":"CV2 2FZ",
    "sg:province":"Warwickshire",
    "sg:tags":[
        "residential",
        "care"
    ],
    "wof:name":"Cottage Close",
    "wof:placetype":"venue"
},
  "geometry": {"coordinates":[-1.4480320215,52.4286003113],"type":"Point"}
}