{
  "type": "Feature",
  "properties": {
    "iso:country":"GB",
    "sg:address":"Port Road East",
    "sg:city":"Barry",
    "sg:classifiers":[
        {
            "category":"Sports & Exercise",
            "subcategory":"Golf",
            "type":"Entertainment"
        }
    ],
    "sg:phone":"+44 1446 742434",
    "sg:postcode":"CF62 9PX",
    "sg:province":"The Vale of Glamorgan",
    "sg:tags":[
        "club",
        "course"
    ],
    "wof:name":"South Wales Golf Range & Course",
    "wof:placetype":"venue"
},
  "geometry": {"coordinates":[-3.272139,51.425484],"type":"Point"}
}