{
  "type": "Feature",
  "properties": {
    "addr:full":"317 Upper Fourth Street, Central Milton Keynes Milton Keynes Buckinghamshire MK9 1EH",
    "addr:housenumber":"317",
    "addr:postcode":"mk9 1eh",
    "addr:street":"Upper Fourth Street",
    "iso:country":"GB",
    "sg:address":"317 Upper Fourth Street, Central Milton Keynes",
    "sg:city":"Milton Keynes",
    "sg:classifiers":[
        {
            "category":"Professional",
            "subcategory":"Lawyer & Legal Services",
            "type":"Services"
        }
    ],
    "sg:phone":"+44 1908 694569",
    "sg:postcode":"MK9 1EH",
    "sg:province":"Buckinghamshire",
    "sg:tags":[
        "conveyancing"
    ],
    "wof:name":"Johnston Alan",
    "wof:placetype":"venue"
},
  "geometry": {"coordinates":[-0.7667819858,52.0381736755],"type":"Point"}
}