{
  "type": "Feature",
  "properties": {
    "addr:full":"Merlin House, 122-126 Kilburn High Road London Greater London NW6 4HY",
    "addr:housenumber":"122-126",
    "addr:postcode":"nw6 4hy",
    "addr:street":"Kilburn High Road",
    "iso:country":"GB",
    "sg:address":"Merlin House, 122-126 Kilburn High Road",
    "sg:city":"London",
    "sg:classifiers":[
        {
            "category":"Shopping",
            "subcategory":"Mobile Phones",
            "type":"Retail Goods"
        },
        {
            "category":"Professional",
            "subcategory":"Business Services",
            "type":"Services"
        }
    ],
    "sg:phone":"+44 20 7692 6789",
    "sg:postcode":"NW6 4HY",
    "sg:province":"Greater London",
    "sg:tags":[
        "answering",
        "telephone"
    ],
    "wof:name":"Messagemail",
    "wof:placetype":"venue"
},
  "geometry": {"coordinates":[-0.19503,51.539623],"type":"Point"}
}