{
  "type": "Feature",
  "properties": {
    "addr:full":"Willow View, Blackcroft Avenue Northwich Cheshire CW8 4HP",
    "addr:postcode":"cw8 4hp",
    "addr:street":"Avenue",
    "iso:country":"GB",
    "sg:address":"Willow View, Blackcroft Avenue",
    "sg:city":"Northwich",
    "sg:classifiers":[
        {
            "category":"Social Services",
            "subcategory":"Retirement Home",
            "type":"Services"
        }
    ],
    "sg:postcode":"CW8 4HP",
    "sg:province":"Cheshire",
    "sg:tags":[
        "residential",
        "care"
    ],
    "wof:name":"C L S Care Services Ltd.",
    "wof:placetype":"venue"
},
  "geometry": {"coordinates":[-2.5251140594,53.2638168335],"type":"Point"}
}