{
  "type": "Feature",
  "properties": {
    "iso:country":"GB",
    "sg:address":"40 Thursby Road, Croft Industrial Estate",
    "sg:city":"Wirral",
    "sg:classifiers":[
        {
            "category":"Banks & Credit Unions",
            "subcategory":"Investment Brokerage",
            "type":"Services"
        },
        {
            "category":"Manufacturing",
            "subcategory":"Wood Products",
            "type":"Manufacturing & Wholesale Goods"
        }
    ],
    "sg:phone":"+44 1475 501000",
    "sg:postcode":"CH62 3PZ",
    "sg:province":"Cheshire",
    "sg:tags":[
        "packaging",
        "crate",
        "pallets",
        "vehicle"
    ],
    "wof:name":"Novathene Films Ltd.",
    "wof:placetype":"venue"
},
  "geometry": {"coordinates":[-2.9765789509,53.3365974426],"type":"Point"}
}