{
  "type": "Feature",
  "properties": {
    "addr:full":"7 Christmas Steps Bristol City of Bristol BS1 5BS",
    "addr:housenumber":"7",
    "addr:postcode":"bs1 5bs",
    "addr:street":"Christmas Steps",
    "iso:country":"GB",
    "sg:address":"7 Christmas Steps",
    "sg:city":"Bristol",
    "sg:classifiers":[
        {
            "category":"Shopping",
            "subcategory":"Shoes",
            "type":"Retail Goods"
        }
    ],
    "sg:postcode":"BS1 5BS",
    "sg:province":"City of Bristol",
    "sg:tags":[
        "shop"
    ],
    "wof:name":"Charles Macwatt Handmade Boots and Shoes",
    "wof:placetype":"venue"
},
  "geometry": {"coordinates":[-2.5968670845,51.4560890198],"type":"Point"}
}