{
  "type": "Feature",
  "properties": {
    "addr:full":"2 Brunswick Road, Withington Manchester Greater Manchester M20 4GA",
    "addr:housenumber":"2",
    "addr:postcode":"m20 4ga",
    "addr:street":"Brunswick Road",
    "iso:country":"GB",
    "sg:address":"2 Brunswick Road, Withington",
    "sg:city":"Manchester",
    "sg:classifiers":[
        {
            "category":"Professional",
            "subcategory":"Secretarial Services",
            "type":"Services"
        }
    ],
    "sg:postcode":"M20 4GA",
    "sg:province":"Greater Manchester",
    "wof:name":"John Shaw Computer Services",
    "wof:placetype":"venue"
},
  "geometry": {"coordinates":[-2.223381,53.435631],"type":"Point"}
}