{
  "type": "Feature",
  "properties": {
    "addr:full":"Room 427london Fruit Exchange, Brushfield Street London Greater London E1 6EL",
    "addr:postcode":"e1 6el",
    "addr:street":"Brushfield Street",
    "iso:country":"GB",
    "sg:address":"Room 427london Fruit Exchange, Brushfield Street",
    "sg:city":"London",
    "sg:classifiers":[
        {
            "category":"Professional",
            "subcategory":"Research",
            "type":"Services"
        }
    ],
    "sg:phone":"+44 20 7377 8885",
    "sg:postcode":"E1 6EL",
    "sg:province":"Greater London",
    "sg:tags":[
        "organisation"
    ],
    "wof:name":"Henry George Foundation of Great Britain Ltd.",
    "wof:placetype":"venue"
},
  "geometry": {"coordinates":[-0.0753780007,51.5190696716],"type":"Point"}
}