{
  "type": "Feature",
  "properties": {
    "addr:full":"21 Baxtergate Whitby North Yorkshire YO21 1BW",
    "addr:housenumber":"21",
    "addr:postcode":"yo21 1bw",
    "addr:street":"Baxtergate",
    "iso:country":"GB",
    "sg:address":"21 Baxtergate",
    "sg:city":"Whitby",
    "sg:classifiers":[
        {
            "category":"Banks & Credit Unions",
            "subcategory":"Bank",
            "type":"Services"
        }
    ],
    "sg:phone":"+44 1723 396000",
    "sg:postcode":"YO21 1BW",
    "sg:province":"North Yorkshire",
    "wof:name":"Barclays Bank Plc",
    "wof:placetype":"venue"
},
  "geometry": {"coordinates":[-0.6145290136,54.4860420227],"type":"Point"}
}