{
  "type": "Feature",
  "properties": {
    "iso:country":"GB",
    "sg:address":"1 Park Place",
    "sg:city":"London",
    "sg:classifiers":[
        {
            "category":"Government",
            "subcategory":"Office",
            "type":"Public Place"
        }
    ],
    "sg:phone":"+44 20 7987 5030",
    "sg:postcode":"E14 4HJ",
    "sg:province":"Greater London",
    "sg:tags":[
        "armed",
        "reserve"
    ],
    "wof:name":"Demon Animatics Ltd.",
    "wof:placetype":"venue"
},
  "geometry": {"coordinates":[-0.024976,51.505077],"type":"Point"}
}