{
  "type": "Feature",
  "properties": {
    "iso:country":"GB",
    "sg:address":"177 Kirkstall Road",
    "sg:city":"Leeds",
    "sg:classifiers":[
        {
            "category":"Wholesale",
            "subcategory":"Construction Materials",
            "type":"Manufacturing & Wholesale Goods"
        }
    ],
    "sg:phone":"+44 113 244 1202",
    "sg:postcode":"LS4 2AQ",
    "sg:province":"West Yorkshire",
    "sg:tags":[
        "distributor",
        "spring"
    ],
    "wof:name":"Thyssenkrupp Woodhead Ltd.",
    "wof:placetype":"venue"
},
  "geometry": {"coordinates":[-1.574529,53.803658],"type":"Point"}
}