{
  "type": "Feature",
  "properties": {
    "addr:full":"Obelisk Way Camberley Berkshire GU15 3SG",
    "addr:postcode":"gu15 3sg",
    "addr:street":"Obelisk Way",
    "iso:country":"GB",
    "sg:address":"Obelisk Way",
    "sg:city":"Camberley",
    "sg:classifiers":[
        {
            "category":"Home & Garden",
            "subcategory":"Household Appliances",
            "type":"Retail Goods"
        }
    ],
    "sg:phone":"+44 1276 64811",
    "sg:postcode":"GU15 3SG",
    "sg:province":"Berkshire",
    "sg:tags":[
        "electrical",
        "domestic"
    ],
    "wof:name":"D S G Retail Ltd.",
    "wof:placetype":"venue"
},
  "geometry": {"coordinates":[-0.7455340028,51.338886261],"type":"Point"}
}