{
  "type": "Feature",
  "properties": {
    "addr:full":"10 Porters Avenue Dagenham Essex RM8 2AQ",
    "addr:housenumber":"10",
    "addr:postcode":"rm8 2aq",
    "addr:street":"Porters Avenue",
    "iso:country":"GB",
    "sg:address":"10 Porters Avenue",
    "sg:city":"Dagenham",
    "sg:classifiers":[
        {
            "category":"Food & Beverages",
            "subcategory":"Liquor & Beverages",
            "type":"Retail Goods"
        }
    ],
    "sg:phone":"+44 20 8595 6025",
    "sg:postcode":"RM8 2AQ",
    "sg:province":"Essex",
    "sg:tags":[
        "beer",
        "spirit",
        "wines"
    ],
    "wof:name":"Maruti Wines",
    "wof:placetype":"venue"
},
  "geometry": {"coordinates":[0.130105,51.55154],"type":"Point"}
}