{
  "type": "Feature",
  "properties": {
    "iso:country":"GB",
    "sg:address":"39 Old Barn Close, Calmove",
    "sg:city":"Southampton",
    "sg:classifiers":[
        {
            "category":"Professional",
            "subcategory":"Engineering",
            "type":"Services"
        }
    ],
    "sg:phone":"+44 23 8086 1399",
    "sg:postcode":"SO40 2SY",
    "sg:province":"Hampshire",
    "sg:tags":[
        "gas",
        "engineer"
    ],
    "wof:name":"Chadvale Electrical Ltd.",
    "wof:placetype":"venue"
},
  "geometry": {"coordinates":[-1.5128970146,50.9308815002],"type":"Point"}
}