{
  "type": "Feature",
  "properties": {
    "iso:country":"GB",
    "sg:address":"26 Chaldon Road",
    "sg:city":"Caterham",
    "sg:classifiers":[
        {
            "category":"Shopping",
            "subcategory":"Pets & Pet Supplies",
            "type":"Retail Goods"
        }
    ],
    "sg:phone":"+44 1883 348814",
    "sg:postcode":"CR3 5PE",
    "sg:province":"Surrey",
    "sg:tags":[
        "shop"
    ],
    "wof:name":"Caterham Hill Pet Centre",
    "wof:placetype":"venue"
},
  "geometry": {"coordinates":[-0.090024,51.287582],"type":"Point"}
}