{
  "type": "Feature",
  "properties": {
    "addr:full":"Waterloo Street Kidderminster Staffordshire DY10 2ED",
    "addr:postcode":"dy10 2ed",
    "addr:street":"Waterloo Street",
    "iso:country":"GB",
    "sg:address":"Waterloo Street",
    "sg:city":"Kidderminster",
    "sg:classifiers":[
        {
            "category":"Real Estate",
            "subcategory":"Real Estate Services",
            "type":"Services"
        },
        {
            "category":"Building & Trades",
            "subcategory":"Plumbing",
            "type":"Services"
        }
    ],
    "sg:postcode":"DY10 2ED",
    "sg:province":"Staffordshire",
    "sg:tags":[
        "property",
        "heating",
        "maintenance"
    ],
    "wof:name":"FIRST FIX MAINTENANCE SERVICES",
    "wof:placetype":"venue"
},
  "geometry": {"coordinates":[-2.2461249828,52.3896980286],"type":"Point"}
}