{
  "type": "Feature",
  "properties": {
    "addr:full":"Bush Est Penicuik Midlothian EH26 0QE",
    "addr:postcode":"eh26 0qe",
    "addr:street":"Bush",
    "iso:country":"GB",
    "sg:address":"Bush Est",
    "sg:city":"Penicuik",
    "sg:classifiers":[
        {
            "category":"Retail",
            "subcategory":"Veterinary Services",
            "type":"Services"
        }
    ],
    "sg:phone":"+44 131 445 7940",
    "sg:postcode":"EH26 0QE",
    "sg:province":"Midlothian",
    "sg:tags":[
        "surgeon"
    ],
    "wof:name":"The East of Scotland College of Agricult",
    "wof:placetype":"venue"
},
  "geometry": {"coordinates":[-3.2199039459,55.8363952637],"type":"Point"}
}