{
  "type": "Feature",
  "properties": {
    "iso:country":"GB",
    "sg:address":"61 Pepper Rd, Hunslet",
    "sg:city":"Leeds",
    "sg:classifiers":[
        {
            "category":"Professional",
            "subcategory":"Business Services",
            "type":"Services"
        }
    ],
    "sg:phone":"+44 113 297 2972",
    "sg:postcode":"LS10 2RU",
    "sg:province":"West Yorkshire",
    "sg:tags":[
        "publishers'"
    ],
    "wof:name":"White Rose Publishing Ltd",
    "wof:placetype":"venue"
},
  "geometry": {"coordinates":[-1.521919,53.773834],"type":"Point"}
}