{
  "type": "Feature",
  "properties": {
    "addr:full":"3 Nelson Road Brixham Devon TQ5 8BH",
    "addr:housenumber":"3",
    "addr:postcode":"tq5 8bh",
    "addr:street":"Nelson Road",
    "iso:country":"GB",
    "sg:address":"3 Nelson Road",
    "sg:city":"Brixham",
    "sg:classifiers":[
        {
            "category":"Social Services",
            "subcategory":"Retirement Home",
            "type":"Services"
        }
    ],
    "sg:phone":"+44 1803 858590",
    "sg:postcode":"TQ5 8BH",
    "sg:province":"Devon",
    "sg:tags":[
        "rest"
    ],
    "wof:name":"Rydan Lodge",
    "wof:placetype":"venue"
},
  "geometry": {"coordinates":[-3.516947031,50.3978157043],"type":"Point"}
}