{
  "type": "Feature",
  "properties": {
    "addr:full":"Unit N Sittingbourne Kent ME9 7NU",
    "addr:postcode":"me9 7nu",
    "iso:country":"GB",
    "sg:address":"Unit N",
    "sg:city":"Sittingbourne",
    "sg:classifiers":[
        {
            "category":"Manufacturing",
            "subcategory":"Building Materials",
            "type":"Manufacturing & Wholesale Goods"
        }
    ],
    "sg:phone":"+44 1795 842338",
    "sg:postcode":"ME9 7NU",
    "sg:province":"Kent",
    "sg:tags":[
        "merchant",
        "builder"
    ],
    "wof:name":"Newington Brickworks",
    "wof:placetype":"venue"
},
  "geometry": {"coordinates":[0.7293000221,51.3373947144],"type":"Point"}
}