{
  "type": "Feature",
  "properties": {
    "addr:full":"407 Birmingham Road, Wylde Grn Sutton Coldfield West Midlands B72 1AU",
    "addr:housenumber":"407",
    "addr:postcode":"b72 1au",
    "addr:street":"Birmingham Road Wylde Grn",
    "iso:country":"GB",
    "sg:address":"407 Birmingham Road, Wylde Grn",
    "sg:city":"Sutton Coldfield",
    "sg:classifiers":[
        {
            "category":"Real Estate",
            "subcategory":"Real Estate Agent",
            "type":"Services"
        }
    ],
    "sg:phone":"+44 121 386 4567",
    "sg:postcode":"B72 1AU",
    "sg:province":"West Midlands",
    "wof:name":"Hunters",
    "wof:placetype":"venue"
},
  "geometry": {"coordinates":[-1.826782,52.536186],"type":"Point"}
}