{
  "type": "Feature",
  "properties": {
    "iso:country":"GB",
    "sg:address":"18 Homestall, Buckingham Industrial Park",
    "sg:city":"Buckingham",
    "sg:classifiers":[
        {
            "category":"Professional",
            "subcategory":"Engineering",
            "type":"Services"
        }
    ],
    "sg:postcode":"MK18 1XJ",
    "sg:province":"Buckinghamshire",
    "sg:tags":[
        "contractor",
        "electrical",
        "engineer"
    ],
    "wof:name":"Goodgame & Brock",
    "wof:placetype":"venue"
},
  "geometry": {"coordinates":[-0.9864789844,52.0007514954],"type":"Point"}
}