{
  "type": "Feature",
  "properties": {
    "addr:full":"Mostyn Street Llandudno Conwy LL30 2NG",
    "addr:postcode":"ll30 2ng",
    "addr:street":"Mostyn Street",
    "iso:country":"GB",
    "sg:address":"Mostyn Street",
    "sg:city":"Llandudno",
    "sg:classifiers":[
        {
            "category":"Government",
            "subcategory":"Post Office",
            "type":"Public Place"
        },
        {
            "category":"Shopping",
            "subcategory":"Pharmacy",
            "type":"Retail Goods"
        }
    ],
    "sg:phone":"+44 1492 878827",
    "sg:postcode":"LL30 2NG",
    "sg:province":"Conwy",
    "sg:tags":[
        "pharmacist",
        "chemist"
    ],
    "wof:name":"Boots the Chemists Ltd.",
    "wof:placetype":"venue"
},
  "geometry": {"coordinates":[-3.8330891132,53.3272399902],"type":"Point"}
}