{
  "type": "Feature",
  "properties": {
    "addr:full":"9 Belair Road Plymouth Devon PL2 3QH",
    "addr:housenumber":"9",
    "addr:postcode":"pl2 3qh",
    "addr:street":"Belair Road",
    "iso:country":"GB",
    "sg:address":"9 Belair Road",
    "sg:city":"Plymouth",
    "sg:classifiers":[
        {
            "category":"Building & Trades",
            "subcategory":"Construction",
            "type":"Services"
        }
    ],
    "sg:phone":"+44 1752 704071",
    "sg:postcode":"PL2 3QH",
    "sg:province":"Devon",
    "sg:tags":[
        "decorator",
        "painter"
    ],
    "wof:name":"David Warren",
    "wof:placetype":"venue"
},
  "geometry": {"coordinates":[-4.149377,50.393341],"type":"Point"}
}