{
  "type": "Feature",
  "properties": {
    "iso:country":"GB",
    "sg:address":"1 Admaral Farm, Turton Marsh",
    "sg:city":"King's Lynn",
    "sg:classifiers":[
        {
            "category":"Utilities",
            "subcategory":"Refuse",
            "type":"Services"
        }
    ],
    "sg:phone":"+44 1553 827062",
    "sg:postcode":"PE34 4JE",
    "sg:province":"Lincolnshire",
    "sg:tags":[
        "skip",
        "hire"
    ],
    "wof:name":"Ace Skips",
    "wof:placetype":"venue"
},
  "geometry": {"coordinates":[0.32626,52.79681],"type":"Point"}
}