{
  "type": "Feature",
  "properties": {
    "addr:full":"30 Lucius Street Torquay Devon TQ2 5UN",
    "addr:housenumber":"30",
    "addr:postcode":"tq2 5un",
    "addr:street":"Lucius Street",
    "iso:country":"GB",
    "sg:address":"30 Lucius Street",
    "sg:city":"Torquay",
    "sg:classifiers":[
        {
            "category":"Food & Beverages",
            "subcategory":"Bakery",
            "type":"Retail Goods"
        }
    ],
    "sg:phone":"+44 1803 292580",
    "sg:postcode":"TQ2 5UN",
    "sg:province":"Devon",
    "sg:tags":[
        "baker"
    ],
    "wof:name":"Startime Patisserie",
    "wof:placetype":"venue"
},
  "geometry": {"coordinates":[-3.5386970043,50.4674263],"type":"Point"}
}