{
  "type": "Feature",
  "properties": {
    "iso:country":"GB",
    "sg:address":"60 Union Street",
    "sg:city":"Harrogate",
    "sg:classifiers":[
        {
            "category":"Building & Trades",
            "subcategory":"Construction",
            "type":"Services"
        }
    ],
    "sg:postcode":"HG1 1BS",
    "sg:province":"North Yorkshire",
    "sg:tags":[
        "joiner",
        "carpenter"
    ],
    "wof:name":"Clarks Joiners",
    "wof:placetype":"venue"
},
  "geometry": {"coordinates":[-1.543111,53.994968],"type":"Point"}
}