{
  "type": "Feature",
  "properties": {
    "addr:full":"Ashby House, Bath Street Ashby-de-la-zouch Derbyshire LE65 2FH",
    "addr:postcode":"le65 2fh",
    "addr:street":"Bath Street",
    "iso:country":"GB",
    "sg:address":"Ashby House, Bath Street",
    "sg:city":"Ashby-de-la-zouch",
    "sg:classifiers":[
        {
            "category":"Banks & Credit Unions",
            "subcategory":"Bank",
            "type":"Services"
        },
        {
            "category":"Banks & Credit Unions",
            "subcategory":"Financial Services",
            "type":"Services"
        }
    ],
    "sg:phone":"+44 1530 415017",
    "sg:postcode":"LE65 2FH",
    "sg:province":"Derbyshire",
    "sg:tags":[
        "consultant",
        "institution"
    ],
    "wof:name":"Bank of Scotland Equipment Finance Ltd.",
    "wof:placetype":"venue"
},
  "geometry": {"coordinates":[-1.4734989405,52.7462692261],"type":"Point"}
}