{
  "type": "Feature",
  "properties": {
    "iso:country":"GB",
    "sg:address":"2 The Embankment, Sovereign St",
    "sg:city":"Leeds",
    "sg:classifiers":[
        {
            "category":"Utilities",
            "subcategory":"Water",
            "type":"Services"
        }
    ],
    "sg:phone":"+44 113 234 3234",
    "sg:postcode":"LS1 4BG",
    "sg:province":"West Yorkshire",
    "wof:name":"Yorkshire Water Estates",
    "wof:placetype":"venue"
},
  "geometry": {"coordinates":[-1.545876,53.793072],"type":"Point"}
}