{
  "type": "Feature",
  "properties": {
    "addr:full":"Back Lane, Hinderwell Saltburn-by-the-sea North Yorkshire TS13 5JR",
    "addr:postcode":"ts13 5jr",
    "addr:street":"Back Lane",
    "iso:country":"GB",
    "sg:address":"Back Lane, Hinderwell",
    "sg:city":"Saltburn-by-the-sea",
    "sg:classifiers":[
        {
            "category":"Recreation",
            "subcategory":"Campground",
            "type":"Entertainment"
        }
    ],
    "sg:phone":"+44 1947 840370",
    "sg:postcode":"TS13 5JR",
    "sg:province":"North Yorkshire",
    "sg:tags":[
        "caravan",
        "park"
    ],
    "wof:name":"Gatehouse Caravan Site",
    "wof:placetype":"venue"
},
  "geometry": {"coordinates":[-0.7808300257,54.5398712158],"type":"Point"}
}