{
  "type": "Feature",
  "properties": {
    "iso:country":"GB",
    "sg:address":"Flat 6, 69 Riddfield Rd, Castle Bromwich",
    "sg:city":"Birmingham",
    "sg:classifiers":[
        {
            "category":"Home & Garden",
            "subcategory":"Carpets & Floor Coverings",
            "type":"Retail Goods"
        }
    ],
    "sg:postcode":"B36 8NT",
    "sg:province":"West Midlands",
    "sg:tags":[
        "cleaner",
        "upholstery"
    ],
    "wof:name":"Freeman,Ashley,",
    "wof:placetype":"venue"
},
  "geometry": {"coordinates":[-1.8008799553,52.5074081421],"type":"Point"}
}