{
  "type": "Feature",
  "properties": {
    "addr:full":"70 George Street Luton Bedfordshire LU1 2BD",
    "addr:housenumber":"70",
    "addr:postcode":"lu1 2bd",
    "addr:street":"George Street",
    "iso:country":"GB",
    "sg:address":"70 George Street",
    "sg:city":"Luton",
    "sg:classifiers":[
        {
            "category":"Shopping",
            "subcategory":"Thrift Store",
            "type":"Retail Goods"
        },
        {
            "category":"Organizations",
            "subcategory":"Non-profit Organization",
            "type":"Services"
        }
    ],
    "sg:phone":"+44 1582 482812",
    "sg:postcode":"LU1 2BD",
    "sg:province":"Bedfordshire",
    "sg:tags":[
        "shop",
        "charitable",
        "organisation",
        "charity"
    ],
    "wof:name":"British Heart Foundation Shops",
    "wof:placetype":"venue"
},
  "geometry": {"coordinates":[-0.416862,51.879456],"type":"Point"}
}