{
  "type": "Feature",
  "properties": {
    "iso:country":"GB",
    "sg:address":"153 Kingsway",
    "sg:city":"Hove",
    "sg:classifiers":[
        {
            "category":"Travel",
            "subcategory":"Hotels & Motels",
            "type":"Entertainment"
        }
    ],
    "sg:phone":"+44 1273 207660",
    "sg:postcode":"BN3 4GR",
    "sg:province":"East Sussex",
    "wof:name":"Princes Marine Hotel",
    "wof:placetype":"venue"
},
  "geometry": {"coordinates":[-0.18217,50.825951],"type":"Point"}
}