{
  "type": "Feature",
  "properties": {
    "addr:full":"80 Blackwell Darlington Durham DL3 8QW",
    "addr:housenumber":"80",
    "addr:postcode":"dl3 8qw",
    "addr:street":"Blackwell Darlington",
    "iso:country":"GB",
    "sg:address":"80 Blackwell",
    "sg:city":"Darlington",
    "sg:classifiers":[
        {
            "category":"Social Services",
            "subcategory":"Job Training",
            "type":"Services"
        }
    ],
    "sg:phone":"+44 1325 488882",
    "sg:postcode":"DL3 8QW",
    "sg:province":"Durham",
    "sg:tags":[
        "draughtsman",
        "drawing"
    ],
    "wof:name":"J W Young & Partner",
    "wof:placetype":"venue"
},
  "geometry": {"coordinates":[-1.5754289627,54.5124511719],"type":"Point"}
}