{
  "type": "Feature",
  "properties": {
    "iso:country":"GB",
    "sg:address":"Chevening Road, Chipstead",
    "sg:city":"Sevenoaks",
    "sg:classifiers":[
        {
            "category":"Education",
            "subcategory":"School",
            "type":"Public Place"
        }
    ],
    "sg:phone":"+44 1732 452895",
    "sg:postcode":"TN13 2SA",
    "sg:province":"Kent",
    "sg:tags":[
        "local",
        "authority"
    ],
    "wof:name":"Chevening C of E Primary School",
    "wof:placetype":"venue"
},
  "geometry": {"coordinates":[0.151009,51.284321],"type":"Point"}
}