{
  "type": "Feature",
  "properties": {
    "iso:country":"GB",
    "sg:address":"Charlock Farm, Abthorpe Road, Silverstone",
    "sg:city":"Towcester",
    "sg:classifiers":[
        {
            "category":"Farming",
            "subcategory":"Livestock Farm",
            "type":"Manufacturing & Wholesale Goods"
        }
    ],
    "sg:phone":"+44 1327 857243",
    "sg:postcode":"NN12 8TW",
    "sg:province":"Buckinghamshire",
    "sg:tags":[
        "others"
    ],
    "wof:name":"A WILLIAMS",
    "wof:placetype":"venue"
},
  "geometry": {"coordinates":[-1.052884,52.112465],"type":"Point"}
}