{
  "type": "Feature",
  "properties": {
    "iso:country":"GB",
    "sg:address":"Earlstrees Court, Earlstrees Road Industrial Estate",
    "sg:city":"Corby",
    "sg:classifiers":[
        {
            "category":"Home & Garden",
            "subcategory":"Building Materials",
            "type":"Retail Goods"
        }
    ],
    "sg:phone":"+44 1536 443888",
    "sg:postcode":"NN17 4AX",
    "sg:province":"Northamptonshire",
    "sg:tags":[
        "equipment",
        "disability"
    ],
    "wof:name":"Freerider (Uk) Ltd.",
    "wof:placetype":"venue"
},
  "geometry": {"coordinates":[-0.693624,52.5093],"type":"Point"}
}