{
  "type": "Feature",
  "properties": {
    "iso:country":"GB",
    "sg:address":"12 Peacock Street",
    "sg:city":"Gravesend",
    "sg:classifiers":[
        {
            "category":"Wholesale",
            "subcategory":"Non-durable Goods",
            "type":"Manufacturing & Wholesale Goods"
        }
    ],
    "sg:phone":"+44 1474 560530",
    "sg:postcode":"DA12 1EE",
    "sg:province":"Kent",
    "sg:tags":[
        "carry",
        "wholesaler",
        "cash"
    ],
    "wof:name":"Singh Cash & Carry",
    "wof:placetype":"venue"
},
  "geometry": {"coordinates":[0.374175,51.441093],"type":"Point"}
}