{
  "type": "Feature",
  "properties": {
    "iso:country":"GB",
    "sg:address":"Commercial Road",
    "sg:city":"Hereford",
    "sg:classifiers":[
        {
            "category":"Cafe",
            "type":"Food & Drink"
        }
    ],
    "sg:phone":"+44 1432 275506",
    "sg:postcode":"HR1 2BL",
    "sg:province":"Herefordshire",
    "sg:tags":[
        "tea",
        "snack",
        "bar",
        "room"
    ],
    "wof:name":"The Bus Station Cafe",
    "wof:placetype":"venue"
},
  "geometry": {"coordinates":[-2.709483,52.058895],"type":"Point"}
}