{
  "type": "Feature",
  "properties": {
    "addr:full":"7 Pevensey Ho, Castle Clo Reigate Surrey RH2 8DJ",
    "addr:housenumber":"7",
    "addr:postcode":"rh2 8dj",
    "addr:street":"Pevensey Ho;Clo",
    "iso:country":"GB",
    "sg:address":"7 Pevensey Ho, Castle Clo",
    "sg:city":"Reigate",
    "sg:classifiers":[
        {
            "category":"Home & Garden",
            "subcategory":"Home Furnishings",
            "type":"Retail Goods"
        }
    ],
    "sg:phone":"+44 1737 277068",
    "sg:postcode":"RH2 8DJ",
    "sg:province":"Surrey",
    "sg:tags":[
        "beds",
        "bedding",
        "blanket"
    ],
    "wof:name":"Beds Direct",
    "wof:placetype":"venue"
},
  "geometry": {"coordinates":[-0.204779,51.235744],"type":"Point"}
}