{
  "type": "Feature",
  "properties": {
    "addr:full":"50 Upperfield Road Welwyn Garden City Hertfordshire AL7 3LW",
    "addr:housenumber":"50",
    "addr:postcode":"al7 3lw",
    "addr:street":"Upperfield Road",
    "iso:country":"GB",
    "sg:address":"50 Upperfield Road",
    "sg:city":"Welwyn Garden City",
    "sg:classifiers":[
        {
            "category":"Education",
            "subcategory":"Special Training",
            "type":"Public Place"
        }
    ],
    "sg:phone":"+44 1707 373829",
    "sg:postcode":"AL7 3LW",
    "sg:province":"Hertfordshire",
    "sg:tags":[
        "product",
        "centre"
    ],
    "wof:name":"J A P Training Services",
    "wof:placetype":"venue"
},
  "geometry": {"coordinates":[-0.190942,51.793388],"type":"Point"}
}