{
  "type": "Feature",
  "properties": {
    "addr:full":"1 Paton Close London Greater London E3 2QD",
    "addr:housenumber":"1",
    "addr:postcode":"e3 2qd",
    "addr:street":"Paton Close",
    "iso:country":"GB",
    "sg:address":"1 Paton Close",
    "sg:city":"London",
    "sg:classifiers":[
        {
            "category":"Professional",
            "subcategory":"Testing Lab",
            "type":"Services"
        }
    ],
    "sg:postcode":"E3 2QD",
    "sg:province":"Greater London",
    "sg:tags":[
        "mot"
    ],
    "wof:name":"Paton Engineering Works",
    "wof:placetype":"venue"
},
  "geometry": {"coordinates":[-0.0204339996,51.5288314819],"type":"Point"}
}