{
  "type": "Feature",
  "properties": {
    "iso:country":"GB",
    "sg:address":"65 Queen Street",
    "sg:city":"Newton Abbot",
    "sg:classifiers":[
        {
            "category":"Shopping",
            "subcategory":"Catalog Store",
            "type":"Retail Goods"
        }
    ],
    "sg:phone":"+44 1626 363224",
    "sg:postcode":"TQ12 2AU",
    "sg:province":"Devon",
    "sg:tags":[
        "catalogue",
        "showroom"
    ],
    "wof:name":"Argos Ltd.",
    "wof:placetype":"venue"
},
  "geometry": {"coordinates":[-3.606012,50.530712],"type":"Point"}
}