{
  "type": "Feature",
  "properties": {
    "addr:full":"2 Curteys, Old Rd Harlow Essex CM17 0JG",
    "addr:housenumber":"2",
    "addr:postcode":"cm17 0jg",
    "addr:street":"Curteys Old Rd",
    "iso:country":"GB",
    "sg:address":"2 Curteys, Old Rd",
    "sg:city":"Harlow",
    "sg:classifiers":[
        {
            "category":"Home & Garden",
            "subcategory":"Home Furnishings",
            "type":"Retail Goods"
        }
    ],
    "sg:phone":"+44 1279 442432",
    "sg:postcode":"CM17 0JG",
    "sg:province":"Essex",
    "sg:tags":[
        "furnishers",
        "planner",
        "kitchen"
    ],
    "wof:name":"Hunters Brook Kitchen",
    "wof:placetype":"venue"
},
  "geometry": {"coordinates":[0.1411699951,51.7886657715],"type":"Point"}
}