{
  "type": "Feature",
  "properties": {
    "iso:country":"GB",
    "sg:address":"Unit 40 Westbrook Rd, Trafford Pk",
    "sg:city":"Manchester",
    "sg:classifiers":[
        {
            "category":"Manufacturing",
            "subcategory":"Chemicals & Compounds",
            "type":"Manufacturing & Wholesale Goods"
        }
    ],
    "sg:postcode":"M17 1AY",
    "sg:province":"Cheshire",
    "sg:tags":[
        "abrasive",
        "product",
        "cleaning"
    ],
    "wof:name":"Bay State S A",
    "wof:placetype":"venue"
},
  "geometry": {"coordinates":[-2.306449,53.470242],"type":"Point"}
}