{
  "type": "Feature",
  "properties": {
    "iso:country":"GB",
    "sg:address":"13 Waterloo Street",
    "sg:city":"Weston-super-mare",
    "sg:classifiers":[
        {
            "category":"Real Estate",
            "subcategory":"Real Estate Agent",
            "type":"Services"
        }
    ],
    "sg:postcode":"BS23 1LA",
    "sg:province":"Somerset",
    "wof:name":"C J Hole",
    "wof:placetype":"venue"
},
  "geometry": {"coordinates":[-2.9781301022,51.3502578735],"type":"Point"}
}