{
  "type": "Feature",
  "properties": {
    "addr:full":"19 Yew Tree Gardens, London Rd Romford Essex RM7 9AA",
    "addr:housenumber":"19",
    "addr:postcode":"rm7 9aa",
    "addr:street":"Yew Tree Gardens London Rd",
    "iso:country":"GB",
    "sg:address":"19 Yew Tree Gardens, London Rd",
    "sg:city":"Romford",
    "sg:classifiers":[
        {
            "category":"Shopping",
            "subcategory":"Party Supplies",
            "type":"Retail Goods"
        }
    ],
    "sg:phone":"+44 1708 377523",
    "sg:postcode":"RM7 9AA",
    "sg:province":"Essex",
    "sg:tags":[
        "equipment",
        "disco"
    ],
    "wof:name":"Black Box Hire",
    "wof:placetype":"venue"
},
  "geometry": {"coordinates":[0.1761649996,51.5773200989],"type":"Point"}
}