{
  "type": "Feature",
  "properties": {
    "iso:country":"GB",
    "sg:address":"10 Sterte Close",
    "sg:city":"Poole",
    "sg:classifiers":[
        {
            "category":"Professional",
            "subcategory":"Computer Services",
            "type":"Services"
        }
    ],
    "sg:phone":"+44 1202 666155",
    "sg:postcode":"BH15 2AT",
    "sg:province":"Dorset",
    "sg:tags":[
        "system",
        "software"
    ],
    "wof:name":"Officeland",
    "wof:placetype":"venue"
},
  "geometry": {"coordinates":[-1.986522,50.724266],"type":"Point"}
}