{
  "type": "Feature",
  "properties": {
    "iso:country":"GB",
    "sg:address":"787 Whalley New Rd",
    "sg:city":"Blackburn",
    "sg:classifiers":[
        {
            "category":"Transit Center",
            "subcategory":"Freight",
            "type":"Transportation"
        }
    ],
    "sg:phone":"+44 1254 245391",
    "sg:postcode":"BB1 9BE",
    "sg:province":"Lancashire",
    "sg:tags":[
        "shop",
        "craft",
        "centre"
    ],
    "wof:name":"Topaz Wearable Arts & Crafts",
    "wof:placetype":"venue"
},
  "geometry": {"coordinates":[-2.477828,53.779022],"type":"Point"}
}