{
  "type": "Feature",
  "properties": {
    "iso:country":"GB",
    "sg:address":"11 Belgrave Rd",
    "sg:city":"Cambridge",
    "sg:classifiers":[
        {
            "category":"Building & Trades",
            "subcategory":"Construction",
            "type":"Services"
        }
    ],
    "sg:phone":"+44 1223 294747",
    "sg:postcode":"CB1 3DE",
    "sg:province":"Cambridgeshire",
    "sg:tags":[
        "glazier"
    ],
    "wof:name":"Cambridge Glass & Glazing",
    "wof:placetype":"venue"
},
  "geometry": {"coordinates":[0.149733,52.197533],"type":"Point"}
}