{
  "type": "Feature",
  "properties": {
    "addr:full":"118 South St Perth Perth and Kinross PH2 8PA",
    "addr:housenumber":"118",
    "addr:postcode":"ph2 8pa",
    "addr:street":"South St",
    "iso:country":"GB",
    "sg:address":"118 South St",
    "sg:city":"Perth",
    "sg:classifiers":[
        {
            "category":"Shopping",
            "subcategory":"Thrift Store",
            "type":"Retail Goods"
        }
    ],
    "sg:phone":"+44 1738 446790",
    "sg:postcode":"PH2 8PA",
    "sg:province":"Perth and Kinross",
    "sg:tags":[
        "shop",
        "charity"
    ],
    "wof:name":"Oxfam",
    "wof:placetype":"venue"
},
  "geometry": {"coordinates":[-3.430907,56.395164],"type":"Point"}
}