{
  "type": "Feature",
  "properties": {
    "addr:full":"Thorncliffe Rd Barrow In Furness Cumbria LA14 5QA",
    "addr:postcode":"la14 5qa",
    "addr:street":"Thorncliffe Rd",
    "iso:country":"GB",
    "sg:address":"Thorncliffe Rd",
    "sg:city":"Barrow In Furness",
    "sg:classifiers":[
        {
            "category":"Community Center",
            "type":"Public Place"
        }
    ],
    "sg:phone":"+44 1229 838881",
    "sg:postcode":"LA14 5QA",
    "sg:province":"Cumbria",
    "sg:tags":[
        "recreation",
        "leisure",
        "centre"
    ],
    "wof:name":"The Hoops Basketball Centre",
    "wof:placetype":"venue"
},
  "geometry": {"coordinates":[-3.2175819874,54.1301994324],"type":"Point"}
}