{
  "type": "Feature",
  "properties": {
    "addr:full":"Penygaer, Dafen Road, Felinfoel Llanelli Carmarthenshire SA14 8LY",
    "addr:postcode":"sa14 8ly",
    "addr:street":"Dafen Road",
    "iso:country":"GB",
    "sg:address":"Penygaer, Dafen Road, Felinfoel",
    "sg:city":"Llanelli",
    "sg:classifiers":[
        {
            "category":"Arena",
            "subcategory":"Sports Club",
            "type":"Entertainment"
        }
    ],
    "sg:phone":"+44 1554 772707",
    "sg:postcode":"SA14 8LY",
    "sg:province":"Carmarthenshire",
    "wof:name":"Felinfoel Rugby Football",
    "wof:placetype":"venue"
},
  "geometry": {"coordinates":[-4.129759,51.691139],"type":"Point"}
}