{
  "type": "Feature",
  "properties": {
    "iso:country":"GB",
    "sg:address":"Whitlock House, 6 Earls Court Road",
    "sg:city":"London",
    "sg:classifiers":[
        {
            "category":"Real Estate",
            "subcategory":"Real Estate Operator",
            "type":"Services"
        }
    ],
    "sg:phone":"+44 20 7937 3848",
    "sg:postcode":"W8 6EA",
    "sg:province":"Greater London",
    "sg:tags":[
        "letting",
        "agent"
    ],
    "wof:name":"Meeting Point",
    "wof:placetype":"venue"
},
  "geometry": {"coordinates":[-0.198392,51.498344],"type":"Point"}
}