{
  "type": "Feature",
  "properties": {
    "iso:country":"GB",
    "sg:address":"C.m.c House, Dark Lane",
    "sg:city":"Manchester",
    "sg:classifiers":[
        {
            "category":"Professional",
            "subcategory":"Business Services",
            "type":"Services"
        }
    ],
    "sg:phone":"+44 161 273 8078",
    "sg:postcode":"M12 6FA",
    "sg:province":"Greater Manchester",
    "sg:tags":[
        "import",
        "export",
        "agent"
    ],
    "wof:name":"A.T.L Spektrum Ventures Ltd",
    "wof:placetype":"venue"
},
  "geometry": {"coordinates":[-2.2182090282,53.4744491577],"type":"Point"}
}