{
  "type": "Feature",
  "properties": {
    "iso:country":"GB",
    "sg:address":"59 Queens Road",
    "sg:city":"Aberdeen",
    "sg:classifiers":[
        {
            "category":"Travel",
            "subcategory":"Hotels & Motels",
            "type":"Entertainment"
        }
    ],
    "sg:phone":"+44 1224 327777",
    "sg:postcode":"AB15 4YP",
    "sg:province":"Aberdeen City",
    "wof:name":"THE SIMPSON TRADING COMPANY LTD",
    "wof:placetype":"venue"
},
  "geometry": {"coordinates":[-2.136673,57.140915],"type":"Point"}
}