{
  "type": "Feature",
  "properties": {
    "addr:full":"1177 Uttoxeter Road Stoke-on-trent Staffordshire ST3 6HJ",
    "addr:housenumber":"1177",
    "addr:postcode":"st3 6hj",
    "addr:street":"Uttoxeter Road",
    "iso:country":"GB",
    "sg:address":"1177 Uttoxeter Road",
    "sg:city":"Stoke-on-trent",
    "sg:classifiers":[
        {
            "category":"Retail",
            "subcategory":"Repair Shop",
            "type":"Services"
        }
    ],
    "sg:phone":"+44 1782 398152",
    "sg:postcode":"ST3 6HJ",
    "sg:province":"Staffordshire",
    "sg:tags":[
        "maintenance"
    ],
    "wof:name":"Geoffrey Lainton",
    "wof:placetype":"venue"
},
  "geometry": {"coordinates":[-2.0871829987,52.9736061096],"type":"Point"}
}