{
  "type": "Feature",
  "properties": {
    "addr:full":"98 Stoke Road Guildford Surrey GU1 4JN",
    "addr:housenumber":"98",
    "addr:postcode":"gu1 4jn",
    "addr:street":"Stoke Road",
    "iso:country":"GB",
    "sg:address":"98 Stoke Road",
    "sg:city":"Guildford",
    "sg:classifiers":[
        {
            "category":"Shopping",
            "subcategory":"News",
            "type":"Retail Goods"
        }
    ],
    "sg:postcode":"GU1 4JN",
    "sg:province":"Surrey",
    "sg:tags":[
        "newsagent"
    ],
    "wof:name":"Condon Stores",
    "wof:placetype":"venue"
},
  "geometry": {"coordinates":[-0.5712760091,51.2423362732],"type":"Point"}
}