{
  "type": "Feature",
  "properties": {
    "iso:country":"GB",
    "sg:address":"Meir Road, Longton",
    "sg:city":"Stoke-on-trent",
    "sg:classifiers":[
        {
            "category":"Manufacturing",
            "subcategory":"Building Materials",
            "type":"Manufacturing & Wholesale Goods"
        }
    ],
    "sg:phone":"+44 1782 599550",
    "sg:postcode":"ST3 7JD",
    "sg:province":"Staffordshire",
    "sg:tags":[
        "merchant",
        "builder"
    ],
    "wof:name":"Norman Rhead (Longton) Ltd.",
    "wof:placetype":"venue"
},
  "geometry": {"coordinates":[-2.116297,52.979553],"type":"Point"}
}