{
  "type": "Feature",
  "properties": {
    "iso:country":"GB",
    "sg:address":"26 Charles Street",
    "sg:city":"Bath",
    "sg:classifiers":[
        {
            "category":"Professional",
            "subcategory":"Lawyer & Legal Services",
            "type":"Services"
        }
    ],
    "sg:phone":"+44 1225 466883",
    "sg:postcode":"BA1 1HU",
    "sg:province":"Bath and North East Somerset",
    "sg:tags":[
        "solicitor"
    ],
    "wof:name":"Anton Bleasdale & Hiatt",
    "wof:placetype":"venue"
},
  "geometry": {"coordinates":[-2.365494,51.382244],"type":"Point"}
}