{
  "type": "Feature",
  "properties": {
    "iso:country":"GB",
    "sg:address":"43 Strand St",
    "sg:city":"Bangor",
    "sg:classifiers":[
        {
            "category":"Bus Charters",
            "type":"Transportation"
        }
    ],
    "sg:phone":"+44 1248 372651",
    "sg:postcode":"LL57 1DH",
    "sg:province":"Gwynedd",
    "sg:tags":[
        "hire",
        "coach"
    ],
    "wof:name":"S.R Williams Private Hire",
    "wof:placetype":"venue"
},
  "geometry": {"coordinates":[-4.117244,53.231724],"type":"Point"}
}