{
  "type": "Feature",
  "properties": {
    "addr:full":"90 Woodlands Rd Redhill Surrey RH1 6HB",
    "addr:housenumber":"90",
    "addr:postcode":"rh1 6hb",
    "addr:street":"Woodlands Rd",
    "iso:country":"GB",
    "sg:address":"90 Woodlands Rd",
    "sg:city":"Redhill",
    "sg:classifiers":[
        {
            "category":"Bars & Pubs",
            "type":"Food & Drink"
        }
    ],
    "sg:phone":"+44 1737 763652",
    "sg:postcode":"RH1 6HB",
    "sg:province":"Surrey",
    "sg:tags":[
        "pubs",
        "inn"
    ],
    "wof:name":"Flying Scud (The)",
    "wof:placetype":"venue"
},
  "geometry": {"coordinates":[-0.174064,51.228058],"type":"Point"}
}