{
  "type": "Feature",
  "properties": {
    "addr:full":"Barbican City Gate, 1-3 Dufferin Street London Greater London EC1Y 8NA",
    "addr:housenumber":"1-3",
    "addr:postcode":"ec1y 8na",
    "addr:street":"Gate;Dufferin Street",
    "iso:country":"GB",
    "sg:address":"Barbican City Gate, 1-3 Dufferin Street",
    "sg:city":"London",
    "sg:classifiers":[
        {
            "category":"Professional",
            "subcategory":"Computer Services",
            "type":"Services"
        }
    ],
    "sg:postcode":"EC1Y 8NA",
    "sg:province":"Greater London",
    "sg:tags":[
        "system",
        "software"
    ],
    "wof:name":"Northdoor Plc",
    "wof:placetype":"venue"
},
  "geometry": {"coordinates":[-0.0922999978,51.5225105286],"type":"Point"}
}