{
  "type": "Feature",
  "properties": {
    "iso:country":"GB",
    "sg:address":"1 Church Street",
    "sg:city":"Brighton",
    "sg:classifiers":[
        {
            "category":"Bars & Pubs",
            "type":"Food & Drink"
        }
    ],
    "sg:phone":"+44 1273 684951",
    "sg:postcode":"BN1 1UE",
    "sg:province":"East Sussex",
    "sg:tags":[
        "pubs",
        "inn"
    ],
    "wof:name":"The Mashtun",
    "wof:placetype":"venue"
},
  "geometry": {"coordinates":[-0.138105,50.823677],"type":"Point"}
}