{
  "type": "Feature",
  "properties": {
    "addr:full":"177 Stafford St Wolverhampton West Midlands WV1 1NA",
    "addr:housenumber":"177",
    "addr:postcode":"wv1 1na",
    "addr:street":"Stafford St",
    "iso:country":"GB",
    "sg:address":"177 Stafford St",
    "sg:city":"Wolverhampton",
    "sg:classifiers":[
        {
            "category":"Personal",
            "subcategory":"Beauty Salon",
            "type":"Services"
        }
    ],
    "sg:postcode":"WV1 1NA",
    "sg:province":"West Midlands",
    "sg:tags":[
        "unisex",
        "hairdresser"
    ],
    "wof:name":"Turner,Julie,",
    "wof:placetype":"venue"
},
  "geometry": {"coordinates":[-2.1261339188,52.5883140564],"type":"Point"}
}