{
  "type": "Feature",
  "properties": {
    "iso:country":"GB",
    "sg:address":"4 The Pleck, Bidford-on-avon",
    "sg:city":"Alcester",
    "sg:classifiers":[
        {
            "category":"Recreation",
            "subcategory":"Boat Charter",
            "type":"Entertainment"
        }
    ],
    "sg:phone":"+44 1789 773205",
    "sg:postcode":"B50 4BB",
    "sg:province":"Warwickshire",
    "sg:tags":[
        "excursion"
    ],
    "wof:name":"Bidford Boats",
    "wof:placetype":"venue"
},
  "geometry": {"coordinates":[-1.861134,52.163933],"type":"Point"}
}