{
  "type": "Feature",
  "properties": {
    "addr:full":"27 Crescent Avenue Whitby North Yorkshire YO21 3EW",
    "addr:housenumber":"27",
    "addr:postcode":"yo21 3ew",
    "addr:street":"Crescent Avenue",
    "iso:country":"GB",
    "sg:address":"27 Crescent Avenue",
    "sg:city":"Whitby",
    "sg:classifiers":[
        {
            "category":"Travel",
            "subcategory":"Hotels & Motels",
            "type":"Entertainment"
        }
    ],
    "sg:phone":"+44 1947 820073",
    "sg:postcode":"YO21 3EW",
    "sg:province":"North Yorkshire",
    "sg:tags":[
        "house",
        "guest"
    ],
    "wof:name":"Crescent Lodge Hotel",
    "wof:placetype":"venue"
},
  "geometry": {"coordinates":[-0.622163,54.487129],"type":"Point"}
}