{
  "type": "Feature",
  "properties": {
    "iso:country":"GB",
    "sg:address":"122 Carden Avenue",
    "sg:city":"Brighton",
    "sg:classifiers":[
        {
            "category":"Education",
            "subcategory":"School",
            "type":"Public Place"
        }
    ],
    "sg:phone":"+44 1273 556976",
    "sg:postcode":"BN1 8NE",
    "sg:province":"East Sussex",
    "sg:tags":[
        "local",
        "authority"
    ],
    "wof:name":"Carden News",
    "wof:placetype":"venue"
},
  "geometry": {"coordinates":[-0.145737,50.859558],"type":"Point"}
}