{
  "type": "Feature",
  "properties": {
    "addr:full":"Sandygate Fen Farm, Horbling Fen Sleaford Lincolnshire NG34 0JX",
    "addr:housenumber":"horbling",
    "addr:postcode":"ng34 0jx",
    "addr:street":"Sandygate Fen;Fen",
    "iso:country":"GB",
    "sg:address":"Sandygate Fen Farm, Horbling Fen",
    "sg:city":"Sleaford",
    "sg:classifiers":[
        {
            "category":"Farming",
            "subcategory":"Farm",
            "type":"Manufacturing & Wholesale Goods"
        }
    ],
    "sg:postcode":"NG34 0JX",
    "sg:province":"Lincolnshire",
    "sg:tags":[
        "mixed",
        "crop"
    ],
    "wof:name":"F J Rickett & Sons",
    "wof:placetype":"venue"
},
  "geometry": {"coordinates":[-0.3380489945,52.9034309387],"type":"Point"}
}