{
  "type": "Feature",
  "properties": {
    "addr:full":"The Dukeries, Whinney Lane Nottingham Nottinghamshire NG22 9TD",
    "addr:postcode":"ng22 9td",
    "addr:street":"Whinney Lane",
    "iso:country":"GB",
    "sg:address":"The Dukeries, Whinney Lane",
    "sg:city":"Nottingham",
    "sg:classifiers":[
        {
            "category":"Farming",
            "subcategory":"Nursery",
            "type":"Manufacturing & Wholesale Goods"
        }
    ],
    "sg:postcode":"NG22 9TD",
    "sg:province":"Nottinghamshire",
    "sg:tags":[
        "creche"
    ],
    "wof:name":"Caring for Kids Private Day Nursery",
    "wof:placetype":"venue"
},
  "geometry": {"coordinates":[-1.00071,53.208939],"type":"Point"}
}