{
  "type": "Feature",
  "properties": {
    "addr:full":"Unit 11 Dock Road Industrial, Estate, Connahs Quay Deeside Flintshire CH5 4DS",
    "addr:housenumber":"unit 11",
    "addr:postcode":"ch5 4ds",
    "addr:street":"Dock Road Industrial Estate;Quay",
    "iso:country":"GB",
    "sg:address":"Unit 11 Dock Road Industrial, Estate, Connahs Quay",
    "sg:city":"Deeside",
    "sg:classifiers":[
        {
            "category":"Building & Trades",
            "subcategory":"Construction",
            "type":"Services"
        }
    ],
    "sg:phone":"+44 1244 818228",
    "sg:postcode":"CH5 4DS",
    "sg:province":"Flintshire",
    "sg:tags":[
        "builder"
    ],
    "wof:name":"Edwards Homes Ltd.",
    "wof:placetype":"venue"
},
  "geometry": {"coordinates":[-3.058831,53.220154],"type":"Point"}
}