{
  "type": "Feature",
  "properties": {
    "addr:full":"Primary House, 65 Arlesey Road, Ickleford Hitchin Bedfordshire SG5 3TG",
    "addr:housenumber":"65",
    "addr:postcode":"sg5 3tg",
    "addr:street":"Arlesey Road",
    "iso:country":"GB",
    "sg:address":"Primary House, 65 Arlesey Road, Ickleford",
    "sg:city":"Hitchin",
    "sg:classifiers":[
        {
            "category":"Building & Trades",
            "subcategory":"Plumbing",
            "type":"Services"
        }
    ],
    "sg:phone":"+44 1462 434464",
    "sg:postcode":"SG5 3TG",
    "sg:province":"Bedfordshire",
    "sg:tags":[
        "heating"
    ],
    "wof:name":"Primary Plumbing Services Ltd.",
    "wof:placetype":"venue"
},
  "geometry": {"coordinates":[-0.277445,51.972816],"type":"Point"}
}