{
  "type": "Feature",
  "properties": {
    "addr:full":"9 Langhill Pl Denny Falkirk FK6 5BY",
    "addr:housenumber":"9",
    "addr:postcode":"fk6 5by",
    "addr:street":"Langhill Pl Denny",
    "iso:country":"GB",
    "sg:address":"9 Langhill Pl",
    "sg:city":"Denny",
    "sg:classifiers":[
        {
            "category":"Utilities",
            "subcategory":"Telephone",
            "type":"Services"
        }
    ],
    "sg:phone":"+44 1324 824728",
    "sg:postcode":"FK6 5BY",
    "sg:province":"Falkirk",
    "sg:tags":[
        "telecommunication"
    ],
    "wof:name":"T.E.S.",
    "wof:placetype":"venue"
},
  "geometry": {"coordinates":[-3.921509,56.014839],"type":"Point"}
}