{
  "type": "Feature",
  "properties": {
    "iso:country":"GB",
    "sg:address":"Ridgefield, Station Road",
    "sg:city":"Petersfield",
    "sg:classifiers":[
        {
            "category":"Travel",
            "subcategory":"Hotels & Motels",
            "type":"Entertainment"
        }
    ],
    "sg:postcode":"GU32 3DE",
    "sg:province":"Hampshire",
    "sg:tags":[
        "house",
        "guest"
    ],
    "wof:name":"Ridgefield",
    "wof:placetype":"venue"
},
  "geometry": {"coordinates":[-0.9358260036,51.0037956238],"type":"Point"}
}