{
  "type": "Feature",
  "properties": {
    "iso:country":"GB",
    "sg:address":"2 Cornmarket Street",
    "sg:city":"Torrington",
    "sg:classifiers":[
        {
            "category":"Real Estate",
            "subcategory":"Surveying",
            "type":"Services"
        }
    ],
    "sg:phone":"+44 1805 623920",
    "sg:postcode":"EX38 8EY",
    "sg:province":"Devon",
    "sg:tags":[
        "surveyor",
        "valuer"
    ],
    "wof:name":"Robinson Cooke Est Agency",
    "wof:placetype":"venue"
},
  "geometry": {"coordinates":[-4.1424369812,50.952205658],"type":"Point"}
}