{
  "type": "Feature",
  "properties": {
    "addr:full":"20 Cliffe High Street Lewes East Sussex BN7 2AH",
    "addr:housenumber":"20",
    "addr:postcode":"bn7 2ah",
    "addr:street":"High Street",
    "iso:country":"GB",
    "sg:address":"20 Cliffe High Street",
    "sg:city":"Lewes",
    "sg:classifiers":[
        {
            "category":"Shopping",
            "subcategory":"Antiques",
            "type":"Retail Goods"
        }
    ],
    "sg:postcode":"BN7 2AH",
    "sg:province":"East Sussex",
    "wof:name":"Lewes Antiques Centre",
    "wof:placetype":"venue"
},
  "geometry": {"coordinates":[0.0177839994,50.874382019],"type":"Point"}
}