{
  "type": "Feature",
  "properties": {
    "addr:full":"3 Redwood Place, Peel Park Compass, East Kilbride Glasgow South Lanarkshire G74 5PB",
    "addr:housenumber":"3",
    "addr:postcode":"east;g74 5pb",
    "addr:street":"Redwood Place Peel Park Compass",
    "iso:country":"GB",
    "sg:address":"3 Redwood Place, Peel Park Compass, East Kilbride",
    "sg:city":"Glasgow",
    "sg:classifiers":[
        {
            "category":"Manufacturing",
            "subcategory":"Electronics",
            "type":"Manufacturing & Wholesale Goods"
        },
        {
            "category":"Military Area",
            "subcategory":"Air Force Base",
            "type":"Public Place"
        }
    ],
    "sg:phone":"+44 1355 234111",
    "sg:postcode":"G74 5PB",
    "sg:province":"South Lanarkshire",
    "sg:tags":[
        "manufacture",
        "control",
        "-",
        "component",
        "equipment",
        "electronic"
    ],
    "wof:name":"Fuji Electric (Scotland) Ltd",
    "wof:placetype":"venue"
},
  "geometry": {"coordinates":[-4.2247138023,55.7674942017],"type":"Point"}
}