{
  "type": "Feature",
  "properties": {
    "iso:country":"GB",
    "sg:address":"44 Dundas Street",
    "sg:city":"Edinburgh",
    "sg:classifiers":[
        {
            "category":"Fast Food",
            "type":"Food & Drink"
        }
    ],
    "sg:phone":"+44 131 558 1168",
    "sg:postcode":"EH3 6JN",
    "sg:province":"City of Edinburgh",
    "sg:tags":[
        "away",
        "take"
    ],
    "wof:name":"New Town Food Co",
    "wof:placetype":"venue"
},
  "geometry": {"coordinates":[-3.199667,55.957516],"type":"Point"}
}