{
  "type": "Feature",
  "properties": {
    "addr:full":"The Gate House,peartree La, Utterby Louth Lincolnshire LN11 0XY",
    "addr:postcode":"ln11 0xy",
    "addr:street":"Louth",
    "iso:country":"GB",
    "sg:address":"The Gate House,peartree La, Utterby",
    "sg:city":"Louth",
    "sg:classifiers":[
        {
            "category":"Banks & Credit Unions",
            "subcategory":"Investment Brokerage",
            "type":"Services"
        }
    ],
    "sg:postcode":"LN11 0XY",
    "sg:province":"Lincolnshire",
    "sg:tags":[
        "contractor"
    ],
    "wof:name":"Patchett,Janet,",
    "wof:placetype":"venue"
},
  "geometry": {"coordinates":[-0.031533,53.420769],"type":"Point"}
}