{
  "type": "Feature",
  "properties": {
    "addr:full":"40a Harris Road Bexleyheath Kent DA7 4QD",
    "addr:housenumber":"40a",
    "addr:postcode":"da7 4qd",
    "addr:street":"Harris Road",
    "iso:country":"GB",
    "sg:address":"40a Harris Road",
    "sg:city":"Bexleyheath",
    "sg:classifiers":[
        {
            "category":"Retail",
            "subcategory":"Auto Repair",
            "type":"Services"
        }
    ],
    "sg:postcode":"DA7 4QD",
    "sg:province":"Kent",
    "sg:tags":[
        "modification",
        "garage"
    ],
    "wof:name":"Martin Smith",
    "wof:placetype":"venue"
},
  "geometry": {"coordinates":[0.1378519982,51.4693145752],"type":"Point"}
}