{
  "type": "Feature",
  "properties": {
    "iso:country":"GB",
    "sg:address":"106 Exeter Street",
    "sg:city":"Salisbury",
    "sg:classifiers":[
        {
            "category":"Professional",
            "subcategory":"Testing Lab",
            "type":"Services"
        }
    ],
    "sg:postcode":"SP1 2SF",
    "sg:province":"Wiltshire",
    "sg:tags":[
        "pregnancy"
    ],
    "wof:name":"Salisbury Pregnancy Help Line",
    "wof:placetype":"venue"
},
  "geometry": {"coordinates":[-1.793889,51.063808],"type":"Point"}
}