{
  "type": "Feature",
  "properties": {
    "iso:country":"GB",
    "sg:address":"105 Central Avenue",
    "sg:city":"Welling",
    "sg:classifiers":[
        {
            "category":"Shopping",
            "subcategory":"News",
            "type":"Retail Goods"
        }
    ],
    "sg:phone":"+44 20 8854 2552",
    "sg:postcode":"DA16 3BG",
    "sg:province":"Kent",
    "sg:tags":[
        "newsagent"
    ],
    "wof:name":"T.J News",
    "wof:placetype":"venue"
},
  "geometry": {"coordinates":[0.100823,51.468109],"type":"Point"}
}