{
  "type": "Feature",
  "properties": {
    "iso:country":"GB",
    "sg:address":"Custley Hey",
    "sg:city":"Liverpool",
    "sg:classifiers":[
        {
            "category":"Organizations",
            "subcategory":"Membership Organization",
            "type":"Services"
        }
    ],
    "sg:postcode":"L28 1RN",
    "sg:province":"Merseyside",
    "sg:tags":[
        "club"
    ],
    "wof:name":"The Village Inn",
    "wof:placetype":"venue"
},
  "geometry": {"coordinates":[-2.865169,53.438519],"type":"Point"}
}