{
  "type": "Feature",
  "properties": {
    "iso:country":"GB",
    "sg:address":"236 Merton High Street",
    "sg:city":"London",
    "sg:classifiers":[
        {
            "category":"Travel",
            "subcategory":"Travel Agent",
            "type":"Entertainment"
        }
    ],
    "sg:phone":"+44 20 8540 2226",
    "sg:postcode":"SW19 1AU",
    "sg:province":"Greater London",
    "wof:name":"Air Savers",
    "wof:placetype":"venue"
},
  "geometry": {"coordinates":[-0.192095,51.415764],"type":"Point"}
}