{
  "type": "Feature",
  "properties": {
    "iso:country":"GB",
    "sg:address":"15 West Street",
    "sg:city":"Morecambe",
    "sg:classifiers":[
        {
            "category":"Building & Trades",
            "subcategory":"Construction",
            "type":"Services"
        }
    ],
    "sg:postcode":"LA3 1RB",
    "sg:province":"Lancashire",
    "sg:tags":[
        "window",
        "replacement"
    ],
    "wof:name":"Lancashire Fascias Ltd.",
    "wof:placetype":"venue"
},
  "geometry": {"coordinates":[-2.882842,54.064621],"type":"Point"}
}