{
  "type": "Feature",
  "properties": {
    "addr:full":"2 Commerce Way Middlesbrough North Yorkshire TS6 6UR",
    "addr:housenumber":"2",
    "addr:postcode":"ts6 6ur",
    "addr:street":"Commerce Way",
    "iso:country":"GB",
    "sg:address":"2 Commerce Way",
    "sg:city":"Middlesbrough",
    "sg:classifiers":[
        {
            "category":"Autos & Motor Vehicles",
            "subcategory":"Auto Supplies",
            "type":"Retail Goods"
        }
    ],
    "sg:postcode":"TS6 6UR",
    "sg:province":"North Yorkshire",
    "sg:tags":[
        "tyre"
    ],
    "wof:name":"Autotreads & Accessories Ltd.",
    "wof:placetype":"venue"
},
  "geometry": {"coordinates":[-1.1759610176,54.5702667236],"type":"Point"}
}