{
  "type": "Feature",
  "properties": {
    "addr:full":"The Wardens Flat, Quarry Dene, Henderson Place Bradford West Yorkshire BD6 1PL",
    "addr:postcode":"bd6 1pl",
    "addr:street":"Dene Henderson Place Bradford West",
    "iso:country":"GB",
    "sg:address":"The Wardens Flat, Quarry Dene, Henderson Place",
    "sg:city":"Bradford",
    "sg:classifiers":[
        {
            "category":"Social Services",
            "subcategory":"Adult Care",
            "type":"Services"
        },
        {
            "category":"Social Services",
            "subcategory":"Retirement Home",
            "type":"Services"
        }
    ],
    "sg:phone":"+44 1274 720102",
    "sg:postcode":"BD6 1PL",
    "sg:province":"West Yorkshire",
    "sg:tags":[
        "housing",
        "sheltered",
        "accommodation"
    ],
    "wof:name":"Quarry Dene",
    "wof:placetype":"venue"
},
  "geometry": {"coordinates":[-1.7669600248,53.7664909363],"type":"Point"}
}