{
  "type": "Feature",
  "properties": {
    "iso:country":"GB",
    "sg:address":"4 Barnpark Drive",
    "sg:city":"Tillicoultry",
    "sg:classifiers":[
        {
            "category":"Building & Trades",
            "subcategory":"Construction",
            "type":"Services"
        }
    ],
    "sg:phone":"+44 1259 751354",
    "sg:postcode":"FK13 6BZ",
    "sg:province":"Clackmannanshire",
    "sg:tags":[
        "joinery",
        "joiner",
        "carpenter",
        "carpentry"
    ],
    "wof:name":"Ochil Joiners",
    "wof:placetype":"venue"
},
  "geometry": {"coordinates":[-3.7499740124,56.1517829895],"type":"Point"}
}