{
  "type": "Feature",
  "properties": {
    "addr:full":"Dock Rd Birkenhead Merseyside L41 1DN",
    "addr:postcode":"l41 1dn",
    "addr:street":"Dock Rd",
    "iso:country":"GB",
    "sg:address":"Dock Rd",
    "sg:city":"Birkenhead",
    "sg:classifiers":[
        {
            "category":"Home & Garden",
            "subcategory":"Building Materials",
            "type":"Retail Goods"
        }
    ],
    "sg:phone":"+44 151 652 8551",
    "sg:postcode":"L41 1DN",
    "sg:province":"Merseyside",
    "sg:tags":[
        "ready",
        "mixed",
        "concrete"
    ],
    "wof:name":"ARC Northern",
    "wof:placetype":"venue"
},
  "geometry": {"coordinates":[-3.0498819351,53.4090270996],"type":"Point"}
}