{
  "type": "Feature",
  "properties": {
    "addr:full":"Mt Siani Cott, Brawby Malton North Yorkshire YO17 6QA",
    "addr:postcode":"yo17 6qa",
    "addr:street":"Mt;Brawby",
    "iso:country":"GB",
    "sg:address":"Mt Siani Cott, Brawby",
    "sg:city":"Malton",
    "sg:classifiers":[
        {
            "category":"Building & Trades",
            "subcategory":"Construction",
            "type":"Services"
        }
    ],
    "sg:phone":"+44 1653 668485",
    "sg:postcode":"YO17 6QA",
    "sg:province":"North Yorkshire",
    "sg:tags":[
        "welder"
    ],
    "wof:name":"Boyes,S,Welding Services Ltd",
    "wof:placetype":"venue"
},
  "geometry": {"coordinates":[-0.7880430222,54.1468658447],"type":"Point"}
}