{
  "type": "Feature",
  "properties": {
    "addr:full":"121 Mungo Park Rd Rainham Essex RM13 7PP",
    "addr:housenumber":"121",
    "addr:postcode":"rm13 7pp",
    "addr:street":"Mungo Park Rd",
    "iso:country":"GB",
    "sg:address":"121 Mungo Park Rd",
    "sg:city":"Rainham",
    "sg:classifiers":[
        {
            "category":"Shopping",
            "subcategory":"News",
            "type":"Retail Goods"
        }
    ],
    "sg:phone":"+44 1708 555561",
    "sg:postcode":"RM13 7PP",
    "sg:province":"Essex",
    "sg:tags":[
        "newsagent"
    ],
    "wof:name":"Gibbs Newsagents",
    "wof:placetype":"venue"
},
  "geometry": {"coordinates":[0.192627,51.540791],"type":"Point"}
}