{
  "type": "Feature",
  "properties": {
    "iso:country":"GB",
    "sg:address":"9 Victoria Road, Adwick-le-street",
    "sg:city":"Doncaster",
    "sg:classifiers":[
        {
            "category":"Retail",
            "subcategory":"Auto Repair",
            "type":"Services"
        }
    ],
    "sg:postcode":"DN6 7AZ",
    "sg:province":"North Yorkshire",
    "sg:tags":[
        "modification",
        "garage"
    ],
    "wof:name":"R & S Auto Centre",
    "wof:placetype":"venue"
},
  "geometry": {"coordinates":[-1.176148057,53.5741157532],"type":"Point"}
}