{
  "type": "Feature",
  "properties": {
    "addr:full":"37 Coate St London Greater London E2 9AG",
    "addr:housenumber":"37",
    "addr:postcode":"e2 9ag",
    "addr:street":"Coate St",
    "iso:country":"GB",
    "sg:address":"37 Coate St",
    "sg:city":"London",
    "sg:classifiers":[
        {
            "category":"Professional",
            "subcategory":"Printing & Photocopies",
            "type":"Services"
        }
    ],
    "sg:phone":"+44 20 7729 6885",
    "sg:postcode":"E2 9AG",
    "sg:province":"Greater London",
    "sg:tags":[
        "printer"
    ],
    "wof:name":"Dart B F S Printing Services Ltd",
    "wof:placetype":"venue"
},
  "geometry": {"coordinates":[-0.0629829988,51.5320358276],"type":"Point"}
}