{
  "type": "Feature",
  "properties": {
    "addr:full":"Ashby Road, Melbourne Derby Derbyshire DE73 1ES",
    "addr:postcode":"de73 1es",
    "addr:street":"Ashby Road",
    "iso:country":"GB",
    "sg:address":"Ashby Road, Melbourne",
    "sg:city":"Derby",
    "sg:classifiers":[
        {
            "category":"Bars & Pubs",
            "type":"Food & Drink"
        },
        {
            "category":"Restaurant",
            "type":"Food & Drink"
        }
    ],
    "sg:phone":"+44 1332 864949",
    "sg:postcode":"DE73 1ES",
    "sg:province":"Derbyshire",
    "sg:tags":[
        "pubs",
        "inn",
        "indian"
    ],
    "wof:name":"The Melbourne Arms Cuisine India",
    "wof:placetype":"venue"
},
  "geometry": {"coordinates":[-1.407071,52.79892],"type":"Point"}
}