{
  "type": "Feature",
  "properties": {
    "iso:country":"GB",
    "sg:address":"55 Shrivenham Hundred Business P, K, Majors Road",
    "sg:city":"Swindon",
    "sg:classifiers":[
        {
            "category":"Manufacturing",
            "subcategory":"Electronics",
            "type":"Manufacturing & Wholesale Goods"
        }
    ],
    "sg:phone":"+44 1793 780306",
    "sg:postcode":"SN6 8TY",
    "sg:province":"Gloucestershire",
    "sg:tags":[
        "mnfrs",
        "transformer"
    ],
    "wof:name":"T C M Tamani Ltd.",
    "wof:placetype":"venue"
},
  "geometry": {"coordinates":[-1.6466089487,51.6137313843],"type":"Point"}
}