{
  "type": "Feature",
  "properties": {
    "addr:full":"87 St. Georges Rd Brighton East Sussex BN2 1EE",
    "addr:housenumber":"87",
    "addr:postcode":"bn2 1ee",
    "addr:street":"St. Georges Rd",
    "iso:country":"GB",
    "sg:address":"87 St. Georges Rd",
    "sg:city":"Brighton",
    "sg:classifiers":[
        {
            "category":"Shopping",
            "subcategory":"Antiques",
            "type":"Retail Goods"
        }
    ],
    "sg:phone":"+44 1273 602389",
    "sg:postcode":"BN2 1EE",
    "sg:province":"East Sussex",
    "wof:name":"Michael Tidey",
    "wof:placetype":"venue"
},
  "geometry": {"coordinates":[-0.120682,50.81826],"type":"Point"}
}