{
  "type": "Feature",
  "properties": {
    "iso:country":"GB",
    "sg:address":"50 Cliveland Street",
    "sg:city":"Birmingham",
    "sg:classifiers":[
        {
            "category":"Freight",
            "type":"Transportation"
        }
    ],
    "sg:phone":"+44 121 333 4455",
    "sg:postcode":"B19 3SH",
    "sg:province":"West Midlands",
    "sg:tags":[
        "forwarders"
    ],
    "wof:name":"METRO SHIPPING LTD",
    "wof:placetype":"venue"
},
  "geometry": {"coordinates":[-1.8971760273,52.4879493713],"type":"Point"}
}