{
  "type": "Feature",
  "properties": {
    "addr:full":"44 Woodhatch Spinney Coulsdon Surrey CR5 2SU",
    "addr:housenumber":"44",
    "addr:postcode":"cr5 2su",
    "addr:street":"Woodhatch Spinney",
    "iso:country":"GB",
    "sg:address":"44 Woodhatch Spinney",
    "sg:city":"Coulsdon",
    "sg:classifiers":[
        {
            "category":"Professional",
            "subcategory":"Engineering",
            "type":"Services"
        }
    ],
    "sg:phone":"+44 20 8668 5892",
    "sg:postcode":"CR5 2SU",
    "sg:province":"Surrey",
    "sg:tags":[
        "structural",
        "engineer"
    ],
    "wof:name":"Colin Utting and Associates",
    "wof:placetype":"venue"
},
  "geometry": {"coordinates":[-0.131114,51.318546],"type":"Point"}
}