{
  "type": "Feature",
  "properties": {
    "addr:full":"Unit 14 & 19 Willow Court, Crystal Drive Smethwick West Midlands B66 1RD",
    "addr:housenumber":"unit 14 & 19",
    "addr:postcode":"b66 1rd",
    "addr:street":"Willow Court Crystal Drive",
    "iso:country":"GB",
    "sg:address":"Unit 14 & 19 Willow Court, Crystal Drive",
    "sg:city":"Smethwick",
    "sg:classifiers":[
        {
            "category":"Shopping",
            "subcategory":"Department Store",
            "type":"Retail Goods"
        },
        {
            "category":"Professional",
            "type":"Services"
        },
        {
            "category":"Transit Center",
            "subcategory":"Freight",
            "type":"Transportation"
        }
    ],
    "sg:phone":"+44 121 544 4946",
    "sg:postcode":"B66 1RD",
    "sg:province":"West Midlands",
    "sg:tags":[
        "item",
        "collector",
        "display",
        "maker"
    ],
    "wof:name":"Picture Pride Displays Ltd.",
    "wof:placetype":"venue"
},
  "geometry": {"coordinates":[-1.99334,52.5037],"type":"Point"}
}