{
  "type": "Feature",
  "properties": {
    "addr:full":"1 Bramble Cotts, Standon Green End, High Cross Ware Hertfordshire SG11 1BW",
    "addr:housenumber":"1;cotts",
    "addr:postcode":"sg11 1bw",
    "addr:street":"Bramble;Green End High Cross Ware",
    "iso:country":"GB",
    "sg:address":"1 Bramble Cotts, Standon Green End, High Cross",
    "sg:city":"Ware",
    "sg:classifiers":[
        {
            "category":"Real Estate",
            "subcategory":"Surveying",
            "type":"Services"
        }
    ],
    "sg:postcode":"SG11 1BW",
    "sg:province":"Hertfordshire",
    "sg:tags":[
        "building",
        "surveyor"
    ],
    "wof:name":"Martin Bridge Building Surveyors",
    "wof:placetype":"venue"
},
  "geometry": {"coordinates":[-0.0232820008,51.8481941223],"type":"Point"}
}