{
  "type": "Feature",
  "properties": {
    "iso:country":"GB",
    "sg:address":"242a Northolt Road, South Harrow",
    "sg:city":"Harrow",
    "sg:classifiers":[
        {
            "category":"Taxi",
            "type":"Transportation"
        }
    ],
    "sg:phone":"+44 20 8423 8000",
    "sg:postcode":"HA2 8DU",
    "sg:province":"Greater London",
    "sg:tags":[
        "mini",
        "cab"
    ],
    "wof:name":"Classic Cars",
    "wof:placetype":"venue"
},
  "geometry": {"coordinates":[-0.353995,51.564423],"type":"Point"}
}