{
  "type": "Feature",
  "properties": {
    "addr:full":"1 Havant Rd, The Square, Horndean Waterlooville Hampshire PO8 0DB",
    "addr:housenumber":"1",
    "addr:postcode":"po8 0db",
    "addr:street":"Havant Rd",
    "iso:country":"GB",
    "sg:address":"1 Havant Rd, The Square, Horndean",
    "sg:city":"Waterlooville",
    "sg:classifiers":[
        {
            "category":"Banks & Credit Unions",
            "subcategory":"Bank",
            "type":"Services"
        }
    ],
    "sg:phone":"+44 23 9257 1909",
    "sg:postcode":"PO8 0DB",
    "sg:province":"Hampshire",
    "sg:tags":[
        "broker",
        "mortgage"
    ],
    "wof:name":"A & R Mortgage Services Ltd",
    "wof:placetype":"venue"
},
  "geometry": {"coordinates":[-0.995733,50.910908],"type":"Point"}
}