{
  "type": "Feature",
  "properties": {
    "addr:full":"Unit 7 Dukes Road Southampton Hampshire SO14 0SQ",
    "addr:housenumber":"unit 7",
    "addr:postcode":"so14 0sq",
    "addr:street":"Dukes Road",
    "iso:country":"GB",
    "sg:address":"Unit 7 Dukes Road",
    "sg:city":"Southampton",
    "sg:classifiers":[
        {
            "category":"Retail",
            "subcategory":"Auto Repair",
            "type":"Services"
        }
    ],
    "sg:phone":"+44 23 8055 5456",
    "sg:postcode":"SO14 0SQ",
    "sg:province":"Hampshire",
    "sg:tags":[
        "modification",
        "garage"
    ],
    "wof:name":"Automatic Transmission Centre",
    "wof:placetype":"venue"
},
  "geometry": {"coordinates":[-1.3922239542,50.9198493958],"type":"Point"}
}