{
  "type": "Feature",
  "properties": {
    "addr:full":", Bontuchel Ruthin Denbighshire LL15 2DE",
    "addr:postcode":"ll15 2de",
    "iso:country":"GB",
    "sg:address":", Bontuchel",
    "sg:city":"Ruthin",
    "sg:classifiers":[
        {
            "category":"Bars & Pubs",
            "type":"Food & Drink"
        }
    ],
    "sg:phone":"+44 1824 710652",
    "sg:postcode":"LL15 2DE",
    "sg:province":"Denbighshire",
    "sg:tags":[
        "pubs",
        "inn"
    ],
    "wof:name":"Bridge Hotel",
    "wof:placetype":"venue"
},
  "geometry": {"coordinates":[-3.334002018,53.0816345215],"type":"Point"}
}