{
  "type": "Feature",
  "properties": {
    "iso:country":"GB",
    "sg:address":"Hikers Way, Drakes Drive",
    "sg:city":"Aylesbury",
    "sg:classifiers":[
        {
            "category":"Professional",
            "subcategory":"Business Services",
            "type":"Services"
        }
    ],
    "sg:phone":"+44 1844 202657",
    "sg:postcode":"HP18 9RW",
    "sg:province":"Buckinghamshire",
    "sg:tags":[
        "food",
        "import",
        "export",
        "agent"
    ],
    "wof:name":"Chalgrove Wines",
    "wof:placetype":"venue"
},
  "geometry": {"coordinates":[-0.9795600176,51.7649879456],"type":"Point"}
}