{
  "type": "Feature",
  "properties": {
    "addr:full":"Tresawls Road Truro Cornwall TR1 3LF",
    "addr:postcode":"tr1 3lf",
    "addr:street":"Tresawls Road",
    "iso:country":"GB",
    "sg:address":"Tresawls Road",
    "sg:city":"Truro",
    "sg:classifiers":[
        {
            "category":"Food & Beverages",
            "subcategory":"Groceries & Convenience Stores",
            "type":"Retail Goods"
        }
    ],
    "sg:phone":"+44 1872 262366",
    "sg:postcode":"TR1 3LF",
    "sg:province":"Cornwall",
    "wof:name":"Dash News & Food",
    "wof:placetype":"venue"
},
  "geometry": {"coordinates":[-5.0993218422,50.2646560669],"type":"Point"}
}