{
  "type": "Feature",
  "properties": {
    "iso:country":"GB",
    "sg:address":"133 Levenshulme Road",
    "sg:city":"Manchester",
    "sg:classifiers":[
        {
            "category":"Personal",
            "subcategory":"Beauty Salon",
            "type":"Services"
        }
    ],
    "sg:phone":"+44 161 231 2402",
    "sg:postcode":"M18 7NF",
    "sg:province":"Greater Manchester",
    "sg:tags":[
        "unisex",
        "hairdresser"
    ],
    "wof:name":"The Village Barber",
    "wof:placetype":"venue"
},
  "geometry": {"coordinates":[-2.174309,53.456051],"type":"Point"}
}