{
  "type": "Feature",
  "properties": {
    "addr:full":"34b Stockport Road Cheadle Cheshire SK8 2AA",
    "addr:housenumber":"34b",
    "addr:postcode":"sk8 2aa",
    "addr:street":"Stockport Road Cheadle",
    "iso:country":"GB",
    "sg:address":"34b Stockport Road",
    "sg:city":"Cheadle",
    "sg:classifiers":[
        {
            "category":"Professional",
            "subcategory":"Detective & Security Services",
            "type":"Services"
        }
    ],
    "sg:postcode":"SK8 2AA",
    "sg:province":"Cheshire",
    "wof:name":"Secure 3 24 Hour Manned Guarding Ltd.",
    "wof:placetype":"venue"
},
  "geometry": {"coordinates":[-2.210217,53.39513],"type":"Point"}
}