{
  "type": "Feature",
  "properties": {
    "iso:country":"GB",
    "sg:address":"25 Woodcroft Street",
    "sg:city":"Rossendale",
    "sg:classifiers":[
        {
            "category":"Building & Trades",
            "subcategory":"Plumbing",
            "type":"Services"
        }
    ],
    "sg:postcode":"BB4 8LG",
    "sg:province":"Lancashire",
    "sg:tags":[
        "heating"
    ],
    "wof:name":"Birtwistle,Stuart,",
    "wof:placetype":"venue"
},
  "geometry": {"coordinates":[-2.290738,53.71492],"type":"Point"}
}