{
  "type": "Feature",
  "properties": {
    "addr:full":"Sycamore Cottage, Manor Walk, Hanging Houghton Northampton Northamptonshire NN6 9EP",
    "addr:postcode":"northamptonshire nn6 9ep",
    "addr:street":"Manor Walk Hanging",
    "iso:country":"GB",
    "sg:address":"Sycamore Cottage, Manor Walk, Hanging Houghton",
    "sg:city":"Northampton",
    "sg:classifiers":[
        {
            "category":"Home & Garden",
            "subcategory":"Home Furnishings",
            "type":"Retail Goods"
        }
    ],
    "sg:phone":"+44 1604 881661",
    "sg:postcode":"NN6 9EP",
    "sg:province":"Northamptonshire",
    "sg:tags":[
        "furnishers",
        "planner",
        "kitchen"
    ],
    "wof:name":"Camberwell Kitchens",
    "wof:placetype":"venue"
},
  "geometry": {"coordinates":[-0.8932359815,52.3563919067],"type":"Point"}
}