{
  "type": "Feature",
  "properties": {
    "iso:country":"GB",
    "sg:address":"5 Seaforth St",
    "sg:city":"Blyth",
    "sg:classifiers":[
        {
            "category":"Professional",
            "subcategory":"Engineering",
            "type":"Services"
        }
    ],
    "sg:phone":"+44 1670 353748",
    "sg:postcode":"NE24 1AY",
    "sg:province":"Northumberland",
    "sg:tags":[
        "contractor",
        "electrical",
        "engineer"
    ],
    "wof:name":"Solo Electrical",
    "wof:placetype":"venue"
},
  "geometry": {"coordinates":[-1.5103789568,55.1284294128],"type":"Point"}
}