{
  "type": "Feature",
  "properties": {
    "addr:full":"Burrows Road, Skewen Neath Neath Port Talbot SA10 6AB",
    "addr:postcode":"sa10 6ab",
    "addr:street":"Burrows Road",
    "iso:country":"GB",
    "sg:address":"Burrows Road, Skewen",
    "sg:city":"Neath",
    "sg:classifiers":[
        {
            "category":"Bars & Pubs",
            "type":"Food & Drink"
        }
    ],
    "sg:phone":"+44 1792 816326",
    "sg:postcode":"SA10 6AB",
    "sg:province":"Neath Port Talbot",
    "sg:tags":[
        "pubs",
        "inn"
    ],
    "wof:name":"Farmers Arms",
    "wof:placetype":"venue"
},
  "geometry": {"coordinates":[-3.8429739475,51.6610717773],"type":"Point"}
}