{
  "type": "Feature",
  "properties": {
    "addr:full":"17 Roggel Road Canvey Island Essex SS8 7HN",
    "addr:housenumber":"17",
    "addr:postcode":"ss8 7hn",
    "addr:street":"Roggel Road",
    "iso:country":"GB",
    "sg:address":"17 Roggel Road",
    "sg:city":"Canvey Island",
    "sg:classifiers":[
        {
            "category":"Professional",
            "type":"Services"
        }
    ],
    "sg:postcode":"SS8 7HN",
    "sg:province":"Essex",
    "sg:tags":[
        "marine"
    ],
    "wof:name":"Odd Job Marine Services",
    "wof:placetype":"venue"
},
  "geometry": {"coordinates":[0.602376,51.516376],"type":"Point"}
}