{
  "type": "Feature",
  "properties": {
    "iso:country":"GB",
    "sg:address":"Northfield Street Garage, Northfield Street",
    "sg:city":"Worcester",
    "sg:classifiers":[
        {
            "category":"Retail",
            "subcategory":"Auto Repair",
            "type":"Services"
        }
    ],
    "sg:phone":"+44 1905 612271",
    "sg:postcode":"WR1 1NS",
    "sg:province":"Worcestershire",
    "sg:tags":[
        "modification",
        "garage"
    ],
    "wof:name":"Arboretum Motor Services",
    "wof:placetype":"venue"
},
  "geometry": {"coordinates":[-2.218584,52.19875],"type":"Point"}
}