{
  "type": "Feature",
  "properties": {
    "iso:country":"GB",
    "sg:address":"40 The Peacocks Centre",
    "sg:city":"Woking",
    "sg:classifiers":[
        {
            "category":"Shopping",
            "subcategory":"Department Store",
            "type":"Retail Goods"
        },
        {
            "category":"Shopping",
            "subcategory":"Music",
            "type":"Retail Goods"
        }
    ],
    "sg:postcode":"GU21 1GD",
    "sg:province":"Surrey",
    "sg:tags":[
        "record",
        "tape",
        "cd"
    ],
    "wof:name":"T M G U K-Delaware Inc",
    "wof:placetype":"venue"
},
  "geometry": {"coordinates":[-0.5585500002,51.3220748901],"type":"Point"}
}