{
  "type": "Feature",
  "properties": {
    "iso:country":"GB",
    "sg:address":"Unit 3, 6 Queensgate",
    "sg:city":"Huddersfield",
    "sg:classifiers":[
        {
            "category":"Wholesale",
            "subcategory":"Sporting Goods",
            "type":"Manufacturing & Wholesale Goods"
        }
    ],
    "sg:phone":"+44 1484 421300",
    "sg:postcode":"HD1 2RD",
    "sg:province":"West Yorkshire",
    "sg:tags":[
        "mnfr",
        "sport",
        "equipment"
    ],
    "wof:name":"American Golf Discount Centre",
    "wof:placetype":"venue"
},
  "geometry": {"coordinates":[-1.782939,53.642559],"type":"Point"}
}