{
  "type": "Feature",
  "properties": {
    "iso:country":"GB",
    "sg:address":"Eastmond Dental Hospital, Grays Inn Road",
    "sg:city":"London",
    "sg:classifiers":[
        {
            "category":"Organizations",
            "subcategory":"Non-profit Organization",
            "type":"Services"
        }
    ],
    "sg:phone":"+44 20 7837 2193",
    "sg:postcode":"WC1X 8LD",
    "sg:province":"Greater London",
    "sg:tags":[
        "organisation",
        "voluntary",
        "charity"
    ],
    "wof:name":"British Orthodontics Society",
    "wof:placetype":"venue"
},
  "geometry": {"coordinates":[-0.12005,51.52911],"type":"Point"}
}