{
  "type": "Feature",
  "properties": {
    "addr:full":"Tanhouse Lane Indust Est, Dennis Rd Widnes Cheshire WA8 0RR",
    "addr:postcode":"wa8 0rr",
    "addr:street":"Tanhouse Lane;Dennis Rd",
    "iso:country":"GB",
    "sg:address":"Tanhouse Lane Indust Est, Dennis Rd",
    "sg:city":"Widnes",
    "sg:classifiers":[
        {
            "category":"Home & Garden",
            "subcategory":"Building Materials",
            "type":"Retail Goods"
        }
    ],
    "sg:phone":"+44 151 424 5150",
    "sg:postcode":"WA8 0RR",
    "sg:province":"Cheshire",
    "sg:tags":[
        "insulation",
        "installers"
    ],
    "wof:name":"Gyproc Insulation Ltd",
    "wof:placetype":"venue"
},
  "geometry": {"coordinates":[-2.718284,53.366943],"type":"Point"}
}