{
  "type": "Feature",
  "properties": {
    "addr:full":"7-15 Newcastle Avenue Worksop Nottinghamshire S80 1EY",
    "addr:housenumber":"7-15",
    "addr:postcode":"s80 1ey",
    "addr:street":"Newcastle Avenue",
    "iso:country":"GB",
    "sg:address":"7-15 Newcastle Avenue",
    "sg:city":"Worksop",
    "sg:classifiers":[
        {
            "category":"Retail",
            "subcategory":"Auto Repair",
            "type":"Services"
        }
    ],
    "sg:phone":"+44 1909 475124",
    "sg:postcode":"S80 1EY",
    "sg:province":"Nottinghamshire",
    "sg:tags":[
        "modification",
        "garage"
    ],
    "wof:name":"Barratt Motors Ltd.",
    "wof:placetype":"venue"
},
  "geometry": {"coordinates":[-1.1249229908,53.3040351868],"type":"Point"}
}