{
  "type": "Feature",
  "properties": {
    "iso:country":"GB",
    "sg:address":"148 Town Row, West Derby",
    "sg:city":"Liverpool",
    "sg:classifiers":[
        {
            "category":"Fast Food",
            "type":"Food & Drink"
        },
        {
            "category":"Food & Beverages",
            "subcategory":"Bakery",
            "type":"Retail Goods"
        }
    ],
    "sg:phone":"+44 151 228 1104",
    "sg:postcode":"L12 8SN",
    "sg:province":"Merseyside",
    "sg:tags":[
        "away",
        "pizza",
        "meal",
        "outlet",
        "take"
    ],
    "wof:name":"Don Ciccio Pizzeria",
    "wof:placetype":"venue"
},
  "geometry": {"coordinates":[-2.902521,53.428867],"type":"Point"}
}