{
  "type": "Feature",
  "properties": {
    "iso:country":"GB",
    "sg:address":"36 Mountcastle Gardens",
    "sg:city":"Edinburgh",
    "sg:classifiers":[
        {
            "category":"Professional",
            "subcategory":"Art Services",
            "type":"Services"
        }
    ],
    "sg:phone":"+44 131 538 1858",
    "sg:postcode":"EH8 7SS",
    "sg:province":"City of Edinburgh",
    "sg:tags":[
        "photographer"
    ],
    "wof:name":"Davidson Read Associates",
    "wof:placetype":"venue"
},
  "geometry": {"coordinates":[-3.1321640015,55.9525718689],"type":"Point"}
}