{
  "type": "Feature",
  "properties": {
    "addr:full":"244 Green Lane London Greater London SE9 3TL",
    "addr:housenumber":"244",
    "addr:postcode":"se9 3tl",
    "addr:street":"Green Lane",
    "iso:country":"GB",
    "sg:address":"244 Green Lane",
    "sg:city":"London",
    "sg:classifiers":[
        {
            "category":"Personal",
            "subcategory":"Beauty Salon",
            "type":"Services"
        }
    ],
    "sg:phone":"+44 20 8857 3337",
    "sg:postcode":"SE9 3TL",
    "sg:province":"Greater London",
    "sg:tags":[
        "unisex",
        "hairdresser"
    ],
    "wof:name":"Hairways",
    "wof:placetype":"venue"
},
  "geometry": {"coordinates":[0.06321,51.435223],"type":"Point"}
}