{
  "type": "Feature",
  "properties": {
    "addr:full":"Unit 9 Midland Court Nottingham Nottinghamshire NG7 3FH",
    "addr:housenumber":"unit 9",
    "addr:postcode":"ng7 3fh",
    "addr:street":"Midland Court",
    "iso:country":"GB",
    "sg:address":"Unit 9 Midland Court",
    "sg:city":"Nottingham",
    "sg:classifiers":[
        {
            "category":"Shopping",
            "subcategory":"Stationery & Office Supplies",
            "type":"Retail Goods"
        }
    ],
    "sg:phone":"+44 115 978 0091",
    "sg:postcode":"NG7 3FH",
    "sg:province":"Nottinghamshire",
    "wof:name":"Prime Stationery Services",
    "wof:placetype":"venue"
},
  "geometry": {"coordinates":[-1.183851,52.95948],"type":"Point"}
}