{
  "type": "Feature",
  "properties": {
    "iso:country":"GB",
    "sg:address":"County House, 12/13 Sussex Street",
    "sg:city":"Plymouth",
    "sg:classifiers":[
        {
            "category":"Social Services",
            "subcategory":"Job Training",
            "type":"Services"
        }
    ],
    "sg:phone":"+44 1752 256176",
    "sg:postcode":"PL1 2HR",
    "sg:province":"Devon",
    "sg:tags":[
        "translator",
        "interpreter"
    ],
    "wof:name":"Prolingua Language Services Ltd.",
    "wof:placetype":"venue"
},
  "geometry": {"coordinates":[-4.141294,50.367222],"type":"Point"}
}