{
  "type": "Feature",
  "properties": {
    "iso:country":"GB",
    "sg:address":"61a Pembury Road",
    "sg:city":"Tonbridge",
    "sg:classifiers":[
        {
            "category":"Building & Trades",
            "subcategory":"Cleaning & Sanitation",
            "type":"Services"
        }
    ],
    "sg:phone":"+44 1732 358950",
    "sg:postcode":"TN9 2JF",
    "sg:province":"Kent",
    "sg:tags":[
        "cleaner",
        "window"
    ],
    "wof:name":"Ace Cleaning Services",
    "wof:placetype":"venue"
},
  "geometry": {"coordinates":[0.273536,51.187511],"type":"Point"}
}