{
  "type": "Feature",
  "properties": {
    "iso:country":"GB",
    "sg:address":"2a Church Street, Morley",
    "sg:city":"Leeds",
    "sg:classifiers":[
        {
            "category":"Home & Garden",
            "subcategory":"Furniture",
            "type":"Retail Goods"
        }
    ],
    "sg:phone":"+44 113 252 5358",
    "sg:postcode":"LS27 8LY",
    "sg:province":"West Yorkshire",
    "wof:name":"Direct Pine & Beds",
    "wof:placetype":"venue"
},
  "geometry": {"coordinates":[-1.599549,53.750511],"type":"Point"}
}