{
  "type": "Feature",
  "properties": {
    "addr:full":"Ebbw Vale Depot, Festival Dr Ebbw Vale Blaenau Gwent NP3 6XF",
    "addr:postcode":"np3 6xf",
    "addr:street":"Festival Dr Ebbw Vale",
    "iso:country":"GB",
    "sg:address":"Ebbw Vale Depot, Festival Dr",
    "sg:city":"Ebbw Vale",
    "sg:classifiers":[
        {
            "category":"Professional",
            "subcategory":"Business Services",
            "type":"Services"
        }
    ],
    "sg:phone":"+44 1495 350310",
    "sg:postcode":"NP3 6XF",
    "sg:province":"Blaenau Gwent",
    "sg:tags":[
        "distribution"
    ],
    "wof:name":"Welsh Brewers Wales & West",
    "wof:placetype":"venue"
},
  "geometry": {"coordinates":[-3.21468,51.79702],"type":"Point"}
}