{
  "type": "Feature",
  "properties": {
    "addr:full":"North Lodge, The Ridgeway Enfield Greater London EN2 8BE",
    "addr:postcode":"en2 8be",
    "addr:street":"The Ridgeway",
    "iso:country":"GB",
    "sg:address":"North Lodge, The Ridgeway",
    "sg:city":"Enfield",
    "sg:classifiers":[
        {
            "category":"Education",
            "subcategory":"School",
            "type":"Public Place"
        }
    ],
    "sg:phone":"+44 20 8366 0035",
    "sg:postcode":"EN2 8BE",
    "sg:province":"Greater London",
    "sg:tags":[
        "independent",
        "preparatory"
    ],
    "wof:name":"ST JOHNS SENIOR SCHOOL",
    "wof:placetype":"venue"
},
  "geometry": {"coordinates":[-0.1117089987,51.6681785583],"type":"Point"}
}