{
  "type": "Feature",
  "properties": {
    "iso:country":"GB",
    "sg:address":"9 Maple Way, Headley Down",
    "sg:city":"Bordon",
    "sg:classifiers":[
        {
            "category":"Taxi",
            "type":"Transportation"
        },
        {
            "category":"Military Area",
            "subcategory":"Air Force Base",
            "type":"Public Place"
        }
    ],
    "sg:phone":"+44 1730 894658",
    "sg:postcode":"GU35 8AZ",
    "sg:province":"Hampshire",
    "sg:tags":[
        "mini",
        "hire",
        "private",
        "cab"
    ],
    "wof:name":"Forest Cars",
    "wof:placetype":"venue"
},
  "geometry": {"coordinates":[-0.8017879725,51.1221504211],"type":"Point"}
}