{
  "type": "Feature",
  "properties": {
    "addr:full":"Abbey Road, Kirstall Leeds West Yorkshire LS5 3EQ",
    "addr:postcode":"ls5 3eq",
    "addr:street":"Abbey Road Kirstall Leeds West",
    "iso:country":"GB",
    "sg:address":"Abbey Road, Kirstall",
    "sg:city":"Leeds",
    "sg:classifiers":[
        {
            "category":"Retail",
            "subcategory":"Funeral Services",
            "type":"Services"
        }
    ],
    "sg:phone":"+44 113 230 4064",
    "sg:postcode":"LS5 3EQ",
    "sg:province":"West Yorkshire",
    "wof:name":"Co-Op Chapel of Rest",
    "wof:placetype":"venue"
},
  "geometry": {"coordinates":[-1.603669,53.819366],"type":"Point"}
}