{
  "type": "Feature",
  "properties": {
    "addr:full":"Renals Farm, Woodthorpe Loughborough Leicestershire LE12 8UG",
    "addr:postcode":"le12 8ug",
    "iso:country":"GB",
    "sg:address":"Renals Farm, Woodthorpe",
    "sg:city":"Loughborough",
    "sg:classifiers":[
        {
            "category":"Farming",
            "subcategory":"Livestock Farm",
            "type":"Manufacturing & Wholesale Goods"
        }
    ],
    "sg:phone":"+44 1509 263447",
    "sg:postcode":"LE12 8UG",
    "sg:province":"Leicestershire",
    "sg:tags":[
        "others"
    ],
    "wof:name":"Bowlers Of Woodthorpe",
    "wof:placetype":"venue"
},
  "geometry": {"coordinates":[-1.1960309744,52.7520713806],"type":"Point"}
}