{
  "type": "Feature",
  "properties": {
    "addr:full":"P O Box 131 Rochdale Lancashire OL16 4FG",
    "addr:housenumber":"131",
    "addr:postcode":"ol16 4fg",
    "addr:street":"P O Box",
    "iso:country":"GB",
    "sg:address":"P O Box 131",
    "sg:city":"Rochdale",
    "sg:classifiers":[
        {
            "category":"Professional",
            "subcategory":"Business Services",
            "type":"Services"
        }
    ],
    "sg:phone":"+44 161 288 2559",
    "sg:postcode":"OL16 4FG",
    "sg:province":"Lancashire",
    "sg:tags":[
        "trade"
    ],
    "wof:name":"Association Of Lighting Defuser Manufacturers UK",
    "wof:placetype":"venue"
},
  "geometry": {"coordinates":[-2.122784,53.589722],"type":"Point"}
}