{
  "type": "Feature",
  "properties": {
    "addr:full":"6 Bennett St Liversedge West Yorkshire WF15 7ES",
    "addr:housenumber":"6",
    "addr:postcode":"wf15 7es",
    "addr:street":"Bennett St",
    "iso:country":"GB",
    "sg:address":"6 Bennett St",
    "sg:city":"Liversedge",
    "sg:classifiers":[
        {
            "category":"Organizations",
            "subcategory":"Membership Organization",
            "type":"Services"
        }
    ],
    "sg:phone":"+44 1924 402696",
    "sg:postcode":"WF15 7ES",
    "sg:province":"West Yorkshire",
    "sg:tags":[
        "club"
    ],
    "wof:name":"Millbridge Working Mens Club",
    "wof:placetype":"venue"
},
  "geometry": {"coordinates":[-1.6880489588,53.7088394165],"type":"Point"}
}