{
  "type": "Feature",
  "properties": {
    "iso:country":"GB",
    "sg:address":"32 Sheriff Dr",
    "sg:city":"Brierley Hill",
    "sg:classifiers":[
        {
            "category":"Manufacturing",
            "subcategory":"Lumber",
            "type":"Manufacturing & Wholesale Goods"
        },
        {
            "category":"Manufacturing",
            "subcategory":"Building Materials",
            "type":"Manufacturing & Wholesale Goods"
        }
    ],
    "sg:postcode":"DY5 1UX",
    "sg:province":"West Midlands",
    "sg:tags":[
        "merchant",
        "merchants",
        "builder",
        "agent",
        "importer",
        "timber"
    ],
    "wof:name":"Walker,M,B M,",
    "wof:placetype":"venue"
},
  "geometry": {"coordinates":[-2.105021,52.478699],"type":"Point"}
}