{
  "type": "Feature",
  "properties": {
    "addr:full":"The White Hart Hotel, Broad St Launceston Cornwall PL15 8AA",
    "addr:postcode":"pl15 8aa",
    "addr:street":"Broad St",
    "iso:country":"GB",
    "sg:address":"The White Hart Hotel, Broad St",
    "sg:city":"Launceston",
    "sg:classifiers":[
        {
            "category":"Personal",
            "type":"Services"
        }
    ],
    "sg:phone":"+44 1726 891015",
    "sg:postcode":"PL15 8AA",
    "sg:province":"Cornwall",
    "sg:tags":[
        "slimming",
        "product"
    ],
    "wof:name":"Slimming World",
    "wof:placetype":"venue"
},
  "geometry": {"coordinates":[-4.363344,50.636707],"type":"Point"}
}