{
  "type": "Feature",
  "properties": {
    "addr:full":"Park Office, Whelpley Hill Chesham Buckinghamshire HP5 3RJ",
    "addr:postcode":"hp5 3rj",
    "addr:street":"Whelpley Hill",
    "iso:country":"GB",
    "sg:address":"Park Office, Whelpley Hill",
    "sg:city":"Chesham",
    "sg:classifiers":[
        {
            "category":"Manufacturing",
            "subcategory":"Buildings",
            "type":"Manufacturing & Wholesale Goods"
        }
    ],
    "sg:phone":"+44 1442 832640",
    "sg:postcode":"HP5 3RJ",
    "sg:province":"Buckinghamshire",
    "sg:tags":[
        "mobile",
        "home"
    ],
    "wof:name":"Whelpley Hill Park Ltd.",
    "wof:placetype":"venue"
},
  "geometry": {"coordinates":[-0.609333,51.710537],"type":"Point"}
}