{
  "type": "Feature",
  "properties": {
    "iso:country":"GB",
    "sg:address":"34 Burnley Road, Padiham",
    "sg:city":"Burnley",
    "sg:classifiers":[
        {
            "category":"Banks & Credit Unions",
            "subcategory":"Financial Services",
            "type":"Services"
        }
    ],
    "sg:phone":"+44 1282 772123",
    "sg:postcode":"BB12 8BW",
    "sg:province":"Lancashire",
    "sg:tags":[
        "building",
        "society"
    ],
    "wof:name":"Bradford & Bingley Plc",
    "wof:placetype":"venue"
},
  "geometry": {"coordinates":[-2.3138840199,53.8011894226],"type":"Point"}
}