{
  "type": "Feature",
  "properties": {
    "addr:full":"58 Victoria Road Aberdeen Aberdeen City AB11 9DS",
    "addr:housenumber":"58",
    "addr:postcode":"ab11 9ds",
    "addr:street":"Victoria Road",
    "iso:country":"GB",
    "sg:address":"58 Victoria Road",
    "sg:city":"Aberdeen",
    "sg:classifiers":[
        {
            "category":"Retail",
            "subcategory":"Laundry & Dry Cleaning",
            "type":"Services"
        }
    ],
    "sg:phone":"+44 1224 878342",
    "sg:postcode":"AB11 9DS",
    "sg:province":"Aberdeen City",
    "sg:tags":[
        "alteration"
    ],
    "wof:name":"Eden Clean",
    "wof:placetype":"venue"
},
  "geometry": {"coordinates":[-2.088712,57.138069],"type":"Point"}
}