{
  "type": "Feature",
  "properties": {
    "addr:full":"Newsham Grange, Little Newsham Darlington Durham DL2 3QW",
    "addr:postcode":"dl2 3qw",
    "addr:street":"Little",
    "iso:country":"GB",
    "sg:address":"Newsham Grange, Little Newsham",
    "sg:city":"Darlington",
    "sg:classifiers":[
        {
            "category":"Farming",
            "subcategory":"Livestock Farm",
            "type":"Manufacturing & Wholesale Goods"
        }
    ],
    "sg:phone":"+44 1833 660210",
    "sg:postcode":"DL2 3QW",
    "sg:province":"Durham",
    "sg:tags":[
        "others"
    ],
    "wof:name":"M S & C F Parker",
    "wof:placetype":"venue"
},
  "geometry": {"coordinates":[-1.8114769459,54.5548057556],"type":"Point"}
}