{
  "type": "Feature",
  "properties": {
    "iso:country":"GB",
    "sg:address":"155 Victoria Road, Wargrave",
    "sg:city":"Reading",
    "sg:classifiers":[
        {
            "category":"Autos & Motor Vehicles",
            "subcategory":"Motorcycle Sales",
            "type":"Retail Goods"
        }
    ],
    "sg:phone":"+44 118 940 3228",
    "sg:postcode":"RG10 8AH",
    "sg:province":"Berkshire",
    "sg:tags":[
        "chauffeur",
        "driven",
        "car"
    ],
    "wof:name":"Gleneagles Garage",
    "wof:placetype":"venue"
},
  "geometry": {"coordinates":[-0.856816,51.50317],"type":"Point"}
}