{
  "type": "Feature",
  "properties": {
    "iso:country":"GB",
    "sg:address":"14 Neilston Rd",
    "sg:city":"Paisley",
    "sg:classifiers":[
        {
            "category":"Real Estate",
            "subcategory":"Architect",
            "type":"Services"
        }
    ],
    "sg:phone":"+44 141 889 7010",
    "sg:postcode":"PA2 6LN",
    "sg:province":"East Renfrewshire",
    "wof:name":"Arena Architects",
    "wof:placetype":"venue"
},
  "geometry": {"coordinates":[-4.424957,55.838276],"type":"Point"}
}