{
  "type": "Feature",
  "properties": {
    "addr:full":"Albion Lodge, 1 Gloucester Road Cheltenham Gloucestershire GL51 8LN",
    "addr:housenumber":"1",
    "addr:postcode":"gl51 8ln",
    "addr:street":"Gloucester Road",
    "iso:country":"GB",
    "sg:address":"Albion Lodge, 1 Gloucester Road",
    "sg:city":"Cheltenham",
    "sg:classifiers":[
        {
            "category":"Retail",
            "subcategory":"Veterinary Services",
            "type":"Services"
        }
    ],
    "sg:phone":"+44 1242 580709",
    "sg:postcode":"GL51 8LN",
    "sg:province":"Gloucestershire",
    "sg:tags":[
        "surgeon",
        "activity"
    ],
    "wof:name":"Stephen Crickmore Vets",
    "wof:placetype":"venue"
},
  "geometry": {"coordinates":[-2.10027,51.90815],"type":"Point"}
}