{
  "type": "Feature",
  "properties": {
    "iso:country":"GB",
    "sg:address":"Long Acre, Townsend Lane, Donington Le Heath",
    "sg:city":"Coalville",
    "sg:classifiers":[
        {
            "category":"Freight",
            "type":"Transportation"
        }
    ],
    "sg:postcode":"LE67 2GF",
    "sg:province":"Leicestershire",
    "sg:tags":[
        "haulage",
        "road"
    ],
    "wof:name":"Newgem",
    "wof:placetype":"venue"
},
  "geometry": {"coordinates":[-1.379287,52.708664],"type":"Point"}
}