{
  "type": "Feature",
  "properties": {
    "iso:country":"GB",
    "sg:address":"146 Merton High Street, Wimbledon",
    "sg:city":"London",
    "sg:classifiers":[
        {
            "category":"Home & Garden",
            "subcategory":"Carpets & Floor Coverings",
            "type":"Retail Goods"
        }
    ],
    "sg:phone":"+44 1959 574176",
    "sg:postcode":"SW19 1BA",
    "sg:province":"Greater London",
    "sg:tags":[
        "carpets",
        "rug",
        "matting"
    ],
    "wof:name":"C W Iles",
    "wof:placetype":"venue"
},
  "geometry": {"coordinates":[-0.18804,51.415894],"type":"Point"}
}