{
  "type": "Feature",
  "properties": {
    "addr:full":"80 Shakespeare Rd Herne Hill Greater London SE24 0PT",
    "addr:housenumber":"80",
    "addr:postcode":"se24 0pt",
    "addr:street":"Shakespeare Rd",
    "iso:country":"GB",
    "sg:address":"80 Shakespeare Rd",
    "sg:city":"Herne Hill",
    "sg:classifiers":[
        {
            "category":"Shopping",
            "subcategory":"Computers & Home Electronics",
            "type":"Retail Goods"
        }
    ],
    "sg:phone":"+44 20 7207 7776",
    "sg:postcode":"SE24 0PT",
    "sg:province":"Greater London",
    "wof:name":"P.C Doctors",
    "wof:placetype":"venue"
},
  "geometry": {"coordinates":[-0.105625,51.456734],"type":"Point"}
}