{
  "type": "Feature",
  "properties": {
    "addr:full":"1 Chapel Lane, Great Doddington Wellingborough Bedfordshire NN29 7TJ",
    "addr:housenumber":"1",
    "addr:postcode":"nn29 7tj",
    "addr:street":"Chapel Lane",
    "iso:country":"GB",
    "sg:address":"1 Chapel Lane, Great Doddington",
    "sg:city":"Wellingborough",
    "sg:classifiers":[
        {
            "category":"Shopping",
            "subcategory":"Department Store",
            "type":"Retail Goods"
        },
        {
            "category":"Food & Beverages",
            "subcategory":"Groceries & Convenience Stores",
            "type":"Retail Goods"
        }
    ],
    "sg:phone":"+44 1933 223902",
    "sg:postcode":"NN29 7TJ",
    "sg:province":"Bedfordshire",
    "wof:name":"The Village Stores",
    "wof:placetype":"venue"
},
  "geometry": {"coordinates":[-0.7093260288,52.2735710144],"type":"Point"}
}