{
  "type": "Feature",
  "properties": {
    "addr:full":"Service & Parts, 151 Western Road Haywards Heath East Sussex RH16 3LH",
    "addr:housenumber":"151",
    "addr:postcode":"rh16 3lh",
    "addr:street":"Western Road",
    "iso:country":"GB",
    "sg:address":"Service & Parts, 151 Western Road",
    "sg:city":"Haywards Heath",
    "sg:classifiers":[
        {
            "category":"Autos & Motor Vehicles",
            "subcategory":"Automobile Sales",
            "type":"Retail Goods"
        }
    ],
    "sg:phone":"+44 1444 452288",
    "sg:postcode":"RH16 3LH",
    "sg:province":"East Sussex",
    "sg:tags":[
        "car"
    ],
    "wof:name":"Frost Cars of Haywards Heath",
    "wof:placetype":"venue"
},
  "geometry": {"coordinates":[-0.0923879966,50.9991073608],"type":"Point"}
}