{
  "type": "Feature",
  "properties": {
    "addr:full":"Unit 24, Mitchell Road, Womble Barnsley South Yorkshire S73 8HA",
    "addr:housenumber":"unit 24",
    "addr:postcode":"s73 8ha",
    "addr:street":"Mitchell Road;Yorkshire",
    "iso:country":"GB",
    "sg:address":"Unit 24, Mitchell Road, Womble",
    "sg:city":"Barnsley",
    "sg:classifiers":[
        {
            "category":"Retail",
            "subcategory":"Auto Repair",
            "type":"Services"
        }
    ],
    "sg:postcode":"S73 8HA",
    "sg:province":"South Yorkshire",
    "sg:tags":[
        "body",
        "car"
    ],
    "wof:name":"Auto Shine",
    "wof:placetype":"venue"
},
  "geometry": {"coordinates":[-1.412734,53.533466],"type":"Point"}
}