{
  "type": "Feature",
  "properties": {
    "addr:full":"162-164 Abbey Street London Greater London SE1 2AN",
    "addr:housenumber":"162-164",
    "addr:postcode":"se1 2an",
    "addr:street":"Abbey Street",
    "iso:country":"GB",
    "sg:address":"162-164 Abbey Street",
    "sg:city":"London",
    "sg:classifiers":[
        {
            "category":"Professional",
            "subcategory":"Art Services",
            "type":"Services"
        }
    ],
    "sg:phone":"+44 20 7740 1477",
    "sg:postcode":"SE1 2AN",
    "sg:province":"Greater London",
    "sg:tags":[
        "consultant",
        "design"
    ],
    "wof:name":"The Redbird Design Co. Ltd.",
    "wof:placetype":"venue"
},
  "geometry": {"coordinates":[-0.072183,51.498135],"type":"Point"}
}