{
  "type": "Feature",
  "properties": {
    "addr:full":"260 Norwood Road London Greater London SE27 9AJ",
    "addr:housenumber":"260",
    "addr:postcode":"se27 9aj",
    "addr:street":"Norwood Road",
    "iso:country":"GB",
    "sg:address":"260 Norwood Road",
    "sg:city":"London",
    "sg:classifiers":[
        {
            "category":"Food & Beverages",
            "subcategory":"Bakery",
            "type":"Retail Goods"
        }
    ],
    "sg:phone":"+44 20 8670 1199",
    "sg:postcode":"SE27 9AJ",
    "sg:province":"Greater London",
    "sg:tags":[
        "pizza"
    ],
    "wof:name":"Pizza 2 Night",
    "wof:placetype":"venue"
},
  "geometry": {"coordinates":[-0.105512999,51.4372215271],"type":"Point"}
}