{
  "type": "Feature",
  "properties": {
    "addr:full":"5 Newry Walk Bristol City of Bristol BS4 1LU",
    "addr:housenumber":"5",
    "addr:postcode":"bs4 1lu",
    "addr:street":"Newry Walk",
    "iso:country":"GB",
    "sg:address":"5 Newry Walk",
    "sg:city":"Bristol",
    "sg:classifiers":[
        {
            "category":"Building & Trades",
            "subcategory":"Cleaning & Sanitation",
            "type":"Services"
        }
    ],
    "sg:phone":"+44 117 963 2828",
    "sg:postcode":"BS4 1LU",
    "sg:province":"City of Bristol",
    "sg:tags":[
        "cleaner",
        "window"
    ],
    "wof:name":"Knowle Cleaning Services",
    "wof:placetype":"venue"
},
  "geometry": {"coordinates":[-2.584485054,51.4285163879],"type":"Point"}
}