{
  "type": "Feature",
  "properties": {
    "iso:country":"GB",
    "sg:address":"92 Lonsdale Way",
    "sg:city":"Oakham",
    "sg:classifiers":[
        {
            "category":"Building & Trades",
            "subcategory":"Cleaning & Sanitation",
            "type":"Services"
        }
    ],
    "sg:phone":"+44 1572 756369",
    "sg:postcode":"LE15 6LR",
    "sg:province":"Leicestershire",
    "sg:tags":[
        "blast"
    ],
    "wof:name":"Advanced Mobile Blast Cleaning",
    "wof:placetype":"venue"
},
  "geometry": {"coordinates":[-0.744256,52.669132],"type":"Point"}
}