{
  "type": "Feature",
  "properties": {
    "iso:country":"GB",
    "sg:address":"17 Church St",
    "sg:city":"Yeovil",
    "sg:classifiers":[
        {
            "category":"Health Services",
            "subcategory":"Dentist",
            "type":"Services"
        }
    ],
    "sg:phone":"+44 1935 840784",
    "sg:postcode":"BA22 8LN",
    "sg:province":"Dorset",
    "wof:name":"Davis S D",
    "wof:placetype":"venue"
},
  "geometry": {"coordinates":[-2.682019,51.001179],"type":"Point"}
}