{
  "type": "Feature",
  "properties": {
    "addr:full":"49 Upper Brook St Winchester Hampshire SO23 8DG",
    "addr:housenumber":"49",
    "addr:postcode":"so23 8dg",
    "addr:street":"Upper Brook St",
    "iso:country":"GB",
    "sg:address":"49 Upper Brook St",
    "sg:city":"Winchester",
    "sg:classifiers":[
        {
            "category":"Shopping",
            "subcategory":"Stationery & Office Supplies",
            "type":"Retail Goods"
        }
    ],
    "sg:phone":"+44 1962 863611",
    "sg:postcode":"SO23 8DG",
    "sg:province":"Hampshire",
    "wof:name":"Worktown Stationers",
    "wof:placetype":"venue"
},
  "geometry": {"coordinates":[-1.312826,51.06369],"type":"Point"}
}