{
  "type": "Feature",
  "properties": {
    "addr:full":"33 Kingsgate Bridlington East Riding of Yorkshire YO15 3PX",
    "addr:housenumber":"33",
    "addr:postcode":"yo15 3px",
    "addr:street":"Kingsgate Bridlington",
    "iso:country":"GB",
    "sg:address":"33 Kingsgate",
    "sg:city":"Bridlington",
    "sg:classifiers":[
        {
            "category":"Professional",
            "subcategory":"Art Services",
            "type":"Services"
        },
        {
            "category":"Building & Trades",
            "subcategory":"Construction",
            "type":"Services"
        }
    ],
    "sg:phone":"+44 1262 602249",
    "sg:postcode":"YO15 3PX",
    "sg:province":"East Riding of Yorkshire",
    "sg:tags":[
        "decorator",
        "painter"
    ],
    "wof:name":"Graham C Pilling",
    "wof:placetype":"venue"
},
  "geometry": {"coordinates":[-0.2044200003,54.0806617737],"type":"Point"}
}