{
  "type": "Feature",
  "properties": {
    "addr:full":"106 St James Road Northampton Northamptonshire NN5 5LF",
    "addr:housenumber":"106",
    "addr:postcode":"nn5 5lf",
    "addr:street":"St James Road",
    "iso:country":"GB",
    "sg:address":"106 St James Road",
    "sg:city":"Northampton",
    "sg:classifiers":[
        {
            "category":"Insurance",
            "subcategory":"Insurance Agent",
            "type":"Services"
        }
    ],
    "sg:phone":"+44 1604 587097",
    "sg:postcode":"NN5 5LF",
    "sg:province":"Northamptonshire",
    "sg:tags":[
        "broker"
    ],
    "wof:name":"Henderson & Co",
    "wof:placetype":"venue"
},
  "geometry": {"coordinates":[-0.914537,52.238972],"type":"Point"}
}