{
  "type": "Feature",
  "properties": {
    "addr:full":"Lower Road Ipswich Suffolk IP6 9AS",
    "addr:postcode":"ip6 9as",
    "addr:street":"Lower Road",
    "iso:country":"GB",
    "sg:address":"Lower Road",
    "sg:city":"Ipswich",
    "sg:classifiers":[
        {
            "category":"Banks & Credit Unions",
            "subcategory":"Financial Services",
            "type":"Services"
        }
    ],
    "sg:postcode":"IP6 9AS",
    "sg:province":"Suffolk",
    "sg:tags":[
        "adviser"
    ],
    "wof:name":"K G S Insurance Services",
    "wof:placetype":"venue"
},
  "geometry": {"coordinates":[1.1199920177,52.1514434814],"type":"Point"}
}