{
  "type": "Feature",
  "properties": {
    "iso:country":"GB",
    "sg:address":"Navigation House, Mill Gate",
    "sg:city":"Newark",
    "sg:classifiers":[
        {
            "category":"Building & Trades",
            "subcategory":"Construction",
            "type":"Services"
        }
    ],
    "sg:phone":"+44 1636 686606",
    "sg:postcode":"NG24 4TS",
    "sg:province":"Nottinghamshire",
    "sg:tags":[
        "builder"
    ],
    "wof:name":"Boundary Builders",
    "wof:placetype":"venue"
},
  "geometry": {"coordinates":[-0.8158140182,53.0747833252],"type":"Point"}
}