{
  "type": "Feature",
  "properties": {
    "addr:full":"145 Uxbridge Road Hampton Greater London TW12 1BQ",
    "addr:housenumber":"145",
    "addr:postcode":"tw12 1bq",
    "addr:street":"Uxbridge Road",
    "iso:country":"GB",
    "sg:address":"145 Uxbridge Road",
    "sg:city":"Hampton",
    "sg:classifiers":[
        {
            "category":"Professional",
            "subcategory":"Art Services",
            "type":"Services"
        }
    ],
    "sg:phone":"+44 20 8941 4949",
    "sg:postcode":"TW12 1BQ",
    "sg:province":"Greater London",
    "sg:tags":[
        "consultant",
        "design"
    ],
    "wof:name":"Lion Studios Ltd.",
    "wof:placetype":"venue"
},
  "geometry": {"coordinates":[-0.3647989929,51.4286575317],"type":"Point"}
}