{
  "type": "Feature",
  "properties": {
    "iso:country":"GB",
    "sg:address":"Ashwell Farm Ho, Ashwell",
    "sg:city":"Ilminster",
    "sg:classifiers":[
        {
            "category":"Manufacturing",
            "subcategory":"Apparel",
            "type":"Manufacturing & Wholesale Goods"
        }
    ],
    "sg:postcode":"TA19 9DX",
    "sg:province":"Somerset",
    "sg:tags":[
        "garment",
        "designer"
    ],
    "wof:name":"Stafford,Sheena,",
    "wof:placetype":"venue"
},
  "geometry": {"coordinates":[-2.91753,50.928669],"type":"Point"}
}