{
  "type": "Feature",
  "properties": {
    "iso:country":"GB",
    "sg:address":"11 West Walk, Yate",
    "sg:city":"Bristol",
    "sg:classifiers":[
        {
            "category":"Travel",
            "subcategory":"Travel Agent",
            "type":"Entertainment"
        }
    ],
    "sg:phone":"+44 1454 325909",
    "sg:postcode":"BS37 4AX",
    "sg:province":"Gloucestershire",
    "wof:name":"Bakers Dolphin Travel",
    "wof:placetype":"venue"
},
  "geometry": {"coordinates":[-2.4096150398,51.5391998291],"type":"Point"}
}