{
  "type": "Feature",
  "properties": {
    "iso:country":"GB",
    "sg:address":"Beechcroft, North Leigh Lane",
    "sg:city":"Wimborne",
    "sg:classifiers":[
        {
            "category":"Professional",
            "subcategory":"Accounting & Tax Preparation",
            "type":"Services"
        }
    ],
    "sg:phone":"+44 1202 882515",
    "sg:postcode":"BH21 2PN",
    "sg:province":"Dorset",
    "sg:tags":[
        "accountant",
        "activity"
    ],
    "sg:website":"http://www.uk.com",
    "wof:name":"Foskett & Co",
    "wof:placetype":"venue"
},
  "geometry": {"coordinates":[-1.9665789604,50.7985801697],"type":"Point"}
}