{
  "type": "Feature",
  "properties": {
    "addr:full":"27 High St Wellingborough Northamptonshire NN8 4JZ",
    "addr:housenumber":"27",
    "addr:postcode":"nn8 4jz",
    "addr:street":"High St",
    "iso:country":"GB",
    "sg:address":"27 High St",
    "sg:city":"Wellingborough",
    "sg:classifiers":[
        {
            "category":"Shopping",
            "subcategory":"News",
            "type":"Retail Goods"
        }
    ],
    "sg:phone":"+44 1933 223035",
    "sg:postcode":"NN8 4JZ",
    "sg:province":"Northamptonshire",
    "sg:tags":[
        "newsagent"
    ],
    "wof:name":"Lisha Newsagents",
    "wof:placetype":"venue"
},
  "geometry": {"coordinates":[-0.697215,52.303207],"type":"Point"}
}