{
  "type": "Feature",
  "properties": {
    "addr:full":"26 Reigate Road, Hookwood Horley Surrey RH6 0HJ",
    "addr:housenumber":"26",
    "addr:postcode":"rh6 0hj",
    "addr:street":"Reigate Road",
    "iso:country":"GB",
    "sg:address":"26 Reigate Road, Hookwood",
    "sg:city":"Horley",
    "sg:classifiers":[
        {
            "category":"Utilities",
            "subcategory":"Refuse",
            "type":"Services"
        },
        {
            "category":"Wholesale",
            "subcategory":"Scrap",
            "type":"Manufacturing & Wholesale Goods"
        }
    ],
    "sg:phone":"+44 1293 820021",
    "sg:postcode":"RH6 0HJ",
    "sg:province":"Surrey",
    "sg:tags":[
        "skip",
        "hire",
        "waste",
        "metal"
    ],
    "wof:name":"Britaniacrest Recycling Ltd.",
    "wof:placetype":"venue"
},
  "geometry": {"coordinates":[-0.196317,51.187626],"type":"Point"}
}