{
  "type": "Feature",
  "properties": {
    "addr:full":"12 Alexander Stephen House, 91 Holmfauld Road Glasgow Glasgow City G51 4RY",
    "addr:housenumber":"12;91",
    "addr:postcode":"g51 4ry",
    "addr:street":"Alexander;Holmfauld Road",
    "iso:country":"GB",
    "sg:address":"12 Alexander Stephen House, 91 Holmfauld Road",
    "sg:city":"Glasgow",
    "sg:classifiers":[
        {
            "category":"Professional",
            "subcategory":"Detective & Security Services",
            "type":"Services"
        }
    ],
    "sg:phone":"+44 141 445 5728",
    "sg:postcode":"G51 4RY",
    "sg:province":"Glasgow City",
    "wof:name":"Ecosse Northern Securities Ltd.",
    "wof:placetype":"venue"
},
  "geometry": {"coordinates":[-4.33175,55.86647],"type":"Point"}
}