{
  "type": "Feature",
  "properties": {
    "iso:country":"GB",
    "sg:address":"Roman Park, Tame Valley, Insdtl Estate",
    "sg:city":"Tamworth",
    "sg:classifiers":[
        {
            "category":"Professional",
            "subcategory":"Engineering",
            "type":"Services"
        }
    ],
    "sg:postcode":"B77 5DQ",
    "sg:province":"Staffordshire",
    "sg:tags":[
        "engineer",
        "mechanical"
    ],
    "wof:name":"Fluid Solutions & Components Ltd.",
    "wof:placetype":"venue"
},
  "geometry": {"coordinates":[-1.6701660156,52.6086463928],"type":"Point"}
}