{
  "type": "Feature",
  "properties": {
    "addr:full":"32 Wellmeadow Road, Lewisham London Greater London SE13 6TB",
    "addr:housenumber":"32",
    "addr:postcode":"se13 6tb",
    "addr:street":"Wellmeadow Road",
    "iso:country":"GB",
    "sg:address":"32 Wellmeadow Road, Lewisham",
    "sg:city":"London",
    "sg:classifiers":[
        {
            "category":"Building & Trades",
            "subcategory":"Construction",
            "type":"Services"
        }
    ],
    "sg:phone":"+44 20 8698 8826",
    "sg:postcode":"SE13 6TB",
    "sg:province":"Greater London",
    "sg:tags":[
        "builder"
    ],
    "wof:name":"Edward Richards Builders",
    "wof:placetype":"venue"
},
  "geometry": {"coordinates":[-0.000064,51.448414],"type":"Point"}
}