{
  "type": "Feature",
  "properties": {
    "addr:full":"Bridge House, Kirkby Rd, Hemsworth Pontefract West Yorkshire WF9 4BU",
    "addr:postcode":"wf9 4bu",
    "addr:street":"Kirkby Rd",
    "iso:country":"GB",
    "sg:address":"Bridge House, Kirkby Rd, Hemsworth",
    "sg:city":"Pontefract",
    "sg:classifiers":[
        {
            "category":"Building & Trades",
            "subcategory":"Construction",
            "type":"Services"
        }
    ],
    "sg:phone":"+44 1977 615888",
    "sg:postcode":"WF9 4BU",
    "sg:province":"West Yorkshire",
    "sg:tags":[
        "guttering"
    ],
    "wof:name":"Amazon Rainwater Systems",
    "wof:placetype":"venue"
},
  "geometry": {"coordinates":[-1.3504840136,53.6097412109],"type":"Point"}
}