{
  "type": "Feature",
  "properties": {
    "iso:country":"GB",
    "sg:address":"77/83 Maldon Road",
    "sg:city":"Witham",
    "sg:classifiers":[
        {
            "category":"Home & Garden",
            "subcategory":"Home Furnishings",
            "type":"Retail Goods"
        }
    ],
    "sg:phone":"+44 1376 514896",
    "sg:postcode":"CM8 1HP",
    "sg:province":"Essex",
    "sg:tags":[
        "furnishers",
        "planner",
        "kitchen"
    ],
    "wof:name":"Daman of Witham",
    "wof:placetype":"venue"
},
  "geometry": {"coordinates":[0.643237,51.795925],"type":"Point"}
}