{
  "type": "Feature",
  "properties": {
    "iso:country":"GB",
    "sg:address":"Dalmilling Cres",
    "sg:city":"Ayr",
    "sg:classifiers":[
        {
            "category":"Place Of Worship",
            "type":"Public Place"
        }
    ],
    "sg:phone":"+44 1292 265716",
    "sg:postcode":"KA8 0QL",
    "sg:province":"South Ayrshire",
    "wof:name":"Good Shepherd Cathedral",
    "wof:placetype":"venue"
},
  "geometry": {"coordinates":[-4.5998101234,55.4690208435],"type":"Point"}
}