{
  "type": "Feature",
  "properties": {
    "iso:country":"GB",
    "sg:address":"1-3 Harrogate Road",
    "sg:city":"Bradford",
    "sg:classifiers":[
        {
            "category":"Shopping",
            "subcategory":"News",
            "type":"Retail Goods"
        }
    ],
    "sg:postcode":"BD2 3DT",
    "sg:province":"West Yorkshire",
    "sg:tags":[
        "newsagent"
    ],
    "wof:name":"J C Poulter & Co",
    "wof:placetype":"venue"
},
  "geometry": {"coordinates":[-1.7174559832,53.8179397583],"type":"Point"}
}