{
  "type": "Feature",
  "properties": {
    "iso:country":"GB",
    "sg:address":"94 Clifton",
    "sg:city":"York",
    "sg:classifiers":[
        {
            "category":"Food & Beverages",
            "subcategory":"Bakery",
            "type":"Retail Goods"
        }
    ],
    "sg:phone":"+44 1904 628891",
    "sg:postcode":"YO30 6BA",
    "sg:province":"North Yorkshire",
    "sg:tags":[
        "baker"
    ],
    "wof:name":"Lawrie's of York Ltd.",
    "wof:placetype":"venue"
},
  "geometry": {"coordinates":[-1.098099,53.968472],"type":"Point"}
}