{
  "type": "Feature",
  "properties": {
    "addr:full":"Pantymeillion, Pontantwn Kidwelly Carmarthenshire SA17 5HY",
    "addr:postcode":"sa17 5hy",
    "iso:country":"GB",
    "sg:address":"Pantymeillion, Pontantwn",
    "sg:city":"Kidwelly",
    "sg:classifiers":[
        {
            "category":"Farming",
            "subcategory":"Livestock Farm",
            "type":"Manufacturing & Wholesale Goods"
        }
    ],
    "sg:phone":"+44 1269 860553",
    "sg:postcode":"SA17 5HY",
    "sg:province":"Carmarthenshire",
    "sg:tags":[
        "others"
    ],
    "wof:name":"M J Jones",
    "wof:placetype":"venue"
},
  "geometry": {"coordinates":[-4.2638840675,51.7945861816],"type":"Point"}
}