{
  "type": "Feature",
  "properties": {
    "addr:full":"Alleyn House, 23-27 Carlton Crescent Southampton Hampshire SO15 2EU",
    "addr:housenumber":"23-27",
    "addr:postcode":"so15 2eu",
    "addr:street":"Carlton Crescent",
    "iso:country":"GB",
    "sg:address":"Alleyn House, 23-27 Carlton Crescent",
    "sg:city":"Southampton",
    "sg:classifiers":[
        {
            "category":"Real Estate",
            "subcategory":"Real Estate Agent",
            "type":"Services"
        }
    ],
    "sg:phone":"+44 23 8023 3303",
    "sg:postcode":"SO15 2EU",
    "sg:province":"Hampshire",
    "wof:name":"Chesterton",
    "wof:placetype":"venue"
},
  "geometry": {"coordinates":[-1.4047869444,50.9137802124],"type":"Point"}
}