{
  "type": "Feature",
  "properties": {
    "iso:country":"GB",
    "sg:address":"70 High Street",
    "sg:city":"Alton",
    "sg:classifiers":[
        {
            "category":"Military Area",
            "subcategory":"Air Force Base",
            "type":"Public Place"
        }
    ],
    "sg:phone":"+44 1420 877554",
    "sg:postcode":"GU34 1ET",
    "sg:province":"Hampshire",
    "sg:tags":[
        "taxi",
        "hire",
        "private"
    ],
    "wof:name":"Moores Taxis",
    "wof:placetype":"venue"
},
  "geometry": {"coordinates":[-0.9770659804,51.1479606628],"type":"Point"}
}