{
  "type": "Feature",
  "properties": {
    "addr:full":"Manor Farm, East Winch King's Lynn Norfolk PE32 1NH",
    "addr:housenumber":"east winch",
    "addr:postcode":"pe32 1nh",
    "addr:street":"Manor",
    "iso:country":"GB",
    "sg:address":"Manor Farm, East Winch",
    "sg:city":"King's Lynn",
    "sg:classifiers":[
        {
            "category":"Farming",
            "subcategory":"Crops",
            "type":"Manufacturing & Wholesale Goods"
        },
        {
            "category":"Farming",
            "subcategory":"Livestock Farm",
            "type":"Manufacturing & Wholesale Goods"
        }
    ],
    "sg:phone":"+44 1553 840276",
    "sg:postcode":"PE32 1NH",
    "sg:province":"Norfolk",
    "sg:tags":[
        "arable",
        "others"
    ],
    "wof:name":"A R Wilson Ltd.",
    "wof:placetype":"venue"
},
  "geometry": {"coordinates":[0.49813,52.712292],"type":"Point"}
}