{
  "type": "Feature",
  "properties": {
    "iso:country":"GB",
    "sg:address":"111 Nantwich Road",
    "sg:city":"Crewe",
    "sg:classifiers":[
        {
            "category":"Home & Garden",
            "subcategory":"Hardware",
            "type":"Retail Goods"
        }
    ],
    "sg:phone":"+44 1270 255277",
    "sg:postcode":"CW2 6BA",
    "sg:province":"Cheshire",
    "sg:tags":[
        "retailer",
        "diy"
    ],
    "wof:name":"C Tilley & Sons",
    "wof:placetype":"venue"
},
  "geometry": {"coordinates":[-2.4413061142,53.0883674622],"type":"Point"}
}