{
  "type": "Feature",
  "properties": {
    "iso:country":"GB",
    "sg:address":"P O Box 167",
    "sg:city":"Deal",
    "sg:classifiers":[
        {
            "category":"Professional",
            "subcategory":"Lawyer & Legal Services",
            "type":"Services"
        }
    ],
    "sg:postcode":"CT14 9GB",
    "sg:province":"Kent",
    "sg:tags":[
        "solicitor"
    ],
    "wof:name":"Nelson Roger Solicitor Mental Health Act Advocate",
    "wof:placetype":"venue"
},
  "geometry": {"coordinates":[1.4032349586,51.2231292725],"type":"Point"}
}