{
  "type": "Feature",
  "properties": {
    "addr:full":"Adam Ho, 25 Auchinairn Rd Glasgow East Dunbartonshire G64 1RX",
    "addr:housenumber":"25",
    "addr:postcode":"g64 1rx",
    "addr:street":"Adam;Auchinairn Rd",
    "iso:country":"GB",
    "sg:address":"Adam Ho, 25 Auchinairn Rd",
    "sg:city":"Glasgow",
    "sg:classifiers":[
        {
            "category":"Autos & Motor Vehicles",
            "subcategory":"Auto Supplies",
            "type":"Retail Goods"
        }
    ],
    "sg:postcode":"G64 1RX",
    "sg:province":"East Dunbartonshire",
    "sg:tags":[
        "tyre"
    ],
    "wof:name":"McInally,David,",
    "wof:placetype":"venue"
},
  "geometry": {"coordinates":[-4.22651,55.896999],"type":"Point"}
}