{
  "type": "Feature",
  "properties": {
    "iso:country":"GB",
    "sg:address":"Vicars Cross Road, Vicars Cross",
    "sg:city":"Chester",
    "sg:classifiers":[
        {
            "category":"Manufacturing",
            "subcategory":"Motor Vehicles & Parts",
            "type":"Manufacturing & Wholesale Goods"
        },
        {
            "category":"Retail",
            "subcategory":"Auto Repair",
            "type":"Services"
        }
    ],
    "sg:phone":"+44 1244 310508",
    "sg:postcode":"CH3 5NL",
    "sg:province":"Cheshire",
    "sg:tags":[
        "lacquer",
        "paint",
        "car",
        "supply",
        "garage",
        "modification",
        "manufacturer"
    ],
    "wof:name":"VOLKSAVE",
    "wof:placetype":"venue"
},
  "geometry": {"coordinates":[-2.8550140858,53.193523407],"type":"Point"}
}