{
  "type": "Feature",
  "properties": {
    "addr:full":"1 Barlby Road Selby East Riding of Yorkshire YO8 5AB",
    "addr:housenumber":"1",
    "addr:postcode":"yo8 5ab",
    "addr:street":"Barlby Road",
    "iso:country":"GB",
    "sg:address":"1 Barlby Road",
    "sg:city":"Selby",
    "sg:classifiers":[
        {
            "category":"Wholesale",
            "subcategory":"Machinery & Supplies",
            "type":"Manufacturing & Wholesale Goods"
        }
    ],
    "sg:phone":"+44 1757 210007",
    "sg:postcode":"YO8 5AB",
    "sg:province":"East Riding of Yorkshire",
    "wof:name":"J C M",
    "wof:placetype":"venue"
},
  "geometry": {"coordinates":[-1.063493,53.785717],"type":"Point"}
}