{
  "type": "Feature",
  "properties": {
    "addr:full":"13 Lower Kings Road Berkhamsted Bedfordshire HP4 2AE",
    "addr:housenumber":"13",
    "addr:postcode":"hp4 2ae",
    "addr:street":"Lower Kings Road",
    "iso:country":"GB",
    "sg:address":"13 Lower Kings Road",
    "sg:city":"Berkhamsted",
    "sg:classifiers":[
        {
            "category":"Personal",
            "subcategory":"Beauty Salon",
            "type":"Services"
        }
    ],
    "sg:phone":"+44 1442 862660",
    "sg:postcode":"HP4 2AE",
    "sg:province":"Bedfordshire",
    "sg:tags":[
        "unisex",
        "hairdresser"
    ],
    "wof:name":"Hair by Christopher John Ltd.",
    "wof:placetype":"venue"
},
  "geometry": {"coordinates":[-0.5649579763,51.7612686157],"type":"Point"}
}