{
  "type": "Feature",
  "properties": {
    "addr:full":"55 Lisburne Lane, Offerton Stockport Cheshire SK2 5RG",
    "addr:housenumber":"55",
    "addr:postcode":"sk2 5rg",
    "addr:street":"Lisburne Lane",
    "iso:country":"GB",
    "sg:address":"55 Lisburne Lane, Offerton",
    "sg:city":"Stockport",
    "sg:classifiers":[
        {
            "category":"Home & Garden",
            "subcategory":"Household Appliances",
            "type":"Retail Goods"
        }
    ],
    "sg:phone":"+44 161 487 1015",
    "sg:postcode":"SK2 5RG",
    "sg:province":"Cheshire",
    "sg:tags":[
        "electrical"
    ],
    "wof:name":"Budget Domestics",
    "wof:placetype":"venue"
},
  "geometry": {"coordinates":[-2.1255879402,53.3941230774],"type":"Point"}
}