{
  "type": "Feature",
  "properties": {
    "iso:country":"GB",
    "sg:address":"9 Piele Road",
    "sg:city":"St Helens",
    "sg:classifiers":[
        {
            "category":"Professional",
            "subcategory":"Engineering",
            "type":"Services"
        }
    ],
    "sg:postcode":"WA11 0JZ",
    "sg:province":"Lancashire",
    "sg:tags":[
        "gas",
        "engineer"
    ],
    "wof:name":"Cliff Whitfield Heating & Plumbing",
    "wof:placetype":"venue"
},
  "geometry": {"coordinates":[-2.661012,53.468197],"type":"Point"}
}