{
  "type": "Feature",
  "properties": {
    "iso:country":"GB",
    "sg:address":"69 High Street",
    "sg:city":"Sidcup",
    "sg:classifiers":[
        {
            "category":"Shopping",
            "subcategory":"Florist",
            "type":"Retail Goods"
        }
    ],
    "sg:phone":"+44 20 8300 2433",
    "sg:postcode":"DA14 6DW",
    "sg:province":"Kent",
    "wof:name":"GILLIAN & ROLAND FLORIST",
    "wof:placetype":"venue"
},
  "geometry": {"coordinates":[0.10228,51.426476],"type":"Point"}
}