{
  "type": "Feature",
  "properties": {
    "addr:full":"Easton Lane Winchester Hampshire SO23 7SL",
    "addr:postcode":"so23 7sl",
    "addr:street":"Easton Lane",
    "iso:country":"GB",
    "sg:address":"Easton Lane",
    "sg:city":"Winchester",
    "sg:classifiers":[
        {
            "category":"Autos & Motor Vehicles",
            "subcategory":"Automobile Sales",
            "type":"Retail Goods"
        }
    ],
    "sg:phone":"+44 1962 841222",
    "sg:postcode":"SO23 7SL",
    "sg:province":"Hampshire",
    "sg:tags":[
        "car"
    ],
    "wof:name":"Martins of Winchester",
    "wof:placetype":"venue"
},
  "geometry": {"coordinates":[-1.2941520214,51.0708198547],"type":"Point"}
}