{
  "type": "Feature",
  "properties": {
    "addr:full":"Unit 5 Taylor La Indstl Est Heanor Derbyshire DE75 7TA",
    "addr:housenumber":"unit 5",
    "addr:postcode":"de75 7ta",
    "addr:street":"Taylor La Indstl Est",
    "iso:country":"GB",
    "sg:address":"Unit 5 Taylor La Indstl Est",
    "sg:city":"Heanor",
    "sg:classifiers":[
        {
            "category":"Professional",
            "subcategory":"Engineering",
            "type":"Services"
        }
    ],
    "sg:phone":"+44 1773 533334",
    "sg:postcode":"DE75 7TA",
    "sg:province":"Derbyshire",
    "wof:name":"J & A Engineering",
    "wof:placetype":"venue"
},
  "geometry": {"coordinates":[-1.3655459881,53.0231208801],"type":"Point"}
}