{
  "type": "Feature",
  "properties": {
    "addr:full":"Powder Mill Lane Twickenham Greater London TW2 6EJ",
    "addr:postcode":"tw2 6ej",
    "addr:street":"Powder Mill Lane",
    "iso:country":"GB",
    "sg:address":"Powder Mill Lane",
    "sg:city":"Twickenham",
    "sg:classifiers":[
        {
            "category":"Retail",
            "subcategory":"Funeral Services",
            "type":"Services"
        }
    ],
    "sg:phone":"+44 20 8894 3830",
    "sg:postcode":"TW2 6EJ",
    "sg:province":"Greater London",
    "sg:tags":[
        "cemetery",
        "crematorium"
    ],
    "wof:name":"Heston & Isleworth Cemetery",
    "wof:placetype":"venue"
},
  "geometry": {"coordinates":[-0.378839,51.449535],"type":"Point"}
}