{
  "type": "Feature",
  "properties": {
    "iso:country":"GB",
    "sg:address":"32 Rhosnesni Lane",
    "sg:city":"Wrexham",
    "sg:classifiers":[
        {
            "category":"Personal",
            "subcategory":"Beauty Salon",
            "type":"Services"
        },
        {
            "category":"Personal",
            "subcategory":"Barber",
            "type":"Services"
        }
    ],
    "sg:phone":"+44 1978 262930",
    "sg:postcode":"LL12 7NA",
    "sg:province":"Wrexham",
    "sg:tags":[
        "unisex",
        "hairdresser"
    ],
    "wof:name":"Flickers For Hair",
    "wof:placetype":"venue"
},
  "geometry": {"coordinates":[-2.983364,53.055595],"type":"Point"}
}