{
  "type": "Feature",
  "properties": {
    "iso:country":"GB",
    "sg:address":"Galleys Corner",
    "sg:city":"Braintree",
    "sg:classifiers":[
        {
            "category":"Professional",
            "subcategory":"Business Services",
            "type":"Services"
        }
    ],
    "sg:phone":"+44 1376 343400",
    "sg:postcode":"CM77 7GN",
    "sg:province":"Essex",
    "sg:tags":[
        "fleet",
        "management",
        "vehicle"
    ],
    "wof:name":"Motek (Vehicle Contracts) Ltd.",
    "wof:placetype":"venue"
},
  "geometry": {"coordinates":[0.582148,51.868385],"type":"Point"}
}