{
  "type": "Feature",
  "properties": {
    "addr:full":"Wilson Ho, 72 Richmond Hill Bournemouth Dorset BH2 6LS",
    "addr:housenumber":"72",
    "addr:postcode":"bh2 6ls",
    "addr:street":"Richmond Hill",
    "iso:country":"GB",
    "sg:address":"Wilson Ho, 72 Richmond Hill",
    "sg:city":"Bournemouth",
    "sg:classifiers":[
        {
            "category":"Communications",
            "type":"Services"
        }
    ],
    "sg:phone":"+44 70 0041 4243",
    "sg:postcode":"BH2 6LS",
    "sg:province":"Dorset",
    "sg:tags":[
        "telecommunication"
    ],
    "wof:name":"Personal Number Co The",
    "wof:placetype":"venue"
},
  "geometry": {"coordinates":[-1.880916,50.720406],"type":"Point"}
}