{
  "type": "Feature",
  "properties": {
    "iso:country":"GB",
    "sg:address":"74 London Road",
    "sg:city":"Bognor Regis",
    "sg:classifiers":[
        {
            "category":"Professional",
            "subcategory":"Management & Consulting",
            "type":"Services"
        }
    ],
    "sg:postcode":"PO21 1DD",
    "sg:province":"West Sussex",
    "sg:tags":[
        "consultant",
        "business"
    ],
    "wof:name":"Sds Consulting Ltd.",
    "wof:placetype":"venue"
},
  "geometry": {"coordinates":[-0.674147,50.78664],"type":"Point"}
}