{
  "type": "Feature",
  "properties": {
    "addr:full":"20 Windle Rd Doncaster South Yorkshire DN4 0HG",
    "addr:housenumber":"20",
    "addr:postcode":"dn4 0hg",
    "addr:street":"Windle Rd",
    "iso:country":"GB",
    "sg:address":"20 Windle Rd",
    "sg:city":"Doncaster",
    "sg:classifiers":[
        {
            "category":"Building & Trades",
            "subcategory":"Construction",
            "type":"Services"
        }
    ],
    "sg:phone":"+44 1302 853957",
    "sg:postcode":"DN4 0HG",
    "sg:province":"South Yorkshire",
    "sg:tags":[
        "joiner",
        "carpenter"
    ],
    "wof:name":"A1 Joinery Services",
    "wof:placetype":"venue"
},
  "geometry": {"coordinates":[-1.155194,53.514431],"type":"Point"}
}