{
  "type": "Feature",
  "properties": {
    "addr:full":"Bressey Lodge, Bressey Gro, South Woodford London Greater London E18 2HP",
    "addr:postcode":"e18 2hp",
    "addr:street":"Bressey Gro",
    "iso:country":"GB",
    "sg:address":"Bressey Lodge, Bressey Gro, South Woodford",
    "sg:city":"London",
    "sg:classifiers":[
        {
            "category":"Professional",
            "subcategory":"Lawyer & Legal Services",
            "type":"Services"
        }
    ],
    "sg:phone":"+44 20 8530 8198",
    "sg:postcode":"E18 2HP",
    "sg:province":"Greater London",
    "sg:tags":[
        "advice",
        "counselling"
    ],
    "wof:name":"The Phoenix Centre",
    "wof:placetype":"venue"
},
  "geometry": {"coordinates":[0.02123,51.592651],"type":"Point"}
}