{
  "type": "Feature",
  "properties": {
    "addr:full":"17 Anderson Close, Harefield Uxbridge Buckinghamshire UB9 6HF",
    "addr:housenumber":"17",
    "addr:postcode":"ub9 6hf",
    "addr:street":"Anderson Close",
    "iso:country":"GB",
    "sg:address":"17 Anderson Close, Harefield",
    "sg:city":"Uxbridge",
    "sg:classifiers":[
        {
            "category":"Retail",
            "subcategory":"Driving School",
            "type":"Services"
        }
    ],
    "sg:phone":"+44 1895 823710",
    "sg:postcode":"UB9 6HF",
    "sg:province":"Buckinghamshire",
    "wof:name":"Paul R Beevor",
    "wof:placetype":"venue"
},
  "geometry": {"coordinates":[-0.4943540096,51.6074905396],"type":"Point"}
}