{
  "type": "Feature",
  "properties": {
    "iso:country":"GB",
    "sg:address":"7 Rattigan Gardens, Whiteley Fareham",
    "sg:city":"Fareham",
    "sg:classifiers":[
        {
            "category":"Building & Trades",
            "subcategory":"Construction",
            "type":"Services"
        }
    ],
    "sg:phone":"+44 1489 565867",
    "sg:postcode":"PO15 7EA",
    "sg:province":"Hampshire",
    "sg:tags":[
        "decorator",
        "painter"
    ],
    "wof:name":"S.C Hopkins Painters & Decorators",
    "wof:placetype":"venue"
},
  "geometry": {"coordinates":[-1.257619,50.886257],"type":"Point"}
}