{
  "type": "Feature",
  "properties": {
    "addr:full":"28 Queens Rd London Greater London SW19 8LR",
    "addr:housenumber":"28",
    "addr:postcode":"sw19 8lr",
    "addr:street":"Queens Rd",
    "iso:country":"GB",
    "sg:address":"28 Queens Rd",
    "sg:city":"London",
    "sg:classifiers":[
        {
            "category":"Professional",
            "subcategory":"Business Services",
            "type":"Services"
        }
    ],
    "sg:postcode":"SW19 8LR",
    "sg:province":"Greater London",
    "sg:tags":[
        "import",
        "export",
        "agent"
    ],
    "wof:name":"Jubilee Books & Music",
    "wof:placetype":"venue"
},
  "geometry": {"coordinates":[-0.201933,51.422615],"type":"Point"}
}