{
  "type": "Feature",
  "properties": {
    "iso:country":"GB",
    "sg:address":"Sunwin House, Swadford St",
    "sg:city":"Skipton",
    "sg:classifiers":[
        {
            "category":"Manufacturing",
            "subcategory":"Textiles",
            "type":"Manufacturing & Wholesale Goods"
        }
    ],
    "sg:phone":"+44 1756 799472",
    "sg:postcode":"BD23 1UR",
    "sg:province":"Lancashire",
    "sg:tags":[
        "made-up"
    ],
    "wof:name":"Mostyns Ltd",
    "wof:placetype":"venue"
},
  "geometry": {"coordinates":[-2.0172491074,53.9604568481],"type":"Point"}
}