{
  "type": "Feature",
  "properties": {
    "addr:full":"24 Epsom Rd Leatherhead Surrey KT22 8SW",
    "addr:housenumber":"24",
    "addr:postcode":"kt22 8sw",
    "addr:street":"Epsom Rd",
    "iso:country":"GB",
    "sg:address":"24 Epsom Rd",
    "sg:city":"Leatherhead",
    "sg:classifiers":[
        {
            "category":"Health Services",
            "subcategory":"Nursing And Care Facility",
            "type":"Services"
        }
    ],
    "sg:phone":"+44 1372 373135",
    "sg:postcode":"KT22 8SW",
    "sg:province":"Surrey",
    "sg:tags":[
        "home"
    ],
    "wof:name":"Oversley Nursing Home The",
    "wof:placetype":"venue"
},
  "geometry": {"coordinates":[-0.318851,51.298149],"type":"Point"}
}