{
  "type": "Feature",
  "properties": {
    "iso:country":"GB",
    "sg:address":"36 Marlborough Rd",
    "sg:city":"Dorking",
    "sg:classifiers":[
        {
            "category":"Building & Trades",
            "subcategory":"Construction",
            "type":"Services"
        }
    ],
    "sg:phone":"+44 1306 886588",
    "sg:postcode":"RH4 2DJ",
    "sg:province":"Surrey",
    "sg:tags":[
        "decorator",
        "painter"
    ],
    "wof:name":"P Evans",
    "wof:placetype":"venue"
},
  "geometry": {"coordinates":[-0.329886,51.230938],"type":"Point"}
}