{
  "type": "Feature",
  "properties": {
    "addr:full":"101-103 London Road, River Dover Kent CT16 3AA",
    "addr:housenumber":"101-103",
    "addr:postcode":"ct16 3aa",
    "addr:street":"London Road",
    "iso:country":"GB",
    "sg:address":"101-103 London Road, River",
    "sg:city":"Dover",
    "sg:classifiers":[
        {
            "category":"Organizations",
            "subcategory":"Non-profit Organization",
            "type":"Services"
        }
    ],
    "sg:phone":"+44 1304 828575",
    "sg:postcode":"CT16 3AA",
    "sg:province":"Kent",
    "sg:tags":[
        "organisation",
        "voluntary",
        "charity"
    ],
    "wof:name":"Kent Association for the Blind",
    "wof:placetype":"venue"
},
  "geometry": {"coordinates":[1.2747,51.148724],"type":"Point"}
}