{
  "type": "Feature",
  "properties": {
    "addr:full":"Unit B, 7a Station Avenue Coventry Warwickshire CV4 9HR",
    "addr:housenumber":"7a",
    "addr:postcode":"cv4 9hr",
    "addr:street":"Station Avenue",
    "iso:country":"GB",
    "sg:address":"Unit B, 7a Station Avenue",
    "sg:city":"Coventry",
    "sg:classifiers":[
        {
            "category":"Personal",
            "subcategory":"Barber",
            "type":"Services"
        }
    ],
    "sg:phone":"+44 24 7646 6050",
    "sg:postcode":"CV4 9HR",
    "sg:province":"Warwickshire",
    "sg:tags":[
        "men's",
        "hairdresser"
    ],
    "wof:name":"Snippits Barbershop",
    "wof:placetype":"venue"
},
  "geometry": {"coordinates":[-1.5951399803,52.3997802734],"type":"Point"}
}