{
  "type": "Feature",
  "properties": {
    "iso:country":"GB",
    "sg:address":"Henllys Way",
    "sg:city":"Cwmbran",
    "sg:classifiers":[
        {
            "category":"Bars & Pubs",
            "type":"Food & Drink"
        }
    ],
    "sg:phone":"+44 1633 484749",
    "sg:postcode":"NP44 4TP",
    "sg:province":"Monmouthshire",
    "sg:tags":[
        "pubs",
        "inn"
    ],
    "wof:name":"The Blinking Owl",
    "wof:placetype":"venue"
},
  "geometry": {"coordinates":[-3.031644,51.644802],"type":"Point"}
}