{
  "type": "Feature",
  "properties": {
    "iso:country":"GB",
    "sg:address":"Tycerrig, Nantycaws",
    "sg:city":"Carmarthen",
    "sg:classifiers":[
        {
            "category":"Farming",
            "subcategory":"Livestock Farm",
            "type":"Manufacturing & Wholesale Goods"
        }
    ],
    "sg:phone":"+44 1267 238335",
    "sg:postcode":"SA32 8EW",
    "sg:province":"Carmarthenshire",
    "sg:tags":[
        "others"
    ],
    "wof:name":"Angus T Macdonald",
    "wof:placetype":"venue"
},
  "geometry": {"coordinates":[-4.239274,51.841942],"type":"Point"}
}