{
  "type": "Feature",
  "properties": {
    "addr:full":"57 Epsom Road Morden Surrey SM4 5PR",
    "addr:housenumber":"57",
    "addr:postcode":"sm4 5pr",
    "addr:street":"Epsom Road",
    "iso:country":"GB",
    "sg:address":"57 Epsom Road",
    "sg:city":"Morden",
    "sg:classifiers":[
        {
            "category":"Professional",
            "subcategory":"Accounting & Tax Preparation",
            "type":"Services"
        }
    ],
    "sg:postcode":"SM4 5PR",
    "sg:province":"Surrey",
    "sg:tags":[
        "accountant"
    ],
    "wof:name":"Paqua Accountants",
    "wof:placetype":"venue"
},
  "geometry": {"coordinates":[-0.207268,51.388905],"type":"Point"}
}