{
  "type": "Feature",
  "properties": {
    "addr:full":"2 Spences Field Lewes East Sussex BN7 2HH",
    "addr:housenumber":"2",
    "addr:postcode":"bn7 2hh",
    "addr:street":"Spences Field",
    "iso:country":"GB",
    "sg:address":"2 Spences Field",
    "sg:city":"Lewes",
    "sg:classifiers":[
        {
            "category":"Shopping",
            "subcategory":"Department Store",
            "type":"Retail Goods"
        },
        {
            "category":"Professional",
            "subcategory":"Art Services",
            "type":"Services"
        }
    ],
    "sg:phone":"+44 1273 483754",
    "sg:postcode":"BN7 2HH",
    "sg:province":"East Sussex",
    "sg:tags":[
        "decorating",
        "painting"
    ],
    "wof:name":"Eco Organic Paint Supplies",
    "wof:placetype":"venue"
},
  "geometry": {"coordinates":[0.0197069999,50.8807373047],"type":"Point"}
}