{
  "type": "Feature",
  "properties": {
    "addr:full":"44 Tooting High Street London Greater London SW17 0SP",
    "addr:housenumber":"44",
    "addr:postcode":"sw17 0sp",
    "addr:street":"Tooting High Street",
    "iso:country":"GB",
    "sg:address":"44 Tooting High Street",
    "sg:city":"London",
    "sg:classifiers":[
        {
            "category":"Shopping",
            "subcategory":"Shoes",
            "type":"Retail Goods"
        }
    ],
    "sg:phone":"+44 20 8672 2871",
    "sg:postcode":"SW17 0SP",
    "sg:province":"Greater London",
    "sg:tags":[
        "shop"
    ],
    "wof:name":"Barratt Shoes",
    "wof:placetype":"venue"
},
  "geometry": {"coordinates":[-0.1678840071,51.4283599854],"type":"Point"}
}