{
  "type": "Feature",
  "properties": {
    "addr:full":"10 Arndale Centre Eastbourne East Sussex BN21 3NW",
    "addr:housenumber":"10",
    "addr:postcode":"bn21 3nw",
    "addr:street":"Arndale Centre",
    "iso:country":"GB",
    "sg:address":"10 Arndale Centre",
    "sg:city":"Eastbourne",
    "sg:classifiers":[
        {
            "category":"Shopping",
            "subcategory":"Optician",
            "type":"Retail Goods"
        }
    ],
    "sg:phone":"+44 1323 720475",
    "sg:postcode":"BN21 3NW",
    "sg:province":"East Sussex",
    "wof:name":"Dollond & Aitchison",
    "wof:placetype":"venue"
},
  "geometry": {"coordinates":[0.28535,50.766911],"type":"Point"}
}