{
  "type": "Feature",
  "properties": {
    "iso:country":"GB",
    "sg:address":"36 Mount Pleasant, Gowerton",
    "sg:city":"Swansea",
    "sg:classifiers":[
        {
            "category":"Building & Trades",
            "subcategory":"Construction",
            "type":"Services"
        }
    ],
    "sg:phone":"+44 1792 875667",
    "sg:postcode":"SA4 3EN",
    "sg:province":"Carmarthenshire",
    "sg:tags":[
        "builder"
    ],
    "wof:name":"R F Associates",
    "wof:placetype":"venue"
},
  "geometry": {"coordinates":[-4.0423297882,51.6485977173],"type":"Point"}
}