{
  "type": "Feature",
  "properties": {
    "addr:full":"Drip Road Stirling Stirling FK8 1RR",
    "addr:postcode":"fk8 1rr",
    "addr:street":"Drip Road",
    "iso:country":"GB",
    "sg:address":"Drip Road",
    "sg:city":"Stirling",
    "sg:classifiers":[
        {
            "category":"Health Services",
            "subcategory":"Nursing And Care Facility",
            "type":"Services"
        }
    ],
    "sg:phone":"+44 1786 474745",
    "sg:postcode":"FK8 1RR",
    "sg:province":"Stirling",
    "sg:tags":[
        "home"
    ],
    "wof:name":"Forthbank Care Center",
    "wof:placetype":"venue"
},
  "geometry": {"coordinates":[-3.9579739571,56.1315994263],"type":"Point"}
}