{
  "type": "Feature",
  "properties": {
    "addr:full":"5 Bridge Street, Wellesbourne Warwick Warwickshire CV35 9QP",
    "addr:housenumber":"5",
    "addr:postcode":"cv35 9qp",
    "addr:street":"Bridge Street",
    "iso:country":"GB",
    "sg:address":"5 Bridge Street, Wellesbourne",
    "sg:city":"Warwick",
    "sg:classifiers":[
        {
            "category":"Personal",
            "subcategory":"Beauty Salon",
            "type":"Services"
        },
        {
            "category":"Personal",
            "subcategory":"Barber",
            "type":"Services"
        }
    ],
    "sg:phone":"+44 1789 841441",
    "sg:postcode":"CV35 9QP",
    "sg:province":"Warwickshire",
    "sg:tags":[
        "unisex",
        "hairdresser"
    ],
    "wof:name":"Flyntz of Wellesbourne",
    "wof:placetype":"venue"
},
  "geometry": {"coordinates":[-1.594020009,52.1951370239],"type":"Point"}
}