{
  "type": "Feature",
  "properties": {
    "addr:full":"112a New Street, Quarry Bank Brierley Hill West Midlands DY5 2BB",
    "addr:housenumber":"112a",
    "addr:postcode":"dy5 2bb",
    "addr:street":"New Street;Brierley Hill",
    "iso:country":"GB",
    "sg:address":"112a New Street, Quarry Bank",
    "sg:city":"Brierley Hill",
    "sg:classifiers":[
        {
            "category":"Manufacturing",
            "subcategory":"Petroleum Products",
            "type":"Manufacturing & Wholesale Goods"
        }
    ],
    "sg:phone":"+44 121 550 7287",
    "sg:postcode":"DY5 2BB",
    "sg:province":"West Midlands",
    "sg:tags":[
        "double",
        "glazing"
    ],
    "wof:name":"Quarry Bank Glass",
    "wof:placetype":"venue"
},
  "geometry": {"coordinates":[-2.10156703,52.47032547],"type":"Point"}
}