{
  "type": "Feature",
  "properties": {
    "iso:country":"GB",
    "sg:address":"Station Road, Deganwy",
    "sg:city":"Llandudno Junction",
    "sg:classifiers":[
        {
            "category":"Personal",
            "subcategory":"Beauty Salon",
            "type":"Services"
        }
    ],
    "sg:postcode":"LL31 9EJ",
    "sg:province":"Conwy",
    "sg:tags":[
        "unisex",
        "hairdresser"
    ],
    "wof:name":"Townstyle",
    "wof:placetype":"venue"
},
  "geometry": {"coordinates":[-3.8358290195,53.2969818115],"type":"Point"}
}