{
  "type": "Feature",
  "properties": {
    "addr:full":"237 Fulwood Road Sheffield South Yorkshire S10 3BA",
    "addr:housenumber":"237",
    "addr:postcode":"s10 3ba",
    "addr:street":"Fulwood Road",
    "iso:country":"GB",
    "sg:address":"237 Fulwood Road",
    "sg:city":"Sheffield",
    "sg:classifiers":[
        {
            "category":"Food & Beverages",
            "subcategory":"Bakery",
            "type":"Retail Goods"
        }
    ],
    "sg:phone":"+44 114 266 2587",
    "sg:postcode":"S10 3BA",
    "sg:province":"South Yorkshire",
    "sg:tags":[
        "baker"
    ],
    "wof:name":"J S & P G Collins",
    "wof:placetype":"venue"
},
  "geometry": {"coordinates":[-1.501363039,53.377243042],"type":"Point"}
}