{
  "type": "Feature",
  "properties": {
    "addr:full":"Elmbridge Lane Woking Surrey GU22 9AL",
    "addr:postcode":"gu22 9al",
    "addr:street":"Elmbridge Lane",
    "iso:country":"GB",
    "sg:address":"Elmbridge Lane",
    "sg:city":"Woking",
    "sg:classifiers":[
        {
            "category":"Education",
            "subcategory":"School",
            "type":"Public Place"
        }
    ],
    "sg:phone":"+44 1483 729343",
    "sg:postcode":"GU22 9AL",
    "sg:province":"Surrey",
    "sg:tags":[
        "college"
    ],
    "wof:name":"St. John the Baptist Roman Catholic Secondary Scho",
    "wof:placetype":"venue"
},
  "geometry": {"coordinates":[-0.550174,51.308605],"type":"Point"}
}