{
  "type": "Feature",
  "properties": {
    "addr:full":"6 Brookside Terrace Sunderland Tyne and Wear SR2 7RN",
    "addr:housenumber":"6",
    "addr:postcode":"sr2 7rn",
    "addr:street":"Brookside Terrace",
    "iso:country":"GB",
    "sg:address":"6 Brookside Terrace",
    "sg:city":"Sunderland",
    "sg:classifiers":[
        {
            "category":"Travel",
            "subcategory":"Hotels & Motels",
            "type":"Entertainment"
        }
    ],
    "sg:phone":"+44 191 565 6739",
    "sg:postcode":"SR2 7RN",
    "sg:province":"Tyne and Wear",
    "sg:tags":[
        "house",
        "guest"
    ],
    "wof:name":"Brookside Guest House",
    "wof:placetype":"venue"
},
  "geometry": {"coordinates":[-1.389911,54.896591],"type":"Point"}
}