{
  "type": "Feature",
  "properties": {
    "iso:country":"GB",
    "sg:address":"7 Fieldfare Road",
    "sg:city":"Newport",
    "sg:classifiers":[
        {
            "category":"Building & Trades",
            "subcategory":"Plumbing",
            "type":"Services"
        }
    ],
    "sg:phone":"+44 1983 528858",
    "sg:postcode":"PO30 5YB",
    "sg:province":"Isle of Wight",
    "sg:tags":[
        "clearance",
        "drain",
        "sewer",
        "sewar"
    ],
    "wof:name":"1 A Isle Of Wight Drain Flow",
    "wof:placetype":"venue"
},
  "geometry": {"coordinates":[-1.313827,50.694046],"type":"Point"}
}