{
  "type": "Feature",
  "properties": {
    "iso:country":"GB",
    "sg:address":"35 Russells Ride, Cheshunt",
    "sg:city":"Waltham Cross",
    "sg:classifiers":[
        {
            "category":"Retail",
            "subcategory":"Auto Repair",
            "type":"Services"
        }
    ],
    "sg:phone":"+44 1992 423722",
    "sg:postcode":"EN8 8TT",
    "sg:province":"Essex",
    "sg:tags":[
        "modification",
        "garage"
    ],
    "wof:name":"East Herts Mobile Autos",
    "wof:placetype":"venue"
},
  "geometry": {"coordinates":[-0.031681,51.697487],"type":"Point"}
}