{
  "type": "Feature",
  "properties": {
    "iso:country":"GB",
    "sg:address":"2a Jamestown Road",
    "sg:city":"London",
    "sg:classifiers":[
        {
            "category":"Restaurant",
            "type":"Food & Drink"
        }
    ],
    "sg:phone":"+44 20 7284 4730",
    "sg:postcode":"NW1 7BY",
    "sg:province":"Greater London",
    "wof:name":"Glodeal Ltd.",
    "wof:placetype":"venue"
},
  "geometry": {"coordinates":[-0.1444749981,51.5407752991],"type":"Point"}
}