{
  "type": "Feature",
  "properties": {
    "addr:full":"5 Crowther Place, Kirk Merrington Spennymoor Durham DL16 7JL",
    "addr:housenumber":"5",
    "addr:postcode":"dl16 7jl",
    "addr:street":"Crowther Place",
    "iso:country":"GB",
    "sg:address":"5 Crowther Place, Kirk Merrington",
    "sg:city":"Spennymoor",
    "sg:classifiers":[
        {
            "category":"Bars & Pubs",
            "type":"Food & Drink"
        },
        {
            "category":"Community Center",
            "subcategory":"Social",
            "type":"Public Place"
        }
    ],
    "sg:phone":"+44 1388 811598",
    "sg:postcode":"DL16 7JL",
    "sg:province":"Durham",
    "sg:tags":[
        "pubs",
        "house",
        "inn",
        "activity"
    ],
    "wof:name":"Half Moon Inn",
    "wof:placetype":"venue"
},
  "geometry": {"coordinates":[-1.595263,54.677101],"type":"Point"}
}