{
  "type": "Feature",
  "properties": {
    "iso:country":"GB",
    "sg:address":"21 Vance Road",
    "sg:city":"Blackpool",
    "sg:classifiers":[
        {
            "category":"Travel",
            "subcategory":"Hotels & Motels",
            "type":"Entertainment"
        }
    ],
    "sg:phone":"+44 1253 624734",
    "sg:postcode":"FY1 4QD",
    "sg:province":"Lancashire",
    "wof:name":"Westbourne House",
    "wof:placetype":"venue"
},
  "geometry": {"coordinates":[-3.051674,53.813999],"type":"Point"}
}