{
  "type": "Feature",
  "properties": {
    "addr:full":"Carmont House, Crichton Royal Estate, Bankend Road Dumfries Dumfries and Galloway DG1 4UQ",
    "addr:postcode":"dg1 4uq",
    "addr:street":"Royal;Bankend Road",
    "iso:country":"GB",
    "sg:address":"Carmont House, Crichton Royal Estate, Bankend Road",
    "sg:city":"Dumfries",
    "sg:classifiers":[
        {
            "category":"Professional",
            "subcategory":"Management & Consulting",
            "type":"Services"
        }
    ],
    "sg:phone":"+44 1387 247010",
    "sg:postcode":"DG1 4UQ",
    "sg:province":"Dumfries and Galloway",
    "sg:tags":[
        "conservation"
    ],
    "wof:name":"Scottish Natural Heritage",
    "wof:placetype":"venue"
},
  "geometry": {"coordinates":[-3.522354,55.001419],"type":"Point"}
}