{
  "type": "Feature",
  "properties": {
    "iso:country":"GB",
    "sg:address":"8 Carter Clo",
    "sg:city":"Oxford",
    "sg:classifiers":[
        {
            "category":"Arts & Performance",
            "subcategory":"Music",
            "type":"Entertainment"
        }
    ],
    "sg:phone":"+44 1865 751130",
    "sg:postcode":"OX3 8ES",
    "sg:province":"Oxfordshire",
    "sg:tags":[
        "mobile",
        "disco"
    ],
    "wof:name":"Thames Two Entertainments",
    "wof:placetype":"venue"
},
  "geometry": {"coordinates":[-1.1920859814,51.7572021484],"type":"Point"}
}