{
  "type": "Feature",
  "properties": {
    "iso:country":"GB",
    "sg:address":"Lismore Road",
    "sg:city":"Scarborough",
    "sg:classifiers":[
        {
            "category":"Community Center",
            "type":"Public Place"
        }
    ],
    "sg:phone":"+44 1723 374461",
    "sg:postcode":"YO12 4DD",
    "sg:province":"North Yorkshire",
    "sg:tags":[
        "centre"
    ],
    "wof:name":"Edgehill Community Centre",
    "wof:placetype":"venue"
},
  "geometry": {"coordinates":[-0.416579,54.262829],"type":"Point"}
}