{
  "type": "Feature",
  "properties": {
    "addr:full":"Llandissilio Clynderwen Carmarthenshire SA66 7SU",
    "addr:postcode":"sa66 7su",
    "iso:country":"GB",
    "sg:address":"Llandissilio",
    "sg:city":"Clynderwen",
    "sg:classifiers":[
        {
            "category":"Travel",
            "subcategory":"Hotels & Motels",
            "type":"Entertainment"
        }
    ],
    "sg:postcode":"SA66 7SU",
    "sg:province":"Carmarthenshire",
    "wof:name":"Nantyffin Motel",
    "wof:placetype":"venue"
},
  "geometry": {"coordinates":[-4.72922,51.839973],"type":"Point"}
}