{
  "type": "Feature",
  "properties": {
    "addr:full":"63 Albert Road Colne Lancashire BB8 0BP",
    "addr:housenumber":"63",
    "addr:postcode":"bb8 0bp",
    "addr:street":"Albert Road",
    "iso:country":"GB",
    "sg:address":"63 Albert Road",
    "sg:city":"Colne",
    "sg:classifiers":[
        {
            "category":"Social Services",
            "subcategory":"Adult Care",
            "type":"Services"
        },
        {
            "category":"Community Center",
            "type":"Public Place"
        }
    ],
    "sg:phone":"+44 1282 869073",
    "sg:postcode":"BB8 0BP",
    "sg:province":"Lancashire",
    "sg:tags":[
        "day",
        "centre"
    ],
    "wof:name":"Stanley Villas",
    "wof:placetype":"venue"
},
  "geometry": {"coordinates":[-2.1757800579,53.8556022644],"type":"Point"}
}