{
  "type": "Feature",
  "properties": {
    "addr:full":"74 Stevenson Court, Stevenson Street Aberdeen Aberdeen City AB2 4GU",
    "addr:housenumber":"74",
    "addr:postcode":"ab2 4gu",
    "addr:street":"Stevenson Court Stevenson Street",
    "iso:country":"GB",
    "sg:address":"74 Stevenson Court, Stevenson Street",
    "sg:city":"Aberdeen",
    "sg:classifiers":[
        {
            "category":"Organizations",
            "subcategory":"Non-profit Organization",
            "type":"Services"
        }
    ],
    "sg:phone":"+44 1224 620516",
    "sg:postcode":"AB2 4GU",
    "sg:province":"Aberdeen City",
    "sg:tags":[
        "organisation",
        "voluntary",
        "charity"
    ],
    "wof:name":"Cornerstone Community Care",
    "wof:placetype":"venue"
},
  "geometry": {"coordinates":[-2.10678,57.153931],"type":"Point"}
}