{
  "type": "Feature",
  "properties": {
    "addr:full":"Manor Yard, Lower Manor Road Godalming Surrey GU7 3EG",
    "addr:postcode":"gu7 3eg",
    "addr:street":"Manor;Lower Manor Road",
    "iso:country":"GB",
    "sg:address":"Manor Yard, Lower Manor Road",
    "sg:city":"Godalming",
    "sg:classifiers":[
        {
            "category":"Retail",
            "subcategory":"Auto Repair",
            "type":"Services"
        }
    ],
    "sg:phone":"+44 1483 426526",
    "sg:postcode":"GU7 3EG",
    "sg:province":"Surrey",
    "sg:tags":[
        "car",
        "commercial",
        "upholsterer",
        "vehicle"
    ],
    "wof:name":"J Mussell & Sons",
    "wof:placetype":"venue"
},
  "geometry": {"coordinates":[-0.6055189967,51.1943283081],"type":"Point"}
}