{
  "type": "Feature",
  "properties": {
    "addr:full":"42-44 Rhosddu Road Wrexham Wrexham LL11 2NT",
    "addr:housenumber":"42-44",
    "addr:postcode":"ll11 2nt",
    "addr:street":"Rhosddu Road",
    "iso:country":"GB",
    "sg:address":"42-44 Rhosddu Road",
    "sg:city":"Wrexham",
    "sg:classifiers":[
        {
            "category":"Shopping",
            "subcategory":"Computers & Home Electronics",
            "type":"Retail Goods"
        }
    ],
    "sg:phone":"+44 1978 361666",
    "sg:postcode":"LL11 2NT",
    "sg:province":"Wrexham",
    "wof:name":"Betabyte Computers",
    "wof:placetype":"venue"
},
  "geometry": {"coordinates":[-2.9964189529,53.0520515442],"type":"Point"}
}