{
  "type": "Feature",
  "properties": {
    "addr:full":"26 Cavendish Avenue London Greater London N3 3QN",
    "addr:housenumber":"26",
    "addr:postcode":"n3 3qn",
    "addr:street":"Cavendish Avenue",
    "iso:country":"GB",
    "sg:address":"26 Cavendish Avenue",
    "sg:city":"London",
    "sg:classifiers":[
        {
            "category":"Communications",
            "subcategory":"Radio Station",
            "type":"Services"
        },
        {
            "category":"Arts & Performance",
            "subcategory":"Theater",
            "type":"Entertainment"
        }
    ],
    "sg:phone":"+44 20 8349 0802",
    "sg:postcode":"N3 3QN",
    "sg:province":"Greater London",
    "sg:tags":[
        "theatrical",
        "television",
        "agency",
        "production"
    ],
    "wof:name":"John Newman & Daphne Palmer",
    "wof:placetype":"venue"
},
  "geometry": {"coordinates":[-0.196004,51.595612],"type":"Point"}
}