{
  "type": "Feature",
  "properties": {
    "addr:full":"The Vicarage, Shelsley Avenue Oldbury West Midlands B69 1BG",
    "addr:postcode":"b69 1bg",
    "addr:street":"Shelsley Avenue Oldbury",
    "iso:country":"GB",
    "sg:address":"The Vicarage, Shelsley Avenue",
    "sg:city":"Oldbury",
    "sg:classifiers":[
        {
            "category":"Place Of Worship",
            "type":"Public Place"
        },
        {
            "category":"Organizations",
            "subcategory":"Non-profit Organization",
            "type":"Services"
        }
    ],
    "sg:postcode":"B69 1BG",
    "sg:province":"West Midlands",
    "sg:tags":[
        "charitable",
        "organisation",
        "charity"
    ],
    "wof:name":"ST JAMES CHURCH",
    "wof:placetype":"venue"
},
  "geometry": {"coordinates":[-2.0158450603,52.5037765503],"type":"Point"}
}