{
  "type": "Feature",
  "properties": {
    "addr:full":"150 Homerton High Street London Greater London E9 6AS",
    "addr:housenumber":"150",
    "addr:postcode":"e9 6as",
    "addr:street":"Homerton High Street",
    "iso:country":"GB",
    "sg:address":"150 Homerton High Street",
    "sg:city":"London",
    "sg:classifiers":[
        {
            "category":"Autos & Motor Vehicles",
            "subcategory":"Auto Supplies",
            "type":"Retail Goods"
        },
        {
            "category":"Shopping",
            "type":"Retail Goods"
        }
    ],
    "sg:phone":"+44 20 8985 1239",
    "sg:postcode":"E9 6AS",
    "sg:province":"Greater London",
    "sg:tags":[
        "car",
        "part",
        "accessory"
    ],
    "wof:name":"Kale Motors",
    "wof:placetype":"venue"
},
  "geometry": {"coordinates":[-0.0406819992,51.548866272],"type":"Point"}
}