{
  "type": "Feature",
  "properties": {
    "addr:full":"130 A Godinton Road Ashford Kent TN23 1LJ",
    "addr:housenumber":"130",
    "addr:postcode":"tn23 1lj",
    "addr:street":"A Godinton Road",
    "iso:country":"GB",
    "sg:address":"130 A Godinton Road",
    "sg:city":"Ashford",
    "sg:classifiers":[
        {
            "category":"Professional",
            "subcategory":"Engineering",
            "type":"Services"
        },
        {
            "category":"Building & Trades",
            "subcategory":"Electrical",
            "type":"Services"
        }
    ],
    "sg:phone":"+44 1233 665107",
    "sg:postcode":"TN23 1LJ",
    "sg:province":"Kent",
    "sg:tags":[
        "engineer",
        "electrician",
        "contractor"
    ],
    "wof:name":"Terry Baker Electrical Contractor Ltd",
    "wof:placetype":"venue"
},
  "geometry": {"coordinates":[0.865406,51.149418],"type":"Point"}
}