{
  "type": "Feature",
  "properties": {
    "addr:full":"166 Dundee Street Carnoustie Angus DD7 7QH",
    "addr:housenumber":"166",
    "addr:postcode":"dd7 7qh",
    "addr:street":"Dundee Street",
    "iso:country":"GB",
    "sg:address":"166 Dundee Street",
    "sg:city":"Carnoustie",
    "sg:classifiers":[
        {
            "category":"Personal",
            "subcategory":"Beauty Salon",
            "type":"Services"
        },
        {
            "category":"Personal",
            "subcategory":"Barber",
            "type":"Services"
        }
    ],
    "sg:phone":"+44 1241 859608",
    "sg:postcode":"DD7 7QH",
    "sg:province":"Angus",
    "sg:tags":[
        "unisex",
        "hairdresser"
    ],
    "wof:name":"Corner Hair Studio",
    "wof:placetype":"venue"
},
  "geometry": {"coordinates":[-2.724389,56.500858],"type":"Point"}
}