{
  "type": "Feature",
  "properties": {
    "addr:full":"79 York Street Heywood Lancashire OL10 4NR",
    "addr:housenumber":"79",
    "addr:postcode":"ol10 4nr",
    "addr:street":"York Street",
    "iso:country":"GB",
    "sg:address":"79 York Street",
    "sg:city":"Heywood",
    "sg:classifiers":[
        {
            "category":"Shopping",
            "subcategory":"Department Store",
            "type":"Retail Goods"
        },
        {
            "category":"Sports & Exercise",
            "subcategory":"Sports Center",
            "type":"Entertainment"
        }
    ],
    "sg:phone":"+44 1706 624040",
    "sg:postcode":"OL10 4NR",
    "sg:province":"Lancashire",
    "sg:tags":[
        "shop"
    ],
    "wof:name":"Heywood Sports & Leisure",
    "wof:placetype":"venue"
},
  "geometry": {"coordinates":[-2.2153880596,53.5935592651],"type":"Point"}
}