{
  "type": "Feature",
  "properties": {
    "iso:country":"GB",
    "sg:address":"Nunnery Fields Hospital, George Roche Way",
    "sg:city":"Canterbury",
    "sg:classifiers":[
        {
            "category":"Organizations",
            "subcategory":"Non-profit Organization",
            "type":"Services"
        }
    ],
    "sg:phone":"+44 1227 783002",
    "sg:postcode":"CT1 3LP",
    "sg:province":"Kent",
    "sg:tags":[
        "organisation",
        "voluntary",
        "charity"
    ],
    "wof:name":"Headway",
    "wof:placetype":"venue"
},
  "geometry": {"coordinates":[1.083191,51.273209],"type":"Point"}
}