{
  "type": "Feature",
  "properties": {
    "addr:full":"9 George La Lewisham Greater London SE13 6HQ",
    "addr:housenumber":"9",
    "addr:postcode":"se13 6hq",
    "addr:street":"George La Lewisham",
    "iso:country":"GB",
    "sg:address":"9 George La",
    "sg:city":"Lewisham",
    "sg:classifiers":[
        {
            "category":"Fast Food",
            "type":"Food & Drink"
        }
    ],
    "sg:phone":"+44 20 8694 1745",
    "sg:postcode":"SE13 6HQ",
    "sg:province":"Greater London",
    "sg:tags":[
        "away",
        "take"
    ],
    "wof:name":"Cummin Up Caribbean Take Away",
    "wof:placetype":"venue"
},
  "geometry": {"coordinates":[-0.0154550001,51.4504814148],"type":"Point"}
}