{
  "type": "Feature",
  "properties": {
    "iso:country":"GB",
    "sg:address":"Harford House 101-103 Great, Portland Street,",
    "sg:city":"London",
    "sg:classifiers":[
        {
            "category":"Professional",
            "subcategory":"Art Services",
            "type":"Services"
        },
        {
            "category":"Professional",
            "subcategory":"Computer Services",
            "type":"Services"
        }
    ],
    "sg:phone":"+44 20 7535 5900",
    "sg:postcode":"W1W 6BH",
    "sg:province":"Greater London",
    "sg:tags":[
        "consultant",
        "design",
        "system",
        "software"
    ],
    "wof:name":"Global Corporate Consultants Ltd",
    "wof:placetype":"venue"
},
  "geometry": {"coordinates":[-0.14261,51.519421],"type":"Point"}
}