{
  "type": "Feature",
  "properties": {
    "iso:country":"GB",
    "sg:address":"188 Westmorland Av",
    "sg:city":"Blackpool",
    "sg:classifiers":[
        {
            "category":"Retail",
            "subcategory":"Repair Shop",
            "type":"Services"
        }
    ],
    "sg:phone":"+44 1253 761600",
    "sg:postcode":"FY1 5QW",
    "sg:province":"Lancashire",
    "sg:tags":[
        "maintenance"
    ],
    "wof:name":"L P Whitham & Son",
    "wof:placetype":"venue"
},
  "geometry": {"coordinates":[-3.0360639095,53.811164856],"type":"Point"}
}