{
  "type": "Feature",
  "properties": {
    "addr:full":"5 Campsie Ct Derby Derbyshire DE24 9RF",
    "addr:housenumber":"5",
    "addr:postcode":"de24 9rf",
    "addr:street":"Campsie Ct",
    "iso:country":"GB",
    "sg:address":"5 Campsie Ct",
    "sg:city":"Derby",
    "sg:classifiers":[
        {
            "category":"Building & Trades",
            "subcategory":"Plumbing",
            "type":"Services"
        }
    ],
    "sg:phone":"+44 1332 270918",
    "sg:postcode":"DE24 9RF",
    "sg:province":"Derbyshire",
    "sg:tags":[
        "drain",
        "clearance",
        "sewer"
    ],
    "wof:name":"Aqua",
    "wof:placetype":"venue"
},
  "geometry": {"coordinates":[-1.4968349934,52.878944397],"type":"Point"}
}