{
  "type": "Feature",
  "properties": {
    "iso:country":"GB",
    "sg:address":"The Bury, Church End, Great Canfield",
    "sg:city":"Dunmow",
    "sg:classifiers":[
        {
            "category":"Home & Garden",
            "subcategory":"Garden Supply",
            "type":"Retail Goods"
        },
        {
            "category":"Farming",
            "subcategory":"Livestock Farm",
            "type":"Manufacturing & Wholesale Goods"
        }
    ],
    "sg:phone":"+44 1371 872213",
    "sg:postcode":"CM6 1JS",
    "sg:province":"Essex",
    "sg:tags":[
        "bulb",
        "grower",
        "others"
    ],
    "wof:name":"R E & E J Clarke",
    "wof:placetype":"venue"
},
  "geometry": {"coordinates":[0.3649770021,51.8706130981],"type":"Point"}
}