{
  "type": "Feature",
  "properties": {
    "addr:full":"1 Thorpe Close, North Kensington London Greater London W10 5XL",
    "addr:housenumber":"1",
    "addr:postcode":"w10 5xl",
    "addr:street":"Thorpe Close",
    "iso:country":"GB",
    "sg:address":"1 Thorpe Close, North Kensington",
    "sg:city":"London",
    "sg:classifiers":[
        {
            "category":"Organizations",
            "subcategory":"Non-profit Organization",
            "type":"Services"
        }
    ],
    "sg:phone":"+44 20 8962 5720",
    "sg:postcode":"W10 5XL",
    "sg:province":"Greater London",
    "sg:tags":[
        "organisation",
        "voluntary",
        "charity"
    ],
    "wof:name":"West Way Development Trust",
    "wof:placetype":"venue"
},
  "geometry": {"coordinates":[-0.209056,51.518044],"type":"Point"}
}