{
  "type": "Feature",
  "properties": {
    "addr:full":"16 Sutton Place London Greater London E9 6EH",
    "addr:housenumber":"16",
    "addr:postcode":"e9 6eh",
    "addr:street":"Sutton Place",
    "iso:country":"GB",
    "sg:address":"16 Sutton Place",
    "sg:city":"London",
    "sg:classifiers":[
        {
            "category":"Real Estate",
            "subcategory":"Architect",
            "type":"Services"
        }
    ],
    "sg:phone":"+44 20 8525 9223",
    "sg:postcode":"E9 6EH",
    "sg:province":"Greater London",
    "wof:name":"John Duane Architects",
    "wof:placetype":"venue"
},
  "geometry": {"coordinates":[-0.050719,51.548717],"type":"Point"}
}