{
  "type": "Feature",
  "properties": {
    "iso:country":"GB",
    "sg:address":"Pillar House 113 -115 Bath Road",
    "sg:city":"Cheltenham",
    "sg:classifiers":[
        {
            "category":"Professional",
            "subcategory":"Computer Services",
            "type":"Services"
        }
    ],
    "sg:phone":"+44 1327 860978",
    "sg:postcode":"GL53 7LS",
    "sg:province":"Gloucestershire",
    "sg:tags":[
        "system",
        "software"
    ],
    "wof:name":"Bessans Ltd.",
    "wof:placetype":"venue"
},
  "geometry": {"coordinates":[-2.075833,51.893768],"type":"Point"}
}