{
  "type": "Feature",
  "properties": {
    "iso:country":"GB",
    "sg:address":"19 Hardley Road",
    "sg:city":"Norwich",
    "sg:classifiers":[
        {
            "category":"Taxi",
            "type":"Transportation"
        },
        {
            "category":"Military Area",
            "subcategory":"Air Force Base",
            "type":"Public Place"
        }
    ],
    "sg:phone":"+44 1508 520705",
    "sg:postcode":"NR14 6NF",
    "sg:province":"Norfolk",
    "sg:tags":[
        "mini",
        "hire",
        "private",
        "cab"
    ],
    "wof:name":"Chet Taxis & Mini Bus Service",
    "wof:placetype":"venue"
},
  "geometry": {"coordinates":[1.4830700159,52.5416069031],"type":"Point"}
}