{
  "type": "Feature",
  "properties": {
    "addr:full":"1-2 George Place, Gloucester Road Ross-on-wye Gloucestershire HR9 5BS",
    "addr:housenumber":"1-2",
    "addr:postcode":"hr9 5bs",
    "addr:street":"George Place Gloucester Road",
    "iso:country":"GB",
    "sg:address":"1-2 George Place, Gloucester Road",
    "sg:city":"Ross-on-wye",
    "sg:classifiers":[
        {
            "category":"Professional",
            "subcategory":"Employment Agencies",
            "type":"Services"
        }
    ],
    "sg:phone":"+44 1989 793400",
    "sg:postcode":"HR9 5BS",
    "sg:province":"Gloucestershire",
    "sg:tags":[
        "consultant"
    ],
    "wof:name":"Employment Service Jobcentre",
    "wof:placetype":"venue"
},
  "geometry": {"coordinates":[-2.5835609436,51.9134674072],"type":"Point"}
}