{
  "type": "Feature",
  "properties": {
    "iso:country":"GB",
    "sg:address":"273 Brighton Road",
    "sg:city":"Sutton",
    "sg:classifiers":[
        {
            "category":"Professional",
            "subcategory":"Employment Agencies",
            "type":"Services"
        }
    ],
    "sg:phone":"+44 1753 869992",
    "sg:postcode":"SM2 5SU",
    "sg:province":"Surrey",
    "sg:tags":[
        "consultant",
        "recruitment"
    ],
    "wof:name":"James Wears & Associates Ltd",
    "wof:placetype":"venue"
},
  "geometry": {"coordinates":[-0.197712,51.34388],"type":"Point"}
}