{
  "type": "Feature",
  "properties": {
    "addr:full":"Unit 2 87 Beddington La Croydon Surrey CR0 4TD",
    "addr:housenumber":"unit;87",
    "addr:postcode":"cr0 4td",
    "addr:street":"Beddington La Croydon",
    "iso:country":"GB",
    "sg:address":"Unit 2 87 Beddington La",
    "sg:city":"Croydon",
    "sg:classifiers":[
        {
            "category":"Professional",
            "subcategory":"Printing & Photocopies",
            "type":"Services"
        }
    ],
    "sg:phone":"+44 20 8665 9090",
    "sg:postcode":"CR0 4TD",
    "sg:province":"Surrey",
    "sg:tags":[
        "printer"
    ],
    "wof:name":"Goldhawk Digital Print Ltd",
    "wof:placetype":"venue"
},
  "geometry": {"coordinates":[-0.136939,51.382484],"type":"Point"}
}