{
  "type": "Feature",
  "properties": {
    "iso:country":"GB",
    "sg:address":"2 Rectory Cotts, Donyatt",
    "sg:city":"Ilminster",
    "sg:classifiers":[
        {
            "category":"Building & Trades",
            "subcategory":"Construction",
            "type":"Services"
        }
    ],
    "sg:phone":"+44 1460 53783",
    "sg:postcode":"TA19 0RU",
    "sg:province":"Somerset",
    "sg:tags":[
        "builder"
    ],
    "wof:name":"Bishop Bros",
    "wof:placetype":"venue"
},
  "geometry": {"coordinates":[-2.947083,50.924095],"type":"Point"}
}