{
  "type": "Feature",
  "properties": {
    "addr:full":"Riverside Building, County Hall, Westminster Bridge Road London Greater London SE1 7PB",
    "addr:postcode":"se1 7pb",
    "addr:street":"Westminster Bridge Road",
    "iso:country":"GB",
    "sg:address":"Riverside Building, County Hall, Westminster Bridge Road",
    "sg:city":"London",
    "sg:classifiers":[
        {
            "category":"Travel",
            "subcategory":"Hotels & Motels",
            "type":"Entertainment"
        }
    ],
    "sg:phone":"+44 20 7928 5200",
    "sg:postcode":"SE1 7PB",
    "sg:province":"Greater London",
    "wof:name":"London Marriott Hotel",
    "wof:placetype":"venue"
},
  "geometry": {"coordinates":[-0.1178,51.502232],"type":"Point"}
}