{
  "type": "Feature",
  "properties": {
    "iso:country":"GB",
    "sg:address":"24 Stonehouse Street, Stonehouse",
    "sg:city":"Plymouth",
    "sg:classifiers":[
        {
            "category":"Professional",
            "type":"Services"
        },
        {
            "category":"Home & Garden",
            "subcategory":"Home Furnishings",
            "type":"Retail Goods"
        }
    ],
    "sg:phone":"+44 1752 515555",
    "sg:postcode":"PL1 3PE",
    "sg:province":"Devon",
    "sg:tags":[
        "furnishers",
        "planner",
        "shopfitters",
        "kitchen"
    ],
    "wof:name":"The Weatherhead Group",
    "wof:placetype":"venue"
},
  "geometry": {"coordinates":[-4.1596221924,50.3686294556],"type":"Point"}
}