{
  "type": "Feature",
  "properties": {
    "addr:full":"Hooper Hall, Consort Road London Greater London SE15 2PH",
    "addr:postcode":"se15 2ph",
    "addr:street":"Consort Road",
    "iso:country":"GB",
    "sg:address":"Hooper Hall, Consort Road",
    "sg:city":"London",
    "sg:classifiers":[
        {
            "category":"Education",
            "subcategory":"Preschool",
            "type":"Public Place"
        }
    ],
    "sg:phone":"+44 20 7252 9230",
    "sg:postcode":"SE15 2PH",
    "sg:province":"Greater London",
    "sg:tags":[
        "pre-school",
        "playgroups"
    ],
    "wof:name":"The Orchard Family Centre",
    "wof:placetype":"venue"
},
  "geometry": {"coordinates":[-0.0641,51.47176],"type":"Point"}
}