{
  "type": "Feature",
  "properties": {
    "addr:full":"26 Chertsey Street Guildford Surrey GU1 4HD",
    "addr:housenumber":"26",
    "addr:postcode":"gu1 4hd",
    "addr:street":"Chertsey Street",
    "iso:country":"GB",
    "sg:address":"26 Chertsey Street",
    "sg:city":"Guildford",
    "sg:classifiers":[
        {
            "category":"Professional",
            "subcategory":"Lawyer & Legal Services",
            "type":"Services"
        }
    ],
    "sg:phone":"+44 1483 537633",
    "sg:postcode":"GU1 4HD",
    "sg:province":"Surrey",
    "sg:tags":[
        "solicitor"
    ],
    "wof:name":"Wheltons",
    "wof:placetype":"venue"
},
  "geometry": {"coordinates":[-0.5703259706,51.2372093201],"type":"Point"}
}