{
  "type": "Feature",
  "properties": {
    "addr:full":"10 The Close, Chilwell Nottingham Nottinghamshire NG9 5DF",
    "addr:housenumber":"10",
    "addr:postcode":"ng9 5df",
    "addr:street":"The Close",
    "iso:country":"GB",
    "sg:address":"10 The Close, Chilwell",
    "sg:city":"Nottingham",
    "sg:classifiers":[
        {
            "category":"Food & Beverages",
            "subcategory":"Groceries & Convenience Stores",
            "type":"Retail Goods"
        }
    ],
    "sg:phone":"+44 115 925 9057",
    "sg:postcode":"NG9 5DF",
    "sg:province":"Nottinghamshire",
    "sg:tags":[
        "coffee"
    ],
    "wof:name":"Select Coffee Service",
    "wof:placetype":"venue"
},
  "geometry": {"coordinates":[-1.233488,52.918385],"type":"Point"}
}