{
  "type": "Feature",
  "properties": {
    "iso:country":"GB",
    "sg:address":"34 Western Road",
    "sg:city":"Hove",
    "sg:classifiers":[
        {
            "category":"Professional",
            "subcategory":"Accounting & Tax Preparation",
            "type":"Services"
        }
    ],
    "sg:phone":"+44 1273 725668",
    "sg:postcode":"BN3 1AF",
    "sg:province":"East Sussex",
    "sg:tags":[
        "accountant"
    ],
    "wof:name":"John Fernley",
    "wof:placetype":"venue"
},
  "geometry": {"coordinates":[-0.159427,50.825703],"type":"Point"}
}