{
  "type": "Feature",
  "properties": {
    "iso:country":"GB",
    "sg:address":"Woodlands, School Road",
    "sg:city":"Potters Bar",
    "sg:classifiers":[
        {
            "category":"Professional",
            "subcategory":"Employment Agencies",
            "type":"Services"
        }
    ],
    "sg:phone":"+44 1707 662500",
    "sg:postcode":"EN6 1JW",
    "sg:province":"Greater London",
    "sg:tags":[
        "consultant"
    ],
    "wof:name":"Stage Miracles Ltd.",
    "wof:placetype":"venue"
},
  "geometry": {"coordinates":[-0.178424,51.693012],"type":"Point"}
}