{
  "type": "Feature",
  "properties": {
    "addr:full":"Baytree Road Weston-super-mare Somerset BS22 8HG",
    "addr:postcode":"bs22 8hg",
    "addr:street":"Baytree Road",
    "iso:country":"GB",
    "sg:address":"Baytree Road",
    "sg:city":"Weston-super-mare",
    "sg:classifiers":[
        {
            "category":"Education",
            "subcategory":"School",
            "type":"Public Place"
        }
    ],
    "sg:phone":"+44 1934 625567",
    "sg:postcode":"BS22 8HG",
    "sg:province":"Somerset",
    "sg:tags":[
        "local",
        "authority"
    ],
    "wof:name":"Baytree Special School",
    "wof:placetype":"venue"
},
  "geometry": {"coordinates":[-2.9459290504,51.3575325012],"type":"Point"}
}