{
  "type": "Feature",
  "properties": {
    "iso:country":"GB",
    "sg:address":"The Old Court, St. Leonards Rd",
    "sg:city":"Windsor",
    "sg:classifiers":[
        {
            "category":"Arts & Performance",
            "subcategory":"Theater",
            "type":"Entertainment"
        }
    ],
    "sg:phone":"+44 1753 859336",
    "sg:postcode":"SL4 3BL",
    "sg:province":"Berkshire",
    "sg:tags":[
        "hall",
        "theatre",
        "concert"
    ],
    "wof:name":"Windsor Arts Centre",
    "wof:placetype":"venue"
},
  "geometry": {"coordinates":[-0.612436,51.479271],"type":"Point"}
}