{
  "type": "Feature",
  "properties": {
    "addr:full":"437 Crow Road Glasgow Glasgow City G11 7DZ",
    "addr:housenumber":"437",
    "addr:postcode":"g11 7dz",
    "addr:street":"Crow Road",
    "iso:country":"GB",
    "sg:address":"437 Crow Road",
    "sg:city":"Glasgow",
    "sg:classifiers":[
        {
            "category":"Professional",
            "type":"Services"
        },
        {
            "category":"Professional",
            "subcategory":"Employment Agencies",
            "type":"Services"
        }
    ],
    "sg:phone":"+44 845 062 3377",
    "sg:postcode":"G11 7DZ",
    "sg:province":"Glasgow City",
    "sg:tags":[
        "entertainer",
        "entertainment"
    ],
    "sg:website":"http://www.neildrover.com",
    "wof:name":"Neil Drover the Agency",
    "wof:placetype":"venue"
},
  "geometry": {"coordinates":[-4.325512,55.880264],"type":"Point"}
}