{
  "type": "Feature",
  "properties": {
    "iso:country":"GB",
    "sg:address":"23 Preston Grange Grange Close, Preston Rd",
    "sg:city":"Brighton",
    "sg:classifiers":[
        {
            "category":"Professional",
            "subcategory":"Management & Consulting",
            "type":"Services"
        }
    ],
    "sg:phone":"+44 1273 552058",
    "sg:postcode":"BN1 6BH",
    "sg:province":"East Sussex",
    "sg:tags":[
        "consultant",
        "business"
    ],
    "wof:name":"Daneco A & A.L Jensen",
    "wof:placetype":"venue"
},
  "geometry": {"coordinates":[-0.149832,50.843575],"type":"Point"}
}