{
  "type": "Feature",
  "properties": {
    "iso:country":"GB",
    "sg:address":"Alder La",
    "sg:city":"Warrington",
    "sg:classifiers":[
        {
            "category":"Building & Trades",
            "subcategory":"Cleaning & Sanitation",
            "type":"Services"
        }
    ],
    "sg:phone":"+44 1925 229493",
    "sg:postcode":"WA5 4BT",
    "sg:province":"Cheshire",
    "sg:tags":[
        "dry",
        "control",
        "damp",
        "rot"
    ],
    "wof:name":"Alder Damp Course",
    "wof:placetype":"venue"
},
  "geometry": {"coordinates":[-2.645674,53.432541],"type":"Point"}
}