{
  "type": "Feature",
  "properties": {
    "addr:full":"11 Bankside Kidlington Buckinghamshire OX5 1JE",
    "addr:housenumber":"11",
    "addr:postcode":"ox5 1je",
    "addr:street":"Bankside",
    "iso:country":"GB",
    "sg:address":"11 Bankside",
    "sg:city":"Kidlington",
    "sg:classifiers":[
        {
            "category":"Retail",
            "subcategory":"Auto Repair",
            "type":"Services"
        }
    ],
    "sg:phone":"+44 1865 841304",
    "sg:postcode":"OX5 1JE",
    "sg:province":"Buckinghamshire",
    "sg:tags":[
        "modification",
        "garage"
    ],
    "wof:name":"P B Motors",
    "wof:placetype":"venue"
},
  "geometry": {"coordinates":[-1.301578,51.82999],"type":"Point"}
}