{
  "type": "Feature",
  "properties": {
    "iso:country":"GB",
    "sg:address":"63 High Street, Ketton",
    "sg:city":"Stamford",
    "sg:classifiers":[
        {
            "category":"Organizations",
            "subcategory":"Membership Organization",
            "type":"Services"
        }
    ],
    "sg:phone":"+44 1780 720272",
    "sg:postcode":"PE9 3TE",
    "sg:province":"Cambridgeshire",
    "sg:tags":[
        "club"
    ],
    "wof:name":"Ketton Club",
    "wof:placetype":"venue"
},
  "geometry": {"coordinates":[-0.500595,52.626858],"type":"Point"}
}