{
  "type": "Feature",
  "properties": {
    "addr:full":"5 Queen Street Bude Cornwall EX23 8AY",
    "addr:housenumber":"5",
    "addr:postcode":"ex23 8ay",
    "addr:street":"Queen Street",
    "iso:country":"GB",
    "sg:address":"5 Queen Street",
    "sg:city":"Bude",
    "sg:classifiers":[
        {
            "category":"Shopping",
            "subcategory":"Crafts & Fabrics",
            "type":"Retail Goods"
        }
    ],
    "sg:phone":"+44 1288 352432",
    "sg:postcode":"EX23 8AY",
    "sg:province":"Cornwall",
    "sg:tags":[
        "shop",
        "needlecraft",
        "wool"
    ],
    "wof:name":"Bude Woolcrafts",
    "wof:placetype":"venue"
},
  "geometry": {"coordinates":[-4.543948,50.830456],"type":"Point"}
}