{
  "type": "Feature",
  "properties": {
    "iso:country":"GB",
    "sg:address":"Woodbine Cottage, Beech Hill Road",
    "sg:city":"Reading",
    "sg:classifiers":[
        {
            "category":"Education",
            "subcategory":"Library",
            "type":"Public Place"
        }
    ],
    "sg:postcode":"RG7 2AZ",
    "sg:province":"Berkshire",
    "sg:tags":[
        "reproduction",
        "furniture"
    ],
    "wof:name":"John Lee",
    "wof:placetype":"venue"
},
  "geometry": {"coordinates":[-0.999743,51.373241],"type":"Point"}
}