{
  "type": "Feature",
  "properties": {
    "iso:country":"GB",
    "sg:address":"Grip Works, Crowhurst Road",
    "sg:city":"Brighton",
    "sg:classifiers":[
        {
            "category":"Professional",
            "subcategory":"Engineering",
            "type":"Services"
        }
    ],
    "sg:phone":"+44 1273 508881",
    "sg:postcode":"BN1 8AT",
    "sg:province":"East Sussex",
    "sg:tags":[
        "precision",
        "engineer"
    ],
    "wof:name":"Talbot Tool Co. Ltd.",
    "wof:placetype":"venue"
},
  "geometry": {"coordinates":[-0.1252799928,50.8667297363],"type":"Point"}
}