{
  "type": "Feature",
  "properties": {
    "addr:full":"106 Roebuck Rd, Chessington Indstl Est Chessington Surrey KT9 1EU",
    "addr:housenumber":"106",
    "addr:postcode":"kt9 1eu",
    "addr:street":"Roebuck Rd;Indstl Est",
    "iso:country":"GB",
    "sg:address":"106 Roebuck Rd, Chessington Indstl Est",
    "sg:city":"Chessington",
    "sg:classifiers":[
        {
            "category":"Autos & Motor Vehicles",
            "subcategory":"Automobile Sales",
            "type":"Retail Goods"
        }
    ],
    "sg:postcode":"KT9 1EU",
    "sg:province":"Surrey",
    "sg:tags":[
        "car",
        "specialist",
        "sales",
        "classic"
    ],
    "wof:name":"Woodlift Ltd",
    "wof:placetype":"venue"
},
  "geometry": {"coordinates":[-0.308645,51.361874],"type":"Point"}
}