{
  "type": "Feature",
  "properties": {
    "iso:country":"GB",
    "sg:address":"57 St. Serfs Rd, Tullibody",
    "sg:city":"Alloa",
    "sg:classifiers":[
        {
            "category":"Building & Trades",
            "subcategory":"Cleaning & Sanitation",
            "type":"Services"
        }
    ],
    "sg:phone":"+44 1259 216188",
    "sg:postcode":"FK10 2RD",
    "sg:province":"Clackmannanshire",
    "sg:tags":[
        "commercial"
    ],
    "wof:name":"Gleam Clean",
    "wof:placetype":"venue"
},
  "geometry": {"coordinates":[-3.839175,56.137859],"type":"Point"}
}