{
  "type": "Feature",
  "properties": {
    "addr:full":"18a Greek Street Stockport Cheshire SK3 8AB",
    "addr:housenumber":"18a",
    "addr:postcode":"sk3 8ab",
    "addr:street":"Greek Street",
    "iso:country":"GB",
    "sg:address":"18a Greek Street",
    "sg:city":"Stockport",
    "sg:classifiers":[
        {
            "category":"Cafe",
            "type":"Food & Drink"
        }
    ],
    "sg:postcode":"SK3 8AB",
    "sg:province":"Cheshire",
    "sg:tags":[
        "tea",
        "room"
    ],
    "wof:name":"Hungries",
    "wof:placetype":"venue"
},
  "geometry": {"coordinates":[-2.160088,53.4044],"type":"Point"}
}