{
  "type": "Feature",
  "properties": {
    "iso:country":"GB",
    "sg:address":"Hall Lane",
    "sg:city":"Bradford",
    "sg:classifiers":[
        {
            "category":"Building & Trades",
            "subcategory":"Construction",
            "type":"Services"
        },
        {
            "category":"Manufacturing",
            "subcategory":"Lumber",
            "type":"Manufacturing & Wholesale Goods"
        }
    ],
    "sg:phone":"+44 1274 727115",
    "sg:postcode":"BD4 7DJ",
    "sg:province":"West Yorkshire",
    "sg:tags":[
        "merchant",
        "roofing",
        "timber"
    ],
    "wof:name":"Bradford Timber Sales",
    "wof:placetype":"venue"
},
  "geometry": {"coordinates":[-1.7450389862,53.7884750366],"type":"Point"}
}