{
  "type": "Feature",
  "properties": {
    "iso:country":"GB",
    "sg:address":"2a Maids Head Parade, High Street, Thorpe-le-soken",
    "sg:city":"Clacton-on-sea",
    "sg:classifiers":[
        {
            "category":"Shopping",
            "subcategory":"Pharmacy",
            "type":"Retail Goods"
        }
    ],
    "sg:phone":"+44 1255 861329",
    "sg:postcode":"CO16 0DY",
    "sg:province":"Essex",
    "sg:tags":[
        "pharmacist",
        "store",
        "drug",
        "chemist"
    ],
    "wof:name":"Mansfield Chemist",
    "wof:placetype":"venue"
},
  "geometry": {"coordinates":[1.163734,51.856934],"type":"Point"}
}