{
  "type": "Feature",
  "properties": {
    "iso:country":"GB",
    "sg:address":"106 Great Western Village, Kemble Drive",
    "sg:city":"Swindon",
    "sg:classifiers":[
        {
            "category":"Shopping",
            "subcategory":"Books",
            "type":"Retail Goods"
        }
    ],
    "sg:phone":"+44 1793 435323",
    "sg:postcode":"SN2 5EE",
    "sg:province":"Wiltshire",
    "sg:tags":[
        "bookseller"
    ],
    "wof:name":"Bookends",
    "wof:placetype":"venue"
},
  "geometry": {"coordinates":[-1.77907,51.59082],"type":"Point"}
}