{
  "type": "Feature",
  "properties": {
    "addr:full":"Windmill Road, Markyate St Albans Hertfordshire AL3 8LP",
    "addr:postcode":"al3 8lp",
    "addr:street":"Windmill Road",
    "iso:country":"GB",
    "sg:address":"Windmill Road, Markyate",
    "sg:city":"St Albans",
    "sg:classifiers":[
        {
            "category":"Shopping",
            "subcategory":"Hobbies, Toys, & Games",
            "type":"Retail Goods"
        },
        {
            "category":"Recreation",
            "type":"Entertainment"
        }
    ],
    "sg:phone":"+44 1582 842280",
    "sg:postcode":"AL3 8LP",
    "sg:province":"Hertfordshire",
    "sg:tags":[
        "corporate",
        "leisure",
        "gunsmith"
    ],
    "wof:name":"Broomhills Shooting Ground Ltd",
    "wof:placetype":"venue"
},
  "geometry": {"coordinates":[-0.460974,51.836399],"type":"Point"}
}