{
  "type": "Feature",
  "properties": {
    "addr:full":"94g West Main Street, Whitburn Bathgate North Lanarkshire EH47 0QU",
    "addr:housenumber":"94g",
    "addr:postcode":"eh47 0qu",
    "addr:street":"West Main Street;Bathgate",
    "iso:country":"GB",
    "sg:address":"94g West Main Street, Whitburn",
    "sg:city":"Bathgate",
    "sg:classifiers":[
        {
            "category":"Health Services",
            "subcategory":"Podiatrist",
            "type":"Services"
        }
    ],
    "sg:postcode":"EH47 0QU",
    "sg:province":"North Lanarkshire",
    "sg:tags":[
        "podiatrists",
        "chiropodist"
    ],
    "wof:name":"The Foot Clinic",
    "wof:placetype":"venue"
},
  "geometry": {"coordinates":[-3.689625,55.866211],"type":"Point"}
}