{
  "type": "Feature",
  "properties": {
    "addr:full":"240a Portobello High Street Edinburgh City of Edinburgh EH15 2AU",
    "addr:housenumber":"240a",
    "addr:postcode":"eh15 2au",
    "addr:street":"Portobello High Street",
    "iso:country":"GB",
    "sg:address":"240a Portobello High Street",
    "sg:city":"Edinburgh",
    "sg:classifiers":[
        {
            "category":"Personal",
            "subcategory":"Beauty Salon",
            "type":"Services"
        }
    ],
    "sg:phone":"+44 131 669 6618",
    "sg:postcode":"EH15 2AU",
    "sg:province":"City of Edinburgh",
    "sg:tags":[
        "unisex",
        "hairdresser"
    ],
    "wof:name":"Pams Hairdressing",
    "wof:placetype":"venue"
},
  "geometry": {"coordinates":[-3.111355,55.952179],"type":"Point"}
}