{
  "type": "Feature",
  "properties": {
    "iso:country":"GB",
    "sg:address":"21 Northernhay Street",
    "sg:city":"Exeter",
    "sg:classifiers":[
        {
            "category":"Banks & Credit Unions",
            "subcategory":"Financial Services",
            "type":"Services"
        },
        {
            "category":"Building & Trades",
            "subcategory":"Construction",
            "type":"Services"
        }
    ],
    "sg:phone":"+44 1392 410200",
    "sg:postcode":"EX4 3ER",
    "sg:province":"Devon",
    "sg:tags":[
        "consultant",
        "flooring"
    ],
    "wof:name":"Guardian Financial Services",
    "wof:placetype":"venue"
},
  "geometry": {"coordinates":[-3.533353,50.72538],"type":"Point"}
}