{
  "type": "Feature",
  "properties": {
    "iso:country":"GB",
    "sg:address":"2 Kennett Gardens, Upton La",
    "sg:city":"Gloucester",
    "sg:classifiers":[
        {
            "category":"Professional",
            "type":"Services"
        }
    ],
    "sg:phone":"+44 1452 372566",
    "sg:postcode":"GL4 5TZ",
    "sg:province":"Gloucestershire",
    "sg:tags":[
        "entertainer"
    ],
    "wof:name":"Premiere Entertainments Agency",
    "wof:placetype":"venue"
},
  "geometry": {"coordinates":[-2.196211,51.839966],"type":"Point"}
}