{
  "type": "Feature",
  "properties": {
    "iso:country":"GB",
    "sg:address":"11a Tanfield Indust Est",
    "sg:city":"Stanley",
    "sg:classifiers":[
        {
            "category":"Food & Beverages",
            "subcategory":"Bakery",
            "type":"Retail Goods"
        }
    ],
    "sg:phone":"+44 1207 233903",
    "sg:postcode":"DH9 9UU",
    "sg:province":"Durham",
    "sg:tags":[
        "confectionery"
    ],
    "wof:name":"C D K Bakery",
    "wof:placetype":"venue"
},
  "geometry": {"coordinates":[-1.692809,54.88295],"type":"Point"}
}