{
  "type": "Feature",
  "properties": {
    "addr:full":"98 Battleton Road Evesham Gloucestershire WR11 1JE",
    "addr:housenumber":"98",
    "addr:postcode":"wr11 1je",
    "addr:street":"Battleton Road",
    "iso:country":"GB",
    "sg:address":"98 Battleton Road",
    "sg:city":"Evesham",
    "sg:classifiers":[
        {
            "category":"Manufacturing",
            "subcategory":"Signs",
            "type":"Manufacturing & Wholesale Goods"
        }
    ],
    "sg:phone":"+44 1386 442761",
    "sg:postcode":"WR11 1JE",
    "sg:province":"Gloucestershire",
    "sg:tags":[
        "writer"
    ],
    "wof:name":"D M Canning",
    "wof:placetype":"venue"
},
  "geometry": {"coordinates":[-1.94017,52.083427],"type":"Point"}
}