{
  "type": "Feature",
  "properties": {
    "iso:country":"GB",
    "sg:address":"40 Potterrow",
    "sg:city":"Edinburgh",
    "sg:classifiers":[
        {
            "category":"Home & Garden",
            "subcategory":"Kitchen Supply",
            "type":"Retail Goods"
        }
    ],
    "sg:phone":"+44 131 667 9225",
    "sg:postcode":"EH8 9BT",
    "sg:province":"City of Edinburgh",
    "sg:tags":[
        "equipment",
        "brewer"
    ],
    "wof:name":"Stevenson Reeves Ltd.",
    "wof:placetype":"venue"
},
  "geometry": {"coordinates":[-3.1864299774,55.9452629089],"type":"Point"}
}