{
  "type": "Feature",
  "properties": {
    "iso:country":"GB",
    "sg:address":"239 Euston Rd",
    "sg:city":"London",
    "sg:classifiers":[
        {
            "category":"Professional",
            "subcategory":"Employment Agencies",
            "type":"Services"
        }
    ],
    "sg:phone":"+44 20 7388 8686",
    "sg:postcode":"NW1 2BU",
    "sg:province":"Greater London",
    "sg:tags":[
        "consultant"
    ],
    "wof:name":"Manpower Plc",
    "wof:placetype":"venue"
},
  "geometry": {"coordinates":[-0.136079,51.525314],"type":"Point"}
}