{
  "type": "Feature",
  "properties": {
    "addr:full":"1 The Squires Field, Great Wilbraham Cambridge Cambridgeshire CB1 5TA",
    "addr:housenumber":"1",
    "addr:postcode":"cb1 5ta",
    "addr:street":"The Squires Field",
    "iso:country":"GB",
    "sg:address":"1 The Squires Field, Great Wilbraham",
    "sg:city":"Cambridge",
    "sg:classifiers":[
        {
            "category":"Professional",
            "type":"Services"
        }
    ],
    "sg:postcode":"CB1 5TA",
    "sg:province":"Cambridgeshire",
    "sg:tags":[
        "caterer"
    ],
    "wof:name":"Party Services",
    "wof:placetype":"venue"
},
  "geometry": {"coordinates":[0.263075,52.191727],"type":"Point"}
}