{
  "type": "Feature",
  "properties": {
    "iso:country":"GB",
    "sg:address":"35 Leamington Road, Ryton-on-dunsmore",
    "sg:city":"Coventry",
    "sg:classifiers":[
        {
            "category":"Professional",
            "subcategory":"Printing & Photocopies",
            "type":"Services"
        }
    ],
    "sg:postcode":"CV8 3FL",
    "sg:province":"Warwickshire",
    "sg:tags":[
        "printer"
    ],
    "wof:name":"John C Challener",
    "wof:placetype":"venue"
},
  "geometry": {"coordinates":[-1.430911,52.363045],"type":"Point"}
}