{
  "type": "Feature",
  "properties": {
    "addr:full":"Target House, Cowbridge Road East Cardiff Cardiff CF11 9AU",
    "addr:postcode":"cf11 9au",
    "addr:street":"Cowbridge Road East",
    "iso:country":"GB",
    "sg:address":"Target House, Cowbridge Road East",
    "sg:city":"Cardiff",
    "sg:classifiers":[
        {
            "category":"Professional",
            "subcategory":"Computer Services",
            "type":"Services"
        }
    ],
    "sg:phone":"+44 29 2030 1401",
    "sg:postcode":"CF11 9AU",
    "sg:province":"Cardiff",
    "sg:tags":[
        "system",
        "software"
    ],
    "wof:name":"Target Group Ltd.",
    "wof:placetype":"venue"
},
  "geometry": {"coordinates":[-3.1881198883,51.4814605713],"type":"Point"}
}