{
  "type": "Feature",
  "properties": {
    "iso:country":"GB",
    "sg:address":"Wellpark Lodge, Green Lane",
    "sg:city":"Yelverton",
    "sg:classifiers":[
        {
            "category":"Professional",
            "subcategory":"Business Services",
            "type":"Services"
        }
    ],
    "sg:phone":"+44 1822 854489",
    "sg:postcode":"PL20 7NP",
    "sg:province":"Devon",
    "sg:tags":[
        "accomodation"
    ],
    "wof:name":"J & S & W Ltd.",
    "wof:placetype":"venue"
},
  "geometry": {"coordinates":[-4.0878591537,50.4923782349],"type":"Point"}
}