{
  "type": "Feature",
  "properties": {
    "iso:country":"GB",
    "sg:address":"1 Oaklands",
    "sg:city":"Strathaven",
    "sg:classifiers":[
        {
            "category":"Professional",
            "subcategory":"Art Services",
            "type":"Services"
        }
    ],
    "sg:phone":"+44 1357 522638",
    "sg:postcode":"ML10 6NP",
    "sg:province":"South Lanarkshire",
    "sg:tags":[
        "graphic",
        "designer"
    ],
    "wof:name":"Sundial Design",
    "wof:placetype":"venue"
},
  "geometry": {"coordinates":[-4.0723290443,55.6761283875],"type":"Point"}
}