{
  "type": "Feature",
  "properties": {
    "addr:full":"Heol Ddu Llanelli Carmarthenshire SA15 4RP",
    "addr:postcode":"sa15 4rp",
    "addr:street":"Heol Ddu;Carmarthenshire",
    "iso:country":"GB",
    "sg:address":"Heol Ddu",
    "sg:city":"Llanelli",
    "sg:classifiers":[
        {
            "category":"Farming",
            "subcategory":"Livestock Farm",
            "type":"Manufacturing & Wholesale Goods"
        }
    ],
    "sg:phone":"+44 1554 810016",
    "sg:postcode":"SA15 4RP",
    "sg:province":"Carmarthenshire",
    "sg:tags":[
        "others"
    ],
    "wof:name":"L J Jones",
    "wof:placetype":"venue"
},
  "geometry": {"coordinates":[-4.225314,51.71183],"type":"Point"}
}