{
  "type": "Feature",
  "properties": {
    "iso:country":"GB",
    "sg:address":"79 Bellevue Rd",
    "sg:city":"Cowes",
    "sg:classifiers":[
        {
            "category":"Personal",
            "type":"Services"
        }
    ],
    "sg:postcode":"PO31 7LD",
    "sg:province":"Isle of Wight",
    "sg:tags":[
        "wedding"
    ],
    "wof:name":"Bon Appetit",
    "wof:placetype":"venue"
},
  "geometry": {"coordinates":[-1.297819,50.757061],"type":"Point"}
}