{
  "type": "Feature",
  "properties": {
    "addr:full":"26 Exeter Rd Newmarket Cambridgeshire CB8 8LX",
    "addr:housenumber":"26",
    "addr:postcode":"cb8 8lx",
    "addr:street":"Exeter Rd",
    "iso:country":"GB",
    "sg:address":"26 Exeter Rd",
    "sg:city":"Newmarket",
    "sg:classifiers":[
        {
            "category":"Professional",
            "subcategory":"Management & Consulting",
            "type":"Services"
        }
    ],
    "sg:phone":"+44 1638 662813",
    "sg:postcode":"CB8 8LX",
    "sg:province":"Cambridgeshire",
    "sg:tags":[
        "consultant",
        "business"
    ],
    "wof:name":"Richard Rigby & Partners",
    "wof:placetype":"venue"
},
  "geometry": {"coordinates":[0.4058229923,52.2465057373],"type":"Point"}
}