{
  "type": "Feature",
  "properties": {
    "iso:country":"GB",
    "sg:address":"Stony Lane",
    "sg:city":"Christchurch",
    "sg:classifiers":[
        {
            "category":"Shopping",
            "subcategory":"Discount & Variety Stores",
            "type":"Retail Goods"
        }
    ],
    "sg:phone":"+44 1202 476902",
    "sg:postcode":"BH23 7LQ",
    "sg:province":"Dorset",
    "sg:tags":[
        "shop",
        "model"
    ],
    "wof:name":"Lesro Models Ltd.",
    "wof:placetype":"venue"
},
  "geometry": {"coordinates":[-1.769021,50.741405],"type":"Point"}
}