{
  "type": "Feature",
  "properties": {
    "iso:country":"GB",
    "sg:address":"Regus Business Park, Centaur House",
    "sg:city":"Fleet",
    "sg:classifiers":[
        {
            "category":"Professional",
            "subcategory":"Credit Reporting & Collection",
            "type":"Services"
        }
    ],
    "sg:phone":"+44 1252 761411",
    "sg:postcode":"GU51 2UJ",
    "sg:province":"Hampshire",
    "sg:tags":[
        "collecting",
        "agency"
    ],
    "wof:name":"Financial Trace & Collections Ltd.",
    "wof:placetype":"venue"
},
  "geometry": {"coordinates":[-0.82003,51.297112],"type":"Point"}
}