{
  "type": "Feature",
  "properties": {
    "addr:full":"26 Ganton Street London Greater London W1F 7QY",
    "addr:housenumber":"26",
    "addr:postcode":"w1f 7qy",
    "addr:street":"Ganton Street",
    "iso:country":"GB",
    "sg:address":"26 Ganton Street",
    "sg:city":"London",
    "sg:classifiers":[
        {
            "category":"Shopping",
            "subcategory":"Thrift Store",
            "type":"Retail Goods"
        }
    ],
    "sg:phone":"+44 20 7437 7338",
    "sg:postcode":"W1F 7QY",
    "sg:province":"Greater London",
    "sg:tags":[
        "shop",
        "charity"
    ],
    "wof:name":"Origin Oxfam",
    "wof:placetype":"venue"
},
  "geometry": {"coordinates":[-0.1384849995,51.5132637024],"type":"Point"}
}