{
  "type": "Feature",
  "properties": {
    "addr:full":"16 Birch Road Chorley Lancashire PR6 0JG",
    "addr:housenumber":"16",
    "addr:postcode":"pr6 0jg",
    "addr:street":"Birch Road",
    "iso:country":"GB",
    "sg:address":"16 Birch Road",
    "sg:city":"Chorley",
    "sg:classifiers":[
        {
            "category":"Professional",
            "subcategory":"Printing & Photocopies",
            "type":"Services"
        },
        {
            "category":"Government",
            "subcategory":"Post Office",
            "type":"Public Place"
        }
    ],
    "sg:phone":"+44 1257 278289",
    "sg:postcode":"PR6 0JG",
    "sg:province":"Lancashire",
    "sg:tags":[
        "print",
        "typesetter",
        "printer"
    ],
    "wof:name":"B D P Design & Print",
    "wof:placetype":"venue"
},
  "geometry": {"coordinates":[-2.621164,53.663754],"type":"Point"}
}