{
  "type": "Feature",
  "properties": {
    "iso:country":"GB",
    "sg:address":"24 High Street, Rishton",
    "sg:city":"Blackburn",
    "sg:classifiers":[
        {
            "category":"Social Services",
            "subcategory":"Adult Care",
            "type":"Services"
        }
    ],
    "sg:phone":"+44 1254 882088",
    "sg:postcode":"BB1 4LA",
    "sg:province":"Lancashire",
    "sg:tags":[
        "home",
        "help",
        "private"
    ],
    "wof:name":"Community Careline Services Ltd.",
    "wof:placetype":"venue"
},
  "geometry": {"coordinates":[-2.413904,53.768543],"type":"Point"}
}