{
  "type": "Feature",
  "properties": {
    "iso:country":"GB",
    "sg:address":"110 Penygraig Road",
    "sg:city":"Swansea",
    "sg:classifiers":[
        {
            "category":"Food & Beverages",
            "subcategory":"Supermarket",
            "type":"Retail Goods"
        }
    ],
    "sg:phone":"+44 1792 655359",
    "sg:postcode":"SA1 6LA",
    "sg:province":"Neath Port Talbot",
    "wof:name":"Johals Supermarket",
    "wof:placetype":"venue"
},
  "geometry": {"coordinates":[-3.9596838951,51.626373291],"type":"Point"}
}