{
  "type": "Feature",
  "properties": {
    "iso:country":"GB",
    "sg:address":"Gwythrian",
    "sg:city":"Pwllheli",
    "sg:classifiers":[
        {
            "category":"Farming",
            "subcategory":"Livestock Farm",
            "type":"Manufacturing & Wholesale Goods"
        }
    ],
    "sg:phone":"+44 1758 760343",
    "sg:postcode":"LL53 8BW",
    "sg:province":"Gwynedd",
    "sg:tags":[
        "others"
    ],
    "wof:name":"Gwythrian Farm",
    "wof:placetype":"venue"
},
  "geometry": {"coordinates":[-4.611854,52.868099],"type":"Point"}
}