{
  "type": "Feature",
  "properties": {
    "iso:country":"GB",
    "sg:address":"5 South Walk",
    "sg:city":"Cwmbran",
    "sg:classifiers":[
        {
            "category":"Shopping",
            "subcategory":"Clothing, Apparel, & Fashions",
            "type":"Retail Goods"
        }
    ],
    "sg:phone":"+44 1633 485800",
    "sg:postcode":"NP44 1PU",
    "sg:province":"Monmouthshire",
    "sg:tags":[
        "menswear"
    ],
    "wof:name":"Suits Plus At Cwmran",
    "wof:placetype":"venue"
},
  "geometry": {"coordinates":[-3.0258638859,51.6574668884],"type":"Point"}
}