{
  "type": "Feature",
  "properties": {
    "iso:country":"GB",
    "sg:address":"Moody House, 6 Moody Street",
    "sg:city":"Congleton",
    "sg:classifiers":[
        {
            "category":"Professional",
            "type":"Services"
        },
        {
            "category":"Real Estate",
            "subcategory":"Real Estate Agent",
            "type":"Services"
        }
    ],
    "sg:phone":"+44 1260 274224",
    "sg:postcode":"CW12 4AP",
    "sg:province":"Cheshire",
    "sg:tags":[
        "auctioneer"
    ],
    "wof:name":"Whittaker & Biggs",
    "wof:placetype":"venue"
},
  "geometry": {"coordinates":[-2.2123000622,53.1627197266],"type":"Point"}
}