{
  "type": "Feature",
  "properties": {
    "addr:full":"34 Pilgrims Way Bedford Bedfordshire MK42 9TU",
    "addr:housenumber":"34",
    "addr:postcode":"mk42 9tu",
    "addr:street":"Pilgrims Way",
    "iso:country":"GB",
    "sg:address":"34 Pilgrims Way",
    "sg:city":"Bedford",
    "sg:classifiers":[
        {
            "category":"Manufacturing",
            "subcategory":"Metals",
            "type":"Manufacturing & Wholesale Goods"
        },
        {
            "category":"Professional",
            "subcategory":"Printing & Photocopies",
            "type":"Services"
        }
    ],
    "sg:postcode":"MK42 9TU",
    "sg:province":"Bedfordshire",
    "sg:tags":[
        "engraving",
        "heat",
        "-",
        "treatment"
    ],
    "wof:name":"Peter D Burkitt",
    "wof:placetype":"venue"
},
  "geometry": {"coordinates":[-0.4655179977,52.1180725098],"type":"Point"}
}