{
  "type": "Feature",
  "properties": {
    "addr:full":"14 Barnfield Close Hastings East Sussex TN34 1TS",
    "addr:housenumber":"14",
    "addr:postcode":"tn34 1ts",
    "addr:street":"Barnfield Close",
    "iso:country":"GB",
    "sg:address":"14 Barnfield Close",
    "sg:city":"Hastings",
    "sg:classifiers":[
        {
            "category":"Professional",
            "subcategory":"Accounting & Tax Preparation",
            "type":"Services"
        }
    ],
    "sg:phone":"+44 1424 438191",
    "sg:postcode":"TN34 1TS",
    "sg:province":"East Sussex",
    "sg:tags":[
        "accountant"
    ],
    "wof:name":"Bryan Coyle & Co",
    "wof:placetype":"venue"
},
  "geometry": {"coordinates":[0.567916,50.860909],"type":"Point"}
}