{
  "type": "Feature",
  "properties": {
    "addr:full":"7 Clifton Villas London Greater London W9 2PH",
    "addr:housenumber":"7",
    "addr:postcode":"w9 2ph",
    "addr:street":"Clifton Villas",
    "iso:country":"GB",
    "sg:address":"7 Clifton Villas",
    "sg:city":"London",
    "sg:classifiers":[
        {
            "category":"Professional",
            "subcategory":"Management & Consulting",
            "type":"Services"
        }
    ],
    "sg:postcode":"W9 2PH",
    "sg:province":"Greater London",
    "sg:tags":[
        "consultant",
        "business"
    ],
    "wof:name":"Fametree Ltd",
    "wof:placetype":"venue"
},
  "geometry": {"coordinates":[-0.178691,51.525684],"type":"Point"}
}