{
  "type": "Feature",
  "properties": {
    "addr:full":"Unit 1 Bradfield Clo, Finedon Road Indstl Est Wellingborough Northamptonshire NN8 4RQ",
    "addr:housenumber":"unit 1",
    "addr:postcode":"nn8 4rq",
    "addr:street":"Finedon Road Indstl Est",
    "iso:country":"GB",
    "sg:address":"Unit 1 Bradfield Clo, Finedon Road Indstl Est",
    "sg:city":"Wellingborough",
    "sg:classifiers":[
        {
            "category":"Shopping",
            "subcategory":"Stationery & Office Supplies",
            "type":"Retail Goods"
        }
    ],
    "sg:phone":"+44 1933 223318",
    "sg:postcode":"NN8 4RQ",
    "sg:province":"Northamptonshire",
    "sg:tags":[
        "box",
        "carton"
    ],
    "wof:name":"Martin,C W,Ltd",
    "wof:placetype":"venue"
},
  "geometry": {"coordinates":[-0.6962959766,52.3024215698],"type":"Point"}
}