{
  "type": "Feature",
  "properties": {
    "iso:country":"GB",
    "sg:address":"28 Parsonage Street",
    "sg:city":"Dursley",
    "sg:classifiers":[
        {
            "category":"Shopping",
            "subcategory":"Shoes",
            "type":"Retail Goods"
        }
    ],
    "sg:phone":"+44 1453 542207",
    "sg:postcode":"GL11 4AA",
    "sg:province":"Gloucestershire",
    "sg:tags":[
        "shop",
        "retailer",
        "footwear"
    ],
    "wof:name":"P HAWKINS",
    "wof:placetype":"venue"
},
  "geometry": {"coordinates":[-2.3573210239,51.6819572449],"type":"Point"}
}