{
  "type": "Feature",
  "properties": {
    "iso:country":"GB",
    "sg:address":"10 Reform St",
    "sg:city":"Dundee",
    "sg:classifiers":[
        {
            "category":"Health Services",
            "subcategory":"Dentist",
            "type":"Services"
        }
    ],
    "sg:phone":"+44 1382 224048",
    "sg:postcode":"DD1 1RG",
    "sg:province":"Dundee City",
    "wof:name":"Andrew J Wright",
    "wof:placetype":"venue"
},
  "geometry": {"coordinates":[-2.97063,56.460819],"type":"Point"}
}