{
  "type": "Feature",
  "properties": {
    "iso:country":"GB",
    "sg:address":"44 Withins Lane",
    "sg:city":"Bolton",
    "sg:classifiers":[
        {
            "category":"Social Services",
            "subcategory":"Adult Care",
            "type":"Services"
        }
    ],
    "sg:phone":"+44 1204 362626",
    "sg:postcode":"BL2 5DZ",
    "sg:province":"Lancashire",
    "sg:tags":[
        "day",
        "centre"
    ],
    "wof:name":"Coaching House Day Care Centre",
    "wof:placetype":"venue"
},
  "geometry": {"coordinates":[-2.390683,53.585274],"type":"Point"}
}