{
  "type": "Feature",
  "properties": {
    "iso:country":"GB",
    "sg:address":"10 The Forum",
    "sg:city":"Wallsend",
    "sg:classifiers":[
        {
            "category":"Shopping",
            "subcategory":"News",
            "type":"Retail Goods"
        }
    ],
    "sg:phone":"+44 191 262 4872",
    "sg:postcode":"NE28 8JR",
    "sg:province":"Tyne and Wear",
    "sg:tags":[
        "newsagent"
    ],
    "wof:name":"New Plus",
    "wof:placetype":"venue"
},
  "geometry": {"coordinates":[-1.545512,54.999081],"type":"Point"}
}