{
  "type": "Feature",
  "properties": {
    "iso:country":"GB",
    "sg:address":"55 High Road, Orsett",
    "sg:city":"Grays",
    "sg:classifiers":[
        {
            "category":"Health Services",
            "subcategory":"Dentist",
            "type":"Services"
        }
    ],
    "sg:phone":"+44 1375 892050",
    "sg:postcode":"RM16 3HB",
    "sg:province":"Essex",
    "wof:name":"Sunnyside Centre",
    "wof:placetype":"venue"
},
  "geometry": {"coordinates":[0.3648000062,51.5120277405],"type":"Point"}
}