{
  "type": "Feature",
  "properties": {
    "addr:full":"61-62 Baxter Gate Loughborough Leicestershire LE11 1TH",
    "addr:housenumber":"61-62",
    "addr:postcode":"le11 1th",
    "addr:street":"Baxter Gate",
    "iso:country":"GB",
    "sg:address":"61-62 Baxter Gate",
    "sg:city":"Loughborough",
    "sg:classifiers":[
        {
            "category":"Shopping",
            "subcategory":"Shoes",
            "type":"Retail Goods"
        }
    ],
    "sg:phone":"+44 1509 218947",
    "sg:postcode":"LE11 1TH",
    "sg:province":"Leicestershire",
    "wof:name":"Saddlers",
    "wof:placetype":"venue"
},
  "geometry": {"coordinates":[-1.2047829628,52.7721366882],"type":"Point"}
}