{
  "type": "Feature",
  "properties": {
    "iso:country":"GB",
    "sg:address":"23-25 Garswood St",
    "sg:city":"Wigan",
    "sg:classifiers":[
        {
            "category":"Shopping",
            "subcategory":"Jewelry",
            "type":"Retail Goods"
        }
    ],
    "sg:phone":"+44 1942 720888",
    "sg:postcode":"WN4 9AF",
    "sg:province":"Lancashire",
    "sg:tags":[
        "gold",
        "silversmith"
    ],
    "wof:name":"Additions",
    "wof:placetype":"venue"
},
  "geometry": {"coordinates":[-2.638844,53.487255],"type":"Point"}
}