{
  "type": "Feature",
  "properties": {
    "addr:full":"90-92 Furtherwick Road Canvey Island Essex SS8 7AJ",
    "addr:housenumber":"90-92",
    "addr:postcode":"ss8 7aj",
    "addr:street":"Furtherwick Road",
    "iso:country":"GB",
    "sg:address":"90-92 Furtherwick Road",
    "sg:city":"Canvey Island",
    "sg:classifiers":[
        {
            "category":"Commercial Area",
            "type":"Public Place"
        }
    ],
    "sg:phone":"+44 1268 685295",
    "sg:postcode":"SS8 7AJ",
    "sg:province":"Essex",
    "sg:tags":[
        "shop",
        "centre"
    ],
    "wof:name":"Canvey Shopping Hall",
    "wof:placetype":"venue"
},
  "geometry": {"coordinates":[0.592278,51.521824],"type":"Point"}
}