{
  "type": "Feature",
  "properties": {
    "iso:country":"GB",
    "sg:address":"1a Wesley Street",
    "sg:city":"Cwmbran",
    "sg:classifiers":[
        {
            "category":"Personal",
            "subcategory":"Barber",
            "type":"Services"
        }
    ],
    "sg:phone":"+44 1633 874553",
    "sg:postcode":"NP44 3LX",
    "sg:province":"Monmouthshire",
    "sg:tags":[
        "men's",
        "gents",
        "hairdresser"
    ],
    "wof:name":"Natale's Hairdressers",
    "wof:placetype":"venue"
},
  "geometry": {"coordinates":[-3.0257470608,51.6477813721],"type":"Point"}
}