{
  "type": "Feature",
  "properties": {
    "iso:country":"GB",
    "sg:address":"1a Ives Close, Yateley",
    "sg:city":"Camberley",
    "sg:classifiers":[
        {
            "category":"Home & Garden",
            "subcategory":"Building Materials",
            "type":"Retail Goods"
        }
    ],
    "sg:phone":"+44 1252 876239",
    "sg:postcode":"GU17 7RD",
    "sg:province":"Hampshire",
    "sg:tags":[
        "fencing"
    ],
    "wof:name":"Crowthorne Fencing",
    "wof:placetype":"venue"
},
  "geometry": {"coordinates":[-0.81166,51.321602],"type":"Point"}
}