{
  "type": "Feature",
  "properties": {
    "addr:full":"101 Banstead Road South Sutton Surrey SM2 5LH",
    "addr:housenumber":"101",
    "addr:postcode":"sm2 5lh",
    "addr:street":"Banstead Road South",
    "iso:country":"GB",
    "sg:address":"101 Banstead Road South",
    "sg:city":"Sutton",
    "sg:classifiers":[
        {
            "category":"Education",
            "subcategory":"Junior College",
            "type":"Public Place"
        }
    ],
    "sg:phone":"+44 20 8770 3866",
    "sg:postcode":"SM2 5LH",
    "sg:province":"Surrey",
    "sg:tags":[
        "educational",
        "resource"
    ],
    "wof:name":"Music Education Supplies Ltd.",
    "wof:placetype":"venue"
},
  "geometry": {"coordinates":[-0.1833799928,51.3452720642],"type":"Point"}
}