{
  "type": "Feature",
  "properties": {
    "addr:full":"Lands End Riding Stables, Park Lane Reading Berkshire RG10 9TR",
    "addr:postcode":"rg10 9tr",
    "addr:street":"Lands End Riding;Park Lane",
    "iso:country":"GB",
    "sg:address":"Lands End Riding Stables, Park Lane",
    "sg:city":"Reading",
    "sg:classifiers":[
        {
            "category":"Retail",
            "subcategory":"Auto Repair",
            "type":"Services"
        }
    ],
    "sg:postcode":"RG10 9TR",
    "sg:province":"Berkshire",
    "sg:tags":[
        "modification",
        "garage"
    ],
    "wof:name":"Able Motor Services",
    "wof:placetype":"venue"
},
  "geometry": {"coordinates":[-0.963009,51.453522],"type":"Point"}
}