{
  "type": "Feature",
  "properties": {
    "iso:country":"GB",
    "sg:address":"Bath Rd",
    "sg:city":"Devizes",
    "sg:classifiers":[
        {
            "category":"Food & Beverages",
            "subcategory":"Groceries & Convenience Stores",
            "type":"Retail Goods"
        }
    ],
    "sg:phone":"+44 1380 724483",
    "sg:postcode":"SN10 2AP",
    "sg:province":"Wiltshire",
    "wof:name":"Spar Food Market",
    "wof:placetype":"venue"
},
  "geometry": {"coordinates":[-2.0091049671,51.3532791138],"type":"Point"}
}