{
  "type": "Feature",
  "properties": {
    "addr:full":"Fosse Park South, Everard Way Leicester Leicestershire LE19 1UT",
    "addr:postcode":"le19 1ut",
    "addr:street":"Fosse Park South Everard Way",
    "iso:country":"GB",
    "sg:address":"Fosse Park South, Everard Way",
    "sg:city":"Leicester",
    "sg:classifiers":[
        {
            "category":"Home & Garden",
            "subcategory":"Furniture",
            "type":"Retail Goods"
        }
    ],
    "sg:phone":"+44 116 289 2300",
    "sg:postcode":"LE19 1UT",
    "sg:province":"Leicestershire",
    "wof:name":"D F S Furniture",
    "wof:placetype":"venue"
},
  "geometry": {"coordinates":[-1.1805889606,52.5997200012],"type":"Point"}
}