{
  "type": "Feature",
  "properties": {
    "iso:country":"GB",
    "sg:address":"75 Mariners Way",
    "sg:city":"Maldon",
    "sg:classifiers":[
        {
            "category":"Manufacturing",
            "subcategory":"Wood Products",
            "type":"Manufacturing & Wholesale Goods"
        },
        {
            "category":"Manufacturing",
            "subcategory":"Paper Products",
            "type":"Manufacturing & Wholesale Goods"
        }
    ],
    "sg:phone":"+44 1621 854100",
    "sg:postcode":"CM9 6YX",
    "sg:province":"Essex",
    "sg:tags":[
        "packaging",
        "material",
        "crate",
        "pallets",
        "manufacturer"
    ],
    "wof:name":"Maldon Packaging",
    "wof:placetype":"venue"
},
  "geometry": {"coordinates":[0.68504,51.719528],"type":"Point"}
}