{
  "type": "Feature",
  "properties": {
    "addr:full":"James Street Market Bradford West Yorkshire BD1 3QB",
    "addr:postcode":"bd1 3qb",
    "addr:street":"James Street;Bradford West",
    "iso:country":"GB",
    "sg:address":"James Street Market",
    "sg:city":"Bradford",
    "sg:classifiers":[
        {
            "category":"Farming",
            "subcategory":"Fish & Marine Products",
            "type":"Manufacturing & Wholesale Goods"
        }
    ],
    "sg:postcode":"BD1 3QB",
    "sg:province":"West Yorkshire",
    "sg:tags":[
        "fishmonger"
    ],
    "wof:name":"W & J M Burn",
    "wof:placetype":"venue"
},
  "geometry": {"coordinates":[-1.756354,53.795528],"type":"Point"}
}