{
  "type": "Feature",
  "properties": {
    "addr:full":"Birmingham Rd, Allesley Coventry West Midlands CV5 9GQ",
    "addr:postcode":"cv5 9gq",
    "addr:street":"Birmingham Rd",
    "iso:country":"GB",
    "sg:address":"Birmingham Rd, Allesley",
    "sg:city":"Coventry",
    "sg:classifiers":[
        {
            "category":"Autos & Motor Vehicles",
            "subcategory":"Automobile Sales",
            "type":"Retail Goods"
        }
    ],
    "sg:phone":"+44 24 7640 4433",
    "sg:postcode":"CV5 9GQ",
    "sg:province":"West Midlands",
    "sg:tags":[
        "car"
    ],
    "wof:name":"Ixion Motor Group Ltd",
    "wof:placetype":"venue"
},
  "geometry": {"coordinates":[-1.604842,52.435364],"type":"Point"}
}