{
  "type": "Feature",
  "properties": {
    "iso:country":"GB",
    "sg:address":"13 Rowand Avenue, Giffnock",
    "sg:city":"Glasgow",
    "sg:classifiers":[
        {
            "category":"Building & Trades",
            "subcategory":"Landscaping Services",
            "type":"Services"
        }
    ],
    "sg:postcode":"G46 7PE",
    "sg:province":"East Renfrewshire",
    "sg:tags":[
        "designer",
        "architect",
        "landscape"
    ],
    "wof:name":"Terra Verde Design",
    "wof:placetype":"venue"
},
  "geometry": {"coordinates":[-4.297554,55.803181],"type":"Point"}
}