{
  "type": "Feature",
  "properties": {
    "addr:full":"Oudle Lane Much Hadham Hertfordshire SG10 6DQ",
    "addr:postcode":"sg10 6dq",
    "addr:street":"Oudle Lane",
    "iso:country":"GB",
    "sg:address":"Oudle Lane",
    "sg:city":"Much Hadham",
    "sg:classifiers":[
        {
            "category":"Education",
            "subcategory":"Preschool",
            "type":"Public Place"
        }
    ],
    "sg:phone":"+44 1279 842614",
    "sg:postcode":"SG10 6DQ",
    "sg:province":"Hertfordshire",
    "sg:tags":[
        "pre",
        "school",
        "playgroups",
        "pre-school"
    ],
    "wof:name":"Much Hadham Playgroup",
    "wof:placetype":"venue"
},
  "geometry": {"coordinates":[0.0736519992,51.8510551453],"type":"Point"}
}