{
  "type": "Feature",
  "properties": {
    "addr:full":"5 Townfields Crescent Winsford Cheshire CW7 1EJ",
    "addr:housenumber":"5",
    "addr:postcode":"cw7 1ej",
    "addr:street":"Townfields Crescent",
    "iso:country":"GB",
    "sg:address":"5 Townfields Crescent",
    "sg:city":"Winsford",
    "sg:classifiers":[
        {
            "category":"Building & Trades",
            "subcategory":"Cleaning & Sanitation",
            "type":"Services"
        }
    ],
    "sg:postcode":"CW7 1EJ",
    "sg:province":"Cheshire",
    "sg:tags":[
        "hygiene",
        "cleansing"
    ],
    "wof:name":"A D Pumps",
    "wof:placetype":"venue"
},
  "geometry": {"coordinates":[-2.530639,53.183865],"type":"Point"}
}