{
  "type": "Feature",
  "properties": {
    "addr:full":"301 Uppingham Rd Leicester Leicestershire LE5 4DG",
    "addr:housenumber":"301",
    "addr:postcode":"le5 4dg",
    "addr:street":"Uppingham Rd",
    "iso:country":"GB",
    "sg:address":"301 Uppingham Rd",
    "sg:city":"Leicester",
    "sg:classifiers":[
        {
            "category":"Manufacturing",
            "subcategory":"Textiles",
            "type":"Manufacturing & Wholesale Goods"
        }
    ],
    "sg:postcode":"LE5 4DG",
    "sg:province":"Leicestershire",
    "sg:tags":[
        "dyer",
        "printer"
    ],
    "wof:name":"Partex (U K) Ltd",
    "wof:placetype":"venue"
},
  "geometry": {"coordinates":[-1.0862649679,52.6419639587],"type":"Point"}
}