{
  "type": "Feature",
  "properties": {
    "iso:country":"GB",
    "sg:address":"P O Box 72",
    "sg:city":"Whitley Bay",
    "sg:classifiers":[
        {
            "category":"Professional",
            "subcategory":"Art Services",
            "type":"Services"
        },
        {
            "category":"Home & Garden",
            "subcategory":"Furniture",
            "type":"Retail Goods"
        }
    ],
    "sg:phone":"+44 191 291 1157",
    "sg:postcode":"NE25 9YL",
    "sg:province":"Northumberland",
    "sg:tags":[
        "framing"
    ],
    "wof:name":"Times Past",
    "wof:placetype":"venue"
},
  "geometry": {"coordinates":[-1.495919,55.046585],"type":"Point"}
}