{
  "type": "Feature",
  "properties": {
    "iso:country":"GB",
    "sg:address":"12 Larchmere Drive, Essington",
    "sg:city":"Wolverhampton",
    "sg:classifiers":[
        {
            "category":"Building & Trades",
            "subcategory":"Construction",
            "type":"Services"
        }
    ],
    "sg:phone":"+44 1922 402566",
    "sg:postcode":"WV11 2DG",
    "sg:province":"Staffordshire",
    "sg:tags":[
        "decorator",
        "painter"
    ],
    "wof:name":"George Chesters Painters & Decorators",
    "wof:placetype":"venue"
},
  "geometry": {"coordinates":[-2.0521519184,52.6271705627],"type":"Point"}
}