{
  "type": "Feature",
  "properties": {
    "addr:full":"Cross Roads Farm Kennels, Caistor Road, Middle Rasen Market Rasen Lincolnshire LN8 3JE",
    "addr:postcode":"ln8 3je",
    "addr:street":"Cross Roads;Caistor Road Middle",
    "iso:country":"GB",
    "sg:address":"Cross Roads Farm Kennels, Caistor Road, Middle Rasen",
    "sg:city":"Market Rasen",
    "sg:classifiers":[
        {
            "category":"Transit Center",
            "subcategory":"Passenger",
            "type":"Transportation"
        },
        {
            "category":"Retail",
            "subcategory":"Pet Boarding",
            "type":"Services"
        }
    ],
    "sg:phone":"+44 1673 842469",
    "sg:postcode":"LN8 3JE",
    "sg:province":"Lincolnshire",
    "sg:tags":[
        "kennel",
        "catteries"
    ],
    "wof:name":"Cross Roads Farm Kennels",
    "wof:placetype":"venue"
},
  "geometry": {"coordinates":[-0.3382480145,53.3890762329],"type":"Point"}
}