{
  "type": "Feature",
  "properties": {
    "addr:full":"9 Charborough Rd Broadstone Dorset BH18 8NE",
    "addr:housenumber":"9",
    "addr:postcode":"bh18 8ne",
    "addr:street":"Charborough Rd",
    "iso:country":"GB",
    "sg:address":"9 Charborough Rd",
    "sg:city":"Broadstone",
    "sg:classifiers":[
        {
            "category":"Professional",
            "subcategory":"Management & Consulting",
            "type":"Services"
        }
    ],
    "sg:phone":"+44 1202 697909",
    "sg:postcode":"BH18 8NE",
    "sg:province":"Dorset",
    "sg:tags":[
        "consultant",
        "business"
    ],
    "wof:name":"Business Solutions",
    "wof:placetype":"venue"
},
  "geometry": {"coordinates":[-1.991686,50.758766],"type":"Point"}
}