{
  "type": "Feature",
  "properties": {
    "addr:full":"6a Poland Street West End Hampshire W1V 3DG",
    "addr:housenumber":"6a",
    "addr:postcode":"w1v 3dg",
    "addr:street":"Poland Street",
    "iso:country":"GB",
    "sg:address":"6a Poland Street",
    "sg:city":"West End",
    "sg:classifiers":[
        {
            "category":"Professional",
            "subcategory":"Advertising",
            "type":"Services"
        }
    ],
    "sg:phone":"+44 20 7734 0599",
    "sg:postcode":"W1V 3DG",
    "sg:province":"Hampshire",
    "sg:tags":[
        "medium"
    ],
    "wof:name":"The Clinic",
    "wof:placetype":"venue"
},
  "geometry": {"coordinates":[-0.1389899999,51.5075798035],"type":"Point"}
}