{
  "type": "Feature",
  "properties": {
    "iso:country":"GB",
    "sg:address":"14 Station Road",
    "sg:city":"South Brent",
    "sg:classifiers":[
        {
            "category":"Shopping",
            "subcategory":"Florist",
            "type":"Retail Goods"
        }
    ],
    "sg:phone":"+44 1364 72751",
    "sg:postcode":"TQ10 9BE",
    "sg:province":"Devon",
    "wof:name":"South Brent Flowers",
    "wof:placetype":"venue"
},
  "geometry": {"coordinates":[-3.833354,50.427444],"type":"Point"}
}