{
  "type": "Feature",
  "properties": {
    "addr:full":"1 Walkways Canvey Island Essex SS8 9TN",
    "addr:housenumber":"1",
    "addr:postcode":"ss8 9tn",
    "addr:street":"Walkways Canvey Island",
    "iso:country":"GB",
    "sg:address":"1 Walkways",
    "sg:city":"Canvey Island",
    "sg:classifiers":[
        {
            "category":"Wholesale",
            "subcategory":"Construction Materials",
            "type":"Manufacturing & Wholesale Goods"
        },
        {
            "category":"Building & Trades",
            "subcategory":"Construction",
            "type":"Services"
        }
    ],
    "sg:postcode":"SS8 9TN",
    "sg:province":"Essex",
    "sg:tags":[
        "merchant",
        "glass",
        "glazier"
    ],
    "wof:name":"S B Watson Glazing Contractors",
    "wof:placetype":"venue"
},
  "geometry": {"coordinates":[0.575815,51.528389],"type":"Point"}
}