{
  "type": "Feature",
  "properties": {
    "iso:country":"GB",
    "sg:address":"2 Wolsley Road",
    "sg:city":"Blackpool",
    "sg:classifiers":[
        {
            "category":"Travel",
            "subcategory":"Hotels & Motels",
            "type":"Entertainment"
        }
    ],
    "sg:postcode":"FY1 6HG",
    "sg:province":"Lancashire",
    "sg:tags":[
        "house",
        "self",
        "guest",
        "catering"
    ],
    "wof:name":"Wolsley Holiday Flats",
    "wof:placetype":"venue"
},
  "geometry": {"coordinates":[-3.0501151085,53.7998390198],"type":"Point"}
}