{
  "type": "Feature",
  "properties": {
    "iso:country":"GB",
    "sg:address":"Unit 4 Coke Street",
    "sg:city":"Derby",
    "sg:classifiers":[
        {
            "category":"Retail",
            "subcategory":"Auto Repair",
            "type":"Services"
        }
    ],
    "sg:phone":"+44 1332 297311",
    "sg:postcode":"DE1 1NE",
    "sg:province":"Derbyshire",
    "sg:tags":[
        "modification",
        "garage"
    ],
    "wof:name":"Jaguar Specialists",
    "wof:placetype":"venue"
},
  "geometry": {"coordinates":[-1.496959,52.920513],"type":"Point"}
}