{
  "type": "Feature",
  "properties": {
    "iso:country":"GB",
    "sg:address":"High Street, Brookland",
    "sg:city":"Romney Marsh",
    "sg:classifiers":[
        {
            "category":"Manufacturing",
            "subcategory":"Tools & Machinery",
            "type":"Manufacturing & Wholesale Goods"
        }
    ],
    "sg:phone":"+44 1797 344433",
    "sg:postcode":"TN29 9QR",
    "sg:province":"Kent",
    "sg:tags":[
        "society",
        "friendly"
    ],
    "wof:name":"Counter & Co. (Adjusters) Ltd.",
    "wof:placetype":"venue"
},
  "geometry": {"coordinates":[0.834711,50.997852],"type":"Point"}
}