{
  "type": "Feature",
  "properties": {
    "addr:full":"Eastwood Road North Leigh-on-sea Essex SS9 4LS",
    "addr:postcode":"ss9 4ls",
    "addr:street":"Eastwood Road North",
    "iso:country":"GB",
    "sg:address":"Eastwood Road North",
    "sg:city":"Leigh-on-sea",
    "sg:classifiers":[
        {
            "category":"Arena",
            "subcategory":"Sports Club",
            "type":"Entertainment"
        }
    ],
    "sg:phone":"+44 1702 421077",
    "sg:postcode":"SS9 4LS",
    "sg:province":"Essex",
    "wof:name":"Southend Hockey Club",
    "wof:placetype":"venue"
},
  "geometry": {"coordinates":[0.6629710197,51.5621604919],"type":"Point"}
}