{
  "type": "Feature",
  "properties": {
    "addr:full":"2 Victoria Road Dundee Dundee City DD1 1JQ",
    "addr:housenumber":"2",
    "addr:postcode":"dd1 1jq",
    "addr:street":"Victoria Road",
    "iso:country":"GB",
    "sg:address":"2 Victoria Road",
    "sg:city":"Dundee",
    "sg:classifiers":[
        {
            "category":"Real Estate",
            "subcategory":"Real Estate Operator",
            "type":"Services"
        }
    ],
    "sg:phone":"+44 1382 206363",
    "sg:postcode":"DD1 1JQ",
    "sg:province":"Dundee City",
    "sg:tags":[
        "letting",
        "agent"
    ],
    "wof:name":"Forthtay Property Factors",
    "wof:placetype":"venue"
},
  "geometry": {"coordinates":[-2.9717819691,56.4638786316],"type":"Point"}
}