{
  "type": "Feature",
  "properties": {
    "addr:full":"7 Lord Street Gainsborough Lincolnshire DN21 2DF",
    "addr:housenumber":"7",
    "addr:postcode":"dn21 2df",
    "addr:street":"Lord Street",
    "iso:country":"GB",
    "sg:address":"7 Lord Street",
    "sg:city":"Gainsborough",
    "sg:classifiers":[
        {
            "category":"Professional",
            "subcategory":"Lawyer & Legal Services",
            "type":"Services"
        }
    ],
    "sg:phone":"+44 1427 611722",
    "sg:postcode":"DN21 2DF",
    "sg:province":"Lincolnshire",
    "sg:tags":[
        "solicitor"
    ],
    "wof:name":"Bell Wright & Dollman",
    "wof:placetype":"venue"
},
  "geometry": {"coordinates":[-0.778261,53.399807],"type":"Point"}
}