{
  "type": "Feature",
  "properties": {
    "addr:full":"19 East Morton Street Thornhill Dumfries and Galloway DG3 5LZ",
    "addr:housenumber":"19",
    "addr:postcode":"dg3 5lz",
    "addr:street":"East Morton Street",
    "iso:country":"GB",
    "sg:address":"19 East Morton Street",
    "sg:city":"Thornhill",
    "sg:classifiers":[
        {
            "category":"Home & Garden",
            "subcategory":"Kitchen Supply",
            "type":"Retail Goods"
        }
    ],
    "sg:phone":"+44 1848 331553",
    "sg:postcode":"DG3 5LZ",
    "sg:province":"Dumfries and Galloway",
    "sg:tags":[
        "glassware",
        "china"
    ],
    "wof:name":"Chintz & China",
    "wof:placetype":"venue"
},
  "geometry": {"coordinates":[-3.763768,55.241302],"type":"Point"}
}