{
  "type": "Feature",
  "properties": {
    "addr:full":"23 Mill Street Mansfield Nottinghamshire NG18 2PQ",
    "addr:housenumber":"23",
    "addr:postcode":"ng18 2pq",
    "addr:street":"Mill Street",
    "iso:country":"GB",
    "sg:address":"23 Mill Street",
    "sg:city":"Mansfield",
    "sg:classifiers":[
        {
            "category":"Organizations",
            "subcategory":"Religious Organization",
            "type":"Services"
        }
    ],
    "sg:phone":"+44 1623 642040",
    "sg:postcode":"NG18 2PQ",
    "sg:province":"Nottinghamshire",
    "sg:tags":[
        "organisation",
        "place",
        "worship"
    ],
    "wof:name":"Jehovah's Witnesses",
    "wof:placetype":"venue"
},
  "geometry": {"coordinates":[-1.1820950508,53.1411857605],"type":"Point"}
}