{
  "type": "Feature",
  "properties": {
    "addr:full":"Suite 430, 80 High St Winchester Hampshire SO23 9AT",
    "addr:housenumber":"suite 430 80",
    "addr:postcode":"so23 9at",
    "addr:street":"High St",
    "iso:country":"GB",
    "sg:address":"Suite 430, 80 High St",
    "sg:city":"Winchester",
    "sg:classifiers":[
        {
            "category":"Professional",
            "subcategory":"Management & Consulting",
            "type":"Services"
        }
    ],
    "sg:phone":"+44 1962 842060",
    "sg:postcode":"SO23 9AT",
    "sg:province":"Hampshire",
    "sg:tags":[
        "consultant",
        "business"
    ],
    "wof:name":"Satex Corporate Services",
    "wof:placetype":"venue"
},
  "geometry": {"coordinates":[-1.318579,51.06356],"type":"Point"}
}