{
  "type": "Feature",
  "properties": {
    "iso:country":"GB",
    "sg:address":"4a St Catherines Road",
    "sg:city":"Perth",
    "sg:classifiers":[
        {
            "category":"Arena",
            "subcategory":"Sports Club",
            "type":"Entertainment"
        }
    ],
    "sg:phone":"+44 1738 638227",
    "sg:postcode":"PH1 5SE",
    "sg:province":"Perth and Kinross",
    "wof:name":"The Mountaineering Council of Scotland",
    "wof:placetype":"venue"
},
  "geometry": {"coordinates":[-3.439025,56.39835],"type":"Point"}
}