{
  "type": "Feature",
  "properties": {
    "addr:full":"77 London Road, Waterlooville Portsmouth Hampshire PO7 7EL",
    "addr:housenumber":"77",
    "addr:postcode":"hampshire po7 7el",
    "addr:street":"London Road",
    "iso:country":"GB",
    "sg:address":"77 London Road, Waterlooville",
    "sg:city":"Portsmouth",
    "sg:classifiers":[
        {
            "category":"Shopping",
            "subcategory":"News",
            "type":"Retail Goods"
        }
    ],
    "sg:phone":"+44 23 9226 2110",
    "sg:postcode":"PO7 7EL",
    "sg:province":"Hampshire",
    "sg:tags":[
        "newsagent"
    ],
    "wof:name":"Falcon Mews",
    "wof:placetype":"venue"
},
  "geometry": {"coordinates":[-1.0333310366,50.8786201477],"type":"Point"}
}