{
  "type": "Feature",
  "properties": {
    "addr:full":"Unit 23, Bonds Mill, Bristol Road Stonehouse Gloucestershire GL10 3RG",
    "addr:housenumber":"unit 23",
    "addr:postcode":"gl10 3rg",
    "addr:street":"Bonds Mill Bristol Road",
    "iso:country":"GB",
    "sg:address":"Unit 23, Bonds Mill, Bristol Road",
    "sg:city":"Stonehouse",
    "sg:classifiers":[
        {
            "category":"Government",
            "subcategory":"Post Office",
            "type":"Public Place"
        }
    ],
    "sg:phone":"+44 1453 825623",
    "sg:postcode":"GL10 3RG",
    "sg:province":"Gloucestershire",
    "sg:tags":[
        "print",
        "typesetter"
    ],
    "wof:name":"Gloucester Typesetting Services",
    "wof:placetype":"venue"
},
  "geometry": {"coordinates":[-2.299894,51.746845],"type":"Point"}
}