{
  "type": "Feature",
  "properties": {
    "addr:full":"492 New Cross Road London Greater London SE14 6TJ",
    "addr:housenumber":"492",
    "addr:postcode":"se14 6tj",
    "addr:street":"New Cross Road",
    "iso:country":"GB",
    "sg:address":"492 New Cross Road",
    "sg:city":"London",
    "sg:classifiers":[
        {
            "category":"Restaurant",
            "type":"Food & Drink"
        }
    ],
    "sg:phone":"+44 20 8692 4904",
    "sg:postcode":"SE14 6TJ",
    "sg:province":"Greater London",
    "wof:name":"London Kebab House",
    "wof:placetype":"venue"
},
  "geometry": {"coordinates":[-0.02741,51.475056],"type":"Point"}
}