{
  "type": "Feature",
  "properties": {
    "addr:full":"27 Whitecraigs Kinross Clackmannanshire KY13 7JN",
    "addr:housenumber":"27",
    "addr:postcode":"ky13 7jn",
    "addr:street":"Whitecraigs Kinross",
    "iso:country":"GB",
    "sg:address":"27 Whitecraigs",
    "sg:city":"Kinross",
    "sg:classifiers":[
        {
            "category":"Utilities",
            "type":"Services"
        }
    ],
    "sg:phone":"+44 1592 840751",
    "sg:postcode":"KY13 7JN",
    "sg:province":"Clackmannanshire",
    "sg:tags":[
        "internet"
    ],
    "wof:name":"Shine Design",
    "wof:placetype":"venue"
},
  "geometry": {"coordinates":[-3.32584,56.210911],"type":"Point"}
}