{
  "type": "Feature",
  "properties": {
    "iso:country":"GB",
    "sg:address":"Unit 7d, Marsh Lane Trading Estate, Henstridge",
    "sg:city":"Templecombe",
    "sg:classifiers":[
        {
            "category":"Retail",
            "subcategory":"Auto Repair",
            "type":"Services"
        }
    ],
    "sg:phone":"+44 1963 362464",
    "sg:postcode":"BA8 0TG",
    "sg:province":"Somerset",
    "sg:tags":[
        "engine",
        "car",
        "specialist"
    ],
    "wof:name":"Auto Gas Services",
    "wof:placetype":"venue"
},
  "geometry": {"coordinates":[-2.370646,50.980526],"type":"Point"}
}