{
  "type": "Feature",
  "properties": {
    "iso:country":"GB",
    "sg:address":"42 Staddon Park Road, Plymstock",
    "sg:city":"Plymouth",
    "sg:classifiers":[
        {
            "category":"Home & Garden",
            "subcategory":"Household Appliances",
            "type":"Retail Goods"
        }
    ],
    "sg:phone":"+44 1752 408548",
    "sg:postcode":"PL9 9HG",
    "sg:province":"Devon",
    "sg:tags":[
        "electrical"
    ],
    "wof:name":"Rapid Repairs",
    "wof:placetype":"venue"
},
  "geometry": {"coordinates":[-4.0893850327,50.3540267944],"type":"Point"}
}