{
  "type": "Feature",
  "properties": {
    "addr:full":"Factory, 117 Grosvenor Road Rugby Warwickshire CV21 3LE",
    "addr:housenumber":"117",
    "addr:postcode":"cv21 3le",
    "addr:street":"Grosvenor Road",
    "iso:country":"GB",
    "sg:address":"Factory, 117 Grosvenor Road",
    "sg:city":"Rugby",
    "sg:classifiers":[
        {
            "category":"Wholesale",
            "subcategory":"Scrap",
            "type":"Manufacturing & Wholesale Goods"
        }
    ],
    "sg:phone":"+44 1788 822551",
    "sg:postcode":"CV21 3LE",
    "sg:province":"Warwickshire",
    "sg:tags":[
        "waste",
        "metal"
    ],
    "wof:name":"Rugby Trading International",
    "wof:placetype":"venue"
},
  "geometry": {"coordinates":[-1.2515399456,52.3746795654],"type":"Point"}
}