{
  "type": "Feature",
  "properties": {
    "iso:country":"GB",
    "sg:address":"8 Gotsfield Clo, Acton",
    "sg:city":"Sudbury",
    "sg:classifiers":[
        {
            "category":"Government",
            "subcategory":"Office",
            "type":"Public Place"
        }
    ],
    "sg:postcode":"CO10 0AS",
    "sg:province":"Essex",
    "sg:tags":[
        "chamber",
        "commerce"
    ],
    "wof:name":"Sudbury Chamber of Commerce",
    "wof:placetype":"venue"
},
  "geometry": {"coordinates":[0.76348,52.070969],"type":"Point"}
}