{
  "type": "Feature",
  "properties": {
    "addr:full":"7 Redearth Road Darwen Lancashire BB3 2AB",
    "addr:housenumber":"7",
    "addr:postcode":"bb3 2ab",
    "addr:street":"Redearth Road",
    "iso:country":"GB",
    "sg:address":"7 Redearth Road",
    "sg:city":"Darwen",
    "sg:classifiers":[
        {
            "category":"Fast Food",
            "type":"Food & Drink"
        }
    ],
    "sg:postcode":"BB3 2AB",
    "sg:province":"Lancashire",
    "sg:tags":[
        "delivery"
    ],
    "wof:name":"Pizza Palace",
    "wof:placetype":"venue"
},
  "geometry": {"coordinates":[-2.465156,53.693859],"type":"Point"}
}