{
  "type": "Feature",
  "properties": {
    "iso:country":"GB",
    "sg:address":"Unit K5 The Cresset, Bretton Centre",
    "sg:city":"Peterborough",
    "sg:classifiers":[
        {
            "category":"Shopping",
            "subcategory":"Hobbies, Toys, & Games",
            "type":"Retail Goods"
        }
    ],
    "sg:postcode":"PE3 8DX",
    "sg:province":"Cambridgeshire",
    "sg:tags":[
        "stamp"
    ],
    "wof:name":"Filan Stamps & Models",
    "wof:placetype":"venue"
},
  "geometry": {"coordinates":[-0.288839,52.6008],"type":"Point"}
}