{
  "type": "Feature",
  "properties": {
    "addr:full":"192 Bedminster Down Road Bristol City of Bristol BS13 7AF",
    "addr:housenumber":"192",
    "addr:postcode":"bs13 7af",
    "addr:street":"Bedminster Down Road",
    "iso:country":"GB",
    "sg:address":"192 Bedminster Down Road",
    "sg:city":"Bristol",
    "sg:classifiers":[
        {
            "category":"Utilities",
            "type":"Services"
        }
    ],
    "sg:phone":"+44 117 905 5166",
    "sg:postcode":"BS13 7AF",
    "sg:province":"City of Bristol",
    "sg:tags":[
        "internet"
    ],
    "wof:name":"Internet Design Ltd.",
    "wof:placetype":"venue"
},
  "geometry": {"coordinates":[-2.610785,51.432796],"type":"Point"}
}