{
  "type": "Feature",
  "properties": {
    "iso:country":"GB",
    "sg:address":"717c Green Lanes, Winchmore Hill",
    "sg:city":"London",
    "sg:classifiers":[
        {
            "category":"Real Estate",
            "subcategory":"Real Estate Agent",
            "type":"Services"
        }
    ],
    "sg:phone":"+44 20 8364 1616",
    "sg:postcode":"N21 3RX",
    "sg:province":"Greater London",
    "wof:name":"Sable Estates Ltd.",
    "wof:placetype":"venue"
},
  "geometry": {"coordinates":[-0.096681,51.630886],"type":"Point"}
}