{
  "type": "Feature",
  "properties": {
    "iso:country":"GB",
    "sg:address":"Open House Centre, Manvers St",
    "sg:city":"Bath",
    "sg:classifiers":[
        {
            "category":"Health Services",
            "subcategory":"Health Practitioner",
            "type":"Services"
        }
    ],
    "sg:phone":"+44 1225 481297",
    "sg:postcode":"BA1 1JW",
    "sg:province":"Bath and North East Somerset",
    "sg:tags":[
        "psychotherapist"
    ],
    "wof:name":"B J McLoughlin",
    "wof:placetype":"venue"
},
  "geometry": {"coordinates":[-2.357044,51.378284],"type":"Point"}
}