{
  "type": "Feature",
  "properties": {
    "addr:full":"474 Woodchurch Road Prenton Merseyside CH43 0SE",
    "addr:housenumber":"474",
    "addr:postcode":"ch43 0se",
    "addr:street":"Woodchurch Road",
    "iso:country":"GB",
    "sg:address":"474 Woodchurch Road",
    "sg:city":"Prenton",
    "sg:classifiers":[
        {
            "category":"Autos & Motor Vehicles",
            "subcategory":"Automobile Sales",
            "type":"Retail Goods"
        }
    ],
    "sg:phone":"+44 151 608 9933",
    "sg:postcode":"CH43 0SE",
    "sg:province":"Merseyside",
    "sg:tags":[
        "car"
    ],
    "wof:name":"Scopecode Ltd",
    "wof:placetype":"venue"
},
  "geometry": {"coordinates":[-3.056039,53.372337],"type":"Point"}
}