{
  "type": "Feature",
  "properties": {
    "iso:country":"GB",
    "sg:address":"2331 Great Western Road",
    "sg:city":"Glasgow",
    "sg:classifiers":[
        {
            "category":"Retail",
            "subcategory":"Auto Repair",
            "type":"Services"
        }
    ],
    "sg:phone":"+44 141 944 0120",
    "sg:postcode":"G15 6RT",
    "sg:province":"Glasgow City",
    "sg:tags":[
        "modification",
        "garage",
        "related"
    ],
    "wof:name":"Blairdardie Service Station",
    "wof:placetype":"venue"
},
  "geometry": {"coordinates":[-4.370385,55.900204],"type":"Point"}
}