{
  "type": "Feature",
  "properties": {
    "iso:country":"GB",
    "sg:address":"Lunsford Yard, Potmans Lane, Catsfield",
    "sg:city":"Battle",
    "sg:classifiers":[
        {
            "category":"Building & Trades",
            "subcategory":"Landscaping Services",
            "type":"Services"
        }
    ],
    "sg:phone":"+44 1424 893166",
    "sg:postcode":"TN33 9BJ",
    "sg:province":"East Sussex",
    "sg:tags":[
        "forestry",
        "tree"
    ],
    "wof:name":"Bexhill Tree Surgeons",
    "wof:placetype":"venue"
},
  "geometry": {"coordinates":[0.44803,50.896187],"type":"Point"}
}