{
  "type": "Feature",
  "properties": {
    "iso:country":"GB",
    "sg:address":"2 Ling Bob",
    "sg:city":"Halifax",
    "sg:classifiers":[
        {
            "category":"Shopping",
            "subcategory":"News",
            "type":"Retail Goods"
        }
    ],
    "sg:phone":"+44 1422 353805",
    "sg:postcode":"HX2 0QE",
    "sg:province":"West Yorkshire",
    "sg:tags":[
        "newsagent"
    ],
    "wof:name":"Pellow News",
    "wof:placetype":"venue"
},
  "geometry": {"coordinates":[-1.8974430561,53.7282485962],"type":"Point"}
}