{
  "type": "Feature",
  "properties": {
    "iso:country":"GB",
    "sg:address":"223a Hatfield Rd",
    "sg:city":"St Albans",
    "sg:classifiers":[
        {
            "category":"Manufacturing",
            "subcategory":"Tools & Machinery",
            "type":"Manufacturing & Wholesale Goods"
        }
    ],
    "sg:postcode":"AL1 4TB",
    "sg:province":"Hertfordshire",
    "sg:tags":[
        "society",
        "friendly"
    ],
    "wof:name":"Holman,E G,",
    "wof:placetype":"venue"
},
  "geometry": {"coordinates":[-0.309991,51.752121],"type":"Point"}
}