{
  "type": "Feature",
  "properties": {
    "addr:full":"20 Vicarage Fields Hailsham East Sussex BN27 1BE",
    "addr:housenumber":"20",
    "addr:postcode":"bn27 1be",
    "addr:street":"Vicarage Fields",
    "iso:country":"GB",
    "sg:address":"20 Vicarage Fields",
    "sg:city":"Hailsham",
    "sg:classifiers":[
        {
            "category":"Shopping",
            "subcategory":"Shoes",
            "type":"Retail Goods"
        }
    ],
    "sg:phone":"+44 1323 442297",
    "sg:postcode":"BN27 1BE",
    "sg:province":"East Sussex",
    "wof:name":"Nodding Cobbler Hailsham",
    "wof:placetype":"venue"
},
  "geometry": {"coordinates":[0.259613,50.863274],"type":"Point"}
}