{
  "type": "Feature",
  "properties": {
    "addr:full":"5 Pockocks Close Bampton Gloucestershire OX18 2JY",
    "addr:housenumber":"5",
    "addr:postcode":"ox18 2jy",
    "addr:street":"Pockocks Close",
    "iso:country":"GB",
    "sg:address":"5 Pockocks Close",
    "sg:city":"Bampton",
    "sg:classifiers":[
        {
            "category":"Home & Garden",
            "subcategory":"Garden Supply",
            "type":"Retail Goods"
        },
        {
            "category":"Home & Garden",
            "subcategory":"Hardware",
            "type":"Retail Goods"
        }
    ],
    "sg:phone":"+44 1993 850927",
    "sg:postcode":"OX18 2JY",
    "sg:province":"Gloucestershire",
    "sg:tags":[
        "lawnmowers",
        "sales",
        "machinery"
    ],
    "wof:name":"Mister Mowerman",
    "wof:placetype":"venue"
},
  "geometry": {"coordinates":[-1.543222,51.728634],"type":"Point"}
}