{
  "type": "Feature",
  "properties": {
    "addr:full":"22 New Street Braintree Essex CM7 1ES",
    "addr:housenumber":"22",
    "addr:postcode":"cm7 1es",
    "addr:street":"New Street",
    "iso:country":"GB",
    "sg:address":"22 New Street",
    "sg:city":"Braintree",
    "sg:classifiers":[
        {
            "category":"Health Services",
            "subcategory":"Chiropractor",
            "type":"Services"
        }
    ],
    "sg:phone":"+44 1376 329129",
    "sg:postcode":"CM7 1ES",
    "sg:province":"Essex",
    "wof:name":"Crown Chiropractic Clinic",
    "wof:placetype":"venue"
},
  "geometry": {"coordinates":[0.5516499877,51.877368927],"type":"Point"}
}