{
  "type": "Feature",
  "properties": {
    "addr:full":"130 Nathan Way, West Thamesmead Business Park London Greater London SE28 0AU",
    "addr:housenumber":"130",
    "addr:postcode":"se28 0au",
    "addr:street":"Nathan Way West Thamesmead Business Park",
    "iso:country":"GB",
    "sg:address":"130 Nathan Way, West Thamesmead Business Park",
    "sg:city":"London",
    "sg:classifiers":[
        {
            "category":"Wholesale",
            "subcategory":"Machinery & Supplies",
            "type":"Manufacturing & Wholesale Goods"
        }
    ],
    "sg:phone":"+44 20 8854 4008",
    "sg:postcode":"SE28 0AU",
    "sg:province":"Greater London",
    "sg:tags":[
        "pump"
    ],
    "wof:name":"Angerstein Engineering Ltd.",
    "wof:placetype":"venue"
},
  "geometry": {"coordinates":[0.095395,51.494011],"type":"Point"}
}