{
  "type": "Feature",
  "properties": {
    "addr:full":"Unit B Poole Road Woking Surrey GU21 6DY",
    "addr:postcode":"gu21 6dy",
    "addr:street":"Poole Road",
    "iso:country":"GB",
    "sg:address":"Unit B Poole Road",
    "sg:city":"Woking",
    "sg:classifiers":[
        {
            "category":"Professional",
            "subcategory":"Engineering",
            "type":"Services"
        }
    ],
    "sg:phone":"+44 1483 773876",
    "sg:postcode":"GU21 6DY",
    "sg:province":"Surrey",
    "sg:tags":[
        "precision",
        "engineer"
    ],
    "wof:name":"Bennett D J Engineering",
    "wof:placetype":"venue"
},
  "geometry": {"coordinates":[-0.5585500002,51.3220748901],"type":"Point"}
}