{
  "type": "Feature",
  "properties": {
    "iso:country":"GB",
    "sg:address":"Sherwood Road",
    "sg:city":"Prestwick",
    "sg:classifiers":[
        {
            "category":"Education",
            "subcategory":"School",
            "type":"Public Place"
        },
        {
            "category":"Government",
            "subcategory":"Office",
            "type":"Public Place"
        }
    ],
    "sg:phone":"+44 1292 477918",
    "sg:postcode":"KA9 1EY",
    "sg:province":"South Ayrshire",
    "sg:tags":[
        "local",
        "authority"
    ],
    "wof:name":"Glenburn Primary School",
    "wof:placetype":"venue"
},
  "geometry": {"coordinates":[-4.598654,55.499805],"type":"Point"}
}