{
  "type": "Feature",
  "properties": {
    "addr:full":"21 'old' Northam Rd Southampton Hampshire SO14 0NZ",
    "addr:housenumber":"21",
    "addr:postcode":"so14 0nz",
    "addr:street":"' Old ' Northam Rd",
    "iso:country":"GB",
    "sg:address":"21 'old' Northam Rd",
    "sg:city":"Southampton",
    "sg:classifiers":[
        {
            "category":"Museum",
            "subcategory":"Art Museum",
            "type":"Entertainment"
        }
    ],
    "sg:phone":"+44 23 8021 1591",
    "sg:postcode":"SO14 0NZ",
    "sg:province":"Hampshire",
    "sg:tags":[
        "gallery"
    ],
    "wof:name":"Brompton Gallery",
    "wof:placetype":"venue"
},
  "geometry": {"coordinates":[-1.39532,50.907272],"type":"Point"}
}