{
  "type": "Feature",
  "properties": {
    "iso:country":"GB",
    "sg:address":"1 High St",
    "sg:city":"Maldon",
    "sg:classifiers":[
        {
            "category":"Shopping",
            "subcategory":"Department Store",
            "type":"Retail Goods"
        },
        {
            "category":"Shopping",
            "subcategory":"Bicycles & Sporting Goods",
            "type":"Retail Goods"
        }
    ],
    "sg:postcode":"CM9 5PB",
    "sg:province":"Essex",
    "sg:tags":[
        "accessory",
        "cycle"
    ],
    "wof:name":"Knight,John,",
    "wof:placetype":"venue"
},
  "geometry": {"coordinates":[0.6748560071,51.7314033508],"type":"Point"}
}