{
  "type": "Feature",
  "properties": {
    "addr:full":"44 High St Ventnor Isle of Wight PO38 1LT",
    "addr:housenumber":"44",
    "addr:postcode":"po38 1lt",
    "addr:street":"High St",
    "iso:country":"GB",
    "sg:address":"44 High St",
    "sg:city":"Ventnor",
    "sg:classifiers":[
        {
            "category":"Shopping",
            "subcategory":"Antiques",
            "type":"Retail Goods"
        }
    ],
    "sg:phone":"+44 1983 853955",
    "sg:postcode":"PO38 1LT",
    "sg:province":"Isle of Wight",
    "wof:name":"Sabine Antiques",
    "wof:placetype":"venue"
},
  "geometry": {"coordinates":[-1.203987,50.595432],"type":"Point"}
}