{
  "type": "Feature",
  "properties": {
    "addr:full":"38 Kingfield Road Sheffield Derbyshire S11 9AS",
    "addr:housenumber":"38",
    "addr:postcode":"s11 9as",
    "addr:street":"Kingfield Road",
    "iso:country":"GB",
    "sg:address":"38 Kingfield Road",
    "sg:city":"Sheffield",
    "sg:classifiers":[
        {
            "category":"Social Services",
            "subcategory":"Retirement Home",
            "type":"Services"
        }
    ],
    "sg:phone":"+44 114 255 3968",
    "sg:postcode":"S11 9AS",
    "sg:province":"Derbyshire",
    "sg:tags":[
        "rest"
    ],
    "wof:name":"Kingfield Holt",
    "wof:placetype":"venue"
},
  "geometry": {"coordinates":[-1.497066021,53.3632278442],"type":"Point"}
}