{
  "type": "Feature",
  "properties": {
    "addr:full":"Rear Of Sutton Timber, Hoghton Rd St Helens Cheshire WA9 3HS",
    "addr:housenumber":"rear of sutton",
    "addr:postcode":"wa9 3hs",
    "addr:street":"Timber Hoghton Rd",
    "iso:country":"GB",
    "sg:address":"Rear Of Sutton Timber, Hoghton Rd",
    "sg:city":"St Helens",
    "sg:classifiers":[
        {
            "category":"Home & Garden",
            "subcategory":"Building Materials",
            "type":"Retail Goods"
        }
    ],
    "sg:phone":"+44 1744 850261",
    "sg:postcode":"WA9 3HS",
    "sg:province":"Cheshire",
    "sg:tags":[
        "ready",
        "mixed",
        "concrete"
    ],
    "wof:name":"C.S.S Mini-Mix Concrete",
    "wof:placetype":"venue"
},
  "geometry": {"coordinates":[-2.69797,53.437511],"type":"Point"}
}