{
  "type": "Feature",
  "properties": {
    "iso:country":"GB",
    "sg:address":"106 Down House, Broomhill Road",
    "sg:city":"London",
    "sg:classifiers":[
        {
            "category":"Retail",
            "subcategory":"Event Space",
            "type":"Services"
        }
    ],
    "sg:postcode":"SW18 4JQ",
    "sg:province":"Greater London",
    "sg:tags":[
        "exhibition",
        "organiser"
    ],
    "wof:name":"Berber Events Ltd",
    "wof:placetype":"venue"
},
  "geometry": {"coordinates":[-0.19831,51.45686],"type":"Point"}
}