{
  "type": "Feature",
  "properties": {
    "addr:full":"Unit 12, Westgate Centre Stevenage Hertfordshire SG1 1QR",
    "addr:housenumber":"unit 12",
    "addr:postcode":"sg1 1qr",
    "addr:street":"Westgate Centre",
    "iso:country":"GB",
    "sg:address":"Unit 12, Westgate Centre",
    "sg:city":"Stevenage",
    "sg:classifiers":[
        {
            "category":"Shopping",
            "subcategory":"Clothing, Apparel, & Fashions",
            "type":"Retail Goods"
        }
    ],
    "sg:phone":"+44 1438 741287",
    "sg:postcode":"SG1 1QR",
    "sg:province":"Hertfordshire",
    "sg:tags":[
        "menswear"
    ],
    "wof:name":"Suit Company",
    "wof:placetype":"venue"
},
  "geometry": {"coordinates":[-0.1982789934,51.8993186951],"type":"Point"}
}