{
  "type": "Feature",
  "properties": {
    "iso:country":"GB",
    "sg:address":"3-5 Broad St",
    "sg:city":"Ottery St Mary",
    "sg:classifiers":[
        {
            "category":"Shopping",
            "subcategory":"Pharmacy",
            "type":"Retail Goods"
        }
    ],
    "sg:phone":"+44 1404 812503",
    "sg:postcode":"EX11 1BT",
    "sg:province":"Devon",
    "sg:tags":[
        "pharmacist",
        "chemist"
    ],
    "wof:name":"Ottery Pharmacy",
    "wof:placetype":"venue"
},
  "geometry": {"coordinates":[-3.279384,50.751156],"type":"Point"}
}