{
  "type": "Feature",
  "properties": {
    "addr:full":"447 Durham Road Gateshead Tyne and Wear NE9 5EX",
    "addr:housenumber":"447",
    "addr:postcode":"ne9 5ex",
    "addr:street":"Durham Road",
    "iso:country":"GB",
    "sg:address":"447 Durham Road",
    "sg:city":"Gateshead",
    "sg:classifiers":[
        {
            "category":"Food & Beverages",
            "subcategory":"Bakery",
            "type":"Retail Goods"
        }
    ],
    "sg:phone":"+44 191 482 0422",
    "sg:postcode":"NE9 5EX",
    "sg:province":"Tyne and Wear",
    "sg:tags":[
        "baker"
    ],
    "wof:name":"Gina's Bakery",
    "wof:placetype":"venue"
},
  "geometry": {"coordinates":[-1.5996249914,54.9368133545],"type":"Point"}
}