{
  "type": "Feature",
  "properties": {
    "addr:full":"Garmonette, Whitecroft Lydney Gloucestershire GL15 4QQ",
    "addr:postcode":"gl15 4qq",
    "addr:street":"Lydney",
    "iso:country":"GB",
    "sg:address":"Garmonette, Whitecroft",
    "sg:city":"Lydney",
    "sg:classifiers":[
        {
            "category":"Professional",
            "subcategory":"Art Services",
            "type":"Services"
        },
        {
            "category":"Manufacturing",
            "subcategory":"Paper Products",
            "type":"Manufacturing & Wholesale Goods"
        }
    ],
    "sg:phone":"+44 1594 562620",
    "sg:postcode":"GL15 4QQ",
    "sg:province":"Gloucestershire",
    "sg:tags":[
        "cardboard",
        "decorator",
        "painter"
    ],
    "wof:name":"Garnet Ruck",
    "wof:placetype":"venue"
},
  "geometry": {"coordinates":[-2.552493,51.75367],"type":"Point"}
}