{
  "type": "Feature",
  "properties": {
    "iso:country":"GB",
    "sg:address":"Alpha House 84 Chepstow Road",
    "sg:city":"Newport",
    "sg:classifiers":[
        {
            "category":"Professional",
            "subcategory":"Detective & Security Services",
            "type":"Services"
        }
    ],
    "sg:phone":"+44 1633 211876",
    "sg:postcode":"NP19 8ED",
    "sg:province":"Newport",
    "sg:tags":[
        "alarm",
        "burglar",
        "system"
    ],
    "wof:name":"Alpha Crime & Fire Prevention Ltd.",
    "wof:placetype":"venue"
},
  "geometry": {"coordinates":[-2.9826829433,51.5902175903],"type":"Point"}
}