{
  "type": "Feature",
  "properties": {
    "iso:country":"GB",
    "sg:address":"10 Cecil Lodge Close, Falmouth Avenue",
    "sg:city":"Newmarket",
    "sg:classifiers":[
        {
            "category":"Building & Trades",
            "subcategory":"Construction",
            "type":"Services"
        }
    ],
    "sg:postcode":"CB8 0ND",
    "sg:province":"Cambridgeshire",
    "sg:tags":[
        "builder"
    ],
    "wof:name":"Peter C Hedger",
    "wof:placetype":"venue"
},
  "geometry": {"coordinates":[0.3952310085,52.2414970398],"type":"Point"}
}