{
  "type": "Feature",
  "properties": {
    "addr:full":"Unit 5, Martin's Industrial Estate Oldbury West Midlands B69 4NL",
    "addr:housenumber":"unit 5",
    "addr:postcode":"b69 4nl",
    "addr:street":"Martin'S Industrial Estate Oldbury",
    "iso:country":"GB",
    "sg:address":"Unit 5, Martin's Industrial Estate",
    "sg:city":"Oldbury",
    "sg:classifiers":[
        {
            "category":"Real Estate",
            "subcategory":"Real Estate Agent",
            "type":"Services"
        }
    ],
    "sg:phone":"+44 121 552 5721",
    "sg:postcode":"B69 4NL",
    "sg:province":"West Midlands",
    "wof:name":"Hall Estates (Birmingham) Ltd.",
    "wof:placetype":"venue"
},
  "geometry": {"coordinates":[-2.0141019821,52.5033302307],"type":"Point"}
}