{
  "type": "Feature",
  "properties": {
    "iso:country":"GB",
    "sg:address":"3d Sopwith Crescent, Hurricane Way",
    "sg:city":"Wickford",
    "sg:classifiers":[
        {
            "category":"Building & Trades",
            "subcategory":"Construction",
            "type":"Services"
        }
    ],
    "sg:phone":"+44 1268 573388",
    "sg:postcode":"SS11 8YU",
    "sg:province":"Essex",
    "sg:tags":[
        "builder"
    ],
    "wof:name":"J M H Construction Ltd.",
    "wof:placetype":"venue"
},
  "geometry": {"coordinates":[0.548659,51.60104],"type":"Point"}
}