{
  "type": "Feature",
  "properties": {
    "iso:country":"GB",
    "sg:address":"141 Belle Vue Road",
    "sg:city":"Bournemouth",
    "sg:classifiers":[
        {
            "category":"Restaurant",
            "type":"Food & Drink"
        }
    ],
    "sg:postcode":"BH6 3EN",
    "sg:province":"Dorset",
    "wof:name":"La Fontaine",
    "wof:placetype":"venue"
},
  "geometry": {"coordinates":[-1.797223,50.721638],"type":"Point"}
}