{
  "type": "Feature",
  "properties": {
    "addr:full":"39 Cropley Street London Greater London N1 7JB",
    "addr:housenumber":"39",
    "addr:postcode":"n1 7jb",
    "addr:street":"Cropley Street",
    "iso:country":"GB",
    "sg:address":"39 Cropley Street",
    "sg:city":"London",
    "sg:classifiers":[
        {
            "category":"Professional",
            "subcategory":"Business Services",
            "type":"Services"
        }
    ],
    "sg:phone":"+44 20 7253 1304",
    "sg:postcode":"N1 7JB",
    "sg:province":"Greater London",
    "sg:tags":[
        "bookmaker"
    ],
    "wof:name":"The Bloxhams Bookmakers",
    "wof:placetype":"venue"
},
  "geometry": {"coordinates":[-0.0903339982,51.5328369141],"type":"Point"}
}