{
  "type": "Feature",
  "properties": {
    "addr:full":"104 Sandgate Road Folkestone Kent CT20 2BS",
    "addr:housenumber":"104",
    "addr:postcode":"ct20 2bs",
    "addr:street":"Sandgate Road",
    "iso:country":"GB",
    "sg:address":"104 Sandgate Road",
    "sg:city":"Folkestone",
    "sg:classifiers":[
        {
            "category":"Banks & Credit Unions",
            "subcategory":"Bank",
            "type":"Services"
        }
    ],
    "sg:phone":"+44 845 765 4321",
    "sg:postcode":"CT20 2BS",
    "sg:province":"Kent",
    "wof:name":"Abbey National Plc",
    "wof:placetype":"venue"
},
  "geometry": {"coordinates":[1.176095,51.078022],"type":"Point"}
}