{
  "type": "Feature",
  "properties": {
    "iso:country":"GB",
    "sg:address":"Rooksmoor, Woodchester",
    "sg:city":"Stroud",
    "sg:classifiers":[
        {
            "category":"Retail",
            "subcategory":"Auto Rental",
            "type":"Services"
        }
    ],
    "sg:phone":"+44 1453 873403",
    "sg:postcode":"GL5 5NE",
    "sg:province":"Gloucestershire",
    "sg:tags":[
        "car",
        "vehicle"
    ],
    "wof:name":"K W Oakey",
    "wof:placetype":"venue"
},
  "geometry": {"coordinates":[-2.2312,51.724079],"type":"Point"}
}