{
  "type": "Feature",
  "properties": {
    "addr:full":"1 Mylord Crescent, Camperdown Industrial Estate, Killingworth Newcastle-upon-tyne Tyne and Wear NE12 5UJ",
    "addr:housenumber":"1",
    "addr:postcode":"ne12 5uj",
    "addr:street":"Mylord Crescent;Industrial Estate",
    "iso:country":"GB",
    "sg:address":"1 Mylord Crescent, Camperdown Industrial Estate, Killingworth",
    "sg:city":"Newcastle-upon-tyne",
    "sg:classifiers":[
        {
            "category":"Professional",
            "subcategory":"Engineering",
            "type":"Services"
        }
    ],
    "sg:phone":"+44 191 216 0355",
    "sg:postcode":"NE12 5UJ",
    "sg:province":"Tyne and Wear",
    "sg:tags":[
        "contractor",
        "electrical",
        "engineer"
    ],
    "wof:name":"A E Fletcher (Electricals) Ltd.",
    "wof:placetype":"venue"
},
  "geometry": {"coordinates":[-1.5852199793,55.0422592163],"type":"Point"}
}