{
  "type": "Feature",
  "properties": {
    "addr:full":"Denton House, 40-44 Wicklow Street Bloomsbury Greater London WC1X 9HL",
    "addr:housenumber":"40-44",
    "addr:postcode":"wc1x 9hl",
    "addr:street":"Wicklow Street",
    "iso:country":"GB",
    "sg:address":"Denton House, 40-44 Wicklow Street",
    "sg:city":"Bloomsbury",
    "sg:classifiers":[
        {
            "category":"Banks & Credit Unions",
            "subcategory":"Financial Services",
            "type":"Services"
        }
    ],
    "sg:postcode":"WC1X 9HL",
    "sg:province":"Greater London",
    "sg:tags":[
        "consultant"
    ],
    "wof:name":"Civic Development Trust",
    "wof:placetype":"venue"
},
  "geometry": {"coordinates":[-0.119595,51.530174],"type":"Point"}
}