{
  "type": "Feature",
  "properties": {
    "iso:country":"GB",
    "sg:address":"Suite 60a Foster House, Maxwell Road",
    "sg:city":"Borehamwood",
    "sg:classifiers":[
        {
            "category":"Professional",
            "subcategory":"Accounting & Tax Preparation",
            "type":"Services"
        }
    ],
    "sg:postcode":"WD6 1JB",
    "sg:province":"Hertfordshire",
    "sg:tags":[
        "accountant"
    ],
    "wof:name":"David B Seear",
    "wof:placetype":"venue"
},
  "geometry": {"coordinates":[-0.266863,51.658474],"type":"Point"}
}