{
  "type": "Feature",
  "properties": {
    "addr:full":"39 Queenstown Road London Greater London SW8 3RF",
    "addr:housenumber":"39",
    "addr:postcode":"sw8 3rf",
    "addr:street":"Queenstown Road",
    "iso:country":"GB",
    "sg:address":"39 Queenstown Road",
    "sg:city":"London",
    "sg:classifiers":[
        {
            "category":"Restaurant",
            "type":"Food & Drink"
        }
    ],
    "sg:phone":"+44 20 7622 7228",
    "sg:postcode":"SW8 3RF",
    "sg:province":"Greater London",
    "sg:tags":[
        "indian"
    ],
    "wof:name":"Queens Star Tandoori Restaurant",
    "wof:placetype":"venue"
},
  "geometry": {"coordinates":[-0.1508260071,51.4674491882],"type":"Point"}
}