{
  "type": "Feature",
  "properties": {
    "iso:country":"GB",
    "sg:address":"47 Winsford Avenue",
    "sg:city":"Coventry",
    "sg:classifiers":[
        {
            "category":"Shopping",
            "subcategory":"News",
            "type":"Retail Goods"
        }
    ],
    "sg:phone":"+44 24 7667 3475",
    "sg:postcode":"CV5 9JG",
    "sg:province":"West Midlands",
    "sg:tags":[
        "newsagent"
    ],
    "wof:name":"Winsford News Ltd.",
    "wof:placetype":"venue"
},
  "geometry": {"coordinates":[-1.554792,52.413235],"type":"Point"}
}