{
  "type": "Feature",
  "properties": {
    "addr:full":"11 Moreton Ave Isleworth Greater London TW7 4NW",
    "addr:housenumber":"11",
    "addr:postcode":"tw7 4nw",
    "addr:street":"Moreton Ave",
    "iso:country":"GB",
    "sg:address":"11 Moreton Ave",
    "sg:city":"Isleworth",
    "sg:classifiers":[
        {
            "category":"Shopping",
            "subcategory":"Comic Books",
            "type":"Retail Goods"
        }
    ],
    "sg:phone":"+44 7956 523699",
    "sg:postcode":"TW7 4NW",
    "sg:province":"Greater London",
    "sg:tags":[
        "jeweller"
    ],
    "wof:name":"Celtic Mystique Ltd",
    "wof:placetype":"venue"
},
  "geometry": {"coordinates":[-0.344767,51.479366],"type":"Point"}
}