{
  "type": "Feature",
  "properties": {
    "addr:full":"2 Arden Cotts, Harrow Road, Knockholt Sevenoaks Kent TN14 7JU",
    "addr:housenumber":"2",
    "addr:postcode":"tn14 7ju",
    "addr:street":"Harrow Road",
    "iso:country":"GB",
    "sg:address":"2 Arden Cotts, Harrow Road, Knockholt",
    "sg:city":"Sevenoaks",
    "sg:classifiers":[
        {
            "category":"Education",
            "subcategory":"School",
            "type":"Public Place"
        }
    ],
    "sg:phone":"+44 1959 532013",
    "sg:postcode":"TN14 7JU",
    "sg:province":"Kent",
    "sg:tags":[
        "private",
        "tuition"
    ],
    "wof:name":"Education Plus",
    "wof:placetype":"venue"
},
  "geometry": {"coordinates":[0.1253799945,51.3170852661],"type":"Point"}
}