{
  "type": "Feature",
  "properties": {
    "iso:country":"GB",
    "sg:address":"44 Arbor Road, Croft",
    "sg:city":"Leicester",
    "sg:classifiers":[
        {
            "category":"Social Services",
            "subcategory":"Retirement Home",
            "type":"Services"
        }
    ],
    "sg:phone":"+44 1455 283013",
    "sg:postcode":"LE9 3GD",
    "sg:province":"Leicestershire",
    "sg:tags":[
        "residential",
        "care"
    ],
    "wof:name":"Arbor House",
    "wof:placetype":"venue"
},
  "geometry": {"coordinates":[-1.240568,52.555656],"type":"Point"}
}