{
  "type": "Feature",
  "properties": {
    "iso:country":"GB",
    "sg:address":"36 High St",
    "sg:city":"Fraserburgh",
    "sg:classifiers":[
        {
            "category":"Home & Garden",
            "subcategory":"Home Furnishings",
            "type":"Retail Goods"
        }
    ],
    "sg:phone":"+44 1771 637999",
    "sg:postcode":"AB43 6SR",
    "sg:province":"Aberdeenshire",
    "sg:tags":[
        "blind",
        "curtain",
        "fitting"
    ],
    "wof:name":"Right Track The",
    "wof:placetype":"venue"
},
  "geometry": {"coordinates":[-2.183879,57.5989],"type":"Point"}
}