{
  "type": "Feature",
  "properties": {
    "addr:full":"Canal Lane, Kirkintillock Glasgow East Dunbartonshire G66 1QL",
    "addr:postcode":"g66 1ql",
    "addr:street":"Canal Lane",
    "iso:country":"GB",
    "sg:address":"Canal Lane, Kirkintillock",
    "sg:city":"Glasgow",
    "sg:classifiers":[
        {
            "category":"Retail",
            "subcategory":"Auto Repair",
            "type":"Services"
        }
    ],
    "sg:postcode":"G66 1QL",
    "sg:province":"East Dunbartonshire",
    "sg:tags":[
        "modification",
        "garage"
    ],
    "wof:name":"The Cross Garage",
    "wof:placetype":"venue"
},
  "geometry": {"coordinates":[-4.151679039,55.9414596558],"type":"Point"}
}