{
  "type": "Feature",
  "properties": {
    "addr:full":"1003 Shettleston Road Glasgow Glasgow City G32 7PB",
    "addr:housenumber":"1003",
    "addr:postcode":"g32 7pb",
    "addr:street":"Shettleston Road",
    "iso:country":"GB",
    "sg:address":"1003 Shettleston Road",
    "sg:city":"Glasgow",
    "sg:classifiers":[
        {
            "category":"Home & Garden",
            "subcategory":"Hardware",
            "type":"Retail Goods"
        }
    ],
    "sg:phone":"+44 141 778 2130",
    "sg:postcode":"G32 7PB",
    "sg:province":"Glasgow City",
    "sg:tags":[
        "merchant",
        "ironmonger"
    ],
    "wof:name":"FULLARTON'S EMPORIUM",
    "wof:placetype":"venue"
},
  "geometry": {"coordinates":[-4.1704349518,55.8518867493],"type":"Point"}
}