{
  "type": "Feature",
  "properties": {
    "addr:full":"Park Office, Bablock Hyth Witney Oxfordshire OX29 5AT",
    "addr:postcode":"ox29 5at",
    "iso:country":"GB",
    "sg:address":"Park Office, Bablock Hyth",
    "sg:city":"Witney",
    "sg:classifiers":[
        {
            "category":"Recreation",
            "subcategory":"Campground",
            "type":"Entertainment"
        }
    ],
    "sg:postcode":"OX29 5AT",
    "sg:province":"Oxfordshire",
    "sg:tags":[
        "caravan",
        "park"
    ],
    "wof:name":"Bablock Hythe Holiday Caravan Park",
    "wof:placetype":"venue"
},
  "geometry": {"coordinates":[-1.3697719574,51.7340393066],"type":"Point"}
}