{
  "type": "Feature",
  "properties": {
    "addr:full":"37 Moorgate Road Rotherham South Yorkshire S60 2AE",
    "addr:housenumber":"37",
    "addr:postcode":"s60 2ae",
    "addr:street":"Moorgate Road",
    "iso:country":"GB",
    "sg:address":"37 Moorgate Road",
    "sg:city":"Rotherham",
    "sg:classifiers":[
        {
            "category":"Building & Trades",
            "subcategory":"Construction",
            "type":"Services"
        }
    ],
    "sg:postcode":"S60 2AE",
    "sg:province":"South Yorkshire",
    "sg:tags":[
        "joinery"
    ],
    "wof:name":"T. Barraclough & Sons Ltd",
    "wof:placetype":"venue"
},
  "geometry": {"coordinates":[-1.353266,53.424438],"type":"Point"}
}