{
  "type": "Feature",
  "properties": {
    "addr:full":"Station Rd Bristol City of Bristol BS15 2XH",
    "addr:postcode":"bs15 2xh",
    "addr:street":"Station Rd",
    "iso:country":"GB",
    "sg:address":"Station Rd",
    "sg:city":"Bristol",
    "sg:classifiers":[
        {
            "category":"Professional",
            "subcategory":"Computer Services",
            "type":"Services"
        }
    ],
    "sg:phone":"+44 117 983 0334",
    "sg:postcode":"BS15 2XH",
    "sg:province":"City of Bristol",
    "sg:tags":[
        "aided",
        "design"
    ],
    "wof:name":"Medway Cad Systems",
    "wof:placetype":"venue"
},
  "geometry": {"coordinates":[-2.591429,51.453667],"type":"Point"}
}