{
  "type": "Feature",
  "properties": {
    "addr:full":"15a Yarm Street Stockton-on-tees Durham TS18 3DR",
    "addr:housenumber":"15a",
    "addr:postcode":"ts18 3dr",
    "addr:street":"Yarm Street",
    "iso:country":"GB",
    "sg:address":"15a Yarm Street",
    "sg:city":"Stockton-on-tees",
    "sg:classifiers":[
        {
            "category":"Shopping",
            "subcategory":"Music",
            "type":"Retail Goods"
        }
    ],
    "sg:phone":"+44 1642 860068",
    "sg:postcode":"TS18 3DR",
    "sg:province":"Durham",
    "sg:tags":[
        "record",
        "tape",
        "cd"
    ],
    "wof:name":"Sound It Out",
    "wof:placetype":"venue"
},
  "geometry": {"coordinates":[-1.3139369488,54.5615768433],"type":"Point"}
}