{
  "type": "Feature",
  "properties": {
    "addr:full":"22 St George's Way Leicester Leicestershire LE1 1SH",
    "addr:housenumber":"22",
    "addr:postcode":"le1 1sh",
    "addr:street":"St George'S Way",
    "iso:country":"GB",
    "sg:address":"22 St George's Way",
    "sg:city":"Leicester",
    "sg:classifiers":[
        {
            "category":"Banks & Credit Unions",
            "subcategory":"Investment Brokerage",
            "type":"Services"
        },
        {
            "category":"Health Services",
            "subcategory":"Nursing And Care Facility",
            "type":"Services"
        }
    ],
    "sg:phone":"+44 116 262 0617",
    "sg:postcode":"LE1 1SH",
    "sg:province":"Leicestershire",
    "sg:tags":[
        "home",
        "property"
    ],
    "wof:name":"The Leicester & County Convalescent Homes Society",
    "wof:placetype":"venue"
},
  "geometry": {"coordinates":[-1.12554,52.633209],"type":"Point"}
}