{
  "type": "Feature",
  "properties": {
    "addr:full":"8 Low Walk, Wellington Centre Aldershot Hampshire GU11 1DB",
    "addr:housenumber":"8",
    "addr:postcode":"gu11 1db",
    "addr:street":"Low Walk",
    "iso:country":"GB",
    "sg:address":"8 Low Walk, Wellington Centre",
    "sg:city":"Aldershot",
    "sg:classifiers":[
        {
            "category":"Shopping",
            "subcategory":"Stationery & Office Supplies",
            "type":"Retail Goods"
        }
    ],
    "sg:postcode":"GU11 1DB",
    "sg:province":"Hampshire",
    "wof:name":"Shepherd,Shirley,",
    "wof:placetype":"venue"
},
  "geometry": {"coordinates":[-0.7593460083,51.2496032715],"type":"Point"}
}