{
  "type": "Feature",
  "properties": {
    "iso:country":"GB",
    "sg:address":"Bull Head Street",
    "sg:city":"Wigston",
    "sg:classifiers":[
        {
            "category":"Autos & Motor Vehicles",
            "subcategory":"Fuel & Gas Station",
            "type":"Retail Goods"
        }
    ],
    "sg:phone":"+44 116 257 0209",
    "sg:postcode":"LE18 1PB",
    "sg:province":"Leicestershire",
    "sg:tags":[
        "petrol",
        "filling"
    ],
    "wof:name":"Moat Service Station",
    "wof:placetype":"venue"
},
  "geometry": {"coordinates":[-1.1033639908,52.5850982666],"type":"Point"}
}