{
  "type": "Feature",
  "properties": {
    "addr:full":"96 Bury Old Road Manchester Greater Manchester M8 5BW",
    "addr:housenumber":"96",
    "addr:postcode":"m8 5bw",
    "addr:street":"Bury Old Road",
    "iso:country":"GB",
    "sg:address":"96 Bury Old Road",
    "sg:city":"Manchester",
    "sg:classifiers":[
        {
            "category":"Restaurant",
            "type":"Food & Drink"
        }
    ],
    "sg:phone":"+44 161 795 5300",
    "sg:postcode":"M8 5BW",
    "sg:province":"Greater Manchester",
    "sg:tags":[
        "-",
        "italian"
    ],
    "sg:website":"http://www.sanrocco.co.uk",
    "wof:name":"San Rocco",
    "wof:placetype":"venue"
},
  "geometry": {"coordinates":[-2.2471749783,53.5146255493],"type":"Point"}
}