{
  "type": "Feature",
  "properties": {
    "iso:country":"GB",
    "sg:address":"High Blaithwaite",
    "sg:city":"Wigton",
    "sg:classifiers":[
        {
            "category":"Farming",
            "subcategory":"Dairy Farm",
            "type":"Manufacturing & Wholesale Goods"
        }
    ],
    "sg:postcode":"CA7 8PW",
    "sg:province":"Cumbria",
    "wof:name":"Messrs G Spark",
    "wof:placetype":"venue"
},
  "geometry": {"coordinates":[-3.087032,54.774658],"type":"Point"}
}