{
  "type": "Feature",
  "properties": {
    "addr:full":"9-11 Sydney St Brighton East Sussex BN1 4EN",
    "addr:housenumber":"9-11",
    "addr:postcode":"bn1 4en",
    "addr:street":"Sydney St",
    "iso:country":"GB",
    "sg:address":"9-11 Sydney St",
    "sg:city":"Brighton",
    "sg:classifiers":[
        {
            "category":"Bars & Pubs",
            "type":"Food & Drink"
        }
    ],
    "sg:phone":"+44 1273 609134",
    "sg:postcode":"BN1 4EN",
    "sg:province":"East Sussex",
    "sg:tags":[
        "pubs",
        "inn"
    ],
    "wof:name":"Green Dragon The",
    "wof:placetype":"venue"
},
  "geometry": {"coordinates":[-0.1380230039,50.8274688721],"type":"Point"}
}