{
  "type": "Feature",
  "properties": {
    "addr:full":", Southburgh Thetford Norfolk IP25 7TJ",
    "addr:postcode":"ip25 7tj",
    "addr:street":"Southburgh",
    "iso:country":"GB",
    "sg:address":", Southburgh",
    "sg:city":"Thetford",
    "sg:classifiers":[
        {
            "category":"Education",
            "subcategory":"Special Training",
            "type":"Public Place"
        },
        {
            "category":"Education",
            "subcategory":"School",
            "type":"Public Place"
        }
    ],
    "sg:phone":"+44 1953 850494",
    "sg:postcode":"IP25 7TJ",
    "sg:province":"Norfolk",
    "wof:name":"Sheridan House School",
    "wof:placetype":"venue"
},
  "geometry": {"coordinates":[0.9478210211,52.6034851074],"type":"Point"}
}