{
  "type": "Feature",
  "properties": {
    "addr:full":"A31, Corfe Mullen Wimborne Dorset BH21 3HA",
    "addr:postcode":"bh21 3ha",
    "iso:country":"GB",
    "sg:address":"A31, Corfe Mullen",
    "sg:city":"Wimborne",
    "sg:classifiers":[
        {
            "category":"Restaurant",
            "type":"Food & Drink"
        }
    ],
    "sg:phone":"+44 1202 883473",
    "sg:postcode":"BH21 3HA",
    "sg:province":"Dorset",
    "wof:name":"Little Chef",
    "wof:placetype":"venue"
},
  "geometry": {"coordinates":[-1.9907900095,50.7908973694],"type":"Point"}
}