{
  "type": "Feature",
  "properties": {
    "addr:full":"15 Oakfield Road Buckley Denbighshire CH7 2AR",
    "addr:housenumber":"15",
    "addr:postcode":"ch7 2ar",
    "addr:street":"Oakfield Road",
    "iso:country":"GB",
    "sg:address":"15 Oakfield Road",
    "sg:city":"Buckley",
    "sg:classifiers":[
        {
            "category":"Professional",
            "subcategory":"Computer Services",
            "type":"Services"
        }
    ],
    "sg:postcode":"CH7 2AR",
    "sg:province":"Denbighshire",
    "sg:tags":[
        "system",
        "software"
    ],
    "wof:name":"Catalyst Software Design Ltd.",
    "wof:placetype":"venue"
},
  "geometry": {"coordinates":[-3.0748729706,53.1632537842],"type":"Point"}
}