{
  "type": "Feature",
  "properties": {
    "addr:full":"Unit 8, Hamper Common Industrial Estate Petworth West Sussex GU28 9NN",
    "addr:housenumber":"unit 8",
    "addr:postcode":"gu28 9nn",
    "addr:street":"Hamper Common Industrial Estate",
    "iso:country":"GB",
    "sg:address":"Unit 8, Hamper Common Industrial Estate",
    "sg:city":"Petworth",
    "sg:classifiers":[
        {
            "category":"Manufacturing",
            "subcategory":"Electronics",
            "type":"Manufacturing & Wholesale Goods"
        }
    ],
    "sg:phone":"+44 1798 343488",
    "sg:postcode":"GU28 9NN",
    "sg:province":"West Sussex",
    "sg:tags":[
        "computer",
        "-",
        "printed",
        "circuit"
    ],
    "wof:name":"Printec Ltd.",
    "wof:placetype":"venue"
},
  "geometry": {"coordinates":[-0.6078540087,50.9861068726],"type":"Point"}
}