{
  "type": "Feature",
  "properties": {
    "iso:country":"GB",
    "sg:address":"458 High St",
    "sg:city":"Kingswinford",
    "sg:classifiers":[
        {
            "category":"Retail",
            "subcategory":"Auto Repair",
            "type":"Services"
        }
    ],
    "sg:phone":"+44 1384 273673",
    "sg:postcode":"DY6 8AW",
    "sg:province":"Staffordshire",
    "sg:tags":[
        "electrician"
    ],
    "wof:name":"J P Automators",
    "wof:placetype":"venue"
},
  "geometry": {"coordinates":[-2.1627008915,52.4981155396],"type":"Point"}
}