{
  "type": "Feature",
  "properties": {
    "addr:full":"1 Giles Avenue, Wath Rotherham South Yorkshire S63 6SG",
    "addr:housenumber":"1",
    "addr:postcode":"s63 6sg",
    "addr:street":"Giles Avenue",
    "iso:country":"GB",
    "sg:address":"1 Giles Avenue, Wath",
    "sg:city":"Rotherham",
    "sg:classifiers":[
        {
            "category":"Building & Trades",
            "subcategory":"Plumbing",
            "type":"Services"
        }
    ],
    "sg:phone":"+44 1709 873518",
    "sg:postcode":"S63 6SG",
    "sg:province":"South Yorkshire",
    "sg:tags":[
        "heating"
    ],
    "wof:name":"John Paskell (Plumbing) Ltd.",
    "wof:placetype":"venue"
},
  "geometry": {"coordinates":[-1.368616,53.500935],"type":"Point"}
}