{
  "type": "Feature",
  "properties": {
    "iso:country":"GB",
    "sg:address":"31 Smithy Lane, Much Hoole",
    "sg:city":"Preston",
    "sg:classifiers":[
        {
            "category":"Professional",
            "subcategory":"Accounting & Tax Preparation",
            "type":"Services"
        }
    ],
    "sg:postcode":"PR4 4GN",
    "sg:province":"Lancashire",
    "sg:tags":[
        "accountant"
    ],
    "wof:name":"S J Stoneley",
    "wof:placetype":"venue"
},
  "geometry": {"coordinates":[-2.80112,53.69952],"type":"Point"}
}