{
  "type": "Feature",
  "properties": {
    "iso:country":"GB",
    "sg:address":"34th Floor, 1 Canada Square, Canary Wharf",
    "sg:city":"Poplar",
    "sg:classifiers":[
        {
            "category":"Government",
            "subcategory":"Office",
            "type":"Public Place"
        }
    ],
    "sg:phone":"+44 20 7512 9615",
    "sg:postcode":"E14 5AA",
    "sg:province":"Greater London",
    "sg:tags":[
        "central"
    ],
    "wof:name":"Agence Du Medicament",
    "wof:placetype":"venue"
},
  "geometry": {"coordinates":[-0.017044,51.504662],"type":"Point"}
}