{
  "type": "Feature",
  "properties": {
    "addr:full":"Ramsay House, 18 Vera Avenue London Greater London N21 1RA",
    "addr:housenumber":"18",
    "addr:postcode":"n21 1ra",
    "addr:street":"Vera Avenue",
    "iso:country":"GB",
    "sg:address":"Ramsay House, 18 Vera Avenue",
    "sg:city":"London",
    "sg:classifiers":[
        {
            "category":"Wholesale",
            "subcategory":"Computers",
            "type":"Manufacturing & Wholesale Goods"
        },
        {
            "category":"Professional",
            "subcategory":"Computer Services",
            "type":"Services"
        }
    ],
    "sg:phone":"+44 20 8360 6600",
    "sg:postcode":"N21 1RA",
    "sg:province":"Greater London",
    "sg:tags":[
        "supplier",
        "consumables",
        "system",
        "software"
    ],
    "wof:name":"Scott Adam Systems Ltd",
    "wof:placetype":"venue"
},
  "geometry": {"coordinates":[-0.098168999,51.6424598694],"type":"Point"}
}