{
  "type": "Feature",
  "properties": {
    "iso:country":"GB",
    "sg:address":"19 Lyndhurst Road",
    "sg:city":"Gosport",
    "sg:classifiers":[
        {
            "category":"Organizations",
            "subcategory":"Non-profit Organization",
            "type":"Services"
        }
    ],
    "sg:phone":"+44 23 9258 2499",
    "sg:postcode":"PO12 3QY",
    "sg:province":"Hampshire",
    "sg:tags":[
        "charitable",
        "organisation",
        "voluntary",
        "charity"
    ],
    "wof:name":"Gosport Railway Society",
    "wof:placetype":"venue"
},
  "geometry": {"coordinates":[-1.147688,50.796295],"type":"Point"}
}