{
  "type": "Feature",
  "properties": {
    "addr:full":"The Pointe, 89 Hartfield Road, Wimbledon London Greater London SW19 3TJ",
    "addr:housenumber":"89",
    "addr:postcode":"sw19 3tj",
    "addr:street":"Hartfield Road",
    "iso:country":"GB",
    "sg:address":"The Pointe, 89 Hartfield Road, Wimbledon",
    "sg:city":"London",
    "sg:classifiers":[
        {
            "category":"Professional",
            "subcategory":"Computer Services",
            "type":"Services"
        }
    ],
    "sg:postcode":"SW19 3TJ",
    "sg:province":"Greater London",
    "sg:tags":[
        "system",
        "software"
    ],
    "wof:name":"Metascybe Systems Ltd.",
    "wof:placetype":"venue"
},
  "geometry": {"coordinates":[-0.207024,51.420998],"type":"Point"}
}