{
  "type": "Feature",
  "properties": {
    "addr:full":"29 Causeyside Street Paisley Renfrewshire PA1 1UL",
    "addr:housenumber":"29",
    "addr:postcode":"pa1 1ul",
    "addr:street":"Causeyside Street",
    "iso:country":"GB",
    "sg:address":"29 Causeyside Street",
    "sg:city":"Paisley",
    "sg:classifiers":[
        {
            "category":"Community Center",
            "subcategory":"Social",
            "type":"Public Place"
        },
        {
            "category":"Food & Beverages",
            "subcategory":"Groceries & Convenience Stores",
            "type":"Retail Goods"
        }
    ],
    "sg:phone":"+44 141 840 1395",
    "sg:postcode":"PA1 1UL",
    "sg:province":"Renfrewshire",
    "sg:tags":[
        "frozen",
        "retailer",
        "freezer",
        "centre"
    ],
    "wof:name":"Farmfoods Ltd",
    "wof:placetype":"venue"
},
  "geometry": {"coordinates":[-4.423368,55.843513],"type":"Point"}
}