{
  "type": "Feature",
  "properties": {
    "addr:full":"Brewers Lane Gosport Hampshire PO13 0JX",
    "addr:postcode":"po13 0jx",
    "addr:street":"Brewers Lane",
    "iso:country":"GB",
    "sg:address":"Brewers Lane",
    "sg:city":"Gosport",
    "sg:classifiers":[
        {
            "category":"Travel",
            "subcategory":"Travel Agent",
            "type":"Entertainment"
        }
    ],
    "sg:phone":"+44 1329 238804",
    "sg:postcode":"PO13 0JX",
    "sg:province":"Hampshire",
    "wof:name":"The Air Ticket Co",
    "wof:placetype":"venue"
},
  "geometry": {"coordinates":[-1.164254,50.821461],"type":"Point"}
}