{
  "type": "Feature",
  "properties": {
    "addr:full":"90 West Street Newbury Berkshire RG14 1BD",
    "addr:housenumber":"90",
    "addr:postcode":"rg14 1bd",
    "addr:street":"West Street",
    "iso:country":"GB",
    "sg:address":"90 West Street",
    "sg:city":"Newbury",
    "sg:classifiers":[
        {
            "category":"Retail",
            "subcategory":"Funeral Services",
            "type":"Services"
        }
    ],
    "sg:phone":"+44 1635 522210",
    "sg:postcode":"RG14 1BD",
    "sg:province":"Berkshire",
    "wof:name":"Camp Hopson Funeral Directors",
    "wof:placetype":"venue"
},
  "geometry": {"coordinates":[-1.3270670176,51.4032516479],"type":"Point"}
}