{
  "type": "Feature",
  "properties": {
    "iso:country":"GB",
    "sg:address":"Chalfont Park, Chalfont St Peter",
    "sg:city":"Gerrards Cross",
    "sg:classifiers":[
        {
            "category":"Farming",
            "subcategory":"Nursery",
            "type":"Manufacturing & Wholesale Goods"
        }
    ],
    "sg:phone":"+44 1753 884163",
    "sg:postcode":"SL9 0QA",
    "sg:province":"Buckinghamshire",
    "sg:tags":[
        "creche"
    ],
    "wof:name":"Chalfont Park Nursery",
    "wof:placetype":"venue"
},
  "geometry": {"coordinates":[-0.5486599803,51.5977401733],"type":"Point"}
}