{
  "type": "Feature",
  "properties": {
    "iso:country":"GB",
    "sg:address":"Main Street, Newburgh",
    "sg:city":"Ellon",
    "sg:classifiers":[
        {
            "category":"Travel",
            "subcategory":"Hotels & Motels",
            "type":"Entertainment"
        }
    ],
    "sg:phone":"+44 1358 789257",
    "sg:postcode":"AB41 6BP",
    "sg:province":"Aberdeenshire",
    "wof:name":"Ythan Hotel",
    "wof:placetype":"venue"
},
  "geometry": {"coordinates":[-2.0001571178,57.3234405518],"type":"Point"}
}