{
  "type": "Feature",
  "properties": {
    "addr:full":"14 High St Stourbridge West Midlands DY9 8JT",
    "addr:housenumber":"14",
    "addr:postcode":"dy9 8jt",
    "addr:street":"High St",
    "iso:country":"GB",
    "sg:address":"14 High St",
    "sg:city":"Stourbridge",
    "sg:classifiers":[
        {
            "category":"Community Center",
            "type":"Public Place"
        }
    ],
    "sg:phone":"+44 1384 424325",
    "sg:postcode":"DY9 8JT",
    "sg:province":"West Midlands",
    "sg:tags":[
        "box",
        "juke"
    ],
    "wof:name":"Belvacode Ltd",
    "wof:placetype":"venue"
},
  "geometry": {"coordinates":[-2.1165089607,52.4581680298],"type":"Point"}
}