{
  "type": "Feature",
  "properties": {
    "addr:full":"The Gables, Garlands Lane, Barlestone Nuneaton Leicestershire CV13 0JD",
    "addr:postcode":"cv13 0jd",
    "addr:street":"Garlands Lane",
    "iso:country":"GB",
    "sg:address":"The Gables, Garlands Lane, Barlestone",
    "sg:city":"Nuneaton",
    "sg:classifiers":[
        {
            "category":"Transit Center",
            "subcategory":"Passenger",
            "type":"Transportation"
        }
    ],
    "sg:phone":"+44 1530 230278",
    "sg:postcode":"CV13 0JD",
    "sg:province":"Leicestershire",
    "sg:tags":[
        "boarding",
        "kennel",
        "catteries"
    ],
    "wof:name":"Gables Kennels",
    "wof:placetype":"venue"
},
  "geometry": {"coordinates":[-1.3696190119,52.6473121643],"type":"Point"}
}