{
  "type": "Feature",
  "properties": {
    "addr:full":"Unit 7 Marston Road Industrial Estate, Marston Road Wolverhampton West Midlands WV2 4LX",
    "addr:housenumber":"unit 7",
    "addr:postcode":"wv2 4lx",
    "addr:street":"Marston Road Industrial Estate Marston Road",
    "iso:country":"GB",
    "sg:address":"Unit 7 Marston Road Industrial Estate, Marston Road",
    "sg:city":"Wolverhampton",
    "sg:classifiers":[
        {
            "category":"Building & Trades",
            "subcategory":"Electrical",
            "type":"Services"
        }
    ],
    "sg:phone":"+44 1902 427550",
    "sg:postcode":"WV2 4LX",
    "sg:province":"West Midlands",
    "sg:tags":[
        "lighting"
    ],
    "wof:name":"Classic Lighting",
    "wof:placetype":"venue"
},
  "geometry": {"coordinates":[-2.1332640648,52.5742034912],"type":"Point"}
}