{
  "type": "Feature",
  "properties": {
    "addr:full":"216 Brigstock Rd Thornton Heath Surrey CR7 7JD",
    "addr:housenumber":"216",
    "addr:postcode":"cr7 7jd",
    "addr:street":"Brigstock Rd",
    "iso:country":"GB",
    "sg:address":"216 Brigstock Rd",
    "sg:city":"Thornton Heath",
    "sg:classifiers":[
        {
            "category":"Retail",
            "subcategory":"Repair Shop",
            "type":"Services"
        }
    ],
    "sg:phone":"+44 20 8684 4609",
    "sg:postcode":"CR7 7JD",
    "sg:province":"Surrey",
    "sg:tags":[
        "radio",
        "television",
        "video"
    ],
    "wof:name":"R & B Electronics",
    "wof:placetype":"venue"
},
  "geometry": {"coordinates":[-0.106714,51.396389],"type":"Point"}
}