{
  "type": "Feature",
  "properties": {
    "iso:country":"GB",
    "sg:address":"North East Suite, Tower Point, 44 North Rd",
    "sg:city":"Brighton",
    "sg:classifiers":[
        {
            "category":"Wholesale",
            "subcategory":"Machinery & Supplies",
            "type":"Manufacturing & Wholesale Goods"
        }
    ],
    "sg:postcode":"BN1 1YR",
    "sg:province":"East Sussex",
    "sg:tags":[
        "industrial",
        "commercial"
    ],
    "wof:name":"L I T C",
    "wof:placetype":"venue"
},
  "geometry": {"coordinates":[-0.14117,50.825878],"type":"Point"}
}