{
  "type": "Feature",
  "properties": {
    "iso:country":"GB",
    "sg:address":"47 Park Street",
    "sg:city":"Bristol",
    "sg:classifiers":[
        {
            "category":"Shopping",
            "subcategory":"Clothing, Apparel, & Fashions",
            "type":"Retail Goods"
        }
    ],
    "sg:postcode":"BS1 5NL",
    "sg:province":"City of Bristol",
    "sg:tags":[
        "clothing"
    ],
    "wof:name":"The T-Shirt Exchange Ltd.",
    "wof:placetype":"venue"
},
  "geometry": {"coordinates":[-2.604344,51.455601],"type":"Point"}
}