{
  "type": "Feature",
  "properties": {
    "addr:full":"15 High St, Burton Upon Stather Scunthorpe Lincolnshire DN15 9DG",
    "addr:housenumber":"15",
    "addr:postcode":"dn15 9dg",
    "addr:street":"High St",
    "iso:country":"GB",
    "sg:address":"15 High St, Burton Upon Stather",
    "sg:city":"Scunthorpe",
    "sg:classifiers":[
        {
            "category":"Government",
            "subcategory":"Post Office",
            "type":"Public Place"
        }
    ],
    "sg:phone":"+44 1724 721079",
    "sg:postcode":"DN15 9DG",
    "sg:province":"Lincolnshire",
    "wof:name":"Usher,M T,",
    "wof:placetype":"venue"
},
  "geometry": {"coordinates":[-0.684656024,53.6491546631],"type":"Point"}
}