{
  "type": "Feature",
  "properties": {
    "iso:country":"GB",
    "sg:address":"First Av, Plymouth Market",
    "sg:city":"Plymouth",
    "sg:classifiers":[
        {
            "category":"Home & Garden",
            "subcategory":"Kitchen Supply",
            "type":"Retail Goods"
        }
    ],
    "sg:phone":"+44 1752 660046",
    "sg:postcode":"PL1 5QF",
    "sg:province":"Devon",
    "sg:tags":[
        "ware"
    ],
    "wof:name":"Household & Fancy Goods",
    "wof:placetype":"venue"
},
  "geometry": {"coordinates":[-4.165619,50.372475],"type":"Point"}
}