{
  "type": "Feature",
  "properties": {
    "iso:country":"GB",
    "sg:address":"11 Ealing Broadway Station, The Broadway",
    "sg:city":"Ealing",
    "sg:classifiers":[
        {
            "category":"Shopping",
            "subcategory":"Clothing, Apparel, & Fashions",
            "type":"Retail Goods"
        }
    ],
    "sg:phone":"+44 20 8567 9799",
    "sg:postcode":"W5 2AD",
    "sg:province":"Greater London",
    "sg:tags":[
        "ladieswear"
    ],
    "wof:name":"Factory Outlet",
    "wof:placetype":"venue"
},
  "geometry": {"coordinates":[-0.296334,51.51572],"type":"Point"}
}