{
  "type": "Feature",
  "properties": {
    "iso:country":"GB",
    "sg:address":"Anchor Dulverton House, 11-14 Eaton Crescent",
    "sg:city":"Bristol",
    "sg:classifiers":[
        {
            "category":"Social Services",
            "subcategory":"Adult Care",
            "type":"Services"
        },
        {
            "category":"Social Services",
            "subcategory":"Retirement Home",
            "type":"Services"
        }
    ],
    "sg:phone":"+44 117 973 7024",
    "sg:postcode":"BS8 2EJ",
    "sg:province":"City of Bristol",
    "sg:tags":[
        "residential",
        "housing",
        "sheltered"
    ],
    "wof:name":"Brunelcare",
    "wof:placetype":"venue"
},
  "geometry": {"coordinates":[-2.613449,51.459194],"type":"Point"}
}