{
  "type": "Feature",
  "properties": {
    "iso:country":"GB",
    "sg:address":"Common Road",
    "sg:city":"Stafford",
    "sg:classifiers":[
        {
            "category":"Home & Garden",
            "subcategory":"Hardware",
            "type":"Retail Goods"
        }
    ],
    "sg:phone":"+44 1785 272727",
    "sg:postcode":"ST16 3EH",
    "sg:province":"Staffordshire",
    "sg:tags":[
        "sealant",
        "glue",
        "adhesives"
    ],
    "wof:name":"Evode Ltd.",
    "wof:placetype":"venue"
},
  "geometry": {"coordinates":[-2.118199,52.819981],"type":"Point"}
}