{
  "type": "Feature",
  "properties": {
    "addr:full":"164 Midland Road, Royston Barnsley South Yorkshire S71 4PX",
    "addr:housenumber":"164",
    "addr:postcode":"s71 4px",
    "addr:street":"Midland Road;Yorkshire",
    "iso:country":"GB",
    "sg:address":"164 Midland Road, Royston",
    "sg:city":"Barnsley",
    "sg:classifiers":[
        {
            "category":"Food & Beverages",
            "subcategory":"Meat & Fish",
            "type":"Retail Goods"
        }
    ],
    "sg:phone":"+44 1226 722610",
    "sg:postcode":"S71 4PX",
    "sg:province":"South Yorkshire",
    "sg:tags":[
        "butcher"
    ],
    "wof:name":"J McNair",
    "wof:placetype":"venue"
},
  "geometry": {"coordinates":[-1.446931,53.600811],"type":"Point"}
}