{
  "type": "Feature",
  "properties": {
    "iso:country":"GB",
    "sg:address":"White House Farm, Melchet Park, Sherfield English",
    "sg:city":"Romsey",
    "sg:classifiers":[
        {
            "category":"Farming",
            "subcategory":"Livestock Farm",
            "type":"Manufacturing & Wholesale Goods"
        }
    ],
    "sg:postcode":"SO51 6FS",
    "sg:province":"Hampshire",
    "sg:tags":[
        "others"
    ],
    "wof:name":"Julian R Newman",
    "wof:placetype":"venue"
},
  "geometry": {"coordinates":[-1.586089,50.99979],"type":"Point"}
}