{
  "type": "Feature",
  "properties": {
    "iso:country":"GB",
    "sg:address":"Quainton House, Camp Road",
    "sg:city":"Gerrards Cross",
    "sg:classifiers":[
        {
            "category":"Autos & Motor Vehicles",
            "subcategory":"Motorcycle Sales",
            "type":"Retail Goods"
        }
    ],
    "sg:postcode":"SL9 7PB",
    "sg:province":"Buckinghamshire",
    "sg:tags":[
        "chauffeur",
        "driven",
        "car"
    ],
    "wof:name":"Braemar Location Vehicles",
    "wof:placetype":"venue"
},
  "geometry": {"coordinates":[-0.561502,51.582275],"type":"Point"}
}