{
  "type": "Feature",
  "properties": {
    "iso:country":"GB",
    "sg:address":"20 Green Farm Road, Colne Engaine",
    "sg:city":"Colchester",
    "sg:classifiers":[
        {
            "category":"Professional",
            "subcategory":"Art Services",
            "type":"Services"
        },
        {
            "category":"Building & Trades",
            "subcategory":"Construction",
            "type":"Services"
        }
    ],
    "sg:phone":"+44 1787 222663",
    "sg:postcode":"CO6 2HA",
    "sg:province":"Essex",
    "sg:tags":[
        "decorator",
        "painter"
    ],
    "wof:name":"LAWRENCE PAGE",
    "wof:placetype":"venue"
},
  "geometry": {"coordinates":[0.698849,51.943542],"type":"Point"}
}