{
  "type": "Feature",
  "properties": {
    "addr:full":"36 Cheyneys Avenue Edgware Greater London HA8 6SF",
    "addr:housenumber":"36",
    "addr:postcode":"ha8 6sf",
    "addr:street":"Cheyneys Avenue",
    "iso:country":"GB",
    "sg:address":"36 Cheyneys Avenue",
    "sg:city":"Edgware",
    "sg:classifiers":[
        {
            "category":"Organizations",
            "subcategory":"Labor Organization",
            "type":"Services"
        },
        {
            "category":"Professional",
            "subcategory":"Business Services",
            "type":"Services"
        }
    ],
    "sg:phone":"+44 20 7402 1940",
    "sg:postcode":"HA8 6SF",
    "sg:province":"Greater London",
    "sg:tags":[
        "import",
        "export",
        "agent"
    ],
    "wof:name":"Chemtechno Ltd.",
    "wof:placetype":"venue"
},
  "geometry": {"coordinates":[-0.296158,51.609474],"type":"Point"}
}