{
  "type": "Feature",
  "properties": {
    "addr:full":"3 Academy Place Warrington Cheshire WA1 2NR",
    "addr:housenumber":"3",
    "addr:postcode":"wa1 2nr",
    "addr:street":"Academy Place",
    "iso:country":"GB",
    "sg:address":"3 Academy Place",
    "sg:city":"Warrington",
    "sg:classifiers":[
        {
            "category":"Shopping",
            "subcategory":"Comic Books",
            "type":"Retail Goods"
        }
    ],
    "sg:postcode":"WA1 2NR",
    "sg:province":"Cheshire",
    "sg:tags":[
        "magazine"
    ],
    "wof:name":"Timezone Inc Ltd.",
    "wof:placetype":"venue"
},
  "geometry": {"coordinates":[-2.58993,53.388676],"type":"Point"}
}