{
  "type": "Feature",
  "properties": {
    "addr:full":"Soundwell Road Bristol City of Bristol BS15 1PN",
    "addr:postcode":"bs15 1pn",
    "addr:street":"Soundwell Road",
    "iso:country":"GB",
    "sg:address":"Soundwell Road",
    "sg:city":"Bristol",
    "sg:classifiers":[
        {
            "category":"Autos & Motor Vehicles",
            "subcategory":"Fuel & Gas Station",
            "type":"Retail Goods"
        }
    ],
    "sg:phone":"+44 117 935 2612",
    "sg:postcode":"BS15 1PN",
    "sg:province":"City of Bristol",
    "sg:tags":[
        "petrol",
        "filling"
    ],
    "wof:name":"Chase Service Station",
    "wof:placetype":"venue"
},
  "geometry": {"coordinates":[-2.5136489868,51.4652862549],"type":"Point"}
}