{
  "type": "Feature",
  "properties": {
    "iso:country":"GB",
    "sg:address":"Clacton Campus, Marine Parade East",
    "sg:city":"Clacton-on-sea",
    "sg:classifiers":[
        {
            "category":"Education",
            "subcategory":"University",
            "type":"Public Place"
        }
    ],
    "sg:phone":"+44 1206 718334",
    "sg:postcode":"CO15 6JQ",
    "sg:province":"Essex",
    "sg:tags":[
        "higher"
    ],
    "wof:name":"Colchester Institute Enterprises Ltd.",
    "wof:placetype":"venue"
},
  "geometry": {"coordinates":[1.1704380512,51.7937011719],"type":"Point"}
}