{
  "type": "Feature",
  "properties": {
    "addr:full":"Unit 24 Manor Industrial Estate, Pleck Road Walsall West Midlands WS2 9XX",
    "addr:housenumber":"unit 24",
    "addr:postcode":"ws2 9xx",
    "addr:street":"Manor Industrial Estate Pleck Road",
    "iso:country":"GB",
    "sg:address":"Unit 24 Manor Industrial Estate, Pleck Road",
    "sg:city":"Walsall",
    "sg:classifiers":[
        {
            "category":"Manufacturing",
            "subcategory":"Petroleum Products",
            "type":"Manufacturing & Wholesale Goods"
        }
    ],
    "sg:postcode":"WS2 9XX",
    "sg:province":"West Midlands",
    "sg:tags":[
        "double",
        "glazing"
    ],
    "wof:name":"Stedek Windows & Doors Ltd.",
    "wof:placetype":"venue"
},
  "geometry": {"coordinates":[-1.9943100214,52.5827102661],"type":"Point"}
}