{
  "type": "Feature",
  "properties": {
    "addr:full":"57 Sea Rd Sunderland Tyne and Wear SR6 9BU",
    "addr:housenumber":"57",
    "addr:postcode":"sr6 9bu",
    "addr:street":"Sea Rd",
    "iso:country":"GB",
    "sg:address":"57 Sea Rd",
    "sg:city":"Sunderland",
    "sg:classifiers":[
        {
            "category":"Banks & Credit Unions",
            "subcategory":"Bank",
            "type":"Services"
        }
    ],
    "sg:phone":"+44 191 233 2777",
    "sg:postcode":"SR6 9BU",
    "sg:province":"Tyne and Wear",
    "wof:name":"NatWest",
    "wof:placetype":"venue"
},
  "geometry": {"coordinates":[-1.3787339926,54.930015564],"type":"Point"}
}