{
  "type": "Feature",
  "properties": {
    "addr:full":"275 Pinner Rd Harrow Greater London HA1 4HF",
    "addr:housenumber":"275",
    "addr:postcode":"ha1 4hf",
    "addr:street":"Pinner Rd",
    "iso:country":"GB",
    "sg:address":"275 Pinner Rd",
    "sg:city":"Harrow",
    "sg:classifiers":[
        {
            "category":"Retail",
            "subcategory":"Photofinishing",
            "type":"Services"
        }
    ],
    "sg:phone":"+44 20 8424 0022",
    "sg:postcode":"HA1 4HF",
    "sg:province":"Greater London",
    "sg:tags":[
        "photographic",
        "processor"
    ],
    "wof:name":"20 20 Image",
    "wof:placetype":"venue"
},
  "geometry": {"coordinates":[-0.3537119925,51.5826797485],"type":"Point"}
}