{
  "type": "Feature",
  "properties": {
    "addr:full":"Union Street Newport Pagnell Buckinghamshire MK16 8AY",
    "addr:postcode":"mk16 8ay",
    "addr:street":"Union Street",
    "iso:country":"GB",
    "sg:address":"Union Street",
    "sg:city":"Newport Pagnell",
    "sg:classifiers":[
        {
            "category":"Social Services",
            "subcategory":"Adult Care",
            "type":"Services"
        },
        {
            "category":"Social Services",
            "subcategory":"Retirement Home",
            "type":"Services"
        }
    ],
    "sg:phone":"+44 1908 216986",
    "sg:postcode":"MK16 8AY",
    "sg:province":"Buckinghamshire",
    "sg:tags":[
        "housing",
        "sheltered",
        "rest"
    ],
    "wof:name":"Lawnsmead Gardens",
    "wof:placetype":"venue"
},
  "geometry": {"coordinates":[-0.721615,52.087761],"type":"Point"}
}