{
  "type": "Feature",
  "properties": {
    "iso:country":"GB",
    "sg:address":"303 Grange Road",
    "sg:city":"London",
    "sg:classifiers":[
        {
            "category":"Shopping",
            "subcategory":"Department Store",
            "type":"Retail Goods"
        }
    ],
    "sg:postcode":"SE25 6TD",
    "sg:province":"Greater London",
    "wof:name":"V R Grocer",
    "wof:placetype":"venue"
},
  "geometry": {"coordinates":[-0.087669,51.4067497253],"type":"Point"}
}