{
  "type": "Feature",
  "properties": {
    "iso:country":"GB",
    "sg:address":"30 Lovers Walk",
    "sg:city":"Dumfries",
    "sg:classifiers":[
        {
            "category":"Travel",
            "subcategory":"Hotels & Motels",
            "type":"Entertainment"
        }
    ],
    "sg:phone":"+44 1387 252262",
    "sg:postcode":"DG1 1LX",
    "sg:province":"Dumfries and Galloway",
    "wof:name":"Fulwood Hotel",
    "wof:placetype":"venue"
},
  "geometry": {"coordinates":[-3.605621,55.072121],"type":"Point"}
}