{
  "type": "Feature",
  "properties": {
    "addr:full":"9 Laxton Drive Maidstone Kent ME17 3SQ",
    "addr:housenumber":"9",
    "addr:postcode":"me17 3sq",
    "addr:street":"Laxton Drive",
    "iso:country":"GB",
    "sg:address":"9 Laxton Drive",
    "sg:city":"Maidstone",
    "sg:classifiers":[
        {
            "category":"Building & Trades",
            "subcategory":"Plumbing",
            "type":"Services"
        }
    ],
    "sg:phone":"+44 1622 747444",
    "sg:postcode":"ME17 3SQ",
    "sg:province":"Kent",
    "sg:tags":[
        "heating"
    ],
    "wof:name":"A A Plumbing",
    "wof:placetype":"venue"
},
  "geometry": {"coordinates":[0.565662,51.224262],"type":"Point"}
}