{
  "type": "Feature",
  "properties": {
    "addr:full":"2 Goodwin Crescent, Swinton Mexborough South Yorkshire S64 8QR",
    "addr:housenumber":"2",
    "addr:postcode":"s64 8qr",
    "addr:street":"Goodwin Crescent",
    "iso:country":"GB",
    "sg:address":"2 Goodwin Crescent, Swinton",
    "sg:city":"Mexborough",
    "sg:classifiers":[
        {
            "category":"Social Services",
            "subcategory":"Child Care",
            "type":"Services"
        },
        {
            "category":"Social Services",
            "subcategory":"Retirement Home",
            "type":"Services"
        },
        {
            "category":"Government",
            "subcategory":"Office",
            "type":"Public Place"
        }
    ],
    "sg:phone":"+44 1709 583539",
    "sg:postcode":"S64 8QR",
    "sg:province":"South Yorkshire",
    "sg:tags":[
        "children's",
        "local"
    ],
    "wof:name":"Goodwin Crescent Children'S Home",
    "wof:placetype":"venue"
},
  "geometry": {"coordinates":[-1.317869,53.487766],"type":"Point"}
}