{
  "type": "Feature",
  "properties": {
    "addr:full":"7 Fiveways Parade, Dane Lane Hazel Grove Stockport Cheshire SK7 6DG",
    "addr:housenumber":"7",
    "addr:postcode":"sk7 6dg",
    "addr:street":"Fiveways Parade Dane Lane",
    "iso:country":"GB",
    "sg:address":"7 Fiveways Parade, Dane Lane Hazel Grove",
    "sg:city":"Stockport",
    "sg:classifiers":[
        {
            "category":"Fast Food",
            "type":"Food & Drink"
        }
    ],
    "sg:phone":"+44 161 224 3226",
    "sg:postcode":"SK7 6DG",
    "sg:province":"Cheshire",
    "sg:tags":[
        "away",
        "take"
    ],
    "wof:name":"Silverwise Ltd.",
    "wof:placetype":"venue"
},
  "geometry": {"coordinates":[-2.113808,53.36758],"type":"Point"}
}