{
  "type": "Feature",
  "properties": {
    "addr:full":"Unit 2b London Greater London N19 4AJ",
    "addr:housenumber":"unit 2b",
    "addr:postcode":"n19 4aj",
    "iso:country":"GB",
    "sg:address":"Unit 2b",
    "sg:city":"London",
    "sg:classifiers":[
        {
            "category":"Wholesale",
            "subcategory":"Electrical",
            "type":"Manufacturing & Wholesale Goods"
        },
        {
            "category":"Home & Garden",
            "subcategory":"Kitchen Supply",
            "type":"Retail Goods"
        }
    ],
    "sg:phone":"+44 20 7263 3153",
    "sg:postcode":"N19 4AJ",
    "sg:province":"Greater London",
    "sg:tags":[
        "equipment",
        "refrigeration",
        "catering"
    ],
    "wof:name":"C R S Refrigeration",
    "wof:placetype":"venue"
},
  "geometry": {"coordinates":[-0.0879139975,51.5073699951],"type":"Point"}
}