{
  "type": "Feature",
  "properties": {
    "iso:country":"GB",
    "sg:address":"Unit 15 Binghams Park Farm, Potten End Hill",
    "sg:city":"Hemel Hempstead",
    "sg:classifiers":[
        {
            "category":"Communications",
            "type":"Services"
        },
        {
            "category":"Professional",
            "subcategory":"Computer Services",
            "type":"Services"
        }
    ],
    "sg:phone":"+44 1442 234808",
    "sg:postcode":"HP1 3BN",
    "sg:province":"Hertfordshire",
    "sg:tags":[
        "support",
        "data",
        "network"
    ],
    "wof:name":"Cable Dynamics Ltd",
    "wof:placetype":"venue"
},
  "geometry": {"coordinates":[-0.496389,51.765163],"type":"Point"}
}