{
  "type": "Feature",
  "properties": {
    "iso:country":"GB",
    "sg:address":"92 Camden High Street",
    "sg:city":"London",
    "sg:classifiers":[
        {
            "category":"Professional",
            "subcategory":"Printing & Photocopies",
            "type":"Services"
        },
        {
            "category":"Government",
            "subcategory":"Post Office",
            "type":"Public Place"
        }
    ],
    "sg:phone":"+44 20 8201 9939",
    "sg:postcode":"NW1 0LT",
    "sg:province":"Greater London",
    "sg:tags":[
        "print",
        "typesetter"
    ],
    "wof:name":"Creative Text Ltd.",
    "wof:placetype":"venue"
},
  "geometry": {"coordinates":[-0.138444,51.539131],"type":"Point"}
}