{
  "type": "Feature",
  "properties": {
    "iso:country":"GB",
    "sg:address":"Newlands Industrial Estate, Leeds Road",
    "sg:city":"Shipley",
    "sg:classifiers":[
        {
            "category":"Retail",
            "subcategory":"Auto Repair",
            "type":"Services"
        }
    ],
    "sg:postcode":"BD18 1BN",
    "sg:province":"West Yorkshire",
    "sg:tags":[
        "modification",
        "garage"
    ],
    "wof:name":"Jerry Royner",
    "wof:placetype":"venue"
},
  "geometry": {"coordinates":[-1.7677899599,53.8352088928],"type":"Point"}
}