{
  "type": "Feature",
  "properties": {
    "addr:full":"47 Goodyers Avenue Radlett Hertfordshire WD7 8AZ",
    "addr:housenumber":"47",
    "addr:postcode":"wd7 8az",
    "addr:street":"Goodyers Avenue",
    "iso:country":"GB",
    "sg:address":"47 Goodyers Avenue",
    "sg:city":"Radlett",
    "sg:classifiers":[
        {
            "category":"Shopping",
            "subcategory":"Department Store",
            "type":"Retail Goods"
        }
    ],
    "sg:phone":"+44 1923 855563",
    "sg:postcode":"WD7 8AZ",
    "sg:province":"Hertfordshire",
    "wof:name":"Microcroft Ltd.",
    "wof:placetype":"venue"
},
  "geometry": {"coordinates":[-0.325042,51.690674],"type":"Point"}
}