{
  "type": "Feature",
  "properties": {
    "addr:full":"33 Mill Vale Bromley Kent BR2 0EN",
    "addr:housenumber":"33",
    "addr:postcode":"br2 0en",
    "addr:street":"Mill Vale",
    "iso:country":"GB",
    "sg:address":"33 Mill Vale",
    "sg:city":"Bromley",
    "sg:classifiers":[
        {
            "category":"Professional",
            "subcategory":"Management & Consulting",
            "type":"Services"
        }
    ],
    "sg:postcode":"BR2 0EN",
    "sg:province":"Kent",
    "sg:tags":[
        "consultant",
        "business"
    ],
    "wof:name":"Cred-A-Bill Consultants Ltd",
    "wof:placetype":"venue"
},
  "geometry": {"coordinates":[0.011212,51.403111],"type":"Point"}
}