{
  "type": "Feature",
  "properties": {
    "iso:country":"GB",
    "sg:address":"57 St Peters Court, High Street, Chalfont St Peter",
    "sg:city":"Gerrards Cross",
    "sg:classifiers":[
        {
            "category":"Real Estate",
            "subcategory":"Real Estate Agent",
            "type":"Services"
        }
    ],
    "sg:phone":"+44 1753 888288",
    "sg:postcode":"SL9 9QQ",
    "sg:province":"Buckinghamshire",
    "wof:name":"The Brampton Partnership",
    "wof:placetype":"venue"
},
  "geometry": {"coordinates":[-0.555914,51.60751],"type":"Point"}
}