{
  "type": "Feature",
  "properties": {
    "iso:country":"GB",
    "sg:address":"4 Hanborough Business Park, Lodge Road",
    "sg:city":"Witney",
    "sg:classifiers":[
        {
            "category":"Wholesale",
            "subcategory":"Groceries",
            "type":"Manufacturing & Wholesale Goods"
        }
    ],
    "sg:postcode":"OX29 8LH",
    "sg:province":"Oxfordshire",
    "sg:tags":[
        "frozen",
        "food",
        "-"
    ],
    "wof:name":"Checkmate International Plc",
    "wof:placetype":"venue"
},
  "geometry": {"coordinates":[-1.3691389561,51.8259468079],"type":"Point"}
}