{
  "type": "Feature",
  "properties": {
    "iso:country":"GB",
    "sg:address":"13 Belle Vue",
    "sg:city":"Bude",
    "sg:classifiers":[
        {
            "category":"Shopping",
            "subcategory":"Clothing, Apparel, & Fashions",
            "type":"Retail Goods"
        }
    ],
    "sg:phone":"+44 1288 353789",
    "sg:postcode":"EX23 8JN",
    "sg:province":"Cornwall",
    "sg:tags":[
        "ladieswear"
    ],
    "wof:name":"Wroe's (Bude) Ltd.",
    "wof:placetype":"venue"
},
  "geometry": {"coordinates":[-4.5452752113,50.8299255371],"type":"Point"}
}