{
  "type": "Feature",
  "properties": {
    "iso:country":"GB",
    "sg:address":"57 Calcutta Road",
    "sg:city":"Tilbury",
    "sg:classifiers":[
        {
            "category":"Health Services",
            "subcategory":"Doctor",
            "type":"Services"
        }
    ],
    "sg:phone":"+44 1375 859535",
    "sg:postcode":"RM18 7QZ",
    "sg:province":"Essex",
    "sg:tags":[
        "practitioners"
    ],
    "wof:name":"Dutta & Mukhopadhyay Drs",
    "wof:placetype":"venue"
},
  "geometry": {"coordinates":[0.3604710102,51.461605072],"type":"Point"}
}