{
  "type": "Feature",
  "properties": {
    "addr:full":"Rogers Hill Farmhouse, Cuxham Watlington Oxfordshire OX49 5NF",
    "addr:postcode":"ox49 5nf",
    "addr:street":"Cuxham",
    "iso:country":"GB",
    "sg:address":"Rogers Hill Farmhouse, Cuxham",
    "sg:city":"Watlington",
    "sg:classifiers":[
        {
            "category":"Professional",
            "subcategory":"Management & Consulting",
            "type":"Services"
        }
    ],
    "sg:postcode":"OX49 5NF",
    "sg:province":"Oxfordshire",
    "sg:tags":[
        "consultant",
        "business"
    ],
    "wof:name":"Martin Hart Associates Ltd",
    "wof:placetype":"venue"
},
  "geometry": {"coordinates":[-1.005681,51.644085],"type":"Point"}
}