{
  "type": "Feature",
  "properties": {
    "iso:country":"GB",
    "sg:address":"Unit 4a & B Alness Industrial Estate",
    "sg:city":"Alness",
    "sg:classifiers":[
        {
            "category":"Manufacturing",
            "subcategory":"Wood Products",
            "type":"Manufacturing & Wholesale Goods"
        }
    ],
    "sg:phone":"+44 1349 882734",
    "sg:postcode":"IV17 0XS",
    "sg:province":"Highland",
    "sg:tags":[
        "packaging",
        "crate",
        "pallets"
    ],
    "wof:name":"Tough Packaging Ltd.",
    "wof:placetype":"venue"
},
  "geometry": {"coordinates":[-4.26401,57.694801],"type":"Point"}
}