{
  "type": "Feature",
  "properties": {
    "addr:full":"2nd Floor Office, 4a Falklands House, 659-666 Green Lanes Hornsey Greater London N8 0QY",
    "addr:housenumber":"2nd floor office 4a falklands;659-666",
    "addr:postcode":"n8 0qy",
    "addr:street":"Green Lanes",
    "iso:country":"GB",
    "sg:address":"2nd Floor Office, 4a Falklands House, 659-666 Green Lanes",
    "sg:city":"Hornsey",
    "sg:classifiers":[
        {
            "category":"Building & Trades",
            "subcategory":"Construction",
            "type":"Services"
        }
    ],
    "sg:phone":"+44 20 8341 6229",
    "sg:postcode":"N8 0QY",
    "sg:province":"Greater London",
    "sg:tags":[
        "builder"
    ],
    "wof:name":"Lavender Construction",
    "wof:placetype":"venue"
},
  "geometry": {"coordinates":[-0.100921,51.586281],"type":"Point"}
}