{
  "type": "Feature",
  "properties": {
    "iso:country":"GB",
    "sg:address":"92 Westwood Rd, Tilehurst",
    "sg:city":"Reading",
    "sg:classifiers":[
        {
            "category":"Health Services",
            "subcategory":"Doctor",
            "type":"Services"
        }
    ],
    "sg:phone":"+44 118 945 2303",
    "sg:postcode":"RG31 5PP",
    "sg:province":"Berkshire",
    "sg:tags":[
        "practitioners"
    ],
    "wof:name":"Underwood Pizura Medical Services",
    "wof:placetype":"venue"
},
  "geometry": {"coordinates":[-1.042366,51.461315],"type":"Point"}
}