{
  "type": "Feature",
  "properties": {
    "iso:country":"GB",
    "sg:address":"Acorn House, Victoria Road",
    "sg:city":"London",
    "sg:classifiers":[
        {
            "category":"Home & Garden",
            "subcategory":"Furniture",
            "type":"Retail Goods"
        }
    ],
    "sg:postcode":"W3 6XU",
    "sg:province":"Greater London",
    "wof:name":"Bedtime & Sofabeds International",
    "wof:placetype":"venue"
},
  "geometry": {"coordinates":[-0.25918,51.5229],"type":"Point"}
}