{
  "type": "Feature",
  "properties": {
    "addr:full":"4 Station Road West Wickham Kent BR4 0PR",
    "addr:housenumber":"4",
    "addr:postcode":"br4 0pr",
    "addr:street":"Station Road",
    "iso:country":"GB",
    "sg:address":"4 Station Road",
    "sg:city":"West Wickham",
    "sg:classifiers":[
        {
            "category":"Shopping",
            "subcategory":"Hobbies, Toys, & Games",
            "type":"Retail Goods"
        }
    ],
    "sg:phone":"+44 20 8776 0248",
    "sg:postcode":"BR4 0PR",
    "sg:province":"Kent",
    "sg:tags":[
        "house",
        "dolls'",
        "doll"
    ],
    "wof:name":"Doll's House Junction",
    "wof:placetype":"venue"
},
  "geometry": {"coordinates":[-0.014619,51.379433],"type":"Point"}
}