{
  "type": "Feature",
  "properties": {
    "addr:full":"6 Markham Crescent, Rawdon Leeds West Yorkshire LS19 6NG",
    "addr:housenumber":"6",
    "addr:postcode":"ls19 6ng",
    "addr:street":"Markham Crescent",
    "iso:country":"GB",
    "sg:address":"6 Markham Crescent, Rawdon",
    "sg:city":"Leeds",
    "sg:classifiers":[
        {
            "category":"Education",
            "subcategory":"University",
            "type":"Public Place"
        }
    ],
    "sg:phone":"+44 113 250 4325",
    "sg:postcode":"LS19 6NG",
    "sg:province":"West Yorkshire",
    "sg:tags":[
        "higher"
    ],
    "wof:name":"Allens School of Motoring",
    "wof:placetype":"venue"
},
  "geometry": {"coordinates":[-1.6768900156,53.8590164185],"type":"Point"}
}