{
  "type": "Feature",
  "properties": {
    "iso:country":"GB",
    "sg:address":"3a Harpings Road",
    "sg:city":"Hull",
    "sg:classifiers":[
        {
            "category":"Manufacturing",
            "subcategory":"Petroleum Products",
            "type":"Manufacturing & Wholesale Goods"
        }
    ],
    "sg:phone":"+44 1482 225638",
    "sg:postcode":"HU5 4JF",
    "sg:province":"East Riding of Yorkshire",
    "sg:tags":[
        "double",
        "glazing"
    ],
    "wof:name":"Goldstar Double Glazing Ltd.",
    "wof:placetype":"venue"
},
  "geometry": {"coordinates":[-0.38115,53.755646],"type":"Point"}
}