{
  "type": "Feature",
  "properties": {
    "iso:country":"GB",
    "sg:address":"21 Main Street, Barton Under Needwood",
    "sg:city":"Burton-on-trent",
    "sg:classifiers":[
        {
            "category":"Professional",
            "subcategory":"Lawyer & Legal Services",
            "type":"Services"
        }
    ],
    "sg:phone":"+44 1283 716218",
    "sg:postcode":"DE13 8AA",
    "sg:province":"Derbyshire",
    "sg:tags":[
        "solicitor"
    ],
    "wof:name":"F B Booth & Co",
    "wof:placetype":"venue"
},
  "geometry": {"coordinates":[-1.722516,52.764294],"type":"Point"}
}