{
  "type": "Feature",
  "properties": {
    "iso:country":"GB",
    "sg:address":"131 Clydesdale Place, Moss Side Industrial Estate",
    "sg:city":"Preston",
    "sg:classifiers":[
        {
            "category":"Building & Trades",
            "subcategory":"Construction",
            "type":"Services"
        }
    ],
    "sg:phone":"+44 1772 623271",
    "sg:postcode":"PR26 7QS",
    "sg:province":"Lancashire",
    "sg:tags":[
        "concrete"
    ],
    "wof:name":"Cracks Ltd.",
    "wof:placetype":"venue"
},
  "geometry": {"coordinates":[-2.721529,53.700089],"type":"Point"}
}