{
  "type": "Feature",
  "properties": {
    "iso:country":"GB",
    "sg:address":"Tayler Bradshaw, Cambridge House 16 High Street",
    "sg:city":"Saffron Walden",
    "sg:classifiers":[
        {
            "category":"Building & Trades",
            "subcategory":"Construction",
            "type":"Services"
        }
    ],
    "sg:postcode":"CB10 1AX",
    "sg:province":"Cambridgeshire",
    "sg:tags":[
        "builder"
    ],
    "wof:name":"Western Electric Contractors Ltd",
    "wof:placetype":"venue"
},
  "geometry": {"coordinates":[0.238812,52.023499],"type":"Point"}
}