{
  "type": "Feature",
  "properties": {
    "addr:full":"P O Box 66 Preston Lancashire PR1 3XZ",
    "addr:housenumber":"box 66",
    "addr:postcode":"pr1 3xz",
    "addr:street":"P O;Preston",
    "iso:country":"GB",
    "sg:address":"P O Box 66",
    "sg:city":"Preston",
    "sg:classifiers":[
        {
            "category":"Professional",
            "subcategory":"Computer Services",
            "type":"Services"
        }
    ],
    "sg:phone":"+44 1772 615966",
    "sg:postcode":"PR1 3XZ",
    "sg:province":"Lancashire",
    "sg:tags":[
        "security",
        "retail"
    ],
    "wof:name":"A D C T Group",
    "wof:placetype":"venue"
},
  "geometry": {"coordinates":[-2.705729,53.757961],"type":"Point"}
}