{
  "type": "Feature",
  "properties": {
    "iso:country":"GB",
    "sg:address":"6 The Priors, Lowdham",
    "sg:city":"Nottingham",
    "sg:classifiers":[
        {
            "category":"Building & Trades",
            "subcategory":"Construction",
            "type":"Services"
        }
    ],
    "sg:postcode":"NG14 7BA",
    "sg:province":"Nottinghamshire",
    "sg:tags":[
        "builder"
    ],
    "wof:name":"Wilkins & Robinson",
    "wof:placetype":"venue"
},
  "geometry": {"coordinates":[-1.0015540123,53.0087013245],"type":"Point"}
}