{
  "type": "Feature",
  "properties": {
    "addr:full":"Gwelva, Trewetha Port Isaac Cornwall PL29 3RU",
    "addr:postcode":"pl29 3ru",
    "iso:country":"GB",
    "sg:address":"Gwelva, Trewetha",
    "sg:city":"Port Isaac",
    "sg:classifiers":[
        {
            "category":"Wholesale",
            "subcategory":"Electrical",
            "type":"Manufacturing & Wholesale Goods"
        }
    ],
    "sg:postcode":"PL29 3RU",
    "sg:province":"Cornwall",
    "sg:tags":[
        "equipment",
        "refrigeration"
    ],
    "wof:name":"Paul & Noyce (Bodmin) Refrigeration Services",
    "wof:placetype":"venue"
},
  "geometry": {"coordinates":[-4.828199,50.592339],"type":"Point"}
}