{
  "type": "Feature",
  "properties": {
    "addr:full":"103 Cordy Lane, Brinsley Nottingham Nottingham Derbyshire NG16 5BZ",
    "addr:housenumber":"103",
    "addr:postcode":"ng16 5bz",
    "addr:street":"Cordy Lane",
    "iso:country":"GB",
    "sg:address":"103 Cordy Lane, Brinsley Nottingham",
    "sg:city":"Nottingham",
    "sg:classifiers":[
        {
            "category":"Building & Trades",
            "subcategory":"Construction",
            "type":"Services"
        }
    ],
    "sg:phone":"+44 1773 719181",
    "sg:postcode":"NG16 5BZ",
    "sg:province":"Derbyshire",
    "sg:tags":[
        "flooring"
    ],
    "wof:name":"20th Century Clean Care",
    "wof:placetype":"venue"
},
  "geometry": {"coordinates":[-1.301498,53.044426],"type":"Point"}
}