{
  "type": "Feature",
  "properties": {
    "addr:full":"Clapham Rd Lowestoft Suffolk NR32 1QR",
    "addr:postcode":"nr32 1qr",
    "addr:street":"Clapham Rd",
    "iso:country":"GB",
    "sg:address":"Clapham Rd",
    "sg:city":"Lowestoft",
    "sg:classifiers":[
        {
            "category":"Building & Trades",
            "subcategory":"Plumbing",
            "type":"Services"
        }
    ],
    "sg:phone":"+44 1502 501950",
    "sg:postcode":"NR32 1QR",
    "sg:province":"Suffolk",
    "sg:tags":[
        "drain",
        "clearance",
        "sewer"
    ],
    "wof:name":"Metro Rod",
    "wof:placetype":"venue"
},
  "geometry": {"coordinates":[1.751341,52.481197],"type":"Point"}
}