{
  "type": "Feature",
  "properties": {
    "addr:full":"145 Church Lane, Lowton Warrington Cheshire WA3 2RH",
    "addr:housenumber":"145",
    "addr:postcode":"wa3 2rh",
    "addr:street":"Church Lane",
    "iso:country":"GB",
    "sg:address":"145 Church Lane, Lowton",
    "sg:city":"Warrington",
    "sg:classifiers":[
        {
            "category":"Building & Trades",
            "subcategory":"Construction",
            "type":"Services"
        }
    ],
    "sg:phone":"+44 1942 714330",
    "sg:postcode":"WA3 2RH",
    "sg:province":"Cheshire",
    "sg:tags":[
        "joiner",
        "carpenter"
    ],
    "wof:name":"M Meedon",
    "wof:placetype":"venue"
},
  "geometry": {"coordinates":[-2.5775339603,53.4724845886],"type":"Point"}
}