{
  "type": "Feature",
  "properties": {
    "addr:full":"18a Bush Hill Pde, Village Rd Enfield Greater London EN1 2HB",
    "addr:housenumber":"18a",
    "addr:postcode":"en1 2hb",
    "addr:street":"Bush Hill Pde Village Rd",
    "iso:country":"GB",
    "sg:address":"18a Bush Hill Pde, Village Rd",
    "sg:city":"Enfield",
    "sg:classifiers":[
        {
            "category":"Shopping",
            "subcategory":"Comic Books",
            "type":"Retail Goods"
        }
    ],
    "sg:postcode":"EN1 2HB",
    "sg:province":"Greater London",
    "sg:tags":[
        "jeweller"
    ],
    "wof:name":"Hewstone Watchmaker",
    "wof:placetype":"venue"
},
  "geometry": {"coordinates":[-0.08093,51.636749],"type":"Point"}
}