{
  "type": "Feature",
  "properties": {
    "iso:country":"GB",
    "sg:address":"35 Worcester Road",
    "sg:city":"Bromsgrove",
    "sg:classifiers":[
        {
            "category":"Personal",
            "subcategory":"Beauty Salon",
            "type":"Services"
        },
        {
            "category":"Personal",
            "subcategory":"Barber",
            "type":"Services"
        }
    ],
    "sg:phone":"+44 1527 880012",
    "sg:postcode":"B61 7DN",
    "sg:province":"Worcestershire",
    "sg:tags":[
        "unisex",
        "hairdresser"
    ],
    "wof:name":"Razors",
    "wof:placetype":"venue"
},
  "geometry": {"coordinates":[-2.063018,52.332745],"type":"Point"}
}