{
  "type": "Feature",
  "properties": {
    "addr:full":"29 Ernest Road, Emerson Park Hornchurch Essex RM11 3JG",
    "addr:housenumber":"29",
    "addr:postcode":"rm11 3jg",
    "addr:street":"Ernest Road",
    "iso:country":"GB",
    "sg:address":"29 Ernest Road, Emerson Park",
    "sg:city":"Hornchurch",
    "sg:classifiers":[
        {
            "category":"Health Services",
            "subcategory":"Health Practitioner",
            "type":"Services"
        }
    ],
    "sg:phone":"+44 1708 455650",
    "sg:postcode":"RM11 3JG",
    "sg:province":"Essex",
    "sg:tags":[
        "osteopath"
    ],
    "wof:name":"Alan Chapman",
    "wof:placetype":"venue"
},
  "geometry": {"coordinates":[0.2302200049,51.5721130371],"type":"Point"}
}