{
  "type": "Feature",
  "properties": {
    "addr:full":"Townhouse, Wharf Lane Bourne End Berkshire SL8 5RS",
    "addr:postcode":"sl8 5rs",
    "addr:street":"Wharf Lane",
    "iso:country":"GB",
    "sg:address":"Townhouse, Wharf Lane",
    "sg:city":"Bourne End",
    "sg:classifiers":[
        {
            "category":"Professional",
            "subcategory":"Engineering",
            "type":"Services"
        }
    ],
    "sg:phone":"+44 1628 526613",
    "sg:postcode":"SL8 5RS",
    "sg:province":"Berkshire",
    "sg:tags":[
        "consulting",
        "engineer"
    ],
    "wof:name":"Streams Consulting",
    "wof:placetype":"venue"
},
  "geometry": {"coordinates":[-0.713174,51.579506],"type":"Point"}
}