{
  "type": "Feature",
  "properties": {
    "addr:full":"275-277 Chanterlands Avenue Hull East Riding of Yorkshire HU5 4DL",
    "addr:postcode":"275-277;hu5 4dl",
    "addr:street":"Chanterlands Avenue",
    "iso:country":"GB",
    "sg:address":"275-277 Chanterlands Avenue",
    "sg:city":"Hull",
    "sg:classifiers":[
        {
            "category":"Shopping",
            "subcategory":"Department Store",
            "type":"Retail Goods"
        },
        {
            "category":"Shopping",
            "subcategory":"Bicycles & Sporting Goods",
            "type":"Retail Goods"
        }
    ],
    "sg:phone":"+44 1482 446341",
    "sg:postcode":"HU5 4DL",
    "sg:province":"East Riding of Yorkshire",
    "sg:tags":[
        "accessory",
        "cycle"
    ],
    "wof:name":"Ken Ellerker Cycles",
    "wof:placetype":"venue"
},
  "geometry": {"coordinates":[-0.3749170005,53.7597007751],"type":"Point"}
}