{
  "type": "Feature",
  "properties": {
    "iso:country":"GB",
    "sg:address":"88 Church Street",
    "sg:city":"Littleborough",
    "sg:classifiers":[
        {
            "category":"Shopping",
            "subcategory":"Clothing, Apparel, & Fashions",
            "type":"Retail Goods"
        }
    ],
    "sg:postcode":"OL15 8AU",
    "sg:province":"Lancashire",
    "sg:tags":[
        "shop"
    ],
    "wof:name":"Good-Buys",
    "wof:placetype":"venue"
},
  "geometry": {"coordinates":[-2.097742,53.643681],"type":"Point"}
}