{
  "type": "Feature",
  "properties": {
    "iso:country":"GB",
    "sg:address":"Glenfarg St",
    "sg:city":"Glasgow",
    "sg:classifiers":[
        {
            "category":"Government",
            "subcategory":"City Hall",
            "type":"Public Place"
        }
    ],
    "sg:phone":"+44 141 332 3651",
    "sg:postcode":"G20 7QE",
    "sg:province":"Glasgow City",
    "wof:name":"Woodside Hall",
    "wof:placetype":"venue"
},
  "geometry": {"coordinates":[-4.2663397789,55.8724403381],"type":"Point"}
}