{
  "type": "Feature",
  "properties": {
    "iso:country":"GB",
    "sg:address":"The Maltings, 54 Bath Street",
    "sg:city":"Gravesend",
    "sg:classifiers":[
        {
            "category":"Professional",
            "subcategory":"Management & Consulting",
            "type":"Services"
        }
    ],
    "sg:phone":"+44 20 8467 6339",
    "sg:postcode":"DA11 0DF",
    "sg:province":"Kent",
    "sg:tags":[
        "marketing",
        "consultant"
    ],
    "wof:name":"Advertising Excellence Ltd.",
    "wof:placetype":"venue"
},
  "geometry": {"coordinates":[0.364606,51.432827],"type":"Point"}
}