{
  "type": "Feature",
  "properties": {
    "addr:full":"Unit 26 Telegraph Way Liverpool Merseyside L32 8US",
    "addr:housenumber":"unit 26",
    "addr:postcode":"l32 8us",
    "addr:street":"Telegraph Way",
    "iso:country":"GB",
    "sg:address":"Unit 26 Telegraph Way",
    "sg:city":"Liverpool",
    "sg:classifiers":[
        {
            "category":"Professional",
            "subcategory":"Business Services",
            "type":"Services"
        }
    ],
    "sg:postcode":"L32 8US",
    "sg:province":"Merseyside",
    "sg:tags":[
        "tile",
        "stockist"
    ],
    "wof:name":"Thomas McEvoy",
    "wof:placetype":"venue"
},
  "geometry": {"coordinates":[-2.8877310753,53.4834785461],"type":"Point"}
}