{
  "type": "Feature",
  "properties": {
    "iso:country":"GB",
    "sg:address":"Elizabeth Way, Pinnacles",
    "sg:city":"Harlow",
    "sg:classifiers":[
        {
            "category":"Autos & Motor Vehicles",
            "subcategory":"Fuel & Gas Station",
            "type":"Retail Goods"
        }
    ],
    "sg:postcode":"CM19 5AR",
    "sg:province":"Essex",
    "sg:tags":[
        "petrol",
        "filling"
    ],
    "wof:name":"Elf Harlow Self Services",
    "wof:placetype":"venue"
},
  "geometry": {"coordinates":[0.0679,51.76796],"type":"Point"}
}