{
  "type": "Feature",
  "properties": {
    "iso:country":"GB",
    "sg:address":"7 Westmede Centre",
    "sg:city":"Coventry",
    "sg:classifiers":[
        {
            "category":"Fast Food",
            "type":"Food & Drink"
        }
    ],
    "sg:phone":"+44 24 7667 7637",
    "sg:postcode":"CV5 9AF",
    "sg:province":"West Midlands",
    "sg:tags":[
        "away",
        "meal",
        "outlet",
        "take"
    ],
    "wof:name":"Pubali Indian Takeway",
    "wof:placetype":"venue"
},
  "geometry": {"coordinates":[-1.554484,52.41301],"type":"Point"}
}