{
  "type": "Feature",
  "properties": {
    "addr:full":"Unit 216 Solent Business Centre, 343 Millbrook Road West Southampton Hampshire SO15 0HW",
    "addr:housenumber":"216;343",
    "addr:postcode":"so15 0hw",
    "addr:street":"Solent Business;Millbrook Road West",
    "iso:country":"GB",
    "sg:address":"Unit 216 Solent Business Centre, 343 Millbrook Road West",
    "sg:city":"Southampton",
    "sg:classifiers":[
        {
            "category":"Professional",
            "type":"Services"
        }
    ],
    "sg:phone":"+44 23 8048 5100",
    "sg:postcode":"SO15 0HW",
    "sg:province":"Hampshire",
    "sg:tags":[
        "interior",
        "furnishers",
        "designer"
    ],
    "wof:name":"Dove Interiors",
    "wof:placetype":"venue"
},
  "geometry": {"coordinates":[-1.4073189497,50.9099388123],"type":"Point"}
}