{
  "type": "Feature",
  "properties": {
    "addr:full":"498 Church Road, Frampton Cotterell Bristol Gloucestershire BS36 2AL",
    "addr:housenumber":"498",
    "addr:postcode":"bs36 2al",
    "addr:street":"Church Road",
    "iso:country":"GB",
    "sg:address":"498 Church Road, Frampton Cotterell",
    "sg:city":"Bristol",
    "sg:classifiers":[
        {
            "category":"Professional",
            "subcategory":"Advertising",
            "type":"Services"
        }
    ],
    "sg:phone":"+44 1454 774271",
    "sg:postcode":"BS36 2AL",
    "sg:province":"Gloucestershire",
    "sg:tags":[
        "agency"
    ],
    "wof:name":"Geoff Bunce Creative Ltd.",
    "wof:placetype":"venue"
},
  "geometry": {"coordinates":[-2.4636180401,51.53099823],"type":"Point"}
}