{
  "type": "Feature",
  "properties": {
    "iso:country":"GB",
    "sg:address":"78 Waterfall Lane",
    "sg:city":"Cradley Heath",
    "sg:classifiers":[
        {
            "category":"Bars & Pubs",
            "type":"Food & Drink"
        }
    ],
    "sg:phone":"+44 121 559 4565",
    "sg:postcode":"B64 6RL",
    "sg:province":"West Midlands",
    "sg:tags":[
        "pubs",
        "inn"
    ],
    "wof:name":"The Three Furnaces",
    "wof:placetype":"venue"
},
  "geometry": {"coordinates":[-2.053619,52.472939],"type":"Point"}
}