{
  "type": "Feature",
  "properties": {
    "addr:full":"20 Crieff Road Perth Perth and Kinross PH1 5AF",
    "addr:housenumber":"20",
    "addr:postcode":"ph1 5af",
    "addr:street":"Crieff Road",
    "iso:country":"GB",
    "sg:address":"20 Crieff Road",
    "sg:city":"Perth",
    "sg:classifiers":[
        {
            "category":"Shopping",
            "subcategory":"News",
            "type":"Retail Goods"
        }
    ],
    "sg:phone":"+44 1738 633554",
    "sg:postcode":"PH1 5AF",
    "sg:province":"Perth and Kinross",
    "sg:tags":[
        "newsagent"
    ],
    "wof:name":"Crieff Road Newsagents",
    "wof:placetype":"venue"
},
  "geometry": {"coordinates":[-3.444746,56.403534],"type":"Point"}
}