{
  "type": "Feature",
  "properties": {
    "addr:full":"Willingham Fen Cambridge Cambridgeshire CB4 5JN",
    "addr:postcode":"cb4 5jn",
    "iso:country":"GB",
    "sg:address":"Willingham Fen",
    "sg:city":"Cambridge",
    "sg:classifiers":[
        {
            "category":"Home & Garden",
            "subcategory":"Garden Supply",
            "type":"Retail Goods"
        },
        {
            "category":"Farming",
            "subcategory":"Livestock Farm",
            "type":"Manufacturing & Wholesale Goods"
        }
    ],
    "sg:postcode":"CB4 5JN",
    "sg:province":"Cambridgeshire",
    "sg:tags":[
        "bulb",
        "grower",
        "others"
    ],
    "wof:name":"E Gilbert & Sons",
    "wof:placetype":"venue"
},
  "geometry": {"coordinates":[0.0574790016,52.313709259],"type":"Point"}
}