{
  "type": "Feature",
  "properties": {
    "addr:full":"Portland House Westminster Greater London SW1E 5DP",
    "addr:postcode":"sw1e 5dp",
    "iso:country":"GB",
    "sg:address":"Portland House",
    "sg:city":"Westminster",
    "sg:classifiers":[
        {
            "category":"Government",
            "subcategory":"Post Office",
            "type":"Public Place"
        }
    ],
    "sg:phone":"+44 171 393 1600",
    "sg:postcode":"SW1E 5DP",
    "sg:province":"Greater London",
    "sg:tags":[
        "organisation",
        "soc",
        "research"
    ],
    "wof:name":"Overseas Development Institute",
    "wof:placetype":"venue"
},
  "geometry": {"coordinates":[-0.123684,51.5009],"type":"Point"}
}