{
  "type": "Feature",
  "properties": {
    "addr:full":"Office No 6 Wellington House, Messeter Place, Eltham London Greater London SE9 5DP",
    "addr:housenumber":"office no 6",
    "addr:postcode":"se9 5dp",
    "addr:street":"Wellington;Messeter Place",
    "iso:country":"GB",
    "sg:address":"Office No 6 Wellington House, Messeter Place, Eltham",
    "sg:city":"London",
    "sg:classifiers":[
        {
            "category":"Organizations",
            "subcategory":"Membership Organization",
            "type":"Services"
        }
    ],
    "sg:phone":"+44 20 8859 6943",
    "sg:postcode":"SE9 5DP",
    "sg:province":"Greater London",
    "sg:tags":[
        "club"
    ],
    "wof:name":"British Sugarcraft Guild",
    "wof:placetype":"venue"
},
  "geometry": {"coordinates":[0.06054,51.450039],"type":"Point"}
}