{
  "type": "Feature",
  "properties": {
    "addr:full":"58 Smithy Lane, Wilnecote Tamworth Staffordshire B77 5LA",
    "addr:housenumber":"58",
    "addr:postcode":"b77 5la",
    "addr:street":"Smithy Lane",
    "iso:country":"GB",
    "sg:address":"58 Smithy Lane, Wilnecote",
    "sg:city":"Tamworth",
    "sg:classifiers":[
        {
            "category":"Building & Trades",
            "subcategory":"Construction",
            "type":"Services"
        }
    ],
    "sg:postcode":"B77 5LA",
    "sg:province":"Staffordshire",
    "sg:tags":[
        "window",
        "replacement"
    ],
    "wof:name":"Justice Windows Ltd",
    "wof:placetype":"venue"
},
  "geometry": {"coordinates":[-1.665079,52.60741],"type":"Point"}
}