{
  "type": "Feature",
  "properties": {
    "iso:country":"GB",
    "sg:address":"179 New Kings Road, Fulham",
    "sg:city":"London",
    "sg:classifiers":[
        {
            "category":"Retail",
            "subcategory":"Laundry & Dry Cleaning",
            "type":"Services"
        }
    ],
    "sg:phone":"+44 20 7731 5114",
    "sg:postcode":"SW6 4SW",
    "sg:province":"Greater London",
    "sg:tags":[
        "alteration"
    ],
    "wof:name":"Peter Falla",
    "wof:placetype":"venue"
},
  "geometry": {"coordinates":[-0.196775,51.473576],"type":"Point"}
}