{
  "type": "Feature",
  "properties": {
    "addr:full":"Unit 379, Main Street Leicester Leicestershire LE9 6RA",
    "addr:housenumber":"379",
    "addr:postcode":"le9 6ra",
    "addr:street":"Main Street",
    "iso:country":"GB",
    "sg:address":"Unit 379, Main Street",
    "sg:city":"Leicester",
    "sg:classifiers":[
        {
            "category":"Home & Garden",
            "subcategory":"Hardware",
            "type":"Retail Goods"
        }
    ],
    "sg:phone":"+44 1455 289141",
    "sg:postcode":"LE9 6RA",
    "sg:province":"Leicestershire",
    "wof:name":"H & H Hardware & Diy",
    "wof:placetype":"venue"
},
  "geometry": {"coordinates":[-1.230766,52.534901],"type":"Point"}
}