{
  "type": "Feature",
  "properties": {
    "addr:full":"3 Nelson Street Stroud Gloucestershire GL5 2HL",
    "addr:housenumber":"3",
    "addr:postcode":"gl5 2hl",
    "addr:street":"Nelson Street",
    "iso:country":"GB",
    "sg:address":"3 Nelson Street",
    "sg:city":"Stroud",
    "sg:classifiers":[
        {
            "category":"Fast Food",
            "type":"Food & Drink"
        }
    ],
    "sg:phone":"+44 1453 763406",
    "sg:postcode":"GL5 2HL",
    "sg:province":"Gloucestershire",
    "sg:tags":[
        "away",
        "meal",
        "outlet",
        "take"
    ],
    "wof:name":"Nargis Tandoori",
    "wof:placetype":"venue"
},
  "geometry": {"coordinates":[-2.213903904,51.7446670532],"type":"Point"}
}