{
  "type": "Feature",
  "properties": {
    "addr:full":"124 Plover Way, Rotherhithe London Greater London SE16 7TZ",
    "addr:housenumber":"124",
    "addr:postcode":"se16 7tz",
    "addr:street":"Plover Way",
    "iso:country":"GB",
    "sg:address":"124 Plover Way, Rotherhithe",
    "sg:city":"London",
    "sg:classifiers":[
        {
            "category":"Manufacturing",
            "subcategory":"Textiles",
            "type":"Manufacturing & Wholesale Goods"
        }
    ],
    "sg:postcode":"SE16 7TZ",
    "sg:province":"Greater London",
    "wof:name":"Leotex Ltd",
    "wof:placetype":"venue"
},
  "geometry": {"coordinates":[-0.039051,51.4964065552],"type":"Point"}
}