{
  "type": "Feature",
  "properties": {
    "addr:full":"5 Station Road, Castle Donington Derby Leicestershire DE74 2NJ",
    "addr:housenumber":"5",
    "addr:postcode":"de74 2nj",
    "addr:street":"Station Road",
    "iso:country":"GB",
    "sg:address":"5 Station Road, Castle Donington",
    "sg:city":"Derby",
    "sg:classifiers":[
        {
            "category":"Personal",
            "subcategory":"Beauty Salon",
            "type":"Services"
        },
        {
            "category":"Personal",
            "subcategory":"Barber",
            "type":"Services"
        }
    ],
    "sg:phone":"+44 1332 810247",
    "sg:postcode":"DE74 2NJ",
    "sg:province":"Leicestershire",
    "sg:tags":[
        "unisex",
        "hairdresser"
    ],
    "wof:name":"Barnet Fair",
    "wof:placetype":"venue"
},
  "geometry": {"coordinates":[-1.3264420033,52.8505821228],"type":"Point"}
}