{
  "type": "Feature",
  "properties": {
    "addr:full":"Sapphire Ho, Fishponds Rd Wokingham Berkshire RG41 2QL",
    "addr:postcode":"rg41 2ql",
    "addr:street":"Fishponds Rd",
    "iso:country":"GB",
    "sg:address":"Sapphire Ho, Fishponds Rd",
    "sg:city":"Wokingham",
    "sg:classifiers":[
        {
            "category":"Shopping",
            "subcategory":"Gifts & Souvenirs",
            "type":"Retail Goods"
        }
    ],
    "sg:phone":"+44 118 979 5070",
    "sg:postcode":"RG41 2QL",
    "sg:province":"Berkshire",
    "sg:tags":[
        "giftware"
    ],
    "wof:name":"Whispers International Ltd",
    "wof:placetype":"venue"
},
  "geometry": {"coordinates":[-0.8466699719,51.4041404724],"type":"Point"}
}