{
  "type": "Feature",
  "properties": {
    "addr:full":"1 Old Whitwell Colliery, Southfield Lane, Whitwell Worksop Nottinghamshire S80 3LQ",
    "addr:housenumber":"1",
    "addr:postcode":"s80 3lq",
    "addr:street":"Old Whitwell Colliery Southfield Lane",
    "iso:country":"GB",
    "sg:address":"1 Old Whitwell Colliery, Southfield Lane, Whitwell",
    "sg:city":"Worksop",
    "sg:classifiers":[
        {
            "category":"Home & Garden",
            "subcategory":"Building Materials",
            "type":"Retail Goods"
        }
    ],
    "sg:phone":"+44 1909 722339",
    "sg:postcode":"S80 3LQ",
    "sg:province":"Nottinghamshire",
    "sg:tags":[
        "ready",
        "mixed",
        "concrete"
    ],
    "wof:name":"Tarmac Topmix Ltd.",
    "wof:placetype":"venue"
},
  "geometry": {"coordinates":[-1.1263099909,53.2869491577],"type":"Point"}
}