{
  "type": "Feature",
  "properties": {
    "iso:country":"GB",
    "sg:address":"8 Watling Street, Bletchley",
    "sg:city":"Milton Keynes",
    "sg:classifiers":[
        {
            "category":"Autos & Motor Vehicles",
            "subcategory":"Auto Supplies",
            "type":"Retail Goods"
        }
    ],
    "sg:phone":"+44 1908 372391",
    "sg:postcode":"MK2 2BS",
    "sg:province":"Buckinghamshire",
    "sg:tags":[
        "tyre"
    ],
    "wof:name":"Hi-Q Tyre Services",
    "wof:placetype":"venue"
},
  "geometry": {"coordinates":[-0.713739,51.997765],"type":"Point"}
}