{
  "type": "Feature",
  "properties": {
    "addr:full":"North Lyminge Folkestone Kent CT19 6DR",
    "addr:postcode":"ct19 6dr",
    "addr:street":"North Lyminge",
    "iso:country":"GB",
    "sg:address":"North Lyminge",
    "sg:city":"Folkestone",
    "sg:classifiers":[
        {
            "category":"Manufacturing",
            "subcategory":"Wood Products",
            "type":"Manufacturing & Wholesale Goods"
        }
    ],
    "sg:phone":"+44 1303 863334",
    "sg:postcode":"CT19 6DR",
    "sg:province":"Kent",
    "sg:tags":[
        "maker",
        "cabinet"
    ],
    "wof:name":"Thoroughly Wood",
    "wof:placetype":"venue"
},
  "geometry": {"coordinates":[1.19203,51.087601],"type":"Point"}
}