{
  "type": "Feature",
  "properties": {
    "addr:full":"44 Lord Street Redcar North Yorkshire TS10 3HL",
    "addr:housenumber":"44",
    "addr:postcode":"ts10 3hl",
    "addr:street":"Lord Street",
    "iso:country":"GB",
    "sg:address":"44 Lord Street",
    "sg:city":"Redcar",
    "sg:classifiers":[
        {
            "category":"Manufacturing",
            "subcategory":"Petroleum Products",
            "type":"Manufacturing & Wholesale Goods"
        }
    ],
    "sg:phone":"+44 1642 473983",
    "sg:postcode":"TS10 3HL",
    "sg:province":"North Yorkshire",
    "sg:tags":[
        "double",
        "glazing"
    ],
    "wof:name":"Saltscar Windows",
    "wof:placetype":"venue"
},
  "geometry": {"coordinates":[-1.0640029907,54.6173019409],"type":"Point"}
}