{
  "type": "Feature",
  "properties": {
    "iso:country":"GB",
    "sg:address":"5 Clifford Street",
    "sg:city":"London",
    "sg:classifiers":[
        {
            "category":"Banks & Credit Unions",
            "subcategory":"Bank",
            "type":"Services"
        }
    ],
    "sg:phone":"+44 20 7439 7191",
    "sg:postcode":"W1S 2LG",
    "sg:province":"Greater London",
    "wof:name":"Campbell Lutyens & Co.  Ltd.",
    "wof:placetype":"venue"
},
  "geometry": {"coordinates":[-0.14162,51.511097],"type":"Point"}
}