{
  "type": "Feature",
  "properties": {
    "addr:full":"Nork House, 33 Nork Way Banstead Surrey SM7 1PB",
    "addr:housenumber":"33",
    "addr:postcode":"sm7 1pb",
    "addr:street":"Nork Way",
    "iso:country":"GB",
    "sg:address":"Nork House, 33 Nork Way",
    "sg:city":"Banstead",
    "sg:classifiers":[
        {
            "category":"Utilities",
            "subcategory":"Telephone",
            "type":"Services"
        },
        {
            "category":"Communications",
            "type":"Services"
        }
    ],
    "sg:phone":"+44 1737 850000",
    "sg:postcode":"SM7 1PB",
    "sg:province":"Surrey",
    "sg:tags":[
        "telecommunication",
        "network"
    ],
    "wof:name":"P R L Systems",
    "wof:placetype":"venue"
},
  "geometry": {"coordinates":[-0.2151470035,51.3273696899],"type":"Point"}
}