{
  "type": "Feature",
  "properties": {
    "addr:full":"109 Knoclaid Road Liverpool Merseyside L13 8DD",
    "addr:housenumber":"109",
    "addr:postcode":"l13 8dd",
    "addr:street":"Knoclaid Road",
    "iso:country":"GB",
    "sg:address":"109 Knoclaid Road",
    "sg:city":"Liverpool",
    "sg:classifiers":[
        {
            "category":"Personal",
            "subcategory":"Beauty Salon",
            "type":"Services"
        }
    ],
    "sg:phone":"+44 151 226 4747",
    "sg:postcode":"L13 8DD",
    "sg:province":"Merseyside",
    "sg:tags":[
        "unisex",
        "hairdresser"
    ],
    "wof:name":"Trimmings",
    "wof:placetype":"venue"
},
  "geometry": {"coordinates":[-2.934101,53.432003],"type":"Point"}
}