{
  "type": "Feature",
  "properties": {
    "iso:country":"GB",
    "sg:address":"426 Limpsfield Road",
    "sg:city":"Warlingham",
    "sg:classifiers":[
        {
            "category":"Professional",
            "subcategory":"Engineering",
            "type":"Services"
        },
        {
            "category":"Building & Trades",
            "subcategory":"Construction",
            "type":"Services"
        }
    ],
    "sg:phone":"+44 1883 622011",
    "sg:postcode":"CR6 9LA",
    "sg:province":"Kent",
    "sg:tags":[
        "ge",
        "engineer",
        "builder",
        "mechanical"
    ],
    "wof:name":"Freshacre Ltd.",
    "wof:placetype":"venue"
},
  "geometry": {"coordinates":[-0.0540769994,51.3091201782],"type":"Point"}
}