{
  "type": "Feature",
  "properties": {
    "addr:full":"44 High St Sheffield South Yorkshire S20 5AE",
    "addr:housenumber":"44",
    "addr:postcode":"s20 5ae",
    "addr:street":"High St",
    "iso:country":"GB",
    "sg:address":"44 High St",
    "sg:city":"Sheffield",
    "sg:classifiers":[
        {
            "category":"Fast Food",
            "type":"Food & Drink"
        }
    ],
    "sg:phone":"+44 114 248 4373",
    "sg:postcode":"S20 5AE",
    "sg:province":"South Yorkshire",
    "sg:tags":[
        "away",
        "take"
    ],
    "wof:name":"M Y'S A Loaf Of Bread",
    "wof:placetype":"venue"
},
  "geometry": {"coordinates":[-1.3623440266,53.3254241943],"type":"Point"}
}