{
  "type": "Feature",
  "properties": {
    "addr:full":"59 Testwood Road Windsor Berkshire SL4 5RL",
    "addr:housenumber":"59",
    "addr:postcode":"sl4 5rl",
    "addr:street":"Testwood Road",
    "iso:country":"GB",
    "sg:address":"59 Testwood Road",
    "sg:city":"Windsor",
    "sg:classifiers":[
        {
            "category":"Community Center",
            "subcategory":"Youth",
            "type":"Public Place"
        }
    ],
    "sg:phone":"+44 1753 856928",
    "sg:postcode":"SL4 5RL",
    "sg:province":"Berkshire",
    "sg:tags":[
        "organisation",
        "centre"
    ],
    "wof:name":"Arundel & Littlehampton Scout District 1ST Rusting",
    "wof:placetype":"venue"
},
  "geometry": {"coordinates":[-0.653084,51.481739],"type":"Point"}
}