{
  "type": "Feature",
  "properties": {
    "iso:country":"GB",
    "sg:address":"62 Pilot Road",
    "sg:city":"Hastings",
    "sg:classifiers":[
        {
            "category":"Home & Garden",
            "subcategory":"Carpets & Floor Coverings",
            "type":"Retail Goods"
        }
    ],
    "sg:phone":"+44 1424 429841",
    "sg:postcode":"TN34 2AN",
    "sg:province":"East Sussex",
    "sg:tags":[
        "carpets",
        "rug",
        "matting"
    ],
    "wof:name":"1ST Choice Floorings & Blinds",
    "wof:placetype":"venue"
},
  "geometry": {"coordinates":[0.593058,50.874889],"type":"Point"}
}