{
  "type": "Feature",
  "properties": {
    "addr:full":"17 Lansdowne Road Bridlington East Riding of Yorkshire YO15 2QU",
    "addr:housenumber":"17",
    "addr:postcode":"yo15 2qu",
    "addr:street":"Lansdowne Road",
    "iso:country":"GB",
    "sg:address":"17 Lansdowne Road",
    "sg:city":"Bridlington",
    "sg:classifiers":[
        {
            "category":"Professional",
            "subcategory":"Business Services",
            "type":"Services"
        },
        {
            "category":"Shopping",
            "subcategory":"Discount & Variety Stores",
            "type":"Retail Goods"
        }
    ],
    "sg:phone":"+44 1262 677231",
    "sg:postcode":"YO15 2QU",
    "sg:province":"East Riding of Yorkshire",
    "sg:tags":[
        "shop",
        "import",
        "model",
        "export",
        "agent"
    ],
    "wof:name":"Croppers Models",
    "wof:placetype":"venue"
},
  "geometry": {"coordinates":[-0.1884469986,54.0851173401],"type":"Point"}
}