{
  "type": "Feature",
  "properties": {
    "addr:full":"17 South View Littlehampton West Sussex BN16 1PX",
    "addr:housenumber":"17",
    "addr:postcode":"bn16 1px",
    "addr:street":"South View",
    "iso:country":"GB",
    "sg:address":"17 South View",
    "sg:city":"Littlehampton",
    "sg:classifiers":[
        {
            "category":"Utilities",
            "type":"Services"
        }
    ],
    "sg:phone":"+44 1903 773969",
    "sg:postcode":"BN16 1PX",
    "sg:province":"West Sussex",
    "sg:tags":[
        "internet"
    ],
    "wof:name":"Web Design",
    "wof:placetype":"venue"
},
  "geometry": {"coordinates":[-0.474212,50.807308],"type":"Point"}
}