{
  "type": "Feature",
  "properties": {
    "addr:full":"21 Station Road Longfield Kent DA3 7QD",
    "addr:housenumber":"21",
    "addr:postcode":"da3 7qd",
    "addr:street":"Station Road",
    "iso:country":"GB",
    "sg:address":"21 Station Road",
    "sg:city":"Longfield",
    "sg:classifiers":[
        {
            "category":"Food & Beverages",
            "subcategory":"Meat & Fish",
            "type":"Retail Goods"
        }
    ],
    "sg:phone":"+44 1474 702143",
    "sg:postcode":"DA3 7QD",
    "sg:province":"Kent",
    "sg:tags":[
        "butcher"
    ],
    "wof:name":"Longfield Village Butchers",
    "wof:placetype":"venue"
},
  "geometry": {"coordinates":[0.3004080057,51.3981704712],"type":"Point"}
}