{
  "type": "Feature",
  "properties": {
    "iso:country":"GB",
    "sg:address":"23-25 Church Street",
    "sg:city":"Chelmsford",
    "sg:classifiers":[
        {
            "category":"Fast Food",
            "type":"Food & Drink"
        },
        {
            "category":"Restaurant",
            "type":"Food & Drink"
        }
    ],
    "sg:phone":"+44 1245 478884",
    "sg:postcode":"CM2 7HX",
    "sg:province":"Essex",
    "sg:tags":[
        "away",
        "take",
        "italian"
    ],
    "wof:name":"Gerrardo's Italian Restaurant Wine Bar & Pizzaeri",
    "wof:placetype":"venue"
},
  "geometry": {"coordinates":[0.503394,51.714977],"type":"Point"}
}