{
  "type": "Feature",
  "properties": {
    "iso:country":"GB",
    "sg:address":"384a Katherine Street",
    "sg:city":"Ashton-under-lyne",
    "sg:classifiers":[
        {
            "category":"Food & Beverages",
            "subcategory":"Bakery",
            "type":"Retail Goods"
        },
        {
            "category":"Home & Garden",
            "subcategory":"Kitchen Supply",
            "type":"Retail Goods"
        }
    ],
    "sg:phone":"+44 161 330 6745",
    "sg:postcode":"OL7 0AL",
    "sg:province":"Greater Manchester",
    "sg:tags":[
        "confectioner",
        "baker",
        "confectionery"
    ],
    "wof:name":"Chapel Bakers",
    "wof:placetype":"venue"
},
  "geometry": {"coordinates":[-2.10795,53.485992],"type":"Point"}
}