{
  "type": "Feature",
  "properties": {
    "addr:full":"3 St Davids Street Neath Neath Port Talbot SA11 3AA",
    "addr:housenumber":"3",
    "addr:postcode":"sa11 3aa",
    "addr:street":"St Davids Street",
    "iso:country":"GB",
    "sg:address":"3 St Davids Street",
    "sg:city":"Neath",
    "sg:classifiers":[
        {
            "category":"Bars & Pubs",
            "type":"Food & Drink"
        }
    ],
    "sg:phone":"+44 1639 643927",
    "sg:postcode":"SA11 3AA",
    "sg:province":"Neath Port Talbot",
    "sg:tags":[
        "pubs",
        "house",
        "inn",
        "public",
        "activity"
    ],
    "wof:name":"Cross Keys Hotel",
    "wof:placetype":"venue"
},
  "geometry": {"coordinates":[-3.8021860123,51.6620178223],"type":"Point"}
}