{
  "type": "Feature",
  "properties": {
    "addr:full":"139-141 Windham Rd Bournemouth Dorset BH1 4RQ",
    "addr:housenumber":"139-141",
    "addr:postcode":"bh1 4rq",
    "addr:street":"Windham Rd",
    "iso:country":"GB",
    "sg:address":"139-141 Windham Rd",
    "sg:city":"Bournemouth",
    "sg:classifiers":[
        {
            "category":"Home & Garden",
            "subcategory":"Carpets & Floor Coverings",
            "type":"Retail Goods"
        }
    ],
    "sg:phone":"+44 1202 300700",
    "sg:postcode":"BH1 4RQ",
    "sg:province":"Dorset",
    "sg:tags":[
        "carpets",
        "rug",
        "matting"
    ],
    "wof:name":"Chapel Carpets",
    "wof:placetype":"venue"
},
  "geometry": {"coordinates":[-1.8505500555,50.7299461365],"type":"Point"}
}