{
  "type": "Feature",
  "properties": {
    "addr:full":"Ings Road Wakefield West Yorkshire WF2 9SD",
    "addr:postcode":"wf2 9sd",
    "addr:street":"Ings Road",
    "iso:country":"GB",
    "sg:address":"Ings Road",
    "sg:city":"Wakefield",
    "sg:classifiers":[
        {
            "category":"Home & Garden",
            "subcategory":"Home Furnishings",
            "type":"Retail Goods"
        }
    ],
    "sg:phone":"+44 1924 200747",
    "sg:postcode":"WF2 9SD",
    "sg:province":"West Yorkshire",
    "sg:tags":[
        "beds",
        "bedding",
        "blanket"
    ],
    "wof:name":"Bensons Bed Centres Ltd.",
    "wof:placetype":"venue"
},
  "geometry": {"coordinates":[-1.5074939728,53.6805839539],"type":"Point"}
}