{
  "type": "Feature",
  "properties": {
    "addr:full":"Ridley Road, Burnt Mill Industrial Estate Basildon Essex SS13 1EG",
    "addr:postcode":"ss13 1eg",
    "addr:street":"Ridley Road Burnt;Industrial Estate",
    "iso:country":"GB",
    "sg:address":"Ridley Road, Burnt Mill Industrial Estate",
    "sg:city":"Basildon",
    "sg:classifiers":[
        {
            "category":"Building & Trades",
            "subcategory":"Construction",
            "type":"Services"
        }
    ],
    "sg:phone":"+44 1268 724422",
    "sg:postcode":"SS13 1EG",
    "sg:province":"Essex",
    "sg:tags":[
        "fork",
        "lift",
        "truck"
    ],
    "wof:name":"Meadows Fork Lift Trucks",
    "wof:placetype":"venue"
},
  "geometry": {"coordinates":[0.5126649737,51.5855712891],"type":"Point"}
}