{
  "type": "Feature",
  "properties": {
    "iso:country":"GB",
    "sg:address":"2 Harlech Rise, Chilwell",
    "sg:city":"Nottingham",
    "sg:classifiers":[
        {
            "category":"Manufacturing",
            "subcategory":"Electronics",
            "type":"Manufacturing & Wholesale Goods"
        }
    ],
    "sg:phone":"+44 115 925 4066",
    "sg:postcode":"NG9 5PD",
    "sg:province":"Nottinghamshire",
    "sg:tags":[
        "control",
        "component",
        "-",
        "electronic"
    ],
    "wof:name":"Solo Audio Accessories Ltd.",
    "wof:placetype":"venue"
},
  "geometry": {"coordinates":[-1.244941,52.917175],"type":"Point"}
}