{
  "type": "Feature",
  "properties": {
    "addr:full":"10 Stanley Close Norwich Norfolk NR13 3RW",
    "addr:housenumber":"10",
    "addr:postcode":"nr13 3rw",
    "addr:street":"Stanley Close",
    "iso:country":"GB",
    "sg:address":"10 Stanley Close",
    "sg:city":"Norwich",
    "sg:classifiers":[
        {
            "category":"Building & Trades",
            "subcategory":"Electrical",
            "type":"Services"
        }
    ],
    "sg:postcode":"NR13 3RW",
    "sg:province":"Norfolk",
    "sg:tags":[
        "consultant",
        "lighting"
    ],
    "wof:name":"Cozens Electrical",
    "wof:placetype":"venue"
},
  "geometry": {"coordinates":[1.5097420216,52.5805892944],"type":"Point"}
}