{
  "type": "Feature",
  "properties": {
    "iso:country":"GB",
    "sg:address":"Bodmin St Garage, Bodmin Street",
    "sg:city":"Holsworthy",
    "sg:classifiers":[
        {
            "category":"Autos & Motor Vehicles",
            "subcategory":"Fuel & Gas Station",
            "type":"Retail Goods"
        }
    ],
    "sg:phone":"+44 1409 253382",
    "sg:postcode":"EX22 6BH",
    "sg:province":"Cornwall",
    "sg:tags":[
        "petrol",
        "filling"
    ],
    "wof:name":"West Devon & North Cornwall Farmers Ltd.",
    "wof:placetype":"venue"
},
  "geometry": {"coordinates":[-4.353759,50.80909],"type":"Point"}
}