{
  "type": "Feature",
  "properties": {
    "iso:country":"GB",
    "sg:address":"11 Halesowen Rd",
    "sg:city":"Halesowen",
    "sg:classifiers":[
        {
            "category":"Food & Beverages",
            "subcategory":"Liquor & Beverages",
            "type":"Retail Goods"
        }
    ],
    "sg:phone":"+44 121 422 2078",
    "sg:postcode":"B62 9AA",
    "sg:province":"West Midlands",
    "sg:tags":[
        "beer",
        "spirit",
        "wines"
    ],
    "wof:name":"B & G Liquor Store",
    "wof:placetype":"venue"
},
  "geometry": {"coordinates":[-2.026054,52.462227],"type":"Point"}
}