{
  "type": "Feature",
  "properties": {
    "addr:full":"26-27 Great Sutton St Clerkenwell Greater London EC1V 0DS",
    "addr:housenumber":"26-27",
    "addr:postcode":"ec1v 0ds",
    "addr:street":"Great Sutton St",
    "iso:country":"GB",
    "sg:address":"26-27 Great Sutton St",
    "sg:city":"Clerkenwell",
    "sg:classifiers":[
        {
            "category":"Professional",
            "subcategory":"Art Services",
            "type":"Services"
        }
    ],
    "sg:phone":"+44 20 7608 2437",
    "sg:postcode":"EC1V 0DS",
    "sg:province":"Greater London",
    "sg:tags":[
        "photographer"
    ],
    "wof:name":"David Stewart",
    "wof:placetype":"venue"
},
  "geometry": {"coordinates":[-0.10132,51.52301],"type":"Point"}
}