{
  "type": "Feature",
  "properties": {
    "addr:full":"Brooklands, Southover High Street Lewes East Sussex BN7 1HU",
    "addr:postcode":"bn7 1hu",
    "addr:street":"High Street",
    "iso:country":"GB",
    "sg:address":"Brooklands, Southover High Street",
    "sg:city":"Lewes",
    "sg:classifiers":[
        {
            "category":"Building & Trades",
            "subcategory":"Construction",
            "type":"Services"
        },
        {
            "category":"Retail",
            "subcategory":"Storage",
            "type":"Services"
        }
    ],
    "sg:phone":"+44 1273 473885",
    "sg:postcode":"BN7 1HU",
    "sg:province":"East Sussex",
    "sg:tags":[
        "builder",
        "household",
        "removal"
    ],
    "wof:name":"Arnolds of Lewes",
    "wof:placetype":"venue"
},
  "geometry": {"coordinates":[0.006885,50.869373],"type":"Point"}
}