{
  "type": "Feature",
  "properties": {
    "addr:full":"12 Holly Rd, Ashurst Southampton Hampshire SO40 7BA",
    "addr:housenumber":"12",
    "addr:postcode":"so40 7ba",
    "addr:street":"Holly Rd",
    "iso:country":"GB",
    "sg:address":"12 Holly Rd, Ashurst",
    "sg:city":"Southampton",
    "sg:classifiers":[
        {
            "category":"Social Services",
            "subcategory":"Job Training",
            "type":"Services"
        }
    ],
    "sg:phone":"+44 23 8029 3757",
    "sg:postcode":"SO40 7BA",
    "sg:province":"Hampshire",
    "sg:tags":[
        "translator",
        "interpreter"
    ],
    "wof:name":"Arabic Language Services",
    "wof:placetype":"venue"
},
  "geometry": {"coordinates":[-1.5216679573,50.8942947388],"type":"Point"}
}