{
  "type": "Feature",
  "properties": {
    "addr:full":"A2 Greenwood Court, Veasey Close, Attleborough Fields Industrial E Nuneaton Leicestershire CV11 6RT",
    "addr:housenumber":"a2",
    "addr:postcode":"cv11 6rt",
    "addr:street":"Greenwood Court Veasey Close;Fields Industrial E",
    "iso:country":"GB",
    "sg:address":"A2 Greenwood Court, Veasey Close, Attleborough Fields Industrial E",
    "sg:city":"Nuneaton",
    "sg:classifiers":[
        {
            "category":"Banks & Credit Unions",
            "subcategory":"Financial Services",
            "type":"Services"
        }
    ],
    "sg:phone":"+44 24 7634 0832",
    "sg:postcode":"CV11 6RT",
    "sg:province":"Leicestershire",
    "sg:tags":[
        "radiographic"
    ],
    "wof:name":"Midland X-Ray Services",
    "wof:placetype":"venue"
},
  "geometry": {"coordinates":[-1.4488500357,52.5158615112],"type":"Point"}
}