{
  "type": "Feature",
  "properties": {
    "addr:full":"19 Carterton Road, Hoylake Wirral Merseyside CH47 4FD",
    "addr:housenumber":"19",
    "addr:postcode":"ch47 4fd",
    "addr:street":"Carterton Road",
    "iso:country":"GB",
    "sg:address":"19 Carterton Road, Hoylake",
    "sg:city":"Wirral",
    "sg:classifiers":[
        {
            "category":"Manufacturing",
            "subcategory":"Rubber & Plastics",
            "type":"Manufacturing & Wholesale Goods"
        }
    ],
    "sg:phone":"+44 151 632 6539",
    "sg:postcode":"CH47 4FD",
    "sg:province":"Merseyside",
    "sg:tags":[
        "injection",
        "moulding"
    ],
    "wof:name":"Hoylake Plastics",
    "wof:placetype":"venue"
},
  "geometry": {"coordinates":[-3.172319,53.391281],"type":"Point"}
}