{
  "type": "Feature",
  "properties": {
    "iso:country":"GB",
    "sg:address":"22 Madeley Street, Tunstall",
    "sg:city":"Stoke-on-trent",
    "sg:classifiers":[
        {
            "category":"Retail",
            "subcategory":"Funeral Services",
            "type":"Services"
        }
    ],
    "sg:phone":"+44 1782 839657",
    "sg:postcode":"ST6 5AT",
    "sg:province":"Staffordshire",
    "wof:name":"John Johnson & Sons",
    "wof:placetype":"venue"
},
  "geometry": {"coordinates":[-2.211388,53.061703],"type":"Point"}
}