{
  "type": "Feature",
  "properties": {
    "iso:country":"GB",
    "sg:address":"18 West Street",
    "sg:city":"Rochford",
    "sg:classifiers":[
        {
            "category":"Home & Garden",
            "subcategory":"Hardware",
            "type":"Retail Goods"
        }
    ],
    "sg:phone":"+44 1702 545201",
    "sg:postcode":"SS4 1AJ",
    "sg:province":"Essex",
    "wof:name":"Homeplus 2",
    "wof:placetype":"venue"
},
  "geometry": {"coordinates":[0.706403,51.582367],"type":"Point"}
}