{
  "type": "Feature",
  "properties": {
    "addr:full":"2-4 Northgate Wakefield West Yorkshire WF1 1HD",
    "addr:housenumber":"2-4",
    "addr:postcode":"wf1 1hd",
    "addr:street":"Northgate",
    "iso:country":"GB",
    "sg:address":"2-4 Northgate",
    "sg:city":"Wakefield",
    "sg:classifiers":[
        {
            "category":"Banks & Credit Unions",
            "subcategory":"Bank",
            "type":"Services"
        }
    ],
    "sg:phone":"+44 1924 373169",
    "sg:postcode":"WF1 1HD",
    "sg:province":"West Yorkshire",
    "wof:name":"Lloyds T S B Group Plc",
    "wof:placetype":"venue"
},
  "geometry": {"coordinates":[-1.4981789589,53.6837043762],"type":"Point"}
}