{
  "type": "Feature",
  "properties": {
    "addr:full":"1 Orchard Close Bedford Bedfordshire MK41 9AU",
    "addr:housenumber":"1",
    "addr:postcode":"mk41 9au",
    "addr:street":"Orchard Close",
    "iso:country":"GB",
    "sg:address":"1 Orchard Close",
    "sg:city":"Bedford",
    "sg:classifiers":[
        {
            "category":"Professional",
            "subcategory":"Computer Services",
            "type":"Services"
        }
    ],
    "sg:phone":"+44 1234 273881",
    "sg:postcode":"MK41 9AU",
    "sg:province":"Bedfordshire",
    "sg:tags":[
        "system",
        "software"
    ],
    "wof:name":"Beacon Professional Services Ltd",
    "wof:placetype":"venue"
},
  "geometry": {"coordinates":[-0.4482519925,52.1515045166],"type":"Point"}
}