{
  "type": "Feature",
  "properties": {
    "iso:country":"GB",
    "sg:address":"83 Bath Street",
    "sg:city":"Market Harborough",
    "sg:classifiers":[
        {
            "category":"Shopping",
            "subcategory":"News",
            "type":"Retail Goods"
        }
    ],
    "sg:phone":"+44 1858 462873",
    "sg:postcode":"LE16 9EJ",
    "sg:province":"Leicestershire",
    "sg:tags":[
        "newsagent"
    ],
    "wof:name":"Montgomery News",
    "wof:placetype":"venue"
},
  "geometry": {"coordinates":[-0.9195079803,52.4709091187],"type":"Point"}
}