{
  "type": "Feature",
  "properties": {
    "addr:full":"Unit 5 Mill Lane, Off Weir Street Blackburn Lancashire BB2 2AN",
    "addr:housenumber":"unit 5",
    "addr:postcode":"bb2 2an",
    "addr:street":"Mill Lane Off Weir Street",
    "iso:country":"GB",
    "sg:address":"Unit 5 Mill Lane, Off Weir Street",
    "sg:city":"Blackburn",
    "sg:classifiers":[
        {
            "category":"Retail",
            "subcategory":"Auto Repair",
            "type":"Services"
        }
    ],
    "sg:postcode":"BB2 2AN",
    "sg:province":"Lancashire",
    "sg:tags":[
        "body",
        "car"
    ],
    "wof:name":"M Rusyn",
    "wof:placetype":"venue"
},
  "geometry": {"coordinates":[-2.4828178883,53.7460479736],"type":"Point"}
}