{
  "type": "Feature",
  "properties": {
    "addr:full":"51 Kensington Court London Greater London W8 5DB",
    "addr:housenumber":"51",
    "addr:postcode":"w8 5db",
    "addr:street":"Kensington Court",
    "iso:country":"GB",
    "sg:address":"51 Kensington Court",
    "sg:city":"London",
    "sg:classifiers":[
        {
            "category":"Travel",
            "subcategory":"Hotels & Motels",
            "type":"Entertainment"
        }
    ],
    "sg:phone":"+44 20 7937 2030",
    "sg:postcode":"W8 5DB",
    "sg:province":"Greater London",
    "wof:name":"51 Kensington Court Ltd",
    "wof:placetype":"venue"
},
  "geometry": {"coordinates":[-0.1885599941,51.5018310547],"type":"Point"}
}