{
  "type": "Feature",
  "properties": {
    "iso:country":"GB",
    "sg:address":"Unit 108 Bradley Fold Trad Est, Radcliffe Moor Road",
    "sg:city":"Bolton",
    "sg:classifiers":[
        {
            "category":"Health Services",
            "subcategory":"Dentist",
            "type":"Services"
        }
    ],
    "sg:phone":"+44 1204 383385",
    "sg:postcode":"BL2 6RT",
    "sg:province":"Lancashire",
    "sg:tags":[
        "technician",
        "dental"
    ],
    "wof:name":"M J Barlow Dental Laboratories",
    "wof:placetype":"venue"
},
  "geometry": {"coordinates":[-2.3668,53.573414],"type":"Point"}
}