{
  "type": "Feature",
  "properties": {
    "addr:full":"43 Poplars Road, Mardy Abergavenny Herefordshire NP7 6LJ",
    "addr:housenumber":"43",
    "addr:postcode":"np7 6lj",
    "addr:street":"Poplars Road",
    "iso:country":"GB",
    "sg:address":"43 Poplars Road, Mardy",
    "sg:city":"Abergavenny",
    "sg:classifiers":[
        {
            "category":"Real Estate",
            "subcategory":"Surveying",
            "type":"Services"
        }
    ],
    "sg:phone":"+44 1873 855741",
    "sg:postcode":"NP7 6LJ",
    "sg:province":"Herefordshire",
    "sg:tags":[
        "surveyor",
        "land"
    ],
    "wof:name":"Roger Channon Land Surveying",
    "wof:placetype":"venue"
},
  "geometry": {"coordinates":[-3.007845,51.83839],"type":"Point"}
}