{
  "type": "Feature",
  "properties": {
    "iso:country":"GB",
    "sg:address":"13 Newlands End",
    "sg:city":"Basildon",
    "sg:classifiers":[
        {
            "category":"Building & Trades",
            "subcategory":"Construction",
            "type":"Services"
        }
    ],
    "sg:postcode":"SS15 6DU",
    "sg:province":"Essex",
    "sg:tags":[
        "valve"
    ],
    "wof:name":"Essex Valve Services",
    "wof:placetype":"venue"
},
  "geometry": {"coordinates":[0.4197719991,51.5826797485],"type":"Point"}
}