{
  "type": "Feature",
  "properties": {
    "addr:full":"13 Crawford Gardens Horsham West Sussex RH13 5AZ",
    "addr:housenumber":"13",
    "addr:postcode":"rh13 5az",
    "addr:street":"Crawford Gardens",
    "iso:country":"GB",
    "sg:address":"13 Crawford Gardens",
    "sg:city":"Horsham",
    "sg:classifiers":[
        {
            "category":"Professional",
            "subcategory":"Lawyer & Legal Services",
            "type":"Services"
        }
    ],
    "sg:phone":"+44 1403 218899",
    "sg:postcode":"RH13 5AZ",
    "sg:province":"West Sussex",
    "wof:name":"Will Writers",
    "wof:placetype":"venue"
},
  "geometry": {"coordinates":[-0.312415,51.070835],"type":"Point"}
}