{
  "type": "Feature",
  "properties": {
    "addr:full":"Prestwick International Airport Prestwick South Ayrshire KA9 2RW",
    "addr:postcode":"ka9 2rw",
    "addr:street":"Prestwick",
    "iso:country":"GB",
    "sg:address":"Prestwick International Airport",
    "sg:city":"Prestwick",
    "sg:classifiers":[
        {
            "category":"Manufacturing",
            "subcategory":"Aerospace",
            "type":"Manufacturing & Wholesale Goods"
        }
    ],
    "sg:phone":"+44 1292 479888",
    "sg:postcode":"KA9 2RW",
    "sg:province":"South Ayrshire",
    "sg:tags":[
        "aircraft",
        "furnishing",
        "fitting"
    ],
    "wof:name":"Jetstream Aircraft Ltd.",
    "wof:placetype":"venue"
},
  "geometry": {"coordinates":[-4.6042342186,55.508769989],"type":"Point"}
}