{
  "type": "Feature",
  "properties": {
    "addr:full":"132 High Street Sidmouth Devon EX10 8EE",
    "addr:housenumber":"132",
    "addr:postcode":"ex10 8ee",
    "addr:street":"High Street",
    "iso:country":"GB",
    "sg:address":"132 High Street",
    "sg:city":"Sidmouth",
    "sg:classifiers":[
        {
            "category":"Government",
            "subcategory":"Post Office",
            "type":"Public Place"
        }
    ],
    "sg:phone":"+44 1395 513950",
    "sg:postcode":"EX10 8EE",
    "sg:province":"Devon",
    "wof:name":"Sidmouth Post Office",
    "wof:placetype":"venue"
},
  "geometry": {"coordinates":[-3.2382330894,50.6821861267],"type":"Point"}
}