{
  "type": "Feature",
  "properties": {
    "iso:country":"GB",
    "sg:address":"Watling St",
    "sg:city":"Cannock",
    "sg:classifiers":[
        {
            "category":"Building & Trades",
            "subcategory":"Construction",
            "type":"Services"
        }
    ],
    "sg:phone":"+44 1543 500062",
    "sg:postcode":"WS11 1TE",
    "sg:province":"Staffordshire",
    "sg:tags":[
        "excavation",
        "groundwork",
        "contractor"
    ],
    "wof:name":"Bridgetown Plant",
    "wof:placetype":"venue"
},
  "geometry": {"coordinates":[-2.0483620167,52.6794204712],"type":"Point"}
}