{
  "type": "Feature",
  "properties": {
    "iso:country":"GB",
    "sg:address":"The Green, Thorne",
    "sg:city":"Doncaster",
    "sg:classifiers":[
        {
            "category":"Bars & Pubs",
            "type":"Food & Drink"
        }
    ],
    "sg:phone":"+44 1405 812349",
    "sg:postcode":"DN8 5AT",
    "sg:province":"East Riding of Yorkshire",
    "sg:tags":[
        "pubs",
        "inn"
    ],
    "wof:name":"Whitbread Hotel Co. Ltd.",
    "wof:placetype":"venue"
},
  "geometry": {"coordinates":[-0.961637,53.611591],"type":"Point"}
}