{
  "type": "Feature",
  "properties": {
    "iso:country":"GB",
    "sg:address":"68 Worthing Road, Rustington",
    "sg:city":"Littlehampton",
    "sg:classifiers":[
        {
            "category":"Building & Trades",
            "subcategory":"Construction",
            "type":"Services"
        },
        {
            "category":"Manufacturing",
            "subcategory":"Paper Products",
            "type":"Manufacturing & Wholesale Goods"
        }
    ],
    "sg:phone":"+44 1903 770799",
    "sg:postcode":"BN16 3LL",
    "sg:province":"West Sussex",
    "sg:tags":[
        "cardboard",
        "decorator",
        "painter"
    ],
    "wof:name":"John Pickup",
    "wof:placetype":"venue"
},
  "geometry": {"coordinates":[-0.507713,50.817402],"type":"Point"}
}