{
  "type": "Feature",
  "properties": {
    "iso:country":"GB",
    "sg:address":"First Floor Flat 36 Dawes Road",
    "sg:city":"London",
    "sg:classifiers":[
        {
            "category":"Professional",
            "subcategory":"Management & Consulting",
            "type":"Services"
        }
    ],
    "sg:phone":"+44 7710 539947",
    "sg:postcode":"SW6 7EN",
    "sg:province":"Greater London",
    "sg:tags":[
        "consultant",
        "business"
    ],
    "wof:name":"Elixir Vitae Consultants Ltd",
    "wof:placetype":"venue"
},
  "geometry": {"coordinates":[-0.20089,51.480541],"type":"Point"}
}