{
  "type": "Feature",
  "properties": {
    "addr:full":"28 Downlands Road Purley Surrey CR8 4JE",
    "addr:housenumber":"28",
    "addr:postcode":"cr8 4je",
    "addr:street":"Downlands Road",
    "iso:country":"GB",
    "sg:address":"28 Downlands Road",
    "sg:city":"Purley",
    "sg:classifiers":[
        {
            "category":"Professional",
            "subcategory":"Art Services",
            "type":"Services"
        }
    ],
    "sg:phone":"+44 1268 571174",
    "sg:postcode":"CR8 4JE",
    "sg:province":"Surrey",
    "sg:tags":[
        "graphic",
        "designer"
    ],
    "wof:name":"Dijit Ltd.",
    "wof:placetype":"venue"
},
  "geometry": {"coordinates":[-0.1282510012,51.3298110962],"type":"Point"}
}