{
  "type": "Feature",
  "properties": {
    "addr:full":"Edward Street Car Park Leeds West Yorkshire LS14 5HG",
    "addr:postcode":"ls14 5hg",
    "addr:street":"Edward;West",
    "iso:country":"GB",
    "sg:address":"Edward Street Car Park",
    "sg:city":"Leeds",
    "sg:classifiers":[
        {
            "category":"Parking",
            "type":"Transportation"
        }
    ],
    "sg:phone":"+44 113 244 2989",
    "sg:postcode":"LS14 5HG",
    "sg:province":"West Yorkshire",
    "sg:tags":[
        "car",
        "park"
    ],
    "wof:name":"Scotsdale Properties",
    "wof:placetype":"venue"
},
  "geometry": {"coordinates":[-1.546587,53.794495],"type":"Point"}
}