{
  "type": "Feature",
  "properties": {
    "iso:country":"GB",
    "sg:address":"Queens Road, Ingrow",
    "sg:city":"Keighley",
    "sg:classifiers":[
        {
            "category":"Education",
            "subcategory":"School",
            "type":"Public Place"
        },
        {
            "category":"Government",
            "subcategory":"Office",
            "type":"Public Place"
        }
    ],
    "sg:phone":"+44 1535 605880",
    "sg:postcode":"BD21 1AR",
    "sg:province":"West Yorkshire",
    "sg:tags":[
        "local",
        "authority"
    ],
    "wof:name":"St Joseph's R C Primary School",
    "wof:placetype":"venue"
},
  "geometry": {"coordinates":[-1.9128639698,53.8591041565],"type":"Point"}
}