{
  "type": "Feature",
  "properties": {
    "addr:full":"Mudstone Lane Brixham Devon TQ5 9EJ",
    "addr:postcode":"tq5 9ej",
    "addr:street":"Mudstone Lane",
    "iso:country":"GB",
    "sg:address":"Mudstone Lane",
    "sg:city":"Brixham",
    "sg:classifiers":[
        {
            "category":"Travel",
            "subcategory":"Hotels & Motels",
            "type":"Entertainment"
        }
    ],
    "sg:phone":"+44 1803 856335",
    "sg:postcode":"TQ5 9EJ",
    "sg:province":"Devon",
    "wof:name":"Manor Parcs",
    "wof:placetype":"venue"
},
  "geometry": {"coordinates":[-3.5060589314,50.3900337219],"type":"Point"}
}