{
  "type": "Feature",
  "properties": {
    "addr:full":"6 Loose Road Maidstone Kent ME15 7TZ",
    "addr:housenumber":"6",
    "addr:postcode":"me15 7tz",
    "addr:street":"Loose Road",
    "iso:country":"GB",
    "sg:address":"6 Loose Road",
    "sg:city":"Maidstone",
    "sg:classifiers":[
        {
            "category":"Arts & Performance",
            "subcategory":"Art Gallery",
            "type":"Entertainment"
        }
    ],
    "sg:postcode":"ME15 7TZ",
    "sg:province":"Kent",
    "wof:name":"Amberfield Gallery",
    "wof:placetype":"venue"
},
  "geometry": {"coordinates":[0.527104,51.265808],"type":"Point"}
}