{
  "type": "Feature",
  "properties": {
    "addr:full":"69 Trent Valley Road Lichfield Staffordshire WS13 6EZ",
    "addr:housenumber":"69",
    "addr:postcode":"ws13 6ez",
    "addr:street":"Trent Valley Road",
    "iso:country":"GB",
    "sg:address":"69 Trent Valley Road",
    "sg:city":"Lichfield",
    "sg:classifiers":[
        {
            "category":"Professional",
            "subcategory":"Computer Services",
            "type":"Services"
        }
    ],
    "sg:phone":"+44 1543 256979",
    "sg:postcode":"WS13 6EZ",
    "sg:province":"Staffordshire",
    "sg:tags":[
        "system",
        "software"
    ],
    "wof:name":"Stuart James Systems Ltd.",
    "wof:placetype":"venue"
},
  "geometry": {"coordinates":[-1.8112020493,52.6860122681],"type":"Point"}
}