{
  "type": "Feature",
  "properties": {
    "addr:full":"118 Lanehouse Road, Thornaby Stockton-on-tees Durham TS17 8EA",
    "addr:housenumber":"118",
    "addr:postcode":"ts17 8ea",
    "addr:street":"Lanehouse Road",
    "iso:country":"GB",
    "sg:address":"118 Lanehouse Road, Thornaby",
    "sg:city":"Stockton-on-tees",
    "sg:classifiers":[
        {
            "category":"Food & Beverages",
            "subcategory":"Supermarket",
            "type":"Retail Goods"
        }
    ],
    "sg:phone":"+44 1642 678073",
    "sg:postcode":"TS17 8EA",
    "sg:province":"Durham",
    "wof:name":"Costcutter",
    "wof:placetype":"venue"
},
  "geometry": {"coordinates":[-1.295171,54.550854],"type":"Point"}
}