{
  "type": "Feature",
  "properties": {
    "addr:full":"Porthbean, Coverack Helston Cornwall TR12 6SF",
    "addr:postcode":"tr12 6sf",
    "iso:country":"GB",
    "sg:address":"Porthbean, Coverack",
    "sg:city":"Helston",
    "sg:classifiers":[
        {
            "category":"Farming",
            "subcategory":"Livestock Farm",
            "type":"Manufacturing & Wholesale Goods"
        }
    ],
    "sg:postcode":"TR12 6SF",
    "sg:province":"Cornwall",
    "sg:tags":[
        "others"
    ],
    "wof:name":"Messrs Coventry",
    "wof:placetype":"venue"
},
  "geometry": {"coordinates":[-5.095593,50.022789],"type":"Point"}
}