{
  "type": "Feature",
  "properties": {
    "iso:country":"GB",
    "sg:address":"18 Church Hill, Etwall",
    "sg:city":"Derby",
    "sg:classifiers":[
        {
            "category":"Shopping",
            "subcategory":"Clothing, Apparel, & Fashions",
            "type":"Retail Goods"
        }
    ],
    "sg:postcode":"DE65 6LT",
    "sg:province":"Derbyshire",
    "sg:tags":[
        "ladieswear"
    ],
    "wof:name":"Sweaty Sue's",
    "wof:placetype":"venue"
},
  "geometry": {"coordinates":[-1.6010010242,52.8853874207],"type":"Point"}
}