{
  "type": "Feature",
  "properties": {
    "addr:full":"Head Office, A C Court, High Street Thames Ditton Surrey KT7 0QA",
    "addr:postcode":"kt7 0qa",
    "addr:street":"High Street",
    "iso:country":"GB",
    "sg:address":"Head Office, A C Court, High Street",
    "sg:city":"Thames Ditton",
    "sg:classifiers":[
        {
            "category":"Social Services",
            "subcategory":"Adult Care",
            "type":"Services"
        }
    ],
    "sg:phone":"+44 1483 519641",
    "sg:postcode":"KT7 0QA",
    "sg:province":"Surrey",
    "sg:tags":[
        "day",
        "centre"
    ],
    "wof:name":"Thames Ditton Family Centre",
    "wof:placetype":"venue"
},
  "geometry": {"coordinates":[-0.3317170143,51.3924064636],"type":"Point"}
}