{
  "type": "Feature",
  "properties": {
    "iso:country":"GB",
    "sg:address":"Church Plain, Mattishall",
    "sg:city":"Dereham",
    "sg:classifiers":[
        {
            "category":"Food & Beverages",
            "subcategory":"Meat & Fish",
            "type":"Retail Goods"
        }
    ],
    "sg:phone":"+44 1362 850273",
    "sg:postcode":"NR20 3QF",
    "sg:province":"Norfolk",
    "sg:tags":[
        "butcher"
    ],
    "wof:name":"Hewitts Butchers",
    "wof:placetype":"venue"
},
  "geometry": {"coordinates":[1.035701,52.659676],"type":"Point"}
}