{
  "type": "Feature",
  "properties": {
    "addr:full":"Kingsmills Elgin Moray IV30 4BX",
    "addr:postcode":"iv30 4bx",
    "iso:country":"GB",
    "sg:address":"Kingsmills",
    "sg:city":"Elgin",
    "sg:classifiers":[
        {
            "category":"Food & Beverages",
            "subcategory":"Liquor & Beverages",
            "type":"Retail Goods"
        }
    ],
    "sg:phone":"+44 1343 542110",
    "sg:postcode":"IV30 4BX",
    "sg:province":"Moray",
    "sg:tags":[
        "drink",
        "soft"
    ],
    "wof:name":"Aberdeen Mineral Water Co. Ltd.",
    "wof:placetype":"venue"
},
  "geometry": {"coordinates":[-3.3012139797,57.6532669067],"type":"Point"}
}