{
  "type": "Feature",
  "properties": {
    "iso:country":"GB",
    "sg:address":"60 Grasmere Avenue, Tilehurst",
    "sg:city":"Reading",
    "sg:classifiers":[
        {
            "category":"Building & Trades",
            "subcategory":"Construction",
            "type":"Services"
        }
    ],
    "sg:phone":"+44 118 945 3469",
    "sg:postcode":"RG30 6XX",
    "sg:province":"Berkshire",
    "sg:tags":[
        "conversion",
        "loft"
    ],
    "wof:name":"The Loft Conversion Co.",
    "wof:placetype":"venue"
},
  "geometry": {"coordinates":[-1.026788,51.468887],"type":"Point"}
}