{
  "type": "Feature",
  "properties": {
    "addr:full":"6 School St, Astley Manchester Greater Manchester M29 7DL",
    "addr:housenumber":"6",
    "addr:postcode":"m29 7dl",
    "addr:street":"School St",
    "iso:country":"GB",
    "sg:address":"6 School St, Astley",
    "sg:city":"Manchester",
    "sg:classifiers":[
        {
            "category":"Retail",
            "subcategory":"Driving School",
            "type":"Services"
        }
    ],
    "sg:phone":"+44 1942 879424",
    "sg:postcode":"M29 7DL",
    "sg:province":"Greater Manchester",
    "wof:name":"H Barton",
    "wof:placetype":"venue"
},
  "geometry": {"coordinates":[-2.470607996,53.5052490234],"type":"Point"}
}