{
  "type": "Feature",
  "properties": {
    "addr:full":"St Georges Street Birmingham West Midlands B19 3QY",
    "addr:postcode":"b19 3qy",
    "addr:street":"St Georges Street",
    "iso:country":"GB",
    "sg:address":"St Georges Street",
    "sg:city":"Birmingham",
    "sg:classifiers":[
        {
            "category":"Education",
            "subcategory":"School",
            "type":"Public Place"
        },
        {
            "category":"Government",
            "subcategory":"Office",
            "type":"Public Place"
        }
    ],
    "sg:phone":"+44 121 359 3432",
    "sg:postcode":"B19 3QY",
    "sg:province":"West Midlands",
    "sg:tags":[
        "local",
        "authority"
    ],
    "wof:name":"St Georges C of E Junior & Infant School",
    "wof:placetype":"venue"
},
  "geometry": {"coordinates":[-1.9027129412,52.4897613525],"type":"Point"}
}