{
  "type": "Feature",
  "properties": {
    "addr:full":"6 Watson Avenue Market Harborough Leicestershire LE16 9NA",
    "addr:housenumber":"6",
    "addr:postcode":"le16 9na",
    "addr:street":"Watson Avenue",
    "iso:country":"GB",
    "sg:address":"6 Watson Avenue",
    "sg:city":"Market Harborough",
    "sg:classifiers":[
        {
            "category":"Professional",
            "subcategory":"Art Services",
            "type":"Services"
        },
        {
            "category":"Building & Trades",
            "subcategory":"Construction",
            "type":"Services"
        }
    ],
    "sg:phone":"+44 1858 463105",
    "sg:postcode":"LE16 9NA",
    "sg:province":"Leicestershire",
    "sg:tags":[
        "decorator",
        "painter"
    ],
    "wof:name":"R C Wells",
    "wof:placetype":"venue"
},
  "geometry": {"coordinates":[-0.93513,52.467094],"type":"Point"}
}