{
  "type": "Feature",
  "properties": {
    "iso:country":"GB",
    "sg:address":"2b Stuart Road, Windle",
    "sg:city":"St Helens",
    "sg:classifiers":[
        {
            "category":"Building & Trades",
            "subcategory":"Plumbing",
            "type":"Services"
        }
    ],
    "sg:postcode":"WA10 6HS",
    "sg:province":"Merseyside",
    "sg:tags":[
        "central",
        "heating"
    ],
    "wof:name":"P D Plumbing & Heating Services",
    "wof:placetype":"venue"
},
  "geometry": {"coordinates":[-2.7686419487,53.4661369324],"type":"Point"}
}