{
  "type": "Feature",
  "properties": {
    "addr:full":"35 Cheriton High St Folkestone Kent CT19 4EY",
    "addr:housenumber":"35",
    "addr:postcode":"ct19 4ey",
    "addr:street":"Cheriton High St",
    "iso:country":"GB",
    "sg:address":"35 Cheriton High St",
    "sg:city":"Folkestone",
    "sg:classifiers":[
        {
            "category":"Professional",
            "subcategory":"Business Services",
            "type":"Services"
        }
    ],
    "sg:phone":"+44 1303 271125",
    "sg:postcode":"CT19 4EY",
    "sg:province":"Kent",
    "sg:tags":[
        "bookmaker"
    ],
    "wof:name":"Alan Bown",
    "wof:placetype":"venue"
},
  "geometry": {"coordinates":[1.144597,51.087723],"type":"Point"}
}