{
  "type": "Feature",
  "properties": {
    "addr:full":"Seymour Gro Manchester Cheshire M16 0LH",
    "addr:postcode":"m16 0lh",
    "addr:street":"Gro",
    "iso:country":"GB",
    "sg:address":"Seymour Gro",
    "sg:city":"Manchester",
    "sg:classifiers":[
        {
            "category":"Shopping",
            "subcategory":"Florist",
            "type":"Retail Goods"
        }
    ],
    "sg:phone":"+44 161 848 0949",
    "sg:postcode":"M16 0LH",
    "sg:province":"Cheshire",
    "wof:name":"Joan Bannister",
    "wof:placetype":"venue"
},
  "geometry": {"coordinates":[-2.273349,53.452888],"type":"Point"}
}