{
  "type": "Feature",
  "properties": {
    "addr:full":"Warrior Club, Lambeth Rd Birmingham West Midlands B44 9NR",
    "addr:postcode":"b44 9nr",
    "addr:street":"Lambeth Rd",
    "iso:country":"GB",
    "sg:address":"Warrior Club, Lambeth Rd",
    "sg:city":"Birmingham",
    "sg:classifiers":[
        {
            "category":"Organizations",
            "subcategory":"Community Association",
            "type":"Services"
        },
        {
            "category":"Organizations",
            "subcategory":"Membership Organization",
            "type":"Services"
        }
    ],
    "sg:phone":"+44 121 360 1857",
    "sg:postcode":"B44 9NR",
    "sg:province":"West Midlands",
    "sg:tags":[
        "club",
        "social"
    ],
    "wof:name":"Royal British Legion The",
    "wof:placetype":"venue"
},
  "geometry": {"coordinates":[-1.893509984,52.5576095581],"type":"Point"}
}