{
  "type": "Feature",
  "properties": {
    "addr:full":"70 Jessie Street Glasgow Glasgow City G42 0PG",
    "addr:housenumber":"70",
    "addr:postcode":"g42 0pg",
    "addr:street":"Jessie Street",
    "iso:country":"GB",
    "sg:address":"70 Jessie Street",
    "sg:city":"Glasgow",
    "sg:classifiers":[
        {
            "category":"Professional",
            "subcategory":"Engineering",
            "type":"Services"
        },
        {
            "category":"Building & Trades",
            "subcategory":"Electrical",
            "type":"Services"
        }
    ],
    "sg:phone":"+44 141 422 1800",
    "sg:postcode":"G42 0PG",
    "sg:province":"Glasgow City",
    "sg:tags":[
        "engineer",
        "electrician",
        "contractor"
    ],
    "wof:name":"Wingate Electrical Plc",
    "wof:placetype":"venue"
},
  "geometry": {"coordinates":[-4.2417812347,55.8348731995],"type":"Point"}
}