{
  "type": "Feature",
  "properties": {
    "addr:full":"101 Queensbridge Road London Greater London E2 8PB",
    "addr:housenumber":"101",
    "addr:postcode":"e2 8pb",
    "addr:street":"Queensbridge Road",
    "iso:country":"GB",
    "sg:address":"101 Queensbridge Road",
    "sg:city":"London",
    "sg:classifiers":[
        {
            "category":"Bars & Pubs",
            "type":"Food & Drink"
        },
        {
            "category":"Community Center",
            "subcategory":"Social",
            "type":"Public Place"
        }
    ],
    "sg:phone":"+44 20 7739 7591",
    "sg:postcode":"E2 8PB",
    "sg:province":"Greater London",
    "sg:tags":[
        "pubs",
        "house",
        "inn",
        "activity"
    ],
    "wof:name":"Duke of Cambridge",
    "wof:placetype":"venue"
},
  "geometry": {"coordinates":[-0.070161,51.533947],"type":"Point"}
}