{
  "type": "Feature",
  "properties": {
    "addr:full":"119 Connaught Avenue Frinton-on-sea Essex CO13 9PS",
    "addr:housenumber":"119",
    "addr:postcode":"co13 9ps",
    "addr:street":"Connaught Avenue",
    "iso:country":"GB",
    "sg:address":"119 Connaught Avenue",
    "sg:city":"Frinton-on-sea",
    "sg:classifiers":[
        {
            "category":"Shopping",
            "subcategory":"Gifts & Souvenirs",
            "type":"Retail Goods"
        }
    ],
    "sg:phone":"+44 1255 674677",
    "sg:postcode":"CO13 9PS",
    "sg:province":"Essex",
    "sg:tags":[
        "shop"
    ],
    "wof:name":"Mayfair Cards & Gifts",
    "wof:placetype":"venue"
},
  "geometry": {"coordinates":[1.2448649406,51.833316803],"type":"Point"}
}