{
  "type": "Feature",
  "properties": {
    "iso:country":"GB",
    "sg:address":"9 Seton Place, Port Seton",
    "sg:city":"Prestonpans",
    "sg:classifiers":[
        {
            "category":"Personal",
            "subcategory":"Beauty Salon",
            "type":"Services"
        },
        {
            "category":"Personal",
            "subcategory":"Barber",
            "type":"Services"
        }
    ],
    "sg:phone":"+44 1875 813436",
    "sg:postcode":"EH32 0DT",
    "sg:province":"East Lothian",
    "sg:tags":[
        "unisex",
        "hairdresser"
    ],
    "wof:name":"Topps",
    "wof:placetype":"venue"
},
  "geometry": {"coordinates":[-2.952788,55.971874],"type":"Point"}
}