{
  "type": "Feature",
  "properties": {
    "iso:country":"GB",
    "sg:address":"Silveys Wharf",
    "sg:city":"Bridgwater",
    "sg:classifiers":[
        {
            "category":"Utilities",
            "subcategory":"Fuel Oil & Lpg",
            "type":"Services"
        }
    ],
    "sg:postcode":"TA6 4BJ",
    "sg:province":"Somerset",
    "sg:tags":[
        "distributor"
    ],
    "wof:name":"Western Fuel Ltd.",
    "wof:placetype":"venue"
},
  "geometry": {"coordinates":[-3.013824,51.127556],"type":"Point"}
}