{
  "type": "Feature",
  "properties": {
    "addr:full":"Unit 8, Harlaw Industrial Estate Inverurie Aberdeenshire AB51 4SG",
    "addr:housenumber":"unit 8;estate",
    "addr:postcode":"ab51 4sg",
    "addr:street":"Harlaw Industrial",
    "iso:country":"GB",
    "sg:address":"Unit 8, Harlaw Industrial Estate",
    "sg:city":"Inverurie",
    "sg:classifiers":[
        {
            "category":"Food & Beverages",
            "subcategory":"Groceries & Convenience Stores",
            "type":"Retail Goods"
        }
    ],
    "sg:phone":"+44 1467 625888",
    "sg:postcode":"AB51 4SG",
    "sg:province":"Aberdeenshire",
    "sg:tags":[
        "coffee"
    ],
    "wof:name":"Aramark Ltd.",
    "wof:placetype":"venue"
},
  "geometry": {"coordinates":[-2.3897941113,57.2911186218],"type":"Point"}
}