{
  "type": "Feature",
  "properties": {
    "addr:full":"320 Pershore Road Birmingham West Midlands B5 7QY",
    "addr:housenumber":"320",
    "addr:postcode":"b5 7qy",
    "addr:street":"Pershore Road",
    "iso:country":"GB",
    "sg:address":"320 Pershore Road",
    "sg:city":"Birmingham",
    "sg:classifiers":[
        {
            "category":"Health Services",
            "subcategory":"Dentist",
            "type":"Services"
        }
    ],
    "sg:postcode":"B5 7QY",
    "sg:province":"West Midlands",
    "wof:name":"Kassam & Parmar",
    "wof:placetype":"venue"
},
  "geometry": {"coordinates":[-1.9062999487,52.4559288025],"type":"Point"}
}