{
  "type": "Feature",
  "properties": {
    "addr:full":"Portview Road, Avonmouth Bristol City of Bristol BS11 9LD",
    "addr:postcode":"bs11 9ld",
    "addr:street":"Portview Road",
    "iso:country":"GB",
    "sg:address":"Portview Road, Avonmouth",
    "sg:city":"Bristol",
    "sg:classifiers":[
        {
            "category":"Retail",
            "subcategory":"Auto Repair",
            "type":"Services"
        }
    ],
    "sg:phone":"+44 117 982 1064",
    "sg:postcode":"BS11 9LD",
    "sg:province":"City of Bristol",
    "sg:tags":[
        "engine",
        "car",
        "specialist"
    ],
    "wof:name":"Price Bros Auto Engineering",
    "wof:placetype":"venue"
},
  "geometry": {"coordinates":[-2.694124,51.498917],"type":"Point"}
}