{
  "type": "Feature",
  "properties": {
    "addr:full":"83 Princes St Yeovil Somerset BA20 1EE",
    "addr:housenumber":"83",
    "addr:postcode":"ba20 1ee",
    "addr:street":"Princes St",
    "iso:country":"GB",
    "sg:address":"83 Princes St",
    "sg:city":"Yeovil",
    "sg:classifiers":[
        {
            "category":"Shopping",
            "subcategory":"Department Store",
            "type":"Retail Goods"
        },
        {
            "category":"Shopping",
            "subcategory":"Discount & Variety Stores",
            "type":"Retail Goods"
        }
    ],
    "sg:postcode":"BA20 1EE",
    "sg:province":"Somerset",
    "sg:tags":[
        "shop",
        "model"
    ],
    "wof:name":"Webb,R,",
    "wof:placetype":"venue"
},
  "geometry": {"coordinates":[-2.633697,50.942883],"type":"Point"}
}