{
  "type": "Feature",
  "properties": {
    "addr:full":"Nantgwylan, Rhydlewis Llandysul Carmarthenshire SA44 5QQ",
    "addr:postcode":"sa44 5qq",
    "iso:country":"GB",
    "sg:address":"Nantgwylan, Rhydlewis",
    "sg:city":"Llandysul",
    "sg:classifiers":[
        {
            "category":"Farming",
            "subcategory":"Livestock Farm",
            "type":"Manufacturing & Wholesale Goods"
        }
    ],
    "sg:postcode":"SA44 5QQ",
    "sg:province":"Carmarthenshire",
    "sg:tags":[
        "others"
    ],
    "wof:name":"A & E S Davies",
    "wof:placetype":"venue"
},
  "geometry": {"coordinates":[-4.414132,52.099144],"type":"Point"}
}