{
  "type": "Feature",
  "properties": {
    "iso:country":"GB",
    "sg:address":"12 Witton Wood Road",
    "sg:city":"Frinton-on-sea",
    "sg:classifiers":[
        {
            "category":"Building & Trades",
            "subcategory":"Construction",
            "type":"Services"
        }
    ],
    "sg:postcode":"CO13 9LB",
    "sg:province":"Essex",
    "sg:tags":[
        "joinery"
    ],
    "wof:name":"Martyn Howard (Frinton) Ltd.",
    "wof:placetype":"venue"
},
  "geometry": {"coordinates":[1.24194,51.837372],"type":"Point"}
}