{
  "type": "Feature",
  "properties": {
    "iso:country":"GB",
    "sg:address":"35 Broad Street, Parkgate",
    "sg:city":"Rotherham",
    "sg:classifiers":[
        {
            "category":"Shopping",
            "subcategory":"Books",
            "type":"Retail Goods"
        }
    ],
    "sg:postcode":"S62 6DX",
    "sg:province":"South Yorkshire",
    "sg:tags":[
        "second-hand"
    ],
    "wof:name":"B D Books",
    "wof:placetype":"venue"
},
  "geometry": {"coordinates":[-1.343718,53.452171],"type":"Point"}
}