{
  "type": "Feature",
  "properties": {
    "addr:full":"Greenway Rd Cardiff Caerphilly CF3 8QS",
    "addr:postcode":"cf3 8qs",
    "addr:street":"Greenway Rd",
    "iso:country":"GB",
    "sg:address":"Greenway Rd",
    "sg:city":"Cardiff",
    "sg:classifiers":[
        {
            "category":"Social Services",
            "type":"Services"
        }
    ],
    "sg:phone":"+44 29 2077 4600",
    "sg:postcode":"CF3 8QS",
    "sg:province":"Caerphilly",
    "wof:name":"Trowbridge Family Centre",
    "wof:placetype":"venue"
},
  "geometry": {"coordinates":[-3.1126689911,51.520198822],"type":"Point"}
}