{
  "type": "Feature",
  "properties": {
    "addr:full":"13 Balby Road Doncaster South Yorkshire DN4 0RA",
    "addr:housenumber":"13",
    "addr:postcode":"dn4 0ra",
    "addr:street":"Balby Road",
    "iso:country":"GB",
    "sg:address":"13 Balby Road",
    "sg:city":"Doncaster",
    "sg:classifiers":[
        {
            "category":"Professional",
            "subcategory":"Testing Lab",
            "type":"Services"
        },
        {
            "category":"Autos & Motor Vehicles",
            "subcategory":"Motorcycle Sales",
            "type":"Retail Goods"
        }
    ],
    "sg:phone":"+44 1302 323846",
    "sg:postcode":"DN4 0RA",
    "sg:province":"South Yorkshire",
    "sg:tags":[
        "scooter",
        "cycle",
        "mot"
    ],
    "wof:name":"Needham's Bike Centre",
    "wof:placetype":"venue"
},
  "geometry": {"coordinates":[-1.141624,53.512344],"type":"Point"}
}