{
  "type": "Feature",
  "properties": {
    "addr:full":"110 Whitehall Industrial Estate, Whitehall Road Leeds West Yorkshire LS12 5JB",
    "addr:housenumber":"110;estate",
    "addr:postcode":"ls12 5jb",
    "addr:street":"Whitehall Industrial;Whitehall Road",
    "iso:country":"GB",
    "sg:address":"110 Whitehall Industrial Estate, Whitehall Road",
    "sg:city":"Leeds",
    "sg:classifiers":[
        {
            "category":"Retail",
            "subcategory":"Car Wash",
            "type":"Services"
        },
        {
            "category":"Retail",
            "subcategory":"Auto Repair",
            "type":"Services"
        }
    ],
    "sg:phone":"+44 113 231 0711",
    "sg:postcode":"LS12 5JB",
    "sg:province":"West Yorkshire",
    "sg:tags":[
        "bodybuilder",
        "repairer",
        "sprayer"
    ],
    "wof:name":"Yorkshire Fleet Services Ltd",
    "wof:placetype":"venue"
},
  "geometry": {"coordinates":[-1.6125940084,53.7809562683],"type":"Point"}
}