{
  "type": "Feature",
  "properties": {
    "addr:full":"3 Sanigar Crt, Whittle Close Newark Nottinghamshire NG24 2BW",
    "addr:housenumber":"3",
    "addr:postcode":"ng24 2bw",
    "addr:street":"Sanigar Crt Whittle Close",
    "iso:country":"GB",
    "sg:address":"3 Sanigar Crt, Whittle Close",
    "sg:city":"Newark",
    "sg:classifiers":[
        {
            "category":"Professional",
            "subcategory":"Testing Lab",
            "type":"Services"
        }
    ],
    "sg:postcode":"NG24 2BW",
    "sg:province":"Nottinghamshire",
    "sg:tags":[
        "laboratory"
    ],
    "wof:name":"Diagenics",
    "wof:placetype":"venue"
},
  "geometry": {"coordinates":[-0.809347,53.073895],"type":"Point"}
}