{
  "type": "Feature",
  "properties": {
    "addr:full":"2 Holtlands Drive Derby Derbyshire DE24 0AR",
    "addr:housenumber":"2",
    "addr:postcode":"de24 0ar",
    "addr:street":"Holtlands Drive",
    "iso:country":"GB",
    "sg:address":"2 Holtlands Drive",
    "sg:city":"Derby",
    "sg:classifiers":[
        {
            "category":"Professional",
            "subcategory":"Engineering",
            "type":"Services"
        }
    ],
    "sg:phone":"+44 1332 572128",
    "sg:postcode":"DE24 0AR",
    "sg:province":"Derbyshire",
    "sg:tags":[
        "consultant",
        "structural"
    ],
    "wof:name":"Tringbeam Ltd.",
    "wof:placetype":"venue"
},
  "geometry": {"coordinates":[-1.4419469833,52.8899650574],"type":"Point"}
}