{
  "type": "Feature",
  "properties": {
    "addr:full":"13 Lavender Way Hitchin Bedfordshire SG5 2LU",
    "addr:housenumber":"13",
    "addr:postcode":"sg5 2lu",
    "addr:street":"Lavender Way",
    "iso:country":"GB",
    "sg:address":"13 Lavender Way",
    "sg:city":"Hitchin",
    "sg:classifiers":[
        {
            "category":"Professional",
            "subcategory":"Engineering",
            "type":"Services"
        }
    ],
    "sg:postcode":"SG5 2LU",
    "sg:province":"Bedfordshire",
    "sg:tags":[
        "contractor",
        "electrical",
        "engineer"
    ],
    "wof:name":"Greenway Electrical",
    "wof:placetype":"venue"
},
  "geometry": {"coordinates":[-0.2880379856,51.9513511658],"type":"Point"}
}