{
  "type": "Feature",
  "properties": {
    "addr:full":"79 Park La Hornchurch Essex RM11 1BH",
    "addr:housenumber":"79",
    "addr:postcode":"rm11 1bh",
    "addr:street":"Park La Hornchurch",
    "iso:country":"GB",
    "sg:address":"79 Park La",
    "sg:city":"Hornchurch",
    "sg:classifiers":[
        {
            "category":"Banks & Credit Unions",
            "subcategory":"Bank",
            "type":"Services"
        }
    ],
    "sg:phone":"+44 1708 732459",
    "sg:postcode":"RM11 1BH",
    "sg:province":"Essex",
    "sg:tags":[
        "concrete",
        "reinforcement"
    ],
    "wof:name":"V F J Ltd",
    "wof:placetype":"venue"
},
  "geometry": {"coordinates":[0.193332,51.569099],"type":"Point"}
}