{
  "type": "Feature",
  "properties": {
    "addr:full":"Moor End Farm, Moor End Wetherby West Yorkshire LS23 6ER",
    "addr:postcode":"ls23 6er",
    "addr:street":"Moor;Moor End",
    "iso:country":"GB",
    "sg:address":"Moor End Farm, Moor End",
    "sg:city":"Wetherby",
    "sg:classifiers":[
        {
            "category":"Banks & Credit Unions",
            "subcategory":"Financial Services",
            "type":"Services"
        }
    ],
    "sg:phone":"+44 1937 844160",
    "sg:postcode":"LS23 6ER",
    "sg:province":"West Yorkshire",
    "sg:tags":[
        "agent",
        "tied"
    ],
    "wof:name":"White Bros",
    "wof:placetype":"venue"
},
  "geometry": {"coordinates":[-1.37131,53.906147],"type":"Point"}
}