{
  "type": "Feature",
  "properties": {
    "iso:country":"GB",
    "sg:address":"80 John Street, Biddulph",
    "sg:city":"Stoke-on-trent",
    "sg:classifiers":[
        {
            "category":"Personal",
            "subcategory":"Beauty Salon",
            "type":"Services"
        }
    ],
    "sg:phone":"+44 1782 513253",
    "sg:postcode":"ST8 6AT",
    "sg:province":"Staffordshire",
    "sg:tags":[
        "lady",
        "hairdresser"
    ],
    "wof:name":"Margaret Pickin",
    "wof:placetype":"venue"
},
  "geometry": {"coordinates":[-2.175641,53.115311],"type":"Point"}
}