{
  "type": "Feature",
  "properties": {
    "addr:full":"Mere Fish Farm, Ivy Mead, Mere Warminster Somerset BA12 6EN",
    "addr:postcode":"ba12 6en",
    "addr:street":"Ivy Mead",
    "iso:country":"GB",
    "sg:address":"Mere Fish Farm, Ivy Mead, Mere",
    "sg:city":"Warminster",
    "sg:classifiers":[
        {
            "category":"Farming",
            "subcategory":"Fish & Marine Products",
            "type":"Manufacturing & Wholesale Goods"
        },
        {
            "category":"Farming",
            "subcategory":"Farm",
            "type":"Manufacturing & Wholesale Goods"
        }
    ],
    "sg:phone":"+44 1747 860461",
    "sg:postcode":"BA12 6EN",
    "sg:province":"Somerset",
    "sg:tags":[
        "hatchery"
    ],
    "wof:name":"Mere Fish Farm",
    "wof:placetype":"venue"
},
  "geometry": {"coordinates":[-2.270171,51.090511],"type":"Point"}
}