{
  "type": "Feature",
  "properties": {
    "addr:full":"16 Northfields, Lambourn Newbury Berkshire RG20 8DG",
    "addr:housenumber":"16;lambourn",
    "addr:postcode":"rg20 8dg",
    "addr:street":"Northfields",
    "iso:country":"GB",
    "sg:address":"16 Northfields, Lambourn",
    "sg:city":"Newbury",
    "sg:classifiers":[
        {
            "category":"Building & Trades",
            "subcategory":"Construction",
            "type":"Services"
        }
    ],
    "sg:postcode":"RG20 8DG",
    "sg:province":"Berkshire",
    "sg:tags":[
        "decorator",
        "painter"
    ],
    "wof:name":"Lambourn Decor",
    "wof:placetype":"venue"
},
  "geometry": {"coordinates":[-1.319179,51.482811],"type":"Point"}
}