{
  "type": "Feature",
  "properties": {
    "addr:full":"Glasgow Airport, Abbotsinch Paisley Renfrewshire PA3 2SW",
    "addr:postcode":"pa3 2sw",
    "iso:country":"GB",
    "sg:address":"Glasgow Airport, Abbotsinch",
    "sg:city":"Paisley",
    "sg:classifiers":[
        {
            "category":"Freight",
            "type":"Transportation"
        }
    ],
    "sg:phone":"+44 141 840 5599",
    "sg:postcode":"PA3 2SW",
    "sg:province":"Renfrewshire",
    "sg:tags":[
        "forwarders"
    ],
    "wof:name":"Walker Freight Services Ltd.",
    "wof:placetype":"venue"
},
  "geometry": {"coordinates":[-4.4334797859,55.8640785217],"type":"Point"}
}