{
  "type": "Feature",
  "properties": {
    "iso:country":"GB",
    "sg:address":"29 West Dyke Rd",
    "sg:city":"Redcar",
    "sg:classifiers":[
        {
            "category":"Shopping",
            "subcategory":"News",
            "type":"Retail Goods"
        }
    ],
    "sg:postcode":"TS10 3ED",
    "sg:province":"North Yorkshire",
    "sg:tags":[
        "newsagent"
    ],
    "wof:name":"Mann,Thomas & Patricia,",
    "wof:placetype":"venue"
},
  "geometry": {"coordinates":[-1.068104,54.616848],"type":"Point"}
}