{
  "type": "Feature",
  "properties": {
    "iso:country":"GB",
    "sg:address":"Cleggs Buildings, Chorley St",
    "sg:city":"Bolton",
    "sg:classifiers":[
        {
            "category":"Autos & Motor Vehicles",
            "subcategory":"Motorcycle Sales",
            "type":"Retail Goods"
        }
    ],
    "sg:phone":"+44 1204 396524",
    "sg:postcode":"BL1 4AL",
    "sg:province":"Lancashire",
    "sg:tags":[
        "component"
    ],
    "wof:name":"Full Throttle",
    "wof:placetype":"venue"
},
  "geometry": {"coordinates":[-2.438859,53.58147],"type":"Point"}
}