{
  "type": "Feature",
  "properties": {
    "iso:country":"GB",
    "sg:address":"Unit 6 Block 8, Moorfield Industrial Estate",
    "sg:city":"Kilmarnock",
    "sg:classifiers":[
        {
            "category":"Retail",
            "subcategory":"Auto Repair",
            "type":"Services"
        }
    ],
    "sg:postcode":"KA2 0BA",
    "sg:province":"East Ayrshire",
    "sg:tags":[
        "modification",
        "garage"
    ],
    "wof:name":"Recorded Fleet Maintenance (Kilmarnock) Ltd.",
    "wof:placetype":"venue"
},
  "geometry": {"coordinates":[-4.53538,55.599739],"type":"Point"}
}