{
  "type": "Feature",
  "properties": {
    "iso:country":"GB",
    "sg:address":"Unit 3 Fordview Estate, 65 New Road",
    "sg:city":"Rainham",
    "sg:classifiers":[
        {
            "category":"Professional",
            "subcategory":"Art Services",
            "type":"Services"
        }
    ],
    "sg:phone":"+44 1708 526262",
    "sg:postcode":"RM13 8ET",
    "sg:province":"Essex",
    "sg:tags":[
        "stone",
        "restoration",
        "cleaning"
    ],
    "wof:name":"The Anti-Graffiti Co. Ltd.",
    "wof:placetype":"venue"
},
  "geometry": {"coordinates":[0.190426,51.517914],"type":"Point"}
}