{
  "type": "Feature",
  "properties": {
    "addr:full":"42-43 Quarry Hill Road Tonbridge Kent TN9 2RS",
    "addr:housenumber":"42-43",
    "addr:postcode":"tn9 2rs",
    "addr:street":"Quarry Hill Road",
    "iso:country":"GB",
    "sg:address":"42-43 Quarry Hill Road",
    "sg:city":"Tonbridge",
    "sg:classifiers":[
        {
            "category":"Shopping",
            "type":"Retail Goods"
        }
    ],
    "sg:phone":"+44 1732 361659",
    "sg:postcode":"TN9 2RS",
    "sg:province":"Kent",
    "sg:tags":[
        "part",
        "accessory"
    ],
    "wof:name":"J & B Motor Spares & Accessories",
    "wof:placetype":"venue"
},
  "geometry": {"coordinates":[0.2687110007,51.1888008118],"type":"Point"}
}