{
  "type": "Feature",
  "properties": {
    "iso:country":"GB",
    "sg:address":"Nomansland, Widegates",
    "sg:city":"Looe",
    "sg:classifiers":[
        {
            "category":"Sports & Exercise",
            "subcategory":"Golf",
            "type":"Entertainment"
        }
    ],
    "sg:phone":"+44 1503 240239",
    "sg:postcode":"PL13 1PX",
    "sg:province":"Cornwall",
    "sg:tags":[
        "club",
        "course"
    ],
    "wof:name":"Looe Golf Club",
    "wof:placetype":"venue"
},
  "geometry": {"coordinates":[-4.455151,50.357052],"type":"Point"}
}