{
  "type": "Feature",
  "properties": {
    "addr:full":"Biencathra, Tan-y-buarth, Bethel Caernarfon Gwynedd LL55 1UP",
    "addr:postcode":"ll55 1up",
    "iso:country":"GB",
    "sg:address":"Biencathra, Tan-y-buarth, Bethel",
    "sg:city":"Caernarfon",
    "sg:classifiers":[
        {
            "category":"Manufacturing",
            "subcategory":"Building Materials",
            "type":"Manufacturing & Wholesale Goods"
        }
    ],
    "sg:phone":"+44 1248 670321",
    "sg:postcode":"LL55 1UP",
    "sg:province":"Gwynedd",
    "sg:tags":[
        "tile",
        "mnfrs"
    ],
    "wof:name":"G Biggs",
    "wof:placetype":"venue"
},
  "geometry": {"coordinates":[-4.2718091011,53.1425933838],"type":"Point"}
}