{
  "type": "Feature",
  "properties": {
    "iso:country":"GB",
    "sg:address":"48 Cow Wynd",
    "sg:city":"Falkirk",
    "sg:classifiers":[
        {
            "category":"Autos & Motor Vehicles",
            "subcategory":"Motorcycle Sales",
            "type":"Retail Goods"
        }
    ],
    "sg:phone":"+44 1324 630600",
    "sg:postcode":"FK1 1PU",
    "sg:province":"Falkirk",
    "sg:tags":[
        "chauffeur",
        "driven",
        "car"
    ],
    "wof:name":"Falkirk Chauffeur Drive",
    "wof:placetype":"venue"
},
  "geometry": {"coordinates":[-3.783406,55.997269],"type":"Point"}
}