{
  "type": "Feature",
  "properties": {
    "addr:full":"Craven Road, Broadheath Altrincham Cheshire WA14 5HJ",
    "addr:postcode":"wa14 5hj",
    "addr:street":"Craven Road",
    "iso:country":"GB",
    "sg:address":"Craven Road, Broadheath",
    "sg:city":"Altrincham",
    "sg:classifiers":[
        {
            "category":"Professional",
            "subcategory":"Engineering",
            "type":"Services"
        }
    ],
    "sg:phone":"+44 161 928 4145",
    "sg:postcode":"WA14 5HJ",
    "sg:province":"Cheshire",
    "sg:tags":[
        "engineer"
    ],
    "wof:name":"Countrywide Tool Distributors Ltd.",
    "wof:placetype":"venue"
},
  "geometry": {"coordinates":[-2.3525509834,53.400390625],"type":"Point"}
}