{
  "type": "Feature",
  "properties": {
    "addr:full":"60 John William Street Huddersfield West Yorkshire HD1 1ER",
    "addr:housenumber":"60",
    "addr:postcode":"hd1 1er",
    "addr:street":"John William Street",
    "iso:country":"GB",
    "sg:address":"60 John William Street",
    "sg:city":"Huddersfield",
    "sg:classifiers":[
        {
            "category":"Professional",
            "subcategory":"Computer Services",
            "type":"Services"
        }
    ],
    "sg:phone":"+44 1484 453690",
    "sg:postcode":"HD1 1ER",
    "sg:province":"West Yorkshire",
    "sg:tags":[
        "system",
        "software"
    ],
    "wof:name":"Computec Distribution Ltd.",
    "wof:placetype":"venue"
},
  "geometry": {"coordinates":[-1.782863,53.648514],"type":"Point"}
}