{
  "type": "Feature",
  "properties": {
    "addr:full":"Lachlan Cres Erskine Renfrewshire PA8 6HJ",
    "addr:postcode":"pa8 6hj",
    "addr:street":"Lachlan Cres Erskine",
    "iso:country":"GB",
    "sg:address":"Lachlan Cres",
    "sg:city":"Erskine",
    "sg:classifiers":[
        {
            "category":"Parking",
            "type":"Transportation"
        }
    ],
    "sg:phone":"+44 141 812 6161",
    "sg:postcode":"PA8 6HJ",
    "sg:province":"Renfrewshire",
    "sg:tags":[
        "car",
        "valet"
    ],
    "wof:name":"Professional Car Care Mobile Car Valeting",
    "wof:placetype":"venue"
},
  "geometry": {"coordinates":[-4.460749,55.904289],"type":"Point"}
}