{
  "type": "Feature",
  "properties": {
    "iso:country":"GB",
    "sg:address":"47 Penybanc Rd",
    "sg:city":"Ammanford",
    "sg:classifiers":[
        {
            "category":"Manufacturing",
            "subcategory":"Metals",
            "type":"Manufacturing & Wholesale Goods"
        }
    ],
    "sg:phone":"+44 1269 595262",
    "sg:postcode":"SA18 3DY",
    "sg:province":"Carmarthenshire",
    "sg:tags":[
        "steel",
        "fabricator",
        "erectors"
    ],
    "wof:name":"Rees Fabrications",
    "wof:placetype":"venue"
},
  "geometry": {"coordinates":[-3.993089,51.789421],"type":"Point"}
}