{
  "type": "Feature",
  "properties": {
    "iso:country":"GB",
    "sg:address":"26 Shelburne Way, Derry Hill",
    "sg:city":"Calne",
    "sg:classifiers":[
        {
            "category":"Communications",
            "type":"Services"
        }
    ],
    "sg:postcode":"SN11 9PA",
    "sg:province":"Wiltshire",
    "sg:tags":[
        "data",
        "network"
    ],
    "wof:name":"Maxim Data Systems Ltd",
    "wof:placetype":"venue"
},
  "geometry": {"coordinates":[-2.030784,51.456932],"type":"Point"}
}