{
  "type": "Feature",
  "properties": {
    "iso:country":"GB",
    "sg:address":"Unit3, Walkham Business Park, Burrington Way",
    "sg:city":"Plymouth",
    "sg:classifiers":[
        {
            "category":"Retail",
            "subcategory":"Auto Repair",
            "type":"Services"
        }
    ],
    "sg:phone":"+44 1752 793118",
    "sg:postcode":"PL5 3LS",
    "sg:province":"Devon",
    "sg:tags":[
        "modification",
        "garage",
        "related"
    ],
    "wof:name":"Burrington Way Garage",
    "wof:placetype":"venue"
},
  "geometry": {"coordinates":[-4.160094,50.403671],"type":"Point"}
}