{
  "type": "Feature",
  "properties": {
    "addr:full":"65 Commercial Street, Rothwell Leeds West Yorkshire LS26 0QD",
    "addr:housenumber":"65",
    "addr:postcode":"ls26 0qd",
    "addr:street":"Commercial Street",
    "iso:country":"GB",
    "sg:address":"65 Commercial Street, Rothwell",
    "sg:city":"Leeds",
    "sg:classifiers":[
        {
            "category":"Professional",
            "subcategory":"Lawyer & Legal Services",
            "type":"Services"
        }
    ],
    "sg:phone":"+44 113 282 4939",
    "sg:postcode":"LS26 0QD",
    "sg:province":"West Yorkshire",
    "sg:tags":[
        "solicitor"
    ],
    "wof:name":"Emsleys Solicitors",
    "wof:placetype":"venue"
},
  "geometry": {"coordinates":[-1.4786410332,53.7484893799],"type":"Point"}
}