{
  "type": "Feature",
  "properties": {
    "iso:country":"GB",
    "sg:address":"69 Havelock Road",
    "sg:city":"Luton",
    "sg:classifiers":[
        {
            "category":"Professional",
            "subcategory":"Engineering",
            "type":"Services"
        },
        {
            "category":"Building & Trades",
            "subcategory":"Electrical",
            "type":"Services"
        }
    ],
    "sg:phone":"+44 1582 731517",
    "sg:postcode":"LU2 7PW",
    "sg:province":"Bedfordshire",
    "sg:tags":[
        "engineer",
        "electrician",
        "contractor"
    ],
    "wof:name":"W Portsmouth & Co. Ltd.",
    "wof:placetype":"venue"
},
  "geometry": {"coordinates":[-0.413292,51.887421],"type":"Point"}
}