{
  "type": "Feature",
  "properties": {
    "iso:country":"GB",
    "sg:address":"9 Delancey Street",
    "sg:city":"London",
    "sg:classifiers":[
        {
            "category":"Travel",
            "subcategory":"Travel Agent",
            "type":"Entertainment"
        }
    ],
    "sg:postcode":"NW1 7NL",
    "sg:province":"Greater London",
    "wof:name":"Crowhurst Travel Ltd.",
    "wof:placetype":"venue"
},
  "geometry": {"coordinates":[-0.141917,51.536873],"type":"Point"}
}