{
  "type": "Feature",
  "properties": {
    "iso:country":"GB",
    "sg:address":"Selecta Ho, The Wharf",
    "sg:city":"Newark",
    "sg:classifiers":[
        {
            "category":"Wholesale",
            "subcategory":"Machinery & Supplies",
            "type":"Manufacturing & Wholesale Goods"
        }
    ],
    "sg:phone":"+44 1636 671721",
    "sg:postcode":"NG24 1EU",
    "sg:province":"Nottinghamshire",
    "sg:tags":[
        "pump"
    ],
    "wof:name":"Vincent H Dobson",
    "wof:placetype":"venue"
},
  "geometry": {"coordinates":[-0.809347,53.073895],"type":"Point"}
}