{
  "type": "Feature",
  "properties": {
    "iso:country":"GB",
    "sg:address":"3 Benbow Ct, Shenley Church End",
    "sg:city":"Milton Keynes",
    "sg:classifiers":[
        {
            "category":"Organizations",
            "subcategory":"Non-profit Organization",
            "type":"Services"
        }
    ],
    "sg:postcode":"MK5 6JG",
    "sg:province":"Buckinghamshire",
    "sg:tags":[
        "organisation",
        "voluntary",
        "charity"
    ],
    "wof:name":"National Energy Foundation",
    "wof:placetype":"venue"
},
  "geometry": {"coordinates":[-0.788981,52.026447],"type":"Point"}
}