{
  "type": "Feature",
  "properties": {
    "addr:full":"68 Farhalls Crescent Horsham West Sussex RH12 4BZ",
    "addr:housenumber":"68",
    "addr:postcode":"rh12 4bz",
    "addr:street":"Farhalls Crescent",
    "iso:country":"GB",
    "sg:address":"68 Farhalls Crescent",
    "sg:city":"Horsham",
    "sg:classifiers":[
        {
            "category":"Wholesale",
            "subcategory":"Office Equipment",
            "type":"Manufacturing & Wholesale Goods"
        }
    ],
    "sg:phone":"+44 1403 750668",
    "sg:postcode":"RH12 4BZ",
    "sg:province":"West Sussex",
    "sg:tags":[
        "partition",
        "cubicle"
    ],
    "wof:name":"S & H Interiors Ltd.",
    "wof:placetype":"venue"
},
  "geometry": {"coordinates":[-0.303143,51.080627],"type":"Point"}
}