{
  "type": "Feature",
  "properties": {
    "iso:country":"GB",
    "sg:address":"71-73 Goodramgate",
    "sg:city":"York",
    "sg:classifiers":[
        {
            "category":"Shopping",
            "subcategory":"Clothing, Apparel, & Fashions",
            "type":"Retail Goods"
        }
    ],
    "sg:phone":"+44 1904 641364",
    "sg:postcode":"YO1 7LS",
    "sg:province":"North Yorkshire",
    "sg:tags":[
        "shop"
    ],
    "wof:name":"Chritain Marcus",
    "wof:placetype":"venue"
},
  "geometry": {"coordinates":[-1.079799,53.960732],"type":"Point"}
}