{
  "type": "Feature",
  "properties": {
    "iso:country":"GB",
    "sg:address":"The Old Potteries, Sandwash Close",
    "sg:city":"St Helens",
    "sg:classifiers":[
        {
            "category":"Home & Garden",
            "subcategory":"Furniture",
            "type":"Retail Goods"
        }
    ],
    "sg:phone":"+44 1744 883976",
    "sg:postcode":"WA11 8LY",
    "sg:province":"Lancashire",
    "wof:name":"Sylvan Pine",
    "wof:placetype":"venue"
},
  "geometry": {"coordinates":[-2.7704,53.491699],"type":"Point"}
}