{
  "type": "Feature",
  "properties": {
    "iso:country":"GB",
    "sg:address":"135 Pump Lane, Rainham",
    "sg:city":"Gillingham",
    "sg:classifiers":[
        {
            "category":"Banks & Credit Unions",
            "subcategory":"Financial Services",
            "type":"Services"
        }
    ],
    "sg:postcode":"ME8 7AP",
    "sg:province":"Kent",
    "sg:tags":[
        "consultant"
    ],
    "wof:name":"Associates Investment Services Ltd",
    "wof:placetype":"venue"
},
  "geometry": {"coordinates":[0.5945490003,51.3724555969],"type":"Point"}
}