{
  "type": "Feature",
  "properties": {
    "iso:country":"GB",
    "sg:address":"74 Dalling Road",
    "sg:city":"London",
    "sg:classifiers":[
        {
            "category":"Insurance",
            "subcategory":"Insurance Agent",
            "type":"Services"
        }
    ],
    "sg:phone":"+44 870 787 0030",
    "sg:postcode":"W6 0JA",
    "sg:province":"Greater London",
    "wof:name":"The Basic Boat Liability Co. Ltd.",
    "wof:placetype":"venue"
},
  "geometry": {"coordinates":[-0.234365,51.494778],"type":"Point"}
}