{
  "type": "Feature",
  "properties": {
    "iso:country":"GB",
    "sg:address":"Tan House Lane, Burwell",
    "sg:city":"Cambridge",
    "sg:classifiers":[
        {
            "category":"Arena",
            "subcategory":"Sports Club",
            "type":"Entertainment"
        }
    ],
    "sg:phone":"+44 1638 743461",
    "sg:postcode":"CB5 0AR",
    "sg:province":"Cambridgeshire",
    "wof:name":"Burwell Cricket Club",
    "wof:placetype":"venue"
},
  "geometry": {"coordinates":[0.327026993,52.2683296204],"type":"Point"}
}