{
  "type": "Feature",
  "properties": {
    "addr:full":"27 Northgate End Bishops Stortford Essex CM23 2ET",
    "addr:housenumber":"27",
    "addr:postcode":"cm23 2et",
    "addr:street":"Northgate End",
    "iso:country":"GB",
    "sg:address":"27 Northgate End",
    "sg:city":"Bishops Stortford",
    "sg:classifiers":[
        {
            "category":"Professional",
            "subcategory":"Business Services",
            "type":"Services"
        }
    ],
    "sg:phone":"+44 1279 467140",
    "sg:postcode":"CM23 2ET",
    "sg:province":"Essex",
    "sg:tags":[
        "import",
        "export",
        "agent"
    ],
    "wof:name":"Team Worldwide Logistics Ltd.",
    "wof:placetype":"venue"
},
  "geometry": {"coordinates":[0.158521,51.874493],"type":"Point"}
}