{
  "type": "Feature",
  "properties": {
    "addr:full":"16a Bank Street Ashford Kent TN23 1BX",
    "addr:housenumber":"16a",
    "addr:postcode":"tn23 1bx",
    "addr:street":"Bank Street",
    "iso:country":"GB",
    "sg:address":"16a Bank Street",
    "sg:city":"Ashford",
    "sg:classifiers":[
        {
            "category":"Personal",
            "subcategory":"Beauty Salon",
            "type":"Services"
        },
        {
            "category":"Personal",
            "subcategory":"Barber",
            "type":"Services"
        }
    ],
    "sg:phone":"+44 1233 622104",
    "sg:postcode":"TN23 1BX",
    "sg:province":"Kent",
    "sg:tags":[
        "unisex",
        "hairdresser"
    ],
    "wof:name":"Waves Of Ashford",
    "wof:placetype":"venue"
},
  "geometry": {"coordinates":[0.870713,51.148273],"type":"Point"}
}