{
  "type": "Feature",
  "properties": {
    "addr:full":"1648 Great Cambridge Road Enfield Greater London EN1 4SZ",
    "addr:housenumber":"1648",
    "addr:postcode":"en1 4sz",
    "addr:street":"Great Cambridge Road",
    "iso:country":"GB",
    "sg:address":"1648 Great Cambridge Road",
    "sg:city":"Enfield",
    "sg:classifiers":[
        {
            "category":"Professional",
            "subcategory":"Computer Services",
            "type":"Services"
        }
    ],
    "sg:phone":"+44 1992 717592",
    "sg:postcode":"EN1 4SZ",
    "sg:province":"Greater London",
    "sg:tags":[
        "development",
        "system",
        "software"
    ],
    "wof:name":"ATU COMPUTERS LTD.",
    "wof:placetype":"venue"
},
  "geometry": {"coordinates":[-0.051601,51.677021],"type":"Point"}
}