{
  "type": "Feature",
  "properties": {
    "addr:full":"56 Clifton Avenue Wirral Cheshire CH62 9EQ",
    "addr:housenumber":"56",
    "addr:postcode":"ch62 9eq",
    "addr:street":"Clifton Avenue",
    "iso:country":"GB",
    "sg:address":"56 Clifton Avenue",
    "sg:city":"Wirral",
    "sg:classifiers":[
        {
            "category":"Shopping",
            "subcategory":"Pets & Pet Supplies",
            "type":"Retail Goods"
        }
    ],
    "sg:postcode":"CH62 9EQ",
    "sg:province":"Cheshire",
    "wof:name":"Anne King",
    "wof:placetype":"venue"
},
  "geometry": {"coordinates":[-2.973099,53.306705],"type":"Point"}
}