{
  "type": "Feature",
  "properties": {
    "addr:full":"New Clubhouse, Delahay Meadow, Stourport Road Bromyard Herefordshire HR7 4SR",
    "addr:postcode":"hr7 4sr",
    "addr:street":"Stourport Road",
    "iso:country":"GB",
    "sg:address":"New Clubhouse, Delahay Meadow, Stourport Road",
    "sg:city":"Bromyard",
    "sg:classifiers":[
        {
            "category":"Arena",
            "subcategory":"Sports Club",
            "type":"Entertainment"
        }
    ],
    "sg:phone":"+44 1885 483974",
    "sg:postcode":"HR7 4SR",
    "sg:province":"Herefordshire",
    "wof:name":"Bromyard Town Football Club",
    "wof:placetype":"venue"
},
  "geometry": {"coordinates":[-2.5103991032,52.1890983582],"type":"Point"}
}