{
  "type": "Feature",
  "properties": {
    "addr:full":"93 Unthank Road Norwich Norfolk NR2 2PE",
    "addr:housenumber":"93",
    "addr:postcode":"nr2 2pe",
    "addr:street":"Unthank Road Norwich Norfolk",
    "iso:country":"GB",
    "sg:address":"93 Unthank Road",
    "sg:city":"Norwich",
    "sg:classifiers":[
        {
            "category":"Professional",
            "subcategory":"Accounting & Tax Preparation",
            "type":"Services"
        }
    ],
    "sg:phone":"+44 1603 617009",
    "sg:postcode":"NR2 2PE",
    "sg:province":"Norfolk",
    "sg:tags":[
        "accountant"
    ],
    "wof:name":"The Financial Advise Centre",
    "wof:placetype":"venue"
},
  "geometry": {"coordinates":[1.277938,52.625023],"type":"Point"}
}