{
  "type": "Feature",
  "properties": {
    "addr:full":"110 Tower Street, Brunswick Business Park Liverpool Merseyside L3 4BJ",
    "addr:housenumber":"110",
    "addr:postcode":"l3 4bj",
    "addr:street":"Tower Street;Business Park",
    "iso:country":"GB",
    "sg:address":"110 Tower Street, Brunswick Business Park",
    "sg:city":"Liverpool",
    "sg:classifiers":[
        {
            "category":"Professional",
            "subcategory":"Accounting & Tax Preparation",
            "type":"Services"
        }
    ],
    "sg:phone":"+44 151 709 2225",
    "sg:postcode":"L3 4BJ",
    "sg:province":"Merseyside",
    "sg:tags":[
        "accountant"
    ],
    "wof:name":"Ziko Associates",
    "wof:placetype":"venue"
},
  "geometry": {"coordinates":[-2.9787170887,53.3841743469],"type":"Point"}
}