{
  "type": "Feature",
  "properties": {
    "addr:full":"2 Darwin Court, Gloucester Avenue London Greater London NW1 7BG",
    "addr:housenumber":"2",
    "addr:postcode":"nw1 7bg",
    "addr:street":"Darwin Court Gloucester Avenue",
    "iso:country":"GB",
    "sg:address":"2 Darwin Court, Gloucester Avenue",
    "sg:city":"London",
    "sg:classifiers":[
        {
            "category":"Professional",
            "subcategory":"Management & Consulting",
            "type":"Services"
        }
    ],
    "sg:phone":"+44 20 7587 3737",
    "sg:postcode":"NW1 7BG",
    "sg:province":"Greater London",
    "sg:tags":[
        "conservation"
    ],
    "wof:name":"Trading Alliance International Ltd.",
    "wof:placetype":"venue"
},
  "geometry": {"coordinates":[-0.148556,51.537888],"type":"Point"}
}