{
  "type": "Feature",
  "properties": {
    "addr:full":"39a Hylton St Birmingham West Midlands B18 6HJ",
    "addr:housenumber":"39a",
    "addr:postcode":"b18 6hj",
    "addr:street":"Hylton St",
    "iso:country":"GB",
    "sg:address":"39a Hylton St",
    "sg:city":"Birmingham",
    "sg:classifiers":[
        {
            "category":"Manufacturing",
            "subcategory":"Metals",
            "type":"Manufacturing & Wholesale Goods"
        }
    ],
    "sg:postcode":"B18 6HJ",
    "sg:province":"West Midlands",
    "sg:tags":[
        "heat",
        "-",
        "treatment"
    ],
    "wof:name":"Twigg,A A,",
    "wof:placetype":"venue"
},
  "geometry": {"coordinates":[-1.9126780033,52.4910354614],"type":"Point"}
}