{
  "type": "Feature",
  "properties": {
    "addr:full":"375 Kennington Lane London Greater London SE11 5QY",
    "addr:housenumber":"375",
    "addr:postcode":"se11 5qy",
    "addr:street":"Kennington Lane",
    "iso:country":"GB",
    "sg:address":"375 Kennington Lane",
    "sg:city":"London",
    "sg:classifiers":[
        {
            "category":"Professional",
            "subcategory":"Lawyer & Legal Services",
            "type":"Services"
        }
    ],
    "sg:phone":"+44 20 7787 6777",
    "sg:postcode":"SE11 5QY",
    "sg:province":"Greater London",
    "sg:tags":[
        "solicitor"
    ],
    "wof:name":"Belmont Hodgson",
    "wof:placetype":"venue"
},
  "geometry": {"coordinates":[-0.11898,51.486328],"type":"Point"}
}