{
  "type": "Feature",
  "properties": {
    "addr:full":"36 Charles Street Manchester Greater Manchester M1 7DB",
    "addr:housenumber":"36",
    "addr:postcode":"m1 7db",
    "addr:street":"Charles Street",
    "iso:country":"GB",
    "sg:address":"36 Charles Street",
    "sg:city":"Manchester",
    "sg:classifiers":[
        {
            "category":"Bars & Pubs",
            "type":"Food & Drink"
        }
    ],
    "sg:phone":"+44 161 273 6932",
    "sg:postcode":"M1 7DB",
    "sg:province":"Greater Manchester",
    "sg:tags":[
        "pubs",
        "inn"
    ],
    "wof:name":"Lass O'Gowrie Brewhouse",
    "wof:placetype":"venue"
},
  "geometry": {"coordinates":[-2.238318,53.473934],"type":"Point"}
}