{
  "type": "Feature",
  "properties": {
    "iso:country":"GB",
    "sg:address":"70 St Mary St",
    "sg:city":"Southampton",
    "sg:classifiers":[
        {
            "category":"Manufacturing",
            "subcategory":"Signs",
            "type":"Manufacturing & Wholesale Goods"
        }
    ],
    "sg:phone":"+44 23 8033 7077",
    "sg:postcode":"SO14 1NW",
    "sg:province":"Hampshire",
    "sg:tags":[
        "nameplate"
    ],
    "wof:name":"Frontier Signs & Canopies",
    "wof:placetype":"venue"
},
  "geometry": {"coordinates":[-1.3967269659,50.9057502747],"type":"Point"}
}