{
  "type": "Feature",
  "properties": {
    "iso:country":"GB",
    "sg:address":"37 Bedford Road",
    "sg:city":"Bedford",
    "sg:classifiers":[
        {
            "category":"Shopping",
            "subcategory":"Department Store",
            "type":"Retail Goods"
        }
    ],
    "sg:phone":"+44 1234 838240",
    "sg:postcode":"MK44 3PP",
    "sg:province":"Bedfordshire",
    "wof:name":"Willington Post Office Stores",
    "wof:placetype":"venue"
},
  "geometry": {"coordinates":[-0.3549270034,52.1565055847],"type":"Point"}
}