{
  "type": "Feature",
  "properties": {
    "addr:full":"18-19 Gaolgate Street Stafford Staffordshire ST16 2BJ",
    "addr:housenumber":"18-19",
    "addr:postcode":"st16 2bj",
    "addr:street":"Gaolgate Street",
    "iso:country":"GB",
    "sg:address":"18-19 Gaolgate Street",
    "sg:city":"Stafford",
    "sg:classifiers":[
        {
            "category":"Shopping",
            "subcategory":"Department Store",
            "type":"Retail Goods"
        }
    ],
    "sg:phone":"+44 1785 252583",
    "sg:postcode":"ST16 2BJ",
    "sg:province":"Staffordshire",
    "wof:name":"Woolworths",
    "wof:placetype":"venue"
},
  "geometry": {"coordinates":[-2.1185948849,52.8085975647],"type":"Point"}
}