{
  "type": "Feature",
  "properties": {
    "addr:full":"Dennis Sneezum Court, Trafalgar Road Downham Market Cambridgeshire PE38 9RL",
    "addr:postcode":"pe38 9rl",
    "addr:street":"Trafalgar Road",
    "iso:country":"GB",
    "sg:address":"Dennis Sneezum Court, Trafalgar Road",
    "sg:city":"Downham Market",
    "sg:classifiers":[
        {
            "category":"Health Services",
            "subcategory":"Nursing And Care Facility",
            "type":"Services"
        }
    ],
    "sg:postcode":"PE38 9RL",
    "sg:province":"Cambridgeshire",
    "sg:tags":[
        "home"
    ],
    "wof:name":"Housing 21",
    "wof:placetype":"venue"
},
  "geometry": {"coordinates":[0.3733560145,52.6008110046],"type":"Point"}
}