{
  "type": "Feature",
  "properties": {
    "addr:full":"16a Sampson Street Liversedge West Yorkshire WF15 6JP",
    "addr:housenumber":"16a",
    "addr:postcode":"wf15 6jp",
    "addr:street":"Sampson Street",
    "iso:country":"GB",
    "sg:address":"16a Sampson Street",
    "sg:city":"Liversedge",
    "sg:classifiers":[
        {
            "category":"Retail",
            "subcategory":"Auto Repair",
            "type":"Services"
        }
    ],
    "sg:phone":"+44 1924 407268",
    "sg:postcode":"WF15 6JP",
    "sg:province":"West Yorkshire",
    "sg:tags":[
        "modification",
        "garage",
        "related"
    ],
    "wof:name":"S J L Motors",
    "wof:placetype":"venue"
},
  "geometry": {"coordinates":[-1.6898909807,53.7097663879],"type":"Point"}
}