{
  "type": "Feature",
  "properties": {
    "addr:full":"93 Coombe Hill Cres Thame Buckinghamshire OX9 2EQ",
    "addr:housenumber":"93",
    "addr:postcode":"ox9 2eq",
    "addr:street":"Coombe Hill Cres",
    "iso:country":"GB",
    "sg:address":"93 Coombe Hill Cres",
    "sg:city":"Thame",
    "sg:classifiers":[
        {
            "category":"Education",
            "subcategory":"School",
            "type":"Public Place"
        }
    ],
    "sg:phone":"+44 1844 213707",
    "sg:postcode":"OX9 2EQ",
    "sg:province":"Buckinghamshire",
    "sg:tags":[
        "private",
        "tuition"
    ],
    "wof:name":"J H Tutorials",
    "wof:placetype":"venue"
},
  "geometry": {"coordinates":[-0.985144,51.743061],"type":"Point"}
}