{
  "type": "Feature",
  "properties": {
    "addr:full":"16 Breakspears Road London Greater London SE4 1UW",
    "addr:housenumber":"16",
    "addr:postcode":"se4 1uw",
    "addr:street":"Breakspears Road",
    "iso:country":"GB",
    "sg:address":"16 Breakspears Road",
    "sg:city":"London",
    "sg:classifiers":[
        {
            "category":"Retail",
            "subcategory":"Auto Repair",
            "type":"Services"
        }
    ],
    "sg:phone":"+44 20 8694 1435",
    "sg:postcode":"SE4 1UW",
    "sg:province":"Greater London",
    "sg:tags":[
        "modification",
        "garage"
    ],
    "wof:name":"Renospeed",
    "wof:placetype":"venue"
},
  "geometry": {"coordinates":[-0.0277699996,51.4676055908],"type":"Point"}
}