{
  "type": "Feature",
  "properties": {
    "iso:country":"GB",
    "sg:address":"123 Muswell Hill Bdwy",
    "sg:city":"London",
    "sg:classifiers":[
        {
            "category":"Home & Garden",
            "subcategory":"Kitchen Supply",
            "type":"Retail Goods"
        }
    ],
    "sg:phone":"+44 20 8444 5236",
    "sg:postcode":"N10 3RS",
    "sg:province":"Greater London",
    "sg:tags":[
        "ware"
    ],
    "wof:name":"Diverse Artefacts",
    "wof:placetype":"venue"
},
  "geometry": {"coordinates":[-0.138989,51.590019],"type":"Point"}
}