{
  "type": "Feature",
  "properties": {
    "addr:full":"Forgue School Huntly Aberdeenshire AB54 6DQ",
    "addr:postcode":"ab54 6dq",
    "addr:street":"Huntly",
    "iso:country":"GB",
    "sg:address":"Forgue School",
    "sg:city":"Huntly",
    "sg:classifiers":[
        {
            "category":"Government",
            "subcategory":"Office",
            "type":"Public Place"
        }
    ],
    "sg:phone":"+44 1466 730232",
    "sg:postcode":"AB54 6DQ",
    "sg:province":"Aberdeenshire",
    "sg:tags":[
        "local"
    ],
    "wof:name":"Aberdeenshire Council",
    "wof:placetype":"venue"
},
  "geometry": {"coordinates":[-2.651031,57.493866],"type":"Point"}
}