{
  "type": "Feature",
  "properties": {
    "iso:country":"GB",
    "sg:address":"10 Throgmorton Av",
    "sg:city":"Moorgate",
    "sg:classifiers":[
        {
            "category":"Communications",
            "subcategory":"Newspaper",
            "type":"Services"
        }
    ],
    "sg:phone":"+44 20 7628 8987",
    "sg:postcode":"EC2N 2DL",
    "sg:province":"Greater London",
    "sg:tags":[
        "magazine"
    ],
    "wof:name":"Throgmorton Press Ltd The",
    "wof:placetype":"venue"
},
  "geometry": {"coordinates":[-0.086616,51.516201],"type":"Point"}
}