{
  "type": "Feature",
  "properties": {
    "addr:full":"12a Hunterston Road West Kilbride North Ayrshire KA23 9EX",
    "addr:housenumber":"12a",
    "addr:postcode":"ka23 9ex",
    "addr:street":"Hunterston Road",
    "iso:country":"GB",
    "sg:address":"12a Hunterston Road",
    "sg:city":"West Kilbride",
    "sg:classifiers":[
        {
            "category":"Building & Trades",
            "subcategory":"Construction",
            "type":"Services"
        }
    ],
    "sg:postcode":"KA23 9EX",
    "sg:province":"North Ayrshire",
    "sg:tags":[
        "bricklaying"
    ],
    "wof:name":"Gordon G Middleton",
    "wof:placetype":"venue"
},
  "geometry": {"coordinates":[-4.8582148552,55.6968307495],"type":"Point"}
}