{
  "type": "Feature",
  "properties": {
    "addr:full":"Ashford Road Maidstone Kent ME14 5PP",
    "addr:postcode":"me14 5pp",
    "addr:street":"Ashford Road",
    "iso:country":"GB",
    "sg:address":"Ashford Road",
    "sg:city":"Maidstone",
    "sg:classifiers":[
        {
            "category":"Insurance",
            "subcategory":"Insurance Agent",
            "type":"Services"
        }
    ],
    "sg:phone":"+44 1622 683913",
    "sg:postcode":"ME14 5PP",
    "sg:province":"Kent",
    "sg:tags":[
        "broker"
    ],
    "wof:name":"McMurdo Potipher Webb Ltd.",
    "wof:placetype":"venue"
},
  "geometry": {"coordinates":[0.5318850279,51.2734794617],"type":"Point"}
}