{
  "type": "Feature",
  "properties": {
    "addr:full":"The New House, Duke Street Broseley Shropshire TF12 5LX",
    "addr:postcode":"tf12 5lx",
    "addr:street":"Duke Street",
    "iso:country":"GB",
    "sg:address":"The New House, Duke Street",
    "sg:city":"Broseley",
    "sg:classifiers":[
        {
            "category":"Manufacturing",
            "subcategory":"Buildings",
            "type":"Manufacturing & Wholesale Goods"
        }
    ],
    "sg:phone":"+44 1952 884157",
    "sg:postcode":"TF12 5LX",
    "sg:province":"Shropshire",
    "sg:tags":[
        "mobile",
        "home"
    ],
    "wof:name":"C & J Nedics",
    "wof:placetype":"venue"
},
  "geometry": {"coordinates":[-2.4846138954,52.6158103943],"type":"Point"}
}