{
  "type": "Feature",
  "properties": {
    "iso:country":"GB",
    "sg:address":"Dalmarnock Bridge, Downiebrae Rd",
    "sg:city":"Glasgow",
    "sg:classifiers":[
        {
            "category":"Freight",
            "type":"Transportation"
        }
    ],
    "sg:phone":"+44 141 613 1111",
    "sg:postcode":"G73 1PQ",
    "sg:province":"Glasgow City",
    "sg:tags":[
        "haulage",
        "road"
    ],
    "wof:name":"Escortrux 92 Ltd",
    "wof:placetype":"venue"
},
  "geometry": {"coordinates":[-4.209174,55.836197],"type":"Point"}
}