{
  "type": "Feature",
  "properties": {
    "addr:full":"17 Market Place Chipping Norton Gloucestershire OX7 5NA",
    "addr:housenumber":"17",
    "addr:postcode":"ox7 5na",
    "addr:street":"Market Place",
    "iso:country":"GB",
    "sg:address":"17 Market Place",
    "sg:city":"Chipping Norton",
    "sg:classifiers":[
        {
            "category":"Home & Garden",
            "subcategory":"Furniture",
            "type":"Retail Goods"
        }
    ],
    "sg:phone":"+44 1608 641466",
    "sg:postcode":"OX7 5NA",
    "sg:province":"Gloucestershire",
    "wof:name":"Porcupine",
    "wof:placetype":"venue"
},
  "geometry": {"coordinates":[-1.545654,51.942558],"type":"Point"}
}