{
  "type": "Feature",
  "properties": {
    "iso:country":"GB",
    "sg:address":"East Blagdon Farm, Cranborne",
    "sg:city":"Wimborne",
    "sg:classifiers":[
        {
            "category":"Farming",
            "subcategory":"Livestock Farm",
            "type":"Manufacturing & Wholesale Goods"
        }
    ],
    "sg:postcode":"BH21 5RZ",
    "sg:province":"Dorset",
    "sg:tags":[
        "stud"
    ],
    "wof:name":"East Blagdon Farm",
    "wof:placetype":"venue"
},
  "geometry": {"coordinates":[-1.921689,50.91935],"type":"Point"}
}