{
  "type": "Feature",
  "properties": {
    "addr:full":"Foolsyke House, Hesketh, Rimington Clitheroe Lancashire BB7 4JH",
    "addr:postcode":"bb7 4jh",
    "iso:country":"GB",
    "sg:address":"Foolsyke House, Hesketh, Rimington",
    "sg:city":"Clitheroe",
    "sg:classifiers":[
        {
            "category":"Building & Trades",
            "subcategory":"Construction",
            "type":"Services"
        }
    ],
    "sg:phone":"+44 1200 445058",
    "sg:postcode":"BB7 4JH",
    "sg:province":"Lancashire",
    "sg:tags":[
        "builder"
    ],
    "wof:name":"Hamilton Associates",
    "wof:placetype":"venue"
},
  "geometry": {"coordinates":[-2.286658,53.908417],"type":"Point"}
}