{
  "type": "Feature",
  "properties": {
    "iso:country":"GB",
    "sg:address":"16 Brookmans Avenue, Quinton",
    "sg:city":"Birmingham",
    "sg:classifiers":[
        {
            "category":"Building & Trades",
            "subcategory":"Construction",
            "type":"Services"
        }
    ],
    "sg:phone":"+44 121 421 5812",
    "sg:postcode":"B32 2SL",
    "sg:province":"West Midlands",
    "sg:tags":[
        "decorator",
        "painter"
    ],
    "wof:name":"Haddon Decorations & Property Repairs",
    "wof:placetype":"venue"
},
  "geometry": {"coordinates":[-1.988227,52.453979],"type":"Point"}
}