{
  "type": "Feature",
  "properties": {
    "iso:country":"GB",
    "sg:address":"83 Union Street",
    "sg:city":"Glasgow",
    "sg:classifiers":[
        {
            "category":"Banks & Credit Unions",
            "subcategory":"Bank",
            "type":"Services"
        }
    ],
    "sg:phone":"+44 141 221 3200",
    "sg:postcode":"G1 3TA",
    "sg:province":"Glasgow City",
    "sg:tags":[
        "broker",
        "mortgage"
    ],
    "wof:name":"MORTGAGE ADVICE BUREAU",
    "wof:placetype":"venue"
},
  "geometry": {"coordinates":[-4.2571592331,55.8599433899],"type":"Point"}
}