{
  "type": "Feature",
  "properties": {
    "addr:full":"Dental Surgery, 24 Bore Street Lichfield Staffordshire WS13 6LL",
    "addr:housenumber":"24",
    "addr:postcode":"ws13 6ll",
    "addr:street":"Bore Street",
    "iso:country":"GB",
    "sg:address":"Dental Surgery, 24 Bore Street",
    "sg:city":"Lichfield",
    "sg:classifiers":[
        {
            "category":"Health Services",
            "subcategory":"Dentist",
            "type":"Services"
        }
    ],
    "sg:postcode":"WS13 6LL",
    "sg:province":"Staffordshire",
    "wof:name":"Bore Street Dental Practice",
    "wof:placetype":"venue"
},
  "geometry": {"coordinates":[-1.8196599483,52.6840286255],"type":"Point"}
}