{
  "type": "Feature",
  "properties": {
    "addr:full":"2 St Johns Place Dunfermline Fife KY12 7TA",
    "addr:housenumber":"2",
    "addr:postcode":"ky12 7ta",
    "addr:street":"St Johns Place Dunfermline",
    "iso:country":"GB",
    "sg:address":"2 St Johns Place",
    "sg:city":"Dunfermline",
    "sg:classifiers":[
        {
            "category":"Retail",
            "subcategory":"Repair Shop",
            "type":"Services"
        }
    ],
    "sg:phone":"+44 7754 581864",
    "sg:postcode":"KY12 7TA",
    "sg:province":"Fife",
    "sg:tags":[
        "television",
        "good",
        "video",
        "servicing",
        "maintenance",
        "radio"
    ],
    "wof:name":"Bill Brown`S",
    "wof:placetype":"venue"
},
  "geometry": {"coordinates":[-3.433451,56.071564],"type":"Point"}
}