{
  "type": "Feature",
  "properties": {
    "addr:full":"3a Market Street Faversham Kent ME13 7AH",
    "addr:housenumber":"3a",
    "addr:postcode":"me13 7ah",
    "addr:street":"Market Street",
    "iso:country":"GB",
    "sg:address":"3a Market Street",
    "sg:city":"Faversham",
    "sg:classifiers":[
        {
            "category":"Shopping",
            "subcategory":"Florist",
            "type":"Retail Goods"
        }
    ],
    "sg:phone":"+44 1795 532734",
    "sg:postcode":"ME13 7AH",
    "sg:province":"Kent",
    "wof:name":"Collins Florist",
    "wof:placetype":"venue"
},
  "geometry": {"coordinates":[0.891508,51.315559],"type":"Point"}
}