{
  "type": "Feature",
  "properties": {
    "addr:full":"18 Russell Bank Rd, Four Oaks Sutton Coldfield Staffordshire B74 4RG",
    "addr:housenumber":"18",
    "addr:postcode":"b74 4rg",
    "addr:street":"Russell Bank Rd",
    "iso:country":"GB",
    "sg:address":"18 Russell Bank Rd, Four Oaks",
    "sg:city":"Sutton Coldfield",
    "sg:classifiers":[
        {
            "category":"Retail",
            "subcategory":"Driving School",
            "type":"Services"
        }
    ],
    "sg:phone":"+44 121 353 4701",
    "sg:postcode":"B74 4RG",
    "sg:province":"Staffordshire",
    "wof:name":"Four Oaks School of Motoring",
    "wof:placetype":"venue"
},
  "geometry": {"coordinates":[-1.8515130281,52.5942001343],"type":"Point"}
}