{
  "type": "Feature",
  "properties": {
    "addr:full":"Unit 7 Riverside, Brambleside Uckfield East Sussex TN22 1QQ",
    "addr:housenumber":"unit 7",
    "addr:postcode":"tn22 1qq",
    "addr:street":"Riverside;Uckfield",
    "iso:country":"GB",
    "sg:address":"Unit 7 Riverside, Brambleside",
    "sg:city":"Uckfield",
    "sg:classifiers":[
        {
            "category":"Building & Trades",
            "subcategory":"Pest Control",
            "type":"Services"
        }
    ],
    "sg:phone":"+44 1825 763159",
    "sg:postcode":"TN22 1QQ",
    "sg:province":"East Sussex",
    "sg:tags":[
        "vermin"
    ],
    "sg:website":"http://www.d-sankey.co.uk",
    "wof:name":"D Sankey Pest Control Services",
    "wof:placetype":"venue"
},
  "geometry": {"coordinates":[0.0856949985,50.9673614502],"type":"Point"}
}