{
  "type": "Feature",
  "properties": {
    "addr:full":"6 Dartmouth Walk, Keynsham Bristol City of Bristol BS31 2NZ",
    "addr:housenumber":"6",
    "addr:postcode":"bs31 2nz",
    "addr:street":"Dartmouth Walk",
    "iso:country":"GB",
    "sg:address":"6 Dartmouth Walk, Keynsham",
    "sg:city":"Bristol",
    "sg:classifiers":[
        {
            "category":"Professional",
            "subcategory":"Computer Services",
            "type":"Services"
        }
    ],
    "sg:phone":"+44 117 986 1677",
    "sg:postcode":"BS31 2NZ",
    "sg:province":"City of Bristol",
    "sg:tags":[
        "system",
        "software"
    ],
    "wof:name":"Sweet Solutions",
    "wof:placetype":"venue"
},
  "geometry": {"coordinates":[-2.507251,51.418419],"type":"Point"}
}