{
  "type": "Feature",
  "properties": {
    "addr:full":"342 Grove Green Road London Greater London E11 4EA",
    "addr:housenumber":"342",
    "addr:postcode":"e11 4ea",
    "addr:street":"Grove Green Road",
    "iso:country":"GB",
    "sg:address":"342 Grove Green Road",
    "sg:city":"London",
    "sg:classifiers":[
        {
            "category":"Personal",
            "subcategory":"Beauty Salon",
            "type":"Services"
        },
        {
            "category":"Personal",
            "subcategory":"Barber",
            "type":"Services"
        }
    ],
    "sg:phone":"+44 20 8518 7971",
    "sg:postcode":"E11 4EA",
    "sg:province":"Greater London",
    "sg:tags":[
        "men's",
        "hairdresser"
    ],
    "wof:name":"Steve's Barber Shop",
    "wof:placetype":"venue"
},
  "geometry": {"coordinates":[0.003633,51.5644302368],"type":"Point"}
}