{
  "type": "Feature",
  "properties": {
    "iso:country":"GB",
    "sg:address":"199 Twyford Avenue, Stamshaw",
    "sg:city":"Portsmouth",
    "sg:classifiers":[
        {
            "category":"Shopping",
            "subcategory":"Bicycles & Sporting Goods",
            "type":"Retail Goods"
        }
    ],
    "sg:postcode":"PO2 8HZ",
    "sg:province":"Hampshire",
    "sg:tags":[
        "cycle",
        "accessory"
    ],
    "wof:name":"Coopers Cycles",
    "wof:placetype":"venue"
},
  "geometry": {"coordinates":[-1.084826,50.818645],"type":"Point"}
}