{
  "type": "Feature",
  "properties": {
    "addr:full":"Rosalind House, Jays Close Basingstoke Hampshire RG22 4BS",
    "addr:postcode":"rg22 4bs",
    "addr:street":"Jays Close",
    "iso:country":"GB",
    "sg:address":"Rosalind House, Jays Close",
    "sg:city":"Basingstoke",
    "sg:classifiers":[
        {
            "category":"Communications",
            "type":"Services"
        }
    ],
    "sg:phone":"+44 1256 858685",
    "sg:postcode":"RG22 4BS",
    "sg:province":"Hampshire",
    "sg:tags":[
        "data",
        "network"
    ],
    "wof:name":"Fibernet U K Ltd.",
    "wof:placetype":"venue"
},
  "geometry": {"coordinates":[-1.0887240171,51.2494010925],"type":"Point"}
}