{
  "type": "Feature",
  "properties": {
    "addr:full":"330 Askew Rd West Gateshead Tyne and Wear NE8 2PB",
    "addr:housenumber":"330",
    "addr:postcode":"ne8 2pb",
    "addr:street":"Askew Rd West",
    "iso:country":"GB",
    "sg:address":"330 Askew Rd West",
    "sg:city":"Gateshead",
    "sg:classifiers":[
        {
            "category":"Shopping",
            "subcategory":"Pharmacy",
            "type":"Retail Goods"
        }
    ],
    "sg:phone":"+44 191 460 4484",
    "sg:postcode":"NE8 2PB",
    "sg:province":"Tyne and Wear",
    "sg:tags":[
        "pharmacist",
        "chemist"
    ],
    "wof:name":"Lloyds Pharmacy",
    "wof:placetype":"venue"
},
  "geometry": {"coordinates":[-1.624556,54.954544],"type":"Point"}
}