{
  "type": "Feature",
  "properties": {
    "iso:country":"GB",
    "sg:address":"36 Hether Drive",
    "sg:city":"Carlisle",
    "sg:classifiers":[
        {
            "category":"Retail",
            "subcategory":"Repair Shop",
            "type":"Services"
        }
    ],
    "sg:postcode":"CA3 0ES",
    "sg:province":"Cumbria",
    "sg:tags":[
        "radio",
        "television",
        "video"
    ],
    "wof:name":"Retel Tv",
    "wof:placetype":"venue"
},
  "geometry": {"coordinates":[-2.95124,54.917789],"type":"Point"}
}