{
  "type": "Feature",
  "properties": {
    "addr:full":"32 Barlby Rd Selby East Riding of Yorkshire YO8 5AA",
    "addr:housenumber":"32",
    "addr:postcode":"yo8 5aa",
    "addr:street":"Barlby Rd",
    "iso:country":"GB",
    "sg:address":"32 Barlby Rd",
    "sg:city":"Selby",
    "sg:classifiers":[
        {
            "category":"Recreation",
            "subcategory":"Fishing",
            "type":"Entertainment"
        }
    ],
    "sg:phone":"+44 1757 704645",
    "sg:postcode":"YO8 5AA",
    "sg:province":"East Riding of Yorkshire",
    "sg:tags":[
        "angling"
    ],
    "wof:name":"Victors Fisheries",
    "wof:placetype":"venue"
},
  "geometry": {"coordinates":[-1.0622260571,53.7863235474],"type":"Point"}
}