{
  "type": "Feature",
  "properties": {
    "addr:full":"Western Road Montrose Aberdeenshire DD10 8LN",
    "addr:postcode":"dd10 8ln",
    "addr:street":"Western Road",
    "iso:country":"GB",
    "sg:address":"Western Road",
    "sg:city":"Montrose",
    "sg:classifiers":[
        {
            "category":"Social Services",
            "subcategory":"Adult Care",
            "type":"Services"
        },
        {
            "category":"Government",
            "subcategory":"Office",
            "type":"Public Place"
        }
    ],
    "sg:phone":"+44 1674 677257",
    "sg:postcode":"DD10 8LN",
    "sg:province":"Aberdeenshire",
    "sg:tags":[
        "housing",
        "local",
        "sheltered"
    ],
    "wof:name":"Blackfriars Court",
    "wof:placetype":"venue"
},
  "geometry": {"coordinates":[-2.4701480865,56.7108726501],"type":"Point"}
}