{
  "type": "Feature",
  "properties": {
    "addr:full":"South Bridgetown Farm, Werrington Launceston Cornwall PL15 9RP",
    "addr:postcode":"pl15 9rp",
    "addr:street":"South Bridgetown",
    "iso:country":"GB",
    "sg:address":"South Bridgetown Farm, Werrington",
    "sg:city":"Launceston",
    "sg:classifiers":[
        {
            "category":"Farming",
            "subcategory":"Farm",
            "type":"Manufacturing & Wholesale Goods"
        }
    ],
    "sg:postcode":"PL15 9RP",
    "sg:province":"Cornwall",
    "sg:tags":[
        "mixed",
        "crop"
    ],
    "wof:name":"D J Lewis",
    "wof:placetype":"venue"
},
  "geometry": {"coordinates":[-4.3633441925,50.6367073059],"type":"Point"}
}