{
  "type": "Feature",
  "properties": {
    "iso:country":"GB",
    "sg:address":"3 Broad Lane, Dalton",
    "sg:city":"Huddersfield",
    "sg:classifiers":[
        {
            "category":"Food & Beverages",
            "subcategory":"Meat & Fish",
            "type":"Retail Goods"
        }
    ],
    "sg:postcode":"HD5 9BU",
    "sg:province":"West Yorkshire",
    "sg:tags":[
        "butcher"
    ],
    "wof:name":"Schofields",
    "wof:placetype":"venue"
},
  "geometry": {"coordinates":[-1.761629,53.645981],"type":"Point"}
}