{
  "type": "Feature",
  "properties": {
    "iso:country":"GB",
    "sg:address":"1 Quarrywood Court, Kirkton North",
    "sg:city":"Livingston",
    "sg:classifiers":[
        {
            "category":"Farming",
            "subcategory":"Nursery",
            "type":"Manufacturing & Wholesale Goods"
        }
    ],
    "sg:phone":"+44 1506 460785",
    "sg:postcode":"EH54 6AX",
    "sg:province":"West Lothian",
    "sg:tags":[
        "creche"
    ],
    "wof:name":"Careshare Nursery",
    "wof:placetype":"venue"
},
  "geometry": {"coordinates":[-3.527819,55.888233],"type":"Point"}
}