{
  "type": "Feature",
  "properties": {
    "addr:full":"Pudding Mews Hexham Northumberland NE46 3SW",
    "addr:postcode":"ne46 3sw",
    "addr:street":"Pudding Mews",
    "iso:country":"GB",
    "sg:address":"Pudding Mews",
    "sg:city":"Hexham",
    "sg:classifiers":[
        {
            "category":"Shopping",
            "subcategory":"Hobbies, Toys, & Games",
            "type":"Retail Goods"
        }
    ],
    "sg:postcode":"NE46 3SW",
    "sg:province":"Northumberland",
    "sg:tags":[
        "shop",
        "toy"
    ],
    "wof:name":"Fairplay",
    "wof:placetype":"venue"
},
  "geometry": {"coordinates":[-2.1012940407,54.970035553],"type":"Point"}
}