{
  "type": "Feature",
  "properties": {
    "iso:country":"GB",
    "sg:address":"Brow Top Farm, Branthwaite",
    "sg:city":"Workington",
    "sg:classifiers":[
        {
            "category":"Home & Garden",
            "subcategory":"Garden Supply",
            "type":"Retail Goods"
        },
        {
            "category":"Farming",
            "subcategory":"Crops",
            "type":"Manufacturing & Wholesale Goods"
        }
    ],
    "sg:phone":"+44 1900 602572",
    "sg:postcode":"CA14 4TG",
    "sg:province":"Cumbria",
    "sg:tags":[
        "bulb",
        "arable",
        "grower"
    ],
    "wof:name":"P & A Jarman",
    "wof:placetype":"venue"
},
  "geometry": {"coordinates":[-3.458624,54.61005],"type":"Point"}
}