{
  "type": "Feature",
  "properties": {
    "iso:country":"GB",
    "sg:address":"20 Queen Street",
    "sg:city":"Dawlish",
    "sg:classifiers":[
        {
            "category":"Food & Beverages",
            "subcategory":"Meat & Fish",
            "type":"Retail Goods"
        },
        {
            "category":"Food & Beverages",
            "subcategory":"Groceries & Convenience Stores",
            "type":"Retail Goods"
        }
    ],
    "sg:phone":"+44 1626 863242",
    "sg:postcode":"EX7 9HB",
    "sg:province":"Devon",
    "sg:tags":[
        "shop",
        "chip"
    ],
    "wof:name":"Model Fish Cafe",
    "wof:placetype":"venue"
},
  "geometry": {"coordinates":[-3.471336,50.581749],"type":"Point"}
}