{
  "type": "Feature",
  "properties": {
    "addr:full":"Churchill House, 1 Beck Lane Bingley West Yorkshire BD16 4EL",
    "addr:housenumber":"1",
    "addr:postcode":"bd16 4el",
    "addr:street":"Beck Lane",
    "iso:country":"GB",
    "sg:address":"Churchill House, 1 Beck Lane",
    "sg:city":"Bingley",
    "sg:classifiers":[
        {
            "category":"Building & Trades",
            "subcategory":"Cleaning & Sanitation",
            "type":"Services"
        }
    ],
    "sg:phone":"+44 1274 568712",
    "sg:postcode":"BD16 4EL",
    "sg:province":"West Yorkshire",
    "sg:tags":[
        "commercial"
    ],
    "wof:name":"Instant Services Ltd.",
    "wof:placetype":"venue"
},
  "geometry": {"coordinates":[-1.8327670097,53.854473114],"type":"Point"}
}