{
  "type": "Feature",
  "properties": {
    "addr:full":"16 Culmington, Stirchley Telford Shropshire TF3 1UL",
    "addr:housenumber":"16",
    "addr:postcode":"tf3 1ul",
    "addr:street":"Culmington",
    "iso:country":"GB",
    "sg:address":"16 Culmington, Stirchley",
    "sg:city":"Telford",
    "sg:classifiers":[
        {
            "category":"Education",
            "subcategory":"Special Training",
            "type":"Public Place"
        }
    ],
    "sg:postcode":"TF3 1UL",
    "sg:province":"Shropshire",
    "sg:tags":[
        "product",
        "centre"
    ],
    "wof:name":"Cube Communications Ltd",
    "wof:placetype":"venue"
},
  "geometry": {"coordinates":[-2.435471,52.658897],"type":"Point"}
}