{
  "type": "Feature",
  "properties": {
    "addr:full":"25 Hitchin Road, Stotfold Hitchin Bedfordshire SG5 4HP",
    "addr:housenumber":"25",
    "addr:postcode":"sg5 4hp",
    "addr:street":"Hitchin Road",
    "iso:country":"GB",
    "sg:address":"25 Hitchin Road, Stotfold",
    "sg:city":"Hitchin",
    "sg:classifiers":[
        {
            "category":"Home & Garden",
            "subcategory":"Building Materials",
            "type":"Retail Goods"
        }
    ],
    "sg:phone":"+44 1462 834318",
    "sg:postcode":"SG5 4HP",
    "sg:province":"Bedfordshire",
    "sg:tags":[
        "fencing"
    ],
    "wof:name":"S J Miller",
    "wof:placetype":"venue"
},
  "geometry": {"coordinates":[-0.234282,52.014866],"type":"Point"}
}