{
  "type": "Feature",
  "properties": {
    "addr:full":"1 Gloucester Road, Cotswold Chambers Cheltenham Gloucestershire GL51 8LN",
    "addr:housenumber":"1",
    "addr:postcode":"gl51 8ln",
    "addr:street":"Gloucester Road",
    "iso:country":"GB",
    "sg:address":"1 Gloucester Road, Cotswold Chambers",
    "sg:city":"Cheltenham",
    "sg:classifiers":[
        {
            "category":"Manufacturing",
            "subcategory":"Petroleum Products",
            "type":"Manufacturing & Wholesale Goods"
        }
    ],
    "sg:postcode":"GL51 8LN",
    "sg:province":"Gloucestershire",
    "sg:tags":[
        "double",
        "glazing"
    ],
    "wof:name":"G T  Windows Ltd.",
    "wof:placetype":"venue"
},
  "geometry": {"coordinates":[-2.091199,51.902649],"type":"Point"}
}