{
  "type": "Feature",
  "properties": {
    "addr:full":"12 Exeter Airport, Clyst Honiton Exeter Devon EX5 2BA",
    "addr:housenumber":"12;airport",
    "addr:postcode":"ex5 2ba",
    "addr:street":"Exeter",
    "iso:country":"GB",
    "sg:address":"12 Exeter Airport, Clyst Honiton",
    "sg:city":"Exeter",
    "sg:classifiers":[
        {
            "category":"Building & Trades",
            "subcategory":"Construction",
            "type":"Services"
        }
    ],
    "sg:postcode":"EX5 2BA",
    "sg:province":"Devon",
    "sg:tags":[
        "builder"
    ],
    "wof:name":"Pugh,C A,",
    "wof:placetype":"venue"
},
  "geometry": {"coordinates":[-3.3994998932,50.7311897278],"type":"Point"}
}