{
  "type": "Feature",
  "properties": {
    "iso:country":"GB",
    "sg:address":"142 West Nile Street",
    "sg:city":"Glasgow",
    "sg:classifiers":[
        {
            "category":"Professional",
            "subcategory":"Accounting & Tax Preparation",
            "type":"Services"
        }
    ],
    "sg:phone":"+44 141 353 6600",
    "sg:postcode":"G1 2RQ",
    "sg:province":"Glasgow City",
    "sg:tags":[
        "accountant",
        "activity"
    ],
    "wof:name":"Armstrongs",
    "wof:placetype":"venue"
},
  "geometry": {"coordinates":[-4.2539958954,55.8641052246],"type":"Point"}
}