{
  "type": "Feature",
  "properties": {
    "addr:full":"83 Salters Road Newcastle-upon-tyne Tyne and Wear NE3 1DU",
    "addr:housenumber":"83",
    "addr:postcode":"ne3 1du",
    "addr:street":"Salters Road",
    "iso:country":"GB",
    "sg:address":"83 Salters Road",
    "sg:city":"Newcastle-upon-tyne",
    "sg:classifiers":[
        {
            "category":"Autos & Motor Vehicles",
            "subcategory":"Auto Supplies",
            "type":"Retail Goods"
        },
        {
            "category":"Shopping",
            "type":"Retail Goods"
        }
    ],
    "sg:phone":"+44 191 213 0204",
    "sg:postcode":"NE3 1DU",
    "sg:province":"Tyne and Wear",
    "sg:tags":[
        "car",
        "part",
        "audio",
        "accessory"
    ],
    "wof:name":"Motor World Ltd.",
    "wof:placetype":"venue"
},
  "geometry": {"coordinates":[-1.623396039,55.0066757202],"type":"Point"}
}