{
  "type": "Feature",
  "properties": {
    "iso:country":"GB",
    "sg:address":"1 Emperors Gate, Chells Maonr Village",
    "sg:city":"Stevenage",
    "sg:classifiers":[
        {
            "category":"Bars & Pubs",
            "type":"Food & Drink"
        }
    ],
    "sg:phone":"+44 1438 730991",
    "sg:postcode":"SG2 7QX",
    "sg:province":"Hertfordshire",
    "sg:tags":[
        "pubs",
        "inn"
    ],
    "wof:name":"Emperors Head",
    "wof:placetype":"venue"
},
  "geometry": {"coordinates":[-0.162044,51.915928],"type":"Point"}
}