{
  "type": "Feature",
  "properties": {
    "iso:country":"GB",
    "sg:address":"Unit F3 Ringway, Bounds Grn Industrial Estate",
    "sg:city":"London",
    "sg:classifiers":[
        {
            "category":"Retail",
            "subcategory":"Auto Repair",
            "type":"Services"
        }
    ],
    "sg:phone":"+44 20 8361 1225",
    "sg:postcode":"N11 2UD",
    "sg:province":"Greater London",
    "sg:tags":[
        "modification",
        "garage",
        "related"
    ],
    "wof:name":"Ringway Motor Services",
    "wof:placetype":"venue"
},
  "geometry": {"coordinates":[-0.12231,51.605591],"type":"Point"}
}