{
  "type": "Feature",
  "properties": {
    "iso:country":"GB",
    "sg:address":"2 Hill Street",
    "sg:city":"Lydney",
    "sg:classifiers":[
        {
            "category":"Professional",
            "subcategory":"Management & Consulting",
            "type":"Services"
        }
    ],
    "sg:phone":"+44 1594 845535",
    "sg:postcode":"GL15 5RF",
    "sg:province":"Gloucestershire",
    "sg:tags":[
        "consultant",
        "specialist"
    ],
    "wof:name":"Nail Attraction",
    "wof:placetype":"venue"
},
  "geometry": {"coordinates":[-2.53358,51.725567],"type":"Point"}
}