{
  "type": "Feature",
  "properties": {
    "addr:full":"7 Bowlers Croft Basildon Essex SS14 3DU",
    "addr:housenumber":"7",
    "addr:postcode":"ss14 3du",
    "addr:street":"Bowlers Croft",
    "iso:country":"GB",
    "sg:address":"7 Bowlers Croft",
    "sg:city":"Basildon",
    "sg:classifiers":[
        {
            "category":"Wholesale",
            "subcategory":"Office Equipment",
            "type":"Manufacturing & Wholesale Goods"
        }
    ],
    "sg:phone":"+44 1268 274060",
    "sg:postcode":"SS14 3DU",
    "sg:province":"Essex",
    "sg:tags":[
        "partition",
        "cubicle"
    ],
    "wof:name":"Dj Interiors Ltd.",
    "wof:placetype":"venue"
},
  "geometry": {"coordinates":[0.490706,51.588364],"type":"Point"}
}