{
  "type": "Feature",
  "properties": {
    "iso:country":"GB",
    "sg:address":"34 Station Road East",
    "sg:city":"Oxted",
    "sg:classifiers":[
        {
            "category":"Personal",
            "subcategory":"Beauty Salon",
            "type":"Services"
        }
    ],
    "sg:phone":"+44 1883 716407",
    "sg:postcode":"RH8 0PG",
    "sg:province":"Surrey",
    "sg:tags":[
        "lady",
        "hairdresser"
    ],
    "wof:name":"B J's Hair & Beauty Salon",
    "wof:placetype":"venue"
},
  "geometry": {"coordinates":[-0.001859,51.257576],"type":"Point"}
}