{
  "type": "Feature",
  "properties": {
    "iso:country":"GB",
    "sg:address":"Warden, 25 Woodbine Gardens",
    "sg:city":"Burnley",
    "sg:classifiers":[
        {
            "category":"Social Services",
            "subcategory":"Adult Care",
            "type":"Services"
        },
        {
            "category":"Government",
            "subcategory":"Office",
            "type":"Public Place"
        }
    ],
    "sg:phone":"+44 1282 415259",
    "sg:postcode":"BB12 6DW",
    "sg:province":"Lancashire",
    "sg:tags":[
        "housing",
        "local",
        "sheltered"
    ],
    "wof:name":"Woodbine Gardens Sheltered Housing",
    "wof:placetype":"venue"
},
  "geometry": {"coordinates":[-2.27486,53.793659],"type":"Point"}
}