{
  "type": "Feature",
  "properties": {
    "addr:full":"Glendoick Perth Perth and Kinross PH2 7NS",
    "addr:postcode":"ph2 7ns",
    "addr:street":"Glendoick",
    "iso:country":"GB",
    "sg:address":"Glendoick",
    "sg:city":"Perth",
    "sg:classifiers":[
        {
            "category":"Home & Garden",
            "subcategory":"Garden Supply",
            "type":"Retail Goods"
        }
    ],
    "sg:phone":"+44 1738 860260",
    "sg:postcode":"PH2 7NS",
    "sg:province":"Perth and Kinross",
    "sg:tags":[
        "nursery",
        "centre"
    ],
    "wof:name":"Glendoick Gardens Ltd.",
    "wof:placetype":"venue"
},
  "geometry": {"coordinates":[-3.29213,56.395931],"type":"Point"}
}