{
  "type": "Feature",
  "properties": {
    "addr:full":"Lakeside, Trafford Park Rd Manchester Cheshire M17 1HP",
    "addr:postcode":"m17 1hp",
    "addr:street":"Park Rd",
    "iso:country":"GB",
    "sg:address":"Lakeside, Trafford Park Rd",
    "sg:city":"Manchester",
    "sg:classifiers":[
        {
            "category":"Professional",
            "subcategory":"Business Services",
            "type":"Services"
        }
    ],
    "sg:phone":"+44 161 872 8291",
    "sg:postcode":"M17 1HP",
    "sg:province":"Cheshire",
    "sg:tags":[
        "holding"
    ],
    "wof:name":"The Hopkinson's Group PLC",
    "wof:placetype":"venue"
},
  "geometry": {"coordinates":[-2.3083589077,53.4681396484],"type":"Point"}
}