{
  "type": "Feature",
  "properties": {
    "addr:full":"2 Tavistock Place London Greater London WC1H 9RA",
    "addr:housenumber":"2",
    "addr:postcode":"wc1h 9ra",
    "addr:street":"Tavistock Place",
    "iso:country":"GB",
    "sg:address":"2 Tavistock Place",
    "sg:city":"London",
    "sg:classifiers":[
        {
            "category":"Professional",
            "subcategory":"Business Services",
            "type":"Services"
        }
    ],
    "sg:phone":"+44 20 7833 1251",
    "sg:postcode":"WC1H 9RA",
    "sg:province":"Greater London",
    "sg:tags":[
        "trade"
    ],
    "wof:name":"Irish Food Board",
    "wof:placetype":"venue"
},
  "geometry": {"coordinates":[-0.1276309937,51.524684906],"type":"Point"}
}