{
  "type": "Feature",
  "properties": {
    "addr:full":"Pretoria Road Larbert Falkirk FK5 4NB",
    "addr:postcode":"fk5 4nb",
    "addr:street":"Pretoria Road",
    "iso:country":"GB",
    "sg:address":"Pretoria Road",
    "sg:city":"Larbert",
    "sg:classifiers":[
        {
            "category":"Arena",
            "subcategory":"Sports Club",
            "type":"Entertainment"
        }
    ],
    "sg:phone":"+44 1324 556819",
    "sg:postcode":"FK5 4NB",
    "sg:province":"Falkirk",
    "wof:name":"Larbert Bowling Club",
    "wof:placetype":"venue"
},
  "geometry": {"coordinates":[-3.8352849483,56.020980835],"type":"Point"}
}