{
  "type": "Feature",
  "properties": {
    "iso:country":"GB",
    "sg:address":"53 London Rd",
    "sg:city":"Dunstable",
    "sg:classifiers":[
        {
            "category":"Food & Beverages",
            "subcategory":"Liquor & Beverages",
            "type":"Retail Goods"
        }
    ],
    "sg:phone":"+44 1582 661971",
    "sg:postcode":"LU6 3DH",
    "sg:province":"Bedfordshire",
    "sg:tags":[
        "beer",
        "spirit",
        "wines"
    ],
    "wof:name":"Thresher Wine Shop",
    "wof:placetype":"venue"
},
  "geometry": {"coordinates":[-0.50887,51.877972],"type":"Point"}
}