{
  "type": "Feature",
  "properties": {
    "iso:country":"GB",
    "sg:address":"High Street, Kirmington",
    "sg:city":"Ulceby",
    "sg:classifiers":[
        {
            "category":"Education",
            "subcategory":"School",
            "type":"Public Place"
        },
        {
            "category":"Government",
            "subcategory":"Office",
            "type":"Public Place"
        }
    ],
    "sg:phone":"+44 1652 688451",
    "sg:postcode":"DN39 6YP",
    "sg:province":"Lincolnshire",
    "sg:tags":[
        "local",
        "authority"
    ],
    "wof:name":"Kirmington Primary School",
    "wof:placetype":"venue"
},
  "geometry": {"coordinates":[-0.3274059892,53.6180000305],"type":"Point"}
}