{
  "type": "Feature",
  "properties": {
    "iso:country":"GB",
    "sg:address":"335 Hope Street",
    "sg:city":"Glasgow",
    "sg:classifiers":[
        {
            "category":"Bars & Pubs",
            "type":"Food & Drink"
        },
        {
            "category":"Community Center",
            "subcategory":"Social",
            "type":"Public Place"
        }
    ],
    "sg:phone":"+44 141 331 6021",
    "sg:postcode":"G2 3PT",
    "sg:province":"Glasgow City",
    "sg:tags":[
        "pubs",
        "house",
        "inn",
        "activity"
    ],
    "wof:name":"MacConnell's",
    "wof:placetype":"venue"
},
  "geometry": {"coordinates":[-4.2565188408,55.866771698],"type":"Point"}
}