{
  "type": "Feature",
  "properties": {
    "iso:country":"GB",
    "sg:address":"21 Samor Way",
    "sg:city":"Didcot",
    "sg:classifiers":[
        {
            "category":"Professional",
            "subcategory":"Accounting & Tax Preparation",
            "type":"Services"
        }
    ],
    "sg:phone":"+44 1235 811095",
    "sg:postcode":"OX11 8RE",
    "sg:province":"Oxfordshire",
    "sg:tags":[
        "accountant"
    ],
    "wof:name":"B'keepin",
    "wof:placetype":"venue"
},
  "geometry": {"coordinates":[-1.251478,51.603672],"type":"Point"}
}