{
  "type": "Feature",
  "properties": {
    "addr:full":"4 Robertson Road Dunfermline Fife KY12 0AS",
    "addr:housenumber":"4",
    "addr:postcode":"ky12 0as",
    "addr:street":"Robertson Road",
    "iso:country":"GB",
    "sg:address":"4 Robertson Road",
    "sg:city":"Dunfermline",
    "sg:classifiers":[
        {
            "category":"Food & Beverages",
            "subcategory":"Meat & Fish",
            "type":"Retail Goods"
        },
        {
            "category":"Food & Beverages",
            "subcategory":"Groceries & Convenience Stores",
            "type":"Retail Goods"
        }
    ],
    "sg:phone":"+44 1383 724361",
    "sg:postcode":"KY12 0AS",
    "sg:province":"Fife",
    "sg:tags":[
        "shop",
        "chip"
    ],
    "wof:name":"Gennaro's Fish Bar",
    "wof:placetype":"venue"
},
  "geometry": {"coordinates":[-3.4485659599,56.0794067383],"type":"Point"}
}