{
  "type": "Feature",
  "properties": {
    "addr:full":"Winter Cottage, Milford Road, Elstead Godalming Surrey GU8 6HY",
    "addr:postcode":"gu8 6hy",
    "addr:street":"Milford Road",
    "iso:country":"GB",
    "sg:address":"Winter Cottage, Milford Road, Elstead",
    "sg:city":"Godalming",
    "sg:classifiers":[
        {
            "category":"Real Estate",
            "subcategory":"Architect",
            "type":"Services"
        }
    ],
    "sg:phone":"+44 1252 702099",
    "sg:postcode":"GU8 6HY",
    "sg:province":"Surrey",
    "sg:tags":[
        "architectural"
    ],
    "wof:name":"David Else & Associates",
    "wof:placetype":"venue"
},
  "geometry": {"coordinates":[-0.698169,51.184124],"type":"Point"}
}