{
  "type": "Feature",
  "properties": {
    "addr:full":"Homefield House, Burridge Road, Burridge Southampton Hampshire SO31 1BT",
    "addr:postcode":"so31 1bt",
    "addr:street":"Burridge Road",
    "iso:country":"GB",
    "sg:address":"Homefield House, Burridge Road, Burridge",
    "sg:city":"Southampton",
    "sg:classifiers":[
        {
            "category":"Autos & Motor Vehicles",
            "subcategory":"Recreational Vehicle Sales",
            "type":"Retail Goods"
        }
    ],
    "sg:phone":"+44 1489 572142",
    "sg:postcode":"SO31 1BT",
    "sg:province":"Hampshire",
    "sg:tags":[
        "caravan"
    ],
    "wof:name":"Nationwide Motor Caravans Ltd.",
    "wof:placetype":"venue"
},
  "geometry": {"coordinates":[-1.2692979574,50.8926124573],"type":"Point"}
}