{
  "type": "Feature",
  "properties": {
    "addr:full":"507 Newport Road, Roath Cardiff Cardiff CF23 9AD",
    "addr:housenumber":"507",
    "addr:postcode":"cf23 9ad",
    "addr:street":"Newport Road",
    "iso:country":"GB",
    "sg:address":"507 Newport Road, Roath",
    "sg:city":"Cardiff",
    "sg:classifiers":[
        {
            "category":"Home & Garden",
            "subcategory":"Furniture",
            "type":"Retail Goods"
        }
    ],
    "sg:phone":"+44 29 2048 9552",
    "sg:postcode":"CF23 9AD",
    "sg:province":"Cardiff",
    "wof:name":"Courts Superstores",
    "wof:placetype":"venue"
},
  "geometry": {"coordinates":[-3.1420209408,51.4975891113],"type":"Point"}
}