{
  "type": "Feature",
  "properties": {
    "iso:country":"GB",
    "sg:address":"9-13 Mid Beveridgewell",
    "sg:city":"Dunfermline",
    "sg:classifiers":[
        {
            "category":"Autos & Motor Vehicles",
            "subcategory":"Automobile Sales",
            "type":"Retail Goods"
        }
    ],
    "sg:phone":"+44 1383 621467",
    "sg:postcode":"KY12 9ES",
    "sg:province":"Fife",
    "sg:tags":[
        "car"
    ],
    "wof:name":"Brookland Motors",
    "wof:placetype":"venue"
},
  "geometry": {"coordinates":[-3.469015,56.077225],"type":"Point"}
}