{
  "type": "Feature",
  "properties": {
    "iso:country":"GB",
    "sg:address":"33 Danson Road",
    "sg:city":"Bexleyheath",
    "sg:classifiers":[
        {
            "category":"Shopping",
            "subcategory":"Pharmacy",
            "type":"Retail Goods"
        }
    ],
    "sg:postcode":"DA6 8HA",
    "sg:province":"Kent",
    "sg:tags":[
        "medicine",
        "therapy"
    ],
    "wof:name":"Peter Chiltern",
    "wof:placetype":"venue"
},
  "geometry": {"coordinates":[0.123532,51.457867],"type":"Point"}
}