{
  "type": "Feature",
  "properties": {
    "iso:country":"GB",
    "sg:address":"13 Little Walk",
    "sg:city":"Harlow",
    "sg:classifiers":[
        {
            "category":"Sports & Exercise",
            "subcategory":"Sports Center",
            "type":"Entertainment"
        }
    ],
    "sg:postcode":"CM20 1HY",
    "sg:province":"Essex",
    "sg:tags":[
        "shop",
        "good"
    ],
    "wof:name":"Sportsworld",
    "wof:placetype":"venue"
},
  "geometry": {"coordinates":[0.092755,51.769806],"type":"Point"}
}