{
  "type": "Feature",
  "properties": {
    "iso:country":"GB",
    "sg:address":"Belle Farm Lodge, Seven Hills Road",
    "sg:city":"Iver",
    "sg:classifiers":[
        {
            "category":"Retail",
            "subcategory":"Auto Repair",
            "type":"Services"
        }
    ],
    "sg:phone":"+44 1753 662474",
    "sg:postcode":"SL0 0PA",
    "sg:province":"Berkshire",
    "sg:tags":[
        "body",
        "car"
    ],
    "wof:name":"C C R (U K)",
    "wof:placetype":"venue"
},
  "geometry": {"coordinates":[-0.5264769793,51.552406311],"type":"Point"}
}