{
  "type": "Feature",
  "properties": {
    "iso:country":"GB",
    "sg:address":"4 Church Street, Abbey Green",
    "sg:city":"Bath",
    "sg:classifiers":[
        {
            "category":"Retail",
            "subcategory":"Repair Shop",
            "type":"Services"
        }
    ],
    "sg:phone":"+44 1225 464481",
    "sg:postcode":"BA1 1NL",
    "sg:province":"Bath and North East Somerset",
    "sg:tags":[
        "clocks",
        "watch"
    ],
    "wof:name":"Tupra",
    "wof:placetype":"venue"
},
  "geometry": {"coordinates":[-2.3588449955,51.3806800842],"type":"Point"}
}