{
  "type": "Feature",
  "properties": {
    "addr:full":"Talbot Mill, 44 Ellesmere St Manchester Cheshire M15 4JY",
    "addr:housenumber":"44",
    "addr:postcode":"m15 4jy",
    "addr:street":"Talbot;Ellesmere St",
    "iso:country":"GB",
    "sg:address":"Talbot Mill, 44 Ellesmere St",
    "sg:city":"Manchester",
    "sg:classifiers":[
        {
            "category":"Manufacturing",
            "subcategory":"Textiles",
            "type":"Manufacturing & Wholesale Goods"
        }
    ],
    "sg:phone":"+44 161 834 8409",
    "sg:postcode":"M15 4JY",
    "sg:province":"Cheshire",
    "sg:tags":[
        "knitwear"
    ],
    "wof:name":"Key Knitwear",
    "wof:placetype":"venue"
},
  "geometry": {"coordinates":[-2.24881,53.479622],"type":"Point"}
}