{
  "type": "Feature",
  "properties": {
    "addr:full":"41 Bushmead Road, Eaton Socon Huntingdon Bedfordshire PE19 3BT",
    "addr:housenumber":"41",
    "addr:postcode":"pe19 3bt",
    "addr:street":"Bushmead Road",
    "iso:country":"GB",
    "sg:address":"41 Bushmead Road, Eaton Socon",
    "sg:city":"Huntingdon",
    "sg:classifiers":[
        {
            "category":"Professional",
            "subcategory":"Engineering",
            "type":"Services"
        }
    ],
    "sg:postcode":"PE19 3BT",
    "sg:province":"Bedfordshire",
    "sg:tags":[
        "electronic",
        "engineer"
    ],
    "wof:name":"Hesing Technology",
    "wof:placetype":"venue"
},
  "geometry": {"coordinates":[-0.2893700004,52.2174682617],"type":"Point"}
}