{
  "type": "Feature",
  "properties": {
    "addr:full":"Spiceball Park, Sports Centre, Spiceball Park Rd Banbury Oxfordshire OX16 8PG",
    "addr:postcode":"ox16 8pg",
    "addr:street":"Park Rd",
    "iso:country":"GB",
    "sg:address":"Spiceball Park, Sports Centre, Spiceball Park Rd",
    "sg:city":"Banbury",
    "sg:classifiers":[
        {
            "category":"Shopping",
            "subcategory":"Pharmacy",
            "type":"Retail Goods"
        }
    ],
    "sg:phone":"+44 1295 278448",
    "sg:postcode":"OX16 8PG",
    "sg:province":"Oxfordshire",
    "sg:tags":[
        "medicine",
        "therapy"
    ],
    "wof:name":"Body Therapy Clinic",
    "wof:placetype":"venue"
},
  "geometry": {"coordinates":[-1.340028,52.061111],"type":"Point"}
}