{
  "type": "Feature",
  "properties": {
    "addr:full":"250 Cowley Road Oxford Oxfordshire OX4 1UH",
    "addr:housenumber":"250",
    "addr:postcode":"ox4 1uh",
    "addr:street":"Cowley Road",
    "iso:country":"GB",
    "sg:address":"250 Cowley Road",
    "sg:city":"Oxford",
    "sg:classifiers":[
        {
            "category":"Cafe",
            "type":"Food & Drink"
        }
    ],
    "sg:phone":"+44 1865 248504",
    "sg:postcode":"OX4 1UH",
    "sg:province":"Oxfordshire",
    "sg:tags":[
        "tea",
        "snack",
        "bar",
        "room"
    ],
    "wof:name":"Excelsior Cafe",
    "wof:placetype":"venue"
},
  "geometry": {"coordinates":[-1.2324500084,51.7460327148],"type":"Point"}
}