{
  "type": "Feature",
  "properties": {
    "addr:full":"Akesmoor Lane, Biddulph Stoke-on-trent Staffordshire ST8 6RT",
    "addr:postcode":"staffordshire st8 6rt",
    "addr:street":"Akesmoor Lane",
    "iso:country":"GB",
    "sg:address":"Akesmoor Lane, Biddulph",
    "sg:city":"Stoke-on-trent",
    "sg:classifiers":[
        {
            "category":"Building & Trades",
            "subcategory":"Equipment Rental",
            "type":"Services"
        }
    ],
    "sg:postcode":"ST8 6RT",
    "sg:province":"Staffordshire",
    "sg:tags":[
        "plant",
        "machinery"
    ],
    "wof:name":"Moody St. Farm",
    "wof:placetype":"venue"
},
  "geometry": {"coordinates":[-2.1762030125,53.1156806946],"type":"Point"}
}