{
  "type": "Feature",
  "properties": {
    "iso:country":"GB",
    "sg:address":"145 Chapel St",
    "sg:city":"Nelson",
    "sg:classifiers":[
        {
            "category":"Home & Garden",
            "subcategory":"Home Furnishings",
            "type":"Retail Goods"
        }
    ],
    "sg:phone":"+44 1282 697908",
    "sg:postcode":"BB9 8EA",
    "sg:province":"Lancashire",
    "sg:tags":[
        "patio",
        "furniture"
    ],
    "wof:name":"Chapel Mount Garden Services",
    "wof:placetype":"venue"
},
  "geometry": {"coordinates":[-2.2060229778,53.8394088745],"type":"Point"}
}