{
  "type": "Feature",
  "properties": {
    "addr:full":"23-25 High St, Stanton Hill Sutton-in-ashfield Nottinghamshire NG17 3GG",
    "addr:housenumber":"23-25",
    "addr:postcode":"ng17 3gg",
    "addr:street":"High St",
    "iso:country":"GB",
    "sg:address":"23-25 High St, Stanton Hill",
    "sg:city":"Sutton-in-ashfield",
    "sg:classifiers":[
        {
            "category":"Recreation",
            "type":"Entertainment"
        }
    ],
    "sg:postcode":"NG17 3GG",
    "sg:province":"Nottinghamshire",
    "sg:tags":[
        "snooker",
        "billiards",
        "pool"
    ],
    "wof:name":"Stanton Hill Snooker Hall",
    "wof:placetype":"venue"
},
  "geometry": {"coordinates":[-1.2787729502,53.1413002014],"type":"Point"}
}