{
  "type": "Feature",
  "properties": {
    "addr:full":"196 Mount Vale York East Riding of Yorkshire YO2 2DL",
    "addr:housenumber":"196",
    "addr:postcode":"yo2 2dl",
    "addr:street":"Mount Vale",
    "iso:country":"GB",
    "sg:address":"196 Mount Vale",
    "sg:city":"York",
    "sg:classifiers":[
        {
            "category":"Social Services",
            "subcategory":"Retirement Home",
            "type":"Services"
        }
    ],
    "sg:phone":"+44 1904 647442",
    "sg:postcode":"YO2 2DL",
    "sg:province":"East Riding of Yorkshire",
    "sg:tags":[
        "residential",
        "care"
    ],
    "wof:name":"Mount Vale House",
    "wof:placetype":"venue"
},
  "geometry": {"coordinates":[-1.099278,53.949741],"type":"Point"}
}