{
  "type": "Feature",
  "properties": {
    "addr:full":"Office 5, 437 Shirley Road Birmingham West Midlands B27 7NX",
    "addr:housenumber":"5 437",
    "addr:postcode":"b27 7nx",
    "addr:street":"Shirley Road",
    "iso:country":"GB",
    "sg:address":"Office 5, 437 Shirley Road",
    "sg:city":"Birmingham",
    "sg:classifiers":[
        {
            "category":"Building & Trades",
            "subcategory":"Landscaping Services",
            "type":"Services"
        }
    ],
    "sg:phone":"+44 121 777 6695",
    "sg:postcode":"B27 7NX",
    "sg:province":"West Midlands",
    "sg:tags":[
        "designer",
        "architect",
        "landscape"
    ],
    "wof:name":"Environmental Design Group",
    "wof:placetype":"venue"
},
  "geometry": {"coordinates":[-1.83179,52.435783],"type":"Point"}
}