{
  "type": "Feature",
  "properties": {
    "addr:full":"12 Vigo Place, Aldridge Walsall Staffordshire WS9 8UG",
    "addr:housenumber":"12",
    "addr:postcode":"ws9 8ug",
    "addr:street":"Vigo Place",
    "iso:country":"GB",
    "sg:address":"12 Vigo Place, Aldridge",
    "sg:city":"Walsall",
    "sg:classifiers":[
        {
            "category":"Education",
            "subcategory":"Special Training",
            "type":"Public Place"
        }
    ],
    "sg:postcode":"WS9 8UG",
    "sg:province":"Staffordshire",
    "sg:tags":[
        "product",
        "centre"
    ],
    "wof:name":"In-Comm Business Services Ltd",
    "wof:placetype":"venue"
},
  "geometry": {"coordinates":[-1.925839,52.61182],"type":"Point"}
}