{
  "type": "Feature",
  "properties": {
    "addr:full":"17-19 Argyle Street London Greater London WC1H 8EJ",
    "addr:housenumber":"17-19",
    "addr:postcode":"wc1h 8ej",
    "addr:street":"Argyle Street",
    "iso:country":"GB",
    "sg:address":"17-19 Argyle Street",
    "sg:city":"London",
    "sg:classifiers":[
        {
            "category":"Travel",
            "subcategory":"Hotels & Motels",
            "type":"Entertainment"
        }
    ],
    "sg:phone":"+44 20 7837 9575",
    "sg:postcode":"WC1H 8EJ",
    "sg:province":"Greater London",
    "wof:name":"Alhambra Hotel Ltd.",
    "wof:placetype":"venue"
},
  "geometry": {"coordinates":[-0.123715,51.529427],"type":"Point"}
}