{
  "type": "Feature",
  "properties": {
    "iso:country":"GB",
    "sg:address":"8 Church St",
    "sg:city":"Southampton",
    "sg:classifiers":[
        {
            "category":"Bars & Pubs",
            "type":"Food & Drink"
        }
    ],
    "sg:postcode":"SO155LF",
    "sg:province":"Hampshire",
    "sg:tags":[
        "pubs",
        "inn"
    ],
    "wof:name":"Cowling,Mrs E,",
    "wof:placetype":"venue"
},
  "geometry": {"coordinates":[-1.432257,50.923187],"type":"Point"}
}