{
  "type": "Feature",
  "properties": {
    "addr:full":"36a The Kiosk, St Pirans Road Perranporth Cornwall TR6 0BJ",
    "addr:housenumber":"36a",
    "addr:postcode":"tr6 0bj",
    "addr:street":"Pirans Road",
    "iso:country":"GB",
    "sg:address":"36a The Kiosk, St Pirans Road",
    "sg:city":"Perranporth",
    "sg:classifiers":[
        {
            "category":"Shopping",
            "subcategory":"Comic Books",
            "type":"Retail Goods"
        }
    ],
    "sg:phone":"+44 1872 573584",
    "sg:postcode":"TR6 0BJ",
    "sg:province":"Cornwall",
    "sg:tags":[
        "jeweller"
    ],
    "wof:name":"Fiddlestix",
    "wof:placetype":"venue"
},
  "geometry": {"coordinates":[-5.1527957916,50.3451843262],"type":"Point"}
}