{
  "type": "Feature",
  "properties": {
    "iso:country":"GB",
    "sg:address":"50 Princes St",
    "sg:city":"Yeovil",
    "sg:classifiers":[
        {
            "category":"Wholesale",
            "subcategory":"Meat",
            "type":"Manufacturing & Wholesale Goods"
        }
    ],
    "sg:postcode":"BA20 1EQ",
    "sg:province":"Somerset",
    "sg:tags":[
        "product"
    ],
    "wof:name":"The Great Western & Pie Co",
    "wof:placetype":"venue"
},
  "geometry": {"coordinates":[-2.633537,50.942528],"type":"Point"}
}