{
  "type": "Feature",
  "properties": {
    "addr:full":", East Orchard Shaftesbury Dorset SP7 0LG",
    "addr:postcode":"sp7 0lg",
    "iso:country":"GB",
    "sg:address":", East Orchard",
    "sg:city":"Shaftesbury",
    "sg:classifiers":[
        {
            "category":"Building & Trades",
            "subcategory":"Landscaping Services",
            "type":"Services"
        }
    ],
    "sg:phone":"+44 1747 811213",
    "sg:postcode":"SP7 0LG",
    "sg:province":"Dorset",
    "sg:tags":[
        "horticultural"
    ],
    "wof:name":"Orchard Soils",
    "wof:placetype":"venue"
},
  "geometry": {"coordinates":[-2.1871240139,51.0057640076],"type":"Point"}
}