{
  "type": "Feature",
  "properties": {
    "addr:full":"Empire Way Gretna Cumbria DG16 5BN",
    "addr:postcode":"dg16 5bn",
    "addr:street":"Empire Way",
    "iso:country":"GB",
    "sg:address":"Empire Way",
    "sg:city":"Gretna",
    "sg:classifiers":[
        {
            "category":"Food & Beverages",
            "subcategory":"Supermarket",
            "type":"Retail Goods"
        }
    ],
    "sg:phone":"+44 1461 338117",
    "sg:postcode":"DG16 5BN",
    "sg:province":"Cumbria",
    "sg:tags":[
        "frozen"
    ],
    "wof:name":"Ancient Recipes Ltd.",
    "wof:placetype":"venue"
},
  "geometry": {"coordinates":[-3.062894,54.991562],"type":"Point"}
}