{
  "type": "Feature",
  "properties": {
    "iso:country":"GB",
    "sg:address":"41 Main Street, Menston",
    "sg:city":"Ilkley",
    "sg:classifiers":[
        {
            "category":"Food & Beverages",
            "subcategory":"Meat & Fish",
            "type":"Retail Goods"
        }
    ],
    "sg:postcode":"LS29 6NB",
    "sg:province":"North Yorkshire",
    "sg:tags":[
        "butcher"
    ],
    "wof:name":"B Jackson",
    "wof:placetype":"venue"
},
  "geometry": {"coordinates":[-1.744786,53.890923],"type":"Point"}
}