{
  "type": "Feature",
  "properties": {
    "addr:full":"17 Water Lane, Totton Southampton Hampshire SO40 3DG",
    "addr:housenumber":"17",
    "addr:postcode":"so40 3dg",
    "addr:street":"Water Lane",
    "iso:country":"GB",
    "sg:address":"17 Water Lane, Totton",
    "sg:city":"Southampton",
    "sg:classifiers":[
        {
            "category":"Health Services",
            "subcategory":"Optometrist",
            "type":"Services"
        }
    ],
    "sg:phone":"+44 23 8086 2456",
    "sg:postcode":"SO40 3DG",
    "sg:province":"Hampshire",
    "sg:tags":[
        "optician"
    ],
    "wof:name":"Leightons Opticians",
    "wof:placetype":"venue"
},
  "geometry": {"coordinates":[-1.491377,50.918522],"type":"Point"}
}