{
  "type": "Feature",
  "properties": {
    "addr:full":"Norfolk Street Sheffield South Yorkshire S1 2JB",
    "addr:postcode":"s1 2jb",
    "addr:street":"Norfolk Street",
    "iso:country":"GB",
    "sg:address":"Norfolk Street",
    "sg:city":"Sheffield",
    "sg:classifiers":[
        {
            "category":"Government",
            "subcategory":"City Hall",
            "type":"Public Place"
        },
        {
            "category":"Retail",
            "subcategory":"Event Space",
            "type":"Services"
        },
        {
            "category":"Organizations",
            "subcategory":"Non-profit Organization",
            "type":"Services"
        }
    ],
    "sg:phone":"+44 114 272 1749",
    "sg:postcode":"S1 2JB",
    "sg:province":"South Yorkshire",
    "sg:tags":[
        "function",
        "hire",
        "room",
        "organisation",
        "charity",
        "voluntary"
    ],
    "wof:name":"Victoria Hall Methodist Mission",
    "wof:placetype":"venue"
},
  "geometry": {"coordinates":[-1.4668689966,53.3815155029],"type":"Point"}
}