{
  "type": "Feature",
  "properties": {
    "addr:full":"30-32 The Concourse Skelmersdale Lancashire WN8 6LQ",
    "addr:housenumber":"30-32",
    "addr:postcode":"wn8 6lq",
    "addr:street":"The Concourse",
    "iso:country":"GB",
    "sg:address":"30-32 The Concourse",
    "sg:city":"Skelmersdale",
    "sg:classifiers":[
        {
            "category":"Sports & Exercise",
            "subcategory":"Sports Center",
            "type":"Entertainment"
        }
    ],
    "sg:phone":"+44 1695 559371",
    "sg:postcode":"WN8 6LQ",
    "sg:province":"Lancashire",
    "sg:tags":[
        "shop",
        "good"
    ],
    "wof:name":"J J B Sports Plc",
    "wof:placetype":"venue"
},
  "geometry": {"coordinates":[-2.7701659203,53.5566558838],"type":"Point"}
}