{
  "type": "Feature",
  "properties": {
    "addr:full":"Western Works, Sandwell Road, Staple Hill Bristol City of Bristol BS16 4NX",
    "addr:postcode":"bs16 4nx",
    "addr:street":"Sandwell Road",
    "iso:country":"GB",
    "sg:address":"Western Works, Sandwell Road, Staple Hill",
    "sg:city":"Bristol",
    "sg:classifiers":[
        {
            "category":"Professional",
            "subcategory":"Engineering",
            "type":"Services"
        }
    ],
    "sg:phone":"+44 117 956 7233",
    "sg:postcode":"BS16 4NX",
    "sg:province":"City of Bristol",
    "wof:name":"W D M (Road Services) Ltd.",
    "wof:placetype":"venue"
},
  "geometry": {"coordinates":[-2.591429,51.453667],"type":"Point"}
}