{
  "type": "Feature",
  "properties": {
    "addr:full":"Po Box 515 Livingston West Lothian EH54 7YF",
    "addr:housenumber":"po",
    "addr:postcode":"eh54 7yf",
    "addr:street":"Box 515",
    "iso:country":"GB",
    "sg:address":"Po Box 515",
    "sg:city":"Livingston",
    "sg:classifiers":[
        {
            "category":"Communications",
            "type":"Services"
        }
    ],
    "sg:phone":"+44 870 521 5215",
    "sg:postcode":"EH54 7YF",
    "sg:province":"West Lothian",
    "sg:tags":[
        "broadcasting"
    ],
    "wof:name":"The Racing Channel",
    "wof:placetype":"venue"
},
  "geometry": {"coordinates":[-3.538159,55.885818],"type":"Point"}
}