{
  "type": "Feature",
  "properties": {
    "addr:full":"Enterprise & Initiative Centre Stockton-on-tees Durham TS19 8RH",
    "addr:postcode":"ts19 8rh",
    "iso:country":"GB",
    "sg:address":"Enterprise & Initiative Centre",
    "sg:city":"Stockton-on-tees",
    "sg:classifiers":[
        {
            "category":"Education",
            "subcategory":"Special Training",
            "type":"Public Place"
        }
    ],
    "sg:phone":"+44 1642 677022",
    "sg:postcode":"TS19 8RH",
    "sg:province":"Durham",
    "sg:tags":[
        "product",
        "centre"
    ],
    "wof:name":"Hardwick in Partnership Ltd.",
    "wof:placetype":"venue"
},
  "geometry": {"coordinates":[-1.35233,54.582668],"type":"Point"}
}