{
  "type": "Feature",
  "properties": {
    "addr:full":"31 Moorgate Lancaster Lancashire LA1 3QF",
    "addr:housenumber":"31",
    "addr:postcode":"la1 3qf",
    "addr:street":"Moorgate",
    "iso:country":"GB",
    "sg:address":"31 Moorgate",
    "sg:city":"Lancaster",
    "sg:classifiers":[
        {
            "category":"Professional",
            "subcategory":"Business Services",
            "type":"Services"
        }
    ],
    "sg:phone":"+44 1524 848828",
    "sg:postcode":"LA1 3QF",
    "sg:province":"Lancashire",
    "sg:tags":[
        "bookmaker"
    ],
    "wof:name":"Moorgate Racing",
    "wof:placetype":"venue"
},
  "geometry": {"coordinates":[-2.79304,54.048431],"type":"Point"}
}