{
  "type": "Feature",
  "properties": {
    "iso:country":"GB",
    "sg:address":"Chapel La",
    "sg:city":"High Wycombe",
    "sg:classifiers":[
        {
            "category":"Autos & Motor Vehicles",
            "subcategory":"Fuel & Gas Station",
            "type":"Retail Goods"
        }
    ],
    "sg:phone":"+44 1494 751900",
    "sg:postcode":"HP12 4BY",
    "sg:province":"Buckinghamshire",
    "sg:tags":[
        "petrol",
        "filling"
    ],
    "wof:name":"Total Oil Filling Station",
    "wof:placetype":"venue"
},
  "geometry": {"coordinates":[-0.7829369903,51.6397972107],"type":"Point"}
}