{
  "type": "Feature",
  "properties": {
    "addr:full":"18 Amber St Batley West Yorkshire WF17 8HN",
    "addr:housenumber":"18",
    "addr:postcode":"wf17 8hn",
    "addr:street":"Amber St",
    "iso:country":"GB",
    "sg:address":"18 Amber St",
    "sg:city":"Batley",
    "sg:classifiers":[
        {
            "category":"Manufacturing",
            "subcategory":"Textiles",
            "type":"Manufacturing & Wholesale Goods"
        }
    ],
    "sg:postcode":"WF17 8HN",
    "sg:province":"West Yorkshire",
    "sg:tags":[
        "merchant",
        "agent"
    ],
    "wof:name":"Zimmerman,S, & Son",
    "wof:placetype":"venue"
},
  "geometry": {"coordinates":[-1.64613,53.721062],"type":"Point"}
}