{
  "type": "Feature",
  "properties": {
    "addr:full":"67 High Street, Collingtree Northampton Northamptonshire NN4 0NE",
    "addr:housenumber":"67",
    "addr:postcode":"nn4 0ne",
    "addr:street":"High Street",
    "iso:country":"GB",
    "sg:address":"67 High Street, Collingtree",
    "sg:city":"Northampton",
    "sg:classifiers":[
        {
            "category":"Government",
            "subcategory":"Post Office",
            "type":"Public Place"
        }
    ],
    "sg:postcode":"NN4 0NE",
    "sg:province":"Northamptonshire",
    "sg:tags":[
        "messenger",
        "courier"
    ],
    "wof:name":"Galaxy Couriers",
    "wof:placetype":"venue"
},
  "geometry": {"coordinates":[-0.9039360285,52.1917610168],"type":"Point"}
}