{
  "type": "Feature",
  "properties": {
    "addr:full":"247 Argyle Road, West Ealing London Greater London W13 0AY",
    "addr:housenumber":"247",
    "addr:postcode":"w13 0ay",
    "addr:street":"Argyle Road",
    "iso:country":"GB",
    "sg:address":"247 Argyle Road, West Ealing",
    "sg:city":"London",
    "sg:classifiers":[
        {
            "category":"Retail",
            "subcategory":"Repair Shop",
            "type":"Services"
        }
    ],
    "sg:phone":"+44 20 8998 4959",
    "sg:postcode":"W13 0AY",
    "sg:province":"Greater London",
    "sg:tags":[
        "radio",
        "television",
        "video"
    ],
    "wof:name":"All Day Tv Repairs",
    "wof:placetype":"venue"
},
  "geometry": {"coordinates":[-0.326789,51.528511],"type":"Point"}
}