{
  "type": "Feature",
  "properties": {
    "addr:full":"53 Spooners Dr St Albans Hertfordshire AL2 2HS",
    "addr:housenumber":"53",
    "addr:postcode":"al2 2hs",
    "addr:street":"Spooners Dr",
    "iso:country":"GB",
    "sg:address":"53 Spooners Dr",
    "sg:city":"St Albans",
    "sg:classifiers":[
        {
            "category":"Shopping",
            "subcategory":"Gifts & Souvenirs",
            "type":"Retail Goods"
        }
    ],
    "sg:phone":"+44 1727 874080",
    "sg:postcode":"AL2 2HS",
    "sg:province":"Hertfordshire",
    "sg:tags":[
        "ducting"
    ],
    "wof:name":"Enviroair",
    "wof:placetype":"venue"
},
  "geometry": {"coordinates":[-0.3486259878,51.7190437317],"type":"Point"}
}