{
  "type": "Feature",
  "properties": {
    "addr:full":"86 Brookside Road London Greater London NW11 9NG",
    "addr:housenumber":"86",
    "addr:postcode":"nw11 9ng",
    "addr:street":"Brookside Road",
    "iso:country":"GB",
    "sg:address":"86 Brookside Road",
    "sg:city":"London",
    "sg:classifiers":[
        {
            "category":"Professional",
            "subcategory":"Management & Consulting",
            "type":"Services"
        }
    ],
    "sg:postcode":"NW11 9NG",
    "sg:province":"Greater London",
    "sg:tags":[
        "consultant",
        "geophysical",
        "geological"
    ],
    "wof:name":"Gtech",
    "wof:placetype":"venue"
},
  "geometry": {"coordinates":[-0.205769,51.579758],"type":"Point"}
}