{
  "type": "Feature",
  "properties": {
    "iso:country":"GB",
    "sg:address":"64 Church Rd",
    "sg:city":"Southampton",
    "sg:classifiers":[
        {
            "category":"Professional",
            "subcategory":"Printing & Photocopies",
            "type":"Services"
        }
    ],
    "sg:phone":"+44 1489 576308",
    "sg:postcode":"SO31 6LQ",
    "sg:province":"Hampshire",
    "sg:tags":[
        "printer"
    ],
    "wof:name":"Computone Services",
    "wof:placetype":"venue"
},
  "geometry": {"coordinates":[-1.269451,50.862827],"type":"Point"}
}