{
  "type": "Feature",
  "properties": {
    "addr:full":"The Square, Ballater Rd Aboyne Aberdeenshire AB34 5HT",
    "addr:postcode":"ab34 5ht",
    "addr:street":"The Square Ballater Rd",
    "iso:country":"GB",
    "sg:address":"The Square, Ballater Rd",
    "sg:city":"Aboyne",
    "sg:classifiers":[
        {
            "category":"Restaurant",
            "type":"Food & Drink"
        }
    ],
    "sg:phone":"+44 1339 886664",
    "sg:postcode":"AB34 5HT",
    "sg:province":"Aberdeenshire",
    "wof:name":"The Sheperd Restaurant",
    "wof:placetype":"venue"
},
  "geometry": {"coordinates":[-2.7800590992,57.0761795044],"type":"Point"}
}