{
  "type": "Feature",
  "properties": {
    "addr:full":"547 Darwen Road, Egerton Bolton Lancashire BL7 9ED",
    "addr:housenumber":"547",
    "addr:postcode":"bl7 9ed",
    "addr:street":"Darwen Road",
    "iso:country":"GB",
    "sg:address":"547 Darwen Road, Egerton",
    "sg:city":"Bolton",
    "sg:classifiers":[
        {
            "category":"Bars & Pubs",
            "type":"Food & Drink"
        }
    ],
    "sg:phone":"+44 1204 597461",
    "sg:postcode":"BL7 9ED",
    "sg:province":"Lancashire",
    "sg:tags":[
        "pubs",
        "inn"
    ],
    "wof:name":"The Dunscar Arms",
    "wof:placetype":"venue"
},
  "geometry": {"coordinates":[-2.432309,53.620773],"type":"Point"}
}