{
  "type": "Feature",
  "properties": {
    "iso:country":"GB",
    "sg:address":"40 Willow Crescent West, New Denham",
    "sg:city":"Uxbridge",
    "sg:classifiers":[
        {
            "category":"Building & Trades",
            "subcategory":"Construction",
            "type":"Services"
        }
    ],
    "sg:postcode":"UB9 4AT",
    "sg:province":"Buckinghamshire",
    "sg:tags":[
        "decorator",
        "painter"
    ],
    "wof:name":"A B Decorating",
    "wof:placetype":"venue"
},
  "geometry": {"coordinates":[-0.4855780005,51.5563087463],"type":"Point"}
}