{
  "type": "Feature",
  "properties": {
    "addr:full":"3 Broomehouse Av Manchester Greater Manchester M44 5FT",
    "addr:housenumber":"3",
    "addr:postcode":"m44 5ft",
    "addr:street":"Av Manchester",
    "iso:country":"GB",
    "sg:address":"3 Broomehouse Av",
    "sg:city":"Manchester",
    "sg:classifiers":[
        {
            "category":"Building & Trades",
            "subcategory":"Landscaping Services",
            "type":"Services"
        }
    ],
    "sg:phone":"+44 161 777 9377",
    "sg:postcode":"M44 5FT",
    "sg:province":"Greater Manchester",
    "sg:tags":[
        "landscape",
        "contractor"
    ],
    "wof:name":"P J Todd",
    "wof:placetype":"venue"
},
  "geometry": {"coordinates":[-2.431896,53.439617],"type":"Point"}
}