{
  "type": "Feature",
  "properties": {
    "iso:country":"GB",
    "sg:address":"143 Weston Road",
    "sg:city":"Guildford",
    "sg:classifiers":[
        {
            "category":"Professional",
            "type":"Services"
        }
    ],
    "sg:postcode":"GU2 8AN",
    "sg:province":"Surrey",
    "sg:tags":[
        "caterer"
    ],
    "wof:name":"The Garden Kitchen",
    "wof:placetype":"venue"
},
  "geometry": {"coordinates":[-0.5931299925,51.2478370667],"type":"Point"}
}