{
  "type": "Feature",
  "properties": {
    "iso:country":"GB",
    "sg:address":"Quebec Street",
    "sg:city":"Ulverston",
    "sg:classifiers":[
        {
            "category":"Autos & Motor Vehicles",
            "subcategory":"Automobile Sales",
            "type":"Retail Goods"
        }
    ],
    "sg:phone":"+44 1229 583082",
    "sg:postcode":"LA12 9AB",
    "sg:province":"Cumbria",
    "sg:tags":[
        "commercial"
    ],
    "wof:name":"Daniel Lowther",
    "wof:placetype":"venue"
},
  "geometry": {"coordinates":[-3.0875439644,54.1961860657],"type":"Point"}
}