{
  "type": "Feature",
  "properties": {
    "iso:country":"GB",
    "sg:address":"Wayside, Albion St, South Hilton",
    "sg:city":"Sunderland",
    "sg:classifiers":[
        {
            "category":"Shopping",
            "subcategory":"Musical Instruments",
            "type":"Retail Goods"
        }
    ],
    "sg:phone":"+44 191 534 4957",
    "sg:postcode":"SR4 0NF",
    "sg:province":"Tyne and Wear",
    "wof:name":"Vincent Organs (Sunderland)",
    "wof:placetype":"venue"
},
  "geometry": {"coordinates":[-1.4532099962,54.9049682617],"type":"Point"}
}