{
  "type": "Feature",
  "properties": {
    "addr:full":"81-83 High Street West Wallsend Tyne and Wear NE28 8JD",
    "addr:housenumber":"81-83",
    "addr:postcode":"ne28 8jd",
    "addr:street":"High Street",
    "iso:country":"GB",
    "sg:address":"81-83 High Street West",
    "sg:city":"Wallsend",
    "sg:classifiers":[
        {
            "category":"Home & Garden",
            "subcategory":"Home Furnishings",
            "type":"Retail Goods"
        }
    ],
    "sg:phone":"+44 191 263 0633",
    "sg:postcode":"NE28 8JD",
    "sg:province":"Tyne and Wear",
    "sg:tags":[
        "beds",
        "bedding",
        "blanket"
    ],
    "wof:name":"Forty Winks Beds",
    "wof:placetype":"venue"
},
  "geometry": {"coordinates":[-1.5365250111,54.9907264709],"type":"Point"}
}