{
  "type": "Feature",
  "properties": {
    "iso:country":"GB",
    "sg:address":"14 Mallard Drive, Burton Latimer",
    "sg:city":"Kettering",
    "sg:classifiers":[
        {
            "category":"Professional",
            "subcategory":"Lawyer & Legal Services",
            "type":"Services"
        }
    ],
    "sg:phone":"+44 7703 332374",
    "sg:postcode":"NN15 5TG",
    "sg:province":"Northamptonshire",
    "sg:tags":[
        "writing"
    ],
    "wof:name":"Clements & Co.",
    "wof:placetype":"venue"
},
  "geometry": {"coordinates":[-0.692892,52.363029],"type":"Point"}
}