{
  "type": "Feature",
  "properties": {
    "addr:full":"110 Whitby Way Darlington Durham DL3 9UH",
    "addr:housenumber":"110",
    "addr:postcode":"dl3 9uh",
    "addr:street":"Whitby Way",
    "iso:country":"GB",
    "sg:address":"110 Whitby Way",
    "sg:city":"Darlington",
    "sg:classifiers":[
        {
            "category":"Fast Food",
            "type":"Food & Drink"
        }
    ],
    "sg:postcode":"DL3 9UH",
    "sg:province":"Durham",
    "sg:tags":[
        "away",
        "take"
    ],
    "wof:name":"Pizza Planet",
    "wof:placetype":"venue"
},
  "geometry": {"coordinates":[-1.5972180367,54.5401992798],"type":"Point"}
}