{
  "type": "Feature",
  "properties": {
    "iso:country":"GB",
    "sg:address":"10 Millbrook Close, St James Business Park",
    "sg:city":"Northampton",
    "sg:classifiers":[
        {
            "category":"Autos & Motor Vehicles",
            "subcategory":"Auto Supplies",
            "type":"Retail Goods"
        }
    ],
    "sg:postcode":"NN5 5JF",
    "sg:province":"Northamptonshire",
    "sg:tags":[
        "windscreen"
    ],
    "wof:name":"Silver Shield Windscreens",
    "wof:placetype":"venue"
},
  "geometry": {"coordinates":[-0.9176530242,52.2331199646],"type":"Point"}
}