{
  "type": "Feature",
  "properties": {
    "iso:country":"GB",
    "sg:address":"Ryeflat Farm, Cleghorn",
    "sg:city":"Lanark",
    "sg:classifiers":[
        {
            "category":"Farming",
            "subcategory":"Livestock Farm",
            "type":"Manufacturing & Wholesale Goods"
        }
    ],
    "sg:phone":"+44 1555 870216",
    "sg:postcode":"ML11 8NT",
    "sg:province":"South Lanarkshire",
    "sg:tags":[
        "others"
    ],
    "wof:name":"Thomas R Walker",
    "wof:placetype":"venue"
},
  "geometry": {"coordinates":[-3.677495,55.716637],"type":"Point"}
}