{
  "type": "Feature",
  "properties": {
    "iso:country":"GB",
    "sg:address":"8 High Street",
    "sg:city":"Oban",
    "sg:classifiers":[
        {
            "category":"Professional",
            "subcategory":"Accounting & Tax Preparation",
            "type":"Services"
        }
    ],
    "sg:phone":"+44 1631 566822",
    "sg:postcode":"PA34 4BG",
    "sg:province":"Argyll and Bute",
    "sg:tags":[
        "accountant",
        "bookkeeping",
        "primarily",
        "activity"
    ],
    "wof:name":"Abacus Book Keeping Services",
    "wof:placetype":"venue"
},
  "geometry": {"coordinates":[-5.471847,56.41177],"type":"Point"}
}