{
  "type": "Feature",
  "properties": {
    "iso:country":"GB",
    "sg:address":"Wakefield Rd, Netherton",
    "sg:city":"Liverpool",
    "sg:classifiers":[
        {
            "category":"Shopping",
            "subcategory":"Discount & Variety Stores",
            "type":"Retail Goods"
        }
    ],
    "sg:phone":"+44 151 525 3525",
    "sg:postcode":"L30 6TP",
    "sg:province":"Merseyside",
    "sg:tags":[
        "cleaning",
        "supply"
    ],
    "wof:name":"E J S Steam Cleaners Ltd",
    "wof:placetype":"venue"
},
  "geometry": {"coordinates":[-2.96467,53.48288],"type":"Point"}
}