{
  "type": "Feature",
  "properties": {
    "iso:country":"GB",
    "sg:address":"25 Manor Road",
    "sg:city":"Brackley",
    "sg:classifiers":[
        {
            "category":"Professional",
            "subcategory":"Testing Lab",
            "type":"Services"
        }
    ],
    "sg:postcode":"NN13 6ED",
    "sg:province":"Buckinghamshire",
    "sg:tags":[
        "mot"
    ],
    "wof:name":"Bird & Eagle",
    "wof:placetype":"venue"
},
  "geometry": {"coordinates":[-1.148985,52.02977],"type":"Point"}
}