{
  "type": "Feature",
  "properties": {
    "iso:country":"GB",
    "sg:address":"68 Valeside Gardens, Colwick",
    "sg:city":"Nottingham",
    "sg:classifiers":[
        {
            "category":"Building & Trades",
            "subcategory":"Landscaping Services",
            "type":"Services"
        }
    ],
    "sg:phone":"+44 115 987 3618",
    "sg:postcode":"NG4 2EP",
    "sg:province":"Nottinghamshire",
    "sg:tags":[
        "gardening"
    ],
    "wof:name":"Complete Garden Maintenance",
    "wof:placetype":"venue"
},
  "geometry": {"coordinates":[-1.0868430138,52.957118988],"type":"Point"}
}