{
  "type": "Feature",
  "properties": {
    "iso:country":"GB",
    "sg:address":"Port Rd",
    "sg:city":"Northampton",
    "sg:classifiers":[
        {
            "category":"Social Services",
            "type":"Services"
        }
    ],
    "sg:phone":"+44 1604 757778",
    "sg:postcode":"NN5 6NS",
    "sg:province":"Northamptonshire",
    "wof:name":"Quarry House",
    "wof:placetype":"venue"
},
  "geometry": {"coordinates":[-0.960904,52.260941],"type":"Point"}
}