{
  "type": "Feature",
  "properties": {
    "iso:country":"GB",
    "sg:address":"15 Gertrude St",
    "sg:city":"West Brompton",
    "sg:classifiers":[
        {
            "category":"Organizations",
            "subcategory":"Non-profit Organization",
            "type":"Services"
        }
    ],
    "sg:phone":"+44 20 7376 4668",
    "sg:postcode":"SW10 0JN",
    "sg:province":"Greater London",
    "sg:tags":[
        "organisation",
        "voluntary",
        "charity"
    ],
    "wof:name":"Smart Projects",
    "wof:placetype":"venue"
},
  "geometry": {"coordinates":[-0.180975005,51.4835014343],"type":"Point"}
}