{
  "type": "Feature",
  "properties": {
    "addr:full":"Units 12/13 Churchfield Court, Bewcastle Road, Top Valley Nottingham Nottinghamshire NG5 9JL",
    "addr:housenumber":"units 12 / 13",
    "addr:postcode":"ng5 9jl",
    "addr:street":"Churchfield Court Bewcastle Road",
    "iso:country":"GB",
    "sg:address":"Units 12/13 Churchfield Court, Bewcastle Road, Top Valley",
    "sg:city":"Nottingham",
    "sg:classifiers":[
        {
            "category":"Sports & Exercise",
            "subcategory":"Playing Field",
            "type":"Entertainment"
        }
    ],
    "sg:phone":"+44 115 840 2722",
    "sg:postcode":"NG5 9JL",
    "sg:province":"Nottinghamshire",
    "sg:tags":[
        "transmission",
        "power"
    ],
    "wof:name":"W T S Donnington Ltd.",
    "wof:placetype":"venue"
},
  "geometry": {"coordinates":[-1.1598199606,53.0096282959],"type":"Point"}
}