{
  "type": "Feature",
  "properties": {
    "iso:country":"GB",
    "sg:address":"41-43 Sheep Street",
    "sg:city":"Northampton",
    "sg:classifiers":[
        {
            "category":"Insurance",
            "subcategory":"Insurance Agent",
            "type":"Services"
        }
    ],
    "sg:phone":"+44 1604 627911",
    "sg:postcode":"NN1 2NE",
    "sg:province":"Northamptonshire",
    "sg:tags":[
        "broker"
    ],
    "wof:name":"Hammon Osborne Ltd.",
    "wof:placetype":"venue"
},
  "geometry": {"coordinates":[-0.898173,52.24028],"type":"Point"}
}