{
  "type": "Feature",
  "properties": {
    "addr:full":"28 Clifton Hill London Greater London NW8 0QG",
    "addr:housenumber":"28",
    "addr:postcode":"nw8 0qg",
    "addr:street":"Clifton Hill",
    "iso:country":"GB",
    "sg:address":"28 Clifton Hill",
    "sg:city":"London",
    "sg:classifiers":[
        {
            "category":"Professional",
            "subcategory":"Engineering",
            "type":"Services"
        }
    ],
    "sg:phone":"+44 20 8740 0555",
    "sg:postcode":"NW8 0QG",
    "sg:province":"Greater London",
    "sg:tags":[
        "design",
        "engineer"
    ],
    "wof:name":"Hyjoin Ltd.",
    "wof:placetype":"venue"
},
  "geometry": {"coordinates":[-0.1807370037,51.537815094],"type":"Point"}
}