{
  "type": "Feature",
  "properties": {
    "addr:full":"30 Abbey St Rhyl Conwy LL18 1NY",
    "addr:housenumber":"30",
    "addr:postcode":"ll18 1ny",
    "addr:street":"Abbey St",
    "iso:country":"GB",
    "sg:address":"30 Abbey St",
    "sg:city":"Rhyl",
    "sg:classifiers":[
        {
            "category":"Building & Trades",
            "subcategory":"Construction",
            "type":"Services"
        }
    ],
    "sg:phone":"+44 1745 332865",
    "sg:postcode":"LL18 1NY",
    "sg:province":"Conwy",
    "sg:tags":[
        "builder"
    ],
    "wof:name":"Builders Act",
    "wof:placetype":"venue"
},
  "geometry": {"coordinates":[-3.495614,53.319153],"type":"Point"}
}