{
  "type": "Feature",
  "properties": {
    "iso:country":"GB",
    "sg:address":"Howells Road",
    "sg:city":"Swansea",
    "sg:classifiers":[
        {
            "category":"Retail",
            "subcategory":"Auto Repair",
            "type":"Services"
        }
    ],
    "sg:postcode":"SA2 7SX",
    "sg:province":"Swansea",
    "sg:tags":[
        "modification",
        "garage"
    ],
    "wof:name":"Andy Davey Motor Services",
    "wof:placetype":"venue"
},
  "geometry": {"coordinates":[-4.031336,51.623707],"type":"Point"}
}