{
  "type": "Feature",
  "properties": {
    "addr:full":"Green Lane, Venture Centre, Walsall Road Cannock Staffordshire WS11 3JJ",
    "addr:postcode":"ws11 3jj",
    "addr:street":"Green Lane;Walsall Road",
    "iso:country":"GB",
    "sg:address":"Green Lane, Venture Centre, Walsall Road",
    "sg:city":"Cannock",
    "sg:classifiers":[
        {
            "category":"Home & Garden",
            "subcategory":"Furniture",
            "type":"Retail Goods"
        },
        {
            "category":"Home & Garden",
            "subcategory":"Carpets & Floor Coverings",
            "type":"Retail Goods"
        }
    ],
    "sg:phone":"+44 1543 506961",
    "sg:postcode":"WS11 3JJ",
    "sg:province":"Staffordshire",
    "sg:tags":[
        "rug",
        "matting",
        "carpets"
    ],
    "wof:name":"Orbitstore Ltd.",
    "wof:placetype":"venue"
},
  "geometry": {"coordinates":[-2.0241239071,52.6757698059],"type":"Point"}
}