{
  "type": "Feature",
  "properties": {
    "addr:full":"19 Radleigh Gardens, Totton Southampton Hampshire SO40 8XS",
    "addr:housenumber":"19",
    "addr:postcode":"so40 8xs",
    "addr:street":"Radleigh Gardens",
    "iso:country":"GB",
    "sg:address":"19 Radleigh Gardens, Totton",
    "sg:city":"Southampton",
    "sg:classifiers":[
        {
            "category":"Real Estate",
            "subcategory":"Surveying",
            "type":"Services"
        }
    ],
    "sg:postcode":"SO40 8XS",
    "sg:province":"Hampshire",
    "sg:tags":[
        "surveyor",
        "quantity"
    ],
    "wof:name":"A B Surveying Ltd.",
    "wof:placetype":"venue"
},
  "geometry": {"coordinates":[-1.5191990137,50.9237174988],"type":"Point"}
}