{
  "type": "Feature",
  "properties": {
    "addr:full":"Chapel Street, Wincham Northwich Cheshire CW9 6DA",
    "addr:postcode":"cw9 6da",
    "addr:street":"Chapel Street",
    "iso:country":"GB",
    "sg:address":"Chapel Street, Wincham",
    "sg:city":"Northwich",
    "sg:classifiers":[
        {
            "category":"Manufacturing",
            "subcategory":"Buildings",
            "type":"Manufacturing & Wholesale Goods"
        },
        {
            "category":"Social Services",
            "subcategory":"Adult Care",
            "type":"Services"
        }
    ],
    "sg:phone":"+44 1606 41512",
    "sg:postcode":"CW9 6DA",
    "sg:province":"Cheshire",
    "sg:tags":[
        "mobile",
        "home",
        "housing",
        "sheltered"
    ],
    "wof:name":"Ashwood Park",
    "wof:placetype":"venue"
},
  "geometry": {"coordinates":[-2.4903850555,53.2728309631],"type":"Point"}
}