{
  "type": "Feature",
  "properties": {
    "addr:full":"Unit 6, Dawkins Road Poole Dorset BH15 4JY",
    "addr:housenumber":"unit 6",
    "addr:postcode":"bh15 4jy",
    "addr:street":"Dawkins Road",
    "iso:country":"GB",
    "sg:address":"Unit 6, Dawkins Road",
    "sg:city":"Poole",
    "sg:classifiers":[
        {
            "category":"Home & Garden",
            "subcategory":"Carpets & Floor Coverings",
            "type":"Retail Goods"
        }
    ],
    "sg:phone":"+44 1202 674671",
    "sg:postcode":"BH15 4JY",
    "sg:province":"Dorset",
    "sg:tags":[
        "rubber",
        "plastic"
    ],
    "wof:name":"D P Seals Ltd.",
    "wof:placetype":"venue"
},
  "geometry": {"coordinates":[-2.0148539543,50.7235984802],"type":"Point"}
}