{
  "type": "Feature",
  "properties": {
    "addr:full":"Esdaile Lane Hoddesdon Essex EN11 8DS",
    "addr:postcode":"en11 8ds",
    "addr:street":"Esdaile Lane",
    "iso:country":"GB",
    "sg:address":"Esdaile Lane",
    "sg:city":"Hoddesdon",
    "sg:classifiers":[
        {
            "category":"Place Of Worship",
            "type":"Public Place"
        }
    ],
    "sg:phone":"+44 1992 440986",
    "sg:postcode":"EN11 8DS",
    "sg:province":"Essex",
    "wof:name":"St. Augustines Catholic Church",
    "wof:placetype":"venue"
},
  "geometry": {"coordinates":[-0.0100090001,51.7582359314],"type":"Point"}
}