{
  "type": "Feature",
  "properties": {
    "addr:full":"Suite 5 Kelvin House, Kelvin Way Crawley Surrey RH10 9WE",
    "addr:housenumber":"suite 5 kelvin house",
    "addr:postcode":"rh10 9we",
    "addr:street":"Kelvin Way",
    "iso:country":"GB",
    "sg:address":"Suite 5 Kelvin House, Kelvin Way",
    "sg:city":"Crawley",
    "sg:classifiers":[
        {
            "category":"Manufacturing",
            "subcategory":"Tools & Machinery",
            "type":"Manufacturing & Wholesale Goods"
        }
    ],
    "sg:phone":"+44 1293 524253",
    "sg:postcode":"RH10 9WE",
    "sg:province":"Surrey",
    "sg:tags":[
        "society",
        "friendly"
    ],
    "wof:name":"Crawford & Co. Risk Services Investments",
    "wof:placetype":"venue"
},
  "geometry": {"coordinates":[-0.1761389971,51.1321487427],"type":"Point"}
}