{
  "type": "Feature",
  "properties": {
    "iso:country":"GB",
    "sg:address":"Bridge Farm, Hospital Bridge Rd, Whitton",
    "sg:city":"Twickenham",
    "sg:classifiers":[
        {
            "category":"Communications",
            "subcategory":"Film & Video Production",
            "type":"Services"
        }
    ],
    "sg:phone":"+44 20 8893 8992",
    "sg:postcode":"TW2 6LH",
    "sg:province":"Greater London",
    "sg:tags":[
        "tv",
        "studio"
    ],
    "wof:name":"Greenery Ltd",
    "wof:placetype":"venue"
},
  "geometry": {"coordinates":[-0.3667989969,51.4496917725],"type":"Point"}
}