{
  "type": "Feature",
  "properties": {
    "addr:full":"18 Kingsbere Avenue Bournemouth Dorset BH10 4DL",
    "addr:housenumber":"18",
    "addr:postcode":"bh10 4dl",
    "addr:street":"Kingsbere Avenue",
    "iso:country":"GB",
    "sg:address":"18 Kingsbere Avenue",
    "sg:city":"Bournemouth",
    "sg:classifiers":[
        {
            "category":"Real Estate",
            "subcategory":"Surveying",
            "type":"Services"
        },
        {
            "category":"Building & Trades",
            "subcategory":"Construction",
            "type":"Services"
        }
    ],
    "sg:phone":"+44 1202 524020",
    "sg:postcode":"BH10 4DL",
    "sg:province":"Dorset",
    "sg:tags":[
        "surveyor",
        "builder",
        "valuer"
    ],
    "wof:name":"Roger Sharland",
    "wof:placetype":"venue"
},
  "geometry": {"coordinates":[-1.903683,50.750977],"type":"Point"}
}