{
  "type": "Feature",
  "properties": {
    "addr:full":"85 High Road, Ickenham Uxbridge Greater London UB10 8LH",
    "addr:housenumber":"85",
    "addr:postcode":"ub10 8lh",
    "addr:street":"High Road",
    "iso:country":"GB",
    "sg:address":"85 High Road, Ickenham",
    "sg:city":"Uxbridge",
    "sg:classifiers":[
        {
            "category":"Shopping",
            "subcategory":"News",
            "type":"Retail Goods"
        }
    ],
    "sg:phone":"+44 1895 639566",
    "sg:postcode":"UB10 8LH",
    "sg:province":"Greater London",
    "sg:tags":[
        "newsagent"
    ],
    "wof:name":"Ickenham News General Store & Off Licence",
    "wof:placetype":"venue"
},
  "geometry": {"coordinates":[-0.465983,51.562641],"type":"Point"}
}