{
  "type": "Feature",
  "properties": {
    "addr:full":"27 Clerkenwell Close London Greater London EC1R 0AT",
    "addr:housenumber":"27",
    "addr:postcode":"ec1r 0at",
    "addr:street":"Clerkenwell Close",
    "iso:country":"GB",
    "sg:address":"27 Clerkenwell Close",
    "sg:city":"London",
    "sg:classifiers":[
        {
            "category":"Retail",
            "subcategory":"Repair Shop",
            "type":"Services"
        }
    ],
    "sg:phone":"+44 20 7608 2528",
    "sg:postcode":"EC1R 0AT",
    "sg:province":"Greater London",
    "sg:tags":[
        "clocks",
        "watch"
    ],
    "wof:name":"P W Constable Watch & Clock Repairs",
    "wof:placetype":"venue"
},
  "geometry": {"coordinates":[-0.106428,51.524197],"type":"Point"}
}