{
  "type": "Feature",
  "properties": {
    "iso:country":"GB",
    "sg:address":"Eightlands Road",
    "sg:city":"Dewsbury",
    "sg:classifiers":[
        {
            "category":"Retail",
            "subcategory":"Auto Repair",
            "type":"Services"
        }
    ],
    "sg:postcode":"WF13 2PF",
    "sg:province":"West Yorkshire",
    "sg:tags":[
        "modification",
        "garage"
    ],
    "wof:name":"M B Auto Services",
    "wof:placetype":"venue"
},
  "geometry": {"coordinates":[-1.633419,53.692966],"type":"Point"}
}