{
  "type": "Feature",
  "properties": {
    "iso:country":"GB",
    "sg:address":"Nevin The St, Ryarsh",
    "sg:city":"West Malling",
    "sg:classifiers":[
        {
            "category":"Real Estate",
            "subcategory":"Real Estate Agent",
            "type":"Services"
        }
    ],
    "sg:phone":"+44 1732 875580",
    "sg:postcode":"ME19 6QL",
    "sg:province":"Kent",
    "wof:name":"Wyvern Associats",
    "wof:placetype":"venue"
},
  "geometry": {"coordinates":[0.41294,51.293709],"type":"Point"}
}