{
  "type": "Feature",
  "properties": {
    "addr:full":"134a Eaton Road, Brynhyfryd Swansea Swansea SA5 9JU",
    "addr:housenumber":"134a",
    "addr:postcode":"sa5 9ju",
    "addr:street":"Eaton Road Brynhyfryd",
    "iso:country":"GB",
    "sg:address":"134a Eaton Road, Brynhyfryd",
    "sg:city":"Swansea",
    "sg:classifiers":[
        {
            "category":"Bus Charters",
            "type":"Transportation"
        }
    ],
    "sg:phone":"+44 1792 460183",
    "sg:postcode":"SA5 9JU",
    "sg:province":"Swansea",
    "sg:tags":[
        "hire",
        "coach"
    ],
    "wof:name":"Cliff Weaver Coaches & Mini Coaches",
    "wof:placetype":"venue"
},
  "geometry": {"coordinates":[-3.9458920956,51.6410331726],"type":"Point"}
}