{
  "type": "Feature",
  "properties": {
    "addr:full":"134 Baker Street London Greater London W1U 6UA",
    "addr:housenumber":"134",
    "addr:postcode":"w1u 6ua",
    "addr:street":"Baker Street",
    "iso:country":"GB",
    "sg:address":"134 Baker Street",
    "sg:city":"London",
    "sg:classifiers":[
        {
            "category":"Retail",
            "subcategory":"Repair Shop",
            "type":"Services"
        }
    ],
    "sg:phone":"+44 20 7486 2526",
    "sg:postcode":"W1U 6UA",
    "sg:province":"Greater London",
    "sg:tags":[
        "radio",
        "television",
        "video"
    ],
    "wof:name":"Sondos Photo Vision Ltd.",
    "wof:placetype":"venue"
},
  "geometry": {"coordinates":[-0.157216,51.521946],"type":"Point"}
}