{
  "type": "Feature",
  "properties": {
    "addr:full":"276 Alcester Road South Birmingham West Midlands B14 6EN",
    "addr:housenumber":"276",
    "addr:postcode":"b14 6en",
    "addr:street":"Alcester Road South",
    "iso:country":"GB",
    "sg:address":"276 Alcester Road South",
    "sg:city":"Birmingham",
    "sg:classifiers":[
        {
            "category":"Home & Garden",
            "subcategory":"Hardware",
            "type":"Retail Goods"
        }
    ],
    "sg:phone":"+44 121 443 3846",
    "sg:postcode":"B14 6EN",
    "sg:province":"West Midlands",
    "sg:tags":[
        "retailer",
        "diy"
    ],
    "wof:name":"Kingsheath",
    "wof:placetype":"venue"
},
  "geometry": {"coordinates":[-1.892109,52.421711],"type":"Point"}
}