{
  "type": "Feature",
  "properties": {
    "addr:full":"5 The Market Place Blackwood Caerphilly NP12 1AU",
    "addr:housenumber":"5",
    "addr:postcode":"np12 1au",
    "addr:street":"The Market Place",
    "iso:country":"GB",
    "sg:address":"5 The Market Place",
    "sg:city":"Blackwood",
    "sg:classifiers":[
        {
            "category":"Shopping",
            "subcategory":"Gifts & Souvenirs",
            "type":"Retail Goods"
        }
    ],
    "sg:postcode":"NP12 1AU",
    "sg:province":"Caerphilly",
    "sg:tags":[
        "poster",
        "card"
    ],
    "wof:name":"Card Scene",
    "wof:placetype":"venue"
},
  "geometry": {"coordinates":[-3.1956140995,51.6672744751],"type":"Point"}
}