{
  "type": "Feature",
  "properties": {
    "addr:full":"Pear Tree Cottage, Old Wells Rd Glastonbury Somerset BA6 8ED",
    "addr:postcode":"ba6 8ed",
    "addr:street":"Old Wells Rd",
    "iso:country":"GB",
    "sg:address":"Pear Tree Cottage, Old Wells Rd",
    "sg:city":"Glastonbury",
    "sg:classifiers":[
        {
            "category":"Retail",
            "subcategory":"Laundry & Dry Cleaning",
            "type":"Services"
        }
    ],
    "sg:postcode":"BA6 8ED",
    "sg:province":"Somerset",
    "sg:tags":[
        "alteration"
    ],
    "wof:name":"Stacey,Jackie,",
    "wof:placetype":"venue"
},
  "geometry": {"coordinates":[-2.717009,51.147591],"type":"Point"}
}