{
  "type": "Feature",
  "properties": {
    "iso:country":"GB",
    "sg:address":"24 Linthurst Newtown, Blackwell",
    "sg:city":"Bromsgrove",
    "sg:classifiers":[
        {
            "category":"Home & Garden",
            "subcategory":"Household Appliances",
            "type":"Retail Goods"
        }
    ],
    "sg:postcode":"B60 1BP",
    "sg:province":"Worcestershire",
    "sg:tags":[
        "electrical"
    ],
    "wof:name":"J W Electrical",
    "wof:placetype":"venue"
},
  "geometry": {"coordinates":[-2.0123679638,52.3493156433],"type":"Point"}
}