{
  "type": "Feature",
  "properties": {
    "addr:full":"Unit 8a, Broom Enterprise Centre, Broom Terrace Hartlepool Durham TS24 8EY",
    "addr:housenumber":"unit 8a broom enterprise centre",
    "addr:postcode":"ts24 8ey",
    "addr:street":"Broom Terrace",
    "iso:country":"GB",
    "sg:address":"Unit 8a, Broom Enterprise Centre, Broom Terrace",
    "sg:city":"Hartlepool",
    "sg:classifiers":[
        {
            "category":"Professional",
            "subcategory":"Management & Consulting",
            "type":"Services"
        }
    ],
    "sg:phone":"+44 1429 862083",
    "sg:postcode":"TS24 8EY",
    "sg:province":"Durham",
    "sg:tags":[
        "consultant",
        "training"
    ],
    "wof:name":"The Elwick Consultancy",
    "wof:placetype":"venue"
},
  "geometry": {"coordinates":[-1.214119,54.685406],"type":"Point"}
}