{
  "type": "Feature",
  "properties": {
    "iso:country":"GB",
    "sg:address":"8 Vale Lane Top, Haworth",
    "sg:city":"Keighley",
    "sg:classifiers":[
        {
            "category":"Freight",
            "type":"Transportation"
        }
    ],
    "sg:phone":"+44 1535 647700",
    "sg:postcode":"BD22 9ER",
    "sg:province":"North Yorkshire",
    "sg:tags":[
        "haulage",
        "road"
    ],
    "wof:name":"S R I Light Haulage",
    "wof:placetype":"venue"
},
  "geometry": {"coordinates":[-1.9389220476,53.8366355896],"type":"Point"}
}