{
  "type": "Feature",
  "properties": {
    "iso:country":"GB",
    "sg:address":", Llanellen",
    "sg:city":"Abergavenny",
    "sg:classifiers":[
        {
            "category":"Education",
            "subcategory":"School",
            "type":"Public Place"
        }
    ],
    "sg:phone":"+44 1873 853721",
    "sg:postcode":"NP7 9HL",
    "sg:province":"Herefordshire",
    "sg:tags":[
        "local",
        "authority"
    ],
    "wof:name":"Llanellen Church Primary School",
    "wof:placetype":"venue"
},
  "geometry": {"coordinates":[-3.012554884,51.7932815552],"type":"Point"}
}