{
  "type": "Feature",
  "properties": {
    "iso:country":"GB",
    "sg:address":"The Poplars, 13 Linton Rd",
    "sg:city":"Swadlincote",
    "sg:classifiers":[
        {
            "category":"Health Services",
            "subcategory":"Doctor",
            "type":"Services"
        }
    ],
    "sg:phone":"+44 1283 217592",
    "sg:postcode":"DE11 9HU",
    "sg:province":"Derbyshire",
    "sg:tags":[
        "practitioners"
    ],
    "wof:name":"Varma, A K",
    "wof:placetype":"venue"
},
  "geometry": {"coordinates":[-1.5522090197,52.7740936279],"type":"Point"}
}