{
  "type": "Feature",
  "properties": {
    "iso:country":"GB",
    "sg:address":"2 Capitol House, Calenick Street",
    "sg:city":"Truro",
    "sg:classifiers":[
        {
            "category":"Shopping",
            "subcategory":"Used Merchandise",
            "type":"Retail Goods"
        }
    ],
    "sg:phone":"+44 1872 272443",
    "sg:postcode":"TR1 2SF",
    "sg:province":"Cornwall",
    "sg:tags":[
        "shop",
        "second-hand"
    ],
    "wof:name":"Cash Converters",
    "wof:placetype":"venue"
},
  "geometry": {"coordinates":[-5.053631,50.26524],"type":"Point"}
}