{
  "type": "Feature",
  "properties": {
    "addr:full":"55 Pellon Lane Halifax West Yorkshire HX1 5SP",
    "addr:housenumber":"55",
    "addr:postcode":"hx1 5sp",
    "addr:street":"Pellon Lane",
    "iso:country":"GB",
    "sg:address":"55 Pellon Lane",
    "sg:city":"Halifax",
    "sg:classifiers":[
        {
            "category":"Professional",
            "subcategory":"Computer Services",
            "type":"Services"
        }
    ],
    "sg:phone":"+44 1422 258888",
    "sg:postcode":"HX1 5SP",
    "sg:province":"West Yorkshire",
    "sg:tags":[
        "system",
        "software"
    ],
    "wof:name":"Prospero",
    "wof:placetype":"venue"
},
  "geometry": {"coordinates":[-1.86461,53.724068],"type":"Point"}
}