{
  "type": "Feature",
  "properties": {
    "addr:full":"Camden House, Claremont Terrace Bath Bath and North East Somerset BA1 6EH",
    "addr:postcode":"ba1 6eh",
    "addr:street":"Claremont Terrace",
    "iso:country":"GB",
    "sg:address":"Camden House, Claremont Terrace",
    "sg:city":"Bath",
    "sg:classifiers":[
        {
            "category":"Real Estate",
            "subcategory":"Real Estate Operator",
            "type":"Services"
        }
    ],
    "sg:phone":"+44 1225 444333",
    "sg:postcode":"BA1 6EH",
    "sg:province":"Bath and North East Somerset",
    "sg:tags":[
        "letting",
        "agent"
    ],
    "wof:name":"Local Lets Of Bath",
    "wof:placetype":"venue"
},
  "geometry": {"coordinates":[-2.3513679504,51.3957138062],"type":"Point"}
}