{
  "type": "Feature",
  "properties": {
    "addr:full":"81 Sheridan Rd, Frimley Camberley Hampshire GU16 7EH",
    "addr:housenumber":"81",
    "addr:postcode":"gu16 7eh",
    "addr:street":"Sheridan Rd",
    "iso:country":"GB",
    "sg:address":"81 Sheridan Rd, Frimley",
    "sg:city":"Camberley",
    "sg:classifiers":[
        {
            "category":"Professional",
            "subcategory":"Management & Consulting",
            "type":"Services"
        }
    ],
    "sg:postcode":"GU16 7EH",
    "sg:province":"Hampshire",
    "sg:tags":[
        "marketing",
        "consultant"
    ],
    "wof:name":"Direct Solutions",
    "wof:placetype":"venue"
},
  "geometry": {"coordinates":[-0.743877,51.311707],"type":"Point"}
}