{
  "type": "Feature",
  "properties": {
    "addr:full":"Granville House, Granville Rd Maidstone Kent ME14 2BJ",
    "addr:postcode":"me14 2bj",
    "addr:street":"Granville Rd",
    "iso:country":"GB",
    "sg:address":"Granville House, Granville Rd",
    "sg:city":"Maidstone",
    "sg:classifiers":[
        {
            "category":"Autos & Motor Vehicles",
            "subcategory":"Auto Supplies",
            "type":"Retail Goods"
        }
    ],
    "sg:phone":"+44 1622 681297",
    "sg:postcode":"ME14 2BJ",
    "sg:province":"Kent",
    "sg:tags":[
        "tyre"
    ],
    "wof:name":"Intertrade International Ltd",
    "wof:placetype":"venue"
},
  "geometry": {"coordinates":[0.5256540179,51.2835540771],"type":"Point"}
}