{
  "type": "Feature",
  "properties": {
    "iso:country":"GB",
    "sg:address":"County Road",
    "sg:city":"Ormskirk",
    "sg:classifiers":[
        {
            "category":"Bars & Pubs",
            "type":"Food & Drink"
        },
        {
            "category":"Community Center",
            "subcategory":"Social",
            "type":"Public Place"
        }
    ],
    "sg:phone":"+44 1695 571157",
    "sg:postcode":"L39 1NN",
    "sg:province":"Lancashire",
    "sg:tags":[
        "pubs",
        "house",
        "inn",
        "activity"
    ],
    "wof:name":"THE COVE (STONEY STANTON) LTD",
    "wof:placetype":"venue"
},
  "geometry": {"coordinates":[-2.878014,53.576286],"type":"Point"}
}