{
  "type": "Feature",
  "properties": {
    "addr:full":"2 Lower Gilmore Pl Edinburgh City of Edinburgh EH3 9NY",
    "addr:housenumber":"2",
    "addr:postcode":"eh3 9ny",
    "addr:street":"Lower Gilmore Pl",
    "iso:country":"GB",
    "sg:address":"2 Lower Gilmore Pl",
    "sg:city":"Edinburgh",
    "sg:classifiers":[
        {
            "category":"Professional",
            "subcategory":"Lawyer & Legal Services",
            "type":"Services"
        }
    ],
    "sg:phone":"+44 131 229 3596",
    "sg:postcode":"EH3 9NY",
    "sg:province":"City of Edinburgh",
    "sg:tags":[
        "advice",
        "counselling"
    ],
    "wof:name":"Lothian Brook Advisory Centre",
    "wof:placetype":"venue"
},
  "geometry": {"coordinates":[-3.2034039497,55.943901062],"type":"Point"}
}