{
  "type": "Feature",
  "properties": {
    "addr:full":"7 Overcote Lane, Needingworth St Ives Cambridgeshire PE27 4TU",
    "addr:housenumber":"7",
    "addr:postcode":"pe27 4tu",
    "addr:street":"Overcote Lane Needingworth",
    "iso:country":"GB",
    "sg:address":"7 Overcote Lane, Needingworth",
    "sg:city":"St Ives",
    "sg:classifiers":[
        {
            "category":"Retail",
            "subcategory":"Funeral Services",
            "type":"Services"
        }
    ],
    "sg:postcode":"PE27 4TU",
    "sg:province":"Cambridgeshire",
    "wof:name":"Robert Arthur Parish",
    "wof:placetype":"venue"
},
  "geometry": {"coordinates":[-0.029699,52.330704],"type":"Point"}
}