{
  "type": "Feature",
  "properties": {
    "addr:full":"Sandpit Farm, East Bower Bridgwater Somerset TA6 4TU",
    "addr:postcode":"ta6 4tu",
    "addr:street":"East Bower",
    "iso:country":"GB",
    "sg:address":"Sandpit Farm, East Bower",
    "sg:city":"Bridgwater",
    "sg:classifiers":[
        {
            "category":"Farming",
            "subcategory":"Dairy Farm",
            "type":"Manufacturing & Wholesale Goods"
        }
    ],
    "sg:postcode":"TA6 4TU",
    "sg:province":"Somerset",
    "wof:name":"Edwin Hill",
    "wof:placetype":"venue"
},
  "geometry": {"coordinates":[-2.975973,51.134506],"type":"Point"}
}