{
  "type": "Feature",
  "properties": {
    "addr:full":"Herringswell Manor, Herringswell Bury St Edmunds Cambridgeshire IP28 6SW",
    "addr:housenumber":"herringswell;herringswell",
    "addr:postcode":"ip28 6sw",
    "addr:street":"St",
    "iso:country":"GB",
    "sg:address":"Herringswell Manor, Herringswell",
    "sg:city":"Bury St Edmunds",
    "sg:classifiers":[
        {
            "category":"Education",
            "subcategory":"School",
            "type":"Public Place"
        }
    ],
    "sg:phone":"+44 1638 750234",
    "sg:postcode":"IP28 6SW",
    "sg:province":"Cambridgeshire",
    "sg:tags":[
        "independent",
        "preparatory"
    ],
    "wof:name":"Shi-Tennoji International Ltd.",
    "wof:placetype":"venue"
},
  "geometry": {"coordinates":[0.51618,52.301159],"type":"Point"}
}