{
  "type": "Feature",
  "properties": {
    "addr:full":"35-36 Week Street Maidstone Kent ME14 1QS",
    "addr:housenumber":"35-36",
    "addr:postcode":"me14 1qs",
    "addr:street":"Week Street",
    "iso:country":"GB",
    "sg:address":"35-36 Week Street",
    "sg:city":"Maidstone",
    "sg:classifiers":[
        {
            "category":"Shopping",
            "subcategory":"Clothing, Apparel, & Fashions",
            "type":"Retail Goods"
        }
    ],
    "sg:phone":"+44 1622 690927",
    "sg:postcode":"ME14 1QS",
    "sg:province":"Kent",
    "sg:tags":[
        "shop"
    ],
    "wof:name":"Principles",
    "wof:placetype":"venue"
},
  "geometry": {"coordinates":[0.522485,51.274738],"type":"Point"}
}