{
  "type": "Feature",
  "properties": {
    "iso:country":"GB",
    "sg:address":"Fitzwilliam House, Kimbolton Road, Higham Ferrers",
    "sg:city":"Rushden",
    "sg:classifiers":[
        {
            "category":"Personal",
            "subcategory":"Skin Care",
            "type":"Services"
        }
    ],
    "sg:phone":"+44 1933 358966",
    "sg:postcode":"NN10 8HL",
    "sg:province":"Bedfordshire",
    "sg:tags":[
        "leather",
        "merchant"
    ],
    "wof:name":"Colin Cross & Co. Ltd.",
    "wof:placetype":"venue"
},
  "geometry": {"coordinates":[-0.5925149918,52.3098945618],"type":"Point"}
}