{
  "type": "Feature",
  "properties": {
    "iso:country":"GB",
    "sg:address":"Lower Town, St Martin's",
    "sg:city":"St Marys",
    "sg:classifiers":[
        {
            "category":"Bars & Pubs",
            "type":"Food & Drink"
        }
    ],
    "sg:postcode":"TR25 0QW",
    "sg:province":"Cornwall",
    "sg:tags":[
        "pubs",
        "inn"
    ],
    "wof:name":"Seven Stones Inn",
    "wof:placetype":"venue"
},
  "geometry": {"coordinates":[-6.31475,49.914471],"type":"Point"}
}