{
  "type": "Feature",
  "properties": {
    "iso:country":"GB",
    "sg:address":"70 Langham Road",
    "sg:city":"Teddington",
    "sg:classifiers":[
        {
            "category":"Professional",
            "subcategory":"Management & Consulting",
            "type":"Services"
        }
    ],
    "sg:phone":"+44 20 8977 0408",
    "sg:postcode":"TW11 9HJ",
    "sg:province":"Greater London",
    "sg:tags":[
        "consultant",
        "business"
    ],
    "wof:name":"Probis",
    "wof:placetype":"venue"
},
  "geometry": {"coordinates":[-0.3242149949,51.4252891541],"type":"Point"}
}