{
  "type": "Feature",
  "properties": {
    "iso:country":"GB",
    "sg:address":"Mellitus Street",
    "sg:city":"London",
    "sg:classifiers":[
        {
            "category":"Education",
            "subcategory":"School",
            "type":"Public Place"
        }
    ],
    "sg:phone":"+44 20 8743 7629",
    "sg:postcode":"W12 0AS",
    "sg:province":"Greater London",
    "sg:tags":[
        "local",
        "authority"
    ],
    "wof:name":"Old Oak Primary School",
    "wof:placetype":"venue"
},
  "geometry": {"coordinates":[-0.2475280017,51.5193138123],"type":"Point"}
}