{
  "type": "Feature",
  "properties": {
    "addr:full":"88 Monmouth Rd Tucking Mill Salisbury Wiltshire SP3 6NR",
    "addr:housenumber":"88",
    "addr:postcode":"sp3 6nr",
    "addr:street":"Monmouth Rd",
    "iso:country":"GB",
    "sg:address":"88 Monmouth Rd Tucking Mill",
    "sg:city":"Salisbury",
    "sg:classifiers":[
        {
            "category":"Building & Trades",
            "subcategory":"Construction",
            "type":"Services"
        }
    ],
    "sg:phone":"+44 1747 870383",
    "sg:postcode":"SP3 6NR",
    "sg:province":"Wiltshire",
    "sg:tags":[
        "joiner",
        "carpenter"
    ],
    "wof:name":"Wilkinson R J",
    "wof:placetype":"venue"
},
  "geometry": {"coordinates":[-2.0906279087,51.0607070923],"type":"Point"}
}