{
  "type": "Feature",
  "properties": {
    "iso:country":"GB",
    "sg:address":"471 Holloway Road",
    "sg:city":"London",
    "sg:classifiers":[
        {
            "category":"Bars & Pubs",
            "type":"Food & Drink"
        },
        {
            "category":"Community Center",
            "subcategory":"Social",
            "type":"Public Place"
        }
    ],
    "sg:phone":"+44 20 7272 3634",
    "sg:postcode":"N7 6LE",
    "sg:province":"Greater London",
    "sg:tags":[
        "pubs",
        "house",
        "inn",
        "activity"
    ],
    "wof:name":"The Quays",
    "wof:placetype":"venue"
},
  "geometry": {"coordinates":[-0.1234920025,51.5603256226],"type":"Point"}
}