{
  "type": "Feature",
  "properties": {
    "iso:country":"GB",
    "sg:address":"Mansfield Barn, Fosse Way",
    "sg:city":"Leamington Spa",
    "sg:classifiers":[
        {
            "category":"Manufacturing",
            "subcategory":"Tools & Machinery",
            "type":"Manufacturing & Wholesale Goods"
        }
    ],
    "sg:postcode":"CV33 9SR",
    "sg:province":"Warwickshire",
    "wof:name":"Jet Clamps",
    "wof:placetype":"venue"
},
  "geometry": {"coordinates":[-1.53628,52.28968],"type":"Point"}
}