{
  "type": "Feature",
  "properties": {
    "addr:full":"New Road, Dinnington Sheffield South Yorkshire S25 2QT",
    "addr:postcode":"s25 2qt",
    "addr:street":"New Road",
    "iso:country":"GB",
    "sg:address":"New Road, Dinnington",
    "sg:city":"Sheffield",
    "sg:classifiers":[
        {
            "category":"Health Services",
            "subcategory":"Doctor",
            "type":"Services"
        }
    ],
    "sg:phone":"+44 1909 550606",
    "sg:postcode":"S25 2QT",
    "sg:province":"South Yorkshire",
    "sg:tags":[
        "practitioners"
    ],
    "wof:name":"New Road Dental Clinic",
    "wof:placetype":"venue"
},
  "geometry": {"coordinates":[-1.209529,53.365307],"type":"Point"}
}