{
  "type": "Feature",
  "properties": {
    "addr:full":"St Johns Close Saffron Walden Essex CB11 4AR",
    "addr:postcode":"cb11 4ar",
    "addr:street":"St Johns Close",
    "iso:country":"GB",
    "sg:address":"St Johns Close",
    "sg:city":"Saffron Walden",
    "sg:classifiers":[
        {
            "category":"Farming",
            "subcategory":"Nursery",
            "type":"Manufacturing & Wholesale Goods"
        },
        {
            "category":"Education",
            "subcategory":"Preschool",
            "type":"Public Place"
        }
    ],
    "sg:phone":"+44 1799 513858",
    "sg:postcode":"CB11 4AR",
    "sg:province":"Essex",
    "sg:tags":[
        "school",
        "creche"
    ],
    "wof:name":"Meadows Montessori Day Nursery School",
    "wof:placetype":"venue"
},
  "geometry": {"coordinates":[0.2425249964,52.0130958557],"type":"Point"}
}