{
  "type": "Feature",
  "properties": {
    "iso:country":"GB",
    "sg:address":"21 Upper Washwell, Painswick",
    "sg:city":"Stroud",
    "sg:classifiers":[
        {
            "category":"Retail",
            "subcategory":"Auto Rental",
            "type":"Services"
        },
        {
            "category":"Autos & Motor Vehicles",
            "subcategory":"Motorcycle Sales",
            "type":"Retail Goods"
        }
    ],
    "sg:phone":"+44 1452 812604",
    "sg:postcode":"GL6 6QY",
    "sg:province":"Gloucestershire",
    "sg:tags":[
        "chauffeur",
        "driven",
        "hire",
        "car"
    ],
    "wof:name":"D R Ryland",
    "wof:placetype":"venue"
},
  "geometry": {"coordinates":[-2.192876,51.787518],"type":"Point"}
}