{
  "type": "Feature",
  "properties": {
    "addr:full":"Rectory Farm, New Rd, Guilden Morden Royston Bedfordshire SG8 0JN",
    "addr:postcode":"sg8 0jn",
    "addr:street":"Rectory;New Rd",
    "iso:country":"GB",
    "sg:address":"Rectory Farm, New Rd, Guilden Morden",
    "sg:city":"Royston",
    "sg:classifiers":[
        {
            "category":"Farming",
            "subcategory":"Livestock Farm",
            "type":"Manufacturing & Wholesale Goods"
        }
    ],
    "sg:postcode":"SG8 0JN",
    "sg:province":"Bedfordshire",
    "sg:tags":[
        "others"
    ],
    "wof:name":"Woodhouse,S,",
    "wof:placetype":"venue"
},
  "geometry": {"coordinates":[-0.13353,52.082436],"type":"Point"}
}