{
  "type": "Feature",
  "properties": {
    "addr:full":"Hillview House, Guthrie Street, Letham Forfar Angus DD8 2PS",
    "addr:postcode":"dd8 2ps",
    "addr:street":"Guthrie Street",
    "iso:country":"GB",
    "sg:address":"Hillview House, Guthrie Street, Letham",
    "sg:city":"Forfar",
    "sg:classifiers":[
        {
            "category":"Building & Trades",
            "subcategory":"Construction",
            "type":"Services"
        }
    ],
    "sg:phone":"+44 1307 818820",
    "sg:postcode":"DD8 2PS",
    "sg:province":"Angus",
    "sg:tags":[
        "builder"
    ],
    "wof:name":"D Gardiner Construction",
    "wof:placetype":"venue"
},
  "geometry": {"coordinates":[-2.7725479603,56.631942749],"type":"Point"}
}