{
  "type": "Feature",
  "properties": {
    "iso:country":"GB",
    "sg:address":"Owdswell Manor, Andoversford",
    "sg:city":"Cheltenham",
    "sg:classifiers":[
        {
            "category":"Farming",
            "subcategory":"Livestock Farm",
            "type":"Manufacturing & Wholesale Goods"
        },
        {
            "category":"Farming",
            "subcategory":"Farm",
            "type":"Manufacturing & Wholesale Goods"
        }
    ],
    "sg:phone":"+44 1242 820297",
    "sg:postcode":"GL54 4LD",
    "sg:province":"Gloucestershire",
    "sg:tags":[
        "mixed",
        "crop",
        "others"
    ],
    "wof:name":"John Richardson",
    "wof:placetype":"venue"
},
  "geometry": {"coordinates":[-1.969802,51.872612],"type":"Point"}
}