{
  "type": "Feature",
  "properties": {
    "addr:full":"143 High Street Broadstairs Kent CT10 1NG",
    "addr:housenumber":"143",
    "addr:postcode":"ct10 1ng",
    "addr:street":"High Street",
    "iso:country":"GB",
    "sg:address":"143 High Street",
    "sg:city":"Broadstairs",
    "sg:classifiers":[
        {
            "category":"Personal",
            "subcategory":"Barber",
            "type":"Services"
        }
    ],
    "sg:phone":"+44 1843 864011",
    "sg:postcode":"CT10 1NG",
    "sg:province":"Kent",
    "sg:tags":[
        "men's",
        "gents",
        "hairdresser"
    ],
    "wof:name":"Matt's Headroom",
    "wof:placetype":"venue"
},
  "geometry": {"coordinates":[1.434553,51.359951],"type":"Point"}
}