{
  "type": "Feature",
  "properties": {
    "addr:full":"Unit 15 Bell Farm Industrial Park, Nuthampstead Royston Bedfordshire SG8 8ND",
    "addr:housenumber":"unit 15",
    "addr:postcode":"sg8 8nd",
    "addr:street":"Bell Farm Industrial Park",
    "iso:country":"GB",
    "sg:address":"Unit 15 Bell Farm Industrial Park, Nuthampstead",
    "sg:city":"Royston",
    "sg:classifiers":[
        {
            "category":"Bus Stop",
            "subcategory":"None",
            "type":"Transportation"
        }
    ],
    "sg:phone":"+44 1763 848849",
    "sg:postcode":"SG8 8ND",
    "sg:province":"Bedfordshire",
    "sg:tags":[
        "gasket"
    ],
    "wof:name":"Premier Gaskets",
    "wof:placetype":"venue"
},
  "geometry": {"coordinates":[-0.0219839998,52.048210144],"type":"Point"}
}