{
  "type": "Feature",
  "properties": {
    "iso:country":"GB",
    "sg:address":"7 Station Road, Hemyock",
    "sg:city":"Cullompton",
    "sg:classifiers":[
        {
            "category":"Organizations",
            "subcategory":"Non-profit Organization",
            "type":"Services"
        }
    ],
    "sg:phone":"+44 1823 680061",
    "sg:postcode":"EX15 3SE",
    "sg:province":"Devon",
    "sg:tags":[
        "charitable",
        "organisation",
        "voluntary",
        "charity"
    ],
    "wof:name":"British Trust For Conservation Volunteers",
    "wof:placetype":"venue"
},
  "geometry": {"coordinates":[-3.227399,50.917034],"type":"Point"}
}