{
  "type": "Feature",
  "properties": {
    "iso:country":"GB",
    "sg:address":"56-58 Chigwell Rd",
    "sg:city":"South Woodford",
    "sg:classifiers":[
        {
            "category":"Autos & Motor Vehicles",
            "subcategory":"Automobile Sales",
            "type":"Retail Goods"
        }
    ],
    "sg:phone":"+44 20 8530 2211",
    "sg:postcode":"E18 1NN",
    "sg:province":"Greater London",
    "sg:tags":[
        "commercial"
    ],
    "wof:name":"South Woodford Motor Co",
    "wof:placetype":"venue"
},
  "geometry": {"coordinates":[0.0350340009,51.5915641785],"type":"Point"}
}