{
  "type": "Feature",
  "properties": {
    "iso:country":"GB",
    "sg:address":"Riverside",
    "sg:city":"Thurso",
    "sg:classifiers":[
        {
            "category":"Social Services",
            "subcategory":"Job Training",
            "type":"Services"
        }
    ],
    "sg:phone":"+44 1847 893702",
    "sg:postcode":"KW14 8BU",
    "sg:province":"Highland",
    "sg:tags":[
        "engineering",
        "marine"
    ],
    "wof:name":"E & M Engineering",
    "wof:placetype":"venue"
},
  "geometry": {"coordinates":[-3.518379,58.593918],"type":"Point"}
}