{
  "type": "Feature",
  "properties": {
    "addr:full":"Woodhead Hall, Cherry Lane, Cheadle Stoke-on-trent Staffordshire ST10 4QS",
    "addr:postcode":"st10 4qs",
    "addr:street":"Cherry Lane",
    "iso:country":"GB",
    "sg:address":"Woodhead Hall, Cherry Lane, Cheadle",
    "sg:city":"Stoke-on-trent",
    "sg:classifiers":[
        {
            "category":"Professional",
            "subcategory":"Engineering",
            "type":"Services"
        }
    ],
    "sg:phone":"+44 1538 752133",
    "sg:postcode":"ST10 4QS",
    "sg:province":"Staffordshire",
    "sg:tags":[
        "contractor",
        "electrical",
        "engineer"
    ],
    "wof:name":"A C Chesters & Son Ltd.",
    "wof:placetype":"venue"
},
  "geometry": {"coordinates":[-1.9676699638,52.994228363],"type":"Point"}
}