{
  "type": "Feature",
  "properties": {
    "iso:country":"GB",
    "sg:address":"Hudson House, Bromley Road",
    "sg:city":"London",
    "sg:classifiers":[
        {
            "category":"Government",
            "subcategory":"Office",
            "type":"Public Place"
        }
    ],
    "sg:phone":"+44 20 8698 5573",
    "sg:postcode":"SE6 2RH",
    "sg:province":"Greater London",
    "sg:tags":[
        "armed",
        "reserve"
    ],
    "wof:name":"Territorial Army",
    "wof:placetype":"venue"
},
  "geometry": {"coordinates":[-0.01538,51.431221],"type":"Point"}
}