{
  "type": "Feature",
  "properties": {
    "addr:full":"49 Broome Path, St. Dials Cwmbran Monmouthshire NP44 4ND",
    "addr:housenumber":"49",
    "addr:postcode":"np44 4nd",
    "addr:street":"Broome Path St.",
    "iso:country":"GB",
    "sg:address":"49 Broome Path, St. Dials",
    "sg:city":"Cwmbran",
    "sg:classifiers":[
        {
            "category":"Professional",
            "subcategory":"Computer Services",
            "type":"Services"
        }
    ],
    "sg:postcode":"NP44 4ND",
    "sg:province":"Monmouthshire",
    "sg:tags":[
        "consultant"
    ],
    "wof:name":"Harmony Computers Ltd",
    "wof:placetype":"venue"
},
  "geometry": {"coordinates":[-3.038174,51.64645],"type":"Point"}
}