{
  "type": "Feature",
  "properties": {
    "addr:full":"4 Lindenwood, Crockford Lane, Chineham Business Park Basingstoke Hampshire RG24 8QY",
    "addr:housenumber":"4",
    "addr:postcode":"rg24 8qy",
    "addr:street":"Lindenwood Crockford Lane",
    "iso:country":"GB",
    "sg:address":"4 Lindenwood, Crockford Lane, Chineham Business Park",
    "sg:city":"Basingstoke",
    "sg:classifiers":[
        {
            "category":"Shopping",
            "subcategory":"Computers & Home Electronics",
            "type":"Retail Goods"
        }
    ],
    "sg:phone":"+44 1256 891700",
    "sg:postcode":"RG24 8QY",
    "sg:province":"Hampshire",
    "sg:tags":[
        "aerial",
        "television",
        "radio"
    ],
    "wof:name":"Audeo Distribution Ltd.",
    "wof:placetype":"venue"
},
  "geometry": {"coordinates":[-1.052407,51.289032],"type":"Point"}
}