{
  "type": "Feature",
  "properties": {
    "addr:full":"62 Marylebone High St West End Hampshire W1M 3AF",
    "addr:housenumber":"62",
    "addr:postcode":"w1m 3af",
    "addr:street":"Marylebone High St",
    "iso:country":"GB",
    "sg:address":"62 Marylebone High St",
    "sg:city":"West End",
    "sg:classifiers":[
        {
            "category":"Professional",
            "subcategory":"Employment Agencies",
            "type":"Services"
        }
    ],
    "sg:phone":"+44 20 7224 1200",
    "sg:postcode":"W1M 3AF",
    "sg:province":"Hampshire",
    "sg:tags":[
        "consultant"
    ],
    "wof:name":"Strongfield International PLC",
    "wof:placetype":"venue"
},
  "geometry": {"coordinates":[-0.1569200009,51.5235900879],"type":"Point"}
}