{
  "type": "Feature",
  "properties": {
    "addr:full":"Rosebery Ave London Greater London EC1R 5HL",
    "addr:postcode":"ec1r 5hl",
    "addr:street":"Rosebery Ave",
    "iso:country":"GB",
    "sg:address":"Rosebery Ave",
    "sg:city":"London",
    "sg:classifiers":[
        {
            "category":"Banks & Credit Unions",
            "subcategory":"Financial Services",
            "type":"Services"
        }
    ],
    "sg:postcode":"EC1R 5HL",
    "sg:province":"Greater London",
    "sg:tags":[
        "consultant"
    ],
    "wof:name":"Walbrook Commercial Finance Ltd",
    "wof:placetype":"venue"
},
  "geometry": {"coordinates":[-0.111809,51.522545],"type":"Point"}
}