{
  "type": "Feature",
  "properties": {
    "addr:full":"12 Arran Close, Cosham Portsmouth Portsmouth Hampshire PO6 3UD",
    "addr:housenumber":"12",
    "addr:postcode":"hampshire po6 3ud",
    "addr:street":"Arran Close",
    "iso:country":"GB",
    "sg:address":"12 Arran Close, Cosham Portsmouth",
    "sg:city":"Portsmouth",
    "sg:classifiers":[
        {
            "category":"Professional",
            "subcategory":"Engineering",
            "type":"Services"
        }
    ],
    "sg:phone":"+44 23 9237 5040",
    "sg:postcode":"PO6 3UD",
    "sg:province":"Hampshire",
    "sg:tags":[
        "design",
        "engineer"
    ],
    "wof:name":"Datatech Engineering Ltd",
    "wof:placetype":"venue"
},
  "geometry": {"coordinates":[-1.0680860281,50.8514633179],"type":"Point"}
}