{
  "type": "Feature",
  "properties": {
    "addr:full":"122 Milton Road Weston-super-mare Somerset BS23 2UW",
    "addr:housenumber":"122",
    "addr:postcode":"bs23 2uw",
    "addr:street":"Milton Road",
    "iso:country":"GB",
    "sg:address":"122 Milton Road",
    "sg:city":"Weston-super-mare",
    "sg:classifiers":[
        {
            "category":"Food & Beverages",
            "subcategory":"Meat & Fish",
            "type":"Retail Goods"
        }
    ],
    "sg:phone":"+44 1934 626563",
    "sg:postcode":"BS23 2UW",
    "sg:province":"Somerset",
    "sg:tags":[
        "merchant"
    ],
    "wof:name":"Harvey's Seafood",
    "wof:placetype":"venue"
},
  "geometry": {"coordinates":[-2.959089,51.351013],"type":"Point"}
}