{
  "type": "Feature",
  "properties": {
    "addr:full":"72 Blackheath Road London Greater London SE10 8DA",
    "addr:housenumber":"72",
    "addr:postcode":"se10 8da",
    "addr:street":"Blackheath Road",
    "iso:country":"GB",
    "sg:address":"72 Blackheath Road",
    "sg:city":"London",
    "sg:classifiers":[
        {
            "category":"Professional",
            "subcategory":"Employment Agencies",
            "type":"Services"
        }
    ],
    "sg:phone":"+44 1732 823530",
    "sg:postcode":"SE10 8DA",
    "sg:province":"Greater London",
    "sg:tags":[
        "consultant"
    ],
    "wof:name":"Sheila Difford",
    "wof:placetype":"venue"
},
  "geometry": {"coordinates":[-0.0189210009,51.4732475281],"type":"Point"}
}