{
  "type": "Feature",
  "properties": {
    "iso:country":"GB",
    "sg:address":"Summerston Shopping Centre, 5 Gorstan St",
    "sg:city":"Glasgow",
    "sg:classifiers":[
        {
            "category":"Food & Beverages",
            "subcategory":"Meat & Fish",
            "type":"Retail Goods"
        }
    ],
    "sg:phone":"+44 141 946 7910",
    "sg:postcode":"G23 5QA",
    "sg:province":"Glasgow City",
    "sg:tags":[
        "chip"
    ],
    "wof:name":"Philadelphia Fish & Chicken Bar",
    "wof:placetype":"venue"
},
  "geometry": {"coordinates":[-4.29258,55.900299],"type":"Point"}
}