{
  "type": "Feature",
  "properties": {
    "addr:full":"The Glen, Drift Rd Maidenhead Berkshire SL6 3ST",
    "addr:postcode":"sl6 3st",
    "addr:street":"The Glen Drift Rd",
    "iso:country":"GB",
    "sg:address":"The Glen, Drift Rd",
    "sg:city":"Maidenhead",
    "sg:classifiers":[
        {
            "category":"Retail",
            "subcategory":"Auto Repair",
            "type":"Services"
        }
    ],
    "sg:phone":"+44 1628 776697",
    "sg:postcode":"SL6 3ST",
    "sg:province":"Berkshire",
    "sg:tags":[
        "body",
        "car"
    ],
    "wof:name":"Glen Alexannder Cars & Commercial Vehicle Servicing",
    "wof:placetype":"venue"
},
  "geometry": {"coordinates":[-0.7272570133,51.5223731995],"type":"Point"}
}