{
  "type": "Feature",
  "properties": {
    "addr:full":"405 Hendon Way London Greater London NW4 3LH",
    "addr:housenumber":"405",
    "addr:postcode":"nw4 3lh",
    "addr:street":"Hendon Way",
    "iso:country":"GB",
    "sg:address":"405 Hendon Way",
    "sg:city":"London",
    "sg:classifiers":[
        {
            "category":"Professional",
            "subcategory":"Lawyer & Legal Services",
            "type":"Services"
        }
    ],
    "sg:postcode":"NW4 3LH",
    "sg:province":"Greater London",
    "sg:tags":[
        "solicitor"
    ],
    "wof:name":"George Brown Son & Vardy",
    "wof:placetype":"venue"
},
  "geometry": {"coordinates":[-0.2272769958,51.5821266174],"type":"Point"}
}