{
  "type": "Feature",
  "properties": {
    "addr:full":"14 Perth Rd St Leonards On Sea East Sussex TN37 7EB",
    "addr:housenumber":"14",
    "addr:postcode":"tn37 7eb",
    "addr:street":"Perth Rd St",
    "iso:country":"GB",
    "sg:address":"14 Perth Rd",
    "sg:city":"St Leonards On Sea",
    "sg:classifiers":[
        {
            "category":"Shopping",
            "subcategory":"Computers & Home Electronics",
            "type":"Retail Goods"
        }
    ],
    "sg:phone":"+44 1424 446265",
    "sg:postcode":"TN37 7EB",
    "sg:province":"East Sussex",
    "sg:tags":[
        "aerial",
        "television",
        "radio"
    ],
    "wof:name":"Aerial Experts",
    "wof:placetype":"venue"
},
  "geometry": {"coordinates":[0.5548430085,50.8721504211],"type":"Point"}
}