{
  "type": "Feature",
  "properties": {
    "iso:country":"GB",
    "sg:address":"Fairlight, John's Green",
    "sg:city":"Sandwich",
    "sg:classifiers":[
        {
            "category":"Professional",
            "subcategory":"Employment Agencies",
            "type":"Services"
        }
    ],
    "sg:phone":"+44 1304 614362",
    "sg:postcode":"CT13 0DE",
    "sg:province":"Kent",
    "sg:tags":[
        "consultant"
    ],
    "wof:name":"S E M S Plus  Ltd.",
    "wof:placetype":"venue"
},
  "geometry": {"coordinates":[1.3291,51.263538],"type":"Point"}
}