{
  "type": "Feature",
  "properties": {
    "iso:country":"GB",
    "sg:address":"Unit 10, Kingfisher Court",
    "sg:city":"Newbury",
    "sg:classifiers":[
        {
            "category":"Building & Trades",
            "subcategory":"Construction",
            "type":"Services"
        }
    ],
    "sg:phone":"+44 1635 529191",
    "sg:postcode":"RG14 5SJ",
    "sg:province":"Berkshire",
    "sg:tags":[
        "dry",
        "plastering",
        "plasterers",
        "lining",
        "related",
        "screeders"
    ],
    "wof:name":"Lloyd Davenport Ltd",
    "wof:placetype":"venue"
},
  "geometry": {"coordinates":[-1.3021990061,51.4002456665],"type":"Point"}
}