{
  "type": "Feature",
  "properties": {
    "addr:full":"12 Queensland Rd Holloway Greater London N7 7AJ",
    "addr:housenumber":"12",
    "addr:postcode":"n7 7aj",
    "addr:street":"Queensland Rd",
    "iso:country":"GB",
    "sg:address":"12 Queensland Rd",
    "sg:city":"Holloway",
    "sg:classifiers":[
        {
            "category":"Shopping",
            "subcategory":"Clothing, Apparel, & Fashions",
            "type":"Retail Goods"
        }
    ],
    "sg:phone":"+44 20 7607 9692",
    "sg:postcode":"N7 7AJ",
    "sg:province":"Greater London",
    "sg:tags":[
        "clothing"
    ],
    "wof:name":"Zigi Fashions Ltd",
    "wof:placetype":"venue"
},
  "geometry": {"coordinates":[-0.108095,51.553314],"type":"Point"}
}