{
  "type": "Feature",
  "properties": {
    "iso:country":"GB",
    "sg:address":"84 Liverpool Road, Cadishead",
    "sg:city":"Manchester",
    "sg:classifiers":[
        {
            "category":"Insurance",
            "subcategory":"Insurance Agent",
            "type":"Services"
        }
    ],
    "sg:phone":"+44 161 775 9088",
    "sg:postcode":"M44 5AN",
    "sg:province":"Greater Manchester",
    "sg:tags":[
        "broker"
    ],
    "wof:name":"Atherton Roberts",
    "wof:placetype":"venue"
},
  "geometry": {"coordinates":[-2.435035,53.429455],"type":"Point"}
}