{
  "type": "Feature",
  "properties": {
    "addr:full":"24 Wigfull Road Sheffield Derbyshire S11 8RJ",
    "addr:housenumber":"24",
    "addr:postcode":"s11 8rj",
    "addr:street":"Wigfull Road",
    "iso:country":"GB",
    "sg:address":"24 Wigfull Road",
    "sg:city":"Sheffield",
    "sg:classifiers":[
        {
            "category":"Taxi",
            "type":"Transportation"
        }
    ],
    "sg:phone":"+44 114 266 5912",
    "sg:postcode":"S11 8RJ",
    "sg:province":"Derbyshire",
    "sg:tags":[
        "mini",
        "cab"
    ],
    "wof:name":"Durkin Taxis",
    "wof:placetype":"venue"
},
  "geometry": {"coordinates":[-1.4993610382,53.3707466125],"type":"Point"}
}