{
  "type": "Feature",
  "properties": {
    "addr:full":"11 Eastheath Avenue Wokingham Berkshire RG41 2PP",
    "addr:housenumber":"11",
    "addr:postcode":"rg41 2pp",
    "addr:street":"Eastheath Avenue",
    "iso:country":"GB",
    "sg:address":"11 Eastheath Avenue",
    "sg:city":"Wokingham",
    "sg:classifiers":[
        {
            "category":"Manufacturing",
            "subcategory":"Signs",
            "type":"Manufacturing & Wholesale Goods"
        }
    ],
    "sg:postcode":"RG41 2PP",
    "sg:province":"Berkshire",
    "sg:tags":[
        "writer"
    ],
    "wof:name":"Allsigns",
    "wof:placetype":"venue"
},
  "geometry": {"coordinates":[-0.8428300023,51.4011230469],"type":"Point"}
}