{
  "type": "Feature",
  "properties": {
    "iso:country":"GB",
    "sg:address":"Windmill Court, William Booth Road",
    "sg:city":"King's Lynn",
    "sg:classifiers":[
        {
            "category":"Social Services",
            "subcategory":"Adult Care",
            "type":"Services"
        }
    ],
    "sg:phone":"+44 1553 764243",
    "sg:postcode":"PE30 4XP",
    "sg:province":"Norfolk",
    "sg:tags":[
        "housing",
        "sheltered"
    ],
    "wof:name":"Sheltered Housing for the Elderly",
    "wof:placetype":"venue"
},
  "geometry": {"coordinates":[0.43454,52.754608],"type":"Point"}
}