{
  "type": "Feature",
  "properties": {
    "addr:full":"17 Bucklers Ct, North End Portsmouth Hampshire PO2 9AW",
    "addr:housenumber":"17",
    "addr:postcode":"hampshire po2 9aw",
    "addr:street":"Bucklers Ct",
    "iso:country":"GB",
    "sg:address":"17 Bucklers Ct, North End",
    "sg:city":"Portsmouth",
    "sg:classifiers":[
        {
            "category":"Professional",
            "subcategory":"Accounting & Tax Preparation",
            "type":"Services"
        }
    ],
    "sg:phone":"+44 23 9267 3069",
    "sg:postcode":"PO2 9AW",
    "sg:province":"Hampshire",
    "sg:tags":[
        "accountant"
    ],
    "wof:name":"Crawley,Frank,",
    "wof:placetype":"venue"
},
  "geometry": {"coordinates":[-1.080796957,50.8176956177],"type":"Point"}
}