{
  "type": "Feature",
  "properties": {
    "iso:country":"GB",
    "sg:address":"15a Balgownie Road, Bridge Of Don",
    "sg:city":"Aberdeen",
    "sg:classifiers":[
        {
            "category":"Wholesale",
            "subcategory":"Computers",
            "type":"Manufacturing & Wholesale Goods"
        },
        {
            "category":"Professional",
            "subcategory":"Computer Services",
            "type":"Services"
        }
    ],
    "sg:phone":"+44 1224 825900",
    "sg:postcode":"AB23 8JN",
    "sg:province":"Aberdeen City",
    "sg:tags":[
        "supplier",
        "consultant",
        "consumables"
    ],
    "wof:name":"Image Hq Ltd.",
    "wof:placetype":"venue"
},
  "geometry": {"coordinates":[-2.093217,57.17709],"type":"Point"}
}