{
  "type": "Feature",
  "properties": {
    "addr:full":"Dringhoe, Beeford Driffield East Riding of Yorkshire YO25 8AG",
    "addr:postcode":"yo25 8ag",
    "addr:street":"Beeford",
    "iso:country":"GB",
    "sg:address":"Dringhoe, Beeford",
    "sg:city":"Driffield",
    "sg:classifiers":[
        {
            "category":"Farming",
            "subcategory":"Farm",
            "type":"Manufacturing & Wholesale Goods"
        }
    ],
    "sg:phone":"+44 1262 468252",
    "sg:postcode":"YO25 8AG",
    "sg:province":"East Riding of Yorkshire",
    "sg:tags":[
        "mixed",
        "crop"
    ],
    "wof:name":"Field House Farm (Dringhoe) Ltd.",
    "wof:placetype":"venue"
},
  "geometry": {"coordinates":[-0.281509,53.970959],"type":"Point"}
}