{
  "type": "Feature",
  "properties": {
    "iso:country":"GB",
    "sg:address":"3 Wester Howgate, Howgate",
    "sg:city":"Penicuik",
    "sg:classifiers":[
        {
            "category":"Education",
            "subcategory":"School",
            "type":"Public Place"
        },
        {
            "category":"Government",
            "subcategory":"Office",
            "type":"Public Place"
        }
    ],
    "sg:phone":"+44 1968 672812",
    "sg:postcode":"EH26 8QB",
    "sg:province":"Midlothian",
    "sg:tags":[
        "local",
        "authority"
    ],
    "wof:name":"Howgate Primary School",
    "wof:placetype":"venue"
},
  "geometry": {"coordinates":[-3.219904,55.836395],"type":"Point"}
}