{
  "type": "Feature",
  "properties": {
    "iso:country":"GB",
    "sg:address":"339 Clepington Road",
    "sg:city":"Dundee",
    "sg:classifiers":[
        {
            "category":"Health Services",
            "subcategory":"Medical Lab",
            "type":"Services"
        },
        {
            "category":"Health Services",
            "subcategory":"Health Practitioner",
            "type":"Services"
        }
    ],
    "sg:phone":"+44 1382 819367",
    "sg:postcode":"DD3 8BA",
    "sg:province":"Dundee City",
    "sg:tags":[
        "alternative",
        "therapy",
        "treatment",
        "osteopath"
    ],
    "wof:name":"Holistic Healing Clinic",
    "wof:placetype":"venue"
},
  "geometry": {"coordinates":[-2.982284,56.478092],"type":"Point"}
}