{
  "type": "Feature",
  "properties": {
    "iso:country":"GB",
    "sg:address":"48 Fordham Road, Soham",
    "sg:city":"Ely",
    "sg:classifiers":[
        {
            "category":"Retail",
            "subcategory":"Veterinary Services",
            "type":"Services"
        },
        {
            "category":"Health Services",
            "subcategory":"Dentist",
            "type":"Services"
        }
    ],
    "sg:phone":"+44 1353 720422",
    "sg:postcode":"CB7 5AH",
    "sg:province":"Cambridgeshire",
    "sg:tags":[
        "surgeon"
    ],
    "wof:name":"Staploe Vetinary Practice",
    "wof:placetype":"venue"
},
  "geometry": {"coordinates":[0.35694,52.317989],"type":"Point"}
}