{
  "type": "Feature",
  "properties": {
    "addr:full":"The Meads, Sedbury Chepstow Gloucestershire NP16 7HN",
    "addr:postcode":"np16 7hn",
    "addr:street":"The Meads Sedbury",
    "iso:country":"GB",
    "sg:address":"The Meads, Sedbury",
    "sg:city":"Chepstow",
    "sg:classifiers":[
        {
            "category":"Utilities",
            "subcategory":"Refuse",
            "type":"Services"
        }
    ],
    "sg:phone":"+44 1291 622486",
    "sg:postcode":"NP16 7HN",
    "sg:province":"Gloucestershire",
    "sg:tags":[
        "skip",
        "hire"
    ],
    "wof:name":"R B Skip Hire Ltd.",
    "wof:placetype":"venue"
},
  "geometry": {"coordinates":[-2.663813,51.644966],"type":"Point"}
}