{
  "type": "Feature",
  "properties": {
    "addr:full":"Rockland St Mary Post Office, 41 The Street, Rockland St Mary Norwich Norfolk NR14 7AH",
    "addr:housenumber":"41",
    "addr:postcode":"nr14 7ah",
    "addr:street":"Rockland;The Street Rockland St;Norwich",
    "iso:country":"GB",
    "sg:address":"Rockland St Mary Post Office, 41 The Street, Rockland St Mary",
    "sg:city":"Norwich",
    "sg:classifiers":[
        {
            "category":"Government",
            "subcategory":"Post Office",
            "type":"Public Place"
        }
    ],
    "sg:postcode":"NR14 7AH",
    "sg:province":"Norfolk",
    "wof:name":"Rockland St.Mary Post Office Stores",
    "wof:placetype":"venue"
},
  "geometry": {"coordinates":[1.418900013,52.5876998901],"type":"Point"}
}