{
  "type": "Feature",
  "properties": {
    "addr:full":"Western App Southend-on-sea Essex SS2 6XY",
    "addr:postcode":"ss2 6xy",
    "iso:country":"GB",
    "sg:address":"Western App",
    "sg:city":"Southend-on-sea",
    "sg:classifiers":[
        {
            "category":"Health Services",
            "subcategory":"Doctor",
            "type":"Services"
        },
        {
            "category":"Health Services",
            "subcategory":"Clinic",
            "type":"Services"
        }
    ],
    "sg:phone":"+44 1702 420642",
    "sg:postcode":"SS2 6XY",
    "sg:province":"Essex",
    "sg:tags":[
        "nh",
        "practitioners"
    ],
    "wof:name":"Essex Family Practitioner",
    "wof:placetype":"venue"
},
  "geometry": {"coordinates":[0.672376,51.571484],"type":"Point"}
}