{
  "type": "Feature",
  "properties": {
    "addr:full":"16 Aigburth Dr Liverpool Merseyside L17 4JG",
    "addr:housenumber":"16",
    "addr:postcode":"l17 4jg",
    "addr:street":"Aigburth Dr",
    "iso:country":"GB",
    "sg:address":"16 Aigburth Dr",
    "sg:city":"Liverpool",
    "sg:classifiers":[
        {
            "category":"Real Estate",
            "subcategory":"Real Estate Agent",
            "type":"Services"
        }
    ],
    "sg:postcode":"L17 4JG",
    "sg:province":"Merseyside",
    "wof:name":"Greda,M,",
    "wof:placetype":"venue"
},
  "geometry": {"coordinates":[-2.942149,53.38205],"type":"Point"}
}