{
  "type": "Feature",
  "properties": {
    "iso:country":"GB",
    "sg:address":"18 Crestwood Avenue",
    "sg:city":"Wigan",
    "sg:classifiers":[
        {
            "category":"Organizations",
            "subcategory":"Membership Organization",
            "type":"Services"
        }
    ],
    "sg:phone":"+44 1942 235999",
    "sg:postcode":"WN3 6SE",
    "sg:province":"Lancashire",
    "sg:tags":[
        "intercom",
        "system"
    ],
    "wof:name":"S W H Security Systems",
    "wof:placetype":"venue"
},
  "geometry": {"coordinates":[-2.654468,53.5228],"type":"Point"}
}