{
  "type": "Feature",
  "properties": {
    "addr:full":"Branchton Road Greenock Inverclyde PA16 0XT",
    "addr:postcode":"pa16 0xt",
    "addr:street":"Branchton Road",
    "iso:country":"GB",
    "sg:address":"Branchton Road",
    "sg:city":"Greenock",
    "sg:classifiers":[
        {
            "category":"Community Center",
            "type":"Public Place"
        }
    ],
    "sg:phone":"+44 1475 638481",
    "sg:postcode":"PA16 0XT",
    "sg:province":"Inverclyde",
    "sg:tags":[
        "centre"
    ],
    "wof:name":"Branchton Community Centre",
    "wof:placetype":"venue"
},
  "geometry": {"coordinates":[-4.8044838905,55.939163208],"type":"Point"}
}