{
  "type": "Feature",
  "properties": {
    "addr:full":"19 Radfield Drive Bradford West Yorkshire BD6 1BY",
    "addr:housenumber":"19",
    "addr:postcode":"bd6 1by",
    "addr:street":"Radfield Drive",
    "iso:country":"GB",
    "sg:address":"19 Radfield Drive",
    "sg:city":"Bradford",
    "sg:classifiers":[
        {
            "category":"Building & Trades",
            "subcategory":"Construction",
            "type":"Services"
        }
    ],
    "sg:phone":"+44 1274 728701",
    "sg:postcode":"BD6 1BY",
    "sg:province":"West Yorkshire",
    "sg:tags":[
        "joinery",
        "joiner",
        "carpenter",
        "carpentry"
    ],
    "wof:name":"Rooley Joinery",
    "wof:placetype":"venue"
},
  "geometry": {"coordinates":[-1.7522219419,53.7663040161],"type":"Point"}
}