{
  "type": "Feature",
  "properties": {
    "addr:full":"Whitfield Buildings, 192-200 Pensby Road, Heswall Wirral Merseyside CH60 7RJ",
    "addr:housenumber":"192-200",
    "addr:postcode":"ch60 7rj",
    "addr:street":"Pensby Road",
    "iso:country":"GB",
    "sg:address":"Whitfield Buildings, 192-200 Pensby Road, Heswall",
    "sg:city":"Wirral",
    "sg:classifiers":[
        {
            "category":"Professional",
            "subcategory":"Art Services",
            "type":"Services"
        }
    ],
    "sg:phone":"+44 151 342 6365",
    "sg:postcode":"CH60 7RJ",
    "sg:province":"Merseyside",
    "sg:tags":[
        "consultant",
        "design"
    ],
    "wof:name":"B R M Partnership",
    "wof:placetype":"venue"
},
  "geometry": {"coordinates":[-3.0987288952,53.3290557861],"type":"Point"}
}