{
  "type": "Feature",
  "properties": {
    "iso:country":"GB",
    "sg:address":"Moorhey Street",
    "sg:city":"Oldham",
    "sg:classifiers":[
        {
            "category":"Manufacturing",
            "subcategory":"Wood Products",
            "type":"Manufacturing & Wholesale Goods"
        }
    ],
    "sg:postcode":"OL4 1BA",
    "sg:province":"Lancashire",
    "sg:tags":[
        "maker",
        "cabinet"
    ],
    "wof:name":"J B Etchells Woodworking",
    "wof:placetype":"venue"
},
  "geometry": {"coordinates":[-2.094379,53.540585],"type":"Point"}
}