{
  "type": "Feature",
  "properties": {
    "addr:full":"91 Victoria Road Cirencester Gloucestershire GL7 1ES",
    "addr:housenumber":"91",
    "addr:postcode":"gl7 1es",
    "addr:street":"Victoria Road",
    "iso:country":"GB",
    "sg:address":"91 Victoria Road",
    "sg:city":"Cirencester",
    "sg:classifiers":[
        {
            "category":"Travel",
            "subcategory":"Hotels & Motels",
            "type":"Entertainment"
        }
    ],
    "sg:phone":"+44 1285 643653",
    "sg:postcode":"GL7 1ES",
    "sg:province":"Gloucestershire",
    "sg:tags":[
        "house",
        "guest"
    ],
    "wof:name":"Wimbourne House",
    "wof:placetype":"venue"
},
  "geometry": {"coordinates":[-1.9604779482,51.7126922607],"type":"Point"}
}