{
  "type": "Feature",
  "properties": {
    "addr:full":"91 Wilkins Road, Cowley Oxford Oxfordshire OX4 2JB",
    "addr:housenumber":"91",
    "addr:postcode":"ox4 2jb",
    "addr:street":"Wilkins Road",
    "iso:country":"GB",
    "sg:address":"91 Wilkins Road, Cowley",
    "sg:city":"Oxford",
    "sg:classifiers":[
        {
            "category":"Health Services",
            "subcategory":"Dentist",
            "type":"Services"
        }
    ],
    "sg:postcode":"OX4 2JB",
    "sg:province":"Oxfordshire",
    "sg:tags":[
        "technician",
        "dental"
    ],
    "wof:name":"P R & D J Glanville",
    "wof:placetype":"venue"
},
  "geometry": {"coordinates":[-1.2057260275,51.7352104187],"type":"Point"}
}