{
  "type": "Feature",
  "properties": {
    "iso:country":"GB",
    "sg:address":"The Round House, 34a High Street",
    "sg:city":"Petersfield",
    "sg:classifiers":[
        {
            "category":"Professional",
            "subcategory":"Lawyer & Legal Services",
            "type":"Services"
        }
    ],
    "sg:postcode":"GU32 3JL",
    "sg:province":"Hampshire",
    "sg:tags":[
        "solicitor"
    ],
    "wof:name":"World Oil & Gas Resources",
    "wof:placetype":"venue"
},
  "geometry": {"coordinates":[-0.93474,51.003815],"type":"Point"}
}