{
  "type": "Feature",
  "properties": {
    "iso:country":"GB",
    "sg:address":"180 Allison St",
    "sg:city":"Glasgow",
    "sg:classifiers":[
        {
            "category":"Government",
            "subcategory":"Post Office",
            "type":"Public Place"
        }
    ],
    "sg:phone":"+44 141 424 4010",
    "sg:postcode":"G42 8RR",
    "sg:province":"Glasgow City",
    "sg:tags":[
        "fax",
        "bureau",
        "telex"
    ],
    "wof:name":"Glasgow International Phone & Fax Service",
    "wof:placetype":"venue"
},
  "geometry": {"coordinates":[-4.2629361153,55.8362045288],"type":"Point"}
}