{
  "type": "Feature",
  "properties": {
    "addr:full":"Kintail House, Beechwood Park Inverness Highland IV2 3BW",
    "addr:postcode":"iv2 3bw",
    "addr:street":"Beechwood Park",
    "iso:country":"GB",
    "sg:address":"Kintail House, Beechwood Park",
    "sg:city":"Inverness",
    "sg:classifiers":[
        {
            "category":"Professional",
            "subcategory":"Lawyer & Legal Services",
            "type":"Services"
        }
    ],
    "sg:phone":"+44 1463 232273",
    "sg:postcode":"IV2 3BW",
    "sg:province":"Highland",
    "sg:tags":[
        "solicitor"
    ],
    "wof:name":"Innes & Mackay",
    "wof:placetype":"venue"
},
  "geometry": {"coordinates":[-4.1975169182,57.4791870117],"type":"Point"}
}