{
  "type": "Feature",
  "properties": {
    "iso:country":"GB",
    "sg:address":"Swi Centre Independent House, 178 Brompton Road",
    "sg:city":"London",
    "sg:classifiers":[
        {
            "category":"Education",
            "subcategory":"School",
            "type":"Public Place"
        }
    ],
    "sg:postcode":"SW3 1HQ",
    "sg:province":"Greater London",
    "sg:tags":[
        "local",
        "authority"
    ],
    "wof:name":"Essence Training Ltd",
    "wof:placetype":"venue"
},
  "geometry": {"coordinates":[-0.164479,51.499161],"type":"Point"}
}