{
  "type": "Feature",
  "properties": {
    "addr:full":"Mains Of Murthly Farm Aberfeldy Perth and Kinross PH15 2EA",
    "addr:postcode":"ph15 2ea",
    "addr:street":"Aberfeldy",
    "iso:country":"GB",
    "sg:address":"Mains Of Murthly Farm",
    "sg:city":"Aberfeldy",
    "sg:classifiers":[
        {
            "category":"Farming",
            "subcategory":"Farm",
            "type":"Manufacturing & Wholesale Goods"
        },
        {
            "category":"Wholesale",
            "subcategory":"Fruits & Vegetables",
            "type":"Manufacturing & Wholesale Goods"
        }
    ],
    "sg:phone":"+44 1887 820427",
    "sg:postcode":"PH15 2EA",
    "sg:province":"Perth and Kinross",
    "sg:tags":[
        "mixed"
    ],
    "wof:name":"John M Mcdiarmid",
    "wof:placetype":"venue"
},
  "geometry": {"coordinates":[-3.86666,56.619183],"type":"Point"}
}