{
  "type": "Feature",
  "properties": {
    "iso:country":"GB",
    "sg:address":"28 Sheep St",
    "sg:city":"Shipston-on-stour",
    "sg:classifiers":[
        {
            "category":"Shopping",
            "subcategory":"Antiques",
            "type":"Retail Goods"
        }
    ],
    "sg:postcode":"CV36 4AF",
    "sg:province":"Warwickshire",
    "wof:name":"Past Present",
    "wof:placetype":"venue"
},
  "geometry": {"coordinates":[-1.626401,52.06287],"type":"Point"}
}