{
  "type": "Feature",
  "properties": {
    "addr:full":"Unit 1 Jedburgh Scottish Borders TD8 6LS",
    "addr:housenumber":"unit 1",
    "addr:postcode":"td8 6ls",
    "addr:street":"Jedburgh",
    "iso:country":"GB",
    "sg:address":"Unit 1",
    "sg:city":"Jedburgh",
    "sg:classifiers":[
        {
            "category":"Building & Trades",
            "subcategory":"Plumbing",
            "type":"Services"
        }
    ],
    "sg:postcode":"TD8 6LS",
    "sg:province":"Scottish Borders",
    "sg:tags":[
        "heating"
    ],
    "wof:name":"Ian Morrison",
    "wof:placetype":"venue"
},
  "geometry": {"coordinates":[-2.5469489098,55.4804000854],"type":"Point"}
}