{
  "type": "Feature",
  "properties": {
    "iso:country":"GB",
    "sg:address":"5 New Rd",
    "sg:city":"Brighton",
    "sg:classifiers":[
        {
            "category":"Home & Garden",
            "subcategory":"Household Appliances",
            "type":"Retail Goods"
        }
    ],
    "sg:phone":"+44 1273 775166",
    "sg:postcode":"BN1 1UF",
    "sg:province":"East Sussex",
    "sg:tags":[
        "electrical",
        "domestic"
    ],
    "wof:name":"Edwards & Hope Electrical Supplies Ltd",
    "wof:placetype":"venue"
},
  "geometry": {"coordinates":[-0.13991,50.82288],"type":"Point"}
}