{
  "type": "Feature",
  "properties": {
    "addr:full":"Moorhayes Farm Cullompton Devon EX15 1QN",
    "addr:housenumber":"cullompton",
    "addr:postcode":"ex15 1qn",
    "addr:street":"Devon",
    "iso:country":"GB",
    "sg:address":"Moorhayes Farm",
    "sg:city":"Cullompton",
    "sg:classifiers":[
        {
            "category":"Farming",
            "subcategory":"Dairy Farm",
            "type":"Manufacturing & Wholesale Goods"
        }
    ],
    "sg:phone":"+44 1884 34917",
    "sg:postcode":"EX15 1QN",
    "sg:province":"Devon",
    "wof:name":"K R & B A Sanders & Sons",
    "wof:placetype":"venue"
},
  "geometry": {"coordinates":[-3.392634,50.858166],"type":"Point"}
}