{
  "type": "Feature",
  "properties": {
    "addr:full":"1-3 Beoley Road West Redditch Warwickshire B98 8LR",
    "addr:housenumber":"1-3",
    "addr:postcode":"b98 8lr",
    "addr:street":"Beoley Road West",
    "iso:country":"GB",
    "sg:address":"1-3 Beoley Road West",
    "sg:city":"Redditch",
    "sg:classifiers":[
        {
            "category":"Shopping",
            "subcategory":"Florist",
            "type":"Retail Goods"
        }
    ],
    "sg:phone":"+44 1527 595593",
    "sg:postcode":"B98 8LR",
    "sg:province":"Warwickshire",
    "wof:name":"Misty Flowers",
    "wof:placetype":"venue"
},
  "geometry": {"coordinates":[-1.928329,52.306225],"type":"Point"}
}