{
  "type": "Feature",
  "properties": {
    "addr:full":"5 Bancroft Avenue, Cheadle Hulme Cheadle Cheshire SK8 5BA",
    "addr:housenumber":"5",
    "addr:postcode":"sk8 5ba",
    "addr:street":"Bancroft Avenue",
    "iso:country":"GB",
    "sg:address":"5 Bancroft Avenue, Cheadle Hulme",
    "sg:city":"Cheadle",
    "sg:classifiers":[
        {
            "category":"Professional",
            "subcategory":"Detective & Security Services",
            "type":"Services"
        }
    ],
    "sg:phone":"+44 161 485 6966",
    "sg:postcode":"SK8 5BA",
    "sg:province":"Cheshire",
    "sg:tags":[
        "equipment"
    ],
    "wof:name":"B.A. Security",
    "wof:placetype":"venue"
},
  "geometry": {"coordinates":[-2.1901669502,53.3729324341],"type":"Point"}
}