{
  "type": "Feature",
  "properties": {
    "addr:full":"Pensby Dental Practice, 67 Ridgewood Dr Wirral Merseyside CH61 8RF",
    "addr:housenumber":"67",
    "addr:postcode":"ch61 8rf",
    "addr:street":"Ridgewood Dr",
    "iso:country":"GB",
    "sg:address":"Pensby Dental Practice, 67 Ridgewood Dr",
    "sg:city":"Wirral",
    "sg:classifiers":[
        {
            "category":"Health Services",
            "subcategory":"Dentist",
            "type":"Services"
        }
    ],
    "sg:phone":"+44 151 648 5098",
    "sg:postcode":"CH61 8RF",
    "sg:province":"Merseyside",
    "wof:name":"L Y Chan",
    "wof:placetype":"venue"
},
  "geometry": {"coordinates":[-3.1025600433,53.3485412598],"type":"Point"}
}