{
  "type": "Feature",
  "properties": {
    "addr:full":"77 Milton Rd Stoke On Trent Staffordshire ST1 6HF",
    "addr:housenumber":"77",
    "addr:postcode":"st1 6hf",
    "addr:street":"Milton Rd",
    "iso:country":"GB",
    "sg:address":"77 Milton Rd",
    "sg:city":"Stoke On Trent",
    "sg:classifiers":[
        {
            "category":"Shopping",
            "subcategory":"Department Store",
            "type":"Retail Goods"
        }
    ],
    "sg:phone":"+44 1782 219297",
    "sg:postcode":"ST1 6HF",
    "sg:province":"Staffordshire",
    "wof:name":"Sneyd Foodmarket",
    "wof:placetype":"venue"
},
  "geometry": {"coordinates":[-2.1675219536,53.0407142639],"type":"Point"}
}