{
  "type": "Feature",
  "properties": {
    "iso:country":"GB",
    "sg:address":"430 Burncross Road",
    "sg:city":"Sheffield",
    "sg:classifiers":[
        {
            "category":"Building & Trades",
            "subcategory":"Construction",
            "type":"Services"
        }
    ],
    "sg:phone":"+44 114 246 8047",
    "sg:postcode":"S35 1SL",
    "sg:province":"South Yorkshire",
    "sg:tags":[
        "builder"
    ],
    "wof:name":"Tebroc Building Services",
    "wof:placetype":"venue"
},
  "geometry": {"coordinates":[-1.4872200489,53.4612960815],"type":"Point"}
}