{
  "type": "Feature",
  "properties": {
    "iso:country":"GB",
    "sg:address":"Community Centre, 287 Herbert Avenue",
    "sg:city":"Poole",
    "sg:classifiers":[
        {
            "category":"Community Center",
            "type":"Public Place"
        }
    ],
    "sg:phone":"+44 1202 740026",
    "sg:postcode":"BH12 4HT",
    "sg:province":"Dorset",
    "sg:tags":[
        "centre"
    ],
    "wof:name":"Alderney Manor Social Club Ltd.",
    "wof:placetype":"venue"
},
  "geometry": {"coordinates":[-1.9406,50.744991],"type":"Point"}
}