{
  "type": "Feature",
  "properties": {
    "iso:country":"GB",
    "sg:address":"Unit 1 John Davey Dr, Treleigh Indstl Est",
    "sg:city":"Redruth",
    "sg:classifiers":[
        {
            "category":"Manufacturing",
            "subcategory":"Pottery",
            "type":"Manufacturing & Wholesale Goods"
        }
    ],
    "sg:phone":"+44 1209 215126",
    "sg:postcode":"TR16 4AX",
    "sg:province":"Cornwall",
    "wof:name":"Prompots Ltd",
    "wof:placetype":"venue"
},
  "geometry": {"coordinates":[-5.2250242233,50.244644165],"type":"Point"}
}