{
  "type": "Feature",
  "properties": {
    "addr:full":"Horn Lane Plymouth Devon PL9 9BR",
    "addr:postcode":"pl9 9br",
    "addr:street":"Horn Lane",
    "iso:country":"GB",
    "sg:address":"Horn Lane",
    "sg:city":"Plymouth",
    "sg:classifiers":[
        {
            "category":"Health Services",
            "subcategory":"Doctor",
            "type":"Services"
        },
        {
            "category":"Health Services",
            "subcategory":"Clinic",
            "type":"Services"
        }
    ],
    "sg:phone":"+44 1752 407129",
    "sg:postcode":"PL9 9BR",
    "sg:province":"Devon",
    "sg:tags":[
        "nh",
        "practitioners"
    ],
    "wof:name":"Barton Surgery",
    "wof:placetype":"venue"
},
  "geometry": {"coordinates":[-4.087373,50.358898],"type":"Point"}
}