{
  "type": "Feature",
  "properties": {
    "iso:country":"GB",
    "sg:address":"Po Box 28, Woodbridge Rd",
    "sg:city":"Sleaford",
    "sg:classifiers":[
        {
            "category":"Manufacturing",
            "subcategory":"Tools & Machinery",
            "type":"Manufacturing & Wholesale Goods"
        }
    ],
    "sg:phone":"+44 1529 413101",
    "sg:postcode":"NG34 7EP",
    "sg:province":"Lincolnshire",
    "wof:name":"Swift Tools ltd",
    "wof:placetype":"venue"
},
  "geometry": {"coordinates":[-0.411869,52.994587],"type":"Point"}
}