{
  "type": "Feature",
  "properties": {
    "addr:full":"93 Vantage Point, Pensnett Trading Estate, Kingswinford Brierley Hill Staffordshire DY6 7FZ",
    "addr:housenumber":"93",
    "addr:postcode":"dy6 7fz",
    "addr:street":"Vantage Point",
    "iso:country":"GB",
    "sg:address":"93 Vantage Point, Pensnett Trading Estate, Kingswinford",
    "sg:city":"Brierley Hill",
    "sg:classifiers":[
        {
            "category":"Professional",
            "subcategory":"Printing & Photocopies",
            "type":"Services"
        }
    ],
    "sg:phone":"+44 1384 404660",
    "sg:postcode":"DY6 7FZ",
    "sg:province":"Staffordshire",
    "sg:tags":[
        "photocopier"
    ],
    "wof:name":"Altodigital Uk Ltd.",
    "wof:placetype":"venue"
},
  "geometry": {"coordinates":[-2.162019968,52.5041618347],"type":"Point"}
}