{
  "type": "Feature",
  "properties": {
    "iso:country":"GB",
    "sg:address":"Top Flat 7 Lammas Park Road, Ealing",
    "sg:city":"London",
    "sg:classifiers":[
        {
            "category":"Professional",
            "subcategory":"Computer Services",
            "type":"Services"
        }
    ],
    "sg:postcode":"W5 5JD",
    "sg:province":"Greater London",
    "sg:tags":[
        "system",
        "software"
    ],
    "wof:name":"Ancrum Associates Ltd",
    "wof:placetype":"venue"
},
  "geometry": {"coordinates":[-0.3078480065,51.5056190491],"type":"Point"}
}