{
  "type": "Feature",
  "properties": {
    "addr:full":"13 King Street Cambridge Cambridgeshire CB1 1LH",
    "addr:housenumber":"13",
    "addr:postcode":"cb1 1lh",
    "addr:street":"King Street",
    "iso:country":"GB",
    "sg:address":"13 King Street",
    "sg:city":"Cambridge",
    "sg:classifiers":[
        {
            "category":"Cafe",
            "type":"Food & Drink"
        }
    ],
    "sg:phone":"+44 1223 355156",
    "sg:postcode":"CB1 1LH",
    "sg:province":"Cambridgeshire",
    "sg:tags":[
        "tea",
        "room"
    ],
    "wof:name":"Casimir",
    "wof:placetype":"venue"
},
  "geometry": {"coordinates":[0.1225299984,52.2072181702],"type":"Point"}
}