{
  "type": "Feature",
  "properties": {
    "addr:full":"37 Napton Drive Leamington Spa Warwickshire CV32 7UX",
    "addr:housenumber":"37",
    "addr:postcode":"cv32 7ux",
    "addr:street":"Napton Drive",
    "iso:country":"GB",
    "sg:address":"37 Napton Drive",
    "sg:city":"Leamington Spa",
    "sg:classifiers":[
        {
            "category":"Professional",
            "type":"Services"
        }
    ],
    "sg:postcode":"CV32 7UX",
    "sg:province":"Warwickshire",
    "sg:tags":[
        "entertainer"
    ],
    "wof:name":"John E Zetterstrom",
    "wof:placetype":"venue"
},
  "geometry": {"coordinates":[-1.524286,52.29892],"type":"Point"}
}