{
  "type": "Feature",
  "properties": {
    "addr:full":"25 Spring Road Abingdon Oxfordshire OX14 1AH",
    "addr:housenumber":"25",
    "addr:postcode":"ox14 1ah",
    "addr:street":"Spring Road",
    "iso:country":"GB",
    "sg:address":"25 Spring Road",
    "sg:city":"Abingdon",
    "sg:classifiers":[
        {
            "category":"Organizations",
            "subcategory":"Membership Organization",
            "type":"Services"
        }
    ],
    "sg:phone":"+44 1235 526389",
    "sg:postcode":"OX14 1AH",
    "sg:province":"Oxfordshire",
    "sg:tags":[
        "club"
    ],
    "wof:name":"Abingdon Royal British Legion Club & Headquarters Ltd.",
    "wof:placetype":"venue"
},
  "geometry": {"coordinates":[-1.295116,51.670376],"type":"Point"}
}