{
  "type": "Feature",
  "properties": {
    "addr:full":"30 Upper Dock Street Newport Newport NP20 1DL",
    "addr:housenumber":"30",
    "addr:postcode":"np20 1dl",
    "addr:street":"Upper Dock Street",
    "iso:country":"GB",
    "sg:address":"30 Upper Dock Street",
    "sg:city":"Newport",
    "sg:classifiers":[
        {
            "category":"Health Services",
            "subcategory":"Optometrist",
            "type":"Services"
        }
    ],
    "sg:phone":"+44 1633 256626",
    "sg:postcode":"NP20 1DL",
    "sg:province":"Newport",
    "sg:tags":[
        "optician"
    ],
    "wof:name":"Greenberg Stewart Opticians",
    "wof:placetype":"venue"
},
  "geometry": {"coordinates":[-2.9953958988,51.5882148743],"type":"Point"}
}