{
  "type": "Feature",
  "properties": {
    "iso:country":"GB",
    "sg:address":"10 Hickman St",
    "sg:city":"Gainsborough",
    "sg:classifiers":[
        {
            "category":"Health Services",
            "subcategory":"Nursing And Care Facility",
            "type":"Services"
        }
    ],
    "sg:phone":"+44 1427 679762",
    "sg:postcode":"DN21 2DZ",
    "sg:province":"Lincolnshire",
    "sg:tags":[
        "home"
    ],
    "wof:name":"West Links Housing Ltd",
    "wof:placetype":"venue"
},
  "geometry": {"coordinates":[-0.7760760188,53.3970909119],"type":"Point"}
}