{
  "type": "Feature",
  "properties": {
    "addr:full":"The Old Station Hotel Llandudno Junction Conwy LL31 9NE",
    "addr:postcode":"ll31 9ne",
    "iso:country":"GB",
    "sg:address":"The Old Station Hotel",
    "sg:city":"Llandudno Junction",
    "sg:classifiers":[
        {
            "category":"Restaurant",
            "type":"Food & Drink"
        }
    ],
    "sg:phone":"+44 1492 581259",
    "sg:postcode":"LL31 9NE",
    "sg:province":"Conwy",
    "wof:name":"The Mill House Inn",
    "wof:placetype":"venue"
},
  "geometry": {"coordinates":[-3.8084480762,53.2844772339],"type":"Point"}
}