{
  "type": "Feature",
  "properties": {
    "addr:full":"11a West Street, Conisbrough Doncaster South Yorkshire DN12 3JH",
    "addr:housenumber":"11a",
    "addr:postcode":"dn12 3jh",
    "addr:street":"West Street",
    "iso:country":"GB",
    "sg:address":"11a West Street, Conisbrough",
    "sg:city":"Doncaster",
    "sg:classifiers":[
        {
            "category":"Home & Garden",
            "subcategory":"Hardware",
            "type":"Retail Goods"
        }
    ],
    "sg:phone":"+44 1709 862676",
    "sg:postcode":"DN12 3JH",
    "sg:province":"South Yorkshire",
    "sg:tags":[
        "retailer",
        "diy"
    ],
    "wof:name":"F & J C Jackson",
    "wof:placetype":"venue"
},
  "geometry": {"coordinates":[-1.2305469513,53.4817199707],"type":"Point"}
}