{
  "type": "Feature",
  "properties": {
    "iso:country":"GB",
    "sg:address":"33-34 The Forum",
    "sg:city":"Sittingbourne",
    "sg:classifiers":[
        {
            "category":"Shopping",
            "subcategory":"Clothing, Apparel, & Fashions",
            "type":"Retail Goods"
        }
    ],
    "sg:phone":"+44 1795 430021",
    "sg:postcode":"ME10 3DL",
    "sg:province":"Kent",
    "sg:tags":[
        "shop"
    ],
    "wof:name":"Peacock's Stores Ltd.",
    "wof:placetype":"venue"
},
  "geometry": {"coordinates":[0.7479799986,51.3419914246],"type":"Point"}
}