{
  "type": "Feature",
  "properties": {
    "iso:country":"GB",
    "sg:address":"Unit 3a Bailie Gate Ind Est",
    "sg:city":"Wimborne",
    "sg:classifiers":[
        {
            "category":"Shopping",
            "subcategory":"Pets & Pet Supplies",
            "type":"Retail Goods"
        }
    ],
    "sg:phone":"+44 1202 602117",
    "sg:postcode":"BH21 2DB",
    "sg:province":"Dorset",
    "sg:tags":[
        "food"
    ],
    "wof:name":"Pets Direct",
    "wof:placetype":"venue"
},
  "geometry": {"coordinates":[-1.988709,50.802235],"type":"Point"}
}