{
  "type": "Feature",
  "properties": {
    "addr:full":"Unit 4 Two Rivers Industrial Estate, Braunton Road Barnstaple Devon EX31 1JY",
    "addr:housenumber":"unit 4",
    "addr:postcode":"ex31 1jy",
    "addr:street":"Industrial Estate Braunton Road",
    "iso:country":"GB",
    "sg:address":"Unit 4 Two Rivers Industrial Estate, Braunton Road",
    "sg:city":"Barnstaple",
    "sg:classifiers":[
        {
            "category":"Professional",
            "subcategory":"Engineering",
            "type":"Services"
        }
    ],
    "sg:phone":"+44 1271 327750",
    "sg:postcode":"EX31 1JY",
    "sg:province":"Devon",
    "sg:tags":[
        "precision",
        "engineer"
    ],
    "wof:name":"D S & B Engineering Ltd.",
    "wof:placetype":"venue"
},
  "geometry": {"coordinates":[-4.0699968338,51.0838127136],"type":"Point"}
}