{
  "type": "Feature",
  "properties": {
    "iso:country":"GB",
    "sg:address":"310 Wellingborough Rd",
    "sg:city":"Northampton",
    "sg:classifiers":[
        {
            "category":"Manufacturing",
            "subcategory":"Buildings",
            "type":"Manufacturing & Wholesale Goods"
        }
    ],
    "sg:postcode":"NN1 4EP",
    "sg:province":"Northamptonshire",
    "sg:tags":[
        "system",
        "air conditioning"
    ],
    "wof:name":"Genaire Global Ltd",
    "wof:placetype":"venue"
},
  "geometry": {"coordinates":[-0.8732439876,52.2429351807],"type":"Point"}
}