{
  "type": "Feature",
  "properties": {
    "addr:full":"424 High Street Oldbury West Midlands B66 3PJ",
    "addr:housenumber":"424",
    "addr:postcode":"b66 3pj",
    "addr:street":"High Street",
    "iso:country":"GB",
    "sg:address":"424 High Street",
    "sg:city":"Oldbury",
    "sg:classifiers":[
        {
            "category":"Food & Beverages",
            "subcategory":"Candy",
            "type":"Retail Goods"
        }
    ],
    "sg:phone":"+44 121 558 5405",
    "sg:postcode":"B66 3PJ",
    "sg:province":"West Midlands",
    "sg:tags":[
        "confectioner"
    ],
    "wof:name":"Sunny Sweet Centre",
    "wof:placetype":"venue"
},
  "geometry": {"coordinates":[-1.96812,52.491112],"type":"Point"}
}