{
  "type": "Feature",
  "properties": {
    "addr:full":"Broomton House, Crask, Culbokie Dingwall Highland IV7 8AS",
    "addr:postcode":"iv7 8as",
    "iso:country":"GB",
    "sg:address":"Broomton House, Crask, Culbokie",
    "sg:city":"Dingwall",
    "sg:classifiers":[
        {
            "category":"Building & Trades",
            "subcategory":"Construction",
            "type":"Services"
        }
    ],
    "sg:phone":"+44 1349 877525",
    "sg:postcode":"IV7 8AS",
    "sg:province":"Highland",
    "sg:tags":[
        "joiner",
        "carpenter"
    ],
    "wof:name":"Croftcraft Joinery",
    "wof:placetype":"venue"
},
  "geometry": {"coordinates":[-4.339747,57.600994],"type":"Point"}
}