{
  "type": "Feature",
  "properties": {
    "iso:country":"GB",
    "sg:address":"34 Kennington Lane",
    "sg:city":"London",
    "sg:classifiers":[
        {
            "category":"Retail",
            "subcategory":"Laundry & Dry Cleaning",
            "type":"Services"
        }
    ],
    "sg:phone":"+44 20 7735 1372",
    "sg:postcode":"SE11 4LS",
    "sg:province":"Greater London",
    "sg:tags":[
        "launderette"
    ],
    "wof:name":"Kennington Lane Launderette",
    "wof:placetype":"venue"
},
  "geometry": {"coordinates":[-0.105794,51.490902],"type":"Point"}
}