{
  "type": "Feature",
  "properties": {
    "iso:country":"GB",
    "sg:address":"415 Lincoln Road",
    "sg:city":"Peterborough",
    "sg:classifiers":[
        {
            "category":"Communications",
            "type":"Services"
        }
    ],
    "sg:phone":"+44 1733 340707",
    "sg:postcode":"PE1 2PF",
    "sg:province":"Cambridgeshire",
    "sg:tags":[
        "tv",
        "video",
        "radio"
    ],
    "wof:name":"Paul Taylor G P A",
    "wof:placetype":"venue"
},
  "geometry": {"coordinates":[-0.249303,52.58931],"type":"Point"}
}