{
  "type": "Feature",
  "properties": {
    "iso:country":"GB",
    "sg:address":"24 Waveney Avenue",
    "sg:city":"Bedford",
    "sg:classifiers":[
        {
            "category":"Professional",
            "subcategory":"Business Services",
            "type":"Services"
        }
    ],
    "sg:phone":"+44 1234 363777",
    "sg:postcode":"MK41 7EA",
    "sg:province":"Bedfordshire",
    "sg:tags":[
        "distribution"
    ],
    "wof:name":"Keith Betteley",
    "wof:placetype":"venue"
},
  "geometry": {"coordinates":[-0.4600920081,52.1566772461],"type":"Point"}
}