{
  "type": "Feature",
  "properties": {
    "iso:country":"GB",
    "sg:address":"The Crest, Off Brent Street",
    "sg:city":"London",
    "sg:classifiers":[
        {
            "category":"Place Of Worship",
            "type":"Public Place"
        }
    ],
    "sg:phone":"+44 20 8202 6687",
    "sg:postcode":"NW4 2HY",
    "sg:province":"Greater London",
    "wof:name":"Ner Yisrael Synagogue",
    "wof:placetype":"venue"
},
  "geometry": {"coordinates":[-0.2188899964,51.5854110718],"type":"Point"}
}