{
  "type": "Feature",
  "properties": {
    "iso:country":"GB",
    "sg:address":"Bulwark Road, Bulwark",
    "sg:city":"Chepstow",
    "sg:classifiers":[
        {
            "category":"Organizations",
            "subcategory":"Community Association",
            "type":"Services"
        },
        {
            "category":"Organizations",
            "subcategory":"Membership Organization",
            "type":"Services"
        }
    ],
    "sg:phone":"+44 1291 622980",
    "sg:postcode":"NP16 5JN",
    "sg:province":"Gloucestershire",
    "sg:tags":[
        "club",
        "social"
    ],
    "wof:name":"Severn Bridge Social Club Ltd",
    "wof:placetype":"venue"
},
  "geometry": {"coordinates":[-2.6798119545,51.637878418],"type":"Point"}
}