{
  "type": "Feature",
  "properties": {
    "addr:full":"41 Ninfield Road, Sidley Bexhill-on-sea East Sussex TN39 5AE",
    "addr:housenumber":"41",
    "addr:postcode":"tn39 5ae",
    "addr:street":"Ninfield Road;Bexhill-On-Sea",
    "iso:country":"GB",
    "sg:address":"41 Ninfield Road, Sidley",
    "sg:city":"Bexhill-on-sea",
    "sg:classifiers":[
        {
            "category":"Home & Garden",
            "subcategory":"Carpets & Floor Coverings",
            "type":"Retail Goods"
        }
    ],
    "sg:phone":"+44 1424 218337",
    "sg:postcode":"TN39 5AE",
    "sg:province":"East Sussex",
    "sg:tags":[
        "carpets",
        "rug",
        "matting"
    ],
    "wof:name":"The Carpet Shop",
    "wof:placetype":"venue"
},
  "geometry": {"coordinates":[0.4714950025,50.8558311462],"type":"Point"}
}