{
  "type": "Feature",
  "properties": {
    "addr:full":"58 Hillfield Road, Selsey Chichester West Sussex PO20 0LF",
    "addr:housenumber":"58",
    "addr:postcode":"po20 0lf",
    "addr:street":"Hillfield Road",
    "iso:country":"GB",
    "sg:address":"58 Hillfield Road, Selsey",
    "sg:city":"Chichester",
    "sg:classifiers":[
        {
            "category":"Social Services",
            "subcategory":"Retirement Home",
            "type":"Services"
        }
    ],
    "sg:postcode":"PO20 0LF",
    "sg:province":"West Sussex",
    "sg:tags":[
        "residential",
        "care"
    ],
    "wof:name":"Meadowcroft Retirement Home",
    "wof:placetype":"venue"
},
  "geometry": {"coordinates":[-0.7956200242,50.7272758484],"type":"Point"}
}