{
  "type": "Feature",
  "properties": {
    "iso:country":"GB",
    "sg:address":"14 Yalding Gardens, Wollaton",
    "sg:city":"Nottingham",
    "sg:classifiers":[
        {
            "category":"Retail",
            "subcategory":"Driving School",
            "type":"Services"
        }
    ],
    "sg:postcode":"NG8 2PZ",
    "sg:province":"Nottinghamshire",
    "wof:name":"Herrods School of Motoring",
    "wof:placetype":"venue"
},
  "geometry": {"coordinates":[-1.2385220528,52.9520683289],"type":"Point"}
}