{
  "type": "Feature",
  "properties": {
    "addr:full":"High St Chinnor Buckinghamshire OX9 4DH",
    "addr:postcode":"ox9 4dh",
    "addr:street":"High St",
    "iso:country":"GB",
    "sg:address":"High St",
    "sg:city":"Chinnor",
    "sg:classifiers":[
        {
            "category":"Place Of Worship",
            "type":"Public Place"
        }
    ],
    "sg:phone":"+44 1844 352938",
    "sg:postcode":"OX9 4DH",
    "sg:province":"Buckinghamshire",
    "wof:name":"Chinnor Congregational Church",
    "wof:placetype":"venue"
},
  "geometry": {"coordinates":[-0.908209,51.705952],"type":"Point"}
}