{
  "type": "Feature",
  "properties": {
    "iso:country":"GB",
    "sg:address":"9 James Street",
    "sg:city":"Ayr",
    "sg:classifiers":[
        {
            "category":"Farming",
            "subcategory":"Nursery",
            "type":"Manufacturing & Wholesale Goods"
        }
    ],
    "sg:phone":"+44 1292 266976",
    "sg:postcode":"KA8 0DH",
    "sg:province":"South Ayrshire",
    "sg:tags":[
        "creche"
    ],
    "wof:name":"The Owl & the Pussycat Nursery Ltd.",
    "wof:placetype":"venue"
},
  "geometry": {"coordinates":[-4.624376,55.465839],"type":"Point"}
}