{
  "type": "Feature",
  "properties": {
    "addr:full":"278 Wellington Road South Stockport Cheshire SK2 6ND",
    "addr:housenumber":"278",
    "addr:postcode":"sk2 6nd",
    "addr:street":"Wellington Road South",
    "iso:country":"GB",
    "sg:address":"278 Wellington Road South",
    "sg:city":"Stockport",
    "sg:classifiers":[
        {
            "category":"Health Services",
            "subcategory":"Medical Lab",
            "type":"Services"
        },
        {
            "category":"Health Services",
            "subcategory":"Dentist",
            "type":"Services"
        }
    ],
    "sg:phone":"+44 161 480 5597",
    "sg:postcode":"SK2 6ND",
    "sg:province":"Cheshire",
    "sg:tags":[
        "technician",
        "instrument",
        "dental",
        "purpose",
        "manufacturer"
    ],
    "wof:name":"Dental Repairs A6",
    "wof:placetype":"venue"
},
  "geometry": {"coordinates":[-2.1537320614,53.3994483948],"type":"Point"}
}