{
  "type": "Feature",
  "properties": {
    "addr:full":"46 High Street Salisbury Wiltshire SP1 2NT",
    "addr:housenumber":"46",
    "addr:postcode":"sp1 2nt",
    "addr:street":"High Street",
    "iso:country":"GB",
    "sg:address":"46 High Street",
    "sg:city":"Salisbury",
    "sg:classifiers":[
        {
            "category":"Personal",
            "subcategory":"Beauty Salon",
            "type":"Services"
        }
    ],
    "sg:phone":"+44 1722 335333",
    "sg:postcode":"SP1 2NT",
    "sg:province":"Wiltshire",
    "sg:tags":[
        "unisex",
        "hairdresser"
    ],
    "wof:name":"Hans Schneider",
    "wof:placetype":"venue"
},
  "geometry": {"coordinates":[-1.797778,51.06757],"type":"Point"}
}