{
  "type": "Feature",
  "properties": {
    "iso:country":"GB",
    "sg:address":"Unit 1 King Edward House",
    "sg:city":"Nuneaton",
    "sg:classifiers":[
        {
            "category":"Autos & Motor Vehicles",
            "subcategory":"Auto Supplies",
            "type":"Retail Goods"
        }
    ],
    "sg:phone":"+44 24 7634 9314",
    "sg:postcode":"CV11 4BB",
    "sg:province":"Leicestershire",
    "sg:tags":[
        "car",
        "component"
    ],
    "wof:name":"Brian Lissaman Ltd.",
    "wof:placetype":"venue"
},
  "geometry": {"coordinates":[-1.461297,52.520931],"type":"Point"}
}