{
  "type": "Feature",
  "properties": {
    "addr:full":"Baird Close, Drayton Fields Industrial Estate Daventry Northamptonshire NN11 5RY",
    "addr:housenumber":"industrial estate",
    "addr:postcode":"nn11 5ry",
    "addr:street":"Baird Close;Fields",
    "iso:country":"GB",
    "sg:address":"Baird Close, Drayton Fields Industrial Estate",
    "sg:city":"Daventry",
    "sg:classifiers":[
        {
            "category":"Professional",
            "subcategory":"Engineering",
            "type":"Services"
        }
    ],
    "sg:phone":"+44 1327 704921",
    "sg:postcode":"NN11 5RY",
    "sg:province":"Northamptonshire",
    "sg:tags":[
        "precision",
        "engineer"
    ],
    "wof:name":"Micron Machine Tools Ltd.",
    "wof:placetype":"venue"
},
  "geometry": {"coordinates":[-1.171591,52.27187],"type":"Point"}
}