{
  "type": "Feature",
  "properties": {
    "iso:country":"GB",
    "sg:address":"25 Leaze Rd",
    "sg:city":"Frome",
    "sg:classifiers":[
        {
            "category":"Building & Trades",
            "subcategory":"Construction",
            "type":"Services"
        }
    ],
    "sg:phone":"+44 1373 466426",
    "sg:postcode":"BA11 3EY",
    "sg:province":"Somerset",
    "sg:tags":[
        "builder"
    ],
    "wof:name":"C & L Pearce Builders",
    "wof:placetype":"venue"
},
  "geometry": {"coordinates":[-2.335947,51.233555],"type":"Point"}
}