{
  "type": "Feature",
  "properties": {
    "addr:full":"24 Hazel Gro Wallingford Oxfordshire OX10 0TA",
    "addr:housenumber":"24",
    "addr:postcode":"ox10 0ta",
    "addr:street":"Hazel Gro",
    "iso:country":"GB",
    "sg:address":"24 Hazel Gro",
    "sg:city":"Wallingford",
    "sg:classifiers":[
        {
            "category":"Building & Trades",
            "subcategory":"Landscaping Services",
            "type":"Services"
        }
    ],
    "sg:phone":"+44 1491 202010",
    "sg:postcode":"OX10 0TA",
    "sg:province":"Oxfordshire",
    "sg:tags":[
        "irrigation",
        "system"
    ],
    "wof:name":"Logic Irrigation Ltd.",
    "wof:placetype":"venue"
},
  "geometry": {"coordinates":[-1.136089,51.60463],"type":"Point"}
}