{
  "type": "Feature",
  "properties": {
    "iso:country":"GB",
    "sg:address":"Unit 3 Queensway",
    "sg:city":"Andover",
    "sg:classifiers":[
        {
            "category":"Building & Trades",
            "subcategory":"Plumbing",
            "type":"Services"
        }
    ],
    "sg:phone":"+44 1933 679292",
    "sg:postcode":"SP10 5LG",
    "sg:province":"Hampshire",
    "sg:tags":[
        "drain",
        "clearance",
        "sewer"
    ],
    "wof:name":"Sewercare Ltd.",
    "wof:placetype":"venue"
},
  "geometry": {"coordinates":[-1.461829,51.219421],"type":"Point"}
}