{
  "type": "Feature",
  "properties": {
    "addr:full":"Lynwood House, Rowan Close Brackley Buckinghamshire NN13 6PB",
    "addr:postcode":"nn13 6pb",
    "addr:street":"Rowan Close",
    "iso:country":"GB",
    "sg:address":"Lynwood House, Rowan Close",
    "sg:city":"Brackley",
    "sg:classifiers":[
        {
            "category":"Professional",
            "subcategory":"Computer Services",
            "type":"Services"
        }
    ],
    "sg:postcode":"NN13 6PB",
    "sg:province":"Buckinghamshire",
    "sg:tags":[
        "system",
        "software"
    ],
    "wof:name":"I.T. Intelligence Consulting Ltd",
    "wof:placetype":"venue"
},
  "geometry": {"coordinates":[-1.1446529627,52.0397987366],"type":"Point"}
}