{
  "type": "Feature",
  "properties": {
    "addr:full":"Unit 1 Bath Business Centre Devizes Wiltshire SN10 1XA",
    "addr:housenumber":"unit 1",
    "addr:postcode":"sn10 1xa",
    "addr:street":"Bath Business Centre",
    "iso:country":"GB",
    "sg:address":"Unit 1 Bath Business Centre",
    "sg:city":"Devizes",
    "sg:classifiers":[
        {
            "category":"Professional",
            "type":"Services"
        }
    ],
    "sg:phone":"+44 1380 729199",
    "sg:postcode":"SN10 1XA",
    "sg:province":"Wiltshire",
    "sg:tags":[
        "valuer",
        "auctioneer"
    ],
    "wof:name":"Henry Aldridge & Son",
    "wof:placetype":"venue"
},
  "geometry": {"coordinates":[-2.0155301094,51.3509635925],"type":"Point"}
}