{
  "type": "Feature",
  "properties": {
    "iso:country":"GB",
    "sg:address":"8 Lymington Rd",
    "sg:city":"Dagenham",
    "sg:classifiers":[
        {
            "category":"Building & Trades",
            "subcategory":"Plumbing",
            "type":"Services"
        }
    ],
    "sg:phone":"+44 20 8597 2098",
    "sg:postcode":"RM8 1RP",
    "sg:province":"Essex",
    "sg:tags":[
        "central",
        "heating"
    ],
    "wof:name":"Water Tihght",
    "wof:placetype":"venue"
},
  "geometry": {"coordinates":[0.1322859973,51.5620384216],"type":"Point"}
}