{
  "type": "Feature",
  "properties": {
    "addr:full":"30 Mitchell Street Bury Lancashire BL8 1SF",
    "addr:housenumber":"30",
    "addr:postcode":"bl8 1sf",
    "addr:street":"Mitchell Street",
    "iso:country":"GB",
    "sg:address":"30 Mitchell Street",
    "sg:city":"Bury",
    "sg:classifiers":[
        {
            "category":"Building & Trades",
            "subcategory":"Construction",
            "type":"Services"
        }
    ],
    "sg:phone":"+44 161 797 4300",
    "sg:postcode":"BL8 1SF",
    "sg:province":"Lancashire",
    "sg:tags":[
        "platform",
        "work",
        "scaffolding"
    ],
    "wof:name":"A &A Scaffolding (Bury) Ltd.",
    "wof:placetype":"venue"
},
  "geometry": {"coordinates":[-2.317665,53.600662],"type":"Point"}
}