{
  "type": "Feature",
  "properties": {
    "iso:country":"GB",
    "sg:address":"22 Ellesmere Road, Uphill",
    "sg:city":"Weston-super-mare",
    "sg:classifiers":[
        {
            "category":"Building & Trades",
            "subcategory":"Construction",
            "type":"Services"
        }
    ],
    "sg:postcode":"BS23 4UT",
    "sg:province":"Somerset",
    "sg:tags":[
        "roofing"
    ],
    "wof:name":"N J Palmer",
    "wof:placetype":"venue"
},
  "geometry": {"coordinates":[-2.982187,51.323551],"type":"Point"}
}