{
  "type": "Feature",
  "properties": {
    "addr:full":"202 Manchester Road, Tyldesley Manchester Greater Manchester M29 8NN",
    "addr:housenumber":"202",
    "addr:postcode":"m29 8nn",
    "addr:street":"Manchester Road",
    "iso:country":"GB",
    "sg:address":"202 Manchester Road, Tyldesley",
    "sg:city":"Manchester",
    "sg:classifiers":[
        {
            "category":"Building & Trades",
            "subcategory":"Plumbing",
            "type":"Services"
        }
    ],
    "sg:phone":"+44 1942 882534",
    "sg:postcode":"M29 8NN",
    "sg:province":"Greater Manchester",
    "sg:tags":[
        "plumber",
        "heating"
    ],
    "wof:name":"Stephen Whittington",
    "wof:placetype":"venue"
},
  "geometry": {"coordinates":[-2.4516649246,53.5135574341],"type":"Point"}
}