{
  "type": "Feature",
  "properties": {
    "iso:country":"GB",
    "sg:address":"50 Hurstbourne Gardens",
    "sg:city":"Barking",
    "sg:classifiers":[
        {
            "category":"Government",
            "subcategory":"Department Of Motor Vehicles",
            "type":"Public Place"
        },
        {
            "category":"Sports & Exercise",
            "subcategory":"Tennis Court",
            "type":"Entertainment"
        }
    ],
    "sg:phone":"+44 20 8507 7604",
    "sg:postcode":"IG11 9UX",
    "sg:province":"Essex",
    "sg:tags":[
        "breakdown",
        "car",
        "recovery"
    ],
    "wof:name":"Haven Breakdown & Recovery",
    "wof:placetype":"venue"
},
  "geometry": {"coordinates":[0.091440998,51.5426635742],"type":"Point"}
}