{
  "type": "Feature",
  "properties": {
    "addr:full":"9 Weymouth St Warminster Somerset BA12 9NP",
    "addr:housenumber":"9",
    "addr:postcode":"ba12 9np",
    "addr:street":"Weymouth St",
    "iso:country":"GB",
    "sg:address":"9 Weymouth St",
    "sg:city":"Warminster",
    "sg:classifiers":[
        {
            "category":"Arts & Performance",
            "subcategory":"Art Gallery",
            "type":"Entertainment"
        }
    ],
    "sg:phone":"+44 1985 846377",
    "sg:postcode":"BA12 9NP",
    "sg:province":"Somerset",
    "wof:name":"Touchwood",
    "wof:placetype":"venue"
},
  "geometry": {"coordinates":[-2.1811499596,51.2044792175],"type":"Point"}
}