{
  "type": "Feature",
  "properties": {
    "iso:country":"GB",
    "sg:address":"31 Alexandra Road",
    "sg:city":"Thornton-cleveleys",
    "sg:classifiers":[
        {
            "category":"Personal",
            "type":"Services"
        }
    ],
    "sg:postcode":"FY5 5DB",
    "sg:province":"Lancashire",
    "sg:tags":[
        "wedding"
    ],
    "wof:name":"SERVICEOME WEDDING CARS",
    "wof:placetype":"venue"
},
  "geometry": {"coordinates":[-3.001476,53.868958],"type":"Point"}
}