{
  "type": "Feature",
  "properties": {
    "addr:full":"90 Victoria Road Oxford Oxfordshire OX2 7QE",
    "addr:housenumber":"90",
    "addr:postcode":"ox2 7qe",
    "addr:street":"Victoria Road",
    "iso:country":"GB",
    "sg:address":"90 Victoria Road",
    "sg:city":"Oxford",
    "sg:classifiers":[
        {
            "category":"Health Services",
            "subcategory":"Health Practitioner",
            "type":"Services"
        }
    ],
    "sg:phone":"+44 1865 553939",
    "sg:postcode":"OX2 7QE",
    "sg:province":"Oxfordshire",
    "sg:tags":[
        "acupuncture"
    ],
    "wof:name":"Hilda C Sanz-de-Deas",
    "wof:placetype":"venue"
},
  "geometry": {"coordinates":[-1.2616050243,51.7827682495],"type":"Point"}
}