{
  "type": "Feature",
  "properties": {
    "addr:full":"10 Cecil Mansions, Marius Road London Greater London SW17 7QN",
    "addr:housenumber":"10",
    "addr:postcode":"sw17 7qn",
    "addr:street":"Cecil Mansions Marius Road",
    "iso:country":"GB",
    "sg:address":"10 Cecil Mansions, Marius Road",
    "sg:city":"London",
    "sg:classifiers":[
        {
            "category":"Professional",
            "subcategory":"Computer Services",
            "type":"Services"
        }
    ],
    "sg:phone":"+44 20 8673 2618",
    "sg:postcode":"SW17 7QN",
    "sg:province":"Greater London",
    "sg:tags":[
        "system",
        "software"
    ],
    "wof:name":"A M  Simons Ltd.",
    "wof:placetype":"venue"
},
  "geometry": {"coordinates":[-0.1588999927,51.4400901794],"type":"Point"}
}