{
  "type": "Feature",
  "properties": {
    "addr:full":"21 Westville Road Bexhill-on-sea East Sussex TN39 3QB",
    "addr:housenumber":"21",
    "addr:postcode":"tn39 3qb",
    "addr:street":"Westville Road",
    "iso:country":"GB",
    "sg:address":"21 Westville Road",
    "sg:city":"Bexhill-on-sea",
    "sg:classifiers":[
        {
            "category":"Professional",
            "subcategory":"Engineering",
            "type":"Services"
        },
        {
            "category":"Building & Trades",
            "subcategory":"Electrical",
            "type":"Services"
        }
    ],
    "sg:phone":"+44 1424 221534",
    "sg:postcode":"TN39 3QB",
    "sg:province":"East Sussex",
    "sg:tags":[
        "engineer",
        "electrician",
        "contractor"
    ],
    "wof:name":"J R Coleman",
    "wof:placetype":"venue"
},
  "geometry": {"coordinates":[0.461112,50.842522],"type":"Point"}
}