{
  "type": "Feature",
  "properties": {
    "addr:full":"Gravelly Hill Market Drayton Shropshire TF9 4PN",
    "addr:postcode":"tf9 4pn",
    "iso:country":"GB",
    "sg:address":"Gravelly Hill",
    "sg:city":"Market Drayton",
    "sg:classifiers":[
        {
            "category":"Government",
            "subcategory":"City Hall",
            "type":"Public Place"
        }
    ],
    "sg:phone":"+44 1630 672905",
    "sg:postcode":"TF9 4PN",
    "sg:province":"Shropshire",
    "wof:name":"Ashley Memorial Hall",
    "wof:placetype":"venue"
},
  "geometry": {"coordinates":[-2.373834,52.924755],"type":"Point"}
}