{
  "type": "Feature",
  "properties": {
    "iso:country":"GB",
    "sg:address":"16 Brookdale Rd",
    "sg:city":"Leicester",
    "sg:classifiers":[
        {
            "category":"Building & Trades",
            "subcategory":"Construction",
            "type":"Services"
        }
    ],
    "sg:postcode":"LE3 6PU",
    "sg:province":"Leicestershire",
    "sg:tags":[
        "ventilation",
        "contractor"
    ],
    "wof:name":"Storer,Gerald,",
    "wof:placetype":"venue"
},
  "geometry": {"coordinates":[-1.193873,52.634422],"type":"Point"}
}