{
  "type": "Feature",
  "properties": {
    "iso:country":"GB",
    "sg:address":"85 Castle Hill Rd",
    "sg:city":"Wigan",
    "sg:classifiers":[
        {
            "category":"Autos & Motor Vehicles",
            "subcategory":"Automobile Sales",
            "type":"Retail Goods"
        }
    ],
    "sg:phone":"+44 1942 256055",
    "sg:postcode":"WN2 4BH",
    "sg:province":"Lancashire",
    "sg:tags":[
        "car"
    ],
    "wof:name":"Victoria Car Sales",
    "wof:placetype":"venue"
},
  "geometry": {"coordinates":[-2.561279,53.541019],"type":"Point"}
}