{
  "type": "Feature",
  "properties": {
    "addr:full":"66 Stebondale Street London Greater London E14 3BX",
    "addr:housenumber":"66",
    "addr:postcode":"e14 3bx",
    "addr:street":"Stebondale Street",
    "iso:country":"GB",
    "sg:address":"66 Stebondale Street",
    "sg:city":"London",
    "sg:classifiers":[
        {
            "category":"Community Center",
            "subcategory":"Youth",
            "type":"Public Place"
        }
    ],
    "sg:postcode":"E14 3BX",
    "sg:province":"Greater London",
    "sg:tags":[
        "organisation",
        "centre"
    ],
    "wof:name":"Ellen Elizabeth Marine Venture Ltd.",
    "wof:placetype":"venue"
},
  "geometry": {"coordinates":[-0.0081270002,51.4906234741],"type":"Point"}
}