{
  "type": "Feature",
  "properties": {
    "iso:country":"GB",
    "sg:address":"Unit 5, Queensway Shopping Centre, Queensway",
    "sg:city":"Banbury",
    "sg:classifiers":[
        {
            "category":"Food & Beverages",
            "subcategory":"Meat & Fish",
            "type":"Retail Goods"
        }
    ],
    "sg:phone":"+44 1295 251468",
    "sg:postcode":"OX16 9LY",
    "sg:province":"Oxfordshire",
    "sg:tags":[
        "chip"
    ],
    "wof:name":"Queensway Fish Saloon",
    "wof:placetype":"venue"
},
  "geometry": {"coordinates":[-1.351779,52.056274],"type":"Point"}
}