{
  "type": "Feature",
  "properties": {
    "addr:full":"4 The Square, Glamis Forfar Angus DD8 1RS",
    "addr:housenumber":"4",
    "addr:postcode":"dd8 1rs",
    "addr:street":"The Square Glamis",
    "iso:country":"GB",
    "sg:address":"4 The Square, Glamis",
    "sg:city":"Forfar",
    "sg:classifiers":[
        {
            "category":"Food & Beverages",
            "subcategory":"Fruits & Vegetables",
            "type":"Retail Goods"
        }
    ],
    "sg:phone":"+44 1307 840222",
    "sg:postcode":"DD8 1RS",
    "sg:province":"Angus",
    "sg:tags":[
        "greengrocer"
    ],
    "wof:name":"The Corner Shop",
    "wof:placetype":"venue"
},
  "geometry": {"coordinates":[-3.0029139519,56.6084060669],"type":"Point"}
}