{
  "type": "Feature",
  "properties": {
    "iso:country":"GB",
    "sg:address":"Green Farm, Mattishall Road",
    "sg:city":"Dereham",
    "sg:classifiers":[
        {
            "category":"Farming",
            "subcategory":"Farm",
            "type":"Manufacturing & Wholesale Goods"
        }
    ],
    "sg:postcode":"NR20 3LR",
    "sg:province":"Norfolk",
    "sg:tags":[
        "mixed",
        "crop"
    ],
    "wof:name":"A L Alston & Co. Ltd.",
    "wof:placetype":"venue"
},
  "geometry": {"coordinates":[1.035701,52.659676],"type":"Point"}
}