{
  "type": "Feature",
  "properties": {
    "iso:country":"GB",
    "sg:address":"Protea Way, Pixmore Avenue",
    "sg:city":"Letchworth",
    "sg:classifiers":[
        {
            "category":"Manufacturing",
            "subcategory":"Wood Products",
            "type":"Manufacturing & Wholesale Goods"
        }
    ],
    "sg:phone":"+44 1462 480808",
    "sg:postcode":"SG6 1JT",
    "sg:province":"Hertfordshire",
    "sg:tags":[
        "packaging",
        "crate",
        "pallets"
    ],
    "wof:name":"Gelplas Ltd.",
    "wof:placetype":"venue"
},
  "geometry": {"coordinates":[-0.215253,51.981079],"type":"Point"}
}