{
  "type": "Feature",
  "properties": {
    "iso:country":"GB",
    "sg:address":"1b St Lawrences Road",
    "sg:city":"Coventry",
    "sg:classifiers":[
        {
            "category":"Utilities",
            "subcategory":"Telephone",
            "type":"Services"
        }
    ],
    "sg:postcode":"CV6 7AE",
    "sg:province":"Warwickshire",
    "sg:tags":[
        "telecommunication"
    ],
    "wof:name":"T M Communications",
    "wof:placetype":"venue"
},
  "geometry": {"coordinates":[-1.4929430485,52.437210083],"type":"Point"}
}