{
  "type": "Feature",
  "properties": {
    "addr:full":"Station Yard, Victoria Bridge Milford Haven Pembrokeshire SA73 1BY",
    "addr:housenumber":"milford",
    "addr:postcode":"sa73 1by",
    "addr:street":"Victoria Bridge",
    "iso:country":"GB",
    "sg:address":"Station Yard, Victoria Bridge",
    "sg:city":"Milford Haven",
    "sg:classifiers":[
        {
            "category":"Taxi",
            "type":"Transportation"
        }
    ],
    "sg:phone":"+44 1646 697472",
    "sg:postcode":"SA73 1BY",
    "sg:province":"Pembrokeshire",
    "sg:tags":[
        "mini",
        "cab"
    ],
    "wof:name":"M.G Taxis",
    "wof:placetype":"venue"
},
  "geometry": {"coordinates":[-4.945544,51.705765],"type":"Point"}
}