{
  "type": "Feature",
  "properties": {
    "iso:country":"GB",
    "sg:address":"84-86 Clarendon Road",
    "sg:city":"Southsea",
    "sg:classifiers":[
        {
            "category":"Home & Garden",
            "subcategory":"Home Furnishings",
            "type":"Retail Goods"
        }
    ],
    "sg:postcode":"PO5 2PB",
    "sg:province":"Hampshire",
    "sg:tags":[
        "awning",
        "canopy",
        "blinds"
    ],
    "wof:name":"Southern Blinds",
    "wof:placetype":"venue"
},
  "geometry": {"coordinates":[-1.080464,50.781273],"type":"Point"}
}