{
  "type": "Feature",
  "properties": {
    "addr:full":"Rear Of 42 Vandyke Road Leighton Buzzard Bedfordshire LU7 3HH",
    "addr:housenumber":"rear of 42",
    "addr:postcode":"lu7 3hh",
    "addr:street":"Vandyke Road",
    "iso:country":"GB",
    "sg:address":"Rear Of 42 Vandyke Road",
    "sg:city":"Leighton Buzzard",
    "sg:classifiers":[
        {
            "category":"Professional",
            "type":"Services"
        }
    ],
    "sg:phone":"+44 1525 372182",
    "sg:postcode":"LU7 3HH",
    "sg:province":"Bedfordshire",
    "sg:tags":[
        "repair",
        "tech",
        "maintenance"
    ],
    "wof:name":"Business Computer Consultancy Ltd.",
    "wof:placetype":"venue"
},
  "geometry": {"coordinates":[-0.663909018,51.917350769],"type":"Point"}
}