{
  "type": "Feature",
  "properties": {
    "addr:full":"2 Oakley Rd Wimborne Dorset BH21 1QJ",
    "addr:housenumber":"2",
    "addr:postcode":"bh21 1qj",
    "addr:street":"Oakley Rd",
    "iso:country":"GB",
    "sg:address":"2 Oakley Rd",
    "sg:city":"Wimborne",
    "sg:classifiers":[
        {
            "category":"Travel",
            "subcategory":"Hotels & Motels",
            "type":"Entertainment"
        }
    ],
    "sg:postcode":"BH21 1QJ",
    "sg:province":"Dorset",
    "sg:tags":[
        "house",
        "guest"
    ],
    "wof:name":"Acacia House",
    "wof:placetype":"venue"
},
  "geometry": {"coordinates":[-1.9767429829,50.7883796692],"type":"Point"}
}