{
  "type": "Feature",
  "properties": {
    "iso:country":"GB",
    "sg:address":"80 Union Rd",
    "sg:city":"Bradford",
    "sg:classifiers":[
        {
            "category":"Personal",
            "subcategory":"Nail Salon",
            "type":"Services"
        }
    ],
    "sg:phone":"+44 1274 604586",
    "sg:postcode":"BD12 0DF",
    "sg:province":"West Yorkshire",
    "sg:tags":[
        "solarium",
        "tanning"
    ],
    "wof:name":"Oasis",
    "wof:placetype":"venue"
},
  "geometry": {"coordinates":[-1.772614,53.758881],"type":"Point"}
}