{
  "type": "Feature",
  "properties": {
    "addr:full":"Barrett Browning Institute, The Homend Ledbury Gloucestershire HR8 1BT",
    "addr:postcode":"hr8 1bt",
    "iso:country":"GB",
    "sg:address":"Barrett Browning Institute, The Homend",
    "sg:city":"Ledbury",
    "sg:classifiers":[
        {
            "category":"Education",
            "subcategory":"Library",
            "type":"Public Place"
        }
    ],
    "sg:phone":"+44 1531 632133",
    "sg:postcode":"HR8 1BT",
    "sg:province":"Gloucestershire",
    "sg:tags":[
        "book"
    ],
    "wof:name":"South Herefordshire District Council",
    "wof:placetype":"venue"
},
  "geometry": {"coordinates":[-2.4243400097,52.0389404297],"type":"Point"}
}