{
  "type": "Feature",
  "properties": {
    "addr:full":"Beaumont Ho, Avonmore Rd West Kensington Greater London W14 8TS",
    "addr:postcode":"w14 8ts",
    "addr:street":"Avonmore Rd",
    "iso:country":"GB",
    "sg:address":"Beaumont Ho, Avonmore Rd",
    "sg:city":"West Kensington",
    "sg:classifiers":[
        {
            "category":"Communications",
            "subcategory":"Film & Video Production",
            "type":"Services"
        }
    ],
    "sg:phone":"+44 20 7605 2401",
    "sg:postcode":"W14 8TS",
    "sg:province":"Greater London",
    "sg:tags":[
        "tv",
        "studio"
    ],
    "wof:name":"Walt Disney Productions",
    "wof:placetype":"venue"
},
  "geometry": {"coordinates":[-0.210473,51.495476],"type":"Point"}
}