{
  "type": "Feature",
  "properties": {
    "iso:country":"GB",
    "sg:address":"715 Stockport Rd",
    "sg:city":"Manchester",
    "sg:classifiers":[
        {
            "category":"Retail",
            "subcategory":"Auto Repair",
            "type":"Services"
        }
    ],
    "sg:phone":"+44 161 225 1915",
    "sg:postcode":"M19 3AG",
    "sg:province":"Greater Manchester",
    "sg:tags":[
        "electrician"
    ],
    "wof:name":"Auto Electrical Services",
    "wof:placetype":"venue"
},
  "geometry": {"coordinates":[-2.1919078827,53.4485588074],"type":"Point"}
}