{
  "type": "Feature",
  "properties": {
    "addr:full":"72 Norfolk Road, Cliftonville Margate Kent CT9 2HZ",
    "addr:housenumber":"72",
    "addr:postcode":"ct9 2hz",
    "addr:street":"Norfolk Road;Margate",
    "iso:country":"GB",
    "sg:address":"72 Norfolk Road, Cliftonville",
    "sg:city":"Margate",
    "sg:classifiers":[
        {
            "category":"Building & Trades",
            "subcategory":"Construction",
            "type":"Services"
        }
    ],
    "sg:postcode":"CT9 2HZ",
    "sg:province":"Kent",
    "sg:tags":[
        "builder"
    ],
    "wof:name":"Noakes Builders",
    "wof:placetype":"venue"
},
  "geometry": {"coordinates":[1.4006340504,51.3881645203],"type":"Point"}
}