{
  "type": "Feature",
  "properties": {
    "iso:country":"GB",
    "sg:address":"Duart House, 31 St John Street",
    "sg:city":"Lichfield",
    "sg:classifiers":[
        {
            "category":"Organizations",
            "subcategory":"Political Organization",
            "type":"Services"
        }
    ],
    "sg:phone":"+44 1543 417868",
    "sg:postcode":"WS13 6NU",
    "sg:province":"Staffordshire",
    "sg:tags":[
        "party"
    ],
    "wof:name":"Conservative Association",
    "wof:placetype":"venue"
},
  "geometry": {"coordinates":[-1.8281799555,52.6812667847],"type":"Point"}
}