{
  "type": "Feature",
  "properties": {
    "addr:full":"Compass House, Common Road, Dunnington York North Yorkshire YO19 5PD",
    "addr:postcode":"yo19 5pd",
    "addr:street":"Common Road",
    "iso:country":"GB",
    "sg:address":"Compass House, Common Road, Dunnington",
    "sg:city":"York",
    "sg:classifiers":[
        {
            "category":"Professional",
            "subcategory":"Business Services",
            "type":"Services"
        },
        {
            "category":"Retail",
            "subcategory":"Storage",
            "type":"Services"
        }
    ],
    "sg:phone":"+44 1904 488488",
    "sg:postcode":"YO19 5PD",
    "sg:province":"North Yorkshire",
    "sg:tags":[
        "import",
        "household",
        "export",
        "agent",
        "removal"
    ],
    "wof:name":"Bootham International",
    "wof:placetype":"venue"
},
  "geometry": {"coordinates":[-0.9789609909,53.9647827148],"type":"Point"}
}