{
  "type": "Feature",
  "properties": {
    "addr:full":"1 Ryshworth Bridge Bingley West Yorkshire BD16 2DX",
    "addr:housenumber":"1",
    "addr:postcode":"bd16 2dx",
    "addr:street":"Ryshworth Bridge Bingley West",
    "iso:country":"GB",
    "sg:address":"1 Ryshworth Bridge",
    "sg:city":"Bingley",
    "sg:classifiers":[
        {
            "category":"Shopping",
            "subcategory":"Department Store",
            "type":"Retail Goods"
        },
        {
            "category":"Shopping",
            "subcategory":"Musical Instruments",
            "type":"Retail Goods"
        }
    ],
    "sg:phone":"+44 1274 510050",
    "sg:postcode":"BD16 2DX",
    "sg:province":"West Yorkshire",
    "sg:tags":[
        "music",
        "sheet"
    ],
    "wof:name":"Windstruments",
    "wof:placetype":"venue"
},
  "geometry": {"coordinates":[-1.8496489525,53.86485672],"type":"Point"}
}