{
  "type": "Feature",
  "properties": {
    "iso:country":"GB",
    "sg:address":"1 Wardpark Road, Wardpark South, Cumbernauld",
    "sg:city":"Glasgow",
    "sg:classifiers":[
        {
            "category":"Building & Trades",
            "subcategory":"Landscaping Services",
            "type":"Services"
        }
    ],
    "sg:phone":"+44 1236 721111",
    "sg:postcode":"G67 3JZ",
    "sg:province":"Falkirk",
    "sg:tags":[
        "horticultural",
        "consultant"
    ],
    "wof:name":"H M Plant",
    "wof:placetype":"venue"
},
  "geometry": {"coordinates":[-3.960139,55.968899],"type":"Point"}
}