{
  "type": "Feature",
  "properties": {
    "addr:full":"Unit 2, 38 Stanstead Road Hoddesdon Essex EN11 0RH",
    "addr:housenumber":"unit;38",
    "addr:postcode":"en11 0rh",
    "addr:street":"Stanstead Road",
    "iso:country":"GB",
    "sg:address":"Unit 2, 38 Stanstead Road",
    "sg:city":"Hoddesdon",
    "sg:classifiers":[
        {
            "category":"Taxi",
            "type":"Transportation"
        }
    ],
    "sg:postcode":"EN11 0RH",
    "sg:province":"Essex",
    "sg:tags":[
        "mini",
        "cab"
    ],
    "wof:name":"Hoddesdon Car Service",
    "wof:placetype":"venue"
},
  "geometry": {"coordinates":[-0.008036,51.767685],"type":"Point"}
}