{
  "type": "Feature",
  "properties": {
    "iso:country":"GB",
    "sg:address":"Nile Mill, Fields New Road, Chadderton",
    "sg:city":"Oldham",
    "sg:classifiers":[
        {
            "category":"Home & Garden",
            "subcategory":"Furniture",
            "type":"Retail Goods"
        }
    ],
    "sg:phone":"+44 161 626 9915",
    "sg:postcode":"OL9 8NT",
    "sg:province":"Lancashire",
    "wof:name":"Nile Mill Textiles",
    "wof:placetype":"venue"
},
  "geometry": {"coordinates":[-2.143439,53.53672],"type":"Point"}
}