{
  "type": "Feature",
  "properties": {
    "iso:country":"GB",
    "sg:address":"2 Armour Road, Tilehurst",
    "sg:city":"Reading",
    "sg:classifiers":[
        {
            "category":"Shopping",
            "subcategory":"Pets & Pet Supplies",
            "type":"Retail Goods"
        }
    ],
    "sg:phone":"+44 118 942 8145",
    "sg:postcode":"RG31 6HT",
    "sg:province":"Berkshire",
    "wof:name":"Pets & Plants",
    "wof:placetype":"venue"
},
  "geometry": {"coordinates":[-1.036497,51.461391],"type":"Point"}
}