{
  "type": "Feature",
  "properties": {
    "addr:full":"127 Mosley Common Rd Manchester Greater Manchester M28 4AH",
    "addr:housenumber":"127",
    "addr:postcode":"m28 4ah",
    "addr:street":"Mosley Common Rd",
    "iso:country":"GB",
    "sg:address":"127 Mosley Common Rd",
    "sg:city":"Manchester",
    "sg:classifiers":[
        {
            "category":"Fast Food",
            "type":"Food & Drink"
        }
    ],
    "sg:phone":"+44 161 790 3300",
    "sg:postcode":"M28 4AH",
    "sg:province":"Greater Manchester",
    "sg:tags":[
        "away",
        "take"
    ],
    "wof:name":"Simla Indian Takeaway",
    "wof:placetype":"venue"
},
  "geometry": {"coordinates":[-2.431553,53.508614],"type":"Point"}
}