{
  "type": "Feature",
  "properties": {
    "addr:full":"52 King Street Southall Greater London UB2 4DB",
    "addr:housenumber":"52",
    "addr:postcode":"ub2 4db",
    "addr:street":"King Street",
    "iso:country":"GB",
    "sg:address":"52 King Street",
    "sg:city":"Southall",
    "sg:classifiers":[
        {
            "category":"Real Estate",
            "subcategory":"Real Estate Operator",
            "type":"Services"
        }
    ],
    "sg:postcode":"UB2 4DB",
    "sg:province":"Greater London",
    "sg:tags":[
        "letting",
        "agent"
    ],
    "wof:name":"Westcote Lettings Ltd",
    "wof:placetype":"venue"
},
  "geometry": {"coordinates":[-0.383266,51.500412],"type":"Point"}
}