{
  "type": "Feature",
  "properties": {
    "iso:country":"GB",
    "sg:address":"Almey Lane Earl Shilton",
    "sg:city":"Leicester",
    "sg:classifiers":[
        {
            "category":"Place Of Worship",
            "type":"Public Place"
        }
    ],
    "sg:phone":"+44 1455 843961",
    "sg:postcode":"LE1 1QE",
    "sg:province":"Leicestershire",
    "wof:name":"St Simon & St Jude Parish Church",
    "wof:placetype":"venue"
},
  "geometry": {"coordinates":[-1.140365,52.637886],"type":"Point"}
}