{
  "type": "Feature",
  "properties": {
    "addr:full":"67 Haigh Lane, Hoylandswaine Sheffield South Yorkshire S36 7JQ",
    "addr:housenumber":"67",
    "addr:postcode":"s36 7jq",
    "addr:street":"Haigh Lane",
    "iso:country":"GB",
    "sg:address":"67 Haigh Lane, Hoylandswaine",
    "sg:city":"Sheffield",
    "sg:classifiers":[
        {
            "category":"Autos & Motor Vehicles",
            "subcategory":"Automobile Sales",
            "type":"Retail Goods"
        }
    ],
    "sg:postcode":"S36 7JQ",
    "sg:province":"South Yorkshire",
    "sg:tags":[
        "car"
    ],
    "wof:name":"Andy McGuinness",
    "wof:placetype":"venue"
},
  "geometry": {"coordinates":[-1.6092040539,53.5420684814],"type":"Point"}
}