{
  "type": "Feature",
  "properties": {
    "iso:country":"GB",
    "sg:address":"Leigh House, 7 Station Approach",
    "sg:city":"Bexleyheath",
    "sg:classifiers":[
        {
            "category":"Professional",
            "subcategory":"Business Services",
            "type":"Services"
        }
    ],
    "sg:phone":"+44 20 8301 2626",
    "sg:postcode":"DA7 4QP",
    "sg:province":"Kent",
    "sg:tags":[
        "import",
        "export",
        "agent"
    ],
    "wof:name":"Chapman Dempsey",
    "wof:placetype":"venue"
},
  "geometry": {"coordinates":[0.132859,51.463848],"type":"Point"}
}