{
  "type": "Feature",
  "properties": {
    "addr:full":"15 Cinques Road, Gamlingay Sandy Bedfordshire SG19 3NJ",
    "addr:housenumber":"15",
    "addr:postcode":"sg19 3nj",
    "addr:street":"Cinques Road",
    "iso:country":"GB",
    "sg:address":"15 Cinques Road, Gamlingay",
    "sg:city":"Sandy",
    "sg:classifiers":[
        {
            "category":"Government",
            "subcategory":"Post Office",
            "type":"Public Place"
        }
    ],
    "sg:phone":"+44 1767 650276",
    "sg:postcode":"SG19 3NJ",
    "sg:province":"Bedfordshire",
    "wof:name":"Gamlingay Post Office",
    "wof:placetype":"venue"
},
  "geometry": {"coordinates":[-0.1944559962,52.1569328308],"type":"Point"}
}