{
  "type": "Feature",
  "properties": {
    "iso:country":"GB",
    "sg:address":"Bryn Meurig, Lombard Street",
    "sg:city":"Dolgellau",
    "sg:classifiers":[
        {
            "category":"Organizations",
            "subcategory":"Political Organization",
            "type":"Services"
        }
    ],
    "sg:phone":"+44 1341 422661",
    "sg:postcode":"LL40 1DS",
    "sg:province":"Gwynedd",
    "sg:tags":[
        "party"
    ],
    "wof:name":"Mentrau Plaid Cymru Cyf",
    "wof:placetype":"venue"
},
  "geometry": {"coordinates":[-3.886729,52.741009],"type":"Point"}
}