{
  "type": "Feature",
  "properties": {
    "iso:country":"GB",
    "sg:address":"5 Charlotte Square",
    "sg:city":"Newcastle-upon-tyne",
    "sg:classifiers":[
        {
            "category":"Manufacturing",
            "subcategory":"Tools & Machinery",
            "type":"Manufacturing & Wholesale Goods"
        }
    ],
    "sg:phone":"+44 191 232 1721",
    "sg:postcode":"NE1 4XF",
    "sg:province":"Tyne and Wear",
    "sg:tags":[
        "society",
        "friendly"
    ],
    "wof:name":"Blackfriars Insurance Services",
    "wof:placetype":"venue"
},
  "geometry": {"coordinates":[-1.6200369596,54.9713096619],"type":"Point"}
}