{
  "type": "Feature",
  "properties": {
    "iso:country":"GB",
    "sg:address":"252 Moston Lane, Moston",
    "sg:city":"Manchester",
    "sg:classifiers":[
        {
            "category":"Home & Garden",
            "subcategory":"Hardware",
            "type":"Retail Goods"
        }
    ],
    "sg:postcode":"M40 9WF",
    "sg:province":"Greater Manchester",
    "wof:name":"Pauls Hardware Plus",
    "wof:placetype":"venue"
},
  "geometry": {"coordinates":[-2.194989,53.510841],"type":"Point"}
}