{
  "type": "Feature",
  "properties": {
    "addr:full":"2 Bedford Street Sunderland Tyne and Wear SR1 1TT",
    "addr:housenumber":"2",
    "addr:postcode":"sr1 1tt",
    "addr:street":"Bedford Street",
    "iso:country":"GB",
    "sg:address":"2 Bedford Street",
    "sg:city":"Sunderland",
    "sg:classifiers":[
        {
            "category":"Bars & Pubs",
            "type":"Food & Drink"
        }
    ],
    "sg:postcode":"SR1 1TT",
    "sg:province":"Tyne and Wear",
    "sg:tags":[
        "pubs",
        "inn"
    ],
    "wof:name":"Rose and Crown",
    "wof:placetype":"venue"
},
  "geometry": {"coordinates":[-1.380669,54.907822],"type":"Point"}
}