{
  "type": "Feature",
  "properties": {
    "iso:country":"GB",
    "sg:address":"Prospect Rd, Sandgate",
    "sg:city":"Folkestone",
    "sg:classifiers":[
        {
            "category":"Professional",
            "subcategory":"Business Services",
            "type":"Services"
        }
    ],
    "sg:phone":"+44 1303 242233",
    "sg:postcode":"CT20 3DG",
    "sg:province":"Kent",
    "sg:tags":[
        "import",
        "export",
        "agent"
    ],
    "wof:name":"Euroflex 92 Ltd",
    "wof:placetype":"venue"
},
  "geometry": {"coordinates":[1.177945,51.084431],"type":"Point"}
}