{
  "type": "Feature",
  "properties": {
    "iso:country":"GB",
    "sg:address":"Grove St",
    "sg:city":"Liverpool",
    "sg:classifiers":[
        {
            "category":"Health Services",
            "subcategory":"Doctor",
            "type":"Services"
        }
    ],
    "sg:phone":"+44 151 709 2806",
    "sg:postcode":"L7 7HG",
    "sg:province":"Merseyside",
    "sg:tags":[
        "practitioners"
    ],
    "wof:name":"Saverimuttu, R K",
    "wof:placetype":"venue"
},
  "geometry": {"coordinates":[-2.9622189999,53.4015350342],"type":"Point"}
}