{
  "type": "Feature",
  "properties": {
    "addr:full":"18 High Street, Kempston Bedford Bedfordshire MK42 7AJ",
    "addr:housenumber":"18",
    "addr:postcode":"mk42 7aj",
    "addr:street":"High Street",
    "iso:country":"GB",
    "sg:address":"18 High Street, Kempston",
    "sg:city":"Bedford",
    "sg:classifiers":[
        {
            "category":"Bars & Pubs",
            "type":"Food & Drink"
        }
    ],
    "sg:phone":"+44 1234 853767",
    "sg:postcode":"MK42 7AJ",
    "sg:province":"Bedfordshire",
    "sg:tags":[
        "pubs",
        "inn"
    ],
    "wof:name":"Greene King Plc",
    "wof:placetype":"venue"
},
  "geometry": {"coordinates":[-0.501644,52.115913],"type":"Point"}
}