{
  "type": "Feature",
  "properties": {
    "addr:full":"11 Cyril Street Leicester Leicestershire LE3 2FF",
    "addr:housenumber":"11",
    "addr:postcode":"le3 2ff",
    "addr:street":"Cyril Street",
    "iso:country":"GB",
    "sg:address":"11 Cyril Street",
    "sg:city":"Leicester",
    "sg:classifiers":[
        {
            "category":"Food & Beverages",
            "subcategory":"Bakery",
            "type":"Retail Goods"
        }
    ],
    "sg:phone":"+44 116 263 0846",
    "sg:postcode":"LE3 2FF",
    "sg:province":"Leicestershire",
    "sg:tags":[
        "confectionery"
    ],
    "wof:name":"Leicester Cake Decorating Supplies",
    "wof:placetype":"venue"
},
  "geometry": {"coordinates":[-1.1687710285,52.609500885],"type":"Point"}
}