{
  "type": "Feature",
  "properties": {
    "addr:full":"Alexandra House, 10 Station Rd, Wood Green Hornsey Greater London N8 8DU",
    "addr:housenumber":"10",
    "addr:postcode":"n8 8du",
    "addr:street":"Station Rd",
    "iso:country":"GB",
    "sg:address":"Alexandra House, 10 Station Rd, Wood Green",
    "sg:city":"Hornsey",
    "sg:classifiers":[
        {
            "category":"Social Services",
            "type":"Services"
        }
    ],
    "sg:phone":"+44 20 8489 0000",
    "sg:postcode":"N8 8DU",
    "sg:province":"Greater London",
    "wof:name":"Social Services",
    "wof:placetype":"venue"
},
  "geometry": {"coordinates":[-0.120637998,51.5818328857],"type":"Point"}
}