{
  "type": "Feature",
  "properties": {
    "addr:full":"Unit 1 High Town Enterprise Cent, Re Luton Bedfordshire LU2 0HA",
    "addr:housenumber":"unit 1 high",
    "addr:postcode":"lu2 0ha",
    "addr:street":"Town",
    "iso:country":"GB",
    "sg:address":"Unit 1 High Town Enterprise Cent, Re",
    "sg:city":"Luton",
    "sg:classifiers":[
        {
            "category":"Professional",
            "subcategory":"Printing & Photocopies",
            "type":"Services"
        }
    ],
    "sg:phone":"+44 1582 877474",
    "sg:postcode":"LU2 0HA",
    "sg:province":"Bedfordshire",
    "sg:tags":[
        "embroiderer"
    ],
    "wof:name":"Raju Embroidery",
    "wof:placetype":"venue"
},
  "geometry": {"coordinates":[-0.409274,51.886105],"type":"Point"}
}