{
  "type": "Feature",
  "properties": {
    "iso:country":"GB",
    "sg:address":"103 Market Street",
    "sg:city":"Bolton",
    "sg:classifiers":[
        {
            "category":"Recreation",
            "subcategory":"Dance Hall",
            "type":"Entertainment"
        }
    ],
    "sg:phone":"+44 1204 796268",
    "sg:postcode":"BL4 7NS",
    "sg:province":"Lancashire",
    "sg:tags":[
        "disco"
    ],
    "wof:name":"Chuffers Discotheque",
    "wof:placetype":"venue"
},
  "geometry": {"coordinates":[-2.393855,53.549156],"type":"Point"}
}