{
  "type": "Feature",
  "properties": {
    "addr:full":"16 Wootton Road King's Lynn Norfolk PE30 4EX",
    "addr:housenumber":"16",
    "addr:postcode":"pe30 4ex",
    "addr:street":"Wootton Road",
    "iso:country":"GB",
    "sg:address":"16 Wootton Road",
    "sg:city":"King's Lynn",
    "sg:classifiers":[
        {
            "category":"Food & Beverages",
            "subcategory":"Bakery",
            "type":"Retail Goods"
        }
    ],
    "sg:phone":"+44 1553 774372",
    "sg:postcode":"PE30 4EX",
    "sg:province":"Norfolk",
    "sg:tags":[
        "shop",
        "baker",
        "confectionery"
    ],
    "wof:name":"Ridouts Bakery",
    "wof:placetype":"venue"
},
  "geometry": {"coordinates":[0.42136,52.757999],"type":"Point"}
}