{
  "type": "Feature",
  "properties": {
    "addr:full":"Cromwell Works Tenbury Wells Herefordshire WR15 8LF",
    "addr:postcode":"wr15 8lf",
    "iso:country":"GB",
    "sg:address":"Cromwell Works",
    "sg:city":"Tenbury Wells",
    "sg:classifiers":[
        {
            "category":"Professional",
            "subcategory":"Business Services",
            "type":"Services"
        }
    ],
    "sg:phone":"+44 1584 811000",
    "sg:postcode":"WR15 8LF",
    "sg:province":"Herefordshire",
    "sg:tags":[
        "holding"
    ],
    "wof:name":"Howle Holdings Plc",
    "wof:placetype":"venue"
},
  "geometry": {"coordinates":[-2.594178915,52.3125839233],"type":"Point"}
}