{
  "type": "Feature",
  "properties": {
    "iso:country":"GB",
    "sg:address":"16 St Johns Street",
    "sg:city":"Cambridge",
    "sg:classifiers":[
        {
            "category":"Shopping",
            "subcategory":"Shoes",
            "type":"Retail Goods"
        }
    ],
    "sg:phone":"+44 1223 300677",
    "sg:postcode":"CB2 1TW",
    "sg:province":"Cambridgeshire",
    "sg:tags":[
        "shop",
        "retailer",
        "footwear"
    ],
    "wof:name":"Amanda Green Shoes",
    "wof:placetype":"venue"
},
  "geometry": {"coordinates":[0.1184239984,52.2080764771],"type":"Point"}
}