{
  "type": "Feature",
  "properties": {
    "addr:full":"39 Bridge Street Wrexham Wrexham LL13 7HP",
    "addr:housenumber":"39",
    "addr:postcode":"ll13 7hp",
    "addr:street":"Bridge Street",
    "iso:country":"GB",
    "sg:address":"39 Bridge Street",
    "sg:city":"Wrexham",
    "sg:classifiers":[
        {
            "category":"Personal",
            "subcategory":"Psychics & Astrologers",
            "type":"Services"
        }
    ],
    "sg:postcode":"LL13 7HP",
    "sg:province":"Wrexham",
    "sg:tags":[
        "clairvoyant",
        "palmist"
    ],
    "wof:name":"Paul Gronow",
    "wof:placetype":"venue"
},
  "geometry": {"coordinates":[-2.9956250191,53.0437164307],"type":"Point"}
}