{
  "type": "Feature",
  "properties": {
    "iso:country":"GB",
    "sg:address":"36a Galley Lane",
    "sg:city":"Barnet",
    "sg:classifiers":[
        {
            "category":"Home & Garden",
            "subcategory":"Garden Supply",
            "type":"Retail Goods"
        }
    ],
    "sg:postcode":"EN5 4AJ",
    "sg:province":"Hertfordshire",
    "sg:tags":[
        "planting",
        "tree",
        "shrub"
    ],
    "wof:name":"Leahurst Nursery",
    "wof:placetype":"venue"
},
  "geometry": {"coordinates":[-0.2274509966,51.6578636169],"type":"Point"}
}