{
  "type": "Feature",
  "properties": {
    "iso:country":"GB",
    "sg:address":"Ashley Rd, Parkstone",
    "sg:city":"Poole",
    "sg:classifiers":[
        {
            "category":"Place Of Worship",
            "type":"Public Place"
        }
    ],
    "sg:phone":"+44 1202 736030",
    "sg:postcode":"BH14 0AW",
    "sg:province":"Dorset",
    "wof:name":"Ashley Road Methodist Church",
    "wof:placetype":"venue"
},
  "geometry": {"coordinates":[-1.952045,50.730774],"type":"Point"}
}