{
  "type": "Feature",
  "properties": {
    "addr:full":"9 Bilston Street, Sedgley Dudley Staffordshire DY3 1JA",
    "addr:housenumber":"9",
    "addr:postcode":"dy3 1ja",
    "addr:street":"Bilston Street",
    "iso:country":"GB",
    "sg:address":"9 Bilston Street, Sedgley",
    "sg:city":"Dudley",
    "sg:classifiers":[
        {
            "category":"Shopping",
            "subcategory":"Shoes",
            "type":"Retail Goods"
        }
    ],
    "sg:phone":"+44 1902 670076",
    "sg:postcode":"DY3 1JA",
    "sg:province":"Staffordshire",
    "sg:tags":[
        "shop"
    ],
    "wof:name":"Sedgley Shoes",
    "wof:placetype":"venue"
},
  "geometry": {"coordinates":[-2.120088,52.542645],"type":"Point"}
}