{
  "type": "Feature",
  "properties": {
    "addr:full":"Barclays Bank Chambers, Severn Street Newtown Powys SY16 2AQ",
    "addr:postcode":"sy16 2aq",
    "addr:street":"Severn Street",
    "iso:country":"GB",
    "sg:address":"Barclays Bank Chambers, Severn Street",
    "sg:city":"Newtown",
    "sg:classifiers":[
        {
            "category":"Professional",
            "subcategory":"Accounting & Tax Preparation",
            "type":"Services"
        }
    ],
    "sg:postcode":"SY16 2AQ",
    "sg:province":"Powys",
    "sg:tags":[
        "accountant"
    ],
    "wof:name":"Robert L Davies & Co",
    "wof:placetype":"venue"
},
  "geometry": {"coordinates":[-3.3146119118,52.5127754211],"type":"Point"}
}