{
  "type": "Feature",
  "properties": {
    "iso:country":"GB",
    "sg:address":"10 Lairgate",
    "sg:city":"Beverley",
    "sg:classifiers":[
        {
            "category":"Professional",
            "subcategory":"Art Services",
            "type":"Services"
        }
    ],
    "sg:phone":"+44 1482 860849",
    "sg:postcode":"HU17 8EE",
    "sg:province":"East Riding of Yorkshire",
    "sg:tags":[
        "framing"
    ],
    "wof:name":"Lairgate Galleries",
    "wof:placetype":"venue"
},
  "geometry": {"coordinates":[-0.433295,53.842953],"type":"Point"}
}