{
  "type": "Feature",
  "properties": {
    "addr:full":"Unit 2 Hobson Industrial Estate, Burnofield Newcastle-upon-tyne Durham NE16 6EA",
    "addr:housenumber":"unit 2",
    "addr:postcode":"ne16 6ea",
    "addr:street":"Hobson Industrial Estate",
    "iso:country":"GB",
    "sg:address":"Unit 2 Hobson Industrial Estate, Burnofield",
    "sg:city":"Newcastle-upon-tyne",
    "sg:classifiers":[
        {
            "category":"Retail",
            "subcategory":"Repair Shop",
            "type":"Services"
        }
    ],
    "sg:postcode":"NE16 6EA",
    "sg:province":"Durham",
    "sg:tags":[
        "upholsterer"
    ],
    "wof:name":"Dacks of Fellside",
    "wof:placetype":"venue"
},
  "geometry": {"coordinates":[-1.73034,54.899132],"type":"Point"}
}