{
  "type": "Feature",
  "properties": {
    "addr:full":"10 Cotton St Liverpool Merseyside L3 7DY",
    "addr:housenumber":"10",
    "addr:postcode":"l3 7dy",
    "addr:street":"Cotton St",
    "iso:country":"GB",
    "sg:address":"10 Cotton St",
    "sg:city":"Liverpool",
    "sg:classifiers":[
        {
            "category":"Recreation",
            "subcategory":"Water Park",
            "type":"Entertainment"
        }
    ],
    "sg:phone":"+44 151 298 2144",
    "sg:postcode":"L3 7DY",
    "sg:province":"Merseyside",
    "sg:tags":[
        "keg",
        "drums",
        "cask"
    ],
    "wof:name":"M.A.K Drums & Containers",
    "wof:placetype":"venue"
},
  "geometry": {"coordinates":[-2.997206,53.419117],"type":"Point"}
}