{
  "type": "Feature",
  "properties": {
    "iso:country":"GB",
    "sg:address":"Cairns, Easingwold Road, Huby",
    "sg:city":"York",
    "sg:classifiers":[
        {
            "category":"Building & Trades",
            "subcategory":"Construction",
            "type":"Services"
        }
    ],
    "sg:postcode":"YO61 1HN",
    "sg:province":"North Yorkshire",
    "sg:tags":[
        "decorator",
        "painter"
    ],
    "wof:name":"Duncan Cook",
    "wof:placetype":"venue"
},
  "geometry": {"coordinates":[-1.1350489855,54.0836181641],"type":"Point"}
}