{
  "type": "Feature",
  "properties": {
    "iso:country":"GB",
    "sg:address":"110a Frimley Road",
    "sg:city":"Camberley",
    "sg:classifiers":[
        {
            "category":"Communications",
            "type":"Services"
        }
    ],
    "sg:phone":"+44 1276 66774",
    "sg:postcode":"GU15 2QN",
    "sg:province":"Berkshire",
    "sg:tags":[
        "tv",
        "video",
        "radio"
    ],
    "wof:name":"P J Microwaves",
    "wof:placetype":"venue"
},
  "geometry": {"coordinates":[-0.755246,51.327751],"type":"Point"}
}