{
  "type": "Feature",
  "properties": {
    "addr:full":"Po Box 951 Chester Cheshire CH2 2WA",
    "addr:housenumber":"po",
    "addr:postcode":"ch2 2wa",
    "addr:street":"Box 951",
    "iso:country":"GB",
    "sg:address":"Po Box 951",
    "sg:city":"Chester",
    "sg:classifiers":[
        {
            "category":"Communications",
            "subcategory":"Newspaper",
            "type":"Services"
        }
    ],
    "sg:phone":"+44 1244 376386",
    "sg:postcode":"CH2 2WA",
    "sg:province":"Cheshire",
    "sg:tags":[
        "magazine"
    ],
    "wof:name":"Micro Biology Europe",
    "wof:placetype":"venue"
},
  "geometry": {"coordinates":[-2.8703429699,53.2076034546],"type":"Point"}
}