{
  "type": "Feature",
  "properties": {
    "addr:full":"Tweed Street Berwick-upon-tweed Northumberland TD15 1NG",
    "addr:postcode":"td15 1ng",
    "addr:street":"Tweed Street;Northumberland",
    "iso:country":"GB",
    "sg:address":"Tweed Street",
    "sg:city":"Berwick-upon-tweed",
    "sg:classifiers":[
        {
            "category":"Social Services",
            "subcategory":"Retirement Home",
            "type":"Services"
        }
    ],
    "sg:postcode":"TD15 1NG",
    "sg:province":"Northumberland",
    "sg:tags":[
        "residential",
        "care"
    ],
    "wof:name":"Tweedview Residential Home",
    "wof:placetype":"venue"
},
  "geometry": {"coordinates":[-2.0082540512,55.7718200684],"type":"Point"}
}