{
  "type": "Feature",
  "properties": {
    "addr:full":"Ambleside, Old Kiln Close, Churt Farnham Hampshire GU10 2JH",
    "addr:postcode":"gu10 2jh",
    "addr:street":"Old Kiln Close",
    "iso:country":"GB",
    "sg:address":"Ambleside, Old Kiln Close, Churt",
    "sg:city":"Farnham",
    "sg:classifiers":[
        {
            "category":"Professional",
            "subcategory":"Art Services",
            "type":"Services"
        },
        {
            "category":"Building & Trades",
            "subcategory":"Construction",
            "type":"Services"
        }
    ],
    "sg:phone":"+44 1428 712602",
    "sg:postcode":"GU10 2JH",
    "sg:province":"Hampshire",
    "sg:tags":[
        "decorator",
        "painter"
    ],
    "wof:name":"Kieron Styles",
    "wof:placetype":"venue"
},
  "geometry": {"coordinates":[-0.7796339989,51.1374168396],"type":"Point"}
}