{
  "type": "Feature",
  "properties": {
    "addr:full":"2369-2375 Dumbarton Road Glasgow Glasgow City G14 0NT",
    "addr:housenumber":"2369-2375",
    "addr:postcode":"g14 0nt",
    "addr:street":"Dumbarton Road",
    "iso:country":"GB",
    "sg:address":"2369-2375 Dumbarton Road",
    "sg:city":"Glasgow",
    "sg:classifiers":[
        {
            "category":"Autos & Motor Vehicles",
            "subcategory":"Auto Supplies",
            "type":"Retail Goods"
        }
    ],
    "sg:phone":"+44 141 952 1862",
    "sg:postcode":"G14 0NT",
    "sg:province":"Glasgow City",
    "sg:tags":[
        "exhaust",
        "absorber",
        "shock"
    ],
    "wof:name":"Kwik-Fit",
    "wof:placetype":"venue"
},
  "geometry": {"coordinates":[-4.3785839081,55.8884010315],"type":"Point"}
}