{
  "type": "Feature",
  "properties": {
    "addr:full":"29a Queen Street Haverhill Essex CB9 9DZ",
    "addr:housenumber":"29a",
    "addr:postcode":"cb9 9dz",
    "addr:street":"Queen Street",
    "iso:country":"GB",
    "sg:address":"29a Queen Street",
    "sg:city":"Haverhill",
    "sg:classifiers":[
        {
            "category":"Shopping",
            "subcategory":"Mobile Phones",
            "type":"Retail Goods"
        },
        {
            "category":"Communications",
            "type":"Services"
        }
    ],
    "sg:postcode":"CB9 9DZ",
    "sg:province":"Essex",
    "sg:tags":[
        "telecommunication"
    ],
    "wof:name":"Sprint Communications",
    "wof:placetype":"venue"
},
  "geometry": {"coordinates":[0.436533,52.084564],"type":"Point"}
}