{
  "type": "Feature",
  "properties": {
    "iso:country":"GB",
    "sg:address":"Laburnum Drive",
    "sg:city":"Oswestry",
    "sg:classifiers":[
        {
            "category":"Place Of Worship",
            "type":"Public Place"
        }
    ],
    "sg:phone":"+44 1691 655546",
    "sg:postcode":"SY11 2QR",
    "sg:province":"Shropshire",
    "wof:name":"Carreg Llwyd Evangelical Church",
    "wof:placetype":"venue"
},
  "geometry": {"coordinates":[-3.045568943,52.858089447],"type":"Point"}
}