{
  "type": "Feature",
  "properties": {
    "addr:full":"26 The High Street Lyndhurst Hampshire SO43 7BG",
    "addr:housenumber":"26",
    "addr:postcode":"so43 7bg",
    "addr:street":"The High Street",
    "iso:country":"GB",
    "sg:address":"26 The High Street",
    "sg:city":"Lyndhurst",
    "sg:classifiers":[
        {
            "category":"Restaurant",
            "type":"Food & Drink"
        }
    ],
    "sg:phone":"+44 23 8028 2656",
    "sg:postcode":"SO43 7BG",
    "sg:province":"Hampshire",
    "wof:name":"Lyndhurst Rooms",
    "wof:placetype":"venue"
},
  "geometry": {"coordinates":[-1.5761799812,50.8724403381],"type":"Point"}
}