{
  "type": "Feature",
  "properties": {
    "addr:full":"11 Ivanhoe Road, Finchampstead Wokingham Berkshire RG40 4QQ",
    "addr:housenumber":"11",
    "addr:postcode":"rg40 4qq",
    "addr:street":"Ivanhoe Road",
    "iso:country":"GB",
    "sg:address":"11 Ivanhoe Road, Finchampstead",
    "sg:city":"Wokingham",
    "sg:classifiers":[
        {
            "category":"Shopping",
            "subcategory":"Stationery & Office Supplies",
            "type":"Retail Goods"
        }
    ],
    "sg:phone":"+44 118 973 0500",
    "sg:postcode":"RG40 4QQ",
    "sg:province":"Berkshire",
    "sg:tags":[
        "printers'"
    ],
    "wof:name":"Tampoprint U K Ltd.",
    "wof:placetype":"venue"
},
  "geometry": {"coordinates":[-0.8595820069,51.3733291626],"type":"Point"}
}