{
  "type": "Feature",
  "properties": {
    "iso:country":"GB",
    "sg:address":"68 High St",
    "sg:city":"Pershore",
    "sg:classifiers":[
        {
            "category":"Personal",
            "subcategory":"Beauty Salon",
            "type":"Services"
        }
    ],
    "sg:phone":"+44 1386 552680",
    "sg:postcode":"WR10 1DU",
    "sg:province":"Worcestershire",
    "sg:tags":[
        "unisex",
        "hairdresser"
    ],
    "wof:name":"Legends Hair Emporium",
    "wof:placetype":"venue"
},
  "geometry": {"coordinates":[-2.076376,52.112129],"type":"Point"}
}