{
  "type": "Feature",
  "properties": {
    "addr:full":"137 Sneiton Dale, Sneiton Nottingham Nottinghamshire NG2 4LW",
    "addr:housenumber":"137",
    "addr:postcode":"ng2 4lw",
    "addr:street":"Sneiton Dale",
    "iso:country":"GB",
    "sg:address":"137 Sneiton Dale, Sneiton",
    "sg:city":"Nottingham",
    "sg:classifiers":[
        {
            "category":"Food & Beverages",
            "subcategory":"Meat & Fish",
            "type":"Retail Goods"
        }
    ],
    "sg:postcode":"NG2 4LW",
    "sg:province":"Nottinghamshire",
    "sg:tags":[
        "butcher"
    ],
    "wof:name":"David J Terry",
    "wof:placetype":"venue"
},
  "geometry": {"coordinates":[-1.1238080263,52.9534835815],"type":"Point"}
}