{
  "type": "Feature",
  "properties": {
    "addr:full":"Bradnop Garage, Bradnop Leek Staffordshire ST13 7LZ",
    "addr:postcode":"st13 7lz",
    "iso:country":"GB",
    "sg:address":"Bradnop Garage, Bradnop",
    "sg:city":"Leek",
    "sg:classifiers":[
        {
            "category":"Professional",
            "subcategory":"Engineering",
            "type":"Services"
        }
    ],
    "sg:postcode":"ST13 7LZ",
    "sg:province":"Staffordshire",
    "wof:name":"Anthony Howson",
    "wof:placetype":"venue"
},
  "geometry": {"coordinates":[-1.987409,53.092167],"type":"Point"}
}