{
  "type": "Feature",
  "properties": {
    "addr:full":"41 Station Rd Liss Hampshire GU33 7DP",
    "addr:housenumber":"41",
    "addr:postcode":"gu33 7dp",
    "addr:street":"Station Rd",
    "iso:country":"GB",
    "sg:address":"41 Station Rd",
    "sg:city":"Liss",
    "sg:classifiers":[
        {
            "category":"Food & Beverages",
            "subcategory":"Meat & Fish",
            "type":"Retail Goods"
        }
    ],
    "sg:postcode":"GU33 7DP",
    "sg:province":"Hampshire",
    "sg:tags":[
        "butcher"
    ],
    "wof:name":"Read,G W,",
    "wof:placetype":"venue"
},
  "geometry": {"coordinates":[-0.89226,51.042694],"type":"Point"}
}