{
  "type": "Feature",
  "properties": {
    "addr:full":"Wal-goch Farm, Nannerch Mold Denbighshire CH7 5RP",
    "addr:postcode":"ch7 5rp",
    "iso:country":"GB",
    "sg:address":"Wal-goch Farm, Nannerch",
    "sg:city":"Mold",
    "sg:classifiers":[
        {
            "category":"Home & Garden",
            "subcategory":"Garden Supply",
            "type":"Retail Goods"
        },
        {
            "category":"Farming",
            "subcategory":"Farm",
            "type":"Manufacturing & Wholesale Goods"
        }
    ],
    "sg:phone":"+44 1352 741378",
    "sg:postcode":"CH7 5RP",
    "sg:province":"Denbighshire",
    "sg:tags":[
        "mixed",
        "bulb",
        "crop",
        "grower"
    ],
    "wof:name":"M J & P J Robinson",
    "wof:placetype":"venue"
},
  "geometry": {"coordinates":[-3.2446830273,53.2161445618],"type":"Point"}
}