{
  "type": "Feature",
  "properties": {
    "iso:country":"GB",
    "sg:address":"44 Church Street",
    "sg:city":"Troon",
    "sg:classifiers":[
        {
            "category":"Shopping",
            "subcategory":"Shoes",
            "type":"Retail Goods"
        }
    ],
    "sg:phone":"+44 1292 315554",
    "sg:postcode":"KA10 6AU",
    "sg:province":"South Ayrshire",
    "sg:tags":[
        "shop",
        "retailer",
        "footwear"
    ],
    "wof:name":"Cica Shoes",
    "wof:placetype":"venue"
},
  "geometry": {"coordinates":[-4.661177,55.543861],"type":"Point"}
}