{
  "type": "Feature",
  "properties": {
    "addr:full":"24 Leazes Crescent Newcastle-upon-tyne Tyne and Wear NE1 4LW",
    "addr:housenumber":"24",
    "addr:postcode":"ne1 4lw",
    "addr:street":"Leazes Crescent",
    "iso:country":"GB",
    "sg:address":"24 Leazes Crescent",
    "sg:city":"Newcastle-upon-tyne",
    "sg:classifiers":[
        {
            "category":"Health Services",
            "subcategory":"Dentist",
            "type":"Services"
        }
    ],
    "sg:postcode":"NE1 4LW",
    "sg:province":"Tyne and Wear",
    "wof:name":"K P S Bamrah",
    "wof:placetype":"venue"
},
  "geometry": {"coordinates":[-1.6186310053,54.9772605896],"type":"Point"}
}