{
  "type": "Feature",
  "properties": {
    "addr:full":"Ealing Gro, Off Sidcup Rd Birmingham West Midlands B44 8LU",
    "addr:postcode":"b44 8lu",
    "addr:street":"Off Sidcup Rd",
    "iso:country":"GB",
    "sg:address":"Ealing Gro, Off Sidcup Rd",
    "sg:city":"Birmingham",
    "sg:classifiers":[
        {
            "category":"Building & Trades",
            "subcategory":"Landscaping Services",
            "type":"Services"
        }
    ],
    "sg:phone":"+44 121 373 9951",
    "sg:postcode":"B44 8LU",
    "sg:province":"West Midlands",
    "sg:tags":[
        "landscape",
        "contractor"
    ],
    "wof:name":"Brophy Ground Maintenance",
    "wof:placetype":"venue"
},
  "geometry": {"coordinates":[-1.8913199902,52.5387001038],"type":"Point"}
}