{
  "type": "Feature",
  "properties": {
    "addr:full":"176 Bolton Road West, Ramsbottom Bury Lancashire BL0 9PE",
    "addr:housenumber":"176",
    "addr:postcode":"bl0 9pe",
    "addr:street":"Bolton Road West",
    "iso:country":"GB",
    "sg:address":"176 Bolton Road West, Ramsbottom",
    "sg:city":"Bury",
    "sg:classifiers":[
        {
            "category":"Bars & Pubs",
            "type":"Food & Drink"
        }
    ],
    "sg:phone":"+44 1706 822485",
    "sg:postcode":"BL0 9PE",
    "sg:province":"Lancashire",
    "sg:tags":[
        "pubs",
        "inn"
    ],
    "wof:name":"The Fusilier",
    "wof:placetype":"venue"
},
  "geometry": {"coordinates":[-2.3277831078,53.6387710571],"type":"Point"}
}