{
  "type": "Feature",
  "properties": {
    "addr:full":"83 High St Andover Hampshire SP10 1LR",
    "addr:housenumber":"83",
    "addr:postcode":"sp10 1lr",
    "addr:street":"High St",
    "iso:country":"GB",
    "sg:address":"83 High St",
    "sg:city":"Andover",
    "sg:classifiers":[
        {
            "category":"Home & Garden",
            "subcategory":"Kitchen Supply",
            "type":"Retail Goods"
        }
    ],
    "sg:phone":"+44 1264 361687",
    "sg:postcode":"SP10 1LR",
    "sg:province":"Hampshire",
    "sg:tags":[
        "table"
    ],
    "wof:name":"The Courtyard",
    "wof:placetype":"venue"
},
  "geometry": {"coordinates":[-1.479114,51.208954],"type":"Point"}
}