{
  "type": "Feature",
  "properties": {
    "iso:country":"GB",
    "sg:address":"47b Station Rd",
    "sg:city":"Kettering",
    "sg:classifiers":[
        {
            "category":"Professional",
            "subcategory":"Computer Services",
            "type":"Services"
        }
    ],
    "sg:phone":"+44 1536 220007",
    "sg:postcode":"NN14 2RS",
    "sg:province":"Northamptonshire",
    "sg:tags":[
        "system",
        "software"
    ],
    "wof:name":"Program Skill Ltd",
    "wof:placetype":"venue"
},
  "geometry": {"coordinates":[-0.81852,52.443394],"type":"Point"}
}