{
  "type": "Feature",
  "properties": {
    "addr:full":"88 St. Marks Rd London Greater London W10 6BY",
    "addr:housenumber":"88",
    "addr:postcode":"w10 6by",
    "addr:street":"St. Marks Rd",
    "iso:country":"GB",
    "sg:address":"88 St. Marks Rd",
    "sg:city":"London",
    "sg:classifiers":[
        {
            "category":"Health Services",
            "subcategory":"Nursing And Care Facility",
            "type":"Services"
        },
        {
            "category":"Social Services",
            "subcategory":"Retirement Home",
            "type":"Services"
        }
    ],
    "sg:phone":"+44 20 8964 1123",
    "sg:postcode":"W10 6BY",
    "sg:province":"Greater London",
    "sg:tags":[
        "residential"
    ],
    "wof:name":"Servite Housing Initiatives Ltd",
    "wof:placetype":"venue"
},
  "geometry": {"coordinates":[-0.2187349945,51.5217895508],"type":"Point"}
}