{
  "type": "Feature",
  "properties": {
    "iso:country":"GB",
    "sg:address":"4a Market Street, Wellington",
    "sg:city":"Telford",
    "sg:classifiers":[
        {
            "category":"Shopping",
            "subcategory":"Gifts & Souvenirs",
            "type":"Retail Goods"
        }
    ],
    "sg:phone":"+44 1952 242924",
    "sg:postcode":"TF1 1DT",
    "sg:province":"Shropshire",
    "sg:tags":[
        "shop",
        "poster",
        "card"
    ],
    "wof:name":"The Card Gallery",
    "wof:placetype":"venue"
},
  "geometry": {"coordinates":[-2.518975,52.701195],"type":"Point"}
}