{
  "type": "Feature",
  "properties": {
    "addr:full":"Old Hall Drive Manchester Greater Manchester M18 7FQ",
    "addr:postcode":"m18 7fq",
    "addr:street":"Old Hall Drive",
    "iso:country":"GB",
    "sg:address":"Old Hall Drive",
    "sg:city":"Manchester",
    "sg:classifiers":[
        {
            "category":"Education",
            "subcategory":"School",
            "type":"Public Place"
        }
    ],
    "sg:phone":"+44 161 223 2805",
    "sg:postcode":"M18 7FQ",
    "sg:province":"Greater Manchester",
    "sg:tags":[
        "local",
        "authority"
    ],
    "wof:name":"Old Hall Drive Primary School",
    "wof:placetype":"venue"
},
  "geometry": {"coordinates":[-2.171014,53.45887],"type":"Point"}
}