{
  "type": "Feature",
  "properties": {
    "addr:full":"The Tower, 6th Floor London Greater London SW19 2JR",
    "addr:housenumber":"6th floor",
    "addr:postcode":"sw19 2jr",
    "iso:country":"GB",
    "sg:address":"The Tower, 6th Floor",
    "sg:city":"London",
    "sg:classifiers":[
        {
            "category":"Professional",
            "subcategory":"Employment Agencies",
            "type":"Services"
        }
    ],
    "sg:phone":"+44 20 8544 9777",
    "sg:postcode":"SW19 2JR",
    "sg:province":"Greater London",
    "sg:tags":[
        "recr",
        "hire",
        "driver"
    ],
    "wof:name":"British Chauffeurs Guild Ltd.",
    "wof:placetype":"venue"
},
  "geometry": {"coordinates":[-0.1753199995,51.4209709167],"type":"Point"}
}