{
  "type": "Feature",
  "properties": {
    "addr:full":"18 All Saints Drive, Four Oaks Sutton Coldfield Staffordshire B74 4AG",
    "addr:housenumber":"18",
    "addr:postcode":"b74 4ag",
    "addr:street":"All Saints Drive",
    "iso:country":"GB",
    "sg:address":"18 All Saints Drive, Four Oaks",
    "sg:city":"Sutton Coldfield",
    "sg:classifiers":[
        {
            "category":"Home & Garden",
            "subcategory":"Carpets & Floor Coverings",
            "type":"Retail Goods"
        }
    ],
    "sg:postcode":"B74 4AG",
    "sg:province":"Staffordshire",
    "sg:tags":[
        "cleaner",
        "upholstery"
    ],
    "wof:name":"Cleaning Associates",
    "wof:placetype":"venue"
},
  "geometry": {"coordinates":[-1.839509964,52.5872840881],"type":"Point"}
}