{
  "type": "Feature",
  "properties": {
    "addr:full":"9 Corbet Close, Beaumont Leys Leicester Leicestershire LE4 0LZ",
    "addr:housenumber":"9",
    "addr:postcode":"le4 0lz",
    "addr:street":"Corbet Close",
    "iso:country":"GB",
    "sg:address":"9 Corbet Close, Beaumont Leys",
    "sg:city":"Leicester",
    "sg:classifiers":[
        {
            "category":"Home & Garden",
            "subcategory":"Building Materials",
            "type":"Retail Goods"
        }
    ],
    "sg:postcode":"LE4 0LZ",
    "sg:province":"Leicestershire",
    "sg:tags":[
        "fencing"
    ],
    "wof:name":"City Landscapes",
    "wof:placetype":"venue"
},
  "geometry": {"coordinates":[-1.164381,52.659325],"type":"Point"}
}