{
  "type": "Feature",
  "properties": {
    "addr:full":"315 Entwisle Road Rochdale Lancashire OL16 2LH",
    "addr:housenumber":"315",
    "addr:postcode":"ol16 2lh",
    "addr:street":"Entwisle Road",
    "iso:country":"GB",
    "sg:address":"315 Entwisle Road",
    "sg:city":"Rochdale",
    "sg:classifiers":[
        {
            "category":"Professional",
            "subcategory":"Printing & Photocopies",
            "type":"Services"
        }
    ],
    "sg:phone":"+44 1706 647277",
    "sg:postcode":"OL16 2LH",
    "sg:province":"Lancashire",
    "sg:tags":[
        "printer"
    ],
    "wof:name":"Hamer Printing",
    "wof:placetype":"venue"
},
  "geometry": {"coordinates":[-2.1439499855,53.6229324341],"type":"Point"}
}