{
  "type": "Feature",
  "properties": {
    "iso:country":"GB",
    "sg:address":"St Marys Way",
    "sg:city":"Melton Mowbray",
    "sg:classifiers":[
        {
            "category":"Organizations",
            "subcategory":"Membership Organization",
            "type":"Services"
        }
    ],
    "sg:phone":"+44 1664 560619",
    "sg:postcode":"LE13 1YE",
    "sg:province":"Leicestershire",
    "sg:tags":[
        "club"
    ],
    "wof:name":"Regal Bingo Club",
    "wof:placetype":"venue"
},
  "geometry": {"coordinates":[-0.886307,52.766003],"type":"Point"}
}