{
  "type": "Feature",
  "properties": {
    "iso:country":"GB",
    "sg:address":"16 Langham Place, Northampton",
    "sg:city":"Northampton",
    "sg:classifiers":[
        {
            "category":"Professional",
            "type":"Services"
        }
    ],
    "sg:phone":"+44 1604 601556",
    "sg:postcode":"NN2 6AA",
    "sg:province":"Northamptonshire",
    "sg:tags":[
        "repair",
        "tech",
        "maintenance"
    ],
    "wof:name":"Rathlin Software Ltd.",
    "wof:placetype":"venue"
},
  "geometry": {"coordinates":[-0.897565,52.246639],"type":"Point"}
}