{
  "type": "Feature",
  "properties": {
    "iso:country":"GB",
    "sg:address":"2 Grafton Rd",
    "sg:city":"Gloucester",
    "sg:classifiers":[
        {
            "category":"Health Services",
            "subcategory":"Dentist",
            "type":"Services"
        }
    ],
    "sg:phone":"+44 1452 531135",
    "sg:postcode":"GL2 0QP",
    "sg:province":"Gloucestershire",
    "wof:name":"J R Davies",
    "wof:placetype":"venue"
},
  "geometry": {"coordinates":[-2.221194,51.868896],"type":"Point"}
}