{
  "type": "Feature",
  "properties": {
    "addr:full":"City Business Park Plymouth Devon PL3 4BB",
    "addr:postcode":"pl3 4bb",
    "addr:street":"Park",
    "iso:country":"GB",
    "sg:address":"City Business Park",
    "sg:city":"Plymouth",
    "sg:classifiers":[
        {
            "category":"Professional",
            "subcategory":"Business Services",
            "type":"Services"
        }
    ],
    "sg:postcode":"PL3 4BB",
    "sg:province":"Devon",
    "sg:tags":[
        "information"
    ],
    "wof:name":"Taste for Enterprise",
    "wof:placetype":"venue"
},
  "geometry": {"coordinates":[-4.1607899666,50.3811607361],"type":"Point"}
}