{
  "type": "Feature",
  "properties": {
    "addr:full":"23 Wrexham Street Mold Denbighshire CH7 1NR",
    "addr:postcode":"ch7 1nr",
    "addr:street":"Wrexham Street",
    "iso:country":"GB",
    "sg:address":"23 Wrexham Street",
    "sg:city":"Mold",
    "sg:classifiers":[
        {
            "category":"Personal",
            "type":"Services"
        }
    ],
    "sg:phone":"+44 1352 756515",
    "sg:postcode":"CH7 1NR",
    "sg:province":"Denbighshire",
    "sg:tags":[
        "tailor"
    ],
    "wof:name":"Sheilas",
    "wof:placetype":"venue"
},
  "geometry": {"coordinates":[-3.141354084,53.1663742065],"type":"Point"}
}