{
  "type": "Feature",
  "properties": {
    "iso:country":"GB",
    "sg:address":"Drove Cottage, Drove Road, Portslade",
    "sg:city":"Brighton",
    "sg:classifiers":[
        {
            "category":"Building & Trades",
            "subcategory":"Construction",
            "type":"Services"
        }
    ],
    "sg:postcode":"BN41 2PA",
    "sg:province":"East Sussex",
    "sg:tags":[
        "contractor"
    ],
    "wof:name":"Knowles Construction",
    "wof:placetype":"venue"
},
  "geometry": {"coordinates":[-0.218145,50.844112],"type":"Point"}
}