{
  "type": "Feature",
  "properties": {
    "iso:country":"GB",
    "sg:address":"12 Mansfield Road, Scone",
    "sg:city":"Perth",
    "sg:classifiers":[
        {
            "category":"Professional",
            "subcategory":"Printing & Photocopies",
            "type":"Services"
        },
        {
            "category":"Wholesale",
            "subcategory":"Books, Periodicals, & Newspapers",
            "type":"Manufacturing & Wholesale Goods"
        }
    ],
    "sg:phone":"+44 1738 553954",
    "sg:postcode":"PH2 6SA",
    "sg:province":"Perth and Kinross",
    "sg:tags":[
        "top",
        "printer",
        "publishing",
        "desk"
    ],
    "wof:name":"THE MERLIN PRESS",
    "wof:placetype":"venue"
},
  "geometry": {"coordinates":[-3.400279,56.420151],"type":"Point"}
}