{
  "type": "Feature",
  "properties": {
    "addr:full":"Units 15a, Hive Industrial Centre, Factory Road Birmingham West Midlands B18 5JJ",
    "addr:housenumber":"units 15a hive industrial centre",
    "addr:postcode":"b18 5jj",
    "addr:street":"Factory Road",
    "iso:country":"GB",
    "sg:address":"Units 15a, Hive Industrial Centre, Factory Road",
    "sg:city":"Birmingham",
    "sg:classifiers":[
        {
            "category":"Shopping",
            "subcategory":"Clothing, Apparel, & Fashions",
            "type":"Retail Goods"
        }
    ],
    "sg:phone":"+44 121 554 7531",
    "sg:postcode":"B18 5JJ",
    "sg:province":"West Midlands",
    "sg:tags":[
        "clothing",
        "fabric"
    ],
    "wof:name":"G K Leisurewear",
    "wof:placetype":"venue"
},
  "geometry": {"coordinates":[-1.908604,52.478596],"type":"Point"}
}