{
  "type": "Feature",
  "properties": {
    "addr:full":"Back Of Market Place Saxmundham Suffolk IP17 1AH",
    "addr:postcode":"ip17 1ah",
    "addr:street":"Back;Place",
    "iso:country":"GB",
    "sg:address":"Back Of Market Place",
    "sg:city":"Saxmundham",
    "sg:classifiers":[
        {
            "category":"Food & Beverages",
            "subcategory":"Bakery",
            "type":"Retail Goods"
        }
    ],
    "sg:phone":"+44 1728 602891",
    "sg:postcode":"IP17 1AH",
    "sg:province":"Suffolk",
    "sg:tags":[
        "shop",
        "baker"
    ],
    "wof:name":"Jackson & Sons",
    "wof:placetype":"venue"
},
  "geometry": {"coordinates":[1.489533,52.216713],"type":"Point"}
}