{
  "type": "Feature",
  "properties": {
    "addr:full":"57 Frodsham Street Chester Cheshire CH1 3JJ",
    "addr:housenumber":"57",
    "addr:postcode":"ch1 3jj",
    "addr:street":"Frodsham Street",
    "iso:country":"GB",
    "sg:address":"57 Frodsham Street",
    "sg:city":"Chester",
    "sg:classifiers":[
        {
            "category":"Restaurant",
            "type":"Food & Drink"
        }
    ],
    "sg:phone":"+44 1244 317873",
    "sg:postcode":"CH1 3JJ",
    "sg:province":"Cheshire",
    "sg:tags":[
        "oriental"
    ],
    "wof:name":"The Slow Boat",
    "wof:placetype":"venue"
},
  "geometry": {"coordinates":[-2.8886959553,53.1930274963],"type":"Point"}
}