{
  "type": "Feature",
  "properties": {
    "addr:full":"115 Tollgate Road Salisbury Wiltshire SP1 2JG",
    "addr:housenumber":"115",
    "addr:postcode":"sp1 2jg",
    "addr:street":"Tollgate Road",
    "iso:country":"GB",
    "sg:address":"115 Tollgate Road",
    "sg:city":"Salisbury",
    "sg:classifiers":[
        {
            "category":"Building & Trades",
            "subcategory":"Plumbing",
            "type":"Services"
        }
    ],
    "sg:phone":"+44 1722 414154",
    "sg:postcode":"SP1 2JG",
    "sg:province":"Wiltshire",
    "sg:tags":[
        "merchant",
        "plumbers'"
    ],
    "wof:name":"Jayhard Ltd.",
    "wof:placetype":"venue"
},
  "geometry": {"coordinates":[-1.784699,51.064659],"type":"Point"}
}