{
  "type": "Feature",
  "properties": {
    "iso:country":"GB",
    "sg:address":"49 Perry Road, Gobowen",
    "sg:city":"Oswestry",
    "sg:classifiers":[
        {
            "category":"Building & Trades",
            "subcategory":"Construction",
            "type":"Services"
        }
    ],
    "sg:postcode":"SY10 7BX",
    "sg:province":"Shropshire",
    "sg:tags":[
        "builder"
    ],
    "wof:name":"Ronald Pryce Davies",
    "wof:placetype":"venue"
},
  "geometry": {"coordinates":[-3.034009,52.900795],"type":"Point"}
}