{
  "type": "Feature",
  "properties": {
    "iso:country":"GB",
    "sg:address":"170 Kensington Church Street",
    "sg:city":"London",
    "sg:classifiers":[
        {
            "category":"Shopping",
            "subcategory":"Antiques",
            "type":"Retail Goods"
        }
    ],
    "sg:phone":"+44 20 7229 2988",
    "sg:postcode":"W8 4BN",
    "sg:province":"Greater London",
    "wof:name":"Peter Kemp Antiques",
    "wof:placetype":"venue"
},
  "geometry": {"coordinates":[-0.1948350072,51.5081214905],"type":"Point"}
}