{
  "type": "Feature",
  "properties": {
    "addr:full":"Unit 6 Stoke-on-trent Staffordshire ST4 3ED",
    "addr:housenumber":"unit 6",
    "addr:postcode":"st4 3ed",
    "iso:country":"GB",
    "sg:address":"Unit 6",
    "sg:city":"Stoke-on-trent",
    "sg:classifiers":[
        {
            "category":"Retail",
            "subcategory":"Auto Repair",
            "type":"Services"
        }
    ],
    "sg:postcode":"ST4 3ED",
    "sg:province":"Staffordshire",
    "sg:tags":[
        "modification",
        "garage"
    ],
    "wof:name":"Rs Motors",
    "wof:placetype":"venue"
},
  "geometry": {"coordinates":[-2.1481499672,52.9954299927],"type":"Point"}
}