{
  "type": "Feature",
  "properties": {
    "addr:full":"24 Nant Twyn Harris, Ystrad Mynach Hengoed Caerphilly CF82 7DG",
    "addr:housenumber":"24",
    "addr:postcode":"cf82 7dg",
    "addr:street":"Nant Twyn",
    "iso:country":"GB",
    "sg:address":"24 Nant Twyn Harris, Ystrad Mynach",
    "sg:city":"Hengoed",
    "sg:classifiers":[
        {
            "category":"Professional",
            "subcategory":"Computer Services",
            "type":"Services"
        }
    ],
    "sg:phone":"+44 1443 814007",
    "sg:postcode":"CF82 7DG",
    "sg:province":"Caerphilly",
    "sg:tags":[
        "system",
        "software"
    ],
    "wof:name":"Holness Connect",
    "wof:placetype":"venue"
},
  "geometry": {"coordinates":[-3.236492,51.630203],"type":"Point"}
}