{
  "type": "Feature",
  "properties": {
    "iso:country":"GB",
    "sg:address":"New Fishmarket",
    "sg:city":"Thurso",
    "sg:classifiers":[
        {
            "category":"Farming",
            "subcategory":"Fish & Marine Products",
            "type":"Manufacturing & Wholesale Goods"
        }
    ],
    "sg:phone":"+44 1847 895403",
    "sg:postcode":"KW14 7AB",
    "sg:province":"Highland",
    "sg:tags":[
        "fishmonger"
    ],
    "wof:name":"H & D Calder",
    "wof:placetype":"venue"
},
  "geometry": {"coordinates":[-3.525867,58.596565],"type":"Point"}
}