{
  "type": "Feature",
  "properties": {
    "addr:full":"38 The Broadway Bedford Bedfordshire MK40 2TH",
    "addr:housenumber":"38",
    "addr:postcode":"mk40 2th",
    "addr:street":"The Broadway",
    "iso:country":"GB",
    "sg:address":"38 The Broadway",
    "sg:city":"Bedford",
    "sg:classifiers":[
        {
            "category":"Shopping",
            "subcategory":"Antiques",
            "type":"Retail Goods"
        }
    ],
    "sg:phone":"+44 1234 404100",
    "sg:postcode":"MK40 2TH",
    "sg:province":"Bedfordshire",
    "wof:name":"Shop Window",
    "wof:placetype":"venue"
},
  "geometry": {"coordinates":[-0.4680530131,52.1397972107],"type":"Point"}
}