{
  "type": "Feature",
  "properties": {
    "addr:full":"77 Belgrave Road Leicester Leicestershire LE4 6AS",
    "addr:housenumber":"77",
    "addr:postcode":"le4 6as",
    "addr:street":"Belgrave Road",
    "iso:country":"GB",
    "sg:address":"77 Belgrave Road",
    "sg:city":"Leicester",
    "sg:classifiers":[
        {
            "category":"Shopping",
            "subcategory":"Shoes",
            "type":"Retail Goods"
        }
    ],
    "sg:phone":"+44 116 266 2577",
    "sg:postcode":"LE4 6AS",
    "sg:province":"Leicestershire",
    "sg:tags":[
        "shop",
        "retailer",
        "footwear"
    ],
    "wof:name":"Footwear Centre",
    "wof:placetype":"venue"
},
  "geometry": {"coordinates":[-1.1229000092,52.6490478516],"type":"Point"}
}