{
  "type": "Feature",
  "properties": {
    "addr:full":"42 Middleham Close, Ouston Chester-le-street Durham DH2 1TA",
    "addr:housenumber":"42",
    "addr:postcode":"dh2 1ta",
    "addr:street":"Middleham Close",
    "iso:country":"GB",
    "sg:address":"42 Middleham Close, Ouston",
    "sg:city":"Chester-le-street",
    "sg:classifiers":[
        {
            "category":"Building & Trades",
            "subcategory":"Landscaping Services",
            "type":"Services"
        }
    ],
    "sg:phone":"+44 191 410 7043",
    "sg:postcode":"DH2 1TA",
    "sg:province":"Durham",
    "sg:tags":[
        "gardening",
        "landscape",
        "contractor"
    ],
    "wof:name":"Greenfingers Landscape Gardeners",
    "wof:placetype":"venue"
},
  "geometry": {"coordinates":[-1.610405,54.883263],"type":"Point"}
}