{
  "type": "Feature",
  "properties": {
    "iso:country":"GB",
    "sg:address":"1 Bradford St",
    "sg:city":"Tonbridge",
    "sg:classifiers":[
        {
            "category":"Professional",
            "subcategory":"Engineering",
            "type":"Services"
        }
    ],
    "sg:phone":"+44 1732 770748",
    "sg:postcode":"TN9 1DU",
    "sg:province":"Kent",
    "sg:tags":[
        "consulting",
        "engineer"
    ],
    "wof:name":"Mervyn Hayes Associates",
    "wof:placetype":"venue"
},
  "geometry": {"coordinates":[0.27371,51.19408],"type":"Point"}
}