{
  "type": "Feature",
  "properties": {
    "addr:full":"24 Winchester Dr, Chelmsley Wood Birmingham West Midlands B37 5QP",
    "addr:housenumber":"24",
    "addr:postcode":"b37 5qp",
    "addr:street":"Winchester Dr",
    "iso:country":"GB",
    "sg:address":"24 Winchester Dr, Chelmsley Wood",
    "sg:city":"Birmingham",
    "sg:classifiers":[
        {
            "category":"Bars & Pubs",
            "type":"Food & Drink"
        }
    ],
    "sg:postcode":"B37 5QP",
    "sg:province":"West Midlands",
    "sg:tags":[
        "pubs",
        "inn"
    ],
    "wof:name":"The Round House",
    "wof:placetype":"venue"
},
  "geometry": {"coordinates":[-1.745239,52.477161],"type":"Point"}
}