{
  "type": "Feature",
  "properties": {
    "iso:country":"GB",
    "sg:address":"24 Chaldon Road",
    "sg:city":"Caterham",
    "sg:classifiers":[
        {
            "category":"Shopping",
            "subcategory":"Gifts & Souvenirs",
            "type":"Retail Goods"
        }
    ],
    "sg:phone":"+44 1883 343234",
    "sg:postcode":"CR3 5PE",
    "sg:province":"Surrey",
    "sg:tags":[
        "shop"
    ],
    "wof:name":"Charisma Gifts Ltd.",
    "wof:placetype":"venue"
},
  "geometry": {"coordinates":[-0.089975,51.28759],"type":"Point"}
}