{
  "type": "Feature",
  "properties": {
    "addr:full":"Bank Top Farm Harrogate North Yorkshire HG3 3JT",
    "addr:postcode":"hg3 3jt",
    "iso:country":"GB",
    "sg:address":"Bank Top Farm",
    "sg:city":"Harrogate",
    "sg:classifiers":[
        {
            "category":"Farming",
            "subcategory":"Livestock Farm",
            "type":"Manufacturing & Wholesale Goods"
        }
    ],
    "sg:phone":"+44 1423 772272",
    "sg:postcode":"HG3 3JT",
    "sg:province":"North Yorkshire",
    "sg:tags":[
        "others"
    ],
    "wof:name":"Specialised Snail Services",
    "wof:placetype":"venue"
},
  "geometry": {"coordinates":[-1.6107200384,54.0605697632],"type":"Point"}
}