{
  "type": "Feature",
  "properties": {
    "iso:country":"GB",
    "sg:address":"Unit 2 Seedbed Centre, Davidson Way",
    "sg:city":"Romford",
    "sg:classifiers":[
        {
            "category":"Home & Garden",
            "subcategory":"Furniture",
            "type":"Retail Goods"
        }
    ],
    "sg:phone":"+44 1708 714223",
    "sg:postcode":"RM7 0AZ",
    "sg:province":"Essex",
    "wof:name":"M Potter Contracts",
    "wof:placetype":"venue"
},
  "geometry": {"coordinates":[0.18427,51.570179],"type":"Point"}
}