{
  "type": "Feature",
  "properties": {
    "addr:full":"16 Duke Street Brighton East Sussex BN1 1AH",
    "addr:housenumber":"16",
    "addr:postcode":"bn1 1ah",
    "addr:street":"Duke Street",
    "iso:country":"GB",
    "sg:address":"16 Duke Street",
    "sg:city":"Brighton",
    "sg:classifiers":[
        {
            "category":"Personal",
            "subcategory":"Beauty Salon",
            "type":"Services"
        }
    ],
    "sg:phone":"+44 1273 328787",
    "sg:postcode":"BN1 1AH",
    "sg:province":"East Sussex",
    "sg:tags":[
        "unisex",
        "hairdresser"
    ],
    "wof:name":"Crowns",
    "wof:placetype":"venue"
},
  "geometry": {"coordinates":[-0.143413,50.822769],"type":"Point"}
}