{
  "type": "Feature",
  "properties": {
    "iso:country":"GB",
    "sg:address":"19 Morestall Drive",
    "sg:city":"Cirencester",
    "sg:classifiers":[
        {
            "category":"Health Services",
            "subcategory":"Health Practitioner",
            "type":"Services"
        }
    ],
    "sg:phone":"+44 1285 640452",
    "sg:postcode":"GL7 1TF",
    "sg:province":"Gloucestershire",
    "sg:tags":[
        "osteopath"
    ],
    "wof:name":"Rebecca A Hill",
    "wof:placetype":"venue"
},
  "geometry": {"coordinates":[-1.978696,51.704819],"type":"Point"}
}