{
  "type": "Feature",
  "properties": {
    "iso:country":"GB",
    "sg:address":"52 Holden Way",
    "sg:city":"Upminster",
    "sg:classifiers":[
        {
            "category":"Manufacturing",
            "subcategory":"Furniture",
            "type":"Manufacturing & Wholesale Goods"
        }
    ],
    "sg:phone":"+44 1708 222568",
    "sg:postcode":"RM14 1BT",
    "sg:province":"Essex",
    "sg:tags":[
        "polishing",
        "french"
    ],
    "wof:name":"Heritage French Polishing",
    "wof:placetype":"venue"
},
  "geometry": {"coordinates":[0.2603830099,51.5666465759],"type":"Point"}
}