{
  "type": "Feature",
  "properties": {
    "addr:full":"Craiglea Ho Livingston West Lothian EH54 6DA",
    "addr:postcode":"eh54 6da",
    "iso:country":"GB",
    "sg:address":"Craiglea Ho",
    "sg:city":"Livingston",
    "sg:classifiers":[
        {
            "category":"Retail",
            "subcategory":"Auto Repair",
            "type":"Services"
        }
    ],
    "sg:phone":"+44 1506 440490",
    "sg:postcode":"EH54 6DA",
    "sg:province":"West Lothian",
    "sg:tags":[
        "modification",
        "garage"
    ],
    "wof:name":"T Greenshields",
    "wof:placetype":"venue"
},
  "geometry": {"coordinates":[-3.509834,55.886246],"type":"Point"}
}