{
  "type": "Feature",
  "properties": {
    "addr:full":"7 St Johns Close Norwich Norfolk NR1 2PR",
    "addr:housenumber":"7",
    "addr:postcode":"nr1 2pr",
    "addr:street":"St Johns Close",
    "iso:country":"GB",
    "sg:address":"7 St Johns Close",
    "sg:city":"Norwich",
    "sg:classifiers":[
        {
            "category":"Home & Garden",
            "subcategory":"Household Appliances",
            "type":"Retail Goods"
        }
    ],
    "sg:phone":"+44 1603 616419",
    "sg:postcode":"NR1 2PR",
    "sg:province":"Norfolk",
    "sg:tags":[
        "electrical"
    ],
    "wof:name":"Secker & Sons (Norwich) Ltd.",
    "wof:placetype":"venue"
},
  "geometry": {"coordinates":[1.29449,52.614506],"type":"Point"}
}