{
  "type": "Feature",
  "properties": {
    "addr:full":"5 Bull Grn, George Square Halifax West Yorkshire HX1 5AB",
    "addr:housenumber":"5",
    "addr:postcode":"hx1 5ab",
    "addr:street":"Bull Grn George Square",
    "iso:country":"GB",
    "sg:address":"5 Bull Grn, George Square",
    "sg:city":"Halifax",
    "sg:classifiers":[
        {
            "category":"Bars & Pubs",
            "type":"Food & Drink"
        }
    ],
    "sg:phone":"+44 1422 352254",
    "sg:postcode":"HX1 5AB",
    "sg:province":"West Yorkshire",
    "sg:tags":[
        "pubs",
        "inn"
    ],
    "wof:name":"Innspire Ltd.",
    "wof:placetype":"venue"
},
  "geometry": {"coordinates":[-1.863594,53.721886],"type":"Point"}
}