{
  "type": "Feature",
  "properties": {
    "iso:country":"GB",
    "sg:address":"58 Barnsley Rd, Dodworth",
    "sg:city":"Barnsley",
    "sg:classifiers":[
        {
            "category":"Home & Garden",
            "subcategory":"Kitchen Supply",
            "type":"Retail Goods"
        }
    ],
    "sg:phone":"+44 1226 785157",
    "sg:postcode":"S75 3JW",
    "sg:province":"South Yorkshire",
    "sg:tags":[
        "table"
    ],
    "wof:name":"Geoff Swift",
    "wof:placetype":"venue"
},
  "geometry": {"coordinates":[-1.5249220133,53.5455169678],"type":"Point"}
}