{
  "type": "Feature",
  "properties": {
    "iso:country":"GB",
    "sg:address":"Hinbros House",
    "sg:city":"Dewsbury",
    "sg:classifiers":[
        {
            "category":"Utilities",
            "subcategory":"Refuse",
            "type":"Services"
        }
    ],
    "sg:phone":"+44 1924 454176",
    "sg:postcode":"WF13 3RE",
    "sg:province":"West Yorkshire",
    "sg:tags":[
        "skip",
        "hire"
    ],
    "wof:name":"Forge Plant Ltd.",
    "wof:placetype":"venue"
},
  "geometry": {"coordinates":[-1.658029,53.681259],"type":"Point"}
}