{
  "type": "Feature",
  "properties": {
    "addr:full":"63 Dane Crescent Ramsgate Kent CT11 7JS",
    "addr:housenumber":"63",
    "addr:postcode":"ct11 7js",
    "addr:street":"Dane Crescent Ramsgate",
    "iso:country":"GB",
    "sg:address":"63 Dane Crescent",
    "sg:city":"Ramsgate",
    "sg:classifiers":[
        {
            "category":"Building & Trades",
            "subcategory":"Construction",
            "type":"Services"
        }
    ],
    "sg:phone":"+44 1843 591960",
    "sg:postcode":"CT11 7JS",
    "sg:province":"Kent",
    "sg:tags":[
        "builder"
    ],
    "wof:name":"Vinstrata Ltd.",
    "wof:placetype":"venue"
},
  "geometry": {"coordinates":[1.4201279879,51.341960907],"type":"Point"}
}