{
  "type": "Feature",
  "properties": {
    "addr:full":"Prospect House, 58 Queens Road Reading Berkshire RG1 4RP",
    "addr:housenumber":"58",
    "addr:postcode":"rg1 4rp",
    "addr:street":"Queens Road",
    "iso:country":"GB",
    "sg:address":"Prospect House, 58 Queens Road",
    "sg:city":"Reading",
    "sg:classifiers":[
        {
            "category":"Professional",
            "subcategory":"Accounting & Tax Preparation",
            "type":"Services"
        }
    ],
    "sg:postcode":"RG1 4RP",
    "sg:province":"Berkshire",
    "sg:tags":[
        "accountant"
    ],
    "wof:name":"Chantrey Vellacott Dfk",
    "wof:placetype":"venue"
},
  "geometry": {"coordinates":[-0.964354,51.453255],"type":"Point"}
}