{
  "type": "Feature",
  "properties": {
    "addr:full":"16 School Road, Bulkington Nuneaton Warwickshire CV12 9JB",
    "addr:housenumber":"16",
    "addr:postcode":"cv12 9jb",
    "addr:street":"School Road",
    "iso:country":"GB",
    "sg:address":"16 School Road, Bulkington",
    "sg:city":"Nuneaton",
    "sg:classifiers":[
        {
            "category":"Shopping",
            "subcategory":"Clothing, Apparel, & Fashions",
            "type":"Retail Goods"
        }
    ],
    "sg:phone":"+44 24 7631 3139",
    "sg:postcode":"CV12 9JB",
    "sg:province":"Warwickshire",
    "sg:tags":[
        "lingerie"
    ],
    "wof:name":"Leaping Cats Ltd.",
    "wof:placetype":"venue"
},
  "geometry": {"coordinates":[-1.422666,52.476341],"type":"Point"}
}