{
  "type": "Feature",
  "properties": {
    "addr:full":"Unit 36-37, Heath Hill Industrial Estate Telford Shropshire TF4 2RH",
    "addr:housenumber":"unit 36-37;estate",
    "addr:postcode":"tf4 2rh",
    "addr:street":"Heath Hill Industrial",
    "iso:country":"GB",
    "sg:address":"Unit 36-37, Heath Hill Industrial Estate",
    "sg:city":"Telford",
    "sg:classifiers":[
        {
            "category":"Manufacturing",
            "subcategory":"Glass & Minerals",
            "type":"Manufacturing & Wholesale Goods"
        }
    ],
    "sg:postcode":"TF4 2RH",
    "sg:province":"Shropshire",
    "sg:tags":[
        "fibre",
        "moulding"
    ],
    "wof:name":"Scobak Fabrications Ltd",
    "wof:placetype":"venue"
},
  "geometry": {"coordinates":[-2.4713289738,52.6652183533],"type":"Point"}
}