{
  "type": "Feature",
  "properties": {
    "addr:full":"Abb Street Huddersfield West Yorkshire HD1 4PA",
    "addr:postcode":"hd1 4pa",
    "addr:street":"Abb Street",
    "iso:country":"GB",
    "sg:address":"Abb Street",
    "sg:city":"Huddersfield",
    "sg:classifiers":[
        {
            "category":"Building & Trades",
            "subcategory":"Plumbing",
            "type":"Services"
        }
    ],
    "sg:postcode":"HD1 4PA",
    "sg:province":"West Yorkshire",
    "sg:tags":[
        "heating"
    ],
    "wof:name":"Raymond Haywood",
    "wof:placetype":"venue"
},
  "geometry": {"coordinates":[-1.8053090572,53.6517410278],"type":"Point"}
}