{
  "type": "Feature",
  "properties": {
    "iso:country":"GB",
    "sg:address":"Olivier Way, Cross Point Business Park",
    "sg:city":"Coventry",
    "sg:classifiers":[
        {
            "category":"Fast Food",
            "type":"Food & Drink"
        }
    ],
    "sg:phone":"+44 24 7660 3661",
    "sg:postcode":"CV2 2SH",
    "sg:province":"Warwickshire",
    "sg:tags":[
        "away",
        "take"
    ],
    "wof:name":"Burger King",
    "wof:placetype":"venue"
},
  "geometry": {"coordinates":[-1.429362,52.434994],"type":"Point"}
}