{
  "type": "Feature",
  "properties": {
    "iso:country":"GB",
    "sg:address":"Court Barton, Venny Tedburn",
    "sg:city":"Crediton",
    "sg:classifiers":[
        {
            "category":"Farming",
            "subcategory":"Livestock Farm",
            "type":"Manufacturing & Wholesale Goods"
        }
    ],
    "sg:phone":"+44 1363 772745",
    "sg:postcode":"EX17 3QB",
    "sg:province":"Devon",
    "sg:tags":[
        "others"
    ],
    "wof:name":"P Cligg",
    "wof:placetype":"venue"
},
  "geometry": {"coordinates":[-3.649697,50.788109],"type":"Point"}
}