{
  "type": "Feature",
  "properties": {
    "addr:full":"Ty Gwyn Farm, Ffordd Ty Gwyn, Eglwysbach Colwyn Bay Conwy LL28 5RN",
    "addr:postcode":"ll28 5rn",
    "addr:street":"Ffordd Ty Gwyn",
    "iso:country":"GB",
    "sg:address":"Ty Gwyn Farm, Ffordd Ty Gwyn, Eglwysbach",
    "sg:city":"Colwyn Bay",
    "sg:classifiers":[
        {
            "category":"Farming",
            "subcategory":"Farm",
            "type":"Manufacturing & Wholesale Goods"
        }
    ],
    "sg:postcode":"LL28 5RN",
    "sg:province":"Conwy",
    "sg:tags":[
        "mixed",
        "crop"
    ],
    "wof:name":"Emyr W Williams",
    "wof:placetype":"venue"
},
  "geometry": {"coordinates":[-3.792649,53.217411],"type":"Point"}
}