{
  "type": "Feature",
  "properties": {
    "iso:country":"GB",
    "sg:address":"22a Pocklingtons Walk",
    "sg:city":"Leicester",
    "sg:classifiers":[
        {
            "category":"Professional",
            "subcategory":"Management & Consulting",
            "type":"Services"
        },
        {
            "category":"Personal",
            "type":"Services"
        }
    ],
    "sg:phone":"+44 116 255 9988",
    "sg:postcode":"LE1 6BU",
    "sg:province":"Leicestershire",
    "sg:tags":[
        "consultant",
        "beauty",
        "specialist"
    ],
    "wof:name":"Nature Care Health & Beauty Clinic",
    "wof:placetype":"venue"
},
  "geometry": {"coordinates":[-1.133971,52.632565],"type":"Point"}
}