{
  "type": "Feature",
  "properties": {
    "addr:full":"21 Woodmancote, Woodmancote Dursley Gloucestershire GL11 4AF",
    "addr:housenumber":"21",
    "addr:postcode":"gl11 4af",
    "addr:street":"Woodmancote Woodmancote",
    "iso:country":"GB",
    "sg:address":"21 Woodmancote, Woodmancote",
    "sg:city":"Dursley",
    "sg:classifiers":[
        {
            "category":"Retail",
            "subcategory":"Auto Repair",
            "type":"Services"
        }
    ],
    "sg:phone":"+44 1453 545219",
    "sg:postcode":"GL11 4AF",
    "sg:province":"Gloucestershire",
    "sg:tags":[
        "body",
        "car",
        "repairer",
        "modification",
        "garage"
    ],
    "wof:name":"Yorke Body Repairs",
    "wof:placetype":"venue"
},
  "geometry": {"coordinates":[-2.3503201008,51.6790351868],"type":"Point"}
}