{
  "type": "Feature",
  "properties": {
    "iso:country":"GB",
    "sg:address":"6 Market Hill",
    "sg:city":"Huntingdon",
    "sg:classifiers":[
        {
            "category":"Professional",
            "subcategory":"Lawyer & Legal Services",
            "type":"Services"
        }
    ],
    "sg:phone":"+44 1480 378123",
    "sg:postcode":"PE18 6NR",
    "sg:province":"Cambridgeshire",
    "sg:tags":[
        "solicitor"
    ],
    "wof:name":"Stephensons Solicitors",
    "wof:placetype":"venue"
},
  "geometry": {"coordinates":[-0.184686,52.330574],"type":"Point"}
}