{
  "type": "Feature",
  "properties": {
    "addr:full":"145 Ashworth Park Knutsford Cheshire WA16 9DJ",
    "addr:housenumber":"145",
    "addr:postcode":"wa16 9dj",
    "addr:street":"Ashworth Park",
    "iso:country":"GB",
    "sg:address":"145 Ashworth Park",
    "sg:city":"Knutsford",
    "sg:classifiers":[
        {
            "category":"Wholesale",
            "subcategory":"Chemicals & Plastics",
            "type":"Manufacturing & Wholesale Goods"
        }
    ],
    "sg:phone":"+44 1565 652644",
    "sg:postcode":"WA16 9DJ",
    "sg:province":"Cheshire",
    "sg:tags":[
        "product",
        "allied"
    ],
    "wof:name":"General Chemical (Great Britain) Ltd",
    "wof:placetype":"venue"
},
  "geometry": {"coordinates":[-2.376507,53.296406],"type":"Point"}
}