{
  "type": "Feature",
  "properties": {
    "addr:full":"12a Fairland Street Wymondham Norfolk NR18 0AW",
    "addr:housenumber":"12a",
    "addr:postcode":"nr18 0aw",
    "addr:street":"Fairland Street",
    "iso:country":"GB",
    "sg:address":"12a Fairland Street",
    "sg:city":"Wymondham",
    "sg:classifiers":[
        {
            "category":"Retail",
            "subcategory":"Laundry & Dry Cleaning",
            "type":"Services"
        }
    ],
    "sg:phone":"+44 1953 607493",
    "sg:postcode":"NR18 0AW",
    "sg:province":"Norfolk",
    "sg:tags":[
        "cleaner",
        "alteration"
    ],
    "wof:name":"Riches & Ross",
    "wof:placetype":"venue"
},
  "geometry": {"coordinates":[1.1140569448,52.5693817139],"type":"Point"}
}