{
  "type": "Feature",
  "properties": {
    "iso:country":"GB",
    "sg:address":"4 Hound Close",
    "sg:city":"Abingdon",
    "sg:classifiers":[
        {
            "category":"Professional",
            "subcategory":"Management & Consulting",
            "type":"Services"
        }
    ],
    "sg:phone":"+44 1235 201926",
    "sg:postcode":"OX14 2LU",
    "sg:province":"Oxfordshire",
    "sg:tags":[
        "marketing",
        "consultant"
    ],
    "wof:name":"Oxford Marketing Partnership",
    "wof:placetype":"venue"
},
  "geometry": {"coordinates":[-1.257764,51.68504],"type":"Point"}
}