{
  "type": "Feature",
  "properties": {
    "addr:full":"High Street, Shifnal Telford Shropshire TF8 7AD",
    "addr:postcode":"tf8 7ad",
    "addr:street":"High Street",
    "iso:country":"GB",
    "sg:address":"High Street, Shifnal",
    "sg:city":"Telford",
    "sg:classifiers":[
        {
            "category":"Bars & Pubs",
            "type":"Food & Drink"
        }
    ],
    "sg:phone":"+44 1952 460746",
    "sg:postcode":"TF8 7AD",
    "sg:province":"Shropshire",
    "sg:tags":[
        "pubs",
        "inn"
    ],
    "wof:name":"Royal George",
    "wof:placetype":"venue"
},
  "geometry": {"coordinates":[-2.483809,52.627811],"type":"Point"}
}