{
  "type": "Feature",
  "properties": {
    "addr:full":"69 Occupation Road, Albert Village Swadlincote Derbyshire DE11 8HA",
    "addr:housenumber":"69",
    "addr:postcode":"de11 8ha",
    "addr:street":"Occupation Road Albert Village",
    "iso:country":"GB",
    "sg:address":"69 Occupation Road, Albert Village",
    "sg:city":"Swadlincote",
    "sg:classifiers":[
        {
            "category":"Food & Beverages",
            "subcategory":"Specialty",
            "type":"Retail Goods"
        },
        {
            "category":"Food & Beverages",
            "subcategory":"Supermarket",
            "type":"Retail Goods"
        }
    ],
    "sg:postcode":"DE11 8HA",
    "sg:province":"Derbyshire",
    "sg:tags":[
        "frozen",
        "dietetic",
        "homogenised"
    ],
    "wof:name":"Ambrosian Vegeterian Foods",
    "wof:placetype":"venue"
},
  "geometry": {"coordinates":[-1.556159,52.75555],"type":"Point"}
}