{
  "type": "Feature",
  "properties": {
    "addr:full":"37 Cedar Rise London Greater London N14 5NJ",
    "addr:housenumber":"37",
    "addr:postcode":"n14 5nj",
    "addr:street":"Cedar Rise",
    "iso:country":"GB",
    "sg:address":"37 Cedar Rise",
    "sg:city":"London",
    "sg:classifiers":[
        {
            "category":"Personal",
            "subcategory":"Beauty Salon",
            "type":"Services"
        }
    ],
    "sg:phone":"+44 20 8361 6700",
    "sg:postcode":"N14 5NJ",
    "sg:province":"Greater London",
    "wof:name":"The Sugaring Co",
    "wof:placetype":"venue"
},
  "geometry": {"coordinates":[-0.1452469975,51.6376266479],"type":"Point"}
}