{
  "type": "Feature",
  "properties": {
    "iso:country":"GB",
    "sg:address":"48a Brimstage Rd",
    "sg:city":"Wirral",
    "sg:classifiers":[
        {
            "category":"Building & Trades",
            "subcategory":"Construction",
            "type":"Services"
        }
    ],
    "sg:phone":"+44 151 342 5526",
    "sg:postcode":"CH60 1XG",
    "sg:province":"Merseyside",
    "sg:tags":[
        "dry",
        "lining",
        "plasterers",
        "screeders"
    ],
    "wof:name":"G A Smith",
    "wof:placetype":"venue"
},
  "geometry": {"coordinates":[-3.078506,53.326221],"type":"Point"}
}