{
  "type": "Feature",
  "properties": {
    "addr:full":"13 Royal St Sandown Isle of Wight PO36 8LP",
    "addr:housenumber":"13",
    "addr:postcode":"po36 8lp",
    "addr:street":"Royal St",
    "iso:country":"GB",
    "sg:address":"13 Royal St",
    "sg:city":"Sandown",
    "sg:classifiers":[
        {
            "category":"Building & Trades",
            "subcategory":"Equipment Rental",
            "type":"Services"
        }
    ],
    "sg:postcode":"PO36 8LP",
    "sg:province":"Isle of Wight",
    "sg:tags":[
        "plant",
        "machinery"
    ],
    "wof:name":"Slater,S D,",
    "wof:placetype":"venue"
},
  "geometry": {"coordinates":[-1.1578110456,50.6537055969],"type":"Point"}
}