{
  "type": "Feature",
  "properties": {
    "addr:full":"Bridge House, South Street Farnham Surrey GU9 7RS",
    "addr:postcode":"gu9 7rs",
    "addr:street":"South Street",
    "iso:country":"GB",
    "sg:address":"Bridge House, South Street",
    "sg:city":"Farnham",
    "sg:classifiers":[
        {
            "category":"Insurance",
            "subcategory":"Insurance Agent",
            "type":"Services"
        }
    ],
    "sg:phone":"+44 1252 892400",
    "sg:postcode":"GU9 7RS",
    "sg:province":"Surrey",
    "wof:name":"Legal & General Assurance Society Ltd.",
    "wof:placetype":"venue"
},
  "geometry": {"coordinates":[-0.796794,51.215027],"type":"Point"}
}