{
  "type": "Feature",
  "properties": {
    "iso:country":"GB",
    "sg:address":"2 Railway Street",
    "sg:city":"Bishop Auckland",
    "sg:classifiers":[
        {
            "category":"Fast Food",
            "type":"Food & Drink"
        }
    ],
    "sg:phone":"+44 1388 662228",
    "sg:postcode":"DL14 7LR",
    "sg:province":"Durham",
    "sg:tags":[
        "away",
        "take"
    ],
    "wof:name":"Happy Valley Chop Suey House",
    "wof:placetype":"venue"
},
  "geometry": {"coordinates":[-1.6725100279,54.659286499],"type":"Point"}
}