{
  "type": "Feature",
  "properties": {
    "addr:full":"11 Seddon Place, Stanley Industrial Estate Skelmersdale Lancashire WN8 8EB",
    "addr:housenumber":"11",
    "addr:postcode":"wn8 8eb",
    "addr:street":"Seddon Place;Industrial Estate",
    "iso:country":"GB",
    "sg:address":"11 Seddon Place, Stanley Industrial Estate",
    "sg:city":"Skelmersdale",
    "sg:classifiers":[
        {
            "category":"Home & Garden",
            "subcategory":"Building Materials",
            "type":"Retail Goods"
        }
    ],
    "sg:phone":"+44 1695 555444",
    "sg:postcode":"WN8 8EB",
    "sg:province":"Lancashire",
    "sg:tags":[
        "wire",
        "cable"
    ],
    "wof:name":"Elwers Ltd.",
    "wof:placetype":"venue"
},
  "geometry": {"coordinates":[-2.799738884,53.5598449707],"type":"Point"}
}