{
  "type": "Feature",
  "properties": {
    "addr:full":"3 High Road Newport-on-tay Fife DD6 8HD",
    "addr:housenumber":"3",
    "addr:postcode":"dd6 8hd",
    "addr:street":"High Road",
    "iso:country":"GB",
    "sg:address":"3 High Road",
    "sg:city":"Newport-on-tay",
    "sg:classifiers":[
        {
            "category":"Health Services",
            "subcategory":"Nursing And Care Facility",
            "type":"Services"
        },
        {
            "category":"Social Services",
            "subcategory":"Retirement Home",
            "type":"Services"
        }
    ],
    "sg:phone":"+44 1382 542276",
    "sg:postcode":"DD6 8HD",
    "sg:province":"Fife",
    "sg:tags":[
        "residential"
    ],
    "wof:name":"St.Serf's Eventide Home",
    "wof:placetype":"venue"
},
  "geometry": {"coordinates":[-2.9421129227,56.4394989014],"type":"Point"}
}