{
  "type": "Feature",
  "properties": {
    "addr:full":"12 Kingsway Road, Fallings Park Wolverhampton Staffordshire WV10 0SD",
    "addr:housenumber":"12",
    "addr:postcode":"wv10 0sd",
    "addr:street":"Kingsway Road",
    "iso:country":"GB",
    "sg:address":"12 Kingsway Road, Fallings Park",
    "sg:city":"Wolverhampton",
    "sg:classifiers":[
        {
            "category":"Shopping",
            "type":"Retail Goods"
        }
    ],
    "sg:phone":"+44 1902 731743",
    "sg:postcode":"WV10 0SD",
    "sg:province":"Staffordshire",
    "sg:tags":[
        "part",
        "accessory"
    ],
    "wof:name":"D & H Volk Spares",
    "wof:placetype":"venue"
},
  "geometry": {"coordinates":[-2.102117,52.60556],"type":"Point"}
}