{
  "type": "Feature",
  "properties": {
    "addr:full":"32 Battersea Business Centre, 99/109 Lavender Hill London Greater London SW11 5QL",
    "addr:housenumber":"32;99 / 109",
    "addr:postcode":"sw11 5ql",
    "addr:street":"Battersea Business;Lavender Hill",
    "iso:country":"GB",
    "sg:address":"32 Battersea Business Centre, 99/109 Lavender Hill",
    "sg:city":"London",
    "sg:classifiers":[
        {
            "category":"Professional",
            "subcategory":"Business Services",
            "type":"Services"
        }
    ],
    "sg:phone":"+44 20 7223 6744",
    "sg:postcode":"SW11 5QL",
    "sg:province":"Greater London",
    "sg:tags":[
        "management",
        "pub"
    ],
    "wof:name":"J & W Johnson & Co. Ltd.",
    "wof:placetype":"venue"
},
  "geometry": {"coordinates":[-0.1559469998,51.4654045105],"type":"Point"}
}