{
  "type": "Feature",
  "properties": {
    "addr:full":"46 Nevern Road Rayleigh Essex SS6 7PE",
    "addr:housenumber":"46",
    "addr:postcode":"ss6 7pe",
    "addr:street":"Nevern Road Rayleigh",
    "iso:country":"GB",
    "sg:address":"46 Nevern Road",
    "sg:city":"Rayleigh",
    "sg:classifiers":[
        {
            "category":"Organizations",
            "subcategory":"Membership Organization",
            "type":"Services"
        }
    ],
    "sg:postcode":"SS6 7PE",
    "sg:province":"Essex",
    "sg:tags":[
        "club"
    ],
    "wof:name":"Victoria Mews (Blocks A  B & C) Management Co. Ltd.",
    "wof:placetype":"venue"
},
  "geometry": {"coordinates":[0.620223,51.577705],"type":"Point"}
}