{
  "type": "Feature",
  "properties": {
    "addr:full":"70 Seymour Grove Manchester Cheshire M16 0LW",
    "addr:housenumber":"70",
    "addr:postcode":"m16 0lw",
    "addr:street":"Seymour Grove",
    "iso:country":"GB",
    "sg:address":"70 Seymour Grove",
    "sg:city":"Manchester",
    "sg:classifiers":[
        {
            "category":"Health Services",
            "subcategory":"Doctor",
            "type":"Services"
        }
    ],
    "sg:phone":"+44 161 877 9230",
    "sg:postcode":"M16 0LW",
    "sg:province":"Cheshire",
    "sg:tags":[
        "practitioners"
    ],
    "wof:name":"K Kuna",
    "wof:placetype":"venue"
},
  "geometry": {"coordinates":[-2.273349,53.452888],"type":"Point"}
}