{
  "type": "Feature",
  "properties": {
    "iso:country":"GB",
    "sg:address":"73 High Street",
    "sg:city":"Hastings",
    "sg:classifiers":[
        {
            "category":"Shopping",
            "subcategory":"Used Merchandise",
            "type":"Retail Goods"
        }
    ],
    "sg:phone":"+44 1424 718206",
    "sg:postcode":"TN34 3EL",
    "sg:province":"East Sussex",
    "sg:tags":[
        "shop",
        "second-hand"
    ],
    "wof:name":"D D's Imporium",
    "wof:placetype":"venue"
},
  "geometry": {"coordinates":[0.591492,50.85762],"type":"Point"}
}