{
  "type": "Feature",
  "properties": {
    "addr:full":"11 Prairie Crescent Burnley Lancashire BB10 1EU",
    "addr:housenumber":"11",
    "addr:postcode":"bb10 1eu",
    "addr:street":"Prairie Crescent",
    "iso:country":"GB",
    "sg:address":"11 Prairie Crescent",
    "sg:city":"Burnley",
    "sg:classifiers":[
        {
            "category":"Building & Trades",
            "subcategory":"Construction",
            "type":"Services"
        }
    ],
    "sg:postcode":"BB10 1EU",
    "sg:province":"Lancashire",
    "sg:tags":[
        "roofing",
        "builder"
    ],
    "wof:name":"A1 Steadfast Building & Roofing Contractors",
    "wof:placetype":"venue"
},
  "geometry": {"coordinates":[-2.235448,53.810349],"type":"Point"}
}