{
  "type": "Feature",
  "properties": {
    "addr:full":"208 Bellenden Road London Greater London SE15 4BW",
    "addr:housenumber":"208",
    "addr:postcode":"se15 4bw",
    "addr:street":"Bellenden Road",
    "iso:country":"GB",
    "sg:address":"208 Bellenden Road",
    "sg:city":"London",
    "sg:classifiers":[
        {
            "category":"Building & Trades",
            "subcategory":"Plumbing",
            "type":"Services"
        }
    ],
    "sg:postcode":"SE15 4BW",
    "sg:province":"Greater London",
    "sg:tags":[
        "heating"
    ],
    "wof:name":"Elite Heating & Plumbing",
    "wof:placetype":"venue"
},
  "geometry": {"coordinates":[-0.0741119981,51.4660682678],"type":"Point"}
}