{
  "type": "Feature",
  "properties": {
    "addr:full":"Unit 309 Grosvenor House, Hollinswood Road, Central Park Telford Shropshire TF2 9TW",
    "addr:housenumber":"309;house",
    "addr:postcode":"tf2 9tw",
    "addr:street":"Grosvenor;Hollinswood Road",
    "iso:country":"GB",
    "sg:address":"Unit 309 Grosvenor House, Hollinswood Road, Central Park",
    "sg:city":"Telford",
    "sg:classifiers":[
        {
            "category":"Professional",
            "subcategory":"Computer Services",
            "type":"Services"
        }
    ],
    "sg:phone":"+44 1952 200024",
    "sg:postcode":"TF2 9TW",
    "sg:province":"Shropshire",
    "sg:tags":[
        "consultant"
    ],
    "wof:name":"Infor Global Solutions Uk (Auto) Ltd.",
    "wof:placetype":"venue"
},
  "geometry": {"coordinates":[-2.4435839653,52.6866149902],"type":"Point"}
}