{
  "type": "Feature",
  "properties": {
    "addr:full":"9-11 Bridge Street Northampton Northamptonshire NN1 1NH",
    "addr:housenumber":"9-11",
    "addr:postcode":"nn1 1nh",
    "addr:street":"Bridge Street",
    "iso:country":"GB",
    "sg:address":"9-11 Bridge Street",
    "sg:city":"Northampton",
    "sg:classifiers":[
        {
            "category":"Real Estate",
            "subcategory":"Real Estate Agent",
            "type":"Services"
        }
    ],
    "sg:phone":"+44 1604 632322",
    "sg:postcode":"NN1 1NH",
    "sg:province":"Northamptonshire",
    "wof:name":"William H Brown",
    "wof:placetype":"venue"
},
  "geometry": {"coordinates":[-0.8970530033,52.2364082336],"type":"Point"}
}