{
  "type": "Feature",
  "properties": {
    "addr:full":"29 Prospect Bank Place Edinburgh City of Edinburgh EH6 7PT",
    "addr:housenumber":"29",
    "addr:postcode":"eh6 7pt",
    "addr:street":"Prospect Bank Place Edinburgh",
    "iso:country":"GB",
    "sg:address":"29 Prospect Bank Place",
    "sg:city":"Edinburgh",
    "sg:classifiers":[
        {
            "category":"Professional",
            "subcategory":"Engineering",
            "type":"Services"
        },
        {
            "category":"Building & Trades",
            "subcategory":"Electrical",
            "type":"Services"
        }
    ],
    "sg:phone":"+44 131 555 0797",
    "sg:postcode":"EH6 7PT",
    "sg:province":"City of Edinburgh",
    "sg:tags":[
        "engineer",
        "electrician",
        "contractor"
    ],
    "wof:name":"L D M Electrical & Associated Services",
    "wof:placetype":"venue"
},
  "geometry": {"coordinates":[-3.1641139984,55.9774932861],"type":"Point"}
}