{
  "type": "Feature",
  "properties": {
    "iso:country":"GB",
    "sg:address":"6 Blackhall Square",
    "sg:city":"Kelty",
    "sg:classifiers":[
        {
            "category":"Farming",
            "subcategory":"Fish & Marine Products",
            "type":"Manufacturing & Wholesale Goods"
        },
        {
            "category":"Food & Beverages",
            "subcategory":"Meat & Fish",
            "type":"Retail Goods"
        }
    ],
    "sg:phone":"+44 1383 830272",
    "sg:postcode":"KY4 0EP",
    "sg:province":"Fife",
    "sg:tags":[
        "fishmonger",
        "butcher"
    ],
    "wof:name":"J Halkett",
    "wof:placetype":"venue"
},
  "geometry": {"coordinates":[-3.389109,56.132553],"type":"Point"}
}