{
  "type": "Feature",
  "properties": {
    "iso:country":"GB",
    "sg:address":"The Strand Shopping Arcade, Stratford Road",
    "sg:city":"Bromsgrove",
    "sg:classifiers":[
        {
            "category":"Personal",
            "subcategory":"Beauty Salon",
            "type":"Services"
        }
    ],
    "sg:phone":"+44 1527 877774",
    "sg:postcode":"B60 1AP",
    "sg:province":"Worcestershire",
    "sg:tags":[
        "unisex",
        "hairdresser"
    ],
    "wof:name":"Perfections Hair Studio",
    "wof:placetype":"venue"
},
  "geometry": {"coordinates":[-2.025205,52.367176],"type":"Point"}
}