{
  "type": "Feature",
  "properties": {
    "addr:full":"Dorn Hill Farm Moreton-in-marsh Gloucestershire GL56 9QG",
    "addr:postcode":"gl56 9qg",
    "addr:street":"Dorn Hill",
    "iso:country":"GB",
    "sg:address":"Dorn Hill Farm",
    "sg:city":"Moreton-in-marsh",
    "sg:classifiers":[
        {
            "category":"Wholesale",
            "subcategory":"Construction Materials",
            "type":"Manufacturing & Wholesale Goods"
        }
    ],
    "sg:phone":"+44 1608 652769",
    "sg:postcode":"GL56 9QG",
    "sg:province":"Gloucestershire",
    "sg:tags":[
        "sawdust",
        "sawmills",
        "shaving"
    ],
    "wof:name":"Batsford Park Saw Mill",
    "wof:placetype":"venue"
},
  "geometry": {"coordinates":[-1.703281045,51.9897270203],"type":"Point"}
}