{
  "type": "Feature",
  "properties": {
    "iso:country":"GB",
    "sg:address":"24 Upr Dicconson St",
    "sg:city":"Wigan",
    "sg:classifiers":[
        {
            "category":"Professional",
            "subcategory":"Accounting & Tax Preparation",
            "type":"Services"
        }
    ],
    "sg:phone":"+44 1942 495040",
    "sg:postcode":"WN1 2AG",
    "sg:province":"Lancashire",
    "sg:tags":[
        "consultant"
    ],
    "wof:name":"Taxation Projects Ltd",
    "wof:placetype":"venue"
},
  "geometry": {"coordinates":[-2.630642,53.550964],"type":"Point"}
}