{
  "type": "Feature",
  "properties": {
    "addr:full":"22 Hildreth Street London Greater London SW12 9RQ",
    "addr:housenumber":"22",
    "addr:postcode":"sw12 9rq",
    "addr:street":"Hildreth Street",
    "iso:country":"GB",
    "sg:address":"22 Hildreth Street",
    "sg:city":"London",
    "sg:classifiers":[
        {
            "category":"Food & Beverages",
            "subcategory":"Meat & Fish",
            "type":"Retail Goods"
        }
    ],
    "sg:phone":"+44 20 8673 7285",
    "sg:postcode":"SW12 9RQ",
    "sg:province":"Greater London",
    "sg:tags":[
        "butcher"
    ],
    "wof:name":"Fair Price",
    "wof:placetype":"venue"
},
  "geometry": {"coordinates":[-0.151088,51.444283],"type":"Point"}
}