{
  "type": "Feature",
  "properties": {
    "iso:country":"GB",
    "sg:address":"250-252 Chingford Mount Road",
    "sg:city":"London",
    "sg:classifiers":[
        {
            "category":"Bars & Pubs",
            "type":"Food & Drink"
        }
    ],
    "sg:phone":"+44 20 8523 9365",
    "sg:postcode":"E4 8JL",
    "sg:province":"Greater London",
    "sg:tags":[
        "pubs",
        "inn"
    ],
    "wof:name":"The Kings Ford",
    "wof:placetype":"venue"
},
  "geometry": {"coordinates":[-0.017244,51.6163902283],"type":"Point"}
}