{
  "type": "Feature",
  "properties": {
    "addr:full":"13 Hall Walk, Coleshill Birmingham Warwickshire B46 3ES",
    "addr:housenumber":"13",
    "addr:postcode":"b46 3es",
    "addr:street":"Hall Walk",
    "iso:country":"GB",
    "sg:address":"13 Hall Walk, Coleshill",
    "sg:city":"Birmingham",
    "sg:classifiers":[
        {
            "category":"Shopping",
            "subcategory":"Party Supplies",
            "type":"Retail Goods"
        }
    ],
    "sg:postcode":"B46 3ES",
    "sg:province":"Warwickshire",
    "sg:tags":[
        "inflatables",
        "bouncy",
        "castle"
    ],
    "wof:name":"Munday,Helen,",
    "wof:placetype":"venue"
},
  "geometry": {"coordinates":[-1.707139,52.48719],"type":"Point"}
}