{
  "type": "Feature",
  "properties": {
    "iso:country":"GB",
    "sg:address":"Parracombe, Yeovil Marsh",
    "sg:city":"Yeovil",
    "sg:classifiers":[
        {
            "category":"Retail",
            "subcategory":"Auto Repair",
            "type":"Services"
        }
    ],
    "sg:phone":"+44 1935 428870",
    "sg:postcode":"BA21 3QY",
    "sg:province":"Somerset",
    "sg:tags":[
        "engine",
        "specialist",
        "diagnostic",
        "tuning",
        "car"
    ],
    "wof:name":"Mobiletuning",
    "wof:placetype":"venue"
},
  "geometry": {"coordinates":[-2.639292,50.948441],"type":"Point"}
}