{
  "type": "Feature",
  "properties": {
    "addr:full":"Northgate Sleaford Lincolnshire NG34 7BB",
    "addr:postcode":"ng34 7bb",
    "addr:street":"Northgate",
    "iso:country":"GB",
    "sg:address":"Northgate",
    "sg:city":"Sleaford",
    "sg:classifiers":[
        {
            "category":"Autos & Motor Vehicles",
            "subcategory":"Auto Supplies",
            "type":"Retail Goods"
        }
    ],
    "sg:phone":"+44 1529 305200",
    "sg:postcode":"NG34 7BB",
    "sg:province":"Lincolnshire",
    "sg:tags":[
        "car",
        "part",
        "tyre",
        "accessory"
    ],
    "wof:name":"B A Bush Tyres",
    "wof:placetype":"venue"
},
  "geometry": {"coordinates":[-0.411869,52.994587],"type":"Point"}
}