{
  "type": "Feature",
  "properties": {
    "iso:country":"GB",
    "sg:address":"72 Highters Road",
    "sg:city":"Birmingham",
    "sg:classifiers":[
        {
            "category":"Professional",
            "subcategory":"Art Services",
            "type":"Services"
        },
        {
            "category":"Building & Trades",
            "subcategory":"Construction",
            "type":"Services"
        }
    ],
    "sg:phone":"+44 121 430 6565",
    "sg:postcode":"B14 4ND",
    "sg:province":"West Midlands",
    "sg:tags":[
        "decorator",
        "painter"
    ],
    "wof:name":"VICTOR SMITH",
    "wof:placetype":"venue"
},
  "geometry": {"coordinates":[-1.879362,52.409966],"type":"Point"}
}