{
  "type": "Feature",
  "properties": {
    "iso:country":"GB",
    "sg:address":"43 Frederick St",
    "sg:city":"Seaham",
    "sg:classifiers":[
        {
            "category":"Building & Trades",
            "subcategory":"Construction",
            "type":"Services"
        }
    ],
    "sg:phone":"+44 191 581 0459",
    "sg:postcode":"SR7 7HX",
    "sg:province":"Durham",
    "sg:tags":[
        "roofing"
    ],
    "wof:name":"Seaham Roofing",
    "wof:placetype":"venue"
},
  "geometry": {"coordinates":[-1.332835,54.834431],"type":"Point"}
}