{
  "type": "Feature",
  "properties": {
    "addr:full":"9 Hangman Lane, Dinnington Sheffield South Yorkshire S25 3PF",
    "addr:housenumber":"9",
    "addr:postcode":"s25 3pf",
    "addr:street":"Hangman Lane",
    "iso:country":"GB",
    "sg:address":"9 Hangman Lane, Dinnington",
    "sg:city":"Sheffield",
    "sg:classifiers":[
        {
            "category":"Building & Trades",
            "subcategory":"Construction",
            "type":"Services"
        }
    ],
    "sg:postcode":"S25 3PF",
    "sg:province":"South Yorkshire",
    "sg:tags":[
        "builder"
    ],
    "wof:name":"Kelwood Heating (1973) Ltd",
    "wof:placetype":"venue"
},
  "geometry": {"coordinates":[-1.231886,53.379322],"type":"Point"}
}