{
  "type": "Feature",
  "properties": {
    "iso:country":"GB",
    "sg:address":"17 Tatton Road, Sale",
    "sg:city":"Manchester",
    "sg:classifiers":[
        {
            "category":"Shopping",
            "subcategory":"Gifts & Souvenirs",
            "type":"Retail Goods"
        }
    ],
    "sg:phone":"+44 161 962 9495",
    "sg:postcode":"M33 7EB",
    "sg:province":"Cheshire",
    "sg:tags":[
        "shop"
    ],
    "wof:name":"Casa",
    "wof:placetype":"venue"
},
  "geometry": {"coordinates":[-2.3203160763,53.4255485535],"type":"Point"}
}