{
  "type": "Feature",
  "properties": {
    "iso:country":"GB",
    "sg:address":"Doncaster Moat Ho, Warmsworth",
    "sg:city":"Doncaster",
    "sg:classifiers":[
        {
            "category":"Sports & Exercise",
            "subcategory":"Gym",
            "type":"Entertainment"
        }
    ],
    "sg:phone":"+44 1302 311102",
    "sg:postcode":"DN4 9UX",
    "sg:province":"South Yorkshire",
    "sg:tags":[
        "club",
        "fitness",
        "health",
        "centre"
    ],
    "wof:name":"DONCASTER MOAT HOUSE",
    "wof:placetype":"venue"
},
  "geometry": {"coordinates":[-1.181324,53.498768],"type":"Point"}
}