{
  "type": "Feature",
  "properties": {
    "addr:full":"9 Broadway Parade, Pinner Road Harrow Greater London HA2 7SZ",
    "addr:housenumber":"9",
    "addr:postcode":"ha2 7sz",
    "addr:street":"Broadway Parade Pinner Road",
    "iso:country":"GB",
    "sg:address":"9 Broadway Parade, Pinner Road",
    "sg:city":"Harrow",
    "sg:classifiers":[
        {
            "category":"Professional",
            "subcategory":"Lawyer & Legal Services",
            "type":"Services"
        }
    ],
    "sg:phone":"+44 20 8427 5292",
    "sg:postcode":"HA2 7SZ",
    "sg:province":"Greater London",
    "sg:tags":[
        "solicitor"
    ],
    "wof:name":"Lynch Hall & Hornby",
    "wof:placetype":"venue"
},
  "geometry": {"coordinates":[-0.361184,51.585739],"type":"Point"}
}