{
  "type": "Feature",
  "properties": {
    "addr:full":"22 Baralgette Gdns New Malden Surrey KT3 5HF",
    "addr:housenumber":"22",
    "addr:postcode":"kt3 5hf",
    "addr:street":"Baralgette Gdns",
    "iso:country":"GB",
    "sg:address":"22 Baralgette Gdns",
    "sg:city":"New Malden",
    "sg:classifiers":[
        {
            "category":"Retail",
            "subcategory":"Repair Shop",
            "type":"Services"
        }
    ],
    "sg:postcode":"KT3 5HF",
    "sg:province":"Surrey",
    "sg:tags":[
        "maintenance"
    ],
    "wof:name":"Alden Builders",
    "wof:placetype":"venue"
},
  "geometry": {"coordinates":[-0.256194,51.401772],"type":"Point"}
}