{
  "type": "Feature",
  "properties": {
    "addr:full":"Susan Back, 78a Downs Park Road London Greater London E8 2HZ",
    "addr:housenumber":"78a",
    "addr:postcode":"e8 2hz",
    "addr:street":"Downs Park Road",
    "iso:country":"GB",
    "sg:address":"Susan Back, 78a Downs Park Road",
    "sg:city":"London",
    "sg:classifiers":[
        {
            "category":"Communications",
            "subcategory":"Newspaper",
            "type":"Services"
        }
    ],
    "sg:postcode":"E8 2HZ",
    "sg:province":"Greater London",
    "sg:tags":[
        "magazine"
    ],
    "wof:name":"Pacific Publications Pty Ltd.",
    "wof:placetype":"venue"
},
  "geometry": {"coordinates":[-0.06463,51.551559],"type":"Point"}
}