{
  "type": "Feature",
  "properties": {
    "iso:country":"GB",
    "sg:address":"Long Barn, Etchden Farm",
    "sg:city":"Ashford",
    "sg:classifiers":[
        {
            "category":"Home & Garden",
            "subcategory":"Household Appliances",
            "type":"Retail Goods"
        }
    ],
    "sg:phone":"+44 1233 820515",
    "sg:postcode":"TN26 3DP",
    "sg:province":"Kent",
    "sg:tags":[
        "cleaner",
        "domestic",
        "vacuum"
    ],
    "wof:name":"Ultravac",
    "wof:placetype":"venue"
},
  "geometry": {"coordinates":[0.78599,51.14222],"type":"Point"}
}