{
  "type": "Feature",
  "properties": {
    "iso:country":"GB",
    "sg:address":"63 Wickfield Rd",
    "sg:city":"Sheffield",
    "sg:classifiers":[
        {
            "category":"Home & Garden",
            "subcategory":"Building Materials",
            "type":"Retail Goods"
        }
    ],
    "sg:phone":"+44 114 253 1859",
    "sg:postcode":"S12 4TW",
    "sg:province":"Derbyshire",
    "sg:tags":[
        "fencing"
    ],
    "wof:name":"M G Fencing",
    "wof:placetype":"venue"
},
  "geometry": {"coordinates":[-1.39091,53.352596],"type":"Point"}
}