{
  "type": "Feature",
  "properties": {
    "addr:full":"1 Glenfield Frith Drive, Glenfield Leicester Leicestershire LE3 8PU",
    "addr:housenumber":"1",
    "addr:postcode":"le3 8pu",
    "addr:street":"Glenfield Frith Drive",
    "iso:country":"GB",
    "sg:address":"1 Glenfield Frith Drive, Glenfield",
    "sg:city":"Leicester",
    "sg:classifiers":[
        {
            "category":"Shopping",
            "subcategory":"Clothing, Apparel, & Fashions",
            "type":"Retail Goods"
        }
    ],
    "sg:phone":"+44 116 287 6123",
    "sg:postcode":"LE3 8PU",
    "sg:province":"Leicestershire",
    "sg:tags":[
        "clothing"
    ],
    "wof:name":"Rowan Styles Ltd.",
    "wof:placetype":"venue"
},
  "geometry": {"coordinates":[-1.184154,52.652912],"type":"Point"}
}