{
  "type": "Feature",
  "properties": {
    "addr:full":"57-61 Mortimer Street London, W1W 8HS",
    "addr:housenumber":"57-61",
    "addr:postcode":"w1w 8hs",
    "addr:street":"Mortimer Street",
    "iso:country":"GB",
    "sg:address":"57-61 Mortimer Street",
    "sg:city":"London,",
    "sg:classifiers":[
        {
            "category":"Professional",
            "subcategory":"Computer Services",
            "type":"Services"
        }
    ],
    "sg:postcode":"W1W 8HS",
    "sg:tags":[
        "web-2-0",
        "web-development",
        "design",
        "strategy",
        "ajax",
        "agency",
        "london",
        "matt-hagger"
    ],
    "sg:website":"http://www.e-man.co.uk",
    "wof:name":"e-Man",
    "wof:placetype":"venue"
},
  "geometry": {"coordinates":[-0.141022,51.517712],"type":"Point"}
}