{
  "type": "Feature",
  "properties": {
    "addr:full":"17 Hillside Road Sutton Coldfield Staffordshire B74 4DG",
    "addr:housenumber":"17",
    "addr:postcode":"b74 4dg",
    "addr:street":"Hillside Road",
    "iso:country":"GB",
    "sg:address":"17 Hillside Road",
    "sg:city":"Sutton Coldfield",
    "sg:classifiers":[
        {
            "category":"Professional",
            "subcategory":"Art Services",
            "type":"Services"
        },
        {
            "category":"Building & Trades",
            "subcategory":"Construction",
            "type":"Services"
        }
    ],
    "sg:phone":"+44 121 308 8872",
    "sg:postcode":"B74 4DG",
    "sg:province":"Staffordshire",
    "sg:tags":[
        "decorator",
        "painter"
    ],
    "wof:name":"Robert J Brown",
    "wof:placetype":"venue"
},
  "geometry": {"coordinates":[-1.837916,52.593395],"type":"Point"}
}