{
  "type": "Feature",
  "properties": {
    "iso:country":"GB",
    "sg:address":"Unit 3a North Deeside Road",
    "sg:city":"Banchory",
    "sg:classifiers":[
        {
            "category":"Retail",
            "subcategory":"Auto Repair",
            "type":"Services"
        }
    ],
    "sg:phone":"+44 1330 822255",
    "sg:postcode":"AB31 3YR",
    "sg:province":"Aberdeen City",
    "sg:tags":[
        "modification",
        "garage"
    ],
    "wof:name":"C & D Autos",
    "wof:placetype":"venue"
},
  "geometry": {"coordinates":[-2.501389,57.051174],"type":"Point"}
}