{
  "type": "Feature",
  "properties": {
    "addr:full":"200 Well Street London Greater London E9 6QT",
    "addr:housenumber":"200",
    "addr:postcode":"e9 6qt",
    "addr:street":"Well Street",
    "iso:country":"GB",
    "sg:address":"200 Well Street",
    "sg:city":"London",
    "sg:classifiers":[
        {
            "category":"Shopping",
            "subcategory":"Gifts & Souvenirs",
            "type":"Retail Goods"
        }
    ],
    "sg:phone":"+44 20 8986 6154",
    "sg:postcode":"E9 6QT",
    "sg:province":"Greater London",
    "sg:tags":[
        "poster",
        "card"
    ],
    "wof:name":"John's Cards",
    "wof:placetype":"venue"
},
  "geometry": {"coordinates":[-0.0468150005,51.5440177917],"type":"Point"}
}