{
  "type": "Feature",
  "properties": {
    "iso:country":"GB",
    "sg:address":"Unit 4 Smethwick, New Enterprise Centre, Rolf Street",
    "sg:city":"Smethwick",
    "sg:classifiers":[
        {
            "category":"Manufacturing",
            "subcategory":"Rubber & Plastics",
            "type":"Manufacturing & Wholesale Goods"
        }
    ],
    "sg:phone":"+44 121 565 0216",
    "sg:postcode":"B66 2AR",
    "sg:province":"West Midlands",
    "sg:tags":[
        "mould"
    ],
    "wof:name":"Runners Precision Tooling",
    "wof:placetype":"venue"
},
  "geometry": {"coordinates":[-1.971184,52.495926],"type":"Point"}
}