{
  "type": "Feature",
  "properties": {
    "addr:full":"2 Grace Close Stroud Gloucestershire GL6 8HB",
    "addr:housenumber":"2",
    "addr:postcode":"gl6 8hb",
    "addr:street":"Grace Close",
    "iso:country":"GB",
    "sg:address":"2 Grace Close",
    "sg:city":"Stroud",
    "sg:classifiers":[
        {
            "category":"Travel",
            "subcategory":"Hotels & Motels",
            "type":"Entertainment"
        }
    ],
    "sg:phone":"+44 1453 885315",
    "sg:postcode":"GL6 8HB",
    "sg:province":"Gloucestershire",
    "sg:tags":[
        "self",
        "catering"
    ],
    "wof:name":"D F H Chapman Properties",
    "wof:placetype":"venue"
},
  "geometry": {"coordinates":[-2.1656000614,51.7319908142],"type":"Point"}
}