{
  "type": "Feature",
  "properties": {
    "iso:country":"GB",
    "sg:address":"45 Holbrook Lane",
    "sg:city":"Chislehurst",
    "sg:classifiers":[
        {
            "category":"Social Services",
            "subcategory":"Retirement Home",
            "type":"Services"
        }
    ],
    "sg:postcode":"BR7 6PE",
    "sg:province":"Kent",
    "sg:tags":[
        "residential",
        "care"
    ],
    "wof:name":"Antokol Home",
    "wof:placetype":"venue"
},
  "geometry": {"coordinates":[0.083115,51.409618],"type":"Point"}
}