{
  "type": "Feature",
  "properties": {
    "addr:full":"The Cold Store, 140 Norman Rd West Malling Kent ME19 6RW",
    "addr:housenumber":"140",
    "addr:postcode":"me19 6rw",
    "addr:street":"Norman Rd",
    "iso:country":"GB",
    "sg:address":"The Cold Store, 140 Norman Rd",
    "sg:city":"West Malling",
    "sg:classifiers":[
        {
            "category":"Shopping",
            "subcategory":"Hobbies, Toys, & Games",
            "type":"Retail Goods"
        }
    ],
    "sg:phone":"+44 1732 870023",
    "sg:postcode":"ME19 6RW",
    "sg:province":"Kent",
    "sg:tags":[
        "gunsmith"
    ],
    "wof:name":"Country Way Airguns",
    "wof:placetype":"venue"
},
  "geometry": {"coordinates":[0.41294,51.293709],"type":"Point"}
}