{
  "type": "Feature",
  "properties": {
    "iso:country":"GB",
    "sg:address":"Highsted Rd",
    "sg:city":"Sittingbourne",
    "sg:classifiers":[
        {
            "category":"Education",
            "subcategory":"Music School",
            "type":"Public Place"
        }
    ],
    "sg:phone":"+44 1795 420586",
    "sg:postcode":"ME10 4PT",
    "sg:province":"Kent",
    "wof:name":"Swale Music Centre",
    "wof:placetype":"venue"
},
  "geometry": {"coordinates":[0.7372969985,51.3352737427],"type":"Point"}
}