{
  "type": "Feature",
  "properties": {
    "addr:full":"Almar, Looe Hill, Seaton Torpoint Cornwall PL11 3JQ",
    "addr:postcode":"pl11 3jq",
    "addr:street":"Looe Hill",
    "iso:country":"GB",
    "sg:address":"Almar, Looe Hill, Seaton",
    "sg:city":"Torpoint",
    "sg:classifiers":[
        {
            "category":"Building & Trades",
            "subcategory":"Plumbing",
            "type":"Services"
        },
        {
            "category":"Train Station",
            "subcategory":"Light Rail",
            "type":"Transportation"
        }
    ],
    "sg:phone":"+44 1503 250536",
    "sg:postcode":"PL11 3JQ",
    "sg:province":"Cornwall",
    "sg:tags":[
        "equipment",
        "energy",
        "heating",
        "solar"
    ],
    "wof:name":"Glastonbury Engineering",
    "wof:placetype":"venue"
},
  "geometry": {"coordinates":[-4.3847742081,50.3647613525],"type":"Point"}
}