{
  "type": "Feature",
  "properties": {
    "iso:country":"GB",
    "sg:address":"9b Clerk Street",
    "sg:city":"Loanhead",
    "sg:classifiers":[
        {
            "category":"Banks & Credit Unions",
            "subcategory":"Financial Services",
            "type":"Services"
        }
    ],
    "sg:phone":"+44 131 440 1492",
    "sg:postcode":"EH20 9DP",
    "sg:province":"Midlothian",
    "sg:tags":[
        "adviser"
    ],
    "wof:name":"Alastair Macdonald Ltd.",
    "wof:placetype":"venue"
},
  "geometry": {"coordinates":[-3.15159,55.880028],"type":"Point"}
}