{
  "type": "Feature",
  "properties": {
    "addr:full":"319 Shoreham St Sheffield South Yorkshire S2 4FA",
    "addr:housenumber":"319",
    "addr:postcode":"s2 4fa",
    "addr:street":"Shoreham St",
    "iso:country":"GB",
    "sg:address":"319 Shoreham St",
    "sg:city":"Sheffield",
    "sg:classifiers":[
        {
            "category":"Personal",
            "subcategory":"Beauty Salon",
            "type":"Services"
        }
    ],
    "sg:phone":"+44 114 272 8914",
    "sg:postcode":"S2 4FA",
    "sg:province":"South Yorkshire",
    "sg:tags":[
        "lady",
        "hairdresser"
    ],
    "wof:name":"Carron's Hairdressers",
    "wof:placetype":"venue"
},
  "geometry": {"coordinates":[-1.4684499502,53.3706130981],"type":"Point"}
}