{
  "type": "Feature",
  "properties": {
    "addr:full":"Oaklands Farm Westbury On Severn Gloucestershire GL14 1NA",
    "addr:postcode":"gl14 1na",
    "iso:country":"GB",
    "sg:address":"Oaklands Farm",
    "sg:city":"Westbury On Severn",
    "sg:classifiers":[
        {
            "category":"Sports & Exercise",
            "subcategory":"Stables",
            "type":"Entertainment"
        }
    ],
    "sg:phone":"+44 1452 760963",
    "sg:postcode":"GL14 1NA",
    "sg:province":"Gloucestershire",
    "sg:tags":[
        "education",
        "equestrian"
    ],
    "wof:name":"D Mason",
    "wof:placetype":"venue"
},
  "geometry": {"coordinates":[-2.4129469395,51.8250579834],"type":"Point"}
}