{
  "type": "Feature",
  "properties": {
    "iso:country":"GB",
    "sg:address":"14 Queens Down, Creech St. Michael",
    "sg:city":"Taunton",
    "sg:classifiers":[
        {
            "category":"Home & Garden",
            "subcategory":"Home Furnishings",
            "type":"Retail Goods"
        }
    ],
    "sg:phone":"+44 1823 442503",
    "sg:postcode":"TA3 5QY",
    "sg:province":"Devon",
    "sg:tags":[
        "furnishers",
        "planner",
        "bedroom"
    ],
    "wof:name":"Ideal Bedrooms",
    "wof:placetype":"venue"
},
  "geometry": {"coordinates":[-3.04393,51.026043],"type":"Point"}
}