{
  "type": "Feature",
  "properties": {
    "addr:full":"7 Wilson Terr, Stoneyburn Bathgate North Lanarkshire EH47 8DB",
    "addr:housenumber":"7",
    "addr:postcode":"eh47 8db",
    "addr:street":"Wilson Terr Stoneyburn Bathgate",
    "iso:country":"GB",
    "sg:address":"7 Wilson Terr, Stoneyburn",
    "sg:city":"Bathgate",
    "sg:classifiers":[
        {
            "category":"Home & Garden",
            "subcategory":"Household Appliances",
            "type":"Retail Goods"
        }
    ],
    "sg:postcode":"EH47 8DB",
    "sg:province":"North Lanarkshire",
    "sg:tags":[
        "electrical"
    ],
    "wof:name":"Moore,Sean,",
    "wof:placetype":"venue"
},
  "geometry": {"coordinates":[-3.639721,55.844982],"type":"Point"}
}