{
  "type": "Feature",
  "properties": {
    "iso:country":"GB",
    "sg:address":"128 High Street, Dunsville",
    "sg:city":"Doncaster",
    "sg:classifiers":[
        {
            "category":"Health Services",
            "subcategory":"Doctor",
            "type":"Services"
        }
    ],
    "sg:phone":"+44 1302 890108",
    "sg:postcode":"DN7 4BY",
    "sg:province":"South Yorkshire",
    "sg:tags":[
        "practitioners"
    ],
    "wof:name":"Dunsville Medical Centre",
    "wof:placetype":"venue"
},
  "geometry": {"coordinates":[-1.028517,53.562325],"type":"Point"}
}