{
  "type": "Feature",
  "properties": {
    "addr:full":"1 Oldlands Avenue Hassocks East Sussex BN6 8DJ",
    "addr:housenumber":"1",
    "addr:postcode":"bn6 8dj",
    "addr:street":"Oldlands Avenue",
    "iso:country":"GB",
    "sg:address":"1 Oldlands Avenue",
    "sg:city":"Hassocks",
    "sg:classifiers":[
        {
            "category":"Utilities",
            "subcategory":"Natural Gas",
            "type":"Services"
        }
    ],
    "sg:phone":"+44 1273 842917",
    "sg:postcode":"BN6 8DJ",
    "sg:province":"East Sussex",
    "sg:tags":[
        "control",
        "energy",
        "management",
        "system"
    ],
    "wof:name":"Hayberry Heating Co",
    "wof:placetype":"venue"
},
  "geometry": {"coordinates":[-0.133034,50.926563],"type":"Point"}
}