{
  "type": "Feature",
  "properties": {
    "addr:full":"Ninewell Hospital & Medical Scho Dundee Dundee City DD1 9SY",
    "addr:postcode":"dd1 9sy",
    "addr:street":"Dundee",
    "iso:country":"GB",
    "sg:address":"Ninewell Hospital & Medical Scho",
    "sg:city":"Dundee",
    "sg:classifiers":[
        {
            "category":"Health Services",
            "subcategory":"Hospital",
            "type":"Services"
        }
    ],
    "sg:phone":"+44 1382 660111",
    "sg:postcode":"DD1 9SY",
    "sg:province":"Dundee City",
    "wof:name":"Dundee Teaching Hospitals N H S Trust",
    "wof:placetype":"venue"
},
  "geometry": {"coordinates":[-2.95427,56.461689],"type":"Point"}
}