{
  "type": "Feature",
  "properties": {
    "iso:country":"GB",
    "sg:address":"Estover Health Centre, Leypark Walk",
    "sg:city":"Plymouth",
    "sg:classifiers":[
        {
            "category":"Health Services",
            "subcategory":"Doctor",
            "type":"Services"
        },
        {
            "category":"Health Services",
            "subcategory":"Clinic",
            "type":"Services"
        }
    ],
    "sg:phone":"+44 1752 314921",
    "sg:postcode":"PL6 8UE",
    "sg:province":"Devon",
    "sg:tags":[
        "nh",
        "practitioners"
    ],
    "wof:name":"Estover Health Centre",
    "wof:placetype":"venue"
},
  "geometry": {"coordinates":[-4.09573,50.41238],"type":"Point"}
}