{
  "type": "Feature",
  "properties": {
    "iso:country":"GB",
    "sg:address":"106b Victoria Drive",
    "sg:city":"Bognor Regis",
    "sg:classifiers":[
        {
            "category":"Building & Trades",
            "subcategory":"Equipment Rental",
            "type":"Services"
        }
    ],
    "sg:postcode":"PO21 2EJ",
    "sg:province":"West Sussex",
    "sg:tags":[
        "hire",
        "centre"
    ],
    "wof:name":"Nigel Jeremy Cleeves",
    "wof:placetype":"venue"
},
  "geometry": {"coordinates":[-0.6776069999,50.7900352478],"type":"Point"}
}