{
  "type": "Feature",
  "properties": {
    "addr:full":"Rake Lane, Little Stanney Chester Cheshire CH2 4HS",
    "addr:postcode":"ch2 4hs",
    "addr:street":"Rake Lane",
    "iso:country":"GB",
    "sg:address":"Rake Lane, Little Stanney",
    "sg:city":"Chester",
    "sg:classifiers":[
        {
            "category":"Bars & Pubs",
            "type":"Food & Drink"
        },
        {
            "category":"Community Center",
            "subcategory":"Social",
            "type":"Public Place"
        }
    ],
    "sg:phone":"+44 151 355 9433",
    "sg:postcode":"CH2 4HS",
    "sg:province":"Cheshire",
    "sg:tags":[
        "pubs",
        "house",
        "inn",
        "activity"
    ],
    "wof:name":"The Rake",
    "wof:placetype":"venue"
},
  "geometry": {"coordinates":[-2.8872,53.256653],"type":"Point"}
}