{
  "type": "Feature",
  "properties": {
    "addr:full":"81-89 Cassington Road, Yarnton Oxford Buckinghamshire OX5 1QB",
    "addr:housenumber":"81-89",
    "addr:postcode":"ox5 1qb",
    "addr:street":"Cassington Road",
    "iso:country":"GB",
    "sg:address":"81-89 Cassington Road, Yarnton",
    "sg:city":"Oxford",
    "sg:classifiers":[
        {
            "category":"Autos & Motor Vehicles",
            "subcategory":"Auto Supplies",
            "type":"Retail Goods"
        }
    ],
    "sg:phone":"+44 1865 842727",
    "sg:postcode":"OX5 1QB",
    "sg:province":"Buckinghamshire",
    "sg:tags":[
        "tyre"
    ],
    "wof:name":"Douglas L Charlett (Tyres) Ltd.",
    "wof:placetype":"venue"
},
  "geometry": {"coordinates":[-1.308679,51.80463],"type":"Point"}
}