{
  "type": "Feature",
  "properties": {
    "iso:country":"GB",
    "sg:address":"4a The Strand",
    "sg:city":"Barnstaple",
    "sg:classifiers":[
        {
            "category":"Shopping",
            "subcategory":"Clothing, Apparel, & Fashions",
            "type":"Retail Goods"
        }
    ],
    "sg:postcode":"EX31 1EU",
    "sg:province":"Devon",
    "sg:tags":[
        "shop",
        "dress",
        "fancy"
    ],
    "wof:name":"Exult",
    "wof:placetype":"venue"
},
  "geometry": {"coordinates":[-4.059143,51.078217],"type":"Point"}
}