{
  "type": "Feature",
  "properties": {
    "iso:country":"GB",
    "sg:address":"25 Southview Rise",
    "sg:city":"Alton",
    "sg:classifiers":[
        {
            "category":"Home & Garden",
            "subcategory":"Household Appliances",
            "type":"Retail Goods"
        }
    ],
    "sg:phone":"+44 1420 86194",
    "sg:postcode":"GU34 2AB",
    "sg:province":"Hampshire",
    "sg:tags":[
        "domestic",
        "oven",
        "microwave"
    ],
    "wof:name":"Alton Electrical Services",
    "wof:placetype":"venue"
},
  "geometry": {"coordinates":[-0.979709,51.15522],"type":"Point"}
}