{
  "type": "Feature",
  "properties": {
    "iso:country":"GB",
    "sg:address":"Brickhouse Farm, Hartpury",
    "sg:city":"Gloucester",
    "sg:classifiers":[
        {
            "category":"Farming",
            "subcategory":"Farm",
            "type":"Manufacturing & Wholesale Goods"
        }
    ],
    "sg:postcode":"GL19 3DD",
    "sg:province":"Gloucestershire",
    "sg:tags":[
        "mixed",
        "crop"
    ],
    "wof:name":"T Pugh & Son",
    "wof:placetype":"venue"
},
  "geometry": {"coordinates":[-2.293399,51.924793],"type":"Point"}
}