{
  "type": "Feature",
  "properties": {
    "addr:full":"Jeflyn, Balcarres Road, Rossington Doncaster South Yorkshire DN11 0NF",
    "addr:postcode":"dn11 0nf",
    "addr:street":"Balcarres Road",
    "iso:country":"GB",
    "sg:address":"Jeflyn, Balcarres Road, Rossington",
    "sg:city":"Doncaster",
    "sg:classifiers":[
        {
            "category":"Home & Garden",
            "subcategory":"Carpets & Floor Coverings",
            "type":"Retail Goods"
        }
    ],
    "sg:phone":"+44 1302 865377",
    "sg:postcode":"DN11 0NF",
    "sg:province":"South Yorkshire",
    "sg:tags":[
        "cleaner",
        "upholstery"
    ],
    "wof:name":"Alpha Cleaners",
    "wof:placetype":"venue"
},
  "geometry": {"coordinates":[-1.130565,53.524391],"type":"Point"}
}