{
  "type": "Feature",
  "properties": {
    "iso:country":"GB",
    "sg:address":"54 Manorville Road",
    "sg:city":"Hemel Hempstead",
    "sg:classifiers":[
        {
            "category":"Organizations",
            "subcategory":"Non-profit Organization",
            "type":"Services"
        }
    ],
    "sg:phone":"+44 1442 230333",
    "sg:postcode":"HP3 0AP",
    "sg:province":"Hertfordshire",
    "sg:tags":[
        "charitable",
        "organisation",
        "voluntary",
        "charity"
    ],
    "wof:name":"Dacorum Narrow Boat Project",
    "wof:placetype":"venue"
},
  "geometry": {"coordinates":[-0.4765059948,51.7352867126],"type":"Point"}
}