{
  "type": "Feature",
  "properties": {
    "addr:full":"62 Staplehurst Bracknell Berkshire RG12 8DD",
    "addr:housenumber":"62",
    "addr:postcode":"rg12 8dd",
    "addr:street":"Staplehurst",
    "iso:country":"GB",
    "sg:address":"62 Staplehurst",
    "sg:city":"Bracknell",
    "sg:classifiers":[
        {
            "category":"Building & Trades",
            "subcategory":"Construction",
            "type":"Services"
        }
    ],
    "sg:phone":"+44 1344 423111",
    "sg:postcode":"RG12 8DD",
    "sg:province":"Berkshire",
    "sg:tags":[
        "builder",
        "welder",
        "welding"
    ],
    "wof:name":"Alan J Cleverly",
    "wof:placetype":"venue"
},
  "geometry": {"coordinates":[-0.777117,51.3941],"type":"Point"}
}