{
  "type": "Feature",
  "properties": {
    "iso:country":"GB",
    "sg:address":"68 Craigcrook Avenue",
    "sg:city":"Edinburgh",
    "sg:classifiers":[
        {
            "category":"Real Estate",
            "subcategory":"Architect",
            "type":"Services"
        }
    ],
    "sg:phone":"+44 131 336 3230",
    "sg:postcode":"EH4 3PT",
    "sg:province":"City of Edinburgh",
    "wof:name":"Kerr Duncan McAllister",
    "wof:placetype":"venue"
},
  "geometry": {"coordinates":[-3.267306,55.959312],"type":"Point"}
}