{
  "type": "Feature",
  "properties": {
    "addr:full":"Toms Hill Estate, Aldbury Tring Buckinghamshire HP23 5SD",
    "addr:postcode":"hp23 5sd",
    "addr:street":"Toms Hill Estate",
    "iso:country":"GB",
    "sg:address":"Toms Hill Estate, Aldbury",
    "sg:city":"Tring",
    "sg:classifiers":[
        {
            "category":"Recreation",
            "subcategory":"Water Park",
            "type":"Entertainment"
        }
    ],
    "sg:phone":"+44 1442 851411",
    "sg:postcode":"HP23 5SD",
    "sg:province":"Buckinghamshire",
    "sg:tags":[
        "supplier",
        "bottled"
    ],
    "wof:name":"Danone Waters",
    "wof:placetype":"venue"
},
  "geometry": {"coordinates":[-0.598477006,51.800743103],"type":"Point"}
}