{
  "type": "Feature",
  "properties": {
    "iso:country":"GB",
    "sg:address":"12 High Street",
    "sg:city":"Chard",
    "sg:classifiers":[
        {
            "category":"Professional",
            "subcategory":"Engineering",
            "type":"Services"
        }
    ],
    "sg:postcode":"TA20 1QB",
    "sg:province":"Devon",
    "sg:tags":[
        "contractor",
        "electrical",
        "engineer"
    ],
    "wof:name":"D T Electrics",
    "wof:placetype":"venue"
},
  "geometry": {"coordinates":[-2.966991,50.872467],"type":"Point"}
}