{
  "type": "Feature",
  "properties": {
    "addr:full":"36 North Station Road Colchester Essex CO1 1RB",
    "addr:housenumber":"36",
    "addr:postcode":"co1 1rb",
    "addr:street":"North Station Road Colchester",
    "iso:country":"GB",
    "sg:address":"36 North Station Road",
    "sg:city":"Colchester",
    "sg:classifiers":[
        {
            "category":"Food & Beverages",
            "subcategory":"Meat & Fish",
            "type":"Retail Goods"
        },
        {
            "category":"Food & Beverages",
            "subcategory":"Groceries & Convenience Stores",
            "type":"Retail Goods"
        }
    ],
    "sg:phone":"+44 1206 542190",
    "sg:postcode":"CO1 1RB",
    "sg:province":"Essex",
    "sg:tags":[
        "shop",
        "chip"
    ],
    "wof:name":"The Golden Plaice",
    "wof:placetype":"venue"
},
  "geometry": {"coordinates":[0.8955770135,51.895275116],"type":"Point"}
}