{
  "type": "Feature",
  "properties": {
    "addr:full":"Wishworthy, Lawhitton Launceston Cornwall PL15 9LJ",
    "addr:postcode":"pl15 9lj",
    "iso:country":"GB",
    "sg:address":"Wishworthy, Lawhitton",
    "sg:city":"Launceston",
    "sg:classifiers":[
        {
            "category":"Home & Garden",
            "subcategory":"Garden Supply",
            "type":"Retail Goods"
        },
        {
            "category":"Farming",
            "subcategory":"Farm",
            "type":"Manufacturing & Wholesale Goods"
        }
    ],
    "sg:phone":"+44 1566 773130",
    "sg:postcode":"PL15 9LJ",
    "sg:province":"Cornwall",
    "sg:tags":[
        "mixed",
        "bulb",
        "crop",
        "grower"
    ],
    "wof:name":"Norman Thomas Charles Lancaster",
    "wof:placetype":"venue"
},
  "geometry": {"coordinates":[-4.3269639015,50.6166267395],"type":"Point"}
}