{
  "type": "Feature",
  "properties": {
    "addr:full":"144 High Street, Tibshelf Alfreton Derbyshire DE55 5PP",
    "addr:housenumber":"144",
    "addr:postcode":"de55 5pp",
    "addr:street":"High Street",
    "iso:country":"GB",
    "sg:address":"144 High Street, Tibshelf",
    "sg:city":"Alfreton",
    "sg:classifiers":[
        {
            "category":"Education",
            "subcategory":"School",
            "type":"Public Place"
        }
    ],
    "sg:phone":"+44 1773 872571",
    "sg:postcode":"DE55 5PP",
    "sg:province":"Derbyshire",
    "sg:tags":[
        "local",
        "authority"
    ],
    "wof:name":"Tibshelf Infant School",
    "wof:placetype":"venue"
},
  "geometry": {"coordinates":[-1.343494,53.142948],"type":"Point"}
}