{
  "type": "Feature",
  "properties": {
    "addr:full":"Westend Works, Main Street, Garton-on-the-wolds Driffield East Riding of Yorkshire YO25 3ET",
    "addr:postcode":"yo25 3et",
    "addr:street":"Main Street Garton-On-The-Wolds",
    "iso:country":"GB",
    "sg:address":"Westend Works, Main Street, Garton-on-the-wolds",
    "sg:city":"Driffield",
    "sg:classifiers":[
        {
            "category":"Manufacturing",
            "subcategory":"Watercraft",
            "type":"Manufacturing & Wholesale Goods"
        }
    ],
    "sg:phone":"+44 1377 254090",
    "sg:postcode":"YO25 3ET",
    "sg:province":"East Riding of Yorkshire",
    "sg:tags":[
        "repair",
        "ship",
        "builder"
    ],
    "wof:name":"R K Atkinson",
    "wof:placetype":"venue"
},
  "geometry": {"coordinates":[-0.503664,54.022511],"type":"Point"}
}