{
  "type": "Feature",
  "properties": {
    "iso:country":"GB",
    "sg:address":"6 Bury Road, Rawtenstall",
    "sg:city":"Rossendale",
    "sg:classifiers":[
        {
            "category":"Shopping",
            "subcategory":"Jewelry",
            "type":"Retail Goods"
        },
        {
            "category":"Shopping",
            "subcategory":"Comic Books",
            "type":"Retail Goods"
        }
    ],
    "sg:phone":"+44 1706 214453",
    "sg:postcode":"BB4 6AA",
    "sg:province":"Lancashire",
    "sg:tags":[
        "jeweller",
        "sale",
        "jewellery"
    ],
    "wof:name":"Arthur H Barrie",
    "wof:placetype":"venue"
},
  "geometry": {"coordinates":[-2.288065,53.700245],"type":"Point"}
}