{
  "type": "Feature",
  "properties": {
    "addr:full":"Unit 5 Giffnock Park Indust Est, Burnfield Rd Glasgow East Renfrewshire G46 7QA",
    "addr:housenumber":"unit 5",
    "addr:postcode":"g46 7qa",
    "addr:street":"Park Indust Est Burnfield Rd",
    "iso:country":"GB",
    "sg:address":"Unit 5 Giffnock Park Indust Est, Burnfield Rd",
    "sg:city":"Glasgow",
    "sg:classifiers":[
        {
            "category":"Communications",
            "type":"Services"
        }
    ],
    "sg:phone":"+44 141 633 5138",
    "sg:postcode":"G46 7QA",
    "sg:province":"East Renfrewshire",
    "sg:tags":[
        "tv",
        "video",
        "radio"
    ],
    "wof:name":"Skyward Aerials",
    "wof:placetype":"venue"
},
  "geometry": {"coordinates":[-4.2967100143,55.8067512512],"type":"Point"}
}