{
  "type": "Feature",
  "properties": {
    "addr:full":"C/o Dains, St Johns Court Lichfield Staffordshire WS14 9DS",
    "addr:postcode":"ws14 9ds",
    "addr:street":"C / O Dains St Johns Court",
    "iso:country":"GB",
    "sg:address":"C/o Dains, St Johns Court",
    "sg:city":"Lichfield",
    "sg:classifiers":[
        {
            "category":"Shopping",
            "type":"Retail Goods"
        }
    ],
    "sg:phone":"+44 1543 480744",
    "sg:postcode":"WS14 9DS",
    "sg:province":"Staffordshire",
    "sg:tags":[
        "bag"
    ],
    "wof:name":"Castleoak Properties Ltd.",
    "wof:placetype":"venue"
},
  "geometry": {"coordinates":[-1.798612,52.673229],"type":"Point"}
}