{
  "type": "Feature",
  "properties": {
    "iso:country":"GB",
    "sg:address":"Unit 6/7, Norwich Livestock Market",
    "sg:city":"Norwich",
    "sg:classifiers":[
        {
            "category":"Shopping",
            "subcategory":"Bicycles & Sporting Goods",
            "type":"Retail Goods"
        }
    ],
    "sg:phone":"+44 1603 505073",
    "sg:postcode":"NR4 6DW",
    "sg:province":"Norfolk",
    "sg:tags":[
        "dance",
        "balletwear"
    ],
    "wof:name":"D & M Shoes",
    "wof:placetype":"venue"
},
  "geometry": {"coordinates":[1.28397,52.600731],"type":"Point"}
}