{
  "type": "Feature",
  "properties": {
    "addr:full":"10 St Matthews Terrace Leyburn North Yorkshire DL8 5EL",
    "addr:housenumber":"10",
    "addr:postcode":"dl8 5el",
    "addr:street":"St Matthews Terrace",
    "iso:country":"GB",
    "sg:address":"10 St Matthews Terrace",
    "sg:city":"Leyburn",
    "sg:classifiers":[
        {
            "category":"Professional",
            "subcategory":"Business Services",
            "type":"Services"
        }
    ],
    "sg:postcode":"DL8 5EL",
    "sg:province":"North Yorkshire",
    "sg:tags":[
        "information"
    ],
    "wof:name":"Nigel Watson Corporate Histories",
    "wof:placetype":"venue"
},
  "geometry": {"coordinates":[-1.8257859945,54.3077507019],"type":"Point"}
}