{
  "type": "Feature",
  "properties": {
    "addr:full":"Unit S8, Second Floor, Waterloo Rd Widnes Cheshire WA8 0PR",
    "addr:housenumber":"second floor",
    "addr:postcode":"wa8 0pr",
    "addr:street":"Waterloo Rd",
    "iso:country":"GB",
    "sg:address":"Unit S8, Second Floor, Waterloo Rd",
    "sg:city":"Widnes",
    "sg:classifiers":[
        {
            "category":"Real Estate",
            "subcategory":"Surveying",
            "type":"Services"
        }
    ],
    "sg:phone":"+44 151 423 6914",
    "sg:postcode":"WA8 0PR",
    "sg:province":"Cheshire",
    "sg:tags":[
        "building",
        "surveyor"
    ],
    "wof:name":"Cassidy & Ashton",
    "wof:placetype":"venue"
},
  "geometry": {"coordinates":[-2.734567,53.357285],"type":"Point"}
}