{
  "type": "Feature",
  "properties": {
    "addr:full":"39 Old Church Road Weston-super-mare Somerset BS23 4UR",
    "addr:housenumber":"39",
    "addr:postcode":"bs23 4ur",
    "addr:street":"Old Church Road",
    "iso:country":"GB",
    "sg:address":"39 Old Church Road",
    "sg:city":"Weston-super-mare",
    "sg:classifiers":[
        {
            "category":"Shopping",
            "subcategory":"Department Store",
            "type":"Retail Goods"
        },
        {
            "category":"Government",
            "subcategory":"Post Office",
            "type":"Public Place"
        }
    ],
    "sg:phone":"+44 1934 620104",
    "sg:postcode":"BS23 4UR",
    "sg:province":"Somerset",
    "wof:name":"Uphill Post Office Stores",
    "wof:placetype":"venue"
},
  "geometry": {"coordinates":[-2.981254,51.324333],"type":"Point"}
}