{
  "type": "Feature",
  "properties": {
    "addr:full":"37 East Street Stanley Durham DH9 0UF",
    "addr:housenumber":"37",
    "addr:postcode":"dh9 0uf",
    "addr:street":"East Street",
    "iso:country":"GB",
    "sg:address":"37 East Street",
    "sg:city":"Stanley",
    "sg:classifiers":[
        {
            "category":"Personal",
            "subcategory":"Beauty Salon",
            "type":"Services"
        }
    ],
    "sg:phone":"+44 1207 235271",
    "sg:postcode":"DH9 0UF",
    "sg:province":"Durham",
    "sg:tags":[
        "unisex",
        "hairdresser"
    ],
    "wof:name":"McPhail Hairdressing",
    "wof:placetype":"venue"
},
  "geometry": {"coordinates":[-1.679284,54.873074],"type":"Point"}
}