{
  "type": "Feature",
  "properties": {
    "addr:full":"95 King Street Lancaster Lancashire LA1 1RH",
    "addr:housenumber":"95",
    "addr:postcode":"la1 1rh",
    "addr:street":"King Street",
    "iso:country":"GB",
    "sg:address":"95 King Street",
    "sg:city":"Lancaster",
    "sg:classifiers":[
        {
            "category":"Social Services",
            "subcategory":"Job Training",
            "type":"Services"
        },
        {
            "category":"Real Estate",
            "subcategory":"Architect",
            "type":"Services"
        }
    ],
    "sg:phone":"+44 1524 751750",
    "sg:postcode":"LA1 1RH",
    "sg:province":"Lancashire",
    "sg:tags":[
        "engineering",
        "marine"
    ],
    "wof:name":"MARTIN YATES MARINE LTD",
    "wof:placetype":"venue"
},
  "geometry": {"coordinates":[-2.8015310764,54.0469398499],"type":"Point"}
}