{
  "type": "Feature",
  "properties": {
    "iso:country":"GB",
    "sg:address":"Bedfont Road",
    "sg:city":"Feltham",
    "sg:classifiers":[
        {
            "category":"Bus Charters",
            "type":"Transportation"
        }
    ],
    "sg:phone":"+44 20 8893 1942",
    "sg:postcode":"TW14 8EB",
    "sg:province":"Greater London",
    "sg:tags":[
        "hire",
        "coach"
    ],
    "wof:name":"Ferlin Coachlines",
    "wof:placetype":"venue"
},
  "geometry": {"coordinates":[-0.444751,51.448307],"type":"Point"}
}