{
  "type": "Feature",
  "properties": {
    "addr:full":"1 Marble Terr Llandysul Carmarthenshire SA44 4DB",
    "addr:housenumber":"1",
    "addr:postcode":"sa44 4db",
    "addr:street":"Marble Terr",
    "iso:country":"GB",
    "sg:address":"1 Marble Terr",
    "sg:city":"Llandysul",
    "sg:classifiers":[
        {
            "category":"Building & Trades",
            "subcategory":"Equipment Rental",
            "type":"Services"
        }
    ],
    "sg:phone":"+44 1559 363636",
    "sg:postcode":"SA44 4DB",
    "sg:province":"Carmarthenshire",
    "sg:tags":[
        "plant",
        "machinery"
    ],
    "wof:name":"Teifi Crane Hire",
    "wof:placetype":"venue"
},
  "geometry": {"coordinates":[-4.3078169823,52.0444793701],"type":"Point"}
}