{
  "type": "Feature",
  "properties": {
    "addr:full":"10 Borough Arcade, High Street Yeovil Somerset BA20 1RG",
    "addr:housenumber":"10;arcade",
    "addr:postcode":"ba20 1rg",
    "addr:street":"Borough;High Street",
    "iso:country":"GB",
    "sg:address":"10 Borough Arcade, High Street",
    "sg:city":"Yeovil",
    "sg:classifiers":[
        {
            "category":"Professional",
            "subcategory":"Management & Consulting",
            "type":"Services"
        }
    ],
    "sg:phone":"+44 1935 413270",
    "sg:postcode":"BA20 1RG",
    "sg:province":"Somerset",
    "sg:tags":[
        "consultant",
        "business"
    ],
    "wof:name":"Policy Mediation",
    "wof:placetype":"venue"
},
  "geometry": {"coordinates":[-2.63226,50.941582],"type":"Point"}
}