{
  "type": "Feature",
  "properties": {
    "addr:full":"Unit C King's Lynn Norfolk PE32 2LP",
    "addr:housenumber":"unit c",
    "addr:postcode":"pe32 2lp",
    "addr:street":"Lynn",
    "iso:country":"GB",
    "sg:address":"Unit C",
    "sg:city":"King's Lynn",
    "sg:classifiers":[
        {
            "category":"Manufacturing",
            "subcategory":"Rubber & Plastics",
            "type":"Manufacturing & Wholesale Goods"
        }
    ],
    "sg:postcode":"PE32 2LP",
    "sg:province":"Norfolk",
    "sg:tags":[
        "injection",
        "moulding"
    ],
    "wof:name":"Protomould",
    "wof:placetype":"venue"
},
  "geometry": {"coordinates":[0.7300699949,52.7033309937],"type":"Point"}
}