{
  "type": "Feature",
  "properties": {
    "addr:full":"Chestnuts Farm, Langton Grn Eye Suffolk IP23 7HL",
    "addr:postcode":"ip23 7hl",
    "addr:street":"Langton",
    "iso:country":"GB",
    "sg:address":"Chestnuts Farm, Langton Grn",
    "sg:city":"Eye",
    "sg:classifiers":[
        {
            "category":"Wholesale",
            "subcategory":"Chemicals & Plastics",
            "type":"Manufacturing & Wholesale Goods"
        }
    ],
    "sg:phone":"+44 1379 870669",
    "sg:postcode":"IP23 7HL",
    "sg:province":"Suffolk",
    "sg:tags":[
        "supplier",
        "w'sale",
        "perfume"
    ],
    "wof:name":"R W Starke & Sons",
    "wof:placetype":"venue"
},
  "geometry": {"coordinates":[1.145876,52.322071],"type":"Point"}
}