{
  "type": "Feature",
  "properties": {
    "iso:country":"GB",
    "sg:address":"2 Exchange Way",
    "sg:city":"Chelmsford",
    "sg:classifiers":[
        {
            "category":"Shopping",
            "subcategory":"Stationery & Office Supplies",
            "type":"Retail Goods"
        }
    ],
    "sg:phone":"+44 1245 355321",
    "sg:postcode":"CM1 1XQ",
    "sg:province":"Essex",
    "sg:tags":[
        "equipment"
    ],
    "wof:name":"J H Clarke & Co. (Chelmsford) Ltd.",
    "wof:placetype":"venue"
},
  "geometry": {"coordinates":[0.471995,51.734371],"type":"Point"}
}