{
  "type": "Feature",
  "properties": {
    "addr:full":"47 Woodside Grn London Greater London SE25 5HQ",
    "addr:housenumber":"47",
    "addr:postcode":"se25 5hq",
    "addr:street":"Woodside Grn",
    "iso:country":"GB",
    "sg:address":"47 Woodside Grn",
    "sg:city":"London",
    "sg:classifiers":[
        {
            "category":"Bars & Pubs",
            "type":"Food & Drink"
        }
    ],
    "sg:phone":"+44 20 8662 1941",
    "sg:postcode":"SE25 5HQ",
    "sg:province":"Greater London",
    "sg:tags":[
        "pubs",
        "inn"
    ],
    "wof:name":"West Midlands Taverns Ltd.",
    "wof:placetype":"venue"
},
  "geometry": {"coordinates":[-0.070672,51.386978],"type":"Point"}
}