{
  "type": "Feature",
  "properties": {
    "iso:country":"GB",
    "sg:address":"76 Mansel Street",
    "sg:city":"Swansea",
    "sg:classifiers":[
        {
            "category":"Shopping",
            "subcategory":"Musical Instruments",
            "type":"Retail Goods"
        }
    ],
    "sg:phone":"+44 1792 649039",
    "sg:postcode":"SA1 5TW",
    "sg:province":"Neath Port Talbot",
    "sg:tags":[
        "music",
        "sheet"
    ],
    "wof:name":"Picton Music Ltd.",
    "wof:placetype":"venue"
},
  "geometry": {"coordinates":[-3.9497179985,51.6208381653],"type":"Point"}
}