{
  "type": "Feature",
  "properties": {
    "addr:full":"397 London Road Westcliff On Sea Essex SS0 7HU",
    "addr:housenumber":"397",
    "addr:postcode":"ss0 7hu",
    "addr:street":"London Road",
    "iso:country":"GB",
    "sg:address":"397 London Road",
    "sg:city":"Westcliff On Sea",
    "sg:classifiers":[
        {
            "category":"Shopping",
            "subcategory":"Department Store",
            "type":"Retail Goods"
        }
    ],
    "sg:phone":"+44 1702 432470",
    "sg:postcode":"SS0 7HU",
    "sg:province":"Essex",
    "wof:name":"Sportshouse",
    "wof:placetype":"venue"
},
  "geometry": {"coordinates":[0.692948,51.543736],"type":"Point"}
}