{
  "type": "Feature",
  "properties": {
    "addr:full":"Milstar, Hambledon Road Portsmouth Hampshire PO7 6PS",
    "addr:postcode":"hampshire po7 6ps",
    "addr:street":"Hambledon Road",
    "iso:country":"GB",
    "sg:address":"Milstar, Hambledon Road",
    "sg:city":"Portsmouth",
    "sg:classifiers":[
        {
            "category":"Building & Trades",
            "subcategory":"Construction",
            "type":"Services"
        }
    ],
    "sg:phone":"+44 23 9223 3033",
    "sg:postcode":"PO7 6PS",
    "sg:province":"Hampshire",
    "sg:tags":[
        "builder"
    ],
    "wof:name":"Springfield Builders (Portsmouth) Ltd.",
    "wof:placetype":"venue"
},
  "geometry": {"coordinates":[-1.0590100288,50.900478363],"type":"Point"}
}