{
  "type": "Feature",
  "properties": {
    "addr:full":"Chantry Way Andover Hampshire SP10 1LT",
    "addr:postcode":"sp10 1lt",
    "addr:street":"Chantry Way",
    "iso:country":"GB",
    "sg:address":"Chantry Way",
    "sg:city":"Andover",
    "sg:classifiers":[
        {
            "category":"Education",
            "subcategory":"Library",
            "type":"Public Place"
        }
    ],
    "sg:phone":"+44 1264 352807",
    "sg:postcode":"SP10 1LT",
    "sg:province":"Hampshire",
    "sg:tags":[
        "book"
    ],
    "wof:name":"Andover Library",
    "wof:placetype":"venue"
},
  "geometry": {"coordinates":[-1.480664,51.209702],"type":"Point"}
}