{
  "type": "Feature",
  "properties": {
    "addr:full":"Richard St Burnley Lancashire BB11 3AJ",
    "addr:postcode":"bb11 3aj",
    "addr:street":"Richard St",
    "iso:country":"GB",
    "sg:address":"Richard St",
    "sg:city":"Burnley",
    "sg:classifiers":[
        {
            "category":"Organizations",
            "subcategory":"Membership Organization",
            "type":"Services"
        }
    ],
    "sg:phone":"+44 1282 424020",
    "sg:postcode":"BB11 3AJ",
    "sg:province":"Lancashire",
    "sg:tags":[
        "club"
    ],
    "wof:name":"Irish Democratic League",
    "wof:placetype":"venue"
},
  "geometry": {"coordinates":[-2.2358970642,53.7861976624],"type":"Point"}
}