{
  "type": "Feature",
  "properties": {
    "addr:full":"1 York Buildings, Edlington Lane, Edlington Doncaster South Yorkshire DN12 1BU",
    "addr:housenumber":"1",
    "addr:postcode":"dn12 1bu",
    "addr:street":"York Buildings Edlington Lane",
    "iso:country":"GB",
    "sg:address":"1 York Buildings, Edlington Lane, Edlington",
    "sg:city":"Doncaster",
    "sg:classifiers":[
        {
            "category":"Shopping",
            "type":"Retail Goods"
        }
    ],
    "sg:phone":"+44 1709 862256",
    "sg:postcode":"DN12 1BU",
    "sg:province":"South Yorkshire",
    "sg:tags":[
        "part",
        "accessory"
    ],
    "wof:name":"Bullseye Motorist Centre",
    "wof:placetype":"venue"
},
  "geometry": {"coordinates":[-1.1900689602,53.4820899963],"type":"Point"}
}