{
  "type": "Feature",
  "properties": {
    "addr:full":"16 Gresham Drive Oldham Lancashire OL9 6LE",
    "addr:housenumber":"16",
    "addr:postcode":"ol9 6le",
    "addr:street":"Gresham Drive",
    "iso:country":"GB",
    "sg:address":"16 Gresham Drive",
    "sg:city":"Oldham",
    "sg:classifiers":[
        {
            "category":"Building & Trades",
            "subcategory":"Construction",
            "type":"Services"
        }
    ],
    "sg:phone":"+44 161 652 9766",
    "sg:postcode":"OL9 6LE",
    "sg:province":"Lancashire",
    "sg:tags":[
        "builder"
    ],
    "wof:name":"J McHale",
    "wof:placetype":"venue"
},
  "geometry": {"coordinates":[-2.1302518845,53.5439453125],"type":"Point"}
}