{
  "type": "Feature",
  "properties": {
    "addr:full":"Unit 13, 137a Warren Avenue Southampton Hampshire SO16 6AF",
    "addr:housenumber":"unit 13 137a",
    "addr:postcode":"so16 6af",
    "addr:street":"Warren Avenue",
    "iso:country":"GB",
    "sg:address":"Unit 13, 137a Warren Avenue",
    "sg:city":"Southampton",
    "sg:classifiers":[
        {
            "category":"Professional",
            "subcategory":"Engineering",
            "type":"Services"
        }
    ],
    "sg:phone":"+44 23 8070 1843",
    "sg:postcode":"SO16 6AF",
    "sg:province":"Hampshire",
    "sg:tags":[
        "precision",
        "engineer"
    ],
    "wof:name":"A G Systems Precision Engineers",
    "wof:placetype":"venue"
},
  "geometry": {"coordinates":[-1.437728,50.929066],"type":"Point"}
}