{
  "type": "Feature",
  "properties": {
    "addr:full":"58 Northbrook Street Newbury Berkshire RG14 1AN",
    "addr:housenumber":"58",
    "addr:postcode":"rg14 1an",
    "addr:street":"Northbrook Street",
    "iso:country":"GB",
    "sg:address":"58 Northbrook Street",
    "sg:city":"Newbury",
    "sg:classifiers":[
        {
            "category":"Fast Food",
            "type":"Food & Drink"
        }
    ],
    "sg:phone":"+44 1635 38385",
    "sg:postcode":"RG14 1AN",
    "sg:province":"Berkshire",
    "sg:tags":[
        "away",
        "take"
    ],
    "wof:name":"Cornish Range",
    "wof:placetype":"venue"
},
  "geometry": {"coordinates":[-1.3248310089,51.4048042297],"type":"Point"}
}