{
  "type": "Feature",
  "properties": {
    "addr:full":"75 Yorkshire Street Rochdale Lancashire OL16 1DB",
    "addr:housenumber":"75",
    "addr:postcode":"ol16 1db",
    "addr:street":"Yorkshire Street",
    "iso:country":"GB",
    "sg:address":"75 Yorkshire Street",
    "sg:city":"Rochdale",
    "sg:classifiers":[
        {
            "category":"Shopping",
            "subcategory":"Shoes",
            "type":"Retail Goods"
        }
    ],
    "sg:phone":"+44 1706 641326",
    "sg:postcode":"OL16 1DB",
    "sg:province":"Lancashire",
    "sg:tags":[
        "shop",
        "retailer",
        "footwear"
    ],
    "wof:name":"Shoe Express",
    "wof:placetype":"venue"
},
  "geometry": {"coordinates":[-2.1566450596,53.6189842224],"type":"Point"}
}