{
  "type": "Feature",
  "properties": {
    "iso:country":"GB",
    "sg:address":"7 Royal Star Arcade, High Street",
    "sg:city":"Maidstone",
    "sg:classifiers":[
        {
            "category":"Shopping",
            "subcategory":"Gifts & Souvenirs",
            "type":"Retail Goods"
        },
        {
            "category":"Shopping",
            "type":"Retail Goods"
        }
    ],
    "sg:phone":"+44 1622 662556",
    "sg:postcode":"ME14 1JL",
    "sg:province":"Kent",
    "sg:tags":[
        "shop",
        "new age"
    ],
    "wof:name":"DESTINY",
    "wof:placetype":"venue"
},
  "geometry": {"coordinates":[0.5250849724,51.2737998962],"type":"Point"}
}