{
  "type": "Feature",
  "properties": {
    "addr:full":"40 Carterweys Dunstable Bedfordshire LU5 4RB",
    "addr:housenumber":"40",
    "addr:postcode":"lu5 4rb",
    "addr:street":"Carterweys",
    "iso:country":"GB",
    "sg:address":"40 Carterweys",
    "sg:city":"Dunstable",
    "sg:classifiers":[
        {
            "category":"Building & Trades",
            "subcategory":"Construction",
            "type":"Services"
        }
    ],
    "sg:phone":"+44 1582 605374",
    "sg:postcode":"LU5 4RB",
    "sg:province":"Bedfordshire",
    "sg:tags":[
        "roofing"
    ],
    "wof:name":"Felt Roofing C & C",
    "wof:placetype":"venue"
},
  "geometry": {"coordinates":[-0.5001149774,51.8931808472],"type":"Point"}
}