{
  "type": "Feature",
  "properties": {
    "addr:full":"36 Kings Road Beith North Ayrshire KA15 2BJ",
    "addr:housenumber":"36",
    "addr:postcode":"ka15 2bj",
    "addr:street":"Kings Road",
    "iso:country":"GB",
    "sg:address":"36 Kings Road",
    "sg:city":"Beith",
    "sg:classifiers":[
        {
            "category":"Home & Garden",
            "subcategory":"Home Furnishings",
            "type":"Retail Goods"
        }
    ],
    "sg:postcode":"KA15 2BJ",
    "sg:province":"North Ayrshire",
    "sg:tags":[
        "blind",
        "curtain",
        "fitting"
    ],
    "wof:name":"One to One Interiors",
    "wof:placetype":"venue"
},
  "geometry": {"coordinates":[-4.634195,55.75333],"type":"Point"}
}