{
  "type": "Feature",
  "properties": {
    "iso:country":"GB",
    "sg:address":"67-68 Moulsham Street",
    "sg:city":"Chelmsford",
    "sg:classifiers":[
        {
            "category":"Food & Beverages",
            "subcategory":"Groceries & Convenience Stores",
            "type":"Retail Goods"
        }
    ],
    "sg:phone":"+44 1245 256927",
    "sg:postcode":"CM2 0JA",
    "sg:province":"Essex",
    "wof:name":"Moulsham Express",
    "wof:placetype":"venue"
},
  "geometry": {"coordinates":[0.470361,51.728493],"type":"Point"}
}