{
  "type": "Feature",
  "properties": {
    "addr:full":"46-47 Britton Street London Greater London EC1M 5UJ",
    "addr:housenumber":"46-47",
    "addr:postcode":"ec1m 5uj",
    "addr:street":"Britton Street",
    "iso:country":"GB",
    "sg:address":"46-47 Britton Street",
    "sg:city":"London",
    "sg:classifiers":[
        {
            "category":"Organizations",
            "subcategory":"Non-profit Organization",
            "type":"Services"
        }
    ],
    "sg:phone":"+44 20 7490 5671",
    "sg:postcode":"EC1M 5UJ",
    "sg:province":"Greater London",
    "sg:tags":[
        "organisation",
        "voluntary",
        "charity"
    ],
    "wof:name":"The Dystonia Society",
    "wof:placetype":"venue"
},
  "geometry": {"coordinates":[-0.1033950001,51.5212135315],"type":"Point"}
}