{
  "type": "Feature",
  "properties": {
    "iso:country":"GB",
    "sg:address":"94 Queen Street",
    "sg:city":"Maidenhead",
    "sg:classifiers":[
        {
            "category":"Shopping",
            "subcategory":"News",
            "type":"Retail Goods"
        }
    ],
    "sg:phone":"+44 1628 799517",
    "sg:postcode":"SL6 1HT",
    "sg:province":"Berkshire",
    "sg:tags":[
        "newsagent"
    ],
    "wof:name":"Newstyme",
    "wof:placetype":"venue"
},
  "geometry": {"coordinates":[-0.721584022,51.5200691223],"type":"Point"}
}