{
  "type": "Feature",
  "properties": {
    "addr:full":"Unit 7, Ford Lane, Busines Park, Ford Lane, Ford Arundel Arundel West Sussex BN18 0UZ",
    "addr:housenumber":"unit 7",
    "addr:postcode":"bn18 0uz",
    "addr:street":"Ford Lane Busines Park Ford Lane",
    "iso:country":"GB",
    "sg:address":"Unit 7, Ford Lane, Busines Park, Ford Lane, Ford Arundel",
    "sg:city":"Arundel",
    "sg:classifiers":[
        {
            "category":"Wholesale",
            "subcategory":"Machinery & Supplies",
            "type":"Manufacturing & Wholesale Goods"
        }
    ],
    "sg:phone":"+44 1243 555558",
    "sg:postcode":"BN18 0UZ",
    "sg:province":"West Sussex",
    "sg:tags":[
        "pump"
    ],
    "wof:name":"Coastline Pumps",
    "wof:placetype":"venue"
},
  "geometry": {"coordinates":[-0.581014,50.824074],"type":"Point"}
}