{
  "type": "Feature",
  "properties": {
    "addr:full":"79 Fore Street, North Petherton Bridgwater Somerset TA6 6QA",
    "addr:housenumber":"79",
    "addr:postcode":"ta6 6qa",
    "addr:street":"Fore Street",
    "iso:country":"GB",
    "sg:address":"79 Fore Street, North Petherton",
    "sg:city":"Bridgwater",
    "sg:classifiers":[
        {
            "category":"Food & Beverages",
            "subcategory":"Groceries & Convenience Stores",
            "type":"Retail Goods"
        }
    ],
    "sg:phone":"+44 1278 662226",
    "sg:postcode":"TA6 6QA",
    "sg:province":"Somerset",
    "wof:name":"Spar Stores",
    "wof:placetype":"venue"
},
  "geometry": {"coordinates":[-3.0145659447,51.0927772522],"type":"Point"}
}