{
  "type": "Feature",
  "properties": {
    "addr:full":"7 Heatherdene Road, Chandlers Ford, Eastleigh Southampton Hampshire SO53 5BP",
    "addr:housenumber":"7",
    "addr:postcode":"so53 5bp",
    "addr:street":"Heatherdene Road",
    "iso:country":"GB",
    "sg:address":"7 Heatherdene Road, Chandlers Ford, Eastleigh",
    "sg:city":"Southampton",
    "sg:classifiers":[
        {
            "category":"Social Services",
            "subcategory":"Job Training",
            "type":"Services"
        }
    ],
    "sg:phone":"+44 23 8026 3906",
    "sg:postcode":"SO53 5BP",
    "sg:province":"Hampshire",
    "sg:tags":[
        "translator",
        "interpreter"
    ],
    "wof:name":"Margaret Woods",
    "wof:placetype":"venue"
},
  "geometry": {"coordinates":[-1.371457,50.997299],"type":"Point"}
}