{
  "type": "Feature",
  "properties": {
    "addr:full":"Whitefield Works, 28 Field Road, Busby Glasgow East Renfrewshire G76 8SF",
    "addr:housenumber":"28",
    "addr:postcode":"g76 8sf",
    "addr:street":"Field Road",
    "iso:country":"GB",
    "sg:address":"Whitefield Works, 28 Field Road, Busby",
    "sg:city":"Glasgow",
    "sg:classifiers":[
        {
            "category":"Building & Trades",
            "subcategory":"Construction",
            "type":"Services"
        }
    ],
    "sg:phone":"+44 141 644 0500",
    "sg:postcode":"G76 8SF",
    "sg:province":"East Renfrewshire",
    "sg:tags":[
        "demolition",
        "contractor"
    ],
    "wof:name":"Demco (Scotland) Ltd.",
    "wof:placetype":"venue"
},
  "geometry": {"coordinates":[-4.2771100998,55.7802391052],"type":"Point"}
}