{
  "type": "Feature",
  "properties": {
    "addr:full":"1149/1151 Cathcart Road, Mount Florida Glasgow Glasgow City G42 9HD",
    "addr:housenumber":"1149 / 1151",
    "addr:postcode":"g42 9hd",
    "addr:street":"Cathcart Road",
    "iso:country":"GB",
    "sg:address":"1149/1151 Cathcart Road, Mount Florida",
    "sg:city":"Glasgow",
    "sg:classifiers":[
        {
            "category":"Shopping",
            "subcategory":"Stationery & Office Supplies",
            "type":"Retail Goods"
        }
    ],
    "sg:postcode":"G42 9HD",
    "sg:province":"Glasgow City",
    "sg:tags":[
        "equipment"
    ],
    "wof:name":"Alpha Office Furniture",
    "wof:placetype":"venue"
},
  "geometry": {"coordinates":[-4.2586832047,55.8233680725],"type":"Point"}
}