{
  "type": "Feature",
  "properties": {
    "addr:full":"19-29 Park Row Leeds West Yorkshire LS1 5JE",
    "addr:housenumber":"19-29",
    "addr:postcode":"ls1 5je",
    "addr:street":"Park Row",
    "iso:country":"GB",
    "sg:address":"19-29 Park Row",
    "sg:city":"Leeds",
    "sg:classifiers":[
        {
            "category":"Manufacturing",
            "subcategory":"Tools & Machinery",
            "type":"Manufacturing & Wholesale Goods"
        },
        {
            "category":"Insurance",
            "subcategory":"Insurance Agent",
            "type":"Services"
        }
    ],
    "sg:postcode":"LS1 5JE",
    "sg:province":"West Yorkshire",
    "sg:tags":[
        "society",
        "friendly"
    ],
    "wof:name":"General Accident Fire & Life Association",
    "wof:placetype":"venue"
},
  "geometry": {"coordinates":[-1.5468369722,53.798915863],"type":"Point"}
}