{
  "type": "Feature",
  "properties": {
    "iso:country":"GB",
    "sg:address":"Earl Road, Rackheath Industrial Estate",
    "sg:city":"Norwich",
    "sg:classifiers":[
        {
            "category":"Professional",
            "subcategory":"Engineering",
            "type":"Services"
        }
    ],
    "sg:phone":"+44 1603 720999",
    "sg:postcode":"NR13 6NT",
    "sg:province":"Norfolk",
    "sg:tags":[
        "electronic",
        "engineer"
    ],
    "wof:name":"Technova",
    "wof:placetype":"venue"
},
  "geometry": {"coordinates":[1.375955,52.673923],"type":"Point"}
}