{
  "type": "Feature",
  "properties": {
    "iso:country":"GB",
    "sg:address":"Unit B, Southgate Way, Orton Southgate",
    "sg:city":"Peterborough",
    "sg:classifiers":[
        {
            "category":"Wholesale",
            "subcategory":"Machinery & Supplies",
            "type":"Manufacturing & Wholesale Goods"
        }
    ],
    "sg:phone":"+44 1733 233633",
    "sg:postcode":"PE2 6YG",
    "sg:province":"Cambridgeshire",
    "sg:tags":[
        "pump"
    ],
    "wof:name":"Advanced Pumping Systems Ltd.",
    "wof:placetype":"venue"
},
  "geometry": {"coordinates":[-0.319989,52.537899],"type":"Point"}
}