{
  "type": "Feature",
  "properties": {
    "iso:country":"GB",
    "sg:address":"Billingsgate Market, Trafalgar Way",
    "sg:city":"London",
    "sg:classifiers":[
        {
            "category":"Food & Beverages",
            "subcategory":"Meat & Fish",
            "type":"Retail Goods"
        }
    ],
    "sg:phone":"+44 20 7537 2759",
    "sg:postcode":"E14 5TG",
    "sg:province":"Greater London",
    "sg:tags":[
        "merchant"
    ],
    "wof:name":"John Koch Ltd.",
    "wof:placetype":"venue"
},
  "geometry": {"coordinates":[-0.0147700002,51.5062713623],"type":"Point"}
}