{
  "type": "Feature",
  "properties": {
    "addr:full":"Frosty House, Burnt Ash Lane Bromley Kent BR1 5DL",
    "addr:postcode":"br1 5dl",
    "addr:street":"Burnt Ash Lane",
    "iso:country":"GB",
    "sg:address":"Frosty House, Burnt Ash Lane",
    "sg:city":"Bromley",
    "sg:classifiers":[
        {
            "category":"Home & Garden",
            "subcategory":"Household Appliances",
            "type":"Retail Goods"
        }
    ],
    "sg:postcode":"BR1 5DL",
    "sg:province":"Kent",
    "sg:tags":[
        "electrical"
    ],
    "wof:name":"Frosty Business",
    "wof:placetype":"venue"
},
  "geometry": {"coordinates":[0.020945,51.426529],"type":"Point"}
}