{
  "type": "Feature",
  "properties": {
    "iso:country":"GB",
    "sg:address":"207 Great Western Road",
    "sg:city":"Glasgow",
    "sg:classifiers":[
        {
            "category":"Health Services",
            "subcategory":"Optometrist",
            "type":"Services"
        },
        {
            "category":"Shopping",
            "subcategory":"Optician",
            "type":"Retail Goods"
        }
    ],
    "sg:phone":"+44 141 332 8444",
    "sg:postcode":"G4 9EB",
    "sg:province":"Glasgow City",
    "sg:tags":[
        "ophthalmic"
    ],
    "wof:name":"Opticare Opticians Ltd",
    "wof:placetype":"venue"
},
  "geometry": {"coordinates":[-4.2732901573,55.872505188],"type":"Point"}
}