{
  "type": "Feature",
  "properties": {
    "addr:full":"Southfields, Wimborne Rd Poole Dorset BH16 6HQ",
    "addr:postcode":"bh16 6hq",
    "addr:street":"Wimborne Rd",
    "iso:country":"GB",
    "sg:address":"Southfields, Wimborne Rd",
    "sg:city":"Poole",
    "sg:classifiers":[
        {
            "category":"Building & Trades",
            "subcategory":"Construction",
            "type":"Services"
        }
    ],
    "sg:phone":"+44 1202 624454",
    "sg:postcode":"BH16 6HQ",
    "sg:province":"Dorset",
    "sg:tags":[
        "dry",
        "lining",
        "plasterers",
        "screeders"
    ],
    "wof:name":"Ayling & Hibberd",
    "wof:placetype":"venue"
},
  "geometry": {"coordinates":[-2.0661699772,50.7618103027],"type":"Point"}
}