{
  "type": "Feature",
  "properties": {
    "addr:full":"James Craig Walk Edinburgh City of Edinburgh EH1 3BA",
    "addr:postcode":"eh1 3ba",
    "addr:street":"James Craig Walk",
    "iso:country":"GB",
    "sg:address":"James Craig Walk",
    "sg:city":"Edinburgh",
    "sg:classifiers":[
        {
            "category":"Social Services",
            "type":"Services"
        }
    ],
    "sg:phone":"+44 131 244 1949",
    "sg:postcode":"EH1 3BA",
    "sg:province":"City of Edinburgh",
    "wof:name":"Central Council for Education & Training in Social Work",
    "wof:placetype":"venue"
},
  "geometry": {"coordinates":[-3.188734,55.953934],"type":"Point"}
}