{
  "type": "Feature",
  "properties": {
    "iso:country":"GB",
    "sg:address":"10 Castlegate",
    "sg:city":"Grantham",
    "sg:classifiers":[
        {
            "category":"Bars & Pubs",
            "type":"Food & Drink"
        }
    ],
    "sg:phone":"+44 1476 404554",
    "sg:postcode":"NG31 6SE",
    "sg:province":"Lincolnshire",
    "sg:tags":[
        "pubs",
        "inn"
    ],
    "wof:name":"The Beehive Inn",
    "wof:placetype":"venue"
},
  "geometry": {"coordinates":[-0.640461,52.912312],"type":"Point"}
}