{
  "type": "Feature",
  "properties": {
    "iso:country":"GB",
    "sg:address":"21 Oakeneaves Avenue",
    "sg:city":"Burnley",
    "sg:classifiers":[
        {
            "category":"Home & Garden",
            "subcategory":"Hardware",
            "type":"Retail Goods"
        }
    ],
    "sg:phone":"+44 1282 428176",
    "sg:postcode":"BB11 5HH",
    "sg:province":"Lancashire",
    "sg:tags":[
        "retailer",
        "diy"
    ],
    "wof:name":"Graphix Signs",
    "wof:placetype":"venue"
},
  "geometry": {"coordinates":[-2.260706,53.772865],"type":"Point"}
}