{
  "type": "Feature",
  "properties": {
    "addr:full":"62 Redcar Rd, South Bank Middlesbrough North Yorkshire TS6 6NJ",
    "addr:housenumber":"62",
    "addr:postcode":"ts6 6nj",
    "addr:street":"Redcar Rd;Bank",
    "iso:country":"GB",
    "sg:address":"62 Redcar Rd, South Bank",
    "sg:city":"Middlesbrough",
    "sg:classifiers":[
        {
            "category":"Shopping",
            "type":"Retail Goods"
        }
    ],
    "sg:phone":"+44 1642 465058",
    "sg:postcode":"TS6 6NJ",
    "sg:province":"North Yorkshire",
    "sg:tags":[
        "household",
        "store"
    ],
    "wof:name":"M.A Wajid",
    "wof:placetype":"venue"
},
  "geometry": {"coordinates":[-1.1764069796,54.5782775879],"type":"Point"}
}