{
  "type": "Feature",
  "properties": {
    "addr:full":"20 London Road, Lynsted Sittingbourne Kent ME9 9QS",
    "addr:housenumber":"20",
    "addr:postcode":"me9 9qs",
    "addr:street":"London Road;Sittingbourne",
    "iso:country":"GB",
    "sg:address":"20 London Road, Lynsted",
    "sg:city":"Sittingbourne",
    "sg:classifiers":[
        {
            "category":"Bars & Pubs",
            "type":"Food & Drink"
        }
    ],
    "sg:phone":"+44 1795 521214",
    "sg:postcode":"ME9 9QS",
    "sg:province":"Kent",
    "sg:tags":[
        "pubs",
        "inn"
    ],
    "wof:name":"Dover Castle Inn",
    "wof:placetype":"venue"
},
  "geometry": {"coordinates":[0.803378,51.326878],"type":"Point"}
}