{
  "type": "Feature",
  "properties": {
    "iso:country":"GB",
    "sg:address":"96 Main Road, Fenwick",
    "sg:city":"Kilmarnock",
    "sg:classifiers":[
        {
            "category":"Shopping",
            "subcategory":"Department Store",
            "type":"Retail Goods"
        },
        {
            "category":"Food & Beverages",
            "subcategory":"Groceries & Convenience Stores",
            "type":"Retail Goods"
        }
    ],
    "sg:phone":"+44 1560 600418",
    "sg:postcode":"KA3 6DY",
    "sg:province":"East Ayrshire",
    "wof:name":"J D Gordon General Stores",
    "wof:placetype":"venue"
},
  "geometry": {"coordinates":[-4.443354,55.662018],"type":"Point"}
}