{
  "type": "Feature",
  "properties": {
    "addr:full":"93 Nunts Park Avenue, Holbrooks Coventry Warwickshire CV6 4GX",
    "addr:housenumber":"93",
    "addr:postcode":"cv6 4gx",
    "addr:street":"Nunts Park Avenue",
    "iso:country":"GB",
    "sg:address":"93 Nunts Park Avenue, Holbrooks",
    "sg:city":"Coventry",
    "sg:classifiers":[
        {
            "category":"Manufacturing",
            "subcategory":"Textiles",
            "type":"Manufacturing & Wholesale Goods"
        }
    ],
    "sg:phone":"+44 24 7636 3923",
    "sg:postcode":"CV6 4GX",
    "sg:province":"Warwickshire",
    "sg:tags":[
        "made-up"
    ],
    "wof:name":"John Beverley",
    "wof:placetype":"venue"
},
  "geometry": {"coordinates":[-1.5189130306,52.4490890503],"type":"Point"}
}