{
  "type": "Feature",
  "properties": {
    "iso:country":"GB",
    "sg:address":"240 High Street",
    "sg:city":"Berkhamsted",
    "sg:classifiers":[
        {
            "category":"Shopping",
            "subcategory":"Shoes",
            "type":"Retail Goods"
        }
    ],
    "sg:postcode":"HP4 1AG",
    "sg:province":"Bedfordshire",
    "sg:tags":[
        "shop"
    ],
    "wof:name":"Colton Footwear",
    "wof:placetype":"venue"
},
  "geometry": {"coordinates":[-0.5668370128,51.761264801],"type":"Point"}
}