{
  "type": "Feature",
  "properties": {
    "addr:full":"3 Lincolns Inn Fields London Greater London WC2A 3AA",
    "addr:housenumber":"3",
    "addr:postcode":"wc2a 3aa",
    "addr:street":"Lincolns;Fields",
    "iso:country":"GB",
    "sg:address":"3 Lincolns Inn Fields",
    "sg:city":"London",
    "sg:classifiers":[
        {
            "category":"Real Estate",
            "subcategory":"Developer",
            "type":"Services"
        }
    ],
    "sg:phone":"+44 171 638 5500",
    "sg:postcode":"WC2A 3AA",
    "sg:province":"Greater London",
    "sg:tags":[
        "property"
    ],
    "wof:name":"Bessa Rbs Xi Plc",
    "wof:placetype":"venue"
},
  "geometry": {"coordinates":[-0.1183419973,51.5166778564],"type":"Point"}
}