{
  "type": "Feature",
  "properties": {
    "addr:full":"Stroud Road, Nailsworth Stroud Gloucestershire GL6 0BE",
    "addr:postcode":"gl6 0be",
    "addr:street":"Stroud Road",
    "iso:country":"GB",
    "sg:address":"Stroud Road, Nailsworth",
    "sg:city":"Stroud",
    "sg:classifiers":[
        {
            "category":"Freight",
            "type":"Transportation"
        }
    ],
    "sg:phone":"+44 1453 832718",
    "sg:postcode":"GL6 0BE",
    "sg:province":"Gloucestershire",
    "sg:tags":[
        "haulage",
        "road"
    ],
    "wof:name":"Gouldings of Nailsworth Ltd.",
    "wof:placetype":"venue"
},
  "geometry": {"coordinates":[-2.217984,51.695816],"type":"Point"}
}