{
  "type": "Feature",
  "properties": {
    "addr:full":"Cotebank, Ryehills Road, Skinburness Wigton Cumbria CA7 4QT",
    "addr:postcode":"ca7 4qt",
    "addr:street":"Ryehills Road",
    "iso:country":"GB",
    "sg:address":"Cotebank, Ryehills Road, Skinburness",
    "sg:city":"Wigton",
    "sg:classifiers":[
        {
            "category":"Health Services",
            "subcategory":"Chiropractor",
            "type":"Services"
        }
    ],
    "sg:postcode":"CA7 4QT",
    "sg:province":"Cumbria",
    "wof:name":"Juliet Thomas",
    "wof:placetype":"venue"
},
  "geometry": {"coordinates":[-3.3655281067,54.8891677856],"type":"Point"}
}