{
  "type": "Feature",
  "properties": {
    "addr:full":"46 Rosedale Road Nottingham Nottinghamshire NG3 7GU",
    "addr:housenumber":"46",
    "addr:postcode":"ng3 7gu",
    "addr:street":"Rosedale Road",
    "iso:country":"GB",
    "sg:address":"46 Rosedale Road",
    "sg:city":"Nottingham",
    "sg:classifiers":[
        {
            "category":"Manufacturing",
            "subcategory":"Textiles",
            "type":"Manufacturing & Wholesale Goods"
        }
    ],
    "sg:phone":"+44 115 987 2631",
    "sg:postcode":"NG3 7GU",
    "sg:province":"Nottinghamshire",
    "sg:tags":[
        "made-up"
    ],
    "wof:name":"Elizabeth's Interiors",
    "wof:placetype":"venue"
},
  "geometry": {"coordinates":[-1.106014967,52.9591140747],"type":"Point"}
}