{
  "type": "Feature",
  "properties": {
    "iso:country":"GB",
    "sg:address":"154 Main St",
    "sg:city":"Glasgow",
    "sg:classifiers":[
        {
            "category":"Food & Beverages",
            "subcategory":"Supermarket",
            "type":"Retail Goods"
        }
    ],
    "sg:postcode":"G69 6AH",
    "sg:province":"East Dunbartonshire",
    "wof:name":"Ahmed,R,",
    "wof:placetype":"venue"
},
  "geometry": {"coordinates":[-4.1086888313,55.8510055542],"type":"Point"}
}