{
  "type": "Feature",
  "properties": {
    "addr:full":"660 Aigburth Road Liverpool Merseyside L19 0NY",
    "addr:housenumber":"660",
    "addr:postcode":"l19 0ny",
    "addr:street":"Aigburth Road",
    "iso:country":"GB",
    "sg:address":"660 Aigburth Road",
    "sg:city":"Liverpool",
    "sg:classifiers":[
        {
            "category":"Personal",
            "subcategory":"Beauty Salon",
            "type":"Services"
        },
        {
            "category":"Personal",
            "subcategory":"Barber",
            "type":"Services"
        }
    ],
    "sg:phone":"+44 151 427 2233",
    "sg:postcode":"L19 0NY",
    "sg:province":"Merseyside",
    "sg:tags":[
        "unisex",
        "hairdresser"
    ],
    "wof:name":"ANITAS CUTTING CABIN",
    "wof:placetype":"venue"
},
  "geometry": {"coordinates":[-2.9125730991,53.3610496521],"type":"Point"}
}