{
  "type": "Feature",
  "properties": {
    "iso:country":"GB",
    "sg:address":"P O Box 114",
    "sg:city":"Chester",
    "sg:classifiers":[
        {
            "category":"Shopping",
            "subcategory":"Hobbies, Toys, & Games",
            "type":"Retail Goods"
        }
    ],
    "sg:phone":"+44 1244 300165",
    "sg:postcode":"CH4 8WQ",
    "sg:province":"Cheshire",
    "sg:tags":[
        "collectors'",
        "item"
    ],
    "wof:name":"Silver Acre Comics",
    "wof:placetype":"venue"
},
  "geometry": {"coordinates":[-2.9355139732,53.1743850708],"type":"Point"}
}