{
  "type": "Feature",
  "properties": {
    "addr:full":"112 Cleveland Street London Greater London W1T 6PA",
    "addr:housenumber":"112",
    "addr:postcode":"w1t 6pa",
    "addr:street":"Cleveland Street",
    "iso:country":"GB",
    "sg:address":"112 Cleveland Street",
    "sg:city":"London",
    "sg:classifiers":[
        {
            "category":"Professional",
            "subcategory":"Engineering",
            "type":"Services"
        }
    ],
    "sg:phone":"+44 20 7387 2064",
    "sg:postcode":"W1T 6PA",
    "sg:province":"Greater London",
    "sg:tags":[
        "contractor",
        "electrical",
        "engineer"
    ],
    "wof:name":"The B Electrical Co",
    "wof:placetype":"venue"
},
  "geometry": {"coordinates":[-0.141534,51.523037],"type":"Point"}
}