{
  "type": "Feature",
  "properties": {
    "addr:full":"Silver End House, Anns Walk Mitcheldean Gloucestershire GL17 0DA",
    "addr:postcode":"gl17 0da",
    "addr:street":"Anns Walk",
    "iso:country":"GB",
    "sg:address":"Silver End House, Anns Walk",
    "sg:city":"Mitcheldean",
    "sg:classifiers":[
        {
            "category":"Organizations",
            "subcategory":"Non-profit Organization",
            "type":"Services"
        }
    ],
    "sg:phone":"+44 1594 543368",
    "sg:postcode":"GL17 0DA",
    "sg:province":"Gloucestershire",
    "sg:tags":[
        "organisation",
        "voluntary",
        "charity"
    ],
    "wof:name":"Muscular Dystrophy Group of Great Britain (The)",
    "wof:placetype":"venue"
},
  "geometry": {"coordinates":[-2.488454,51.859547],"type":"Point"}
}