{
  "type": "Feature",
  "properties": {
    "addr:full":"29 Buttershaw Lane Bradford West Yorkshire BD6 2DD",
    "addr:housenumber":"29",
    "addr:postcode":"bd6 2dd",
    "addr:street":"Buttershaw Lane",
    "iso:country":"GB",
    "sg:address":"29 Buttershaw Lane",
    "sg:city":"Bradford",
    "sg:classifiers":[
        {
            "category":"Building & Trades",
            "subcategory":"Construction",
            "type":"Services"
        }
    ],
    "sg:phone":"+44 1274 602123",
    "sg:postcode":"BD6 2DD",
    "sg:province":"West Yorkshire",
    "sg:tags":[
        "platform",
        "builder",
        "work",
        "scaffolding"
    ],
    "wof:name":"Michael Hawley",
    "wof:placetype":"venue"
},
  "geometry": {"coordinates":[-1.7807199955,53.7615470886],"type":"Point"}
}