{
  "type": "Feature",
  "properties": {
    "addr:full":"61-79 Field Lane, Litherland Liverpool Merseyside L21 9LY",
    "addr:housenumber":"61-79",
    "addr:postcode":"l21 9ly",
    "addr:street":"Field Lane",
    "iso:country":"GB",
    "sg:address":"61-79 Field Lane, Litherland",
    "sg:city":"Liverpool",
    "sg:classifiers":[
        {
            "category":"Professional",
            "subcategory":"Printing & Photocopies",
            "type":"Services"
        }
    ],
    "sg:phone":"+44 151 928 1602",
    "sg:postcode":"L21 9LY",
    "sg:province":"Merseyside",
    "sg:tags":[
        "process",
        "screen",
        "printer"
    ],
    "wof:name":"Fingerprint Communications Ltd",
    "wof:placetype":"venue"
},
  "geometry": {"coordinates":[-3.0077090263,53.4767112732],"type":"Point"}
}