{
  "type": "Feature",
  "properties": {
    "addr:full":"19b Southwell Road Nottingham Nottinghamshire NG14 7DQ",
    "addr:housenumber":"19b",
    "addr:postcode":"ng14 7dq",
    "addr:street":"Southwell Road",
    "iso:country":"GB",
    "sg:address":"19b Southwell Road",
    "sg:city":"Nottingham",
    "sg:classifiers":[
        {
            "category":"Building & Trades",
            "subcategory":"Construction",
            "type":"Services"
        }
    ],
    "sg:phone":"+44 115 966 4059",
    "sg:postcode":"NG14 7DQ",
    "sg:province":"Nottinghamshire",
    "sg:tags":[
        "builder"
    ],
    "wof:name":"Thomas Trevlyn Hall",
    "wof:placetype":"venue"
},
  "geometry": {"coordinates":[-0.9943749905,53.0132446289],"type":"Point"}
}