{
  "type": "Feature",
  "properties": {
    "iso:country":"GB",
    "sg:address":"89 Grove Road",
    "sg:city":"Windsor",
    "sg:classifiers":[
        {
            "category":"Arts & Performance",
            "subcategory":"Art Gallery",
            "type":"Entertainment"
        }
    ],
    "sg:postcode":"SL4 1HT",
    "sg:province":"Berkshire",
    "wof:name":"N Dowling",
    "wof:placetype":"venue"
},
  "geometry": {"coordinates":[-0.612284,51.477394],"type":"Point"}
}