{
  "type": "Feature",
  "properties": {
    "iso:country":"GB",
    "sg:address":"19 Europa Boulevard, Gemini Business Park",
    "sg:city":"Warrington",
    "sg:classifiers":[
        {
            "category":"Professional",
            "subcategory":"Business Services",
            "type":"Services"
        }
    ],
    "sg:phone":"+44 1925 434200",
    "sg:postcode":"WA5 5TP",
    "sg:province":"Cheshire",
    "sg:tags":[
        "distribution"
    ],
    "wof:name":"Newsquest Letterbox Marketing",
    "wof:placetype":"venue"
},
  "geometry": {"coordinates":[-2.6486,53.405991],"type":"Point"}
}