{
  "type": "Feature",
  "properties": {
    "addr:full":"The Lace Market, 12 Pilcher Gate Nottingham Nottinghamshire NG1 1QE",
    "addr:housenumber":"12",
    "addr:postcode":"ng1 1qe",
    "addr:street":"Pilcher Gate",
    "iso:country":"GB",
    "sg:address":"The Lace Market, 12 Pilcher Gate",
    "sg:city":"Nottingham",
    "sg:classifiers":[
        {
            "category":"Professional",
            "subcategory":"Art Services",
            "type":"Services"
        }
    ],
    "sg:phone":"+44 115 956 2283",
    "sg:postcode":"NG1 1QE",
    "sg:province":"Nottinghamshire",
    "sg:tags":[
        "graphic",
        "designer"
    ],
    "wof:name":"Media 12",
    "wof:placetype":"venue"
},
  "geometry": {"coordinates":[-1.1439239979,52.9492263794],"type":"Point"}
}