{
  "type": "Feature",
  "properties": {
    "iso:country":"GB",
    "sg:address":"Jacob Street",
    "sg:city":"Bradford",
    "sg:classifiers":[
        {
            "category":"Retail",
            "subcategory":"Auto Repair",
            "type":"Services"
        }
    ],
    "sg:phone":"+44 1274 729343",
    "sg:postcode":"BD5 7LX",
    "sg:province":"West Yorkshire",
    "sg:tags":[
        "body",
        "car"
    ],
    "wof:name":"Albion Motors",
    "wof:placetype":"venue"
},
  "geometry": {"coordinates":[-1.760819,53.780529],"type":"Point"}
}