{
  "type": "Feature",
  "properties": {
    "addr:full":"58 Osborne Rd Southsea Hampshire PO5 3LU",
    "addr:housenumber":"58",
    "addr:postcode":"po5 3lu",
    "addr:street":"Osborne Rd",
    "iso:country":"GB",
    "sg:address":"58 Osborne Rd",
    "sg:city":"Southsea",
    "sg:classifiers":[
        {
            "category":"Restaurant",
            "type":"Food & Drink"
        }
    ],
    "sg:phone":"+44 23 9275 0200",
    "sg:postcode":"PO5 3LU",
    "sg:province":"Hampshire",
    "wof:name":"Chicago Tender Chicken",
    "wof:placetype":"venue"
},
  "geometry": {"coordinates":[-1.0905569792,50.7848434448],"type":"Point"}
}