{
  "type": "Feature",
  "properties": {
    "addr:full":"149a Common Lane, Washwood Heath Birmingham West Midlands B8 2UW",
    "addr:housenumber":"149a",
    "addr:postcode":"b8 2uw",
    "addr:street":"Common Lane",
    "iso:country":"GB",
    "sg:address":"149a Common Lane, Washwood Heath",
    "sg:city":"Birmingham",
    "sg:classifiers":[
        {
            "category":"Professional",
            "subcategory":"Management & Consulting",
            "type":"Services"
        }
    ],
    "sg:postcode":"B8 2UW",
    "sg:province":"West Midlands",
    "sg:tags":[
        "consultant",
        "business"
    ],
    "wof:name":"Oakleigh Q.M. Ltd",
    "wof:placetype":"venue"
},
  "geometry": {"coordinates":[-1.8434189558,52.4995727539],"type":"Point"}
}