{
  "type": "Feature",
  "properties": {
    "iso:country":"GB",
    "sg:address":"Wood End Rd",
    "sg:city":"Wolverhampton",
    "sg:classifiers":[
        {
            "category":"Community Center",
            "type":"Public Place"
        }
    ],
    "sg:phone":"+44 1902 552442",
    "sg:postcode":"WV11 1YG",
    "sg:province":"Staffordshire",
    "sg:tags":[
        "centre"
    ],
    "wof:name":"Long Knowle Community Centre",
    "wof:placetype":"venue"
},
  "geometry": {"coordinates":[-2.086744,52.615314],"type":"Point"}
}