{
  "type": "Feature",
  "properties": {
    "addr:full":"27 Carlton Close Plymouth Devon PL3 6JS",
    "addr:housenumber":"27",
    "addr:postcode":"pl3 6js",
    "addr:street":"Carlton Close",
    "iso:country":"GB",
    "sg:address":"27 Carlton Close",
    "sg:city":"Plymouth",
    "sg:classifiers":[
        {
            "category":"Building & Trades",
            "subcategory":"Construction",
            "type":"Services"
        }
    ],
    "sg:postcode":"PL3 6JS",
    "sg:province":"Devon",
    "sg:tags":[
        "joiner",
        "carpenter"
    ],
    "wof:name":"Mike Pierce Property Maintenance",
    "wof:placetype":"venue"
},
  "geometry": {"coordinates":[-4.117924,50.38707],"type":"Point"}
}