{
  "type": "Feature",
  "properties": {
    "iso:country":"GB",
    "sg:address":"Po Box 15",
    "sg:city":"Redruth",
    "sg:classifiers":[
        {
            "category":"Professional",
            "subcategory":"Engineering",
            "type":"Services"
        }
    ],
    "sg:postcode":"TR15 2UE",
    "sg:province":"Cornwall",
    "sg:tags":[
        "consulting",
        "engineer"
    ],
    "wof:name":"Flame & Emission Technology Ltd",
    "wof:placetype":"venue"
},
  "geometry": {"coordinates":[-5.22321,50.230949],"type":"Point"}
}