{
  "type": "Feature",
  "properties": {
    "addr:full":"2 Witham Drive, Huntington York North Yorkshire YO32 9YD",
    "addr:housenumber":"2",
    "addr:postcode":"yo32 9yd",
    "addr:street":"Witham Drive",
    "iso:country":"GB",
    "sg:address":"2 Witham Drive, Huntington",
    "sg:city":"York",
    "sg:classifiers":[
        {
            "category":"Retail",
            "subcategory":"Driving School",
            "type":"Services"
        }
    ],
    "sg:postcode":"YO32 9YD",
    "sg:province":"North Yorkshire",
    "wof:name":"Senior School of Motoring",
    "wof:placetype":"venue"
},
  "geometry": {"coordinates":[-1.0539480448,54.0012588501],"type":"Point"}
}