{
  "type": "Feature",
  "properties": {
    "addr:full":"106 King Edward Road Maidstone Kent ME15 6PL",
    "addr:housenumber":"106",
    "addr:postcode":"me15 6pl",
    "addr:street":"King Edward Road",
    "iso:country":"GB",
    "sg:address":"106 King Edward Road",
    "sg:city":"Maidstone",
    "sg:classifiers":[
        {
            "category":"Retail",
            "subcategory":"Repair Shop",
            "type":"Services"
        }
    ],
    "sg:postcode":"ME15 6PL",
    "sg:province":"Kent",
    "sg:tags":[
        "furniture"
    ],
    "wof:name":"Brockwells Ltd.",
    "wof:placetype":"venue"
},
  "geometry": {"coordinates":[0.5195659995,51.2650794983],"type":"Point"}
}