{
  "type": "Feature",
  "properties": {
    "addr:full":"22 Courtland Avenue London Greater London E4 6DU",
    "addr:housenumber":"22",
    "addr:postcode":"e4 6du",
    "addr:street":"Courtland Avenue",
    "iso:country":"GB",
    "sg:address":"22 Courtland Avenue",
    "sg:city":"London",
    "sg:classifiers":[
        {
            "category":"Organizations",
            "subcategory":"Membership Organization",
            "type":"Services"
        }
    ],
    "sg:phone":"+44 20 8559 3377",
    "sg:postcode":"E4 6DU",
    "sg:province":"Greater London",
    "sg:tags":[
        "club"
    ],
    "wof:name":"Queens Road (Block I) Management Co. Ltd.",
    "wof:placetype":"venue"
},
  "geometry": {"coordinates":[0.0166069996,51.6262054443],"type":"Point"}
}