{
  "type": "Feature",
  "properties": {
    "addr:full":"1125 Argyle Street Glasgow Glasgow City G3 8ND",
    "addr:housenumber":"1125",
    "addr:postcode":"g3 8nd",
    "addr:street":"Argyle Street",
    "iso:country":"GB",
    "sg:address":"1125 Argyle Street",
    "sg:city":"Glasgow",
    "sg:classifiers":[
        {
            "category":"Professional",
            "subcategory":"Art Services",
            "type":"Services"
        }
    ],
    "sg:postcode":"G3 8ND",
    "sg:province":"Glasgow City",
    "sg:tags":[
        "graphic",
        "designer"
    ],
    "wof:name":"J P McNocher",
    "wof:placetype":"venue"
},
  "geometry": {"coordinates":[-4.284252,55.864674],"type":"Point"}
}