{
  "type": "Feature",
  "properties": {
    "iso:country":"GB",
    "sg:address":"11 Dogpole",
    "sg:city":"Shrewsbury",
    "sg:classifiers":[
        {
            "category":"Travel",
            "subcategory":"Hotels & Motels",
            "type":"Entertainment"
        }
    ],
    "sg:phone":"+44 1743 361440",
    "sg:postcode":"SY1 1EN",
    "sg:province":"Shropshire",
    "wof:name":"Cromwells Of Shrewsbury Hotel",
    "wof:placetype":"venue"
},
  "geometry": {"coordinates":[-2.751318,52.70715],"type":"Point"}
}