{
  "type": "Feature",
  "properties": {
    "addr:full":"331 Midland Road, Royston Barnsley South Yorkshire S71 4AZ",
    "addr:housenumber":"331",
    "addr:postcode":"s71 4az",
    "addr:street":"Midland Road;Yorkshire",
    "iso:country":"GB",
    "sg:address":"331 Midland Road, Royston",
    "sg:city":"Barnsley",
    "sg:classifiers":[
        {
            "category":"Building & Trades",
            "subcategory":"Construction",
            "type":"Services"
        }
    ],
    "sg:phone":"+44 1226 727864",
    "sg:postcode":"S71 4AZ",
    "sg:province":"South Yorkshire",
    "sg:tags":[
        "roofing"
    ],
    "wof:name":"A-Z Roofing",
    "wof:placetype":"venue"
},
  "geometry": {"coordinates":[-1.438872,53.600597],"type":"Point"}
}