{
  "type": "Feature",
  "properties": {
    "iso:country":"GB",
    "sg:address":"84-86 Regent Street",
    "sg:city":"Weston-super-mare",
    "sg:classifiers":[
        {
            "category":"Restaurant",
            "type":"Food & Drink"
        }
    ],
    "sg:postcode":"BS23 1SR",
    "sg:province":"Somerset",
    "wof:name":"Coffins Fish Restaurant",
    "wof:placetype":"venue"
},
  "geometry": {"coordinates":[-2.9764831066,51.347026825],"type":"Point"}
}