{
  "type": "Feature",
  "properties": {
    "iso:country":"GB",
    "sg:address":"55 Chislehurst Rd",
    "sg:city":"Chislehurst",
    "sg:classifiers":[
        {
            "category":"Real Estate",
            "subcategory":"Real Estate Agent",
            "type":"Services"
        }
    ],
    "sg:postcode":"BR7 5NP",
    "sg:province":"Kent",
    "wof:name":"Lebens",
    "wof:placetype":"venue"
},
  "geometry": {"coordinates":[0.055444,51.40749],"type":"Point"}
}