{
  "type": "Feature",
  "properties": {
    "addr:full":"55 Chislehurst Rd Chislehurst Kent BR7 5NP",
    "addr:housenumber":"55",
    "addr:postcode":"br7 5np",
    "addr:street":"Chislehurst Rd",
    "iso:country":"GB",
    "sg:address":"55 Chislehurst Rd",
    "sg:city":"Chislehurst",
    "sg:classifiers":[
        {
            "category":"Real Estate",
            "subcategory":"Real Estate Agent",
            "type":"Services"
        }
    ],
    "sg:postcode":"BR7 5NP",
    "sg:province":"Kent",
    "wof:name":"Lebens",
    "wof:placetype":"venue"
},
  "geometry": {"coordinates":[0.055444,51.40749],"type":"Point"}
}