{
  "type": "Feature",
  "properties": {
    "iso:country":"GB",
    "sg:address":"79 Station Road",
    "sg:city":"New Milton",
    "sg:classifiers":[
        {
            "category":"Shopping",
            "subcategory":"Thrift Store",
            "type":"Retail Goods"
        }
    ],
    "sg:phone":"+44 1425 611772",
    "sg:postcode":"BH25 6JD",
    "sg:province":"Hampshire",
    "sg:tags":[
        "shop",
        "charity"
    ],
    "wof:name":"Sue Ryder Care",
    "wof:placetype":"venue"
},
  "geometry": {"coordinates":[-1.654388,50.752087],"type":"Point"}
}