{
  "type": "Feature",
  "properties": {
    "addr:full":"44 Clockhouse Road Farnborough Hampshire GU14 7QZ",
    "addr:housenumber":"44",
    "addr:postcode":"gu14 7qz",
    "addr:street":"Clockhouse Road",
    "iso:country":"GB",
    "sg:address":"44 Clockhouse Road",
    "sg:city":"Farnborough",
    "sg:classifiers":[
        {
            "category":"Shopping",
            "subcategory":"Books",
            "type":"Retail Goods"
        }
    ],
    "sg:phone":"+44 1252 541602",
    "sg:postcode":"GU14 7QZ",
    "sg:province":"Hampshire",
    "sg:tags":[
        "retailer"
    ],
    "wof:name":"Thames & Hudson Distributors Ltd.",
    "wof:placetype":"venue"
},
  "geometry": {"coordinates":[-0.757486,51.294834],"type":"Point"}
}