{
  "type": "Feature",
  "properties": {
    "iso:country":"GB",
    "sg:address":"106 Poulton Street, Kirkham",
    "sg:city":"Preston",
    "sg:classifiers":[
        {
            "category":"Taxi",
            "type":"Transportation"
        },
        {
            "category":"Military Area",
            "subcategory":"Air Force Base",
            "type":"Public Place"
        }
    ],
    "sg:phone":"+44 1772 685658",
    "sg:postcode":"PR4 2AH",
    "sg:province":"Lancashire",
    "sg:tags":[
        "hire",
        "private"
    ],
    "wof:name":"Phil Cunningham & Walter McCracken",
    "wof:placetype":"venue"
},
  "geometry": {"coordinates":[-2.87607,53.782108],"type":"Point"}
}