{
  "type": "Feature",
  "properties": {
    "addr:full":"131a Milner Road, Heswall Wirral Merseyside CH60 5RX",
    "addr:housenumber":"131a",
    "addr:postcode":"ch60 5rx",
    "addr:street":"Milner Road",
    "iso:country":"GB",
    "sg:address":"131a Milner Road, Heswall",
    "sg:city":"Wirral",
    "sg:classifiers":[
        {
            "category":"Wholesale",
            "subcategory":"Construction Materials",
            "type":"Manufacturing & Wholesale Goods"
        },
        {
            "category":"Manufacturing",
            "subcategory":"Building Materials",
            "type":"Manufacturing & Wholesale Goods"
        }
    ],
    "sg:phone":"+44 151 342 4017",
    "sg:postcode":"CH60 5RX",
    "sg:province":"Merseyside",
    "sg:tags":[
        "tarmac",
        "macadam",
        "laying",
        "asphalt",
        "contractor"
    ],
    "wof:name":"Heswall Tarmacs",
    "wof:placetype":"venue"
},
  "geometry": {"coordinates":[-3.0886061192,53.3291740417],"type":"Point"}
}