{
  "type": "Feature",
  "properties": {
    "addr:full":"9 Crescent Gardens London Greater London SW19 8AJ",
    "addr:housenumber":"9",
    "addr:postcode":"sw19 8aj",
    "addr:street":"Crescent Gardens",
    "iso:country":"GB",
    "sg:address":"9 Crescent Gardens",
    "sg:city":"London",
    "sg:classifiers":[
        {
            "category":"Place Of Worship",
            "type":"Public Place"
        }
    ],
    "sg:phone":"+44 20 8946 2091",
    "sg:postcode":"SW19 8AJ",
    "sg:province":"Greater London",
    "wof:name":"Christ the King Catholic Church",
    "wof:placetype":"venue"
},
  "geometry": {"coordinates":[-0.1981080025,51.4343147278],"type":"Point"}
}