{
  "type": "Feature",
  "properties": {
    "addr:full":"Unit 4, Gaol Mews Gaol Rd Stafford Staffordshire ST16 3AN",
    "addr:housenumber":"unit 4",
    "addr:postcode":"st16 3an",
    "addr:street":"Gaol Mews Gaol Rd",
    "iso:country":"GB",
    "sg:address":"Unit 4, Gaol Mews Gaol Rd",
    "sg:city":"Stafford",
    "sg:classifiers":[
        {
            "category":"Communications",
            "type":"Services"
        }
    ],
    "sg:phone":"+44 1785 255904",
    "sg:postcode":"ST16 3AN",
    "sg:province":"Staffordshire",
    "sg:tags":[
        "data",
        "network"
    ],
    "wof:name":"Shaman Ltd",
    "wof:placetype":"venue"
},
  "geometry": {"coordinates":[-2.121768,52.803959],"type":"Point"}
}