{
  "type": "Feature",
  "properties": {
    "iso:country":"GB",
    "sg:address":"Ladywood Farm, Weston",
    "sg:city":"Newark",
    "sg:classifiers":[
        {
            "category":"Farming",
            "subcategory":"Farm",
            "type":"Manufacturing & Wholesale Goods"
        }
    ],
    "sg:phone":"+44 1636 821455",
    "sg:postcode":"NG23 6TD",
    "sg:province":"Lincolnshire",
    "sg:tags":[
        "mixed",
        "crop"
    ],
    "wof:name":"David M Chase",
    "wof:placetype":"venue"
},
  "geometry": {"coordinates":[-0.846199,53.202438],"type":"Point"}
}