{
  "type": "Feature",
  "properties": {
    "addr:full":"Halifax Road Bradford West Yorkshire BD6 1JQ",
    "addr:postcode":"bd6 1jq",
    "addr:street":"Halifax Road",
    "iso:country":"GB",
    "sg:address":"Halifax Road",
    "sg:city":"Bradford",
    "sg:classifiers":[
        {
            "category":"Bars & Pubs",
            "type":"Food & Drink"
        }
    ],
    "sg:postcode":"BD6 1JQ",
    "sg:province":"West Yorkshire",
    "sg:tags":[
        "pubs",
        "inn"
    ],
    "wof:name":"Moonrakers",
    "wof:placetype":"venue"
},
  "geometry": {"coordinates":[-1.772834,53.761395],"type":"Point"}
}