{
  "type": "Feature",
  "properties": {
    "addr:full":"34 Haven Road, Eastoke Hayling Island Hampshire PO11 9RY",
    "addr:housenumber":"34",
    "addr:postcode":"po11 9ry",
    "addr:street":"Haven Road Eastoke",
    "iso:country":"GB",
    "sg:address":"34 Haven Road, Eastoke",
    "sg:city":"Hayling Island",
    "sg:classifiers":[
        {
            "category":"Recreation",
            "subcategory":"Campground",
            "type":"Entertainment"
        }
    ],
    "sg:phone":"+44 23 9246 4508",
    "sg:postcode":"PO11 9RY",
    "sg:province":"Hampshire",
    "sg:tags":[
        "caravan",
        "park"
    ],
    "wof:name":"Ethelville Caravan Park",
    "wof:placetype":"venue"
},
  "geometry": {"coordinates":[-0.947689,50.780952],"type":"Point"}
}