{
  "type": "Feature",
  "properties": {
    "addr:full":"41-43 Bebington Rd, New Ferry Wirral Cheshire CH62 5BE",
    "addr:housenumber":"41-43",
    "addr:postcode":"ch62 5be",
    "addr:street":"Bebington Rd",
    "iso:country":"GB",
    "sg:address":"41-43 Bebington Rd, New Ferry",
    "sg:city":"Wirral",
    "sg:classifiers":[
        {
            "category":"Professional",
            "subcategory":"Employment Agencies",
            "type":"Services"
        }
    ],
    "sg:postcode":"CH62 5BE",
    "sg:province":"Cheshire",
    "sg:tags":[
        "career",
        "guidance"
    ],
    "wof:name":"Career Connections Ltd",
    "wof:placetype":"venue"
},
  "geometry": {"coordinates":[-2.9992959499,53.3593482971],"type":"Point"}
}