{
  "type": "Feature",
  "properties": {
    "iso:country":"GB",
    "sg:address":"Nuttaberry Hill",
    "sg:city":"Bideford",
    "sg:classifiers":[
        {
            "category":"Building & Trades",
            "subcategory":"Construction",
            "type":"Services"
        }
    ],
    "sg:phone":"+44 1237 479236",
    "sg:postcode":"EX39 4EA",
    "sg:province":"Devon",
    "sg:tags":[
        "builder"
    ],
    "wof:name":"Colour Coating",
    "wof:placetype":"venue"
},
  "geometry": {"coordinates":[-4.200761,51.01347],"type":"Point"}
}