{
  "type": "Feature",
  "properties": {
    "addr:full":"6 Runnymede Road, Whitton Twickenham Greater London TW2 7HF",
    "addr:housenumber":"6",
    "addr:postcode":"tw2 7hf",
    "addr:street":"Runnymede Road",
    "iso:country":"GB",
    "sg:address":"6 Runnymede Road, Whitton",
    "sg:city":"Twickenham",
    "sg:classifiers":[
        {
            "category":"Manufacturing",
            "subcategory":"Furniture",
            "type":"Manufacturing & Wholesale Goods"
        }
    ],
    "sg:phone":"+44 20 8755 0016",
    "sg:postcode":"TW2 7HF",
    "sg:province":"Greater London",
    "sg:tags":[
        "polishing",
        "french"
    ],
    "wof:name":"John Pegrum",
    "wof:placetype":"venue"
},
  "geometry": {"coordinates":[-0.362638,51.457188],"type":"Point"}
}