{
  "type": "Feature",
  "properties": {
    "addr:full":"1-4 East Parade Rhyl Conwy LL18 3AD",
    "addr:housenumber":"1-4",
    "addr:postcode":"ll18 3ad",
    "addr:street":"East Parade",
    "iso:country":"GB",
    "sg:address":"1-4 East Parade",
    "sg:city":"Rhyl",
    "sg:classifiers":[
        {
            "category":"Shopping",
            "subcategory":"Department Store",
            "type":"Retail Goods"
        }
    ],
    "sg:phone":"+44 1745 334191",
    "sg:postcode":"LL18 3AD",
    "sg:province":"Conwy",
    "sg:tags":[
        "departmental"
    ],
    "wof:name":"Woolworths plc",
    "wof:placetype":"venue"
},
  "geometry": {"coordinates":[-3.490799,53.322819],"type":"Point"}
}