{
  "type": "Feature",
  "properties": {
    "addr:full":"55 Leroy St Southwark Greater London SE1 4SN",
    "addr:housenumber":"55",
    "addr:postcode":"se1 4sn",
    "addr:street":"Leroy St",
    "iso:country":"GB",
    "sg:address":"55 Leroy St",
    "sg:city":"Southwark",
    "sg:classifiers":[
        {
            "category":"Professional",
            "subcategory":"Art Services",
            "type":"Services"
        }
    ],
    "sg:phone":"+44 20 7394 9520",
    "sg:postcode":"SE1 4SN",
    "sg:province":"Greater London",
    "sg:tags":[
        "photographer"
    ],
    "wof:name":"Angus Thompson",
    "wof:placetype":"venue"
},
  "geometry": {"coordinates":[-0.0837320015,51.4951667786],"type":"Point"}
}