{
  "type": "Feature",
  "properties": {
    "iso:country":"GB",
    "sg:address":"Carr Lane",
    "sg:city":"Alford",
    "sg:classifiers":[
        {
            "category":"Retail",
            "subcategory":"Auto Repair",
            "type":"Services"
        }
    ],
    "sg:phone":"+44 1507 462256",
    "sg:postcode":"LN13 9AD",
    "sg:province":"Lincolnshire",
    "sg:tags":[
        "body",
        "car"
    ],
    "wof:name":"Don White Accident Repairs",
    "wof:placetype":"venue"
},
  "geometry": {"coordinates":[0.179875,53.260136],"type":"Point"}
}