{
  "type": "Feature",
  "properties": {
    "addr:full":"5 Wynnstay Rd Colwyn Bay Conwy LL29 8NB",
    "addr:housenumber":"5",
    "addr:postcode":"ll29 8nb",
    "addr:street":"Wynnstay Rd",
    "iso:country":"GB",
    "sg:address":"5 Wynnstay Rd",
    "sg:city":"Colwyn Bay",
    "sg:classifiers":[
        {
            "category":"Health Services",
            "subcategory":"Health Practitioner",
            "type":"Services"
        }
    ],
    "sg:phone":"+44 1492 534248",
    "sg:postcode":"LL29 8NB",
    "sg:province":"Conwy",
    "sg:tags":[
        "physiotherapist"
    ],
    "wof:name":"J Donovan",
    "wof:placetype":"venue"
},
  "geometry": {"coordinates":[-3.730348,53.296478],"type":"Point"}
}