{
  "type": "Feature",
  "properties": {
    "iso:country":"GB",
    "sg:address":"59 Beechley Road",
    "sg:city":"Wrexham",
    "sg:classifiers":[
        {
            "category":"Organizations",
            "subcategory":"Community Association",
            "type":"Services"
        }
    ],
    "sg:phone":"+44 1978 364418",
    "sg:postcode":"LL13 7AU",
    "sg:province":"Wrexham",
    "sg:tags":[
        "co-operatives",
        "society",
        "housing",
        "trust"
    ],
    "wof:name":"Abbeyfield Wrexham Society",
    "wof:placetype":"venue"
},
  "geometry": {"coordinates":[-2.99049,53.03941],"type":"Point"}
}