{
  "type": "Feature",
  "properties": {
    "iso:country":"GB",
    "sg:address":"Mitchell Rd, Churchfields Industrial Estate",
    "sg:city":"Salisbury",
    "sg:classifiers":[
        {
            "category":"Autos & Motor Vehicles",
            "subcategory":"Automobile Sales",
            "type":"Retail Goods"
        }
    ],
    "sg:phone":"+44 1722 414425",
    "sg:postcode":"SP2 7PY",
    "sg:province":"Wiltshire",
    "sg:tags":[
        "commercial"
    ],
    "wof:name":"Avh Commercials",
    "wof:placetype":"venue"
},
  "geometry": {"coordinates":[-1.815959,51.069031],"type":"Point"}
}