{
  "type": "Feature",
  "properties": {
    "addr:full":"22 London Road Tilbury Essex RM18 8DU",
    "addr:housenumber":"22",
    "addr:postcode":"rm18 8du",
    "addr:street":"London Road",
    "iso:country":"GB",
    "sg:address":"22 London Road",
    "sg:city":"Tilbury",
    "sg:classifiers":[
        {
            "category":"Building & Trades",
            "subcategory":"Construction",
            "type":"Services"
        }
    ],
    "sg:phone":"+44 1375 850773",
    "sg:postcode":"RM18 8DU",
    "sg:province":"Essex",
    "sg:tags":[
        "fork",
        "lift",
        "truck"
    ],
    "wof:name":"A L M Training Service",
    "wof:placetype":"venue"
},
  "geometry": {"coordinates":[0.369713,51.460266],"type":"Point"}
}