{
  "type": "Feature",
  "properties": {
    "addr:full":"18 Harcourt Terrace London Greater London SW10 9JR",
    "addr:housenumber":"18",
    "addr:postcode":"sw10 9jr",
    "addr:street":"Harcourt Terrace",
    "iso:country":"GB",
    "sg:address":"18 Harcourt Terrace",
    "sg:city":"London",
    "sg:classifiers":[
        {
            "category":"Banks & Credit Unions",
            "subcategory":"Financial Services",
            "type":"Services"
        },
        {
            "category":"Organizations",
            "subcategory":"Membership Organization",
            "type":"Services"
        }
    ],
    "sg:phone":"+44 1403 210200",
    "sg:postcode":"SW10 9JR",
    "sg:province":"Greater London",
    "sg:tags":[
        "consultant"
    ],
    "wof:name":"Harcourt Property Management & Financial Services Ltd.",
    "wof:placetype":"venue"
},
  "geometry": {"coordinates":[-0.186548,51.487251],"type":"Point"}
}