{
  "type": "Feature",
  "properties": {
    "iso:country":"GB",
    "sg:address":"28 Church Street, Arnold",
    "sg:city":"Nottingham",
    "sg:classifiers":[
        {
            "category":"Health Services",
            "subcategory":"Nursing And Care Facility",
            "type":"Services"
        },
        {
            "category":"Social Services",
            "subcategory":"Retirement Home",
            "type":"Services"
        }
    ],
    "sg:phone":"+44 115 953 5577",
    "sg:postcode":"NG5 8FB",
    "sg:province":"Nottinghamshire",
    "sg:tags":[
        "residential"
    ],
    "wof:name":"Manor Residential Home",
    "wof:placetype":"venue"
},
  "geometry": {"coordinates":[-1.125692,53.009121],"type":"Point"}
}