{
  "type": "Feature",
  "properties": {
    "addr:full":"75 Maxse Rd, Knowle Bristol City of Bristol BS4 2JQ",
    "addr:housenumber":"75",
    "addr:postcode":"bs4 2jq",
    "addr:street":"Maxse Rd",
    "iso:country":"GB",
    "sg:address":"75 Maxse Rd, Knowle",
    "sg:city":"Bristol",
    "sg:classifiers":[
        {
            "category":"Shopping",
            "subcategory":"Pharmacy",
            "type":"Retail Goods"
        }
    ],
    "sg:phone":"+44 117 977 1648",
    "sg:postcode":"BS4 2JQ",
    "sg:province":"City of Bristol",
    "sg:tags":[
        "medicine",
        "therapy"
    ],
    "wof:name":"Brian J Day",
    "wof:placetype":"venue"
},
  "geometry": {"coordinates":[-2.5660049915,51.4358596802],"type":"Point"}
}