{
  "type": "Feature",
  "properties": {
    "addr:full":"92 Normandy Avenue Barnet Hertfordshire EN5 2HS",
    "addr:housenumber":"92",
    "addr:postcode":"en5 2hs",
    "addr:street":"Normandy Avenue",
    "iso:country":"GB",
    "sg:address":"92 Normandy Avenue",
    "sg:city":"Barnet",
    "sg:classifiers":[
        {
            "category":"Travel",
            "subcategory":"Hotels & Motels",
            "type":"Entertainment"
        }
    ],
    "sg:phone":"+44 20 8440 0857",
    "sg:postcode":"EN5 2HS",
    "sg:province":"Hertfordshire",
    "sg:tags":[
        "house",
        "guest"
    ],
    "wof:name":"London Visitors Accommodation Bureau",
    "wof:placetype":"venue"
},
  "geometry": {"coordinates":[-0.200869,51.648632],"type":"Point"}
}