{
  "type": "Feature",
  "properties": {
    "iso:country":"GB",
    "sg:address":"The Street, Newbourne",
    "sg:city":"Woodbridge",
    "sg:classifiers":[
        {
            "category":"Bars & Pubs",
            "type":"Food & Drink"
        }
    ],
    "sg:phone":"+44 1473 736307",
    "sg:postcode":"IP12 4NY",
    "sg:province":"Suffolk",
    "sg:tags":[
        "pubs",
        "inn"
    ],
    "wof:name":"The Fox Inn",
    "wof:placetype":"venue"
},
  "geometry": {"coordinates":[1.319365,52.040615],"type":"Point"}
}