{
  "type": "Feature",
  "properties": {
    "iso:country":"GB",
    "sg:address":"Fifth Floor, 33 Bothwell Street",
    "sg:city":"Glasgow",
    "sg:classifiers":[
        {
            "category":"Wholesale",
            "subcategory":"Medical Equipment & Supplies",
            "type":"Manufacturing & Wholesale Goods"
        }
    ],
    "sg:postcode":"G2 6NL",
    "sg:province":"Glasgow City",
    "sg:tags":[
        "hospital"
    ],
    "wof:name":"Next Century Technology Ltd.",
    "wof:placetype":"venue"
},
  "geometry": {"coordinates":[-4.260342,55.861088],"type":"Point"}
}