{
  "type": "Feature",
  "properties": {
    "addr:full":"The Old Health Centre, Horseman Lane, Copmanthorpe York North Yorkshire YO23 3UA",
    "addr:postcode":"yo23 3ua",
    "addr:street":"Horseman Lane",
    "iso:country":"GB",
    "sg:address":"The Old Health Centre, Horseman Lane, Copmanthorpe",
    "sg:city":"York",
    "sg:classifiers":[
        {
            "category":"Professional",
            "type":"Services"
        }
    ],
    "sg:phone":"+44 1904 709367",
    "sg:postcode":"YO23 3UA",
    "sg:province":"North Yorkshire",
    "sg:tags":[
        "interior",
        "furnishers",
        "designer"
    ],
    "wof:name":"Rossett Design Contracts Ltd.",
    "wof:placetype":"venue"
},
  "geometry": {"coordinates":[-1.1420710087,53.9136734009],"type":"Point"}
}