{
  "type": "Feature",
  "properties": {
    "iso:country":"GB",
    "sg:address":"13 Osborn Road South",
    "sg:city":"Fareham",
    "sg:classifiers":[
        {
            "category":"Professional",
            "subcategory":"Accounting & Tax Preparation",
            "type":"Services"
        }
    ],
    "sg:phone":"+44 1329 822966",
    "sg:postcode":"PO16 7DF",
    "sg:province":"Hampshire",
    "sg:tags":[
        "accountant"
    ],
    "wof:name":"Thomas & Woolven",
    "wof:placetype":"venue"
},
  "geometry": {"coordinates":[-1.182091,50.853706],"type":"Point"}
}