{
  "type": "Feature",
  "properties": {
    "addr:full":"14-15 Lordshill District Centre Southampton Hampshire SO16 8HY",
    "addr:housenumber":"14-15",
    "addr:postcode":"so16 8hy",
    "addr:street":"Lordshill District Centre",
    "iso:country":"GB",
    "sg:address":"14-15 Lordshill District Centre",
    "sg:city":"Southampton",
    "sg:classifiers":[
        {
            "category":"Shopping",
            "subcategory":"News",
            "type":"Retail Goods"
        }
    ],
    "sg:phone":"+44 23 8074 1952",
    "sg:postcode":"SO16 8HY",
    "sg:province":"Hampshire",
    "sg:tags":[
        "newsagent"
    ],
    "wof:name":"Martin the Newsagent",
    "wof:placetype":"venue"
},
  "geometry": {"coordinates":[-1.43321,50.94368],"type":"Point"}
}