{
  "type": "Feature",
  "properties": {
    "addr:full":"33 The Rushes Loughborough Leicestershire LE11 5BG",
    "addr:housenumber":"33",
    "addr:postcode":"le11 5bg",
    "addr:street":"The Rushes",
    "iso:country":"GB",
    "sg:address":"33 The Rushes",
    "sg:city":"Loughborough",
    "sg:classifiers":[
        {
            "category":"Sports & Exercise",
            "subcategory":"Gym",
            "type":"Entertainment"
        }
    ],
    "sg:postcode":"LE11 5BG",
    "sg:province":"Leicestershire",
    "sg:tags":[
        "fitness",
        "health",
        "centre"
    ],
    "wof:name":"The Mill Health & Leisure Club",
    "wof:placetype":"venue"
},
  "geometry": {"coordinates":[-1.210078001,52.7737236023],"type":"Point"}
}