{
  "type": "Feature",
  "properties": {
    "addr:full":"30 Station Road Hinckley Leicestershire LE10 1AW",
    "addr:housenumber":"30",
    "addr:postcode":"le10 1aw",
    "addr:street":"Station Road",
    "iso:country":"GB",
    "sg:address":"30 Station Road",
    "sg:city":"Hinckley",
    "sg:classifiers":[
        {
            "category":"Autos & Motor Vehicles",
            "subcategory":"Automobile Sales",
            "type":"Retail Goods"
        }
    ],
    "sg:phone":"+44 1455 632478",
    "sg:postcode":"LE10 1AW",
    "sg:province":"Leicestershire",
    "sg:tags":[
        "car"
    ],
    "wof:name":"Frank Taylor Ltd.",
    "wof:placetype":"venue"
},
  "geometry": {"coordinates":[-1.372838974,52.5387039185],"type":"Point"}
}