{
  "type": "Feature",
  "properties": {
    "addr:full":"2 Frankley Beeches Road, Northfield Birmingham West Midlands B31 5AA",
    "addr:housenumber":"2",
    "addr:postcode":"b31 5aa",
    "addr:street":"Frankley Beeches Road",
    "iso:country":"GB",
    "sg:address":"2 Frankley Beeches Road, Northfield",
    "sg:city":"Birmingham",
    "sg:classifiers":[
        {
            "category":"Autos & Motor Vehicles",
            "subcategory":"Automobile Sales",
            "type":"Retail Goods"
        }
    ],
    "sg:phone":"+44 121 475 3900",
    "sg:postcode":"B31 5AA",
    "sg:province":"West Midlands",
    "sg:tags":[
        "car"
    ],
    "wof:name":"Bristol Road Garage",
    "wof:placetype":"venue"
},
  "geometry": {"coordinates":[-1.9732350111,52.4125442505],"type":"Point"}
}