{
  "type": "Feature",
  "properties": {
    "addr:full":"7 Castle Canyke Road Bodmin Cornwall PL31 1DX",
    "addr:housenumber":"7",
    "addr:postcode":"pl31 1dx",
    "addr:street":"Castle Canyke Road",
    "iso:country":"GB",
    "sg:address":"7 Castle Canyke Road",
    "sg:city":"Bodmin",
    "sg:classifiers":[
        {
            "category":"Military Area",
            "subcategory":"Coast Guard Base",
            "type":"Public Place"
        },
        {
            "category":"Government",
            "subcategory":"Office",
            "type":"Public Place"
        }
    ],
    "sg:phone":"+44 1208 73183",
    "sg:postcode":"PL31 1DX",
    "sg:province":"Cornwall",
    "sg:tags":[
        "force",
        "armed",
        "reserve"
    ],
    "wof:name":"Cornwall Army Cadet Force",
    "wof:placetype":"venue"
},
  "geometry": {"coordinates":[-4.7144241333,50.4653282166],"type":"Point"}
}