{
  "type": "Feature",
  "properties": {
    "iso:country":"GB",
    "sg:address":"81 Davidson Terrace",
    "sg:city":"Haddington",
    "sg:classifiers":[
        {
            "category":"Professional",
            "subcategory":"Art Services",
            "type":"Services"
        },
        {
            "category":"Building & Trades",
            "subcategory":"Construction",
            "type":"Services"
        }
    ],
    "sg:phone":"+44 1620 824670",
    "sg:postcode":"EH41 3BG",
    "sg:province":"East Lothian",
    "sg:tags":[
        "decorator",
        "painter"
    ],
    "wof:name":"Alec Dodds Painting & Decorating",
    "wof:placetype":"venue"
},
  "geometry": {"coordinates":[-2.7938079834,55.9581336975],"type":"Point"}
}