{
  "type": "Feature",
  "properties": {
    "iso:country":"GB",
    "sg:address":"The Green, Wingrave",
    "sg:city":"Aylesbury",
    "sg:classifiers":[
        {
            "category":"Bars & Pubs",
            "type":"Food & Drink"
        }
    ],
    "sg:phone":"+44 1296 681257",
    "sg:postcode":"HP22 4PD",
    "sg:province":"Buckinghamshire",
    "sg:tags":[
        "pubs",
        "inn"
    ],
    "wof:name":"Inn Business Ltd.",
    "wof:placetype":"venue"
},
  "geometry": {"coordinates":[-0.7706890106,51.8735466003],"type":"Point"}
}