{
  "type": "Feature",
  "properties": {
    "iso:country":"GB",
    "sg:address":"9 Bidder Street, Canning Town",
    "sg:city":"London",
    "sg:classifiers":[
        {
            "category":"Manufacturing",
            "subcategory":"Lumber",
            "type":"Manufacturing & Wholesale Goods"
        }
    ],
    "sg:phone":"+44 20 7511 8400",
    "sg:postcode":"E16 4ST",
    "sg:province":"Greater London",
    "sg:tags":[
        "importer",
        "merchants",
        "agent",
        "timber"
    ],
    "wof:name":"G S M Exclusive Components Ltd.",
    "wof:placetype":"venue"
},
  "geometry": {"coordinates":[0.00564,51.515709],"type":"Point"}
}