{
  "type": "Feature",
  "properties": {
    "iso:country":"GB",
    "sg:address":"100 Upper High Street",
    "sg:city":"Epsom",
    "sg:classifiers":[
        {
            "category":"Taxi",
            "type":"Transportation"
        }
    ],
    "sg:phone":"+44 1372 727275",
    "sg:postcode":"KT17 4RQ",
    "sg:province":"Surrey",
    "sg:tags":[
        "mini",
        "cab"
    ],
    "wof:name":"Call-A-Car",
    "wof:placetype":"venue"
},
  "geometry": {"coordinates":[-0.25743,51.334766],"type":"Point"}
}