{
  "type": "Feature",
  "properties": {
    "addr:full":"69 Stanstead Road, Forest Hill London Greater London SE23 1HQ",
    "addr:housenumber":"69",
    "addr:postcode":"se23 1hq",
    "addr:street":"Stanstead Road",
    "iso:country":"GB",
    "sg:address":"69 Stanstead Road, Forest Hill",
    "sg:city":"London",
    "sg:classifiers":[
        {
            "category":"Building & Trades",
            "subcategory":"Construction",
            "type":"Services"
        }
    ],
    "sg:postcode":"SE23 1HQ",
    "sg:province":"Greater London",
    "sg:tags":[
        "builder"
    ],
    "wof:name":"D R Knight Developments (London) Ltd.",
    "wof:placetype":"venue"
},
  "geometry": {"coordinates":[-0.050338,51.442493],"type":"Point"}
}