{
  "type": "Feature",
  "properties": {
    "iso:country":"GB",
    "sg:address":"Borelli Ho, Borelli Yard",
    "sg:city":"Farnham",
    "sg:classifiers":[
        {
            "category":"Professional",
            "subcategory":"Detective & Security Services",
            "type":"Services"
        }
    ],
    "sg:phone":"+44 1252 733322",
    "sg:postcode":"GU9 7NU",
    "sg:province":"Surrey",
    "sg:tags":[
        "agency"
    ],
    "wof:name":"Hogan & Co",
    "wof:placetype":"venue"
},
  "geometry": {"coordinates":[-0.8008369803,51.2143211365],"type":"Point"}
}