{
  "type": "Feature",
  "properties": {
    "addr:full":"2 Derwen Deg, Station Road Abergavenny Herefordshire NP7 9RG",
    "addr:housenumber":"2",
    "addr:postcode":"np7 9rg",
    "addr:street":"Derwen;Station Road",
    "iso:country":"GB",
    "sg:address":"2 Derwen Deg, Station Road",
    "sg:city":"Abergavenny",
    "sg:classifiers":[
        {
            "category":"Professional",
            "subcategory":"Business Services",
            "type":"Services"
        }
    ],
    "sg:phone":"+44 1873 830415",
    "sg:postcode":"NP7 9RG",
    "sg:province":"Herefordshire",
    "sg:tags":[
        "trade"
    ],
    "wof:name":"Licensed Victuallers (Wales) Ltd.",
    "wof:placetype":"venue"
},
  "geometry": {"coordinates":[-3.066368103,51.8168640137],"type":"Point"}
}