{
  "type": "Feature",
  "properties": {
    "addr:full":"290 Stanton Road Burton-on-trent Derbyshire DE15 9SQ",
    "addr:housenumber":"290",
    "addr:postcode":"de15 9sq",
    "addr:street":"Stanton Road",
    "iso:country":"GB",
    "sg:address":"290 Stanton Road",
    "sg:city":"Burton-on-trent",
    "sg:classifiers":[
        {
            "category":"Autos & Motor Vehicles",
            "subcategory":"Fuel & Gas Station",
            "type":"Retail Goods"
        }
    ],
    "sg:phone":"+44 1283 562054",
    "sg:postcode":"DE15 9SQ",
    "sg:province":"Derbyshire",
    "sg:tags":[
        "petrol",
        "filling"
    ],
    "wof:name":"Murco Petroleum",
    "wof:placetype":"venue"
},
  "geometry": {"coordinates":[-1.612036,52.783005],"type":"Point"}
}