{
  "type": "Feature",
  "properties": {
    "iso:country":"GB",
    "sg:address":"17 Cluny Sq",
    "sg:city":"Southend-on-sea",
    "sg:classifiers":[
        {
            "category":"Farming",
            "subcategory":"Fish & Marine Products",
            "type":"Manufacturing & Wholesale Goods"
        }
    ],
    "sg:postcode":"SS2 4AF",
    "sg:province":"Essex",
    "sg:tags":[
        "fishmonger"
    ],
    "wof:name":"Henleys Butchers",
    "wof:placetype":"venue"
},
  "geometry": {"coordinates":[0.725807,51.550758],"type":"Point"}
}