{
  "type": "Feature",
  "properties": {
    "addr:full":"Blackburn Road, Ribchester Preston Lancashire PR3 3ZQ",
    "addr:postcode":"pr3 3zq",
    "addr:street":"Blackburn Road",
    "iso:country":"GB",
    "sg:address":"Blackburn Road, Ribchester",
    "sg:city":"Preston",
    "sg:classifiers":[
        {
            "category":"Farming",
            "subcategory":"Livestock Farm",
            "type":"Manufacturing & Wholesale Goods"
        }
    ],
    "sg:phone":"+44 1254 878332",
    "sg:postcode":"PR3 3ZQ",
    "sg:province":"Lancashire",
    "sg:tags":[
        "others"
    ],
    "wof:name":"F Walmsley",
    "wof:placetype":"venue"
},
  "geometry": {"coordinates":[-2.5341010094,53.813205719],"type":"Point"}
}