{
  "type": "Feature",
  "properties": {
    "iso:country":"GB",
    "sg:address":"4 Turf La",
    "sg:city":"Oldham",
    "sg:classifiers":[
        {
            "category":"Shopping",
            "subcategory":"Department Store",
            "type":"Retail Goods"
        }
    ],
    "sg:postcode":"OL9 8HL",
    "sg:province":"Lancashire",
    "wof:name":"Carpet Experience",
    "wof:placetype":"venue"
},
  "geometry": {"coordinates":[-2.149335,53.525234],"type":"Point"}
}