{
  "type": "Feature",
  "properties": {
    "iso:country":"GB",
    "sg:address":"Linnell Way, Telford Way Industrial Estate",
    "sg:city":"Kettering",
    "sg:classifiers":[
        {
            "category":"Shopping",
            "subcategory":"Computers & Home Electronics",
            "type":"Retail Goods"
        }
    ],
    "sg:phone":"+44 1302 822833",
    "sg:postcode":"NN16 8PS",
    "sg:province":"Northamptonshire",
    "sg:tags":[
        "electrical"
    ],
    "wof:name":"Cefco Lamps",
    "wof:placetype":"venue"
},
  "geometry": {"coordinates":[-0.7400670052,52.40990448],"type":"Point"}
}