{
  "type": "Feature",
  "properties": {
    "addr:full":"33 Ashcroft Road Newcastle Staffordshire ST5 8EP",
    "addr:housenumber":"33",
    "addr:postcode":"st5 8ep",
    "addr:street":"Ashcroft Road",
    "iso:country":"GB",
    "sg:address":"33 Ashcroft Road",
    "sg:city":"Newcastle",
    "sg:classifiers":[
        {
            "category":"Building & Trades",
            "subcategory":"Construction",
            "type":"Services"
        }
    ],
    "sg:phone":"+44 1782 564926",
    "sg:postcode":"ST5 8EP",
    "sg:province":"Staffordshire",
    "sg:tags":[
        "joiner",
        "carpenter"
    ],
    "wof:name":"Nixon & Pearson",
    "wof:placetype":"venue"
},
  "geometry": {"coordinates":[-2.232217,53.036381],"type":"Point"}
}