{
  "type": "Feature",
  "properties": {
    "addr:full":"183 Bermondsey St London Greater London SE1 3UW",
    "addr:housenumber":"183",
    "addr:postcode":"se1 3uw",
    "addr:street":"Bermondsey St",
    "iso:country":"GB",
    "sg:address":"183 Bermondsey St",
    "sg:city":"London",
    "sg:classifiers":[
        {
            "category":"Shopping",
            "subcategory":"Antiques",
            "type":"Retail Goods"
        }
    ],
    "sg:postcode":"SE1 3UW",
    "sg:province":"Greater London",
    "wof:name":"Antiques Bargain Centre",
    "wof:placetype":"venue"
},
  "geometry": {"coordinates":[-0.081194,51.49971],"type":"Point"}
}