{
  "type": "Feature",
  "properties": {
    "addr:full":"5a The Avenue Chingford Greater London E4 9LB",
    "addr:housenumber":"5a",
    "addr:postcode":"e4 9lb",
    "addr:street":"The Avenue",
    "iso:country":"GB",
    "sg:address":"5a The Avenue",
    "sg:city":"Chingford",
    "sg:classifiers":[
        {
            "category":"Food & Beverages",
            "subcategory":"Groceries & Convenience Stores",
            "type":"Retail Goods"
        }
    ],
    "sg:phone":"+44 20 8527 6436",
    "sg:postcode":"E4 9LB",
    "sg:province":"Greater London",
    "wof:name":"West News",
    "wof:placetype":"venue"
},
  "geometry": {"coordinates":[-0.00013,51.6081047058],"type":"Point"}
}