{
  "type": "Feature",
  "properties": {
    "addr:full":"6 Green Lane, Braughing Ware Hertfordshire SG11 2QG",
    "addr:housenumber":"6",
    "addr:postcode":"sg11 2qg",
    "addr:street":"Green Lane",
    "iso:country":"GB",
    "sg:address":"6 Green Lane, Braughing",
    "sg:city":"Ware",
    "sg:classifiers":[
        {
            "category":"Arena",
            "subcategory":"Sports Club",
            "type":"Entertainment"
        }
    ],
    "sg:postcode":"SG11 2QG",
    "sg:province":"Hertfordshire",
    "wof:name":"Stort Valley Auto Club",
    "wof:placetype":"venue"
},
  "geometry": {"coordinates":[0.030251,51.906544],"type":"Point"}
}