{
  "type": "Feature",
  "properties": {
    "iso:country":"GB",
    "sg:address":"117 High Street",
    "sg:city":"Lowestoft",
    "sg:classifiers":[
        {
            "category":"Wholesale",
            "subcategory":"Books, Periodicals, & Newspapers",
            "type":"Manufacturing & Wholesale Goods"
        }
    ],
    "sg:postcode":"NR32 1HN",
    "sg:province":"Suffolk",
    "sg:tags":[
        "publishing"
    ],
    "wof:name":"Rushmere Publishing",
    "wof:placetype":"venue"
},
  "geometry": {"coordinates":[1.755522,52.480167],"type":"Point"}
}