{
  "type": "Feature",
  "properties": {
    "addr:full":"37 Houndsditch London Greater London EC3A 7DB",
    "addr:housenumber":"37",
    "addr:postcode":"ec3a 7db",
    "addr:street":"Houndsditch",
    "iso:country":"GB",
    "sg:address":"37 Houndsditch",
    "sg:city":"London",
    "sg:classifiers":[
        {
            "category":"Education",
            "subcategory":"Special Training",
            "type":"Public Place"
        }
    ],
    "sg:phone":"+44 20 7444 4000",
    "sg:postcode":"EC3A 7DB",
    "sg:province":"Greater London",
    "sg:tags":[
        "product",
        "centre"
    ],
    "wof:name":"Training for Life Ltd.",
    "wof:placetype":"venue"
},
  "geometry": {"coordinates":[-0.0785510018,51.515045166],"type":"Point"}
}