{
  "type": "Feature",
  "properties": {
    "addr:full":"77 Otley Rd Shipley West Yorkshire BD18 2BJ",
    "addr:housenumber":"77",
    "addr:postcode":"bd18 2bj",
    "addr:street":"Otley Rd",
    "iso:country":"GB",
    "sg:address":"77 Otley Rd",
    "sg:city":"Shipley",
    "sg:classifiers":[
        {
            "category":"Professional",
            "subcategory":"Business Services",
            "type":"Services"
        }
    ],
    "sg:phone":"+44 1274 770252",
    "sg:postcode":"BD18 2BJ",
    "sg:province":"West Yorkshire",
    "sg:tags":[
        "tile",
        "stockist"
    ],
    "wof:name":"Ceramic Tile Importers",
    "wof:placetype":"venue"
},
  "geometry": {"coordinates":[-1.775659,53.831692],"type":"Point"}
}