{
  "type": "Feature",
  "properties": {
    "iso:country":"GB",
    "sg:address":"275 Archway Road",
    "sg:city":"London",
    "sg:classifiers":[
        {
            "category":"Restaurant",
            "type":"Food & Drink"
        }
    ],
    "sg:phone":"+44 20 8348 5385",
    "sg:postcode":"N6 5AA",
    "sg:province":"Greater London",
    "sg:tags":[
        "chinese"
    ],
    "wof:name":"THE WONDERFUL PALACE",
    "wof:placetype":"venue"
},
  "geometry": {"coordinates":[-0.145108,51.576656],"type":"Point"}
}