{
  "type": "Feature",
  "properties": {
    "addr:full":"Shop 1-2 Spring Gardens Narberth Carmarthenshire SA67 7BN",
    "addr:housenumber":"1-2",
    "addr:postcode":"sa67 7bn",
    "addr:street":"Spring Gardens",
    "iso:country":"GB",
    "sg:address":"Shop 1-2 Spring Gardens",
    "sg:city":"Narberth",
    "sg:classifiers":[
        {
            "category":"Food & Beverages",
            "subcategory":"Bakery",
            "type":"Retail Goods"
        }
    ],
    "sg:phone":"+44 1834 861437",
    "sg:postcode":"SA67 7BN",
    "sg:province":"Carmarthenshire",
    "sg:tags":[
        "baker"
    ],
    "wof:name":"Liz's Bakery",
    "wof:placetype":"venue"
},
  "geometry": {"coordinates":[-4.744227,51.80117],"type":"Point"}
}