{
  "type": "Feature",
  "properties": {
    "iso:country":"GB",
    "sg:address":"22 High Street, Wootton Bridge",
    "sg:city":"Ryde",
    "sg:classifiers":[
        {
            "category":"Retail",
            "subcategory":"Repair Shop",
            "type":"Services"
        }
    ],
    "sg:phone":"+44 1983 882758",
    "sg:postcode":"PO33 4PE",
    "sg:province":"Isle of Wight",
    "sg:tags":[
        "radio",
        "television",
        "video"
    ],
    "wof:name":"Havenstreet Electrical Ltd.",
    "wof:placetype":"venue"
},
  "geometry": {"coordinates":[-1.22897,50.725029],"type":"Point"}
}