{
  "type": "Feature",
  "properties": {
    "addr:full":"13 The Walnuts Orpington Kent BR6 0TW",
    "addr:housenumber":"13",
    "addr:postcode":"br6 0tw",
    "addr:street":"The Walnuts Orpington",
    "iso:country":"GB",
    "sg:address":"13 The Walnuts",
    "sg:city":"Orpington",
    "sg:classifiers":[
        {
            "category":"Building & Trades",
            "subcategory":"Plumbing",
            "type":"Services"
        }
    ],
    "sg:phone":"+44 1689 873886",
    "sg:postcode":"BR6 0TW",
    "sg:province":"Kent",
    "sg:tags":[
        "merchant",
        "plumbers'"
    ],
    "wof:name":"The Wholesale Outlet",
    "wof:placetype":"venue"
},
  "geometry": {"coordinates":[0.10062,51.377048],"type":"Point"}
}