{
  "type": "Feature",
  "properties": {
    "addr:full":"49a Queen St, Morley Leeds West Yorkshire LS27 8EE",
    "addr:housenumber":"49a",
    "addr:postcode":"ls27 8ee",
    "addr:street":"Queen St",
    "iso:country":"GB",
    "sg:address":"49a Queen St, Morley",
    "sg:city":"Leeds",
    "sg:classifiers":[
        {
            "category":"Manufacturing",
            "subcategory":"Petroleum Products",
            "type":"Manufacturing & Wholesale Goods"
        }
    ],
    "sg:postcode":"LS27 8EE",
    "sg:province":"West Yorkshire",
    "sg:tags":[
        "double",
        "glazing"
    ],
    "wof:name":"Oakdale Windows Ltd",
    "wof:placetype":"venue"
},
  "geometry": {"coordinates":[-1.602381,53.74757],"type":"Point"}
}