{
  "type": "Feature",
  "properties": {
    "iso:country":"GB",
    "sg:address":"114 High Street",
    "sg:city":"Dover",
    "sg:classifiers":[
        {
            "category":"Shopping",
            "subcategory":"Clothing, Apparel, & Fashions",
            "type":"Retail Goods"
        }
    ],
    "sg:phone":"+44 1304 213138",
    "sg:postcode":"CT16 1EG",
    "sg:province":"Kent",
    "sg:tags":[
        "shop"
    ],
    "wof:name":"Panache Boutique",
    "wof:placetype":"venue"
},
  "geometry": {"coordinates":[1.305398,51.130299],"type":"Point"}
}