{
  "type": "Feature",
  "properties": {
    "addr:full":"Bradgers Hill Road Luton Bedfordshire LU2 7EW",
    "addr:postcode":"lu2 7ew",
    "addr:street":"Bradgers Hill Road",
    "iso:country":"GB",
    "sg:address":"Bradgers Hill Road",
    "sg:city":"Luton",
    "sg:classifiers":[
        {
            "category":"Education",
            "subcategory":"College",
            "type":"Public Place"
        },
        {
            "category":"Education",
            "subcategory":"School",
            "type":"Public Place"
        }
    ],
    "sg:phone":"+44 1582 877500",
    "sg:postcode":"LU2 7EW",
    "sg:province":"Bedfordshire",
    "sg:tags":[
        "local",
        "authority"
    ],
    "sg:website":"http://www.lutonsfc.ac.uk",
    "wof:name":"Luton Sixth Form College",
    "wof:placetype":"venue"
},
  "geometry": {"coordinates":[-0.4112089872,51.9015846252],"type":"Point"}
}