{
  "type": "Feature",
  "properties": {
    "addr:full":"Rockford Road Snodland Kent ME6 5AH",
    "addr:postcode":"me6 5ah",
    "addr:street":"Rockford Road",
    "iso:country":"GB",
    "sg:address":"Rockford Road",
    "sg:city":"Snodland",
    "sg:classifiers":[
        {
            "category":"Professional",
            "subcategory":"Research",
            "type":"Services"
        }
    ],
    "sg:postcode":"ME6 5AH",
    "sg:province":"Kent",
    "sg:tags":[
        "analytical",
        "consulting",
        "chemist"
    ],
    "wof:name":"Eclipse Scientific Ltd.",
    "wof:placetype":"venue"
},
  "geometry": {"coordinates":[0.446165,51.327026],"type":"Point"}
}