{
  "type": "Feature",
  "properties": {
    "addr:full":"2nd Floor, Babbacombe House, 2 Babbacombe Road Bromley Kent BR1 3LW",
    "addr:housenumber":"2nd floor babbacombe house 2",
    "addr:postcode":"br1 3lw",
    "addr:street":"Babbacombe Road",
    "iso:country":"GB",
    "sg:address":"2nd Floor, Babbacombe House, 2 Babbacombe Road",
    "sg:city":"Bromley",
    "sg:classifiers":[
        {
            "category":"Banks & Credit Unions",
            "subcategory":"Financial Services",
            "type":"Services"
        }
    ],
    "sg:phone":"+44 20 8315 5100",
    "sg:postcode":"BR1 3LW",
    "sg:province":"Kent",
    "sg:tags":[
        "consultant"
    ],
    "wof:name":"Lombard Business Finance",
    "wof:placetype":"venue"
},
  "geometry": {"coordinates":[0.0174359996,51.4105834961],"type":"Point"}
}