{
  "type": "Feature",
  "properties": {
    "addr:full":"Sands Lane, Holme-on-spalding-molane York East Riding of Yorkshire YO43 4EX",
    "addr:postcode":"yo43 4ex",
    "addr:street":"Sands Lane",
    "iso:country":"GB",
    "sg:address":"Sands Lane, Holme-on-spalding-molane",
    "sg:city":"York",
    "sg:classifiers":[
        {
            "category":"Food & Beverages",
            "subcategory":"Farmers Market",
            "type":"Retail Goods"
        }
    ],
    "sg:phone":"+44 1430 860301",
    "sg:postcode":"YO43 4EX",
    "sg:province":"East Riding of Yorkshire",
    "sg:tags":[
        "gardener"
    ],
    "wof:name":"B W Seller Sands Lane Nurseries",
    "wof:placetype":"venue"
},
  "geometry": {"coordinates":[-0.6750919819,53.8247642517],"type":"Point"}
}