{
  "type": "Feature",
  "properties": {
    "addr:full":"Ymca, Bonnygate Cupar Fife KY15 4LG",
    "addr:postcode":"ky15 4lg",
    "addr:street":"Bonnygate",
    "iso:country":"GB",
    "sg:address":"Ymca, Bonnygate",
    "sg:city":"Cupar",
    "sg:classifiers":[
        {
            "category":"Education",
            "subcategory":"School",
            "type":"Public Place"
        },
        {
            "category":"Sports & Exercise",
            "subcategory":"Tennis Court",
            "type":"Entertainment"
        }
    ],
    "sg:phone":"+44 1334 657899",
    "sg:postcode":"KY15 4LG",
    "sg:province":"Fife",
    "sg:tags":[
        "activities",
        "based",
        "leisure"
    ],
    "wof:name":"Cupar After School Club",
    "wof:placetype":"venue"
},
  "geometry": {"coordinates":[-3.0117590427,56.3194961548],"type":"Point"}
}