{
  "type": "Feature",
  "properties": {
    "addr:full":"The Holywell Centre, 1 Phipp Street London Greater London EC2A 4PS",
    "addr:housenumber":"1",
    "addr:postcode":"ec2a 4ps",
    "addr:street":"Phipp Street",
    "iso:country":"GB",
    "sg:address":"The Holywell Centre, 1 Phipp Street",
    "sg:city":"London",
    "sg:classifiers":[
        {
            "category":"Shopping",
            "subcategory":"Antiques",
            "type":"Retail Goods"
        }
    ],
    "sg:phone":"+44 20 7739 5738",
    "sg:postcode":"EC2A 4PS",
    "sg:province":"Greater London",
    "wof:name":"Boswell & Davis",
    "wof:placetype":"venue"
},
  "geometry": {"coordinates":[-0.0818200037,51.5236091614],"type":"Point"}
}