{
  "type": "Feature",
  "properties": {
    "iso:country":"GB",
    "sg:address":"Windsor House, 192-194 Stafford St",
    "sg:city":"Walsall",
    "sg:classifiers":[
        {
            "category":"Home & Garden",
            "subcategory":"Home Furnishings",
            "type":"Retail Goods"
        }
    ],
    "sg:phone":"+44 1922 627400",
    "sg:postcode":"WS2 8ED",
    "sg:province":"West Midlands",
    "sg:tags":[
        "loose",
        "cover"
    ],
    "wof:name":"Cosyfit Covers",
    "wof:placetype":"venue"
},
  "geometry": {"coordinates":[-1.985178,52.590099],"type":"Point"}
}