{
  "type": "Feature",
  "properties": {
    "addr:full":"The Warehouse, Cavendish Street Peterborough Cambridgeshire PE1 5EQ",
    "addr:postcode":"pe1 5eq",
    "addr:street":"Cavendish Street",
    "iso:country":"GB",
    "sg:address":"The Warehouse, Cavendish Street",
    "sg:city":"Peterborough",
    "sg:classifiers":[
        {
            "category":"Shopping",
            "subcategory":"Discount & Variety Stores",
            "type":"Retail Goods"
        }
    ],
    "sg:postcode":"PE1 5EQ",
    "sg:province":"Cambridgeshire",
    "sg:tags":[
        "cleaning",
        "supply"
    ],
    "wof:name":"Cleaning Supplies",
    "wof:placetype":"venue"
},
  "geometry": {"coordinates":[-0.2311500013,52.5804214478],"type":"Point"}
}