{
  "type": "Feature",
  "properties": {
    "addr:full":"14 Somerset Gardens London Greater London SE13 7SY",
    "addr:housenumber":"14",
    "addr:postcode":"se13 7sy",
    "addr:street":"Somerset Gardens",
    "iso:country":"GB",
    "sg:address":"14 Somerset Gardens",
    "sg:city":"London",
    "sg:classifiers":[
        {
            "category":"Professional",
            "type":"Services"
        }
    ],
    "sg:phone":"+44 20 8469 3900",
    "sg:postcode":"SE13 7SY",
    "sg:province":"Greater London",
    "sg:tags":[
        "entertainer"
    ],
    "wof:name":"Crowd Pullers",
    "wof:placetype":"venue"
},
  "geometry": {"coordinates":[-0.021077,51.4678],"type":"Point"}
}