{
  "type": "Feature",
  "properties": {
    "addr:full":"Lower Clough Business Centre, Pendle Street, Barrowford Nelson Lancashire BB9 6JD",
    "addr:postcode":"barrowford;bb9 6jd",
    "addr:street":"Lower Clough;Pendle Street",
    "iso:country":"GB",
    "sg:address":"Lower Clough Business Centre, Pendle Street, Barrowford",
    "sg:city":"Nelson",
    "sg:classifiers":[
        {
            "category":"Home & Garden",
            "subcategory":"Home Furnishings",
            "type":"Retail Goods"
        }
    ],
    "sg:postcode":"BB9 6JD",
    "sg:province":"Lancashire",
    "sg:tags":[
        "soft"
    ],
    "wof:name":"Jade Cushions",
    "wof:placetype":"venue"
},
  "geometry": {"coordinates":[-2.2111999989,53.8544807434],"type":"Point"}
}