{
  "type": "Feature",
  "properties": {
    "addr:full":"15 Cross St Ryde Isle of Wight PO33 2AD",
    "addr:housenumber":"15",
    "addr:postcode":"po33 2ad",
    "addr:street":"Cross St",
    "iso:country":"GB",
    "sg:address":"15 Cross St",
    "sg:city":"Ryde",
    "sg:classifiers":[
        {
            "category":"Shopping",
            "subcategory":"Books",
            "type":"Retail Goods"
        }
    ],
    "sg:postcode":"PO33 2AD",
    "sg:province":"Isle of Wight",
    "sg:tags":[
        "bookseller"
    ],
    "wof:name":"Collins,John,Bookshop",
    "wof:placetype":"venue"
},
  "geometry": {"coordinates":[-1.161455,50.729713],"type":"Point"}
}