{
  "type": "Feature",
  "properties": {
    "iso:country":"GB",
    "sg:address":"9-15 Neal St",
    "sg:city":"Holborn",
    "sg:classifiers":[
        {
            "category":"Professional",
            "subcategory":"Art Services",
            "type":"Services"
        }
    ],
    "sg:phone":"+44 20 7379 1110",
    "sg:postcode":"WC2H 9PU",
    "sg:province":"Greater London",
    "sg:tags":[
        "consultant",
        "design"
    ],
    "wof:name":"Society Design",
    "wof:placetype":"venue"
},
  "geometry": {"coordinates":[-0.1245559976,51.5133934021],"type":"Point"}
}