{
  "type": "Feature",
  "properties": {
    "addr:full":"61 William Street, Marston Oxford Oxfordshire OX3 0ES",
    "addr:housenumber":"61",
    "addr:postcode":"ox3 0es",
    "addr:street":"William Street",
    "iso:country":"GB",
    "sg:address":"61 William Street, Marston",
    "sg:city":"Oxford",
    "sg:classifiers":[
        {
            "category":"Building & Trades",
            "subcategory":"Construction",
            "type":"Services"
        }
    ],
    "sg:phone":"+44 1480 356027",
    "sg:postcode":"OX3 0ES",
    "sg:province":"Oxfordshire",
    "sg:tags":[
        "builder"
    ],
    "wof:name":"Pennyfen Ltd.",
    "wof:placetype":"venue"
},
  "geometry": {"coordinates":[-1.232451,51.759659],"type":"Point"}
}