{
  "type": "Feature",
  "properties": {
    "addr:full":"36 Market Place Beverley East Riding of Yorkshire HU17 9AG",
    "addr:housenumber":"36",
    "addr:postcode":"hu17 9ag",
    "addr:street":"Market Place",
    "iso:country":"GB",
    "sg:address":"36 Market Place",
    "sg:city":"Beverley",
    "sg:classifiers":[
        {
            "category":"Education",
            "subcategory":"Special Training",
            "type":"Public Place"
        }
    ],
    "sg:phone":"+44 1723 515777",
    "sg:postcode":"HU17 9AG",
    "sg:province":"East Riding of Yorkshire",
    "sg:tags":[
        "product",
        "centre"
    ],
    "wof:name":"Humberside Youth Association Ltd.",
    "wof:placetype":"venue"
},
  "geometry": {"coordinates":[-0.432449013,53.8428115845],"type":"Point"}
}