{
  "type": "Feature",
  "properties": {
    "iso:country":"GB",
    "sg:address":"15 Gainsborough Close",
    "sg:city":"Cambridge",
    "sg:classifiers":[
        {
            "category":"Professional",
            "subcategory":"Management & Consulting",
            "type":"Services"
        }
    ],
    "sg:phone":"+44 1223 426514",
    "sg:postcode":"CB4 1SY",
    "sg:province":"Cambridgeshire",
    "sg:tags":[
        "conservation"
    ],
    "wof:name":"Council for the Protection of Rural England",
    "wof:placetype":"venue"
},
  "geometry": {"coordinates":[0.1483010054,52.2280387878],"type":"Point"}
}