{
  "type": "Feature",
  "properties": {
    "iso:country":"GB",
    "sg:address":"2 Carlton Street",
    "sg:city":"Castleford",
    "sg:classifiers":[
        {
            "category":"Shopping",
            "subcategory":"Used Merchandise",
            "type":"Retail Goods"
        }
    ],
    "sg:phone":"+44 1977 552195",
    "sg:postcode":"WF10 1AY",
    "sg:province":"West Yorkshire",
    "sg:tags":[
        "shop",
        "second-hand"
    ],
    "wof:name":"Castleford Sale & Exchange",
    "wof:placetype":"venue"
},
  "geometry": {"coordinates":[-1.349321,53.726967],"type":"Point"}
}