{
  "type": "Feature",
  "properties": {
    "iso:country":"GB",
    "sg:address":"21 Lodge La",
    "sg:city":"Grays",
    "sg:classifiers":[
        {
            "category":"Retail",
            "subcategory":"Repair Shop",
            "type":"Services"
        }
    ],
    "sg:postcode":"RM17 5RY",
    "sg:province":"Essex",
    "sg:tags":[
        "maintenance"
    ],
    "wof:name":"John Mullin Construction Ltd",
    "wof:placetype":"venue"
},
  "geometry": {"coordinates":[0.340523,51.488922],"type":"Point"}
}