{
  "type": "Feature",
  "properties": {
    "iso:country":"GB",
    "sg:address":"Parkdyke",
    "sg:city":"Stirling",
    "sg:classifiers":[
        {
            "category":"Autos & Motor Vehicles",
            "subcategory":"Motorcycle Sales",
            "type":"Retail Goods"
        }
    ],
    "sg:phone":"+44 1786 448448",
    "sg:postcode":"FK7 9LR",
    "sg:province":"Falkirk",
    "sg:tags":[
        "chauffeur",
        "driven",
        "car"
    ],
    "wof:name":"All-Ways",
    "wof:placetype":"venue"
},
  "geometry": {"coordinates":[-3.960714,56.112595],"type":"Point"}
}