{
  "type": "Feature",
  "properties": {
    "addr:full":"14 The Tithings, Kibworth Leicester Leicestershire LE8 0PU",
    "addr:housenumber":"14",
    "addr:postcode":"le8 0pu",
    "addr:street":"The Tithings Kibworth",
    "iso:country":"GB",
    "sg:address":"14 The Tithings, Kibworth",
    "sg:city":"Leicester",
    "sg:classifiers":[
        {
            "category":"Wholesale",
            "subcategory":"Vending Machines",
            "type":"Manufacturing & Wholesale Goods"
        }
    ],
    "sg:phone":"+44 116 279 6027",
    "sg:postcode":"LE8 0PU",
    "sg:province":"Leicestershire",
    "sg:tags":[
        "sale"
    ],
    "wof:name":"Supa Snacks (Vending) Ltd.",
    "wof:placetype":"venue"
},
  "geometry": {"coordinates":[-0.989264,52.5397],"type":"Point"}
}