{
  "type": "Feature",
  "properties": {
    "addr:full":"Rose Tree Cottage, Thropton Morpeth Northumberland NE65 7NA",
    "addr:postcode":"ne65 7na",
    "iso:country":"GB",
    "sg:address":"Rose Tree Cottage, Thropton",
    "sg:city":"Morpeth",
    "sg:classifiers":[
        {
            "category":"Professional",
            "subcategory":"Art Services",
            "type":"Services"
        }
    ],
    "sg:phone":"+44 1669 621272",
    "sg:postcode":"NE65 7NA",
    "sg:province":"Northumberland",
    "sg:tags":[
        "graphic",
        "designer"
    ],
    "wof:name":"J T D Design",
    "wof:placetype":"venue"
},
  "geometry": {"coordinates":[-1.955799,55.314335],"type":"Point"}
}