{
  "type": "Feature",
  "properties": {
    "iso:country":"GB",
    "sg:address":"33 Stow Hill",
    "sg:city":"Newport",
    "sg:classifiers":[
        {
            "category":"Organizations",
            "subcategory":"Membership Organization",
            "type":"Services"
        }
    ],
    "sg:phone":"+44 1633 254741",
    "sg:postcode":"NP20 1JH",
    "sg:province":"Newport",
    "sg:tags":[
        "club"
    ],
    "wof:name":"GREAT WESTERN RAILWAYS STAFF ASSOCIATION",
    "wof:placetype":"venue"
},
  "geometry": {"coordinates":[-2.996715,51.585945],"type":"Point"}
}