{
  "type": "Feature",
  "properties": {
    "addr:full":"23 Station Rd Hinckley Leicestershire LE10 1AW",
    "addr:housenumber":"23",
    "addr:postcode":"le10 1aw",
    "addr:street":"Station Rd",
    "iso:country":"GB",
    "sg:address":"23 Station Rd",
    "sg:city":"Hinckley",
    "sg:classifiers":[
        {
            "category":"Professional",
            "subcategory":"Accounting & Tax Preparation",
            "type":"Services"
        }
    ],
    "sg:phone":"+44 1455 251150",
    "sg:postcode":"LE10 1AW",
    "sg:province":"Leicestershire",
    "sg:tags":[
        "accountant"
    ],
    "wof:name":"Newby Castleman",
    "wof:placetype":"venue"
},
  "geometry": {"coordinates":[-1.3726760149,52.5388412476],"type":"Point"}
}