{
  "type": "Feature",
  "properties": {
    "addr:full":"Rivehill Farm, Kingswells Aberdeen Aberdeen City AB15 8RP",
    "addr:postcode":"ab15 8rp",
    "addr:street":"Kingswells",
    "iso:country":"GB",
    "sg:address":"Rivehill Farm, Kingswells",
    "sg:city":"Aberdeen",
    "sg:classifiers":[
        {
            "category":"Home & Garden",
            "subcategory":"Garden Supply",
            "type":"Retail Goods"
        },
        {
            "category":"Farming",
            "subcategory":"Livestock Farm",
            "type":"Manufacturing & Wholesale Goods"
        }
    ],
    "sg:phone":"+44 1224 790377",
    "sg:postcode":"AB15 8RP",
    "sg:province":"Aberdeen City",
    "sg:tags":[
        "bulb",
        "grower",
        "others"
    ],
    "wof:name":"S A & G Beattie",
    "wof:placetype":"venue"
},
  "geometry": {"coordinates":[-2.226133,57.155704],"type":"Point"}
}