{
  "type": "Feature",
  "properties": {
    "addr:full":"74 Gillygate York North Yorkshire YO31 7EQ",
    "addr:housenumber":"74",
    "addr:postcode":"yo31 7eq",
    "addr:street":"Gillygate York",
    "iso:country":"GB",
    "sg:address":"74 Gillygate",
    "sg:city":"York",
    "sg:classifiers":[
        {
            "category":"Food & Beverages",
            "subcategory":"Bakery",
            "type":"Retail Goods"
        }
    ],
    "sg:phone":"+44 1904 625184",
    "sg:postcode":"YO31 7EQ",
    "sg:province":"North Yorkshire",
    "sg:tags":[
        "baker"
    ],
    "wof:name":"Oven Gloves",
    "wof:placetype":"venue"
},
  "geometry": {"coordinates":[-1.0831899643,53.9646835327],"type":"Point"}
}