{
  "type": "Feature",
  "properties": {
    "iso:country":"GB",
    "sg:address":"196 Sandcross Lane",
    "sg:city":"Reigate",
    "sg:classifiers":[
        {
            "category":"Professional",
            "type":"Services"
        },
        {
            "category":"Professional",
            "subcategory":"Art Services",
            "type":"Services"
        }
    ],
    "sg:phone":"+44 1737 222656",
    "sg:postcode":"RH2 8HQ",
    "sg:province":"Surrey",
    "sg:tags":[
        "interior",
        "furnishers",
        "designer"
    ],
    "wof:name":"Marketplace Concepts",
    "wof:placetype":"venue"
},
  "geometry": {"coordinates":[-0.212785,51.225258],"type":"Point"}
}