{
  "type": "Feature",
  "properties": {
    "iso:country":"GB",
    "sg:address":"Church Lane",
    "sg:city":"East Grinstead",
    "sg:classifiers":[
        {
            "category":"Organizations",
            "subcategory":"Non-profit Organization",
            "type":"Services"
        }
    ],
    "sg:phone":"+44 1342 326561",
    "sg:postcode":"RH19 3AZ",
    "sg:province":"East Sussex",
    "sg:tags":[
        "organisation",
        "voluntary",
        "charity"
    ],
    "wof:name":"Sackville College",
    "wof:placetype":"venue"
},
  "geometry": {"coordinates":[-0.004798,51.125332],"type":"Point"}
}