{
  "type": "Feature",
  "properties": {
    "addr:full":"Beacon Tree Plaza Reading Berkshire RG2 0BP",
    "addr:postcode":"rg2 0bp",
    "iso:country":"GB",
    "sg:address":"Beacon Tree Plaza",
    "sg:city":"Reading",
    "sg:classifiers":[
        {
            "category":"Professional",
            "subcategory":"Computer Services",
            "type":"Services"
        }
    ],
    "sg:postcode":"RG2 0BP",
    "sg:province":"Berkshire",
    "sg:tags":[
        "consultant"
    ],
    "wof:name":"Avenir (U K) Ltd",
    "wof:placetype":"venue"
},
  "geometry": {"coordinates":[-0.9800500274,51.4319610596],"type":"Point"}
}