{
  "type": "Feature",
  "properties": {
    "iso:country":"GB",
    "sg:address":"Shalimar, Victoria, Roche",
    "sg:city":"St Austell",
    "sg:classifiers":[
        {
            "category":"Military Area",
            "subcategory":"Army Base",
            "type":"Public Place"
        }
    ],
    "sg:postcode":"PL26 8LT",
    "sg:province":"Cornwall",
    "sg:tags":[
        "transportation",
        "livestock"
    ],
    "wof:name":"P T Jones",
    "wof:placetype":"venue"
},
  "geometry": {"coordinates":[-4.833774,50.40641],"type":"Point"}
}