{
  "type": "Feature",
  "properties": {
    "iso:country":"GB",
    "sg:address":"Waulkmill, Strachan",
    "sg:city":"Banchory",
    "sg:classifiers":[
        {
            "category":"Farming",
            "subcategory":"Farm",
            "type":"Manufacturing & Wholesale Goods"
        }
    ],
    "sg:phone":"+44 1330 850640",
    "sg:postcode":"AB31 6NS",
    "sg:province":"Aberdeen City",
    "sg:tags":[
        "mixed",
        "crop"
    ],
    "wof:name":"M F Horsfall",
    "wof:placetype":"venue"
},
  "geometry": {"coordinates":[-2.535373,57.020695],"type":"Point"}
}