{
  "type": "Feature",
  "properties": {
    "addr:full":"Marsh Grn Library, Harrow Road, Marsh Grn Wigan Lancashire WN5 0QL",
    "addr:postcode":"wn5 0ql",
    "addr:street":"Marsh;Harrow Road Marsh Grn",
    "iso:country":"GB",
    "sg:address":"Marsh Grn Library, Harrow Road, Marsh Grn",
    "sg:city":"Wigan",
    "sg:classifiers":[
        {
            "category":"Professional",
            "subcategory":"Computer Services",
            "type":"Services"
        }
    ],
    "sg:phone":"+44 1942 221881",
    "sg:postcode":"WN5 0QL",
    "sg:province":"Lancashire",
    "sg:tags":[
        "information"
    ],
    "wof:name":"The Guidance Shop",
    "wof:placetype":"venue"
},
  "geometry": {"coordinates":[-2.665546,53.551373],"type":"Point"}
}