{
  "type": "Feature",
  "properties": {
    "iso:country":"GB",
    "sg:address":"23-25 Garfield Street",
    "sg:city":"Hawick",
    "sg:classifiers":[
        {
            "category":"Building & Trades",
            "subcategory":"Construction",
            "type":"Services"
        }
    ],
    "sg:phone":"+44 1450 370760",
    "sg:postcode":"TD9 9HA",
    "sg:province":"Cumbria",
    "sg:tags":[
        "joiner",
        "carpenter"
    ],
    "wof:name":"A & J Robson",
    "wof:placetype":"venue"
},
  "geometry": {"coordinates":[-2.7849640846,55.4219741821],"type":"Point"}
}