{
  "type": "Feature",
  "properties": {
    "iso:country":"GB",
    "sg:address":"17 Second Avenue",
    "sg:city":"Walton On Thames",
    "sg:classifiers":[
        {
            "category":"Communications",
            "type":"Services"
        }
    ],
    "sg:phone":"+44 1932 246179",
    "sg:postcode":"KT12 2HW",
    "sg:province":"Surrey",
    "sg:tags":[
        "telecommunication"
    ],
    "wof:name":"Telefax Plus",
    "wof:placetype":"venue"
},
  "geometry": {"coordinates":[-0.4068560004,51.3919410706],"type":"Point"}
}