{
  "type": "Feature",
  "properties": {
    "addr:full":"75 Hollway Rd Bristol City of Bristol BS14 8PG",
    "addr:housenumber":"75",
    "addr:postcode":"bs14 8pg",
    "addr:street":"Hollway Rd",
    "iso:country":"GB",
    "sg:address":"75 Hollway Rd",
    "sg:city":"Bristol",
    "sg:classifiers":[
        {
            "category":"Social Services",
            "subcategory":"Retirement Home",
            "type":"Services"
        }
    ],
    "sg:phone":"+44 1275 833998",
    "sg:postcode":"BS14 8PG",
    "sg:province":"City of Bristol",
    "sg:tags":[
        "residential",
        "care"
    ],
    "wof:name":"Bowmead Residential Care",
    "wof:placetype":"venue"
},
  "geometry": {"coordinates":[-2.5463459492,51.4119148254],"type":"Point"}
}