{
  "type": "Feature",
  "properties": {
    "addr:full":"33a High Street, Stony Stratford Milton Keynes Buckinghamshire MK11 1AA",
    "addr:housenumber":"33a",
    "addr:postcode":"mk11 1aa",
    "addr:street":"High Street",
    "iso:country":"GB",
    "sg:address":"33a High Street, Stony Stratford",
    "sg:city":"Milton Keynes",
    "sg:classifiers":[
        {
            "category":"Professional",
            "subcategory":"Accounting & Tax Preparation",
            "type":"Services"
        }
    ],
    "sg:phone":"+44 1908 305270",
    "sg:postcode":"MK11 1AA",
    "sg:province":"Buckinghamshire",
    "sg:tags":[
        "accountant"
    ],
    "wof:name":"Gallaghers",
    "wof:placetype":"venue"
},
  "geometry": {"coordinates":[-0.8522660136,52.0563850403],"type":"Point"}
}