{
  "type": "Feature",
  "properties": {
    "iso:country":"GB",
    "sg:address":"Ketton Road",
    "sg:city":"Stockton-on-tees",
    "sg:classifiers":[
        {
            "category":"Community Center",
            "subcategory":"Youth",
            "type":"Public Place"
        }
    ],
    "sg:phone":"+44 1642 393533",
    "sg:postcode":"TS19 8BU",
    "sg:province":"Durham",
    "sg:tags":[
        "organisation",
        "centre"
    ],
    "wof:name":"Hardwick Youth Centre",
    "wof:placetype":"venue"
},
  "geometry": {"coordinates":[-1.345083952,54.5852813721],"type":"Point"}
}