{
  "type": "Feature",
  "properties": {
    "addr:full":"15 St Austins Gro Sheringham Norfolk NR26 8DF",
    "addr:housenumber":"15",
    "addr:postcode":"nr26 8df",
    "addr:street":"St Austins Gro",
    "iso:country":"GB",
    "sg:address":"15 St Austins Gro",
    "sg:city":"Sheringham",
    "sg:classifiers":[
        {
            "category":"Professional",
            "subcategory":"Computer Services",
            "type":"Services"
        }
    ],
    "sg:phone":"+44 1298 71267",
    "sg:postcode":"NR26 8DF",
    "sg:province":"Norfolk",
    "sg:tags":[
        "system",
        "software"
    ],
    "wof:name":"Freeford Computer Services Ltd.",
    "wof:placetype":"venue"
},
  "geometry": {"coordinates":[1.222334981,52.9415626526],"type":"Point"}
}