{
  "type": "Feature",
  "properties": {
    "iso:country":"GB",
    "sg:address":"Unit 12, Dunton Close",
    "sg:city":"Derby",
    "sg:classifiers":[
        {
            "category":"Retail",
            "subcategory":"Auto Repair",
            "type":"Services"
        }
    ],
    "sg:phone":"+44 1332 370660",
    "sg:postcode":"DE21 6XB",
    "sg:province":"Derbyshire",
    "sg:tags":[
        "engine",
        "car",
        "specialist"
    ],
    "wof:name":"Replacement Engines",
    "wof:placetype":"venue"
},
  "geometry": {"coordinates":[-1.464779,52.922699],"type":"Point"}
}