{
  "type": "Feature",
  "properties": {
    "addr:full":"1 Tollcross Road Glasgow Glasgow City G31 4UG",
    "addr:housenumber":"1",
    "addr:postcode":"g31 4ug",
    "addr:street":"Tollcross Road",
    "iso:country":"GB",
    "sg:address":"1 Tollcross Road",
    "sg:city":"Glasgow",
    "sg:classifiers":[
        {
            "category":"Professional",
            "subcategory":"Lawyer & Legal Services",
            "type":"Services"
        }
    ],
    "sg:phone":"+44 141 556 6651",
    "sg:postcode":"G31 4UG",
    "sg:province":"Glasgow City",
    "sg:tags":[
        "solicitor"
    ],
    "wof:name":"Finlayson Wise",
    "wof:placetype":"venue"
},
  "geometry": {"coordinates":[-4.1971611977,55.8513374329],"type":"Point"}
}