{
  "type": "Feature",
  "properties": {
    "addr:full":"21 Station Square, Petts Wood Orpington Kent BR5 1LY",
    "addr:housenumber":"21",
    "addr:postcode":"br5 1ly",
    "addr:street":"Station Square Petts",
    "iso:country":"GB",
    "sg:address":"21 Station Square, Petts Wood",
    "sg:city":"Orpington",
    "sg:classifiers":[
        {
            "category":"Manufacturing",
            "subcategory":"Wood Products",
            "type":"Manufacturing & Wholesale Goods"
        }
    ],
    "sg:phone":"+44 1689 873055",
    "sg:postcode":"BR5 1LY",
    "sg:province":"Kent",
    "sg:tags":[
        "maker",
        "cabinet"
    ],
    "wof:name":"Westway Kitchens Ltd.",
    "wof:placetype":"venue"
},
  "geometry": {"coordinates":[0.0757649988,51.389339447],"type":"Point"}
}