{
  "type": "Feature",
  "properties": {
    "addr:full":"32 Meeting House Lane Brighton East Sussex BN1 1HB",
    "addr:housenumber":"32",
    "addr:postcode":"bn1 1hb",
    "addr:street":"Meeting House Lane",
    "iso:country":"GB",
    "sg:address":"32 Meeting House Lane",
    "sg:city":"Brighton",
    "sg:classifiers":[
        {
            "category":"Shopping",
            "subcategory":"Comic Books",
            "type":"Retail Goods"
        }
    ],
    "sg:phone":"+44 1273 220272",
    "sg:postcode":"BN1 1HB",
    "sg:province":"East Sussex",
    "sg:tags":[
        "jeweller"
    ],
    "wof:name":"The Gallery Jewellers",
    "wof:placetype":"venue"
},
  "geometry": {"coordinates":[-0.1405110061,50.8218612671],"type":"Point"}
}