{
  "type": "Feature",
  "properties": {
    "addr:full":"Ardlair, High Street, Conon Bridge Dingwall Highland IV7 8AZ",
    "addr:postcode":"iv7 8az",
    "addr:street":"High Street",
    "iso:country":"GB",
    "sg:address":"Ardlair, High Street, Conon Bridge",
    "sg:city":"Dingwall",
    "sg:classifiers":[
        {
            "category":"Retail",
            "subcategory":"Veterinary Services",
            "type":"Services"
        }
    ],
    "sg:phone":"+44 1349 861203",
    "sg:postcode":"IV7 8AZ",
    "sg:province":"Highland",
    "sg:tags":[
        "surgeon",
        "activity"
    ],
    "wof:name":"Conanvet",
    "wof:placetype":"venue"
},
  "geometry": {"coordinates":[-4.4363689423,57.5658493042],"type":"Point"}
}