{
  "type": "Feature",
  "properties": {
    "addr:full":"93 Market Street Stalybridge Greater Manchester SK15 2AA",
    "addr:housenumber":"93",
    "addr:postcode":"sk15 2aa",
    "addr:street":"Market Street",
    "iso:country":"GB",
    "sg:address":"93 Market Street",
    "sg:city":"Stalybridge",
    "sg:classifiers":[
        {
            "category":"Personal",
            "subcategory":"Barber",
            "type":"Services"
        }
    ],
    "sg:phone":"+44 161 304 8552",
    "sg:postcode":"SK15 2AA",
    "sg:province":"Greater Manchester",
    "sg:tags":[
        "men's",
        "hairdresser"
    ],
    "wof:name":"Brian Hudson Hairdressing",
    "wof:placetype":"venue"
},
  "geometry": {"coordinates":[-2.057029,53.48381],"type":"Point"}
}