{
  "type": "Feature",
  "properties": {
    "iso:country":"GB",
    "sg:address":"1 & 2 Victoria Square",
    "sg:city":"Holsworthy",
    "sg:classifiers":[
        {
            "category":"Home & Garden",
            "subcategory":"Home Furnishings",
            "type":"Retail Goods"
        }
    ],
    "sg:postcode":"EX22 6AD",
    "sg:province":"Cornwall",
    "sg:tags":[
        "blind",
        "curtain",
        "fitting"
    ],
    "wof:name":"Holsworthy Drapes",
    "wof:placetype":"venue"
},
  "geometry": {"coordinates":[-4.353941,50.81023],"type":"Point"}
}