{
  "type": "Feature",
  "properties": {
    "addr:full":"28 Horsefair Street, Charlton Kings Cheltenham Gloucestershire GL53 8JE",
    "addr:housenumber":"28",
    "addr:postcode":"gl53 8je",
    "addr:street":"Horsefair Street",
    "iso:country":"GB",
    "sg:address":"28 Horsefair Street, Charlton Kings",
    "sg:city":"Cheltenham",
    "sg:classifiers":[
        {
            "category":"Professional",
            "subcategory":"Art Services",
            "type":"Services"
        }
    ],
    "sg:postcode":"GL53 8JE",
    "sg:province":"Gloucestershire",
    "sg:tags":[
        "graphic",
        "designer"
    ],
    "wof:name":"Browns",
    "wof:placetype":"venue"
},
  "geometry": {"coordinates":[-2.0545730591,51.8831481934],"type":"Point"}
}