{
  "type": "Feature",
  "properties": {
    "iso:country":"GB",
    "sg:address":"96 Ael-y-bryn",
    "sg:city":"Cardiff",
    "sg:classifiers":[
        {
            "category":"Professional",
            "subcategory":"Art Services",
            "type":"Services"
        }
    ],
    "sg:phone":"+44 29 2073 2049",
    "sg:postcode":"CF23 9LL",
    "sg:province":"Cardiff",
    "sg:tags":[
        "photographer"
    ],
    "wof:name":"Eye Level Photographic",
    "wof:placetype":"venue"
},
  "geometry": {"coordinates":[-3.155379,51.511551],"type":"Point"}
}