{
  "type": "Feature",
  "properties": {
    "iso:country":"GB",
    "sg:address":"42 Whalley Banks",
    "sg:city":"Blackburn",
    "sg:classifiers":[
        {
            "category":"Food & Beverages",
            "subcategory":"Candy",
            "type":"Retail Goods"
        },
        {
            "category":"Food & Beverages",
            "subcategory":"Bakery",
            "type":"Retail Goods"
        }
    ],
    "sg:phone":"+44 1254 264669",
    "sg:postcode":"BB2 1NU",
    "sg:province":"Lancashire",
    "sg:tags":[
        "confectioner",
        "baker"
    ],
    "wof:name":"Wholemeal",
    "wof:placetype":"venue"
},
  "geometry": {"coordinates":[-2.491857,53.744102],"type":"Point"}
}