{
  "type": "Feature",
  "properties": {
    "addr:full":"Jms House, Railway Rd Leigh Lancashire WN7 4AN",
    "addr:postcode":"wn7 4an",
    "addr:street":"Railway Rd",
    "iso:country":"GB",
    "sg:address":"Jms House, Railway Rd",
    "sg:city":"Leigh",
    "sg:classifiers":[
        {
            "category":"Professional",
            "type":"Services"
        }
    ],
    "sg:phone":"+44 1942 269372",
    "sg:postcode":"WN7 4AN",
    "sg:province":"Lancashire",
    "sg:tags":[
        "shopfitters"
    ],
    "wof:name":"JMS Design",
    "wof:placetype":"venue"
},
  "geometry": {"coordinates":[-2.5259010792,53.4981079102],"type":"Point"}
}