{
  "type": "Feature",
  "properties": {
    "addr:full":"Suite 410, Lonsdale Ho Birmingham West Midlands B1 1QU",
    "addr:housenumber":"suite 410",
    "addr:postcode":"b1 1qu",
    "iso:country":"GB",
    "sg:address":"Suite 410, Lonsdale Ho",
    "sg:city":"Birmingham",
    "sg:classifiers":[
        {
            "category":"Home & Garden",
            "subcategory":"Hardware",
            "type":"Retail Goods"
        },
        {
            "category":"Building & Trades",
            "subcategory":"Construction",
            "type":"Services"
        }
    ],
    "sg:postcode":"B1 1QU",
    "sg:province":"West Midlands",
    "sg:tags":[
        "supplier",
        "paint",
        "cladding",
        "installers"
    ],
    "wof:name":"Superior Exterior Coatings Ltd",
    "wof:placetype":"venue"
},
  "geometry": {"coordinates":[-1.908604,52.478596],"type":"Point"}
}