{
  "type": "Feature",
  "properties": {
    "addr:full":"20 Norwich Rd Norwich Norfolk NR10 3LB",
    "addr:housenumber":"20",
    "addr:postcode":"nr10 3lb",
    "addr:street":"Norwich Rd",
    "iso:country":"GB",
    "sg:address":"20 Norwich Rd",
    "sg:city":"Norwich",
    "sg:classifiers":[
        {
            "category":"Health Services",
            "subcategory":"Doctor",
            "type":"Services"
        }
    ],
    "sg:phone":"+44 1603 898235",
    "sg:postcode":"NR10 3LB",
    "sg:province":"Norfolk",
    "sg:tags":[
        "practitioners"
    ],
    "wof:name":"Daykin, S M",
    "wof:placetype":"venue"
},
  "geometry": {"coordinates":[1.2820899487,52.6909294128],"type":"Point"}
}