{
  "type": "Feature",
  "properties": {
    "addr:full":"22 Reabrook Rd Birmingham West Midlands B31 4EP",
    "addr:housenumber":"22",
    "addr:postcode":"b31 4ep",
    "addr:street":"Reabrook Rd",
    "iso:country":"GB",
    "sg:address":"22 Reabrook Rd",
    "sg:city":"Birmingham",
    "sg:classifiers":[
        {
            "category":"Taxi",
            "type":"Transportation"
        }
    ],
    "sg:phone":"+44 121 411 1313",
    "sg:postcode":"B31 4EP",
    "sg:province":"West Midlands",
    "sg:tags":[
        "mini",
        "cab"
    ],
    "wof:name":"Southern Line Cars",
    "wof:placetype":"venue"
},
  "geometry": {"coordinates":[-1.978417,52.397804],"type":"Point"}
}