{
  "type": "Feature",
  "properties": {
    "iso:country":"GB",
    "sg:address":"147 Thorne Road",
    "sg:city":"Doncaster",
    "sg:classifiers":[
        {
            "category":"Health Services",
            "subcategory":"Doctor",
            "type":"Services"
        },
        {
            "category":"Health Services",
            "subcategory":"Health Practitioner",
            "type":"Services"
        }
    ],
    "sg:phone":"+44 1302 366258",
    "sg:postcode":"DN2 5BH",
    "sg:province":"South Yorkshire",
    "sg:tags":[
        "physiotherapist",
        "practitioners"
    ],
    "wof:name":"R NEILL",
    "wof:placetype":"venue"
},
  "geometry": {"coordinates":[-1.114199996,53.5308113098],"type":"Point"}
}