{
  "type": "Feature",
  "properties": {
    "addr:full":"107 Gloucester Road Croydon Surrey CR0 2DN",
    "addr:housenumber":"107",
    "addr:postcode":"cr0 2dn",
    "addr:street":"Gloucester Road",
    "iso:country":"GB",
    "sg:address":"107 Gloucester Road",
    "sg:city":"Croydon",
    "sg:classifiers":[
        {
            "category":"Retail",
            "subcategory":"Auto Repair",
            "type":"Services"
        }
    ],
    "sg:phone":"+44 20 8684 3264",
    "sg:postcode":"CR0 2DN",
    "sg:province":"Surrey",
    "sg:tags":[
        "modification",
        "garage"
    ],
    "wof:name":"G W Services",
    "wof:placetype":"venue"
},
  "geometry": {"coordinates":[-0.0896499977,51.3849411011],"type":"Point"}
}