{
  "type": "Feature",
  "properties": {
    "addr:full":"Suite 312 Trelawney House, The Dock Felixstowe Suffolk IP11 3GE",
    "addr:housenumber":"suite 312 trelawney house the",
    "addr:postcode":"ip11 3ge",
    "addr:street":"Felixstowe",
    "iso:country":"GB",
    "sg:address":"Suite 312 Trelawney House, The Dock",
    "sg:city":"Felixstowe",
    "sg:classifiers":[
        {
            "category":"Freight",
            "type":"Transportation"
        }
    ],
    "sg:phone":"+44 1394 674353",
    "sg:postcode":"IP11 3GE",
    "sg:province":"Suffolk",
    "sg:tags":[
        "overseas",
        "forwarders",
        "shipping",
        "removal"
    ],
    "wof:name":"Anglia Forwarding Ltd.",
    "wof:placetype":"venue"
},
  "geometry": {"coordinates":[1.3271579742,51.9555931091],"type":"Point"}
}