{
  "type": "Feature",
  "properties": {
    "addr:full":"13 Hawthorne Road Godalming Surrey GU7 2NE",
    "addr:housenumber":"13",
    "addr:postcode":"gu7 2ne",
    "addr:street":"Hawthorne Road",
    "iso:country":"GB",
    "sg:address":"13 Hawthorne Road",
    "sg:city":"Godalming",
    "sg:classifiers":[
        {
            "category":"Autos & Motor Vehicles",
            "subcategory":"Fuel & Gas Station",
            "type":"Retail Goods"
        }
    ],
    "sg:postcode":"GU7 2NE",
    "sg:province":"Surrey",
    "sg:tags":[
        "aga",
        "cooker"
    ],
    "wof:name":"M N Nichols",
    "wof:placetype":"venue"
},
  "geometry": {"coordinates":[-0.63062,51.176121],"type":"Point"}
}