{
  "type": "Feature",
  "properties": {
    "iso:country":"GB",
    "sg:address":"U P R High Street",
    "sg:city":"Epsom",
    "sg:classifiers":[
        {
            "category":"Professional",
            "subcategory":"Computer Services",
            "type":"Services"
        }
    ],
    "sg:phone":"+44 1372 817091",
    "sg:postcode":"KT17 4RS",
    "sg:province":"Surrey",
    "sg:tags":[
        "aided",
        "design"
    ],
    "wof:name":"Top Cad Ltd.",
    "wof:placetype":"venue"
},
  "geometry": {"coordinates":[-0.257844,51.334854],"type":"Point"}
}