{
  "type": "Feature",
  "properties": {
    "iso:country":"GB",
    "sg:address":"Unit 32, Cornwallis House, Howard Chase",
    "sg:city":"Basildon",
    "sg:classifiers":[
        {
            "category":"Communications",
            "type":"Services"
        }
    ],
    "sg:phone":"+44 1268 274600",
    "sg:postcode":"SS14 3BB",
    "sg:province":"Essex",
    "sg:tags":[
        "audio-visual"
    ],
    "wof:name":"Time-line",
    "wof:placetype":"venue"
},
  "geometry": {"coordinates":[0.454581,51.581951],"type":"Point"}
}