{
  "type": "Feature",
  "properties": {
    "iso:country":"GB",
    "sg:address":"1 Dashwood Avenue",
    "sg:city":"High Wycombe",
    "sg:classifiers":[
        {
            "category":"Fast Food",
            "type":"Food & Drink"
        }
    ],
    "sg:phone":"+44 1494 531286",
    "sg:postcode":"HP12 3DN",
    "sg:province":"Buckinghamshire",
    "sg:tags":[
        "away",
        "take"
    ],
    "wof:name":"New Hong Kong House",
    "wof:placetype":"venue"
},
  "geometry": {"coordinates":[-0.768083,51.633064],"type":"Point"}
}