{
  "type": "Feature",
  "properties": {
    "addr:full":"I C G House, Station App, Oldfield Lane North Greenford Greater London UB6 0AL",
    "addr:postcode":"ub6 0al",
    "addr:street":"C;Oldfield Lane North",
    "iso:country":"GB",
    "sg:address":"I C G House, Station App, Oldfield Lane North",
    "sg:city":"Greenford",
    "sg:classifiers":[
        {
            "category":"Home & Garden",
            "subcategory":"Household Appliances",
            "type":"Retail Goods"
        }
    ],
    "sg:phone":"+44 20 8575 6112",
    "sg:postcode":"UB6 0AL",
    "sg:province":"Greater London",
    "sg:tags":[
        "domestic",
        "oven",
        "microwave"
    ],
    "wof:name":"Algar Domestic Appliance Engineers",
    "wof:placetype":"venue"
},
  "geometry": {"coordinates":[-0.339769,51.551765],"type":"Point"}
}