{
  "type": "Feature",
  "properties": {
    "addr:full":"6 Pine Avenue West Wickham Kent BR4 0LW",
    "addr:housenumber":"6",
    "addr:postcode":"br4 0lw",
    "addr:street":"Pine Avenue",
    "iso:country":"GB",
    "sg:address":"6 Pine Avenue",
    "sg:city":"West Wickham",
    "sg:classifiers":[
        {
            "category":"Professional",
            "subcategory":"Computer Services",
            "type":"Services"
        }
    ],
    "sg:postcode":"BR4 0LW",
    "sg:province":"Kent",
    "sg:tags":[
        "consultant"
    ],
    "wof:name":"Christopher Taylor",
    "wof:placetype":"venue"
},
  "geometry": {"coordinates":[-0.019297,51.379776001],"type":"Point"}
}