{
  "type": "Feature",
  "properties": {
    "addr:full":"143 Wincheap Canterbury Kent CT1 3SE",
    "addr:housenumber":"143",
    "addr:postcode":"ct1 3se",
    "addr:street":"Wincheap Canterbury",
    "iso:country":"GB",
    "sg:address":"143 Wincheap",
    "sg:city":"Canterbury",
    "sg:classifiers":[
        {
            "category":"Retail",
            "subcategory":"Repair Shop",
            "type":"Services"
        },
        {
            "category":"Shopping",
            "subcategory":"Used Merchandise",
            "type":"Retail Goods"
        }
    ],
    "sg:phone":"+44 1227 764007",
    "sg:postcode":"CT1 3SE",
    "sg:province":"Kent",
    "sg:tags":[
        "sale",
        "second-hand"
    ],
    "wof:name":"Bits 'N' Pieces",
    "wof:placetype":"venue"
},
  "geometry": {"coordinates":[1.067937,51.271656],"type":"Point"}
}