{
  "type": "Feature",
  "properties": {
    "iso:country":"GB",
    "sg:address":"Blendon Road",
    "sg:city":"Bexley",
    "sg:classifiers":[
        {
            "category":"Bars & Pubs",
            "type":"Food & Drink"
        }
    ],
    "sg:phone":"+44 20 8298 9841",
    "sg:postcode":"DA5 1BX",
    "sg:province":"Kent",
    "sg:tags":[
        "pubs",
        "inn"
    ],
    "wof:name":"Three Blackbirds",
    "wof:placetype":"venue"
},
  "geometry": {"coordinates":[0.1203449965,51.4480934143],"type":"Point"}
}