{
  "type": "Feature",
  "properties": {
    "addr:full":"Unit 16 Elswick Way South Shields Tyne and Wear NE34 0QW",
    "addr:housenumber":"unit 16",
    "addr:postcode":"ne34 0qw",
    "addr:street":"Elswick Way",
    "iso:country":"GB",
    "sg:address":"Unit 16 Elswick Way",
    "sg:city":"South Shields",
    "sg:classifiers":[
        {
            "category":"Manufacturing",
            "subcategory":"Petroleum Products",
            "type":"Manufacturing & Wholesale Goods"
        }
    ],
    "sg:phone":"+44 191 454 8103",
    "sg:postcode":"NE34 0QW",
    "sg:province":"Tyne and Wear",
    "sg:tags":[
        "double",
        "glazing"
    ],
    "wof:name":"Select UK Ltd",
    "wof:placetype":"venue"
},
  "geometry": {"coordinates":[-1.4329799414,54.9761009216],"type":"Point"}
}