{
  "type": "Feature",
  "properties": {
    "iso:country":"GB",
    "sg:address":"Criftin Farm, Catwick Lane, Long Riston",
    "sg:city":"Hull",
    "sg:classifiers":[
        {
            "category":"Farming",
            "subcategory":"Livestock Farm",
            "type":"Manufacturing & Wholesale Goods"
        }
    ],
    "sg:phone":"+44 1964 562314",
    "sg:postcode":"HU11 5JR",
    "sg:province":"East Riding of Yorkshire",
    "sg:tags":[
        "others"
    ],
    "wof:name":"Kirkwood & Son",
    "wof:placetype":"venue"
},
  "geometry": {"coordinates":[-0.2886730134,53.8647384644],"type":"Point"}
}