{
  "type": "Feature",
  "properties": {
    "addr:full":"The Corner House, Soulby Kirkby Stephen Cumbria CA17 4PJ",
    "addr:postcode":"ca17 4pj",
    "iso:country":"GB",
    "sg:address":"The Corner House, Soulby",
    "sg:city":"Kirkby Stephen",
    "sg:classifiers":[
        {
            "category":"Professional",
            "subcategory":"Accounting & Tax Preparation",
            "type":"Services"
        }
    ],
    "sg:postcode":"CA17 4PJ",
    "sg:province":"Cumbria",
    "sg:tags":[
        "accountant"
    ],
    "wof:name":"John H Broster",
    "wof:placetype":"venue"
},
  "geometry": {"coordinates":[-2.348623,54.472717],"type":"Point"}
}