{
  "type": "Feature",
  "properties": {
    "addr:full":"Unit 5 Wharf Buildings, Wharf Terrace, Madeley Heath Crewe Cheshire CW3 9LW",
    "addr:housenumber":"unit 5",
    "addr:postcode":"cw3 9lw",
    "addr:street":"Wharf Buildings Wharf Terrace",
    "iso:country":"GB",
    "sg:address":"Unit 5 Wharf Buildings, Wharf Terrace, Madeley Heath",
    "sg:city":"Crewe",
    "sg:classifiers":[
        {
            "category":"Home & Garden",
            "subcategory":"Building Materials",
            "type":"Retail Goods"
        }
    ],
    "sg:phone":"+44 1782 750740",
    "sg:postcode":"CW3 9LW",
    "sg:province":"Cheshire",
    "sg:tags":[
        "roofing",
        "rafter",
        "beams"
    ],
    "wof:name":"Duncan Beech",
    "wof:placetype":"venue"
},
  "geometry": {"coordinates":[-2.3201088905,53.0078239441],"type":"Point"}
}