{
  "type": "Feature",
  "properties": {
    "addr:full":"Court Ho, Walliscote Rd Weston Super Mare Somerset BS23 1UX",
    "addr:postcode":"bs23 1ux",
    "addr:street":"Court;Walliscote Rd",
    "iso:country":"GB",
    "sg:address":"Court Ho, Walliscote Rd",
    "sg:city":"Weston Super Mare",
    "sg:classifiers":[
        {
            "category":"Government",
            "subcategory":"Court House",
            "type":"Public Place"
        }
    ],
    "sg:phone":"+44 1934 621503",
    "sg:postcode":"BS23 1UX",
    "sg:province":"Somerset",
    "wof:name":"Woodspring Magistrates Court",
    "wof:placetype":"venue"
},
  "geometry": {"coordinates":[-2.9763290882,51.3470077515],"type":"Point"}
}