{
  "type": "Feature",
  "properties": {
    "iso:country":"GB",
    "sg:address":"38 Ormiston Gro",
    "sg:city":"London",
    "sg:classifiers":[
        {
            "category":"Professional",
            "subcategory":"Management & Consulting",
            "type":"Services"
        }
    ],
    "sg:phone":"+44 20 8740 5001",
    "sg:postcode":"W12 0JT",
    "sg:province":"Greater London",
    "sg:tags":[
        "sport"
    ],
    "wof:name":"Brompton Leisure Consultants Ltd.",
    "wof:placetype":"venue"
},
  "geometry": {"coordinates":[-0.243089,51.510792],"type":"Point"}
}