{
  "type": "Feature",
  "properties": {
    "iso:country":"GB",
    "sg:address":"Champion Court, Henlow Drive",
    "sg:city":"Dursley",
    "sg:classifiers":[
        {
            "category":"Social Services",
            "subcategory":"Retirement Home",
            "type":"Services"
        },
        {
            "category":"Organizations",
            "subcategory":"Community Association",
            "type":"Services"
        }
    ],
    "sg:phone":"+44 1453 544953",
    "sg:postcode":"GL11 4BE",
    "sg:province":"Gloucestershire",
    "sg:tags":[
        "accomodation",
        "housing",
        "sheltered",
        "society"
    ],
    "wof:name":"TOUCHSTONE HOUSING ASSOCIATION LTD",
    "wof:placetype":"venue"
},
  "geometry": {"coordinates":[-2.353284,51.67952],"type":"Point"}
}