{
  "type": "Feature",
  "properties": {
    "addr:full":"Abbey Close Paisley Renfrewshire PA1 1JG",
    "addr:postcode":"pa1 1jg",
    "addr:street":"Abbey Close",
    "iso:country":"GB",
    "sg:address":"Abbey Close",
    "sg:city":"Paisley",
    "sg:classifiers":[
        {
            "category":"Professional",
            "type":"Services"
        },
        {
            "category":"Place Of Worship",
            "type":"Public Place"
        }
    ],
    "sg:postcode":"PA1 1JG",
    "sg:province":"Renfrewshire",
    "sg:tags":[
        "entertainer"
    ],
    "wof:name":"Paisley Abbey",
    "wof:placetype":"venue"
},
  "geometry": {"coordinates":[-4.421143,55.844906],"type":"Point"}
}