{
  "type": "Feature",
  "properties": {
    "addr:full":"Unit 17 Smeaton Road, West Portway Andover Hampshire SP10 3LF",
    "addr:housenumber":"unit 17",
    "addr:postcode":"sp10 3lf",
    "addr:street":"Smeaton Road West Portway",
    "iso:country":"GB",
    "sg:address":"Unit 17 Smeaton Road, West Portway",
    "sg:city":"Andover",
    "sg:classifiers":[
        {
            "category":"Retail",
            "subcategory":"Auto Repair",
            "type":"Services"
        }
    ],
    "sg:phone":"+44 1264 332588",
    "sg:postcode":"SP10 3LF",
    "sg:province":"Hampshire",
    "sg:tags":[
        "modification",
        "garage"
    ],
    "wof:name":"Boarhant Garage",
    "wof:placetype":"venue"
},
  "geometry": {"coordinates":[-1.516355,51.216507],"type":"Point"}
}