{
  "type": "Feature",
  "properties": {
    "addr:full":"1st Floor, Queensgate, 121 Suffolk Street Birmingham West Midlands B1 1LX",
    "addr:housenumber":"121",
    "addr:postcode":"b1 1lx",
    "addr:street":"Queensgate;Suffolk Street",
    "iso:country":"GB",
    "sg:address":"1st Floor, Queensgate, 121 Suffolk Street",
    "sg:city":"Birmingham",
    "sg:classifiers":[
        {
            "category":"Bars & Pubs",
            "subcategory":"Nightclub",
            "type":"Food & Drink"
        }
    ],
    "sg:postcode":"B1 1LX",
    "sg:province":"West Midlands",
    "sg:tags":[
        "warehouse",
        "club"
    ],
    "wof:name":"Moneyclub Distribution Ltd.",
    "wof:placetype":"venue"
},
  "geometry": {"coordinates":[-1.908604,52.478596],"type":"Point"}
}