{
  "type": "Feature",
  "properties": {
    "iso:country":"GB",
    "sg:address":"Unit B Dawley Brook, Wartell Bank",
    "sg:city":"Kingswinford",
    "sg:classifiers":[
        {
            "category":"Professional",
            "subcategory":"Employment Agencies",
            "type":"Services"
        }
    ],
    "sg:phone":"+44 1384 401453",
    "sg:postcode":"DY6 7AS",
    "sg:province":"Staffordshire",
    "sg:tags":[
        "agricultural",
        "advice"
    ],
    "wof:name":"Shepherd & Norton Pressing Ltd",
    "wof:placetype":"venue"
},
  "geometry": {"coordinates":[-2.1676740646,52.495803833],"type":"Point"}
}