{
  "type": "Feature",
  "properties": {
    "addr:full":"Hopkins Farm, Lower Tysoe Warwick Warwickshire CV35 0BN",
    "addr:postcode":"cv35 0bn",
    "addr:street":"Lower Tysoe",
    "iso:country":"GB",
    "sg:address":"Hopkins Farm, Lower Tysoe",
    "sg:city":"Warwick",
    "sg:classifiers":[
        {
            "category":"Farming",
            "subcategory":"Livestock Farm",
            "type":"Manufacturing & Wholesale Goods"
        }
    ],
    "sg:postcode":"CV35 0BN",
    "sg:province":"Warwickshire",
    "sg:tags":[
        "others"
    ],
    "wof:name":"J Matthews",
    "wof:placetype":"venue"
},
  "geometry": {"coordinates":[-1.50317204,52.1048431396],"type":"Point"}
}