{
  "type": "Feature",
  "properties": {
    "iso:country":"GB",
    "sg:address":"34 Stamford Road, Lees",
    "sg:city":"Oldham",
    "sg:classifiers":[
        {
            "category":"Health Services",
            "subcategory":"Nursing And Care Facility",
            "type":"Services"
        }
    ],
    "sg:phone":"+44 161 624 4594",
    "sg:postcode":"OL4 3LH",
    "sg:province":"Lancashire",
    "sg:tags":[
        "home"
    ],
    "wof:name":"Oakdene Residential Care Home",
    "wof:placetype":"venue"
},
  "geometry": {"coordinates":[-2.0674829483,53.5432319641],"type":"Point"}
}