{
  "type": "Feature",
  "properties": {
    "iso:country":"GB",
    "sg:address":"Everglades, Baunton",
    "sg:city":"Cirencester",
    "sg:classifiers":[
        {
            "category":"Building & Trades",
            "subcategory":"Landscaping Services",
            "type":"Services"
        }
    ],
    "sg:postcode":"GL7 7BB",
    "sg:province":"Gloucestershire",
    "sg:tags":[
        "pond",
        "aquarium"
    ],
    "wof:name":"Everglades Aquatic Products",
    "wof:placetype":"venue"
},
  "geometry": {"coordinates":[-1.9664809704,51.7386550903],"type":"Point"}
}