{
  "type": "Feature",
  "properties": {
    "addr:full":"87 Backhold Lane, Siddal Halifax West Yorkshire HX3 9EJ",
    "addr:housenumber":"87",
    "addr:postcode":"hx3 9ej",
    "addr:street":"Backhold Lane",
    "iso:country":"GB",
    "sg:address":"87 Backhold Lane, Siddal",
    "sg:city":"Halifax",
    "sg:classifiers":[
        {
            "category":"Building & Trades",
            "subcategory":"Construction",
            "type":"Services"
        }
    ],
    "sg:phone":"+44 1422 364682",
    "sg:postcode":"HX3 9EJ",
    "sg:province":"West Yorkshire",
    "sg:tags":[
        "roofing"
    ],
    "wof:name":"J & B Property Repairs",
    "wof:placetype":"venue"
},
  "geometry": {"coordinates":[-1.8517210484,53.7008018494],"type":"Point"}
}