{
  "type": "Feature",
  "properties": {
    "addr:full":"11 Stonepail Road, Gatley Cheadle Cheshire SK8 4EZ",
    "addr:housenumber":"11",
    "addr:postcode":"sk8 4ez",
    "addr:street":"Stonepail Road;Cheadle",
    "iso:country":"GB",
    "sg:address":"11 Stonepail Road, Gatley",
    "sg:city":"Cheadle",
    "sg:classifiers":[
        {
            "category":"Personal",
            "subcategory":"Beauty Salon",
            "type":"Services"
        }
    ],
    "sg:phone":"+44 161 428 1932",
    "sg:postcode":"SK8 4EZ",
    "sg:province":"Cheshire",
    "sg:tags":[
        "unisex",
        "hairdresser"
    ],
    "wof:name":"Howards Hair & Beauty",
    "wof:placetype":"venue"
},
  "geometry": {"coordinates":[-2.240221,53.391308],"type":"Point"}
}