{
  "type": "Feature",
  "properties": {
    "addr:full":"Vaughan Road Wirral Merseyside CH45 1LH",
    "addr:postcode":"ch45 1lh",
    "addr:street":"Vaughan Road",
    "iso:country":"GB",
    "sg:address":"Vaughan Road",
    "sg:city":"Wirral",
    "sg:classifiers":[
        {
            "category":"Education",
            "subcategory":"School",
            "type":"Public Place"
        }
    ],
    "sg:phone":"+44 151 639 3869",
    "sg:postcode":"CH45 1LH",
    "sg:province":"Merseyside",
    "sg:tags":[
        "local",
        "authority"
    ],
    "wof:name":"New Brighton Primary School",
    "wof:placetype":"venue"
},
  "geometry": {"coordinates":[-3.0408799648,53.4335594177],"type":"Point"}
}