{
  "type": "Feature",
  "properties": {
    "addr:full":"Phantassie East Linton East Lothian EH40 3DF",
    "addr:postcode":"eh40 3df",
    "iso:country":"GB",
    "sg:address":"Phantassie",
    "sg:city":"East Linton",
    "sg:classifiers":[
        {
            "category":"Professional",
            "subcategory":"Printing & Photocopies",
            "type":"Services"
        }
    ],
    "sg:phone":"+44 1620 860239",
    "sg:postcode":"EH40 3DF",
    "sg:province":"East Lothian",
    "sg:tags":[
        "process",
        "screen",
        "printer"
    ],
    "wof:name":"Clouty Designs",
    "wof:placetype":"venue"
},
  "geometry": {"coordinates":[-2.655973,55.986298],"type":"Point"}
}