{
  "type": "Feature",
  "properties": {
    "iso:country":"GB",
    "sg:address":"110 Whitchurch Rd,",
    "sg:city":"Cardiff",
    "sg:classifiers":[
        {
            "category":"Manufacturing",
            "subcategory":"Rubber & Plastics",
            "type":"Manufacturing & Wholesale Goods"
        }
    ],
    "sg:postcode":"CF14 3LY",
    "sg:province":"Cardiff",
    "sg:tags":[
        "product"
    ],
    "wof:name":"Pipe Joist Clip Co Ltd",
    "wof:placetype":"venue"
},
  "geometry": {"coordinates":[-3.18779,51.50106],"type":"Point"}
}