{
  "type": "Feature",
  "properties": {
    "addr:full":"New Dwelling, Kingswood Welshpool Shropshire SY21 8TT",
    "addr:postcode":"sy21 8tt",
    "iso:country":"GB",
    "sg:address":"New Dwelling, Kingswood",
    "sg:city":"Welshpool",
    "sg:classifiers":[
        {
            "category":"Building & Trades",
            "subcategory":"Plumbing",
            "type":"Services"
        }
    ],
    "sg:phone":"+44 1938 580349",
    "sg:postcode":"SY21 8TT",
    "sg:province":"Shropshire",
    "sg:tags":[
        "central",
        "heating"
    ],
    "wof:name":"The Oil Man",
    "wof:placetype":"venue"
},
  "geometry": {"coordinates":[-3.145203,52.66119],"type":"Point"}
}