{
  "type": "Feature",
  "properties": {
    "addr:full":"77 Richmond Park Crescent Sheffield South Yorkshire S13 8HF",
    "addr:housenumber":"77",
    "addr:postcode":"s13 8hf",
    "addr:street":"Richmond Park Crescent",
    "iso:country":"GB",
    "sg:address":"77 Richmond Park Crescent",
    "sg:city":"Sheffield",
    "sg:classifiers":[
        {
            "category":"Building & Trades",
            "subcategory":"Plumbing",
            "type":"Services"
        }
    ],
    "sg:phone":"+44 114 244 4705",
    "sg:postcode":"S13 8HF",
    "sg:province":"South Yorkshire",
    "sg:tags":[
        "central",
        "heating"
    ],
    "wof:name":"D Nugent",
    "wof:placetype":"venue"
},
  "geometry": {"coordinates":[-1.39884,53.375778],"type":"Point"}
}