{
  "type": "Feature",
  "properties": {
    "iso:country":"GB",
    "sg:address":"17 Oldfield Road",
    "sg:city":"Salford",
    "sg:classifiers":[
        {
            "category":"Cafe",
            "type":"Food & Drink"
        }
    ],
    "sg:phone":"+44 161 819 1920",
    "sg:postcode":"M5 4NE",
    "sg:province":"Greater Manchester",
    "sg:tags":[
        "tea",
        "snack",
        "bar",
        "room"
    ],
    "wof:name":"Michael Moran",
    "wof:placetype":"venue"
},
  "geometry": {"coordinates":[-2.264315,53.482712],"type":"Point"}
}