{
  "type": "Feature",
  "properties": {
    "addr:full":"Wern Garage, Gilfachrheda New Quay Ceredigion SA45 9ST",
    "addr:postcode":"sa45 9st",
    "iso:country":"GB",
    "sg:address":"Wern Garage, Gilfachrheda",
    "sg:city":"New Quay",
    "sg:classifiers":[
        {
            "category":"Retail",
            "subcategory":"Auto Repair",
            "type":"Services"
        }
    ],
    "sg:phone":"+44 1545 580531",
    "sg:postcode":"SA45 9ST",
    "sg:province":"Ceredigion",
    "sg:tags":[
        "car",
        "specialist",
        "customizing"
    ],
    "wof:name":"Performance Tyres",
    "wof:placetype":"venue"
},
  "geometry": {"coordinates":[-4.3607897758,52.2136726379],"type":"Point"}
}