{
  "type": "Feature",
  "properties": {
    "addr:full":"Redruth Business Centre, School La Redruth Cornwall TR15 2DU",
    "addr:postcode":"tr15 2du",
    "addr:street":"La Redruth",
    "iso:country":"GB",
    "sg:address":"Redruth Business Centre, School La",
    "sg:city":"Redruth",
    "sg:classifiers":[
        {
            "category":"Professional",
            "type":"Services"
        }
    ],
    "sg:postcode":"TR15 2DU",
    "sg:province":"Cornwall",
    "sg:tags":[
        "specialist",
        "coating"
    ],
    "wof:name":"Westpoint Specialist Coatings Ltd",
    "wof:placetype":"venue"
},
  "geometry": {"coordinates":[-5.229434,50.23251],"type":"Point"}
}