{
  "type": "Feature",
  "properties": {
    "addr:full":"6 Deans Service Industries, St Andrews Way, Deans Livingston West Lothian EH54 8QH",
    "addr:housenumber":"6",
    "addr:postcode":"eh54 8qh",
    "addr:street":"Deans;St Andrews Way",
    "iso:country":"GB",
    "sg:address":"6 Deans Service Industries, St Andrews Way, Deans",
    "sg:city":"Livingston",
    "sg:classifiers":[
        {
            "category":"Shopping",
            "subcategory":"Crafts & Fabrics",
            "type":"Retail Goods"
        }
    ],
    "sg:phone":"+44 1506 497248",
    "sg:postcode":"EH54 8QH",
    "sg:province":"West Lothian",
    "sg:tags":[
        "material",
        "art"
    ],
    "wof:name":"Beautiful Craft Ceramics",
    "wof:placetype":"venue"
},
  "geometry": {"coordinates":[-3.5600988865,55.9046897888],"type":"Point"}
}