{
  "type": "Feature",
  "properties": {
    "addr:full":"157-159 London Road Camberley Berkshire GU15 3JS",
    "addr:housenumber":"157-159",
    "addr:postcode":"gu15 3js",
    "addr:street":"London Road",
    "iso:country":"GB",
    "sg:address":"157-159 London Road",
    "sg:city":"Camberley",
    "sg:classifiers":[
        {
            "category":"Wholesale",
            "subcategory":"Sporting Goods",
            "type":"Manufacturing & Wholesale Goods"
        },
        {
            "category":"Shopping",
            "subcategory":"Discount & Variety Stores",
            "type":"Retail Goods"
        }
    ],
    "sg:phone":"+44 1276 61550",
    "sg:postcode":"GU15 3JS",
    "sg:province":"Berkshire",
    "sg:tags":[
        "supplier",
        "equipment",
        "surplus",
        "camping"
    ],
    "sg:website":"http://www.hmsupplies.com",
    "wof:name":"H M Supplies Ltd",
    "wof:placetype":"venue"
},
  "geometry": {"coordinates":[-0.747252,51.339291],"type":"Point"}
}