{
  "type": "Feature",
  "properties": {
    "iso:country":"GB",
    "sg:address":"59 Silversea Drive",
    "sg:city":"Westcliff On Sea",
    "sg:classifiers":[
        {
            "category":"Organizations",
            "subcategory":"Non-profit Organization",
            "type":"Services"
        }
    ],
    "sg:phone":"+44 1702 477899",
    "sg:postcode":"SS0 9XD",
    "sg:province":"Essex",
    "sg:tags":[
        "organisation",
        "voluntary",
        "charity"
    ],
    "wof:name":"National Federation of the Blind",
    "wof:placetype":"venue"
},
  "geometry": {"coordinates":[0.674268,51.547375],"type":"Point"}
}