{
  "type": "Feature",
  "properties": {
    "iso:country":"GB",
    "sg:address":"Homerton High St, Kenworthy Rd",
    "sg:city":"Hackney",
    "sg:classifiers":[
        {
            "category":"Farming",
            "subcategory":"Nursery",
            "type":"Manufacturing & Wholesale Goods"
        }
    ],
    "sg:phone":"+44 20 8985 8006",
    "sg:postcode":"E9 6BE",
    "sg:province":"Greater London",
    "sg:tags":[
        "creche"
    ],
    "wof:name":"Hackney Roundabout Creche",
    "wof:placetype":"venue"
},
  "geometry": {"coordinates":[-0.038384,51.54911],"type":"Point"}
}