{
  "type": "Feature",
  "properties": {
    "addr:full":"40 Eldon Gardens Newcastle Upon Tyne Tyne and Wear NE1 7RA",
    "addr:housenumber":"40",
    "addr:postcode":"ne1 7ra",
    "addr:street":"Eldon Gardens",
    "iso:country":"GB",
    "sg:address":"40 Eldon Gardens",
    "sg:city":"Newcastle Upon Tyne",
    "sg:classifiers":[
        {
            "category":"Shopping",
            "subcategory":"Antiques",
            "type":"Retail Goods"
        }
    ],
    "sg:phone":"+44 191 261 2232",
    "sg:postcode":"NE1 7RA",
    "sg:province":"Tyne and Wear",
    "wof:name":"Linen Lace & Bygone Crafts Antiques",
    "wof:placetype":"venue"
},
  "geometry": {"coordinates":[-1.7070660591,54.9823303223],"type":"Point"}
}