{
  "type": "Feature",
  "properties": {
    "addr:full":"171-173 Crayford Road Dartford Kent DA1 4HA",
    "addr:postcode":"171-173;da1 4ha",
    "addr:street":"Crayford Road",
    "iso:country":"GB",
    "sg:address":"171-173 Crayford Road",
    "sg:city":"Dartford",
    "sg:classifiers":[
        {
            "category":"Home & Garden",
            "subcategory":"Home Furnishings",
            "type":"Retail Goods"
        }
    ],
    "sg:postcode":"DA1 4HA",
    "sg:province":"Kent",
    "sg:tags":[
        "blind",
        "curtain",
        "fitting"
    ],
    "wof:name":"Curtain & Wool Centre",
    "wof:placetype":"venue"
},
  "geometry": {"coordinates":[0.179497,51.451084],"type":"Point"}
}