{
  "type": "Feature",
  "properties": {
    "addr:full":"3 Church Street Cardiff Cardiff CF10 1BG",
    "addr:housenumber":"3",
    "addr:postcode":"cf10 1bg",
    "addr:street":"Church Street",
    "iso:country":"GB",
    "sg:address":"3 Church Street",
    "sg:city":"Cardiff",
    "sg:classifiers":[
        {
            "category":"Cafe",
            "type":"Food & Drink"
        }
    ],
    "sg:postcode":"CF10 1BG",
    "sg:province":"Cardiff",
    "sg:tags":[
        "tea",
        "room"
    ],
    "wof:name":"Truffles Tea Room",
    "wof:placetype":"venue"
},
  "geometry": {"coordinates":[-3.179677,51.480354],"type":"Point"}
}