{
  "type": "Feature",
  "properties": {
    "addr:full":"1 Poole Road Wimborne Dorset BH21 1QA",
    "addr:housenumber":"1",
    "addr:postcode":"bh21 1qa",
    "addr:street":"Poole Road",
    "iso:country":"GB",
    "sg:address":"1 Poole Road",
    "sg:city":"Wimborne",
    "sg:classifiers":[
        {
            "category":"Community Center",
            "subcategory":"Senior",
            "type":"Public Place"
        },
        {
            "category":"Professional",
            "subcategory":"Business Services",
            "type":"Services"
        }
    ],
    "sg:phone":"+44 1202 841212",
    "sg:postcode":"BH21 1QA",
    "sg:province":"Dorset",
    "sg:tags":[
        "operator",
        "stall",
        "market"
    ],
    "wof:name":"Wimborne Market",
    "wof:placetype":"venue"
},
  "geometry": {"coordinates":[-1.9842129946,50.7979316711],"type":"Point"}
}