{
  "type": "Feature",
  "properties": {
    "iso:country":"GB",
    "sg:address":"Redwither Complex",
    "sg:city":"Wrexham",
    "sg:classifiers":[
        {
            "category":"Social Services",
            "type":"Services"
        }
    ],
    "sg:phone":"+44 1978 660271",
    "sg:postcode":"LL13 9UE",
    "sg:province":"Wrexham",
    "wof:name":"Redwrither Business Centre",
    "wof:placetype":"venue"
},
  "geometry": {"coordinates":[-2.91579,53.039108],"type":"Point"}
}