{
  "type": "Feature",
  "properties": {
    "iso:country":"GB",
    "sg:address":"38 High Street, Catterick",
    "sg:city":"Richmond",
    "sg:classifiers":[
        {
            "category":"Ice Cream",
            "type":"Food & Drink"
        }
    ],
    "sg:phone":"+44 1748 811555",
    "sg:postcode":"DL10 7LD",
    "sg:province":"North Yorkshire",
    "sg:tags":[
        "mnfr"
    ],
    "wof:name":"Northern Select Foods Ltd.",
    "wof:placetype":"venue"
},
  "geometry": {"coordinates":[-1.6317449808,54.3780250549],"type":"Point"}
}