{
  "type": "Feature",
  "properties": {
    "addr:full":"Unit 9 St Marys Arcade Chepstow Gloucestershire NP16 5EU",
    "addr:housenumber":"unit 9 st marys arcade",
    "addr:postcode":"np16 5eu",
    "iso:country":"GB",
    "sg:address":"Unit 9 St Marys Arcade",
    "sg:city":"Chepstow",
    "sg:classifiers":[
        {
            "category":"Fast Food",
            "type":"Food & Drink"
        }
    ],
    "sg:phone":"+44 1291 621112",
    "sg:postcode":"NP16 5EU",
    "sg:province":"Gloucestershire",
    "sg:tags":[
        "away",
        "take"
    ],
    "wof:name":"Baguettes",
    "wof:placetype":"venue"
},
  "geometry": {"coordinates":[-2.6741039753,51.6424598694],"type":"Point"}
}