{
  "type": "Feature",
  "properties": {
    "iso:country":"GB",
    "sg:address":"17-19 Foley St",
    "sg:city":"West End",
    "sg:classifiers":[
        {
            "category":"Communications",
            "type":"Services"
        }
    ],
    "sg:phone":"+44 20 7316 7800",
    "sg:postcode":"W1P 7LH",
    "sg:province":"Hampshire",
    "sg:tags":[
        "audio-visual"
    ],
    "wof:name":"One Ltd",
    "wof:placetype":"venue"
},
  "geometry": {"coordinates":[-0.139824,51.519623],"type":"Point"}
}