{
  "type": "Feature",
  "properties": {
    "addr:full":"Hermitage Lane Mansfield Nottinghamshire NG18 5HD",
    "addr:postcode":"ng18 5hd",
    "addr:street":"Hermitage Lane",
    "iso:country":"GB",
    "sg:address":"Hermitage Lane",
    "sg:city":"Mansfield",
    "sg:classifiers":[
        {
            "category":"Manufacturing",
            "subcategory":"Rubber & Plastics",
            "type":"Manufacturing & Wholesale Goods"
        }
    ],
    "sg:phone":"+44 1623 420525",
    "sg:postcode":"NG18 5HD",
    "sg:province":"Nottinghamshire",
    "sg:tags":[
        "product"
    ],
    "wof:name":"Stokes Coatings Fasteners",
    "wof:placetype":"venue"
},
  "geometry": {"coordinates":[-1.217284,53.131557],"type":"Point"}
}