{
  "type": "Feature",
  "properties": {
    "iso:country":"GB",
    "sg:address":"20 Wickdown Ave",
    "sg:city":"Swindon",
    "sg:classifiers":[
        {
            "category":"Professional",
            "subcategory":"Management & Consulting",
            "type":"Services"
        }
    ],
    "sg:postcode":"SN25 3EA",
    "sg:province":"Wiltshire",
    "sg:tags":[
        "consultant",
        "training"
    ],
    "wof:name":"Hughes,Helen,",
    "wof:placetype":"venue"
},
  "geometry": {"coordinates":[-1.804519,51.583439],"type":"Point"}
}