{
  "type": "Feature",
  "properties": {
    "addr:full":"5 Est Rd,south Humberside Indstl Est, Pyewipe Grimsby Lincolnshire DN31 2TL",
    "addr:housenumber":"5",
    "addr:postcode":"dn31 2tl",
    "addr:street":"Est Rd",
    "iso:country":"GB",
    "sg:address":"5 Est Rd,south Humberside Indstl Est, Pyewipe",
    "sg:city":"Grimsby",
    "sg:classifiers":[
        {
            "category":"Home & Garden",
            "subcategory":"Home Furnishings",
            "type":"Retail Goods"
        }
    ],
    "sg:phone":"+44 1472 345721",
    "sg:postcode":"DN31 2TL",
    "sg:province":"Lincolnshire",
    "sg:tags":[
        "awning",
        "canopy",
        "blinds"
    ],
    "wof:name":"Hall Blinds Ltd",
    "wof:placetype":"venue"
},
  "geometry": {"coordinates":[-0.1113699973,53.5755081177],"type":"Point"}
}