{
  "type": "Feature",
  "properties": {
    "iso:country":"GB",
    "sg:address":"Garden Flat, 11 Belvedere Rd, Westbury Pk",
    "sg:city":"Bristol",
    "sg:classifiers":[
        {
            "category":"Shopping",
            "subcategory":"Department Store",
            "type":"Retail Goods"
        }
    ],
    "sg:postcode":"BS6 7JG",
    "sg:province":"City of Bristol",
    "wof:name":"Birbeck Gallery Ltd",
    "wof:placetype":"venue"
},
  "geometry": {"coordinates":[-2.61257,51.475769],"type":"Point"}
}