{
  "type": "Feature",
  "properties": {
    "addr:full":"Church Lane, Eaton Bray Dunstable Bedfordshire LU6 2DJ",
    "addr:postcode":"lu6 2dj",
    "addr:street":"Church Lane",
    "iso:country":"GB",
    "sg:address":"Church Lane, Eaton Bray",
    "sg:city":"Dunstable",
    "sg:classifiers":[
        {
            "category":"Community Center",
            "type":"Public Place"
        }
    ],
    "sg:phone":"+44 1525 220180",
    "sg:postcode":"LU6 2DJ",
    "sg:province":"Bedfordshire",
    "sg:tags":[
        "centre"
    ],
    "wof:name":"Eaton Bray Hall",
    "wof:placetype":"venue"
},
  "geometry": {"coordinates":[-0.592503,51.876389],"type":"Point"}
}