{
  "type": "Feature",
  "properties": {
    "addr:full":"Nottingham Road Ilkeston Derbyshire DE7 5NX",
    "addr:postcode":"de7 5nx",
    "addr:street":"Nottingham Road",
    "iso:country":"GB",
    "sg:address":"Nottingham Road",
    "sg:city":"Ilkeston",
    "sg:classifiers":[
        {
            "category":"Bars & Pubs",
            "type":"Food & Drink"
        }
    ],
    "sg:phone":"+44 115 930 4825",
    "sg:postcode":"DE7 5NX",
    "sg:province":"Derbyshire",
    "sg:tags":[
        "pubs",
        "inn"
    ],
    "wof:name":"The White Cow",
    "wof:placetype":"venue"
},
  "geometry": {"coordinates":[-1.306484,52.967415],"type":"Point"}
}