{
  "type": "Feature",
  "properties": {
    "addr:full":"145a St John's Avenue Bridlington East Riding of Yorkshire YO16 4NP",
    "addr:housenumber":"145a",
    "addr:postcode":"yo16 4np",
    "addr:street":"St John'S Avenue",
    "iso:country":"GB",
    "sg:address":"145a St John's Avenue",
    "sg:city":"Bridlington",
    "sg:classifiers":[
        {
            "category":"Retail",
            "subcategory":"Auto Repair",
            "type":"Services"
        }
    ],
    "sg:phone":"+44 1262 675416",
    "sg:postcode":"YO16 4NP",
    "sg:province":"East Riding of Yorkshire",
    "sg:tags":[
        "modification",
        "garage"
    ],
    "wof:name":"Reg Lee (Motor Engineers) Ltd.",
    "wof:placetype":"venue"
},
  "geometry": {"coordinates":[-0.20676,54.084499],"type":"Point"}
}