{
  "type": "Feature",
  "properties": {
    "iso:country":"GB",
    "sg:address":"Sophia House, 28 Cathedral Road",
    "sg:city":"Cardiff",
    "sg:classifiers":[
        {
            "category":"Home & Garden",
            "subcategory":"Building Materials",
            "type":"Retail Goods"
        }
    ],
    "sg:phone":"+44 29 2048 8812",
    "sg:postcode":"CF11 9LJ",
    "sg:province":"Cardiff",
    "sg:tags":[
        "stairlifts"
    ],
    "wof:name":"Trinity Stairlifts",
    "wof:placetype":"venue"
},
  "geometry": {"coordinates":[-3.190737,51.483364],"type":"Point"}
}