{
  "type": "Feature",
  "properties": {
    "addr:full":"Palatine Road, Goring-by-sea Worthing West Sussex BN12 6JP",
    "addr:postcode":"bn12 6jp",
    "addr:street":"Palatine Road",
    "iso:country":"GB",
    "sg:address":"Palatine Road, Goring-by-sea",
    "sg:city":"Worthing",
    "sg:classifiers":[
        {
            "category":"Education",
            "subcategory":"School",
            "type":"Public Place"
        }
    ],
    "sg:phone":"+44 1903 242835",
    "sg:postcode":"BN12 6JP",
    "sg:province":"West Sussex",
    "sg:tags":[
        "local",
        "authority"
    ],
    "wof:name":"Palatine School",
    "wof:placetype":"venue"
},
  "geometry": {"coordinates":[-0.4144139886,50.8240203857],"type":"Point"}
}