{
  "type": "Feature",
  "properties": {
    "addr:full":"30 Cove Road Farnborough Hampshire GU14 0EN",
    "addr:housenumber":"30",
    "addr:postcode":"gu14 0en",
    "addr:street":"Cove Road",
    "iso:country":"GB",
    "sg:address":"30 Cove Road",
    "sg:city":"Farnborough",
    "sg:classifiers":[
        {
            "category":"Fast Food",
            "type":"Food & Drink"
        }
    ],
    "sg:phone":"+44 1252 378080",
    "sg:postcode":"GU14 0EN",
    "sg:province":"Hampshire",
    "sg:tags":[
        "away",
        "take"
    ],
    "wof:name":"Tasty Tucker",
    "wof:placetype":"venue"
},
  "geometry": {"coordinates":[-0.766594,51.292614],"type":"Point"}
}