{
  "type": "Feature",
  "properties": {
    "addr:full":"1 Carlisle Road Eastbourne East Sussex BN21 4BT",
    "addr:housenumber":"1",
    "addr:postcode":"bn21 4bt",
    "addr:street":"Carlisle Road",
    "iso:country":"GB",
    "sg:address":"1 Carlisle Road",
    "sg:city":"Eastbourne",
    "sg:classifiers":[
        {
            "category":"Shopping",
            "subcategory":"Clothing, Apparel, & Fashions",
            "type":"Retail Goods"
        },
        {
            "category":"Building & Trades",
            "subcategory":"Construction",
            "type":"Services"
        }
    ],
    "sg:phone":"+44 1323 412800",
    "sg:postcode":"BN21 4BT",
    "sg:province":"East Sussex",
    "sg:tags":[
        "builder",
        "ladieswear"
    ],
    "wof:name":"Cameo Fashions",
    "wof:placetype":"venue"
},
  "geometry": {"coordinates":[0.286453,50.762493],"type":"Point"}
}