{
  "type": "Feature",
  "properties": {
    "addr:full":"1b Bankhead Indstrl Estate, Bankhead Avenue, Bucksburn Aberdeen Aberdeen City AB21 9ET",
    "addr:housenumber":"1b",
    "addr:postcode":"ab21 9et",
    "addr:street":"Bankhead Indstrl Estate Bankhead Avenue",
    "iso:country":"GB",
    "sg:address":"1b Bankhead Indstrl Estate, Bankhead Avenue, Bucksburn",
    "sg:city":"Aberdeen",
    "sg:classifiers":[
        {
            "category":"Manufacturing",
            "subcategory":"Metals",
            "type":"Manufacturing & Wholesale Goods"
        }
    ],
    "sg:phone":"+44 1224 714140",
    "sg:postcode":"AB21 9ET",
    "sg:province":"Aberdeen City",
    "sg:tags":[
        "steel",
        "fabricator",
        "erectors"
    ],
    "wof:name":"Gas & Hydraulics Engineering & Fabrication Ltd.",
    "wof:placetype":"venue"
},
  "geometry": {"coordinates":[-2.1816599369,57.1781387329],"type":"Point"}
}