{
  "type": "Feature",
  "properties": {
    "addr:full":"175 Manchester Road, Greenfield Oldham Lancashire OL3 7HN",
    "addr:housenumber":"175",
    "addr:postcode":"ol3 7hn",
    "addr:street":"Manchester Road",
    "iso:country":"GB",
    "sg:address":"175 Manchester Road, Greenfield",
    "sg:city":"Oldham",
    "sg:classifiers":[
        {
            "category":"Shopping",
            "subcategory":"News",
            "type":"Retail Goods"
        }
    ],
    "sg:postcode":"OL3 7HN",
    "sg:province":"Lancashire",
    "sg:tags":[
        "newsagent"
    ],
    "wof:name":"Brogden's News Cards & Confectionery",
    "wof:placetype":"venue"
},
  "geometry": {"coordinates":[-2.0180370808,53.5311088562],"type":"Point"}
}