{
  "type": "Feature",
  "properties": {
    "iso:country":"GB",
    "sg:address":"Unit 4 Eagle Road, Quarry Hill Industrial Estate",
    "sg:city":"Ilkeston",
    "sg:classifiers":[
        {
            "category":"Wholesale",
            "subcategory":"Construction Materials",
            "type":"Manufacturing & Wholesale Goods"
        }
    ],
    "sg:phone":"+44 115 944 4275",
    "sg:postcode":"DE7 4RB",
    "sg:province":"Derbyshire",
    "sg:tags":[
        "coating",
        "powder"
    ],
    "wof:name":"Cannon Coatings",
    "wof:placetype":"venue"
},
  "geometry": {"coordinates":[-1.3062939644,52.9551010132],"type":"Point"}
}