{
  "type": "Feature",
  "properties": {
    "addr:full":"47f Broad St Banbury Oxfordshire OX16 5BT",
    "addr:housenumber":"47f",
    "addr:postcode":"ox16 5bt",
    "addr:street":"Broad St",
    "iso:country":"GB",
    "sg:address":"47f Broad St",
    "sg:city":"Banbury",
    "sg:classifiers":[
        {
            "category":"Shopping",
            "subcategory":"Bicycles & Sporting Goods",
            "type":"Retail Goods"
        }
    ],
    "sg:postcode":"OX16 5BT",
    "sg:province":"Oxfordshire",
    "sg:tags":[
        "riding",
        "saddlery",
        "wear"
    ],
    "wof:name":"Jordon-Windgrove,Louise,",
    "wof:placetype":"venue"
},
  "geometry": {"coordinates":[-1.335588,52.059772],"type":"Point"}
}