{
  "type": "Feature",
  "properties": {
    "iso:country":"GB",
    "sg:address":"Crawford Street",
    "sg:city":"Wigan",
    "sg:classifiers":[
        {
            "category":"Government",
            "subcategory":"Court House",
            "type":"Public Place"
        }
    ],
    "sg:phone":"+44 1942 246481",
    "sg:postcode":"WN1 1NA",
    "sg:province":"Lancashire",
    "wof:name":"Wigan County Court",
    "wof:placetype":"venue"
},
  "geometry": {"coordinates":[-2.634094,53.545715],"type":"Point"}
}