{
  "type": "Feature",
  "properties": {
    "iso:country":"GB",
    "sg:address":"376 Ringwood Rd",
    "sg:city":"Poole",
    "sg:classifiers":[
        {
            "category":"Retail",
            "subcategory":"Auto Repair",
            "type":"Services"
        }
    ],
    "sg:phone":"+44 1202 730480",
    "sg:postcode":"BH12 3LT",
    "sg:province":"Dorset",
    "sg:tags":[
        "modification",
        "garage"
    ],
    "wof:name":"Mike Hankins Garage",
    "wof:placetype":"venue"
},
  "geometry": {"coordinates":[-1.9504569769,50.7369651794],"type":"Point"}
}