{
  "type": "Feature",
  "properties": {
    "addr:full":"Storridge Malvern Gloucestershire WR13 5EN",
    "addr:postcode":"wr13 5en",
    "iso:country":"GB",
    "sg:address":"Storridge",
    "sg:city":"Malvern",
    "sg:classifiers":[
        {
            "category":"Retail",
            "subcategory":"Auto Repair",
            "type":"Services"
        }
    ],
    "sg:postcode":"WR13 5EN",
    "sg:province":"Gloucestershire",
    "sg:tags":[
        "modification",
        "garage"
    ],
    "wof:name":"Millbank Garages (Cradley)",
    "wof:placetype":"venue"
},
  "geometry": {"coordinates":[-2.364068985,52.1340103149],"type":"Point"}
}