{
  "type": "Feature",
  "properties": {
    "addr:full":"2399 Coventry Road, Sheldon Birmingham West Midlands B26 3PN",
    "addr:housenumber":"2399",
    "addr:postcode":"b26 3pn",
    "addr:street":"Coventry Road",
    "iso:country":"GB",
    "sg:address":"2399 Coventry Road, Sheldon",
    "sg:city":"Birmingham",
    "sg:classifiers":[
        {
            "category":"Travel",
            "subcategory":"Hotels & Motels",
            "type":"Entertainment"
        }
    ],
    "sg:phone":"+44 121 742 0017",
    "sg:postcode":"B26 3PN",
    "sg:province":"West Midlands",
    "sg:tags":[
        "house",
        "guest"
    ],
    "wof:name":"Homelea Guest House",
    "wof:placetype":"venue"
},
  "geometry": {"coordinates":[-1.7718590498,52.4515304565],"type":"Point"}
}