{
  "type": "Feature",
  "properties": {
    "addr:full":"Pit Lark Farm, Stancomb Broad Lane, Medstead Alton Hampshire GU34 5QD",
    "addr:postcode":"gu34 5qd",
    "addr:street":"Broad Lane",
    "iso:country":"GB",
    "sg:address":"Pit Lark Farm, Stancomb Broad Lane, Medstead",
    "sg:city":"Alton",
    "sg:classifiers":[
        {
            "category":"Freight",
            "type":"Transportation"
        }
    ],
    "sg:phone":"+44 1420 563340",
    "sg:postcode":"GU34 5QD",
    "sg:province":"Hampshire",
    "sg:tags":[
        "haulage",
        "road"
    ],
    "wof:name":"R H Blackman & Sons",
    "wof:placetype":"venue"
},
  "geometry": {"coordinates":[-1.064815,51.129547],"type":"Point"}
}