{
  "type": "Feature",
  "properties": {
    "addr:full":"Prospect Road, Toll Bar Doncaster South Yorkshire DN5 0QP",
    "addr:postcode":"dn5 0qp",
    "addr:street":"Prospect Road",
    "iso:country":"GB",
    "sg:address":"Prospect Road, Toll Bar",
    "sg:city":"Doncaster",
    "sg:classifiers":[
        {
            "category":"Organizations",
            "subcategory":"Membership Organization",
            "type":"Services"
        },
        {
            "category":"Arena",
            "subcategory":"Sports Club",
            "type":"Entertainment"
        }
    ],
    "sg:phone":"+44 1302 872012",
    "sg:postcode":"DN5 0QP",
    "sg:province":"South Yorkshire",
    "wof:name":"DONCASTER TOLLBAR AMATEUR RUGBY LEAGUE CLUB",
    "wof:placetype":"venue"
},
  "geometry": {"coordinates":[-1.1522489786,53.5651893616],"type":"Point"}
}