{
  "type": "Feature",
  "properties": {
    "addr:full":"27 Cedar Road, Oxhey Watford Hertfordshire WD19 4QP",
    "addr:housenumber":"27",
    "addr:postcode":"wd19 4qp",
    "addr:street":"Cedar Road",
    "iso:country":"GB",
    "sg:address":"27 Cedar Road, Oxhey",
    "sg:city":"Watford",
    "sg:classifiers":[
        {
            "category":"Manufacturing",
            "subcategory":"Signs",
            "type":"Manufacturing & Wholesale Goods"
        }
    ],
    "sg:phone":"+44 1923 244688",
    "sg:postcode":"WD19 4QP",
    "sg:province":"Hertfordshire",
    "sg:tags":[
        "nameplate"
    ],
    "wof:name":"E P S Residential",
    "wof:placetype":"venue"
},
  "geometry": {"coordinates":[-0.3888759911,51.643371582],"type":"Point"}
}