{
  "type": "Feature",
  "properties": {
    "addr:full":"7 Bell Lane, Kitts Green Birmingham West Midlands B33 0HS",
    "addr:housenumber":"7",
    "addr:postcode":"b33 0hs",
    "addr:street":"Bell Lane",
    "iso:country":"GB",
    "sg:address":"7 Bell Lane, Kitts Green",
    "sg:city":"Birmingham",
    "sg:classifiers":[
        {
            "category":"Food & Beverages",
            "subcategory":"Supermarket",
            "type":"Retail Goods"
        }
    ],
    "sg:phone":"+44 121 779 6330",
    "sg:postcode":"B33 0HS",
    "sg:province":"West Midlands",
    "wof:name":"Bell Lane Supermarket",
    "wof:placetype":"venue"
},
  "geometry": {"coordinates":[-1.762987,52.473801],"type":"Point"}
}