{
  "type": "Feature",
  "properties": {
    "addr:full":"St Johns Ho, Cross Church St Cleckheaton West Yorkshire BD19 3RQ",
    "addr:postcode":"bd19 3rq",
    "addr:street":"St;West",
    "iso:country":"GB",
    "sg:address":"St Johns Ho, Cross Church St",
    "sg:city":"Cleckheaton",
    "sg:classifiers":[
        {
            "category":"Health Services",
            "subcategory":"Doctor",
            "type":"Services"
        }
    ],
    "sg:phone":"+44 1274 851188",
    "sg:postcode":"BD19 3RQ",
    "sg:province":"West Yorkshire",
    "sg:tags":[
        "practitioners"
    ],
    "wof:name":"Woodhall, A J",
    "wof:placetype":"venue"
},
  "geometry": {"coordinates":[-1.709329,53.723675],"type":"Point"}
}