{
  "type": "Feature",
  "properties": {
    "addr:full":"Unit A8 Brownlow Business Centre, Darley Street Bolton Lancashire BL1 3DX",
    "addr:housenumber":"a8",
    "addr:postcode":"bl1 3dx",
    "addr:street":"Brownlow Business Centre Darley Street",
    "iso:country":"GB",
    "sg:address":"Unit A8 Brownlow Business Centre, Darley Street",
    "sg:city":"Bolton",
    "sg:classifiers":[
        {
            "category":"Home & Garden",
            "subcategory":"Home Furnishings",
            "type":"Retail Goods"
        }
    ],
    "sg:phone":"+44 1204 365577",
    "sg:postcode":"BL1 3DX",
    "sg:province":"Lancashire",
    "sg:tags":[
        "furnishers",
        "planner",
        "bedroom"
    ],
    "sg:website":"http://www.fittedbedrooms.co.uk",
    "wof:name":"Classic Bedrooms",
    "wof:placetype":"venue"
},
  "geometry": {"coordinates":[-2.426594,53.578289],"type":"Point"}
}