{
  "type": "Feature",
  "properties": {
    "addr:full":"P O Box 214 Ashford Kent TN24 8WW",
    "addr:housenumber":"214",
    "addr:postcode":"tn24 8ww",
    "addr:street":"P O Box",
    "iso:country":"GB",
    "sg:address":"P O Box 214",
    "sg:city":"Ashford",
    "sg:classifiers":[
        {
            "category":"Shopping",
            "subcategory":"Music",
            "type":"Retail Goods"
        }
    ],
    "sg:postcode":"TN24 8WW",
    "sg:province":"Kent",
    "sg:tags":[
        "record",
        "tape",
        "cd"
    ],
    "wof:name":"Imajica Records",
    "wof:placetype":"venue"
},
  "geometry": {"coordinates":[0.883899,51.150513],"type":"Point"}
}