{
  "type": "Feature",
  "properties": {
    "iso:country":"GB",
    "sg:address":"55 East Rd",
    "sg:city":"Islington",
    "sg:classifiers":[
        {
            "category":"Utilities",
            "type":"Services"
        }
    ],
    "sg:phone":"+44 20 7250 3969",
    "sg:postcode":"N1 6AH",
    "sg:province":"Greater London",
    "sg:tags":[
        "internet"
    ],
    "wof:name":"Netro Communications Ltd",
    "wof:placetype":"venue"
},
  "geometry": {"coordinates":[-0.086399,51.53022],"type":"Point"}
}