{
  "type": "Feature",
  "properties": {
    "addr:full":"2 Royal Quays Factory Outlets, Coble Dene Road North Shields Tyne and Wear NE29 6DW",
    "addr:housenumber":"2",
    "addr:postcode":"ne29 6dw",
    "addr:street":"Royal Quays;Dene Road",
    "iso:country":"GB",
    "sg:address":"2 Royal Quays Factory Outlets, Coble Dene Road",
    "sg:city":"North Shields",
    "sg:classifiers":[
        {
            "category":"Shopping",
            "subcategory":"Clothing, Apparel, & Fashions",
            "type":"Retail Goods"
        }
    ],
    "sg:phone":"+44 191 296 2911",
    "sg:postcode":"NE29 6DW",
    "sg:province":"Tyne and Wear",
    "sg:tags":[
        "ladieswear"
    ],
    "wof:name":"Discount Clothing Store",
    "wof:placetype":"venue"
},
  "geometry": {"coordinates":[-1.4652099609,54.9952087402],"type":"Point"}
}