{
  "type": "Feature",
  "properties": {
    "addr:full":"North Down Business Park, Ashford Road Maidstone Kent ME17 2DL",
    "addr:postcode":"me17 2dl",
    "addr:street":"North;Ashford Road",
    "iso:country":"GB",
    "sg:address":"North Down Business Park, Ashford Road",
    "sg:city":"Maidstone",
    "sg:classifiers":[
        {
            "category":"Shopping",
            "type":"Retail Goods"
        }
    ],
    "sg:phone":"+44 1622 850057",
    "sg:postcode":"ME17 2DL",
    "sg:province":"Kent",
    "sg:tags":[
        "merchant"
    ],
    "wof:name":"Denimex",
    "wof:placetype":"venue"
},
  "geometry": {"coordinates":[0.7312700152,51.236038208],"type":"Point"}
}