{
  "type": "Feature",
  "properties": {
    "addr:full":"Civic Offices, St Nicholas Way Sutton Surrey SM1 1EA",
    "addr:postcode":"sm1 1ea",
    "addr:street":"St Nicholas Way",
    "iso:country":"GB",
    "sg:address":"Civic Offices, St Nicholas Way",
    "sg:city":"Sutton",
    "sg:classifiers":[
        {
            "category":"Travel",
            "subcategory":"Travel Agent",
            "type":"Entertainment"
        },
        {
            "category":"Government",
            "subcategory":"Office",
            "type":"Public Place"
        }
    ],
    "sg:phone":"+44 20 8770 5000",
    "sg:postcode":"SM1 1EA",
    "sg:province":"Surrey",
    "sg:tags":[
        "agency",
        "local",
        "activity"
    ],
    "wof:name":"LONDON BOROUGH OF SUTTON",
    "wof:placetype":"venue"
},
  "geometry": {"coordinates":[-0.196044,51.367153],"type":"Point"}
}