{
  "type": "Feature",
  "properties": {
    "iso:country":"GB",
    "sg:address":"25 Lambourne Crescent",
    "sg:city":"Worcester",
    "sg:classifiers":[
        {
            "category":"Building & Trades",
            "subcategory":"Construction",
            "type":"Services"
        }
    ],
    "sg:phone":"+44 1905 422506",
    "sg:postcode":"WR2 6ER",
    "sg:province":"Worcestershire",
    "sg:tags":[
        "decorator",
        "painter"
    ],
    "wof:name":"Vernon Rowberry",
    "wof:placetype":"venue"
},
  "geometry": {"coordinates":[-2.247145,52.208073],"type":"Point"}
}