{
  "type": "Feature",
  "properties": {
    "addr:full":"25 Goodramgate York North Yorkshire YO1 7LW",
    "addr:housenumber":"25",
    "addr:postcode":"yo1 7lw",
    "addr:street":"Goodramgate",
    "iso:country":"GB",
    "sg:address":"25 Goodramgate",
    "sg:city":"York",
    "sg:classifiers":[
        {
            "category":"Shopping",
            "subcategory":"Thrift Store",
            "type":"Retail Goods"
        },
        {
            "category":"Organizations",
            "subcategory":"Non-profit Organization",
            "type":"Services"
        }
    ],
    "sg:phone":"+44 1904 639451",
    "sg:postcode":"YO1 7LW",
    "sg:province":"North Yorkshire",
    "sg:tags":[
        "shop",
        "charitable",
        "organisation",
        "charity"
    ],
    "sg:website":"http://www.mind.org.uk",
    "wof:name":"Mind",
    "wof:placetype":"venue"
},
  "geometry": {"coordinates":[-1.079219,53.961948],"type":"Point"}
}