{
  "type": "Feature",
  "properties": {
    "addr:full":"Westbere Court, Island Road, Westbere Canterbury Kent CT3 4HD",
    "addr:postcode":"ct3 4hd",
    "addr:street":"Westbere Court Island Road",
    "iso:country":"GB",
    "sg:address":"Westbere Court, Island Road, Westbere",
    "sg:city":"Canterbury",
    "sg:classifiers":[
        {
            "category":"Personal",
            "type":"Services"
        }
    ],
    "sg:phone":"+44 1227 711765",
    "sg:postcode":"CT3 4HD",
    "sg:province":"Kent",
    "sg:tags":[
        "wedding"
    ],
    "wof:name":"Chaffeur Driven Bentley",
    "wof:placetype":"venue"
},
  "geometry": {"coordinates":[1.1711610556,51.3169708252],"type":"Point"}
}