{
  "type": "Feature",
  "properties": {
    "addr:full":"57 Russell Way, Metrocentre Gateshead Tyne and Wear NE11 9XX",
    "addr:housenumber":"57",
    "addr:postcode":"ne11 9xx",
    "addr:street":"Russell Way",
    "iso:country":"GB",
    "sg:address":"57 Russell Way, Metrocentre",
    "sg:city":"Gateshead",
    "sg:classifiers":[
        {
            "category":"Travel",
            "subcategory":"Travel Agent",
            "type":"Entertainment"
        }
    ],
    "sg:phone":"+44 191 493 2026",
    "sg:postcode":"NE11 9XX",
    "sg:province":"Tyne and Wear",
    "sg:tags":[
        "agency",
        "activity"
    ],
    "wof:name":"Callers Pegasus Travel Service Ltd",
    "wof:placetype":"venue"
},
  "geometry": {"coordinates":[-1.6685400009,54.957660675],"type":"Point"}
}