{
  "type": "Feature",
  "properties": {
    "addr:full":"37 Coombe Terr Brighton East Sussex BN2 4AD",
    "addr:housenumber":"37",
    "addr:postcode":"bn2 4ad",
    "addr:street":"Coombe Terr",
    "iso:country":"GB",
    "sg:address":"37 Coombe Terr",
    "sg:city":"Brighton",
    "sg:classifiers":[
        {
            "category":"Home & Garden",
            "subcategory":"Household Appliances",
            "type":"Retail Goods"
        }
    ],
    "sg:postcode":"BN2 4AD",
    "sg:province":"East Sussex",
    "sg:tags":[
        "domestic",
        "oven",
        "microwave"
    ],
    "wof:name":"Repair Centre (The)",
    "wof:placetype":"venue"
},
  "geometry": {"coordinates":[-0.119401,50.839771],"type":"Point"}
}