{
  "type": "Feature",
  "properties": {
    "addr:full":"St. Catherines Hospital, Tickhill Rd, Balby Doncaster South Yorkshire DN4 8QN",
    "addr:postcode":"dn4 8qn",
    "addr:street":"Tickhill Rd",
    "iso:country":"GB",
    "sg:address":"St. Catherines Hospital, Tickhill Rd, Balby",
    "sg:city":"Doncaster",
    "sg:classifiers":[
        {
            "category":"Health Services",
            "subcategory":"Hospital",
            "type":"Services"
        },
        {
            "category":"Health Services",
            "subcategory":"Nursing And Care Facility",
            "type":"Services"
        },
        {
            "category":"Health Services",
            "subcategory":"Clinic",
            "type":"Services"
        }
    ],
    "sg:phone":"+44 1302 796000",
    "sg:postcode":"DN4 8QN",
    "sg:province":"South Yorkshire",
    "sg:tags":[
        "nh",
        "home",
        "private"
    ],
    "wof:name":"Doncaster & South Humber Healthcare N H S Trust",
    "wof:placetype":"venue"
},
  "geometry": {"coordinates":[-1.1398789883,53.5106925964],"type":"Point"}
}