{
  "type": "Feature",
  "properties": {
    "iso:country":"GB",
    "sg:address":"86a Liverpool Rd South",
    "sg:city":"Liverpool",
    "sg:classifiers":[
        {
            "category":"Health Services",
            "subcategory":"Podiatrist",
            "type":"Services"
        }
    ],
    "sg:phone":"+44 151 526 3780",
    "sg:postcode":"L31 7AG",
    "sg:province":"Lancashire",
    "sg:tags":[
        "podiatrists",
        "chiropodist"
    ],
    "wof:name":"L Chappell M.Inst.Ch",
    "wof:placetype":"venue"
},
  "geometry": {"coordinates":[-2.9468979836,53.5055274963],"type":"Point"}
}