{
  "type": "Feature",
  "properties": {
    "addr:full":"92 Leagrave Rd Luton Bedfordshire LU4 8HZ",
    "addr:housenumber":"92",
    "addr:postcode":"lu4 8hz",
    "addr:street":"Leagrave Rd",
    "iso:country":"GB",
    "sg:address":"92 Leagrave Rd",
    "sg:city":"Luton",
    "sg:classifiers":[
        {
            "category":"Fast Food",
            "type":"Food & Drink"
        }
    ],
    "sg:postcode":"LU4 8HZ",
    "sg:province":"Bedfordshire",
    "sg:tags":[
        "away",
        "take"
    ],
    "wof:name":"Ellis,Myrna,",
    "wof:placetype":"venue"
},
  "geometry": {"coordinates":[-0.4314160049,51.8880081177],"type":"Point"}
}