{
  "type": "Feature",
  "properties": {
    "addr:full":"Rickmansworth Road Northwood Greater London HA6 2RN",
    "addr:postcode":"ha6 2rn",
    "addr:street":"Rickmansworth Road",
    "iso:country":"GB",
    "sg:address":"Rickmansworth Road",
    "sg:city":"Northwood",
    "sg:classifiers":[
        {
            "category":"Taxi",
            "type":"Transportation"
        }
    ],
    "sg:phone":"+44 1923 822400",
    "sg:postcode":"HA6 2RN",
    "sg:province":"Greater London",
    "sg:tags":[
        "mini",
        "cab"
    ],
    "wof:name":"Henry's Minicabs",
    "wof:placetype":"venue"
},
  "geometry": {"coordinates":[-0.426386,51.606323],"type":"Point"}
}