{
  "type": "Feature",
  "properties": {
    "iso:country":"GB",
    "sg:address":"Paulton House, 8 Shepherdess Walk",
    "sg:city":"London",
    "sg:classifiers":[
        {
            "category":"Wholesale",
            "subcategory":"Books, Periodicals, & Newspapers",
            "type":"Manufacturing & Wholesale Goods"
        },
        {
            "category":"Professional",
            "subcategory":"Credit Reporting & Collection",
            "type":"Services"
        }
    ],
    "sg:phone":"+44 20 7490 0049",
    "sg:postcode":"N1 7LB",
    "sg:province":"Greater London",
    "sg:tags":[
        "agency",
        "publishing",
        "reference"
    ],
    "wof:name":"Wilmington Business Information Ltd.",
    "wof:placetype":"venue"
},
  "geometry": {"coordinates":[-0.091798,51.528954],"type":"Point"}
}