{
  "type": "Feature",
  "properties": {
    "addr:full":"16 Dovecote Close Wolverhampton Shropshire WV6 8NA",
    "addr:housenumber":"16",
    "addr:postcode":"wv6 8na",
    "addr:street":"Dovecote Close",
    "iso:country":"GB",
    "sg:address":"16 Dovecote Close",
    "sg:city":"Wolverhampton",
    "sg:classifiers":[
        {
            "category":"Professional",
            "subcategory":"Accounting & Tax Preparation",
            "type":"Services"
        }
    ],
    "sg:postcode":"WV6 8NA",
    "sg:province":"Shropshire",
    "sg:tags":[
        "accountant"
    ],
    "wof:name":"H E Pressey",
    "wof:placetype":"venue"
},
  "geometry": {"coordinates":[-2.17711,52.595798],"type":"Point"}
}