{
  "type": "Feature",
  "properties": {
    "iso:country":"GB",
    "sg:address":"Bourne Road, Corby Glen",
    "sg:city":"Grantham",
    "sg:classifiers":[
        {
            "category":"Education",
            "subcategory":"School",
            "type":"Public Place"
        },
        {
            "category":"Government",
            "subcategory":"Office",
            "type":"Public Place"
        }
    ],
    "sg:postcode":"NG33 4NT",
    "sg:province":"Leicestershire",
    "sg:tags":[
        "local",
        "authority"
    ],
    "wof:name":"The Charles Read School",
    "wof:placetype":"venue"
},
  "geometry": {"coordinates":[-0.5206040144,52.8121376038],"type":"Point"}
}