{
  "type": "Feature",
  "properties": {
    "iso:country":"GB",
    "sg:address":"14 Clarence Rd, Stony Stratford",
    "sg:city":"Milton Keynes",
    "sg:classifiers":[
        {
            "category":"Utilities",
            "subcategory":"Natural Gas",
            "type":"Services"
        }
    ],
    "sg:phone":"+44 1908 262440",
    "sg:postcode":"MK11 1JD",
    "sg:province":"Buckinghamshire",
    "sg:tags":[
        "welding"
    ],
    "wof:name":"Pro Systems",
    "wof:placetype":"venue"
},
  "geometry": {"coordinates":[-0.846057,52.057056],"type":"Point"}
}