{
  "type": "Feature",
  "properties": {
    "addr:full":"Unit 9, Silicon Business Centre, 26 Wadsworth Road Greenford Greater London UB6 7JD",
    "addr:housenumber":"unit;26",
    "addr:postcode":"ub6 7jd",
    "addr:street":"Silicon;Wadsworth Road",
    "iso:country":"GB",
    "sg:address":"Unit 9, Silicon Business Centre, 26 Wadsworth Road",
    "sg:city":"Greenford",
    "sg:classifiers":[
        {
            "category":"Building & Trades",
            "subcategory":"Construction",
            "type":"Services"
        }
    ],
    "sg:phone":"+44 20 8991 2849",
    "sg:postcode":"UB6 7JD",
    "sg:province":"Greater London",
    "sg:tags":[
        "joiner",
        "carpenter"
    ],
    "wof:name":"J D Joinery",
    "wof:placetype":"venue"
},
  "geometry": {"coordinates":[-0.339899987,51.5492706299],"type":"Point"}
}