{
  "type": "Feature",
  "properties": {
    "addr:full":"Bryn Coch, Abererch Pwllheli Gwynedd LL53 6BZ",
    "addr:postcode":"ll53 6bz",
    "addr:street":"Bryn;Abererch",
    "iso:country":"GB",
    "sg:address":"Bryn Coch, Abererch",
    "sg:city":"Pwllheli",
    "sg:classifiers":[
        {
            "category":"Military Area",
            "subcategory":"Air Force Base",
            "type":"Public Place"
        }
    ],
    "sg:phone":"+44 1758 613711",
    "sg:postcode":"LL53 6BZ",
    "sg:province":"Gwynedd",
    "sg:tags":[
        "taxi",
        "hire",
        "private"
    ],
    "wof:name":"Blue Cars",
    "wof:placetype":"venue"
},
  "geometry": {"coordinates":[-4.3814592361,52.9040031433],"type":"Point"}
}