{
  "type": "Feature",
  "properties": {
    "addr:full":"18 Kings Walk Gloucester Gloucestershire GL1 1RW",
    "addr:housenumber":"18",
    "addr:postcode":"gl1 1rw",
    "addr:street":"Kings Walk",
    "iso:country":"GB",
    "sg:address":"18 Kings Walk",
    "sg:city":"Gloucester",
    "sg:classifiers":[
        {
            "category":"Shopping",
            "subcategory":"Music",
            "type":"Retail Goods"
        }
    ],
    "sg:phone":"+44 1452 302231",
    "sg:postcode":"GL1 1RW",
    "sg:province":"Gloucestershire",
    "sg:tags":[
        "record",
        "tape",
        "cd"
    ],
    "wof:name":"H M V (U K) Ltd.",
    "wof:placetype":"venue"
},
  "geometry": {"coordinates":[-2.2425498962,51.8648796082],"type":"Point"}
}