{
  "type": "Feature",
  "properties": {
    "addr:full":"1st Floor, 14 Central Chambers, The Broadway London Greater London W5 2NR",
    "addr:housenumber":"14",
    "addr:postcode":"w5 2nr",
    "addr:street":"Central Chambers The Broadway",
    "iso:country":"GB",
    "sg:address":"1st Floor, 14 Central Chambers, The Broadway",
    "sg:city":"London",
    "sg:classifiers":[
        {
            "category":"Real Estate",
            "subcategory":"Real Estate Operator",
            "type":"Services"
        }
    ],
    "sg:phone":"+44 20 8840 2146",
    "sg:postcode":"W5 2NR",
    "sg:province":"Greater London",
    "sg:tags":[
        "letting",
        "agent"
    ],
    "wof:name":"Alexander's Residential Lettings & Property Manage",
    "wof:placetype":"venue"
},
  "geometry": {"coordinates":[-0.30416,51.513378],"type":"Point"}
}