{
  "type": "Feature",
  "properties": {
    "addr:full":"30 George Street Pontypool Monmouthshire NP4 6BY",
    "addr:housenumber":"30",
    "addr:postcode":"np4 6by",
    "addr:street":"George Street",
    "iso:country":"GB",
    "sg:address":"30 George Street",
    "sg:city":"Pontypool",
    "sg:classifiers":[
        {
            "category":"Shopping",
            "subcategory":"Jewelry",
            "type":"Retail Goods"
        },
        {
            "category":"Shopping",
            "subcategory":"Comic Books",
            "type":"Retail Goods"
        }
    ],
    "sg:phone":"+44 1495 751432",
    "sg:postcode":"NP4 6BY",
    "sg:province":"Monmouthshire",
    "sg:tags":[
        "jeweller",
        "sale",
        "jewellery"
    ],
    "wof:name":"Andrews Jewellers",
    "wof:placetype":"venue"
},
  "geometry": {"coordinates":[-3.0423469543,51.7038192749],"type":"Point"}
}