{
  "type": "Feature",
  "properties": {
    "iso:country":"GB",
    "sg:address":"7 Lynwood Avenue, St Thomas",
    "sg:city":"Exeter",
    "sg:classifiers":[
        {
            "category":"Professional",
            "subcategory":"Engineering",
            "type":"Services"
        }
    ],
    "sg:phone":"+44 1392 211109",
    "sg:postcode":"EX4 1EF",
    "sg:province":"Devon",
    "sg:tags":[
        "contractor",
        "electrical",
        "engineer"
    ],
    "wof:name":"Ac Electrical",
    "wof:placetype":"venue"
},
  "geometry": {"coordinates":[-3.544184,50.720787],"type":"Point"}
}