{
  "type": "Feature",
  "properties": {
    "iso:country":"GB",
    "sg:address":"B R Goods Yard, Gatwick Road",
    "sg:city":"Crawley",
    "sg:classifiers":[
        {
            "category":"Wholesale",
            "subcategory":"Construction Materials",
            "type":"Manufacturing & Wholesale Goods"
        }
    ],
    "sg:phone":"+44 1293 538669",
    "sg:postcode":"RH10 9RE",
    "sg:province":"Surrey",
    "sg:tags":[
        "whole",
        "asphalt",
        "macadam"
    ],
    "wof:name":"Foster Yeoman Ltd.",
    "wof:placetype":"venue"
},
  "geometry": {"coordinates":[-0.184753,51.118458],"type":"Point"}
}