{
  "type": "Feature",
  "properties": {
    "addr:full":"Unit 7c, Grays Farm Production Village, Grays Farm Road Orpington Kent BR5 3BD",
    "addr:housenumber":"unit 7c;farm production",
    "addr:postcode":"br5 3bd",
    "addr:street":"Grays;Village Grays Farm Road",
    "iso:country":"GB",
    "sg:address":"Unit 7c, Grays Farm Production Village, Grays Farm Road",
    "sg:city":"Orpington",
    "sg:classifiers":[
        {
            "category":"Retail",
            "subcategory":"Driving School",
            "type":"Services"
        }
    ],
    "sg:phone":"+44 20 8300 6690",
    "sg:postcode":"BR5 3BD",
    "sg:province":"Kent",
    "wof:name":"Way Ahead School of Motoring",
    "wof:placetype":"venue"
},
  "geometry": {"coordinates":[0.11191,51.408199],"type":"Point"}
}