{
  "type": "Feature",
  "properties": {
    "addr:full":"2 Blakey Close Bolton Lancashire BL3 4XU",
    "addr:housenumber":"2",
    "addr:postcode":"bl3 4xu",
    "addr:street":"Blakey Close",
    "iso:country":"GB",
    "sg:address":"2 Blakey Close",
    "sg:city":"Bolton",
    "sg:classifiers":[
        {
            "category":"Building & Trades",
            "subcategory":"Plumbing",
            "type":"Services"
        },
        {
            "category":"Building & Trades",
            "subcategory":"Equipment Rental",
            "type":"Services"
        }
    ],
    "sg:phone":"+44 1204 665794",
    "sg:postcode":"BL3 4XU",
    "sg:province":"Lancashire",
    "sg:tags":[
        "clearance",
        "sewer",
        "drain"
    ],
    "wof:name":"North West Drain Cleaning Co",
    "wof:placetype":"venue"
},
  "geometry": {"coordinates":[-2.4762818813,53.5646743774],"type":"Point"}
}