{
  "type": "Feature",
  "properties": {
    "addr:full":"4 Pentland Court, Satire Business Park Glenrothes Fife KY6 2DA",
    "addr:housenumber":"4",
    "addr:postcode":"ky6 2da",
    "addr:street":"Pentland Court Satire Business Park Glenrothes",
    "iso:country":"GB",
    "sg:address":"4 Pentland Court, Satire Business Park",
    "sg:city":"Glenrothes",
    "sg:classifiers":[
        {
            "category":"Wholesale",
            "subcategory":"Machinery & Supplies",
            "type":"Manufacturing & Wholesale Goods"
        }
    ],
    "sg:phone":"+44 1592 771188",
    "sg:postcode":"KY6 2DA",
    "sg:province":"Fife",
    "sg:tags":[
        "equipment",
        "handling",
        "lifting"
    ],
    "wof:name":"Kaiser & Kraft",
    "wof:placetype":"venue"
},
  "geometry": {"coordinates":[-3.1841320992,56.1893424988],"type":"Point"}
}