{
  "type": "Feature",
  "properties": {
    "iso:country":"GB",
    "sg:address":"Thomas Mills High School, Saxtead Rd",
    "sg:city":"Woodbridge",
    "sg:classifiers":[
        {
            "category":"Education",
            "subcategory":"University",
            "type":"Public Place"
        }
    ],
    "sg:phone":"+44 1728 724374",
    "sg:postcode":"IP13 9HE",
    "sg:province":"Suffolk",
    "sg:tags":[
        "adult"
    ],
    "wof:name":"Adult Education Centre",
    "wof:placetype":"venue"
},
  "geometry": {"coordinates":[1.309322,52.241634],"type":"Point"}
}