{
  "type": "Feature",
  "properties": {
    "addr:full":"Unit 34 Alloa Business Centre, The Whins Alloa Clackmannanshire FK10 3SA",
    "addr:housenumber":"unit 34;business centre",
    "addr:postcode":"fk10 3sa",
    "addr:street":"The Whins",
    "iso:country":"GB",
    "sg:address":"Unit 34 Alloa Business Centre, The Whins",
    "sg:city":"Alloa",
    "sg:classifiers":[
        {
            "category":"Real Estate",
            "subcategory":"Surveying",
            "type":"Services"
        },
        {
            "category":"Real Estate",
            "subcategory":"Architect",
            "type":"Services"
        }
    ],
    "sg:postcode":"FK10 3SA",
    "sg:province":"Clackmannanshire",
    "sg:tags":[
        "surveyor",
        "quantity"
    ],
    "wof:name":"Carroll Associates",
    "wof:placetype":"venue"
},
  "geometry": {"coordinates":[-3.7951939106,56.1163215637],"type":"Point"}
}