{
  "type": "Feature",
  "properties": {
    "addr:full":"55 Hoghton Street Southport Lancashire PR9 0PG",
    "addr:housenumber":"55",
    "addr:postcode":"pr9 0pg",
    "addr:street":"Hoghton Street",
    "iso:country":"GB",
    "sg:address":"55 Hoghton Street",
    "sg:city":"Southport",
    "sg:classifiers":[
        {
            "category":"Retail",
            "subcategory":"Storage",
            "type":"Services"
        }
    ],
    "sg:phone":"+44 1704 501222",
    "sg:postcode":"PR9 0PG",
    "sg:province":"Lancashire",
    "sg:tags":[
        "household",
        "activity",
        "domestic",
        "removal"
    ],
    "wof:name":"Southport & Formby Removals",
    "wof:placetype":"venue"
},
  "geometry": {"coordinates":[-2.99913,53.649776],"type":"Point"}
}