{
  "type": "Feature",
  "properties": {
    "addr:full":"Woodlands Av Reading Berkshire RG6 1HY",
    "addr:postcode":"rg6 1hy",
    "addr:street":"Woodlands Av",
    "iso:country":"GB",
    "sg:address":"Woodlands Av",
    "sg:city":"Reading",
    "sg:classifiers":[
        {
            "category":"Organizations",
            "subcategory":"Non-profit Organization",
            "type":"Services"
        }
    ],
    "sg:phone":"+44 118 935 1936",
    "sg:postcode":"RG6 1HY",
    "sg:province":"Berkshire",
    "sg:tags":[
        "organisation",
        "voluntary",
        "charity"
    ],
    "wof:name":"Assets Communication",
    "wof:placetype":"venue"
},
  "geometry": {"coordinates":[-0.9504640102,51.4748458862],"type":"Point"}
}