{
  "type": "Feature",
  "properties": {
    "iso:country":"GB",
    "sg:address":"Seafield Industrial Estate, Seafield Way",
    "sg:city":"Edinburgh",
    "sg:classifiers":[
        {
            "category":"Retail",
            "subcategory":"Auto Repair",
            "type":"Services"
        }
    ],
    "sg:phone":"+44 131 657 2143",
    "sg:postcode":"EH15 1TB",
    "sg:province":"City of Edinburgh",
    "sg:tags":[
        "modification",
        "garage"
    ],
    "wof:name":"Lex Autocentres",
    "wof:placetype":"venue"
},
  "geometry": {"coordinates":[-3.1323399544,55.9655418396],"type":"Point"}
}