{
  "type": "Feature",
  "properties": {
    "addr:full":"Unit 6-7 Bancombe Court, Stapleton Road Martock Somerset TA12 6HH",
    "addr:housenumber":"unit 6-7",
    "addr:postcode":"ta12 6hh",
    "addr:street":"Bancombe Court Stapleton Road",
    "iso:country":"GB",
    "sg:address":"Unit 6-7 Bancombe Court, Stapleton Road",
    "sg:city":"Martock",
    "sg:classifiers":[
        {
            "category":"Recreation",
            "type":"Entertainment"
        }
    ],
    "sg:phone":"+44 1935 826122",
    "sg:postcode":"TA12 6HH",
    "sg:province":"Somerset",
    "sg:tags":[
        "snooker",
        "billiards",
        "hall",
        "pool"
    ],
    "wof:name":"Martock Snooker Centre",
    "wof:placetype":"venue"
},
  "geometry": {"coordinates":[-2.770669,50.967247],"type":"Point"}
}