{
  "type": "Feature",
  "properties": {
    "addr:full":"26 Monkton Close Ferndown Dorset BH22 9LN",
    "addr:housenumber":"26",
    "addr:postcode":"bh22 9ln",
    "addr:street":"Monkton Close",
    "iso:country":"GB",
    "sg:address":"26 Monkton Close",
    "sg:city":"Ferndown",
    "sg:classifiers":[
        {
            "category":"Building & Trades",
            "subcategory":"Landscaping Services",
            "type":"Services"
        }
    ],
    "sg:phone":"+44 1202 873153",
    "sg:postcode":"BH22 9LN",
    "sg:province":"Dorset",
    "sg:tags":[
        "consultant"
    ],
    "wof:name":"A C Hayden",
    "wof:placetype":"venue"
},
  "geometry": {"coordinates":[-1.8893179893,50.8078804016],"type":"Point"}
}