{
  "type": "Feature",
  "properties": {
    "iso:country":"GB",
    "sg:address":"29b Albert Road",
    "sg:city":"Rochford",
    "sg:classifiers":[
        {
            "category":"Professional",
            "type":"Services"
        }
    ],
    "sg:phone":"+44 1702 546642",
    "sg:postcode":"SS4 3EX",
    "sg:province":"Essex",
    "sg:tags":[
        "directory",
        "pub"
    ],
    "wof:name":"Robert P Lyons",
    "wof:placetype":"venue"
},
  "geometry": {"coordinates":[0.689166,51.604626],"type":"Point"}
}