{
  "type": "Feature",
  "properties": {
    "iso:country":"GB",
    "sg:address":"226 Balunie Avenue",
    "sg:city":"Dundee",
    "sg:classifiers":[
        {
            "category":"Building & Trades",
            "subcategory":"Construction",
            "type":"Services"
        }
    ],
    "sg:phone":"+44 1382 779097",
    "sg:postcode":"DD4 8TJ",
    "sg:province":"Dundee City",
    "sg:tags":[
        "contractor",
        "paving",
        "driveway"
    ],
    "wof:name":"Albro Contractors",
    "wof:placetype":"venue"
},
  "geometry": {"coordinates":[-2.8918480873,56.4791793823],"type":"Point"}
}