{
  "type": "Feature",
  "properties": {
    "addr:full":"Mallory Park Racing Circuit, Church Rd, Kirkby Mallory Leicester Leicestershire LE9 7QE",
    "addr:postcode":"le9 7qe",
    "addr:street":"Church Rd",
    "iso:country":"GB",
    "sg:address":"Mallory Park Racing Circuit, Church Rd, Kirkby Mallory",
    "sg:city":"Leicester",
    "sg:classifiers":[
        {
            "category":"Sports & Exercise",
            "subcategory":"Race Track",
            "type":"Entertainment"
        }
    ],
    "sg:phone":"+44 870 789 0888",
    "sg:postcode":"LE9 7QE",
    "sg:province":"Leicestershire",
    "sg:tags":[
        "motor"
    ],
    "wof:name":"Everyman Corporate Events",
    "wof:placetype":"venue"
},
  "geometry": {"coordinates":[-1.330564,52.574306],"type":"Point"}
}