{
  "type": "Feature",
  "properties": {
    "addr:full":"435 Chester Road, Victoria Court Manchester Cheshire M16 0HA",
    "addr:housenumber":"435",
    "addr:postcode":"m16 0ha",
    "addr:street":"Chester Road;Court",
    "iso:country":"GB",
    "sg:address":"435 Chester Road, Victoria Court",
    "sg:city":"Manchester",
    "sg:classifiers":[
        {
            "category":"Professional",
            "subcategory":"Computer Services",
            "type":"Services"
        }
    ],
    "sg:phone":"+44 161 872 0921",
    "sg:postcode":"M16 0HA",
    "sg:province":"Cheshire",
    "sg:tags":[
        "system",
        "software"
    ],
    "wof:name":"C M Y K Computers Ltd.",
    "wof:placetype":"venue"
},
  "geometry": {"coordinates":[-2.277919,53.462921],"type":"Point"}
}