{
  "type": "Feature",
  "properties": {
    "addr:full":"Ludgate, Burgh-by-sands Carlisle Cumbria CA5 6AP",
    "addr:postcode":"ca5 6ap",
    "addr:street":"Ludgate Burgh-By-Sands",
    "iso:country":"GB",
    "sg:address":"Ludgate, Burgh-by-sands",
    "sg:city":"Carlisle",
    "sg:classifiers":[
        {
            "category":"Building & Trades",
            "subcategory":"Construction",
            "type":"Services"
        }
    ],
    "sg:phone":"+44 1228 576418",
    "sg:postcode":"CA5 6AP",
    "sg:province":"Cumbria",
    "sg:tags":[
        "builder"
    ],
    "wof:name":"S.R Thompson",
    "wof:placetype":"venue"
},
  "geometry": {"coordinates":[-3.0603239536,54.9212036133],"type":"Point"}
}