{
  "type": "Feature",
  "properties": {
    "iso:country":"GB",
    "sg:address":"Culcabock Road",
    "sg:city":"Inverness",
    "sg:classifiers":[
        {
            "category":"Shopping",
            "subcategory":"Department Store",
            "type":"Retail Goods"
        },
        {
            "category":"Sports & Exercise",
            "subcategory":"Golf",
            "type":"Entertainment"
        }
    ],
    "sg:phone":"+44 1463 231989",
    "sg:postcode":"IV2 3XQ",
    "sg:province":"Highland",
    "sg:tags":[
        "equipment"
    ],
    "wof:name":"Alastair P Thompson",
    "wof:placetype":"venue"
},
  "geometry": {"coordinates":[-4.204632,57.473141],"type":"Point"}
}