{
  "type": "Feature",
  "properties": {
    "addr:full":"552-554 Bristol Road, Selly Oak Birmingham West Midlands B27 6BD",
    "addr:housenumber":"552-554",
    "addr:postcode":"b27 6bd",
    "addr:street":"Bristol Road",
    "iso:country":"GB",
    "sg:address":"552-554 Bristol Road, Selly Oak",
    "sg:city":"Birmingham",
    "sg:classifiers":[
        {
            "category":"Building & Trades",
            "subcategory":"Cleaning & Sanitation",
            "type":"Services"
        }
    ],
    "sg:postcode":"B27 6BD",
    "sg:province":"West Midlands",
    "sg:tags":[
        "blast"
    ],
    "wof:name":"Materials Enhancement Ltd",
    "wof:placetype":"venue"
},
  "geometry": {"coordinates":[-1.8189400434,52.4495697021],"type":"Point"}
}