{
  "type": "Feature",
  "properties": {
    "iso:country":"GB",
    "sg:address":"15 Albion Road",
    "sg:city":"Scarborough",
    "sg:classifiers":[
        {
            "category":"Social Services",
            "subcategory":"Retirement Home",
            "type":"Services"
        }
    ],
    "sg:postcode":"YO11 2BT",
    "sg:province":"North Yorkshire",
    "sg:tags":[
        "residential",
        "care"
    ],
    "wof:name":"Havenwood Residential Home for the Elderly",
    "wof:placetype":"venue"
},
  "geometry": {"coordinates":[-0.401367,54.275383],"type":"Point"}
}