{
  "type": "Feature",
  "properties": {
    "addr:full":"2a Beetham Road Milnthorpe Cumbria LA7 7QR",
    "addr:housenumber":"2a",
    "addr:postcode":"la7 7qr",
    "addr:street":"Beetham Road",
    "iso:country":"GB",
    "sg:address":"2a Beetham Road",
    "sg:city":"Milnthorpe",
    "sg:classifiers":[
        {
            "category":"Taxi",
            "type":"Transportation"
        },
        {
            "category":"Military Area",
            "subcategory":"Air Force Base",
            "type":"Public Place"
        }
    ],
    "sg:postcode":"LA7 7QR",
    "sg:province":"Cumbria",
    "sg:tags":[
        "mini",
        "hire",
        "private",
        "cab"
    ],
    "wof:name":"Milnthorpe Taxi",
    "wof:placetype":"venue"
},
  "geometry": {"coordinates":[-2.7732620239,54.2267570496],"type":"Point"}
}