{
  "type": "Feature",
  "properties": {
    "addr:full":"Castle Court, 59 Castle Blvd Nottingham Nottinghamshire NG7 1FD",
    "addr:housenumber":"59",
    "addr:postcode":"ng7 1fd",
    "addr:street":"Castle;Castle Blvd",
    "iso:country":"GB",
    "sg:address":"Castle Court, 59 Castle Blvd",
    "sg:city":"Nottingham",
    "sg:classifiers":[
        {
            "category":"Shopping",
            "subcategory":"Pharmacy",
            "type":"Retail Goods"
        }
    ],
    "sg:phone":"+44 115 955 3355",
    "sg:postcode":"NG7 1FD",
    "sg:province":"Nottinghamshire",
    "sg:tags":[
        "pharmaceutical"
    ],
    "wof:name":"Delta Biotechnology Ltd.",
    "wof:placetype":"venue"
},
  "geometry": {"coordinates":[-1.154314,52.948326],"type":"Point"}
}