{
  "type": "Feature",
  "properties": {
    "addr:full":"111 Caernarvon Way, Cowbridge Cardiff Caerphilly CF3 1RX",
    "addr:housenumber":"111",
    "addr:postcode":"cf3 1rx",
    "addr:street":"Caernarvon Way",
    "iso:country":"GB",
    "sg:address":"111 Caernarvon Way, Cowbridge",
    "sg:city":"Cardiff",
    "sg:classifiers":[
        {
            "category":"Shopping",
            "subcategory":"Department Store",
            "type":"Retail Goods"
        }
    ],
    "sg:phone":"+44 29 2079 8936",
    "sg:postcode":"CF3 1RX",
    "sg:province":"Caerphilly",
    "wof:name":"Jays Stores",
    "wof:placetype":"venue"
},
  "geometry": {"coordinates":[-3.110896,51.516193],"type":"Point"}
}