{
  "type": "Feature",
  "properties": {
    "addr:full":"Church St Lutterworth Leicestershire LE17 4AN",
    "addr:postcode":"le17 4an",
    "addr:street":"Church St",
    "iso:country":"GB",
    "sg:address":"Church St",
    "sg:city":"Lutterworth",
    "sg:classifiers":[
        {
            "category":"Place Of Worship",
            "type":"Public Place"
        }
    ],
    "sg:phone":"+44 1455 558797",
    "sg:postcode":"LE17 4AN",
    "sg:province":"Leicestershire",
    "wof:name":"St Mary's Lutterworth",
    "wof:placetype":"venue"
},
  "geometry": {"coordinates":[-1.200691,52.455578],"type":"Point"}
}