{
  "type": "Feature",
  "properties": {
    "iso:country":"GB",
    "sg:address":"Unit 60/65, The Warren, East Goscote",
    "sg:city":"Leicester",
    "sg:classifiers":[
        {
            "category":"Manufacturing",
            "subcategory":"Wood Products",
            "type":"Manufacturing & Wholesale Goods"
        }
    ],
    "sg:phone":"+44 116 264 1060",
    "sg:postcode":"LE7 3XA",
    "sg:province":"Leicestershire",
    "sg:tags":[
        "packaging",
        "crate",
        "pallets"
    ],
    "wof:name":"William Colton & Sons",
    "wof:placetype":"venue"
},
  "geometry": {"coordinates":[-1.046512,52.715782],"type":"Point"}
}