{
  "type": "Feature",
  "properties": {
    "iso:country":"GB",
    "sg:address":"73a Town Street, Armley",
    "sg:city":"Leeds",
    "sg:classifiers":[
        {
            "category":"Professional",
            "subcategory":"Accounting & Tax Preparation",
            "type":"Services"
        }
    ],
    "sg:phone":"+44 113 231 0540",
    "sg:postcode":"LS12 3HD",
    "sg:province":"West Yorkshire",
    "sg:tags":[
        "accountant"
    ],
    "wof:name":"A Dobson",
    "wof:placetype":"venue"
},
  "geometry": {"coordinates":[-1.5924580097,53.7964706421],"type":"Point"}
}