{
  "type": "Feature",
  "properties": {
    "iso:country":"GB",
    "sg:address":"4 South Hill Crescent",
    "sg:city":"Sunderland",
    "sg:classifiers":[
        {
            "category":"Real Estate",
            "subcategory":"Real Estate Agent",
            "type":"Services"
        }
    ],
    "sg:phone":"+44 191 510 2252",
    "sg:postcode":"SR2 7PA",
    "sg:province":"Tyne and Wear",
    "wof:name":"South Hill Properties",
    "wof:placetype":"venue"
},
  "geometry": {"coordinates":[-1.39553,54.901939],"type":"Point"}
}