{
  "type": "Feature",
  "properties": {
    "addr:full":"4 South Hill Crescent Sunderland Tyne and Wear SR2 7PA",
    "addr:housenumber":"4",
    "addr:postcode":"sr2 7pa",
    "addr:street":"South Hill Crescent",
    "iso:country":"GB",
    "sg:address":"4 South Hill Crescent",
    "sg:city":"Sunderland",
    "sg:classifiers":[
        {
            "category":"Real Estate",
            "subcategory":"Real Estate Agent",
            "type":"Services"
        }
    ],
    "sg:phone":"+44 191 510 2252",
    "sg:postcode":"SR2 7PA",
    "sg:province":"Tyne and Wear",
    "wof:name":"South Hill Properties",
    "wof:placetype":"venue"
},
  "geometry": {"coordinates":[-1.39553,54.901939],"type":"Point"}
}