{
  "type": "Feature",
  "properties": {
    "addr:full":"18 Glenville Way, Denton Manchester Greater Manchester M34 6BS",
    "addr:housenumber":"18",
    "addr:postcode":"m34 6bs",
    "addr:street":"Glenville Way",
    "iso:country":"GB",
    "sg:address":"18 Glenville Way, Denton",
    "sg:city":"Manchester",
    "sg:classifiers":[
        {
            "category":"Banks & Credit Unions",
            "subcategory":"Bank",
            "type":"Services"
        }
    ],
    "sg:phone":"+44 161 336 0856",
    "sg:postcode":"M34 6BS",
    "sg:province":"Greater Manchester",
    "sg:tags":[
        "broker",
        "mortgage"
    ],
    "wof:name":"M J Mortgage Services",
    "wof:placetype":"venue"
},
  "geometry": {"coordinates":[-2.10267,53.448994],"type":"Point"}
}