{
  "type": "Feature",
  "properties": {
    "iso:country":"GB",
    "sg:address":"Britannia Wharf, Arctic Rd",
    "sg:city":"Cowes",
    "sg:classifiers":[
        {
            "category":"Manufacturing",
            "subcategory":"Furniture",
            "type":"Manufacturing & Wholesale Goods"
        }
    ],
    "sg:phone":"+44 1983 282999",
    "sg:postcode":"PO31 7PG",
    "sg:province":"Isle of Wight",
    "sg:tags":[
        "mnfr",
        "upholsterer"
    ],
    "wof:name":"J.S Shirlaw",
    "wof:placetype":"venue"
},
  "geometry": {"coordinates":[-1.2978659868,50.7581214905],"type":"Point"}
}