{
  "type": "Feature",
  "properties": {
    "iso:country":"GB",
    "sg:address":"107a The Street, Poringland",
    "sg:city":"Norwich",
    "sg:classifiers":[
        {
            "category":"Real Estate",
            "subcategory":"Real Estate Agent",
            "type":"Services"
        },
        {
            "category":"Real Estate",
            "subcategory":"Architect",
            "type":"Services"
        }
    ],
    "sg:phone":"+44 1508 495050",
    "sg:postcode":"NR14 7RP",
    "sg:province":"Norfolk",
    "wof:name":"Howards (Estate Agents)",
    "wof:placetype":"venue"
},
  "geometry": {"coordinates":[1.348494,52.566841],"type":"Point"}
}