{
  "type": "Feature",
  "properties": {
    "addr:full":"Unit 8 Hertford Industrial Estate, Hertford Street Ashton-under-lyne Greater Manchester OL7 0TB",
    "addr:housenumber":"unit 8;estate",
    "addr:postcode":"ol7 0tb",
    "addr:street":"Industrial;Hertford Street",
    "iso:country":"GB",
    "sg:address":"Unit 8 Hertford Industrial Estate, Hertford Street",
    "sg:city":"Ashton-under-lyne",
    "sg:classifiers":[
        {
            "category":"Shopping",
            "subcategory":"Stationery & Office Supplies",
            "type":"Retail Goods"
        }
    ],
    "sg:phone":"+44 161 330 5093",
    "sg:postcode":"OL7 0TB",
    "sg:province":"Greater Manchester",
    "sg:tags":[
        "printers'"
    ],
    "wof:name":"National Printing Ink Co. Ltd.",
    "wof:placetype":"venue"
},
  "geometry": {"coordinates":[-2.1031301022,53.4810409546],"type":"Point"}
}