{
  "type": "Feature",
  "properties": {
    "addr:full":"105-113 Broadway London Greater London W13 9BE",
    "addr:housenumber":"105-113",
    "addr:postcode":"w13 9be",
    "addr:street":"Broadway",
    "iso:country":"GB",
    "sg:address":"105-113 Broadway",
    "sg:city":"London",
    "sg:classifiers":[
        {
            "category":"Organizations",
            "subcategory":"Community Association",
            "type":"Services"
        }
    ],
    "sg:phone":"+44 20 8840 0423",
    "sg:postcode":"W13 9BE",
    "sg:province":"Greater London",
    "sg:tags":[
        "society",
        "housing"
    ],
    "wof:name":"Northcote Housing Association Ltd.",
    "wof:placetype":"venue"
},
  "geometry": {"coordinates":[-0.3267639875,51.5096817017],"type":"Point"}
}