{
  "type": "Feature",
  "properties": {
    "addr:full":"The Slough, Thaxted Rd, Debden Saffron Walden Essex CB11 3LS",
    "addr:postcode":"cb11 3ls",
    "addr:street":"Thaxted Rd",
    "iso:country":"GB",
    "sg:address":"The Slough, Thaxted Rd, Debden",
    "sg:city":"Saffron Walden",
    "sg:classifiers":[
        {
            "category":"Professional",
            "subcategory":"Research",
            "type":"Services"
        }
    ],
    "sg:phone":"+44 1799 542280",
    "sg:postcode":"CB11 3LS",
    "sg:province":"Essex",
    "sg:tags":[
        "organisation"
    ],
    "wof:name":"Redberry Services",
    "wof:placetype":"venue"
},
  "geometry": {"coordinates":[0.266466,51.976994],"type":"Point"}
}