{
  "type": "Feature",
  "properties": {
    "iso:country":"GB",
    "sg:address":"Embankment House, Woodseats Close",
    "sg:city":"Sheffield",
    "sg:classifiers":[
        {
            "category":"Sports & Exercise",
            "subcategory":"Sports Center",
            "type":"Entertainment"
        }
    ],
    "sg:phone":"+44 114 250 9480",
    "sg:postcode":"S8 0TB",
    "sg:province":"Derbyshire",
    "sg:tags":[
        "coaching"
    ],
    "wof:name":"Champs Sports Camps",
    "wof:placetype":"venue"
},
  "geometry": {"coordinates":[-1.4863209724,53.3508033752],"type":"Point"}
}