{
  "type": "Feature",
  "properties": {
    "iso:country":"GB",
    "sg:address":"Unit 18e Boxer Place, Moss Side Industrial Estate",
    "sg:city":"Preston",
    "sg:classifiers":[
        {
            "category":"Professional",
            "subcategory":"Printing & Photocopies",
            "type":"Services"
        }
    ],
    "sg:phone":"+44 1772 456522",
    "sg:postcode":"PR26 7QL",
    "sg:province":"Lancashire",
    "sg:tags":[
        "process",
        "screen",
        "printer"
    ],
    "wof:name":"Fingerprint",
    "wof:placetype":"venue"
},
  "geometry": {"coordinates":[-2.722046,53.701477],"type":"Point"}
}