{
  "type": "Feature",
  "properties": {
    "iso:country":"GB",
    "sg:address":"Broadway House Surgery, Peter St",
    "sg:city":"Yeovil",
    "sg:classifiers":[
        {
            "category":"Health Services",
            "subcategory":"Health Practitioner",
            "type":"Services"
        }
    ],
    "sg:phone":"+44 1935 476855",
    "sg:postcode":"BA20 1PN",
    "sg:province":"Somerset",
    "sg:tags":[
        "osteopath"
    ],
    "wof:name":"R Campion & Associates",
    "wof:placetype":"venue"
},
  "geometry": {"coordinates":[-2.63071,50.940819],"type":"Point"}
}