{
  "type": "Feature",
  "properties": {
    "addr:full":"Crown St Surgery, 17 Crown Street, Swinton Mexborough South Yorkshire S64 8NB",
    "addr:housenumber":"17",
    "addr:postcode":"s64 8nb",
    "addr:street":"Crown;Crown Street",
    "iso:country":"GB",
    "sg:address":"Crown St Surgery, 17 Crown Street, Swinton",
    "sg:city":"Mexborough",
    "sg:classifiers":[
        {
            "category":"Shopping",
            "subcategory":"Pharmacy",
            "type":"Retail Goods"
        }
    ],
    "sg:phone":"+44 1709 582183",
    "sg:postcode":"S64 8NB",
    "sg:province":"South Yorkshire",
    "sg:tags":[
        "pharmacist",
        "dispensing",
        "chemist"
    ],
    "wof:name":"H I Weldrick Ltd",
    "wof:placetype":"venue"
},
  "geometry": {"coordinates":[-1.317868948,53.4877662659],"type":"Point"}
}