{
  "type": "Feature",
  "properties": {
    "addr:full":"Post Office Buildings, Chapel Street Abergele Conwy LL22 7AW",
    "addr:postcode":"ll22 7aw",
    "addr:street":"Chapel Street",
    "iso:country":"GB",
    "sg:address":"Post Office Buildings, Chapel Street",
    "sg:city":"Abergele",
    "sg:classifiers":[
        {
            "category":"Taxi",
            "type":"Transportation"
        },
        {
            "category":"Military Area",
            "subcategory":"Air Force Base",
            "type":"Public Place"
        }
    ],
    "sg:phone":"+44 1745 825375",
    "sg:postcode":"LL22 7AW",
    "sg:province":"Conwy",
    "sg:tags":[
        "mini",
        "hire",
        "private",
        "cab"
    ],
    "wof:name":"Ken's Taxis",
    "wof:placetype":"venue"
},
  "geometry": {"coordinates":[-3.5811440945,53.2843551636],"type":"Point"}
}