{
  "type": "Feature",
  "properties": {
    "iso:country":"GB",
    "sg:address":"51 Grant Rd",
    "sg:city":"Croydon",
    "sg:classifiers":[
        {
            "category":"Professional",
            "subcategory":"Art Services",
            "type":"Services"
        }
    ],
    "sg:postcode":"CR0 6PJ",
    "sg:province":"Surrey",
    "sg:tags":[
        "photographer"
    ],
    "wof:name":"Bruce,John,",
    "wof:placetype":"venue"
},
  "geometry": {"coordinates":[-0.0786990002,51.3805274963],"type":"Point"}
}