{
  "type": "Feature",
  "properties": {
    "addr:full":"26 Northway Northwich Cheshire CW8 4DF",
    "addr:housenumber":"26",
    "addr:postcode":"cw8 4df",
    "addr:street":"Northway",
    "iso:country":"GB",
    "sg:address":"26 Northway",
    "sg:city":"Northwich",
    "sg:classifiers":[
        {
            "category":"Organizations",
            "subcategory":"Political Organization",
            "type":"Services"
        }
    ],
    "sg:postcode":"CW8 4DF",
    "sg:province":"Cheshire",
    "sg:tags":[
        "party"
    ],
    "wof:name":"Northwich Labour Party",
    "wof:placetype":"venue"
},
  "geometry": {"coordinates":[-2.527939,53.264221],"type":"Point"}
}