{
  "type": "Feature",
  "properties": {
    "iso:country":"GB",
    "sg:address":"The Pines",
    "sg:city":"Doncaster",
    "sg:classifiers":[
        {
            "category":"Professional",
            "subcategory":"Engineering",
            "type":"Services"
        }
    ],
    "sg:phone":"+44 1302 759031",
    "sg:postcode":"DN11 9TZ",
    "sg:province":"South Yorkshire",
    "sg:tags":[
        "consulting",
        "engineer"
    ],
    "wof:name":"Kirby Charles Associates",
    "wof:placetype":"venue"
},
  "geometry": {"coordinates":[-1.130565,53.524391],"type":"Point"}
}