{
  "type": "Feature",
  "properties": {
    "addr:full":"Wilton Church Hall, Dickson Street Hawick Cumbria TD9 7EL",
    "addr:postcode":"td9 7el",
    "addr:street":"Dickson Street",
    "iso:country":"GB",
    "sg:address":"Wilton Church Hall, Dickson Street",
    "sg:city":"Hawick",
    "sg:classifiers":[
        {
            "category":"Farming",
            "subcategory":"Nursery",
            "type":"Manufacturing & Wholesale Goods"
        }
    ],
    "sg:phone":"+44 1450 370170",
    "sg:postcode":"TD9 7EL",
    "sg:province":"Cumbria",
    "sg:tags":[
        "creche"
    ],
    "wof:name":"Sunshine Kindergarten",
    "wof:placetype":"venue"
},
  "geometry": {"coordinates":[-2.787549,55.422146],"type":"Point"}
}