{
  "type": "Feature",
  "properties": {
    "addr:full":"Birdbrook Close Dagenham Essex RM10 9XE",
    "addr:postcode":"rm10 9xe",
    "addr:street":"Birdbrook Close",
    "iso:country":"GB",
    "sg:address":"Birdbrook Close",
    "sg:city":"Dagenham",
    "sg:classifiers":[
        {
            "category":"Home & Garden",
            "subcategory":"Building Materials",
            "type":"Retail Goods"
        }
    ],
    "sg:postcode":"RM10 9XE",
    "sg:province":"Essex",
    "sg:tags":[
        "fencing"
    ],
    "wof:name":"Down to Earth Fencing",
    "wof:placetype":"venue"
},
  "geometry": {"coordinates":[0.166625,51.537987],"type":"Point"}
}