{
  "type": "Feature",
  "properties": {
    "addr:full":"28 Green Lane Addlestone Surrey KT15 2UA",
    "addr:housenumber":"28",
    "addr:postcode":"kt15 2ua",
    "addr:street":"Green Lane",
    "iso:country":"GB",
    "sg:address":"28 Green Lane",
    "sg:city":"Addlestone",
    "sg:classifiers":[
        {
            "category":"Building & Trades",
            "subcategory":"Construction",
            "type":"Services"
        }
    ],
    "sg:phone":"+44 1932 828066",
    "sg:postcode":"KT15 2UA",
    "sg:province":"Surrey",
    "sg:tags":[
        "builder"
    ],
    "wof:name":"K P Brickwork",
    "wof:placetype":"venue"
},
  "geometry": {"coordinates":[-0.4938119948,51.3739700317],"type":"Point"}
}