{
  "type": "Feature",
  "properties": {
    "iso:country":"GB",
    "sg:address":"Unit 2, Trafalgar Way",
    "sg:city":"Camberley",
    "sg:classifiers":[
        {
            "category":"Retail",
            "subcategory":"Storage",
            "type":"Services"
        }
    ],
    "sg:phone":"+44 1276 679661",
    "sg:postcode":"GU15 3BN",
    "sg:province":"Berkshire",
    "sg:tags":[
        "household",
        "removal"
    ],
    "wof:name":"Access Storage Space",
    "wof:placetype":"venue"
},
  "geometry": {"coordinates":[-0.771124,51.332211],"type":"Point"}
}