{
  "type": "Feature",
  "properties": {
    "addr:full":"Unit 2 Llwyn Y Graig, Garnoch Industrial Estate, Gorseinon Swansea Carmarthenshire SA4 9WG",
    "addr:housenumber":"unit 2",
    "addr:postcode":"sa4 9wg",
    "addr:street":"Llwyn Y Graig Garnoch Industrial Estate",
    "iso:country":"GB",
    "sg:address":"Unit 2 Llwyn Y Graig, Garnoch Industrial Estate, Gorseinon",
    "sg:city":"Swansea",
    "sg:classifiers":[
        {
            "category":"Professional",
            "subcategory":"Engineering",
            "type":"Services"
        }
    ],
    "sg:phone":"+44 1792 895111",
    "sg:postcode":"SA4 9WG",
    "sg:province":"Carmarthenshire",
    "sg:tags":[
        "contractor",
        "electrical",
        "engineer"
    ],
    "wof:name":"Amico Enterprises (Wales) Ltd.",
    "wof:placetype":"venue"
},
  "geometry": {"coordinates":[-4.018136,51.665321],"type":"Point"}
}