{
  "type": "Feature",
  "properties": {
    "addr:full":"60 Wyle Cop Shrewsbury Shropshire SY1 1UX",
    "addr:housenumber":"60",
    "addr:postcode":"sy1 1ux",
    "addr:street":"Wyle Cop",
    "iso:country":"GB",
    "sg:address":"60 Wyle Cop",
    "sg:city":"Shrewsbury",
    "sg:classifiers":[
        {
            "category":"Home & Garden",
            "subcategory":"Home Furnishings",
            "type":"Retail Goods"
        }
    ],
    "sg:phone":"+44 1743 351611",
    "sg:postcode":"SY1 1UX",
    "sg:province":"Shropshire",
    "sg:tags":[
        "beds",
        "bedding",
        "blanket"
    ],
    "wof:name":"County Sleep Shop",
    "wof:placetype":"venue"
},
  "geometry": {"coordinates":[-2.7504580021,52.7061805725],"type":"Point"}
}