{
  "type": "Feature",
  "properties": {
    "addr:full":"Unit 4 Rowan Ct, Crystal Dr Smethwick West Midlands B66 1RB",
    "addr:housenumber":"unit 4",
    "addr:postcode":"b66 1rb",
    "addr:street":"Rowan Ct Crystal Dr",
    "iso:country":"GB",
    "sg:address":"Unit 4 Rowan Ct, Crystal Dr",
    "sg:city":"Smethwick",
    "sg:classifiers":[
        {
            "category":"Professional",
            "subcategory":"Engineering",
            "type":"Services"
        }
    ],
    "sg:phone":"+44 121 544 9114",
    "sg:postcode":"B66 1RB",
    "sg:province":"West Midlands",
    "sg:tags":[
        "contractor",
        "electrical",
        "engineer"
    ],
    "wof:name":"All Tec Electrical And Communications",
    "wof:placetype":"venue"
},
  "geometry": {"coordinates":[-1.971184,52.495926],"type":"Point"}
}