{
  "type": "Feature",
  "properties": {
    "iso:country":"GB",
    "sg:address":"Suite 5, 12 Market Place",
    "sg:city":"Spalding",
    "sg:classifiers":[
        {
            "category":"Social Services",
            "subcategory":"Job Training",
            "type":"Services"
        }
    ],
    "sg:phone":"+44 1775 760226",
    "sg:postcode":"PE11 1SL",
    "sg:province":"Lincolnshire",
    "sg:tags":[
        "draughtsman",
        "drawing"
    ],
    "wof:name":"Helter Designs",
    "wof:placetype":"venue"
},
  "geometry": {"coordinates":[-0.1506980062,52.7865257263],"type":"Point"}
}