{
  "type": "Feature",
  "properties": {
    "addr:full":"7 Cornfield Pl Livingston West Lothian EH54 6TE",
    "addr:housenumber":"7",
    "addr:postcode":"eh54 6te",
    "addr:street":"Cornfield Pl",
    "iso:country":"GB",
    "sg:address":"7 Cornfield Pl",
    "sg:city":"Livingston",
    "sg:classifiers":[
        {
            "category":"Home & Garden",
            "subcategory":"Hardware",
            "type":"Retail Goods"
        }
    ],
    "sg:phone":"+44 1506 414727",
    "sg:postcode":"EH54 6TE",
    "sg:province":"West Lothian",
    "sg:tags":[
        "sealant",
        "glue",
        "adhesives"
    ],
    "wof:name":"Technical Sealing Products",
    "wof:placetype":"venue"
},
  "geometry": {"coordinates":[-3.542965889,55.8922348022],"type":"Point"}
}