{
  "type": "Feature",
  "properties": {
    "iso:country":"GB",
    "sg:address":"Huddersfield Road, Haigh",
    "sg:city":"Barnsley",
    "sg:classifiers":[
        {
            "category":"Restaurant",
            "type":"Food & Drink"
        }
    ],
    "sg:phone":"+44 1226 387619",
    "sg:postcode":"S75 4DE",
    "sg:province":"South Yorkshire",
    "wof:name":"The Old Post Office",
    "wof:placetype":"venue"
},
  "geometry": {"coordinates":[-1.550721,53.598026],"type":"Point"}
}