{
  "type": "Feature",
  "properties": {
    "iso:country":"GB",
    "sg:address":"7 Victoria Lane, Whitefield",
    "sg:city":"Manchester",
    "sg:classifiers":[
        {
            "category":"Manufacturing",
            "subcategory":"Rubber & Plastics",
            "type":"Manufacturing & Wholesale Goods"
        },
        {
            "category":"Manufacturing",
            "subcategory":"Textiles",
            "type":"Manufacturing & Wholesale Goods"
        }
    ],
    "sg:phone":"+44 161 766 9819",
    "sg:postcode":"M45 6BL",
    "sg:province":"Lancashire",
    "sg:tags":[
        "made-up",
        "manufacturer"
    ],
    "wof:name":"Rogal Manufacturing Co",
    "wof:placetype":"venue"
},
  "geometry": {"coordinates":[-2.2902860641,53.5452575684],"type":"Point"}
}