{
  "type": "Feature",
  "properties": {
    "iso:country":"GB",
    "sg:address":"55 Chesterfield St, Carlton",
    "sg:city":"Nottingham",
    "sg:classifiers":[
        {
            "category":"Professional",
            "subcategory":"Computer Services",
            "type":"Services"
        }
    ],
    "sg:postcode":"NG4 1EF",
    "sg:province":"Nottinghamshire",
    "sg:tags":[
        "system",
        "software"
    ],
    "wof:name":"Splash Technology",
    "wof:placetype":"venue"
},
  "geometry": {"coordinates":[-1.0943870544,52.9667243958],"type":"Point"}
}