{
  "type": "Feature",
  "properties": {
    "addr:full":"151 Trafalgar Road London Greater London SE10 9TX",
    "addr:housenumber":"151",
    "addr:postcode":"se10 9tx",
    "addr:street":"Trafalgar Road",
    "iso:country":"GB",
    "sg:address":"151 Trafalgar Road",
    "sg:city":"London",
    "sg:classifiers":[
        {
            "category":"Shopping",
            "subcategory":"Clothing, Apparel, & Fashions",
            "type":"Retail Goods"
        }
    ],
    "sg:phone":"+44 20 8293 1280",
    "sg:postcode":"SE10 9TX",
    "sg:province":"Greater London",
    "sg:tags":[
        "t-shirt"
    ],
    "wof:name":"R T Promotions",
    "wof:placetype":"venue"
},
  "geometry": {"coordinates":[0.0030129999,51.4846992493],"type":"Point"}
}