{
  "type": "Feature",
  "properties": {
    "iso:country":"GB",
    "sg:address":"Care Of Bhs, 26 High Rd",
    "sg:city":"Wood Green",
    "sg:classifiers":[
        {
            "category":"Personal",
            "subcategory":"Beauty Salon",
            "type":"Services"
        }
    ],
    "sg:phone":"+44 20 8881 9059",
    "sg:postcode":"N22 6BX",
    "sg:province":"Greater London",
    "sg:tags":[
        "unisex",
        "hairdresser"
    ],
    "wof:name":"Regis Europe Salon",
    "wof:placetype":"venue"
},
  "geometry": {"coordinates":[-0.104208,51.591412],"type":"Point"}
}