{
  "type": "Feature",
  "properties": {
    "addr:full":"Coleridge Vale, Playing Fields, Coleridge Vale Rd North Clevedon Somerset BS21 6PS",
    "addr:postcode":"bs21 6ps",
    "addr:street":"Coleridge Vale Playing;Coleridge Vale Rd North",
    "iso:country":"GB",
    "sg:address":"Coleridge Vale, Playing Fields, Coleridge Vale Rd North",
    "sg:city":"Clevedon",
    "sg:classifiers":[
        {
            "category":"Arena",
            "subcategory":"Sports Club",
            "type":"Entertainment"
        }
    ],
    "sg:phone":"+44 1275 871878",
    "sg:postcode":"BS21 6PS",
    "sg:province":"Somerset",
    "wof:name":"Clevedon United A.F.C.",
    "wof:placetype":"venue"
},
  "geometry": {"coordinates":[-2.855039,51.435925],"type":"Point"}
}