{
  "type": "Feature",
  "properties": {
    "iso:country":"GB",
    "sg:address":"62 Saltisford, Birmigham Road",
    "sg:city":"Warwick",
    "sg:classifiers":[
        {
            "category":"Bars & Pubs",
            "type":"Food & Drink"
        }
    ],
    "sg:phone":"+44 1926 403989",
    "sg:postcode":"CV34 4TD",
    "sg:province":"Warwickshire",
    "sg:tags":[
        "pubs",
        "inn"
    ],
    "wof:name":"The Blackhorse Inn",
    "wof:placetype":"venue"
},
  "geometry": {"coordinates":[-1.592468,52.284771],"type":"Point"}
}