{
  "type": "Feature",
  "properties": {
    "addr:full":"10 Hartley Court Nottingham Nottinghamshire NG7 3AN",
    "addr:housenumber":"10",
    "addr:postcode":"ng7 3an",
    "addr:street":"Hartley Court",
    "iso:country":"GB",
    "sg:address":"10 Hartley Court",
    "sg:city":"Nottingham",
    "sg:classifiers":[
        {
            "category":"Retail",
            "subcategory":"Auto Repair",
            "type":"Services"
        }
    ],
    "sg:phone":"+44 115 979 0153",
    "sg:postcode":"NG7 3AN",
    "sg:province":"Nottinghamshire",
    "sg:tags":[
        "modification",
        "garage"
    ],
    "wof:name":"Layton Motor Services",
    "wof:placetype":"venue"
},
  "geometry": {"coordinates":[-1.171358,52.961105],"type":"Point"}
}