{
  "type": "Feature",
  "properties": {
    "addr:full":"20 Homestead Rd Hull East Riding of Yorkshire HU12 9PT",
    "addr:housenumber":"20",
    "addr:postcode":"hu12 9pt",
    "addr:street":"Homestead Rd",
    "iso:country":"GB",
    "sg:address":"20 Homestead Rd",
    "sg:city":"Hull",
    "sg:classifiers":[
        {
            "category":"Banks & Credit Unions",
            "subcategory":"Bank",
            "type":"Services"
        }
    ],
    "sg:phone":"+44 1964 624994",
    "sg:postcode":"HU12 9PT",
    "sg:province":"East Riding of Yorkshire",
    "sg:tags":[
        "broker",
        "mortgage"
    ],
    "wof:name":"L Thomas",
    "wof:placetype":"venue"
},
  "geometry": {"coordinates":[-0.167249,53.717789],"type":"Point"}
}