{
  "type": "Feature",
  "properties": {
    "iso:country":"GB",
    "sg:address":"502 London Rd, Davenham",
    "sg:city":"Northwich",
    "sg:classifiers":[
        {
            "category":"Banks & Credit Unions",
            "subcategory":"Financial Services",
            "type":"Services"
        }
    ],
    "sg:phone":"+44 1606 352066",
    "sg:postcode":"CW9 8HS",
    "sg:province":"Cheshire",
    "sg:tags":[
        "adviser"
    ],
    "wof:name":"Vale Financial Services",
    "wof:placetype":"venue"
},
  "geometry": {"coordinates":[-2.5125889778,53.2361946106],"type":"Point"}
}