{
  "type": "Feature",
  "properties": {
    "iso:country":"GB",
    "sg:address":"124 Burnley Road, Padiham",
    "sg:city":"Burnley",
    "sg:classifiers":[
        {
            "category":"Shopping",
            "subcategory":"Florist",
            "type":"Retail Goods"
        }
    ],
    "sg:phone":"+44 1282 773062",
    "sg:postcode":"BB12 8QN",
    "sg:province":"Lancashire",
    "wof:name":"Daisy Mae's",
    "wof:placetype":"venue"
},
  "geometry": {"coordinates":[-2.3088729382,53.7989311218],"type":"Point"}
}