{
  "type": "Feature",
  "properties": {
    "iso:country":"GB",
    "sg:address":"242 Peniel Green Road, Llansamlet",
    "sg:city":"Swansea",
    "sg:classifiers":[
        {
            "category":"Education",
            "subcategory":"Library",
            "type":"Public Place"
        }
    ],
    "sg:phone":"+44 1792 771652",
    "sg:postcode":"SA7 9BD",
    "sg:province":"Neath Port Talbot",
    "sg:tags":[
        "book"
    ],
    "wof:name":"Llansamlet Library",
    "wof:placetype":"venue"
},
  "geometry": {"coordinates":[-3.885569,51.662151],"type":"Point"}
}