{
  "type": "Feature",
  "properties": {
    "addr:full":"Penhaligon Building, Trevenson Lane, Pool Redruth Cornwall TR15 3RG",
    "addr:postcode":"tr15 3rg",
    "addr:street":"Trevenson Lane",
    "iso:country":"GB",
    "sg:address":"Penhaligon Building, Trevenson Lane, Pool",
    "sg:city":"Redruth",
    "sg:classifiers":[
        {
            "category":"Education",
            "subcategory":"University",
            "type":"Public Place"
        }
    ],
    "sg:phone":"+44 1209 616901",
    "sg:postcode":"TR15 3RG",
    "sg:province":"Cornwall",
    "sg:tags":[
        "medical",
        "school"
    ],
    "wof:name":"Institute of Health Studies University of Plymouth",
    "wof:placetype":"venue"
},
  "geometry": {"coordinates":[-5.266689,50.228035],"type":"Point"}
}