{
  "type": "Feature",
  "properties": {
    "addr:full":"1 Heol Singleton, Llansaint Kidwelly Carmarthenshire SA17 5JG",
    "addr:housenumber":"1",
    "addr:postcode":"sa17 5jg",
    "addr:street":"Heol Singleton",
    "iso:country":"GB",
    "sg:address":"1 Heol Singleton, Llansaint",
    "sg:city":"Kidwelly",
    "sg:classifiers":[
        {
            "category":"Government",
            "subcategory":"Post Office",
            "type":"Public Place"
        }
    ],
    "sg:phone":"+44 1267 267432",
    "sg:postcode":"SA17 5JG",
    "sg:province":"Carmarthenshire",
    "wof:name":"Llansaint Post Office",
    "wof:placetype":"venue"
},
  "geometry": {"coordinates":[-4.3404188156,51.7479858398],"type":"Point"}
}