{
  "type": "Feature",
  "properties": {
    "iso:country":"GB",
    "sg:address":"51 Hugh Street",
    "sg:city":"London",
    "sg:classifiers":[
        {
            "category":"Bars & Pubs",
            "type":"Food & Drink"
        }
    ],
    "sg:phone":"+44 20 7932 0863",
    "sg:postcode":"SW1V 4PR",
    "sg:province":"Greater London",
    "sg:tags":[
        "pubs",
        "inn"
    ],
    "wof:name":"Punch Inns (U K) Ltd.",
    "wof:placetype":"venue"
},
  "geometry": {"coordinates":[-0.146117,51.491554],"type":"Point"}
}