{
  "type": "Feature",
  "properties": {
    "addr:full":"Huntsman Place, Torwood Retford Nottinghamshire DN22 8NR",
    "addr:postcode":"dn22 8nr",
    "addr:street":"Huntsman Place",
    "iso:country":"GB",
    "sg:address":"Huntsman Place, Torwood",
    "sg:city":"Retford",
    "sg:classifiers":[
        {
            "category":"Food & Beverages",
            "subcategory":"Fruits & Vegetables",
            "type":"Retail Goods"
        }
    ],
    "sg:phone":"+44 1777 816900",
    "sg:postcode":"DN22 8NR",
    "sg:province":"Nottinghamshire",
    "sg:tags":[
        "greengrocer"
    ],
    "wof:name":"A Taylor",
    "wof:placetype":"venue"
},
  "geometry": {"coordinates":[-1.013634,53.375519],"type":"Point"}
}