{
  "type": "Feature",
  "properties": {
    "addr:full":"460 Wilbraham Rd Manchester Cheshire M21 0AG",
    "addr:housenumber":"460",
    "addr:postcode":"m21 0ag",
    "addr:street":"Wilbraham Rd",
    "iso:country":"GB",
    "sg:address":"460 Wilbraham Rd",
    "sg:city":"Manchester",
    "sg:classifiers":[
        {
            "category":"Shopping",
            "subcategory":"Thrift Store",
            "type":"Retail Goods"
        }
    ],
    "sg:phone":"+44 161 860 4004",
    "sg:postcode":"M21 0AG",
    "sg:province":"Cheshire",
    "sg:tags":[
        "shop",
        "charity"
    ],
    "wof:name":"Peoples Dispensary for Sick Animals",
    "wof:placetype":"venue"
},
  "geometry": {"coordinates":[-2.276574,53.442524],"type":"Point"}
}