{
  "type": "Feature",
  "properties": {
    "addr:full":"1 Lowfold Huddersfield West Yorkshire HD5 0JJ",
    "addr:housenumber":"1",
    "addr:postcode":"hd5 0jj",
    "addr:street":"Lowfold Huddersfield West",
    "iso:country":"GB",
    "sg:address":"1 Lowfold",
    "sg:city":"Huddersfield",
    "sg:classifiers":[
        {
            "category":"Professional",
            "subcategory":"Management & Consulting",
            "type":"Services"
        }
    ],
    "sg:phone":"+44 1484 304055",
    "sg:postcode":"HD5 0JJ",
    "sg:province":"West Yorkshire",
    "sg:tags":[
        "consultant",
        "specialist"
    ],
    "wof:name":"Elegance Mobile Beauty Therapy",
    "wof:placetype":"venue"
},
  "geometry": {"coordinates":[-1.725649,53.65992],"type":"Point"}
}