{
  "type": "Feature",
  "properties": {
    "addr:full":"62 Westgate Wetherby North Yorkshire LS22 6NJ",
    "addr:housenumber":"62",
    "addr:postcode":"ls22 6nj",
    "addr:street":"Westgate",
    "iso:country":"GB",
    "sg:address":"62 Westgate",
    "sg:city":"Wetherby",
    "sg:classifiers":[
        {
            "category":"Home & Garden",
            "subcategory":"Furniture",
            "type":"Retail Goods"
        }
    ],
    "sg:phone":"+44 1937 584846",
    "sg:postcode":"LS22 6NJ",
    "sg:province":"North Yorkshire",
    "wof:name":"Hopkinson Soft Furnishings",
    "wof:placetype":"venue"
},
  "geometry": {"coordinates":[-1.392749,53.930061],"type":"Point"}
}