{
  "type": "Feature",
  "properties": {
    "addr:full":"2 Eastgate Lincoln Lincolnshire LN2 1QA",
    "addr:housenumber":"2",
    "addr:postcode":"ln2 1qa",
    "addr:street":"Eastgate Lincoln",
    "iso:country":"GB",
    "sg:address":"2 Eastgate",
    "sg:city":"Lincoln",
    "sg:classifiers":[
        {
            "category":"Real Estate",
            "subcategory":"Surveying",
            "type":"Services"
        }
    ],
    "sg:phone":"+44 1522 544444",
    "sg:postcode":"LN2 1QA",
    "sg:province":"Lincolnshire",
    "sg:tags":[
        "surveyor",
        "valuer"
    ],
    "sg:website":"http://www.humberts.co.uk",
    "wof:name":"Humberts",
    "wof:placetype":"venue"
},
  "geometry": {"coordinates":[-0.5383189917,53.2349777222],"type":"Point"}
}