{
  "type": "Feature",
  "properties": {
    "iso:country":"GB",
    "sg:address":"Unit 1b, Walney Road Industrial Estate",
    "sg:city":"Barrow-in-furness",
    "sg:classifiers":[
        {
            "category":"Manufacturing",
            "subcategory":"Signs",
            "type":"Manufacturing & Wholesale Goods"
        }
    ],
    "sg:phone":"+44 1229 823333",
    "sg:postcode":"LA14 5UG",
    "sg:province":"Cumbria",
    "sg:tags":[
        "maker"
    ],
    "wof:name":"Instant Signs & Design Ltd.",
    "wof:placetype":"venue"
},
  "geometry": {"coordinates":[-3.238072,54.122681],"type":"Point"}
}