{
  "type": "Feature",
  "properties": {
    "addr:full":"R A Smith & Co, 1 Church Hill Leigh-on-sea Essex SS9 2DE",
    "addr:housenumber":"1",
    "addr:postcode":"ss9 2de",
    "addr:street":"R;Church Hill",
    "iso:country":"GB",
    "sg:address":"R A Smith & Co, 1 Church Hill",
    "sg:city":"Leigh-on-sea",
    "sg:classifiers":[
        {
            "category":"Travel",
            "subcategory":"Travel Agent",
            "type":"Entertainment"
        }
    ],
    "sg:postcode":"SS9 2DE",
    "sg:province":"Essex",
    "wof:name":"Keytour Ltd",
    "wof:placetype":"venue"
},
  "geometry": {"coordinates":[0.654030025,51.5409011841],"type":"Point"}
}