{
  "type": "Feature",
  "properties": {
    "addr:full":"38a Circus Lodge, Circus Rd St John's Wood Greater London NW8 9JN",
    "addr:housenumber":"38a",
    "addr:postcode":"nw8 9jn",
    "addr:street":"Circus Lodge Circus Rd",
    "iso:country":"GB",
    "sg:address":"38a Circus Lodge, Circus Rd",
    "sg:city":"St John's Wood",
    "sg:classifiers":[
        {
            "category":"Professional",
            "subcategory":"Lawyer & Legal Services",
            "type":"Services"
        }
    ],
    "sg:phone":"+44 20 7266 1676",
    "sg:postcode":"NW8 9JN",
    "sg:province":"Greater London",
    "sg:tags":[
        "advice",
        "counselling"
    ],
    "wof:name":"Living Water Centre",
    "wof:placetype":"venue"
},
  "geometry": {"coordinates":[-0.1752350032,51.5311470032],"type":"Point"}
}