{
  "type": "Feature",
  "properties": {
    "addr:full":"Seath Road, Rutherglen Glasgow Glasgow City G73 1RW",
    "addr:postcode":"g73 1rw",
    "addr:street":"Seath Road",
    "iso:country":"GB",
    "sg:address":"Seath Road, Rutherglen",
    "sg:city":"Glasgow",
    "sg:classifiers":[
        {
            "category":"Wholesale",
            "subcategory":"Scrap",
            "type":"Manufacturing & Wholesale Goods"
        }
    ],
    "sg:postcode":"G73 1RW",
    "sg:province":"Glasgow City",
    "sg:tags":[
        "breaker",
        "dismantlers"
    ],
    "wof:name":"Birnam Motor Salvage",
    "wof:placetype":"venue"
},
  "geometry": {"coordinates":[-4.2177472115,55.8333625793],"type":"Point"}
}