{
  "type": "Feature",
  "properties": {
    "addr:full":"Grove Manor, 24-26 Grove Pk Liverpool Merseyside L8 0TL",
    "addr:housenumber":"24-26",
    "addr:postcode":"l8 0tl",
    "addr:street":"Grove Pk",
    "iso:country":"GB",
    "sg:address":"Grove Manor, 24-26 Grove Pk",
    "sg:city":"Liverpool",
    "sg:classifiers":[
        {
            "category":"Shopping",
            "subcategory":"Pharmacy",
            "type":"Retail Goods"
        }
    ],
    "sg:phone":"+44 151 733 8955",
    "sg:postcode":"L8 0TL",
    "sg:province":"Merseyside",
    "sg:tags":[
        "medical"
    ],
    "wof:name":"T R S Electronics Ltd",
    "wof:placetype":"venue"
},
  "geometry": {"coordinates":[-2.9477300644,53.3909301758],"type":"Point"}
}