{
  "type": "Feature",
  "properties": {
    "addr:full":"Pinder House, 249 Upper Third Street, Wiran Gate West Milton Keynes Buckinghamshire MK9 1DS",
    "addr:housenumber":"249",
    "addr:postcode":"mk9 1ds",
    "addr:street":"Upper Third Street Wiran Gate West",
    "iso:country":"GB",
    "sg:address":"Pinder House, 249 Upper Third Street, Wiran Gate West",
    "sg:city":"Milton Keynes",
    "sg:classifiers":[
        {
            "category":"Professional",
            "type":"Services"
        }
    ],
    "sg:phone":"+44 1908 350550",
    "sg:postcode":"MK9 1DS",
    "sg:province":"Buckinghamshire",
    "sg:tags":[
        "repair",
        "tech",
        "maintenance"
    ],
    "wof:name":"Venners Computer Systems Ltd.",
    "wof:placetype":"venue"
},
  "geometry": {"coordinates":[-0.7681490183,52.0384750366],"type":"Point"}
}