{
  "type": "Feature",
  "properties": {
    "iso:country":"GB",
    "sg:address":"The Hawthorns, Froghall",
    "sg:city":"Stoke-on-trent",
    "sg:classifiers":[
        {
            "category":"Wholesale",
            "subcategory":"Scrap",
            "type":"Manufacturing & Wholesale Goods"
        }
    ],
    "sg:phone":"+44 1538 754814",
    "sg:postcode":"ST10 2HA",
    "sg:province":"Staffordshire",
    "sg:tags":[
        "breaker",
        "dismantlers"
    ],
    "wof:name":"Auto Line Motor Salvage",
    "wof:placetype":"venue"
},
  "geometry": {"coordinates":[-1.965634,53.024773],"type":"Point"}
}