{
  "type": "Feature",
  "properties": {
    "addr:full":"Trunkwell Park, Beech Hill Road, Beech Hill Reading Berkshire RG7 2AT",
    "addr:postcode":"rg7 2at",
    "addr:street":"Beech Hill Road",
    "iso:country":"GB",
    "sg:address":"Trunkwell Park, Beech Hill Road, Beech Hill",
    "sg:city":"Reading",
    "sg:classifiers":[
        {
            "category":"Organizations",
            "subcategory":"Non-profit Organization",
            "type":"Services"
        }
    ],
    "sg:phone":"+44 118 988 5688",
    "sg:postcode":"RG7 2AT",
    "sg:province":"Berkshire",
    "sg:tags":[
        "charitable",
        "organisation",
        "voluntary",
        "charity"
    ],
    "sg:website":"http://www.thrive.org.uk",
    "wof:name":"Society For Horticultural Therapy",
    "wof:placetype":"venue"
},
  "geometry": {"coordinates":[-0.9997429848,51.3732414246],"type":"Point"}
}