{
  "type": "Feature",
  "properties": {
    "addr:full":"1 Kings Place, Kings Avenue Muswell Hill Greater London N10 1PA",
    "addr:housenumber":"1",
    "addr:postcode":"n10 1pa",
    "addr:street":"Kings Place Kings Avenue",
    "iso:country":"GB",
    "sg:address":"1 Kings Place, Kings Avenue",
    "sg:city":"Muswell Hill",
    "sg:classifiers":[
        {
            "category":"Shopping",
            "subcategory":"Photographic Equipment",
            "type":"Retail Goods"
        }
    ],
    "sg:phone":"+44 20 8374 7578",
    "sg:postcode":"N10 1PA",
    "sg:province":"Greater London",
    "wof:name":"Muswell Hill Photographics",
    "wof:placetype":"venue"
},
  "geometry": {"coordinates":[-0.1471299976,51.5924682617],"type":"Point"}
}