{
  "type": "Feature",
  "properties": {
    "addr:full":"503 Lordship Lane London Greater London SE22 8JY",
    "addr:housenumber":"503",
    "addr:postcode":"se22 8jy",
    "addr:street":"Lordship Lane",
    "iso:country":"GB",
    "sg:address":"503 Lordship Lane",
    "sg:city":"London",
    "sg:classifiers":[
        {
            "category":"Transit Center",
            "subcategory":"Passenger",
            "type":"Transportation"
        }
    ],
    "sg:phone":"+44 20 8299 0132",
    "sg:postcode":"SE22 8JY",
    "sg:province":"Greater London",
    "sg:tags":[
        "boarding",
        "kennel",
        "catteries"
    ],
    "wof:name":"Wastdale Pet Shop & Cattery",
    "wof:placetype":"venue"
},
  "geometry": {"coordinates":[-0.067931,51.443832],"type":"Point"}
}