{
  "type": "Feature",
  "properties": {
    "iso:country":"GB",
    "sg:address":"P O Box 251",
    "sg:city":"Bristol",
    "sg:classifiers":[
        {
            "category":"Professional",
            "subcategory":"Management & Consulting",
            "type":"Services"
        }
    ],
    "sg:phone":"+44 117 942 6660",
    "sg:postcode":"BS99 1HP",
    "sg:province":"City of Bristol",
    "sg:tags":[
        "consultant",
        "energy",
        "conservation"
    ],
    "wof:name":"Costplug Ltd.",
    "wof:placetype":"venue"
},
  "geometry": {"coordinates":[-2.58545,51.45026],"type":"Point"}
}