{
  "type": "Feature",
  "properties": {
    "addr:full":"Po Box 56 Southampton Hampshire SO14 5DA",
    "addr:housenumber":"po box 56",
    "addr:postcode":"so14 5da",
    "iso:country":"GB",
    "sg:address":"Po Box 56",
    "sg:city":"Southampton",
    "sg:classifiers":[
        {
            "category":"Professional",
            "subcategory":"Art Services",
            "type":"Services"
        }
    ],
    "sg:phone":"+44 23 8040 6570",
    "sg:postcode":"SO14 5DA",
    "sg:province":"Hampshire",
    "sg:tags":[
        "consultant",
        "design"
    ],
    "wof:name":"Sherwill Design",
    "wof:placetype":"venue"
},
  "geometry": {"coordinates":[-1.3865400553,50.9097213745],"type":"Point"}
}