{
  "type": "Feature",
  "properties": {
    "addr:full":"81 Coal Clough Lane Burnley Lancashire BB11 4NS",
    "addr:housenumber":"81",
    "addr:postcode":"bb11 4ns",
    "addr:street":"Coal Clough Lane",
    "iso:country":"GB",
    "sg:address":"81 Coal Clough Lane",
    "sg:city":"Burnley",
    "sg:classifiers":[
        {
            "category":"Personal",
            "subcategory":"Barber",
            "type":"Services"
        }
    ],
    "sg:postcode":"BB11 4NS",
    "sg:province":"Lancashire",
    "sg:tags":[
        "men's",
        "hairdresser"
    ],
    "wof:name":"Pauls Barbers",
    "wof:placetype":"venue"
},
  "geometry": {"coordinates":[-2.258479,53.785515],"type":"Point"}
}