{
  "type": "Feature",
  "properties": {
    "addr:full":"Service Road Forfar Angus DD8 3ER",
    "addr:postcode":"dd8 3er",
    "addr:street":"Service Road",
    "iso:country":"GB",
    "sg:address":"Service Road",
    "sg:city":"Forfar",
    "sg:classifiers":[
        {
            "category":"Retail",
            "subcategory":"Car Wash",
            "type":"Services"
        },
        {
            "category":"Retail",
            "subcategory":"Auto Repair",
            "type":"Services"
        }
    ],
    "sg:phone":"+44 1307 467138",
    "sg:postcode":"DD8 3ER",
    "sg:province":"Angus",
    "sg:tags":[
        "sprayer",
        "painter"
    ],
    "wof:name":"Milne & Wilson",
    "wof:placetype":"venue"
},
  "geometry": {"coordinates":[-2.8802399635,56.6498565674],"type":"Point"}
}