{
  "type": "Feature",
  "properties": {
    "addr:full":"Manor Farm, Catthorpe Lutterworth Leicestershire LE17 6DB",
    "addr:postcode":"le17 6db",
    "addr:street":"Manor",
    "iso:country":"GB",
    "sg:address":"Manor Farm, Catthorpe",
    "sg:city":"Lutterworth",
    "sg:classifiers":[
        {
            "category":"Farming",
            "subcategory":"Farm",
            "type":"Manufacturing & Wholesale Goods"
        }
    ],
    "sg:phone":"+44 1788 860470",
    "sg:postcode":"LE17 6DB",
    "sg:province":"Leicestershire",
    "sg:tags":[
        "mixed",
        "crop"
    ],
    "wof:name":"M G Grindal",
    "wof:placetype":"venue"
},
  "geometry": {"coordinates":[-1.1881680489,52.3986206055],"type":"Point"}
}