{
  "type": "Feature",
  "properties": {
    "iso:country":"GB",
    "sg:address":"53 Parsons St",
    "sg:city":"Banbury",
    "sg:classifiers":[
        {
            "category":"Travel",
            "subcategory":"Travel Agent",
            "type":"Entertainment"
        }
    ],
    "sg:phone":"+44 1295 269494",
    "sg:postcode":"OX16 8NB",
    "sg:province":"Oxfordshire",
    "wof:name":"Jeffs Travel",
    "wof:placetype":"venue"
},
  "geometry": {"coordinates":[-1.337109,52.06242],"type":"Point"}
}