{
  "type": "Feature",
  "properties": {
    "iso:country":"GB",
    "sg:address":"Royal London House 22-25, Finsbury Square,",
    "sg:city":"London",
    "sg:classifiers":[
        {
            "category":"Organizations",
            "subcategory":"Community Association",
            "type":"Services"
        }
    ],
    "sg:postcode":"EC2A 1DS",
    "sg:province":"Greater London",
    "sg:tags":[
        "relation",
        "public"
    ],
    "wof:name":"Holborn Public Relations Ltd",
    "wof:placetype":"venue"
},
  "geometry": {"coordinates":[-0.0870189965,51.5215797424],"type":"Point"}
}