{
  "type": "Feature",
  "properties": {
    "iso:country":"GB",
    "sg:address":"4 Station Rd",
    "sg:city":"Folkestone",
    "sg:classifiers":[
        {
            "category":"Home & Garden",
            "subcategory":"Hardware",
            "type":"Retail Goods"
        }
    ],
    "sg:phone":"+44 1303 862105",
    "sg:postcode":"CT18 8HP",
    "sg:province":"Kent",
    "wof:name":"Gills Hardware Store",
    "wof:placetype":"venue"
},
  "geometry": {"coordinates":[1.091621,51.127762],"type":"Point"}
}