{
  "type": "Feature",
  "properties": {
    "addr:full":"Within Children Worlds, Trafalgar Way Croydon Surrey CR9 4PB",
    "addr:postcode":"cr9 4pb",
    "addr:street":"Trafalgar Way",
    "iso:country":"GB",
    "sg:address":"Within Children Worlds, Trafalgar Way",
    "sg:city":"Croydon",
    "sg:classifiers":[
        {
            "category":"Shopping",
            "subcategory":"Shoes",
            "type":"Retail Goods"
        }
    ],
    "sg:phone":"+44 20 8686 2571",
    "sg:postcode":"CR9 4PB",
    "sg:province":"Surrey",
    "sg:tags":[
        "shop"
    ],
    "wof:name":"Clarks Shoes",
    "wof:placetype":"venue"
},
  "geometry": {"coordinates":[-0.099451,51.372349],"type":"Point"}
}