{
  "type": "Feature",
  "properties": {
    "addr:full":"13 Woodmansterne Street Banstead Surrey SM7 3NW",
    "addr:housenumber":"13",
    "addr:postcode":"sm7 3nw",
    "addr:street":"Woodmansterne Street",
    "iso:country":"GB",
    "sg:address":"13 Woodmansterne Street",
    "sg:city":"Banstead",
    "sg:classifiers":[
        {
            "category":"Professional",
            "subcategory":"Accounting & Tax Preparation",
            "type":"Services"
        }
    ],
    "sg:phone":"+44 1737 379264",
    "sg:postcode":"SM7 3NW",
    "sg:province":"Surrey",
    "sg:tags":[
        "accountant"
    ],
    "wof:name":"Simon Cook & Associates",
    "wof:placetype":"venue"
},
  "geometry": {"coordinates":[-0.191529,51.325157],"type":"Point"}
}