{
  "type": "Feature",
  "properties": {
    "iso:country":"GB",
    "sg:address":"Wind Whistle, Cockmarsh",
    "sg:city":"Bourne End",
    "sg:classifiers":[
        {
            "category":"Government",
            "subcategory":"Office",
            "type":"Public Place"
        }
    ],
    "sg:phone":"+44 1628 528334",
    "sg:postcode":"SL8 5RG",
    "sg:province":"Berkshire",
    "sg:tags":[
        "education",
        "agency",
        "authority"
    ],
    "wof:name":"Dyslexia Centre",
    "wof:placetype":"venue"
},
  "geometry": {"coordinates":[-0.713174,51.579506],"type":"Point"}
}