{
  "type": "Feature",
  "properties": {
    "iso:country":"GB",
    "sg:address":"Unit 7 8 Burton Rd",
    "sg:city":"Blackpool",
    "sg:classifiers":[
        {
            "category":"Home & Garden",
            "subcategory":"Home Furnishings",
            "type":"Retail Goods"
        }
    ],
    "sg:phone":"+44 1253 695555",
    "sg:postcode":"FY4 4NW",
    "sg:province":"Lancashire",
    "sg:tags":[
        "merchant",
        "diy",
        "decorators'"
    ],
    "wof:name":"Miller Corporation Ltd",
    "wof:placetype":"venue"
},
  "geometry": {"coordinates":[-3.018436,53.798466],"type":"Point"}
}