{
  "type": "Feature",
  "properties": {
    "iso:country":"GB",
    "sg:address":"29 Warley Hall Road",
    "sg:city":"Oldbury",
    "sg:classifiers":[
        {
            "category":"Arts & Performance",
            "subcategory":"Music",
            "type":"Entertainment"
        }
    ],
    "sg:postcode":"B68 9JR",
    "sg:province":"West Midlands",
    "sg:tags":[
        "mobile",
        "disco"
    ],
    "wof:name":"The T C B Roadshow Mobile Disco",
    "wof:placetype":"venue"
},
  "geometry": {"coordinates":[-1.991757,52.472637],"type":"Point"}
}