{
  "type": "Feature",
  "properties": {
    "iso:country":"GB",
    "sg:address":"80 Beechings Way",
    "sg:city":"Gillingham",
    "sg:classifiers":[
        {
            "category":"Communications",
            "subcategory":"Newspaper",
            "type":"Services"
        }
    ],
    "sg:phone":"+44 1634 264857",
    "sg:postcode":"ME8 6LX",
    "sg:province":"Kent",
    "sg:tags":[
        "magazine"
    ],
    "wof:name":"Terra Nova Childrens Publications",
    "wof:placetype":"venue"
},
  "geometry": {"coordinates":[0.582817,51.378262],"type":"Point"}
}