{
  "type": "Feature",
  "properties": {
    "addr:full":"5 Dace Road London Greater London E3 2NG",
    "addr:housenumber":"5",
    "addr:postcode":"e3 2ng",
    "addr:street":"Dace Road",
    "iso:country":"GB",
    "sg:address":"5 Dace Road",
    "sg:city":"London",
    "sg:classifiers":[
        {
            "category":"Shopping",
            "subcategory":"Clothing, Apparel, & Fashions",
            "type":"Retail Goods"
        }
    ],
    "sg:phone":"+44 20 8986 3300",
    "sg:postcode":"E3 2NG",
    "sg:province":"Greater London",
    "sg:tags":[
        "t-shirt"
    ],
    "wof:name":"Bakersville Ltd.",
    "wof:placetype":"venue"
},
  "geometry": {"coordinates":[-0.0231790002,51.5335006714],"type":"Point"}
}