{
  "type": "Feature",
  "properties": {
    "iso:country":"GB",
    "sg:address":"42 Bedford Row",
    "sg:city":"London",
    "sg:classifiers":[
        {
            "category":"Professional",
            "subcategory":"Computer Services",
            "type":"Services"
        }
    ],
    "sg:phone":"+44 1344 891008",
    "sg:postcode":"WC1R 4JL",
    "sg:province":"Greater London",
    "sg:tags":[
        "system",
        "software"
    ],
    "wof:name":"Mpi Tech Ltd.",
    "wof:placetype":"venue"
},
  "geometry": {"coordinates":[-0.115926,51.519238],"type":"Point"}
}