{
  "type": "Feature",
  "properties": {
    "addr:full":"Braeside Park Avenue, Rawdon Leeds West Yorkshire LS19 6ER",
    "addr:postcode":"ls19 6er",
    "addr:street":"Park Avenue",
    "iso:country":"GB",
    "sg:address":"Braeside Park Avenue, Rawdon",
    "sg:city":"Leeds",
    "sg:classifiers":[
        {
            "category":"Building & Trades",
            "subcategory":"Plumbing",
            "type":"Services"
        }
    ],
    "sg:phone":"+44 113 250 4574",
    "sg:postcode":"LS19 6ER",
    "sg:province":"West Yorkshire",
    "sg:tags":[
        "heating"
    ],
    "wof:name":"Chris Jennings Plumbing & Heating",
    "wof:placetype":"venue"
},
  "geometry": {"coordinates":[-1.682068,53.855892],"type":"Point"}
}