{
  "type": "Feature",
  "properties": {
    "addr:full":"10 Vine Crescent Reading Berkshire RG30 3LU",
    "addr:housenumber":"10",
    "addr:postcode":"rg30 3lu",
    "addr:street":"Vine Crescent",
    "iso:country":"GB",
    "sg:address":"10 Vine Crescent",
    "sg:city":"Reading",
    "sg:classifiers":[
        {
            "category":"Home & Garden",
            "subcategory":"Household Appliances",
            "type":"Retail Goods"
        }
    ],
    "sg:postcode":"RG30 3LU",
    "sg:province":"Berkshire",
    "sg:tags":[
        "electrical"
    ],
    "wof:name":"Artic Refrigeration",
    "wof:placetype":"venue"
},
  "geometry": {"coordinates":[-1.0208280087,51.4393157959],"type":"Point"}
}