{
  "type": "Feature",
  "properties": {
    "iso:country":"GB",
    "sg:address":"The Old School House, Kirklington",
    "sg:city":"Bedale",
    "sg:classifiers":[
        {
            "category":"Professional",
            "subcategory":"Management & Consulting",
            "type":"Services"
        }
    ],
    "sg:phone":"+44 1845 567295",
    "sg:postcode":"DL8 2NG",
    "sg:province":"North Yorkshire",
    "sg:tags":[
        "consultant",
        "business"
    ],
    "wof:name":"Tim Kendall Consultancy Ltd.",
    "wof:placetype":"venue"
},
  "geometry": {"coordinates":[-1.5120830536,54.2241210938],"type":"Point"}
}