{
  "type": "Feature",
  "properties": {
    "iso:country":"GB",
    "sg:address":"2nd Floor The Nethergate Centre, 35 Yeaman Shore",
    "sg:city":"Dundee",
    "sg:classifiers":[
        {
            "category":"Banks & Credit Unions",
            "subcategory":"Financial Services",
            "type":"Services"
        }
    ],
    "sg:phone":"+44 1382 372700",
    "sg:postcode":"DD1 4BU",
    "sg:province":"Dundee City",
    "sg:tags":[
        "consultant"
    ],
    "wof:name":"Allied Dunbar Assurance Plc",
    "wof:placetype":"venue"
},
  "geometry": {"coordinates":[-2.9676089287,56.4613761902],"type":"Point"}
}