{
  "type": "Feature",
  "properties": {
    "iso:country":"GB",
    "sg:address":"26 Bagnall Road, Milton",
    "sg:city":"Stoke-on-trent",
    "sg:classifiers":[
        {
            "category":"Food & Beverages",
            "subcategory":"Liquor & Beverages",
            "type":"Retail Goods"
        }
    ],
    "sg:postcode":"ST2 7AZ",
    "sg:province":"Staffordshire",
    "sg:tags":[
        "beer",
        "spirit",
        "wines"
    ],
    "wof:name":"J D's",
    "wof:placetype":"venue"
},
  "geometry": {"coordinates":[-2.137958,53.049564],"type":"Point"}
}