{
  "type": "Feature",
  "properties": {
    "addr:full":"26 Wrestwood Avenue Eastbourne East Sussex BN22 0HB",
    "addr:housenumber":"26",
    "addr:postcode":"bn22 0hb",
    "addr:street":"Wrestwood Avenue",
    "iso:country":"GB",
    "sg:address":"26 Wrestwood Avenue",
    "sg:city":"Eastbourne",
    "sg:classifiers":[
        {
            "category":"Building & Trades",
            "subcategory":"Construction",
            "type":"Services"
        }
    ],
    "sg:phone":"+44 1323 506666",
    "sg:postcode":"BN22 0HB",
    "sg:province":"East Sussex",
    "sg:tags":[
        "builder"
    ],
    "wof:name":"D Roche (Builders) Ltd.",
    "wof:placetype":"venue"
},
  "geometry": {"coordinates":[0.259024,50.79731],"type":"Point"}
}