{
  "type": "Feature",
  "properties": {
    "addr:full":"27-29 Bridge Pl Worksop Nottinghamshire S80 1DA",
    "addr:housenumber":"27-29",
    "addr:postcode":"s80 1da",
    "addr:street":"Bridge Pl",
    "iso:country":"GB",
    "sg:address":"27-29 Bridge Pl",
    "sg:city":"Worksop",
    "sg:classifiers":[
        {
            "category":"Shopping",
            "subcategory":"Clothing, Apparel, & Fashions",
            "type":"Retail Goods"
        }
    ],
    "sg:postcode":"S80 1DA",
    "sg:province":"Nottinghamshire",
    "sg:tags":[
        "shop"
    ],
    "wof:name":"Mackays Stores Ltd",
    "wof:placetype":"venue"
},
  "geometry": {"coordinates":[-1.1238609552,53.3058662415],"type":"Point"}
}