{
  "type": "Feature",
  "properties": {
    "iso:country":"GB",
    "sg:address":"10 Cottingley Road, Allerton",
    "sg:city":"Bradford",
    "sg:classifiers":[
        {
            "category":"Personal",
            "subcategory":"Beauty Salon",
            "type":"Services"
        }
    ],
    "sg:phone":"+44 1274 773544",
    "sg:postcode":"BD15 9JP",
    "sg:province":"West Yorkshire",
    "sg:tags":[
        "unisex",
        "ladies",
        "hairdresser"
    ],
    "wof:name":"Cut 'N' Dried",
    "wof:placetype":"venue"
},
  "geometry": {"coordinates":[-1.832991,53.813869],"type":"Point"}
}