{
  "type": "Feature",
  "properties": {
    "addr:full":"1a South Place Waltham Abbey Essex EN9 1EP",
    "addr:housenumber":"1a",
    "addr:postcode":"en9 1ep",
    "addr:street":"South Place Waltham Abbey",
    "iso:country":"GB",
    "sg:address":"1a South Place",
    "sg:city":"Waltham Abbey",
    "sg:classifiers":[
        {
            "category":"Shopping",
            "subcategory":"Clothing, Apparel, & Fashions",
            "type":"Retail Goods"
        }
    ],
    "sg:phone":"+44 1992 715966",
    "sg:postcode":"EN9 1EP",
    "sg:province":"Essex",
    "sg:tags":[
        "clothing"
    ],
    "wof:name":"J & R Supplies",
    "wof:placetype":"venue"
},
  "geometry": {"coordinates":[0.0014900001,51.6864204407],"type":"Point"}
}