{
  "type": "Feature",
  "properties": {
    "iso:country":"GB",
    "sg:address":"Blundellsands Road West",
    "sg:city":"Liverpool",
    "sg:classifiers":[
        {
            "category":"Government",
            "subcategory":"Office",
            "type":"Public Place"
        }
    ],
    "sg:postcode":"L23 6TF",
    "sg:province":"Merseyside",
    "sg:tags":[
        "education",
        "agency",
        "authority"
    ],
    "wof:name":"Blundellsands Kindergarten",
    "wof:placetype":"venue"
},
  "geometry": {"coordinates":[-3.041674,53.486839],"type":"Point"}
}