{
  "type": "Feature",
  "properties": {
    "iso:country":"GB",
    "sg:address":"Leamington Close",
    "sg:city":"Derby",
    "sg:classifiers":[
        {
            "category":"Health Services",
            "subcategory":"Nursing And Care Facility",
            "type":"Services"
        },
        {
            "category":"Social Services",
            "subcategory":"Retirement Home",
            "type":"Services"
        }
    ],
    "sg:phone":"+44 1332 776904",
    "sg:postcode":"DE23 6HF",
    "sg:province":"Derbyshire",
    "sg:tags":[
        "residential"
    ],
    "wof:name":"Windy Ridge",
    "wof:placetype":"venue"
},
  "geometry": {"coordinates":[-1.496174,52.90572],"type":"Point"}
}