{
  "type": "Feature",
  "properties": {
    "iso:country":"GB",
    "sg:address":"1 Vincent Avenue, Crownhill",
    "sg:city":"Milton Keynes",
    "sg:classifiers":[
        {
            "category":"Shopping",
            "subcategory":"Clothing, Apparel, & Fashions",
            "type":"Retail Goods"
        }
    ],
    "sg:phone":"+44 1908 262101",
    "sg:postcode":"MK8 0AB",
    "sg:province":"Buckinghamshire",
    "sg:tags":[
        "ladieswear"
    ],
    "wof:name":"Weekenders U K Ltd.",
    "wof:placetype":"venue"
},
  "geometry": {"coordinates":[-0.801476,52.030056],"type":"Point"}
}