{
  "type": "Feature",
  "properties": {
    "addr:full":"5 Dalmahoy Road, Ratho Newbridge City of Edinburgh EH28 8RE",
    "addr:housenumber":"5",
    "addr:postcode":"eh28 8re",
    "addr:street":"Dalmahoy Road",
    "iso:country":"GB",
    "sg:address":"5 Dalmahoy Road, Ratho",
    "sg:city":"Newbridge",
    "sg:classifiers":[
        {
            "category":"Coffee & Tea",
            "type":"Food & Drink"
        }
    ],
    "sg:phone":"+44 131 333 1129",
    "sg:postcode":"EH28 8RE",
    "sg:province":"City of Edinburgh",
    "sg:tags":[
        "machine"
    ],
    "wof:name":"Hall Enterprises",
    "wof:placetype":"venue"
},
  "geometry": {"coordinates":[-3.380094,55.921631],"type":"Point"}
}