{
  "type": "Feature",
  "properties": {
    "addr:full":"Linacre La Bootle Merseyside L20 5AG",
    "addr:postcode":"l20 5ag",
    "addr:street":"Linacre La Bootle",
    "iso:country":"GB",
    "sg:address":"Linacre La",
    "sg:city":"Bootle",
    "sg:classifiers":[
        {
            "category":"Autos & Motor Vehicles",
            "subcategory":"Fuel & Gas Station",
            "type":"Retail Goods"
        }
    ],
    "sg:phone":"+44 151 922 2478",
    "sg:postcode":"L20 5AG",
    "sg:province":"Merseyside",
    "sg:tags":[
        "hr",
        "petrol"
    ],
    "wof:name":"Elf Service Station",
    "wof:placetype":"venue"
},
  "geometry": {"coordinates":[-2.9889791012,53.4593086243],"type":"Point"}
}