{
  "type": "Feature",
  "properties": {
    "iso:country":"GB",
    "sg:address":"11a Durham Road Trading Estate",
    "sg:city":"Chester Le Street",
    "sg:classifiers":[
        {
            "category":"Shopping",
            "type":"Retail Goods"
        }
    ],
    "sg:phone":"+44 191 410 4488",
    "sg:postcode":"DH3 1JS",
    "sg:province":"Durham",
    "sg:tags":[
        "part",
        "accessory"
    ],
    "wof:name":"Classic Auto Motors",
    "wof:placetype":"venue"
},
  "geometry": {"coordinates":[-1.578598,54.904266],"type":"Point"}
}