{
  "type": "Feature",
  "properties": {
    "iso:country":"GB",
    "sg:address":"Plevna Crescent",
    "sg:city":"London",
    "sg:classifiers":[
        {
            "category":"Farming",
            "subcategory":"Nursery",
            "type":"Manufacturing & Wholesale Goods"
        },
        {
            "category":"Social Services",
            "subcategory":"Child Care",
            "type":"Services"
        }
    ],
    "sg:phone":"+44 20 8802 1064",
    "sg:postcode":"N15 6DN",
    "sg:province":"Greater London",
    "sg:tags":[
        "creche"
    ],
    "wof:name":"Plevna Under 5's Centre",
    "wof:placetype":"venue"
},
  "geometry": {"coordinates":[-0.0780949965,51.5791893005],"type":"Point"}
}