{
  "type": "Feature",
  "properties": {
    "iso:country":"GB",
    "sg:address":"10 Savel Way",
    "sg:city":"Royston",
    "sg:classifiers":[
        {
            "category":"Professional",
            "subcategory":"Employment Agencies",
            "type":"Services"
        }
    ],
    "sg:phone":"+44 1223 208008",
    "sg:postcode":"SG8 7TU",
    "sg:province":"Bedfordshire",
    "sg:tags":[
        "consultant"
    ],
    "wof:name":"Recruitment to Recruitment Ltd.",
    "wof:placetype":"venue"
},
  "geometry": {"coordinates":[-0.021984,52.04821],"type":"Point"}
}