{
  "type": "Feature",
  "properties": {
    "iso:country":"GB",
    "sg:address":"Cheylesmore Community Centre, Poitiers Rd",
    "sg:city":"Coventry",
    "sg:classifiers":[
        {
            "category":"Education",
            "subcategory":"Special Training",
            "type":"Public Place"
        }
    ],
    "sg:phone":"+44 24 7650 5576",
    "sg:postcode":"CV3 5JX",
    "sg:province":"Warwickshire",
    "sg:tags":[
        "product",
        "centre"
    ],
    "wof:name":"Learning Through Adventure",
    "wof:placetype":"venue"
},
  "geometry": {"coordinates":[-1.50357,52.388931],"type":"Point"}
}