{
  "type": "Feature",
  "properties": {
    "addr:full":"Hollinswood Community Centre, 7 Downemead Telford Shropshire TF3 2EW",
    "addr:housenumber":"7",
    "addr:postcode":"tf3 2ew",
    "addr:street":"Downemead",
    "iso:country":"GB",
    "sg:address":"Hollinswood Community Centre, 7 Downemead",
    "sg:city":"Telford",
    "sg:classifiers":[
        {
            "category":"Government",
            "subcategory":"Office",
            "type":"Public Place"
        }
    ],
    "sg:phone":"+44 1952 299830",
    "sg:postcode":"TF3 2EW",
    "sg:province":"Shropshire",
    "sg:tags":[
        "local"
    ],
    "wof:name":"Wrekin Council",
    "wof:placetype":"venue"
},
  "geometry": {"coordinates":[-2.4413990974,52.6713485718],"type":"Point"}
}