{
  "type": "Feature",
  "properties": {
    "iso:country":"GB",
    "sg:address":"Whitchurch Rd",
    "sg:city":"Cardiff",
    "sg:classifiers":[
        {
            "category":"Organizations",
            "subcategory":"Membership Organization",
            "type":"Services"
        }
    ],
    "sg:phone":"+44 29 2061 9286",
    "sg:postcode":"CF4 3JN",
    "sg:province":"Cardiff",
    "sg:tags":[
        "club"
    ],
    "wof:name":"St Josephs Catholic Social Club",
    "wof:placetype":"venue"
},
  "geometry": {"coordinates":[-3.1968839169,51.5043792725],"type":"Point"}
}