{
  "type": "Feature",
  "properties": {
    "iso:country":"GB",
    "sg:address":"99 Tivoli Rd",
    "sg:city":"Hounslow",
    "sg:classifiers":[
        {
            "category":"Retail",
            "subcategory":"Auto Repair",
            "type":"Services"
        }
    ],
    "sg:postcode":"TW4 6AS",
    "sg:province":"Greater London",
    "sg:tags":[
        "modification",
        "garage"
    ],
    "wof:name":"Lawler,Tony,",
    "wof:placetype":"venue"
},
  "geometry": {"coordinates":[-0.3859730065,51.4644126892],"type":"Point"}
}