{
  "type": "Feature",
  "properties": {
    "addr:full":"Unit 3 Culme Way, Dunkeswell Honiton Devon EX14 4JP",
    "addr:housenumber":"unit 3",
    "addr:postcode":"ex14 4jp",
    "addr:street":"Culme Way",
    "iso:country":"GB",
    "sg:address":"Unit 3 Culme Way, Dunkeswell",
    "sg:city":"Honiton",
    "sg:classifiers":[
        {
            "category":"Personal",
            "subcategory":"Beauty Salon",
            "type":"Services"
        }
    ],
    "sg:phone":"+44 1404 891133",
    "sg:postcode":"EX14 4JP",
    "sg:province":"Devon",
    "sg:tags":[
        "unisex",
        "hairdresser"
    ],
    "wof:name":"Visions Unisex",
    "wof:placetype":"venue"
},
  "geometry": {"coordinates":[-3.2217390537,50.854095459],"type":"Point"}
}