{
  "type": "Feature",
  "properties": {
    "addr:full":"Ridgewood Buildings, 244 Station Road, Yate Bristol Gloucestershire BS37 5HT",
    "addr:housenumber":"244",
    "addr:postcode":"bs37 5ht",
    "addr:street":"Station Road Yate",
    "iso:country":"GB",
    "sg:address":"Ridgewood Buildings, 244 Station Road, Yate",
    "sg:city":"Bristol",
    "sg:classifiers":[
        {
            "category":"Education",
            "subcategory":"Dance Studio",
            "type":"Public Place"
        }
    ],
    "sg:phone":"+44 1454 273067",
    "sg:postcode":"BS37 5HT",
    "sg:province":"Gloucestershire",
    "sg:tags":[
        "school",
        "dancing"
    ],
    "wof:name":"The Packard Dance Centre",
    "wof:placetype":"venue"
},
  "geometry": {"coordinates":[-2.4301900864,51.5409317017],"type":"Point"}
}