{
  "type": "Feature",
  "properties": {
    "addr:full":"17 Clapham Common South Side London Greater London SW4 7AB",
    "addr:housenumber":"17",
    "addr:postcode":"sw4 7ab",
    "addr:street":"Clapham Common South Side",
    "iso:country":"GB",
    "sg:address":"17 Clapham Common South Side",
    "sg:city":"London",
    "sg:classifiers":[
        {
            "category":"Real Estate",
            "subcategory":"Real Estate Agent",
            "type":"Services"
        }
    ],
    "sg:phone":"+44 20 7622 6686",
    "sg:postcode":"SW4 7AB",
    "sg:province":"Greater London",
    "wof:name":"Woolwich Property Services",
    "wof:placetype":"venue"
},
  "geometry": {"coordinates":[-0.13305,51.460464],"type":"Point"}
}