{
  "type": "Feature",
  "properties": {
    "iso:country":"GB",
    "sg:address":"Deanhouse Farm, Church Rd",
    "sg:city":"Dorking",
    "sg:classifiers":[
        {
            "category":"Shopping",
            "subcategory":"Clothing, Apparel, & Fashions",
            "type":"Retail Goods"
        }
    ],
    "sg:phone":"+44 1306 631830",
    "sg:postcode":"RH5 5DL",
    "sg:province":"Surrey",
    "sg:tags":[
        "shop",
        "dress",
        "fancy"
    ],
    "wof:name":"Encore Fancy Dress",
    "wof:placetype":"venue"
},
  "geometry": {"coordinates":[-0.28681,51.165321],"type":"Point"}
}