{
  "type": "Feature",
  "properties": {
    "iso:country":"GB",
    "sg:address":"26 St. Lawrence St",
    "sg:city":"Horncastle",
    "sg:classifiers":[
        {
            "category":"Professional",
            "subcategory":"Art Services",
            "type":"Services"
        }
    ],
    "sg:phone":"+44 1507 523519",
    "sg:postcode":"LN9 5DN",
    "sg:province":"Lincolnshire",
    "sg:tags":[
        "picture",
        "restoration"
    ],
    "wof:name":"DeMilo's",
    "wof:placetype":"venue"
},
  "geometry": {"coordinates":[-0.11611,53.209587],"type":"Point"}
}