{
  "type": "Feature",
  "properties": {
    "iso:country":"GB",
    "sg:address":"41 South Harbour Street",
    "sg:city":"Ayr",
    "sg:classifiers":[
        {
            "category":"Real Estate",
            "subcategory":"Real Estate Agent",
            "type":"Services"
        }
    ],
    "sg:postcode":"KA7 1JA",
    "sg:province":"South Ayrshire",
    "wof:name":"Fongs (Property) Ltd",
    "wof:placetype":"venue"
},
  "geometry": {"coordinates":[-4.638994,55.467625],"type":"Point"}
}