{
  "type": "Feature",
  "properties": {
    "addr:full":"Unit 1, Lawrence Road Hounslow Greater London TW4 6DU",
    "addr:housenumber":"unit 1",
    "addr:postcode":"tw4 6du",
    "addr:street":"Lawrence Road",
    "iso:country":"GB",
    "sg:address":"Unit 1, Lawrence Road",
    "sg:city":"Hounslow",
    "sg:classifiers":[
        {
            "category":"Wholesale",
            "subcategory":"Machinery & Supplies",
            "type":"Manufacturing & Wholesale Goods"
        }
    ],
    "sg:phone":"+44 20 8572 9300",
    "sg:postcode":"TW4 6DU",
    "sg:province":"Greater London",
    "sg:tags":[
        "hydraulic"
    ],
    "wof:name":"Jade Adaptors Ltd.",
    "wof:placetype":"venue"
},
  "geometry": {"coordinates":[-0.3992840052,51.4650840759],"type":"Point"}
}