{
  "type": "Feature",
  "properties": {
    "addr:full":"13 The Broadway, Tolworth Surbiton Surrey KT6 7DJ",
    "addr:housenumber":"13",
    "addr:postcode":"kt6 7dj",
    "addr:street":"The Broadway",
    "iso:country":"GB",
    "sg:address":"13 The Broadway, Tolworth",
    "sg:city":"Surbiton",
    "sg:classifiers":[
        {
            "category":"Shopping",
            "subcategory":"Stationery & Office Supplies",
            "type":"Retail Goods"
        }
    ],
    "sg:postcode":"KT6 7DJ",
    "sg:province":"Surrey",
    "wof:name":"Davey,Chris,",
    "wof:placetype":"venue"
},
  "geometry": {"coordinates":[-0.283589,51.381611],"type":"Point"}
}