{
  "type": "Feature",
  "properties": {
    "addr:full":"The Shrubbery, Church Street St Neots Bedfordshire PE19 2PQ",
    "addr:postcode":"pe19 2pq",
    "addr:street":"Church Street",
    "iso:country":"GB",
    "sg:address":"The Shrubbery, Church Street",
    "sg:city":"St Neots",
    "sg:classifiers":[
        {
            "category":"Real Estate",
            "subcategory":"Real Estate Agent",
            "type":"Services"
        }
    ],
    "sg:phone":"+44 1480 211000",
    "sg:postcode":"PE19 2PQ",
    "sg:province":"Bedfordshire",
    "wof:name":"Homecheck Service UK",
    "wof:placetype":"venue"
},
  "geometry": {"coordinates":[-0.2618739903,52.2278785706],"type":"Point"}
}