{
  "type": "Feature",
  "properties": {
    "iso:country":"GB",
    "sg:address":"Ebrook Rd",
    "sg:city":"Sutton Coldfield",
    "sg:classifiers":[
        {
            "category":"Building & Trades",
            "subcategory":"Landscaping Services",
            "type":"Services"
        }
    ],
    "sg:postcode":"B72 1NU",
    "sg:province":"West Midlands",
    "sg:tags":[
        "forestry",
        "tree"
    ],
    "wof:name":"Griffiths,Mark,",
    "wof:placetype":"venue"
},
  "geometry": {"coordinates":[-1.81865,52.560886],"type":"Point"}
}