{
  "type": "Feature",
  "properties": {
    "iso:country":"GB",
    "sg:address":"47 Whytescauseway",
    "sg:city":"Kirkcaldy",
    "sg:classifiers":[
        {
            "category":"Professional",
            "subcategory":"Lawyer & Legal Services",
            "type":"Services"
        }
    ],
    "sg:phone":"+44 1592 205000",
    "sg:postcode":"KY1 1XD",
    "sg:province":"Fife",
    "sg:tags":[
        "solicitor"
    ],
    "wof:name":"Miller W S Drummond",
    "wof:placetype":"venue"
},
  "geometry": {"coordinates":[-3.162407,56.109344],"type":"Point"}
}