{
  "type": "Feature",
  "properties": {
    "addr:full":"20 Chamberlain St Wells Somerset BA5 2PF",
    "addr:housenumber":"20",
    "addr:postcode":"ba5 2pf",
    "addr:street":"Chamberlain St",
    "iso:country":"GB",
    "sg:address":"20 Chamberlain St",
    "sg:city":"Wells",
    "sg:classifiers":[
        {
            "category":"Social Services",
            "subcategory":"Retirement Home",
            "type":"Services"
        }
    ],
    "sg:postcode":"BA5 2PF",
    "sg:province":"Somerset",
    "sg:tags":[
        "rest"
    ],
    "wof:name":"Abbeyfield (Wells) Society Ltd",
    "wof:placetype":"venue"
},
  "geometry": {"coordinates":[-2.648456,51.21006],"type":"Point"}
}