{
  "type": "Feature",
  "properties": {
    "addr:full":"30 Lodge La Leeds West Yorkshire LS11 6LR",
    "addr:housenumber":"30",
    "addr:postcode":"ls11 6lr",
    "addr:street":"Lodge La Leeds West",
    "iso:country":"GB",
    "sg:address":"30 Lodge La",
    "sg:city":"Leeds",
    "sg:classifiers":[
        {
            "category":"Shopping",
            "subcategory":"Used Merchandise",
            "type":"Retail Goods"
        }
    ],
    "sg:postcode":"LS11 6LR",
    "sg:province":"West Yorkshire",
    "sg:tags":[
        "furniture"
    ],
    "wof:name":"Greaves,Malcolm,",
    "wof:placetype":"venue"
},
  "geometry": {"coordinates":[-1.5522689819,53.7752494812],"type":"Point"}
}