{
  "type": "Feature",
  "properties": {
    "addr:full":"Central Car Park Road Keswick Cumbria CA12 5DF",
    "addr:postcode":"ca12 5df",
    "addr:street":"Park Road",
    "iso:country":"GB",
    "sg:address":"Central Car Park Road",
    "sg:city":"Keswick",
    "sg:classifiers":[
        {
            "category":"Manufacturing",
            "subcategory":"Pottery",
            "type":"Manufacturing & Wholesale Goods"
        }
    ],
    "sg:phone":"+44 17687 73983",
    "sg:postcode":"CA12 5DF",
    "sg:province":"Cumbria",
    "wof:name":"The Tea Pottery",
    "wof:placetype":"venue"
},
  "geometry": {"coordinates":[-3.138964,54.60173],"type":"Point"}
}