{
  "type": "Feature",
  "properties": {
    "iso:country":"GB",
    "sg:address":"226 Mulgrave Road",
    "sg:city":"Sutton",
    "sg:classifiers":[
        {
            "category":"Building & Trades",
            "subcategory":"Construction",
            "type":"Services"
        }
    ],
    "sg:phone":"+44 20 8642 0513",
    "sg:postcode":"SM2 6JT",
    "sg:province":"Surrey",
    "sg:tags":[
        "builder"
    ],
    "wof:name":"H Turnbull & Co Ltd",
    "wof:placetype":"venue"
},
  "geometry": {"coordinates":[-0.194294,51.358376],"type":"Point"}
}