{
  "type": "Feature",
  "properties": {
    "iso:country":"GB",
    "sg:address":"10 Ransom Close",
    "sg:city":"Hitchin",
    "sg:classifiers":[
        {
            "category":"Real Estate",
            "subcategory":"Developer",
            "type":"Services"
        }
    ],
    "sg:phone":"+44 1462 421420",
    "sg:postcode":"SG4 9AX",
    "sg:province":"Hertfordshire",
    "sg:tags":[
        "property"
    ],
    "wof:name":"Medipark (London) Ltd.",
    "wof:placetype":"venue"
},
  "geometry": {"coordinates":[-0.273438,51.936749],"type":"Point"}
}