{
  "type": "Feature",
  "properties": {
    "addr:full":"38 Station Road, Chingford London Greater London E4 7BE",
    "addr:housenumber":"38",
    "addr:postcode":"e4 7be",
    "addr:street":"Station Road",
    "iso:country":"GB",
    "sg:address":"38 Station Road, Chingford",
    "sg:city":"London",
    "sg:classifiers":[
        {
            "category":"Personal",
            "subcategory":"Barber",
            "type":"Services"
        }
    ],
    "sg:phone":"+44 205243499",
    "sg:postcode":"E4 7BE",
    "sg:province":"Greater London",
    "sg:tags":[
        "men's",
        "hairdresser"
    ],
    "wof:name":"Tash the Barber Stop",
    "wof:placetype":"venue"
},
  "geometry": {"coordinates":[-0.032962,51.578514],"type":"Point"}
}