{
  "type": "Feature",
  "properties": {
    "iso:country":"GB",
    "sg:address":"Alexandra Crt",
    "sg:city":"Prestwick",
    "sg:classifiers":[
        {
            "category":"Health Services",
            "subcategory":"Nursing And Care Facility",
            "type":"Services"
        },
        {
            "category":"Organizations",
            "subcategory":"Community Association",
            "type":"Services"
        }
    ],
    "sg:phone":"+44 1292 678116",
    "sg:postcode":"KA9 1BF",
    "sg:province":"South Ayrshire",
    "sg:tags":[
        "co-operatives",
        "residential",
        "housing",
        "trust",
        "society"
    ],
    "sg:website":"http://www.hsha.org.uk",
    "wof:name":"HANOVER (SCOTLAND) HOUSING ASSOCIATION LTD",
    "wof:placetype":"venue"
},
  "geometry": {"coordinates":[-4.6138892174,55.4947357178],"type":"Point"}
}