{
  "type": "Feature",
  "properties": {
    "addr:full":"38 Clarence Road Chesterfield Derbyshire S40 1LQ",
    "addr:housenumber":"38",
    "addr:postcode":"s40 1lq",
    "addr:street":"Clarence Road",
    "iso:country":"GB",
    "sg:address":"38 Clarence Road",
    "sg:city":"Chesterfield",
    "sg:classifiers":[
        {
            "category":"Health Services",
            "subcategory":"Dentist",
            "type":"Services"
        }
    ],
    "sg:phone":"+44 1246 232784",
    "sg:postcode":"S40 1LQ",
    "sg:province":"Derbyshire",
    "wof:name":"Kirkland & Ko Dental Practice",
    "wof:placetype":"venue"
},
  "geometry": {"coordinates":[-1.4347339869,53.2373542786],"type":"Point"}
}