{
  "type": "Feature",
  "properties": {
    "iso:country":"GB",
    "sg:address":", Burlescombe",
    "sg:city":"Tiverton",
    "sg:classifiers":[
        {
            "category":"Education",
            "subcategory":"School",
            "type":"Public Place"
        }
    ],
    "sg:phone":"+44 1823 672521",
    "sg:postcode":"EX16 7JH",
    "sg:province":"Devon",
    "sg:tags":[
        "local",
        "authority"
    ],
    "wof:name":"Burlescombe C Of E Primary School",
    "wof:placetype":"venue"
},
  "geometry": {"coordinates":[-3.399238,50.933472],"type":"Point"}
}