{
  "type": "Feature",
  "properties": {
    "addr:full":"Wyberton West Road Boston Lincolnshire PE21 7JU",
    "addr:housenumber":"wyberton",
    "addr:postcode":"pe21 7ju",
    "addr:street":"West Road",
    "iso:country":"GB",
    "sg:address":"Wyberton West Road",
    "sg:city":"Boston",
    "sg:classifiers":[
        {
            "category":"Health Services",
            "subcategory":"Nursing And Care Facility",
            "type":"Services"
        }
    ],
    "sg:phone":"+44 1205 353271",
    "sg:postcode":"PE21 7JU",
    "sg:province":"Lincolnshire",
    "sg:tags":[
        "home"
    ],
    "wof:name":"MEADOW EDGE NURSING HOME",
    "wof:placetype":"venue"
},
  "geometry": {"coordinates":[-0.0342309996,52.9675140381],"type":"Point"}
}