{
  "type": "Feature",
  "properties": {
    "addr:full":"Moor End, Frieth Henley-on-thames Berkshire RG9 6PY",
    "addr:postcode":"rg9 6py",
    "addr:street":"Moor;Frieth",
    "iso:country":"GB",
    "sg:address":"Moor End, Frieth",
    "sg:city":"Henley-on-thames",
    "sg:classifiers":[
        {
            "category":"Bars & Pubs",
            "type":"Food & Drink"
        }
    ],
    "sg:phone":"+44 1494 881683",
    "sg:postcode":"RG9 6PY",
    "sg:province":"Berkshire",
    "sg:tags":[
        "pubs",
        "inn"
    ],
    "wof:name":"The Prince Albert",
    "wof:placetype":"venue"
},
  "geometry": {"coordinates":[-0.8517680168,51.6052703857],"type":"Point"}
}