{
  "type": "Feature",
  "properties": {
    "iso:country":"GB",
    "sg:address":"98 Liverpool Road, Crosby",
    "sg:city":"Liverpool",
    "sg:classifiers":[
        {
            "category":"Retail",
            "subcategory":"Repair Shop",
            "type":"Services"
        },
        {
            "category":"Communications",
            "type":"Services"
        }
    ],
    "sg:phone":"+44 151 924 7287",
    "sg:postcode":"L23 5TG",
    "sg:province":"Merseyside",
    "sg:tags":[
        "television",
        "good",
        "tv",
        "video",
        "servicing",
        "maintenance",
        "radio"
    ],
    "wof:name":"P & A Audio Video Ltd.",
    "wof:placetype":"venue"
},
  "geometry": {"coordinates":[-3.0241580009,53.4889678955],"type":"Point"}
}