{
  "type": "Feature",
  "properties": {
    "addr:full":"Great Leighs Post Office, 103 Main Rd Chelmsford Essex CM3 1NN",
    "addr:housenumber":"103",
    "addr:postcode":"cm3 1nn",
    "addr:street":"Main Rd",
    "iso:country":"GB",
    "sg:address":"Great Leighs Post Office, 103 Main Rd",
    "sg:city":"Chelmsford",
    "sg:classifiers":[
        {
            "category":"Shopping",
            "subcategory":"Department Store",
            "type":"Retail Goods"
        },
        {
            "category":"Food & Beverages",
            "subcategory":"Groceries & Convenience Stores",
            "type":"Retail Goods"
        }
    ],
    "sg:phone":"+44 1245 361261",
    "sg:postcode":"CM3 1NN",
    "sg:province":"Essex",
    "wof:name":"Great Leighs Village Store",
    "wof:placetype":"venue"
},
  "geometry": {"coordinates":[0.50673,51.828442],"type":"Point"}
}