{
  "type": "Feature",
  "properties": {
    "addr:full":"66 Kingsland High St Hackney Greater London E8 2JP",
    "addr:housenumber":"66",
    "addr:postcode":"e8 2jp",
    "addr:street":"Kingsland High St",
    "iso:country":"GB",
    "sg:address":"66 Kingsland High St",
    "sg:city":"Hackney",
    "sg:classifiers":[
        {
            "category":"Retail",
            "subcategory":"Photofinishing",
            "type":"Services"
        }
    ],
    "sg:phone":"+44 20 7254 9636",
    "sg:postcode":"E8 2JP",
    "sg:province":"Greater London",
    "sg:tags":[
        "photographic",
        "processor"
    ],
    "wof:name":"SupaSnaps",
    "wof:placetype":"venue"
},
  "geometry": {"coordinates":[-0.075476,51.547699],"type":"Point"}
}