{
  "type": "Feature",
  "properties": {
    "addr:full":"64 Millrise Road, Milton Stoke On Trent Staffordshire ST2 7DN",
    "addr:housenumber":"64",
    "addr:postcode":"st2 7dn",
    "addr:street":"Millrise Road",
    "iso:country":"GB",
    "sg:address":"64 Millrise Road, Milton",
    "sg:city":"Stoke On Trent",
    "sg:classifiers":[
        {
            "category":"Food & Beverages",
            "subcategory":"Supermarket",
            "type":"Retail Goods"
        }
    ],
    "sg:phone":"+44 1782 535376",
    "sg:postcode":"ST2 7DN",
    "sg:province":"Staffordshire",
    "wof:name":"J L Thornton",
    "wof:placetype":"venue"
},
  "geometry": {"coordinates":[-2.1429700851,53.0492019653],"type":"Point"}
}