{
  "type": "Feature",
  "properties": {
    "iso:country":"GB",
    "sg:address":"43a Gipsy Rd",
    "sg:city":"Leicester",
    "sg:classifiers":[
        {
            "category":"Professional",
            "subcategory":"Engineering",
            "type":"Services"
        }
    ],
    "sg:postcode":"LE4 6QJ",
    "sg:province":"Leicestershire",
    "sg:tags":[
        "contractor",
        "electrical",
        "engineer"
    ],
    "wof:name":"Branson,F,",
    "wof:placetype":"venue"
},
  "geometry": {"coordinates":[-1.115137,52.656105],"type":"Point"}
}