{
  "type": "Feature",
  "properties": {
    "addr:full":"103 High St Berkhamsted Bedfordshire HP4 2DG",
    "addr:housenumber":"103",
    "addr:postcode":"hp4 2dg",
    "addr:street":"High St",
    "iso:country":"GB",
    "sg:address":"103 High St",
    "sg:city":"Berkhamsted",
    "sg:classifiers":[
        {
            "category":"Recreation",
            "type":"Entertainment"
        }
    ],
    "sg:phone":"+44 1442 865804",
    "sg:postcode":"HP4 2DG",
    "sg:province":"Bedfordshire",
    "sg:tags":[
        "outdoor",
        "pursuit"
    ],
    "wof:name":"The Moorehead Consultancy",
    "wof:placetype":"venue"
},
  "geometry": {"coordinates":[-0.56067,51.759052],"type":"Point"}
}