{
  "type": "Feature",
  "properties": {
    "addr:full":"8a Moulsham Street Chelmsford Essex CM2 0HR",
    "addr:housenumber":"8a",
    "addr:postcode":"cm2 0hr",
    "addr:street":"Moulsham Street",
    "iso:country":"GB",
    "sg:address":"8a Moulsham Street",
    "sg:city":"Chelmsford",
    "sg:classifiers":[
        {
            "category":"Personal",
            "subcategory":"Nail Salon",
            "type":"Services"
        }
    ],
    "sg:postcode":"CM2 0HR",
    "sg:province":"Essex",
    "sg:tags":[
        "technician"
    ],
    "wof:name":"Nails At Naturelle",
    "wof:placetype":"venue"
},
  "geometry": {"coordinates":[0.474052012,51.7307624817],"type":"Point"}
}