{
  "type": "Feature",
  "properties": {
    "addr:full":"2c St Francis Way Shefford Bedfordshire SG17 5DZ",
    "addr:housenumber":"2c",
    "addr:postcode":"sg17 5dz",
    "addr:street":"St Francis Way",
    "iso:country":"GB",
    "sg:address":"2c St Francis Way",
    "sg:city":"Shefford",
    "sg:classifiers":[
        {
            "category":"Professional",
            "subcategory":"Computer Services",
            "type":"Services"
        }
    ],
    "sg:phone":"+44 1462 851951",
    "sg:postcode":"SG17 5DZ",
    "sg:province":"Bedfordshire",
    "sg:tags":[
        "system",
        "software"
    ],
    "wof:name":"Integra",
    "wof:placetype":"venue"
},
  "geometry": {"coordinates":[-0.3334580064,52.0372962952],"type":"Point"}
}