{
  "type": "Feature",
  "properties": {
    "addr:full":"271 Roundhay Road Leeds West Yorkshire LS8 4HS",
    "addr:housenumber":"271",
    "addr:postcode":"ls8 4hs",
    "addr:street":"Roundhay Road",
    "iso:country":"GB",
    "sg:address":"271 Roundhay Road",
    "sg:city":"Leeds",
    "sg:classifiers":[
        {
            "category":"Health Services",
            "subcategory":"Optometrist",
            "type":"Services"
        },
        {
            "category":"Shopping",
            "subcategory":"Optician",
            "type":"Retail Goods"
        }
    ],
    "sg:phone":"+44 113 248 0020",
    "sg:postcode":"LS8 4HS",
    "sg:province":"West Yorkshire",
    "sg:tags":[
        "ophthalmic"
    ],
    "wof:name":"Optikaal Vision Care Centre",
    "wof:placetype":"venue"
},
  "geometry": {"coordinates":[-1.517277,53.816826],"type":"Point"}
}