{
  "type": "Feature",
  "properties": {
    "addr:full":"The A38, West Huntspill Highbridge Somerset TA9 3RH",
    "addr:postcode":"ta9 3rh",
    "addr:street":"West",
    "iso:country":"GB",
    "sg:address":"The A38, West Huntspill",
    "sg:city":"Highbridge",
    "sg:classifiers":[
        {
            "category":"Manufacturing",
            "subcategory":"Lumber",
            "type":"Manufacturing & Wholesale Goods"
        }
    ],
    "sg:phone":"+44 1278 788978",
    "sg:postcode":"TA9 3RH",
    "sg:province":"Somerset",
    "sg:tags":[
        "importer",
        "merchants",
        "agent",
        "timber"
    ],
    "wof:name":"The Wood Pile",
    "wof:placetype":"venue"
},
  "geometry": {"coordinates":[-2.9829819202,51.2153968811],"type":"Point"}
}