{
  "type": "Feature",
  "properties": {
    "addr:full":"4 Godolphin Way Newquay Cornwall TR7 3BU",
    "addr:housenumber":"4",
    "addr:postcode":"tr7 3bu",
    "addr:street":"Godolphin Way",
    "iso:country":"GB",
    "sg:address":"4 Godolphin Way",
    "sg:city":"Newquay",
    "sg:classifiers":[
        {
            "category":"Travel",
            "subcategory":"Hotels & Motels",
            "type":"Entertainment"
        }
    ],
    "sg:phone":"+44 1637 875840",
    "sg:postcode":"TR7 3BU",
    "sg:province":"Cornwall",
    "sg:tags":[
        "house",
        "guest"
    ],
    "wof:name":"Blue Haven",
    "wof:placetype":"venue"
},
  "geometry": {"coordinates":[-5.059264,50.418785],"type":"Point"}
}