{
  "type": "Feature",
  "properties": {
    "addr:full":"205 Cann Hall Road Wanstead Greater London E11 3NJ",
    "addr:housenumber":"205",
    "addr:postcode":"e11 3nj",
    "addr:street":"Cann Hall Road",
    "iso:country":"GB",
    "sg:address":"205 Cann Hall Road",
    "sg:city":"Wanstead",
    "sg:classifiers":[
        {
            "category":"Place Of Worship",
            "type":"Public Place"
        }
    ],
    "sg:phone":"+44 20 8519 2483",
    "sg:postcode":"E11 3NJ",
    "sg:province":"Greater London",
    "wof:name":"Pentecostal Church Of Jesus Christ United",
    "wof:placetype":"venue"
},
  "geometry": {"coordinates":[0.013159,51.555931],"type":"Point"}
}