{
  "type": "Feature",
  "properties": {
    "iso:country":"GB",
    "sg:address":"8 Willow Ho, Willow Walk, The Grange Est, Finchley",
    "sg:city":"London",
    "sg:classifiers":[
        {
            "category":"Shopping",
            "type":"Retail Goods"
        }
    ],
    "sg:postcode":"N2 8EL",
    "sg:province":"Greater London",
    "sg:tags":[
        "part",
        "accessory"
    ],
    "wof:name":"French Factors Ltd",
    "wof:placetype":"venue"
},
  "geometry": {"coordinates":[-0.17215,51.59581],"type":"Point"}
}