{
  "type": "Feature",
  "properties": {
    "addr:full":"152 High Street Lee-on-the-solent Hampshire PO13 9DD",
    "addr:housenumber":"152",
    "addr:postcode":"po13 9dd",
    "addr:street":"High Street",
    "iso:country":"GB",
    "sg:address":"152 High Street",
    "sg:city":"Lee-on-the-solent",
    "sg:classifiers":[
        {
            "category":"Health Services",
            "subcategory":"Dentist",
            "type":"Services"
        }
    ],
    "sg:phone":"+44 23 9255 4485",
    "sg:postcode":"PO13 9DD",
    "sg:province":"Hampshire",
    "wof:name":"The Kea Family Dental Health Centre",
    "wof:placetype":"venue"
},
  "geometry": {"coordinates":[-1.203014,50.802814],"type":"Point"}
}