{
  "type": "Feature",
  "properties": {
    "addr:full":"82 Conduit St Leicester Leicestershire LE2 0JN",
    "addr:housenumber":"82",
    "addr:postcode":"le2 0jn",
    "addr:street":"Conduit St",
    "iso:country":"GB",
    "sg:address":"82 Conduit St",
    "sg:city":"Leicester",
    "sg:classifiers":[
        {
            "category":"Retail",
            "subcategory":"Repair Shop",
            "type":"Services"
        }
    ],
    "sg:phone":"+44 116 254 7894",
    "sg:postcode":"LE2 0JN",
    "sg:province":"Leicestershire",
    "sg:tags":[
        "plant",
        "machinery"
    ],
    "wof:name":"Plant Services",
    "wof:placetype":"venue"
},
  "geometry": {"coordinates":[-1.121534,52.63195],"type":"Point"}
}