{
  "type": "Feature",
  "properties": {
    "iso:country":"GB",
    "sg:address":"Dalreoch Yard",
    "sg:city":"Dumbarton",
    "sg:classifiers":[
        {
            "category":"Wholesale",
            "subcategory":"Scrap",
            "type":"Manufacturing & Wholesale Goods"
        },
        {
            "category":"Retail",
            "subcategory":"Auto Repair",
            "type":"Services"
        }
    ],
    "sg:phone":"+44 1389 732576",
    "sg:postcode":"G82 4BW",
    "sg:province":"Argyll and Bute",
    "sg:tags":[
        "modification",
        "garage",
        "breaker",
        "dismantlers"
    ],
    "wof:name":"Carberry Transport Ltd.",
    "wof:placetype":"venue"
},
  "geometry": {"coordinates":[-4.5809879303,55.9481124878],"type":"Point"}
}