{
  "type": "Feature",
  "properties": {
    "iso:country":"GB",
    "sg:address":"Great Western Industrial Centre",
    "sg:city":"Dorchester",
    "sg:classifiers":[
        {
            "category":"Autos & Motor Vehicles",
            "subcategory":"Auto Supplies",
            "type":"Retail Goods"
        }
    ],
    "sg:phone":"+44 1305 264756",
    "sg:postcode":"DT1 1RD",
    "sg:province":"Dorset",
    "sg:tags":[
        "tyre"
    ],
    "wof:name":"A T S Western Ltd.",
    "wof:placetype":"venue"
},
  "geometry": {"coordinates":[-2.441564,50.711906],"type":"Point"}
}