{
  "type": "Feature",
  "properties": {
    "iso:country":"GB",
    "sg:address":"19 North View Drive",
    "sg:city":"Brierley Hill",
    "sg:classifiers":[
        {
            "category":"Home & Garden",
            "subcategory":"Building Materials",
            "type":"Retail Goods"
        }
    ],
    "sg:phone":"+44 1384 869105",
    "sg:postcode":"DY5 1LP",
    "sg:province":"West Midlands",
    "sg:tags":[
        "shutter",
        "door"
    ],
    "wof:name":"Hart Industrial Doors",
    "wof:placetype":"venue"
},
  "geometry": {"coordinates":[-2.116435,52.494034],"type":"Point"}
}