{
  "type": "Feature",
  "properties": {
    "addr:full":"The Willows, Mill Road, Thorpe Abbotts Diss Norfolk IP21 4HX",
    "addr:postcode":"ip21 4hx",
    "addr:street":"Mill Road",
    "iso:country":"GB",
    "sg:address":"The Willows, Mill Road, Thorpe Abbotts",
    "sg:city":"Diss",
    "sg:classifiers":[
        {
            "category":"Professional",
            "subcategory":"Engineering",
            "type":"Services"
        }
    ],
    "sg:postcode":"IP21 4HX",
    "sg:province":"Norfolk",
    "sg:tags":[
        "contractor",
        "electrical",
        "engineer"
    ],
    "wof:name":"Tony P Garrod",
    "wof:placetype":"venue"
},
  "geometry": {"coordinates":[1.222551,52.372303],"type":"Point"}
}