{
  "type": "Feature",
  "properties": {
    "iso:country":"GB",
    "sg:address":"6 Newbarn Lane, Feltham",
    "sg:city":"Bognor Regis",
    "sg:classifiers":[
        {
            "category":"Building & Trades",
            "subcategory":"Plumbing",
            "type":"Services"
        }
    ],
    "sg:phone":"+44 1243 583841",
    "sg:postcode":"PO22 8LP",
    "sg:province":"West Sussex",
    "sg:tags":[
        "plumber",
        "heating"
    ],
    "wof:name":"Paul R Cozens",
    "wof:placetype":"venue"
},
  "geometry": {"coordinates":[-0.6402739882,50.7970085144],"type":"Point"}
}