{
  "type": "Feature",
  "properties": {
    "addr:full":"2c Eastwood Road Rayleigh Essex SS6 7JQ",
    "addr:housenumber":"2c",
    "addr:postcode":"ss6 7jq",
    "addr:street":"Eastwood Road Rayleigh",
    "iso:country":"GB",
    "sg:address":"2c Eastwood Road",
    "sg:city":"Rayleigh",
    "sg:classifiers":[
        {
            "category":"Shopping",
            "subcategory":"Clothing, Apparel, & Fashions",
            "type":"Retail Goods"
        }
    ],
    "sg:phone":"+44 1268 741139",
    "sg:postcode":"SS6 7JQ",
    "sg:province":"Essex",
    "sg:tags":[
        "ladieswear"
    ],
    "wof:name":"Rita's Seperates",
    "wof:placetype":"venue"
},
  "geometry": {"coordinates":[0.604811,51.585316],"type":"Point"}
}