{
  "type": "Feature",
  "properties": {
    "addr:full":"4 Perrins La Hampstead Greater London NW3 1QY",
    "addr:housenumber":"4",
    "addr:postcode":"nw3 1qy",
    "addr:street":"Perrins La Hampstead",
    "iso:country":"GB",
    "sg:address":"4 Perrins La",
    "sg:city":"Hampstead",
    "sg:classifiers":[
        {
            "category":"Professional",
            "subcategory":"Art Services",
            "type":"Services"
        }
    ],
    "sg:phone":"+44 20 7794 8437",
    "sg:postcode":"NW3 1QY",
    "sg:province":"Greater London",
    "sg:tags":[
        "consultant",
        "design"
    ],
    "wof:name":"Dessin Par Joseph",
    "wof:placetype":"venue"
},
  "geometry": {"coordinates":[-0.177272,51.555676],"type":"Point"}
}