{
  "type": "Feature",
  "properties": {
    "iso:country":"GB",
    "sg:address":"109 South Avenue",
    "sg:city":"Abingdon",
    "sg:classifiers":[
        {
            "category":"Professional",
            "subcategory":"Business Services",
            "type":"Services"
        }
    ],
    "sg:phone":"+44 1235 521560",
    "sg:postcode":"OX14 1QS",
    "sg:province":"Oxfordshire",
    "sg:tags":[
        "assessment",
        "quality"
    ],
    "wof:name":"Quality Matters",
    "wof:placetype":"venue"
},
  "geometry": {"coordinates":[-1.276635,51.686001],"type":"Point"}
}