{
  "type": "Feature",
  "properties": {
    "iso:country":"GB",
    "sg:address":"Quarry Bungalow, Huddleston, South Milford",
    "sg:city":"Leeds",
    "sg:classifiers":[
        {
            "category":"Farming",
            "subcategory":"Farm",
            "type":"Manufacturing & Wholesale Goods"
        }
    ],
    "sg:phone":"+44 1977 681378",
    "sg:postcode":"LS25 6JU",
    "sg:province":"North Yorkshire",
    "sg:tags":[
        "mixed",
        "crop"
    ],
    "wof:name":"N Hawkin",
    "wof:placetype":"venue"
},
  "geometry": {"coordinates":[-1.28269,53.795959],"type":"Point"}
}