{
  "type": "Feature",
  "properties": {
    "iso:country":"GB",
    "sg:address":"Channing House, Eagle Way, Sowton",
    "sg:city":"Exeter",
    "sg:classifiers":[
        {
            "category":"Professional",
            "subcategory":"Advertising",
            "type":"Services"
        },
        {
            "category":"Government",
            "subcategory":"Post Office",
            "type":"Public Place"
        }
    ],
    "sg:phone":"+44 1392 445995",
    "sg:postcode":"EX2 7HY",
    "sg:province":"Devon",
    "sg:tags":[
        "mail",
        "direct",
        "provider"
    ],
    "sg:website":"http://www.hwcltd.co.uk",
    "wof:name":"Handle With Care Ltd.",
    "wof:placetype":"venue"
},
  "geometry": {"coordinates":[-3.4641981125,50.7192153931],"type":"Point"}
}