{
  "type": "Feature",
  "properties": {
    "addr:full":"15 Church Street Coatbridge North Lanarkshire ML5 3EB",
    "addr:housenumber":"15",
    "addr:postcode":"ml5 3eb",
    "addr:street":"Church Street",
    "iso:country":"GB",
    "sg:address":"15 Church Street",
    "sg:city":"Coatbridge",
    "sg:classifiers":[
        {
            "category":"Health Services",
            "subcategory":"Dentist",
            "type":"Services"
        }
    ],
    "sg:phone":"+44 1236 423862",
    "sg:postcode":"ML5 3EB",
    "sg:province":"North Lanarkshire",
    "wof:name":"John A Blair",
    "wof:placetype":"venue"
},
  "geometry": {"coordinates":[-4.0271878242,55.8640975952],"type":"Point"}
}