{
  "type": "Feature",
  "properties": {
    "iso:country":"GB",
    "sg:address":"10 Raglan Street",
    "sg:city":"Harrogate",
    "sg:classifiers":[
        {
            "category":"Banks & Credit Unions",
            "subcategory":"Financial Services",
            "type":"Services"
        }
    ],
    "sg:phone":"+44 1423 528742",
    "sg:postcode":"HG1 1LE",
    "sg:province":"North Yorkshire",
    "sg:tags":[
        "adviser"
    ],
    "wof:name":"J Matthews & Co",
    "wof:placetype":"venue"
},
  "geometry": {"coordinates":[-1.539705,53.99123],"type":"Point"}
}