{
  "type": "Feature",
  "properties": {
    "iso:country":"GB",
    "sg:address":"5 Mill Street",
    "sg:city":"Congleton",
    "sg:classifiers":[
        {
            "category":"Fast Food",
            "type":"Food & Drink"
        }
    ],
    "sg:postcode":"CW12 1AB",
    "sg:province":"Cheshire",
    "sg:tags":[
        "away",
        "take"
    ],
    "wof:name":"Wood,Ivy,",
    "wof:placetype":"venue"
},
  "geometry": {"coordinates":[-2.214269,53.164047],"type":"Point"}
}