{
  "type": "Feature",
  "properties": {
    "addr:full":"18 Ravenscroft Road Beckenham Kent BR3 4TR",
    "addr:housenumber":"18",
    "addr:postcode":"br3 4tr",
    "addr:street":"Ravenscroft Road",
    "iso:country":"GB",
    "sg:address":"18 Ravenscroft Road",
    "sg:city":"Beckenham",
    "sg:classifiers":[
        {
            "category":"Professional",
            "subcategory":"Engineering",
            "type":"Services"
        }
    ],
    "sg:phone":"+44 20 8325 2001",
    "sg:postcode":"BR3 4TR",
    "sg:province":"Kent",
    "sg:tags":[
        "contractor",
        "electrical",
        "engineer"
    ],
    "wof:name":"Bromley Electric Co. Ltd.",
    "wof:placetype":"venue"
},
  "geometry": {"coordinates":[-0.047931999,51.4102554321],"type":"Point"}
}