{
  "type": "Feature",
  "properties": {
    "iso:country":"GB",
    "sg:address":"369 Chepstow Road",
    "sg:city":"Newport",
    "sg:classifiers":[
        {
            "category":"Professional",
            "subcategory":"Computer Services",
            "type":"Services"
        }
    ],
    "sg:postcode":"NP19 8HJ",
    "sg:province":"Newport",
    "sg:tags":[
        "system",
        "software"
    ],
    "wof:name":"T B R Software",
    "wof:placetype":"venue"
},
  "geometry": {"coordinates":[-2.964939,51.588207],"type":"Point"}
}