{
  "type": "Feature",
  "properties": {
    "iso:country":"GB",
    "sg:address":"Kepplestone, The Grove",
    "sg:city":"Sevenoaks",
    "sg:classifiers":[
        {
            "category":"Building & Trades",
            "subcategory":"Construction",
            "type":"Services"
        }
    ],
    "sg:phone":"+44 1474 852535",
    "sg:postcode":"TN15 6JJ",
    "sg:province":"Kent",
    "sg:tags":[
        "builder"
    ],
    "wof:name":"Kestral Construction",
    "wof:placetype":"venue"
},
  "geometry": {"coordinates":[0.2632099986,51.3365783691],"type":"Point"}
}