{
  "type": "Feature",
  "properties": {
    "addr:full":"11 The Spinney Weston-super-mare Somerset BS24 9LH",
    "addr:housenumber":"11;weston-super-mare",
    "addr:postcode":"bs24 9lh",
    "addr:street":"The Spinney",
    "iso:country":"GB",
    "sg:address":"11 The Spinney",
    "sg:city":"Weston-super-mare",
    "sg:classifiers":[
        {
            "category":"Professional",
            "subcategory":"Management & Consulting",
            "type":"Services"
        }
    ],
    "sg:postcode":"BS24 9LH",
    "sg:province":"Somerset",
    "sg:tags":[
        "consultant",
        "specialist"
    ],
    "wof:name":"Lydian Face & Body Sugaring",
    "wof:placetype":"venue"
},
  "geometry": {"coordinates":[-2.9646909237,51.3202095032],"type":"Point"}
}