{
  "type": "Feature",
  "properties": {
    "addr:full":"2 St Botolphs Terrace Walton-on-the-naze Essex CO14 8DA",
    "addr:housenumber":"2",
    "addr:postcode":"co14 8da",
    "addr:street":"St Botolphs Terrace",
    "iso:country":"GB",
    "sg:address":"2 St Botolphs Terrace",
    "sg:city":"Walton-on-the-naze",
    "sg:classifiers":[
        {
            "category":"Food & Beverages",
            "subcategory":"Bakery",
            "type":"Retail Goods"
        }
    ],
    "sg:postcode":"CO14 8DA",
    "sg:province":"Essex",
    "sg:tags":[
        "baker"
    ],
    "wof:name":"Bread Basket",
    "wof:placetype":"venue"
},
  "geometry": {"coordinates":[1.2669090033,51.8471107483],"type":"Point"}
}