{
  "type": "Feature",
  "properties": {
    "addr:full":"6 Clancey Road Norwich Norfolk NR7 9AA",
    "addr:housenumber":"6",
    "addr:postcode":"nr7 9aa",
    "addr:street":"Clancey Road Norwich Norfolk",
    "iso:country":"GB",
    "sg:address":"6 Clancey Road",
    "sg:city":"Norwich",
    "sg:classifiers":[
        {
            "category":"Professional",
            "subcategory":"Engineering",
            "type":"Services"
        }
    ],
    "sg:phone":"+44 1603 437409",
    "sg:postcode":"NR7 9AA",
    "sg:province":"Norfolk",
    "sg:tags":[
        "contractor",
        "electrical",
        "engineer"
    ],
    "wof:name":"Norwich Aerials",
    "wof:placetype":"venue"
},
  "geometry": {"coordinates":[1.331099987,52.6445274353],"type":"Point"}
}