{
  "type": "Feature",
  "properties": {
    "iso:country":"GB",
    "sg:address":"650 Davidson Rd",
    "sg:city":"Croydon",
    "sg:classifiers":[
        {
            "category":"Building & Trades",
            "subcategory":"Landscaping Services",
            "type":"Services"
        }
    ],
    "sg:phone":"+44 7956 975222",
    "sg:postcode":"CR0 6DJ",
    "sg:province":"Surrey",
    "sg:tags":[
        "landscape",
        "contractor"
    ],
    "wof:name":"Seaward Landscapes",
    "wof:placetype":"venue"
},
  "geometry": {"coordinates":[-0.075649,51.392052],"type":"Point"}
}