{
  "type": "Feature",
  "properties": {
    "addr:full":"137 Sheen Road Richmond Greater London TW9 1YJ",
    "addr:housenumber":"137",
    "addr:postcode":"tw9 1yj",
    "addr:street":"Sheen Road",
    "iso:country":"GB",
    "sg:address":"137 Sheen Road",
    "sg:city":"Richmond",
    "sg:classifiers":[
        {
            "category":"Conference Center",
            "type":"Public Place"
        }
    ],
    "sg:phone":"+44 20 8940 3431",
    "sg:postcode":"TW9 1YJ",
    "sg:province":"Greater London",
    "wof:name":"Geoffrey V Smith Associates",
    "wof:placetype":"venue"
},
  "geometry": {"coordinates":[-0.2940140069,51.4621429443],"type":"Point"}
}