{
  "type": "Feature",
  "properties": {
    "iso:country":"GB",
    "sg:address":"Unit 2-3 43-45 Newland Street",
    "sg:city":"Witham",
    "sg:classifiers":[
        {
            "category":"Home & Garden",
            "subcategory":"Home Furnishings",
            "type":"Retail Goods"
        }
    ],
    "sg:phone":"+44 1376 518726",
    "sg:postcode":"CM8 2BD",
    "sg:province":"Essex",
    "sg:tags":[
        "wall",
        "wallpaper",
        "covering"
    ],
    "wof:name":"A G Stanley Ltd.",
    "wof:placetype":"venue"
},
  "geometry": {"coordinates":[0.639991,51.800713],"type":"Point"}
}