{
  "type": "Feature",
  "properties": {
    "addr:full":"185 Lower Addiscombe Road, Addiscombe Croydon Surrey CR0 6RA",
    "addr:housenumber":"185",
    "addr:postcode":"cr0 6ra",
    "addr:street":"Lower Addiscombe Road",
    "iso:country":"GB",
    "sg:address":"185 Lower Addiscombe Road, Addiscombe",
    "sg:city":"Croydon",
    "sg:classifiers":[
        {
            "category":"Shopping",
            "subcategory":"Bicycles & Sporting Goods",
            "type":"Retail Goods"
        },
        {
            "category":"Sports & Exercise",
            "subcategory":"Sports Center",
            "type":"Entertainment"
        }
    ],
    "sg:phone":"+44 20 8654 9513",
    "sg:postcode":"CR0 6RA",
    "sg:province":"Surrey",
    "sg:tags":[
        "shop",
        "sale"
    ],
    "wof:name":"Addiscombe Sports",
    "wof:placetype":"venue"
},
  "geometry": {"coordinates":[-0.075172998,51.3793373108],"type":"Point"}
}