{
  "type": "Feature",
  "properties": {
    "addr:full":"18 Overton Crescent, Dyce Aberdeen Aberdeen City AB21 7FW",
    "addr:housenumber":"18",
    "addr:postcode":"ab21 7fw",
    "addr:street":"Overton Crescent",
    "iso:country":"GB",
    "sg:address":"18 Overton Crescent, Dyce",
    "sg:city":"Aberdeen",
    "sg:classifiers":[
        {
            "category":"Professional",
            "subcategory":"Management & Consulting",
            "type":"Services"
        }
    ],
    "sg:postcode":"AB21 7FW",
    "sg:province":"Aberdeen City",
    "sg:tags":[
        "consultant",
        "business"
    ],
    "wof:name":"The Sigma Consultancy (Scotland) Ltd.",
    "wof:placetype":"venue"
},
  "geometry": {"coordinates":[-2.174367,57.202374],"type":"Point"}
}