{
  "type": "Feature",
  "properties": {
    "iso:country":"GB",
    "sg:address":"Waterside Ho, 47 High St",
    "sg:city":"Rickmansworth",
    "sg:classifiers":[
        {
            "category":"Professional",
            "subcategory":"Computer Services",
            "type":"Services"
        }
    ],
    "sg:phone":"+44 1923 771111",
    "sg:postcode":"WD3 1ES",
    "sg:province":"Hertfordshire",
    "sg:tags":[
        "bureau",
        "facility"
    ],
    "wof:name":"P C L Alpha Numeric",
    "wof:placetype":"venue"
},
  "geometry": {"coordinates":[-0.468275,51.641438],"type":"Point"}
}