{
  "type": "Feature",
  "properties": {
    "addr:full":"Newbrough Hexham Northumberland NE47 5AR",
    "addr:postcode":"ne47 5ar",
    "addr:street":"Newbrough",
    "iso:country":"GB",
    "sg:address":"Newbrough",
    "sg:city":"Hexham",
    "sg:classifiers":[
        {
            "category":"Bars & Pubs",
            "type":"Food & Drink"
        },
        {
            "category":"Community Center",
            "subcategory":"Social",
            "type":"Public Place"
        }
    ],
    "sg:phone":"+44 1434 674226",
    "sg:postcode":"NE47 5AR",
    "sg:province":"Northumberland",
    "sg:tags":[
        "pubs",
        "house",
        "inn",
        "activity"
    ],
    "wof:name":"The Red Lion",
    "wof:placetype":"venue"
},
  "geometry": {"coordinates":[-2.1985299587,55.0055885315],"type":"Point"}
}