{
  "type": "Feature",
  "properties": {
    "addr:full":"1 Redwood Close, Dibden Purlieu Southampton Hampshire SO45 5SN",
    "addr:housenumber":"1",
    "addr:postcode":"so45 5sn",
    "addr:street":"Redwood Close;Purlieu",
    "iso:country":"GB",
    "sg:address":"1 Redwood Close, Dibden Purlieu",
    "sg:city":"Southampton",
    "sg:classifiers":[
        {
            "category":"Building & Trades",
            "subcategory":"Construction",
            "type":"Services"
        }
    ],
    "sg:postcode":"SO45 5SN",
    "sg:province":"Hampshire",
    "sg:tags":[
        "conversion",
        "loft"
    ],
    "wof:name":"Shaun Lawford Carpenter Building",
    "wof:placetype":"venue"
},
  "geometry": {"coordinates":[-1.425831,50.861057],"type":"Point"}
}