{
  "type": "Feature",
  "properties": {
    "addr:full":"111 Empire Rd Sheffield South Yorkshire S7 1GN",
    "addr:housenumber":"111",
    "addr:postcode":"s7 1gn",
    "addr:street":"Empire Rd",
    "iso:country":"GB",
    "sg:address":"111 Empire Rd",
    "sg:city":"Sheffield",
    "sg:classifiers":[
        {
            "category":"Building & Trades",
            "subcategory":"Cleaning & Sanitation",
            "type":"Services"
        }
    ],
    "sg:phone":"+44 114 249 1282",
    "sg:postcode":"S7 1GN",
    "sg:province":"South Yorkshire",
    "sg:tags":[
        "commercial"
    ],
    "wof:name":"Graffitection",
    "wof:placetype":"venue"
},
  "geometry": {"coordinates":[-1.4809169769,53.3598098755],"type":"Point"}
}