{
  "type": "Feature",
  "properties": {
    "addr:full":"Block 3 Blantyre Industrial Estate, West Avenue, Blantyre Glasgow South Lanarkshire G72 0UP",
    "addr:postcode":"g72 0up",
    "addr:street":"Blantyre Industrial Estate West Avenue",
    "iso:country":"GB",
    "sg:address":"Block 3 Blantyre Industrial Estate, West Avenue, Blantyre",
    "sg:city":"Glasgow",
    "sg:classifiers":[
        {
            "category":"Building & Trades",
            "subcategory":"Cleaning & Sanitation",
            "type":"Services"
        }
    ],
    "sg:phone":"+44 1698 821432",
    "sg:postcode":"G72 0UP",
    "sg:province":"South Lanarkshire",
    "sg:tags":[
        "hygiene",
        "cleansing"
    ],
    "wof:name":"Cannon Hygiene Ltd.",
    "wof:placetype":"venue"
},
  "geometry": {"coordinates":[-4.0928077698,55.7846603394],"type":"Point"}
}