{
  "type": "Feature",
  "properties": {
    "addr:full":"81 Craigweil Crescent Stockton-on-tees Durham TS19 0DY",
    "addr:housenumber":"81",
    "addr:postcode":"ts19 0dy",
    "addr:street":"Craigweil Crescent",
    "iso:country":"GB",
    "sg:address":"81 Craigweil Crescent",
    "sg:city":"Stockton-on-tees",
    "sg:classifiers":[
        {
            "category":"Building & Trades",
            "subcategory":"Construction",
            "type":"Services"
        }
    ],
    "sg:phone":"+44 1642 607126",
    "sg:postcode":"TS19 0DY",
    "sg:province":"Durham",
    "sg:tags":[
        "excavation",
        "groundwork",
        "contractor"
    ],
    "wof:name":"Roseworth Groundworkers",
    "wof:placetype":"venue"
},
  "geometry": {"coordinates":[-1.327534,54.575771],"type":"Point"}
}