{
  "type": "Feature",
  "properties": {
    "addr:full":"445 Duke Street Glasgow Glasgow City G31 1RD",
    "addr:housenumber":"445",
    "addr:postcode":"g31 1rd",
    "addr:street":"Duke Street",
    "iso:country":"GB",
    "sg:address":"445 Duke Street",
    "sg:city":"Glasgow",
    "sg:classifiers":[
        {
            "category":"Travel",
            "subcategory":"Travel Agent",
            "type":"Entertainment"
        }
    ],
    "sg:postcode":"G31 1RD",
    "sg:province":"Glasgow City",
    "wof:name":"Home & Away Travel",
    "wof:placetype":"venue"
},
  "geometry": {"coordinates":[-4.2205610275,55.8585014343],"type":"Point"}
}