{
  "type": "Feature",
  "properties": {
    "addr:full":"Lawrence Yard, Lawrence Road London Greater London N15 4EG",
    "addr:postcode":"n15 4eg",
    "addr:street":"Lawrence Road",
    "iso:country":"GB",
    "sg:address":"Lawrence Yard, Lawrence Road",
    "sg:city":"London",
    "sg:classifiers":[
        {
            "category":"Shopping",
            "subcategory":"Clothing, Apparel, & Fashions",
            "type":"Retail Goods"
        }
    ],
    "sg:phone":"+44 20 8880 1004",
    "sg:postcode":"N15 4EG",
    "sg:province":"Greater London",
    "sg:tags":[
        "clothing",
        "fabric"
    ],
    "wof:name":"Rasco",
    "wof:placetype":"venue"
},
  "geometry": {"coordinates":[-0.080009,51.588749],"type":"Point"}
}