{
  "type": "Feature",
  "properties": {
    "addr:full":"Chapeltown Pudsey West Yorkshire LS28 8BS",
    "addr:postcode":"ls28 8bs",
    "addr:street":"West",
    "iso:country":"GB",
    "sg:address":"Chapeltown",
    "sg:city":"Pudsey",
    "sg:classifiers":[
        {
            "category":"Bars & Pubs",
            "type":"Food & Drink"
        }
    ],
    "sg:postcode":"LS28 8BS",
    "sg:province":"West Yorkshire",
    "sg:tags":[
        "pubs",
        "inn"
    ],
    "wof:name":"Commercial Hotel",
    "wof:placetype":"venue"
},
  "geometry": {"coordinates":[-1.670783,53.792324],"type":"Point"}
}