{
  "type": "Feature",
  "properties": {
    "addr:full":"39 Wyville Road Frome Somerset BA11 2BX",
    "addr:housenumber":"39",
    "addr:postcode":"ba11 2bx",
    "addr:street":"Wyville Road",
    "iso:country":"GB",
    "sg:address":"39 Wyville Road",
    "sg:city":"Frome",
    "sg:classifiers":[
        {
            "category":"Professional",
            "subcategory":"Accounting & Tax Preparation",
            "type":"Services"
        }
    ],
    "sg:phone":"+44 1373 471927",
    "sg:postcode":"BA11 2BX",
    "sg:province":"Somerset",
    "sg:tags":[
        "consultant"
    ],
    "wof:name":"B S Tax Services",
    "wof:placetype":"venue"
},
  "geometry": {"coordinates":[-2.300876,51.235447],"type":"Point"}
}