{
  "type": "Feature",
  "properties": {
    "addr:full":"123 Chadburn, Paston Peterborough Cambridgeshire PE4 7DH",
    "addr:housenumber":"123",
    "addr:postcode":"pe4 7dh",
    "addr:street":"Chadburn Paston Peterborough",
    "iso:country":"GB",
    "sg:address":"123 Chadburn, Paston",
    "sg:city":"Peterborough",
    "sg:classifiers":[
        {
            "category":"Fast Food",
            "type":"Food & Drink"
        }
    ],
    "sg:phone":"+44 1733 571908",
    "sg:postcode":"PE4 7DH",
    "sg:province":"Cambridgeshire",
    "sg:tags":[
        "away",
        "meal",
        "outlet",
        "take"
    ],
    "wof:name":"Welcome House Takeaway",
    "wof:placetype":"venue"
},
  "geometry": {"coordinates":[-0.2467110008,52.6063766479],"type":"Point"}
}