{
  "type": "Feature",
  "properties": {
    "addr:full":"Unit 4-5 Phoenix Centre, Road One Industrial Estate Winsford Cheshire CW7 3PZ",
    "addr:housenumber":"unit 4-5",
    "addr:postcode":"cw7 3pz",
    "addr:street":"Phoenix Centre Road One Industrial",
    "iso:country":"GB",
    "sg:address":"Unit 4-5 Phoenix Centre, Road One Industrial Estate",
    "sg:city":"Winsford",
    "sg:classifiers":[
        {
            "category":"Freight",
            "type":"Transportation"
        }
    ],
    "sg:postcode":"CW7 3PZ",
    "sg:province":"Cheshire",
    "sg:tags":[
        "haulage",
        "road"
    ],
    "wof:name":"Panicold Temperature Controled Transport",
    "wof:placetype":"venue"
},
  "geometry": {"coordinates":[-2.489659071,53.1973762512],"type":"Point"}
}