{
  "type": "Feature",
  "properties": {
    "iso:country":"GB",
    "sg:address":"Litcham Road, Mileham",
    "sg:city":"King's Lynn",
    "sg:classifiers":[
        {
            "category":"Government",
            "subcategory":"Post Office",
            "type":"Public Place"
        }
    ],
    "sg:postcode":"PE32 2PS",
    "sg:province":"Norfolk",
    "wof:name":"Mileham Post Office & Stores",
    "wof:placetype":"venue"
},
  "geometry": {"coordinates":[0.83159,52.736622],"type":"Point"}
}