{
  "type": "Feature",
  "properties": {
    "iso:country":"GB",
    "sg:address":"Broomhill Lane",
    "sg:city":"Mansfield",
    "sg:classifiers":[
        {
            "category":"Bars & Pubs",
            "type":"Food & Drink"
        }
    ],
    "sg:phone":"+44 1623 624690",
    "sg:postcode":"NG19 6BN",
    "sg:province":"Derbyshire",
    "sg:tags":[
        "pubs",
        "inn"
    ],
    "wof:name":"The Green Dragon",
    "wof:placetype":"venue"
},
  "geometry": {"coordinates":[-1.213318944,53.1525192261],"type":"Point"}
}