{
  "type": "Feature",
  "properties": {
    "iso:country":"GB",
    "sg:address":"Holcombe Road, Helmshore",
    "sg:city":"Rossendale",
    "sg:classifiers":[
        {
            "category":"Manufacturing",
            "subcategory":"Textiles",
            "type":"Manufacturing & Wholesale Goods"
        },
        {
            "category":"Home & Garden",
            "subcategory":"Furniture",
            "type":"Retail Goods"
        }
    ],
    "sg:phone":"+44 1706 244200",
    "sg:postcode":"BB4 4NP",
    "sg:province":"Lancashire",
    "wof:name":"E Sunter Ltd.",
    "wof:placetype":"venue"
},
  "geometry": {"coordinates":[-2.329174,53.689205],"type":"Point"}
}