{
  "type": "Feature",
  "properties": {
    "iso:country":"GB",
    "sg:address":"23 Horsendale Avenue, Nuthall",
    "sg:city":"Nottingham",
    "sg:classifiers":[
        {
            "category":"Health Services",
            "subcategory":"Podiatrist",
            "type":"Services"
        }
    ],
    "sg:phone":"+44 115 927 2156",
    "sg:postcode":"NG16 1AQ",
    "sg:province":"Derbyshire",
    "sg:tags":[
        "podiatrists",
        "chiropodist"
    ],
    "wof:name":"Elizabeth Pollard Chiropodists",
    "wof:placetype":"venue"
},
  "geometry": {"coordinates":[-1.216958,52.986626],"type":"Point"}
}