{
  "type": "Feature",
  "properties": {
    "iso:country":"GB",
    "sg:address":"7a High Street",
    "sg:city":"Dingwall",
    "sg:classifiers":[
        {
            "category":"Shopping",
            "subcategory":"News",
            "type":"Retail Goods"
        }
    ],
    "sg:postcode":"IV15 9HL",
    "sg:province":"Highland",
    "sg:tags":[
        "newsagent"
    ],
    "wof:name":"Conon Newsagents",
    "wof:placetype":"venue"
},
  "geometry": {"coordinates":[-4.4256529808,57.5951728821],"type":"Point"}
}