{
  "type": "Feature",
  "properties": {
    "iso:country":"GB",
    "sg:address":"Mill Lane, Wick",
    "sg:city":"Littlehampton",
    "sg:classifiers":[
        {
            "category":"Utilities",
            "subcategory":"Refuse",
            "type":"Services"
        }
    ],
    "sg:phone":"+44 1903 713269",
    "sg:postcode":"BN17 7PH",
    "sg:province":"West Sussex",
    "sg:tags":[
        "disposal",
        "waste"
    ],
    "wof:name":"Viridor Waste",
    "wof:placetype":"venue"
},
  "geometry": {"coordinates":[-0.542584002,50.8268814087],"type":"Point"}
}