{
  "type": "Feature",
  "properties": {
    "addr:full":"Waterhouse Lane, Kingswood Tadworth Surrey KT20 6EQ",
    "addr:postcode":"kt20 6eq",
    "addr:street":"Waterhouse Lane",
    "iso:country":"GB",
    "sg:address":"Waterhouse Lane, Kingswood",
    "sg:city":"Tadworth",
    "sg:classifiers":[
        {
            "category":"Home & Garden",
            "subcategory":"Hardware",
            "type":"Retail Goods"
        }
    ],
    "sg:phone":"+44 1737 352111",
    "sg:postcode":"KT20 6EQ",
    "sg:province":"Surrey",
    "sg:tags":[
        "lawnmowers",
        "retailer",
        "machinery",
        "diy"
    ],
    "wof:name":"The Stores",
    "wof:placetype":"venue"
},
  "geometry": {"coordinates":[-0.2148769945,51.2953910828],"type":"Point"}
}