{
  "type": "Feature",
  "properties": {
    "iso:country":"GB",
    "sg:address":"10 Church Street",
    "sg:city":"Ilfracombe",
    "sg:classifiers":[
        {
            "category":"Food & Beverages",
            "subcategory":"Fruits & Vegetables",
            "type":"Retail Goods"
        }
    ],
    "sg:phone":"+44 1271 865738",
    "sg:postcode":"EX34 8HA",
    "sg:province":"Devon",
    "sg:tags":[
        "greengrocer"
    ],
    "wof:name":"Sara's Basket",
    "wof:placetype":"venue"
},
  "geometry": {"coordinates":[-4.126514,51.205833],"type":"Point"}
}