{
  "type": "Feature",
  "properties": {
    "iso:country":"GB",
    "sg:address":"Lewes Rd, Halland",
    "sg:city":"Lewes",
    "sg:classifiers":[
        {
            "category":"Government",
            "subcategory":"Post Office",
            "type":"Public Place"
        }
    ],
    "sg:postcode":"BN8 6PN",
    "sg:province":"East Sussex",
    "wof:name":"Frazzell,Valerie,",
    "wof:placetype":"venue"
},
  "geometry": {"coordinates":[0.1791249961,50.8927841187],"type":"Point"}
}