{
  "type": "Feature",
  "properties": {
    "iso:country":"GB",
    "sg:address":"Ashford Business Complex, 166 Feltham Rd",
    "sg:city":"Ashford",
    "sg:classifiers":[
        {
            "category":"Personal",
            "type":"Services"
        }
    ],
    "sg:postcode":"TW15 1YQ",
    "sg:province":"Greater London",
    "sg:tags":[
        "delivery"
    ],
    "wof:name":"James,Andrew,",
    "wof:placetype":"venue"
},
  "geometry": {"coordinates":[-0.462444,51.432976],"type":"Point"}
}