{
  "type": "Feature",
  "properties": {
    "iso:country":"GB",
    "sg:address":"118 Commercial Street",
    "sg:city":"London",
    "sg:classifiers":[
        {
            "category":"Professional",
            "subcategory":"Computer Services",
            "type":"Services"
        }
    ],
    "sg:phone":"+44 20 7247 5385",
    "sg:postcode":"E1 6NF",
    "sg:province":"Greater London",
    "sg:tags":[
        "information"
    ],
    "wof:name":"British American Arts Association",
    "wof:placetype":"venue"
},
  "geometry": {"coordinates":[-0.0745,51.520615],"type":"Point"}
}