{
  "type": "Feature",
  "properties": {
    "iso:country":"GB",
    "sg:address":"Berry Hill, Stanton",
    "sg:city":"Morpeth",
    "sg:classifiers":[
        {
            "category":"Farming",
            "subcategory":"Livestock Farm",
            "type":"Manufacturing & Wholesale Goods"
        }
    ],
    "sg:postcode":"NE65 8PR",
    "sg:province":"Northumberland",
    "sg:tags":[
        "others"
    ],
    "wof:name":"G Redpath & Sons",
    "wof:placetype":"venue"
},
  "geometry": {"coordinates":[-1.794799,55.202717],"type":"Point"}
}