{
  "type": "Feature",
  "properties": {
    "addr:full":"Unit 6 Block 2 River Pl Kilbirnie North Ayrshire KA25 7EN",
    "addr:housenumber":"unit 6 block 2",
    "addr:postcode":"ka25 7en",
    "addr:street":"River Pl",
    "iso:country":"GB",
    "sg:address":"Unit 6 Block 2 River Pl",
    "sg:city":"Kilbirnie",
    "sg:classifiers":[
        {
            "category":"Retail",
            "subcategory":"Repair Shop",
            "type":"Services"
        }
    ],
    "sg:phone":"+44 1505 682219",
    "sg:postcode":"KA25 7EN",
    "sg:province":"North Ayrshire",
    "sg:tags":[
        "radio",
        "television",
        "video"
    ],
    "wof:name":"P J C Electronics",
    "wof:placetype":"venue"
},
  "geometry": {"coordinates":[-4.6834402084,55.7502212524],"type":"Point"}
}