{
  "type": "Feature",
  "properties": {
    "iso:country":"GB",
    "sg:address":"Unith, 83 Lynch Lane",
    "sg:city":"Weymouth",
    "sg:classifiers":[
        {
            "category":"Retail",
            "subcategory":"Auto Repair",
            "type":"Services"
        }
    ],
    "sg:phone":"+44 1305 789103",
    "sg:postcode":"DT4 9DN",
    "sg:province":"Dorset",
    "sg:tags":[
        "modification",
        "garage",
        "related"
    ],
    "wof:name":"Mico Motors",
    "wof:placetype":"venue"
},
  "geometry": {"coordinates":[-2.4871389866,50.6076087952],"type":"Point"}
}