{
  "type": "Feature",
  "properties": {
    "addr:full":"19 Nurseries Rd Glasgow East Dunbartonshire G69 6UL",
    "addr:housenumber":"19",
    "addr:postcode":"g69 6ul",
    "addr:street":"Nurseries Rd",
    "iso:country":"GB",
    "sg:address":"19 Nurseries Rd",
    "sg:city":"Glasgow",
    "sg:classifiers":[
        {
            "category":"Building & Trades",
            "subcategory":"Equipment Rental",
            "type":"Services"
        }
    ],
    "sg:phone":"+44 141 771 7388",
    "sg:postcode":"G69 6UL",
    "sg:province":"East Dunbartonshire",
    "sg:tags":[
        "plant",
        "machinery"
    ],
    "wof:name":"UK Plant Ltd",
    "wof:placetype":"venue"
},
  "geometry": {"coordinates":[-4.105596,55.852322],"type":"Point"}
}