{
  "type": "Feature",
  "properties": {
    "addr:full":"Unit 2 Bordenwingate, Primrosehill Stockton-on-tees Durham TS19 0BJ",
    "addr:housenumber":"unit 2",
    "addr:postcode":"ts19 0bj",
    "addr:street":"Bordenwingate Primrosehill",
    "iso:country":"GB",
    "sg:address":"Unit 2 Bordenwingate, Primrosehill",
    "sg:city":"Stockton-on-tees",
    "sg:classifiers":[
        {
            "category":"Manufacturing",
            "subcategory":"Building Materials",
            "type":"Manufacturing & Wholesale Goods"
        }
    ],
    "sg:phone":"+44 1642 615806",
    "sg:postcode":"TS19 0BJ",
    "sg:province":"Durham",
    "sg:tags":[
        "mnfr",
        "marble",
        "specialist"
    ],
    "wof:name":"Athenium Marble",
    "wof:placetype":"venue"
},
  "geometry": {"coordinates":[-1.330024004,54.5784950256],"type":"Point"}
}