{
  "type": "Feature",
  "properties": {
    "addr:full":"5 Lower Downside, Downside Shepton Mallet Somerset BA4 4JP",
    "addr:housenumber":"5",
    "addr:postcode":"ba4 4jp",
    "addr:street":"Lower Downside",
    "iso:country":"GB",
    "sg:address":"5 Lower Downside, Downside",
    "sg:city":"Shepton Mallet",
    "sg:classifiers":[
        {
            "category":"Retail",
            "subcategory":"Repair Shop",
            "type":"Services"
        }
    ],
    "sg:phone":"+44 1749 345295",
    "sg:postcode":"BA4 4JP",
    "sg:province":"Somerset",
    "sg:tags":[
        "maintenance"
    ],
    "wof:name":"Lesley G Oxborough",
    "wof:placetype":"venue"
},
  "geometry": {"coordinates":[-2.579556942,51.1648330688],"type":"Point"}
}