{
  "type": "Feature",
  "properties": {
    "addr:full":"Dodmoore Farm Grounds, Dodford Northampton Buckinghamshire NN7 4TA",
    "addr:postcode":"nn7 4ta",
    "addr:street":"Dodford",
    "iso:country":"GB",
    "sg:address":"Dodmoore Farm Grounds, Dodford",
    "sg:city":"Northampton",
    "sg:classifiers":[
        {
            "category":"Wholesale",
            "subcategory":"Farm Supplies",
            "type":"Manufacturing & Wholesale Goods"
        }
    ],
    "sg:postcode":"NN7 4TA",
    "sg:province":"Buckinghamshire",
    "sg:tags":[
        "straw",
        "hay",
        "merchant"
    ],
    "wof:name":"B M Summers Farming Contractor",
    "wof:placetype":"venue"
},
  "geometry": {"coordinates":[-1.101331,52.23951],"type":"Point"}
}