{
  "type": "Feature",
  "properties": {
    "addr:full":"Unit 14, Bingswood Trading Estate, Whaley Bridge High Peak Cheshire SK23 7LY",
    "addr:housenumber":"unit 14;estate whaley",
    "addr:postcode":"sk23 7ly",
    "addr:street":"Trading",
    "iso:country":"GB",
    "sg:address":"Unit 14, Bingswood Trading Estate, Whaley Bridge",
    "sg:city":"High Peak",
    "sg:classifiers":[
        {
            "category":"Shopping",
            "subcategory":"Computers & Home Electronics",
            "type":"Retail Goods"
        }
    ],
    "sg:postcode":"SK23 7LY",
    "sg:province":"Cheshire",
    "sg:tags":[
        "equipment",
        "audio-visual"
    ],
    "wof:name":"Remphoto Ltd.",
    "wof:placetype":"venue"
},
  "geometry": {"coordinates":[-1.999753,53.320736],"type":"Point"}
}