{
  "type": "Feature",
  "properties": {
    "addr:full":"35 Wells Road, Chilcompton Bath Somerset BA3 4EX",
    "addr:housenumber":"35",
    "addr:postcode":"ba3 4ex",
    "addr:street":"Wells Road",
    "iso:country":"GB",
    "sg:address":"35 Wells Road, Chilcompton",
    "sg:city":"Bath",
    "sg:classifiers":[
        {
            "category":"Autos & Motor Vehicles",
            "subcategory":"Automobile Sales",
            "type":"Retail Goods"
        }
    ],
    "sg:phone":"+44 1761 232345",
    "sg:postcode":"BA3 4EX",
    "sg:province":"Somerset",
    "sg:tags":[
        "car"
    ],
    "wof:name":"The Downside Motor Co. (Mendip) Ltd.",
    "wof:placetype":"venue"
},
  "geometry": {"coordinates":[-2.50137,51.261024],"type":"Point"}
}