{
  "type": "Feature",
  "properties": {
    "iso:country":"GB",
    "sg:address":"Unit 1, 184 Greathampton Row, Hockley",
    "sg:city":"Birmingham",
    "sg:classifiers":[
        {
            "category":"Shopping",
            "subcategory":"Computers & Home Electronics",
            "type":"Retail Goods"
        }
    ],
    "sg:phone":"+44 121 236 2552",
    "sg:postcode":"B19 3JP",
    "sg:province":"West Midlands",
    "wof:name":"New World Tech",
    "wof:placetype":"venue"
},
  "geometry": {"coordinates":[-1.906387,52.489292],"type":"Point"}
}