{
  "type": "Feature",
  "properties": {
    "addr:full":"9 Walsingham Place Truro Cornwall TR1 2RP",
    "addr:housenumber":"9",
    "addr:postcode":"tr1 2rp",
    "addr:street":"Walsingham Place",
    "iso:country":"GB",
    "sg:address":"9 Walsingham Place",
    "sg:city":"Truro",
    "sg:classifiers":[
        {
            "category":"Professional",
            "subcategory":"Employment Agencies",
            "type":"Services"
        }
    ],
    "sg:phone":"+44 1872 223603",
    "sg:postcode":"TR1 2RP",
    "sg:province":"Cornwall",
    "sg:tags":[
        "consultant"
    ],
    "wof:name":"Travail Employment Group",
    "wof:placetype":"venue"
},
  "geometry": {"coordinates":[-5.051049,50.259529],"type":"Point"}
}