{
  "type": "Feature",
  "properties": {
    "iso:country":"GB",
    "sg:address":"Unit B3, Hortonpark Industrial Estate, Hortonwood",
    "sg:city":"Telford",
    "sg:classifiers":[
        {
            "category":"Manufacturing",
            "subcategory":"Wood Products",
            "type":"Manufacturing & Wholesale Goods"
        }
    ],
    "sg:phone":"+44 1952 606633",
    "sg:postcode":"TF1 7GX",
    "sg:province":"Shropshire",
    "sg:tags":[
        "packaging",
        "crate",
        "pallets"
    ],
    "wof:name":"Eurofilms Extrusion Ltd.",
    "wof:placetype":"venue"
},
  "geometry": {"coordinates":[-2.462514,52.71497],"type":"Point"}
}