{
  "type": "Feature",
  "properties": {
    "iso:country":"GB",
    "sg:address":"The Nursery, 54 Mapledene Road",
    "sg:city":"London",
    "sg:classifiers":[
        {
            "category":"Farming",
            "subcategory":"Nursery",
            "type":"Manufacturing & Wholesale Goods"
        }
    ],
    "sg:phone":"+44 20 7249 8139",
    "sg:postcode":"E8 3LE",
    "sg:province":"Greater London",
    "sg:tags":[
        "creche"
    ],
    "wof:name":"The Mapledene Early Years Centre",
    "wof:placetype":"venue"
},
  "geometry": {"coordinates":[-0.06425,51.541889],"type":"Point"}
}