{
  "type": "Feature",
  "properties": {
    "iso:country":"GB",
    "sg:address":"13 St Nicholas Centre, St Nicholas Way",
    "sg:city":"Sutton",
    "sg:classifiers":[
        {
            "category":"Banks & Credit Unions",
            "subcategory":"Bank",
            "type":"Services"
        }
    ],
    "sg:phone":"+44 20 8776 6993",
    "sg:postcode":"SM1 1AW",
    "sg:province":"Surrey",
    "wof:name":"NatWest",
    "wof:placetype":"venue"
},
  "geometry": {"coordinates":[-0.196369,51.367851],"type":"Point"}
}