{
  "type": "Feature",
  "properties": {
    "addr:full":"Beech Cottage, 2 The Grn Preston Lancashire PR3 0HS",
    "addr:housenumber":"2",
    "addr:postcode":"pr3 0hs",
    "addr:street":"The Grn",
    "iso:country":"GB",
    "sg:address":"Beech Cottage, 2 The Grn",
    "sg:city":"Preston",
    "sg:classifiers":[
        {
            "category":"Organizations",
            "subcategory":"Community Association",
            "type":"Services"
        }
    ],
    "sg:postcode":"PR3 0HS",
    "sg:province":"Lancashire",
    "sg:tags":[
        "relation",
        "public"
    ],
    "wof:name":"Jane Barratt",
    "wof:placetype":"venue"
},
  "geometry": {"coordinates":[-2.800564,53.879898],"type":"Point"}
}