{
  "type": "Feature",
  "properties": {
    "iso:country":"GB",
    "sg:address":"Suite 7 The Sanctuary, 23 Oak Hill Grove",
    "sg:city":"Surbiton",
    "sg:classifiers":[
        {
            "category":"Professional",
            "subcategory":"Accounting & Tax Preparation",
            "type":"Services"
        }
    ],
    "sg:phone":"+44 20 8390 3344",
    "sg:postcode":"KT6 6DU",
    "sg:province":"Surrey",
    "sg:tags":[
        "accountant"
    ],
    "wof:name":"Cohen & Partners",
    "wof:placetype":"venue"
},
  "geometry": {"coordinates":[-0.306949,51.392059],"type":"Point"}
}