{
  "type": "Feature",
  "properties": {
    "addr:full":"491 Abergele Road, Old Colwyn Colwyn Bay Conwy LL29 9AE",
    "addr:housenumber":"491",
    "addr:postcode":"ll29 9ae",
    "addr:street":"Abergele Road",
    "iso:country":"GB",
    "sg:address":"491 Abergele Road, Old Colwyn",
    "sg:city":"Colwyn Bay",
    "sg:classifiers":[
        {
            "category":"Building & Trades",
            "subcategory":"Construction",
            "type":"Services"
        },
        {
            "category":"Organizations",
            "subcategory":"Professional Association",
            "type":"Services"
        }
    ],
    "sg:phone":"+44 1492 516416",
    "sg:postcode":"LL29 9AE",
    "sg:province":"Conwy",
    "sg:tags":[
        "union",
        "activity"
    ],
    "wof:name":"Unison",
    "wof:placetype":"venue"
},
  "geometry": {"coordinates":[-3.688006,53.289455],"type":"Point"}
}