{
  "type": "Feature",
  "properties": {
    "addr:full":"55 Mardy Crescent, Castle Park Estate Caerphilly Caerphilly CF83 1PT",
    "addr:housenumber":"55",
    "addr:postcode":"cf83 1pt",
    "addr:street":"Mardy Crescent;Park",
    "iso:country":"GB",
    "sg:address":"55 Mardy Crescent, Castle Park Estate",
    "sg:city":"Caerphilly",
    "sg:classifiers":[
        {
            "category":"Building & Trades",
            "subcategory":"Construction",
            "type":"Services"
        }
    ],
    "sg:postcode":"CF83 1PT",
    "sg:province":"Caerphilly",
    "sg:tags":[
        "builder"
    ],
    "wof:name":"John Torres & Sons",
    "wof:placetype":"venue"
},
  "geometry": {"coordinates":[-3.2106330395,51.5765609741],"type":"Point"}
}