{
  "type": "Feature",
  "properties": {
    "iso:country":"GB",
    "sg:address":"Glenmavis Garage, Torphichen Road",
    "sg:city":"Bathgate",
    "sg:classifiers":[
        {
            "category":"Autos & Motor Vehicles",
            "subcategory":"Auto Supplies",
            "type":"Retail Goods"
        }
    ],
    "sg:phone":"+44 1506 636663",
    "sg:postcode":"EH48 4LA",
    "sg:province":"West Lothian",
    "sg:tags":[
        "tyre"
    ],
    "wof:name":"Rapid Fit",
    "wof:placetype":"venue"
},
  "geometry": {"coordinates":[-3.6547269821,55.9338340759],"type":"Point"}
}