{
  "type": "Feature",
  "properties": {
    "addr:full":"Unit C4 Hilton Trading Estate, Hilton Road Wolverhampton Staffordshire WV4 6DW",
    "addr:postcode":"wv4 6dw",
    "addr:street":"Hilton Road",
    "iso:country":"GB",
    "sg:address":"Unit C4 Hilton Trading Estate, Hilton Road",
    "sg:city":"Wolverhampton",
    "sg:classifiers":[
        {
            "category":"Professional",
            "subcategory":"Engineering",
            "type":"Services"
        }
    ],
    "sg:postcode":"WV4 6DW",
    "sg:province":"Staffordshire",
    "wof:name":"J H B Hocknell & Sons",
    "wof:placetype":"venue"
},
  "geometry": {"coordinates":[-2.1084690094,52.5599403381],"type":"Point"}
}