{
  "type": "Feature",
  "properties": {
    "addr:full":"37-41 Bissell Street Birmingham West Midlands B5 7HR",
    "addr:housenumber":"37-41",
    "addr:postcode":"b5 7hr",
    "addr:street":"Bissell Street",
    "iso:country":"GB",
    "sg:address":"37-41 Bissell Street",
    "sg:city":"Birmingham",
    "sg:classifiers":[
        {
            "category":"Shopping",
            "subcategory":"Bicycles & Sporting Goods",
            "type":"Retail Goods"
        }
    ],
    "sg:phone":"+44 121 622 4475",
    "sg:postcode":"B5 7HR",
    "sg:province":"West Midlands",
    "sg:tags":[
        "equipment",
        "marine",
        "supply"
    ],
    "wof:name":"Atbara Ci Ltd.",
    "wof:placetype":"venue"
},
  "geometry": {"coordinates":[-1.893134,52.468807],"type":"Point"}
}