{
  "type": "Feature",
  "properties": {
    "addr:full":"De Grey Rooms, St. Leonards Place York North Yorkshire YO1 7HB",
    "addr:postcode":"yo1 7hb",
    "addr:street":"De;St. Leonards Place York",
    "iso:country":"GB",
    "sg:address":"De Grey Rooms, St. Leonards Place",
    "sg:city":"York",
    "sg:classifiers":[
        {
            "category":"Arts & Performance",
            "subcategory":"Arts Center",
            "type":"Entertainment"
        }
    ],
    "sg:phone":"+44 1904 642761",
    "sg:postcode":"YO1 7HB",
    "sg:province":"North Yorkshire",
    "sg:tags":[
        "centre"
    ],
    "wof:name":"York Arts Arena",
    "wof:placetype":"venue"
},
  "geometry": {"coordinates":[-1.085345,53.961651],"type":"Point"}
}