{
  "type": "Feature",
  "properties": {
    "addr:full":"16-17 The Square, Alvechurch Birmingham Worcestershire B48 7LA",
    "addr:housenumber":"16-17",
    "addr:postcode":"b48 7la",
    "addr:street":"The Square Alvechurch",
    "iso:country":"GB",
    "sg:address":"16-17 The Square, Alvechurch",
    "sg:city":"Birmingham",
    "sg:classifiers":[
        {
            "category":"Manufacturing",
            "subcategory":"Tools & Machinery",
            "type":"Manufacturing & Wholesale Goods"
        },
        {
            "category":"Insurance",
            "subcategory":"Insurance Agent",
            "type":"Services"
        }
    ],
    "sg:phone":"+44 121 445 3307",
    "sg:postcode":"B48 7LA",
    "sg:province":"Worcestershire",
    "sg:tags":[
        "society",
        "broker",
        "friendly"
    ],
    "wof:name":"DAVID E MATTHEWS",
    "wof:placetype":"venue"
},
  "geometry": {"coordinates":[-1.9595019817,52.3517951965],"type":"Point"}
}