{
  "type": "Feature",
  "properties": {
    "addr:full":"5 Larchfield Rd, Bearsden Glasgow East Dunbartonshire G61 1AR",
    "addr:housenumber":"5",
    "addr:postcode":"g61 1ar",
    "addr:street":"Larchfield Rd",
    "iso:country":"GB",
    "sg:address":"5 Larchfield Rd, Bearsden",
    "sg:city":"Glasgow",
    "sg:classifiers":[
        {
            "category":"Building & Trades",
            "subcategory":"Construction",
            "type":"Services"
        }
    ],
    "sg:phone":"+44 141 942 7247",
    "sg:postcode":"G61 1AR",
    "sg:province":"East Dunbartonshire",
    "sg:tags":[
        "joiner",
        "carpenter"
    ],
    "wof:name":"Forrest Contracts",
    "wof:placetype":"venue"
},
  "geometry": {"coordinates":[-4.324502,55.903381],"type":"Point"}
}