{
  "type": "Feature",
  "properties": {
    "iso:country":"GB",
    "sg:address":"79 Marylebone High Street",
    "sg:city":"London",
    "sg:classifiers":[
        {
            "category":"Bars & Pubs",
            "type":"Food & Drink"
        }
    ],
    "sg:phone":"+44 20 7486 1350",
    "sg:postcode":"W1U 5JZ",
    "sg:province":"Greater London",
    "sg:tags":[
        "pubs",
        "inn"
    ],
    "wof:name":"Punch Retail (Holdings) Ltd.",
    "wof:placetype":"venue"
},
  "geometry": {"coordinates":[-0.151969,51.520802],"type":"Point"}
}