{
  "type": "Feature",
  "properties": {
    "iso:country":"GB",
    "sg:address":"Standingstone, Alves",
    "sg:city":"Elgin",
    "sg:classifiers":[
        {
            "category":"Travel",
            "subcategory":"Hotels & Motels",
            "type":"Entertainment"
        }
    ],
    "sg:phone":"+44 1343 850269",
    "sg:postcode":"IV30 8UZ",
    "sg:province":"Moray",
    "sg:tags":[
        "self",
        "catering"
    ],
    "wof:name":"Oliphant,G,",
    "wof:placetype":"venue"
},
  "geometry": {"coordinates":[-3.4479839802,57.642375946],"type":"Point"}
}