{
  "type": "Feature",
  "properties": {
    "addr:full":"11 Brookland Dr, Maghull Liverpool Lancashire L31 3HN",
    "addr:housenumber":"11",
    "addr:postcode":"l31 3hn",
    "addr:street":"Brookland Dr",
    "iso:country":"GB",
    "sg:address":"11 Brookland Dr, Maghull",
    "sg:city":"Liverpool",
    "sg:classifiers":[
        {
            "category":"Farming",
            "subcategory":"Fish & Marine Products",
            "type":"Manufacturing & Wholesale Goods"
        }
    ],
    "sg:postcode":"L31 3HN",
    "sg:province":"Lancashire",
    "sg:tags":[
        "fishmonger"
    ],
    "wof:name":"J J G Meats",
    "wof:placetype":"venue"
},
  "geometry": {"coordinates":[-2.9366929531,53.5084991455],"type":"Point"}
}