{
  "type": "Feature",
  "properties": {
    "iso:country":"GB",
    "sg:address":"4 St Christopher Close, Rawnsley",
    "sg:city":"Cannock",
    "sg:classifiers":[
        {
            "category":"Professional",
            "subcategory":"Engineering",
            "type":"Services"
        }
    ],
    "sg:postcode":"WS12 5FH",
    "sg:province":"Staffordshire",
    "sg:tags":[
        "contractor",
        "electrical",
        "engineer"
    ],
    "wof:name":"G W F Electrical Services",
    "wof:placetype":"venue"
},
  "geometry": {"coordinates":[-1.967557,52.709026],"type":"Point"}
}