{
  "type": "Feature",
  "properties": {
    "addr:full":"Unit 10 Blackburn Road Bathgate West Lothian EH48 2ER",
    "addr:housenumber":"unit 10",
    "addr:postcode":"eh48 2er",
    "addr:street":"Blackburn Road Bathgate",
    "iso:country":"GB",
    "sg:address":"Unit 10 Blackburn Road",
    "sg:city":"Bathgate",
    "sg:classifiers":[
        {
            "category":"Personal",
            "type":"Services"
        }
    ],
    "sg:phone":"+44 1506 630459",
    "sg:postcode":"EH48 2ER",
    "sg:province":"West Lothian",
    "sg:tags":[
        "delivery"
    ],
    "wof:name":"Interlink Clyde Valley",
    "wof:placetype":"venue"
},
  "geometry": {"coordinates":[-3.6216239929,55.8924942017],"type":"Point"}
}