{
  "type": "Feature",
  "properties": {
    "addr:full":"28 Stratford Road Leicester Leicestershire LE3 2SU",
    "addr:housenumber":"28",
    "addr:postcode":"le3 2su",
    "addr:street":"Stratford Road",
    "iso:country":"GB",
    "sg:address":"28 Stratford Road",
    "sg:city":"Leicester",
    "sg:classifiers":[
        {
            "category":"Transit Center",
            "subcategory":"Passenger",
            "type":"Transportation"
        },
        {
            "category":"Retail",
            "subcategory":"Animal Services",
            "type":"Services"
        }
    ],
    "sg:phone":"+44 116 289 5562",
    "sg:postcode":"LE3 2SU",
    "sg:province":"Leicestershire",
    "sg:tags":[
        "boarding",
        "pet",
        "kennel",
        "catteries"
    ],
    "wof:name":"Hazelhurst Cattery",
    "wof:placetype":"venue"
},
  "geometry": {"coordinates":[-1.1744389534,52.616268158],"type":"Point"}
}