{
  "type": "Feature",
  "properties": {
    "addr:full":"18 Arnside Road Waterlooville Hampshire PO7 7UP",
    "addr:housenumber":"18",
    "addr:postcode":"po7 7up",
    "addr:street":"Arnside Road",
    "iso:country":"GB",
    "sg:address":"18 Arnside Road",
    "sg:city":"Waterlooville",
    "sg:classifiers":[
        {
            "category":"Manufacturing",
            "subcategory":"Wood Products",
            "type":"Manufacturing & Wholesale Goods"
        }
    ],
    "sg:phone":"+44 23 9245 5878",
    "sg:postcode":"PO7 7UP",
    "sg:province":"Hampshire",
    "sg:tags":[
        "maker",
        "cabinet"
    ],
    "wof:name":"Unetech Ltd.",
    "wof:placetype":"venue"
},
  "geometry": {"coordinates":[-1.032691,50.882805],"type":"Point"}
}