{
  "type": "Feature",
  "properties": {
    "addr:full":"95 Gloucester Street Cirencester Gloucestershire GL7 2DW",
    "addr:housenumber":"95",
    "addr:postcode":"gl7 2dw",
    "addr:street":"Gloucester Street",
    "iso:country":"GB",
    "sg:address":"95 Gloucester Street",
    "sg:city":"Cirencester",
    "sg:classifiers":[
        {
            "category":"Freight",
            "type":"Transportation"
        },
        {
            "category":"Professional",
            "subcategory":"Business Services",
            "type":"Services"
        }
    ],
    "sg:phone":"+44 1285 831496",
    "sg:postcode":"GL7 2DW",
    "sg:province":"Gloucestershire",
    "sg:tags":[
        "haulage",
        "hospitality",
        "corporate",
        "transport",
        "road"
    ],
    "wof:name":"EVENTS LOGISTICS",
    "wof:placetype":"venue"
},
  "geometry": {"coordinates":[-1.9726109505,51.7213935852],"type":"Point"}
}