{
  "type": "Feature",
  "properties": {
    "addr:full":"Bury Old Road, Prestwich Manchester Greater Manchester M25 0EX",
    "addr:postcode":"m25 0ex",
    "addr:street":"Old Road",
    "iso:country":"GB",
    "sg:address":"Bury Old Road, Prestwich",
    "sg:city":"Manchester",
    "sg:classifiers":[
        {
            "category":"Place Of Worship",
            "type":"Public Place"
        }
    ],
    "sg:phone":"+44 161 740 1634",
    "sg:postcode":"M25 0EX",
    "sg:province":"Greater Manchester",
    "wof:name":"Holy Law Synagogue",
    "wof:placetype":"venue"
},
  "geometry": {"coordinates":[-2.2635331154,53.5236091614],"type":"Point"}
}