{
  "type": "Feature",
  "properties": {
    "addr:full":"Chapel St, Stanley Crook Durham DL15 9SA",
    "addr:postcode":"dl15 9sa",
    "addr:street":"Chapel St",
    "iso:country":"GB",
    "sg:address":"Chapel St, Stanley",
    "sg:city":"Crook",
    "sg:classifiers":[
        {
            "category":"Freight",
            "type":"Transportation"
        }
    ],
    "sg:phone":"+44 1388 762645",
    "sg:postcode":"DL15 9SA",
    "sg:province":"Durham",
    "sg:tags":[
        "haulage",
        "road"
    ],
    "wof:name":"Mount Pleasant Motors",
    "wof:placetype":"venue"
},
  "geometry": {"coordinates":[-1.748794,54.714363],"type":"Point"}
}