{
  "type": "Feature",
  "properties": {
    "iso:country":"GB",
    "sg:address":"Kelvin House, 1 Totteridge Avenue",
    "sg:city":"High Wycombe",
    "sg:classifiers":[
        {
            "category":"Professional",
            "subcategory":"Management & Consulting",
            "type":"Services"
        }
    ],
    "sg:phone":"+44 1494 533088",
    "sg:postcode":"HP13 6XG",
    "sg:province":"Buckinghamshire",
    "sg:tags":[
        "consultant",
        "business"
    ],
    "wof:name":"Afro Caribbean Trade of Excellence Ltd",
    "wof:placetype":"venue"
},
  "geometry": {"coordinates":[-0.73735,51.629417],"type":"Point"}
}