{
  "type": "Feature",
  "properties": {
    "addr:full":"57 Barn Lane, Golborne Warrington Cheshire WA3 3NU",
    "addr:housenumber":"57",
    "addr:postcode":"wa3 3nu",
    "addr:street":"Barn Lane",
    "iso:country":"GB",
    "sg:address":"57 Barn Lane, Golborne",
    "sg:city":"Warrington",
    "sg:classifiers":[
        {
            "category":"Manufacturing",
            "subcategory":"Signs",
            "type":"Manufacturing & Wholesale Goods"
        }
    ],
    "sg:postcode":"WA3 3NU",
    "sg:province":"Cheshire",
    "sg:tags":[
        "writer"
    ],
    "wof:name":"A B C D E-Signs",
    "wof:placetype":"venue"
},
  "geometry": {"coordinates":[-2.6045780182,53.4744644165],"type":"Point"}
}