{
  "type": "Feature",
  "properties": {
    "iso:country":"GB",
    "sg:address":"Unit 5 Stretton Green Distributi, On Park, Langford Way Appl",
    "sg:city":"Warrington",
    "sg:classifiers":[
        {
            "category":"Shopping",
            "subcategory":"Computers & Home Electronics",
            "type":"Retail Goods"
        },
        {
            "category":"Professional",
            "subcategory":"Computer Services",
            "type":"Services"
        }
    ],
    "sg:phone":"+44 1925 260700",
    "sg:postcode":"WA4 4TQ",
    "sg:province":"Cheshire",
    "sg:tags":[
        "system",
        "software"
    ],
    "wof:name":"Service Source Europe Ltd.",
    "wof:placetype":"venue"
},
  "geometry": {"coordinates":[-2.545164,53.350422],"type":"Point"}
}