{
  "type": "Feature",
  "properties": {
    "addr:full":"8 Newbury Street Andover Hampshire SP10 1DW",
    "addr:housenumber":"8",
    "addr:postcode":"sp10 1dw",
    "addr:street":"Newbury Street",
    "iso:country":"GB",
    "sg:address":"8 Newbury Street",
    "sg:city":"Andover",
    "sg:classifiers":[
        {
            "category":"Professional",
            "subcategory":"Lawyer & Legal Services",
            "type":"Services"
        }
    ],
    "sg:phone":"+44 1264 400500",
    "sg:postcode":"SP10 1DW",
    "sg:province":"Hampshire",
    "sg:tags":[
        "solicitor"
    ],
    "wof:name":"Parker Bullen Solicitors",
    "wof:placetype":"venue"
},
  "geometry": {"coordinates":[-1.477875948,51.2093315125],"type":"Point"}
}