{
  "type": "Feature",
  "properties": {
    "addr:full":"42 High Street Swanage Dorset BH19 2NX",
    "addr:housenumber":"42",
    "addr:postcode":"bh19 2nx",
    "addr:street":"High Street",
    "iso:country":"GB",
    "sg:address":"42 High Street",
    "sg:city":"Swanage",
    "sg:classifiers":[
        {
            "category":"Shopping",
            "subcategory":"Florist",
            "type":"Retail Goods"
        }
    ],
    "sg:postcode":"BH19 2NX",
    "sg:province":"Dorset",
    "wof:name":"Fletcher Ann Eleanor",
    "wof:placetype":"venue"
},
  "geometry": {"coordinates":[-1.958135,50.608513],"type":"Point"}
}