{
  "type": "Feature",
  "properties": {
    "addr:full":"62 Locks Heath Park Road, Locks Heath Southampton Hampshire SO31 6LZ",
    "addr:housenumber":"62",
    "addr:postcode":"so31 6lz",
    "addr:street":"Locks Heath Park Road",
    "iso:country":"GB",
    "sg:address":"62 Locks Heath Park Road, Locks Heath",
    "sg:city":"Southampton",
    "sg:classifiers":[
        {
            "category":"Home & Garden",
            "subcategory":"Household Appliances",
            "type":"Retail Goods"
        }
    ],
    "sg:phone":"+44 1489 573422",
    "sg:postcode":"SO31 6LZ",
    "sg:province":"Hampshire",
    "sg:tags":[
        "refrigeration",
        "air conditioning"
    ],
    "wof:name":"Southcold Refrigeration & Air Conditioning",
    "wof:placetype":"venue"
},
  "geometry": {"coordinates":[-1.2711119652,50.8598747253],"type":"Point"}
}