{
  "type": "Feature",
  "properties": {
    "iso:country":"GB",
    "sg:address":"Gloucester Road, Wolverton",
    "sg:city":"Milton Keynes",
    "sg:classifiers":[
        {
            "category":"Health Services",
            "subcategory":"Doctor",
            "type":"Services"
        },
        {
            "category":"Health Services",
            "subcategory":"Clinic",
            "type":"Services"
        }
    ],
    "sg:phone":"+44 1908 316617",
    "sg:postcode":"MK12 5DF",
    "sg:province":"Buckinghamshire",
    "sg:tags":[
        "nh",
        "practitioners"
    ],
    "wof:name":"MILTON KEYNES COMMUNITY FOUNDATION LTD",
    "wof:placetype":"venue"
},
  "geometry": {"coordinates":[-0.8092089891,52.0562667847],"type":"Point"}
}