{
  "type": "Feature",
  "properties": {
    "addr:full":"24-26 Orchard Square Sheffield South Yorkshire S1 2FB",
    "addr:housenumber":"24-26",
    "addr:postcode":"s1 2fb",
    "addr:street":"Orchard Square",
    "iso:country":"GB",
    "sg:address":"24-26 Orchard Square",
    "sg:city":"Sheffield",
    "sg:classifiers":[
        {
            "category":"Shopping",
            "subcategory":"Books",
            "type":"Retail Goods"
        }
    ],
    "sg:phone":"+44 114 272 8971",
    "sg:postcode":"S1 2FB",
    "sg:province":"South Yorkshire",
    "sg:tags":[
        "bookseller"
    ],
    "wof:name":"Waterstones",
    "wof:placetype":"venue"
},
  "geometry": {"coordinates":[-1.470299,53.381359],"type":"Point"}
}