{
  "type": "Feature",
  "properties": {
    "addr:full":"Robert Boby Way Bury St Edmunds Suffolk IP33 3DH",
    "addr:postcode":"ip33 3dh",
    "addr:street":"Boby Way",
    "iso:country":"GB",
    "sg:address":"Robert Boby Way",
    "sg:city":"Bury St Edmunds",
    "sg:classifiers":[
        {
            "category":"Shopping",
            "type":"Retail Goods"
        }
    ],
    "sg:phone":"+44 1284 704812",
    "sg:postcode":"IP33 3DH",
    "sg:province":"Suffolk",
    "sg:tags":[
        "part",
        "accessory"
    ],
    "wof:name":"Halfords Superstore",
    "wof:placetype":"venue"
},
  "geometry": {"coordinates":[0.7088209987,52.2435302734],"type":"Point"}
}