{
  "type": "Feature",
  "properties": {
    "addr:full":"92 Sedlescombe Rd, Fulham Fulham Greater London SW6 1RB",
    "addr:housenumber":"92",
    "addr:postcode":"sw6 1rb",
    "addr:street":"Sedlescombe Rd",
    "iso:country":"GB",
    "sg:address":"92 Sedlescombe Rd, Fulham",
    "sg:city":"Fulham",
    "sg:classifiers":[
        {
            "category":"Professional",
            "subcategory":"Art Services",
            "type":"Services"
        }
    ],
    "sg:phone":"+44 20 7381 9987",
    "sg:postcode":"SW6 1RB",
    "sg:province":"Greater London",
    "sg:tags":[
        "picture",
        "restoration"
    ],
    "wof:name":"D & J Winter",
    "wof:placetype":"venue"
},
  "geometry": {"coordinates":[-0.1979500055,51.4856147766],"type":"Point"}
}