{
  "type": "Feature",
  "properties": {
    "addr:full":"72 Alston Dr Milton Keynes Buckinghamshire MK13 9HG",
    "addr:housenumber":"72",
    "addr:postcode":"mk13 9hg",
    "addr:street":"Alston Dr",
    "iso:country":"GB",
    "sg:address":"72 Alston Dr",
    "sg:city":"Milton Keynes",
    "sg:classifiers":[
        {
            "category":"Professional",
            "type":"Services"
        }
    ],
    "sg:phone":"+44 1908 226446",
    "sg:postcode":"MK13 9HG",
    "sg:province":"Buckinghamshire",
    "sg:tags":[
        "aircraft",
        "maintenance"
    ],
    "wof:name":"Metroaviation Ltd",
    "wof:placetype":"venue"
},
  "geometry": {"coordinates":[-0.793686,52.044975],"type":"Point"}
}