{
  "type": "Feature",
  "properties": {
    "addr:full":"45 Standard Way Fareham Hampshire PO16 8XD",
    "addr:housenumber":"45",
    "addr:postcode":"po16 8xd",
    "addr:street":"Standard Way",
    "iso:country":"GB",
    "sg:address":"45 Standard Way",
    "sg:city":"Fareham",
    "sg:classifiers":[
        {
            "category":"Home & Garden",
            "subcategory":"Building Materials",
            "type":"Retail Goods"
        }
    ],
    "sg:phone":"+44 1329 828233",
    "sg:postcode":"PO16 8XD",
    "sg:province":"Hampshire",
    "sg:tags":[
        "ready",
        "mixed",
        "concrete"
    ],
    "wof:name":"Concrete Testing Services",
    "wof:placetype":"venue"
},
  "geometry": {"coordinates":[-1.175189,50.860809],"type":"Point"}
}