{
  "type": "Feature",
  "properties": {
    "addr:full":"Hobgate Rd Wolverhampton Staffordshire WV10 0PR",
    "addr:postcode":"wv10 0pr",
    "addr:street":"Hobgate Rd",
    "iso:country":"GB",
    "sg:address":"Hobgate Rd",
    "sg:city":"Wolverhampton",
    "sg:classifiers":[
        {
            "category":"Government",
            "subcategory":"Office",
            "type":"Public Place"
        }
    ],
    "sg:postcode":"WV10 0PR",
    "sg:province":"Staffordshire",
    "sg:tags":[
        "local"
    ],
    "wof:name":"Wolverhampton Borough Council",
    "wof:placetype":"venue"
},
  "geometry": {"coordinates":[-2.107273,52.594032],"type":"Point"}
}