{
  "type": "Feature",
  "properties": {
    "iso:country":"GB",
    "sg:address":"Care Of The Vicarage, 34 Northend",
    "sg:city":"Bath",
    "sg:classifiers":[
        {
            "category":"Place Of Worship",
            "type":"Public Place"
        }
    ],
    "sg:phone":"+44 1225 858192",
    "sg:postcode":"BA1 7ES",
    "sg:province":"Bath and North East Somerset",
    "wof:name":"St Catherine's C Of E Church",
    "wof:placetype":"venue"
},
  "geometry": {"coordinates":[-2.3151290417,51.4063911438],"type":"Point"}
}