{
  "type": "Feature",
  "properties": {
    "addr:full":"Hill House Edge Quarry, Cartworth Moor Huddersfield South Yorkshire HD9 2RL",
    "addr:postcode":"hd9 2rl",
    "addr:street":"Cartworth Moor",
    "iso:country":"GB",
    "sg:address":"Hill House Edge Quarry, Cartworth Moor",
    "sg:city":"Huddersfield",
    "sg:classifiers":[
        {
            "category":"Wholesale",
            "subcategory":"Construction Materials",
            "type":"Manufacturing & Wholesale Goods"
        }
    ],
    "sg:phone":"+44 1484 684152",
    "sg:postcode":"HD9 2RL",
    "sg:province":"South Yorkshire",
    "sg:tags":[
        "merchant",
        "stone"
    ],
    "wof:name":"George Graham Sons & Co. Ltd.",
    "wof:placetype":"venue"
},
  "geometry": {"coordinates":[-1.80232,53.556629],"type":"Point"}
}