{
  "type": "Feature",
  "properties": {
    "addr:full":"Unit 11b Wilsons Park Manchester Greater Manchester M40 8WN",
    "addr:housenumber":"unit 11b",
    "addr:postcode":"m40 8wn",
    "addr:street":"Wilsons Park",
    "iso:country":"GB",
    "sg:address":"Unit 11b Wilsons Park",
    "sg:city":"Manchester",
    "sg:classifiers":[
        {
            "category":"Retail",
            "subcategory":"Auto Repair",
            "type":"Services"
        }
    ],
    "sg:phone":"+44 161 203 4755",
    "sg:postcode":"M40 8WN",
    "sg:province":"Greater Manchester",
    "sg:tags":[
        "modification",
        "garage"
    ],
    "wof:name":"M & G Repairs",
    "wof:placetype":"venue"
},
  "geometry": {"coordinates":[-2.2115950584,53.4962158203],"type":"Point"}
}