{
  "type": "Feature",
  "properties": {
    "iso:country":"GB",
    "sg:address":"1-3 Saville Street",
    "sg:city":"Sheffield",
    "sg:classifiers":[
        {
            "category":"Shopping",
            "type":"Retail Goods"
        }
    ],
    "sg:phone":"+44 114 275 7776",
    "sg:postcode":"S4 7TF",
    "sg:province":"South Yorkshire",
    "sg:tags":[
        "part",
        "accessory"
    ],
    "wof:name":"Hartwell Motor Factors",
    "wof:placetype":"venue"
},
  "geometry": {"coordinates":[-1.45897,53.38908],"type":"Point"}
}