{
  "type": "Feature",
  "properties": {
    "addr:full":"A47 Thorney Road, Guyhirn Wisbech Cambridgeshire PE13 4AA",
    "addr:postcode":"pe13 4aa",
    "addr:street":"Thorney Road",
    "iso:country":"GB",
    "sg:address":"A47 Thorney Road, Guyhirn",
    "sg:city":"Wisbech",
    "sg:classifiers":[
        {
            "category":"Restaurant",
            "type":"Food & Drink"
        }
    ],
    "sg:phone":"+44 1945 450200",
    "sg:postcode":"PE13 4AA",
    "sg:province":"Cambridgeshire",
    "wof:name":"Little Chef",
    "wof:placetype":"venue"
},
  "geometry": {"coordinates":[0.0153550003,52.6125526428],"type":"Point"}
}