{
  "type": "Feature",
  "properties": {
    "addr:full":"Millers Barn Worcester Herefordshire WR6 5DH",
    "addr:postcode":"wr6 5dh",
    "iso:country":"GB",
    "sg:address":"Millers Barn",
    "sg:city":"Worcester",
    "sg:classifiers":[
        {
            "category":"Building & Trades",
            "subcategory":"Construction",
            "type":"Services"
        }
    ],
    "sg:phone":"+44 1886 884729",
    "sg:postcode":"WR6 5DH",
    "sg:province":"Herefordshire",
    "sg:tags":[
        "builder"
    ],
    "wof:name":"John Shuker Construction Ltd",
    "wof:placetype":"venue"
},
  "geometry": {"coordinates":[-2.420249939,52.1719818115],"type":"Point"}
}