{
  "type": "Feature",
  "properties": {
    "addr:full":"22 Mellor Road, Branston Burton-on-trent Derbyshire DE14 3EE",
    "addr:housenumber":"22",
    "addr:postcode":"de14 3ee",
    "addr:street":"Mellor Road",
    "iso:country":"GB",
    "sg:address":"22 Mellor Road, Branston",
    "sg:city":"Burton-on-trent",
    "sg:classifiers":[
        {
            "category":"Building & Trades",
            "subcategory":"Construction",
            "type":"Services"
        }
    ],
    "sg:phone":"+44 1283 535517",
    "sg:postcode":"DE14 3EE",
    "sg:province":"Derbyshire",
    "sg:tags":[
        "glazier",
        "decorator",
        "painter"
    ],
    "wof:name":"R Jones",
    "wof:placetype":"venue"
},
  "geometry": {"coordinates":[-1.654872,52.787849],"type":"Point"}
}