{
  "type": "Feature",
  "properties": {
    "iso:country":"GB",
    "sg:address":"16 Broad Street",
    "sg:city":"Ross-on-wye",
    "sg:classifiers":[
        {
            "category":"Shopping",
            "subcategory":"Clothing, Apparel, & Fashions",
            "type":"Retail Goods"
        }
    ],
    "sg:phone":"+44 1989 763565",
    "sg:postcode":"HR9 7EA",
    "sg:province":"Gloucestershire",
    "sg:tags":[
        "shop"
    ],
    "wof:name":"Ruby Tuesday",
    "wof:placetype":"venue"
},
  "geometry": {"coordinates":[-2.582914114,51.9152908325],"type":"Point"}
}