{
  "type": "Feature",
  "properties": {
    "addr:full":"183 High St South Dunstable Bedfordshire LU6 3SJ",
    "addr:housenumber":"183",
    "addr:postcode":"lu6 3sj",
    "addr:street":"High St South",
    "iso:country":"GB",
    "sg:address":"183 High St South",
    "sg:city":"Dunstable",
    "sg:classifiers":[
        {
            "category":"Bars & Pubs",
            "type":"Food & Drink"
        }
    ],
    "sg:postcode":"LU6 3SJ",
    "sg:province":"Bedfordshire",
    "sg:tags":[
        "pubs",
        "inn"
    ],
    "wof:name":"The Froth & Elbow",
    "wof:placetype":"venue"
},
  "geometry": {"coordinates":[-0.514626,51.882065],"type":"Point"}
}