{
  "type": "Feature",
  "properties": {
    "addr:full":"The Wheel House, Bonds Mill Stonehouse Gloucestershire GL10 3RF",
    "addr:postcode":"gl10 3rf",
    "addr:street":"Bonds Mill",
    "iso:country":"GB",
    "sg:address":"The Wheel House, Bonds Mill",
    "sg:city":"Stonehouse",
    "sg:classifiers":[
        {
            "category":"Social Services",
            "subcategory":"Retirement Home",
            "type":"Services"
        }
    ],
    "sg:phone":"+44 1453 792121",
    "sg:postcode":"GL10 3RF",
    "sg:province":"Gloucestershire",
    "sg:tags":[
        "care"
    ],
    "wof:name":"The Caring Connection Ltd",
    "wof:placetype":"venue"
},
  "geometry": {"coordinates":[-2.299894,51.746845],"type":"Point"}
}