{
  "type": "Feature",
  "properties": {
    "iso:country":"GB",
    "sg:address":"Oak Lodge, Primrose Lane, Manningford Bruce",
    "sg:city":"Pewsey",
    "sg:classifiers":[
        {
            "category":"Retail",
            "subcategory":"Driving School",
            "type":"Services"
        }
    ],
    "sg:phone":"+44 1672 563336",
    "sg:postcode":"SN9 6JG",
    "sg:province":"Wiltshire",
    "wof:name":"Central Wilts Driving School",
    "wof:placetype":"venue"
},
  "geometry": {"coordinates":[-1.803116,51.328327],"type":"Point"}
}