{
  "type": "Feature",
  "properties": {
    "addr:full":"Unit 4 Britannia Business Park Waltham Cross Essex EN8 7PF",
    "addr:housenumber":"unit 4 britannia business",
    "addr:postcode":"en8 7pf",
    "addr:street":"Park Waltham Cross",
    "iso:country":"GB",
    "sg:address":"Unit 4 Britannia Business Park",
    "sg:city":"Waltham Cross",
    "sg:classifiers":[
        {
            "category":"Recreation",
            "subcategory":"Amusement Park",
            "type":"Entertainment"
        }
    ],
    "sg:phone":"+44 1992 788277",
    "sg:postcode":"EN8 7PF",
    "sg:province":"Essex",
    "sg:tags":[
        "arcade"
    ],
    "wof:name":"Music Hire Group Ltd.",
    "wof:placetype":"venue"
},
  "geometry": {"coordinates":[-0.033814,51.69051],"type":"Point"}
}