{
  "type": "Feature",
  "properties": {
    "iso:country":"GB",
    "sg:address":"8 Bridge Street",
    "sg:city":"Hemel Hempstead",
    "sg:classifiers":[
        {
            "category":"Restaurant",
            "type":"Food & Drink"
        }
    ],
    "sg:phone":"+44 1442 254056",
    "sg:postcode":"HP1 1EF",
    "sg:province":"Hertfordshire",
    "wof:name":"Watergardens",
    "wof:placetype":"venue"
},
  "geometry": {"coordinates":[-0.472643,51.751141],"type":"Point"}
}