{
  "type": "Feature",
  "properties": {
    "addr:full":"361 New Kings Road London Greater London SW6 4RJ",
    "addr:housenumber":"361",
    "addr:postcode":"sw6 4rj",
    "addr:street":"New Kings Road",
    "iso:country":"GB",
    "sg:address":"361 New Kings Road",
    "sg:city":"London",
    "sg:classifiers":[
        {
            "category":"Professional",
            "type":"Services"
        }
    ],
    "sg:phone":"+44 20 7384 1522",
    "sg:postcode":"SW6 4RJ",
    "sg:province":"Greater London",
    "sg:tags":[
        "caterer"
    ],
    "wof:name":"Sumner's Ltd.",
    "wof:placetype":"venue"
},
  "geometry": {"coordinates":[-0.206431,51.471153],"type":"Point"}
}