{
  "type": "Feature",
  "properties": {
    "addr:full":"75-77 Chatsworth Drive, Cherwell Banbury Oxfordshire OX16 8XY",
    "addr:housenumber":"75-77",
    "addr:postcode":"ox16 8xy",
    "addr:street":"Chatsworth Drive",
    "iso:country":"GB",
    "sg:address":"75-77 Chatsworth Drive, Cherwell",
    "sg:city":"Banbury",
    "sg:classifiers":[
        {
            "category":"Retail",
            "subcategory":"Funeral Services",
            "type":"Services"
        }
    ],
    "sg:phone":"+44 1295 267365",
    "sg:postcode":"OX16 8XY",
    "sg:province":"Oxfordshire",
    "wof:name":"Cherwell Heights",
    "wof:placetype":"venue"
},
  "geometry": {"coordinates":[-1.3400280476,52.0611114502],"type":"Point"}
}