{
  "type": "Feature",
  "properties": {
    "addr:full":"5 Church Road, Hetton Le Hole Houghton-le-spring Durham DH5 9AH",
    "addr:housenumber":"5",
    "addr:postcode":"dh5 9ah",
    "addr:street":"Church Road",
    "iso:country":"GB",
    "sg:address":"5 Church Road, Hetton Le Hole",
    "sg:city":"Houghton-le-spring",
    "sg:classifiers":[
        {
            "category":"Building & Trades",
            "subcategory":"Construction",
            "type":"Services"
        }
    ],
    "sg:phone":"+44 191 526 8665",
    "sg:postcode":"DH5 9AH",
    "sg:province":"Durham",
    "sg:tags":[
        "builder"
    ],
    "wof:name":"D W Jefferson & Sons",
    "wof:placetype":"venue"
},
  "geometry": {"coordinates":[-1.4515030384,54.8265228271],"type":"Point"}
}