{
  "type": "Feature",
  "properties": {
    "iso:country":"GB",
    "sg:address":"West Crossleys",
    "sg:city":"Dumfries",
    "sg:classifiers":[
        {
            "category":"Military Area",
            "subcategory":"Army Base",
            "type":"Public Place"
        }
    ],
    "sg:postcode":"DG2 0RA",
    "sg:province":"Dumfries and Galloway",
    "sg:tags":[
        "joinery",
        "centre"
    ],
    "wof:name":"A B Hastings & Son",
    "wof:placetype":"venue"
},
  "geometry": {"coordinates":[-3.65679,55.110168],"type":"Point"}
}