{
  "type": "Feature",
  "properties": {
    "addr:full":"1 West End, Pentewan St Austell Cornwall PL26 6BX",
    "addr:housenumber":"1",
    "addr:postcode":"pl26 6bx",
    "addr:street":"West End Pentewan",
    "iso:country":"GB",
    "sg:address":"1 West End, Pentewan",
    "sg:city":"St Austell",
    "sg:classifiers":[
        {
            "category":"Sports & Exercise",
            "subcategory":"Bicycle Rental",
            "type":"Entertainment"
        },
        {
            "category":"Parking",
            "subcategory":"Bicycle",
            "type":"Transportation"
        }
    ],
    "sg:phone":"+44 1726 844242",
    "sg:postcode":"PL26 6BX",
    "sg:province":"Cornwall",
    "sg:tags":[
        "renting",
        "leasing",
        "cycle"
    ],
    "wof:name":"Pentewan Valley Cycle Hire",
    "wof:placetype":"venue"
},
  "geometry": {"coordinates":[-4.785545,50.291813],"type":"Point"}
}