{
  "type": "Feature",
  "properties": {
    "addr:full":"Narborough Wood House, Desford Road, Enderby Leicester Leicestershire LE19 4AD",
    "addr:postcode":"le19 4ad",
    "addr:street":"Narborough;Desford Road",
    "iso:country":"GB",
    "sg:address":"Narborough Wood House, Desford Road, Enderby",
    "sg:city":"Leicester",
    "sg:classifiers":[
        {
            "category":"Shopping",
            "subcategory":"Clothing, Apparel, & Fashions",
            "type":"Retail Goods"
        }
    ],
    "sg:postcode":"LE19 4AD",
    "sg:province":"Leicestershire",
    "sg:tags":[
        "shop",
        "hat"
    ],
    "wof:name":"The House of Hats",
    "wof:placetype":"venue"
},
  "geometry": {"coordinates":[-1.2064640522,52.5886383057],"type":"Point"}
}