{
  "type": "Feature",
  "properties": {
    "addr:full":"Garbetts Hall, Buttington Welshpool Shropshire SY21 8HB",
    "addr:postcode":"sy21 8hb",
    "iso:country":"GB",
    "sg:address":"Garbetts Hall, Buttington",
    "sg:city":"Welshpool",
    "sg:classifiers":[
        {
            "category":"Farming",
            "subcategory":"Farm",
            "type":"Manufacturing & Wholesale Goods"
        }
    ],
    "sg:postcode":"SY21 8HB",
    "sg:province":"Shropshire",
    "sg:tags":[
        "mixed",
        "crop"
    ],
    "wof:name":"W K Davies",
    "wof:placetype":"venue"
},
  "geometry": {"coordinates":[-3.1118030548,52.6653137207],"type":"Point"}
}