{
  "type": "Feature",
  "properties": {
    "iso:country":"GB",
    "sg:address":"Newbury Hill, Hampstead Norreys",
    "sg:city":"Thatcham",
    "sg:classifiers":[
        {
            "category":"Education",
            "subcategory":"School",
            "type":"Public Place"
        },
        {
            "category":"Government",
            "subcategory":"Office",
            "type":"Public Place"
        }
    ],
    "sg:phone":"+44 1635 201371",
    "sg:postcode":"RG18 0TR",
    "sg:province":"Berkshire",
    "sg:tags":[
        "local",
        "authority"
    ],
    "wof:name":"Hampstead Norreys C of E Primary School",
    "wof:placetype":"venue"
},
  "geometry": {"coordinates":[-1.240419,51.483891],"type":"Point"}
}