{
  "type": "Feature",
  "properties": {
    "addr:full":"The Old Post House, Ampney Crucis Cirencester Gloucestershire GL7 5RR",
    "addr:postcode":"gl7 5rr",
    "iso:country":"GB",
    "sg:address":"The Old Post House, Ampney Crucis",
    "sg:city":"Cirencester",
    "sg:classifiers":[
        {
            "category":"Banks & Credit Unions",
            "subcategory":"Bureau De Change",
            "type":"Services"
        }
    ],
    "sg:postcode":"GL7 5RR",
    "sg:province":"Gloucestershire",
    "sg:tags":[
        "town",
        "consultant",
        "planning"
    ],
    "wof:name":"John Alison",
    "wof:placetype":"venue"
},
  "geometry": {"coordinates":[-1.8616089821,51.6711883545],"type":"Point"}
}