{
  "type": "Feature",
  "properties": {
    "iso:country":"GB",
    "sg:address":"105 Nelson Rd",
    "sg:city":"Gillingham",
    "sg:classifiers":[
        {
            "category":"Health Services",
            "subcategory":"Doctor",
            "type":"Services"
        }
    ],
    "sg:phone":"+44 1634 582992",
    "sg:postcode":"ME7 4LT",
    "sg:province":"Kent",
    "sg:tags":[
        "practitioners"
    ],
    "wof:name":"Ghosh Dr K",
    "wof:placetype":"venue"
},
  "geometry": {"coordinates":[0.550735,51.379498],"type":"Point"}
}