{
  "type": "Feature",
  "properties": {
    "addr:full":"Jesmond Buildings, Jesmond Rd Chester Cheshire CH1 4DQ",
    "addr:postcode":"ch1 4dq",
    "addr:street":"Jesmond Rd",
    "iso:country":"GB",
    "sg:address":"Jesmond Buildings, Jesmond Rd",
    "sg:city":"Chester",
    "sg:classifiers":[
        {
            "category":"Shopping",
            "subcategory":"Computers & Home Electronics",
            "type":"Retail Goods"
        }
    ],
    "sg:phone":"+44 1244 399223",
    "sg:postcode":"CH1 4DQ",
    "sg:province":"Cheshire",
    "sg:tags":[
        "sound",
        "equipment"
    ],
    "wof:name":"Dels Sound System",
    "wof:placetype":"venue"
},
  "geometry": {"coordinates":[-2.903889,53.196548],"type":"Point"}
}