{
  "type": "Feature",
  "properties": {
    "addr:full":"6 The Centre Bristol City of Bristol BS18 1ED",
    "addr:housenumber":"6",
    "addr:postcode":"bs18 1ed",
    "addr:street":"The Centre",
    "iso:country":"GB",
    "sg:address":"6 The Centre",
    "sg:city":"Bristol",
    "sg:classifiers":[
        {
            "category":"Sports & Exercise",
            "subcategory":"Gym",
            "type":"Entertainment"
        }
    ],
    "sg:phone":"+44 7973 225178",
    "sg:postcode":"BS18 1ED",
    "sg:province":"City of Bristol",
    "sg:tags":[
        "fitness",
        "health",
        "centre"
    ],
    "wof:name":"Bosue's Health & Fitness Studio",
    "wof:placetype":"venue"
},
  "geometry": {"coordinates":[-2.561153,51.435631],"type":"Point"}
}