{
  "type": "Feature",
  "properties": {
    "addr:full":"130a High Street Street Somerset BA16 0ER",
    "addr:housenumber":"130a",
    "addr:postcode":"ba16 0er",
    "addr:street":"High Street Street",
    "iso:country":"GB",
    "sg:address":"130a High Street",
    "sg:city":"Street",
    "sg:classifiers":[
        {
            "category":"Professional",
            "subcategory":"Lawyer & Legal Services",
            "type":"Services"
        }
    ],
    "sg:phone":"+44 1458 443461",
    "sg:postcode":"BA16 0ER",
    "sg:province":"Somerset",
    "sg:tags":[
        "solicitor"
    ],
    "wof:name":"Helliar & Co.",
    "wof:placetype":"venue"
},
  "geometry": {"coordinates":[-2.742777,51.125286],"type":"Point"}
}