{
  "type": "Feature",
  "properties": {
    "addr:full":"90 High Street Harrow Greater London HA1 3LP",
    "addr:housenumber":"90",
    "addr:postcode":"ha1 3lp",
    "addr:street":"High Street",
    "iso:country":"GB",
    "sg:address":"90 High Street",
    "sg:city":"Harrow",
    "sg:classifiers":[
        {
            "category":"Home & Garden",
            "subcategory":"Hardware",
            "type":"Retail Goods"
        }
    ],
    "sg:postcode":"HA1 3LP",
    "sg:province":"Greater London",
    "sg:tags":[
        "heat",
        "mech",
        "exchanger"
    ],
    "wof:name":"Frigor-Box Uk Limited",
    "wof:placetype":"venue"
},
  "geometry": {"coordinates":[-0.339868,51.570225],"type":"Point"}
}