{
  "type": "Feature",
  "properties": {
    "addr:full":"228 Church Street, Westhoughton Bolton Lancashire BL5 3QW",
    "addr:housenumber":"228",
    "addr:postcode":"bl5 3qw",
    "addr:street":"Church Street",
    "iso:country":"GB",
    "sg:address":"228 Church Street, Westhoughton",
    "sg:city":"Bolton",
    "sg:classifiers":[
        {
            "category":"Home & Garden",
            "subcategory":"Carpets & Floor Coverings",
            "type":"Retail Goods"
        }
    ],
    "sg:phone":"+44 1942 818612",
    "sg:postcode":"BL5 3QW",
    "sg:province":"Lancashire",
    "sg:tags":[
        "carpets",
        "retailer",
        "rug",
        "matting"
    ],
    "wof:name":"Peter Bashall Carpets",
    "wof:placetype":"venue"
},
  "geometry": {"coordinates":[-2.52353,53.555454],"type":"Point"}
}