{
  "type": "Feature",
  "properties": {
    "iso:country":"GB",
    "sg:address":"11 Cratfield Road",
    "sg:city":"Bury St Edmunds",
    "sg:classifiers":[
        {
            "category":"Shopping",
            "subcategory":"Bicycles & Sporting Goods",
            "type":"Retail Goods"
        }
    ],
    "sg:phone":"+44 1284 755006",
    "sg:postcode":"IP32 7DF",
    "sg:province":"Suffolk",
    "sg:tags":[
        "water",
        "cooler"
    ],
    "wof:name":"Pure Choice",
    "wof:placetype":"venue"
},
  "geometry": {"coordinates":[0.745332,52.238716],"type":"Point"}
}