{
  "type": "Feature",
  "properties": {
    "addr:full":"Lichfield Ho, 32 Bore St Lichfield Staffordshire WS13 6LL",
    "addr:housenumber":"32",
    "addr:postcode":"ws13 6ll",
    "addr:street":"Bore St",
    "iso:country":"GB",
    "sg:address":"Lichfield Ho, 32 Bore St",
    "sg:city":"Lichfield",
    "sg:classifiers":[
        {
            "category":"Shopping",
            "subcategory":"Antiques",
            "type":"Retail Goods"
        }
    ],
    "sg:phone":"+44 1543 416008",
    "sg:postcode":"WS13 6LL",
    "sg:province":"Staffordshire",
    "wof:name":"Tudor Antique Centre",
    "wof:placetype":"venue"
},
  "geometry": {"coordinates":[-1.8196599483,52.6840286255],"type":"Point"}
}