{
  "type": "Feature",
  "properties": {
    "iso:country":"GB",
    "sg:address":"Blairgowrie, Staffords Corner, Great Wigborough",
    "sg:city":"Colchester",
    "sg:classifiers":[
        {
            "category":"Farming",
            "subcategory":"Livestock Farm",
            "type":"Manufacturing & Wholesale Goods"
        }
    ],
    "sg:phone":"+44 1206 735412",
    "sg:postcode":"CO5 7RP",
    "sg:province":"Essex",
    "sg:tags":[
        "others"
    ],
    "wof:name":"Alfred J Roots",
    "wof:placetype":"venue"
},
  "geometry": {"coordinates":[0.853297,51.799072],"type":"Point"}
}