{
  "type": "Feature",
  "properties": {
    "iso:country":"GB",
    "sg:address":"81 Seafield Road",
    "sg:city":"Aberdeen",
    "sg:classifiers":[
        {
            "category":"Travel",
            "subcategory":"Hotels & Motels",
            "type":"Entertainment"
        }
    ],
    "sg:postcode":"AB15 7YU",
    "sg:province":"Aberdeen City",
    "wof:name":"Big Beat Ltd.",
    "wof:placetype":"venue"
},
  "geometry": {"coordinates":[-2.1464710236,57.1334075928],"type":"Point"}
}