{
  "type": "Feature",
  "properties": {
    "iso:country":"GB",
    "sg:address":"Unit 12, Cwmdraw Industrial Estate, Newtown",
    "sg:city":"Ebbw Vale",
    "sg:classifiers":[
        {
            "category":"Manufacturing",
            "subcategory":"Watercraft",
            "type":"Manufacturing & Wholesale Goods"
        }
    ],
    "sg:phone":"+44 1495 306431",
    "sg:postcode":"NP23 5AE",
    "sg:province":"Blaenau Gwent",
    "sg:tags":[
        "repairer",
        "sailmaker"
    ],
    "wof:name":"Topflight Sails",
    "wof:placetype":"venue"
},
  "geometry": {"coordinates":[-3.200026,51.777477],"type":"Point"}
}