{
  "type": "Feature",
  "properties": {
    "iso:country":"GB",
    "sg:address":"The Hills, Arrow Lane, North Littleton",
    "sg:city":"Evesham",
    "sg:classifiers":[
        {
            "category":"Building & Trades",
            "subcategory":"Landscaping Services",
            "type":"Services"
        }
    ],
    "sg:phone":"+44 1386 830647",
    "sg:postcode":"WR11 8QS",
    "sg:province":"Gloucestershire",
    "sg:tags":[
        "landscape",
        "contractor"
    ],
    "wof:name":"Vale Garden & Building Services",
    "wof:placetype":"venue"
},
  "geometry": {"coordinates":[-1.8815740347,52.1238861084],"type":"Point"}
}