{
  "type": "Feature",
  "properties": {
    "addr:full":"11 Castle Street Swansea Neath Port Talbot SA1 1JF",
    "addr:housenumber":"11",
    "addr:postcode":"sa1 1jf",
    "addr:street":"Castle Street",
    "iso:country":"GB",
    "sg:address":"11 Castle Street",
    "sg:city":"Swansea",
    "sg:classifiers":[
        {
            "category":"Shopping",
            "subcategory":"Thrift Store",
            "type":"Retail Goods"
        }
    ],
    "sg:phone":"+44 1792 466099",
    "sg:postcode":"SA1 1JF",
    "sg:province":"Neath Port Talbot",
    "sg:tags":[
        "shop",
        "charity"
    ],
    "wof:name":"Christian Lewis Trust",
    "wof:placetype":"venue"
},
  "geometry": {"coordinates":[-3.942144,51.62075],"type":"Point"}
}