{
  "type": "Feature",
  "properties": {
    "addr:full":"Old House Farm, Ardingly Road, West Hoathly East Grinstead East Sussex RH19 4RA",
    "addr:postcode":"rh19 4ra",
    "addr:street":"Ardingly Road West",
    "iso:country":"GB",
    "sg:address":"Old House Farm, Ardingly Road, West Hoathly",
    "sg:city":"East Grinstead",
    "sg:classifiers":[
        {
            "category":"Farming",
            "subcategory":"Livestock Farm",
            "type":"Manufacturing & Wholesale Goods"
        },
        {
            "category":"Farming",
            "subcategory":"Farm",
            "type":"Manufacturing & Wholesale Goods"
        }
    ],
    "sg:phone":"+44 1342 715480",
    "sg:postcode":"RH19 4RA",
    "sg:province":"East Sussex",
    "sg:tags":[
        "mixed",
        "crop",
        "others"
    ],
    "wof:name":"George R Furse",
    "wof:placetype":"venue"
},
  "geometry": {"coordinates":[-0.07753,51.083939],"type":"Point"}
}