{
  "type": "Feature",
  "properties": {
    "iso:country":"GB",
    "sg:address":"19 Harbour Street, Shopping Centre",
    "sg:city":"Whitstable",
    "sg:classifiers":[
        {
            "category":"Professional",
            "subcategory":"Printing & Photocopies",
            "type":"Services"
        }
    ],
    "sg:phone":"+44 1227 277698",
    "sg:postcode":"CT5 1AQ",
    "sg:province":"Kent",
    "sg:tags":[
        "trophy"
    ],
    "wof:name":"Martins Trophies & Engraving",
    "wof:placetype":"venue"
},
  "geometry": {"coordinates":[1.024711,51.361362],"type":"Point"}
}