{
  "type": "Feature",
  "properties": {
    "addr:full":"31 Theobalds Way, Frimley Camberley Hampshire GU16 9RF",
    "addr:housenumber":"31",
    "addr:postcode":"gu16 9rf",
    "addr:street":"Theobalds Way",
    "iso:country":"GB",
    "sg:address":"31 Theobalds Way, Frimley",
    "sg:city":"Camberley",
    "sg:classifiers":[
        {
            "category":"Professional",
            "subcategory":"Computer Services",
            "type":"Services"
        }
    ],
    "sg:phone":"+44 7973 311638",
    "sg:postcode":"GU16 9RF",
    "sg:province":"Hampshire",
    "sg:tags":[
        "system",
        "software"
    ],
    "wof:name":"Sandshore Ltd.",
    "wof:placetype":"venue"
},
  "geometry": {"coordinates":[-0.7019050121,51.3258132935],"type":"Point"}
}