{
  "type": "Feature",
  "properties": {
    "iso:country":"GB",
    "sg:address":"49 Holywell Street",
    "sg:city":"Glasgow",
    "sg:classifiers":[
        {
            "category":"Manufacturing",
            "subcategory":"Food",
            "type":"Manufacturing & Wholesale Goods"
        },
        {
            "category":"Food & Beverages",
            "subcategory":"Supermarket",
            "type":"Retail Goods"
        }
    ],
    "sg:phone":"+44 141 554 1137",
    "sg:postcode":"G31 4BT",
    "sg:province":"Glasgow City",
    "sg:tags":[
        "frozen",
        "product",
        "manufacturer"
    ],
    "wof:name":"Cardowan Creameries Ltd",
    "wof:placetype":"venue"
},
  "geometry": {"coordinates":[-4.2078838348,55.8527069092],"type":"Point"}
}