{
  "type": "Feature",
  "properties": {
    "addr:full":"West Orchard Farm Wareham Dorset BH20 5NU",
    "addr:postcode":"bh20 5nu",
    "addr:street":"West Orchard Farm",
    "iso:country":"GB",
    "sg:address":"West Orchard Farm",
    "sg:city":"Wareham",
    "sg:classifiers":[
        {
            "category":"Farming",
            "subcategory":"Livestock Farm",
            "type":"Manufacturing & Wholesale Goods"
        }
    ],
    "sg:phone":"+44 1929 480734",
    "sg:postcode":"BH20 5NU",
    "sg:province":"Dorset",
    "sg:tags":[
        "others"
    ],
    "wof:name":"R F Percy",
    "wof:placetype":"venue"
},
  "geometry": {"coordinates":[-2.0573039055,50.6376075745],"type":"Point"}
}