{
  "type": "Feature",
  "properties": {
    "addr:full":"14 Fort Road Margate Kent CT9 1HF",
    "addr:housenumber":"14",
    "addr:postcode":"ct9 1hf",
    "addr:street":"Fort Road",
    "iso:country":"GB",
    "sg:address":"14 Fort Road",
    "sg:city":"Margate",
    "sg:classifiers":[
        {
            "category":"Professional",
            "subcategory":"Testing Lab",
            "type":"Services"
        },
        {
            "category":"Retail",
            "subcategory":"Auto Repair",
            "type":"Services"
        }
    ],
    "sg:phone":"+44 1843 232100",
    "sg:postcode":"CT9 1HF",
    "sg:province":"Kent",
    "sg:tags":[
        "modification",
        "garage",
        "mot"
    ],
    "wof:name":"Thanet Testing Centre",
    "wof:placetype":"venue"
},
  "geometry": {"coordinates":[1.3820979595,51.3907279968],"type":"Point"}
}