{
  "type": "Feature",
  "properties": {
    "addr:full":"1 Church St Belper Derbyshire DE56 1EY",
    "addr:housenumber":"1",
    "addr:postcode":"de56 1ey",
    "addr:street":"Church St",
    "iso:country":"GB",
    "sg:address":"1 Church St",
    "sg:city":"Belper",
    "sg:classifiers":[
        {
            "category":"Personal",
            "subcategory":"Beauty Salon",
            "type":"Services"
        }
    ],
    "sg:phone":"+44 1773 820345",
    "sg:postcode":"DE56 1EY",
    "sg:province":"Derbyshire",
    "sg:tags":[
        "unisex",
        "hairdresser"
    ],
    "wof:name":"Carl Anthonys",
    "wof:placetype":"venue"
},
  "geometry": {"coordinates":[-1.4788160324,53.0245399475],"type":"Point"}
}