{
  "type": "Feature",
  "properties": {
    "iso:country":"GB",
    "sg:address":"18 Waterside Court",
    "sg:city":"Fleet",
    "sg:classifiers":[
        {
            "category":"Professional",
            "subcategory":"Lawyer & Legal Services",
            "type":"Services"
        }
    ],
    "sg:postcode":"GU51 2RH",
    "sg:province":"Hampshire",
    "wof:name":"The Will Writing Shop Ltd",
    "wof:placetype":"venue"
},
  "geometry": {"coordinates":[-0.830196,51.291615],"type":"Point"}
}