{
  "type": "Feature",
  "properties": {
    "addr:full":"66 Wolson Street London Greater London EC2A 2JX",
    "addr:housenumber":"66",
    "addr:postcode":"ec2a 2jx",
    "addr:street":"Wolson Street",
    "iso:country":"GB",
    "sg:address":"66 Wolson Street",
    "sg:city":"London",
    "sg:classifiers":[
        {
            "category":"Professional",
            "subcategory":"Research",
            "type":"Services"
        }
    ],
    "sg:postcode":"EC2A 2JX",
    "sg:province":"Greater London",
    "sg:tags":[
        "market"
    ],
    "wof:name":"Customer Satisfaction Surveys Ltd.",
    "wof:placetype":"venue"
},
  "geometry": {"coordinates":[-0.084606,51.521626],"type":"Point"}
}