{
  "type": "Feature",
  "properties": {
    "addr:full":"102 Gore Rd Hackney Greater London E9 7HW",
    "addr:housenumber":"102",
    "addr:postcode":"e9 7hw",
    "addr:street":"Gore Rd",
    "iso:country":"GB",
    "sg:address":"102 Gore Rd",
    "sg:city":"Hackney",
    "sg:classifiers":[
        {
            "category":"Building & Trades",
            "subcategory":"Construction",
            "type":"Services"
        }
    ],
    "sg:phone":"+44 20 8533 0557",
    "sg:postcode":"E9 7HW",
    "sg:province":"Greater London",
    "sg:tags":[
        "builder"
    ],
    "wof:name":"R & M Gale",
    "wof:placetype":"venue"
},
  "geometry": {"coordinates":[-0.0444369987,51.5363273621],"type":"Point"}
}