{
  "type": "Feature",
  "properties": {
    "iso:country":"GB",
    "sg:address":"3-4 Bath St",
    "sg:city":"Cheltenham",
    "sg:classifiers":[
        {
            "category":"Professional",
            "subcategory":"Employment Agencies",
            "type":"Services"
        }
    ],
    "sg:phone":"+44 1242 581555",
    "sg:postcode":"GL50 1YE",
    "sg:province":"Gloucestershire",
    "sg:tags":[
        "consultant"
    ],
    "wof:name":"Olympain Management & Training Services",
    "wof:placetype":"venue"
},
  "geometry": {"coordinates":[-2.072871,51.898636],"type":"Point"}
}