{
  "type": "Feature",
  "properties": {
    "iso:country":"GB",
    "sg:address":"Rampside Road",
    "sg:city":"Barrow-in-furness",
    "sg:classifiers":[
        {
            "category":"Retail",
            "subcategory":"Auto Repair",
            "type":"Services"
        }
    ],
    "sg:phone":"+44 1229 823213",
    "sg:postcode":"LA13 0HN",
    "sg:province":"Cumbria",
    "sg:tags":[
        "modification",
        "garage",
        "related"
    ],
    "wof:name":"Roosecote Service Station",
    "wof:placetype":"venue"
},
  "geometry": {"coordinates":[-3.1841490269,54.1091651917],"type":"Point"}
}