{
  "type": "Feature",
  "properties": {
    "addr:full":"105 Headstone Road Harrow Greater London HA1 1PG",
    "addr:housenumber":"105",
    "addr:postcode":"ha1 1pg",
    "addr:street":"Headstone Road",
    "iso:country":"GB",
    "sg:address":"105 Headstone Road",
    "sg:city":"Harrow",
    "sg:classifiers":[
        {
            "category":"Shopping",
            "subcategory":"Pharmacy",
            "type":"Retail Goods"
        }
    ],
    "sg:phone":"+44 20 8427 2350",
    "sg:postcode":"HA1 1PG",
    "sg:province":"Greater London",
    "sg:tags":[
        "pharmacist",
        "dispensing",
        "chemist"
    ],
    "wof:name":"Webbers",
    "wof:placetype":"venue"
},
  "geometry": {"coordinates":[-0.341036,51.583771],"type":"Point"}
}