{
  "type": "Feature",
  "properties": {
    "iso:country":"GB",
    "sg:address":"142 Silver Road",
    "sg:city":"Norwich",
    "sg:classifiers":[
        {
            "category":"Food & Beverages",
            "subcategory":"Meat & Fish",
            "type":"Retail Goods"
        }
    ],
    "sg:phone":"+44 1603 423340",
    "sg:postcode":"NR3 4TG",
    "sg:province":"Norfolk",
    "sg:tags":[
        "chip"
    ],
    "wof:name":"Silver Fish Bar",
    "wof:placetype":"venue"
},
  "geometry": {"coordinates":[1.302553,52.641369],"type":"Point"}
}