{
  "type": "Feature",
  "properties": {
    "iso:country":"GB",
    "sg:address":"932 London Road",
    "sg:city":"Leigh-on-sea",
    "sg:classifiers":[
        {
            "category":"Retail",
            "subcategory":"Veterinary Services",
            "type":"Services"
        }
    ],
    "sg:postcode":"SS9 3NG",
    "sg:province":"Essex",
    "sg:tags":[
        "surgeon"
    ],
    "wof:name":"Downes & Partners",
    "wof:placetype":"venue"
},
  "geometry": {"coordinates":[0.662433,51.547447],"type":"Point"}
}