{
  "type": "Feature",
  "properties": {
    "addr:full":"42 Cleveden Road Glasgow Glasgow City G12 0JW",
    "addr:housenumber":"42",
    "addr:postcode":"g12 0jw",
    "addr:street":"Cleveden Road",
    "iso:country":"GB",
    "sg:address":"42 Cleveden Road",
    "sg:city":"Glasgow",
    "sg:classifiers":[
        {
            "category":"Education",
            "subcategory":"School",
            "type":"Public Place"
        }
    ],
    "sg:phone":"+44 141 334 6118",
    "sg:postcode":"G12 0JW",
    "sg:province":"Glasgow City",
    "sg:tags":[
        "local",
        "authority"
    ],
    "wof:name":"Cleveden Secondary School",
    "wof:placetype":"venue"
},
  "geometry": {"coordinates":[-4.3056960106,55.8877182007],"type":"Point"}
}