{
  "type": "Feature",
  "properties": {
    "iso:country":"GB",
    "sg:address":"156 Loxley Clo",
    "sg:city":"Redditch",
    "sg:classifiers":[
        {
            "category":"Shopping",
            "subcategory":"Computers & Home Electronics",
            "type":"Retail Goods"
        }
    ],
    "sg:postcode":"B98 9JJ",
    "sg:province":"Warwickshire",
    "sg:tags":[
        "aerial",
        "television",
        "radio"
    ],
    "wof:name":"Aerial Answers",
    "wof:placetype":"venue"
},
  "geometry": {"coordinates":[-1.900526,52.315536],"type":"Point"}
}