{
  "type": "Feature",
  "properties": {
    "addr:full":"2 Canterbury Avenue Slough Berkshire SL2 1EQ",
    "addr:housenumber":"2",
    "addr:postcode":"sl2 1eq",
    "addr:street":"Canterbury Avenue",
    "iso:country":"GB",
    "sg:address":"2 Canterbury Avenue",
    "sg:city":"Slough",
    "sg:classifiers":[
        {
            "category":"Home & Garden",
            "subcategory":"Kitchen Supply",
            "type":"Retail Goods"
        }
    ],
    "sg:phone":"+44 1753 523455",
    "sg:postcode":"SL2 1EQ",
    "sg:province":"Berkshire",
    "sg:tags":[
        "catering"
    ],
    "wof:name":"Global Enterprise",
    "wof:placetype":"venue"
},
  "geometry": {"coordinates":[-0.6100100279,51.5261077881],"type":"Point"}
}