{
  "type": "Feature",
  "properties": {
    "addr:full":"Yellow House, 49 Seabourne Road Bournemouth Dorset BH5 2HA",
    "addr:housenumber":"49",
    "addr:postcode":"bh5 2ha",
    "addr:street":"Yellow House;Seabourne Road",
    "iso:country":"GB",
    "sg:address":"Yellow House, 49 Seabourne Road",
    "sg:city":"Bournemouth",
    "sg:classifiers":[
        {
            "category":"Shopping",
            "subcategory":"Pharmacy",
            "type":"Retail Goods"
        }
    ],
    "sg:phone":"+44 1202 771248",
    "sg:postcode":"BH5 2HA",
    "sg:province":"Dorset",
    "sg:tags":[
        "medicine",
        "therapy"
    ],
    "wof:name":"The Centre",
    "wof:placetype":"venue"
},
  "geometry": {"coordinates":[-1.823595,50.729942],"type":"Point"}
}