{
  "type": "Feature",
  "properties": {
    "iso:country":"GB",
    "sg:address":"135 Market St",
    "sg:city":"St. Andrews",
    "sg:classifiers":[
        {
            "category":"Utilities",
            "subcategory":"Electric",
            "type":"Services"
        }
    ],
    "sg:phone":"+44 1334 472128",
    "sg:postcode":"KY16 9PF",
    "sg:province":"Fife",
    "sg:tags":[
        "electricity"
    ],
    "wof:name":"ScottishPower",
    "wof:placetype":"venue"
},
  "geometry": {"coordinates":[-2.798106,56.340603],"type":"Point"}
}