{
  "type": "Feature",
  "properties": {
    "addr:full":"Vauxhall Industrial Estate, Ruabon Wrexham Wrexham LL14 6HA",
    "addr:postcode":"ll14 6ha",
    "iso:country":"GB",
    "sg:address":"Vauxhall Industrial Estate, Ruabon",
    "sg:city":"Wrexham",
    "sg:classifiers":[
        {
            "category":"Freight",
            "type":"Transportation"
        }
    ],
    "sg:phone":"+44 1978 822769",
    "sg:postcode":"LL14 6HA",
    "sg:province":"Wrexham",
    "sg:tags":[
        "shipping"
    ],
    "wof:name":"P & O Nedlloyd Ltd.",
    "wof:placetype":"venue"
},
  "geometry": {"coordinates":[-3.0391139984,52.9874382019],"type":"Point"}
}