{
  "type": "Feature",
  "properties": {
    "iso:country":"GB",
    "sg:address":"3 Irthlingborough Road",
    "sg:city":"Wellingborough",
    "sg:classifiers":[
        {
            "category":"Shopping",
            "type":"Retail Goods"
        }
    ],
    "sg:phone":"+44 1933 681100",
    "sg:postcode":"NN9 5EH",
    "sg:province":"Northamptonshire",
    "sg:tags":[
        "merchant"
    ],
    "wof:name":"Findstock Ltd.",
    "wof:placetype":"venue"
},
  "geometry": {"coordinates":[-0.64841,52.339794],"type":"Point"}
}