{
  "type": "Feature",
  "properties": {
    "addr:full":"Gambia 4 Saint Saviours Lane Padstow Cornwall PL28 8BD",
    "addr:housenumber":"4",
    "addr:postcode":"pl28 8bd",
    "addr:street":"Gambia;Saint Saviours Lane",
    "iso:country":"GB",
    "sg:address":"Gambia 4 Saint Saviours Lane",
    "sg:city":"Padstow",
    "sg:classifiers":[
        {
            "category":"Professional",
            "subcategory":"Management & Consulting",
            "type":"Services"
        }
    ],
    "sg:postcode":"PL28 8BD",
    "sg:province":"Cornwall",
    "sg:tags":[
        "consultant",
        "business"
    ],
    "wof:name":"Drilserv (Oilfield Consultants) Ltd",
    "wof:placetype":"venue"
},
  "geometry": {"coordinates":[-4.941839,50.537365],"type":"Point"}
}