{
  "type": "Feature",
  "properties": {
    "iso:country":"GB",
    "sg:address":"Quaker Meeting House, Welders Lane, Jordans",
    "sg:city":"Beaconsfield",
    "sg:classifiers":[
        {
            "category":"Place Of Worship",
            "type":"Public Place"
        }
    ],
    "sg:phone":"+44 1494 874146",
    "sg:postcode":"HP9 2SN",
    "sg:province":"Buckinghamshire",
    "wof:name":"Religious Society of Friends",
    "wof:placetype":"venue"
},
  "geometry": {"coordinates":[-0.591975987,51.6096191406],"type":"Point"}
}