{
  "type": "Feature",
  "properties": {
    "addr:full":"Gateshead Road Borehamwood Hertfordshire WD6 4NJ",
    "addr:postcode":"wd6 4nj",
    "addr:street":"Gateshead Road",
    "iso:country":"GB",
    "sg:address":"Gateshead Road",
    "sg:city":"Borehamwood",
    "sg:classifiers":[
        {
            "category":"Education",
            "subcategory":"School",
            "type":"Public Place"
        }
    ],
    "sg:phone":"+44 20 8953 3953",
    "sg:postcode":"WD6 4NJ",
    "sg:province":"Hertfordshire",
    "sg:tags":[
        "local",
        "authority"
    ],
    "wof:name":"Hertfordshire County Council",
    "wof:placetype":"venue"
},
  "geometry": {"coordinates":[-0.281974,51.665524],"type":"Point"}
}