{
  "type": "Feature",
  "properties": {
    "iso:country":"GB",
    "sg:address":"280 Kirkdale",
    "sg:city":"London",
    "sg:classifiers":[
        {
            "category":"Retail",
            "subcategory":"Laundry & Dry Cleaning",
            "type":"Services"
        }
    ],
    "sg:phone":"+44 20 8659 7050",
    "sg:postcode":"SE26 4RS",
    "sg:province":"Greater London",
    "sg:tags":[
        "alteration"
    ],
    "wof:name":"L B Cleaners",
    "wof:placetype":"venue"
},
  "geometry": {"coordinates":[-0.056538,51.427879],"type":"Point"}
}