{
  "type": "Feature",
  "properties": {
    "addr:full":"Abbey Lane Barnsley South Yorkshire S71 5QD",
    "addr:postcode":"s71 5qd",
    "addr:street":"Abbey Lane;Yorkshire",
    "iso:country":"GB",
    "sg:address":"Abbey Lane",
    "sg:city":"Barnsley",
    "sg:classifiers":[
        {
            "category":"Farming",
            "subcategory":"Nursery",
            "type":"Manufacturing & Wholesale Goods"
        }
    ],
    "sg:phone":"+44 1226 203966",
    "sg:postcode":"S71 5QD",
    "sg:province":"South Yorkshire",
    "sg:tags":[
        "creche"
    ],
    "wof:name":"Burton Grange Nursery School",
    "wof:placetype":"venue"
},
  "geometry": {"coordinates":[-1.439234,53.554806],"type":"Point"}
}