{
  "type": "Feature",
  "properties": {
    "iso:country":"GB",
    "sg:address":"54 Florence Road",
    "sg:city":"London",
    "sg:classifiers":[
        {
            "category":"Education",
            "subcategory":"School",
            "type":"Public Place"
        }
    ],
    "sg:postcode":"SW19 8TJ",
    "sg:province":"Greater London",
    "sg:tags":[
        "local",
        "authority"
    ],
    "wof:name":"Covebay Training Ltd",
    "wof:placetype":"venue"
},
  "geometry": {"coordinates":[-0.194634,51.421005],"type":"Point"}
}