{
  "type": "Feature",
  "properties": {
    "addr:full":"Station Rd, Kirkham Preston Lancashire PR4 2HD",
    "addr:postcode":"pr4 2hd",
    "addr:street":"Station Rd",
    "iso:country":"GB",
    "sg:address":"Station Rd, Kirkham",
    "sg:city":"Preston",
    "sg:classifiers":[
        {
            "category":"Bars & Pubs",
            "type":"Food & Drink"
        }
    ],
    "sg:phone":"+44 1772 490310",
    "sg:postcode":"PR4 2HD",
    "sg:province":"Lancashire",
    "sg:tags":[
        "pubs",
        "inn"
    ],
    "wof:name":"Derby Arms",
    "wof:placetype":"venue"
},
  "geometry": {"coordinates":[-2.8839550018,53.7866744995],"type":"Point"}
}