{
  "type": "Feature",
  "properties": {
    "addr:full":"Blwyd Street Ruthin Denbighshire LL15 1HF",
    "addr:postcode":"ll15 1hf",
    "addr:street":"Blwyd Street",
    "iso:country":"GB",
    "sg:address":"Blwyd Street",
    "sg:city":"Ruthin",
    "sg:classifiers":[
        {
            "category":"Manufacturing",
            "subcategory":"Apparel",
            "type":"Manufacturing & Wholesale Goods"
        }
    ],
    "sg:postcode":"LL15 1HF",
    "sg:province":"Denbighshire",
    "sg:tags":[
        "garment",
        "designer"
    ],
    "wof:name":"Enid Tudor",
    "wof:placetype":"venue"
},
  "geometry": {"coordinates":[-3.3045220375,53.1140174866],"type":"Point"}
}