{
  "type": "Feature",
  "properties": {
    "addr:full":"17 Tan Y Berllan Conwy Conwy LL31 9RD",
    "addr:housenumber":"17",
    "addr:postcode":"ll31 9rd",
    "addr:street":"Tan Y Berllan",
    "iso:country":"GB",
    "sg:address":"17 Tan Y Berllan",
    "sg:city":"Conwy",
    "sg:classifiers":[
        {
            "category":"Professional",
            "subcategory":"Management & Consulting",
            "type":"Services"
        }
    ],
    "sg:postcode":"LL31 9RD",
    "sg:province":"Conwy",
    "sg:tags":[
        "marketing",
        "consultant"
    ],
    "wof:name":"Axon Marketing",
    "wof:placetype":"venue"
},
  "geometry": {"coordinates":[-3.8143520355,53.2923660278],"type":"Point"}
}