{
  "type": "Feature",
  "properties": {
    "iso:country":"GB",
    "sg:address":"17 Tan Y Berllan",
    "sg:city":"Conwy",
    "sg:classifiers":[
        {
            "category":"Professional",
            "subcategory":"Management & Consulting",
            "type":"Services"
        }
    ],
    "sg:postcode":"LL31 9RD",
    "sg:province":"Conwy",
    "sg:tags":[
        "marketing",
        "consultant"
    ],
    "wof:name":"Axon Marketing",
    "wof:placetype":"venue"
},
  "geometry": {"coordinates":[-3.8143520355,53.2923660278],"type":"Point"}
}