{
  "type": "Feature",
  "properties": {
    "iso:country":"GB",
    "sg:address":"Citadel East, Killingworth",
    "sg:city":"Newcastle-upon-tyne",
    "sg:classifiers":[
        {
            "category":"Education",
            "subcategory":"Library",
            "type":"Public Place"
        },
        {
            "category":"Community Center",
            "type":"Public Place"
        }
    ],
    "sg:phone":"+44 191 268 1350",
    "sg:postcode":"NE12 6UQ",
    "sg:province":"Tyne and Wear",
    "sg:tags":[
        "recreation",
        "book",
        "leisure",
        "centre"
    ],
    "wof:name":"Killingworth Social Club",
    "wof:placetype":"venue"
},
  "geometry": {"coordinates":[-1.569304,55.036621],"type":"Point"}
}