{
  "type": "Feature",
  "properties": {
    "iso:country":"GB",
    "sg:address":"1 Whitegate Drive",
    "sg:city":"Blackpool",
    "sg:classifiers":[
        {
            "category":"Place Of Worship",
            "type":"Public Place"
        },
        {
            "category":"Organizations",
            "subcategory":"Religious Organization",
            "type":"Services"
        }
    ],
    "sg:phone":"+44 1253 392667",
    "sg:postcode":"FY3 9AE",
    "sg:province":"Lancashire",
    "sg:tags":[
        "organisation"
    ],
    "wof:name":"Christian Science Reading Room",
    "wof:placetype":"venue"
},
  "geometry": {"coordinates":[-3.03795,53.817902],"type":"Point"}
}