{
  "type": "Feature",
  "properties": {
    "iso:country":"GB",
    "sg:address":"Unit 22 Blyth Valley Venture Workshops, Plessey Rd",
    "sg:city":"Blyth",
    "sg:classifiers":[
        {
            "category":"Education",
            "subcategory":"Special Training",
            "type":"Public Place"
        }
    ],
    "sg:phone":"+44 1670 540165",
    "sg:postcode":"NE24 4BN",
    "sg:province":"Northumberland",
    "sg:tags":[
        "product",
        "centre"
    ],
    "wof:name":"K D Construction Service",
    "wof:placetype":"venue"
},
  "geometry": {"coordinates":[-1.515669,55.123665],"type":"Point"}
}