{
  "type": "Feature",
  "properties": {
    "iso:country":"GB",
    "sg:address":"St Leonard St",
    "sg:city":"Lanark",
    "sg:classifiers":[
        {
            "category":"Government",
            "subcategory":"City Hall",
            "type":"Public Place"
        }
    ],
    "sg:phone":"+44 1555 665383",
    "sg:postcode":"ML11 7DU",
    "sg:province":"South Lanarkshire",
    "wof:name":"Lanark Memorial Hall",
    "wof:placetype":"venue"
},
  "geometry": {"coordinates":[-3.7620639801,55.678653717],"type":"Point"}
}