{
  "type": "Feature",
  "properties": {
    "addr:full":"Glascote Road Tamworth Staffordshire B77 2AX",
    "addr:postcode":"b77 2ax",
    "addr:street":"Glascote Road",
    "iso:country":"GB",
    "sg:address":"Glascote Road",
    "sg:city":"Tamworth",
    "sg:classifiers":[
        {
            "category":"Fast Food",
            "type":"Food & Drink"
        }
    ],
    "sg:phone":"+44 1827 55086",
    "sg:postcode":"B77 2AX",
    "sg:province":"Staffordshire",
    "sg:tags":[
        "away",
        "take"
    ],
    "wof:name":"The Jolly Fryer",
    "wof:placetype":"venue"
},
  "geometry": {"coordinates":[-1.661954,52.624771],"type":"Point"}
}