{
  "type": "Feature",
  "properties": {
    "iso:country":"GB",
    "sg:address":"2 The Fishery, Peckhams Copse La",
    "sg:city":"Chichester",
    "sg:classifiers":[
        {
            "category":"Recreation",
            "subcategory":"Fishing",
            "type":"Entertainment"
        }
    ],
    "sg:phone":"+44 1243 533738",
    "sg:postcode":"PO20 6LB",
    "sg:province":"West Sussex",
    "sg:tags":[
        "angling"
    ],
    "wof:name":"Prime Angling",
    "wof:placetype":"venue"
},
  "geometry": {"coordinates":[-0.77543,50.836159],"type":"Point"}
}