{
  "type": "Feature",
  "properties": {
    "addr:full":"Cairo Cottage, Chapel Lane, Pimperne Blandford Forum Dorset DT11 8TZ",
    "addr:postcode":"dt11 8tz",
    "addr:street":"Chapel Lane",
    "iso:country":"GB",
    "sg:address":"Cairo Cottage, Chapel Lane, Pimperne",
    "sg:city":"Blandford Forum",
    "sg:classifiers":[
        {
            "category":"Home & Garden",
            "subcategory":"Home Furnishings",
            "type":"Retail Goods"
        },
        {
            "category":"Building & Trades",
            "subcategory":"Construction",
            "type":"Services"
        },
        {
            "category":"Home & Garden",
            "subcategory":"Carpets & Floor Coverings",
            "type":"Retail Goods"
        }
    ],
    "sg:phone":"+44 1258 453860",
    "sg:postcode":"DT11 8TZ",
    "sg:province":"Dorset",
    "sg:tags":[
        "rug",
        "contractor",
        "fitting",
        "tiling",
        "matting",
        "carpets"
    ],
    "wof:name":"Keith B Churchill",
    "wof:placetype":"venue"
},
  "geometry": {"coordinates":[-2.1345388889,50.8820304871],"type":"Point"}
}