{
  "type": "Feature",
  "properties": {
    "addr:full":"Gamblyn Farm, Skilgate Taunton Devon TA4 2DF",
    "addr:postcode":"ta4 2df",
    "addr:street":"Skilgate;Devon",
    "iso:country":"GB",
    "sg:address":"Gamblyn Farm, Skilgate",
    "sg:city":"Taunton",
    "sg:classifiers":[
        {
            "category":"Farming",
            "subcategory":"Farm",
            "type":"Manufacturing & Wholesale Goods"
        }
    ],
    "sg:phone":"+44 1398 331524",
    "sg:postcode":"TA4 2DF",
    "sg:province":"Devon",
    "sg:tags":[
        "mixed",
        "crop"
    ],
    "wof:name":"R J Ware",
    "wof:placetype":"venue"
},
  "geometry": {"coordinates":[-3.443776,51.035889],"type":"Point"}
}