{
  "type": "Feature",
  "properties": {
    "addr:full":"80 Colston Street Bristol City of Bristol BS1 5BB",
    "addr:housenumber":"80",
    "addr:postcode":"bs1 5bb",
    "addr:street":"Colston Street",
    "iso:country":"GB",
    "sg:address":"80 Colston Street",
    "sg:city":"Bristol",
    "sg:classifiers":[
        {
            "category":"Shopping",
            "subcategory":"Music",
            "type":"Retail Goods"
        }
    ],
    "sg:postcode":"BS1 5BB",
    "sg:province":"City of Bristol",
    "sg:tags":[
        "record",
        "tape",
        "cd"
    ],
    "wof:name":"Bang Bang",
    "wof:placetype":"venue"
},
  "geometry": {"coordinates":[-2.5972828865,51.4566497803],"type":"Point"}
}