{
  "type": "Feature",
  "properties": {
    "iso:country":"GB",
    "sg:address":"Dulce Domen, Oak Hill Road, Stapleford Abbotts",
    "sg:city":"Romford",
    "sg:classifiers":[
        {
            "category":"Transit Center",
            "subcategory":"Passenger",
            "type":"Transportation"
        }
    ],
    "sg:phone":"+44 1708 721913",
    "sg:postcode":"RM4 1JJ",
    "sg:province":"Essex",
    "sg:tags":[
        "boarding",
        "kennel",
        "catteries"
    ],
    "wof:name":"Stapleford Cattery",
    "wof:placetype":"venue"
},
  "geometry": {"coordinates":[0.16912,51.63644],"type":"Point"}
}