{
  "type": "Feature",
  "properties": {
    "addr:full":"The Green, Cavendish Sudbury Essex CO10 8BB",
    "addr:postcode":"co10 8bb",
    "addr:street":"Green",
    "iso:country":"GB",
    "sg:address":"The Green, Cavendish",
    "sg:city":"Sudbury",
    "sg:classifiers":[
        {
            "category":"Shopping",
            "subcategory":"Florist",
            "type":"Retail Goods"
        }
    ],
    "sg:postcode":"CO10 8BB",
    "sg:province":"Essex",
    "wof:name":"Cavendish Flowers",
    "wof:placetype":"venue"
},
  "geometry": {"coordinates":[0.5487750173,52.0502967834],"type":"Point"}
}