{
  "type": "Feature",
  "properties": {
    "addr:full":"82 Main Road, Moulton Northwich Cheshire CW9 8PB",
    "addr:housenumber":"82",
    "addr:postcode":"cw9 8pb",
    "addr:street":"Main Road",
    "iso:country":"GB",
    "sg:address":"82 Main Road, Moulton",
    "sg:city":"Northwich",
    "sg:classifiers":[
        {
            "category":"Food & Beverages",
            "subcategory":"Meat & Fish",
            "type":"Retail Goods"
        }
    ],
    "sg:phone":"+44 1606 862447",
    "sg:postcode":"CW9 8PB",
    "sg:province":"Cheshire",
    "sg:tags":[
        "chip"
    ],
    "wof:name":"The Moulton Chippy",
    "wof:placetype":"venue"
},
  "geometry": {"coordinates":[-2.517719,53.223183],"type":"Point"}
}