{
  "type": "Feature",
  "properties": {
    "addr:full":"351 Bradford Road Batley West Yorkshire WF17 5PQ",
    "addr:housenumber":"351",
    "addr:postcode":"wf17 5pq",
    "addr:street":"Bradford Road",
    "iso:country":"GB",
    "sg:address":"351 Bradford Road",
    "sg:city":"Batley",
    "sg:classifiers":[
        {
            "category":"Home & Garden",
            "subcategory":"Carpets & Floor Coverings",
            "type":"Retail Goods"
        }
    ],
    "sg:phone":"+44 1924 420404",
    "sg:postcode":"WF17 5PQ",
    "sg:province":"West Yorkshire",
    "sg:tags":[
        "carpets",
        "rug",
        "matting"
    ],
    "wof:name":"Mike's Carpets Ltd.",
    "wof:placetype":"venue"
},
  "geometry": {"coordinates":[-1.627111,53.709343],"type":"Point"}
}