{
  "type": "Feature",
  "properties": {
    "addr:full":"Ferry Terminal Weymouth Dorset DT4 8AP",
    "addr:postcode":"dt4 8ap",
    "iso:country":"GB",
    "sg:address":"Ferry Terminal",
    "sg:city":"Weymouth",
    "sg:classifiers":[
        {
            "category":"Freight",
            "type":"Transportation"
        }
    ],
    "sg:phone":"+44 1305 768155",
    "sg:postcode":"DT4 8AP",
    "sg:province":"Dorset",
    "sg:tags":[
        "forwarders"
    ],
    "wof:name":"Channel Seaways",
    "wof:placetype":"venue"
},
  "geometry": {"coordinates":[-2.459206,50.609901],"type":"Point"}
}