{
  "type": "Feature",
  "properties": {
    "iso:country":"GB",
    "sg:address":"70 Woodbrooke Way, Corringham",
    "sg:city":"Stanford-le-hope",
    "sg:classifiers":[
        {
            "category":"Education",
            "subcategory":"Music School",
            "type":"Public Place"
        }
    ],
    "sg:phone":"+44 1375 671171",
    "sg:postcode":"SS17 9DW",
    "sg:province":"Essex",
    "sg:tags":[
        "conservatory"
    ],
    "wof:name":"Clarendon Developments",
    "wof:placetype":"venue"
},
  "geometry": {"coordinates":[0.461497,51.530548],"type":"Point"}
}