{
  "type": "Feature",
  "properties": {
    "iso:country":"GB",
    "sg:address":"Unit 7 Shopping Precinct, Scholes",
    "sg:city":"Wigan",
    "sg:classifiers":[
        {
            "category":"Personal",
            "subcategory":"Beauty Salon",
            "type":"Services"
        }
    ],
    "sg:postcode":"WN1 3SD",
    "sg:province":"Lancashire",
    "sg:tags":[
        "unisex",
        "hairdresser"
    ],
    "wof:name":"Profile the Studio",
    "wof:placetype":"venue"
},
  "geometry": {"coordinates":[-2.633532,53.544155],"type":"Point"}
}