{
  "type": "Feature",
  "properties": {
    "iso:country":"GB",
    "sg:address":"Unit 6, Blue Lias Industrial Estate, Rugby Road",
    "sg:city":"Southam",
    "sg:classifiers":[
        {
            "category":"Wholesale",
            "subcategory":"Machinery & Supplies",
            "type":"Manufacturing & Wholesale Goods"
        }
    ],
    "sg:phone":"+44 1926 815676",
    "sg:postcode":"CV47 8HN",
    "sg:province":"Warwickshire",
    "sg:tags":[
        "industrial",
        "commercial"
    ],
    "wof:name":"Industrial Timber Technology Ltd.",
    "wof:placetype":"venue"
},
  "geometry": {"coordinates":[-1.332578,52.252148],"type":"Point"}
}