{
  "type": "Feature",
  "properties": {
    "addr:full":"48 Queen Street Deal Kent CT14 6HD",
    "addr:housenumber":"48",
    "addr:postcode":"ct14 6hd",
    "addr:street":"Queen Street Deal",
    "iso:country":"GB",
    "sg:address":"48 Queen Street",
    "sg:city":"Deal",
    "sg:classifiers":[
        {
            "category":"Home & Garden",
            "subcategory":"Garden Supply",
            "type":"Retail Goods"
        },
        {
            "category":"Cafe",
            "type":"Food & Drink"
        }
    ],
    "sg:phone":"+44 1304 373069",
    "sg:postcode":"CT14 6HD",
    "sg:province":"Kent",
    "sg:tags":[
        "tea",
        "room",
        "centre"
    ],
    "wof:name":"Deal Garden Centre",
    "wof:placetype":"venue"
},
  "geometry": {"coordinates":[1.399821043,51.2228431702],"type":"Point"}
}