{
  "type": "Feature",
  "properties": {
    "addr:full":"St. Georges La Lincoln Lincolnshire LN2 2LQ",
    "addr:postcode":"ln2 2lq",
    "iso:country":"GB",
    "sg:address":"St. Georges La",
    "sg:city":"Lincoln",
    "sg:classifiers":[
        {
            "category":"Travel",
            "subcategory":"Hotels & Motels",
            "type":"Entertainment"
        }
    ],
    "sg:phone":"+44 1522 527997",
    "sg:postcode":"LN2 2LQ",
    "sg:province":"Lincolnshire",
    "sg:tags":[
        "house",
        "guest"
    ],
    "wof:name":"Groveside",
    "wof:placetype":"venue"
},
  "geometry": {"coordinates":[-0.5348929763,53.2563095093],"type":"Point"}
}