{
  "type": "Feature",
  "properties": {
    "addr:full":"Main Road Rugeley Staffordshire WS15 1DY",
    "addr:postcode":"ws15 1dy",
    "addr:street":"Main Road",
    "iso:country":"GB",
    "sg:address":"Main Road",
    "sg:city":"Rugeley",
    "sg:classifiers":[
        {
            "category":"Travel",
            "subcategory":"Hotels & Motels",
            "type":"Entertainment"
        }
    ],
    "sg:phone":"+44 1889 584241",
    "sg:postcode":"WS15 1DY",
    "sg:province":"Staffordshire",
    "wof:name":"Cedar Tree Hotel & Restaurant",
    "wof:placetype":"venue"
},
  "geometry": {"coordinates":[-1.932999,52.75528],"type":"Point"}
}