{
  "type": "Feature",
  "properties": {
    "iso:country":"GB",
    "sg:address":"408-410 Archway Road, Corner Of Shepherds Hill, Highgate",
    "sg:city":"London",
    "sg:classifiers":[
        {
            "category":"Shopping",
            "subcategory":"Antiques",
            "type":"Retail Goods"
        }
    ],
    "sg:phone":"+44 20 8340 4987",
    "sg:postcode":"N6 5AT",
    "sg:province":"Greater London",
    "wof:name":"Betty Gould Antiques",
    "wof:placetype":"venue"
},
  "geometry": {"coordinates":[-0.14663,51.57761],"type":"Point"}
}