{
  "type": "Feature",
  "properties": {
    "iso:country":"GB",
    "sg:address":"40 Bickford Road, Witton",
    "sg:city":"Birmingham",
    "sg:classifiers":[
        {
            "category":"Professional",
            "subcategory":"Engineering",
            "type":"Services"
        }
    ],
    "sg:postcode":"B6 7EE",
    "sg:province":"West Midlands",
    "sg:tags":[
        "precision",
        "engineer"
    ],
    "wof:name":"Phillips Hybird",
    "wof:placetype":"venue"
},
  "geometry": {"coordinates":[-1.8758980036,52.5109100342],"type":"Point"}
}