{
  "type": "Feature",
  "properties": {
    "addr:full":"High Street, Carcroft Doncaster North Yorkshire DN6 8DN",
    "addr:postcode":"dn6 8dn",
    "addr:street":"High Street",
    "iso:country":"GB",
    "sg:address":"High Street, Carcroft",
    "sg:city":"Doncaster",
    "sg:classifiers":[
        {
            "category":"Food & Beverages",
            "subcategory":"Supermarket",
            "type":"Retail Goods"
        }
    ],
    "sg:phone":"+44 1302 721771",
    "sg:postcode":"DN6 8DN",
    "sg:province":"North Yorkshire",
    "sg:website":"http://www.asda.co.uk",
    "wof:name":"Asda Stores Ltd",
    "wof:placetype":"venue"
},
  "geometry": {"coordinates":[-1.1802090406,53.5832290649],"type":"Point"}
}