{
  "type": "Feature",
  "properties": {
    "addr:full":"Leicester House, Penrallt Street Machynlleth Ceredigion SY20 8AT",
    "addr:postcode":"sy20 8at",
    "addr:street":"Penrallt Street",
    "iso:country":"GB",
    "sg:address":"Leicester House, Penrallt Street",
    "sg:city":"Machynlleth",
    "sg:classifiers":[
        {
            "category":"Shopping",
            "subcategory":"Used Merchandise",
            "type":"Retail Goods"
        }
    ],
    "sg:phone":"+44 1654 702738",
    "sg:postcode":"SY20 8AT",
    "sg:province":"Ceredigion",
    "sg:tags":[
        "shop",
        "second-hand"
    ],
    "wof:name":"Susie's Allsorts",
    "wof:placetype":"venue"
},
  "geometry": {"coordinates":[-3.846723,52.590961],"type":"Point"}
}