{
  "type": "Feature",
  "properties": {
    "addr:full":"5 Shore Street, Rosehearty Fraserburgh Aberdeenshire AB43 4JQ",
    "addr:housenumber":"5",
    "addr:postcode":"ab43 4jq",
    "addr:street":"Shore Street",
    "iso:country":"GB",
    "sg:address":"5 Shore Street, Rosehearty",
    "sg:city":"Fraserburgh",
    "sg:classifiers":[
        {
            "category":"Retail",
            "subcategory":"Auto Repair",
            "type":"Services"
        }
    ],
    "sg:postcode":"AB43 4JQ",
    "sg:province":"Aberdeenshire",
    "sg:tags":[
        "body",
        "garage",
        "modification",
        "car"
    ],
    "wof:name":"Auto Spray",
    "wof:placetype":"venue"
},
  "geometry": {"coordinates":[-2.0158441067,57.6944198608],"type":"Point"}
}