{
  "type": "Feature",
  "properties": {
    "iso:country":"GB",
    "sg:address":"44 Alexandra Road",
    "sg:city":"Lowestoft",
    "sg:classifiers":[
        {
            "category":"Building & Trades",
            "subcategory":"Construction",
            "type":"Services"
        }
    ],
    "sg:phone":"+44 1502 574177",
    "sg:postcode":"NR32 1PJ",
    "sg:province":"Suffolk",
    "sg:tags":[
        "builder"
    ],
    "wof:name":"M G Riddell Ltd.",
    "wof:placetype":"venue"
},
  "geometry": {"coordinates":[1.752422,52.478809],"type":"Point"}
}