{
  "type": "Feature",
  "properties": {
    "iso:country":"GB",
    "sg:address":"Carlton Road",
    "sg:city":"Redhill",
    "sg:classifiers":[
        {
            "category":"Social Services",
            "subcategory":"Adult Care",
            "type":"Services"
        },
        {
            "category":"Government",
            "subcategory":"Office",
            "type":"Public Place"
        }
    ],
    "sg:postcode":"RH1 2BS",
    "sg:province":"Surrey",
    "sg:tags":[
        "housing",
        "local",
        "sheltered"
    ],
    "wof:name":"Alton House Sheltered Housing",
    "wof:placetype":"venue"
},
  "geometry": {"coordinates":[-0.179764,51.248699],"type":"Point"}
}