{
  "type": "Feature",
  "properties": {
    "iso:country":"GB",
    "sg:address":"26 Black Horse Lane, Swavesey",
    "sg:city":"Cambridge",
    "sg:classifiers":[
        {
            "category":"Shopping",
            "subcategory":"Pets & Pet Supplies",
            "type":"Retail Goods"
        }
    ],
    "sg:phone":"+44 1954 231166",
    "sg:postcode":"CB4 5QR",
    "sg:province":"Cambridgeshire",
    "sg:tags":[
        "food"
    ],
    "wof:name":"Feed Specialties Ltd.",
    "wof:placetype":"venue"
},
  "geometry": {"coordinates":[-0.006307,52.301571],"type":"Point"}
}