{
  "type": "Feature",
  "properties": {
    "addr:full":"Unit 1, Argyle Way Stevenage Hertfordshire SG1 2AD",
    "addr:housenumber":"unit 1",
    "addr:postcode":"sg1 2ad",
    "addr:street":"Argyle Way",
    "iso:country":"GB",
    "sg:address":"Unit 1, Argyle Way",
    "sg:city":"Stevenage",
    "sg:classifiers":[
        {
            "category":"Building & Trades",
            "subcategory":"Equipment Rental",
            "type":"Services"
        }
    ],
    "sg:phone":"+44 1438 750850",
    "sg:postcode":"SG1 2AD",
    "sg:province":"Hertfordshire",
    "sg:tags":[
        "hire",
        "centre"
    ],
    "wof:name":"Hss Hire Shops",
    "wof:placetype":"venue"
},
  "geometry": {"coordinates":[-0.2101439983,51.902923584],"type":"Point"}
}