{
  "type": "Feature",
  "properties": {
    "addr:full":"68a North St Romford Essex RM1 1DA",
    "addr:housenumber":"68a",
    "addr:postcode":"rm1 1da",
    "addr:street":"North St",
    "iso:country":"GB",
    "sg:address":"68a North St",
    "sg:city":"Romford",
    "sg:classifiers":[
        {
            "category":"Building & Trades",
            "subcategory":"Construction",
            "type":"Services"
        }
    ],
    "sg:postcode":"RM1 1DA",
    "sg:province":"Essex",
    "sg:tags":[
        "builder"
    ],
    "wof:name":"Leadstone Construction Ltd",
    "wof:placetype":"venue"
},
  "geometry": {"coordinates":[0.1780849993,51.5805625916],"type":"Point"}
}