{
  "type": "Feature",
  "properties": {
    "addr:full":"Old Gunville Road, Tarrant Hinton Blandford Forum Dorset DT11 8JA",
    "addr:postcode":"dt11 8ja",
    "addr:street":"Old Gunville Road",
    "iso:country":"GB",
    "sg:address":"Old Gunville Road, Tarrant Hinton",
    "sg:city":"Blandford Forum",
    "sg:classifiers":[
        {
            "category":"Retail",
            "subcategory":"Auto Repair",
            "type":"Services"
        }
    ],
    "sg:phone":"+44 1258 830211",
    "sg:postcode":"DT11 8JA",
    "sg:province":"Dorset",
    "sg:tags":[
        "modification",
        "garage",
        "related"
    ],
    "wof:name":"Handfords Garage",
    "wof:placetype":"venue"
},
  "geometry": {"coordinates":[-2.0891339779,50.8979682922],"type":"Point"}
}