{
  "type": "Feature",
  "properties": {
    "iso:country":"GB",
    "sg:address":"55-59 King Street",
    "sg:city":"Stirling",
    "sg:classifiers":[
        {
            "category":"Shopping",
            "subcategory":"Department Store",
            "type":"Retail Goods"
        }
    ],
    "sg:phone":"+44 1786 465646",
    "sg:postcode":"FK8 1DR",
    "sg:province":"Stirling",
    "wof:name":"McAree Brothers Ltd.",
    "wof:placetype":"venue"
},
  "geometry": {"coordinates":[-3.938307,56.118214],"type":"Point"}
}