{
  "type": "Feature",
  "properties": {
    "addr:full":"6 Collwood Close Poole Dorset BH15 3HF",
    "addr:housenumber":"6",
    "addr:postcode":"bh15 3hf",
    "addr:street":"Collwood Close",
    "iso:country":"GB",
    "sg:address":"6 Collwood Close",
    "sg:city":"Poole",
    "sg:classifiers":[
        {
            "category":"Building & Trades",
            "subcategory":"Construction",
            "type":"Services"
        }
    ],
    "sg:phone":"+44 1202 675158",
    "sg:postcode":"BH15 3HF",
    "sg:province":"Dorset",
    "sg:tags":[
        "decorator",
        "painter"
    ],
    "wof:name":"G G Frampton",
    "wof:placetype":"venue"
},
  "geometry": {"coordinates":[-1.9810810089,50.7381210327],"type":"Point"}
}