{
  "type": "Feature",
  "properties": {
    "addr:full":"Shooters Hill London Greater London SE18 3RZ",
    "addr:postcode":"se18 3rz",
    "addr:street":"Hill",
    "iso:country":"GB",
    "sg:address":"Shooters Hill",
    "sg:city":"London",
    "sg:classifiers":[
        {
            "category":"Communications",
            "type":"Services"
        }
    ],
    "sg:phone":"+44 20 8856 1120",
    "sg:postcode":"SE18 3RZ",
    "sg:province":"Greater London",
    "sg:tags":[
        "broadcasting"
    ],
    "wof:name":"Meridian Radio",
    "wof:placetype":"venue"
},
  "geometry": {"coordinates":[0.0638500005,51.4681816101],"type":"Point"}
}