{
  "type": "Feature",
  "properties": {
    "addr:full":"40 Rosslyn Avenue Liverpool Lancashire L31 8AS",
    "addr:housenumber":"40",
    "addr:postcode":"l31 8as",
    "addr:street":"Rosslyn Avenue",
    "iso:country":"GB",
    "sg:address":"40 Rosslyn Avenue",
    "sg:city":"Liverpool",
    "sg:classifiers":[
        {
            "category":"Building & Trades",
            "subcategory":"Plumbing",
            "type":"Services"
        }
    ],
    "sg:postcode":"L31 8AS",
    "sg:province":"Lancashire",
    "sg:tags":[
        "central",
        "heating"
    ],
    "wof:name":"Boilercare",
    "wof:placetype":"venue"
},
  "geometry": {"coordinates":[-2.9517710209,53.5085334778],"type":"Point"}
}