{
  "type": "Feature",
  "properties": {
    "iso:country":"GB",
    "sg:address":"Studio 1 38 Murray Road",
    "sg:city":"Northwood",
    "sg:classifiers":[
        {
            "category":"Shopping",
            "subcategory":"Stationery & Office Supplies",
            "type":"Retail Goods"
        },
        {
            "category":"Professional",
            "subcategory":"Business Services",
            "type":"Services"
        }
    ],
    "sg:phone":"+44 1923 842111",
    "sg:postcode":"HA6 2YL",
    "sg:province":"Greater London",
    "sg:tags":[
        "interior",
        "planning",
        "design"
    ],
    "wof:name":"Dimensions Interiors Ltd.",
    "wof:placetype":"venue"
},
  "geometry": {"coordinates":[-0.4241859913,51.611541748],"type":"Point"}
}