{
  "type": "Feature",
  "properties": {
    "addr:full":"Whitehorse St Baldock Bedfordshire SG7 6PX",
    "addr:postcode":"sg7 6px",
    "addr:street":"Whitehorse St",
    "iso:country":"GB",
    "sg:address":"Whitehorse St",
    "sg:city":"Baldock",
    "sg:classifiers":[
        {
            "category":"Place Of Worship",
            "type":"Public Place"
        }
    ],
    "sg:phone":"+44 1462 895052",
    "sg:postcode":"SG7 6PX",
    "sg:province":"Bedfordshire",
    "wof:name":"Baldock Methodist Church",
    "wof:placetype":"venue"
},
  "geometry": {"coordinates":[-0.188411,51.989967],"type":"Point"}
}