{
  "type": "Feature",
  "properties": {
    "addr:full":"Gwerninog Farm, Llansoy Usk Monmouthshire NP15 1DT",
    "addr:postcode":"np15 1dt",
    "iso:country":"GB",
    "sg:address":"Gwerninog Farm, Llansoy",
    "sg:city":"Usk",
    "sg:classifiers":[
        {
            "category":"Farming",
            "subcategory":"Livestock Farm",
            "type":"Manufacturing & Wholesale Goods"
        },
        {
            "category":"Farming",
            "subcategory":"Farm",
            "type":"Manufacturing & Wholesale Goods"
        }
    ],
    "sg:phone":"+44 1291 650220",
    "sg:postcode":"NP15 1DT",
    "sg:province":"Monmouthshire",
    "sg:tags":[
        "mixed",
        "crop",
        "others"
    ],
    "wof:name":"R A & J B Parry",
    "wof:placetype":"venue"
},
  "geometry": {"coordinates":[-2.808859,51.719379],"type":"Point"}
}