{
  "type": "Feature",
  "properties": {
    "iso:country":"GB",
    "sg:address":"West Grn, Newton St Cyres",
    "sg:city":"Exeter",
    "sg:classifiers":[
        {
            "category":"Real Estate",
            "subcategory":"Architect",
            "type":"Services"
        }
    ],
    "sg:phone":"+44 1392 851295",
    "sg:postcode":"EX5 5AG",
    "sg:province":"Devon",
    "wof:name":"Donald Hanson",
    "wof:placetype":"venue"
},
  "geometry": {"coordinates":[-3.56028,50.765751],"type":"Point"}
}