{
  "type": "Feature",
  "properties": {
    "addr:full":"5 Victoria Road, Gorleston Great Yarmouth Norfolk NR31 6EP",
    "addr:housenumber":"5",
    "addr:postcode":"nr31 6ep",
    "addr:street":"Victoria Road",
    "iso:country":"GB",
    "sg:address":"5 Victoria Road, Gorleston",
    "sg:city":"Great Yarmouth",
    "sg:classifiers":[
        {
            "category":"Shopping",
            "subcategory":"Bicycles & Sporting Goods",
            "type":"Retail Goods"
        },
        {
            "category":"Sports & Exercise",
            "subcategory":"Stables",
            "type":"Entertainment"
        }
    ],
    "sg:phone":"+44 1493 601486",
    "sg:postcode":"NR31 6EP",
    "sg:province":"Norfolk",
    "sg:tags":[
        "equipment",
        "saddlery",
        "equestrian",
        "riding",
        "wear"
    ],
    "wof:name":"The Gorleston Tack Room",
    "wof:placetype":"venue"
},
  "geometry": {"coordinates":[1.7259149551,52.5704727173],"type":"Point"}
}