{
  "type": "Feature",
  "properties": {
    "addr:full":"Lowndes Road, Wollaston Stourbridge Staffordshire DY8 3ST",
    "addr:postcode":"dy8 3st",
    "addr:street":"Lowndes Road",
    "iso:country":"GB",
    "sg:address":"Lowndes Road, Wollaston",
    "sg:city":"Stourbridge",
    "sg:classifiers":[
        {
            "category":"Building & Trades",
            "subcategory":"Construction",
            "type":"Services"
        }
    ],
    "sg:phone":"+44 1384 376200",
    "sg:postcode":"DY8 3ST",
    "sg:province":"Staffordshire",
    "sg:tags":[
        "supplier",
        "installers",
        "cladding"
    ],
    "wof:name":"Laser Claddings Ltd.",
    "wof:placetype":"venue"
},
  "geometry": {"coordinates":[-2.1566870213,52.4598083496],"type":"Point"}
}