{
  "type": "Feature",
  "properties": {
    "iso:country":"GB",
    "sg:address":"14 High Street, Carcroft",
    "sg:city":"Doncaster",
    "sg:classifiers":[
        {
            "category":"Shopping",
            "subcategory":"Pharmacy",
            "type":"Retail Goods"
        }
    ],
    "sg:postcode":"DN6 8DP",
    "sg:province":"North Yorkshire",
    "sg:tags":[
        "pharmacist",
        "store",
        "drug",
        "chemist"
    ],
    "wof:name":"Vantage Chemist",
    "wof:placetype":"venue"
},
  "geometry": {"coordinates":[-1.1835939884,53.5825538635],"type":"Point"}
}