{
  "type": "Feature",
  "properties": {
    "addr:full":"3 Lower Brook Mews Ipswich Suffolk IP4 1RA",
    "addr:housenumber":"3",
    "addr:postcode":"ip4 1ra",
    "addr:street":"Lower Brook Mews",
    "iso:country":"GB",
    "sg:address":"3 Lower Brook Mews",
    "sg:city":"Ipswich",
    "sg:classifiers":[
        {
            "category":"Real Estate",
            "subcategory":"Architect",
            "type":"Services"
        }
    ],
    "sg:phone":"+44 1473 252961",
    "sg:postcode":"IP4 1RA",
    "sg:province":"Suffolk",
    "sg:tags":[
        "architectural"
    ],
    "wof:name":"Last & Tricker Partnership",
    "wof:placetype":"venue"
},
  "geometry": {"coordinates":[1.156198,52.055687],"type":"Point"}
}