{
  "type": "Feature",
  "properties": {
    "addr:full":"3 Five Acres, Farington Moss Preston Lancashire PR26 6PZ",
    "addr:housenumber":"3",
    "addr:postcode":"pr26 6pz",
    "addr:street":"Five Acres",
    "iso:country":"GB",
    "sg:address":"3 Five Acres, Farington Moss",
    "sg:city":"Preston",
    "sg:classifiers":[
        {
            "category":"Retail",
            "subcategory":"Driving School",
            "type":"Services"
        }
    ],
    "sg:phone":"+44 1772 433154",
    "sg:postcode":"PR26 6PZ",
    "sg:province":"Lancashire",
    "wof:name":"Able School of Motoring",
    "wof:placetype":"venue"
},
  "geometry": {"coordinates":[-2.710024,53.70845],"type":"Point"}
}