{
  "type": "Feature",
  "properties": {
    "iso:country":"GB",
    "sg:address":"760 Anniesland Road",
    "sg:city":"Glasgow",
    "sg:classifiers":[
        {
            "category":"Travel",
            "subcategory":"Travel Agent",
            "type":"Entertainment"
        }
    ],
    "sg:phone":"+44 141 954 9636",
    "sg:postcode":"G14 0YU",
    "sg:province":"Glasgow City",
    "wof:name":"A T Mays",
    "wof:placetype":"venue"
},
  "geometry": {"coordinates":[-4.359829,55.885777],"type":"Point"}
}