{
  "type": "Feature",
  "properties": {
    "addr:full":"130 Blackstock Road London Greater London N4 2DX",
    "addr:housenumber":"130",
    "addr:postcode":"n4 2dx",
    "addr:street":"Blackstock Road",
    "iso:country":"GB",
    "sg:address":"130 Blackstock Road",
    "sg:city":"London",
    "sg:classifiers":[
        {
            "category":"Restaurant",
            "type":"Food & Drink"
        }
    ],
    "sg:phone":"+44 20 7359 5388",
    "sg:postcode":"N4 2DX",
    "sg:province":"Greater London",
    "sg:tags":[
        "indian"
    ],
    "wof:name":"Ruman Balti & Tandoori Restaurant",
    "wof:placetype":"venue"
},
  "geometry": {"coordinates":[-0.0994760022,51.5613861084],"type":"Point"}
}