{
  "type": "Feature",
  "properties": {
    "iso:country":"GB",
    "sg:address":"194 Astley Street",
    "sg:city":"Dukinfield",
    "sg:classifiers":[
        {
            "category":"Shopping",
            "subcategory":"News",
            "type":"Retail Goods"
        }
    ],
    "sg:phone":"+44 161 330 8179",
    "sg:postcode":"SK16 4QD",
    "sg:province":"Greater Manchester",
    "sg:tags":[
        "newsagent"
    ],
    "wof:name":"Astley News",
    "wof:placetype":"venue"
},
  "geometry": {"coordinates":[-2.097949028,53.4783668518],"type":"Point"}
}