{
  "type": "Feature",
  "properties": {
    "addr:full":"56 Grove Vale London Greater London SE22 8DT",
    "addr:housenumber":"56",
    "addr:postcode":"se22 8dt",
    "addr:street":"Grove Vale",
    "iso:country":"GB",
    "sg:address":"56 Grove Vale",
    "sg:city":"London",
    "sg:classifiers":[
        {
            "category":"Shopping",
            "subcategory":"News",
            "type":"Retail Goods"
        }
    ],
    "sg:phone":"+44 20 8693 4534",
    "sg:postcode":"SE22 8DT",
    "sg:province":"Greater London",
    "sg:tags":[
        "newsagent"
    ],
    "wof:name":"K N V News",
    "wof:placetype":"venue"
},
  "geometry": {"coordinates":[-0.078188,51.461437],"type":"Point"}
}