{
  "type": "Feature",
  "properties": {
    "addr:full":"Unit 5, 1555 Tarring Rd Worthing West Sussex BN11 4HE",
    "addr:housenumber":"unit 5",
    "addr:postcode":"1555;bn11 4he",
    "addr:street":"Tarring Rd",
    "iso:country":"GB",
    "sg:address":"Unit 5, 1555 Tarring Rd",
    "sg:city":"Worthing",
    "sg:classifiers":[
        {
            "category":"Shopping",
            "subcategory":"Shoes",
            "type":"Retail Goods"
        }
    ],
    "sg:postcode":"BN11 4HE",
    "sg:province":"West Sussex",
    "sg:tags":[
        "shop"
    ],
    "wof:name":"Hope,Frederick,",
    "wof:placetype":"venue"
},
  "geometry": {"coordinates":[-0.391858995,50.8182792664],"type":"Point"}
}