{
  "type": "Feature",
  "properties": {
    "addr:full":"12 Newquay Drive, Bramhall Stockport Cheshire SK7 2HT",
    "addr:housenumber":"12",
    "addr:postcode":"sk7 2ht",
    "addr:street":"Newquay Drive",
    "iso:country":"GB",
    "sg:address":"12 Newquay Drive, Bramhall",
    "sg:city":"Stockport",
    "sg:classifiers":[
        {
            "category":"Building & Trades",
            "subcategory":"Plumbing",
            "type":"Services"
        }
    ],
    "sg:phone":"+44 161 439 4488",
    "sg:postcode":"SK7 2HT",
    "sg:province":"Cheshire",
    "sg:tags":[
        "central",
        "installation",
        "system",
        "servicing",
        "heating"
    ],
    "wof:name":"APS",
    "wof:placetype":"venue"
},
  "geometry": {"coordinates":[-2.1570920944,53.3637313843],"type":"Point"}
}