{
  "type": "Feature",
  "properties": {
    "addr:full":"Unit 3, Carlton Trading Estate Leeds West Yorkshire LS12 2QG",
    "addr:housenumber":"unit 3",
    "addr:postcode":"ls12 2qg",
    "addr:street":"Carlton Trading Estate",
    "iso:country":"GB",
    "sg:address":"Unit 3, Carlton Trading Estate",
    "sg:city":"Leeds",
    "sg:classifiers":[
        {
            "category":"Professional",
            "subcategory":"Management & Consulting",
            "type":"Services"
        }
    ],
    "sg:phone":"+44 113 279 1065",
    "sg:postcode":"LS12 2QG",
    "sg:province":"West Yorkshire",
    "sg:tags":[
        "consultant",
        "business"
    ],
    "wof:name":"Jagger Management Services Ltd.",
    "wof:placetype":"venue"
},
  "geometry": {"coordinates":[-1.5780860186,53.8009185791],"type":"Point"}
}