{
  "type": "Feature",
  "properties": {
    "addr:full":"2a Milton Street, Kirby In Ashfield Nottingham Nottinghamshire NG17 7JB",
    "addr:housenumber":"2a",
    "addr:postcode":"ng17 7jb",
    "addr:street":"Milton Street",
    "iso:country":"GB",
    "sg:address":"2a Milton Street, Kirby In Ashfield",
    "sg:city":"Nottingham",
    "sg:classifiers":[
        {
            "category":"Bus Charters",
            "type":"Transportation"
        }
    ],
    "sg:phone":"+44 1623 722227",
    "sg:postcode":"NG17 7JB",
    "sg:province":"Nottinghamshire",
    "sg:tags":[
        "mini",
        "hire",
        "leasing"
    ],
    "wof:name":"Bloo Line Coaches",
    "wof:placetype":"venue"
},
  "geometry": {"coordinates":[-1.2455179691,53.1027107239],"type":"Point"}
}