{
  "type": "Feature",
  "properties": {
    "addr:full":"4 Stansted Road Bishops Stortford Essex CM23 2DX",
    "addr:housenumber":"4",
    "addr:postcode":"cm23 2dx",
    "addr:street":"Stansted Road",
    "iso:country":"GB",
    "sg:address":"4 Stansted Road",
    "sg:city":"Bishops Stortford",
    "sg:classifiers":[
        {
            "category":"Fast Food",
            "type":"Food & Drink"
        }
    ],
    "sg:phone":"+44 1279 655385",
    "sg:postcode":"CM23 2DX",
    "sg:province":"Essex",
    "sg:tags":[
        "away",
        "take"
    ],
    "wof:name":"Raj Bubon",
    "wof:placetype":"venue"
},
  "geometry": {"coordinates":[0.1669750065,51.8698120117],"type":"Point"}
}