{
  "type": "Feature",
  "properties": {
    "addr:full":"20 Lord Street, Croft Warrington Cheshire WA3 7DD",
    "addr:housenumber":"20",
    "addr:postcode":"wa3 7dd",
    "addr:street":"Lord Street Croft",
    "iso:country":"GB",
    "sg:address":"20 Lord Street, Croft",
    "sg:city":"Warrington",
    "sg:classifiers":[
        {
            "category":"Shopping",
            "subcategory":"Department Store",
            "type":"Retail Goods"
        },
        {
            "category":"Food & Beverages",
            "subcategory":"Supermarket",
            "type":"Retail Goods"
        }
    ],
    "sg:postcode":"WA3 7DD",
    "sg:province":"Cheshire",
    "wof:name":"R V B Friar",
    "wof:placetype":"venue"
},
  "geometry": {"coordinates":[-2.5546290874,53.437953949],"type":"Point"}
}