{
  "type": "Feature",
  "properties": {
    "iso:country":"GB",
    "sg:address":"52 Esplanade Avenue",
    "sg:city":"Porthcawl",
    "sg:classifiers":[
        {
            "category":"Travel",
            "subcategory":"Hotels & Motels",
            "type":"Entertainment"
        }
    ],
    "sg:phone":"+44 1656 782428",
    "sg:postcode":"CF36 3YU",
    "sg:province":"Bridgend",
    "wof:name":"Minerva Hotel",
    "wof:placetype":"venue"
},
  "geometry": {"coordinates":[-3.706778,51.476566],"type":"Point"}
}