{
  "type": "Feature",
  "properties": {
    "addr:full":"27 Hill Street Wisbech Cambridgeshire PE13 1BA",
    "addr:housenumber":"27",
    "addr:postcode":"pe13 1ba",
    "addr:street":"Hill Street",
    "iso:country":"GB",
    "sg:address":"27 Hill Street",
    "sg:city":"Wisbech",
    "sg:classifiers":[
        {
            "category":"Personal",
            "subcategory":"Beauty Salon",
            "type":"Services"
        }
    ],
    "sg:phone":"+44 1945 584272",
    "sg:postcode":"PE13 1BA",
    "sg:province":"Cambridgeshire",
    "wof:name":"Top To Toe Beauty & Hair",
    "wof:placetype":"venue"
},
  "geometry": {"coordinates":[0.1604450047,52.6659622192],"type":"Point"}
}