{
  "type": "Feature",
  "properties": {
    "iso:country":"GB",
    "sg:address":"Po Box 10",
    "sg:city":"Middlesbrough",
    "sg:classifiers":[
        {
            "category":"Manufacturing",
            "subcategory":"Metals",
            "type":"Manufacturing & Wholesale Goods"
        }
    ],
    "sg:postcode":"TS2 1HH",
    "sg:province":"Durham",
    "sg:tags":[
        "steel",
        "fabricator",
        "erectors",
        "stockholder"
    ],
    "wof:name":"Parson & Crosland Ltd.",
    "wof:placetype":"venue"
},
  "geometry": {"coordinates":[-1.237379,54.584888],"type":"Point"}
}