{
  "type": "Feature",
  "properties": {
    "iso:country":"GB",
    "sg:address":"Unit 6",
    "sg:city":"Lewes",
    "sg:classifiers":[
        {
            "category":"Freight",
            "type":"Transportation"
        }
    ],
    "sg:phone":"+44 1273 814383",
    "sg:postcode":"BN8 5NN",
    "sg:province":"East Sussex",
    "sg:tags":[
        "haulage",
        "road"
    ],
    "wof:name":"Burnt Oak Haulage",
    "wof:placetype":"venue"
},
  "geometry": {"coordinates":[0.04661,50.904072],"type":"Point"}
}