{
  "type": "Feature",
  "properties": {
    "iso:country":"GB",
    "sg:address":"2 Delamere Road, Hazel Gro",
    "sg:city":"Stockport",
    "sg:classifiers":[
        {
            "category":"Retail",
            "subcategory":"Repair Shop",
            "type":"Services"
        }
    ],
    "sg:phone":"+44 161 285 1681",
    "sg:postcode":"SK7 4NW",
    "sg:province":"Cheshire",
    "sg:tags":[
        "maintenance"
    ],
    "wof:name":"G Smith Builders",
    "wof:placetype":"venue"
},
  "geometry": {"coordinates":[-2.1037199497,53.3818092346],"type":"Point"}
}