{
  "type": "Feature",
  "properties": {
    "iso:country":"GB",
    "sg:address":"27 High Street",
    "sg:city":"Leigh-on-sea",
    "sg:classifiers":[
        {
            "category":"Bars & Pubs",
            "type":"Food & Drink"
        }
    ],
    "sg:phone":"+44 1702 475666",
    "sg:postcode":"SS9 2EN",
    "sg:province":"Essex",
    "sg:tags":[
        "pubs",
        "inn"
    ],
    "wof:name":"Peter Boat Inn",
    "wof:placetype":"venue"
},
  "geometry": {"coordinates":[0.6488549709,51.5404014587],"type":"Point"}
}