{
  "type": "Feature",
  "properties": {
    "iso:country":"GB",
    "sg:address":"9 Henry Street",
    "sg:city":"Lytham St Annes",
    "sg:classifiers":[
        {
            "category":"Home & Garden",
            "subcategory":"Hardware",
            "type":"Retail Goods"
        }
    ],
    "sg:postcode":"FY8 5LE",
    "sg:province":"Lancashire",
    "sg:tags":[
        "retailer",
        "diy"
    ],
    "wof:name":"Worths",
    "wof:placetype":"venue"
},
  "geometry": {"coordinates":[-2.964035,53.736633],"type":"Point"}
}