{
  "type": "Feature",
  "properties": {
    "iso:country":"GB",
    "sg:address":"4 Heath Gardens, Netley Abbey",
    "sg:city":"Southampton",
    "sg:classifiers":[
        {
            "category":"Building & Trades",
            "subcategory":"Plumbing",
            "type":"Services"
        }
    ],
    "sg:postcode":"SO31 5FL",
    "sg:province":"Hampshire",
    "sg:tags":[
        "heating"
    ],
    "wof:name":"A S A P Plumbing",
    "wof:placetype":"venue"
},
  "geometry": {"coordinates":[-1.339743,50.880833],"type":"Point"}
}