{
  "type": "Feature",
  "properties": {
    "addr:full":"Four Oaks Road, Headcorn Ashford Kent TN27 9NY",
    "addr:postcode":"tn27 9ny",
    "addr:street":"Four Oaks Road",
    "iso:country":"GB",
    "sg:address":"Four Oaks Road, Headcorn",
    "sg:city":"Ashford",
    "sg:classifiers":[
        {
            "category":"Farming",
            "subcategory":"Livestock Farm",
            "type":"Manufacturing & Wholesale Goods"
        }
    ],
    "sg:postcode":"TN27 9NY",
    "sg:province":"Kent",
    "sg:tags":[
        "others"
    ],
    "wof:name":"Kelsham Farm",
    "wof:placetype":"venue"
},
  "geometry": {"coordinates":[0.63093,51.166901],"type":"Point"}
}