{
  "type": "Feature",
  "properties": {
    "addr:full":"9 Britannia Rd Ipswich Suffolk IP4 5LE",
    "addr:housenumber":"9",
    "addr:postcode":"ip4 5le",
    "addr:street":"Britannia Rd",
    "iso:country":"GB",
    "sg:address":"9 Britannia Rd",
    "sg:city":"Ipswich",
    "sg:classifiers":[
        {
            "category":"Autos & Motor Vehicles",
            "subcategory":"Automobile Sales",
            "type":"Retail Goods"
        }
    ],
    "sg:phone":"+44 1473 400631",
    "sg:postcode":"IP4 5LE",
    "sg:province":"Suffolk",
    "sg:tags":[
        "commercial"
    ],
    "wof:name":"Woodgate Motorsport Cars",
    "wof:placetype":"venue"
},
  "geometry": {"coordinates":[1.19055,52.059502],"type":"Point"}
}