{
  "type": "Feature",
  "properties": {
    "addr:full":"220a Blythe Road London Greater London W14 0HH",
    "addr:housenumber":"220a",
    "addr:postcode":"w14 0hh",
    "addr:street":"Blythe Road",
    "iso:country":"GB",
    "sg:address":"220a Blythe Road",
    "sg:city":"London",
    "sg:classifiers":[
        {
            "category":"Professional",
            "subcategory":"Management & Consulting",
            "type":"Services"
        },
        {
            "category":"Organizations",
            "subcategory":"Membership Organization",
            "type":"Services"
        }
    ],
    "sg:phone":"+44 20 8222 6628",
    "sg:postcode":"W14 0HH",
    "sg:province":"Greater London",
    "sg:tags":[
        "club",
        "consultant",
        "business"
    ],
    "wof:name":"Delancey Business Management Ltd.",
    "wof:placetype":"venue"
},
  "geometry": {"coordinates":[-0.220886,51.499615],"type":"Point"}
}