{
  "type": "Feature",
  "properties": {
    "addr:full":"88a Regent Quay, Waterloo Goods Yard Aberdeen Aberdeen City AB11 5AS",
    "addr:housenumber":"88a",
    "addr:postcode":"ab11 5as",
    "addr:street":"Regent Quay;Goods Yard",
    "iso:country":"GB",
    "sg:address":"88a Regent Quay, Waterloo Goods Yard",
    "sg:city":"Aberdeen",
    "sg:classifiers":[
        {
            "category":"Manufacturing",
            "subcategory":"Paper Products",
            "type":"Manufacturing & Wholesale Goods"
        }
    ],
    "sg:phone":"+44 1224 572768",
    "sg:postcode":"AB11 5AS",
    "sg:province":"Aberdeen City",
    "sg:tags":[
        "board"
    ],
    "wof:name":"Omya Croxton & Garry Ltd",
    "wof:placetype":"venue"
},
  "geometry": {"coordinates":[-2.0894498825,57.146686554],"type":"Point"}
}