{
  "type": "Feature",
  "properties": {
    "iso:country":"GB",
    "sg:address":"89 Leigh Road",
    "sg:city":"Eastleigh",
    "sg:classifiers":[
        {
            "category":"Professional",
            "subcategory":"Engineering",
            "type":"Services"
        }
    ],
    "sg:postcode":"SO50 9DQ",
    "sg:province":"Hampshire",
    "sg:tags":[
        "design",
        "engineer"
    ],
    "wof:name":"Engineering Innovations Ltd",
    "wof:placetype":"venue"
},
  "geometry": {"coordinates":[-1.357052,50.969639],"type":"Point"}
}