{
  "type": "Feature",
  "properties": {
    "addr:full":"170 Merton High Street London Greater London SW19 1AY",
    "addr:housenumber":"170",
    "addr:postcode":"sw19 1ay",
    "addr:street":"Merton High Street",
    "iso:country":"GB",
    "sg:address":"170 Merton High Street",
    "sg:city":"London",
    "sg:classifiers":[
        {
            "category":"Professional",
            "subcategory":"Computer Services",
            "type":"Services"
        }
    ],
    "sg:phone":"+44 20 8241 3000",
    "sg:postcode":"SW19 1AY",
    "sg:province":"Greater London",
    "sg:tags":[
        "system",
        "software"
    ],
    "wof:name":"Bolingbrooke Contracts (Uk) Ltd",
    "wof:placetype":"venue"
},
  "geometry": {"coordinates":[-0.18942,51.415859],"type":"Point"}
}