{
  "type": "Feature",
  "properties": {
    "iso:country":"GB",
    "sg:address":"15 Bursledon Road",
    "sg:city":"Waterlooville",
    "sg:classifiers":[
        {
            "category":"Building & Trades",
            "subcategory":"Construction",
            "type":"Services"
        }
    ],
    "sg:postcode":"PO7 5NJ",
    "sg:province":"Hampshire",
    "sg:tags":[
        "builder"
    ],
    "wof:name":"J V Minter",
    "wof:placetype":"venue"
},
  "geometry": {"coordinates":[-1.038277,50.869583],"type":"Point"}
}