{
  "type": "Feature",
  "properties": {
    "addr:full":"14 First Avenue Emsworth Hampshire PO10 8HN",
    "addr:housenumber":"14",
    "addr:postcode":"po10 8hn",
    "addr:street":"First Avenue",
    "iso:country":"GB",
    "sg:address":"14 First Avenue",
    "sg:city":"Emsworth",
    "sg:classifiers":[
        {
            "category":"Education",
            "subcategory":"Library",
            "type":"Public Place"
        }
    ],
    "sg:phone":"+44 1243 375924",
    "sg:postcode":"PO10 8HN",
    "sg:province":"Hampshire",
    "sg:tags":[
        "book"
    ],
    "wof:name":"Southbourne Library",
    "wof:placetype":"venue"
},
  "geometry": {"coordinates":[-0.909725,50.847755],"type":"Point"}
}