{
  "type": "Feature",
  "properties": {
    "iso:country":"GB",
    "sg:address":"47 Blackburn Road",
    "sg:city":"Herne Bay",
    "sg:classifiers":[
        {
            "category":"Building & Trades",
            "subcategory":"Plumbing",
            "type":"Services"
        }
    ],
    "sg:phone":"+44 1227 366685",
    "sg:postcode":"CT6 7RG",
    "sg:province":"Kent",
    "sg:tags":[
        "plumber",
        "heating"
    ],
    "wof:name":"R W Starkey & Son",
    "wof:placetype":"venue"
},
  "geometry": {"coordinates":[1.098826,51.360992],"type":"Point"}
}