{
  "type": "Feature",
  "properties": {
    "iso:country":"GB",
    "sg:address":"43 High Street, Clydach",
    "sg:city":"Swansea",
    "sg:classifiers":[
        {
            "category":"Government",
            "subcategory":"Post Office",
            "type":"Public Place"
        }
    ],
    "sg:phone":"+44 1792 843539",
    "sg:postcode":"SA6 5LH",
    "sg:province":"Swansea",
    "wof:name":"Clydach Post Office",
    "wof:placetype":"venue"
},
  "geometry": {"coordinates":[-3.895348,51.69519],"type":"Point"}
}