{
  "type": "Feature",
  "properties": {
    "iso:country":"GB",
    "sg:address":"120 Burton Road",
    "sg:city":"Derby",
    "sg:classifiers":[
        {
            "category":"Professional",
            "subcategory":"Management & Consulting",
            "type":"Services"
        }
    ],
    "sg:phone":"+44 1332 721396",
    "sg:postcode":"DE1 1TG",
    "sg:province":"Derbyshire",
    "sg:tags":[
        "marketing",
        "consultant"
    ],
    "wof:name":"Club Colours",
    "wof:placetype":"venue"
},
  "geometry": {"coordinates":[-1.480861,52.915749],"type":"Point"}
}