{
  "type": "Feature",
  "properties": {
    "iso:country":"GB",
    "sg:address":"19 Roach",
    "sg:city":"Grays",
    "sg:classifiers":[
        {
            "category":"Professional",
            "subcategory":"Detective & Security Services",
            "type":"Services"
        }
    ],
    "sg:phone":"+44 1375 851779",
    "sg:postcode":"RM18 8RZ",
    "sg:province":"Essex",
    "sg:tags":[
        "agency"
    ],
    "wof:name":"D & R Security Services",
    "wof:placetype":"venue"
},
  "geometry": {"coordinates":[0.3851700127,51.472038269],"type":"Point"}
}