{
  "type": "Feature",
  "properties": {
    "iso:country":"GB",
    "sg:address":"1 Litchdon St",
    "sg:city":"Barnstaple",
    "sg:classifiers":[
        {
            "category":"Insurance",
            "subcategory":"Insurance Agent",
            "type":"Services"
        }
    ],
    "sg:postcode":"EX32 8ND",
    "sg:province":"Devon",
    "sg:tags":[
        "broker"
    ],
    "wof:name":"John Walker & Co",
    "wof:placetype":"venue"
},
  "geometry": {"coordinates":[-4.057913,51.077812],"type":"Point"}
}