{
  "type": "Feature",
  "properties": {
    "addr:full":"359 Warwick Road Solihull West Midlands B91 1BQ",
    "addr:housenumber":"359",
    "addr:postcode":"b91 1bq",
    "addr:street":"Warwick Road",
    "iso:country":"GB",
    "sg:address":"359 Warwick Road",
    "sg:city":"Solihull",
    "sg:classifiers":[
        {
            "category":"Food & Beverages",
            "subcategory":"Meat & Fish",
            "type":"Retail Goods"
        }
    ],
    "sg:phone":"+44 121 707 7887",
    "sg:postcode":"B91 1BQ",
    "sg:province":"West Midlands",
    "sg:tags":[
        "butcher"
    ],
    "wof:name":"Dove House Butchers",
    "wof:placetype":"venue"
},
  "geometry": {"coordinates":[-1.797904,52.429386],"type":"Point"}
}