{
  "type": "Feature",
  "properties": {
    "addr:full":"Mount Works, Mount Rd Feltham Greater London TW13 6AR",
    "addr:postcode":"tw13 6ar",
    "addr:street":"Mount Rd",
    "iso:country":"GB",
    "sg:address":"Mount Works, Mount Rd",
    "sg:city":"Feltham",
    "sg:classifiers":[
        {
            "category":"Personal",
            "type":"Services"
        }
    ],
    "sg:phone":"+44 20 8893 4077",
    "sg:postcode":"TW13 6AR",
    "sg:province":"Greater London",
    "sg:tags":[
        "humidifiers",
        "dehumidifiers"
    ],
    "wof:name":"Dryvent Ltd",
    "wof:placetype":"venue"
},
  "geometry": {"coordinates":[-0.409204,51.447075],"type":"Point"}
}