{
  "type": "Feature",
  "properties": {
    "iso:country":"GB",
    "sg:address":"Tatten, London Road",
    "sg:city":"Crowborough",
    "sg:classifiers":[
        {
            "category":"Transit Center",
            "subcategory":"Passenger",
            "type":"Transportation"
        },
        {
            "category":"Retail",
            "subcategory":"Pet Boarding",
            "type":"Services"
        }
    ],
    "sg:phone":"+44 1892 665182",
    "sg:postcode":"TN6 1TD",
    "sg:province":"East Sussex",
    "sg:tags":[
        "kennel",
        "catteries"
    ],
    "wof:name":"Crowborough Cattery",
    "wof:placetype":"venue"
},
  "geometry": {"coordinates":[0.15336,51.069889],"type":"Point"}
}