{
  "type": "Feature",
  "properties": {
    "addr:full":"49 Hamilton Close Feltham Greater London TW13 4PT",
    "addr:housenumber":"49",
    "addr:postcode":"tw13 4pt",
    "addr:street":"Hamilton Close",
    "iso:country":"GB",
    "sg:address":"49 Hamilton Close",
    "sg:city":"Feltham",
    "sg:classifiers":[
        {
            "category":"Professional",
            "subcategory":"Management & Consulting",
            "type":"Services"
        }
    ],
    "sg:postcode":"TW13 4PT",
    "sg:province":"Greater London",
    "sg:tags":[
        "marketing",
        "consultant"
    ],
    "wof:name":"Total Recall Ltd.",
    "wof:placetype":"venue"
},
  "geometry": {"coordinates":[-0.4223130047,51.4325408936],"type":"Point"}
}