{
  "type": "Feature",
  "properties": {
    "addr:full":"55-57 Rivington Street London Greater London EC2A 3QA",
    "addr:housenumber":"55-57",
    "addr:postcode":"ec2a 3qa",
    "addr:street":"Rivington Street",
    "iso:country":"GB",
    "sg:address":"55-57 Rivington Street",
    "sg:city":"London",
    "sg:classifiers":[
        {
            "category":"Building & Trades",
            "subcategory":"Construction",
            "type":"Services"
        }
    ],
    "sg:phone":"+44 20 7729 1579",
    "sg:postcode":"EC2A 3QA",
    "sg:province":"Greater London",
    "sg:tags":[
        "contractor"
    ],
    "wof:name":"H J Contracts Ltd.",
    "wof:placetype":"venue"
},
  "geometry": {"coordinates":[-0.080687,51.526257],"type":"Point"}
}