{
  "type": "Feature",
  "properties": {
    "iso:country":"GB",
    "sg:address":"Warwick Parade, Kenton Lane",
    "sg:city":"Harrow",
    "sg:classifiers":[
        {
            "category":"Shopping",
            "subcategory":"Florist",
            "type":"Retail Goods"
        }
    ],
    "sg:postcode":"HA3 8SA",
    "sg:province":"Greater London",
    "wof:name":"M Parker",
    "wof:placetype":"venue"
},
  "geometry": {"coordinates":[-0.31804,51.600761],"type":"Point"}
}