{
  "type": "Feature",
  "properties": {
    "addr:full":"Middlewich Road Sandbach Cheshire CW11 3NT",
    "addr:postcode":"cw11 3nt",
    "addr:street":"Middlewich Road",
    "iso:country":"GB",
    "sg:address":"Middlewich Road",
    "sg:city":"Sandbach",
    "sg:classifiers":[
        {
            "category":"Education",
            "subcategory":"Special Training",
            "type":"Public Place"
        }
    ],
    "sg:phone":"+44 1270 759948",
    "sg:postcode":"CW11 3NT",
    "sg:province":"Cheshire",
    "sg:tags":[
        "product",
        "centre"
    ],
    "wof:name":"Sandbach Adult Education Centre",
    "wof:placetype":"venue"
},
  "geometry": {"coordinates":[-2.387971,53.147732],"type":"Point"}
}