{
  "type": "Feature",
  "properties": {
    "addr:full":"Gelliron Farm, Pontycymmer Bridgend Bridgend CF32 8HR",
    "addr:postcode":"cf32 8hr",
    "addr:street":"Bridgend",
    "iso:country":"GB",
    "sg:address":"Gelliron Farm, Pontycymmer",
    "sg:city":"Bridgend",
    "sg:classifiers":[
        {
            "category":"Farming",
            "subcategory":"Livestock Farm",
            "type":"Manufacturing & Wholesale Goods"
        }
    ],
    "sg:postcode":"CF32 8HR",
    "sg:province":"Bridgend",
    "sg:tags":[
        "others"
    ],
    "wof:name":"J Phillips",
    "wof:placetype":"venue"
},
  "geometry": {"coordinates":[-3.5777499676,51.6112709045],"type":"Point"}
}