{
  "type": "Feature",
  "properties": {
    "iso:country":"GB",
    "sg:address":"Naseby, Pump Lane, Springfield",
    "sg:city":"Chelmsford",
    "sg:classifiers":[
        {
            "category":"Professional",
            "subcategory":"Computer Services",
            "type":"Services"
        }
    ],
    "sg:phone":"+44 1245 462772",
    "sg:postcode":"CM1 6TA",
    "sg:province":"Essex",
    "sg:tags":[
        "system",
        "software"
    ],
    "wof:name":"J & S Systems Ltd.",
    "wof:placetype":"venue"
},
  "geometry": {"coordinates":[0.4951699972,51.7508811951],"type":"Point"}
}