{
  "type": "Feature",
  "properties": {
    "addr:full":"Russelheim Way Rugby Warwickshire CV22 7TB",
    "addr:postcode":"cv22 7tb",
    "addr:street":"Russelheim Way",
    "iso:country":"GB",
    "sg:address":"Russelheim Way",
    "sg:city":"Rugby",
    "sg:classifiers":[
        {
            "category":"Place Of Worship",
            "type":"Public Place"
        }
    ],
    "sg:phone":"+44 1788 579068",
    "sg:postcode":"CV22 7TB",
    "sg:province":"Warwickshire",
    "wof:name":"Rugby Methodist Church Centre",
    "wof:placetype":"venue"
},
  "geometry": {"coordinates":[-1.267511,52.370071],"type":"Point"}
}