{
  "type": "Feature",
  "properties": {
    "iso:country":"GB",
    "sg:address":"6 Silver St",
    "sg:city":"Bradford-on-avon",
    "sg:classifiers":[
        {
            "category":"Shopping",
            "subcategory":"Pharmacy",
            "type":"Retail Goods"
        }
    ],
    "sg:phone":"+44 1225 862212",
    "sg:postcode":"BA15 1JX",
    "sg:province":"Wiltshire",
    "sg:tags":[
        "pharmacist",
        "chemist"
    ],
    "wof:name":"Scrine,Arnold,Ltd",
    "wof:placetype":"venue"
},
  "geometry": {"coordinates":[-2.250028,51.347904],"type":"Point"}
}