{
  "type": "Feature",
  "properties": {
    "iso:country":"GB",
    "sg:address":"727-729 Market Street, Whitworth",
    "sg:city":"Rochdale",
    "sg:classifiers":[
        {
            "category":"Organizations",
            "subcategory":"Community Association",
            "type":"Services"
        },
        {
            "category":"Organizations",
            "subcategory":"Membership Organization",
            "type":"Services"
        }
    ],
    "sg:phone":"+44 1706 852657",
    "sg:postcode":"OL12 8LD",
    "sg:province":"Lancashire",
    "sg:tags":[
        "club",
        "social"
    ],
    "wof:name":"SHAUN HOARE",
    "wof:placetype":"venue"
},
  "geometry": {"coordinates":[-2.1705811024,53.6680107117],"type":"Point"}
}