{
  "type": "Feature",
  "properties": {
    "addr:full":"1-2 Endsleigh St Bloomsbury Greater London WC1H 0DS",
    "addr:housenumber":"1-2",
    "addr:postcode":"wc1h 0ds",
    "addr:street":"Endsleigh St",
    "iso:country":"GB",
    "sg:address":"1-2 Endsleigh St",
    "sg:city":"Bloomsbury",
    "sg:classifiers":[
        {
            "category":"Organizations",
            "subcategory":"Non-profit Organization",
            "type":"Services"
        }
    ],
    "sg:phone":"+44 20 7387 5954",
    "sg:postcode":"WC1H 0DS",
    "sg:province":"Greater London",
    "sg:tags":[
        "organisation",
        "voluntary",
        "charity"
    ],
    "wof:name":"Hillel House",
    "wof:placetype":"venue"
},
  "geometry": {"coordinates":[-0.1309809983,51.5264015198],"type":"Point"}
}