{
  "type": "Feature",
  "properties": {
    "addr:full":"30 Highbury Road West Lytham St Annes Lancashire FY8 2RE",
    "addr:housenumber":"30",
    "addr:postcode":"fy8 2re",
    "addr:street":"Highbury Road West;St",
    "iso:country":"GB",
    "sg:address":"30 Highbury Road West",
    "sg:city":"Lytham St Annes",
    "sg:classifiers":[
        {
            "category":"Home & Garden",
            "subcategory":"Household Appliances",
            "type":"Retail Goods"
        }
    ],
    "sg:phone":"+44 1253 722487",
    "sg:postcode":"FY8 2RE",
    "sg:province":"Lancashire",
    "sg:tags":[
        "electrical"
    ],
    "wof:name":"Fylde Appliance Care",
    "wof:placetype":"venue"
},
  "geometry": {"coordinates":[-3.0402500629,53.7619895935],"type":"Point"}
}