{
  "type": "Feature",
  "properties": {
    "addr:full":"Netherley Health Centre, Middlemass Hey Liverpool Merseyside L27 7AF",
    "addr:postcode":"l27 7af",
    "addr:street":"Hey",
    "iso:country":"GB",
    "sg:address":"Netherley Health Centre, Middlemass Hey",
    "sg:city":"Liverpool",
    "sg:classifiers":[
        {
            "category":"Health Services",
            "subcategory":"Doctor",
            "type":"Services"
        }
    ],
    "sg:phone":"+44 151 498 4054",
    "sg:postcode":"L27 7AF",
    "sg:province":"Merseyside",
    "sg:tags":[
        "practitioners"
    ],
    "wof:name":"Bracey, A P",
    "wof:placetype":"venue"
},
  "geometry": {"coordinates":[-2.8396100998,53.3883094788],"type":"Point"}
}