{
  "type": "Feature",
  "properties": {
    "iso:country":"GB",
    "sg:address":"Orrell Road, Orrell",
    "sg:city":"Wigan",
    "sg:classifiers":[
        {
            "category":"Education",
            "subcategory":"University",
            "type":"Public Place"
        },
        {
            "category":"Education",
            "subcategory":"School",
            "type":"Public Place"
        }
    ],
    "sg:postcode":"WN5 8HN",
    "sg:province":"Lancashire",
    "sg:tags":[
        "local",
        "adult",
        "authority"
    ],
    "wof:name":"Abraham Guest High School",
    "wof:placetype":"venue"
},
  "geometry": {"coordinates":[-2.7099790573,53.5401268005],"type":"Point"}
}