{
  "type": "Feature",
  "properties": {
    "addr:full":"Ditchfield Rd, Hough Green Widnes Cheshire WA8 8XR",
    "addr:postcode":"wa8 8xr",
    "addr:street":"Ditchfield Rd",
    "iso:country":"GB",
    "sg:address":"Ditchfield Rd, Hough Green",
    "sg:city":"Widnes",
    "sg:classifiers":[
        {
            "category":"Organizations",
            "subcategory":"Membership Organization",
            "type":"Services"
        }
    ],
    "sg:phone":"+44 151 424 5850",
    "sg:postcode":"WA8 8XR",
    "sg:province":"Cheshire",
    "sg:tags":[
        "club"
    ],
    "wof:name":"Hough Green Social Club",
    "wof:placetype":"venue"
},
  "geometry": {"coordinates":[-2.776054,53.369808],"type":"Point"}
}