{
  "type": "Feature",
  "properties": {
    "addr:full":"Unit A1, Horsted Keynes Industrial Estate Haywards Heath East Sussex RH17 7BA",
    "addr:postcode":"rh17 7ba",
    "addr:street":"Keynes Industrial",
    "iso:country":"GB",
    "sg:address":"Unit A1, Horsted Keynes Industrial Estate",
    "sg:city":"Haywards Heath",
    "sg:classifiers":[
        {
            "category":"Manufacturing",
            "subcategory":"Buildings",
            "type":"Manufacturing & Wholesale Goods"
        }
    ],
    "sg:phone":"+44 1342 811333",
    "sg:postcode":"RH17 7BA",
    "sg:province":"East Sussex",
    "sg:tags":[
        "system",
        "air conditioning"
    ],
    "wof:name":"Datum Controls Ltd.",
    "wof:placetype":"venue"
},
  "geometry": {"coordinates":[-0.036129,51.047794],"type":"Point"}
}