{
  "type": "Feature",
  "properties": {
    "iso:country":"GB",
    "sg:address":"Tower Close",
    "sg:city":"East Grinstead",
    "sg:classifiers":[
        {
            "category":"Autos & Motor Vehicles",
            "subcategory":"Automobile Sales",
            "type":"Retail Goods"
        }
    ],
    "sg:phone":"+44 1342 311177",
    "sg:postcode":"RH19 3JX",
    "sg:province":"East Sussex",
    "sg:tags":[
        "car"
    ],
    "wof:name":"Parkfield Motors",
    "wof:placetype":"venue"
},
  "geometry": {"coordinates":[-0.01379,51.12981],"type":"Point"}
}