{
  "type": "Feature",
  "properties": {
    "iso:country":"GB",
    "sg:address":"Hirings Office Management, Town Hall",
    "sg:city":"Ipswich",
    "sg:classifiers":[
        {
            "category":"Community Center",
            "type":"Public Place"
        },
        {
            "category":"Government",
            "subcategory":"Office",
            "type":"Public Place"
        }
    ],
    "sg:phone":"+44 1473 255851",
    "sg:postcode":"IP1 1DH",
    "sg:province":"Suffolk",
    "sg:tags":[
        "entertainment",
        "local",
        "centre"
    ],
    "wof:name":"Corn Exchange & Town Hall Conference Entertainment",
    "wof:placetype":"venue"
},
  "geometry": {"coordinates":[1.143788,52.057777],"type":"Point"}
}