{
  "type": "Feature",
  "properties": {
    "addr:full":"74 Camberwell Church Street London Greater London SE5 8QZ",
    "addr:housenumber":"74",
    "addr:postcode":"se5 8qz",
    "addr:street":"Camberwell Church Street",
    "iso:country":"GB",
    "sg:address":"74 Camberwell Church Street",
    "sg:city":"London",
    "sg:classifiers":[
        {
            "category":"Professional",
            "subcategory":"Lawyer & Legal Services",
            "type":"Services"
        }
    ],
    "sg:phone":"+44 20 7708 0077",
    "sg:postcode":"SE5 8QZ",
    "sg:province":"Greater London",
    "sg:tags":[
        "solicitor"
    ],
    "wof:name":"Osibanjo Ete & Co.",
    "wof:placetype":"venue"
},
  "geometry": {"coordinates":[-0.0898670033,51.4740028381],"type":"Point"}
}