{
  "type": "Feature",
  "properties": {
    "addr:full":"96 Brithweunydd Road, Trealew Tonypandy Rhondda, Cynon, Taff CF40 2UF",
    "addr:housenumber":"96",
    "addr:postcode":"cf40 2uf",
    "addr:street":"Brithweunydd Road Trealew;Cynon Taff",
    "iso:country":"GB",
    "sg:address":"96 Brithweunydd Road, Trealew",
    "sg:city":"Tonypandy",
    "sg:classifiers":[
        {
            "category":"Social Services",
            "subcategory":"Retirement Home",
            "type":"Services"
        }
    ],
    "sg:postcode":"CF40 2UF",
    "sg:province":"Rhondda, Cynon, Taff",
    "sg:tags":[
        "residential",
        "care"
    ],
    "wof:name":"Highfield Residential Home",
    "wof:placetype":"venue"
},
  "geometry": {"coordinates":[-3.43608,51.619072],"type":"Point"}
}