{
  "type": "Feature",
  "properties": {
    "addr:full":"Cross-o-the-hands Farm, Cross-o-the-hands, Turnditch Belper Derbyshire DE56 2LT",
    "addr:postcode":"de56 2lt",
    "addr:street":"Cross-O-The-Hands",
    "iso:country":"GB",
    "sg:address":"Cross-o-the-hands Farm, Cross-o-the-hands, Turnditch",
    "sg:city":"Belper",
    "sg:classifiers":[
        {
            "category":"Farming",
            "subcategory":"Livestock Farm",
            "type":"Manufacturing & Wholesale Goods"
        },
        {
            "category":"Farming",
            "subcategory":"Farm",
            "type":"Manufacturing & Wholesale Goods"
        }
    ],
    "sg:phone":"+44 1773 550383",
    "sg:postcode":"DE56 2LT",
    "sg:province":"Derbyshire",
    "sg:tags":[
        "mixed",
        "crop",
        "others"
    ],
    "wof:name":"LEONARD A NEALE",
    "wof:placetype":"venue"
},
  "geometry": {"coordinates":[-1.5593789816,53.0159416199],"type":"Point"}
}