{
  "type": "Feature",
  "properties": {
    "addr:full":"24 Greenham Rd Newbury Berkshire RG14 7HR",
    "addr:housenumber":"24",
    "addr:postcode":"rg14 7hr",
    "addr:street":"Greenham Rd",
    "iso:country":"GB",
    "sg:address":"24 Greenham Rd",
    "sg:city":"Newbury",
    "sg:classifiers":[
        {
            "category":"Shopping",
            "subcategory":"Stationery & Office Supplies",
            "type":"Retail Goods"
        }
    ],
    "sg:phone":"+44 1635 524881",
    "sg:postcode":"RG14 7HR",
    "sg:province":"Berkshire",
    "sg:tags":[
        "equipment"
    ],
    "wof:name":"Office World",
    "wof:placetype":"venue"
},
  "geometry": {"coordinates":[-1.317933,51.390305],"type":"Point"}
}