{
  "type": "Feature",
  "properties": {
    "addr:full":"Unit 5, Cardigan House Cannock Staffordshire WS12 5AQ",
    "addr:housenumber":"unit 5",
    "addr:postcode":"ws12 5aq",
    "iso:country":"GB",
    "sg:address":"Unit 5, Cardigan House",
    "sg:city":"Cannock",
    "sg:classifiers":[
        {
            "category":"Retail",
            "subcategory":"Repair Shop",
            "type":"Services"
        }
    ],
    "sg:phone":"+44 1543 878382",
    "sg:postcode":"WS12 5AQ",
    "sg:province":"Staffordshire",
    "sg:tags":[
        "clocks",
        "watch"
    ],
    "wof:name":"Russell Watch Repairs",
    "wof:placetype":"venue"
},
  "geometry": {"coordinates":[-1.990659,52.699478],"type":"Point"}
}