{
  "type": "Feature",
  "properties": {
    "addr:full":"Mill Hill Leeds West Yorkshire LS1 5DQ",
    "addr:postcode":"ls1 5dq",
    "addr:street":"Mill Hill",
    "iso:country":"GB",
    "sg:address":"Mill Hill",
    "sg:city":"Leeds",
    "sg:classifiers":[
        {
            "category":"Recreation",
            "subcategory":"Amusement Park",
            "type":"Entertainment"
        }
    ],
    "sg:phone":"+44 113 245 1135",
    "sg:postcode":"LS1 5DQ",
    "sg:province":"West Yorkshire",
    "sg:tags":[
        "arcade"
    ],
    "wof:name":"Metsmatics Limited",
    "wof:placetype":"venue"
},
  "geometry": {"coordinates":[-1.5456290245,53.7954444885],"type":"Point"}
}