{
  "type": "Feature",
  "properties": {
    "iso:country":"GB",
    "sg:address":"Front Street, Chirton",
    "sg:city":"North Shields",
    "sg:classifiers":[
        {
            "category":"Bars & Pubs",
            "type":"Food & Drink"
        }
    ],
    "sg:phone":"+44 191 258 4436",
    "sg:postcode":"NE29 7QW",
    "sg:province":"Tyne and Wear",
    "sg:tags":[
        "pubs",
        "inn"
    ],
    "wof:name":"Robin Hood Inn",
    "wof:placetype":"venue"
},
  "geometry": {"coordinates":[-1.462744,55.007889],"type":"Point"}
}