{
  "type": "Feature",
  "properties": {
    "addr:full":"1 Clifton Close, Cheshunt Waltham Cross Essex EN8 9HX",
    "addr:housenumber":"1",
    "addr:postcode":"en8 9hx",
    "addr:street":"Clifton Close",
    "iso:country":"GB",
    "sg:address":"1 Clifton Close, Cheshunt",
    "sg:city":"Waltham Cross",
    "sg:classifiers":[
        {
            "category":"Autos & Motor Vehicles",
            "subcategory":"Auto Supplies",
            "type":"Retail Goods"
        }
    ],
    "sg:phone":"+44 1992 622531",
    "sg:postcode":"EN8 9HX",
    "sg:province":"Essex",
    "sg:tags":[
        "component"
    ],
    "wof:name":"A & S Supplies",
    "wof:placetype":"venue"
},
  "geometry": {"coordinates":[-0.028453,51.704834],"type":"Point"}
}