{
  "type": "Feature",
  "properties": {
    "addr:full":"219 Timberlog Lane Basildon Essex SS14 1PB",
    "addr:housenumber":"219",
    "addr:postcode":"ss14 1pb",
    "addr:street":"Timberlog Lane",
    "iso:country":"GB",
    "sg:address":"219 Timberlog Lane",
    "sg:city":"Basildon",
    "sg:classifiers":[
        {
            "category":"Shopping",
            "subcategory":"News",
            "type":"Retail Goods"
        }
    ],
    "sg:phone":"+44 1268 553560",
    "sg:postcode":"SS14 1PB",
    "sg:province":"Essex",
    "sg:tags":[
        "newsagent"
    ],
    "wof:name":"Martin Retail Group Ltd.",
    "wof:placetype":"venue"
},
  "geometry": {"coordinates":[0.4853779972,51.5707969666],"type":"Point"}
}