{
  "type": "Feature",
  "properties": {
    "addr:full":"343 High Street, Walton Felixstowe Suffolk IP11 9QL",
    "addr:housenumber":"343",
    "addr:postcode":"ip11 9ql",
    "addr:street":"High Street",
    "iso:country":"GB",
    "sg:address":"343 High Street, Walton",
    "sg:city":"Felixstowe",
    "sg:classifiers":[
        {
            "category":"Bus Charters",
            "type":"Transportation"
        }
    ],
    "sg:phone":"+44 1394 277556",
    "sg:postcode":"IP11 9QL",
    "sg:province":"Suffolk",
    "sg:tags":[
        "hire",
        "coach"
    ],
    "wof:name":"Gilpatricks Coaches",
    "wof:placetype":"venue"
},
  "geometry": {"coordinates":[1.3344709873,51.9740753174],"type":"Point"}
}