{
  "type": "Feature",
  "properties": {
    "addr:full":"Glancleddau, Dwr Bach Fishguard Pembrokeshire SA65 9RH",
    "addr:postcode":"sa65 9rh",
    "addr:street":"Glancleddau Dwr Bach",
    "iso:country":"GB",
    "sg:address":"Glancleddau, Dwr Bach",
    "sg:city":"Fishguard",
    "sg:classifiers":[
        {
            "category":"Farming",
            "subcategory":"Livestock Farm",
            "type":"Manufacturing & Wholesale Goods"
        }
    ],
    "sg:postcode":"SA65 9RH",
    "sg:province":"Pembrokeshire",
    "sg:tags":[
        "others"
    ],
    "wof:name":"D P Evans",
    "wof:placetype":"venue"
},
  "geometry": {"coordinates":[-4.977396965,51.9943733215],"type":"Point"}
}