{
  "type": "Feature",
  "properties": {
    "addr:full":"Unit 12, Fysh House Farm, Cuckoo Hill Bures Essex CO8 5LD",
    "addr:housenumber":"unit 12 fysh house farm",
    "addr:postcode":"co8 5ld",
    "addr:street":"Cuckoo Hill",
    "iso:country":"GB",
    "sg:address":"Unit 12, Fysh House Farm, Cuckoo Hill",
    "sg:city":"Bures",
    "sg:classifiers":[
        {
            "category":"Manufacturing",
            "subcategory":"Wood Products",
            "type":"Manufacturing & Wholesale Goods"
        }
    ],
    "sg:phone":"+44 1787 227770",
    "sg:postcode":"CO8 5LD",
    "sg:province":"Essex",
    "sg:tags":[
        "maker",
        "cabinet"
    ],
    "wof:name":"Millstore Fine Furniture",
    "wof:placetype":"venue"
},
  "geometry": {"coordinates":[0.7810080051,51.974571228],"type":"Point"}
}