{
  "type": "Feature",
  "properties": {
    "addr:full":"147 Walbrook Road Derby Derbyshire DE23 8SF",
    "addr:housenumber":"147",
    "addr:postcode":"de23 8sf",
    "addr:street":"Walbrook Road",
    "iso:country":"GB",
    "sg:address":"147 Walbrook Road",
    "sg:city":"Derby",
    "sg:classifiers":[
        {
            "category":"Personal",
            "subcategory":"Beauty Salon",
            "type":"Services"
        },
        {
            "category":"Personal",
            "subcategory":"Barber",
            "type":"Services"
        }
    ],
    "sg:phone":"+44 1332 760209",
    "sg:postcode":"DE23 8SF",
    "sg:province":"Derbyshire",
    "sg:tags":[
        "unisex",
        "hairdresser"
    ],
    "wof:name":"The Hair Shop",
    "wof:placetype":"venue"
},
  "geometry": {"coordinates":[-1.4844379425,52.9024047852],"type":"Point"}
}