{
  "type": "Feature",
  "properties": {
    "iso:country":"GB",
    "sg:address":"2-4 Garrick Street",
    "sg:city":"London",
    "sg:classifiers":[
        {
            "category":"Restaurant",
            "type":"Food & Drink"
        }
    ],
    "sg:phone":"+44 20 7497 2779",
    "sg:postcode":"WC2E 9BH",
    "sg:province":"Greater London",
    "wof:name":"Cafe Pasta Ltd.",
    "wof:placetype":"venue"
},
  "geometry": {"coordinates":[-0.1256570071,51.5114784241],"type":"Point"}
}