{
  "type": "Feature",
  "properties": {
    "iso:country":"GB",
    "sg:address":"Unit 1a Craven Enterprise Park, Hopwood Lane",
    "sg:city":"Halifax",
    "sg:classifiers":[
        {
            "category":"Wholesale",
            "subcategory":"Non-durable Goods",
            "type":"Manufacturing & Wholesale Goods"
        }
    ],
    "sg:postcode":"HX1 5ED",
    "sg:province":"West Yorkshire",
    "sg:tags":[
        "carry",
        "cash"
    ],
    "wof:name":"Somia Cash & Carry",
    "wof:placetype":"venue"
},
  "geometry": {"coordinates":[-1.862224,53.721233],"type":"Point"}
}