{
  "type": "Feature",
  "properties": {
    "addr:full":"Firtree Crook Durham DL15 8BL",
    "addr:postcode":"dl15 8bl",
    "iso:country":"GB",
    "sg:address":"Firtree",
    "sg:city":"Crook",
    "sg:classifiers":[
        {
            "category":"Travel",
            "subcategory":"Hotels & Motels",
            "type":"Entertainment"
        }
    ],
    "sg:phone":"+44 1388 763143",
    "sg:postcode":"DL15 8BL",
    "sg:province":"Durham",
    "wof:name":"Greenhead Country House Hotel",
    "wof:placetype":"venue"
},
  "geometry": {"coordinates":[-1.756459,54.695423],"type":"Point"}
}