{
  "type": "Feature",
  "properties": {
    "iso:country":"GB",
    "sg:address":"Enterprise House Ironworks Park, Bowling Back Lane",
    "sg:city":"Bradford",
    "sg:classifiers":[
        {
            "category":"Home & Garden",
            "subcategory":"Hardware",
            "type":"Retail Goods"
        }
    ],
    "sg:postcode":"BD4 8SX",
    "sg:province":"West Yorkshire",
    "sg:tags":[
        "equipment",
        "bathroom",
        "fitting"
    ],
    "wof:name":"Clearwater Collection Ltd.",
    "wof:placetype":"venue"
},
  "geometry": {"coordinates":[-1.7278100252,53.7862892151],"type":"Point"}
}