{
  "type": "Feature",
  "properties": {
    "iso:country":"GB",
    "sg:address":"3 Riverside Albert Wharf, 22 Hester Road",
    "sg:city":"London",
    "sg:classifiers":[
        {
            "category":"Real Estate",
            "subcategory":"Architect",
            "type":"Services"
        }
    ],
    "sg:phone":"+44 20 7738 0455",
    "sg:postcode":"SW11 4AN",
    "sg:province":"Greater London",
    "sg:website":"http://www.fosterandpartners.com",
    "wof:name":"Foster & Partners Ltd.",
    "wof:placetype":"venue"
},
  "geometry": {"coordinates":[-0.1687400043,51.4799194336],"type":"Point"}
}