{
  "type": "Feature",
  "properties": {
    "iso:country":"GB",
    "sg:address":", Bottomhouse",
    "sg:city":"Leek",
    "sg:classifiers":[
        {
            "category":"Bars & Pubs",
            "type":"Food & Drink"
        }
    ],
    "sg:phone":"+44 1538 304360",
    "sg:postcode":"ST13 7QJ",
    "sg:province":"Staffordshire",
    "sg:tags":[
        "pubs",
        "inn"
    ],
    "wof:name":"Green Man Inn",
    "wof:placetype":"venue"
},
  "geometry": {"coordinates":[-1.9404489994,53.0721282959],"type":"Point"}
}