{
  "type": "Feature",
  "properties": {
    "addr:full":"69 Westbourne Gro London Greater London W2 4UJ",
    "addr:housenumber":"69",
    "addr:postcode":"w2 4uj",
    "addr:street":"Westbourne Gro",
    "iso:country":"GB",
    "sg:address":"69 Westbourne Gro",
    "sg:city":"London",
    "sg:classifiers":[
        {
            "category":"Recreation",
            "subcategory":"Gun Range",
            "type":"Entertainment"
        }
    ],
    "sg:phone":"+44 20 7792 1188",
    "sg:postcode":"W2 4UJ",
    "sg:province":"Greater London",
    "sg:tags":[
        "operator",
        "tour"
    ],
    "wof:name":"White Roc Ski",
    "wof:placetype":"venue"
},
  "geometry": {"coordinates":[-0.191556,51.515297],"type":"Point"}
}