{
  "type": "Feature",
  "properties": {
    "iso:country":"GB",
    "sg:address":"22 Old Buildings",
    "sg:city":"London",
    "sg:classifiers":[
        {
            "category":"Professional",
            "subcategory":"Lawyer & Legal Services",
            "type":"Services"
        }
    ],
    "sg:postcode":"WC2A 3UT",
    "sg:province":"Greater London",
    "sg:tags":[
        "barrister"
    ],
    "wof:name":"Stephen Stewart",
    "wof:placetype":"venue"
},
  "geometry": {"coordinates":[-0.112431,51.516117],"type":"Point"}
}