{
  "type": "Feature",
  "properties": {
    "addr:full":"87 Cavendish Place Eastbourne East Sussex BN21 3RR",
    "addr:housenumber":"87",
    "addr:postcode":"bn21 3rr",
    "addr:street":"Cavendish Place",
    "iso:country":"GB",
    "sg:address":"87 Cavendish Place",
    "sg:city":"Eastbourne",
    "sg:classifiers":[
        {
            "category":"Food & Beverages",
            "subcategory":"Meat & Fish",
            "type":"Retail Goods"
        }
    ],
    "sg:postcode":"BN21 3RR",
    "sg:province":"East Sussex",
    "sg:tags":[
        "butcher"
    ],
    "wof:name":"G Price & Son",
    "wof:placetype":"venue"
},
  "geometry": {"coordinates":[0.2891660035,50.7711029053],"type":"Point"}
}