{
  "type": "Feature",
  "properties": {
    "addr:full":"5 Sundorne Avenue Shrewsbury Shropshire SY1 4JW",
    "addr:housenumber":"5",
    "addr:postcode":"sy1 4jw",
    "addr:street":"Sundorne Avenue",
    "iso:country":"GB",
    "sg:address":"5 Sundorne Avenue",
    "sg:city":"Shrewsbury",
    "sg:classifiers":[
        {
            "category":"Fast Food",
            "type":"Food & Drink"
        }
    ],
    "sg:phone":"+44 1743 343636",
    "sg:postcode":"SY1 4JW",
    "sg:province":"Shropshire",
    "sg:tags":[
        "away",
        "take"
    ],
    "wof:name":"Loi Kee",
    "wof:placetype":"venue"
},
  "geometry": {"coordinates":[-2.7275528908,52.7281227112],"type":"Point"}
}