{
  "type": "Feature",
  "properties": {
    "addr:full":"1029 London Road Thornton Heath Surrey CR7 6YP",
    "addr:housenumber":"1029",
    "addr:postcode":"cr7 6yp",
    "addr:street":"London Road",
    "iso:country":"GB",
    "sg:address":"1029 London Road",
    "sg:city":"Thornton Heath",
    "sg:classifiers":[
        {
            "category":"Professional",
            "subcategory":"Lawyer & Legal Services",
            "type":"Services"
        }
    ],
    "sg:phone":"+44 20 8684 5656",
    "sg:postcode":"CR7 6YP",
    "sg:province":"Surrey",
    "sg:tags":[
        "solicitor"
    ],
    "wof:name":"Atkins Hope",
    "wof:placetype":"venue"
},
  "geometry": {"coordinates":[-0.1179950014,51.4004096985],"type":"Point"}
}