{
  "type": "Feature",
  "properties": {
    "addr:full":"8 Annesley Road, Hucknall Nottingham Nottinghamshire NG15 7AB",
    "addr:housenumber":"8",
    "addr:postcode":"ng15 7ab",
    "addr:street":"Annesley Road",
    "iso:country":"GB",
    "sg:address":"8 Annesley Road, Hucknall",
    "sg:city":"Nottingham",
    "sg:classifiers":[
        {
            "category":"Personal",
            "subcategory":"Shoe Repair & Shine",
            "type":"Services"
        },
        {
            "category":"Shopping",
            "subcategory":"Shoes",
            "type":"Retail Goods"
        }
    ],
    "sg:phone":"+44 115 955 9198",
    "sg:postcode":"NG15 7AB",
    "sg:province":"Nottinghamshire",
    "wof:name":"Shoe Repairs & Key Cutting Service",
    "wof:placetype":"venue"
},
  "geometry": {"coordinates":[-1.2080130577,53.0404586792],"type":"Point"}
}