{
  "type": "Feature",
  "properties": {
    "iso:country":"GB",
    "sg:address":"22 High Street",
    "sg:city":"Newhaven",
    "sg:classifiers":[
        {
            "category":"Professional",
            "subcategory":"Business Services",
            "type":"Services"
        },
        {
            "category":"Shopping",
            "subcategory":"Pets & Pet Supplies",
            "type":"Retail Goods"
        }
    ],
    "sg:postcode":"BN9 9PD",
    "sg:province":"East Sussex",
    "sg:tags":[
        "import",
        "export",
        "agent"
    ],
    "wof:name":"Peckanory Pets",
    "wof:placetype":"venue"
},
  "geometry": {"coordinates":[0.048872,50.794384],"type":"Point"}
}