{
  "type": "Feature",
  "properties": {
    "addr:full":"48 Bruce Avenue Shepperton Surrey TW17 9DW",
    "addr:housenumber":"48",
    "addr:postcode":"tw17 9dw",
    "addr:street":"Bruce Avenue",
    "iso:country":"GB",
    "sg:address":"48 Bruce Avenue",
    "sg:city":"Shepperton",
    "sg:classifiers":[
        {
            "category":"Professional",
            "subcategory":"Engineering",
            "type":"Services"
        }
    ],
    "sg:postcode":"TW17 9DW",
    "sg:province":"Surrey",
    "sg:tags":[
        "contractor",
        "electrical",
        "engineer"
    ],
    "wof:name":"B J Dineen Electrical Contractors",
    "wof:placetype":"venue"
},
  "geometry": {"coordinates":[-0.445669,51.393833],"type":"Point"}
}