{
  "type": "Feature",
  "properties": {
    "iso:country":"GB",
    "sg:address":"Unit 2, 3, & 4 The Drift",
    "sg:city":"Fakenham",
    "sg:classifiers":[
        {
            "category":"Home & Garden",
            "subcategory":"Carpets & Floor Coverings",
            "type":"Retail Goods"
        }
    ],
    "sg:phone":"+44 1328 863609",
    "sg:postcode":"NR21 8EE",
    "sg:province":"Norfolk",
    "sg:tags":[
        "textile",
        "floorcoverings"
    ],
    "wof:name":"Mike Smith Carpet Warehouse",
    "wof:placetype":"venue"
},
  "geometry": {"coordinates":[0.859698,52.831951],"type":"Point"}
}