{
  "type": "Feature",
  "properties": {
    "addr:full":"Town Farm, South End, Milton Bryan Milton Keynes Bedfordshire MK17 9HS",
    "addr:postcode":"mk17 9hs",
    "addr:street":"Bryan",
    "iso:country":"GB",
    "sg:address":"Town Farm, South End, Milton Bryan",
    "sg:city":"Milton Keynes",
    "sg:classifiers":[
        {
            "category":"Professional",
            "type":"Services"
        },
        {
            "category":"Banks & Credit Unions",
            "subcategory":"Investment Brokerage",
            "type":"Services"
        }
    ],
    "sg:phone":"+44 1525 210001",
    "sg:postcode":"MK17 9HS",
    "sg:province":"Bedfordshire",
    "sg:tags":[
        "farm",
        "agricultural",
        "contractor"
    ],
    "wof:name":"JOHN HARRIS",
    "wof:placetype":"venue"
},
  "geometry": {"coordinates":[-0.5894820094,51.9668769836],"type":"Point"}
}