{
  "type": "Feature",
  "properties": {
    "addr:full":"220 Sheffield Road Barnsley South Yorkshire S70 4PF",
    "addr:housenumber":"220",
    "addr:postcode":"s70 4pf",
    "addr:street":"Sheffield Road;Yorkshire",
    "iso:country":"GB",
    "sg:address":"220 Sheffield Road",
    "sg:city":"Barnsley",
    "sg:classifiers":[
        {
            "category":"Professional",
            "subcategory":"Engineering",
            "type":"Services"
        },
        {
            "category":"Building & Trades",
            "subcategory":"Electrical",
            "type":"Services"
        }
    ],
    "sg:phone":"+44 1226 282576",
    "sg:postcode":"S70 4PF",
    "sg:province":"South Yorkshire",
    "sg:tags":[
        "engineer",
        "electrician",
        "contractor"
    ],
    "wof:name":"D H Marrion Ltd",
    "wof:placetype":"venue"
},
  "geometry": {"coordinates":[-1.472512,53.544743],"type":"Point"}
}