{
  "type": "Feature",
  "properties": {
    "addr:full":"7 Alexandra Terrace St Ives Cornwall TR26 1EW",
    "addr:housenumber":"7",
    "addr:postcode":"tr26 1ew",
    "addr:street":"Alexandra Terrace",
    "iso:country":"GB",
    "sg:address":"7 Alexandra Terrace",
    "sg:city":"St Ives",
    "sg:classifiers":[
        {
            "category":"Building & Trades",
            "subcategory":"Construction",
            "type":"Services"
        }
    ],
    "sg:phone":"+44 1736 796980",
    "sg:postcode":"TR26 1EW",
    "sg:province":"Cornwall",
    "sg:tags":[
        "heating",
        "contractor"
    ],
    "wof:name":"G M Care",
    "wof:placetype":"venue"
},
  "geometry": {"coordinates":[-5.4909210205,50.2113952637],"type":"Point"}
}