{
  "type": "Feature",
  "properties": {
    "iso:country":"GB",
    "sg:address":"126 Melton Road, West Bridgford",
    "sg:city":"Nottingham",
    "sg:classifiers":[
        {
            "category":"Professional",
            "subcategory":"Computer Services",
            "type":"Services"
        }
    ],
    "sg:phone":"+44 115 974 4422",
    "sg:postcode":"NG2 6EP",
    "sg:province":"Nottinghamshire",
    "sg:tags":[
        "system",
        "software"
    ],
    "wof:name":"Prime Technology",
    "wof:placetype":"venue"
},
  "geometry": {"coordinates":[-1.129875,52.927383],"type":"Point"}
}