{
  "type": "Feature",
  "properties": {
    "addr:full":"102 Sidney Street London Greater London SW3 6NJ",
    "addr:housenumber":"102",
    "addr:postcode":"sw3 6nj",
    "addr:street":"Sidney Street",
    "iso:country":"GB",
    "sg:address":"102 Sidney Street",
    "sg:city":"London",
    "sg:classifiers":[
        {
            "category":"Wholesale",
            "subcategory":"Books, Periodicals, & Newspapers",
            "type":"Manufacturing & Wholesale Goods"
        }
    ],
    "sg:phone":"+44 20 7368 9600",
    "sg:postcode":"SW3 6NJ",
    "sg:province":"Greater London",
    "sg:tags":[
        "publishing"
    ],
    "wof:name":"Brass Tacks Customer Magazines Ltd.",
    "wof:placetype":"venue"
},
  "geometry": {"coordinates":[-0.16899,51.488022],"type":"Point"}
}