{
  "type": "Feature",
  "properties": {
    "iso:country":"GB",
    "sg:address":"225 Ravenshouse Road",
    "sg:city":"Dewsbury",
    "sg:classifiers":[
        {
            "category":"Professional",
            "type":"Services"
        },
        {
            "category":"Wholesale",
            "subcategory":"Groceries",
            "type":"Manufacturing & Wholesale Goods"
        }
    ],
    "sg:postcode":"WF13 3QU",
    "sg:province":"West Yorkshire",
    "sg:tags":[
        "food",
        "supplier",
        "drink",
        "caterer"
    ],
    "wof:name":"Mortimers Bakery",
    "wof:placetype":"venue"
},
  "geometry": {"coordinates":[-1.6554290056,53.6871795654],"type":"Point"}
}