{
  "type": "Feature",
  "properties": {
    "iso:country":"GB",
    "sg:address":"3 High St",
    "sg:city":"Lanark",
    "sg:classifiers":[
        {
            "category":"Restaurant",
            "type":"Food & Drink"
        }
    ],
    "sg:phone":"+44 1555 666041",
    "sg:postcode":"ML11 7LU",
    "sg:province":"South Lanarkshire",
    "wof:name":"Caesar's Restaurant",
    "wof:placetype":"venue"
},
  "geometry": {"coordinates":[-3.780564,55.673897],"type":"Point"}
}