{
  "type": "Feature",
  "properties": {
    "addr:full":"12 The Cornfields, Hatch Warren Basingstoke Hampshire RG22 4QB",
    "addr:housenumber":"12",
    "addr:postcode":"rg22 4qb",
    "addr:street":"The Cornfields",
    "iso:country":"GB",
    "sg:address":"12 The Cornfields, Hatch Warren",
    "sg:city":"Basingstoke",
    "sg:classifiers":[
        {
            "category":"Shopping",
            "subcategory":"Computers & Home Electronics",
            "type":"Retail Goods"
        }
    ],
    "sg:postcode":"RG22 4QB",
    "sg:province":"Hampshire",
    "sg:tags":[
        "equipment",
        "radio"
    ],
    "wof:name":"Yearsley,Janice,",
    "wof:placetype":"venue"
},
  "geometry": {"coordinates":[-1.131999,51.233913],"type":"Point"}
}