{
  "type": "Feature",
  "properties": {
    "iso:country":"GB",
    "sg:address":"35 Guildford Road",
    "sg:city":"Woking",
    "sg:classifiers":[
        {
            "category":"Utilities",
            "subcategory":"Fuel Oil & Lpg",
            "type":"Services"
        }
    ],
    "sg:phone":"+44 1224 205000",
    "sg:postcode":"GU22 7QT",
    "sg:province":"Surrey",
    "sg:tags":[
        "gas"
    ],
    "wof:name":"Conocophillips Pension Plan Trustees Ltd.",
    "wof:placetype":"venue"
},
  "geometry": {"coordinates":[-0.560065,51.314674],"type":"Point"}
}