{
  "type": "Feature",
  "properties": {
    "iso:country":"GB",
    "sg:address":"Church Road, Cook And Dean",
    "sg:city":"Maidenhead",
    "sg:classifiers":[
        {
            "category":"Bars & Pubs",
            "type":"Food & Drink"
        },
        {
            "category":"Community Center",
            "subcategory":"Social",
            "type":"Public Place"
        }
    ],
    "sg:phone":"+44 1628 482905",
    "sg:postcode":"SL6 9PD",
    "sg:province":"Berkshire",
    "sg:tags":[
        "pubs",
        "house",
        "inn",
        "activity"
    ],
    "wof:name":"Jolly Farmer",
    "wof:placetype":"venue"
},
  "geometry": {"coordinates":[-0.744593,51.558754],"type":"Point"}
}