{
  "type": "Feature",
  "properties": {
    "addr:full":"59 The Street, Wrecclesham Farnham Hampshire GU10 4QS",
    "addr:housenumber":"59",
    "addr:postcode":"gu10 4qs",
    "addr:street":"The Street",
    "iso:country":"GB",
    "sg:address":"59 The Street, Wrecclesham",
    "sg:city":"Farnham",
    "sg:classifiers":[
        {
            "category":"Bars & Pubs",
            "type":"Food & Drink"
        }
    ],
    "sg:phone":"+44 1252 716845",
    "sg:postcode":"GU10 4QS",
    "sg:province":"Hampshire",
    "sg:tags":[
        "pubs",
        "inn"
    ],
    "wof:name":"The Royal Oak",
    "wof:placetype":"venue"
},
  "geometry": {"coordinates":[-0.8208060265,51.196521759],"type":"Point"}
}