{
  "type": "Feature",
  "properties": {
    "iso:country":"GB",
    "sg:address":"106 Birmingham Road",
    "sg:city":"Wolverhampton",
    "sg:classifiers":[
        {
            "category":"Home & Garden",
            "subcategory":"Home Furnishings",
            "type":"Retail Goods"
        }
    ],
    "sg:phone":"+44 1902 459321",
    "sg:postcode":"WV2 3NZ",
    "sg:province":"West Midlands",
    "sg:tags":[
        "blind",
        "curtain",
        "fitting"
    ],
    "wof:name":"Yarnolds (Wolverhampton) Ltd.",
    "wof:placetype":"venue"
},
  "geometry": {"coordinates":[-2.1244120598,52.5764427185],"type":"Point"}
}