{
  "type": "Feature",
  "properties": {
    "addr:full":"5 Churchill Parade, The Street, Rustington Littlehampton West Sussex BN16 3DJ",
    "addr:housenumber":"5",
    "addr:postcode":"bn16 3dj",
    "addr:street":"Churchill Parade The Street",
    "iso:country":"GB",
    "sg:address":"5 Churchill Parade, The Street, Rustington",
    "sg:city":"Littlehampton",
    "sg:classifiers":[
        {
            "category":"Shopping",
            "subcategory":"Pharmacy",
            "type":"Retail Goods"
        }
    ],
    "sg:phone":"+44 1903 784338",
    "sg:postcode":"BN16 3DJ",
    "sg:province":"West Sussex",
    "sg:tags":[
        "pharmacist",
        "chemist"
    ],
    "wof:name":"Lloyds Pharmacy",
    "wof:placetype":"venue"
},
  "geometry": {"coordinates":[-0.50754,50.810749],"type":"Point"}
}