{
  "type": "Feature",
  "properties": {
    "addr:full":"122 High Street London Greater London NW10 4SP",
    "addr:housenumber":"122",
    "addr:postcode":"nw10 4sp",
    "addr:street":"High Street",
    "iso:country":"GB",
    "sg:address":"122 High Street",
    "sg:city":"London",
    "sg:classifiers":[
        {
            "category":"Social Services",
            "type":"Services"
        },
        {
            "category":"Health Services",
            "subcategory":"Hospital",
            "type":"Services"
        }
    ],
    "sg:phone":"+44 20 8961 9005",
    "sg:postcode":"NW10 4SP",
    "sg:province":"Greater London",
    "sg:tags":[
        "authority"
    ],
    "wof:name":"Brent Sickle Cell & Thalassaemia Centre",
    "wof:placetype":"venue"
},
  "geometry": {"coordinates":[-0.2446659952,51.5357475281],"type":"Point"}
}