{
  "type": "Feature",
  "properties": {
    "addr:full":"8 Christchurch Mount Epsom Surrey KT19 8LU",
    "addr:housenumber":"8",
    "addr:postcode":"kt19 8lu",
    "addr:street":"Christchurch Mount",
    "iso:country":"GB",
    "sg:address":"8 Christchurch Mount",
    "sg:city":"Epsom",
    "sg:classifiers":[
        {
            "category":"Professional",
            "subcategory":"Computer Services",
            "type":"Services"
        }
    ],
    "sg:postcode":"KT19 8LU",
    "sg:province":"Surrey",
    "sg:tags":[
        "consultant"
    ],
    "wof:name":"Decision Associates",
    "wof:placetype":"venue"
},
  "geometry": {"coordinates":[-0.283228,51.339272],"type":"Point"}
}