{
  "type": "Feature",
  "properties": {
    "addr:full":"Bloomsbury House London Greater London WC1B 3DA",
    "addr:postcode":"wc1b 3da",
    "iso:country":"GB",
    "sg:address":"Bloomsbury House",
    "sg:city":"London",
    "sg:classifiers":[
        {
            "category":"Organizations",
            "subcategory":"Non-profit Organization",
            "type":"Services"
        }
    ],
    "sg:phone":"+44 20 7612 0730",
    "sg:postcode":"WC1B 3DA",
    "sg:province":"Greater London",
    "sg:tags":[
        "organisation",
        "voluntary",
        "charity"
    ],
    "wof:name":"Contemporary Art Society Projects Ltd.",
    "wof:placetype":"venue"
},
  "geometry": {"coordinates":[-0.0879139975,51.5073699951],"type":"Point"}
}