{
  "type": "Feature",
  "properties": {
    "iso:country":"GB",
    "sg:address":"Omnibus Business Centre, 39-41 North Road",
    "sg:city":"London",
    "sg:classifiers":[
        {
            "category":"Shopping",
            "subcategory":"Discount & Variety Stores",
            "type":"Retail Goods"
        }
    ],
    "sg:postcode":"N7 9DP",
    "sg:province":"Greater London",
    "sg:tags":[
        "shop",
        "model"
    ],
    "wof:name":"Frewer International Uk",
    "wof:placetype":"venue"
},
  "geometry": {"coordinates":[-0.120551,51.549191],"type":"Point"}
}