{
  "type": "Feature",
  "properties": {
    "iso:country":"GB",
    "sg:address":"1 Oxford Rd, Denham",
    "sg:city":"Uxbridge",
    "sg:classifiers":[
        {
            "category":"Professional",
            "subcategory":"Computer Services",
            "type":"Services"
        }
    ],
    "sg:phone":"+44 1895 810066",
    "sg:postcode":"UB9 4DA",
    "sg:province":"Buckinghamshire",
    "sg:tags":[
        "system",
        "software"
    ],
    "wof:name":"Information Advantage International Ltd",
    "wof:placetype":"venue"
},
  "geometry": {"coordinates":[-0.486776,51.551662],"type":"Point"}
}