{
  "type": "Feature",
  "properties": {
    "addr:full":"31 St Margarets Street Canterbury Kent CT1 2TG",
    "addr:housenumber":"31",
    "addr:postcode":"ct1 2tg",
    "addr:street":"St Margarets Street",
    "iso:country":"GB",
    "sg:address":"31 St Margarets Street",
    "sg:city":"Canterbury",
    "sg:classifiers":[
        {
            "category":"Organizations",
            "subcategory":"Membership Organization",
            "type":"Services"
        }
    ],
    "sg:phone":"+44 1227 463393",
    "sg:postcode":"CT1 2TG",
    "sg:province":"Kent",
    "sg:tags":[
        "club"
    ],
    "wof:name":"East Kent & Canterbury Conservative Club",
    "wof:placetype":"venue"
},
  "geometry": {"coordinates":[1.079866,51.278381],"type":"Point"}
}