{
  "type": "Feature",
  "properties": {
    "addr:full":"89b Lynchford Road Farnborough Hampshire GU14 6ET",
    "addr:housenumber":"89b",
    "addr:postcode":"gu14 6et",
    "addr:street":"Lynchford Road",
    "iso:country":"GB",
    "sg:address":"89b Lynchford Road",
    "sg:city":"Farnborough",
    "sg:classifiers":[
        {
            "category":"Organizations",
            "subcategory":"Membership Organization",
            "type":"Services"
        }
    ],
    "sg:postcode":"GU14 6ET",
    "sg:province":"Hampshire",
    "sg:tags":[
        "club"
    ],
    "wof:name":"Courtney Randall Agency Ltd",
    "wof:placetype":"venue"
},
  "geometry": {"coordinates":[-0.746851,51.274857],"type":"Point"}
}