{
  "type": "Feature",
  "properties": {
    "addr:full":"Cornerfields, Hollybush Lane, Denham Uxbridge Buckinghamshire UB9 4HB",
    "addr:postcode":"ub9 4hb",
    "addr:street":"Hollybush Lane",
    "iso:country":"GB",
    "sg:address":"Cornerfields, Hollybush Lane, Denham",
    "sg:city":"Uxbridge",
    "sg:classifiers":[
        {
            "category":"Farming",
            "subcategory":"Livestock Farm",
            "type":"Manufacturing & Wholesale Goods"
        }
    ],
    "sg:phone":"+44 1895 832780",
    "sg:postcode":"UB9 4HB",
    "sg:province":"Buckinghamshire",
    "sg:tags":[
        "others"
    ],
    "wof:name":"T Harding",
    "wof:placetype":"venue"
},
  "geometry": {"coordinates":[-0.5089,51.558399],"type":"Point"}
}