{
  "type": "Feature",
  "properties": {
    "iso:country":"GB",
    "sg:address":"Newquay Drive, Lower Earley",
    "sg:city":"Reading",
    "sg:classifiers":[
        {
            "category":"Health Services",
            "subcategory":"Nursing And Care Facility",
            "type":"Services"
        },
        {
            "category":"Organizations",
            "subcategory":"Community Association",
            "type":"Services"
        }
    ],
    "sg:phone":"+44 118 987 5145",
    "sg:postcode":"RG6 4EJ",
    "sg:province":"Berkshire",
    "sg:tags":[
        "co-operatives",
        "society",
        "housing",
        "trust",
        "home"
    ],
    "wof:name":"Rowan Court",
    "wof:placetype":"venue"
},
  "geometry": {"coordinates":[-0.9303789735,51.4207763672],"type":"Point"}
}