{
  "type": "Feature",
  "properties": {
    "addr:full":"13a Star Chambers, Splott Rd Bridge, Splott Cardiff Cardiff CF24 2BU",
    "addr:housenumber":"13a",
    "addr:postcode":"cf24 2bu",
    "addr:street":"Splott Rd Bridge",
    "iso:country":"GB",
    "sg:address":"13a Star Chambers, Splott Rd Bridge, Splott",
    "sg:city":"Cardiff",
    "sg:classifiers":[
        {
            "category":"Professional",
            "subcategory":"Lawyer & Legal Services",
            "type":"Services"
        }
    ],
    "sg:phone":"+44 29 2045 5401",
    "sg:postcode":"CF24 2BU",
    "sg:province":"Cardiff",
    "sg:tags":[
        "solicitor"
    ],
    "wof:name":"Mordey & Co",
    "wof:placetype":"venue"
},
  "geometry": {"coordinates":[-3.1510539055,51.4831504822],"type":"Point"}
}