{
  "type": "Feature",
  "properties": {
    "addr:full":"182 Garratt Lane London Greater London SW18 4ED",
    "addr:housenumber":"182",
    "addr:postcode":"sw18 4ed",
    "addr:street":"Garratt Lane",
    "iso:country":"GB",
    "sg:address":"182 Garratt Lane",
    "sg:city":"London",
    "sg:classifiers":[
        {
            "category":"Food & Beverages",
            "subcategory":"Candy",
            "type":"Retail Goods"
        }
    ],
    "sg:phone":"+44 20 8874 4265",
    "sg:postcode":"SW18 4ED",
    "sg:province":"Greater London",
    "sg:tags":[
        "confectioner"
    ],
    "wof:name":"Humphrey H & Ellen Ballard",
    "wof:placetype":"venue"
},
  "geometry": {"coordinates":[-0.1896740049,51.4480438232],"type":"Point"}
}