{
  "type": "Feature",
  "properties": {
    "addr:full":"Alcoa House, Regal Road Stratford-upon-avon Warwickshire CV37 0ED",
    "addr:postcode":"cv37 0ed",
    "addr:street":"Regal Road",
    "iso:country":"GB",
    "sg:address":"Alcoa House, Regal Road",
    "sg:city":"Stratford-upon-avon",
    "sg:classifiers":[
        {
            "category":"Wholesale",
            "subcategory":"Metals & Minerals",
            "type":"Manufacturing & Wholesale Goods"
        }
    ],
    "sg:phone":"+44 1789 268923",
    "sg:postcode":"CV37 0ED",
    "sg:province":"Warwickshire",
    "sg:tags":[
        "aluminium",
        "stockholder"
    ],
    "wof:name":"Alcoa Systems (U K) Ltd.",
    "wof:placetype":"venue"
},
  "geometry": {"coordinates":[-1.711093,52.199341],"type":"Point"}
}