{
  "type": "Feature",
  "properties": {
    "addr:full":"19 Marian Croft Birmingham West Midlands B26 3LZ",
    "addr:housenumber":"19",
    "addr:postcode":"b26 3lz",
    "addr:street":"Marian Croft",
    "iso:country":"GB",
    "sg:address":"19 Marian Croft",
    "sg:city":"Birmingham",
    "sg:classifiers":[
        {
            "category":"Professional",
            "subcategory":"Engineering",
            "type":"Services"
        },
        {
            "category":"Building & Trades",
            "subcategory":"Electrical",
            "type":"Services"
        }
    ],
    "sg:phone":"+44 121 743 0781",
    "sg:postcode":"B26 3LZ",
    "sg:province":"West Midlands",
    "sg:tags":[
        "engineer",
        "electrician",
        "contractor"
    ],
    "wof:name":"T F McCabe",
    "wof:placetype":"venue"
},
  "geometry": {"coordinates":[-1.771822,52.453964],"type":"Point"}
}