{
  "type": "Feature",
  "properties": {
    "addr:full":"150 Cambridge Road, Great Shelford Cambridge Cambridgeshire CB2 5JU",
    "addr:housenumber":"150",
    "addr:postcode":"cb2 5ju",
    "addr:street":"Cambridge Road",
    "iso:country":"GB",
    "sg:address":"150 Cambridge Road, Great Shelford",
    "sg:city":"Cambridge",
    "sg:classifiers":[
        {
            "category":"Building & Trades",
            "subcategory":"Plumbing",
            "type":"Services"
        }
    ],
    "sg:phone":"+44 1223 842033",
    "sg:postcode":"CB2 5JU",
    "sg:province":"Cambridgeshire",
    "sg:tags":[
        "heating"
    ],
    "wof:name":"G H Whalley",
    "wof:placetype":"venue"
},
  "geometry": {"coordinates":[0.124733,52.16116],"type":"Point"}
}