{
  "type": "Feature",
  "properties": {
    "addr:full":"The Vicarage, Church Lane Alderley Edge Cheshire SK9 7UZ",
    "addr:postcode":"sk9 7uz",
    "addr:street":"Church Lane",
    "iso:country":"GB",
    "sg:address":"The Vicarage, Church Lane",
    "sg:city":"Alderley Edge",
    "sg:classifiers":[
        {
            "category":"Place Of Worship",
            "type":"Public Place"
        }
    ],
    "sg:phone":"+44 1625 583249",
    "sg:postcode":"SK9 7UZ",
    "sg:province":"Cheshire",
    "wof:name":"St Philip's Church",
    "wof:placetype":"venue"
},
  "geometry": {"coordinates":[-2.238894,53.304138],"type":"Point"}
}