{
  "type": "Feature",
  "properties": {
    "iso:country":"GB",
    "sg:address":"Shop 1 Richards Court, 8 Lower Bore Street",
    "sg:city":"Bodmin",
    "sg:classifiers":[
        {
            "category":"Retail",
            "subcategory":"Repair Shop",
            "type":"Services"
        }
    ],
    "sg:postcode":"PL31 2JS",
    "sg:province":"Cornwall",
    "sg:tags":[
        "upholsterer"
    ],
    "wof:name":"Richard Hollister Upholsterer",
    "wof:placetype":"venue"
},
  "geometry": {"coordinates":[-4.716369,50.471046],"type":"Point"}
}