{
  "type": "Feature",
  "properties": {
    "iso:country":"GB",
    "sg:address":"112 High Street",
    "sg:city":"Burntisland",
    "sg:classifiers":[
        {
            "category":"Arena",
            "subcategory":"Sports Club",
            "type":"Entertainment"
        }
    ],
    "sg:postcode":"KY3 9AS",
    "sg:province":"Fife",
    "sg:tags":[
        "ground"
    ],
    "wof:name":"Burntisland Recreation Co. Ltd.",
    "wof:placetype":"venue"
},
  "geometry": {"coordinates":[-3.233583,56.059238],"type":"Point"}
}