{
  "type": "Feature",
  "properties": {
    "addr:full":"9 Christchurch Road Ringwood Dorset BH24 1DG",
    "addr:housenumber":"9",
    "addr:postcode":"bh24 1dg",
    "addr:street":"Christchurch Road",
    "iso:country":"GB",
    "sg:address":"9 Christchurch Road",
    "sg:city":"Ringwood",
    "sg:classifiers":[
        {
            "category":"Shopping",
            "subcategory":"Florist",
            "type":"Retail Goods"
        }
    ],
    "sg:phone":"+44 1425 473849",
    "sg:postcode":"BH24 1DG",
    "sg:province":"Dorset",
    "wof:name":"Patricia's",
    "wof:placetype":"venue"
},
  "geometry": {"coordinates":[-1.7908140421,50.8458557129],"type":"Point"}
}