{
  "type": "Feature",
  "properties": {
    "iso:country":"GB",
    "sg:address":"211 Allison Street",
    "sg:city":"Glasgow",
    "sg:classifiers":[
        {
            "category":"Food & Beverages",
            "subcategory":"Meat & Fish",
            "type":"Retail Goods"
        }
    ],
    "sg:phone":"+44 141 424 1668",
    "sg:postcode":"G42 8RU",
    "sg:province":"Glasgow City",
    "sg:tags":[
        "butcher"
    ],
    "wof:name":"A A Continential Stores",
    "wof:placetype":"venue"
},
  "geometry": {"coordinates":[-4.2617688179,55.8362731934],"type":"Point"}
}