{
  "type": "Feature",
  "properties": {
    "addr:full":"12 Fothergill Street, Treforest Pontypridd Caerphilly CF37 1SG",
    "addr:housenumber":"12",
    "addr:postcode":"cf37 1sg",
    "addr:street":"Fothergill Street",
    "iso:country":"GB",
    "sg:address":"12 Fothergill Street, Treforest",
    "sg:city":"Pontypridd",
    "sg:classifiers":[
        {
            "category":"Professional",
            "subcategory":"Accounting & Tax Preparation",
            "type":"Services"
        }
    ],
    "sg:phone":"+44 1443 402394",
    "sg:postcode":"CF37 1SG",
    "sg:province":"Caerphilly",
    "sg:tags":[
        "accountant"
    ],
    "wof:name":"Leach &Co",
    "wof:placetype":"venue"
},
  "geometry": {"coordinates":[-3.3257548809,51.5947341919],"type":"Point"}
}