{
  "type": "Feature",
  "properties": {
    "addr:full":"159 Blendon Road Bexley Kent DA5 1BT",
    "addr:housenumber":"159",
    "addr:postcode":"da5 1bt",
    "addr:street":"Blendon Road",
    "iso:country":"GB",
    "sg:address":"159 Blendon Road",
    "sg:city":"Bexley",
    "sg:classifiers":[
        {
            "category":"Professional",
            "subcategory":"Accounting & Tax Preparation",
            "type":"Services"
        }
    ],
    "sg:phone":"+44 20 8298 7808",
    "sg:postcode":"DA5 1BT",
    "sg:province":"Kent",
    "sg:tags":[
        "accountant"
    ],
    "wof:name":"P J Carlton & Co",
    "wof:placetype":"venue"
},
  "geometry": {"coordinates":[0.1208240017,51.4480209351],"type":"Point"}
}