{
  "type": "Feature",
  "properties": {
    "addr:full":"133 St Johns Way London Greater London N19 3RQ",
    "addr:housenumber":"133",
    "addr:postcode":"n19 3rq",
    "addr:street":"St Johns Way",
    "iso:country":"GB",
    "sg:address":"133 St Johns Way",
    "sg:city":"London",
    "sg:classifiers":[
        {
            "category":"Social Services",
            "subcategory":"Adult Care",
            "type":"Services"
        }
    ],
    "sg:phone":"+44 20 7263 3537",
    "sg:postcode":"N19 3RQ",
    "sg:province":"Greater London",
    "sg:tags":[
        "day",
        "centre"
    ],
    "wof:name":"St Johns Day Centre",
    "wof:placetype":"venue"
},
  "geometry": {"coordinates":[-0.1302700043,51.5692825317],"type":"Point"}
}