{
  "type": "Feature",
  "properties": {
    "iso:country":"GB",
    "sg:address":"Wishaw Lane, Hunts Grn, Middleton",
    "sg:city":"Tamworth",
    "sg:classifiers":[
        {
            "category":"Farming",
            "subcategory":"Nursery",
            "type":"Manufacturing & Wholesale Goods"
        },
        {
            "category":"Home & Garden",
            "subcategory":"Garden Supply",
            "type":"Retail Goods"
        }
    ],
    "sg:phone":"+44 121 311 1421",
    "sg:postcode":"B78 2AX",
    "sg:province":"Staffordshire",
    "sg:tags":[
        "centre"
    ],
    "wof:name":"Atlantic Nurseries Wholesale",
    "wof:placetype":"venue"
},
  "geometry": {"coordinates":[-1.739399,52.582394],"type":"Point"}
}