{
  "type": "Feature",
  "properties": {
    "iso:country":"GB",
    "sg:address":"19 Greenwood Pl",
    "sg:city":"London",
    "sg:classifiers":[
        {
            "category":"Professional",
            "subcategory":"Computer Services",
            "type":"Services"
        }
    ],
    "sg:postcode":"NW5 1LB",
    "sg:province":"Greater London",
    "sg:tags":[
        "system",
        "software"
    ],
    "wof:name":"Argent Computer Services",
    "wof:placetype":"venue"
},
  "geometry": {"coordinates":[-0.1431909949,51.5527915955],"type":"Point"}
}