{
  "type": "Feature",
  "properties": {
    "addr:full":"17 Rhodes Street North Hyde Cheshire SK14 2BR",
    "addr:housenumber":"17",
    "addr:postcode":"sk14 2br",
    "addr:street":"Rhodes Street North Hyde",
    "iso:country":"GB",
    "sg:address":"17 Rhodes Street North",
    "sg:city":"Hyde",
    "sg:classifiers":[
        {
            "category":"Building & Trades",
            "subcategory":"Construction",
            "type":"Services"
        }
    ],
    "sg:phone":"+44 161 366 1933",
    "sg:postcode":"SK14 2BR",
    "sg:province":"Cheshire",
    "sg:tags":[
        "decorator",
        "painter"
    ],
    "wof:name":"Strip-It",
    "wof:placetype":"venue"
},
  "geometry": {"coordinates":[-2.088759,53.453285],"type":"Point"}
}