{
  "type": "Feature",
  "properties": {
    "addr:full":"168 Walmersley Road Bury Lancashire BL9 6LL",
    "addr:housenumber":"168",
    "addr:postcode":"bl9 6ll",
    "addr:street":"Walmersley Road",
    "iso:country":"GB",
    "sg:address":"168 Walmersley Road",
    "sg:city":"Bury",
    "sg:classifiers":[
        {
            "category":"Professional",
            "subcategory":"Business Services",
            "type":"Services"
        }
    ],
    "sg:phone":"+44 161 761 1252",
    "sg:postcode":"BL9 6LL",
    "sg:province":"Lancashire",
    "sg:tags":[
        "bookmaker"
    ],
    "wof:name":"Tote Bookmakers Ltd.",
    "wof:placetype":"venue"
},
  "geometry": {"coordinates":[-2.2902081013,53.6016807556],"type":"Point"}
}