{
  "type": "Feature",
  "properties": {
    "addr:full":"Lucre House Derby Derbyshire DE22 3FQ",
    "addr:housenumber":"lucre",
    "addr:postcode":"de22 3fq",
    "iso:country":"GB",
    "sg:address":"Lucre House",
    "sg:city":"Derby",
    "sg:classifiers":[
        {
            "category":"Professional",
            "subcategory":"Accounting & Tax Preparation",
            "type":"Services"
        }
    ],
    "sg:postcode":"DE22 3FQ",
    "sg:province":"Derbyshire",
    "sg:tags":[
        "accountant"
    ],
    "wof:name":"Accountancy & Advice for Small Businesses Ltd.",
    "wof:placetype":"venue"
},
  "geometry": {"coordinates":[-1.49205,52.92548],"type":"Point"}
}