{
  "type": "Feature",
  "properties": {
    "iso:country":"GB",
    "sg:address":"Ocean Road",
    "sg:city":"South Shields",
    "sg:classifiers":[
        {
            "category":"Bars & Pubs",
            "type":"Food & Drink"
        },
        {
            "category":"Community Center",
            "subcategory":"Social",
            "type":"Public Place"
        }
    ],
    "sg:phone":"+44 191 454 7654",
    "sg:postcode":"NE33 2HT",
    "sg:province":"Tyne and Wear",
    "sg:tags":[
        "pubs",
        "house",
        "inn",
        "activity"
    ],
    "wof:name":"Kirkpatricks",
    "wof:placetype":"venue"
},
  "geometry": {"coordinates":[-1.4249989986,55.0003814697],"type":"Point"}
}