{
  "type": "Feature",
  "properties": {
    "addr:full":"2 Glencathara Rd Bognor Regis West Sussex PO21 2SF",
    "addr:housenumber":"2",
    "addr:postcode":"po21 2sf",
    "addr:street":"Glencathara Rd",
    "iso:country":"GB",
    "sg:address":"2 Glencathara Rd",
    "sg:city":"Bognor Regis",
    "sg:classifiers":[
        {
            "category":"Manufacturing",
            "subcategory":"Building Materials",
            "type":"Manufacturing & Wholesale Goods"
        }
    ],
    "sg:phone":"+44 1243 868850",
    "sg:postcode":"PO21 2SF",
    "sg:province":"West Sussex",
    "sg:tags":[
        "stonemason"
    ],
    "wof:name":"D M Gibson Stonemasonry",
    "wof:placetype":"venue"
},
  "geometry": {"coordinates":[-0.685678,50.783173],"type":"Point"}
}