{
  "type": "Feature",
  "properties": {
    "addr:full":"53 Boothferry Road Goole East Riding of Yorkshire DN14 5DE",
    "addr:housenumber":"53",
    "addr:postcode":"dn14 5de",
    "addr:street":"Boothferry Road",
    "iso:country":"GB",
    "sg:address":"53 Boothferry Road",
    "sg:city":"Goole",
    "sg:classifiers":[
        {
            "category":"Cafe",
            "type":"Food & Drink"
        }
    ],
    "sg:phone":"+44 1405 766110",
    "sg:postcode":"DN14 5DE",
    "sg:province":"East Riding of Yorkshire",
    "sg:tags":[
        "tea",
        "snack",
        "bar",
        "room"
    ],
    "wof:name":"THE CONTINENTAL COFFEE SHOP",
    "wof:placetype":"venue"
},
  "geometry": {"coordinates":[-0.873991,53.704502],"type":"Point"}
}