{
  "type": "Feature",
  "properties": {
    "iso:country":"GB",
    "sg:address":"Little Rait Farm",
    "sg:city":"Perth",
    "sg:classifiers":[
        {
            "category":"Shopping",
            "subcategory":"Antiques",
            "type":"Retail Goods"
        }
    ],
    "sg:phone":"+44 1821 670505",
    "sg:postcode":"PH2 7RT",
    "sg:province":"Perth and Kinross",
    "wof:name":"Sinclair Antiques",
    "wof:placetype":"venue"
},
  "geometry": {"coordinates":[-3.255414,56.426788],"type":"Point"}
}