{
  "type": "Feature",
  "properties": {
    "iso:country":"GB",
    "sg:address":"19 High Street, Pennygoes",
    "sg:city":"Caernarfon",
    "sg:classifiers":[
        {
            "category":"Shopping",
            "type":"Retail Goods"
        }
    ],
    "sg:phone":"+44 1286 880650",
    "sg:postcode":"LL54 6PL",
    "sg:province":"Gwynedd",
    "sg:tags":[
        "bag"
    ],
    "wof:name":"R & J Wholesale",
    "wof:placetype":"venue"
},
  "geometry": {"coordinates":[-4.282743,53.056541],"type":"Point"}
}