{
  "type": "Feature",
  "properties": {
    "addr:full":"Nelson Street Widnes Cheshire WA8 0QD",
    "addr:postcode":"wa8 0qd",
    "addr:street":"Nelson Street",
    "iso:country":"GB",
    "sg:address":"Nelson Street",
    "sg:city":"Widnes",
    "sg:classifiers":[
        {
            "category":"Wholesale",
            "subcategory":"Meat",
            "type":"Manufacturing & Wholesale Goods"
        }
    ],
    "sg:postcode":"WA8 0QD",
    "sg:province":"Cheshire",
    "sg:tags":[
        "-"
    ],
    "wof:name":"Hall & Roberts (Provisions) Ltd.",
    "wof:placetype":"venue"
},
  "geometry": {"coordinates":[-2.7357990742,53.356338501],"type":"Point"}
}