{
  "type": "Feature",
  "properties": {
    "addr:full":"84 High Street, Wednesfield Wolverhampton Staffordshire WV11 1SZ",
    "addr:housenumber":"84",
    "addr:postcode":"wv11 1sz",
    "addr:street":"High Street",
    "iso:country":"GB",
    "sg:address":"84 High Street, Wednesfield",
    "sg:city":"Wolverhampton",
    "sg:classifiers":[
        {
            "category":"Travel",
            "subcategory":"Travel Agent",
            "type":"Entertainment"
        }
    ],
    "sg:phone":"+44 1902 861086",
    "sg:postcode":"WV11 1SZ",
    "sg:province":"Staffordshire",
    "wof:name":"Co-Op Travel Ltd.",
    "wof:placetype":"venue"
},
  "geometry": {"coordinates":[-2.082775,52.599644],"type":"Point"}
}