{
  "type": "Feature",
  "properties": {
    "iso:country":"GB",
    "sg:address":"27 King John Road, Kingsclere",
    "sg:city":"Newbury",
    "sg:classifiers":[
        {
            "category":"Home & Garden",
            "subcategory":"Household Appliances",
            "type":"Retail Goods"
        }
    ],
    "sg:phone":"+44 1635 298300",
    "sg:postcode":"RG20 5NJ",
    "sg:province":"Berkshire",
    "sg:tags":[
        "electrical"
    ],
    "wof:name":"R D F",
    "wof:placetype":"venue"
},
  "geometry": {"coordinates":[-1.2442890406,51.3235816956],"type":"Point"}
}