{
  "type": "Feature",
  "properties": {
    "addr:full":"The Plassey Wrexham Wrexham LL13 0SP",
    "addr:postcode":"ll13 0sp",
    "iso:country":"GB",
    "sg:address":"The Plassey",
    "sg:city":"Wrexham",
    "sg:classifiers":[
        {
            "category":"Shopping",
            "subcategory":"Hobbies, Toys, & Games",
            "type":"Retail Goods"
        }
    ],
    "sg:phone":"+44 1978 780706",
    "sg:postcode":"LL13 0SP",
    "sg:province":"Wrexham",
    "sg:tags":[
        "collectors'",
        "item"
    ],
    "wof:name":"Palethorpe Bears",
    "wof:placetype":"venue"
},
  "geometry": {"coordinates":[-2.9620740414,53.0244789124],"type":"Point"}
}