{
  "type": "Feature",
  "properties": {
    "iso:country":"GB",
    "sg:address":"Montgomery Way",
    "sg:city":"Biggleswade",
    "sg:classifiers":[
        {
            "category":"Professional",
            "type":"Services"
        }
    ],
    "sg:phone":"+44 1767 316610",
    "sg:postcode":"SG18 8UB",
    "sg:province":"Bedfordshire",
    "sg:tags":[
        "services",
        "belt",
        "conveyor"
    ],
    "wof:name":"Alma Engineering Co. Ltd.",
    "wof:placetype":"venue"
},
  "geometry": {"coordinates":[-0.240353,52.074581],"type":"Point"}
}