{
  "type": "Feature",
  "properties": {
    "addr:full":"Rear Of 9 & 10 Kensington Place, London Road Bath Bath and North East Somerset BA1 6AW",
    "addr:housenumber":"rear of 9 & 10",
    "addr:postcode":"ba1 6aw",
    "addr:street":"Kensington Place London Road",
    "iso:country":"GB",
    "sg:address":"Rear Of 9 & 10 Kensington Place, London Road",
    "sg:city":"Bath",
    "sg:classifiers":[
        {
            "category":"Communications",
            "subcategory":"Film & Video Production",
            "type":"Services"
        },
        {
            "category":"Wholesale",
            "subcategory":"Machinery & Supplies",
            "type":"Manufacturing & Wholesale Goods"
        },
        {
            "category":"Communications",
            "type":"Services"
        }
    ],
    "sg:phone":"+44 1225 315617",
    "sg:postcode":"BA1 6AW",
    "sg:province":"Bath and North East Somerset",
    "sg:tags":[
        "theatrical",
        "system",
        "recording",
        "studio",
        "address",
        "music",
        "public"
    ],
    "wof:name":"Production Electrics",
    "wof:placetype":"venue"
},
  "geometry": {"coordinates":[-2.3506100178,51.3923988342],"type":"Point"}
}