{
  "type": "Feature",
  "properties": {
    "addr:full":"Bridge Works, Iver Lane Uxbridge Buckinghamshire UB8 2JF",
    "addr:postcode":"ub8 2jf",
    "addr:street":"Iver Lane",
    "iso:country":"GB",
    "sg:address":"Bridge Works, Iver Lane",
    "sg:city":"Uxbridge",
    "sg:classifiers":[
        {
            "category":"Manufacturing",
            "subcategory":"Wood Products",
            "type":"Manufacturing & Wholesale Goods"
        }
    ],
    "sg:phone":"+44 1895 230111",
    "sg:postcode":"UB8 2JF",
    "sg:province":"Buckinghamshire",
    "sg:tags":[
        "packaging",
        "crate",
        "pallets"
    ],
    "wof:name":"Contour Packaging International Ltd.",
    "wof:placetype":"venue"
},
  "geometry": {"coordinates":[-0.474536,51.544071],"type":"Point"}
}