{
  "type": "Feature",
  "properties": {
    "iso:country":"GB",
    "sg:address":"181 Whiteladies Road, Clifton",
    "sg:city":"Bristol",
    "sg:classifiers":[
        {
            "category":"Organizations",
            "subcategory":"Membership Organization",
            "type":"Services"
        }
    ],
    "sg:postcode":"BS8 2RY",
    "sg:province":"City of Bristol",
    "sg:tags":[
        "club"
    ],
    "wof:name":"14, 15 Royal Park (Management) Limited",
    "wof:placetype":"venue"
},
  "geometry": {"coordinates":[-2.6139190197,51.4691314697],"type":"Point"}
}