{
  "type": "Feature",
  "properties": {
    "iso:country":"GB",
    "sg:address":"24 Newmarket St",
    "sg:city":"Falkirk",
    "sg:classifiers":[
        {
            "category":"Real Estate",
            "subcategory":"Real Estate Agent",
            "type":"Services"
        }
    ],
    "sg:postcode":"FK1 1JQ",
    "sg:province":"Falkirk",
    "wof:name":"Edinburgh Solicitors Property Centre Ltd",
    "wof:placetype":"venue"
},
  "geometry": {"coordinates":[-3.785515,56.000893],"type":"Point"}
}