{
  "type": "Feature",
  "properties": {
    "iso:country":"GB",
    "sg:address":"Old Lake Road",
    "sg:city":"Ambleside",
    "sg:classifiers":[
        {
            "category":"Manufacturing",
            "subcategory":"Textiles",
            "type":"Manufacturing & Wholesale Goods"
        }
    ],
    "sg:phone":"+44 15394 32445",
    "sg:postcode":"LA22 0DH",
    "sg:province":"Cumbria",
    "sg:tags":[
        "made-up"
    ],
    "wof:name":"Lakeland Sweaters Ltd.",
    "wof:placetype":"venue"
},
  "geometry": {"coordinates":[-2.9619789124,54.429359436],"type":"Point"}
}