{
  "type": "Feature",
  "properties": {
    "addr:full":"5 James Street Morecambe Lancashire LA4 5TE",
    "addr:housenumber":"5",
    "addr:postcode":"la4 5te",
    "addr:street":"James Street",
    "iso:country":"GB",
    "sg:address":"5 James Street",
    "sg:city":"Morecambe",
    "sg:classifiers":[
        {
            "category":"Health Services",
            "subcategory":"Doctor",
            "type":"Services"
        }
    ],
    "sg:phone":"+44 1524 831111",
    "sg:postcode":"LA4 5TE",
    "sg:province":"Lancashire",
    "sg:tags":[
        "practitioners"
    ],
    "wof:name":"York Bridge Surgery",
    "wof:placetype":"venue"
},
  "geometry": {"coordinates":[-2.855851,54.070461],"type":"Point"}
}