{
  "type": "Feature",
  "properties": {
    "addr:full":"Unit 19 Monks Brook Indstl Pk, Chandlers Ford Eastleigh Hampshire SO53 4RA",
    "addr:housenumber":"unit 19",
    "addr:postcode":"so53 4ra",
    "addr:street":"Monks Brook Indstl Pk Chandlers",
    "iso:country":"GB",
    "sg:address":"Unit 19 Monks Brook Indstl Pk, Chandlers Ford",
    "sg:city":"Eastleigh",
    "sg:classifiers":[
        {
            "category":"Shopping",
            "subcategory":"Mobile Phones",
            "type":"Retail Goods"
        }
    ],
    "sg:postcode":"SO53 4RA",
    "sg:province":"Hampshire",
    "wof:name":"Southern Cellular Services",
    "wof:placetype":"venue"
},
  "geometry": {"coordinates":[-1.395442,50.98222],"type":"Point"}
}