{
  "type": "Feature",
  "properties": {
    "addr:full":"10a Capel Rd London Greater London E7 0JD",
    "addr:housenumber":"10a",
    "addr:postcode":"e7 0jd",
    "addr:street":"Capel Rd",
    "iso:country":"GB",
    "sg:address":"10a Capel Rd",
    "sg:city":"London",
    "sg:classifiers":[
        {
            "category":"Retail",
            "subcategory":"Auto Repair",
            "type":"Services"
        }
    ],
    "sg:postcode":"E7 0JD",
    "sg:province":"Greater London",
    "sg:tags":[
        "modification",
        "garage"
    ],
    "wof:name":"Patel,I,",
    "wof:placetype":"venue"
},
  "geometry": {"coordinates":[0.0292700008,51.554309845],"type":"Point"}
}