{
  "type": "Feature",
  "properties": {
    "addr:full":"84 High Road, Beeston Nottingham Nottinghamshire NG9 2LF",
    "addr:housenumber":"84",
    "addr:postcode":"ng9 2lf",
    "addr:street":"High Road",
    "iso:country":"GB",
    "sg:address":"84 High Road, Beeston",
    "sg:city":"Nottingham",
    "sg:classifiers":[
        {
            "category":"Professional",
            "subcategory":"Accounting & Tax Preparation",
            "type":"Services"
        }
    ],
    "sg:phone":"+44 115 922 2419",
    "sg:postcode":"NG9 2LF",
    "sg:province":"Nottinghamshire",
    "sg:tags":[
        "accountant"
    ],
    "wof:name":"Belvat Services",
    "wof:placetype":"venue"
},
  "geometry": {"coordinates":[-1.2126630545,52.9284172058],"type":"Point"}
}