{
  "type": "Feature",
  "properties": {
    "addr:full":"68 Brookhouse Hill Sheffield South Yorkshire S10 3TB",
    "addr:housenumber":"68",
    "addr:postcode":"s10 3tb",
    "addr:street":"Brookhouse Hill",
    "iso:country":"GB",
    "sg:address":"68 Brookhouse Hill",
    "sg:city":"Sheffield",
    "sg:classifiers":[
        {
            "category":"Home & Garden",
            "subcategory":"Household Appliances",
            "type":"Retail Goods"
        }
    ],
    "sg:postcode":"S10 3TB",
    "sg:province":"South Yorkshire",
    "sg:tags":[
        "electrical"
    ],
    "wof:name":"Asbery Washing Machine Repairs",
    "wof:placetype":"venue"
},
  "geometry": {"coordinates":[-1.5442320108,53.3647842407],"type":"Point"}
}