{
  "type": "Feature",
  "properties": {
    "iso:country":"GB",
    "sg:address":"Westmoor Lane, Hambridge",
    "sg:city":"Langport",
    "sg:classifiers":[
        {
            "category":"Retail",
            "subcategory":"Repair Shop",
            "type":"Services"
        },
        {
            "category":"Manufacturing",
            "subcategory":"Furniture",
            "type":"Manufacturing & Wholesale Goods"
        }
    ],
    "sg:phone":"+44 1460 281535",
    "sg:postcode":"TA10 0AS",
    "sg:province":"Somerset",
    "sg:tags":[
        "restored"
    ],
    "wof:name":"Westmoor Furniture",
    "wof:placetype":"venue"
},
  "geometry": {"coordinates":[-2.862154,50.991169],"type":"Point"}
}