{
  "type": "Feature",
  "properties": {
    "addr:full":"The Postings Kirkcaldy Fife KY1 1HN",
    "addr:postcode":"ky1 1hn",
    "addr:street":"Postings",
    "iso:country":"GB",
    "sg:address":"The Postings",
    "sg:city":"Kirkcaldy",
    "sg:classifiers":[
        {
            "category":"Home & Garden",
            "subcategory":"Household Appliances",
            "type":"Retail Goods"
        }
    ],
    "sg:phone":"+44 1592 268159",
    "sg:postcode":"KY1 1HN",
    "sg:province":"Fife",
    "sg:tags":[
        "electrical",
        "domestic"
    ],
    "wof:name":"Tandy",
    "wof:placetype":"venue"
},
  "geometry": {"coordinates":[-3.1630289555,56.1095962524],"type":"Point"}
}