{
  "type": "Feature",
  "properties": {
    "addr:full":"Yew Tree House, Pedlinge Hythe Kent CT21 4JL",
    "addr:postcode":"ct21 4jl",
    "addr:street":"Yew;Pedlinge",
    "iso:country":"GB",
    "sg:address":"Yew Tree House, Pedlinge",
    "sg:city":"Hythe",
    "sg:classifiers":[
        {
            "category":"Shopping",
            "subcategory":"Clothing, Apparel, & Fashions",
            "type":"Retail Goods"
        }
    ],
    "sg:phone":"+44 1303 265535",
    "sg:postcode":"CT21 4JL",
    "sg:province":"Kent",
    "sg:tags":[
        "shop",
        "dress",
        "outlet",
        "fancy"
    ],
    "wof:name":"Annie Owen Costume Hire",
    "wof:placetype":"venue"
},
  "geometry": {"coordinates":[1.054015,51.078403],"type":"Point"}
}