{
  "type": "Feature",
  "properties": {
    "addr:full":"19 Broad Street Bury Lancashire BL9 0DA",
    "addr:housenumber":"19",
    "addr:postcode":"bl9 0da",
    "addr:street":"Broad Street",
    "iso:country":"GB",
    "sg:address":"19 Broad Street",
    "sg:city":"Bury",
    "sg:classifiers":[
        {
            "category":"Travel",
            "subcategory":"Travel Agent",
            "type":"Entertainment"
        }
    ],
    "sg:phone":"+44 161 764 2910",
    "sg:postcode":"BL9 0DA",
    "sg:province":"Lancashire",
    "wof:name":"Estelle Travel Centre",
    "wof:placetype":"venue"
},
  "geometry": {"coordinates":[-2.2975769043,53.5925521851],"type":"Point"}
}