{
  "type": "Feature",
  "properties": {
    "addr:full":"41 Market Place Bishop Auckland Durham DL14 7PB",
    "addr:housenumber":"41",
    "addr:postcode":"dl14 7pb",
    "addr:street":"Market Place",
    "iso:country":"GB",
    "sg:address":"41 Market Place",
    "sg:city":"Bishop Auckland",
    "sg:classifiers":[
        {
            "category":"Travel",
            "subcategory":"Hotels & Motels",
            "type":"Entertainment"
        }
    ],
    "sg:phone":"+44 1388 458322",
    "sg:postcode":"DL14 7PB",
    "sg:province":"Durham",
    "wof:name":"The Castle Hotel",
    "wof:placetype":"venue"
},
  "geometry": {"coordinates":[-1.6742529869,54.6654701233],"type":"Point"}
}