{
  "type": "Feature",
  "properties": {
    "addr:full":"18 The Forum Sittingbourne Kent ME10 3DL",
    "addr:housenumber":"18",
    "addr:postcode":"me10 3dl",
    "addr:street":"The Forum",
    "iso:country":"GB",
    "sg:address":"18 The Forum",
    "sg:city":"Sittingbourne",
    "sg:classifiers":[
        {
            "category":"Shopping",
            "subcategory":"News",
            "type":"Retail Goods"
        }
    ],
    "sg:phone":"+44 1795 476300",
    "sg:postcode":"ME10 3DL",
    "sg:province":"Kent",
    "sg:tags":[
        "newsagent"
    ],
    "wof:name":"John Menzies",
    "wof:placetype":"venue"
},
  "geometry": {"coordinates":[0.7479799986,51.3419914246],"type":"Point"}
}