{
  "type": "Feature",
  "properties": {
    "addr:full":"37 Huddersfield Rd, Holmfirth Huddersfield West Yorkshire HD7 1JH",
    "addr:housenumber":"37",
    "addr:postcode":"hd7 1jh",
    "addr:street":"Huddersfield Rd",
    "iso:country":"GB",
    "sg:address":"37 Huddersfield Rd, Holmfirth",
    "sg:city":"Huddersfield",
    "sg:classifiers":[
        {
            "category":"Health Services",
            "subcategory":"Dentist",
            "type":"Services"
        }
    ],
    "sg:phone":"+44 1484 686753",
    "sg:postcode":"HD7 1JH",
    "sg:province":"West Yorkshire",
    "wof:name":"J.A Edwards B.Ch.D. L.D.S.R.C.S.",
    "wof:placetype":"venue"
},
  "geometry": {"coordinates":[-1.78268,53.64695],"type":"Point"}
}