{
  "type": "Feature",
  "properties": {
    "iso:country":"GB",
    "sg:address":"Eastern Road, Farlington",
    "sg:city":"Portsmouth",
    "sg:classifiers":[
        {
            "category":"Travel",
            "subcategory":"Hotels & Motels",
            "type":"Entertainment"
        }
    ],
    "sg:phone":"+44 23 9221 9111",
    "sg:postcode":"PO6 1UN",
    "sg:province":"Hampshire",
    "wof:name":"Hilton",
    "wof:placetype":"venue"
},
  "geometry": {"coordinates":[-1.035494,50.847019],"type":"Point"}
}