{
  "type": "Feature",
  "properties": {
    "iso:country":"GB",
    "sg:address":"120 Gartocher Rd",
    "sg:city":"Glasgow",
    "sg:classifiers":[
        {
            "category":"Communications",
            "subcategory":"Film & Video Production",
            "type":"Services"
        }
    ],
    "sg:postcode":"G32 0HA",
    "sg:province":"Glasgow City",
    "sg:tags":[
        "erectors",
        "sign"
    ],
    "wof:name":"Thomas,Trevor,",
    "wof:placetype":"venue"
},
  "geometry": {"coordinates":[-4.1544380188,55.8530158997],"type":"Point"}
}