{
  "type": "Feature",
  "properties": {
    "iso:country":"GB",
    "sg:address":"123 Mansfield Road",
    "sg:city":"Chesterfield",
    "sg:classifiers":[
        {
            "category":"Shopping",
            "subcategory":"Jewelry",
            "type":"Retail Goods"
        }
    ],
    "sg:phone":"+44 1246 234348",
    "sg:postcode":"S41 0JG",
    "sg:province":"Derbyshire",
    "sg:tags":[
        "gold",
        "silversmith"
    ],
    "wof:name":"H Green",
    "wof:placetype":"venue"
},
  "geometry": {"coordinates":[-1.400413,53.217468],"type":"Point"}
}