{
  "type": "Feature",
  "properties": {
    "addr:full":"P O Box 13592 South Norwood Greater London SE25 4ZD",
    "addr:housenumber":"box 13592",
    "addr:postcode":"se25 4zd",
    "addr:street":"Norwood",
    "iso:country":"GB",
    "sg:address":"P O Box 13592",
    "sg:city":"South Norwood",
    "sg:classifiers":[
        {
            "category":"Organizations",
            "subcategory":"Religious Organization",
            "type":"Services"
        }
    ],
    "sg:phone":"+44 20 8768 1378",
    "sg:postcode":"SE25 4ZD",
    "sg:province":"Greater London",
    "sg:tags":[
        "organisation"
    ],
    "wof:name":"Rhema Christian Ministries",
    "wof:placetype":"venue"
},
  "geometry": {"coordinates":[-0.0739940032,51.3991546631],"type":"Point"}
}