{
  "type": "Feature",
  "properties": {
    "addr:full":"16 Gorse Close Rugby Warwickshire CV22 6SJ",
    "addr:housenumber":"16",
    "addr:postcode":"cv22 6sj",
    "addr:street":"Gorse Close",
    "iso:country":"GB",
    "sg:address":"16 Gorse Close",
    "sg:city":"Rugby",
    "sg:classifiers":[
        {
            "category":"Retail",
            "subcategory":"Auto Repair",
            "type":"Services"
        }
    ],
    "sg:phone":"+44 1788 536014",
    "sg:postcode":"CV22 6SJ",
    "sg:province":"Warwickshire",
    "sg:tags":[
        "car",
        "upholsterer"
    ],
    "wof:name":"Mr Klean Valeting Services",
    "wof:placetype":"venue"
},
  "geometry": {"coordinates":[-1.276722,52.362823],"type":"Point"}
}