{
  "type": "Feature",
  "properties": {
    "iso:country":"GB",
    "sg:address":"35 Ferndale Road, Waterloo",
    "sg:city":"Liverpool",
    "sg:classifiers":[
        {
            "category":"Professional",
            "subcategory":"Art Services",
            "type":"Services"
        }
    ],
    "sg:postcode":"L22 9QN",
    "sg:province":"Merseyside",
    "sg:tags":[
        "picture",
        "restoration",
        "cleaning"
    ],
    "wof:name":"G N Tudhope",
    "wof:placetype":"venue"
},
  "geometry": {"coordinates":[-3.0264599323,53.4799003601],"type":"Point"}
}