{
  "type": "Feature",
  "properties": {
    "addr:full":"37 Ventnor Gardens Whitley Bay Northumberland NE26 1QD",
    "addr:housenumber":"37",
    "addr:postcode":"ne26 1qd",
    "addr:street":"Ventnor Gardens",
    "iso:country":"GB",
    "sg:address":"37 Ventnor Gardens",
    "sg:city":"Whitley Bay",
    "sg:classifiers":[
        {
            "category":"Building & Trades",
            "subcategory":"Construction",
            "type":"Services"
        }
    ],
    "sg:phone":"+44 191 251 1970",
    "sg:postcode":"NE26 1QD",
    "sg:province":"Northumberland",
    "sg:tags":[
        "tiling",
        "contractor"
    ],
    "wof:name":"Wright Tiling",
    "wof:placetype":"venue"
},
  "geometry": {"coordinates":[-1.452216,55.048496],"type":"Point"}
}