{
  "type": "Feature",
  "properties": {
    "addr:full":"3 Market Street Barnstaple Devon EX31 1BX",
    "addr:housenumber":"3",
    "addr:postcode":"ex31 1bx",
    "addr:street":"Market Street",
    "iso:country":"GB",
    "sg:address":"3 Market Street",
    "sg:city":"Barnstaple",
    "sg:classifiers":[
        {
            "category":"Food & Beverages",
            "subcategory":"Bakery",
            "type":"Retail Goods"
        }
    ],
    "sg:postcode":"EX31 1BX",
    "sg:province":"Devon",
    "sg:tags":[
        "shop",
        "baker"
    ],
    "wof:name":"K JONES",
    "wof:placetype":"venue"
},
  "geometry": {"coordinates":[-4.059259,51.080956],"type":"Point"}
}