{
  "type": "Feature",
  "properties": {
    "addr:full":"191 Barns Road Oxford Oxfordshire OX4 3UT",
    "addr:housenumber":"191",
    "addr:postcode":"ox4 3ut",
    "addr:street":"Barns Road",
    "iso:country":"GB",
    "sg:address":"191 Barns Road",
    "sg:city":"Oxford",
    "sg:classifiers":[
        {
            "category":"Personal",
            "subcategory":"Beauty Salon",
            "type":"Services"
        }
    ],
    "sg:phone":"+44 1865 771185",
    "sg:postcode":"OX4 3UT",
    "sg:province":"Oxfordshire",
    "sg:tags":[
        "unisex",
        "hairdresser"
    ],
    "wof:name":"Hi-Lites",
    "wof:placetype":"venue"
},
  "geometry": {"coordinates":[-1.214657,51.731304],"type":"Point"}
}