{
  "type": "Feature",
  "properties": {
    "addr:full":"17 Murray Road Workington Cumbria CA14 2AD",
    "addr:housenumber":"17",
    "addr:postcode":"ca14 2ad",
    "addr:street":"Murray Road",
    "iso:country":"GB",
    "sg:address":"17 Murray Road",
    "sg:city":"Workington",
    "sg:classifiers":[
        {
            "category":"Home & Garden",
            "subcategory":"Household Appliances",
            "type":"Retail Goods"
        }
    ],
    "sg:phone":"+44 1900 601112",
    "sg:postcode":"CA14 2AD",
    "sg:province":"Cumbria",
    "sg:tags":[
        "electrical",
        "domestic"
    ],
    "wof:name":"Tandy",
    "wof:placetype":"venue"
},
  "geometry": {"coordinates":[-3.547609,54.643642],"type":"Point"}
}