{
  "type": "Feature",
  "properties": {
    "iso:country":"GB",
    "sg:address":"280a Union St",
    "sg:city":"Torquay",
    "sg:classifiers":[
        {
            "category":"Home & Garden",
            "subcategory":"Carpets & Floor Coverings",
            "type":"Retail Goods"
        }
    ],
    "sg:phone":"+44 1803 214813",
    "sg:postcode":"TQ2 5QY",
    "sg:province":"Devon",
    "sg:tags":[
        "carpets",
        "rug",
        "matting"
    ],
    "wof:name":"Carpet Merchants & Bed Centre",
    "wof:placetype":"venue"
},
  "geometry": {"coordinates":[-3.538229,50.470608],"type":"Point"}
}