{
  "type": "Feature",
  "properties": {
    "addr:full":"Stepaside Cottage, Petworth Road, Wormley Godalming Surrey GU8 5TU",
    "addr:postcode":"gu8 5tu",
    "addr:street":"Petworth Road",
    "iso:country":"GB",
    "sg:address":"Stepaside Cottage, Petworth Road, Wormley",
    "sg:city":"Godalming",
    "sg:classifiers":[
        {
            "category":"Health Services",
            "subcategory":"Health Practitioner",
            "type":"Services"
        }
    ],
    "sg:phone":"+44 1428 685777",
    "sg:postcode":"GU8 5TU",
    "sg:province":"Surrey",
    "sg:tags":[
        "homoeopathic"
    ],
    "wof:name":"van Haeften A",
    "wof:placetype":"venue"
},
  "geometry": {"coordinates":[-0.6453740001,51.1400794983],"type":"Point"}
}