{
  "type": "Feature",
  "properties": {
    "addr:full":"184 Horbury Road Wakefield West Yorkshire WF2 8BQ",
    "addr:housenumber":"184",
    "addr:postcode":"wf2 8bq",
    "addr:street":"Horbury Road",
    "iso:country":"GB",
    "sg:address":"184 Horbury Road",
    "sg:city":"Wakefield",
    "sg:classifiers":[
        {
            "category":"Shopping",
            "subcategory":"Stationery & Office Supplies",
            "type":"Retail Goods"
        },
        {
            "category":"Professional",
            "subcategory":"Printing & Photocopies",
            "type":"Services"
        }
    ],
    "sg:phone":"+44 1924 299066",
    "sg:postcode":"WF2 8BQ",
    "sg:province":"West Yorkshire",
    "sg:tags":[
        "printers'",
        "printer"
    ],
    "sg:website":"http://www.robertsgraphics.co.uk",
    "wof:name":"Roberts Graphics Ltd",
    "wof:placetype":"venue"
},
  "geometry": {"coordinates":[-1.519741,53.673069],"type":"Point"}
}