{
  "type": "Feature",
  "properties": {
    "addr:full":"9a St. Nicholas St Bodmin Cornwall PL31 1AB",
    "addr:housenumber":"9a",
    "addr:postcode":"pl31 1ab",
    "addr:street":"St. Nicholas St",
    "iso:country":"GB",
    "sg:address":"9a St. Nicholas St",
    "sg:city":"Bodmin",
    "sg:classifiers":[
        {
            "category":"Freight",
            "type":"Transportation"
        }
    ],
    "sg:postcode":"PL31 1AB",
    "sg:province":"Cornwall",
    "sg:tags":[
        "haulage",
        "road"
    ],
    "wof:name":"M R Freight",
    "wof:placetype":"venue"
},
  "geometry": {"coordinates":[-4.7187738419,50.4695930481],"type":"Point"}
}