{
  "type": "Feature",
  "properties": {
    "addr:full":"Archway House, Playford Ipswich Suffolk IP6 9DP",
    "addr:postcode":"ip6 9dp",
    "iso:country":"GB",
    "sg:address":"Archway House, Playford",
    "sg:city":"Ipswich",
    "sg:classifiers":[
        {
            "category":"Building & Trades",
            "subcategory":"Landscaping Services",
            "type":"Services"
        }
    ],
    "sg:phone":"+44 1473 624883",
    "sg:postcode":"IP6 9DP",
    "sg:province":"Suffolk",
    "sg:tags":[
        "design",
        "garden"
    ],
    "wof:name":"Viviene Gorlin",
    "wof:placetype":"venue"
},
  "geometry": {"coordinates":[1.2342380285,52.0857315063],"type":"Point"}
}