{
  "type": "Feature",
  "properties": {
    "addr:full":"Little Burton, Monkland Leominster Herefordshire HR6 9DJ",
    "addr:postcode":"hr6 9dj",
    "iso:country":"GB",
    "sg:address":"Little Burton, Monkland",
    "sg:city":"Leominster",
    "sg:classifiers":[
        {
            "category":"Building & Trades",
            "subcategory":"Cleaning & Sanitation",
            "type":"Services"
        }
    ],
    "sg:phone":"+44 1544 388297",
    "sg:postcode":"HR6 9DJ",
    "sg:province":"Herefordshire",
    "sg:tags":[
        "commercial"
    ],
    "wof:name":"Company Care Contracts Cleaners",
    "wof:placetype":"venue"
},
  "geometry": {"coordinates":[-2.792279,52.214668],"type":"Point"}
}