{
  "type": "Feature",
  "properties": {
    "addr:full":"Gorseinon Road, Penllergaer Swansea Carmarthenshire SA4 9GW",
    "addr:postcode":"sa4 9gw",
    "addr:street":"Gorseinon Road",
    "iso:country":"GB",
    "sg:address":"Gorseinon Road, Penllergaer",
    "sg:city":"Swansea",
    "sg:classifiers":[
        {
            "category":"Autos & Motor Vehicles",
            "subcategory":"Automobile Sales",
            "type":"Retail Goods"
        }
    ],
    "sg:phone":"+44 1792 899000",
    "sg:postcode":"SA4 9GW",
    "sg:province":"Carmarthenshire",
    "sg:tags":[
        "car"
    ],
    "wof:name":"Sinclair Garages Ltd.",
    "wof:placetype":"venue"
},
  "geometry": {"coordinates":[-4.0086832047,51.6707420349],"type":"Point"}
}