{
  "type": "Feature",
  "properties": {
    "addr:full":"27 Almondvale South Livingston West Lothian EH54 6NB",
    "addr:housenumber":"27",
    "addr:postcode":"eh54 6nb",
    "addr:street":"Almondvale South",
    "iso:country":"GB",
    "sg:address":"27 Almondvale South",
    "sg:city":"Livingston",
    "sg:classifiers":[
        {
            "category":"Banks & Credit Unions",
            "subcategory":"Bank",
            "type":"Services"
        }
    ],
    "sg:phone":"+44 845 765 4321",
    "sg:postcode":"EH54 6NB",
    "sg:province":"West Lothian",
    "sg:tags":[
        "financial",
        "institution"
    ],
    "wof:name":"Abbey National plc",
    "wof:placetype":"venue"
},
  "geometry": {"coordinates":[-3.5088050365,55.8842964172],"type":"Point"}
}