{
  "type": "Feature",
  "properties": {
    "iso:country":"GB",
    "sg:address":"62a Westbourne Gro",
    "sg:city":"London",
    "sg:classifiers":[
        {
            "category":"Shopping",
            "subcategory":"News",
            "type":"Retail Goods"
        }
    ],
    "sg:phone":"+44 20 7221 0032",
    "sg:postcode":"W2 5SH",
    "sg:province":"Greater London",
    "sg:tags":[
        "newsagent"
    ],
    "wof:name":"Jag Vati Newsagents & Off Licence",
    "wof:placetype":"venue"
},
  "geometry": {"coordinates":[-0.192772,51.518288],"type":"Point"}
}