{
  "type": "Feature",
  "properties": {
    "iso:country":"GB",
    "sg:address":"4 Smithfield Street",
    "sg:city":"Oswestry",
    "sg:classifiers":[
        {
            "category":"Real Estate",
            "subcategory":"Real Estate Agent",
            "type":"Services"
        }
    ],
    "sg:phone":"+44 1691 671071",
    "sg:postcode":"SY11 2EG",
    "sg:province":"Shropshire",
    "wof:name":"Malcolm & Evans Ltd.",
    "wof:placetype":"venue"
},
  "geometry": {"coordinates":[-3.0558381081,52.8575592041],"type":"Point"}
}