{
  "type": "Feature",
  "properties": {
    "addr:full":"2a Aries House, Straight Bit High Wycombe Buckinghamshire HP10 9NB",
    "addr:housenumber":"2a",
    "addr:postcode":"hp10 9nb",
    "addr:street":"Aries House Straight",
    "iso:country":"GB",
    "sg:address":"2a Aries House, Straight Bit",
    "sg:city":"High Wycombe",
    "sg:classifiers":[
        {
            "category":"Professional",
            "subcategory":"Engineering",
            "type":"Services"
        }
    ],
    "sg:phone":"+44 1628 533076",
    "sg:postcode":"HP10 9NB",
    "sg:province":"Buckinghamshire",
    "sg:tags":[
        "contractor",
        "electrical",
        "engineer"
    ],
    "wof:name":"Connect Tec Ltd.",
    "wof:placetype":"venue"
},
  "geometry": {"coordinates":[-0.710162,51.601482],"type":"Point"}
}