{
  "type": "Feature",
  "properties": {
    "addr:full":"35 Watergate Grantham Lincolnshire NG31 6NS",
    "addr:housenumber":"35",
    "addr:postcode":"ng31 6ns",
    "addr:street":"Watergate Grantham",
    "iso:country":"GB",
    "sg:address":"35 Watergate",
    "sg:city":"Grantham",
    "sg:classifiers":[
        {
            "category":"Shopping",
            "subcategory":"Clothing, Apparel, & Fashions",
            "type":"Retail Goods"
        },
        {
            "category":"Shopping",
            "subcategory":"Bridal",
            "type":"Retail Goods"
        }
    ],
    "sg:phone":"+44 1476 578668",
    "sg:postcode":"NG31 6NS",
    "sg:province":"Lincolnshire",
    "sg:tags":[
        "shop",
        "gown",
        "clothing",
        "fabric"
    ],
    "wof:name":"Busy B's Bridals",
    "wof:placetype":"venue"
},
  "geometry": {"coordinates":[-0.6450449824,52.9099884033],"type":"Point"}
}