{
  "type": "Feature",
  "properties": {
    "addr:full":"82 Front Street Newbiggin-by-the-sea Northumberland NE64 6QD",
    "addr:housenumber":"82",
    "addr:postcode":"ne64 6qd",
    "addr:street":"Front Street;Northumberland",
    "iso:country":"GB",
    "sg:address":"82 Front Street",
    "sg:city":"Newbiggin-by-the-sea",
    "sg:classifiers":[
        {
            "category":"Shopping",
            "subcategory":"Clothing, Apparel, & Fashions",
            "type":"Retail Goods"
        }
    ],
    "sg:postcode":"NE64 6QD",
    "sg:province":"Northumberland",
    "sg:tags":[
        "shop"
    ],
    "wof:name":"Chelsea Lily",
    "wof:placetype":"venue"
},
  "geometry": {"coordinates":[-1.5111199617,55.1854057312],"type":"Point"}
}