{
  "type": "Feature",
  "properties": {
    "iso:country":"GB",
    "sg:address":"8 Betley Court",
    "sg:city":"Walton-on-thames",
    "sg:classifiers":[
        {
            "category":"Education",
            "subcategory":"Music School",
            "type":"Public Place"
        }
    ],
    "sg:postcode":"KT12 3BT",
    "sg:province":"Surrey",
    "sg:tags":[
        "teacher"
    ],
    "wof:name":"Musical Keyboard Services",
    "wof:placetype":"venue"
},
  "geometry": {"coordinates":[-0.406935,51.376087],"type":"Point"}
}