{
  "type": "Feature",
  "properties": {
    "addr:full":"30 Sefton Avenue, Heaton Newcastle-upon-tyne Tyne and Wear NE6 5QR",
    "addr:housenumber":"30",
    "addr:postcode":"ne6 5qr",
    "addr:street":"Sefton Avenue",
    "iso:country":"GB",
    "sg:address":"30 Sefton Avenue, Heaton",
    "sg:city":"Newcastle-upon-tyne",
    "sg:classifiers":[
        {
            "category":"Health Services",
            "subcategory":"Health Practitioner",
            "type":"Services"
        }
    ],
    "sg:phone":"+44 191 265 0202",
    "sg:postcode":"NE6 5QR",
    "sg:province":"Tyne and Wear",
    "sg:tags":[
        "acupuncture"
    ],
    "wof:name":"Neil J Thompson",
    "wof:placetype":"venue"
},
  "geometry": {"coordinates":[-1.579005003,54.9897003174],"type":"Point"}
}