{
  "type": "Feature",
  "properties": {
    "iso:country":"GB",
    "sg:address":"East Park Farm, Roddymoor Road, Tow Law",
    "sg:city":"Bishop Auckland",
    "sg:classifiers":[
        {
            "category":"Home & Garden",
            "subcategory":"Garden Supply",
            "type":"Retail Goods"
        },
        {
            "category":"Farming",
            "subcategory":"Farm",
            "type":"Manufacturing & Wholesale Goods"
        }
    ],
    "sg:phone":"+44 1388 730390",
    "sg:postcode":"DL13 4NL",
    "sg:province":"Durham",
    "sg:tags":[
        "mixed",
        "bulb",
        "crop",
        "grower"
    ],
    "wof:name":"Frederick Whitfield",
    "wof:placetype":"venue"
},
  "geometry": {"coordinates":[-1.8152339458,54.7478561401],"type":"Point"}
}