{
  "type": "Feature",
  "properties": {
    "addr:full":"Dental Surgery, 329 Lordship Lane London Greater London N17 6AB",
    "addr:housenumber":"329",
    "addr:postcode":"n17 6ab",
    "addr:street":"Lordship Lane",
    "iso:country":"GB",
    "sg:address":"Dental Surgery, 329 Lordship Lane",
    "sg:city":"London",
    "sg:classifiers":[
        {
            "category":"Health Services",
            "subcategory":"Dentist",
            "type":"Services"
        }
    ],
    "sg:phone":"+44 20 8808 4686",
    "sg:postcode":"N17 6AB",
    "sg:province":"Greater London",
    "wof:name":"James C H Lee",
    "wof:placetype":"venue"
},
  "geometry": {"coordinates":[-0.0871800035,51.5978317261],"type":"Point"}
}