{
  "type": "Feature",
  "properties": {
    "addr:full":"2 Bullens Court Yard, Mill Lane Ashby-de-la-zouch Derbyshire LE65 1HP",
    "addr:housenumber":"2",
    "addr:postcode":"le65 1hp",
    "addr:street":"Bullens Court Yard Mill Lane",
    "iso:country":"GB",
    "sg:address":"2 Bullens Court Yard, Mill Lane",
    "sg:city":"Ashby-de-la-zouch",
    "sg:classifiers":[
        {
            "category":"Shopping",
            "subcategory":"Discount & Variety Stores",
            "type":"Retail Goods"
        }
    ],
    "sg:phone":"+44 1530 416827",
    "sg:postcode":"LE65 1HP",
    "sg:province":"Derbyshire",
    "sg:tags":[
        "shop",
        "model"
    ],
    "wof:name":"Steves Models",
    "wof:placetype":"venue"
},
  "geometry": {"coordinates":[-1.4748610258,52.7480926514],"type":"Point"}
}