{
  "type": "Feature",
  "properties": {
    "iso:country":"GB",
    "sg:address":"7 The Market, Scotch Street",
    "sg:city":"Carlisle",
    "sg:classifiers":[
        {
            "category":"Shopping",
            "subcategory":"Department Store",
            "type":"Retail Goods"
        },
        {
            "category":"Shopping",
            "subcategory":"Jewelry",
            "type":"Retail Goods"
        },
        {
            "category":"Shopping",
            "subcategory":"Comic Books",
            "type":"Retail Goods"
        }
    ],
    "sg:phone":"+44 1228 511163",
    "sg:postcode":"CA3 8QX",
    "sg:province":"Cumbria",
    "sg:tags":[
        "jeweller",
        "sale",
        "jewellery"
    ],
    "wof:name":"D & M Jewellery",
    "wof:placetype":"venue"
},
  "geometry": {"coordinates":[-2.9361689091,54.8965148926],"type":"Point"}
}