{
  "type": "Feature",
  "properties": {
    "iso:country":"GB",
    "sg:address":"Knowle House, Rotherfield Rd",
    "sg:city":"Crowborough",
    "sg:classifiers":[
        {
            "category":"Autos & Motor Vehicles",
            "subcategory":"Automobile Sales",
            "type":"Retail Goods"
        }
    ],
    "sg:phone":"+44 1892 661555",
    "sg:postcode":"TN6 3DY",
    "sg:province":"East Sussex",
    "sg:tags":[
        "commercial"
    ],
    "wof:name":"J J Autos",
    "wof:placetype":"venue"
},
  "geometry": {"coordinates":[0.1972350031,51.0461578369],"type":"Point"}
}