{
  "type": "Feature",
  "properties": {
    "addr:full":"Northern Parade Portsmouth Hampshire PO2 9LU",
    "addr:postcode":"hampshire po2 9lu",
    "addr:street":"Northern Parade",
    "iso:country":"GB",
    "sg:address":"Northern Parade",
    "sg:city":"Portsmouth",
    "sg:classifiers":[
        {
            "category":"Bars & Pubs",
            "type":"Food & Drink"
        }
    ],
    "sg:phone":"+44 23 9266 0745",
    "sg:postcode":"PO2 9LU",
    "sg:province":"Hampshire",
    "sg:tags":[
        "pubs",
        "inn"
    ],
    "wof:name":"The Oakwood",
    "wof:placetype":"venue"
},
  "geometry": {"coordinates":[-1.072524,50.833527],"type":"Point"}
}