{
  "type": "Feature",
  "properties": {
    "addr:full":"Unit 26 George Holmes Business P, K, George Holmes Way Swadlincote Derbyshire DE11 9DF",
    "addr:housenumber":"unit 26",
    "addr:postcode":"de11 9df",
    "addr:street":"George Holmes;P K George Holmes Way",
    "iso:country":"GB",
    "sg:address":"Unit 26 George Holmes Business P, K, George Holmes Way",
    "sg:city":"Swadlincote",
    "sg:classifiers":[
        {
            "category":"Building & Trades",
            "subcategory":"Construction",
            "type":"Services"
        }
    ],
    "sg:phone":"+44 1283 222081",
    "sg:postcode":"DE11 9DF",
    "sg:province":"Derbyshire",
    "sg:tags":[
        "dry",
        "lining",
        "plasterers",
        "screeders"
    ],
    "wof:name":"Hennessy Plastering & Dry Lining Contrators",
    "wof:placetype":"venue"
},
  "geometry": {"coordinates":[-1.569699049,52.7721405029],"type":"Point"}
}