{
  "type": "Feature",
  "properties": {
    "iso:country":"GB",
    "sg:address":"8 Commercial Road",
    "sg:city":"Hereford",
    "sg:classifiers":[
        {
            "category":"Retail",
            "subcategory":"Laundry & Dry Cleaning",
            "type":"Services"
        }
    ],
    "sg:phone":"+44 1432 265973",
    "sg:postcode":"HR1 2BB",
    "sg:province":"Herefordshire",
    "sg:tags":[
        "cleaner",
        "alteration"
    ],
    "wof:name":"Speedplus Dry Cleaners",
    "wof:placetype":"venue"
},
  "geometry": {"coordinates":[-2.711892,52.058006],"type":"Point"}
}