{
  "type": "Feature",
  "properties": {
    "iso:country":"GB",
    "sg:address":"Unit 4, Wellington Rd",
    "sg:city":"Folkestone",
    "sg:classifiers":[
        {
            "category":"Shopping Center",
            "type":"Public Place"
        }
    ],
    "sg:phone":"+44 1303 273111",
    "sg:postcode":"CT20 3EH",
    "sg:province":"Kent",
    "sg:tags":[
        "clutch",
        "brake",
        "centre"
    ],
    "wof:name":"Premier Clutches",
    "wof:placetype":"venue"
},
  "geometry": {"coordinates":[1.1374000311,51.0848503113],"type":"Point"}
}