{
  "type": "Feature",
  "properties": {
    "addr:full":"37 Ironmarket Newcastle Staffordshire ST5 1PA",
    "addr:housenumber":"37",
    "addr:postcode":"st5 1pa",
    "addr:street":"Ironmarket",
    "iso:country":"GB",
    "sg:address":"37 Ironmarket",
    "sg:city":"Newcastle",
    "sg:classifiers":[
        {
            "category":"Personal",
            "type":"Services"
        }
    ],
    "sg:phone":"+44 20 7250 2888",
    "sg:postcode":"ST5 1PA",
    "sg:province":"Staffordshire",
    "sg:tags":[
        "delivery"
    ],
    "wof:name":"Consignia Plc",
    "wof:placetype":"venue"
},
  "geometry": {"coordinates":[-2.2248420715,53.0124282837],"type":"Point"}
}