{
  "type": "Feature",
  "properties": {
    "addr:full":"Gundrymoor Trading Estate, Collingwood Rd, West Moors Wimborne Dorset BH21 6QJ",
    "addr:postcode":"bh21 6qj",
    "addr:street":"Collingwood Rd",
    "iso:country":"GB",
    "sg:address":"Gundrymoor Trading Estate, Collingwood Rd, West Moors",
    "sg:city":"Wimborne",
    "sg:classifiers":[
        {
            "category":"Retail",
            "subcategory":"Auto Repair",
            "type":"Services"
        }
    ],
    "sg:phone":"+44 1202 891911",
    "sg:postcode":"BH21 6QJ",
    "sg:province":"Dorset",
    "sg:tags":[
        "car",
        "upholsterer"
    ],
    "wof:name":"South Coast Valeting",
    "wof:placetype":"venue"
},
  "geometry": {"coordinates":[-1.884919,50.841541],"type":"Point"}
}