{
  "type": "Feature",
  "properties": {
    "iso:country":"GB",
    "sg:address":"20 The Ridge, Sketty",
    "sg:city":"Swansea",
    "sg:classifiers":[
        {
            "category":"Organizations",
            "subcategory":"Non-profit Organization",
            "type":"Services"
        }
    ],
    "sg:postcode":"SA2 8AG",
    "sg:province":"Swansea",
    "sg:tags":[
        "organisation",
        "voluntary",
        "charity"
    ],
    "wof:name":"Swansea & Gower Talking Magazine for the Blind",
    "wof:placetype":"venue"
},
  "geometry": {"coordinates":[-3.993992,51.605457],"type":"Point"}
}