{
  "type": "Feature",
  "properties": {
    "iso:country":"GB",
    "sg:address":"Round Green Lodge, Rockley Lane",
    "sg:city":"Barnsley",
    "sg:classifiers":[
        {
            "category":"Personal",
            "type":"Services"
        }
    ],
    "sg:phone":"+44 1226 299969",
    "sg:postcode":"S75 3DR",
    "sg:province":"South Yorkshire",
    "sg:tags":[
        "wedding"
    ],
    "wof:name":"Blue Line Horse & Carriage",
    "wof:placetype":"venue"
},
  "geometry": {"coordinates":[-1.496153,53.525284],"type":"Point"}
}