{
  "type": "Feature",
  "properties": {
    "addr:full":"29 Fishpond Lane, Holbeach Spalding Cambridgeshire PE12 7DQ",
    "addr:housenumber":"29",
    "addr:postcode":"pe12 7dq",
    "addr:street":"Fishpond Lane;Spalding",
    "iso:country":"GB",
    "sg:address":"29 Fishpond Lane, Holbeach",
    "sg:city":"Spalding",
    "sg:classifiers":[
        {
            "category":"Building & Trades",
            "subcategory":"Construction",
            "type":"Services"
        }
    ],
    "sg:phone":"+44 1406 424162",
    "sg:postcode":"PE12 7DQ",
    "sg:province":"Cambridgeshire",
    "sg:tags":[
        "flooring"
    ],
    "wof:name":"Acast Industrial Flooring Ltd.",
    "wof:placetype":"venue"
},
  "geometry": {"coordinates":[0.021531,52.801395],"type":"Point"}
}