{
  "type": "Feature",
  "properties": {
    "addr:full":"Estate Office & House, Ascott Leighton Buzzard Bedfordshire LU7 0PS",
    "addr:postcode":"lu7 0ps",
    "iso:country":"GB",
    "sg:address":"Estate Office & House, Ascott",
    "sg:city":"Leighton Buzzard",
    "sg:classifiers":[
        {
            "category":"Farming",
            "subcategory":"Farm",
            "type":"Manufacturing & Wholesale Goods"
        },
        {
            "category":"Government",
            "subcategory":"Post Office",
            "type":"Public Place"
        },
        {
            "category":"Landmark",
            "subcategory":"Tourist Attraction",
            "type":"Public Place"
        }
    ],
    "sg:phone":"+44 1296 688242",
    "sg:postcode":"LU7 0PS",
    "sg:province":"Bedfordshire",
    "sg:tags":[
        "mixed",
        "interest",
        "crop"
    ],
    "wof:name":"Ascott Properties Ltd.",
    "wof:placetype":"venue"
},
  "geometry": {"coordinates":[-0.7102130055,51.8981666565],"type":"Point"}
}