{
  "type": "Feature",
  "properties": {
    "addr:full":"8a Moor Lane, Crosby Liverpool Merseyside L23 2UE",
    "addr:housenumber":"8a",
    "addr:postcode":"l23 2ue",
    "addr:street":"Moor Lane",
    "iso:country":"GB",
    "sg:address":"8a Moor Lane, Crosby",
    "sg:city":"Liverpool",
    "sg:classifiers":[
        {
            "category":"Shopping",
            "subcategory":"Pharmacy",
            "type":"Retail Goods"
        }
    ],
    "sg:phone":"+44 151 474 5800",
    "sg:postcode":"L23 2UE",
    "sg:province":"Merseyside",
    "sg:tags":[
        "store",
        "drug"
    ],
    "wof:name":"Bodycare",
    "wof:placetype":"venue"
},
  "geometry": {"coordinates":[-3.0254039764,53.4922676086],"type":"Point"}
}