{
  "type": "Feature",
  "properties": {
    "addr:full":"1a Pelham Street Ilkeston Derbyshire DE7 8AR",
    "addr:housenumber":"1a",
    "addr:postcode":"de7 8ar",
    "addr:street":"Pelham Street",
    "iso:country":"GB",
    "sg:address":"1a Pelham Street",
    "sg:city":"Ilkeston",
    "sg:classifiers":[
        {
            "category":"Shopping",
            "subcategory":"Florist",
            "type":"Retail Goods"
        }
    ],
    "sg:phone":"+44 115 932 9368",
    "sg:postcode":"DE7 8AR",
    "sg:province":"Derbyshire",
    "wof:name":"Eileen's Flowers",
    "wof:placetype":"venue"
},
  "geometry": {"coordinates":[-1.309596,52.976181],"type":"Point"}
}