{
  "type": "Feature",
  "properties": {
    "iso:country":"GB",
    "sg:address":"23 Sedgeford Road, Shepherds Bush",
    "sg:city":"London",
    "sg:classifiers":[
        {
            "category":"Arts & Performance",
            "subcategory":"Theater",
            "type":"Entertainment"
        }
    ],
    "sg:phone":"+44 20 8743 9380",
    "sg:postcode":"W12 0NA",
    "sg:province":"Greater London",
    "sg:tags":[
        "theatrical",
        "presentation",
        "theatre"
    ],
    "wof:name":"Image Theatre Co",
    "wof:placetype":"venue"
},
  "geometry": {"coordinates":[-0.244458,51.508984],"type":"Point"}
}