{
  "type": "Feature",
  "properties": {
    "iso:country":"GB",
    "sg:address":"15-17 Upper Albert Road",
    "sg:city":"Sheffield",
    "sg:classifiers":[
        {
            "category":"Social Services",
            "subcategory":"Retirement Home",
            "type":"Services"
        }
    ],
    "sg:phone":"+44 114 258 1717",
    "sg:postcode":"S8 9HR",
    "sg:province":"Derbyshire",
    "sg:tags":[
        "rest"
    ],
    "wof:name":"Sunningdale (Yorkshire) Ltd.",
    "wof:placetype":"venue"
},
  "geometry": {"coordinates":[-1.4641339779,53.3551521301],"type":"Point"}
}