{
  "type": "Feature",
  "properties": {
    "addr:full":"Middleton Road Sudbury Essex CO10 7LJ",
    "addr:postcode":"co10 7lj",
    "addr:street":"Middleton Road",
    "iso:country":"GB",
    "sg:address":"Middleton Road",
    "sg:city":"Sudbury",
    "sg:classifiers":[
        {
            "category":"Manufacturing",
            "subcategory":"Metals",
            "type":"Manufacturing & Wholesale Goods"
        },
        {
            "category":"Wholesale",
            "subcategory":"Scrap",
            "type":"Manufacturing & Wholesale Goods"
        }
    ],
    "sg:phone":"+44 1787 372454",
    "sg:postcode":"CO10 7LJ",
    "sg:province":"Essex",
    "sg:tags":[
        "waste"
    ],
    "wof:name":"Shaddock & Co Ltd",
    "wof:placetype":"venue"
},
  "geometry": {"coordinates":[0.7191590071,52.031879425],"type":"Point"}
}