{
  "type": "Feature",
  "properties": {
    "addr:full":"Unit 14 E, Panmure Industrial Estate Carnoustie Angus DD7 7NP",
    "addr:housenumber":"unit 14 e",
    "addr:postcode":"dd7 7np",
    "addr:street":"Panmure Industrial Estate",
    "iso:country":"GB",
    "sg:address":"Unit 14 E, Panmure Industrial Estate",
    "sg:city":"Carnoustie",
    "sg:classifiers":[
        {
            "category":"Professional",
            "subcategory":"Testing Lab",
            "type":"Services"
        }
    ],
    "sg:phone":"+44 1241 857393",
    "sg:postcode":"DD7 7NP",
    "sg:province":"Angus",
    "sg:tags":[
        "laboratory"
    ],
    "wof:name":"Chrome Craft",
    "wof:placetype":"venue"
},
  "geometry": {"coordinates":[-2.7275838852,56.4975166321],"type":"Point"}
}