{
  "type": "Feature",
  "properties": {
    "addr:full":"363 Wimborne Road, Winton Bournemouth Dorset BH9 2AD",
    "addr:housenumber":"363",
    "addr:postcode":"bh9 2ad",
    "addr:street":"Wimborne Road",
    "iso:country":"GB",
    "sg:address":"363 Wimborne Road, Winton",
    "sg:city":"Bournemouth",
    "sg:classifiers":[
        {
            "category":"Shopping",
            "subcategory":"Comic Books",
            "type":"Retail Goods"
        }
    ],
    "sg:phone":"+44 1202 549332",
    "sg:postcode":"BH9 2AD",
    "sg:province":"Dorset",
    "sg:tags":[
        "jeweller"
    ],
    "wof:name":"Michael Matthews Jewellery Ltd.",
    "wof:placetype":"venue"
},
  "geometry": {"coordinates":[-1.879074,50.741299],"type":"Point"}
}