{
  "type": "Feature",
  "properties": {
    "addr:full":"41 Elsham Road London Greater London W14 8HB",
    "addr:housenumber":"41",
    "addr:postcode":"w14 8hb",
    "addr:street":"Elsham Road",
    "iso:country":"GB",
    "sg:address":"41 Elsham Road",
    "sg:city":"London",
    "sg:classifiers":[
        {
            "category":"Wholesale",
            "subcategory":"Music Publishers",
            "type":"Manufacturing & Wholesale Goods"
        }
    ],
    "sg:phone":"+44 20 7460 1867",
    "sg:postcode":"W14 8HB",
    "sg:province":"Greater London",
    "sg:tags":[
        "record"
    ],
    "wof:name":"Fluffy Freako Records",
    "wof:placetype":"venue"
},
  "geometry": {"coordinates":[-0.2139240056,51.5021362305],"type":"Point"}
}