{
  "type": "Feature",
  "properties": {
    "addr:full":"Whiston Bank Farm, The Deanery, Penkridge Stafford Shropshire ST19 5QQ",
    "addr:housenumber":"whiston;the;penkridge",
    "addr:postcode":"st19 5qq",
    "iso:country":"GB",
    "sg:address":"Whiston Bank Farm, The Deanery, Penkridge",
    "sg:city":"Stafford",
    "sg:classifiers":[
        {
            "category":"Farming",
            "subcategory":"Livestock Farm",
            "type":"Manufacturing & Wholesale Goods"
        }
    ],
    "sg:phone":"+44 1785 712525",
    "sg:postcode":"ST19 5QQ",
    "sg:province":"Shropshire",
    "sg:tags":[
        "others"
    ],
    "wof:name":"Jade Jerseys",
    "wof:placetype":"venue"
},
  "geometry": {"coordinates":[-2.11634,52.722607],"type":"Point"}
}