{
  "type": "Feature",
  "properties": {
    "addr:full":"The Health Centre, Robin Hood La Sutton Surrey SM1 2RG",
    "addr:postcode":"sm1 2rg",
    "addr:street":"Robin Hood La Sutton",
    "iso:country":"GB",
    "sg:address":"The Health Centre, Robin Hood La",
    "sg:city":"Sutton",
    "sg:classifiers":[
        {
            "category":"Health Services",
            "subcategory":"Doctor",
            "type":"Services"
        }
    ],
    "sg:phone":"+44 20 8642 3848",
    "sg:postcode":"SM1 2RG",
    "sg:province":"Surrey",
    "sg:tags":[
        "practitioners"
    ],
    "wof:name":"Seyan, R",
    "wof:placetype":"venue"
},
  "geometry": {"coordinates":[-0.197558,51.361191],"type":"Point"}
}