{
  "type": "Feature",
  "properties": {
    "iso:country":"GB",
    "sg:address":"30 & 26 Great King Street",
    "sg:city":"Dumfries",
    "sg:classifiers":[
        {
            "category":"Social Services",
            "subcategory":"Retirement Home",
            "type":"Services"
        }
    ],
    "sg:phone":"+44 1387 262699",
    "sg:postcode":"DG1 1BD",
    "sg:province":"Dumfries and Galloway",
    "sg:tags":[
        "care"
    ],
    "wof:name":"Philomel Care",
    "wof:placetype":"venue"
},
  "geometry": {"coordinates":[-3.609787,55.069408],"type":"Point"}
}