{
  "type": "Feature",
  "properties": {
    "addr:full":"St Olaf House, London Bridge City London Greater London SE1 2PE",
    "addr:postcode":"se1 2pe",
    "addr:street":"London Bridge",
    "iso:country":"GB",
    "sg:address":"St Olaf House, London Bridge City",
    "sg:city":"London",
    "sg:classifiers":[
        {
            "category":"Professional",
            "subcategory":"Research",
            "type":"Services"
        }
    ],
    "sg:phone":"+44 20 7357 7171",
    "sg:postcode":"SE1 2PE",
    "sg:province":"Greater London",
    "sg:tags":[
        "actuary"
    ],
    "wof:name":"Bacon & Woodrow Ltd.",
    "wof:placetype":"venue"
},
  "geometry": {"coordinates":[-0.0875739977,51.5084037781],"type":"Point"}
}