{
  "type": "Feature",
  "properties": {
    "addr:full":"Kingsland School, Shacklewell Lane London Greater London E8 2EY",
    "addr:postcode":"e8 2ey",
    "addr:street":"Shacklewell Lane",
    "iso:country":"GB",
    "sg:address":"Kingsland School, Shacklewell Lane",
    "sg:city":"London",
    "sg:classifiers":[
        {
            "category":"Community Center",
            "subcategory":"Youth",
            "type":"Public Place"
        }
    ],
    "sg:phone":"+44 20 7254 4034",
    "sg:postcode":"E8 2EY",
    "sg:province":"Greater London",
    "sg:tags":[
        "organisation",
        "centre"
    ],
    "wof:name":"The A Space",
    "wof:placetype":"venue"
},
  "geometry": {"coordinates":[-0.075629,51.547115],"type":"Point"}
}