{
  "type": "Feature",
  "properties": {
    "iso:country":"GB",
    "sg:address":"Lewes Road",
    "sg:city":"Haywards Heath",
    "sg:classifiers":[
        {
            "category":"Home & Garden",
            "subcategory":"Garden Supply",
            "type":"Retail Goods"
        }
    ],
    "sg:phone":"+44 1444 831673",
    "sg:postcode":"RH17 7PG",
    "sg:province":"East Sussex",
    "sg:tags":[
        "nursery",
        "centre"
    ],
    "wof:name":"Scaynes Hill Nursery",
    "wof:placetype":"venue"
},
  "geometry": {"coordinates":[-0.070213,50.995445],"type":"Point"}
}