{
  "type": "Feature",
  "properties": {
    "addr:full":"Fishergate Centre Preston Lancashire PR1 8HJ",
    "addr:postcode":"pr1 8hj",
    "addr:street":"Fishergate;Preston",
    "iso:country":"GB",
    "sg:address":"Fishergate Centre",
    "sg:city":"Preston",
    "sg:classifiers":[
        {
            "category":"Shopping",
            "subcategory":"Comic Books",
            "type":"Retail Goods"
        }
    ],
    "sg:phone":"+44 1772 562062",
    "sg:postcode":"PR1 8HJ",
    "sg:province":"Lancashire",
    "sg:tags":[
        "jeweller",
        "sale",
        "jewellery"
    ],
    "wof:name":"Rebecca's Antiques",
    "wof:placetype":"venue"
},
  "geometry": {"coordinates":[-2.703359,53.75779],"type":"Point"}
}