{
  "type": "Feature",
  "properties": {
    "addr:full":"27 Westbourne Road Huddersfield West Yorkshire HD1 4LQ",
    "addr:housenumber":"27",
    "addr:postcode":"hd1 4lq",
    "addr:street":"Westbourne Road",
    "iso:country":"GB",
    "sg:address":"27 Westbourne Road",
    "sg:city":"Huddersfield",
    "sg:classifiers":[
        {
            "category":"Home & Garden",
            "subcategory":"Home Furnishings",
            "type":"Retail Goods"
        }
    ],
    "sg:phone":"+44 1484 519172",
    "sg:postcode":"HD1 4LQ",
    "sg:province":"West Yorkshire",
    "sg:tags":[
        "blind",
        "curtain",
        "fitting"
    ],
    "wof:name":"Croxfords At Marsh",
    "wof:placetype":"venue"
},
  "geometry": {"coordinates":[-1.804267,53.651588],"type":"Point"}
}