{
  "type": "Feature",
  "properties": {
    "iso:country":"GB",
    "sg:address":"Victoria Road, Waunarlwydd",
    "sg:city":"Swansea",
    "sg:classifiers":[
        {
            "category":"Community Center",
            "type":"Public Place"
        }
    ],
    "sg:phone":"+44 1792 872301",
    "sg:postcode":"SA5 4TB",
    "sg:province":"Swansea",
    "sg:tags":[
        "centre"
    ],
    "wof:name":"Waunarlywdd Community Centre",
    "wof:placetype":"venue"
},
  "geometry": {"coordinates":[-4.022279,51.640141],"type":"Point"}
}