{
  "type": "Feature",
  "properties": {
    "iso:country":"GB",
    "sg:address":"31 West St, Wilton",
    "sg:city":"Salisbury",
    "sg:classifiers":[
        {
            "category":"Professional",
            "subcategory":"Business Services",
            "type":"Services"
        }
    ],
    "sg:postcode":"SP2 0DL",
    "sg:province":"Wiltshire",
    "sg:tags":[
        "transfer",
        "agent"
    ],
    "wof:name":"Everett Masson & Furby",
    "wof:placetype":"venue"
},
  "geometry": {"coordinates":[-1.8663589954,51.0814781189],"type":"Point"}
}