{
  "type": "Feature",
  "properties": {
    "addr:full":"Twyford Abbey Road London Greater London NW10 7DN",
    "addr:postcode":"nw10 7dn",
    "addr:street":"Abbey Road",
    "iso:country":"GB",
    "sg:address":"Twyford Abbey Road",
    "sg:city":"London",
    "sg:classifiers":[
        {
            "category":"Education",
            "subcategory":"School",
            "type":"Public Place"
        },
        {
            "category":"Government",
            "subcategory":"Office",
            "type":"Public Place"
        }
    ],
    "sg:phone":"+44 20 8965 6858",
    "sg:postcode":"NW10 7DN",
    "sg:province":"Greater London",
    "sg:tags":[
        "local",
        "authority"
    ],
    "wof:name":"West Twyford Primary School",
    "wof:placetype":"venue"
},
  "geometry": {"coordinates":[-0.2798460126,51.5347480774],"type":"Point"}
}