{
  "type": "Feature",
  "properties": {
    "addr:full":"Fishtoft Road, Fishtoft Boston Lincolnshire PE21 0QR",
    "addr:postcode":"pe21 0qr",
    "addr:street":"Fishtoft Road",
    "iso:country":"GB",
    "sg:address":"Fishtoft Road, Fishtoft",
    "sg:city":"Boston",
    "sg:classifiers":[
        {
            "category":"Retail",
            "subcategory":"Auto Repair",
            "type":"Services"
        }
    ],
    "sg:phone":"+44 1205 361010",
    "sg:postcode":"PE21 0QR",
    "sg:province":"Lincolnshire",
    "sg:tags":[
        "modification",
        "garage",
        "related"
    ],
    "wof:name":"Brian Fairweather Autos",
    "wof:placetype":"venue"
},
  "geometry": {"coordinates":[0.025954,52.961658],"type":"Point"}
}