{
  "type": "Feature",
  "properties": {
    "addr:full":"Boyton Hall Farm, Boyton Hall Lane, Roxwell Chelmsford Essex CM1 4LN",
    "addr:housenumber":"boyton",
    "addr:postcode":"cm1 4ln",
    "addr:street":"Hall Lane",
    "iso:country":"GB",
    "sg:address":"Boyton Hall Farm, Boyton Hall Lane, Roxwell",
    "sg:city":"Chelmsford",
    "sg:classifiers":[
        {
            "category":"Farming",
            "subcategory":"Livestock Farm",
            "type":"Manufacturing & Wholesale Goods"
        }
    ],
    "sg:phone":"+44 1245 248664",
    "sg:postcode":"CM1 4LN",
    "sg:province":"Essex",
    "sg:tags":[
        "others"
    ],
    "wof:name":"A P T Farming Ltd.",
    "wof:placetype":"venue"
},
  "geometry": {"coordinates":[0.3889810145,51.7587890625],"type":"Point"}
}