{
  "type": "Feature",
  "properties": {
    "iso:country":"GB",
    "sg:address":"West House",
    "sg:city":"Burnham-on-crouch",
    "sg:classifiers":[
        {
            "category":"Health Services",
            "subcategory":"Optometrist",
            "type":"Services"
        }
    ],
    "sg:phone":"+44 1621 782048",
    "sg:postcode":"CM0 8AG",
    "sg:province":"Essex",
    "sg:tags":[
        "optician"
    ],
    "wof:name":"Edward Watts & David Wood Opticians",
    "wof:placetype":"venue"
},
  "geometry": {"coordinates":[0.815427,51.63184],"type":"Point"}
}