{
  "type": "Feature",
  "properties": {
    "iso:country":"GB",
    "sg:address":"37 Heolddu Grove",
    "sg:city":"Bargoed",
    "sg:classifiers":[
        {
            "category":"Social Services",
            "subcategory":"Adult Care",
            "type":"Services"
        }
    ],
    "sg:phone":"+44 1443 829300",
    "sg:postcode":"CF81 8UX",
    "sg:province":"Caerphilly",
    "sg:tags":[
        "domestic",
        "cleaning"
    ],
    "wof:name":"Pristine Cleaning Services",
    "wof:placetype":"venue"
},
  "geometry": {"coordinates":[-3.237589,51.691174],"type":"Point"}
}