{
  "type": "Feature",
  "properties": {
    "iso:country":"GB",
    "sg:address":"92 Church St, Stapleford",
    "sg:city":"Nottingham",
    "sg:classifiers":[
        {
            "category":"Autos & Motor Vehicles",
            "subcategory":"Automobile Sales",
            "type":"Retail Goods"
        }
    ],
    "sg:phone":"+44 115 939 1111",
    "sg:postcode":"NG9 8DJ",
    "sg:province":"Nottinghamshire",
    "sg:tags":[
        "car"
    ],
    "wof:name":"Manor Garage Car Sales",
    "wof:placetype":"venue"
},
  "geometry": {"coordinates":[-1.272924,52.933453],"type":"Point"}
}