{
  "type": "Feature",
  "properties": {
    "addr:full":"128 St Johns Road London Greater London E17 4JJ",
    "addr:housenumber":"128",
    "addr:postcode":"e17 4jj",
    "addr:street":"St Johns Road",
    "iso:country":"GB",
    "sg:address":"128 St Johns Road",
    "sg:city":"London",
    "sg:classifiers":[
        {
            "category":"Health Services",
            "subcategory":"Doctor",
            "type":"Services"
        }
    ],
    "sg:phone":"+44 20 8531 2776",
    "sg:postcode":"E17 4JJ",
    "sg:province":"Greater London",
    "sg:tags":[
        "practitioners"
    ],
    "wof:name":"M M Rahman",
    "wof:placetype":"venue"
},
  "geometry": {"coordinates":[-0.008371,51.594063],"type":"Point"}
}