{
  "type": "Feature",
  "properties": {
    "iso:country":"GB",
    "sg:address":"27 Windsor Drive",
    "sg:city":"Gloucester",
    "sg:classifiers":[
        {
            "category":"Banks & Credit Unions",
            "subcategory":"Bank",
            "type":"Services"
        }
    ],
    "sg:phone":"+44 1452 310110",
    "sg:postcode":"GL4 0QJ",
    "sg:province":"Gloucestershire",
    "sg:tags":[
        "broker",
        "mortgage"
    ],
    "wof:name":"Steve Gooch Mortgage Advice Bureau Ltd.",
    "wof:placetype":"venue"
},
  "geometry": {"coordinates":[-2.257609,51.828484],"type":"Point"}
}