{
  "type": "Feature",
  "properties": {
    "iso:country":"GB",
    "sg:address":"51 Parliament Street, Norton",
    "sg:city":"Malton",
    "sg:classifiers":[
        {
            "category":"Professional",
            "subcategory":"Printing & Photocopies",
            "type":"Services"
        }
    ],
    "sg:phone":"+44 1653 693819",
    "sg:postcode":"YO17 9HE",
    "sg:province":"North Yorkshire",
    "sg:tags":[
        "printer"
    ],
    "wof:name":"Best & Design",
    "wof:placetype":"venue"
},
  "geometry": {"coordinates":[-0.779533,54.133301],"type":"Point"}
}