{
  "type": "Feature",
  "properties": {
    "addr:full":"26 Roundhill Road, Livermead Torquay Devon TQ2 6TH",
    "addr:housenumber":"26",
    "addr:postcode":"tq2 6th",
    "addr:street":"Roundhill Road",
    "iso:country":"GB",
    "sg:address":"26 Roundhill Road, Livermead",
    "sg:city":"Torquay",
    "sg:classifiers":[
        {
            "category":"Personal",
            "subcategory":"Beauty Salon",
            "type":"Services"
        }
    ],
    "sg:phone":"+44 1803 605390",
    "sg:postcode":"TQ2 6TH",
    "sg:province":"Devon",
    "sg:tags":[
        "unisex",
        "hairdresser"
    ],
    "wof:name":"Robert & Ruth Hair Design",
    "wof:placetype":"venue"
},
  "geometry": {"coordinates":[-3.556281,50.454937],"type":"Point"}
}