{
  "type": "Feature",
  "properties": {
    "addr:full":"Beak Farm, Wakes Colne Colchester Essex CO6 2BD",
    "addr:postcode":"co6 2bd",
    "addr:street":"Colne Colchester",
    "iso:country":"GB",
    "sg:address":"Beak Farm, Wakes Colne",
    "sg:city":"Colchester",
    "sg:classifiers":[
        {
            "category":"Home & Garden",
            "subcategory":"Garden Supply",
            "type":"Retail Goods"
        }
    ],
    "sg:postcode":"CO6 2BD",
    "sg:province":"Essex",
    "sg:tags":[
        "bulb",
        "grower"
    ],
    "wof:name":"Tawell,R T,",
    "wof:placetype":"venue"
},
  "geometry": {"coordinates":[0.755685,51.923264],"type":"Point"}
}