{
  "type": "Feature",
  "properties": {
    "addr:full":"41 Landscape View Saffron Walden Essex CB11 4AT",
    "addr:housenumber":"41",
    "addr:postcode":"cb11 4at",
    "addr:street":"Landscape View",
    "iso:country":"GB",
    "sg:address":"41 Landscape View",
    "sg:city":"Saffron Walden",
    "sg:classifiers":[
        {
            "category":"Retail",
            "subcategory":"Driving School",
            "type":"Services"
        }
    ],
    "sg:phone":"+44 1799 522894",
    "sg:postcode":"CB11 4AT",
    "sg:province":"Essex",
    "wof:name":"Gary Pipe",
    "wof:placetype":"venue"
},
  "geometry": {"coordinates":[0.2419719994,52.0094985962],"type":"Point"}
}