{
  "type": "Feature",
  "properties": {
    "iso:country":"GB",
    "sg:address":"61 Weston Road",
    "sg:city":"Stafford",
    "sg:classifiers":[
        {
            "category":"Fast Food",
            "type":"Food & Drink"
        }
    ],
    "sg:phone":"+44 1785 251303",
    "sg:postcode":"ST16 3RL",
    "sg:province":"Staffordshire",
    "sg:tags":[
        "away",
        "take"
    ],
    "wof:name":"Algy's",
    "wof:placetype":"venue"
},
  "geometry": {"coordinates":[-2.102694,52.807457],"type":"Point"}
}