{
  "type": "Feature",
  "properties": {
    "iso:country":"GB",
    "sg:address":"70 Leytonstone Road",
    "sg:city":"London",
    "sg:classifiers":[
        {
            "category":"Shopping",
            "subcategory":"Pharmacy",
            "type":"Retail Goods"
        }
    ],
    "sg:phone":"+44 20 8555 8403",
    "sg:postcode":"E15 1SQ",
    "sg:province":"Greater London",
    "sg:tags":[
        "pharmacist",
        "chemist"
    ],
    "wof:name":"Chemifarm",
    "wof:placetype":"venue"
},
  "geometry": {"coordinates":[0.005329,51.549343],"type":"Point"}
}