{
  "type": "Feature",
  "properties": {
    "iso:country":"GB",
    "sg:address":"33 Anns Hill Road",
    "sg:city":"Gosport",
    "sg:classifiers":[
        {
            "category":"Bars & Pubs",
            "type":"Food & Drink"
        }
    ],
    "sg:phone":"+44 23 9258 4042",
    "sg:postcode":"PO12 3JU",
    "sg:province":"Hampshire",
    "sg:tags":[
        "pubs",
        "inn"
    ],
    "wof:name":"The Barley Mow",
    "wof:placetype":"venue"
},
  "geometry": {"coordinates":[-1.149155,50.802265],"type":"Point"}
}