{
  "type": "Feature",
  "properties": {
    "addr:full":"2a Fox St Gillingham Kent ME7 1HQ",
    "addr:housenumber":"2a",
    "addr:postcode":"me7 1hq",
    "addr:street":"Fox St",
    "iso:country":"GB",
    "sg:address":"2a Fox St",
    "sg:city":"Gillingham",
    "sg:classifiers":[
        {
            "category":"Organizations",
            "subcategory":"Non-profit Organization",
            "type":"Services"
        }
    ],
    "sg:phone":"+44 1634 572330",
    "sg:postcode":"ME7 1HQ",
    "sg:province":"Kent",
    "sg:tags":[
        "organisation",
        "voluntary",
        "charity"
    ],
    "wof:name":"The Childrens Health Care Charity",
    "wof:placetype":"venue"
},
  "geometry": {"coordinates":[0.543380022,51.3892326355],"type":"Point"}
}