{
  "type": "Feature",
  "properties": {
    "iso:country":"GB",
    "sg:address":"Eighton Lodge, Low Eighton",
    "sg:city":"Gateshead",
    "sg:classifiers":[
        {
            "category":"Social Services",
            "subcategory":"Retirement Home",
            "type":"Services"
        }
    ],
    "sg:phone":"+44 191 410 3665",
    "sg:postcode":"NE9 7UB",
    "sg:province":"Tyne and Wear",
    "sg:tags":[
        "rest"
    ],
    "wof:name":"Eighton Lodge Rest Home",
    "wof:placetype":"venue"
},
  "geometry": {"coordinates":[-1.581352,54.912682],"type":"Point"}
}