{
  "type": "Feature",
  "properties": {
    "addr:full":"2 Hobbs Way, Bow Crediton Devon EX17 6JZ",
    "addr:housenumber":"2",
    "addr:postcode":"ex17 6jz",
    "addr:street":"Hobbs Way",
    "iso:country":"GB",
    "sg:address":"2 Hobbs Way, Bow",
    "sg:city":"Crediton",
    "sg:classifiers":[
        {
            "category":"Building & Trades",
            "subcategory":"Plumbing",
            "type":"Services"
        }
    ],
    "sg:postcode":"EX17 6JZ",
    "sg:province":"Devon",
    "sg:tags":[
        "central",
        "installation",
        "system",
        "servicing",
        "heating"
    ],
    "wof:name":"GASPRO",
    "wof:placetype":"venue"
},
  "geometry": {"coordinates":[-3.818242,50.798935],"type":"Point"}
}