{
  "type": "Feature",
  "properties": {
    "iso:country":"GB",
    "sg:address":"3 Hamilton Place, Barrhill Road",
    "sg:city":"Cumnock",
    "sg:classifiers":[
        {
            "category":"Home & Garden",
            "subcategory":"Hardware",
            "type":"Retail Goods"
        }
    ],
    "sg:phone":"+44 1290 421471",
    "sg:postcode":"KA18 1DB",
    "sg:province":"East Ayrshire",
    "wof:name":"Nith Valley Co-Operative Society Ltd.",
    "wof:placetype":"venue"
},
  "geometry": {"coordinates":[-4.264099,55.453255],"type":"Point"}
}