{
  "type": "Feature",
  "properties": {
    "addr:full":"163 South Brink Wisbech Cambridgeshire PE14 0RY",
    "addr:housenumber":"163",
    "addr:postcode":"pe14 0ry",
    "addr:street":"South Brink",
    "iso:country":"GB",
    "sg:address":"163 South Brink",
    "sg:city":"Wisbech",
    "sg:classifiers":[
        {
            "category":"Government",
            "subcategory":"Office",
            "type":"Public Place"
        }
    ],
    "sg:phone":"+44 1945 583707",
    "sg:postcode":"PE14 0RY",
    "sg:province":"Cambridgeshire",
    "sg:tags":[
        "local"
    ],
    "wof:name":"Waldersey Drainage Board",
    "wof:placetype":"venue"
},
  "geometry": {"coordinates":[0.14209,52.65226],"type":"Point"}
}