{
  "type": "Feature",
  "properties": {
    "addr:full":"4 St James Terrace Newcastle-upon-tyne Tyne and Wear NE1 4NE",
    "addr:housenumber":"4",
    "addr:postcode":"ne1 4ne",
    "addr:street":"St James Terrace",
    "iso:country":"GB",
    "sg:address":"4 St James Terrace",
    "sg:city":"Newcastle-upon-tyne",
    "sg:classifiers":[
        {
            "category":"Real Estate",
            "subcategory":"Developer",
            "type":"Services"
        }
    ],
    "sg:phone":"+44 191 221 2606",
    "sg:postcode":"NE1 4NE",
    "sg:province":"Tyne and Wear",
    "sg:tags":[
        "property"
    ],
    "wof:name":"Highbridge Holdings Ltd.",
    "wof:placetype":"venue"
},
  "geometry": {"coordinates":[-1.6195360422,54.9751205444],"type":"Point"}
}