{
  "type": "Feature",
  "properties": {
    "iso:country":"GB",
    "sg:address":"Chester Close",
    "sg:city":"Runcorn",
    "sg:classifiers":[
        {
            "category":"Place Of Worship",
            "type":"Public Place"
        }
    ],
    "sg:phone":"+44 1928 563636",
    "sg:postcode":"WA7 2HY",
    "sg:province":"Cheshire",
    "wof:name":"Christ Church Castlefields",
    "wof:placetype":"venue"
},
  "geometry": {"coordinates":[-2.6922700405,53.3374481201],"type":"Point"}
}