{
  "type": "Feature",
  "properties": {
    "iso:country":"GB",
    "sg:address":"The Boatmans Shelter",
    "sg:city":"Plymouth",
    "sg:classifiers":[
        {
            "category":"Professional",
            "subcategory":"Business Services",
            "type":"Services"
        },
        {
            "category":"Organizations",
            "subcategory":"Non-profit Organization",
            "type":"Services"
        }
    ],
    "sg:phone":"+44 1752 254198",
    "sg:postcode":"PL1 2LR",
    "sg:province":"Devon",
    "sg:tags":[
        "voluntary",
        "organisation",
        "agent",
        "export",
        "import",
        "charity"
    ],
    "wof:name":"R N L I Shop",
    "wof:placetype":"venue"
},
  "geometry": {"coordinates":[-4.13431,50.366161],"type":"Point"}
}