{
  "type": "Feature",
  "properties": {
    "addr:full":"46 Balls Pond Road London Greater London N1 4AP",
    "addr:housenumber":"46",
    "addr:postcode":"n1 4ap",
    "addr:street":"Balls Pond Road",
    "iso:country":"GB",
    "sg:address":"46 Balls Pond Road",
    "sg:city":"London",
    "sg:classifiers":[
        {
            "category":"Professional",
            "subcategory":"Lawyer & Legal Services",
            "type":"Services"
        }
    ],
    "sg:phone":"+44 20 7275 0030",
    "sg:postcode":"N1 4AP",
    "sg:province":"Greater London",
    "sg:tags":[
        "solicitor"
    ],
    "wof:name":"Jonathan & Co",
    "wof:placetype":"venue"
},
  "geometry": {"coordinates":[-0.07805,51.54631],"type":"Point"}
}