{
  "type": "Feature",
  "properties": {
    "iso:country":"GB",
    "sg:address":"18 Hartley Street, Featherstone",
    "sg:city":"Pontefract",
    "sg:classifiers":[
        {
            "category":"Bars & Pubs",
            "subcategory":"Nightclub",
            "type":"Food & Drink"
        }
    ],
    "sg:phone":"+44 1977 701039",
    "sg:postcode":"WF7 5HU",
    "sg:province":"West Yorkshire",
    "sg:tags":[
        "karaoke"
    ],
    "wof:name":"Karaoke Krazy",
    "wof:placetype":"venue"
},
  "geometry": {"coordinates":[-1.3611270189,53.6736106873],"type":"Point"}
}