{
  "type": "Feature",
  "properties": {
    "addr:full":"63 Church Av Mortlake Greater London SW14 8NL",
    "addr:housenumber":"63",
    "addr:postcode":"sw14 8nl",
    "addr:street":"Church Av",
    "iso:country":"GB",
    "sg:address":"63 Church Av",
    "sg:city":"Mortlake",
    "sg:classifiers":[
        {
            "category":"Travel",
            "subcategory":"Hotels & Motels",
            "type":"Entertainment"
        }
    ],
    "sg:phone":"+44 20 8540 7942",
    "sg:postcode":"SW14 8NL",
    "sg:province":"Greater London",
    "sg:tags":[
        "house",
        "guest"
    ],
    "wof:name":"Holiday Host Agency",
    "wof:placetype":"venue"
},
  "geometry": {"coordinates":[-0.26385,51.467552],"type":"Point"}
}