{
  "type": "Feature",
  "properties": {
    "addr:full":"338 Albert Royds St Rochdale Lancashire OL16 5AA",
    "addr:housenumber":"338",
    "addr:postcode":"ol16 5aa",
    "addr:street":"Albert Royds St",
    "iso:country":"GB",
    "sg:address":"338 Albert Royds St",
    "sg:city":"Rochdale",
    "sg:classifiers":[
        {
            "category":"Real Estate",
            "subcategory":"Developer",
            "type":"Services"
        }
    ],
    "sg:phone":"+44 1706 342805",
    "sg:postcode":"OL16 5AA",
    "sg:province":"Lancashire",
    "sg:tags":[
        "property"
    ],
    "wof:name":"Belfield Hall Developments",
    "wof:placetype":"venue"
},
  "geometry": {"coordinates":[-2.129948,53.619709],"type":"Point"}
}