{
  "type": "Feature",
  "properties": {
    "iso:country":"GB",
    "sg:address":"10 West Edge, Bicton Heath",
    "sg:city":"Shrewsbury",
    "sg:classifiers":[
        {
            "category":"Home & Garden",
            "subcategory":"Carpets & Floor Coverings",
            "type":"Retail Goods"
        }
    ],
    "sg:postcode":"SY3 5EZ",
    "sg:province":"Shropshire",
    "sg:tags":[
        "cleaner",
        "upholstery"
    ],
    "wof:name":"Brighta Clean",
    "wof:placetype":"venue"
},
  "geometry": {"coordinates":[-2.810087,52.709846],"type":"Point"}
}