{
  "type": "Feature",
  "properties": {
    "addr:full":"4 Tower Close Andover Hampshire SP10 4RS",
    "addr:housenumber":"4",
    "addr:postcode":"sp10 4rs",
    "addr:street":"Tower Close",
    "iso:country":"GB",
    "sg:address":"4 Tower Close",
    "sg:city":"Andover",
    "sg:classifiers":[
        {
            "category":"Shopping",
            "type":"Retail Goods"
        }
    ],
    "sg:phone":"+44 1264 394410",
    "sg:postcode":"SP10 4RS",
    "sg:province":"Hampshire",
    "sg:tags":[
        "part",
        "accessory"
    ],
    "wof:name":"Topboxes of Andover",
    "wof:placetype":"venue"
},
  "geometry": {"coordinates":[-1.5030390024,51.2222862244],"type":"Point"}
}