{
  "type": "Feature",
  "properties": {
    "iso:country":"GB",
    "sg:address":"Unit 11 Farrington Road, Rossen, Rossendale Industrial Estate",
    "sg:city":"Burnley",
    "sg:postcode":"BB11 5SH",
    "sg:province":"Lancashire",
    "wof:name":"Sedin U K Ltd.",
    "wof:placetype":"venue"
},
  "geometry": {"coordinates":[-2.274394,53.778816],"type":"Point"}
}