{
  "type": "Feature",
  "properties": {
    "iso:country":"GB",
    "sg:address":"Ysguborfawr, Myddfai",
    "sg:city":"Llandovery",
    "sg:classifiers":[
        {
            "category":"Farming",
            "subcategory":"Livestock Farm",
            "type":"Manufacturing & Wholesale Goods"
        }
    ],
    "sg:postcode":"SA20 0PQ",
    "sg:province":"Carmarthenshire",
    "sg:tags":[
        "others"
    ],
    "wof:name":"Peter J Foot",
    "wof:placetype":"venue"
},
  "geometry": {"coordinates":[-3.800155,51.994087],"type":"Point"}
}