{
  "type": "Feature",
  "properties": {
    "addr:full":"112 Dimsdale View West Newcastle Staffordshire ST5 8EL",
    "addr:housenumber":"112",
    "addr:postcode":"st5 8el",
    "addr:street":"Dimsdale View West",
    "iso:country":"GB",
    "sg:address":"112 Dimsdale View West",
    "sg:city":"Newcastle",
    "sg:classifiers":[
        {
            "category":"Manufacturing",
            "subcategory":"Signs",
            "type":"Manufacturing & Wholesale Goods"
        }
    ],
    "sg:phone":"+44 1782 561396",
    "sg:postcode":"ST5 8EL",
    "sg:province":"Staffordshire",
    "sg:tags":[
        "writer"
    ],
    "wof:name":"D J Reynolds",
    "wof:placetype":"venue"
},
  "geometry": {"coordinates":[-2.230328,53.036758],"type":"Point"}
}