{
  "type": "Feature",
  "properties": {
    "addr:full":"5 Monks Way Orpington Kent BR5 1HN",
    "addr:housenumber":"5",
    "addr:postcode":"br5 1hn",
    "addr:street":"Monks Way",
    "iso:country":"GB",
    "sg:address":"5 Monks Way",
    "sg:city":"Orpington",
    "sg:classifiers":[
        {
            "category":"Professional",
            "subcategory":"Management & Consulting",
            "type":"Services"
        }
    ],
    "sg:phone":"+44 1689 870700",
    "sg:postcode":"BR5 1HN",
    "sg:province":"Kent",
    "sg:tags":[
        "consultant",
        "business"
    ],
    "wof:name":"Core F M Ltd.",
    "wof:placetype":"venue"
},
  "geometry": {"coordinates":[0.075581,51.375999],"type":"Point"}
}