{
  "type": "Feature",
  "properties": {
    "iso:country":"GB",
    "sg:address":"Mobility House, 492 Kingston Road, Raynes Park",
    "sg:city":"London",
    "sg:classifiers":[
        {
            "category":"Building & Trades",
            "subcategory":"Equipment Rental",
            "type":"Services"
        }
    ],
    "sg:phone":"+44 20 8542 1021",
    "sg:postcode":"SW20 8DX",
    "sg:province":"Greater London",
    "sg:tags":[
        "plant",
        "machinery"
    ],
    "wof:name":"All Handling Ltd.",
    "wof:placetype":"venue"
},
  "geometry": {"coordinates":[-0.2200099975,51.4105529785],"type":"Point"}
}