{
  "type": "Feature",
  "properties": {
    "addr:full":"45 Norbury Road Thornton Heath Surrey CR7 8JP",
    "addr:housenumber":"45",
    "addr:postcode":"cr7 8jp",
    "addr:street":"Norbury Road",
    "iso:country":"GB",
    "sg:address":"45 Norbury Road",
    "sg:city":"Thornton Heath",
    "sg:classifiers":[
        {
            "category":"Shopping",
            "subcategory":"Clothing, Apparel, & Fashions",
            "type":"Retail Goods"
        },
        {
            "category":"Home & Garden",
            "subcategory":"Home Furnishings",
            "type":"Retail Goods"
        }
    ],
    "sg:phone":"+44 20 8653 9828",
    "sg:postcode":"CR7 8JP",
    "sg:province":"Surrey",
    "sg:tags":[
        "shop",
        "beds",
        "bedding",
        "blanket",
        "bed"
    ],
    "wof:name":"Payless Discount Warehouse",
    "wof:placetype":"venue"
},
  "geometry": {"coordinates":[-0.0978239998,51.4047966003],"type":"Point"}
}