{
  "type": "Feature",
  "properties": {
    "addr:full":"134 Horncastle Road Woodhall Spa Lincolnshire LN10 6UU",
    "addr:housenumber":"134",
    "addr:postcode":"ln10 6uu",
    "addr:street":"Horncastle Road",
    "iso:country":"GB",
    "sg:address":"134 Horncastle Road",
    "sg:city":"Woodhall Spa",
    "sg:classifiers":[
        {
            "category":"Manufacturing",
            "subcategory":"Buildings",
            "type":"Manufacturing & Wholesale Goods"
        }
    ],
    "sg:phone":"+44 1526 352312",
    "sg:postcode":"LN10 6UU",
    "sg:province":"Lincolnshire",
    "sg:tags":[
        "mobile",
        "home"
    ],
    "wof:name":"Oaklands Park",
    "wof:placetype":"venue"
},
  "geometry": {"coordinates":[-0.200289,53.15519],"type":"Point"}
}