{
  "type": "Feature",
  "properties": {
    "addr:full":"77 Buttmead Northampton Buckinghamshire NN7 3DQ",
    "addr:housenumber":"77",
    "addr:postcode":"nn7 3dq",
    "addr:street":"Buttmead Northampton",
    "iso:country":"GB",
    "sg:address":"77 Buttmead",
    "sg:city":"Northampton",
    "sg:classifiers":[
        {
            "category":"Arts & Performance",
            "subcategory":"Music",
            "type":"Entertainment"
        }
    ],
    "sg:phone":"+44 1604 859236",
    "sg:postcode":"NN7 3DQ",
    "sg:province":"Buckinghamshire",
    "sg:tags":[
        "mobile",
        "disco"
    ],
    "wof:name":"Silver Knight Disco",
    "wof:placetype":"venue"
},
  "geometry": {"coordinates":[-0.9350469708,52.1733932495],"type":"Point"}
}