{
  "type": "Feature",
  "properties": {
    "iso:country":"GB",
    "sg:address":"52 St Mary's Street",
    "sg:city":"Edinburgh",
    "sg:classifiers":[
        {
            "category":"Food & Beverages",
            "subcategory":"Candy",
            "type":"Retail Goods"
        }
    ],
    "sg:phone":"+44 131 556 6082",
    "sg:postcode":"EH1 1SX",
    "sg:province":"City of Edinburgh",
    "sg:tags":[
        "confectionery"
    ],
    "wof:name":"Casey's Confenctioners",
    "wof:placetype":"venue"
},
  "geometry": {"coordinates":[-3.186457,55.948505],"type":"Point"}
}