{
  "type": "Feature",
  "properties": {
    "iso:country":"GB",
    "sg:address":"Redgate House, Hoyle Street",
    "sg:city":"Manchester",
    "sg:classifiers":[
        {
            "category":"Building & Trades",
            "subcategory":"Construction",
            "type":"Services"
        }
    ],
    "sg:phone":"+44 161 273 3130",
    "sg:postcode":"M12 6HG",
    "sg:province":"Greater Manchester",
    "sg:tags":[
        "demolition",
        "contractor"
    ],
    "wof:name":"Complete Contractors Ltd.",
    "wof:placetype":"venue"
},
  "geometry": {"coordinates":[-2.223447,53.475048],"type":"Point"}
}