{
  "type": "Feature",
  "properties": {
    "addr:full":"Durkins Road East Grinstead East Sussex RH19 2ER",
    "addr:postcode":"rh19 2er",
    "addr:street":"Durkins Road",
    "iso:country":"GB",
    "sg:address":"Durkins Road",
    "sg:city":"East Grinstead",
    "sg:classifiers":[
        {
            "category":"Wholesale",
            "subcategory":"Machinery & Supplies",
            "type":"Manufacturing & Wholesale Goods"
        }
    ],
    "sg:phone":"+44 1342 327675",
    "sg:postcode":"RH19 2ER",
    "sg:province":"East Sussex",
    "sg:tags":[
        "industrial",
        "commercial"
    ],
    "wof:name":"U K - Worldwide Engineering Ltd.",
    "wof:placetype":"venue"
},
  "geometry": {"coordinates":[-0.014567,51.133961],"type":"Point"}
}