{
  "type": "Feature",
  "properties": {
    "addr:full":"The Bungalow, West Hall Insch Aberdeenshire AB52 6RW",
    "addr:postcode":"ab52 6rw",
    "addr:street":"West Hall",
    "iso:country":"GB",
    "sg:address":"The Bungalow, West Hall",
    "sg:city":"Insch",
    "sg:classifiers":[
        {
            "category":"Building & Trades",
            "subcategory":"Plumbing",
            "type":"Services"
        }
    ],
    "sg:postcode":"AB52 6RW",
    "sg:province":"Aberdeenshire",
    "sg:tags":[
        "heating"
    ],
    "wof:name":"R G Robertson",
    "wof:placetype":"venue"
},
  "geometry": {"coordinates":[-2.6130108833,57.342918396],"type":"Point"}
}