{
  "type": "Feature",
  "properties": {
    "addr:full":"34 North Street Bridgwater Somerset TA6 3YD",
    "addr:housenumber":"34",
    "addr:postcode":"ta6 3yd",
    "addr:street":"North Street",
    "iso:country":"GB",
    "sg:address":"34 North Street",
    "sg:city":"Bridgwater",
    "sg:classifiers":[
        {
            "category":"Communications",
            "type":"Services"
        }
    ],
    "sg:postcode":"TA6 3YD",
    "sg:province":"Somerset",
    "sg:tags":[
        "data",
        "network"
    ],
    "wof:name":"Webnet Data Systems Ltd.",
    "wof:placetype":"venue"
},
  "geometry": {"coordinates":[-3.0101950169,51.1280136108],"type":"Point"}
}