{
  "type": "Feature",
  "properties": {
    "iso:country":"GB",
    "sg:address":"39 Fairoak Av",
    "sg:city":"Stafford",
    "sg:classifiers":[
        {
            "category":"Building & Trades",
            "subcategory":"Construction",
            "type":"Services"
        }
    ],
    "sg:phone":"+44 1785 243684",
    "sg:postcode":"ST16 1LU",
    "sg:province":"Staffordshire",
    "sg:tags":[
        "welder"
    ],
    "wof:name":"Site Welding Services",
    "wof:placetype":"venue"
},
  "geometry": {"coordinates":[-2.126928,52.828972],"type":"Point"}
}