{
  "type": "Feature",
  "properties": {
    "addr:full":"4a Church Lane Banbury Oxfordshire OX16 5LR",
    "addr:housenumber":"4a",
    "addr:postcode":"ox16 5lr",
    "addr:street":"Church Lane",
    "iso:country":"GB",
    "sg:address":"4a Church Lane",
    "sg:city":"Banbury",
    "sg:classifiers":[
        {
            "category":"Food & Beverages",
            "subcategory":"Specialty",
            "type":"Retail Goods"
        }
    ],
    "sg:postcode":"OX16 5LR",
    "sg:province":"Oxfordshire",
    "sg:tags":[
        "product",
        "health"
    ],
    "wof:name":"Natures Harvest",
    "wof:placetype":"venue"
},
  "geometry": {"coordinates":[-1.3385440111,52.0606155396],"type":"Point"}
}