{
  "type": "Feature",
  "properties": {
    "addr:full":"142 Rodney Rd Elephant And Castle Greater London SE17 1RA",
    "addr:housenumber":"142",
    "addr:postcode":"se17 1ra",
    "addr:street":"Rodney Rd",
    "iso:country":"GB",
    "sg:address":"142 Rodney Rd",
    "sg:city":"Elephant And Castle",
    "sg:classifiers":[
        {
            "category":"Place Of Worship",
            "type":"Public Place"
        }
    ],
    "sg:phone":"+44 20 7703 4967",
    "sg:postcode":"SE17 1RA",
    "sg:province":"Greater London",
    "wof:name":"English Martyrs R.C Church",
    "wof:placetype":"venue"
},
  "geometry": {"coordinates":[-0.0885509998,51.4910011292],"type":"Point"}
}