{
  "type": "Feature",
  "properties": {
    "iso:country":"GB",
    "sg:address":"150 Homerton High Street",
    "sg:city":"London",
    "sg:classifiers":[
        {
            "category":"Fast Food",
            "type":"Food & Drink"
        }
    ],
    "sg:postcode":"E9 6JA",
    "sg:province":"Greater London",
    "sg:tags":[
        "away",
        "take"
    ],
    "wof:name":"Oriental Meals",
    "wof:placetype":"venue"
},
  "geometry": {"coordinates":[-0.040555,51.548885],"type":"Point"}
}