{
  "type": "Feature",
  "properties": {
    "iso:country":"GB",
    "sg:address":"4 Crown Lane",
    "sg:city":"London",
    "sg:classifiers":[
        {
            "category":"Bars & Pubs",
            "type":"Food & Drink"
        }
    ],
    "sg:phone":"+44 20 8670 6622",
    "sg:postcode":"SW16 3JG",
    "sg:province":"Greater London",
    "sg:tags":[
        "pubs",
        "inn"
    ],
    "wof:name":"The Rose & Crown",
    "wof:placetype":"venue"
},
  "geometry": {"coordinates":[-0.111034,51.423672],"type":"Point"}
}