{
  "type": "Feature",
  "properties": {
    "iso:country":"GB",
    "sg:address":"20 Keptie St",
    "sg:city":"Arbroath",
    "sg:classifiers":[
        {
            "category":"Building & Trades",
            "subcategory":"Plumbing",
            "type":"Services"
        }
    ],
    "sg:postcode":"DD11 3AF",
    "sg:province":"Angus",
    "sg:tags":[
        "heating"
    ],
    "wof:name":"Cramond Plumbing & Heating Ltd",
    "wof:placetype":"venue"
},
  "geometry": {"coordinates":[-2.6035759449,56.5618400574],"type":"Point"}
}