{
  "type": "Feature",
  "properties": {
    "addr:full":"25 Dunkeld Court, Balfron Glasgow Argyll and Bute G63 0TL",
    "addr:housenumber":"25",
    "addr:postcode":"g63 0tl",
    "addr:street":"Dunkeld Court",
    "iso:country":"GB",
    "sg:address":"25 Dunkeld Court, Balfron",
    "sg:city":"Glasgow",
    "sg:classifiers":[
        {
            "category":"Retail",
            "subcategory":"Laundry & Dry Cleaning",
            "type":"Services"
        }
    ],
    "sg:phone":"+44 1360 440505",
    "sg:postcode":"G63 0TL",
    "sg:province":"Argyll and Bute",
    "sg:tags":[
        "home",
        "ironing"
    ],
    "wof:name":"Drymen Ironing Services",
    "wof:placetype":"venue"
},
  "geometry": {"coordinates":[-4.337354,56.069241],"type":"Point"}
}