{
  "type": "Feature",
  "properties": {
    "iso:country":"GB",
    "sg:address":"Hilton Road, Rosyth",
    "sg:city":"Dunfermline",
    "sg:classifiers":[
        {
            "category":"Organizations",
            "subcategory":"Non-profit Organization",
            "type":"Services"
        }
    ],
    "sg:phone":"+44 1383 419969",
    "sg:postcode":"KY11 2XH",
    "sg:province":"Fife",
    "sg:tags":[
        "organisation",
        "voluntary",
        "charity"
    ],
    "wof:name":"King Georges Fund for Sailors",
    "wof:placetype":"venue"
},
  "geometry": {"coordinates":[-3.4268639088,56.0364265442],"type":"Point"}
}