{
  "type": "Feature",
  "properties": {
    "iso:country":"GB",
    "sg:address":"184 New Road",
    "sg:city":"Rainham",
    "sg:classifiers":[
        {
            "category":"Retail",
            "subcategory":"Auto Rental",
            "type":"Services"
        }
    ],
    "sg:phone":"+44 1708 553541",
    "sg:postcode":"RM13 8RS",
    "sg:province":"Essex",
    "sg:tags":[
        "truck",
        "hire",
        "van"
    ],
    "wof:name":"Ilford Plant Hire & Sales Ltd.",
    "wof:placetype":"venue"
},
  "geometry": {"coordinates":[0.178667,51.523296],"type":"Point"}
}