{
  "type": "Feature",
  "properties": {
    "addr:full":"Glen Rose Fareham Hampshire PO15 5NU",
    "addr:postcode":"po15 5nu",
    "addr:street":"Glen",
    "iso:country":"GB",
    "sg:address":"Glen Rose",
    "sg:city":"Fareham",
    "sg:classifiers":[
        {
            "category":"Health Services",
            "subcategory":"Nursing And Care Facility",
            "type":"Services"
        }
    ],
    "sg:phone":"+44 1329 511155",
    "sg:postcode":"PO15 5NU",
    "sg:province":"Hampshire",
    "sg:tags":[
        "home"
    ],
    "wof:name":"Glen Care Homes Ltd.",
    "wof:placetype":"venue"
},
  "geometry": {"coordinates":[-1.2257100344,50.8510894775],"type":"Point"}
}