{
  "type": "Feature",
  "properties": {
    "addr:full":"9 Church St, Stratford Stratford Greater London E15 3HU",
    "addr:housenumber":"9",
    "addr:postcode":"e15 3hu",
    "addr:street":"Church St",
    "iso:country":"GB",
    "sg:address":"9 Church St, Stratford",
    "sg:city":"Stratford",
    "sg:classifiers":[
        {
            "category":"Taxi",
            "type":"Transportation"
        }
    ],
    "sg:phone":"+44 20 8534 1066",
    "sg:postcode":"E15 3HU",
    "sg:province":"Greater London",
    "sg:tags":[
        "mini",
        "cab"
    ],
    "wof:name":"Access Cars",
    "wof:placetype":"venue"
},
  "geometry": {"coordinates":[0.007546,51.536167],"type":"Point"}
}