{
  "type": "Feature",
  "properties": {
    "addr:full":"211 High Road, Harrow Weald Harrow Greater London HA3 5EE",
    "addr:housenumber":"211",
    "addr:postcode":"ha3 5ee",
    "addr:street":"High Road",
    "iso:country":"GB",
    "sg:address":"211 High Road, Harrow Weald",
    "sg:city":"Harrow",
    "sg:classifiers":[
        {
            "category":"Shopping",
            "subcategory":"Pharmacy",
            "type":"Retail Goods"
        }
    ],
    "sg:phone":"+44 20 8427 1067",
    "sg:postcode":"HA3 5EE",
    "sg:province":"Greater London",
    "sg:tags":[
        "pharmacist",
        "chemist"
    ],
    "wof:name":"Radias Dispensing Chemist",
    "wof:placetype":"venue"
},
  "geometry": {"coordinates":[-0.336989,51.59782],"type":"Point"}
}