{
  "type": "Feature",
  "properties": {
    "iso:country":"GB",
    "sg:address":"46 Station Road, Mickleover",
    "sg:city":"Derby",
    "sg:classifiers":[
        {
            "category":"Shopping",
            "subcategory":"Pharmacy",
            "type":"Retail Goods"
        }
    ],
    "sg:postcode":"DE3 9GH",
    "sg:province":"Derbyshire",
    "sg:tags":[
        "pharmacist",
        "chemist"
    ],
    "wof:name":"P J Singleton",
    "wof:placetype":"venue"
},
  "geometry": {"coordinates":[-1.5443890095,52.9074401855],"type":"Point"}
}