{
  "type": "Feature",
  "properties": {
    "iso:country":"GB",
    "sg:address":"Thurstaston Rd, Irby",
    "sg:city":"Wirral",
    "sg:classifiers":[
        {
            "category":"Education",
            "subcategory":"Library",
            "type":"Public Place"
        }
    ],
    "sg:phone":"+44 151 648 1348",
    "sg:postcode":"CH61 0HE",
    "sg:province":"Merseyside",
    "sg:tags":[
        "book"
    ],
    "wof:name":"Irby Library",
    "wof:placetype":"venue"
},
  "geometry": {"coordinates":[-3.128288,53.354492],"type":"Point"}
}