{
  "type": "Feature",
  "properties": {
    "addr:full":"12 Solway Street, Silloth Wigton Cumbria CA7 4AR",
    "addr:housenumber":"12",
    "addr:postcode":"ca7 4ar",
    "addr:street":"Solway Street",
    "iso:country":"GB",
    "sg:address":"12 Solway Street, Silloth",
    "sg:city":"Wigton",
    "sg:classifiers":[
        {
            "category":"Fast Food",
            "type":"Food & Drink"
        },
        {
            "category":"Food & Beverages",
            "subcategory":"Groceries & Convenience Stores",
            "type":"Retail Goods"
        }
    ],
    "sg:phone":"+44 16973 31597",
    "sg:postcode":"CA7 4AR",
    "sg:province":"Cumbria",
    "sg:tags":[
        "shop",
        "fish",
        "take",
        "chip",
        "away"
    ],
    "wof:name":"John's Plaice",
    "wof:placetype":"venue"
},
  "geometry": {"coordinates":[-3.386619091,54.868560791],"type":"Point"}
}