{
  "type": "Feature",
  "properties": {
    "addr:full":"16 Elm Tree Avenue Frinton-on-sea Essex CO13 0BE",
    "addr:housenumber":"16",
    "addr:postcode":"co13 0be",
    "addr:street":"Elm Tree Avenue",
    "iso:country":"GB",
    "sg:address":"16 Elm Tree Avenue",
    "sg:city":"Frinton-on-sea",
    "sg:classifiers":[
        {
            "category":"Retail",
            "subcategory":"Driving School",
            "type":"Services"
        }
    ],
    "sg:phone":"+44 1255 673762",
    "sg:postcode":"CO13 0BE",
    "sg:province":"Essex",
    "wof:name":"1ST Gear Driving School",
    "wof:placetype":"venue"
},
  "geometry": {"coordinates":[1.2451239824,51.8389472961],"type":"Point"}
}