{
  "type": "Feature",
  "properties": {
    "addr:full":"25 Floral Street, Covent Gardens London Greater London WC2E 9TE",
    "addr:housenumber":"25",
    "addr:postcode":"wc2e 9te",
    "addr:street":"Floral Street Covent Gardens",
    "iso:country":"GB",
    "sg:address":"25 Floral Street, Covent Gardens",
    "sg:city":"London",
    "sg:classifiers":[
        {
            "category":"Real Estate",
            "subcategory":"Real Estate Agent",
            "type":"Services"
        }
    ],
    "sg:phone":"+44 1306 651800",
    "sg:postcode":"WC2E 9TE",
    "sg:province":"Greater London",
    "wof:name":"F&C Property Investments Ltd.",
    "wof:placetype":"venue"
},
  "geometry": {"coordinates":[-0.1253490001,51.5119285583],"type":"Point"}
}