{
  "type": "Feature",
  "properties": {
    "addr:full":"30 Withy Close Trowbridge Wiltshire BA14 7NB",
    "addr:housenumber":"30",
    "addr:postcode":"ba14 7nb",
    "addr:street":"Withy Close",
    "iso:country":"GB",
    "sg:address":"30 Withy Close",
    "sg:city":"Trowbridge",
    "sg:classifiers":[
        {
            "category":"Autos & Motor Vehicles",
            "subcategory":"Auto Supplies",
            "type":"Retail Goods"
        }
    ],
    "sg:postcode":"BA14 7NB",
    "sg:province":"Wiltshire",
    "sg:tags":[
        "component"
    ],
    "wof:name":"Cleanwell Services Ltd",
    "wof:placetype":"venue"
},
  "geometry": {"coordinates":[-2.20074296,51.3330802917],"type":"Point"}
}