{
  "type": "Feature",
  "properties": {
    "addr:full":"The Weighbridge, Old Colliery Yard, Sacriston Durham Durham DH7 6AN",
    "addr:postcode":"dh7 6an",
    "addr:street":"Old Colliery Yard",
    "iso:country":"GB",
    "sg:address":"The Weighbridge, Old Colliery Yard, Sacriston",
    "sg:city":"Durham",
    "sg:classifiers":[
        {
            "category":"Wholesale",
            "subcategory":"Scrap",
            "type":"Manufacturing & Wholesale Goods"
        }
    ],
    "sg:postcode":"DH7 6AN",
    "sg:province":"Durham",
    "sg:tags":[
        "breaker",
        "dismantlers"
    ],
    "wof:name":"Peugeot Spares",
    "wof:placetype":"venue"
},
  "geometry": {"coordinates":[-1.626584053,54.81772995],"type":"Point"}
}