{
  "type": "Feature",
  "properties": {
    "addr:full":"Riverbank Ho, 1 Putney Bridge Approach Fulham Greater London SW6 3JD",
    "addr:housenumber":"1",
    "addr:postcode":"sw6 3jd",
    "addr:street":"Putney Bridge Approach",
    "iso:country":"GB",
    "sg:address":"Riverbank Ho, 1 Putney Bridge Approach",
    "sg:city":"Fulham",
    "sg:classifiers":[
        {
            "category":"Professional",
            "subcategory":"Management & Consulting",
            "type":"Services"
        }
    ],
    "sg:phone":"+44 20 7736 7633",
    "sg:postcode":"SW6 3JD",
    "sg:province":"Greater London",
    "sg:tags":[
        "marketing",
        "consultant"
    ],
    "wof:name":"Licensing & Marketing Group",
    "wof:placetype":"venue"
},
  "geometry": {"coordinates":[-0.21078,51.468658],"type":"Point"}
}