{
  "type": "Feature",
  "properties": {
    "addr:full":"4a The Score, Northgate Beccles Norfolk NR34 9AR",
    "addr:housenumber":"4a",
    "addr:postcode":"nr34 9ar",
    "addr:street":"The;Northgate",
    "iso:country":"GB",
    "sg:address":"4a The Score, Northgate",
    "sg:city":"Beccles",
    "sg:classifiers":[
        {
            "category":"Organizations",
            "subcategory":"Non-profit Organization",
            "type":"Services"
        }
    ],
    "sg:phone":"+44 1502 710777",
    "sg:postcode":"NR34 9AR",
    "sg:province":"Norfolk",
    "sg:tags":[
        "charitable",
        "organisation",
        "voluntary",
        "charity"
    ],
    "wof:name":"Beccles & District Volunteer Centre",
    "wof:placetype":"venue"
},
  "geometry": {"coordinates":[1.5625749826,52.459854126],"type":"Point"}
}