{
  "type": "Feature",
  "properties": {
    "iso:country":"GB",
    "sg:address":"104 Edinburgh Street",
    "sg:city":"Goole",
    "sg:classifiers":[
        {
            "category":"Food & Beverages",
            "subcategory":"Bakery",
            "type":"Retail Goods"
        }
    ],
    "sg:phone":"+44 1405 767223",
    "sg:postcode":"DN14 5EH",
    "sg:province":"East Riding of Yorkshire",
    "sg:tags":[
        "baker"
    ],
    "wof:name":"Fullers Quality Bakers",
    "wof:placetype":"venue"
},
  "geometry": {"coordinates":[-0.866309,53.705292],"type":"Point"}
}