{
  "type": "Feature",
  "properties": {
    "iso:country":"GB",
    "sg:address":"Riverside Primary School, Janeway Street",
    "sg:city":"London",
    "sg:classifiers":[
        {
            "category":"Education",
            "subcategory":"School",
            "type":"Public Place"
        },
        {
            "category":"Government",
            "subcategory":"Office",
            "type":"Public Place"
        }
    ],
    "sg:phone":"+44 20 7231 9795",
    "sg:postcode":"SE16 4PS",
    "sg:province":"Greater London",
    "sg:tags":[
        "local",
        "authority"
    ],
    "wof:name":"Riverside After School Club",
    "wof:placetype":"venue"
},
  "geometry": {"coordinates":[-0.0638699979,51.4990997314],"type":"Point"}
}