{
  "type": "Feature",
  "properties": {
    "addr:full":"16 Kiln Close, Sandford On Thames Oxford Oxfordshire OX4 4YS",
    "addr:housenumber":"16",
    "addr:postcode":"ox4 4ys",
    "addr:street":"Kiln Close",
    "iso:country":"GB",
    "sg:address":"16 Kiln Close, Sandford On Thames",
    "sg:city":"Oxford",
    "sg:classifiers":[
        {
            "category":"Building & Trades",
            "subcategory":"Construction",
            "type":"Services"
        }
    ],
    "sg:postcode":"OX4 4YS",
    "sg:province":"Oxfordshire",
    "sg:tags":[
        "glazier"
    ],
    "wof:name":"A A Glazing",
    "wof:placetype":"venue"
},
  "geometry": {"coordinates":[-1.2202500105,51.7121925354],"type":"Point"}
}