{
  "type": "Feature",
  "properties": {
    "iso:country":"GB",
    "sg:address":"Longridge, Hepscott",
    "sg:city":"Morpeth",
    "sg:classifiers":[
        {
            "category":"Retail",
            "subcategory":"Repair Shop",
            "type":"Services"
        },
        {
            "category":"Home & Garden",
            "subcategory":"Carpets & Floor Coverings",
            "type":"Retail Goods"
        }
    ],
    "sg:phone":"+44 1670 514266",
    "sg:postcode":"NE61 6LT",
    "sg:province":"Northumberland",
    "sg:tags":[
        "wall",
        "tie",
        "maintenance",
        "replacement"
    ],
    "wof:name":"British Remedial Wall Tie Services",
    "wof:placetype":"venue"
},
  "geometry": {"coordinates":[-1.6570390463,55.1465339661],"type":"Point"}
}