{
  "type": "Feature",
  "properties": {
    "addr:full":"7 Waterside Business Park, Eastways Witham Essex CM8 3YQ",
    "addr:housenumber":"7",
    "addr:postcode":"cm8 3yq",
    "addr:street":"Waterside Business Park Eastways Witham",
    "iso:country":"GB",
    "sg:address":"7 Waterside Business Park, Eastways",
    "sg:city":"Witham",
    "sg:classifiers":[
        {
            "category":"Professional",
            "subcategory":"Engineering",
            "type":"Services"
        }
    ],
    "sg:phone":"+44 1376 515515",
    "sg:postcode":"CM8 3YQ",
    "sg:province":"Essex",
    "wof:name":"Doel Engineering Ltd.",
    "wof:placetype":"venue"
},
  "geometry": {"coordinates":[0.65287,51.810749],"type":"Point"}
}