{
  "type": "Feature",
  "properties": {
    "addr:full":"11 St George Street London Greater London W1S 2FD",
    "addr:housenumber":"11",
    "addr:postcode":"w1s 2fd",
    "addr:street":"St George Street",
    "iso:country":"GB",
    "sg:address":"11 St George Street",
    "sg:city":"London",
    "sg:classifiers":[
        {
            "category":"Personal",
            "type":"Services"
        }
    ],
    "sg:phone":"+44 20 7629 5047",
    "sg:postcode":"W1S 2FD",
    "sg:province":"Greater London",
    "sg:tags":[
        "tailor"
    ],
    "wof:name":"Wells",
    "wof:placetype":"venue"
},
  "geometry": {"coordinates":[-0.1432040036,51.5125236511],"type":"Point"}
}