{
  "type": "Feature",
  "properties": {
    "addr:full":"34 Station Street, Kirkby In Ashfield Nottingham Nottinghamshire NG17 7AS",
    "addr:housenumber":"34",
    "addr:postcode":"ng17 7as",
    "addr:street":"Station Street",
    "iso:country":"GB",
    "sg:address":"34 Station Street, Kirkby In Ashfield",
    "sg:city":"Nottingham",
    "sg:classifiers":[
        {
            "category":"Retail",
            "subcategory":"Repair Shop",
            "type":"Services"
        },
        {
            "category":"Manufacturing",
            "subcategory":"Building Materials",
            "type":"Manufacturing & Wholesale Goods"
        }
    ],
    "sg:postcode":"NG17 7AS",
    "sg:province":"Nottinghamshire",
    "sg:tags":[
        "mnfr",
        "loose",
        "cover",
        "upholsterer"
    ],
    "wof:name":"The Cover Co",
    "wof:placetype":"venue"
},
  "geometry": {"coordinates":[-1.2468190193,53.0990982056],"type":"Point"}
}