{
  "type": "Feature",
  "properties": {
    "addr:full":"Birmingham & Midland Institute, Margaret Street Birmingham West Midlands B3 3BT",
    "addr:postcode":"b3 3bt",
    "addr:street":"Margaret Street",
    "iso:country":"GB",
    "sg:address":"Birmingham & Midland Institute, Margaret Street",
    "sg:city":"Birmingham",
    "sg:classifiers":[
        {
            "category":"Real Estate",
            "subcategory":"Surveying",
            "type":"Services"
        }
    ],
    "sg:phone":"+44 121 236 7241",
    "sg:postcode":"B3 3BT",
    "sg:province":"West Midlands",
    "sg:tags":[
        "surveyor",
        "valuer"
    ],
    "wof:name":"Royal Institution of Chartered Surveyors",
    "wof:placetype":"venue"
},
  "geometry": {"coordinates":[-1.90402,52.481419],"type":"Point"}
}