{
  "type": "Feature",
  "properties": {
    "iso:country":"GB",
    "sg:address":"3 First Avenue",
    "sg:city":"Clacton-on-sea",
    "sg:classifiers":[
        {
            "category":"Building & Trades",
            "subcategory":"Construction",
            "type":"Services"
        }
    ],
    "sg:phone":"+44 1255 420146",
    "sg:postcode":"CO15 5AH",
    "sg:province":"Essex",
    "sg:tags":[
        "joiner",
        "carpenter"
    ],
    "wof:name":"F R Spiller",
    "wof:placetype":"venue"
},
  "geometry": {"coordinates":[1.172637,51.794979],"type":"Point"}
}