{
  "type": "Feature",
  "properties": {
    "addr:full":"Unit 4 Banford Precinct, Nordon Rd Rochdale Lancashire OL11 5NT",
    "addr:housenumber":"unit 4",
    "addr:postcode":"ol11 5nt",
    "addr:street":"Nordon Rd",
    "iso:country":"GB",
    "sg:address":"Unit 4 Banford Precinct, Nordon Rd",
    "sg:city":"Rochdale",
    "sg:classifiers":[
        {
            "category":"Personal",
            "subcategory":"Beauty Salon",
            "type":"Services"
        }
    ],
    "sg:phone":"+44 1706 526472",
    "sg:postcode":"OL11 5NT",
    "sg:province":"Lancashire",
    "sg:tags":[
        "unisex",
        "hairdresser"
    ],
    "wof:name":"Village Hair & Beauty Studio The",
    "wof:placetype":"venue"
},
  "geometry": {"coordinates":[-2.2089040279,53.6144714355],"type":"Point"}
}