{
  "type": "Feature",
  "properties": {
    "addr:full":"8 Queens Pde, Queens Rd Hendon Greater London NW4 3NS",
    "addr:housenumber":"8",
    "addr:postcode":"nw4 3ns",
    "addr:street":"Queens Pde Queens Rd",
    "iso:country":"GB",
    "sg:address":"8 Queens Pde, Queens Rd",
    "sg:city":"Hendon",
    "sg:classifiers":[
        {
            "category":"Shopping",
            "subcategory":"Pharmacy",
            "type":"Retail Goods"
        }
    ],
    "sg:phone":"+44 20 8202 1288",
    "sg:postcode":"NW4 3NS",
    "sg:province":"Greater London",
    "sg:tags":[
        "medicine",
        "therapy"
    ],
    "wof:name":"Hendon Traditional Chinese Medicine Centre",
    "wof:placetype":"venue"
},
  "geometry": {"coordinates":[-0.226631,51.582748],"type":"Point"}
}