{
  "type": "Feature",
  "properties": {
    "addr:full":"101 Briarmeads, Oadby Leicester Leicestershire LE2 5WE",
    "addr:housenumber":"101",
    "addr:postcode":"le2 5we",
    "addr:street":"Briarmeads",
    "iso:country":"GB",
    "sg:address":"101 Briarmeads, Oadby",
    "sg:city":"Leicester",
    "sg:classifiers":[
        {
            "category":"Transit Center",
            "subcategory":"Freight",
            "type":"Transportation"
        }
    ],
    "sg:phone":"+44 116 272 1500",
    "sg:postcode":"LE2 5WE",
    "sg:province":"Leicestershire",
    "sg:tags":[
        "piano",
        "accessory"
    ],
    "wof:name":"Richard Young Pianos",
    "wof:placetype":"venue"
},
  "geometry": {"coordinates":[-1.0793839693,52.5897521973],"type":"Point"}
}