{
  "type": "Feature",
  "properties": {
    "iso:country":"GB",
    "sg:address":"Stand 176 Grays Antique Market, 58 Davies Street",
    "sg:city":"London",
    "sg:classifiers":[
        {
            "category":"Shopping",
            "subcategory":"Comic Books",
            "type":"Retail Goods"
        }
    ],
    "sg:phone":"+44 20 7495 0592",
    "sg:postcode":"W1K 5LP",
    "sg:province":"Greater London",
    "sg:tags":[
        "jeweller"
    ],
    "wof:name":"Finishing Touch",
    "wof:placetype":"venue"
},
  "geometry": {"coordinates":[-0.14861,51.513401],"type":"Point"}
}