{
  "type": "Feature",
  "properties": {
    "addr:full":"Station Road, Hatton Warwick Warwickshire CV35 7LH",
    "addr:postcode":"cv35 7lh",
    "addr:street":"Station Road Hatton",
    "iso:country":"GB",
    "sg:address":"Station Road, Hatton",
    "sg:city":"Warwick",
    "sg:classifiers":[
        {
            "category":"Professional",
            "subcategory":"Business Services",
            "type":"Services"
        }
    ],
    "sg:postcode":"CV35 7LH",
    "sg:province":"Warwickshire",
    "sg:tags":[
        "accomodation"
    ],
    "wof:name":"Oakslade",
    "wof:placetype":"venue"
},
  "geometry": {"coordinates":[-1.65849,52.303143],"type":"Point"}
}