{
  "type": "Feature",
  "properties": {
    "addr:full":"Northgate Farm, Northgate Lane, Ellisfield Basingstoke Hampshire RG25 2QT",
    "addr:postcode":"rg25 2qt",
    "addr:street":"Northgate;Northgate Lane",
    "iso:country":"GB",
    "sg:address":"Northgate Farm, Northgate Lane, Ellisfield",
    "sg:city":"Basingstoke",
    "sg:classifiers":[
        {
            "category":"Shopping",
            "subcategory":"Pets & Pet Supplies",
            "type":"Retail Goods"
        }
    ],
    "sg:phone":"+44 1256 381230",
    "sg:postcode":"RG25 2QT",
    "sg:province":"Hampshire",
    "wof:name":"Northgate Kennels & Cattery",
    "wof:placetype":"venue"
},
  "geometry": {"coordinates":[-1.0902719498,51.2125473022],"type":"Point"}
}