{
  "type": "Feature",
  "properties": {
    "addr:full":"4 Abberley Park, Stockton Rd Worcester Herefordshire WR6 6AW",
    "addr:housenumber":"4",
    "addr:postcode":"wr6 6aw",
    "addr:street":"Abberley Park Stockton Rd",
    "iso:country":"GB",
    "sg:address":"4 Abberley Park, Stockton Rd",
    "sg:city":"Worcester",
    "sg:classifiers":[
        {
            "category":"Shopping",
            "subcategory":"Clothing, Apparel, & Fashions",
            "type":"Retail Goods"
        }
    ],
    "sg:phone":"+44 1299 896902",
    "sg:postcode":"WR6 6AW",
    "sg:province":"Herefordshire",
    "sg:tags":[
        "dresswear"
    ],
    "wof:name":"Frock Around The Clock",
    "wof:placetype":"venue"
},
  "geometry": {"coordinates":[-2.3821599483,52.3025093079],"type":"Point"}
}