{
  "type": "Feature",
  "properties": {
    "addr:full":"1 Sandell Street London Greater London SE1 8UH",
    "addr:housenumber":"1",
    "addr:postcode":"se1 8uh",
    "addr:street":"Sandell Street",
    "iso:country":"GB",
    "sg:address":"1 Sandell Street",
    "sg:city":"London",
    "sg:classifiers":[
        {
            "category":"Restaurant",
            "type":"Food & Drink"
        }
    ],
    "sg:phone":"+44 20 7633 0610",
    "sg:postcode":"SE1 8UH",
    "sg:province":"Greater London",
    "sg:tags":[
        "french"
    ],
    "wof:name":"Auberge",
    "wof:placetype":"venue"
},
  "geometry": {"coordinates":[-0.110919,51.503773],"type":"Point"}
}