{
  "type": "Feature",
  "properties": {
    "addr:full":"Newport House, Topsham Road Exeter Devon EX2 7DT",
    "addr:postcode":"ex2 7dt",
    "addr:street":"Topsham Road",
    "iso:country":"GB",
    "sg:address":"Newport House, Topsham Road",
    "sg:city":"Exeter",
    "sg:classifiers":[
        {
            "category":"Real Estate",
            "subcategory":"Real Estate Agent",
            "type":"Services"
        }
    ],
    "sg:phone":"+44 1392 874411",
    "sg:postcode":"EX2 7DT",
    "sg:province":"Devon",
    "wof:name":"Fox Leisure (Exeter) Ltd.",
    "wof:placetype":"venue"
},
  "geometry": {"coordinates":[-3.4920990467,50.6996841431],"type":"Point"}
}