{
  "type": "Feature",
  "properties": {
    "addr:full":"Unit 12 Phoenix Centre, Watling Street, Bridgtown Cannock Staffordshire WS11 3BN",
    "addr:housenumber":"unit 12",
    "addr:postcode":"ws11 3bn",
    "addr:street":"Phoenix Centre Watling Street",
    "iso:country":"GB",
    "sg:address":"Unit 12 Phoenix Centre, Watling Street, Bridgtown",
    "sg:city":"Cannock",
    "sg:classifiers":[
        {
            "category":"Autos & Motor Vehicles",
            "subcategory":"Auto Supplies",
            "type":"Retail Goods"
        }
    ],
    "sg:phone":"+44 1543 462490",
    "sg:postcode":"WS11 3BN",
    "sg:province":"Staffordshire",
    "sg:tags":[
        "tyre"
    ],
    "wof:name":"Tyre Sales (Birmingham) Ltd.",
    "wof:placetype":"venue"
},
  "geometry": {"coordinates":[-2.025671,52.683681],"type":"Point"}
}