{
  "type": "Feature",
  "properties": {
    "addr:full":"40 St Michaels Road Yeovil Somerset BA21 5AG",
    "addr:housenumber":"40",
    "addr:postcode":"ba21 5ag",
    "addr:street":"St Michaels Road",
    "iso:country":"GB",
    "sg:address":"40 St Michaels Road",
    "sg:city":"Yeovil",
    "sg:classifiers":[
        {
            "category":"Personal",
            "type":"Services"
        }
    ],
    "sg:postcode":"BA21 5AG",
    "sg:province":"Somerset",
    "sg:tags":[
        "dressmaker"
    ],
    "wof:name":"Tricia Gowns",
    "wof:placetype":"venue"
},
  "geometry": {"coordinates":[-2.6176829338,50.9474029541],"type":"Point"}
}