{
  "type": "Feature",
  "properties": {
    "iso:country":"GB",
    "sg:address":"Wolverton Rd, Great Linford",
    "sg:city":"Milton Keynes",
    "sg:classifiers":[
        {
            "category":"Professional",
            "subcategory":"Management & Consulting",
            "type":"Services"
        }
    ],
    "sg:phone":"+44 1908 604810",
    "sg:postcode":"MK14 5AH",
    "sg:province":"Buckinghamshire",
    "sg:tags":[
        "conservation"
    ],
    "wof:name":"ARC Environmental Study Centre",
    "wof:placetype":"venue"
},
  "geometry": {"coordinates":[-0.755194,52.06477],"type":"Point"}
}