{
  "type": "Feature",
  "properties": {
    "addr:full":"The Red Cow Paddock, Church Street, Donington Spalding Lincolnshire PE11 4UA",
    "addr:postcode":"pe11 4ua",
    "addr:street":"Church Street",
    "iso:country":"GB",
    "sg:address":"The Red Cow Paddock, Church Street, Donington",
    "sg:city":"Spalding",
    "sg:classifiers":[
        {
            "category":"Organizations",
            "subcategory":"Non-profit Organization",
            "type":"Services"
        }
    ],
    "sg:phone":"+44 1775 821257",
    "sg:postcode":"PE11 4UA",
    "sg:province":"Lincolnshire",
    "sg:tags":[
        "organisation",
        "voluntary",
        "charity"
    ],
    "wof:name":"Donington Pop-in Centre",
    "wof:placetype":"venue"
},
  "geometry": {"coordinates":[-0.198248,52.904034],"type":"Point"}
}