{
  "type": "Feature",
  "properties": {
    "iso:country":"GB",
    "sg:address":"26 Archibald Road",
    "sg:city":"London",
    "sg:classifiers":[
        {
            "category":"Building & Trades",
            "subcategory":"Construction",
            "type":"Services"
        }
    ],
    "sg:phone":"+44 20 7281 6976",
    "sg:postcode":"N7 0AL",
    "sg:province":"Greater London",
    "sg:tags":[
        "decorator",
        "painter"
    ],
    "wof:name":"Highcliffe Building Contractors",
    "wof:placetype":"venue"
},
  "geometry": {"coordinates":[-0.1318890005,51.5557746887],"type":"Point"}
}