{
  "type": "Feature",
  "properties": {
    "iso:country":"GB",
    "sg:address":"396-398 Corporation Road",
    "sg:city":"Newport",
    "sg:classifiers":[
        {
            "category":"Manufacturing",
            "subcategory":"Building Materials",
            "type":"Manufacturing & Wholesale Goods"
        }
    ],
    "sg:phone":"+44 1633 214158",
    "sg:postcode":"NP19 0GA",
    "sg:province":"Newport",
    "sg:tags":[
        "merchant",
        "builder"
    ],
    "wof:name":"Faber & Smith Ltd.",
    "wof:placetype":"venue"
},
  "geometry": {"coordinates":[-2.9750769138,51.5828895569],"type":"Point"}
}