{
  "type": "Feature",
  "properties": {
    "addr:full":"Cavendish Rd Blackpool Lancashire FY2 9JR",
    "addr:postcode":"fy2 9jr",
    "addr:street":"Cavendish Rd",
    "iso:country":"GB",
    "sg:address":"Cavendish Rd",
    "sg:city":"Blackpool",
    "sg:classifiers":[
        {
            "category":"Place Of Worship",
            "type":"Public Place"
        },
        {
            "category":"Organizations",
            "subcategory":"Religious Organization",
            "type":"Services"
        }
    ],
    "sg:phone":"+44 1253 358131",
    "sg:postcode":"FY2 9JR",
    "sg:province":"Lancashire",
    "sg:tags":[
        "organisation"
    ],
    "wof:name":"Bispham United Reformed Church",
    "wof:placetype":"venue"
},
  "geometry": {"coordinates":[-3.042398,53.850983],"type":"Point"}
}