{
  "type": "Feature",
  "properties": {
    "iso:country":"GB",
    "sg:address":"156a High Street",
    "sg:city":"Uckfield",
    "sg:classifiers":[
        {
            "category":"Professional",
            "subcategory":"Lawyer & Legal Services",
            "type":"Services"
        }
    ],
    "sg:phone":"+44 1825 763334",
    "sg:postcode":"TN22 1AT",
    "sg:province":"East Sussex",
    "sg:tags":[
        "solicitor"
    ],
    "wof:name":"David Renshaw & Co",
    "wof:placetype":"venue"
},
  "geometry": {"coordinates":[0.09682,50.971668],"type":"Point"}
}