{
  "type": "Feature",
  "properties": {
    "iso:country":"GB",
    "sg:address":"1 Mainwaring Drive, Saltney Ferry",
    "sg:city":"Chester",
    "sg:classifiers":[
        {
            "category":"Personal",
            "subcategory":"Beauty Salon",
            "type":"Services"
        },
        {
            "category":"Personal",
            "subcategory":"Barber",
            "type":"Services"
        }
    ],
    "sg:phone":"+44 1244 683800",
    "sg:postcode":"CH4 0AX",
    "sg:province":"Cheshire",
    "sg:tags":[
        "unisex",
        "hairdresser"
    ],
    "wof:name":"Locks",
    "wof:placetype":"venue"
},
  "geometry": {"coordinates":[-2.94276,53.176147],"type":"Point"}
}