{
  "type": "Feature",
  "properties": {
    "addr:full":"Unit 10, Kensington Road Coventry West Midlands CV5 6GG",
    "addr:housenumber":"unit 10",
    "addr:postcode":"cv5 6gg",
    "addr:street":"Kensington Road",
    "iso:country":"GB",
    "sg:address":"Unit 10, Kensington Road",
    "sg:city":"Coventry",
    "sg:classifiers":[
        {
            "category":"Manufacturing",
            "subcategory":"Watercraft",
            "type":"Manufacturing & Wholesale Goods"
        }
    ],
    "sg:phone":"+44 24 7671 1716",
    "sg:postcode":"CV5 6GG",
    "sg:province":"West Midlands",
    "sg:tags":[
        "repairer",
        "sailmaker"
    ],
    "wof:name":"Edge One-Design",
    "wof:placetype":"venue"
},
  "geometry": {"coordinates":[-1.5273849964,52.4028511047],"type":"Point"}
}