{
  "type": "Feature",
  "properties": {
    "addr:full":"254 Stapleton Rd Bristol City of Bristol BS5 0NP",
    "addr:housenumber":"254",
    "addr:postcode":"bs5 0np",
    "addr:street":"Stapleton Rd",
    "iso:country":"GB",
    "sg:address":"254 Stapleton Rd",
    "sg:city":"Bristol",
    "sg:classifiers":[
        {
            "category":"Professional",
            "subcategory":"Lawyer & Legal Services",
            "type":"Services"
        }
    ],
    "sg:phone":"+44 117 952 2544",
    "sg:postcode":"BS5 0NP",
    "sg:province":"City of Bristol",
    "sg:tags":[
        "solicitor"
    ],
    "wof:name":"Bobbetts Mackan Law Shop",
    "wof:placetype":"venue"
},
  "geometry": {"coordinates":[-2.5693199635,51.4660491943],"type":"Point"}
}