{
  "type": "Feature",
  "properties": {
    "addr:full":"300 Derby Road Ripley Derbyshire DE5 8JN",
    "addr:housenumber":"300",
    "addr:postcode":"de5 8jn",
    "addr:street":"Derby Road",
    "iso:country":"GB",
    "sg:address":"300 Derby Road",
    "sg:city":"Ripley",
    "sg:classifiers":[
        {
            "category":"Retail",
            "subcategory":"Auto Repair",
            "type":"Services"
        }
    ],
    "sg:phone":"+44 1773 570470",
    "sg:postcode":"DE5 8JN",
    "sg:province":"Derbyshire",
    "sg:tags":[
        "modification",
        "garage",
        "related"
    ],
    "wof:name":"Marehay Garage Ltd",
    "wof:placetype":"venue"
},
  "geometry": {"coordinates":[-1.405933,53.03223],"type":"Point"}
}