{
  "type": "Feature",
  "properties": {
    "addr:full":"The Cottage, Clarkes Hill, White Field Manchester Lancashire M45 7TG",
    "addr:postcode":"m45 7tg",
    "addr:street":"Clarkes Hill White Field",
    "iso:country":"GB",
    "sg:address":"The Cottage, Clarkes Hill, White Field",
    "sg:city":"Manchester",
    "sg:classifiers":[
        {
            "category":"Building & Trades",
            "subcategory":"Construction",
            "type":"Services"
        }
    ],
    "sg:postcode":"M45 7TG",
    "sg:province":"Lancashire",
    "sg:tags":[
        "builder"
    ],
    "wof:name":"D & M Ashton",
    "wof:placetype":"venue"
},
  "geometry": {"coordinates":[-2.3215699196,53.5453681946],"type":"Point"}
}