{
  "type": "Feature",
  "properties": {
    "addr:full":"96 Lowfield Street Dartford Kent DA1 1HS",
    "addr:housenumber":"96",
    "addr:postcode":"da1 1hs",
    "addr:street":"Lowfield Street",
    "iso:country":"GB",
    "sg:address":"96 Lowfield Street",
    "sg:city":"Dartford",
    "sg:classifiers":[
        {
            "category":"Personal",
            "subcategory":"Beauty Salon",
            "type":"Services"
        }
    ],
    "sg:postcode":"DA1 1HS",
    "sg:province":"Kent",
    "sg:tags":[
        "unisex",
        "hairdresser"
    ],
    "wof:name":"Changes",
    "wof:placetype":"venue"
},
  "geometry": {"coordinates":[0.215828,51.441502],"type":"Point"}
}