{
  "type": "Feature",
  "properties": {
    "addr:full":"9a High Street, Topsham Exeter Devon EX3 0EA",
    "addr:housenumber":"9a",
    "addr:postcode":"ex3 0ea",
    "addr:street":"High Street",
    "iso:country":"GB",
    "sg:address":"9a High Street, Topsham",
    "sg:city":"Exeter",
    "sg:classifiers":[
        {
            "category":"Health Services",
            "subcategory":"Nursing And Care Facility",
            "type":"Services"
        }
    ],
    "sg:phone":"+44 1392 876700",
    "sg:postcode":"EX3 0EA",
    "sg:province":"Devon",
    "sg:tags":[
        "agency"
    ],
    "wof:name":"Partners in Care",
    "wof:placetype":"venue"
},
  "geometry": {"coordinates":[-3.4679419994,50.6870765686],"type":"Point"}
}