{
  "type": "Feature",
  "properties": {
    "iso:country":"GB",
    "sg:address":"Layton Burroughs, Off Layton Avenue",
    "sg:city":"Mansfield",
    "sg:classifiers":[
        {
            "category":"Organizations",
            "subcategory":"Community Association",
            "type":"Services"
        }
    ],
    "sg:phone":"+44 1623 420480",
    "sg:postcode":"NG18 5PY",
    "sg:province":"Nottinghamshire",
    "sg:tags":[
        "society",
        "housing"
    ],
    "wof:name":"Leicester Housing Association Ltd.",
    "wof:placetype":"venue"
},
  "geometry": {"coordinates":[-1.205498,53.144775],"type":"Point"}
}