{
  "type": "Feature",
  "properties": {
    "addr:full":"Unit 37, Gyle Shopping Centre, 60 Gyle Avenue Edinburgh City of Edinburgh EH12 9JU",
    "addr:housenumber":"unit 37;60",
    "addr:postcode":"eh12 9ju",
    "addr:street":"Shopping;Gyle Avenue Edinburgh",
    "iso:country":"GB",
    "sg:address":"Unit 37, Gyle Shopping Centre, 60 Gyle Avenue",
    "sg:city":"Edinburgh",
    "sg:classifiers":[
        {
            "category":"Travel",
            "subcategory":"Travel Agent",
            "type":"Entertainment"
        }
    ],
    "sg:phone":"+44 131 456 8000",
    "sg:postcode":"EH12 9JU",
    "sg:province":"City of Edinburgh",
    "wof:name":"Thomas Cook",
    "wof:placetype":"venue"
},
  "geometry": {"coordinates":[-3.361504,55.944645],"type":"Point"}
}