{
  "type": "Feature",
  "properties": {
    "iso:country":"GB",
    "sg:address":"1a Stratfield Avenue",
    "sg:city":"Tadley",
    "sg:classifiers":[
        {
            "category":"Professional",
            "subcategory":"Lawyer & Legal Services",
            "type":"Services"
        }
    ],
    "sg:postcode":"RG26 3UD",
    "sg:province":"Berkshire",
    "sg:tags":[
        "solicitor"
    ],
    "wof:name":"C Coupland",
    "wof:placetype":"venue"
},
  "geometry": {"coordinates":[-1.139684,51.347431],"type":"Point"}
}