{
  "type": "Feature",
  "properties": {
    "addr:full":"3 Dickins Road Warwick Warwickshire CV34 5NR",
    "addr:housenumber":"3",
    "addr:postcode":"cv34 5nr",
    "addr:street":"Dickins Road",
    "iso:country":"GB",
    "sg:address":"3 Dickins Road",
    "sg:city":"Warwick",
    "sg:classifiers":[
        {
            "category":"Retail",
            "subcategory":"Driving School",
            "type":"Services"
        }
    ],
    "sg:phone":"+44 1926 498618",
    "sg:postcode":"CV34 5NR",
    "sg:province":"Warwickshire",
    "wof:name":"Midway Driving School",
    "wof:placetype":"venue"
},
  "geometry": {"coordinates":[-1.5668749809,52.2906913757],"type":"Point"}
}