{
  "type": "Feature",
  "properties": {
    "iso:country":"GB",
    "sg:address":"Unit 45 Rowland Hill, Orchard Studios, 2 Manor Gardens",
    "sg:city":"Holloway",
    "sg:classifiers":[
        {
            "category":"Home & Garden",
            "subcategory":"Home Furnishings",
            "type":"Retail Goods"
        }
    ],
    "sg:phone":"+44 20 7263 7999",
    "sg:postcode":"N7 6JZ",
    "sg:province":"Greater London",
    "sg:tags":[
        "blind",
        "curtain",
        "fitting"
    ],
    "wof:name":"Fabricant Ltd",
    "wof:placetype":"venue"
},
  "geometry": {"coordinates":[-0.114534,51.55439],"type":"Point"}
}