{
  "type": "Feature",
  "properties": {
    "addr:full":"Oakvale, Holnest Sherborne Dorset DT9 5PX",
    "addr:postcode":"dt9 5px",
    "iso:country":"GB",
    "sg:address":"Oakvale, Holnest",
    "sg:city":"Sherborne",
    "sg:classifiers":[
        {
            "category":"Arts & Performance",
            "subcategory":"Music",
            "type":"Entertainment"
        }
    ],
    "sg:postcode":"DT9 5PX",
    "sg:province":"Dorset",
    "sg:tags":[
        "mobile",
        "disco"
    ],
    "wof:name":"Human Nature Road Show",
    "wof:placetype":"venue"
},
  "geometry": {"coordinates":[-2.487944,50.885063],"type":"Point"}
}