{
  "type": "Feature",
  "properties": {
    "addr:full":"Narborough Health Centre, Thornton Dr Leicester Leicestershire LE9 5GX",
    "addr:postcode":"le9 5gx",
    "addr:street":"Thornton Dr",
    "iso:country":"GB",
    "sg:address":"Narborough Health Centre, Thornton Dr",
    "sg:city":"Leicester",
    "sg:classifiers":[
        {
            "category":"Health Services",
            "subcategory":"Doctor",
            "type":"Services"
        }
    ],
    "sg:phone":"+44 116 286 2386",
    "sg:postcode":"LE9 5GX",
    "sg:province":"Leicestershire",
    "sg:tags":[
        "practitioners"
    ],
    "wof:name":"Raja, S T",
    "wof:placetype":"venue"
},
  "geometry": {"coordinates":[-1.27391,52.585522],"type":"Point"}
}