{
  "type": "Feature",
  "properties": {
    "addr:full":"17 Mount Street Cannock Staffordshire WS12 4DE",
    "addr:housenumber":"17",
    "addr:postcode":"ws12 4de",
    "addr:street":"Mount Street",
    "iso:country":"GB",
    "sg:address":"17 Mount Street",
    "sg:city":"Cannock",
    "sg:classifiers":[
        {
            "category":"Shopping",
            "subcategory":"Department Store",
            "type":"Retail Goods"
        }
    ],
    "sg:phone":"+44 1543 422517",
    "sg:postcode":"WS12 4DE",
    "sg:province":"Staffordshire",
    "wof:name":"Station Road Sub-Post Office",
    "wof:placetype":"venue"
},
  "geometry": {"coordinates":[-1.9983099699,52.7147941589],"type":"Point"}
}