{
  "type": "Feature",
  "properties": {
    "iso:country":"GB",
    "sg:address":"Unit 7 Birds Industrial Estate Commerci",
    "sg:city":"Newport",
    "sg:classifiers":[
        {
            "category":"Freight",
            "type":"Transportation"
        }
    ],
    "sg:postcode":"NP11 6EE",
    "sg:province":"Blaenau Gwent",
    "sg:tags":[
        "haulage",
        "road"
    ],
    "wof:name":"M & M Transport",
    "wof:placetype":"venue"
},
  "geometry": {"coordinates":[-3.097773,51.607761],"type":"Point"}
}