{
  "type": "Feature",
  "properties": {
    "iso:country":"GB",
    "sg:address":"12a Hibbert Rd",
    "sg:city":"Harrow",
    "sg:classifiers":[
        {
            "category":"Arts & Performance",
            "subcategory":"Music",
            "type":"Entertainment"
        }
    ],
    "sg:phone":"+44 20 8930 8611",
    "sg:postcode":"HA3 7JS",
    "sg:province":"Greater London",
    "sg:tags":[
        "musician",
        "composer"
    ],
    "wof:name":"Andy Wood",
    "wof:placetype":"venue"
},
  "geometry": {"coordinates":[-0.328493,51.599033],"type":"Point"}
}