{
  "type": "Feature",
  "properties": {
    "addr:full":"18 Coombe Road Brighton East Sussex BN2 4EA",
    "addr:housenumber":"18",
    "addr:postcode":"bn2 4ea",
    "addr:street":"Coombe Road",
    "iso:country":"GB",
    "sg:address":"18 Coombe Road",
    "sg:city":"Brighton",
    "sg:classifiers":[
        {
            "category":"Wholesale",
            "subcategory":"Home Furnishings",
            "type":"Manufacturing & Wholesale Goods"
        }
    ],
    "sg:phone":"+44 1273 697584",
    "sg:postcode":"BN2 4EA",
    "sg:province":"East Sussex",
    "sg:tags":[
        "wsale",
        "rug",
        "carpet"
    ],
    "wof:name":"D J Flooring",
    "wof:placetype":"venue"
},
  "geometry": {"coordinates":[-0.121285,50.840195],"type":"Point"}
}