{
  "type": "Feature",
  "properties": {
    "addr:full":"Grosvenor Playing Fields Hayes Greater London UB4 8BZ",
    "addr:postcode":"ub4 8bz",
    "iso:country":"GB",
    "sg:address":"Grosvenor Playing Fields",
    "sg:city":"Hayes",
    "sg:classifiers":[
        {
            "category":"Arena",
            "subcategory":"Sports Club",
            "type":"Entertainment"
        }
    ],
    "sg:phone":"+44 20 8845 4963",
    "sg:postcode":"UB4 8BZ",
    "sg:province":"Greater London",
    "wof:name":"Hayes Rugby Club",
    "wof:placetype":"venue"
},
  "geometry": {"coordinates":[-0.421833992,51.5371246338],"type":"Point"}
}