{
  "type": "Feature",
  "properties": {
    "addr:full":"Durham Road Spennymoor Durham DL16 6SL",
    "addr:postcode":"dl16 6sl",
    "addr:street":"Durham Road",
    "iso:country":"GB",
    "sg:address":"Durham Road",
    "sg:city":"Spennymoor",
    "sg:classifiers":[
        {
            "category":"Retail",
            "subcategory":"Auto Repair",
            "type":"Services"
        }
    ],
    "sg:phone":"+44 1388 814104",
    "sg:postcode":"DL16 6SL",
    "sg:province":"Durham",
    "sg:tags":[
        "modification",
        "garage"
    ],
    "wof:name":"Lane Ends Garage",
    "wof:placetype":"venue"
},
  "geometry": {"coordinates":[-1.5919309855,54.7065467834],"type":"Point"}
}