{
  "type": "Feature",
  "properties": {
    "iso:country":"GB",
    "sg:address":"Gruinard Place, Cleish",
    "sg:city":"Kinross",
    "sg:classifiers":[
        {
            "category":"Utilities",
            "subcategory":"Refuse",
            "type":"Services"
        }
    ],
    "sg:phone":"+44 1577 850296",
    "sg:postcode":"KY13 0LS",
    "sg:province":"Clackmannanshire",
    "sg:tags":[
        "disposal",
        "waste"
    ],
    "wof:name":"Vermicon",
    "wof:placetype":"venue"
},
  "geometry": {"coordinates":[-3.4482810497,56.1688728333],"type":"Point"}
}