{
  "type": "Feature",
  "properties": {
    "iso:country":"GB",
    "sg:address":"537 Glasgow Road",
    "sg:city":"Wishaw",
    "sg:classifiers":[
        {
            "category":"Bars & Pubs",
            "type":"Food & Drink"
        }
    ],
    "sg:postcode":"ML2 7SW",
    "sg:province":"North Lanarkshire",
    "sg:tags":[
        "pubs",
        "inn"
    ],
    "wof:name":"The Central Bar",
    "wof:placetype":"venue"
},
  "geometry": {"coordinates":[-3.9506380558,55.7776031494],"type":"Point"}
}