{
  "type": "Feature",
  "properties": {
    "addr:full":"Unit 4 5 6 Radiance Road Doncaster South Yorkshire DN1 2TE",
    "addr:housenumber":"unit;5 6",
    "addr:postcode":"dn1 2te",
    "addr:street":"Radiance Road",
    "iso:country":"GB",
    "sg:address":"Unit 4 5 6 Radiance Road",
    "sg:city":"Doncaster",
    "sg:classifiers":[
        {
            "category":"Retail",
            "subcategory":"Auto Repair",
            "type":"Services"
        }
    ],
    "sg:phone":"+44 1302 768590",
    "sg:postcode":"DN1 2TE",
    "sg:province":"South Yorkshire",
    "sg:tags":[
        "modification",
        "garage"
    ],
    "wof:name":"P & S Autos",
    "wof:placetype":"venue"
},
  "geometry": {"coordinates":[-1.124287,53.5336],"type":"Point"}
}