{
  "type": "Feature",
  "properties": {
    "addr:full":"36 Anchor Road Bournemouth Dorset BH11 9HS",
    "addr:housenumber":"36",
    "addr:postcode":"bh11 9hs",
    "addr:street":"Anchor Road",
    "iso:country":"GB",
    "sg:address":"36 Anchor Road",
    "sg:city":"Bournemouth",
    "sg:classifiers":[
        {
            "category":"Fast Food",
            "type":"Food & Drink"
        },
        {
            "category":"Food & Beverages",
            "subcategory":"Groceries & Convenience Stores",
            "type":"Retail Goods"
        },
        {
            "category":"Food & Beverages",
            "subcategory":"Fruits & Vegetables",
            "type":"Retail Goods"
        },
        {
            "category":"Food & Beverages",
            "subcategory":"Meat & Fish",
            "type":"Retail Goods"
        }
    ],
    "sg:phone":"+44 1202 572981",
    "sg:postcode":"BH11 9HS",
    "sg:province":"Dorset",
    "sg:tags":[
        "shop",
        "chip",
        "away",
        "take",
        "greengrocer"
    ],
    "wof:name":"Bear Cross Fisheries",
    "wof:placetype":"venue"
},
  "geometry": {"coordinates":[-1.918022,50.767078],"type":"Point"}
}