{
  "type": "Feature",
  "properties": {
    "addr:full":"72 Barston Road, Oldbury, Warley Smethwick West Midlands B68 0PS",
    "addr:housenumber":"72",
    "addr:postcode":"b68 0ps",
    "addr:street":"Barston Road",
    "iso:country":"GB",
    "sg:address":"72 Barston Road, Oldbury, Warley",
    "sg:city":"Smethwick",
    "sg:classifiers":[
        {
            "category":"Building & Trades",
            "subcategory":"Construction",
            "type":"Services"
        }
    ],
    "sg:phone":"+44 121 421 5015",
    "sg:postcode":"B68 0PS",
    "sg:province":"West Midlands",
    "sg:tags":[
        "builder"
    ],
    "wof:name":"Terry Watson",
    "wof:placetype":"venue"
},
  "geometry": {"coordinates":[-2.006373,52.464336],"type":"Point"}
}