{
  "type": "Feature",
  "properties": {
    "addr:full":"252 High Road London Greater London NW10 2NX",
    "addr:housenumber":"252",
    "addr:postcode":"nw10 2nx",
    "addr:street":"High Road",
    "iso:country":"GB",
    "sg:address":"252 High Road",
    "sg:city":"London",
    "sg:classifiers":[
        {
            "category":"Shopping",
            "subcategory":"Pharmacy",
            "type":"Retail Goods"
        }
    ],
    "sg:phone":"+44 20 8459 1872",
    "sg:postcode":"NW10 2NX",
    "sg:province":"Greater London",
    "sg:tags":[
        "pharmacist",
        "chemist"
    ],
    "wof:name":"Edgars Chemist",
    "wof:placetype":"venue"
},
  "geometry": {"coordinates":[-0.236846,51.547768],"type":"Point"}
}