{
  "type": "Feature",
  "properties": {
    "iso:country":"GB",
    "sg:address":"6 Latimer Street",
    "sg:city":"Romsey",
    "sg:classifiers":[
        {
            "category":"Health Services",
            "subcategory":"Chiropractor",
            "type":"Services"
        }
    ],
    "sg:phone":"+44 1794 518772",
    "sg:postcode":"SO51 8DG",
    "sg:province":"Hampshire",
    "wof:name":"Abbey Chiropractic Clinic",
    "wof:placetype":"venue"
},
  "geometry": {"coordinates":[-1.497898,50.989239],"type":"Point"}
}