{
  "type": "Feature",
  "properties": {
    "addr:full":"19a Manchester St Luton Bedfordshire LU1 2QB",
    "addr:housenumber":"19a",
    "addr:postcode":"lu1 2qb",
    "addr:street":"Manchester St",
    "iso:country":"GB",
    "sg:address":"19a Manchester St",
    "sg:city":"Luton",
    "sg:classifiers":[
        {
            "category":"Professional",
            "subcategory":"Accounting & Tax Preparation",
            "type":"Services"
        }
    ],
    "sg:phone":"+44 1582 727049",
    "sg:postcode":"LU1 2QB",
    "sg:province":"Bedfordshire",
    "sg:tags":[
        "accountant"
    ],
    "wof:name":"Leon Spiro & Co",
    "wof:placetype":"venue"
},
  "geometry": {"coordinates":[-0.417833,51.880161],"type":"Point"}
}