{
  "type": "Feature",
  "properties": {
    "addr:full":"Plumstead Service Station, Wickham Lane Abbey Wood Greater London SE2 0XJ",
    "addr:postcode":"se2 0xj",
    "addr:street":"Wickham Lane",
    "iso:country":"GB",
    "sg:address":"Plumstead Service Station, Wickham Lane",
    "sg:city":"Abbey Wood",
    "sg:classifiers":[
        {
            "category":"Autos & Motor Vehicles",
            "subcategory":"Recreational Vehicle Sales",
            "type":"Retail Goods"
        }
    ],
    "sg:phone":"+44 20 8316 5745",
    "sg:postcode":"SE2 0XJ",
    "sg:province":"Greater London",
    "sg:tags":[
        "caravan"
    ],
    "wof:name":"Caravan Contacts",
    "wof:placetype":"venue"
},
  "geometry": {"coordinates":[0.102289997,51.4848098755],"type":"Point"}
}