{
  "type": "Feature",
  "properties": {
    "addr:full":"7 Marescroft Road Slough Berkshire SL2 2LN",
    "addr:housenumber":"7",
    "addr:postcode":"sl2 2ln",
    "addr:street":"Marescroft Road",
    "iso:country":"GB",
    "sg:address":"7 Marescroft Road",
    "sg:city":"Slough",
    "sg:classifiers":[
        {
            "category":"Building & Trades",
            "subcategory":"Plumbing",
            "type":"Services"
        },
        {
            "category":"Building & Trades",
            "subcategory":"Construction",
            "type":"Services"
        }
    ],
    "sg:postcode":"SL2 2LN",
    "sg:province":"Berkshire",
    "sg:tags":[
        "central",
        "builder",
        "system",
        "heating",
        "servicing",
        "installation"
    ],
    "wof:name":"Corrigan Ductwork Installations Ltd",
    "wof:placetype":"venue"
},
  "geometry": {"coordinates":[-0.6378719807,51.5290870667],"type":"Point"}
}