{
  "type": "Feature",
  "properties": {
    "addr:full":"Ashes Lane, Springhead Oldham Lancashire OL4 4PF",
    "addr:postcode":"ol4 4pf",
    "addr:street":"Ashes Lane",
    "iso:country":"GB",
    "sg:address":"Ashes Lane, Springhead",
    "sg:city":"Oldham",
    "sg:classifiers":[
        {
            "category":"Education",
            "subcategory":"University",
            "type":"Public Place"
        }
    ],
    "sg:phone":"+44 161 620 1348",
    "sg:postcode":"OL4 4PF",
    "sg:province":"Lancashire",
    "sg:tags":[
        "adult"
    ],
    "wof:name":"Springhead Youth & Community Education Centre",
    "wof:placetype":"venue"
},
  "geometry": {"coordinates":[-2.06484,53.53899],"type":"Point"}
}