{
  "type": "Feature",
  "properties": {
    "iso:country":"GB",
    "sg:address":"Haddon Acre, Sires Hill, North Moreton",
    "sg:city":"Didcot",
    "sg:classifiers":[
        {
            "category":"Building & Trades",
            "subcategory":"Landscaping Services",
            "type":"Services"
        }
    ],
    "sg:postcode":"OX11 9BG",
    "sg:province":"Oxfordshire",
    "sg:tags":[
        "gardening"
    ],
    "wof:name":"Green & Tidy",
    "wof:placetype":"venue"
},
  "geometry": {"coordinates":[-1.1907509565,51.6006278992],"type":"Point"}
}