{
  "type": "Feature",
  "properties": {
    "addr:full":"242 High Street Beckenham Kent BR3 1EN",
    "addr:housenumber":"242",
    "addr:postcode":"br3 1en",
    "addr:street":"High Street",
    "iso:country":"GB",
    "sg:address":"242 High Street",
    "sg:city":"Beckenham",
    "sg:classifiers":[
        {
            "category":"Shopping",
            "subcategory":"Comic Books",
            "type":"Retail Goods"
        }
    ],
    "sg:phone":"+44 20 8658 8454",
    "sg:postcode":"BR3 1EN",
    "sg:province":"Kent",
    "sg:tags":[
        "jeweller"
    ],
    "wof:name":"Ashton Jewellers",
    "wof:placetype":"venue"
},
  "geometry": {"coordinates":[-0.029731,51.40654],"type":"Point"}
}