{
  "type": "Feature",
  "properties": {
    "addr:full":"3 The Springs Wakefield West Yorkshire WF1 1PU",
    "addr:housenumber":"3",
    "addr:postcode":"wf1 1pu",
    "addr:street":"The Springs",
    "iso:country":"GB",
    "sg:address":"3 The Springs",
    "sg:city":"Wakefield",
    "sg:classifiers":[
        {
            "category":"Recreation",
            "subcategory":"Fishing",
            "type":"Entertainment"
        }
    ],
    "sg:phone":"+44 1924 373820",
    "sg:postcode":"WF1 1PU",
    "sg:province":"West Yorkshire",
    "sg:tags":[
        "equipment",
        "angling"
    ],
    "wof:name":"Fred Alexander",
    "wof:placetype":"venue"
},
  "geometry": {"coordinates":[-1.4951250553,53.6833076477],"type":"Point"}
}