{
  "type": "Feature",
  "properties": {
    "addr:full":"Park House, Parkhouse Business Centre High Wycombe Buckinghamshire HP12 3DJ",
    "addr:postcode":"hp12 3dj",
    "iso:country":"GB",
    "sg:address":"Park House, Parkhouse Business Centre",
    "sg:city":"High Wycombe",
    "sg:classifiers":[
        {
            "category":"Professional",
            "subcategory":"Management & Consulting",
            "type":"Services"
        }
    ],
    "sg:postcode":"HP12 3DJ",
    "sg:province":"Buckinghamshire",
    "sg:tags":[
        "marketing",
        "consultant"
    ],
    "wof:name":"Hps Group Ltd.",
    "wof:placetype":"venue"
},
  "geometry": {"coordinates":[-0.7734339833,51.6255302429],"type":"Point"}
}