{
  "type": "Feature",
  "properties": {
    "iso:country":"GB",
    "sg:address":"Oldmills Road",
    "sg:city":"Elgin",
    "sg:classifiers":[
        {
            "category":"Shopping",
            "subcategory":"Clothing, Apparel, & Fashions",
            "type":"Retail Goods"
        }
    ],
    "sg:phone":"+44 1343 540698",
    "sg:postcode":"IV30 1YH",
    "sg:province":"Moray",
    "sg:tags":[
        "clothing",
        "fabric"
    ],
    "wof:name":"Working Watermill",
    "wof:placetype":"venue"
},
  "geometry": {"coordinates":[-3.317868948,57.6493682861],"type":"Point"}
}