{
  "type": "Feature",
  "properties": {
    "addr:full":"26 Trinity Street Halstead Essex CO9 1JA",
    "addr:housenumber":"26",
    "addr:postcode":"co9 1ja",
    "addr:street":"Trinity Street",
    "iso:country":"GB",
    "sg:address":"26 Trinity Street",
    "sg:city":"Halstead",
    "sg:classifiers":[
        {
            "category":"Shopping",
            "subcategory":"News",
            "type":"Retail Goods"
        }
    ],
    "sg:postcode":"CO9 1JA",
    "sg:province":"Essex",
    "sg:tags":[
        "newsagent"
    ],
    "wof:name":"The Newsbox",
    "wof:placetype":"venue"
},
  "geometry": {"coordinates":[0.6327959895,51.9439125061],"type":"Point"}
}