{
  "type": "Feature",
  "properties": {
    "addr:full":"Powlett Road Hartlepool Durham TS24 8LY",
    "addr:postcode":"ts24 8ly",
    "addr:street":"Powlett Road",
    "iso:country":"GB",
    "sg:address":"Powlett Road",
    "sg:city":"Hartlepool",
    "sg:classifiers":[
        {
            "category":"Shopping",
            "subcategory":"Clothing, Apparel, & Fashions",
            "type":"Retail Goods"
        }
    ],
    "sg:phone":"+44 1429 242500",
    "sg:postcode":"TS24 8LY",
    "sg:province":"Durham",
    "sg:tags":[
        "clothing",
        "fabric"
    ],
    "wof:name":"Baird Menswear Brands Ltd.",
    "wof:placetype":"venue"
},
  "geometry": {"coordinates":[-1.2128889561,54.6982040405],"type":"Point"}
}