{
  "type": "Feature",
  "properties": {
    "iso:country":"GB",
    "sg:address":"4 St Marks Place, Wimbledon",
    "sg:city":"London",
    "sg:classifiers":[
        {
            "category":"Professional",
            "subcategory":"Art Services",
            "type":"Services"
        }
    ],
    "sg:phone":"+44 20 8946 5302",
    "sg:postcode":"SW19 7ND",
    "sg:province":"Greater London",
    "sg:tags":[
        "photographer"
    ],
    "wof:name":"James Russell Studio",
    "wof:placetype":"venue"
},
  "geometry": {"coordinates":[-0.2079810053,51.4220504761],"type":"Point"}
}