{
  "type": "Feature",
  "properties": {
    "iso:country":"GB",
    "sg:address":"Hardwicke Farm, Stottesdon",
    "sg:city":"Kidderminster",
    "sg:classifiers":[
        {
            "category":"Travel",
            "subcategory":"Hotels & Motels",
            "type":"Entertainment"
        },
        {
            "category":"Farming",
            "subcategory":"Farm",
            "type":"Manufacturing & Wholesale Goods"
        }
    ],
    "sg:phone":"+44 1746 718220",
    "sg:postcode":"DY14 8TN",
    "sg:province":"Shropshire",
    "sg:tags":[
        "mixed",
        "house",
        "guest",
        "crop"
    ],
    "wof:name":"Andrew J Meredith",
    "wof:placetype":"venue"
},
  "geometry": {"coordinates":[-2.4838910103,52.4415855408],"type":"Point"}
}