{
  "type": "Feature",
  "properties": {
    "iso:country":"GB",
    "sg:address":"66 Cardiff Road, Glan-y-llyn, Taffs Well",
    "sg:city":"Cardiff",
    "sg:classifiers":[
        {
            "category":"Professional",
            "subcategory":"Business Services",
            "type":"Services"
        }
    ],
    "sg:phone":"+44 29 2081 0661",
    "sg:postcode":"CF15 7YA",
    "sg:province":"Caerphilly",
    "sg:tags":[
        "trade"
    ],
    "wof:name":"Building Employers Confederation",
    "wof:placetype":"venue"
},
  "geometry": {"coordinates":[-3.2689900398,51.5437011719],"type":"Point"}
}