{
  "type": "Feature",
  "properties": {
    "iso:country":"GB",
    "sg:address":"58 Redlands Lane",
    "sg:city":"Fareham",
    "sg:classifiers":[
        {
            "category":"Building & Trades",
            "subcategory":"Construction",
            "type":"Services"
        }
    ],
    "sg:phone":"+44 1329 230300",
    "sg:postcode":"PO14 1PJ",
    "sg:province":"Hampshire",
    "sg:tags":[
        "roofing"
    ],
    "wof:name":"Mallard Roofing Services (Southern)",
    "wof:placetype":"venue"
},
  "geometry": {"coordinates":[-1.192959,50.849583],"type":"Point"}
}