{
  "type": "Feature",
  "properties": {
    "addr:full":"Sanford Ho, 5 Medwin Walk Horsham West Sussex RH12 1AZ",
    "addr:housenumber":"5",
    "addr:postcode":"rh12 1az",
    "addr:street":"Medwin Walk",
    "iso:country":"GB",
    "sg:address":"Sanford Ho, 5 Medwin Walk",
    "sg:city":"Horsham",
    "sg:classifiers":[
        {
            "category":"Professional",
            "subcategory":"Business Services",
            "type":"Services"
        }
    ],
    "sg:phone":"+44 1403 210355",
    "sg:postcode":"RH12 1AZ",
    "sg:province":"West Sussex",
    "sg:tags":[
        "management",
        "pub"
    ],
    "wof:name":"Pub Invest Ltd",
    "wof:placetype":"venue"
},
  "geometry": {"coordinates":[-0.3291069865,51.0651817322],"type":"Point"}
}