{
  "type": "Feature",
  "properties": {
    "addr:full":"1112 Uxbridge Road Hayes Greater London UB4 8QH",
    "addr:housenumber":"1112",
    "addr:postcode":"ub4 8qh",
    "addr:street":"Uxbridge Road",
    "iso:country":"GB",
    "sg:address":"1112 Uxbridge Road",
    "sg:city":"Hayes",
    "sg:classifiers":[
        {
            "category":"Home & Garden",
            "subcategory":"Building Materials",
            "type":"Retail Goods"
        }
    ],
    "sg:phone":"+44 20 8561 3900",
    "sg:postcode":"UB4 8QH",
    "sg:province":"Greater London",
    "sg:tags":[
        "furnishers",
        "bathroom",
        "planner",
        "fixture",
        "fitting"
    ],
    "wof:name":"Tropical Heating",
    "wof:placetype":"venue"
},
  "geometry": {"coordinates":[-0.422901,51.523376],"type":"Point"}
}