{
  "type": "Feature",
  "properties": {
    "addr:full":"46 Sidwell St Exeter Devon EX4 6NS",
    "addr:housenumber":"46",
    "addr:postcode":"ex4 6ns",
    "addr:street":"Sidwell St",
    "iso:country":"GB",
    "sg:address":"46 Sidwell St",
    "sg:city":"Exeter",
    "sg:classifiers":[
        {
            "category":"Cinema",
            "subcategory":"Movie Rental",
            "type":"Entertainment"
        }
    ],
    "sg:phone":"+44 1392 259898",
    "sg:postcode":"EX4 6NS",
    "sg:province":"Devon",
    "sg:tags":[
        "video",
        "library"
    ],
    "wof:name":"Blockbuster Video Express",
    "wof:placetype":"venue"
},
  "geometry": {"coordinates":[-3.523876,50.727413],"type":"Point"}
}