{
  "type": "Feature",
  "properties": {
    "addr:full":"4 St. Andrews Indstl Est, Sydney Rd Birmingham West Midlands B9 4QB",
    "addr:housenumber":"4",
    "addr:postcode":"b9 4qb",
    "addr:street":"St. Andrews Indstl Est Sydney Rd",
    "iso:country":"GB",
    "sg:address":"4 St. Andrews Indstl Est, Sydney Rd",
    "sg:city":"Birmingham",
    "sg:classifiers":[
        {
            "category":"Manufacturing",
            "subcategory":"Metals",
            "type":"Manufacturing & Wholesale Goods"
        }
    ],
    "sg:postcode":"B9 4QB",
    "sg:province":"West Midlands",
    "wof:name":"McDonald,Ian,",
    "wof:placetype":"venue"
},
  "geometry": {"coordinates":[-1.8678300381,52.4785804749],"type":"Point"}
}