{
  "type": "Feature",
  "properties": {
    "addr:full":"7 High Street Bideford Devon EX39 2AA",
    "addr:housenumber":"7",
    "addr:postcode":"ex39 2aa",
    "addr:street":"High Street",
    "iso:country":"GB",
    "sg:address":"7 High Street",
    "sg:city":"Bideford",
    "sg:classifiers":[
        {
            "category":"Shopping",
            "subcategory":"News",
            "type":"Retail Goods"
        }
    ],
    "sg:phone":"+44 1237 473043",
    "sg:postcode":"EX39 2AA",
    "sg:province":"Devon",
    "sg:tags":[
        "newsagent"
    ],
    "wof:name":"Watson's",
    "wof:placetype":"venue"
},
  "geometry": {"coordinates":[-4.2056269646,51.0177116394],"type":"Point"}
}