{
  "type": "Feature",
  "properties": {
    "iso:country":"GB",
    "sg:address":"11 Whitelegge Street",
    "sg:city":"Bury",
    "sg:classifiers":[
        {
            "category":"Fast Food",
            "type":"Food & Drink"
        }
    ],
    "sg:phone":"+44 161 761 6006",
    "sg:postcode":"BL8 1SW",
    "sg:province":"Lancashire",
    "sg:tags":[
        "away",
        "take"
    ],
    "wof:name":"Made Marian Hot & Cold Food",
    "wof:placetype":"venue"
},
  "geometry": {"coordinates":[-2.319015,53.600834],"type":"Point"}
}