{
  "type": "Feature",
  "properties": {
    "addr:full":"29 Greenwich South Street, Greenwich London Greater London SE10 8NT",
    "addr:housenumber":"29",
    "addr:postcode":"se10 8nt",
    "addr:street":"Greenwich South Street",
    "iso:country":"GB",
    "sg:address":"29 Greenwich South Street, Greenwich",
    "sg:city":"London",
    "sg:classifiers":[
        {
            "category":"Building & Trades",
            "subcategory":"Construction",
            "type":"Services"
        }
    ],
    "sg:phone":"+44 20 8858 1304",
    "sg:postcode":"SE10 8NT",
    "sg:province":"Greater London",
    "sg:tags":[
        "builder"
    ],
    "wof:name":"Millenncraft Ltd.",
    "wof:placetype":"venue"
},
  "geometry": {"coordinates":[-0.012325,51.4770202637],"type":"Point"}
}