{
  "type": "Feature",
  "properties": {
    "iso:country":"GB",
    "sg:address":"47 Grosvenor Way",
    "sg:city":"Newcastle-upon-tyne",
    "sg:classifiers":[
        {
            "category":"Building & Trades",
            "subcategory":"Construction",
            "type":"Services"
        }
    ],
    "sg:phone":"+44 191 264 1983",
    "sg:postcode":"NE5 1RZ",
    "sg:province":"Tyne and Wear",
    "sg:tags":[
        "pipework",
        "contractor"
    ],
    "wof:name":"316 Installations Ltd",
    "wof:placetype":"venue"
},
  "geometry": {"coordinates":[-1.7079180479,54.9977149963],"type":"Point"}
}