{
  "type": "Feature",
  "properties": {
    "addr:full":"126 Trinity Street Gainsborough Lincolnshire DN21 1JD",
    "addr:housenumber":"126",
    "addr:postcode":"dn21 1jd",
    "addr:street":"Trinity Street",
    "iso:country":"GB",
    "sg:address":"126 Trinity Street",
    "sg:city":"Gainsborough",
    "sg:classifiers":[
        {
            "category":"Retail",
            "subcategory":"Repair Shop",
            "type":"Services"
        }
    ],
    "sg:phone":"+44 1427 612950",
    "sg:postcode":"DN21 1JD",
    "sg:province":"Lincolnshire",
    "sg:tags":[
        "radio",
        "television",
        "video"
    ],
    "wof:name":"David Edwards Tv & Video",
    "wof:placetype":"venue"
},
  "geometry": {"coordinates":[-0.7725999951,53.3945960999],"type":"Point"}
}