{
  "type": "Feature",
  "properties": {
    "addr:full":"28 Dorchester Road Weymouth Dorset DT4 7JU",
    "addr:housenumber":"28",
    "addr:postcode":"dt4 7ju",
    "addr:street":"Dorchester Road",
    "iso:country":"GB",
    "sg:address":"28 Dorchester Road",
    "sg:city":"Weymouth",
    "sg:classifiers":[
        {
            "category":"Health Services",
            "subcategory":"Nursing And Care Facility",
            "type":"Services"
        },
        {
            "category":"Social Services",
            "subcategory":"Retirement Home",
            "type":"Services"
        },
        {
            "category":"Government",
            "subcategory":"Office",
            "type":"Public Place"
        }
    ],
    "sg:phone":"+44 1305 782343",
    "sg:postcode":"DT4 7JU",
    "sg:province":"Dorset",
    "sg:tags":[
        "residential",
        "central"
    ],
    "wof:name":"Kingsleigh Court",
    "wof:placetype":"venue"
},
  "geometry": {"coordinates":[-2.4544909,50.6226501465],"type":"Point"}
}