{
  "type": "Feature",
  "properties": {
    "iso:country":"GB",
    "sg:address":"West Renfrew House, 26 Brougham Street",
    "sg:city":"Greenock",
    "sg:classifiers":[
        {
            "category":"Real Estate",
            "subcategory":"Surveying",
            "type":"Services"
        }
    ],
    "sg:phone":"+44 1475 888342",
    "sg:postcode":"PA16 8AD",
    "sg:province":"Inverclyde",
    "sg:tags":[
        "surveyor",
        "quantity"
    ],
    "wof:name":"Binnie Murray & Hutton",
    "wof:placetype":"venue"
},
  "geometry": {"coordinates":[-4.767228,55.954647],"type":"Point"}
}