{
  "type": "Feature",
  "properties": {
    "iso:country":"GB",
    "sg:address":"6 Hillmead Court, Station Road, Taplow",
    "sg:city":"Maidenhead",
    "sg:classifiers":[
        {
            "category":"Shopping",
            "subcategory":"Stationery & Office Supplies",
            "type":"Retail Goods"
        },
        {
            "category":"Shopping",
            "subcategory":"Gifts & Souvenirs",
            "type":"Retail Goods"
        }
    ],
    "sg:phone":"+44 1628 605071",
    "sg:postcode":"SL6 0QA",
    "sg:province":"Berkshire",
    "sg:tags":[
        "supplier",
        "publisher",
        "greeting",
        "card"
    ],
    "wof:name":"Melvyn Johnson Greeting Cards",
    "wof:placetype":"venue"
},
  "geometry": {"coordinates":[-0.6806259751,51.5274467468],"type":"Point"}
}