{
  "type": "Feature",
  "properties": {
    "addr:full":"63 Harley Street London Greater London W1G 8QY",
    "addr:housenumber":"63",
    "addr:postcode":"w1g 8qy",
    "addr:street":"Harley Street",
    "iso:country":"GB",
    "sg:address":"63 Harley Street",
    "sg:city":"London",
    "sg:classifiers":[
        {
            "category":"Health Services",
            "subcategory":"Doctor",
            "type":"Services"
        }
    ],
    "sg:phone":"+44 20 7636 4326",
    "sg:postcode":"W1G 8QY",
    "sg:province":"Greater London",
    "sg:tags":[
        "surgeon"
    ],
    "wof:name":"P A J Starr",
    "wof:placetype":"venue"
},
  "geometry": {"coordinates":[-0.147237,51.51918],"type":"Point"}
}