{
  "type": "Feature",
  "properties": {
    "addr:full":"37 Stafford Rd Stone Staffordshire ST15 0HG",
    "addr:housenumber":"37",
    "addr:postcode":"st15 0hg",
    "addr:street":"Stafford Rd",
    "iso:country":"GB",
    "sg:address":"37 Stafford Rd",
    "sg:city":"Stone",
    "sg:classifiers":[
        {
            "category":"Health Services",
            "subcategory":"Nursing And Care Facility",
            "type":"Services"
        }
    ],
    "sg:phone":"+44 1785 812885",
    "sg:postcode":"ST15 0HG",
    "sg:province":"Staffordshire",
    "sg:tags":[
        "home"
    ],
    "wof:name":"Autumn House Nursing Home",
    "wof:placetype":"venue"
},
  "geometry": {"coordinates":[-2.1476500034,52.8951835632],"type":"Point"}
}