{
  "type": "Feature",
  "properties": {
    "iso:country":"GB",
    "sg:address":"53a Greensleeves Avenue, Broadstone",
    "sg:city":"Poole",
    "sg:classifiers":[
        {
            "category":"Professional",
            "subcategory":"Management & Consulting",
            "type":"Services"
        }
    ],
    "sg:postcode":"BH18 8BJ",
    "sg:province":"Dorset",
    "sg:tags":[
        "consultant",
        "business"
    ],
    "wof:name":"Curteis Energy Ltd",
    "wof:placetype":"venue"
},
  "geometry": {"coordinates":[-1.9886050224,50.7713737488],"type":"Point"}
}