{
  "type": "Feature",
  "properties": {
    "addr:full":"165 South Street St Andrews Fife KY16 9EE",
    "addr:housenumber":"165",
    "addr:postcode":"ky16 9ee",
    "addr:street":"South Street",
    "iso:country":"GB",
    "sg:address":"165 South Street",
    "sg:city":"St Andrews",
    "sg:classifiers":[
        {
            "category":"Transit Center",
            "subcategory":"Freight",
            "type":"Transportation"
        },
        {
            "category":"Shopping",
            "subcategory":"Crafts & Fabrics",
            "type":"Retail Goods"
        }
    ],
    "sg:phone":"+44 1334 477651",
    "sg:postcode":"KY16 9EE",
    "sg:province":"Fife",
    "sg:tags":[
        "shop",
        "outlet",
        "centre"
    ],
    "wof:name":"Simply Scotland Trading Co",
    "wof:placetype":"venue"
},
  "geometry": {"coordinates":[-2.791969,56.339588],"type":"Point"}
}