{
  "type": "Feature",
  "properties": {
    "addr:full":"17 Pensham Hill Pershore Worcestershire WR10 3HA",
    "addr:housenumber":"17",
    "addr:postcode":"wr10 3ha",
    "addr:street":"Pensham Hill",
    "iso:country":"GB",
    "sg:address":"17 Pensham Hill",
    "sg:city":"Pershore",
    "sg:classifiers":[
        {
            "category":"Professional",
            "subcategory":"Lawyer & Legal Services",
            "type":"Services"
        }
    ],
    "sg:postcode":"WR10 3HA",
    "sg:province":"Worcestershire",
    "wof:name":"Legal Systems Worcestershire",
    "wof:placetype":"venue"
},
  "geometry": {"coordinates":[-2.074903965,52.0985298157],"type":"Point"}
}