{
  "type": "Feature",
  "properties": {
    "iso:country":"GB",
    "sg:address":"Mansfield Road, Aston",
    "sg:city":"Sheffield",
    "sg:classifiers":[
        {
            "category":"Manufacturing",
            "subcategory":"Metals",
            "type":"Manufacturing & Wholesale Goods"
        },
        {
            "category":"Manufacturing",
            "subcategory":"Chemicals & Compounds",
            "type":"Manufacturing & Wholesale Goods"
        },
        {
            "category":"Retail",
            "subcategory":"Repair Shop",
            "type":"Services"
        }
    ],
    "sg:phone":"+44 114 287 4522",
    "sg:postcode":"S26 2BR",
    "sg:province":"South Yorkshire",
    "sg:tags":[
        "abrasive",
        "product",
        "tool",
        "sharpening",
        "cleaning",
        "tungsten"
    ],
    "wof:name":"Harthill Regrinding Services Ltd.",
    "wof:placetype":"venue"
},
  "geometry": {"coordinates":[-1.315413,53.359032],"type":"Point"}
}