{
  "type": "Feature",
  "properties": {
    "addr:full":"Unit 9, Derwent Park Industrial Estate Burton-on-trent Derbyshire DE14 1QA",
    "addr:housenumber":"unit 9",
    "addr:postcode":"de14 1qa",
    "addr:street":"Park Industrial",
    "iso:country":"GB",
    "sg:address":"Unit 9, Derwent Park Industrial Estate",
    "sg:city":"Burton-on-trent",
    "sg:classifiers":[
        {
            "category":"Professional",
            "subcategory":"Engineering",
            "type":"Services"
        }
    ],
    "sg:phone":"+44 1283 568015",
    "sg:postcode":"DE14 1QA",
    "sg:province":"Derbyshire",
    "sg:tags":[
        "contractor",
        "electrical",
        "engineer"
    ],
    "wof:name":"S M Vorley (Electrical Contractors) Ltd.",
    "wof:placetype":"venue"
},
  "geometry": {"coordinates":[-1.629914,52.814598],"type":"Point"}
}