{
  "type": "Feature",
  "properties": {
    "iso:country":"GB",
    "sg:address":"26 Station Street",
    "sg:city":"Keswick",
    "sg:classifiers":[
        {
            "category":"Fast Food",
            "type":"Food & Drink"
        },
        {
            "category":"Ice Cream",
            "type":"Food & Drink"
        }
    ],
    "sg:phone":"+44 17687 74991",
    "sg:postcode":"CA12 5HF",
    "sg:province":"Cumbria",
    "sg:tags":[
        "shop",
        "mobile",
        "away",
        "parlour",
        "take"
    ],
    "wof:name":"Ashleys Ice Cream Parlour",
    "wof:placetype":"venue"
},
  "geometry": {"coordinates":[-3.1351690292,54.6006889343],"type":"Point"}
}