{
  "type": "Feature",
  "properties": {
    "iso:country":"GB",
    "sg:address":"20 Copley Crescent",
    "sg:city":"Doncaster",
    "sg:classifiers":[
        {
            "category":"Communications",
            "subcategory":"Film & Video Production",
            "type":"Services"
        },
        {
            "category":"Professional",
            "subcategory":"Art Services",
            "type":"Services"
        }
    ],
    "sg:phone":"+44 1302 788189",
    "sg:postcode":"DN5 8QL",
    "sg:province":"South Yorkshire",
    "sg:tags":[
        "illustrator",
        "artist"
    ],
    "wof:name":"R Peel",
    "wof:placetype":"venue"
},
  "geometry": {"coordinates":[-1.180291,53.537922],"type":"Point"}
}