{
  "type": "Feature",
  "properties": {
    "addr:full":"23a Julian Street Grimsby Lincolnshire DN32 8BG",
    "addr:housenumber":"23a",
    "addr:postcode":"dn32 8bg",
    "addr:street":"Julian Street",
    "iso:country":"GB",
    "sg:address":"23a Julian Street",
    "sg:city":"Grimsby",
    "sg:classifiers":[
        {
            "category":"Banks & Credit Unions",
            "subcategory":"Bureau De Change",
            "type":"Services"
        },
        {
            "category":"Building & Trades",
            "subcategory":"Construction",
            "type":"Services"
        }
    ],
    "sg:phone":"+44 1472 241211",
    "sg:postcode":"DN32 8BG",
    "sg:province":"Lincolnshire",
    "sg:tags":[
        "paint",
        "varnish",
        "decorator",
        "remover",
        "painter"
    ],
    "wof:name":"K S Pine",
    "wof:placetype":"venue"
},
  "geometry": {"coordinates":[-0.0679740012,53.5641403198],"type":"Point"}
}