{
  "type": "Feature",
  "properties": {
    "addr:full":"11 Silver Street Kettering Northamptonshire NN16 0BN",
    "addr:housenumber":"11",
    "addr:postcode":"nn16 0bn",
    "addr:street":"Silver Street",
    "iso:country":"GB",
    "sg:address":"11 Silver Street",
    "sg:city":"Kettering",
    "sg:classifiers":[
        {
            "category":"Professional",
            "subcategory":"Computer Services",
            "type":"Services"
        }
    ],
    "sg:phone":"+44 1536 482100",
    "sg:postcode":"NN16 0BN",
    "sg:province":"Northamptonshire",
    "sg:tags":[
        "system",
        "software"
    ],
    "wof:name":"4 U Systems",
    "wof:placetype":"venue"
},
  "geometry": {"coordinates":[-0.725620985,52.4007415771],"type":"Point"}
}