{
  "type": "Feature",
  "properties": {
    "addr:full":"473 Roman Rd London Greater London E3 5LX",
    "addr:housenumber":"473",
    "addr:postcode":"e3 5lx",
    "addr:street":"Roman Rd",
    "iso:country":"GB",
    "sg:address":"473 Roman Rd",
    "sg:city":"London",
    "sg:classifiers":[
        {
            "category":"Sports & Exercise",
            "subcategory":"Sports Center",
            "type":"Entertainment"
        }
    ],
    "sg:postcode":"E3 5LX",
    "sg:province":"Greater London",
    "sg:tags":[
        "shop",
        "good"
    ],
    "wof:name":"Honeyman,Christeen,",
    "wof:placetype":"venue"
},
  "geometry": {"coordinates":[-0.034037,51.532116],"type":"Point"}
}