{
  "type": "Feature",
  "properties": {
    "iso:country":"GB",
    "sg:address":"237 Hilltown",
    "sg:city":"Dundee",
    "sg:classifiers":[
        {
            "category":"Home & Garden",
            "subcategory":"Furniture",
            "type":"Retail Goods"
        }
    ],
    "sg:postcode":"DD3 7AN",
    "sg:province":"Dundee City",
    "wof:name":"Robert Adams Pine Direct",
    "wof:placetype":"venue"
},
  "geometry": {"coordinates":[-2.9740889072,56.4658699036],"type":"Point"}
}