{
  "type": "Feature",
  "properties": {
    "addr:full":"55 Dover St Canterbury Kent CT1 3HD",
    "addr:housenumber":"55",
    "addr:postcode":"ct1 3hd",
    "addr:street":"Dover St",
    "iso:country":"GB",
    "sg:address":"55 Dover St",
    "sg:city":"Canterbury",
    "sg:classifiers":[
        {
            "category":"Place Of Worship",
            "type":"Public Place"
        }
    ],
    "sg:phone":"+44 1227 455440",
    "sg:postcode":"CT1 3HD",
    "sg:province":"Kent",
    "wof:name":"City Church Canterbury The",
    "wof:placetype":"venue"
},
  "geometry": {"coordinates":[1.084408,51.275654],"type":"Point"}
}