{
  "type": "Feature",
  "properties": {
    "iso:country":"GB",
    "sg:address":"Owens Ho, 281-283 Goswell Rd",
    "sg:city":"Clerkenwell",
    "sg:classifiers":[
        {
            "category":"Real Estate",
            "subcategory":"Architect",
            "type":"Services"
        }
    ],
    "sg:phone":"+44 20 7713 1881",
    "sg:postcode":"EC1V 7NT",
    "sg:province":"Greater London",
    "wof:name":"Proun Architects",
    "wof:placetype":"venue"
},
  "geometry": {"coordinates":[-0.10377,51.5303],"type":"Point"}
}