{
  "type": "Feature",
  "properties": {
    "addr:full":"195 High St Enfield Greater London EN3 4DZ",
    "addr:housenumber":"195",
    "addr:postcode":"en3 4dz",
    "addr:street":"High St",
    "iso:country":"GB",
    "sg:address":"195 High St",
    "sg:city":"Enfield",
    "sg:classifiers":[
        {
            "category":"Professional",
            "subcategory":"Printing & Photocopies",
            "type":"Services"
        }
    ],
    "sg:phone":"+44 20 8804 7468",
    "sg:postcode":"EN3 4DZ",
    "sg:province":"Greater London",
    "sg:tags":[
        "printer"
    ],
    "wof:name":"Barfield Publishing",
    "wof:placetype":"venue"
},
  "geometry": {"coordinates":[-0.0465020016,51.6499290466],"type":"Point"}
}