{
  "type": "Feature",
  "properties": {
    "addr:full":"Unit 2 87a Maple Rd Surbiton Surrey KT6 4AW",
    "addr:housenumber":"unit;87a",
    "addr:postcode":"kt6 4aw",
    "addr:street":"Maple Rd",
    "iso:country":"GB",
    "sg:address":"Unit 2 87a Maple Rd",
    "sg:city":"Surbiton",
    "sg:classifiers":[
        {
            "category":"Shopping",
            "subcategory":"Music",
            "type":"Retail Goods"
        }
    ],
    "sg:phone":"+44 20 8339 9965",
    "sg:postcode":"KT6 4AW",
    "sg:province":"Surrey",
    "sg:tags":[
        "record",
        "tape",
        "cd"
    ],
    "wof:name":"GFT Mail Order Ltd",
    "wof:placetype":"venue"
},
  "geometry": {"coordinates":[-0.307736,51.395145],"type":"Point"}
}