{
  "type": "Feature",
  "properties": {
    "addr:full":"82a High Street, Nailsea Bristol Somerset BS48 1AS",
    "addr:housenumber":"82a",
    "addr:postcode":"bs48 1as",
    "addr:street":"High Street",
    "iso:country":"GB",
    "sg:address":"82a High Street, Nailsea",
    "sg:city":"Bristol",
    "sg:classifiers":[
        {
            "category":"Professional",
            "subcategory":"Accounting & Tax Preparation",
            "type":"Services"
        }
    ],
    "sg:postcode":"BS48 1AS",
    "sg:province":"Somerset",
    "sg:tags":[
        "accountant"
    ],
    "wof:name":"Philip Cleverdon",
    "wof:placetype":"venue"
},
  "geometry": {"coordinates":[-2.7541389465,51.4347839355],"type":"Point"}
}