{
  "type": "Feature",
  "properties": {
    "addr:full":"12 Victoria Centre Crewe Cheshire CW1 2PU",
    "addr:housenumber":"12",
    "addr:postcode":"cw1 2pu",
    "addr:street":"Victoria Centre",
    "iso:country":"GB",
    "sg:address":"12 Victoria Centre",
    "sg:city":"Crewe",
    "sg:classifiers":[
        {
            "category":"Shopping",
            "subcategory":"Optician",
            "type":"Retail Goods"
        },
        {
            "category":"Health Services",
            "subcategory":"Optometrist",
            "type":"Services"
        }
    ],
    "sg:phone":"+44 1270 215945",
    "sg:postcode":"CW1 2PU",
    "sg:province":"Cheshire",
    "sg:tags":[
        "opthalmic"
    ],
    "sg:website":"http://www.scrivens.com",
    "wof:name":"Scrivens Ltd.",
    "wof:placetype":"venue"
},
  "geometry": {"coordinates":[-2.442416,53.098892],"type":"Point"}
}