{
  "type": "Feature",
  "properties": {
    "iso:country":"GB",
    "sg:address":"Prospect Ho, 11 Lonsdale Gdns",
    "sg:city":"Tunbridge Wells",
    "sg:classifiers":[
        {
            "category":"Organizations",
            "subcategory":"Community Association",
            "type":"Services"
        }
    ],
    "sg:phone":"+44 1892 707807",
    "sg:postcode":"TN1 1NU",
    "sg:province":"Kent",
    "sg:tags":[
        "relation",
        "public"
    ],
    "wof:name":"Thorn Public Relations Ltd",
    "wof:placetype":"venue"
},
  "geometry": {"coordinates":[0.2635500133,51.1333732605],"type":"Point"}
}