{
  "type": "Feature",
  "properties": {
    "addr:full":"Regent Ho, High St Seaview Isle of Wight PO34 5EX",
    "addr:postcode":"po34 5ex",
    "addr:street":"High St",
    "iso:country":"GB",
    "sg:address":"Regent Ho, High St",
    "sg:city":"Seaview",
    "sg:classifiers":[
        {
            "category":"Communications",
            "subcategory":"Newspaper",
            "type":"Services"
        }
    ],
    "sg:phone":"+44 1983 613362",
    "sg:postcode":"PO34 5EX",
    "sg:province":"Isle of Wight",
    "sg:tags":[
        "magazine"
    ],
    "wof:name":"Islander County Magazine",
    "wof:placetype":"venue"
},
  "geometry": {"coordinates":[-1.1102739573,50.7195587158],"type":"Point"}
}