{
  "type": "Feature",
  "properties": {
    "addr:full":"28a Regal Drive, Soham Ely Cambridgeshire CB7 5BE",
    "addr:housenumber":"28a",
    "addr:postcode":"cb7 5be",
    "addr:street":"Regal Drive",
    "iso:country":"GB",
    "sg:address":"28a Regal Drive, Soham",
    "sg:city":"Ely",
    "sg:classifiers":[
        {
            "category":"Building & Trades",
            "subcategory":"Construction",
            "type":"Services"
        }
    ],
    "sg:postcode":"CB7 5BE",
    "sg:province":"Cambridgeshire",
    "sg:tags":[
        "decorator",
        "painter"
    ],
    "wof:name":"Ktf Group Ltd.",
    "wof:placetype":"venue"
},
  "geometry": {"coordinates":[0.351351,52.325901],"type":"Point"}
}