{
  "type": "Feature",
  "properties": {
    "iso:country":"GB",
    "sg:address":"Manor House Farm, Petherton Park, North Petherton",
    "sg:city":"Bridgwater",
    "sg:classifiers":[
        {
            "category":"Farming",
            "subcategory":"Livestock Farm",
            "type":"Manufacturing & Wholesale Goods"
        }
    ],
    "sg:phone":"+44 1278 662360",
    "sg:postcode":"TA7 0DT",
    "sg:province":"Somerset",
    "sg:tags":[
        "others"
    ],
    "wof:name":"R H Harris",
    "wof:placetype":"venue"
},
  "geometry": {"coordinates":[-3.002426,51.073841],"type":"Point"}
}