{
  "type": "Feature",
  "properties": {
    "addr:full":"17 Crossfield Road Keighley North Yorkshire BD22 9SD",
    "addr:housenumber":"17",
    "addr:postcode":"bd22 9sd",
    "addr:street":"Crossfield Road",
    "iso:country":"GB",
    "sg:address":"17 Crossfield Road",
    "sg:city":"Keighley",
    "sg:classifiers":[
        {
            "category":"Professional",
            "subcategory":"Engineering",
            "type":"Services"
        }
    ],
    "sg:postcode":"BD22 9SD",
    "sg:province":"North Yorkshire",
    "wof:name":"Brancast Ltd.",
    "wof:placetype":"venue"
},
  "geometry": {"coordinates":[-1.955568,53.814838],"type":"Point"}
}