{
  "type": "Feature",
  "properties": {
    "addr:full":"31 Osborne Place Aberdeen Aberdeen City AB25 2BX",
    "addr:housenumber":"31",
    "addr:postcode":"ab25 2bx",
    "addr:street":"Osborne Place",
    "iso:country":"GB",
    "sg:address":"31 Osborne Place",
    "sg:city":"Aberdeen",
    "sg:classifiers":[
        {
            "category":"Arts & Performance",
            "subcategory":"Music",
            "type":"Entertainment"
        }
    ],
    "sg:phone":"+44 1224 643807",
    "sg:postcode":"AB25 2BX",
    "sg:province":"Aberdeen City",
    "sg:tags":[
        "musician",
        "composer"
    ],
    "wof:name":"The Four By Four String Quartet",
    "wof:placetype":"venue"
},
  "geometry": {"coordinates":[-2.12121,57.145531],"type":"Point"}
}