{
  "type": "Feature",
  "properties": {
    "addr:full":"29-30 Church Road Business Centr Sittingbourne Kent ME10 3RS",
    "addr:housenumber":"29-30",
    "addr:postcode":"me10 3rs",
    "addr:street":"Church Road",
    "iso:country":"GB",
    "sg:address":"29-30 Church Road Business Centr",
    "sg:city":"Sittingbourne",
    "sg:classifiers":[
        {
            "category":"Professional",
            "subcategory":"Printing & Photocopies",
            "type":"Services"
        }
    ],
    "sg:phone":"+44 1795 427153",
    "sg:postcode":"ME10 3RS",
    "sg:province":"Kent",
    "sg:tags":[
        "printer"
    ],
    "wof:name":"Colourbank Graphics Ltd.",
    "wof:placetype":"venue"
},
  "geometry": {"coordinates":[0.75331,51.344791],"type":"Point"}
}