{
  "type": "Feature",
  "properties": {
    "addr:full":"Unit 3, 9 Thames Road Barking Essex IG11 0HN",
    "addr:housenumber":"unit;9",
    "addr:postcode":"ig11 0hn",
    "addr:street":"Thames Road",
    "iso:country":"GB",
    "sg:address":"Unit 3, 9 Thames Road",
    "sg:city":"Barking",
    "sg:classifiers":[
        {
            "category":"Manufacturing",
            "subcategory":"Textiles",
            "type":"Manufacturing & Wholesale Goods"
        },
        {
            "category":"Professional",
            "subcategory":"Printing & Photocopies",
            "type":"Services"
        }
    ],
    "sg:postcode":"IG11 0HN",
    "sg:province":"Essex",
    "sg:tags":[
        "embroiderer",
        "designer"
    ],
    "wof:name":"New India Fashions",
    "wof:placetype":"venue"
},
  "geometry": {"coordinates":[0.0991830006,51.5253829956],"type":"Point"}
}