{
  "type": "Feature",
  "properties": {
    "iso:country":"GB",
    "sg:address":"76-88 High Street",
    "sg:city":"Staines",
    "sg:classifiers":[
        {
            "category":"Professional",
            "subcategory":"Management & Consulting",
            "type":"Services"
        },
        {
            "category":"Communications",
            "type":"Services"
        },
        {
            "category":"Shopping",
            "subcategory":"Computers & Home Electronics",
            "type":"Retail Goods"
        }
    ],
    "sg:postcode":"TW18 4DP",
    "sg:province":"Berkshire",
    "sg:tags":[
        "consultant",
        "business",
        "audio-visual"
    ],
    "wof:name":"M A Consultancy",
    "wof:placetype":"venue"
},
  "geometry": {"coordinates":[-0.510434,51.434422],"type":"Point"}
}