{
  "type": "Feature",
  "properties": {
    "addr:full":"Bridge Rd Ipswich Suffolk IP10 0NA",
    "addr:postcode":"ip10 0na",
    "addr:street":"Bridge Rd",
    "iso:country":"GB",
    "sg:address":"Bridge Rd",
    "sg:city":"Ipswich",
    "sg:classifiers":[
        {
            "category":"Professional",
            "subcategory":"Employment Agencies",
            "type":"Services"
        }
    ],
    "sg:phone":"+44 1473 654205",
    "sg:postcode":"IP10 0NA",
    "sg:province":"Suffolk",
    "sg:tags":[
        "consultant"
    ],
    "wof:name":"Elite Recruitment Consultants",
    "wof:placetype":"venue"
},
  "geometry": {"coordinates":[1.2532470226,52.0078163147],"type":"Point"}
}