{
  "type": "Feature",
  "properties": {
    "addr:full":"Coronation Street Retford Nottinghamshire DN22 6DX",
    "addr:postcode":"dn22 6dx",
    "addr:street":"Coronation Street",
    "iso:country":"GB",
    "sg:address":"Coronation Street",
    "sg:city":"Retford",
    "sg:classifiers":[
        {
            "category":"Arts & Performance",
            "subcategory":"Theater",
            "type":"Entertainment"
        }
    ],
    "sg:phone":"+44 1777 706866",
    "sg:postcode":"DN22 6DX",
    "sg:province":"Nottinghamshire",
    "sg:tags":[
        "hall",
        "theatre",
        "concert"
    ],
    "wof:name":"Majestic Theatre",
    "wof:placetype":"venue"
},
  "geometry": {"coordinates":[-0.943397,53.321209],"type":"Point"}
}