{
  "type": "Feature",
  "properties": {
    "addr:full":"Charnwood House, Rankers Lane Bristol Somerset BS39 4JY",
    "addr:postcode":"bs39 4jy",
    "addr:street":"Rankers Lane",
    "iso:country":"GB",
    "sg:address":"Charnwood House, Rankers Lane",
    "sg:city":"Bristol",
    "sg:classifiers":[
        {
            "category":"Building & Trades",
            "subcategory":"Construction",
            "type":"Services"
        }
    ],
    "sg:postcode":"BS39 4JY",
    "sg:province":"Somerset",
    "sg:tags":[
        "joiner",
        "carpenter"
    ],
    "wof:name":"J W Sheridan",
    "wof:placetype":"venue"
},
  "geometry": {"coordinates":[-2.5117950439,51.3755455017],"type":"Point"}
}