{
  "type": "Feature",
  "properties": {
    "addr:full":"9 Victoria Street Aberdeen Aberdeen City AB10 1XB",
    "addr:housenumber":"9",
    "addr:postcode":"ab10 1xb",
    "addr:street":"Victoria Street",
    "iso:country":"GB",
    "sg:address":"9 Victoria Street",
    "sg:city":"Aberdeen",
    "sg:classifiers":[
        {
            "category":"Real Estate",
            "subcategory":"Surveying",
            "type":"Services"
        }
    ],
    "sg:phone":"+44 1224 646949",
    "sg:postcode":"AB10 1XB",
    "sg:province":"Aberdeen City",
    "sg:tags":[
        "surveyor",
        "land",
        "valuer"
    ],
    "wof:name":"COUNTRYWIDE SURVEYORS (1994)",
    "wof:placetype":"venue"
},
  "geometry": {"coordinates":[-2.1135621071,57.1434860229],"type":"Point"}
}