{
  "type": "Feature",
  "properties": {
    "iso:country":"GB",
    "sg:address":"22 Glenesk Rd",
    "sg:city":"Eltham",
    "sg:classifiers":[
        {
            "category":"Health Services",
            "subcategory":"Health Practitioner",
            "type":"Services"
        }
    ],
    "sg:phone":"+44 20 8850 6682",
    "sg:postcode":"SE9 1AG",
    "sg:province":"Greater London",
    "sg:tags":[
        "osteopath"
    ],
    "wof:name":"W.H Morris D.O. D.Phys. LCSP",
    "wof:placetype":"venue"
},
  "geometry": {"coordinates":[0.066346,51.45314],"type":"Point"}
}