{
  "type": "Feature",
  "properties": {
    "iso:country":"GB",
    "sg:address":"73 High Street",
    "sg:city":"Tring",
    "sg:classifiers":[
        {
            "category":"Personal",
            "subcategory":"Beauty Salon",
            "type":"Services"
        },
        {
            "category":"Personal",
            "subcategory":"Barber",
            "type":"Services"
        }
    ],
    "sg:phone":"+44 1442 828121",
    "sg:postcode":"HP23 4AB",
    "sg:province":"Buckinghamshire",
    "sg:tags":[
        "unisex",
        "hairdresser"
    ],
    "wof:name":"One to One Hairdressing",
    "wof:placetype":"venue"
},
  "geometry": {"coordinates":[-0.663437,51.793259],"type":"Point"}
}