{
  "type": "Feature",
  "properties": {
    "iso:country":"GB",
    "sg:address":"511 Hilton Lane, Worsley",
    "sg:city":"Manchester",
    "sg:classifiers":[
        {
            "category":"Retail",
            "subcategory":"Auto Repair",
            "type":"Services"
        }
    ],
    "sg:postcode":"M28 3TE",
    "sg:province":"Greater Manchester",
    "sg:tags":[
        "modification",
        "garage"
    ],
    "wof:name":"M & I Garage Services",
    "wof:placetype":"venue"
},
  "geometry": {"coordinates":[-2.404521,53.518211],"type":"Point"}
}