{
  "type": "Feature",
  "properties": {
    "iso:country":"GB",
    "sg:address":"1 Ives St",
    "sg:city":"Chelsea",
    "sg:classifiers":[
        {
            "category":"Transit Center",
            "subcategory":"Freight",
            "type":"Transportation"
        }
    ],
    "sg:phone":"+44 20 7581 0077",
    "sg:postcode":"SW3 2ND",
    "sg:province":"Greater London",
    "sg:tags":[
        "shop",
        "craft",
        "centre"
    ],
    "wof:name":"Makers",
    "wof:placetype":"venue"
},
  "geometry": {"coordinates":[-0.167128,51.493565],"type":"Point"}
}