{
  "type": "Feature",
  "properties": {
    "addr:full":"Cardiff Rd Reading Berkshire RG1 8HY",
    "addr:postcode":"rg1 8hy",
    "addr:street":"Cardiff Rd",
    "iso:country":"GB",
    "sg:address":"Cardiff Rd",
    "sg:city":"Reading",
    "sg:classifiers":[
        {
            "category":"Retail",
            "subcategory":"Auto Repair",
            "type":"Services"
        }
    ],
    "sg:phone":"+44 118 957 4511",
    "sg:postcode":"RG1 8HY",
    "sg:province":"Berkshire",
    "sg:tags":[
        "modification",
        "garage"
    ],
    "wof:name":"Cardiff Road Service Station",
    "wof:placetype":"venue"
},
  "geometry": {"coordinates":[-0.987894,51.461842],"type":"Point"}
}