{
  "type": "Feature",
  "properties": {
    "addr:full":"50 Ilkeston Road Heanor Derbyshire DE75 7DT",
    "addr:housenumber":"50",
    "addr:postcode":"de75 7dt",
    "addr:street":"Ilkeston Road",
    "iso:country":"GB",
    "sg:address":"50 Ilkeston Road",
    "sg:city":"Heanor",
    "sg:classifiers":[
        {
            "category":"Organizations",
            "subcategory":"Non-profit Organization",
            "type":"Services"
        }
    ],
    "sg:phone":"+44 1773 712062",
    "sg:postcode":"DE75 7DT",
    "sg:province":"Derbyshire",
    "sg:tags":[
        "charitable",
        "organisation",
        "voluntary",
        "charity"
    ],
    "wof:name":"Heanor Miners Welfare",
    "wof:placetype":"venue"
},
  "geometry": {"coordinates":[-1.35139,53.01133],"type":"Point"}
}