{
  "type": "Feature",
  "properties": {
    "iso:country":"GB",
    "sg:address":"Belville House, Ponteland",
    "sg:city":"Newcastle-upon-tyne",
    "sg:classifiers":[
        {
            "category":"Shopping",
            "subcategory":"Computers & Home Electronics",
            "type":"Retail Goods"
        }
    ],
    "sg:phone":"+44 1661 803000",
    "sg:postcode":"NE20 9BD",
    "sg:province":"Northumberland",
    "wof:name":"Newcastle Computer Services Plc",
    "wof:placetype":"venue"
},
  "geometry": {"coordinates":[-1.739671,55.049992],"type":"Point"}
}