{
  "type": "Feature",
  "properties": {
    "addr:full":"Alfred Street Montrose Aberdeenshire DD10 8HW",
    "addr:postcode":"dd10 8hw",
    "addr:street":"Alfred Street",
    "iso:country":"GB",
    "sg:address":"Alfred Street",
    "sg:city":"Montrose",
    "sg:classifiers":[
        {
            "category":"Manufacturing",
            "subcategory":"Building Materials",
            "type":"Manufacturing & Wholesale Goods"
        }
    ],
    "sg:phone":"+44 1674 672792",
    "sg:postcode":"DD10 8HW",
    "sg:province":"Aberdeenshire",
    "sg:tags":[
        "concrete",
        "product"
    ],
    "wof:name":"Ian Rennie Precast",
    "wof:placetype":"venue"
},
  "geometry": {"coordinates":[-2.4621639252,56.7082099915],"type":"Point"}
}