{
  "type": "Feature",
  "properties": {
    "addr:full":"Coombe Farm, Goodleigh Barnstaple Devon EX32 7NB",
    "addr:postcode":"ex32 7nb",
    "iso:country":"GB",
    "sg:address":"Coombe Farm, Goodleigh",
    "sg:city":"Barnstaple",
    "sg:classifiers":[
        {
            "category":"Organizations",
            "subcategory":"Non-profit Organization",
            "type":"Services"
        }
    ],
    "sg:phone":"+44 1271 378824",
    "sg:postcode":"EX32 7NB",
    "sg:province":"Devon",
    "sg:tags":[
        "organisation",
        "voluntary",
        "charity"
    ],
    "wof:name":"Cancer Relief Macmillan Fund",
    "wof:placetype":"venue"
},
  "geometry": {"coordinates":[-4.0025901794,51.0890541077],"type":"Point"}
}