{
  "type": "Feature",
  "properties": {
    "iso:country":"GB",
    "sg:address":"Club Lane, Chipping",
    "sg:city":"Preston",
    "sg:classifiers":[
        {
            "category":"Education",
            "subcategory":"School",
            "type":"Public Place"
        }
    ],
    "sg:phone":"+44 1995 61367",
    "sg:postcode":"PR3 2QH",
    "sg:province":"Lancashire",
    "sg:tags":[
        "local",
        "authority"
    ],
    "wof:name":"St Mary's R C School",
    "wof:placetype":"venue"
},
  "geometry": {"coordinates":[-2.57736,53.88409],"type":"Point"}
}