{
  "type": "Feature",
  "properties": {
    "addr:full":"209a Great Horton Road Bradford West Yorkshire BD7 1RP",
    "addr:housenumber":"209a",
    "addr:postcode":"bd7 1rp",
    "addr:street":"Great Horton Road",
    "iso:country":"GB",
    "sg:address":"209a Great Horton Road",
    "sg:city":"Bradford",
    "sg:classifiers":[
        {
            "category":"Taxi",
            "type":"Transportation"
        },
        {
            "category":"Military Area",
            "subcategory":"Air Force Base",
            "type":"Public Place"
        }
    ],
    "sg:phone":"+44 1274 576866",
    "sg:postcode":"BD7 1RP",
    "sg:province":"West Yorkshire",
    "sg:tags":[
        "hire",
        "private"
    ],
    "wof:name":"ROYAL TAXIS",
    "wof:placetype":"venue"
},
  "geometry": {"coordinates":[-1.7734669447,53.7870941162],"type":"Point"}
}