{
  "type": "Feature",
  "properties": {
    "iso:country":"GB",
    "sg:address":"21 Nodgham Lane, Carisbrooke",
    "sg:city":"Newport",
    "sg:classifiers":[
        {
            "category":"Professional",
            "subcategory":"Engineering",
            "type":"Services"
        }
    ],
    "sg:phone":"+44 1983 525970",
    "sg:postcode":"PO30 1NY",
    "sg:province":"Isle of Wight",
    "sg:tags":[
        "contractor",
        "electrical",
        "engineer"
    ],
    "wof:name":"Geoff Pike Electrical",
    "wof:placetype":"venue"
},
  "geometry": {"coordinates":[-1.320075,50.68985],"type":"Point"}
}