{
  "type": "Feature",
  "properties": {
    "iso:country":"GB",
    "sg:address":"Beechtrees, Digmoor",
    "sg:city":"Skelmersdale",
    "sg:classifiers":[
        {
            "category":"Organizations",
            "subcategory":"Religious Organization",
            "type":"Services"
        }
    ],
    "sg:postcode":"WN8 9EZ",
    "sg:province":"Lancashire",
    "sg:tags":[
        "organisation"
    ],
    "wof:name":"Holy Family Convent",
    "wof:placetype":"venue"
},
  "geometry": {"coordinates":[-2.763354,53.540134],"type":"Point"}
}