{
  "type": "Feature",
  "properties": {
    "iso:country":"GB",
    "sg:address":"Garrison Lane",
    "sg:city":"St Marys",
    "sg:classifiers":[
        {
            "category":"Shopping",
            "subcategory":"Gifts & Souvenirs",
            "type":"Retail Goods"
        }
    ],
    "sg:postcode":"TR21 0JD",
    "sg:province":"Cornwall",
    "sg:tags":[
        "shop"
    ],
    "wof:name":"Gibson-Kyne",
    "wof:placetype":"venue"
},
  "geometry": {"coordinates":[-6.324264,49.910225],"type":"Point"}
}