{
  "type": "Feature",
  "properties": {
    "iso:country":"GB",
    "sg:address":"41 Jackson Road",
    "sg:city":"Clacton-on-sea",
    "sg:classifiers":[
        {
            "category":"Sports & Exercise",
            "subcategory":"Sports Center",
            "type":"Entertainment"
        },
        {
            "category":"Shopping",
            "subcategory":"Comic Books",
            "type":"Retail Goods"
        }
    ],
    "sg:postcode":"CO15 1JA",
    "sg:province":"Essex",
    "sg:tags":[
        "shop",
        "jeweller"
    ],
    "wof:name":"More Sports",
    "wof:placetype":"venue"
},
  "geometry": {"coordinates":[1.1504100561,51.7887382507],"type":"Point"}
}