{
  "type": "Feature",
  "properties": {
    "addr:full":"183 North Cray Road Sidcup Kent DA14 5LT",
    "addr:housenumber":"183",
    "addr:postcode":"da14 5lt",
    "addr:street":"North Cray Road",
    "iso:country":"GB",
    "sg:address":"183 North Cray Road",
    "sg:city":"Sidcup",
    "sg:classifiers":[
        {
            "category":"Professional",
            "subcategory":"Engineering",
            "type":"Services"
        }
    ],
    "sg:postcode":"DA14 5LT",
    "sg:province":"Kent",
    "sg:tags":[
        "contractor",
        "electrical",
        "engineer"
    ],
    "wof:name":"Parkdale Electrical",
    "wof:placetype":"venue"
},
  "geometry": {"coordinates":[0.1290069968,51.4163780212],"type":"Point"}
}