{
  "type": "Feature",
  "properties": {
    "iso:country":"GB",
    "sg:address":"508 Coniscliffe Road",
    "sg:city":"Darlington",
    "sg:classifiers":[
        {
            "category":"Building & Trades",
            "subcategory":"Construction",
            "type":"Services"
        }
    ],
    "sg:postcode":"DL3 8TB",
    "sg:province":"Durham",
    "sg:tags":[
        "builder"
    ],
    "wof:name":"Robert Wytcherley Building Contractors Ltd.",
    "wof:placetype":"venue"
},
  "geometry": {"coordinates":[-1.5995390415,54.5192108154],"type":"Point"}
}