{
  "type": "Feature",
  "properties": {
    "addr:full":"5 Oxford Road, Garsington Oxford Oxfordshire OX44 9DA",
    "addr:housenumber":"5",
    "addr:postcode":"ox44 9da",
    "addr:street":"Oxford Road",
    "iso:country":"GB",
    "sg:address":"5 Oxford Road, Garsington",
    "sg:city":"Oxford",
    "sg:classifiers":[
        {
            "category":"Professional",
            "subcategory":"Engineering",
            "type":"Services"
        }
    ],
    "sg:phone":"+44 1865 368191",
    "sg:postcode":"OX44 9DA",
    "sg:province":"Oxfordshire",
    "sg:tags":[
        "contractor",
        "electrical",
        "engineer"
    ],
    "wof:name":"F W Electrics",
    "wof:placetype":"venue"
},
  "geometry": {"coordinates":[-1.224208951,51.7215843201],"type":"Point"}
}