{
  "type": "Feature",
  "properties": {
    "iso:country":"GB",
    "sg:address":"Westleton House, The Street, Westleton",
    "sg:city":"Saxmundham",
    "sg:classifiers":[
        {
            "category":"Shopping",
            "subcategory":"Department Store",
            "type":"Retail Goods"
        },
        {
            "category":"Shopping",
            "subcategory":"Gifts & Souvenirs",
            "type":"Retail Goods"
        }
    ],
    "sg:phone":"+44 1728 648227",
    "sg:postcode":"IP17 3AA",
    "sg:province":"Suffolk",
    "sg:tags":[
        "shop"
    ],
    "wof:name":"Westleton Cottage Crafts & Tea Room",
    "wof:placetype":"venue"
},
  "geometry": {"coordinates":[1.534078,52.277332],"type":"Point"}
}