{
  "type": "Feature",
  "properties": {
    "addr:full":"246 Kings Cross Road Halifax West Yorkshire HX1 3JP",
    "addr:housenumber":"246",
    "addr:postcode":"hx1 3jp",
    "addr:street":"Kings Cross Road",
    "iso:country":"GB",
    "sg:address":"246 Kings Cross Road",
    "sg:city":"Halifax",
    "sg:classifiers":[
        {
            "category":"Cinema",
            "subcategory":"Movie Rental",
            "type":"Entertainment"
        }
    ],
    "sg:phone":"+44 1422 367887",
    "sg:postcode":"HX1 3JP",
    "sg:province":"West Yorkshire",
    "sg:tags":[
        "video",
        "library"
    ],
    "wof:name":"Star Videos & Computer Game Centre",
    "wof:placetype":"venue"
},
  "geometry": {"coordinates":[-1.8805589676,53.7154998779],"type":"Point"}
}