{
  "type": "Feature",
  "properties": {
    "iso:country":"GB",
    "sg:address":"6 Cogan Street",
    "sg:city":"Glasgow",
    "sg:classifiers":[
        {
            "category":"Retail",
            "subcategory":"Auto Repair",
            "type":"Services"
        }
    ],
    "sg:phone":"+44 141 881 5081",
    "sg:postcode":"G78 1QP",
    "sg:province":"East Ayrshire",
    "sg:tags":[
        "modification",
        "garage"
    ],
    "wof:name":"Bryers & Mulholland",
    "wof:placetype":"venue"
},
  "geometry": {"coordinates":[-4.398164,55.800022],"type":"Point"}
}