{
  "type": "Feature",
  "properties": {
    "addr:full":"32 Lees Lane Bristol Gloucestershire BS30 8LB",
    "addr:housenumber":"32",
    "addr:postcode":"bs30 8lb",
    "addr:street":"Lees Lane",
    "iso:country":"GB",
    "sg:address":"32 Lees Lane",
    "sg:city":"Bristol",
    "sg:classifiers":[
        {
            "category":"Personal",
            "subcategory":"Beauty Salon",
            "type":"Services"
        }
    ],
    "sg:postcode":"BS30 8LB",
    "sg:province":"Gloucestershire",
    "sg:tags":[
        "lady",
        "hairdresser"
    ],
    "wof:name":"Tara's Mobile Hairdressing",
    "wof:placetype":"venue"
},
  "geometry": {"coordinates":[-2.4670050144,51.4492263794],"type":"Point"}
}