{
  "type": "Feature",
  "properties": {
    "addr:full":"7 Hollins Grove St Darwen Lancashire BB3 1HG",
    "addr:housenumber":"7",
    "addr:postcode":"bb3 1hg",
    "addr:street":"Hollins Grove St",
    "iso:country":"GB",
    "sg:address":"7 Hollins Grove St",
    "sg:city":"Darwen",
    "sg:classifiers":[
        {
            "category":"Retail",
            "subcategory":"Repair Shop",
            "type":"Services"
        }
    ],
    "sg:phone":"+44 1254 775510",
    "sg:postcode":"BB3 1HG",
    "sg:province":"Lancashire",
    "sg:tags":[
        "furniture"
    ],
    "wof:name":"ALLWOODS PAINT STRIPPERS",
    "wof:placetype":"venue"
},
  "geometry": {"coordinates":[-2.477575,53.705902],"type":"Point"}
}