{
  "type": "Feature",
  "properties": {
    "addr:full":"35 Field Lane, Pelsall Walsall West Midlands WS4 1DN",
    "addr:housenumber":"35",
    "addr:postcode":"ws4 1dn",
    "addr:street":"Field Lane",
    "iso:country":"GB",
    "sg:address":"35 Field Lane, Pelsall",
    "sg:city":"Walsall",
    "sg:classifiers":[
        {
            "category":"Personal",
            "type":"Services"
        }
    ],
    "sg:phone":"+44 1922 691528",
    "sg:postcode":"WS4 1DN",
    "sg:province":"West Midlands",
    "sg:tags":[
        "wedding"
    ],
    "wof:name":"Barry James Photography",
    "wof:placetype":"venue"
},
  "geometry": {"coordinates":[-1.958379,52.621754],"type":"Point"}
}