{
  "type": "Feature",
  "properties": {
    "addr:full":"Station Road, Stow Bridge King's Lynn Lincolnshire PE34 3PH",
    "addr:postcode":"pe34 3ph",
    "addr:street":"Station Road",
    "iso:country":"GB",
    "sg:address":"Station Road, Stow Bridge",
    "sg:city":"King's Lynn",
    "sg:classifiers":[
        {
            "category":"Bars & Pubs",
            "type":"Food & Drink"
        }
    ],
    "sg:phone":"+44 1366 384147",
    "sg:postcode":"PE34 3PH",
    "sg:province":"Lincolnshire",
    "sg:tags":[
        "pubs",
        "inn"
    ],
    "wof:name":"The Heron Hotel",
    "wof:placetype":"venue"
},
  "geometry": {"coordinates":[0.37492,52.636829],"type":"Point"}
}