{
  "type": "Feature",
  "properties": {
    "addr:full":"57 Lynn Road King's Lynn Norfolk PE30 4PY",
    "addr:housenumber":"57",
    "addr:postcode":"pe30 4py",
    "addr:street":"Lynn Road",
    "iso:country":"GB",
    "sg:address":"57 Lynn Road",
    "sg:city":"King's Lynn",
    "sg:classifiers":[
        {
            "category":"Personal",
            "subcategory":"Beauty Salon",
            "type":"Services"
        }
    ],
    "sg:phone":"+44 1553 774853",
    "sg:postcode":"PE30 4PY",
    "sg:province":"Norfolk",
    "sg:tags":[
        "unisex",
        "hairdresser"
    ],
    "wof:name":"Charles Hair Designs",
    "wof:placetype":"venue"
},
  "geometry": {"coordinates":[0.41965,52.757198],"type":"Point"}
}