{
  "type": "Feature",
  "properties": {
    "iso:country":"GB",
    "sg:address":"Harcourt House, 19a Cavendish Square",
    "sg:city":"London",
    "sg:classifiers":[
        {
            "category":"Professional",
            "subcategory":"Employment Agencies",
            "type":"Services"
        }
    ],
    "sg:postcode":"W1G 0PN",
    "sg:province":"Greater London",
    "sg:tags":[
        "consultant"
    ],
    "wof:name":"Lewis Briggs & Partners Ltd.",
    "wof:placetype":"venue"
},
  "geometry": {"coordinates":[-0.144107,51.516586],"type":"Point"}
}