{
  "type": "Feature",
  "properties": {
    "addr:full":"Huntershill St Glasgow East Dunbartonshire G21 3SU",
    "addr:postcode":"g21 3su",
    "addr:street":"St",
    "iso:country":"GB",
    "sg:address":"Huntershill St",
    "sg:city":"Glasgow",
    "sg:classifiers":[
        {
            "category":"Place Of Worship",
            "type":"Public Place"
        }
    ],
    "sg:phone":"+44 141 558 1868",
    "sg:postcode":"G21 3SU",
    "sg:province":"East Dunbartonshire",
    "wof:name":"Springburn Baptist Church",
    "wof:placetype":"venue"
},
  "geometry": {"coordinates":[-4.2323508263,55.8919410706],"type":"Point"}
}