{
  "type": "Feature",
  "properties": {
    "addr:full":"Unit 17 Vulcan Ho, Vulcan Rd Leicester Leicestershire LE5 3EF",
    "addr:housenumber":"unit 17",
    "addr:postcode":"le5 3ef",
    "addr:street":"Vulcan Ho Vulcan Rd",
    "iso:country":"GB",
    "sg:address":"Unit 17 Vulcan Ho, Vulcan Rd",
    "sg:city":"Leicester",
    "sg:classifiers":[
        {
            "category":"Manufacturing",
            "subcategory":"Textiles",
            "type":"Manufacturing & Wholesale Goods"
        }
    ],
    "sg:phone":"+44 116 253 8628",
    "sg:postcode":"LE5 3EF",
    "sg:province":"Leicestershire",
    "sg:tags":[
        "merchant",
        "agent"
    ],
    "wof:name":"Britannica Clothing Company",
    "wof:placetype":"venue"
},
  "geometry": {"coordinates":[-1.1148500443,52.6388511658],"type":"Point"}
}