{
  "type": "Feature",
  "properties": {
    "iso:country":"GB",
    "sg:address":"Auckland Road, Sparkbrook",
    "sg:city":"Birmingham",
    "sg:classifiers":[
        {
            "category":"Professional",
            "subcategory":"Printing & Photocopies",
            "type":"Services"
        }
    ],
    "sg:phone":"+44 121 772 2702",
    "sg:postcode":"B11 1RH",
    "sg:province":"West Midlands",
    "sg:tags":[
        "printer"
    ],
    "wof:name":"H W Owen & Co Ltd",
    "wof:placetype":"venue"
},
  "geometry": {"coordinates":[-1.875997,52.463089],"type":"Point"}
}