{
  "type": "Feature",
  "properties": {
    "addr:full":"3 Jillygate York North Yorkshire YO30 7EA",
    "addr:housenumber":"3",
    "addr:postcode":"yo30 7ea",
    "addr:street":"Jillygate York",
    "iso:country":"GB",
    "sg:address":"3 Jillygate",
    "sg:city":"York",
    "sg:classifiers":[
        {
            "category":"Personal",
            "type":"Services"
        },
        {
            "category":"Arts & Performance",
            "subcategory":"Theater",
            "type":"Entertainment"
        }
    ],
    "sg:phone":"+44 1904 626051",
    "sg:postcode":"YO30 7EA",
    "sg:province":"North Yorkshire",
    "sg:tags":[
        "dressmaker",
        "ballet",
        "dancewear"
    ],
    "wof:name":"Dancers",
    "wof:placetype":"venue"
},
  "geometry": {"coordinates":[-1.0854879618,53.9631652832],"type":"Point"}
}