{
  "type": "Feature",
  "properties": {
    "addr:full":"3 Selby Walk Woking Surrey GU21 3DT",
    "addr:housenumber":"3",
    "addr:postcode":"gu21 3dt",
    "addr:street":"Selby Walk",
    "iso:country":"GB",
    "sg:address":"3 Selby Walk",
    "sg:city":"Woking",
    "sg:classifiers":[
        {
            "category":"Building & Trades",
            "subcategory":"Construction",
            "type":"Services"
        }
    ],
    "sg:phone":"+44 1483 769184",
    "sg:postcode":"GU21 3DT",
    "sg:province":"Surrey",
    "sg:tags":[
        "joiner",
        "carpenter"
    ],
    "wof:name":"Parker Interiors",
    "wof:placetype":"venue"
},
  "geometry": {"coordinates":[-0.5836889744,51.3160095215],"type":"Point"}
}