{
  "type": "Feature",
  "properties": {
    "iso:country":"GB",
    "sg:address":"Intergas House, Speedwell Road, Parkhouse East",
    "sg:city":"Newcastle",
    "sg:classifiers":[
        {
            "category":"Utilities",
            "subcategory":"Natural Gas",
            "type":"Services"
        }
    ],
    "sg:phone":"+44 1782 565556",
    "sg:postcode":"ST5 7RG",
    "sg:province":"Staffordshire",
    "sg:tags":[
        "supplier",
        "industrial"
    ],
    "wof:name":"International Gases & Chemicals Ltd.",
    "wof:placetype":"venue"
},
  "geometry": {"coordinates":[-2.242192,53.05032],"type":"Point"}
}