{
  "type": "Feature",
  "properties": {
    "addr:full":"PO Box 259 Ware SG12 0US",
    "addr:housenumber":"po",
    "addr:postcode":"sg12 0us",
    "addr:street":"Box 259",
    "iso:country":"GB",
    "sg:address":"PO Box 259",
    "sg:city":"Ware",
    "sg:classifiers":[
        {
            "category":"Professional",
            "subcategory":"Business Services",
            "type":"Services"
        }
    ],
    "sg:postcode":"SG12 0US",
    "sg:tags":[
        "audio",
        "phonecast",
        "social-networking",
        "social-media",
        "broadcast",
        "phlog",
        "blog"
    ],
    "sg:website":"http://www.ipadio.com",
    "wof:name":"Ipadio",
    "wof:placetype":"venue"
},
  "geometry": {"coordinates":[0.0118608,51.8205815],"type":"Point"}
}