{
  "type": "Feature",
  "properties": {
    "addr:full":"Unit 13, Bright House, Bright Rd, Eccles Manchester Greater Manchester M30 0WG",
    "addr:housenumber":"unit 13",
    "addr:postcode":"m30 0wg",
    "addr:street":"Bright Rd",
    "iso:country":"GB",
    "sg:address":"Unit 13, Bright House, Bright Rd, Eccles",
    "sg:city":"Manchester",
    "sg:classifiers":[
        {
            "category":"Manufacturing",
            "subcategory":"Metals",
            "type":"Manufacturing & Wholesale Goods"
        }
    ],
    "sg:phone":"+44 161 707 1856",
    "sg:postcode":"M30 0WG",
    "sg:province":"Greater Manchester",
    "sg:tags":[
        "steel",
        "fabricator",
        "erectors"
    ],
    "wof:name":"J.D Fabrications",
    "wof:placetype":"venue"
},
  "geometry": {"coordinates":[-2.3450040817,53.485080719],"type":"Point"}
}