{
  "type": "Feature",
  "properties": {
    "addr:full":"71 Forest Rd Sandown Isle of Wight PO36 0JZ",
    "addr:housenumber":"71",
    "addr:postcode":"po36 0jz",
    "addr:street":"Forest Rd",
    "iso:country":"GB",
    "sg:address":"71 Forest Rd",
    "sg:city":"Sandown",
    "sg:classifiers":[
        {
            "category":"Building & Trades",
            "subcategory":"Construction",
            "type":"Services"
        }
    ],
    "sg:phone":"+44 1983 401414",
    "sg:postcode":"PO36 0JZ",
    "sg:province":"Isle of Wight",
    "sg:tags":[
        "demolition",
        "contractor"
    ],
    "wof:name":"Shanklin Salvage Demolition Contractor",
    "wof:placetype":"venue"
},
  "geometry": {"coordinates":[-1.2011660337,50.6551055908],"type":"Point"}
}