{
  "type": "Feature",
  "properties": {
    "iso:country":"GB",
    "sg:address":"20 Lowgate, Lutton",
    "sg:city":"Spalding",
    "sg:classifiers":[
        {
            "category":"Education",
            "subcategory":"Dance Studio",
            "type":"Public Place"
        }
    ],
    "sg:phone":"+44 1406 365650",
    "sg:postcode":"PE12 9HP",
    "sg:province":"Cambridgeshire",
    "sg:tags":[
        "school",
        "dancing"
    ],
    "wof:name":"Lowgate School of Dancing",
    "wof:placetype":"venue"
},
  "geometry": {"coordinates":[0.142935,52.84906],"type":"Point"}
}