{
  "type": "Feature",
  "properties": {
    "addr:full":"17 Dordon Close, Shirley Solihull West Midlands B90 1AH",
    "addr:housenumber":"17",
    "addr:postcode":"b90 1ah",
    "addr:street":"Dordon Close",
    "iso:country":"GB",
    "sg:address":"17 Dordon Close, Shirley",
    "sg:city":"Solihull",
    "sg:classifiers":[
        {
            "category":"Professional",
            "subcategory":"Secretarial Services",
            "type":"Services"
        }
    ],
    "sg:phone":"+44 121 244 9825",
    "sg:postcode":"B90 1AH",
    "sg:province":"West Midlands",
    "wof:name":"Coton Admin Services",
    "wof:placetype":"venue"
},
  "geometry": {"coordinates":[-1.848548,52.402134],"type":"Point"}
}