{
  "type": "Feature",
  "properties": {
    "addr:full":"Blueride Lodge, East Horsley Leatherhead Surrey KT24 6NU",
    "addr:postcode":"kt24 6nu",
    "iso:country":"GB",
    "sg:address":"Blueride Lodge, East Horsley",
    "sg:city":"Leatherhead",
    "sg:classifiers":[
        {
            "category":"Building & Trades",
            "subcategory":"Construction",
            "type":"Services"
        }
    ],
    "sg:phone":"+44 1483 282156",
    "sg:postcode":"KT24 6NU",
    "sg:province":"Surrey",
    "sg:tags":[
        "builder"
    ],
    "wof:name":"J Rogerson Building & Restoration",
    "wof:placetype":"venue"
},
  "geometry": {"coordinates":[-0.435424,51.2776298523],"type":"Point"}
}