{
  "type": "Feature",
  "properties": {
    "addr:full":"The Chapel, Coffin Lane, Kirk Ireton Ashbourne Derbyshire DE6 3JW",
    "addr:postcode":"de6 3jw",
    "addr:street":"Coffin Lane",
    "iso:country":"GB",
    "sg:address":"The Chapel, Coffin Lane, Kirk Ireton",
    "sg:city":"Ashbourne",
    "sg:classifiers":[
        {
            "category":"Professional",
            "type":"Services"
        },
        {
            "category":"Professional",
            "subcategory":"Art Services",
            "type":"Services"
        }
    ],
    "sg:phone":"+44 1335 370783",
    "sg:postcode":"DE6 3JW",
    "sg:province":"Derbyshire",
    "sg:tags":[
        "interior",
        "furnishers",
        "designer"
    ],
    "wof:name":"Interior Artistry",
    "wof:placetype":"venue"
},
  "geometry": {"coordinates":[-1.602169,53.048016],"type":"Point"}
}