{
  "type": "Feature",
  "properties": {
    "iso:country":"GB",
    "sg:address":"346 Main Street",
    "sg:city":"Larbert",
    "sg:classifiers":[
        {
            "category":"Food & Beverages",
            "subcategory":"Fruits & Vegetables",
            "type":"Retail Goods"
        }
    ],
    "sg:phone":"+44 1324 562282",
    "sg:postcode":"FK5 3JR",
    "sg:province":"Falkirk",
    "sg:tags":[
        "greengrocer"
    ],
    "wof:name":"J & E Heeps",
    "wof:placetype":"venue"
},
  "geometry": {"coordinates":[-3.814419,56.025742],"type":"Point"}
}