{
  "type": "Feature",
  "properties": {
    "addr:full":"12 The Waits, St Ives St Ives Cambridgeshire PE27 5BY",
    "addr:housenumber":"12",
    "addr:postcode":"pe27 5by",
    "addr:street":"The Waits St Ives",
    "iso:country":"GB",
    "sg:address":"12 The Waits, St Ives",
    "sg:city":"St Ives",
    "sg:classifiers":[
        {
            "category":"Food & Beverages",
            "subcategory":"Candy",
            "type":"Retail Goods"
        },
        {
            "category":"Food & Beverages",
            "subcategory":"Bakery",
            "type":"Retail Goods"
        }
    ],
    "sg:phone":"+44 1480 356125",
    "sg:postcode":"PE27 5BY",
    "sg:province":"Cambridgeshire",
    "sg:tags":[
        "confectioner",
        "baker"
    ],
    "wof:name":"Bowdens",
    "wof:placetype":"venue"
},
  "geometry": {"coordinates":[-0.078011997,52.3260650635],"type":"Point"}
}