{
  "type": "Feature",
  "properties": {
    "iso:country":"GB",
    "sg:address":"Roseacre, Alcester Rd",
    "sg:city":"Birmingham",
    "sg:classifiers":[
        {
            "category":"Building & Trades",
            "subcategory":"Construction",
            "type":"Services"
        }
    ],
    "sg:phone":"+44 1564 822528",
    "sg:postcode":"B48 7HX",
    "sg:province":"Worcestershire",
    "sg:tags":[
        "concrete"
    ],
    "wof:name":"Steel Fixing & Bending Co Ltd",
    "wof:placetype":"venue"
},
  "geometry": {"coordinates":[-1.887929,52.35788],"type":"Point"}
}