{
  "type": "Feature",
  "properties": {
    "addr:full":"9-9a Leachfield Industrial Estate, Green Lane West Preston Lancashire PR3 1PR",
    "addr:housenumber":"9-9a",
    "addr:postcode":"pr3 1pr",
    "addr:street":"Leachfield Industrial Estate Green Lane West",
    "iso:country":"GB",
    "sg:address":"9-9a Leachfield Industrial Estate, Green Lane West",
    "sg:city":"Preston",
    "sg:classifiers":[
        {
            "category":"Retail",
            "subcategory":"Auto Repair",
            "type":"Services"
        }
    ],
    "sg:phone":"+44 1995 605649",
    "sg:postcode":"PR3 1PR",
    "sg:province":"Lancashire",
    "sg:tags":[
        "modification",
        "garage",
        "related"
    ],
    "wof:name":"Garstang Motors",
    "wof:placetype":"venue"
},
  "geometry": {"coordinates":[-2.77958,53.909672],"type":"Point"}
}