{
  "type": "Feature",
  "properties": {
    "addr:full":"Lime Lane Walsall Staffordshire WS3 5AS",
    "addr:postcode":"ws3 5as",
    "addr:street":"Lime Lane",
    "iso:country":"GB",
    "sg:address":"Lime Lane",
    "sg:city":"Walsall",
    "sg:classifiers":[
        {
            "category":"Manufacturing",
            "subcategory":"Glass & Minerals",
            "type":"Manufacturing & Wholesale Goods"
        }
    ],
    "sg:phone":"+44 1543 452612",
    "sg:postcode":"WS3 5AS",
    "sg:province":"Staffordshire",
    "sg:tags":[
        "stained"
    ],
    "wof:name":"C G D Glazing Specialists",
    "wof:placetype":"venue"
},
  "geometry": {"coordinates":[-1.972943,52.657623],"type":"Point"}
}