{
  "type": "Feature",
  "properties": {
    "iso:country":"GB",
    "sg:address":"199-201 Byres Road",
    "sg:city":"Glasgow",
    "sg:classifiers":[
        {
            "category":"Shopping",
            "subcategory":"Pawn Shop",
            "type":"Retail Goods"
        }
    ],
    "sg:phone":"+44 141 357 6655",
    "sg:postcode":"G12 8TW",
    "sg:province":"Glasgow City",
    "sg:tags":[
        "pawnbroker"
    ],
    "wof:name":"Robert Biggar",
    "wof:placetype":"venue"
},
  "geometry": {"coordinates":[-4.295037,55.874458],"type":"Point"}
}