{
  "type": "Feature",
  "properties": {
    "iso:country":"GB",
    "sg:address":"Deepwater Dalskairth",
    "sg:city":"Dumfries",
    "sg:classifiers":[
        {
            "category":"Sports & Exercise",
            "subcategory":"Stables",
            "type":"Entertainment"
        }
    ],
    "sg:phone":"+44 1387 268311",
    "sg:postcode":"DG2 8ND",
    "sg:province":"Dumfries and Galloway",
    "sg:tags":[
        "equestrian",
        "centre",
        "livery",
        "schools",
        "riding",
        "education"
    ],
    "wof:name":"Deep Water Equitation Centre",
    "wof:placetype":"venue"
},
  "geometry": {"coordinates":[-3.66503,55.042049],"type":"Point"}
}