{
  "type": "Feature",
  "properties": {
    "iso:country":"GB",
    "sg:address":"Penllyn, Boverton",
    "sg:city":"Llantwit Major",
    "sg:classifiers":[
        {
            "category":"Professional",
            "subcategory":"Engineering",
            "type":"Services"
        },
        {
            "category":"Building & Trades",
            "subcategory":"Electrical",
            "type":"Services"
        }
    ],
    "sg:phone":"+44 1446 796823",
    "sg:postcode":"CF61 1UH",
    "sg:province":"The Vale of Glamorgan",
    "sg:tags":[
        "engineer",
        "electrician",
        "contractor"
    ],
    "wof:name":"C & D ELECTRICAL SERVICES",
    "wof:placetype":"venue"
},
  "geometry": {"coordinates":[-3.488492,51.41016],"type":"Point"}
}