{
  "type": "Feature",
  "properties": {
    "iso:country":"GB",
    "sg:address":"122 Main Street, Newtongrange",
    "sg:city":"Dalkeith",
    "sg:classifiers":[
        {
            "category":"Fast Food",
            "type":"Food & Drink"
        }
    ],
    "sg:phone":"+44 131 663 0547",
    "sg:postcode":"EH22 4PF",
    "sg:province":"City of Edinburgh",
    "sg:tags":[
        "away",
        "take"
    ],
    "wof:name":"Tak Po Chop Suey House",
    "wof:placetype":"venue"
},
  "geometry": {"coordinates":[-3.066367,55.865414],"type":"Point"}
}