{
  "type": "Feature",
  "properties": {
    "addr:full":"107 Commercial Street Newport Newport NP20 1LU",
    "addr:housenumber":"107",
    "addr:postcode":"np20 1lu",
    "addr:street":"Commercial Street",
    "iso:country":"GB",
    "sg:address":"107 Commercial Street",
    "sg:city":"Newport",
    "sg:classifiers":[
        {
            "category":"Shopping",
            "subcategory":"Musical Instruments",
            "type":"Retail Goods"
        },
        {
            "category":"Food & Beverages",
            "subcategory":"Groceries & Convenience Stores",
            "type":"Retail Goods"
        }
    ],
    "sg:phone":"+44 1633 263867",
    "sg:postcode":"NP20 1LU",
    "sg:province":"Newport",
    "sg:tags":[
        "music",
        "sheet"
    ],
    "wof:name":"Gamlin's Music Centre",
    "wof:placetype":"venue"
},
  "geometry": {"coordinates":[-2.993063,51.583256],"type":"Point"}
}