{
  "type": "Feature",
  "properties": {
    "addr:full":"Sales Lidgate Crescent, Langthwaite Grange Industrial Es Pontefract West Yorkshire WF9 3NR",
    "addr:postcode":"wf9 3nr",
    "addr:street":"Lidgate Crescent Langthwaite Grange Industrial;West",
    "iso:country":"GB",
    "sg:address":"Sales Lidgate Crescent, Langthwaite Grange Industrial Es",
    "sg:city":"Pontefract",
    "sg:classifiers":[
        {
            "category":"Coffee & Tea",
            "type":"Food & Drink"
        }
    ],
    "sg:phone":"+44 1977 649362",
    "sg:postcode":"WF9 3NR",
    "sg:province":"West Yorkshire",
    "wof:name":"Ringtons Tea & Coffee Merchants",
    "wof:placetype":"venue"
},
  "geometry": {"coordinates":[-1.30729,53.592834],"type":"Point"}
}