{
  "type": "Feature",
  "properties": {
    "addr:full":"53 George Street, Hunters Quay Dunoon Argyll and Bute PA23 8JX",
    "addr:housenumber":"53",
    "addr:postcode":"pa23 8jx",
    "addr:street":"George Street",
    "iso:country":"GB",
    "sg:address":"53 George Street, Hunters Quay",
    "sg:city":"Dunoon",
    "sg:classifiers":[
        {
            "category":"Social Services",
            "subcategory":"Retirement Home",
            "type":"Services"
        }
    ],
    "sg:phone":"+44 1369 702705",
    "sg:postcode":"PA23 8JX",
    "sg:province":"Argyll and Bute",
    "sg:tags":[
        "residential",
        "care"
    ],
    "wof:name":"Annfield Home",
    "wof:placetype":"venue"
},
  "geometry": {"coordinates":[-4.925388,55.951546],"type":"Point"}
}