{
  "type": "Feature",
  "properties": {
    "iso:country":"GB",
    "sg:address":"Moorfield Lane, Wombleton",
    "sg:city":"York",
    "sg:classifiers":[
        {
            "category":"Recreation",
            "subcategory":"Campground",
            "type":"Entertainment"
        }
    ],
    "sg:phone":"+44 1751 431684",
    "sg:postcode":"YO62 7RY",
    "sg:province":"North Yorkshire",
    "sg:tags":[
        "caravan",
        "park"
    ],
    "wof:name":"Wombleton Caravan Park",
    "wof:placetype":"venue"
},
  "geometry": {"coordinates":[-0.974659,54.247471],"type":"Point"}
}