{
  "type": "Feature",
  "properties": {
    "addr:full":"Serials Section, University Library Lancaster Lancashire LA1 4YW",
    "addr:postcode":"la1 4yw",
    "iso:country":"GB",
    "sg:address":"Serials Section, University Library",
    "sg:city":"Lancaster",
    "sg:classifiers":[
        {
            "category":"Education",
            "subcategory":"University",
            "type":"Public Place"
        }
    ],
    "sg:phone":"+44 1524 65201",
    "sg:postcode":"LA1 4YW",
    "sg:province":"Lancashire",
    "sg:tags":[
        "medical",
        "school"
    ],
    "wof:name":"The University of Lancaster",
    "wof:placetype":"venue"
},
  "geometry": {"coordinates":[-2.799029,54.044537],"type":"Point"}
}