{
  "type": "Feature",
  "properties": {
    "iso:country":"GB",
    "sg:address":"1 Market House, Market Place, Chalfont St Peter",
    "sg:city":"Gerrards Cross",
    "sg:classifiers":[
        {
            "category":"Real Estate",
            "subcategory":"Developer",
            "type":"Services"
        }
    ],
    "sg:phone":"+44 1753 886684",
    "sg:postcode":"SL9 9HA",
    "sg:province":"Buckinghamshire",
    "sg:tags":[
        "property"
    ],
    "wof:name":"Flohouse Ltd.",
    "wof:placetype":"venue"
},
  "geometry": {"coordinates":[-0.55993,51.60614],"type":"Point"}
}