{
  "type": "Feature",
  "properties": {
    "addr:full":"19 Esplanade Ryde Isle of Wight PO33 2EH",
    "addr:housenumber":"19",
    "addr:postcode":"po33 2eh",
    "addr:street":"Esplanade Ryde",
    "iso:country":"GB",
    "sg:address":"19 Esplanade",
    "sg:city":"Ryde",
    "sg:classifiers":[
        {
            "category":"Health Services",
            "subcategory":"Doctor",
            "type":"Services"
        }
    ],
    "sg:phone":"+44 1983 813600",
    "sg:postcode":"PO33 2EH",
    "sg:province":"Isle of Wight",
    "sg:tags":[
        "practitioners"
    ],
    "wof:name":"Burton, G",
    "wof:placetype":"venue"
},
  "geometry": {"coordinates":[-1.158776,50.732197],"type":"Point"}
}