{
  "type": "Feature",
  "properties": {
    "addr:full":"55a Andover Way Aldershot Hampshire GU11 3RJ",
    "addr:housenumber":"55a",
    "addr:postcode":"gu11 3rj",
    "addr:street":"Andover Way",
    "iso:country":"GB",
    "sg:address":"55a Andover Way",
    "sg:city":"Aldershot",
    "sg:classifiers":[
        {
            "category":"Health Services",
            "subcategory":"Health Practitioner",
            "type":"Services"
        }
    ],
    "sg:postcode":"GU11 3RJ",
    "sg:province":"Hampshire",
    "sg:tags":[
        "technique",
        "alexander"
    ],
    "wof:name":"J Bond",
    "wof:placetype":"venue"
},
  "geometry": {"coordinates":[-0.7565230131,51.2339744568],"type":"Point"}
}