{
  "type": "Feature",
  "properties": {
    "addr:full":"18 Deloraine Ct Hawick Cumbria TD9 7QE",
    "addr:housenumber":"18",
    "addr:postcode":"td9 7qe",
    "addr:street":"Deloraine Ct Hawick",
    "iso:country":"GB",
    "sg:address":"18 Deloraine Ct",
    "sg:city":"Hawick",
    "sg:classifiers":[
        {
            "category":"Organizations",
            "subcategory":"Religious Organization",
            "type":"Services"
        }
    ],
    "sg:phone":"+44 1450 373350",
    "sg:postcode":"TD9 7QE",
    "sg:province":"Cumbria",
    "sg:tags":[
        "organisation"
    ],
    "wof:name":"Jehovah's Witnesses",
    "wof:placetype":"venue"
},
  "geometry": {"coordinates":[-2.7928230762,55.4344558716],"type":"Point"}
}