{
  "type": "Feature",
  "properties": {
    "iso:country":"GB",
    "sg:address":"4 Maghull Business Centre, Liverpool Rd North",
    "sg:city":"Liverpool",
    "sg:classifiers":[
        {
            "category":"Fast Food",
            "type":"Food & Drink"
        }
    ],
    "sg:postcode":"L31 2HB",
    "sg:province":"Lancashire",
    "sg:tags":[
        "away",
        "take"
    ],
    "wof:name":"Feltdene Ltd",
    "wof:placetype":"venue"
},
  "geometry": {"coordinates":[-2.94491,53.51302],"type":"Point"}
}