{
  "type": "Feature",
  "properties": {
    "addr:full":"28 Beaumont Rd Windsor Berkshire SL4 1HY",
    "addr:housenumber":"28",
    "addr:postcode":"sl4 1hy",
    "addr:street":"Beaumont Rd",
    "iso:country":"GB",
    "sg:address":"28 Beaumont Rd",
    "sg:city":"Windsor",
    "sg:classifiers":[
        {
            "category":"Government",
            "subcategory":"Office",
            "type":"Public Place"
        }
    ],
    "sg:phone":"+44 1753 853238",
    "sg:postcode":"SL4 1HY",
    "sg:province":"Berkshire",
    "sg:tags":[
        "local"
    ],
    "wof:name":"Windsor Locality Teams",
    "wof:placetype":"venue"
},
  "geometry": {"coordinates":[-0.613439,51.476089],"type":"Point"}
}