{
  "type": "Feature",
  "properties": {
    "iso:country":"GB",
    "sg:address":"288 Barnsley Road, Cudworth",
    "sg:city":"Barnsley",
    "sg:classifiers":[
        {
            "category":"Home & Garden",
            "subcategory":"Home Furnishings",
            "type":"Retail Goods"
        },
        {
            "category":"Building & Trades",
            "subcategory":"Construction",
            "type":"Services"
        }
    ],
    "sg:phone":"+44 1226 780793",
    "sg:postcode":"S72 8SY",
    "sg:province":"South Yorkshire",
    "sg:tags":[
        "mantelpiece",
        "fireplace"
    ],
    "sg:website":"http://www.homestyleinteriors.net",
    "wof:name":"Home Style Interiors",
    "wof:placetype":"venue"
},
  "geometry": {"coordinates":[-1.415367,53.578362],"type":"Point"}
}