{
  "type": "Feature",
  "properties": {
    "iso:country":"GB",
    "sg:address":"47 Northstead Manor Drive",
    "sg:city":"Scarborough",
    "sg:classifiers":[
        {
            "category":"Travel",
            "subcategory":"Hotels & Motels",
            "type":"Entertainment"
        }
    ],
    "sg:phone":"+44 1723 375188",
    "sg:postcode":"YO12 6AF",
    "sg:province":"North Yorkshire",
    "wof:name":"Ryndle Court Hotel",
    "wof:placetype":"venue"
},
  "geometry": {"coordinates":[-0.4156689942,54.2902946472],"type":"Point"}
}