{
  "type": "Feature",
  "properties": {
    "iso:country":"GB",
    "sg:address":"339 Plungington Road, Fulwood",
    "sg:city":"Preston",
    "sg:classifiers":[
        {
            "category":"Retail",
            "subcategory":"Auto Rental",
            "type":"Services"
        }
    ],
    "sg:postcode":"PR2 3PS",
    "sg:province":"Lancashire",
    "sg:tags":[
        "car"
    ],
    "wof:name":"William & L Patten",
    "wof:placetype":"venue"
},
  "geometry": {"coordinates":[-2.715035,53.775974],"type":"Point"}
}