{
  "type": "Feature",
  "properties": {
    "addr:full":"141 Fenchurch Street London Greater London EC3M 6BQ",
    "addr:housenumber":"141",
    "addr:postcode":"ec3m 6bq",
    "addr:street":"Fenchurch Street",
    "iso:country":"GB",
    "sg:address":"141 Fenchurch Street",
    "sg:city":"London",
    "sg:classifiers":[
        {
            "category":"Professional",
            "subcategory":"Lawyer & Legal Services",
            "type":"Services"
        }
    ],
    "sg:postcode":"EC3M 6BQ",
    "sg:province":"Greater London",
    "wof:name":"Langheid Bach & Dallmayr",
    "wof:placetype":"venue"
},
  "geometry": {"coordinates":[-0.082494,51.511715],"type":"Point"}
}