{
  "type": "Feature",
  "properties": {
    "iso:country":"GB",
    "sg:address":"32 St. George St",
    "sg:city":"West End",
    "sg:classifiers":[
        {
            "category":"Museum",
            "subcategory":"Art Museum",
            "type":"Entertainment"
        }
    ],
    "sg:phone":"+44 20 7495 4284",
    "sg:postcode":"W1R 9FA",
    "sg:province":"Hampshire",
    "sg:tags":[
        "gallery"
    ],
    "wof:name":"Bruno Meissner Fine Arts Ltd",
    "wof:placetype":"venue"
},
  "geometry": {"coordinates":[-0.142914,51.512489],"type":"Point"}
}