{
  "type": "Feature",
  "properties": {
    "iso:country":"GB",
    "sg:address":"Building 3, British Gypsum Business Park, Leake Road",
    "sg:city":"Nottingham",
    "sg:classifiers":[
        {
            "category":"Professional",
            "subcategory":"Engineering",
            "type":"Services"
        }
    ],
    "sg:phone":"+44 115 983 0884",
    "sg:postcode":"NG11 0LB",
    "sg:province":"Nottinghamshire",
    "sg:tags":[
        "precision",
        "engineer"
    ],
    "wof:name":"Bridgford Pressings Ltd.",
    "wof:placetype":"venue"
},
  "geometry": {"coordinates":[-1.200429,52.858135],"type":"Point"}
}