{
  "type": "Feature",
  "properties": {
    "iso:country":"GB",
    "sg:address":"257-259 Freeman Street",
    "sg:city":"Grimsby",
    "sg:classifiers":[
        {
            "category":"Place Of Worship",
            "type":"Public Place"
        }
    ],
    "sg:phone":"+44 1472 240071",
    "sg:postcode":"DN32 9DW",
    "sg:province":"Lincolnshire",
    "wof:name":"Cleethorpes New Life Christian Fellowship",
    "wof:placetype":"venue"
},
  "geometry": {"coordinates":[-0.0743770003,53.5679168701],"type":"Point"}
}