{
  "type": "Feature",
  "properties": {
    "iso:country":"GB",
    "sg:address":"Hartlebury Garage, Worchester Road",
    "sg:city":"Kidderminster",
    "sg:classifiers":[
        {
            "category":"Autos & Motor Vehicles",
            "subcategory":"Automobile Sales",
            "type":"Retail Goods"
        }
    ],
    "sg:phone":"+44 1299 250025",
    "sg:postcode":"DY11 7XH",
    "sg:province":"Staffordshire",
    "sg:tags":[
        "car"
    ],
    "wof:name":"Mike Duncan",
    "wof:placetype":"venue"
},
  "geometry": {"coordinates":[-2.23169,52.328892],"type":"Point"}
}