{
  "type": "Feature",
  "properties": {
    "addr:full":"30 Marshall St Birmingham West Midlands B1 1LE",
    "addr:housenumber":"30",
    "addr:postcode":"b1 1le",
    "addr:street":"Marshall St",
    "iso:country":"GB",
    "sg:address":"30 Marshall St",
    "sg:city":"Birmingham",
    "sg:classifiers":[
        {
            "category":"Arts & Performance",
            "subcategory":"Art Gallery",
            "type":"Entertainment"
        }
    ],
    "sg:phone":"+44 121 643 4474",
    "sg:postcode":"B1 1LE",
    "sg:province":"West Midlands",
    "wof:name":"Washington Green Halcyon Group Ltd",
    "wof:placetype":"venue"
},
  "geometry": {"coordinates":[-1.9038959742,52.4736747742],"type":"Point"}
}