{
  "type": "Feature",
  "properties": {
    "iso:country":"GB",
    "sg:address":"Rear Of 33 Richmond Road",
    "sg:city":"Kingston-upon-thames",
    "sg:classifiers":[
        {
            "category":"Retail",
            "subcategory":"Auto Repair",
            "type":"Services"
        }
    ],
    "sg:phone":"+44 20 8549 7944",
    "sg:postcode":"KT2 5BW",
    "sg:province":"Greater London",
    "sg:tags":[
        "modification",
        "garage"
    ],
    "wof:name":"H A B Motors",
    "wof:placetype":"venue"
},
  "geometry": {"coordinates":[-0.2914740145,51.411026001],"type":"Point"}
}