{
  "type": "Feature",
  "properties": {
    "addr:full":"29 Mornington Road Woodford Green Essex IG8 0TN",
    "addr:housenumber":"29",
    "addr:postcode":"ig8 0tn",
    "addr:street":"Mornington Road",
    "iso:country":"GB",
    "sg:address":"29 Mornington Road",
    "sg:city":"Woodford Green",
    "sg:classifiers":[
        {
            "category":"Home & Garden",
            "subcategory":"Kitchen Supply",
            "type":"Retail Goods"
        }
    ],
    "sg:phone":"+44 20 8505 0038",
    "sg:postcode":"IG8 0TN",
    "sg:province":"Essex",
    "sg:tags":[
        "equipment",
        "catering"
    ],
    "wof:name":"Acme Catering & Bar Equipment Co",
    "wof:placetype":"venue"
},
  "geometry": {"coordinates":[0.020741,51.617157],"type":"Point"}
}