{
  "type": "Feature",
  "properties": {
    "addr:full":"Jet Service Stn, Bulford Camp Salisbury Hampshire SP4 9LZ",
    "addr:postcode":"sp4 9lz",
    "addr:street":"Bulford",
    "iso:country":"GB",
    "sg:address":"Jet Service Stn, Bulford Camp",
    "sg:city":"Salisbury",
    "sg:classifiers":[
        {
            "category":"Autos & Motor Vehicles",
            "subcategory":"Automobile Sales",
            "type":"Retail Goods"
        }
    ],
    "sg:postcode":"SP4 9LZ",
    "sg:province":"Hampshire",
    "sg:tags":[
        "car"
    ],
    "wof:name":"South West Trading",
    "wof:placetype":"venue"
},
  "geometry": {"coordinates":[-1.7610570192,51.1902160645],"type":"Point"}
}