{
  "type": "Feature",
  "properties": {
    "addr:full":"46 Charlotte Sq Edinburgh City of Edinburgh EH2 4HQ",
    "addr:housenumber":"46",
    "addr:postcode":"eh2 4hq",
    "addr:street":"Charlotte Sq",
    "iso:country":"GB",
    "sg:address":"46 Charlotte Sq",
    "sg:city":"Edinburgh",
    "sg:classifiers":[
        {
            "category":"Real Estate",
            "subcategory":"Surveying",
            "type":"Services"
        }
    ],
    "sg:postcode":"EH2 4HQ",
    "sg:province":"City of Edinburgh",
    "sg:tags":[
        "surveyor",
        "valuer"
    ],
    "wof:name":"Savills Plc",
    "wof:placetype":"venue"
},
  "geometry": {"coordinates":[-3.20697,55.952633],"type":"Point"}
}