{
  "type": "Feature",
  "properties": {
    "iso:country":"GB",
    "sg:address":"43 Ladygrove, Pixton Way",
    "sg:city":"Croydon",
    "sg:classifiers":[
        {
            "category":"Building & Trades",
            "subcategory":"Construction",
            "type":"Services"
        }
    ],
    "sg:phone":"+44 20 8651 0636",
    "sg:postcode":"CR0 9LS",
    "sg:province":"Surrey",
    "sg:tags":[
        "builder"
    ],
    "wof:name":"Updale Builders & Property Maintenance",
    "wof:placetype":"venue"
},
  "geometry": {"coordinates":[-0.0482360013,51.3465881348],"type":"Point"}
}