{
  "type": "Feature",
  "properties": {
    "addr:full":"Weston Park Shifnal Shropshire TF11 8NA",
    "addr:postcode":"tf11 8na",
    "addr:street":"Shropshire",
    "iso:country":"GB",
    "sg:address":"Weston Park",
    "sg:city":"Shifnal",
    "sg:classifiers":[
        {
            "category":"Landmark",
            "subcategory":"Tourist Attraction",
            "type":"Public Place"
        }
    ],
    "sg:phone":"+44 1952 850385",
    "sg:postcode":"TF11 8NA",
    "sg:province":"Shropshire",
    "sg:tags":[
        "interest"
    ],
    "wof:name":"Bradford Earl of",
    "wof:placetype":"venue"
},
  "geometry": {"coordinates":[-2.296266,52.693256],"type":"Point"}
}