{
  "type": "Feature",
  "properties": {
    "addr:full":"153-157 Heneage Road Grimsby Lincolnshire DN32 9JG",
    "addr:postcode":"153-157;dn32 9jg",
    "addr:street":"Heneage Road",
    "iso:country":"GB",
    "sg:address":"153-157 Heneage Road",
    "sg:city":"Grimsby",
    "sg:classifiers":[
        {
            "category":"Autos & Motor Vehicles",
            "subcategory":"Automobile Sales",
            "type":"Retail Goods"
        }
    ],
    "sg:phone":"+44 1472 240330",
    "sg:postcode":"DN32 9JG",
    "sg:province":"Lincolnshire",
    "sg:tags":[
        "car",
        "used"
    ],
    "wof:name":"Heneage Motor Co Ltd",
    "wof:placetype":"venue"
},
  "geometry": {"coordinates":[-0.074412,53.562195],"type":"Point"}
}