{
  "type": "Feature",
  "properties": {
    "iso:country":"GB",
    "sg:address":"76 Lawrence Road",
    "sg:city":"Liverpool",
    "sg:classifiers":[
        {
            "category":"Home & Garden",
            "subcategory":"Household Appliances",
            "type":"Retail Goods"
        },
        {
            "category":"Utilities",
            "subcategory":"Natural Gas",
            "type":"Services"
        }
    ],
    "sg:phone":"+44 151 734 1190",
    "sg:postcode":"L15 0EG",
    "sg:province":"Merseyside",
    "sg:tags":[
        "sale"
    ],
    "wof:name":"Gainsborough Cookers",
    "wof:placetype":"venue"
},
  "geometry": {"coordinates":[-2.934398,53.396881],"type":"Point"}
}