{
  "type": "Feature",
  "properties": {
    "addr:full":"5 Oxford Street, Exning Newmarket Cambridgeshire CB8 7EW",
    "addr:housenumber":"5",
    "addr:postcode":"cb8 7ew",
    "addr:street":"Oxford Street",
    "iso:country":"GB",
    "sg:address":"5 Oxford Street, Exning",
    "sg:city":"Newmarket",
    "sg:classifiers":[
        {
            "category":"Shopping",
            "subcategory":"Antiques",
            "type":"Retail Goods"
        }
    ],
    "sg:phone":"+44 1638 600073",
    "sg:postcode":"CB8 7EW",
    "sg:province":"Cambridgeshire",
    "wof:name":"Exning Antiques & Interiors",
    "wof:placetype":"venue"
},
  "geometry": {"coordinates":[0.3691630065,52.2655258179],"type":"Point"}
}