{
  "type": "Feature",
  "properties": {
    "addr:full":"Staffordshire House, Garner St Stoke On Trent Staffordshire ST4 7AS",
    "addr:postcode":"st4 7as",
    "addr:street":"Garner St",
    "iso:country":"GB",
    "sg:address":"Staffordshire House, Garner St",
    "sg:city":"Stoke On Trent",
    "sg:classifiers":[
        {
            "category":"Retail",
            "subcategory":"Storage",
            "type":"Services"
        }
    ],
    "sg:phone":"+44 1782 266652",
    "sg:postcode":"ST4 7AS",
    "sg:province":"Staffordshire",
    "sg:tags":[
        "household",
        "removal"
    ],
    "wof:name":"Midlans Storage Ltd",
    "wof:placetype":"venue"
},
  "geometry": {"coordinates":[-2.2007329464,53.0160560608],"type":"Point"}
}