{
  "type": "Feature",
  "properties": {
    "iso:country":"GB",
    "sg:address":"Salisbury House, London Wall",
    "sg:city":"London",
    "sg:classifiers":[
        {
            "category":"Professional",
            "subcategory":"Lawyer & Legal Services",
            "type":"Services"
        }
    ],
    "sg:phone":"+44 20 7628 7576",
    "sg:postcode":"EC2M 5QY",
    "sg:province":"Greater London",
    "sg:tags":[
        "solicitor"
    ],
    "wof:name":"Devonshires Ltd.",
    "wof:placetype":"venue"
},
  "geometry": {"coordinates":[-0.0884940028,51.5172958374],"type":"Point"}
}