{
  "type": "Feature",
  "properties": {
    "addr:full":"115 Sidwell St Exeter Devon EX4 6RY",
    "addr:housenumber":"115",
    "addr:postcode":"ex4 6ry",
    "addr:street":"Sidwell St",
    "iso:country":"GB",
    "sg:address":"115 Sidwell St",
    "sg:city":"Exeter",
    "sg:classifiers":[
        {
            "category":"Health Services",
            "subcategory":"Optometrist",
            "type":"Services"
        }
    ],
    "sg:phone":"+44 1392 255790",
    "sg:postcode":"EX4 6RY",
    "sg:province":"Devon",
    "sg:tags":[
        "optician"
    ],
    "wof:name":"Bacon & Evans",
    "wof:placetype":"venue"
},
  "geometry": {"coordinates":[-3.5218520164,50.7282028198],"type":"Point"}
}