{
  "type": "Feature",
  "properties": {
    "addr:full":"32 Lichfield Street Walsall West Midlands WS1 1TJ",
    "addr:housenumber":"32",
    "addr:postcode":"ws1 1tj",
    "addr:street":"Lichfield Street",
    "iso:country":"GB",
    "sg:address":"32 Lichfield Street",
    "sg:city":"Walsall",
    "sg:classifiers":[
        {
            "category":"Real Estate",
            "subcategory":"Real Estate Agent",
            "type":"Services"
        }
    ],
    "sg:postcode":"WS1 1TJ",
    "sg:province":"West Midlands",
    "wof:name":"Kempson Properties Limited",
    "wof:placetype":"venue"
},
  "geometry": {"coordinates":[-1.977196,52.587734],"type":"Point"}
}