{
  "type": "Feature",
  "properties": {
    "addr:full":"Millpond Street Ross-on-wye Gloucestershire HR9 7AP",
    "addr:postcode":"hr9 7ap",
    "addr:street":"Millpond Street",
    "iso:country":"GB",
    "sg:address":"Millpond Street",
    "sg:city":"Ross-on-wye",
    "sg:classifiers":[
        {
            "category":"Retail",
            "subcategory":"Auto Repair",
            "type":"Services"
        }
    ],
    "sg:postcode":"HR9 7AP",
    "sg:province":"Gloucestershire",
    "sg:tags":[
        "modification",
        "garage"
    ],
    "wof:name":"Bowens Garage",
    "wof:placetype":"venue"
},
  "geometry": {"coordinates":[-2.5804750919,51.9162559509],"type":"Point"}
}