{
  "type": "Feature",
  "properties": {
    "iso:country":"GB",
    "sg:address":"Unit 1, Newport Road, Holbrooks",
    "sg:city":"Coventry",
    "sg:classifiers":[
        {
            "category":"Building & Trades",
            "subcategory":"Construction",
            "type":"Services"
        }
    ],
    "sg:phone":"+44 24 7666 7511",
    "sg:postcode":"CV6 4BQ",
    "sg:province":"Warwickshire",
    "sg:tags":[
        "window",
        "sale"
    ],
    "wof:name":"S T P Windows Ltd.",
    "wof:placetype":"venue"
},
  "geometry": {"coordinates":[-1.5050740242,52.4374351501],"type":"Point"}
}