{
  "type": "Feature",
  "properties": {
    "addr:full":"123 Neasham Rd Darlington Durham DL1 4BE",
    "addr:housenumber":"123",
    "addr:postcode":"dl1 4be",
    "addr:street":"Neasham Rd",
    "iso:country":"GB",
    "sg:address":"123 Neasham Rd",
    "sg:city":"Darlington",
    "sg:classifiers":[
        {
            "category":"Recreation",
            "subcategory":"Fishing",
            "type":"Entertainment"
        }
    ],
    "sg:phone":"+44 1325 355156",
    "sg:postcode":"DL1 4BE",
    "sg:province":"Durham",
    "sg:tags":[
        "angling"
    ],
    "wof:name":"Eastbourne Fishing Tackle",
    "wof:placetype":"venue"
},
  "geometry": {"coordinates":[-1.542581,54.518929],"type":"Point"}
}