{
  "type": "Feature",
  "properties": {
    "iso:country":"GB",
    "sg:address":"70 Brookly Road",
    "sg:city":"Brockenhurst",
    "sg:classifiers":[
        {
            "category":"Farming",
            "subcategory":"Fish & Marine Products",
            "type":"Manufacturing & Wholesale Goods"
        }
    ],
    "sg:phone":"+44 1590 623391",
    "sg:postcode":"SO42 7RA",
    "sg:province":"Hampshire",
    "sg:tags":[
        "fishmonger"
    ],
    "wof:name":"New Forest Fishmongers",
    "wof:placetype":"venue"
},
  "geometry": {"coordinates":[-1.577801,50.819313],"type":"Point"}
}