{
  "type": "Feature",
  "properties": {
    "iso:country":"GB",
    "sg:address":"99-100 The Arches, Ravenscourt Place",
    "sg:city":"London",
    "sg:classifiers":[
        {
            "category":"Retail",
            "subcategory":"Auto Repair",
            "type":"Services"
        }
    ],
    "sg:phone":"+44 20 8741 0528",
    "sg:postcode":"W6 0UN",
    "sg:province":"Greater London",
    "sg:tags":[
        "modification",
        "garage"
    ],
    "wof:name":"Autostrada Engineering",
    "wof:placetype":"venue"
},
  "geometry": {"coordinates":[-0.23548,51.493999],"type":"Point"}
}