{
  "type": "Feature",
  "properties": {
    "addr:full":"25 Gatehill Gardens Luton Bedfordshire LU3 4EZ",
    "addr:housenumber":"25",
    "addr:postcode":"lu3 4ez",
    "addr:street":"Gatehill Gardens",
    "iso:country":"GB",
    "sg:address":"25 Gatehill Gardens",
    "sg:city":"Luton",
    "sg:classifiers":[
        {
            "category":"Building & Trades",
            "subcategory":"Construction",
            "type":"Services"
        }
    ],
    "sg:phone":"+44 1582 848712",
    "sg:postcode":"LU3 4EZ",
    "sg:province":"Bedfordshire",
    "sg:tags":[
        "dry",
        "lining",
        "screeders",
        "plasterers",
        "contractor"
    ],
    "wof:name":"S R C Contractors Ltd.",
    "wof:placetype":"venue"
},
  "geometry": {"coordinates":[-0.432956,51.926426],"type":"Point"}
}