{
  "type": "Feature",
  "properties": {
    "iso:country":"GB",
    "sg:address":"Morlaix, School Lane, Stourmouth",
    "sg:city":"Canterbury",
    "sg:classifiers":[
        {
            "category":"Food & Beverages",
            "subcategory":"Farmers Market",
            "type":"Retail Goods"
        },
        {
            "category":"Wholesale",
            "subcategory":"Fruits & Vegetables",
            "type":"Manufacturing & Wholesale Goods"
        }
    ],
    "sg:phone":"+44 1227 722275",
    "sg:postcode":"CT3 1JA",
    "sg:province":"Kent",
    "sg:tags":[
        "shop",
        "farm",
        "producers",
        "pyo"
    ],
    "wof:name":"Herons Gate Farm",
    "wof:placetype":"venue"
},
  "geometry": {"coordinates":[1.24775,51.316711],"type":"Point"}
}