{
  "type": "Feature",
  "properties": {
    "addr:full":"Unit 3 Triangle House, 2 Broomhill Road London Greater London SW18 4HX",
    "addr:housenumber":"unit 3;2",
    "addr:postcode":"sw18 4hx",
    "addr:street":"Triangle;Broomhill Road",
    "iso:country":"GB",
    "sg:address":"Unit 3 Triangle House, 2 Broomhill Road",
    "sg:city":"London",
    "sg:classifiers":[
        {
            "category":"Health Services",
            "subcategory":"Doctor",
            "type":"Services"
        }
    ],
    "sg:phone":"+44 20 8874 1700",
    "sg:postcode":"SW18 4HX",
    "sg:province":"Greater London",
    "sg:tags":[
        "practitioners"
    ],
    "wof:name":"Triangle Surgery",
    "wof:placetype":"venue"
},
  "geometry": {"coordinates":[-0.197877,51.45536],"type":"Point"}
}