{
  "type": "Feature",
  "properties": {
    "iso:country":"GB",
    "sg:address":"Tavistock St",
    "sg:city":"Milton Keynes",
    "sg:classifiers":[
        {
            "category":"Building & Trades",
            "subcategory":"Equipment Rental",
            "type":"Services"
        }
    ],
    "sg:phone":"+44 1908 374641",
    "sg:postcode":"MK2 2PH",
    "sg:province":"Buckinghamshire",
    "sg:tags":[
        "plant",
        "machinery"
    ],
    "wof:name":"Castlewyse",
    "wof:placetype":"venue"
},
  "geometry": {"coordinates":[-0.7235789895,51.9994773865],"type":"Point"}
}