{
  "type": "Feature",
  "properties": {
    "addr:full":"41-49 Bancroft Road, Eastern Industrial Estate, South Woodham Ferrers Chelmsford Essex CM3 5UQ",
    "addr:housenumber":"41-49",
    "addr:postcode":"cm3 5uq",
    "addr:street":"Bancroft Road;Estate;Woodham Ferrers",
    "iso:country":"GB",
    "sg:address":"41-49 Bancroft Road, Eastern Industrial Estate, South Woodham Ferrers",
    "sg:city":"Chelmsford",
    "sg:classifiers":[
        {
            "category":"Manufacturing",
            "subcategory":"Wood Products",
            "type":"Manufacturing & Wholesale Goods"
        }
    ],
    "sg:phone":"+44 1245 322400",
    "sg:postcode":"CM3 5UQ",
    "sg:province":"Essex",
    "sg:tags":[
        "packaging",
        "crate",
        "pallets"
    ],
    "wof:name":"Resource Packaging Ltd.",
    "wof:placetype":"venue"
},
  "geometry": {"coordinates":[0.6193249822,51.6507568359],"type":"Point"}
}