{
  "type": "Feature",
  "properties": {
    "iso:country":"GB",
    "sg:address":"34 Harburn Road",
    "sg:city":"West Calder",
    "sg:classifiers":[
        {
            "category":"Manufacturing",
            "subcategory":"Petroleum Products",
            "type":"Manufacturing & Wholesale Goods"
        },
        {
            "category":"Building & Trades",
            "subcategory":"Construction",
            "type":"Services"
        }
    ],
    "sg:phone":"+44 1506 871602",
    "sg:postcode":"EH55 8AH",
    "sg:province":"South Lanarkshire",
    "sg:tags":[
        "double",
        "glazier",
        "glazing"
    ],
    "wof:name":"ACE WINDOWS & DOORS",
    "wof:placetype":"venue"
},
  "geometry": {"coordinates":[-3.5679619312,55.8518791199],"type":"Point"}
}