{
  "type": "Feature",
  "properties": {
    "iso:country":"GB",
    "sg:address":"Lancots Lane",
    "sg:city":"St Helens",
    "sg:classifiers":[
        {
            "category":"Home & Garden",
            "subcategory":"Hardware",
            "type":"Retail Goods"
        }
    ],
    "sg:phone":"+44 1744 736295",
    "sg:postcode":"WA9 3EX",
    "sg:province":"Cheshire",
    "sg:tags":[
        "tarpaulin"
    ],
    "wof:name":"Bowen Tarpaulin Repairs",
    "wof:placetype":"venue"
},
  "geometry": {"coordinates":[-2.708291,53.440063],"type":"Point"}
}