{
  "type": "Feature",
  "properties": {
    "iso:country":"GB",
    "sg:address":"Jaques House, Fircroft Way",
    "sg:city":"Edenbridge",
    "sg:classifiers":[
        {
            "category":"Real Estate",
            "subcategory":"Surveying",
            "type":"Services"
        }
    ],
    "sg:postcode":"TN8 6EU",
    "sg:province":"East Sussex",
    "sg:tags":[
        "instrument"
    ],
    "wof:name":"J B Sales Ltd.",
    "wof:placetype":"venue"
},
  "geometry": {"coordinates":[0.064218,51.20673],"type":"Point"}
}