{
  "type": "Feature",
  "properties": {
    "iso:country":"GB",
    "sg:address":"Sales, Catfoot La",
    "sg:city":"Nottingham",
    "sg:classifiers":[
        {
            "category":"Home & Garden",
            "subcategory":"Hardware",
            "type":"Retail Goods"
        }
    ],
    "sg:phone":"+44 115 967 1211",
    "sg:postcode":"NG4 4QL",
    "sg:province":"Nottinghamshire",
    "sg:tags":[
        "lawnmowers",
        "machinery"
    ],
    "wof:name":"Mower CO",
    "wof:placetype":"venue"
},
  "geometry": {"coordinates":[-1.08362,53.006802],"type":"Point"}
}