{
  "type": "Feature",
  "properties": {
    "addr:full":"48 Hill Road, Costessey Norwich Norfolk NR5 0LZ",
    "addr:housenumber":"48",
    "addr:postcode":"nr5 0lz",
    "addr:street":"Hill Road;Norwich Norfolk",
    "iso:country":"GB",
    "sg:address":"48 Hill Road, Costessey",
    "sg:city":"Norwich",
    "sg:classifiers":[
        {
            "category":"Home & Garden",
            "subcategory":"Building Materials",
            "type":"Retail Goods"
        },
        {
            "category":"Building & Trades",
            "subcategory":"Construction",
            "type":"Services"
        }
    ],
    "sg:phone":"+44 1603 743407",
    "sg:postcode":"NR5 0LZ",
    "sg:province":"Norfolk",
    "sg:tags":[
        "insulation",
        "plastering",
        "related",
        "installers"
    ],
    "wof:name":"J Payne Insulations",
    "wof:placetype":"venue"
},
  "geometry": {"coordinates":[1.226743,52.65023],"type":"Point"}
}