{
  "type": "Feature",
  "properties": {
    "iso:country":"GB",
    "sg:address":"114 Drew Street",
    "sg:city":"Brixham",
    "sg:classifiers":[
        {
            "category":"Restaurant",
            "type":"Food & Drink"
        }
    ],
    "sg:phone":"+44 1803 857592",
    "sg:postcode":"TQ5 9JY",
    "sg:province":"Devon",
    "sg:tags":[
        "oriental"
    ],
    "wof:name":"Kam Boat Restaurant",
    "wof:placetype":"venue"
},
  "geometry": {"coordinates":[-3.520028,50.38586],"type":"Point"}
}