{
  "type": "Feature",
  "properties": {
    "iso:country":"GB",
    "sg:address":"Unit Buckinham Close",
    "sg:city":"Nuneaton",
    "sg:classifiers":[
        {
            "category":"Building & Trades",
            "subcategory":"Construction",
            "type":"Services"
        }
    ],
    "sg:phone":"+44 24 7635 3096",
    "sg:postcode":"CV10 7JT",
    "sg:province":"Leicestershire",
    "sg:tags":[
        "valve"
    ],
    "wof:name":"Erhard Valves Ltd.",
    "wof:placetype":"venue"
},
  "geometry": {"coordinates":[-1.473845005,52.5077400208],"type":"Point"}
}