{
  "type": "Feature",
  "properties": {
    "addr:full":"75 Squires Gate, Rogerstone Newport Caerphilly NP10 0BQ",
    "addr:housenumber":"75",
    "addr:postcode":"np10 0bq",
    "addr:street":"Squires Gate",
    "iso:country":"GB",
    "sg:address":"75 Squires Gate, Rogerstone",
    "sg:city":"Newport",
    "sg:classifiers":[
        {
            "category":"Manufacturing",
            "subcategory":"Petroleum Products",
            "type":"Manufacturing & Wholesale Goods"
        }
    ],
    "sg:phone":"+44 1633 892954",
    "sg:postcode":"NP10 0BQ",
    "sg:province":"Caerphilly",
    "sg:tags":[
        "double",
        "glazing"
    ],
    "wof:name":"John M Jones",
    "wof:placetype":"venue"
},
  "geometry": {"coordinates":[-3.048284,51.592369],"type":"Point"}
}