{
  "type": "Feature",
  "properties": {
    "iso:country":"GB",
    "sg:address":"307 Bedford Road, Kempston",
    "sg:city":"Bedford",
    "sg:classifiers":[
        {
            "category":"Place Of Worship",
            "type":"Public Place"
        }
    ],
    "sg:phone":"+44 1234 854125",
    "sg:postcode":"MK42 8QB",
    "sg:province":"Bedfordshire",
    "wof:name":"Our Lady of Ransom R C Church",
    "wof:placetype":"venue"
},
  "geometry": {"coordinates":[-0.496495,52.118069],"type":"Point"}
}