{
  "type": "Feature",
  "properties": {
    "addr:full":"5th Floor, Royex Ho, Aldermanbury Sq London Greater London EC2V 7HR",
    "addr:housenumber":"5th floor",
    "addr:postcode":"ec2v 7hr",
    "addr:street":"Royex Ho Aldermanbury Sq",
    "iso:country":"GB",
    "sg:address":"5th Floor, Royex Ho, Aldermanbury Sq",
    "sg:city":"London",
    "sg:classifiers":[
        {
            "category":"Banks & Credit Unions",
            "subcategory":"Financial Services",
            "type":"Services"
        }
    ],
    "sg:phone":"+44 20 7216 1777",
    "sg:postcode":"EC2V 7HR",
    "sg:province":"Greater London",
    "sg:tags":[
        "consultant"
    ],
    "wof:name":"Mesirow Financial (U K) Holdings Ltd",
    "wof:placetype":"venue"
},
  "geometry": {"coordinates":[-0.09329,51.517071],"type":"Point"}
}