{
  "type": "Feature",
  "properties": {
    "addr:full":"Priory Farm, Andwell Hook Berkshire RG27 9PA",
    "addr:postcode":"rg27 9pa",
    "iso:country":"GB",
    "sg:address":"Priory Farm, Andwell",
    "sg:city":"Hook",
    "sg:classifiers":[
        {
            "category":"Farming",
            "subcategory":"Farm",
            "type":"Manufacturing & Wholesale Goods"
        }
    ],
    "sg:phone":"+44 1256 760199",
    "sg:postcode":"RG27 9PA",
    "sg:province":"Berkshire",
    "sg:tags":[
        "agricultural"
    ],
    "wof:name":"Permplant",
    "wof:placetype":"venue"
},
  "geometry": {"coordinates":[-0.9657189846,51.2813606262],"type":"Point"}
}