{
  "type": "Feature",
  "properties": {
    "addr:full":"15 Leigham Court Drive Leigh-on-sea Essex SS9 1PS",
    "addr:housenumber":"15",
    "addr:postcode":"ss9 1ps",
    "addr:street":"Leigham Court Drive Leigh-On-Sea",
    "iso:country":"GB",
    "sg:address":"15 Leigham Court Drive",
    "sg:city":"Leigh-on-sea",
    "sg:classifiers":[
        {
            "category":"Health Services",
            "subcategory":"Health Practitioner",
            "type":"Services"
        }
    ],
    "sg:postcode":"SS9 1PS",
    "sg:province":"Essex",
    "sg:tags":[
        "therapist",
        "speech"
    ],
    "wof:name":"Communication & Theatre Studies",
    "wof:placetype":"venue"
},
  "geometry": {"coordinates":[0.6610710025,51.5444297791],"type":"Point"}
}