{
  "type": "Feature",
  "properties": {
    "addr:full":"24 Deneside Cres Stockport Cheshire SK7 4NU",
    "addr:housenumber":"24",
    "addr:postcode":"sk7 4nu",
    "addr:street":"Deneside Cres",
    "iso:country":"GB",
    "sg:address":"24 Deneside Cres",
    "sg:city":"Stockport",
    "sg:classifiers":[
        {
            "category":"Building & Trades",
            "subcategory":"Construction",
            "type":"Services"
        }
    ],
    "sg:phone":"+44 161 487 3303",
    "sg:postcode":"SK7 4NU",
    "sg:province":"Cheshire",
    "sg:tags":[
        "contractor",
        "paving",
        "driveway"
    ],
    "wof:name":"Drivewise",
    "wof:placetype":"venue"
},
  "geometry": {"coordinates":[-2.1107850075,53.3822517395],"type":"Point"}
}