{
  "type": "Feature",
  "properties": {
    "addr:full":"4 Old Hall La Stockport Cheshire SK7 1RN",
    "addr:housenumber":"4",
    "addr:postcode":"sk7 1rn",
    "addr:street":"Old Hall La Stockport",
    "iso:country":"GB",
    "sg:address":"4 Old Hall La",
    "sg:city":"Stockport",
    "sg:classifiers":[
        {
            "category":"Organizations",
            "subcategory":"Community Association",
            "type":"Services"
        }
    ],
    "sg:phone":"+44 161 439 9067",
    "sg:postcode":"SK7 1RN",
    "sg:province":"Cheshire",
    "sg:tags":[
        "relation",
        "public"
    ],
    "wof:name":"Paradime",
    "wof:placetype":"venue"
},
  "geometry": {"coordinates":[-2.1603939533,53.3309364319],"type":"Point"}
}