{
  "type": "Feature",
  "properties": {
    "addr:full":"29 Glen Road Wadebridge Cornwall PL27 7PE",
    "addr:housenumber":"29",
    "addr:postcode":"pl27 7pe",
    "addr:street":"Glen Road",
    "iso:country":"GB",
    "sg:address":"29 Glen Road",
    "sg:city":"Wadebridge",
    "sg:classifiers":[
        {
            "category":"Real Estate",
            "subcategory":"Surveying",
            "type":"Services"
        }
    ],
    "sg:phone":"+44 1208 816404",
    "sg:postcode":"PL27 7PE",
    "sg:province":"Cornwall",
    "sg:tags":[
        "surveyor",
        "valuer"
    ],
    "wof:name":"Property & Construction Consultants Ltd.",
    "wof:placetype":"venue"
},
  "geometry": {"coordinates":[-4.8381958008,50.5129966736],"type":"Point"}
}