{
  "type": "Feature",
  "properties": {
    "iso:country":"GB",
    "sg:address":"108 Corporation Street",
    "sg:city":"Birmingham",
    "sg:classifiers":[
        {
            "category":"Shopping",
            "subcategory":"Clothing, Apparel, & Fashions",
            "type":"Retail Goods"
        }
    ],
    "sg:phone":"+44 870 060 0200",
    "sg:postcode":"B4 6SX",
    "sg:province":"West Midlands",
    "sg:tags":[
        "supplier",
        "workwear",
        "protective",
        "uniform"
    ],
    "wof:name":"Alexandra plc",
    "wof:placetype":"venue"
},
  "geometry": {"coordinates":[-1.8947819471,52.4815940857],"type":"Point"}
}