{
  "type": "Feature",
  "properties": {
    "iso:country":"GB",
    "sg:address":"11 & 15 Harlequins, Paul Street",
    "sg:city":"Exeter",
    "sg:classifiers":[
        {
            "category":"Shopping",
            "subcategory":"Clothing, Apparel, & Fashions",
            "type":"Retail Goods"
        }
    ],
    "sg:phone":"+44 1392 274840",
    "sg:postcode":"EX4 3TT",
    "sg:province":"Devon",
    "sg:tags":[
        "menswear",
        "ladieswear"
    ],
    "wof:name":"Dukes Fine Clothes Ltd.",
    "wof:placetype":"venue"
},
  "geometry": {"coordinates":[-3.53336,50.72438],"type":"Point"}
}