{
  "type": "Feature",
  "properties": {
    "addr:full":"7 Plato Road London Greater London SW2 5UP",
    "addr:housenumber":"7",
    "addr:postcode":"sw2 5up",
    "addr:street":"Plato Road",
    "iso:country":"GB",
    "sg:address":"7 Plato Road",
    "sg:city":"London",
    "sg:classifiers":[
        {
            "category":"Professional",
            "type":"Services"
        }
    ],
    "sg:postcode":"SW2 5UP",
    "sg:province":"Greater London",
    "sg:tags":[
        "writer"
    ],
    "wof:name":"Lexis Technical Writing Ltd.",
    "wof:placetype":"venue"
},
  "geometry": {"coordinates":[-0.1259759963,51.4600257874],"type":"Point"}
}