{
  "type": "Feature",
  "properties": {
    "addr:full":"56 Blenheim Crescent Notting Hill Greater London W11 1NY",
    "addr:housenumber":"56",
    "addr:postcode":"w11 1ny",
    "addr:street":"Blenheim Crescent",
    "iso:country":"GB",
    "sg:address":"56 Blenheim Crescent",
    "sg:city":"Notting Hill",
    "sg:classifiers":[
        {
            "category":"Professional",
            "subcategory":"Accounting & Tax Preparation",
            "type":"Services"
        }
    ],
    "sg:phone":"+44 20 7912 0656",
    "sg:postcode":"W11 1NY",
    "sg:province":"Greater London",
    "sg:tags":[
        "accountant",
        "activity"
    ],
    "wof:name":"Tuffrey Jones & Banks",
    "wof:placetype":"venue"
},
  "geometry": {"coordinates":[-0.209852,51.514706],"type":"Point"}
}