{
  "type": "Feature",
  "properties": {
    "iso:country":"GB",
    "sg:address":"54 Jermyn Street",
    "sg:city":"London",
    "sg:classifiers":[
        {
            "category":"Professional",
            "subcategory":"Employment Agencies",
            "type":"Services"
        }
    ],
    "sg:phone":"+44 20 7529 1750",
    "sg:postcode":"SW1Y 6LX",
    "sg:province":"Greater London",
    "sg:tags":[
        "consultant"
    ],
    "wof:name":"Norman Broadbent International Ltd.",
    "wof:placetype":"venue"
},
  "geometry": {"coordinates":[-0.139129,51.507645],"type":"Point"}
}