{
  "type": "Feature",
  "properties": {
    "iso:country":"GB",
    "sg:address":"Larkfield Trading Estate, New Hythe Lane, Larkfield",
    "sg:city":"Aylesford",
    "sg:classifiers":[
        {
            "category":"Utilities",
            "subcategory":"Refuse",
            "type":"Services"
        }
    ],
    "sg:phone":"+44 1622 792000",
    "sg:postcode":"ME20 6GN",
    "sg:province":"Kent",
    "sg:tags":[
        "disposal",
        "waste"
    ],
    "wof:name":"Serviceteam Ltd.",
    "wof:placetype":"venue"
},
  "geometry": {"coordinates":[0.4420050085,51.3011512756],"type":"Point"}
}