{
  "type": "Feature",
  "properties": {
    "addr:full":"Unit 40, The Arms Wickford Essex SS12 9EP",
    "addr:housenumber":"unit 40",
    "addr:postcode":"ss12 9ep",
    "addr:street":"The",
    "iso:country":"GB",
    "sg:address":"Unit 40, The Arms",
    "sg:city":"Wickford",
    "sg:classifiers":[
        {
            "category":"Building & Trades",
            "subcategory":"Construction",
            "type":"Services"
        }
    ],
    "sg:phone":"+44 1268 768888",
    "sg:postcode":"SS12 9EP",
    "sg:province":"Essex",
    "sg:tags":[
        "platform",
        "work",
        "scaffolding"
    ],
    "wof:name":"South East (Scaffolding) Ltd.",
    "wof:placetype":"venue"
},
  "geometry": {"coordinates":[0.527632,51.595467],"type":"Point"}
}