{
  "type": "Feature",
  "properties": {
    "iso:country":"GB",
    "sg:address":"Wyndley Lane",
    "sg:city":"Sutton Coldfield",
    "sg:classifiers":[
        {
            "category":"Organizations",
            "subcategory":"Non-profit Organization",
            "type":"Services"
        }
    ],
    "sg:phone":"+44 121 354 5369",
    "sg:postcode":"B73 6ES",
    "sg:province":"West Midlands",
    "sg:tags":[
        "charitable",
        "organisation",
        "voluntary",
        "charity"
    ],
    "wof:name":"DISABILITY SPORT ENGLAND",
    "wof:placetype":"venue"
},
  "geometry": {"coordinates":[-1.8321449757,52.559677124],"type":"Point"}
}