{
  "type": "Feature",
  "properties": {
    "addr:full":"98 Mill Street Kidderminster Staffordshire DY11 6XG",
    "addr:housenumber":"98",
    "addr:postcode":"dy11 6xg",
    "addr:street":"Mill Street",
    "iso:country":"GB",
    "sg:address":"98 Mill Street",
    "sg:city":"Kidderminster",
    "sg:classifiers":[
        {
            "category":"Sports & Exercise",
            "subcategory":"Gym",
            "type":"Entertainment"
        }
    ],
    "sg:phone":"+44 1562 865225",
    "sg:postcode":"DY11 6XG",
    "sg:province":"Staffordshire",
    "sg:tags":[
        "club",
        "fitness",
        "health",
        "centre"
    ],
    "wof:name":"Unique Fitness",
    "wof:placetype":"venue"
},
  "geometry": {"coordinates":[-2.253858,52.389221],"type":"Point"}
}