{
  "type": "Feature",
  "properties": {
    "iso:country":"GB",
    "sg:address":"Hotspur Avenue",
    "sg:city":"Whitley Bay",
    "sg:classifiers":[
        {
            "category":"Retail",
            "subcategory":"Auto Repair",
            "type":"Services"
        }
    ],
    "sg:phone":"+44 191 252 6518",
    "sg:postcode":"NE25 8RP",
    "sg:province":"Northumberland",
    "sg:tags":[
        "modification",
        "garage"
    ],
    "wof:name":"Hillheads Motor Engineers",
    "wof:placetype":"venue"
},
  "geometry": {"coordinates":[-1.45134902,55.0374183655],"type":"Point"}
}