{
  "type": "Feature",
  "properties": {
    "addr:full":"29 Stroud Green Road London Greater London N4 3EF",
    "addr:housenumber":"29",
    "addr:postcode":"n4 3ef",
    "addr:street":"Stroud Green Road",
    "iso:country":"GB",
    "sg:address":"29 Stroud Green Road",
    "sg:city":"London",
    "sg:classifiers":[
        {
            "category":"Food & Beverages",
            "subcategory":"Meat & Fish",
            "type":"Retail Goods"
        }
    ],
    "sg:phone":"+44 20 7263 6625",
    "sg:postcode":"N4 3EF",
    "sg:province":"Greater London",
    "sg:tags":[
        "butcher"
    ],
    "wof:name":"K M Butchers",
    "wof:placetype":"venue"
},
  "geometry": {"coordinates":[-0.108896,51.567371],"type":"Point"}
}