{
  "type": "Feature",
  "properties": {
    "addr:full":"12 Moseley Street Manchester Greater Manchester M2 3AU",
    "addr:housenumber":"12",
    "addr:postcode":"m2 3au",
    "addr:street":"Moseley Street",
    "iso:country":"GB",
    "sg:address":"12 Moseley Street",
    "sg:city":"Manchester",
    "sg:classifiers":[
        {
            "category":"Banks & Credit Unions",
            "subcategory":"Bank",
            "type":"Services"
        }
    ],
    "sg:phone":"+44 117 943 3433",
    "sg:postcode":"M2 3AU",
    "sg:province":"Greater Manchester",
    "wof:name":"Tsb Bank Ltd.",
    "wof:placetype":"venue"
},
  "geometry": {"coordinates":[-2.239244,53.480827],"type":"Point"}
}