{
  "type": "Feature",
  "properties": {
    "addr:full":"12 Lower Ashley Road New Milton Hampshire BH25 5AD",
    "addr:housenumber":"12",
    "addr:postcode":"bh25 5ad",
    "addr:street":"Lower Ashley Road",
    "iso:country":"GB",
    "sg:address":"12 Lower Ashley Road",
    "sg:city":"New Milton",
    "sg:classifiers":[
        {
            "category":"Building & Trades",
            "subcategory":"Construction",
            "type":"Services"
        }
    ],
    "sg:postcode":"BH25 5AD",
    "sg:province":"Hampshire",
    "sg:tags":[
        "roofing"
    ],
    "wof:name":"Saunders & Herridge",
    "wof:placetype":"venue"
},
  "geometry": {"coordinates":[-1.6716519594,50.7576179504],"type":"Point"}
}