{
  "type": "Feature",
  "properties": {
    "addr:full":"6 Sunnyside, Kilmaurs Kilmarnock East Ayrshire KA3 2RZ",
    "addr:housenumber":"6;kilmaurs",
    "addr:postcode":"ka3 2rz",
    "addr:street":"Sunnyside;East",
    "iso:country":"GB",
    "sg:address":"6 Sunnyside, Kilmaurs",
    "sg:city":"Kilmarnock",
    "sg:classifiers":[
        {
            "category":"Freight",
            "type":"Transportation"
        }
    ],
    "sg:phone":"+44 1563 538666",
    "sg:postcode":"KA3 2RZ",
    "sg:province":"East Ayrshire",
    "sg:tags":[
        "haulage",
        "transport",
        "road"
    ],
    "wof:name":"Kirk Haulage",
    "wof:placetype":"venue"
},
  "geometry": {"coordinates":[-4.522619,55.6395],"type":"Point"}
}