{
  "type": "Feature",
  "properties": {
    "addr:full":"12-16 Lonsdale Pl London Greater London N1 1EL",
    "addr:housenumber":"12-16",
    "addr:postcode":"n1 1el",
    "addr:street":"Lonsdale Pl",
    "iso:country":"GB",
    "sg:address":"12-16 Lonsdale Pl",
    "sg:city":"London",
    "sg:classifiers":[
        {
            "category":"Manufacturing",
            "subcategory":"Wood Products",
            "type":"Manufacturing & Wholesale Goods"
        }
    ],
    "sg:phone":"+44 20 7607 4196",
    "sg:postcode":"N1 1EL",
    "sg:province":"Greater London",
    "sg:tags":[
        "stone"
    ],
    "wof:name":"Shaw,F E,",
    "wof:placetype":"venue"
},
  "geometry": {"coordinates":[-0.1075790003,51.5396766663],"type":"Point"}
}