{
  "type": "Feature",
  "properties": {
    "iso:country":"GB",
    "sg:address":"Starcombe House, Sidbury",
    "sg:city":"Sidmouth",
    "sg:classifiers":[
        {
            "category":"Travel",
            "subcategory":"Hotels & Motels",
            "type":"Entertainment"
        }
    ],
    "sg:postcode":"EX10 0QN",
    "sg:province":"Devon",
    "sg:tags":[
        "self",
        "catering"
    ],
    "wof:name":"Susan Paradise French Holidays",
    "wof:placetype":"venue"
},
  "geometry": {"coordinates":[-3.2204639912,50.7191505432],"type":"Point"}
}