{
  "type": "Feature",
  "properties": {
    "iso:country":"GB",
    "sg:address":"1 Grape Lane, Pocklington",
    "sg:city":"York",
    "sg:classifiers":[
        {
            "category":"Personal",
            "subcategory":"Beauty Salon",
            "type":"Services"
        }
    ],
    "sg:phone":"+44 1759 306965",
    "sg:postcode":"YO42 2RA",
    "sg:province":"East Riding of Yorkshire",
    "sg:tags":[
        "unisex",
        "hairdresser"
    ],
    "wof:name":"The Hair Studio",
    "wof:placetype":"venue"
},
  "geometry": {"coordinates":[-0.780675,53.930466],"type":"Point"}
}