{
  "type": "Feature",
  "properties": {
    "iso:country":"GB",
    "sg:address":"90 Swakeleys Road, Ickenham",
    "sg:city":"Uxbridge",
    "sg:classifiers":[
        {
            "category":"Retail",
            "subcategory":"Veterinary Services",
            "type":"Services"
        }
    ],
    "sg:phone":"+44 1895 673993",
    "sg:postcode":"UB10 8BB",
    "sg:province":"Greater London",
    "sg:tags":[
        "surgeon"
    ],
    "wof:name":"Greenwood Veterinary Clinic",
    "wof:placetype":"venue"
},
  "geometry": {"coordinates":[-0.4534130096,51.5652809143],"type":"Point"}
}