{
  "type": "Feature",
  "properties": {
    "iso:country":"GB",
    "sg:address":"27a Swan Street, Longtown",
    "sg:city":"Carlisle",
    "sg:classifiers":[
        {
            "category":"Professional",
            "subcategory":"Printing & Photocopies",
            "type":"Services"
        }
    ],
    "sg:phone":"+44 1228 791492",
    "sg:postcode":"CA6 5UZ",
    "sg:province":"Cumbria",
    "sg:tags":[
        "printer"
    ],
    "wof:name":"Murrays Printers",
    "wof:placetype":"venue"
},
  "geometry": {"coordinates":[-2.970341,55.009266],"type":"Point"}
}