{
  "type": "Feature",
  "properties": {
    "addr:full":"Unit 46-48 Surrey Quays Ctre, Redriff Road London Greater London SE16 7LL",
    "addr:housenumber":"unit 46-48",
    "addr:postcode":"se16 7ll",
    "addr:street":"Quays;Redriff Road",
    "iso:country":"GB",
    "sg:address":"Unit 46-48 Surrey Quays Ctre, Redriff Road",
    "sg:city":"London",
    "sg:classifiers":[
        {
            "category":"Shopping",
            "subcategory":"Baby Store",
            "type":"Retail Goods"
        }
    ],
    "sg:phone":"+44 20 7237 2025",
    "sg:postcode":"SE16 7LL",
    "sg:province":"Greater London",
    "sg:tags":[
        "nursery",
        "accessory"
    ],
    "wof:name":"Mothercare (U K) Ltd.",
    "wof:placetype":"venue"
},
  "geometry": {"coordinates":[-0.045819,51.497787],"type":"Point"}
}