{
  "type": "Feature",
  "properties": {
    "addr:full":"Rr Stores Shrewsbury Shropshire SY5 8LA",
    "addr:postcode":"sy5 8la",
    "addr:street":"Shrewsbury",
    "iso:country":"GB",
    "sg:address":"Rr Stores",
    "sg:city":"Shrewsbury",
    "sg:classifiers":[
        {
            "category":"Food & Beverages",
            "subcategory":"Groceries & Convenience Stores",
            "type":"Retail Goods"
        }
    ],
    "sg:phone":"+44 1743 860454",
    "sg:postcode":"SY5 8LA",
    "sg:province":"Shropshire",
    "wof:name":"S Raj",
    "wof:placetype":"venue"
},
  "geometry": {"coordinates":[-2.813799,52.66428],"type":"Point"}
}