{
  "type": "Feature",
  "properties": {
    "iso:country":"GB",
    "sg:address":"70 St Martins Lane",
    "sg:city":"London",
    "sg:classifiers":[
        {
            "category":"Restaurant",
            "type":"Food & Drink"
        }
    ],
    "sg:phone":"+44 20 7836 0484",
    "sg:postcode":"WC2N 4JS",
    "sg:province":"Greater London",
    "sg:tags":[
        "italian"
    ],
    "wof:name":"Bella Pasta",
    "wof:placetype":"venue"
},
  "geometry": {"coordinates":[-0.12701,51.51136],"type":"Point"}
}