{
  "type": "Feature",
  "properties": {
    "addr:full":"59 Northampton Road, Broughton Kettering Northamptonshire NN14 1NR",
    "addr:housenumber":"59",
    "addr:postcode":"nn14 1nr",
    "addr:street":"Northampton Road",
    "iso:country":"GB",
    "sg:address":"59 Northampton Road, Broughton",
    "sg:city":"Kettering",
    "sg:classifiers":[
        {
            "category":"Professional",
            "subcategory":"Engineering",
            "type":"Services"
        }
    ],
    "sg:phone":"+44 1536 790588",
    "sg:postcode":"NN14 1NR",
    "sg:province":"Northamptonshire",
    "sg:tags":[
        "contractor",
        "electrical",
        "engineer"
    ],
    "wof:name":"Roy Sharp Electrical Services",
    "wof:placetype":"venue"
},
  "geometry": {"coordinates":[-0.778441,52.370281],"type":"Point"}
}