{
  "type": "Feature",
  "properties": {
    "addr:full":"19 Union St Larkhall South Lanarkshire ML9 1DY",
    "addr:housenumber":"19",
    "addr:postcode":"ml9 1dy",
    "addr:street":"Union St",
    "iso:country":"GB",
    "sg:address":"19 Union St",
    "sg:city":"Larkhall",
    "sg:classifiers":[
        {
            "category":"Shopping",
            "subcategory":"Crafts & Fabrics",
            "type":"Retail Goods"
        }
    ],
    "sg:postcode":"ML9 1DY",
    "sg:province":"South Lanarkshire",
    "sg:tags":[
        "shop"
    ],
    "wof:name":"Russell,A,",
    "wof:placetype":"venue"
},
  "geometry": {"coordinates":[-3.9746499062,55.7411384583],"type":"Point"}
}