{
  "type": "Feature",
  "properties": {
    "iso:country":"GB",
    "sg:address":"19 Union St",
    "sg:city":"Larkhall",
    "sg:classifiers":[
        {
            "category":"Shopping",
            "subcategory":"Crafts & Fabrics",
            "type":"Retail Goods"
        }
    ],
    "sg:postcode":"ML9 1DY",
    "sg:province":"South Lanarkshire",
    "sg:tags":[
        "shop"
    ],
    "wof:name":"Russell,A,",
    "wof:placetype":"venue"
},
  "geometry": {"coordinates":[-3.9746499062,55.7411384583],"type":"Point"}
}