{
  "type": "Feature",
  "properties": {
    "iso:country":"GB",
    "sg:address":"Thames Ho, Middlegreen Trading Est, Middlegreen",
    "sg:city":"Slough",
    "sg:classifiers":[
        {
            "category":"Health Services",
            "subcategory":"Dentist",
            "type":"Services"
        }
    ],
    "sg:phone":"+44 1753 553591",
    "sg:postcode":"SL3 6DF",
    "sg:province":"Berkshire",
    "sg:tags":[
        "technician",
        "dental"
    ],
    "wof:name":"Denture World",
    "wof:placetype":"venue"
},
  "geometry": {"coordinates":[-0.5572959781,51.5139427185],"type":"Point"}
}