{
  "type": "Feature",
  "properties": {
    "addr:full":"962 Crow Road North Glasgow Glasgow City G13 1JF",
    "addr:housenumber":"962",
    "addr:postcode":"g13 1jf",
    "addr:street":"Crow Road North",
    "iso:country":"GB",
    "sg:address":"962 Crow Road North",
    "sg:city":"Glasgow",
    "sg:classifiers":[
        {
            "category":"Autos & Motor Vehicles",
            "subcategory":"Fuel & Gas Station",
            "type":"Retail Goods"
        }
    ],
    "sg:phone":"+44 141 402 9161",
    "sg:postcode":"G13 1JF",
    "sg:province":"Glasgow City",
    "sg:tags":[
        "petrol",
        "filling"
    ],
    "wof:name":"Autogas Services",
    "wof:placetype":"venue"
},
  "geometry": {"coordinates":[-4.3224401474,55.8930969238],"type":"Point"}
}