{
  "type": "Feature",
  "properties": {
    "addr:full":"Unit 5 Trinity Industrial Estate, Millbrook Road West Southampton Hampshire SO15 0LA",
    "addr:housenumber":"unit 5;estate",
    "addr:postcode":"so15 0la",
    "addr:street":"Trinity Industrial;Millbrook Road West",
    "iso:country":"GB",
    "sg:address":"Unit 5 Trinity Industrial Estate, Millbrook Road West",
    "sg:city":"Southampton",
    "sg:classifiers":[
        {
            "category":"Autos & Motor Vehicles",
            "subcategory":"Auto Supplies",
            "type":"Retail Goods"
        },
        {
            "category":"Retail",
            "subcategory":"Auto Repair",
            "type":"Services"
        }
    ],
    "sg:phone":"+44 23 8078 3855",
    "sg:postcode":"SO15 0LA",
    "sg:province":"Hampshire",
    "sg:tags":[
        "modification",
        "car",
        "part",
        "garage",
        "accessory"
    ],
    "wof:name":"Euro Car Parts Ltd",
    "wof:placetype":"venue"
},
  "geometry": {"coordinates":[-1.407319,50.909939],"type":"Point"}
}