{
  "type": "Feature",
  "properties": {
    "iso:country":"GB",
    "sg:address":"57 Avondale Close",
    "sg:city":"Horley",
    "sg:classifiers":[
        {
            "category":"Professional",
            "subcategory":"Management & Consulting",
            "type":"Services"
        },
        {
            "category":"Wholesale",
            "subcategory":"Computers",
            "type":"Manufacturing & Wholesale Goods"
        }
    ],
    "sg:phone":"+44 1293 822362",
    "sg:postcode":"RH6 8BN",
    "sg:province":"Surrey",
    "sg:tags":[
        "supplier",
        "consultant",
        "consumables",
        "business"
    ],
    "wof:name":"Synopsys Consulting Ltd.",
    "wof:placetype":"venue"
},
  "geometry": {"coordinates":[-0.169256,51.183983],"type":"Point"}
}