{
  "type": "Feature",
  "properties": {
    "addr:full":"12 The Avenue Eastbourne East Sussex BN21 3YA",
    "addr:housenumber":"12",
    "addr:postcode":"bn21 3ya",
    "addr:street":"The Avenue",
    "iso:country":"GB",
    "sg:address":"12 The Avenue",
    "sg:city":"Eastbourne",
    "sg:classifiers":[
        {
            "category":"Farming",
            "subcategory":"Nursery",
            "type":"Manufacturing & Wholesale Goods"
        }
    ],
    "sg:phone":"+44 1323 647630",
    "sg:postcode":"BN21 3YA",
    "sg:province":"East Sussex",
    "sg:tags":[
        "creche"
    ],
    "wof:name":"Tom Thumb Nursery School",
    "wof:placetype":"venue"
},
  "geometry": {"coordinates":[0.280427,50.771381],"type":"Point"}
}