{
  "type": "Feature",
  "properties": {
    "iso:country":"GB",
    "sg:address":"Clarence Bldgs, Avenue Rd",
    "sg:city":"Freshwater",
    "sg:classifiers":[
        {
            "category":"Food & Beverages",
            "subcategory":"Specialty",
            "type":"Retail Goods"
        }
    ],
    "sg:postcode":"PO40 9UU",
    "sg:province":"Isle of Wight",
    "sg:tags":[
        "product",
        "health"
    ],
    "wof:name":"Fletcher,Ian,",
    "wof:placetype":"venue"
},
  "geometry": {"coordinates":[-1.524884,50.682568],"type":"Point"}
}