{
  "type": "Feature",
  "properties": {
    "addr:full":"Tyne Dock South Shields Tyne and Wear NE34 9PL",
    "addr:postcode":"ne34 9pl",
    "iso:country":"GB",
    "sg:address":"Tyne Dock",
    "sg:city":"South Shields",
    "sg:classifiers":[
        {
            "category":"Freight",
            "type":"Transportation"
        }
    ],
    "sg:phone":"+44 191 455 8881",
    "sg:postcode":"NE34 9PL",
    "sg:province":"Tyne and Wear",
    "sg:tags":[
        "haulage",
        "road"
    ],
    "wof:name":"Team Hawk",
    "wof:placetype":"venue"
},
  "geometry": {"coordinates":[-1.4546999931,54.9766082764],"type":"Point"}
}