{
  "type": "Feature",
  "properties": {
    "addr:full":"Furnace Hill, Clay Cross Chesterfield Derbyshire S45 9NF",
    "addr:postcode":"s45 9nf",
    "addr:street":"Furnace Hill",
    "iso:country":"GB",
    "sg:address":"Furnace Hill, Clay Cross",
    "sg:city":"Chesterfield",
    "sg:classifiers":[
        {
            "category":"Professional",
            "type":"Services"
        }
    ],
    "sg:phone":"+44 1246 250773",
    "sg:postcode":"S45 9NF",
    "sg:province":"Derbyshire",
    "sg:tags":[
        "pattern",
        "industrial",
        "maker"
    ],
    "wof:name":"Light Pattern & Tooling",
    "wof:placetype":"venue"
},
  "geometry": {"coordinates":[-1.415717,53.165791],"type":"Point"}
}