{
  "type": "Feature",
  "properties": {
    "iso:country":"GB",
    "sg:address":"257 Banbury Road, Summertown",
    "sg:city":"Oxford",
    "sg:classifiers":[
        {
            "category":"Real Estate",
            "subcategory":"Real Estate Agent",
            "type":"Services"
        }
    ],
    "sg:phone":"+44 1865 310300",
    "sg:postcode":"OX2 7HN",
    "sg:province":"Oxfordshire",
    "wof:name":"Adkin",
    "wof:placetype":"venue"
},
  "geometry": {"coordinates":[-1.2655869722,51.7782783508],"type":"Point"}
}