{
  "type": "Feature",
  "properties": {
    "iso:country":"GB",
    "sg:address":"171 Caerau Rd",
    "sg:city":"Maesteg",
    "sg:classifiers":[
        {
            "category":"Taxi",
            "type":"Transportation"
        }
    ],
    "sg:phone":"+44 1656 733333",
    "sg:postcode":"CF34 0PD",
    "sg:province":"Bridgend",
    "sg:tags":[
        "mini",
        "cab"
    ],
    "wof:name":"Imperial Cars",
    "wof:placetype":"venue"
},
  "geometry": {"coordinates":[-3.654364109,51.6356620789],"type":"Point"}
}