{
  "type": "Feature",
  "properties": {
    "addr:full":"162 Parrock St Gravesend Kent DA12 1ER",
    "addr:housenumber":"162",
    "addr:postcode":"da12 1er",
    "addr:street":"Parrock St",
    "iso:country":"GB",
    "sg:address":"162 Parrock St",
    "sg:city":"Gravesend",
    "sg:classifiers":[
        {
            "category":"Shopping",
            "subcategory":"Department Store",
            "type":"Retail Goods"
        }
    ],
    "sg:postcode":"DA12 1ER",
    "sg:province":"Kent",
    "wof:name":"Carter,Robert,",
    "wof:placetype":"venue"
},
  "geometry": {"coordinates":[0.37099,51.440128],"type":"Point"}
}