{
  "type": "Feature",
  "properties": {
    "addr:full":"Local Enquiries, 183 Kingsdown Av South Croydon Surrey CR2 6QS",
    "addr:housenumber":"183",
    "addr:postcode":"cr2 6qs",
    "addr:street":"Kingsdown Av",
    "iso:country":"GB",
    "sg:address":"Local Enquiries, 183 Kingsdown Av",
    "sg:city":"South Croydon",
    "sg:classifiers":[
        {
            "category":"Organizations",
            "subcategory":"Religious Organization",
            "type":"Services"
        }
    ],
    "sg:phone":"+44 20 8660 1954",
    "sg:postcode":"CR2 6QS",
    "sg:province":"Surrey",
    "sg:tags":[
        "organisation",
        "place",
        "worship"
    ],
    "wof:name":"Gideons International",
    "wof:placetype":"venue"
},
  "geometry": {"coordinates":[-0.097764,51.354515],"type":"Point"}
}