{
  "type": "Feature",
  "properties": {
    "iso:country":"GB",
    "sg:address":"Swallow End, Swallowfields",
    "sg:city":"Welwyn Garden City",
    "sg:classifiers":[
        {
            "category":"Professional",
            "subcategory":"Computer Services",
            "type":"Services"
        }
    ],
    "sg:phone":"+44 1707 322528",
    "sg:postcode":"AL7 1JA",
    "sg:province":"Hertfordshire",
    "sg:tags":[
        "system",
        "software"
    ],
    "wof:name":"Pointing Device Co. Ltd.",
    "wof:placetype":"venue"
},
  "geometry": {"coordinates":[-0.1901240051,51.801158905],"type":"Point"}
}