{
  "type": "Feature",
  "properties": {
    "iso:country":"GB",
    "sg:address":"66 The Mall",
    "sg:city":"Bexleyheath",
    "sg:classifiers":[
        {
            "category":"Shopping",
            "subcategory":"Music",
            "type":"Retail Goods"
        }
    ],
    "sg:phone":"+44 20 8298 0876",
    "sg:postcode":"DA6 7JJ",
    "sg:province":"Kent",
    "sg:tags":[
        "record",
        "tape",
        "cd"
    ],
    "wof:name":"H M V (U K) Ltd.",
    "wof:placetype":"venue"
},
  "geometry": {"coordinates":[0.15153,51.450935],"type":"Point"}
}