{
  "type": "Feature",
  "properties": {
    "iso:country":"GB",
    "sg:address":"Sunnyside, Yapton Road, Barnham",
    "sg:city":"Bognor Regis",
    "sg:classifiers":[
        {
            "category":"Home & Garden",
            "subcategory":"Garden Supply",
            "type":"Retail Goods"
        }
    ],
    "sg:phone":"+44 1243 553062",
    "sg:postcode":"PO22 0AX",
    "sg:province":"West Sussex",
    "sg:tags":[
        "nursery",
        "centre"
    ],
    "wof:name":"T H Beck & Sons",
    "wof:placetype":"venue"
},
  "geometry": {"coordinates":[-0.6241639853,50.833278656],"type":"Point"}
}