{
  "type": "Feature",
  "properties": {
    "addr:full":"1 Victoria Place, Promenade Kingsbridge Devon TQ7 1JG",
    "addr:housenumber":"1",
    "addr:postcode":"tq7 1jg",
    "addr:street":"Victoria Place Promenade",
    "iso:country":"GB",
    "sg:address":"1 Victoria Place, Promenade",
    "sg:city":"Kingsbridge",
    "sg:classifiers":[
        {
            "category":"Professional",
            "subcategory":"Accounting & Tax Preparation",
            "type":"Services"
        }
    ],
    "sg:phone":"+44 1548 856309",
    "sg:postcode":"TQ7 1JG",
    "sg:province":"Devon",
    "sg:tags":[
        "accountant"
    ],
    "wof:name":"James Cording & Co.",
    "wof:placetype":"venue"
},
  "geometry": {"coordinates":[-3.777619,50.283104],"type":"Point"}
}