{
  "type": "Feature",
  "properties": {
    "addr:full":"Grove Square, Leyburn Darlington North Yorkshire DL8 5AE",
    "addr:postcode":"dl8 5ae",
    "addr:street":"Square",
    "iso:country":"GB",
    "sg:address":"Grove Square, Leyburn",
    "sg:city":"Darlington",
    "sg:classifiers":[
        {
            "category":"Bars & Pubs",
            "type":"Food & Drink"
        }
    ],
    "sg:phone":"+44 1969 622272",
    "sg:postcode":"DL8 5AE",
    "sg:province":"North Yorkshire",
    "sg:tags":[
        "pubs",
        "inn"
    ],
    "wof:name":"King's Head Hotel",
    "wof:placetype":"venue"
},
  "geometry": {"coordinates":[-1.830434,54.310139],"type":"Point"}
}