{
  "type": "Feature",
  "properties": {
    "iso:country":"GB",
    "sg:address":"Freight House, Gatwick Road",
    "sg:city":"Crawley",
    "sg:classifiers":[
        {
            "category":"Retail",
            "subcategory":"Driving School",
            "type":"Services"
        }
    ],
    "sg:phone":"+44 1293 886018",
    "sg:postcode":"RH10 9RE",
    "sg:province":"Surrey",
    "wof:name":"Crawley L G V Driver Training",
    "wof:placetype":"venue"
},
  "geometry": {"coordinates":[-0.164524,51.138241],"type":"Point"}
}