{
  "type": "Feature",
  "properties": {
    "addr:full":"54-56 Commercial St New Tredegar Caerphilly NP2 6AA",
    "addr:housenumber":"54-56",
    "addr:postcode":"np2 6aa",
    "addr:street":"Commercial St",
    "iso:country":"GB",
    "sg:address":"54-56 Commercial St",
    "sg:city":"New Tredegar",
    "sg:classifiers":[
        {
            "category":"Food & Beverages",
            "subcategory":"Groceries & Convenience Stores",
            "type":"Retail Goods"
        }
    ],
    "sg:phone":"+44 1443 831221",
    "sg:postcode":"NP2 6AA",
    "sg:province":"Caerphilly",
    "wof:name":"Greenfields Convenience Store",
    "wof:placetype":"venue"
},
  "geometry": {"coordinates":[-3.243352,51.721897],"type":"Point"}
}