{
  "type": "Feature",
  "properties": {
    "addr:full":"Horsham Road, Handcross Haywards Heath East Sussex RH17 6DJ",
    "addr:postcode":"rh17 6dj",
    "addr:street":"Horsham Road",
    "iso:country":"GB",
    "sg:address":"Horsham Road, Handcross",
    "sg:city":"Haywards Heath",
    "sg:classifiers":[
        {
            "category":"Bars & Pubs",
            "type":"Food & Drink"
        }
    ],
    "sg:phone":"+44 1444 401406",
    "sg:postcode":"RH17 6DJ",
    "sg:province":"East Sussex",
    "sg:tags":[
        "pubs",
        "house",
        "inn",
        "public",
        "activity"
    ],
    "wof:name":"The Royal Oak Inn",
    "wof:placetype":"venue"
},
  "geometry": {"coordinates":[-0.1999180019,51.0542411804],"type":"Point"}
}