{
  "type": "Feature",
  "properties": {
    "addr:full":"Middle Street Taunton Somerset TA1 1SH",
    "addr:postcode":"ta1 1sh",
    "addr:street":"Middle Street",
    "iso:country":"GB",
    "sg:address":"Middle Street",
    "sg:city":"Taunton",
    "sg:classifiers":[
        {
            "category":"Communications",
            "type":"Services"
        }
    ],
    "sg:phone":"+44 1823 336000",
    "sg:postcode":"TA1 1SH",
    "sg:province":"Somerset",
    "sg:tags":[
        "tv",
        "video",
        "radio"
    ],
    "wof:name":"Paul Lawrence Visibly Sounder",
    "wof:placetype":"venue"
},
  "geometry": {"coordinates":[-3.1013190746,51.0168304443],"type":"Point"}
}