{
  "type": "Feature",
  "properties": {
    "addr:full":"55 Foryd Road, Kinmel Bay Rhyl Conwy LL18 3BU",
    "addr:housenumber":"55",
    "addr:postcode":"ll18 3bu",
    "addr:street":"Foryd Road",
    "iso:country":"GB",
    "sg:address":"55 Foryd Road, Kinmel Bay",
    "sg:city":"Rhyl",
    "sg:classifiers":[
        {
            "category":"Farming",
            "subcategory":"Fish & Marine Products",
            "type":"Manufacturing & Wholesale Goods"
        }
    ],
    "sg:postcode":"LL18 3BU",
    "sg:province":"Conwy",
    "sg:tags":[
        "fishmonger"
    ],
    "wof:name":"Charlies",
    "wof:placetype":"venue"
},
  "geometry": {"coordinates":[-3.472383976,53.311580658],"type":"Point"}
}