{
  "type": "Feature",
  "properties": {
    "iso:country":"GB",
    "sg:address":"2 Lorne Rd",
    "sg:city":"Northampton",
    "sg:classifiers":[
        {
            "category":"Professional",
            "subcategory":"Art Services",
            "type":"Services"
        }
    ],
    "sg:phone":"+44 1604 626279",
    "sg:postcode":"NN1 3RN",
    "sg:province":"Northamptonshire",
    "sg:tags":[
        "photographer"
    ],
    "wof:name":"Tracey Sherwood Photography",
    "wof:placetype":"venue"
},
  "geometry": {"coordinates":[-0.894345,52.244495],"type":"Point"}
}