{
  "type": "Feature",
  "properties": {
    "iso:country":"GB",
    "sg:address":"80 Broad Street, Parkgate",
    "sg:city":"Rotherham",
    "sg:classifiers":[
        {
            "category":"Shopping",
            "subcategory":"Clothing, Apparel, & Fashions",
            "type":"Retail Goods"
        }
    ],
    "sg:phone":"+44 1709 719325",
    "sg:postcode":"S62 6EQ",
    "sg:province":"South Yorkshire",
    "sg:tags":[
        "shop"
    ],
    "wof:name":"London Connection",
    "wof:placetype":"venue"
},
  "geometry": {"coordinates":[-1.3446500301,53.4510002136],"type":"Point"}
}