{
  "type": "Feature",
  "properties": {
    "addr:full":"127 Bradshaw Meadows Bolton Lancashire BL2 4NF",
    "addr:housenumber":"127",
    "addr:postcode":"bl2 4nf",
    "addr:street":"Bradshaw Meadows",
    "iso:country":"GB",
    "sg:address":"127 Bradshaw Meadows",
    "sg:city":"Bolton",
    "sg:classifiers":[
        {
            "category":"Professional",
            "type":"Services"
        }
    ],
    "sg:postcode":"BL2 4NF",
    "sg:province":"Lancashire",
    "sg:tags":[
        "entertainer"
    ],
    "wof:name":"Live Puppets",
    "wof:placetype":"venue"
},
  "geometry": {"coordinates":[-2.3982241154,53.6095314026],"type":"Point"}
}