{
  "type": "Feature",
  "properties": {
    "iso:country":"GB",
    "sg:address":"The Old Police House, Keal Hill, West Keal",
    "sg:city":"Spilsby",
    "sg:classifiers":[
        {
            "category":"Professional",
            "type":"Services"
        }
    ],
    "sg:phone":"+44 1790 754056",
    "sg:postcode":"PE23 4BE",
    "sg:province":"Lincolnshire",
    "sg:tags":[
        "entertainer"
    ],
    "wof:name":"Estelle Entertainments",
    "wof:placetype":"venue"
},
  "geometry": {"coordinates":[0.050366,53.151146],"type":"Point"}
}