{
  "type": "Feature",
  "properties": {
    "iso:country":"GB",
    "sg:address":"21 St Johns Road",
    "sg:city":"Huddersfield",
    "sg:classifiers":[
        {
            "category":"Government",
            "subcategory":"Office",
            "type":"Public Place"
        }
    ],
    "sg:phone":"+44 1484 427272",
    "sg:postcode":"HD1 5AY",
    "sg:province":"West Yorkshire",
    "sg:tags":[
        "central"
    ],
    "wof:name":"The Probabtion Service",
    "wof:placetype":"venue"
},
  "geometry": {"coordinates":[-1.784129,53.650791],"type":"Point"}
}