{
  "type": "Feature",
  "properties": {
    "iso:country":"GB",
    "sg:address":"1 Viewfield Road",
    "sg:city":"Arbroath",
    "sg:classifiers":[
        {
            "category":"Travel",
            "subcategory":"Hotels & Motels",
            "type":"Entertainment"
        }
    ],
    "sg:phone":"+44 1241 872446",
    "sg:postcode":"DD11 2BS",
    "sg:province":"Angus",
    "wof:name":"Viewfield Hotel",
    "wof:placetype":"venue"
},
  "geometry": {"coordinates":[-2.604317,56.558506],"type":"Point"}
}