{
  "type": "Feature",
  "properties": {
    "iso:country":"GB",
    "sg:address":"2 Main Street, Stoneyburn",
    "sg:city":"Bathgate",
    "sg:classifiers":[
        {
            "category":"Education",
            "subcategory":"School",
            "type":"Public Place"
        },
        {
            "category":"Government",
            "subcategory":"Office",
            "type":"Public Place"
        }
    ],
    "sg:phone":"+44 1501 762253",
    "sg:postcode":"EH47 8BA",
    "sg:province":"North Lanarkshire",
    "sg:tags":[
        "local",
        "authority"
    ],
    "wof:name":"Stoneyburn Primary School",
    "wof:placetype":"venue"
},
  "geometry": {"coordinates":[-3.679281,55.84465],"type":"Point"}
}