{
  "type": "Feature",
  "properties": {
    "addr:full":"52-56 Percy Road Whitley Bay Northumberland NE26 2AY",
    "addr:housenumber":"52-56",
    "addr:postcode":"ne26 2ay",
    "addr:street":"Percy Road",
    "iso:country":"GB",
    "sg:address":"52-56 Percy Road",
    "sg:city":"Whitley Bay",
    "sg:classifiers":[
        {
            "category":"Social Services",
            "subcategory":"Retirement Home",
            "type":"Services"
        }
    ],
    "sg:phone":"+44 191 252 7262",
    "sg:postcode":"NE26 2AY",
    "sg:province":"Northumberland",
    "sg:tags":[
        "rest"
    ],
    "wof:name":"Risedale Rest Home",
    "wof:placetype":"venue"
},
  "geometry": {"coordinates":[-1.4393899441,55.043258667],"type":"Point"}
}