{
  "type": "Feature",
  "properties": {
    "addr:full":"3 Clay Lane, Burtonwood Warrington Cheshire WA5 4HH",
    "addr:housenumber":"3",
    "addr:postcode":"wa5 4hh",
    "addr:street":"Clay Lane",
    "iso:country":"GB",
    "sg:address":"3 Clay Lane, Burtonwood",
    "sg:city":"Warrington",
    "sg:classifiers":[
        {
            "category":"Professional",
            "subcategory":"Business Services",
            "type":"Services"
        }
    ],
    "sg:postcode":"WA5 4HH",
    "sg:province":"Cheshire",
    "sg:tags":[
        "bookmaker"
    ],
    "wof:name":"Bill Forber",
    "wof:placetype":"venue"
},
  "geometry": {"coordinates":[-2.66041,53.43103],"type":"Point"}
}