{
  "type": "Feature",
  "properties": {
    "addr:full":"56 Old Edinburgh Road Inverness Highland IV2 3PG",
    "addr:housenumber":"56",
    "addr:postcode":"iv2 3pg",
    "addr:street":"Old Edinburgh Road",
    "iso:country":"GB",
    "sg:address":"56 Old Edinburgh Road",
    "sg:city":"Inverness",
    "sg:classifiers":[
        {
            "category":"Retail",
            "subcategory":"Driving School",
            "type":"Services"
        }
    ],
    "sg:postcode":"IV2 3PG",
    "sg:province":"Highland",
    "wof:name":"George Strachen",
    "wof:placetype":"venue"
},
  "geometry": {"coordinates":[-4.2170948982,57.4709281921],"type":"Point"}
}