{
  "type": "Feature",
  "properties": {
    "iso:country":"GB",
    "sg:address":"448 Alum Rock Road",
    "sg:city":"Birmingham",
    "sg:classifiers":[
        {
            "category":"Government",
            "subcategory":"Post Office",
            "type":"Public Place"
        }
    ],
    "sg:phone":"+44 121 327 3295",
    "sg:postcode":"B8 3HT",
    "sg:province":"West Midlands",
    "wof:name":"Shaw Hill Sub Post Office",
    "wof:placetype":"venue"
},
  "geometry": {"coordinates":[-1.8411849737,52.4880599976],"type":"Point"}
}