{
  "type": "Feature",
  "properties": {
    "addr:full":"63 Broad Street Fraserburgh Aberdeenshire AB43 9AU",
    "addr:housenumber":"63",
    "addr:postcode":"ab43 9au",
    "addr:street":"Broad Street",
    "iso:country":"GB",
    "sg:address":"63 Broad Street",
    "sg:city":"Fraserburgh",
    "sg:classifiers":[
        {
            "category":"Travel",
            "subcategory":"Hotels & Motels",
            "type":"Entertainment"
        }
    ],
    "sg:phone":"+44 1346 518524",
    "sg:postcode":"AB43 9AU",
    "sg:province":"Aberdeenshire",
    "wof:name":"Royal Hotel Fraserburgh",
    "wof:placetype":"venue"
},
  "geometry": {"coordinates":[-2.0047171116,57.6917304993],"type":"Point"}
}