{
  "type": "Feature",
  "properties": {
    "addr:full":"51a Yarmouth Road, Caister On Sea Great Yarmouth Norfolk NR30 5DL",
    "addr:housenumber":"51a",
    "addr:postcode":"nr30 5dl",
    "addr:street":"Yarmouth Road;Great Yarmouth",
    "iso:country":"GB",
    "sg:address":"51a Yarmouth Road, Caister On Sea",
    "sg:city":"Great Yarmouth",
    "sg:classifiers":[
        {
            "category":"Manufacturing",
            "subcategory":"Petroleum Products",
            "type":"Manufacturing & Wholesale Goods"
        }
    ],
    "sg:phone":"+44 1493 377377",
    "sg:postcode":"NR30 5DL",
    "sg:province":"Norfolk",
    "sg:tags":[
        "double",
        "glazing"
    ],
    "wof:name":"County Home Improvements",
    "wof:placetype":"venue"
},
  "geometry": {"coordinates":[1.7292699814,52.644153595],"type":"Point"}
}