{
  "type": "Feature",
  "properties": {
    "addr:full":"The Clubhouse, Oaklands Rd Buckfastleigh Devon TQ11 0BL",
    "addr:postcode":"tq11 0bl",
    "addr:street":"Oaklands Rd",
    "iso:country":"GB",
    "sg:address":"The Clubhouse, Oaklands Rd",
    "sg:city":"Buckfastleigh",
    "sg:classifiers":[
        {
            "category":"Arena",
            "subcategory":"Sports Club",
            "type":"Entertainment"
        }
    ],
    "sg:phone":"+44 1364 643895",
    "sg:postcode":"TQ11 0BL",
    "sg:province":"Devon",
    "wof:name":"Buckfastleigh Cricket Club",
    "wof:placetype":"venue"
},
  "geometry": {"coordinates":[-3.7792088985,50.4813690186],"type":"Point"}
}