{
  "type": "Feature",
  "properties": {
    "addr:full":"Suite 7 Crystal House, New Bedford Road Luton Bedfordshire LU1 1HS",
    "addr:housenumber":"suite 7 crystal house",
    "addr:postcode":"lu1 1hs",
    "addr:street":"New Bedford Road",
    "iso:country":"GB",
    "sg:address":"Suite 7 Crystal House, New Bedford Road",
    "sg:city":"Luton",
    "sg:classifiers":[
        {
            "category":"Manufacturing",
            "subcategory":"Glass & Minerals",
            "type":"Manufacturing & Wholesale Goods"
        }
    ],
    "sg:postcode":"LU1 1HS",
    "sg:province":"Bedfordshire",
    "sg:tags":[
        "fibre",
        "optic"
    ],
    "wof:name":"Fons",
    "wof:placetype":"venue"
},
  "geometry": {"coordinates":[-0.418734,51.881844],"type":"Point"}
}