{
  "type": "Feature",
  "properties": {
    "iso:country":"GB",
    "sg:address":"Po Box 20",
    "sg:city":"Orpington",
    "sg:classifiers":[
        {
            "category":"Shopping",
            "subcategory":"Optical Goods",
            "type":"Retail Goods"
        }
    ],
    "sg:phone":"+44 1689 862533",
    "sg:postcode":"BR6 8SF",
    "sg:province":"Kent",
    "wof:name":"Direct Optical Lens Cleaners",
    "wof:placetype":"venue"
},
  "geometry": {"coordinates":[0.10108,51.37804],"type":"Point"}
}