{
  "type": "Feature",
  "properties": {
    "iso:country":"GB",
    "sg:address":"Hales Green Farm",
    "sg:city":"Norwich",
    "sg:classifiers":[
        {
            "category":"Professional",
            "subcategory":"Accounting & Tax Preparation",
            "type":"Services"
        }
    ],
    "sg:postcode":"NR14 6QW",
    "sg:province":"Norfolk",
    "sg:tags":[
        "accountant"
    ],
    "wof:name":"J P Webster",
    "wof:placetype":"venue"
},
  "geometry": {"coordinates":[1.5085849762,52.5216064453],"type":"Point"}
}