{
  "type": "Feature",
  "properties": {
    "addr:full":"Maes Y Llan, Guilsfield Welshpool Shropshire SY21 9NF",
    "addr:postcode":"sy21 9nf",
    "addr:street":"Maes Y Llan Guilsfield",
    "iso:country":"GB",
    "sg:address":"Maes Y Llan, Guilsfield",
    "sg:city":"Welshpool",
    "sg:classifiers":[
        {
            "category":"Building & Trades",
            "subcategory":"Construction",
            "type":"Services"
        }
    ],
    "sg:postcode":"SY21 9NF",
    "sg:province":"Shropshire",
    "sg:tags":[
        "dry",
        "lining",
        "plasterers",
        "screeders"
    ],
    "wof:name":"Paul Gwilt",
    "wof:placetype":"venue"
},
  "geometry": {"coordinates":[-3.1555891037,52.6966896057],"type":"Point"}
}