{
  "type": "Feature",
  "properties": {
    "iso:country":"GB",
    "sg:address":"433 St Helens Road",
    "sg:city":"Bolton",
    "sg:classifiers":[
        {
            "category":"Manufacturing",
            "subcategory":"Petroleum Products",
            "type":"Manufacturing & Wholesale Goods"
        }
    ],
    "sg:phone":"+44 1204 659754",
    "sg:postcode":"BL3 3RT",
    "sg:province":"Lancashire",
    "sg:tags":[
        "double",
        "glazing"
    ],
    "wof:name":"Thomas Brown",
    "wof:placetype":"venue"
},
  "geometry": {"coordinates":[-2.4462840557,53.5653648376],"type":"Point"}
}