{
  "type": "Feature",
  "properties": {
    "iso:country":"GB",
    "sg:address":"Ballogie Shop, Ballogie",
    "sg:city":"Aboyne",
    "sg:classifiers":[
        {
            "category":"Shopping",
            "subcategory":"Gifts & Souvenirs",
            "type":"Retail Goods"
        }
    ],
    "sg:phone":"+44 1339 886104",
    "sg:postcode":"AB34 5DP",
    "sg:province":"Aberdeenshire",
    "sg:tags":[
        "shop"
    ],
    "wof:name":"Sarah Butterworth Speciality Showcase",
    "wof:placetype":"venue"
},
  "geometry": {"coordinates":[-2.7800590992,57.0761795044],"type":"Point"}
}