{
  "type": "Feature",
  "properties": {
    "iso:country":"GB",
    "sg:address":"345 Aylestone Road",
    "sg:city":"Leicester",
    "sg:classifiers":[
        {
            "category":"Health Services",
            "subcategory":"Dentist",
            "type":"Services"
        }
    ],
    "sg:phone":"+44 116 283 2701",
    "sg:postcode":"LE2 8TA",
    "sg:province":"Leicestershire",
    "wof:name":"Aylestone House Dental Practice",
    "wof:placetype":"venue"
},
  "geometry": {"coordinates":[-1.1426980495,52.6127586365],"type":"Point"}
}