{
  "type": "Feature",
  "properties": {
    "iso:country":"GB",
    "sg:address":"3 West Street",
    "sg:city":"Buckingham",
    "sg:classifiers":[
        {
            "category":"Home & Garden",
            "subcategory":"Hardware",
            "type":"Retail Goods"
        }
    ],
    "sg:phone":"+44 1280 822248",
    "sg:postcode":"MK18 1HL",
    "sg:province":"Buckinghamshire",
    "sg:tags":[
        "retailer",
        "lighting"
    ],
    "wof:name":"Brightlights of Buckingham",
    "wof:placetype":"venue"
},
  "geometry": {"coordinates":[-0.988829,52.000256],"type":"Point"}
}