{
  "type": "Feature",
  "properties": {
    "iso:country":"GB",
    "sg:address":"1349-1353 London Road",
    "sg:city":"Leigh-on-sea",
    "sg:classifiers":[
        {
            "category":"Professional",
            "subcategory":"Advertising",
            "type":"Services"
        }
    ],
    "sg:postcode":"SS9 2AB",
    "sg:province":"Essex",
    "sg:tags":[
        "agency"
    ],
    "wof:name":"Wren Vision Ltd",
    "wof:placetype":"venue"
},
  "geometry": {"coordinates":[0.6493729949,51.5486335754],"type":"Point"}
}