{
  "type": "Feature",
  "properties": {
    "iso:country":"GB",
    "sg:address":"Checketts Road",
    "sg:city":"Leicester",
    "sg:classifiers":[
        {
            "category":"Autos & Motor Vehicles",
            "subcategory":"Automobile Sales",
            "type":"Retail Goods"
        }
    ],
    "sg:postcode":"LE4 5ER",
    "sg:province":"Leicestershire",
    "sg:tags":[
        "car"
    ],
    "wof:name":"Eurocar",
    "wof:placetype":"venue"
},
  "geometry": {"coordinates":[-1.121439,52.658844],"type":"Point"}
}