{
  "type": "Feature",
  "properties": {
    "addr:full":"Stocklake Industrial Estate, Pembroke Road Aylesbury Buckinghamshire HP20 1DB",
    "addr:postcode":"hp20 1db",
    "addr:street":"Estate Pembroke Road",
    "iso:country":"GB",
    "sg:address":"Stocklake Industrial Estate, Pembroke Road",
    "sg:city":"Aylesbury",
    "sg:classifiers":[
        {
            "category":"Manufacturing",
            "subcategory":"Tools & Machinery",
            "type":"Manufacturing & Wholesale Goods"
        }
    ],
    "sg:phone":"+44 1296 482030",
    "sg:postcode":"HP20 1DB",
    "sg:province":"Buckinghamshire",
    "sg:tags":[
        "equipment",
        "builder",
        "metal"
    ],
    "wof:name":"Thomas Bugden & Co. Ltd.",
    "wof:placetype":"venue"
},
  "geometry": {"coordinates":[-0.8118640184,51.8187789917],"type":"Point"}
}