{
  "type": "Feature",
  "properties": {
    "iso:country":"GB",
    "sg:address":"12 Popes Mead",
    "sg:city":"Haslemere",
    "sg:classifiers":[
        {
            "category":"Utilities",
            "subcategory":"Fuel Oil & Lpg",
            "type":"Services"
        },
        {
            "category":"Building & Trades",
            "subcategory":"Construction",
            "type":"Services"
        }
    ],
    "sg:postcode":"GU27 2AR",
    "sg:province":"Hampshire",
    "sg:tags":[
        "peat",
        "firewood",
        "logs",
        "restoration",
        "refurbishment"
    ],
    "wof:name":"Haslemere Logs",
    "wof:placetype":"venue"
},
  "geometry": {"coordinates":[-0.711575,51.090038],"type":"Point"}
}