{
  "type": "Feature",
  "properties": {
    "iso:country":"GB",
    "sg:address":"318 Oxbridge Road",
    "sg:city":"London",
    "sg:classifiers":[
        {
            "category":"Professional",
            "subcategory":"Printing & Photocopies",
            "type":"Services"
        }
    ],
    "sg:postcode":"W3 9QP",
    "sg:province":"Greater London",
    "sg:tags":[
        "duplicating",
        "copying"
    ],
    "wof:name":"B M E (Office Technology)",
    "wof:placetype":"venue"
},
  "geometry": {"coordinates":[-0.277384,51.508442],"type":"Point"}
}