{
  "type": "Feature",
  "properties": {
    "addr:full":"Unit 12, The Quadrangle Ruchill St Glasgow Glasgow City G20 9PX",
    "addr:housenumber":"unit 12",
    "addr:postcode":"g20 9px",
    "addr:street":"The Quadrangle;St",
    "iso:country":"GB",
    "sg:address":"Unit 12, The Quadrangle Ruchill St",
    "sg:city":"Glasgow",
    "sg:classifiers":[
        {
            "category":"Professional",
            "subcategory":"Computer Services",
            "type":"Services"
        }
    ],
    "sg:phone":"+44 141 402 6552",
    "sg:postcode":"G20 9PX",
    "sg:province":"Glasgow City",
    "sg:tags":[
        "system",
        "software"
    ],
    "wof:name":"Reactive Network Cabling",
    "wof:placetype":"venue"
},
  "geometry": {"coordinates":[-4.2829799652,55.8871612549],"type":"Point"}
}