{
  "type": "Feature",
  "properties": {
    "iso:country":"GB",
    "sg:address":"96 Darley Avenue",
    "sg:city":"Birmingham",
    "sg:classifiers":[
        {
            "category":"Building & Trades",
            "subcategory":"Construction",
            "type":"Services"
        }
    ],
    "sg:phone":"+44 121 730 1009",
    "sg:postcode":"B34 6JN",
    "sg:province":"West Midlands",
    "sg:tags":[
        "bricklaying"
    ],
    "wof:name":"Philip C Carroll",
    "wof:placetype":"venue"
},
  "geometry": {"coordinates":[-1.7949689627,52.4972496033],"type":"Point"}
}