{
  "type": "Feature",
  "properties": {
    "addr:full":"Silverstone Cottage, Heath Road, North Elmham Dereham Norfolk NR20 5EU",
    "addr:postcode":"nr20 5eu",
    "addr:street":"Heath Road North;Dereham",
    "iso:country":"GB",
    "sg:address":"Silverstone Cottage, Heath Road, North Elmham",
    "sg:city":"Dereham",
    "sg:classifiers":[
        {
            "category":"Taxi",
            "type":"Transportation"
        },
        {
            "category":"Military Area",
            "subcategory":"Air Force Base",
            "type":"Public Place"
        }
    ],
    "sg:phone":"+44 1362 668500",
    "sg:postcode":"NR20 5EU",
    "sg:province":"Norfolk",
    "sg:tags":[
        "hire",
        "private"
    ],
    "wof:name":"Dave Taxis",
    "wof:placetype":"venue"
},
  "geometry": {"coordinates":[0.9393519759,52.7489776611],"type":"Point"}
}