{
  "type": "Feature",
  "properties": {
    "iso:country":"GB",
    "sg:address":"Station Road North, Murton",
    "sg:city":"Seaham",
    "sg:classifiers":[
        {
            "category":"Government",
            "subcategory":"Post Office",
            "type":"Public Place"
        }
    ],
    "sg:phone":"+44 191 526 1736",
    "sg:postcode":"SR7 9RX",
    "sg:province":"Durham",
    "wof:name":"Murton Station Post Office",
    "wof:placetype":"venue"
},
  "geometry": {"coordinates":[-1.4046289921,54.8174438477],"type":"Point"}
}