{
  "type": "Feature",
  "properties": {
    "addr:full":"South East Leter Delivery Office, Pitt Lane Sheffield Derbyshire S12 2AF",
    "addr:postcode":"leter;s12 2af",
    "addr:street":"Pitt Lane",
    "iso:country":"GB",
    "sg:address":"South East Leter Delivery Office, Pitt Lane",
    "sg:city":"Sheffield",
    "sg:classifiers":[
        {
            "category":"Professional",
            "type":"Services"
        },
        {
            "category":"Personal",
            "type":"Services"
        }
    ],
    "sg:phone":"+44 114 239 9827",
    "sg:postcode":"S12 2AF",
    "sg:province":"Derbyshire",
    "sg:tags":[
        "delivery",
        "good"
    ],
    "wof:name":"South East Postman Delivery Office",
    "wof:placetype":"venue"
},
  "geometry": {"coordinates":[-1.4645440578,53.3831100464],"type":"Point"}
}