{
  "type": "Feature",
  "properties": {
    "addr:full":"Malthouse Road, Llantarnam Cwmbran Monmouthshire NP44 3EE",
    "addr:postcode":"np44 3ee",
    "addr:street":"Malthouse Road",
    "iso:country":"GB",
    "sg:address":"Malthouse Road, Llantarnam",
    "sg:city":"Cwmbran",
    "sg:classifiers":[
        {
            "category":"Farming",
            "subcategory":"Livestock Farm",
            "type":"Manufacturing & Wholesale Goods"
        }
    ],
    "sg:phone":"+44 1633 864514",
    "sg:postcode":"NP44 3EE",
    "sg:province":"Monmouthshire",
    "sg:tags":[
        "others"
    ],
    "wof:name":"ANDREW E TOVEY",
    "wof:placetype":"venue"
},
  "geometry": {"coordinates":[-2.988868,51.627182],"type":"Point"}
}