{
  "type": "Feature",
  "properties": {
    "addr:full":"165 Terminus Road Eastbourne East Sussex BN21 3NX",
    "addr:housenumber":"165",
    "addr:postcode":"bn21 3nx",
    "addr:street":"Terminus Road",
    "iso:country":"GB",
    "sg:address":"165 Terminus Road",
    "sg:city":"Eastbourne",
    "sg:classifiers":[
        {
            "category":"Organizations",
            "subcategory":"Non-profit Organization",
            "type":"Services"
        }
    ],
    "sg:phone":"+44 1323 640213",
    "sg:postcode":"BN21 3NX",
    "sg:province":"East Sussex",
    "sg:tags":[
        "organisation",
        "voluntary",
        "charity"
    ],
    "wof:name":"British Heart Foundation",
    "wof:placetype":"venue"
},
  "geometry": {"coordinates":[0.288513,50.768017],"type":"Point"}
}