{
  "type": "Feature",
  "properties": {
    "addr:full":"151 Vartry Road London Greater London N15 6HB",
    "addr:housenumber":"151",
    "addr:postcode":"n15 6hb",
    "addr:street":"Vartry Road",
    "iso:country":"GB",
    "sg:address":"151 Vartry Road",
    "sg:city":"London",
    "sg:classifiers":[
        {
            "category":"Manufacturing",
            "subcategory":"Metals",
            "type":"Manufacturing & Wholesale Goods"
        },
        {
            "category":"Manufacturing",
            "subcategory":"Furniture",
            "type":"Manufacturing & Wholesale Goods"
        }
    ],
    "sg:postcode":"N15 6HB",
    "sg:province":"Greater London",
    "sg:tags":[
        "polishing",
        "heat",
        "-",
        "treatment",
        "french"
    ],
    "wof:name":"Adrian Martell",
    "wof:placetype":"venue"
},
  "geometry": {"coordinates":[-0.082721,51.575691],"type":"Point"}
}