{
  "type": "Feature",
  "properties": {
    "iso:country":"GB",
    "sg:address":"20-22 Gillibrand Street",
    "sg:city":"Chorley",
    "sg:classifiers":[
        {
            "category":"Organizations",
            "subcategory":"Non-profit Organization",
            "type":"Services"
        }
    ],
    "sg:phone":"+44 1257 267293",
    "sg:postcode":"PR7 2EJ",
    "sg:province":"Lancashire",
    "sg:tags":[
        "organisation",
        "voluntary",
        "charity"
    ],
    "wof:name":"Age Concern",
    "wof:placetype":"venue"
},
  "geometry": {"coordinates":[-2.632612,53.651447],"type":"Point"}
}