{
  "type": "Feature",
  "properties": {
    "addr:full":"5 Hayland St Sheffield South Yorkshire S9 1BY",
    "addr:housenumber":"5",
    "addr:postcode":"s9 1by",
    "addr:street":"Hayland St",
    "iso:country":"GB",
    "sg:address":"5 Hayland St",
    "sg:city":"Sheffield",
    "sg:classifiers":[
        {
            "category":"Manufacturing",
            "subcategory":"Metals",
            "type":"Manufacturing & Wholesale Goods"
        }
    ],
    "sg:phone":"+44 114 244 7599",
    "sg:postcode":"S9 1BY",
    "sg:province":"South Yorkshire",
    "sg:tags":[
        "merchant"
    ],
    "wof:name":"Transcommodities Ltd",
    "wof:placetype":"venue"
},
  "geometry": {"coordinates":[-1.4200290442,53.4122200012],"type":"Point"}
}