{
  "type": "Feature",
  "properties": {
    "addr:full":"16 Cawston Lane, Dunchurch Rugby Warwickshire CV22 6QE",
    "addr:housenumber":"16",
    "addr:postcode":"cv22 6qe",
    "addr:street":"Cawston Lane",
    "iso:country":"GB",
    "sg:address":"16 Cawston Lane, Dunchurch",
    "sg:city":"Rugby",
    "sg:classifiers":[
        {
            "category":"Building & Trades",
            "subcategory":"Construction",
            "type":"Services"
        }
    ],
    "sg:phone":"+44 1788 521200",
    "sg:postcode":"CV22 6QE",
    "sg:province":"Warwickshire",
    "sg:tags":[
        "roofing",
        "contracting"
    ],
    "wof:name":"R G Bland (Roofing) Ltd.",
    "wof:placetype":"venue"
},
  "geometry": {"coordinates":[-1.290684,52.341087],"type":"Point"}
}