{
  "type": "Feature",
  "properties": {
    "iso:country":"GB",
    "sg:address":"45 Evering Avenue",
    "sg:city":"Poole",
    "sg:classifiers":[
        {
            "category":"Professional",
            "subcategory":"Engineering",
            "type":"Services"
        }
    ],
    "sg:phone":"+44 1202 734579",
    "sg:postcode":"BH12 4JF",
    "sg:province":"Dorset",
    "sg:tags":[
        "civil",
        "engineer"
    ],
    "wof:name":"C W Stanley Surface & Co",
    "wof:placetype":"venue"
},
  "geometry": {"coordinates":[-1.935037,50.746262],"type":"Point"}
}