{
  "type": "Feature",
  "properties": {
    "iso:country":"GB",
    "sg:address":"Cobourg Road",
    "sg:city":"London",
    "sg:classifiers":[
        {
            "category":"Education",
            "subcategory":"School",
            "type":"Public Place"
        },
        {
            "category":"Government",
            "subcategory":"Office",
            "type":"Public Place"
        }
    ],
    "sg:phone":"+44 20 7703 2583",
    "sg:postcode":"SE5 0JD",
    "sg:province":"Greater London",
    "sg:tags":[
        "local",
        "authority"
    ],
    "wof:name":"Cobourg Primary School",
    "wof:placetype":"venue"
},
  "geometry": {"coordinates":[-0.0766889974,51.4845657349],"type":"Point"}
}