{
  "type": "Feature",
  "properties": {
    "iso:country":"GB",
    "sg:address":"30 Cross Close",
    "sg:city":"Newquay",
    "sg:classifiers":[
        {
            "category":"Taxi",
            "type":"Transportation"
        }
    ],
    "sg:phone":"+44 1637 859000",
    "sg:postcode":"TR7 3LB",
    "sg:province":"Cornwall",
    "sg:tags":[
        "mini",
        "cab"
    ],
    "wof:name":"On The Dot Private Hire",
    "wof:placetype":"venue"
},
  "geometry": {"coordinates":[-5.052115,50.419029],"type":"Point"}
}