{
  "type": "Feature",
  "properties": {
    "iso:country":"GB",
    "sg:address":"Queens House, 129 Queens Road",
    "sg:city":"Norwich",
    "sg:classifiers":[
        {
            "category":"Real Estate",
            "subcategory":"Architect",
            "type":"Services"
        }
    ],
    "sg:phone":"+44 1603 620326",
    "sg:postcode":"NR1 3PL",
    "sg:province":"Norfolk",
    "wof:name":"OWEN BOND PLANNING SUPERVISORS LTD",
    "wof:placetype":"venue"
},
  "geometry": {"coordinates":[1.2949,52.622494],"type":"Point"}
}