{
  "type": "Feature",
  "properties": {
    "iso:country":"GB",
    "sg:address":"Townsend Farm, Waterperry",
    "sg:city":"Oxford",
    "sg:classifiers":[
        {
            "category":"Professional",
            "subcategory":"Detective & Security Services",
            "type":"Services"
        }
    ],
    "sg:phone":"+44 1865 367890",
    "sg:postcode":"OX33 1LG",
    "sg:province":"Buckinghamshire",
    "wof:name":"Rampart Security Ltd.",
    "wof:placetype":"venue"
},
  "geometry": {"coordinates":[-1.0920180082,51.7537612915],"type":"Point"}
}