{
  "type": "Feature",
  "properties": {
    "addr:full":"5 Kenworth Cl, Seabridge Newcastle Staffordshire ST5 3LH",
    "addr:housenumber":"5",
    "addr:postcode":"st5 3lh",
    "addr:street":"Kenworth Cl Seabridge",
    "iso:country":"GB",
    "sg:address":"5 Kenworth Cl, Seabridge",
    "sg:city":"Newcastle",
    "sg:classifiers":[
        {
            "category":"Autos & Motor Vehicles",
            "subcategory":"Auto Supplies",
            "type":"Retail Goods"
        }
    ],
    "sg:postcode":"ST5 3LH",
    "sg:province":"Staffordshire",
    "sg:tags":[
        "equipment",
        "diesel"
    ],
    "wof:name":"Stafordshire Diesel & Auto Services",
    "wof:placetype":"venue"
},
  "geometry": {"coordinates":[-2.2370009422,52.988494873],"type":"Point"}
}