{
  "type": "Feature",
  "properties": {
    "addr:full":"114 Scotland Road Nelson Lancashire BB9 7XJ",
    "addr:housenumber":"114",
    "addr:postcode":"bb9 7xj",
    "addr:street":"Scotland Road",
    "iso:country":"GB",
    "sg:address":"114 Scotland Road",
    "sg:city":"Nelson",
    "sg:classifiers":[
        {
            "category":"Shopping",
            "subcategory":"News",
            "type":"Retail Goods"
        }
    ],
    "sg:phone":"+44 1282 613977",
    "sg:postcode":"BB9 7XJ",
    "sg:province":"Lancashire",
    "sg:tags":[
        "newsagent"
    ],
    "wof:name":"M & M Newsagents",
    "wof:placetype":"venue"
},
  "geometry": {"coordinates":[-2.2140049934,53.8404693604],"type":"Point"}
}