{
  "type": "Feature",
  "properties": {
    "addr:full":"70 Fore Street, Kingskerswell Newton Abbot Devon TQ12 5JB",
    "addr:housenumber":"70",
    "addr:postcode":"tq12 5jb",
    "addr:street":"Fore Street",
    "iso:country":"GB",
    "sg:address":"70 Fore Street, Kingskerswell",
    "sg:city":"Newton Abbot",
    "sg:classifiers":[
        {
            "category":"Real Estate",
            "subcategory":"Surveying",
            "type":"Services"
        }
    ],
    "sg:postcode":"TQ12 5JB",
    "sg:province":"Devon",
    "sg:tags":[
        "building",
        "surveyor"
    ],
    "wof:name":"Robert Vickridge",
    "wof:placetype":"venue"
},
  "geometry": {"coordinates":[-3.5773949623,50.4976501465],"type":"Point"}
}