{
  "type": "Feature",
  "properties": {
    "addr:full":"75 The Grove London Greater London W5 5LL",
    "addr:housenumber":"75",
    "addr:postcode":"w5 5ll",
    "addr:street":"The Grove",
    "iso:country":"GB",
    "sg:address":"75 The Grove",
    "sg:city":"London",
    "sg:classifiers":[
        {
            "category":"Communications",
            "subcategory":"Television Station",
            "type":"Services"
        }
    ],
    "sg:postcode":"W5 5LL",
    "sg:province":"Greater London",
    "sg:tags":[
        "video"
    ],
    "wof:name":"Comrex U K",
    "wof:placetype":"venue"
},
  "geometry": {"coordinates":[-0.3014760017,51.5110321045],"type":"Point"}
}