{
  "type": "Feature",
  "properties": {
    "addr:full":"18a St James St Newport Isle of Wight PO30 5HB",
    "addr:housenumber":"18a",
    "addr:postcode":"po30 5hb",
    "addr:street":"St James St",
    "iso:country":"GB",
    "sg:address":"18a St James St",
    "sg:city":"Newport",
    "sg:classifiers":[
        {
            "category":"Real Estate",
            "subcategory":"Surveying",
            "type":"Services"
        }
    ],
    "sg:phone":"+44 1983 523414",
    "sg:postcode":"PO30 5HB",
    "sg:province":"Isle of Wight",
    "sg:tags":[
        "surveyor",
        "valuer"
    ],
    "wof:name":"Colleys Professional Services",
    "wof:placetype":"venue"
},
  "geometry": {"coordinates":[-1.2970130444,50.7019805908],"type":"Point"}
}