{
  "type": "Feature",
  "properties": {
    "addr:full":"16 Barracks Square, Barracks Road Newcastle Staffordshire ST5 1LG",
    "addr:housenumber":"16",
    "addr:postcode":"st5 1lg",
    "addr:street":"Barracks Square Barracks Road",
    "iso:country":"GB",
    "sg:address":"16 Barracks Square, Barracks Road",
    "sg:city":"Newcastle",
    "sg:classifiers":[
        {
            "category":"Arts & Performance",
            "subcategory":"Arts Center",
            "type":"Entertainment"
        },
        {
            "category":"Arts & Performance",
            "subcategory":"Theater",
            "type":"Entertainment"
        }
    ],
    "sg:phone":"+44 1782 717326",
    "sg:postcode":"ST5 1LG",
    "sg:province":"Staffordshire",
    "sg:tags":[
        "theatre",
        "centre"
    ],
    "wof:name":"Beavers Arts Ltd.",
    "wof:placetype":"venue"
},
  "geometry": {"coordinates":[-2.228601,53.008801],"type":"Point"}
}