{
  "type": "Feature",
  "properties": {
    "iso:country":"GB",
    "sg:address":"Unit 21 Lancaster Way Business P",
    "sg:city":"Ely",
    "sg:classifiers":[
        {
            "category":"Building & Trades",
            "subcategory":"Construction",
            "type":"Services"
        }
    ],
    "sg:postcode":"CB6 3NW",
    "sg:province":"Cambridgeshire",
    "sg:tags":[
        "equipment"
    ],
    "wof:name":"Lorry Loaders Ltd.",
    "wof:placetype":"venue"
},
  "geometry": {"coordinates":[0.22162,52.383018],"type":"Point"}
}