{
  "type": "Feature",
  "properties": {
    "addr:full":"74 Preston Road Brighton East Sussex BN1 4QG",
    "addr:housenumber":"74",
    "addr:postcode":"bn1 4qg",
    "addr:street":"Preston Road",
    "iso:country":"GB",
    "sg:address":"74 Preston Road",
    "sg:city":"Brighton",
    "sg:classifiers":[
        {
            "category":"Autos & Motor Vehicles",
            "subcategory":"Auto Supplies",
            "type":"Retail Goods"
        }
    ],
    "sg:phone":"+44 1273 279678",
    "sg:postcode":"BN1 4QG",
    "sg:province":"East Sussex",
    "sg:tags":[
        "tyre"
    ],
    "wof:name":"Strafford Tyres",
    "wof:placetype":"venue"
},
  "geometry": {"coordinates":[-0.1414619982,50.8354492188],"type":"Point"}
}