{
  "type": "Feature",
  "properties": {
    "iso:country":"GB",
    "sg:address":"62 Grove Road",
    "sg:city":"Amersham",
    "sg:classifiers":[
        {
            "category":"Taxi",
            "type":"Transportation"
        },
        {
            "category":"Military Area",
            "subcategory":"Air Force Base",
            "type":"Public Place"
        }
    ],
    "sg:phone":"+44 1494 434949",
    "sg:postcode":"HP6 6LY",
    "sg:province":"Buckinghamshire",
    "sg:tags":[
        "hire",
        "private"
    ],
    "wof:name":"Crystal Cars",
    "wof:placetype":"venue"
},
  "geometry": {"coordinates":[-0.586713,51.677277],"type":"Point"}
}