{
  "type": "Feature",
  "properties": {
    "iso:country":"GB",
    "sg:address":"3 Downview Close, East Wittering",
    "sg:city":"Chichester",
    "sg:classifiers":[
        {
            "category":"Home & Garden",
            "subcategory":"Building Materials",
            "type":"Retail Goods"
        }
    ],
    "sg:phone":"+44 1243 673983",
    "sg:postcode":"PO20 8NS",
    "sg:province":"West Sussex",
    "sg:tags":[
        "dust",
        "extraction",
        "system"
    ],
    "wof:name":"Complete Ventilation",
    "wof:placetype":"venue"
},
  "geometry": {"coordinates":[-0.8650280237,50.7668418884],"type":"Point"}
}