{
  "type": "Feature",
  "properties": {
    "addr:full":"12 Grange Indust Est, Rawcliffe Rd Goole East Riding of Yorkshire DN14 6TY",
    "addr:housenumber":"12",
    "addr:postcode":"dn14 6ty",
    "addr:street":"Grange Indust Est Rawcliffe Rd",
    "iso:country":"GB",
    "sg:address":"12 Grange Indust Est, Rawcliffe Rd",
    "sg:city":"Goole",
    "sg:classifiers":[
        {
            "category":"Government",
            "subcategory":"Post Office",
            "type":"Public Place"
        }
    ],
    "sg:phone":"+44 1405 766844",
    "sg:postcode":"DN14 6TY",
    "sg:province":"East Riding of Yorkshire",
    "sg:tags":[
        "messenger",
        "courier"
    ],
    "wof:name":"Direct Couriers",
    "wof:placetype":"venue"
},
  "geometry": {"coordinates":[-0.8869299889,53.7043418884],"type":"Point"}
}