{
  "type": "Feature",
  "properties": {
    "iso:country":"GB",
    "sg:address":"Wharfebank House, Ilkley Road",
    "sg:city":"Otley",
    "sg:classifiers":[
        {
            "category":"Professional",
            "subcategory":"Management & Consulting",
            "type":"Services"
        }
    ],
    "sg:phone":"+44 1943 851144",
    "sg:postcode":"LS21 3JP",
    "sg:province":"North Yorkshire",
    "sg:tags":[
        "consultant",
        "training"
    ],
    "wof:name":"Lifeskills International Ltd.",
    "wof:placetype":"venue"
},
  "geometry": {"coordinates":[-1.707358,53.902607],"type":"Point"}
}