{
  "type": "Feature",
  "properties": {
    "addr:full":"Gwastadcoed, Aberangell Machynlleth Ceredigion SY20 9NF",
    "addr:postcode":"sy20 9nf",
    "iso:country":"GB",
    "sg:address":"Gwastadcoed, Aberangell",
    "sg:city":"Machynlleth",
    "sg:classifiers":[
        {
            "category":"Farming",
            "subcategory":"Livestock Farm",
            "type":"Manufacturing & Wholesale Goods"
        }
    ],
    "sg:postcode":"SY20 9NF",
    "sg:province":"Ceredigion",
    "sg:tags":[
        "others"
    ],
    "wof:name":"J Phillip Jones",
    "wof:placetype":"venue"
},
  "geometry": {"coordinates":[-3.7081038952,52.6759643555],"type":"Point"}
}