{
  "type": "Feature",
  "properties": {
    "iso:country":"GB",
    "sg:address":"8 Parton Road",
    "sg:city":"Aylesbury",
    "sg:classifiers":[
        {
            "category":"Professional",
            "subcategory":"Business Services",
            "type":"Services"
        }
    ],
    "sg:phone":"+44 1296 399466",
    "sg:postcode":"HP20 1NG",
    "sg:province":"Buckinghamshire",
    "sg:tags":[
        "bookmaker"
    ],
    "wof:name":"John Horwood",
    "wof:placetype":"venue"
},
  "geometry": {"coordinates":[-0.784769,51.813732],"type":"Point"}
}