{
  "type": "Feature",
  "properties": {
    "addr:full":"20 Plumbe Street Burnley Lancashire BB11 3AA",
    "addr:housenumber":"20",
    "addr:postcode":"bb11 3aa",
    "addr:street":"Plumbe Street",
    "iso:country":"GB",
    "sg:address":"20 Plumbe Street",
    "sg:city":"Burnley",
    "sg:classifiers":[
        {
            "category":"Military Area",
            "subcategory":"Air Force Base",
            "type":"Public Place"
        }
    ],
    "sg:phone":"+44 1282 454966",
    "sg:postcode":"BB11 3AA",
    "sg:province":"Lancashire",
    "sg:tags":[
        "taxi",
        "hire",
        "private"
    ],
    "wof:name":"Union Cabs",
    "wof:placetype":"venue"
},
  "geometry": {"coordinates":[-2.235886097,53.7884864807],"type":"Point"}
}