{
  "type": "Feature",
  "properties": {
    "iso:country":"GB",
    "sg:address":"Unit 4 Huxley Court",
    "sg:city":"Alresford",
    "sg:classifiers":[
        {
            "category":"Retail",
            "subcategory":"Auto Repair",
            "type":"Services"
        }
    ],
    "sg:postcode":"SO24 9BH",
    "sg:province":"Hampshire",
    "sg:tags":[
        "modification",
        "garage"
    ],
    "wof:name":"Phoenix Auto Services",
    "wof:placetype":"venue"
},
  "geometry": {"coordinates":[-1.152479,51.104179],"type":"Point"}
}