{
  "type": "Feature",
  "properties": {
    "iso:country":"GB",
    "sg:address":"43 Ness Road",
    "sg:city":"Southend-on-sea",
    "sg:classifiers":[
        {
            "category":"Food & Beverages",
            "subcategory":"Meat & Fish",
            "type":"Retail Goods"
        }
    ],
    "sg:phone":"+44 1702 292567",
    "sg:postcode":"SS3 9DB",
    "sg:province":"Essex",
    "sg:tags":[
        "chip"
    ],
    "wof:name":"Ness Road Fish & Chips",
    "wof:placetype":"venue"
},
  "geometry": {"coordinates":[0.782225,51.532043],"type":"Point"}
}