{
  "type": "Feature",
  "properties": {
    "addr:full":"1 William Clo Manchester Cheshire M41 9SJ",
    "addr:housenumber":"1",
    "addr:postcode":"m41 9sj",
    "addr:street":"William Clo",
    "iso:country":"GB",
    "sg:address":"1 William Clo",
    "sg:city":"Manchester",
    "sg:classifiers":[
        {
            "category":"Building & Trades",
            "subcategory":"Construction",
            "type":"Services"
        }
    ],
    "sg:phone":"+44 161 747 3212",
    "sg:postcode":"M41 9SJ",
    "sg:province":"Cheshire",
    "sg:tags":[
        "decorator",
        "painter"
    ],
    "wof:name":"Pearson R Decorators",
    "wof:placetype":"venue"
},
  "geometry": {"coordinates":[-2.3578979969,53.4468688965],"type":"Point"}
}