{
  "type": "Feature",
  "properties": {
    "addr:full":"461 South End Rd Hornchurch Essex RM12 5NX",
    "addr:housenumber":"461",
    "addr:postcode":"rm12 5nx",
    "addr:street":"South End Rd",
    "iso:country":"GB",
    "sg:address":"461 South End Rd",
    "sg:city":"Hornchurch",
    "sg:classifiers":[
        {
            "category":"Professional",
            "subcategory":"Business Services",
            "type":"Services"
        }
    ],
    "sg:phone":"+44 1708 445444",
    "sg:postcode":"RM12 5NX",
    "sg:province":"Essex",
    "sg:tags":[
        "import",
        "export",
        "agent"
    ],
    "wof:name":"Pekaes Representives",
    "wof:placetype":"venue"
},
  "geometry": {"coordinates":[0.202639997,51.5424804688],"type":"Point"}
}