{
  "type": "Feature",
  "properties": {
    "iso:country":"GB",
    "sg:address":"17-19 High St, Wath-on-dearne",
    "sg:city":"Rotherham",
    "sg:classifiers":[
        {
            "category":"Professional",
            "subcategory":"Printing & Photocopies",
            "type":"Services"
        }
    ],
    "sg:phone":"+44 1709 878091",
    "sg:postcode":"S63 7QQ",
    "sg:province":"South Yorkshire",
    "sg:tags":[
        "printer"
    ],
    "wof:name":"Fact & Fiction",
    "wof:placetype":"venue"
},
  "geometry": {"coordinates":[-1.344391,53.502651],"type":"Point"}
}