{
  "type": "Feature",
  "properties": {
    "iso:country":"GB",
    "sg:address":"9 New Street",
    "sg:city":"Ashford",
    "sg:classifiers":[
        {
            "category":"Health Services",
            "subcategory":"Clinic",
            "type":"Services"
        },
        {
            "category":"Personal",
            "type":"Services"
        },
        {
            "category":"Personal",
            "subcategory":"Nail Salon",
            "type":"Services"
        }
    ],
    "sg:phone":"+44 1233 661662",
    "sg:postcode":"TN24 8TN",
    "sg:province":"Kent",
    "sg:tags":[
        "slimming",
        "product",
        "tanning",
        "solarium",
        "private"
    ],
    "wof:name":"Ashford Diet Centre",
    "wof:placetype":"venue"
},
  "geometry": {"coordinates":[0.8687739968,51.1504554749],"type":"Point"}
}