{
  "type": "Feature",
  "properties": {
    "iso:country":"GB",
    "sg:address":"Wrights Lane",
    "sg:city":"Cradley Heath",
    "sg:classifiers":[
        {
            "category":"Education",
            "subcategory":"School",
            "type":"Public Place"
        }
    ],
    "sg:phone":"+44 1384 566598",
    "sg:postcode":"B64 6QU",
    "sg:province":"West Midlands",
    "sg:tags":[
        "college"
    ],
    "wof:name":"Heathfield Foundation School",
    "wof:placetype":"venue"
},
  "geometry": {"coordinates":[-2.0619339943,52.4778137207],"type":"Point"}
}