{
  "type": "Feature",
  "properties": {
    "iso:country":"GB",
    "sg:address":"58 Lemon Street",
    "sg:city":"Truro",
    "sg:classifiers":[
        {
            "category":"Professional",
            "type":"Services"
        }
    ],
    "sg:phone":"+44 1872 272722",
    "sg:postcode":"TR1 2PY",
    "sg:province":"Cornwall",
    "sg:tags":[
        "auctioneer"
    ],
    "wof:name":"Lodge & Thomas",
    "wof:placetype":"venue"
},
  "geometry": {"coordinates":[-5.053096,50.26104],"type":"Point"}
}