{
  "type": "Feature",
  "properties": {
    "iso:country":"GB",
    "sg:address":"254a Wendover Rd",
    "sg:city":"Aylesbury",
    "sg:classifiers":[
        {
            "category":"Professional",
            "subcategory":"Management & Consulting",
            "type":"Services"
        }
    ],
    "sg:postcode":"HP21 9PD",
    "sg:province":"Buckinghamshire",
    "sg:tags":[
        "marketing",
        "consultant"
    ],
    "wof:name":"Speakman,J J,& Associates",
    "wof:placetype":"venue"
},
  "geometry": {"coordinates":[-0.786609,51.798428],"type":"Point"}
}