{
  "type": "Feature",
  "properties": {
    "iso:country":"GB",
    "sg:address":"Balivanich Primary School, Columba Pl, Balivanich",
    "sg:city":"Isle Of Benbecula",
    "sg:classifiers":[
        {
            "category":"Education",
            "subcategory":"University",
            "type":"Public Place"
        }
    ],
    "sg:postcode":"HS7 5LS",
    "sg:province":"Eilean Siar",
    "sg:tags":[
        "medical",
        "school"
    ],
    "wof:name":"Open University (The)",
    "wof:placetype":"venue"
},
  "geometry": {"coordinates":[-7.3367199898,57.4238433838],"type":"Point"}
}