{
  "type": "Feature",
  "properties": {
    "addr:full":"Woodside, Fane Road Benfleet Essex SS7 3NH",
    "addr:postcode":"ss7 3nh",
    "addr:street":"Fane Road",
    "iso:country":"GB",
    "sg:address":"Woodside, Fane Road",
    "sg:city":"Benfleet",
    "sg:classifiers":[
        {
            "category":"Professional",
            "subcategory":"Engineering",
            "type":"Services"
        }
    ],
    "sg:phone":"+44 1268 747204",
    "sg:postcode":"SS7 3NH",
    "sg:province":"Essex",
    "sg:tags":[
        "civil",
        "engineer"
    ],
    "wof:name":"Renmore (Ssm) Ltd.",
    "wof:placetype":"venue"
},
  "geometry": {"coordinates":[0.56264,51.543316],"type":"Point"}
}