{
  "type": "Feature",
  "properties": {
    "addr:full":"Holm Wrangle Hatchery, Armanthwaite Carlisle Cumbria CA4 9QY",
    "addr:postcode":"ca4 9qy",
    "addr:street":"Armanthwaite",
    "iso:country":"GB",
    "sg:address":"Holm Wrangle Hatchery, Armanthwaite",
    "sg:city":"Carlisle",
    "sg:classifiers":[
        {
            "category":"Farming",
            "subcategory":"Farm",
            "type":"Manufacturing & Wholesale Goods"
        }
    ],
    "sg:phone":"+44 1768 896630",
    "sg:postcode":"CA4 9QY",
    "sg:province":"Cumbria",
    "sg:tags":[
        "hatchery"
    ],
    "wof:name":"Lakeland Unst Ltd.",
    "wof:placetype":"venue"
},
  "geometry": {"coordinates":[-2.75331,54.82642],"type":"Point"}
}