{
  "type": "Feature",
  "properties": {
    "addr:full":"3 West Bawtry Road Rotherham South Yorkshire S60 2XG",
    "addr:housenumber":"3",
    "addr:postcode":"s60 2xg",
    "addr:street":"West Bawtry Road",
    "iso:country":"GB",
    "sg:address":"3 West Bawtry Road",
    "sg:city":"Rotherham",
    "sg:classifiers":[
        {
            "category":"Retail",
            "subcategory":"Auto Repair",
            "type":"Services"
        }
    ],
    "sg:phone":"+44 1709 370213",
    "sg:postcode":"S60 2XG",
    "sg:province":"South Yorkshire",
    "sg:tags":[
        "garage"
    ],
    "wof:name":"Cymac Damon Group",
    "wof:placetype":"venue"
},
  "geometry": {"coordinates":[-1.3612920046,53.4096832275],"type":"Point"}
}