{
  "type": "Feature",
  "properties": {
    "iso:country":"GB",
    "sg:address":"46 East Grn, West Auckland",
    "sg:city":"Bishop Auckland",
    "sg:classifiers":[
        {
            "category":"Professional",
            "subcategory":"Business Services",
            "type":"Services"
        },
        {
            "category":"Shopping",
            "type":"Retail Goods"
        }
    ],
    "sg:phone":"+44 1388 833678",
    "sg:postcode":"DL14 9HJ",
    "sg:province":"Durham",
    "sg:tags":[
        "merchant",
        "agricultural"
    ],
    "wof:name":"Hall Shaw Farm Supplies Ltd",
    "wof:placetype":"venue"
},
  "geometry": {"coordinates":[-1.7217390537,54.6317749023],"type":"Point"}
}