{
  "type": "Feature",
  "properties": {
    "addr:full":"Sharsted Hill, Newnham Sittingbourne Kent ME9 0JX",
    "addr:postcode":"me9 0jx",
    "addr:street":"Sharsted Hill",
    "iso:country":"GB",
    "sg:address":"Sharsted Hill, Newnham",
    "sg:city":"Sittingbourne",
    "sg:classifiers":[
        {
            "category":"Home & Garden",
            "subcategory":"Home Furnishings",
            "type":"Retail Goods"
        }
    ],
    "sg:phone":"+44 1795 890820",
    "sg:postcode":"ME9 0JX",
    "sg:province":"Kent",
    "sg:tags":[
        "patio",
        "furniture"
    ],
    "wof:name":"Stable Woodcrafts",
    "wof:placetype":"venue"
},
  "geometry": {"coordinates":[0.800333,51.284489],"type":"Point"}
}