{
  "type": "Feature",
  "properties": {
    "iso:country":"GB",
    "sg:address":"12 Royal Terr",
    "sg:city":"Glasgow",
    "sg:classifiers":[
        {
            "category":"Organizations",
            "subcategory":"Political Organization",
            "type":"Services"
        }
    ],
    "sg:postcode":"G3 7NY",
    "sg:province":"Glasgow City",
    "sg:tags":[
        "party"
    ],
    "wof:name":"Anniesland Conservative & Unionist Assoc",
    "wof:placetype":"venue"
},
  "geometry": {"coordinates":[-4.282297,55.866665],"type":"Point"}
}