{
  "type": "Feature",
  "properties": {
    "addr:full":"11 Mayfield Gro Harrogate North Yorkshire HG1 5HD",
    "addr:housenumber":"11",
    "addr:postcode":"hg1 5hd",
    "addr:street":"Mayfield Gro",
    "iso:country":"GB",
    "sg:address":"11 Mayfield Gro",
    "sg:city":"Harrogate",
    "sg:classifiers":[
        {
            "category":"Shopping",
            "subcategory":"Books",
            "type":"Retail Goods"
        }
    ],
    "sg:phone":"+44 1423 505817",
    "sg:postcode":"HG1 5HD",
    "sg:province":"North Yorkshire",
    "sg:tags":[
        "second-hand"
    ],
    "wof:name":"Bookstop Bookshop",
    "wof:placetype":"venue"
},
  "geometry": {"coordinates":[-1.5378420353,53.9970397949],"type":"Point"}
}