{
  "type": "Feature",
  "properties": {
    "addr:full":"201 Penncricket Lane Rowley Regis West Midlands B65 0PF",
    "addr:housenumber":"201",
    "addr:postcode":"b65 0pf",
    "addr:street":"Penncricket Lane",
    "iso:country":"GB",
    "sg:address":"201 Penncricket Lane",
    "sg:city":"Rowley Regis",
    "sg:classifiers":[
        {
            "category":"Utilities",
            "subcategory":"Refuse",
            "type":"Services"
        }
    ],
    "sg:phone":"+44 7961 377222",
    "sg:postcode":"B65 0PF",
    "sg:province":"West Midlands",
    "sg:tags":[
        "skip",
        "hire"
    ],
    "wof:name":"Move Waste",
    "wof:placetype":"venue"
},
  "geometry": {"coordinates":[-2.028098,52.482777],"type":"Point"}
}