{
  "type": "Feature",
  "properties": {
    "iso:country":"GB",
    "sg:address":"31 Taywood Road, Hungerhill",
    "sg:city":"Bolton",
    "sg:classifiers":[
        {
            "category":"Professional",
            "subcategory":"Engineering",
            "type":"Services"
        }
    ],
    "sg:phone":"+44 1942 812005",
    "sg:postcode":"BL3 4SJ",
    "sg:province":"Lancashire",
    "sg:tags":[
        "contractor",
        "electrical",
        "engineer"
    ],
    "wof:name":"Dennis Finn & Sons",
    "wof:placetype":"venue"
},
  "geometry": {"coordinates":[-2.491644,53.558422],"type":"Point"}
}