{
  "type": "Feature",
  "properties": {
    "addr:full":"6 Allington Crescent Lewes East Sussex BN8 4NT",
    "addr:housenumber":"6",
    "addr:postcode":"bn8 4nt",
    "addr:street":"Allington Crescent",
    "iso:country":"GB",
    "sg:address":"6 Allington Crescent",
    "sg:city":"Lewes",
    "sg:classifiers":[
        {
            "category":"Professional",
            "subcategory":"Employment Agencies",
            "type":"Services"
        }
    ],
    "sg:phone":"+44 1825 724497",
    "sg:postcode":"BN8 4NT",
    "sg:province":"East Sussex",
    "sg:tags":[
        "consultant"
    ],
    "wof:name":"Specialized Driving Force Ltd.",
    "wof:placetype":"venue"
},
  "geometry": {"coordinates":[0.0099360002,50.9714126587],"type":"Point"}
}