{
  "type": "Feature",
  "properties": {
    "iso:country":"GB",
    "sg:address":"Slate Mill",
    "sg:city":"Haverfordwest",
    "sg:classifiers":[
        {
            "category":"Farming",
            "subcategory":"Livestock Farm",
            "type":"Manufacturing & Wholesale Goods"
        }
    ],
    "sg:phone":"+44 1646 636258",
    "sg:postcode":"SA62 3QR",
    "sg:province":"Pembrokeshire",
    "sg:tags":[
        "others"
    ],
    "wof:name":"J E Davies",
    "wof:placetype":"venue"
},
  "geometry": {"coordinates":[-5.158780098,51.7382583618],"type":"Point"}
}