{
  "type": "Feature",
  "properties": {
    "addr:full":"17 Manchester Road Warrington Cheshire WA1 3AB",
    "addr:housenumber":"17",
    "addr:postcode":"wa1 3ab",
    "addr:street":"Manchester Road",
    "iso:country":"GB",
    "sg:address":"17 Manchester Road",
    "sg:city":"Warrington",
    "sg:classifiers":[
        {
            "category":"Personal",
            "subcategory":"Beauty Salon",
            "type":"Services"
        }
    ],
    "sg:phone":"+44 1925 234342",
    "sg:postcode":"WA1 3AB",
    "sg:province":"Cheshire",
    "sg:tags":[
        "unisex",
        "hairdresser"
    ],
    "wof:name":"Splitz Hair Studio",
    "wof:placetype":"venue"
},
  "geometry": {"coordinates":[-2.5800569057,53.3927841187],"type":"Point"}
}