{
  "type": "Feature",
  "properties": {
    "iso:country":"GB",
    "sg:address":"Unit 5 Spring Rise, Falconer Road",
    "sg:city":"Haverhill",
    "sg:classifiers":[
        {
            "category":"Professional",
            "subcategory":"Printing & Photocopies",
            "type":"Services"
        }
    ],
    "sg:phone":"+44 1440 706866",
    "sg:postcode":"CB9 7XU",
    "sg:province":"Essex",
    "sg:tags":[
        "printer"
    ],
    "wof:name":"Brimsden Colour & Commercial Printers Ltd.",
    "wof:placetype":"venue"
},
  "geometry": {"coordinates":[0.435798,52.085129],"type":"Point"}
}