{
  "type": "Feature",
  "properties": {
    "iso:country":"GB",
    "sg:address":"122 Bordesley Green",
    "sg:city":"Birmingham",
    "sg:classifiers":[
        {
            "category":"Community Center",
            "type":"Public Place"
        }
    ],
    "sg:phone":"+44 121 766 6371",
    "sg:postcode":"B9 4TS",
    "sg:province":"West Midlands",
    "sg:tags":[
        "centre"
    ],
    "wof:name":"Bordesley Green Islamic Centre",
    "wof:placetype":"venue"
},
  "geometry": {"coordinates":[-1.856201,52.47979],"type":"Point"}
}