{
  "type": "Feature",
  "properties": {
    "addr:full":"18 Burlington St Chesterfield Derbyshire S40 1RR",
    "addr:housenumber":"18",
    "addr:postcode":"s40 1rr",
    "addr:street":"Burlington St",
    "iso:country":"GB",
    "sg:address":"18 Burlington St",
    "sg:city":"Chesterfield",
    "sg:classifiers":[
        {
            "category":"Communications",
            "type":"Services"
        }
    ],
    "sg:phone":"+44 1246 205040",
    "sg:postcode":"S40 1RR",
    "sg:province":"Derbyshire",
    "sg:tags":[
        "telecommunication"
    ],
    "wof:name":"Phones 4 U",
    "wof:placetype":"venue"
},
  "geometry": {"coordinates":[-1.4267439842,53.2360267639],"type":"Point"}
}