{
  "type": "Feature",
  "properties": {
    "iso:country":"GB",
    "sg:address":"45 Turner St",
    "sg:city":"Whitechapel",
    "sg:classifiers":[
        {
            "category":"Building & Trades",
            "subcategory":"Construction",
            "type":"Services"
        }
    ],
    "sg:phone":"+44 20 7265 9494",
    "sg:postcode":"E1 2AU",
    "sg:province":"Greater London",
    "sg:tags":[
        "builder"
    ],
    "wof:name":"Prideglen Building Services Ltd",
    "wof:placetype":"venue"
},
  "geometry": {"coordinates":[-0.06077,51.516087],"type":"Point"}
}