{
  "type": "Feature",
  "properties": {
    "iso:country":"GB",
    "sg:address":"439-443 Penistone Road",
    "sg:city":"Sheffield",
    "sg:classifiers":[
        {
            "category":"Autos & Motor Vehicles",
            "subcategory":"Motorcycle Sales",
            "type":"Retail Goods"
        }
    ],
    "sg:phone":"+44 114 285 5580",
    "sg:postcode":"S6 2FL",
    "sg:province":"South Yorkshire",
    "wof:name":"Hillsborough Motor Cycles",
    "wof:placetype":"venue"
},
  "geometry": {"coordinates":[-1.4884370565,53.3982772827],"type":"Point"}
}