{
  "type": "Feature",
  "properties": {
    "addr:full":"Whiteways, White Notley Witham Essex CM8 1SE",
    "addr:postcode":"cm8 1se",
    "addr:street":"Witham",
    "iso:country":"GB",
    "sg:address":"Whiteways, White Notley",
    "sg:city":"Witham",
    "sg:classifiers":[
        {
            "category":"Professional",
            "subcategory":"Management & Consulting",
            "type":"Services"
        }
    ],
    "sg:postcode":"CM8 1SE",
    "sg:province":"Essex",
    "sg:tags":[
        "consultant",
        "business"
    ],
    "wof:name":"Gwynne-James Associates",
    "wof:placetype":"venue"
},
  "geometry": {"coordinates":[0.589114,51.836437],"type":"Point"}
}