{
  "type": "Feature",
  "properties": {
    "iso:country":"GB",
    "sg:address":"East Donington St",
    "sg:city":"Darvel",
    "sg:classifiers":[
        {
            "category":"Health Services",
            "subcategory":"Doctor",
            "type":"Services"
        }
    ],
    "sg:phone":"+44 1560 320205",
    "sg:postcode":"KA17 0JR",
    "sg:province":"East Ayrshire",
    "sg:tags":[
        "practitioners"
    ],
    "wof:name":"Robertson, M A",
    "wof:placetype":"venue"
},
  "geometry": {"coordinates":[-4.2801990509,55.6098251343],"type":"Point"}
}