{
  "type": "Feature",
  "properties": {
    "addr:full":"618 High Lane Stoke-on-trent Staffordshire ST6 7JW",
    "addr:housenumber":"618",
    "addr:postcode":"st6 7jw",
    "addr:street":"High Lane",
    "iso:country":"GB",
    "sg:address":"618 High Lane",
    "sg:city":"Stoke-on-trent",
    "sg:classifiers":[
        {
            "category":"Food & Beverages",
            "subcategory":"Bakery",
            "type":"Retail Goods"
        }
    ],
    "sg:phone":"+44 1782 822615",
    "sg:postcode":"ST6 7JW",
    "sg:province":"Staffordshire",
    "sg:tags":[
        "baker"
    ],
    "wof:name":"Goodies Bakeshop",
    "wof:placetype":"venue"
},
  "geometry": {"coordinates":[-2.1902270317,53.0617103577],"type":"Point"}
}