{
  "type": "Feature",
  "properties": {
    "iso:country":"GB",
    "sg:address":"Gustard Wood, Wheathampstead",
    "sg:city":"St Albans",
    "sg:classifiers":[
        {
            "category":"Bars & Pubs",
            "type":"Food & Drink"
        }
    ],
    "sg:phone":"+44 1582 832165",
    "sg:postcode":"AL4 8LA",
    "sg:province":"Hertfordshire",
    "sg:tags":[
        "pubs",
        "inn"
    ],
    "wof:name":"The Cross Keys",
    "wof:placetype":"venue"
},
  "geometry": {"coordinates":[-0.2992140055,51.8342514038],"type":"Point"}
}