{
  "type": "Feature",
  "properties": {
    "iso:country":"GB",
    "sg:address":"202 Bloomfield Road",
    "sg:city":"Bristol",
    "sg:classifiers":[
        {
            "category":"Personal",
            "type":"Services"
        }
    ],
    "sg:phone":"+44 117 977 7660",
    "sg:postcode":"BS4 3QU",
    "sg:province":"City of Bristol",
    "sg:tags":[
        "tailor"
    ],
    "wof:name":"Antoinette's",
    "wof:placetype":"venue"
},
  "geometry": {"coordinates":[-2.5520889759,51.4453239441],"type":"Point"}
}