{
  "type": "Feature",
  "properties": {
    "addr:full":"Blackwater Marina, Marine Pde, Maylandsea Chelmsford Essex CM3 6AN",
    "addr:postcode":"cm3 6an",
    "iso:country":"GB",
    "sg:address":"Blackwater Marina, Marine Pde, Maylandsea",
    "sg:city":"Chelmsford",
    "sg:classifiers":[
        {
            "category":"Building & Trades",
            "subcategory":"Landscaping Services",
            "type":"Services"
        },
        {
            "category":"Manufacturing",
            "subcategory":"Retail Goods",
            "type":"Manufacturing & Wholesale Goods"
        }
    ],
    "sg:postcode":"CM3 6AN",
    "sg:province":"Essex",
    "sg:tags":[
        "horticultural",
        "chandler",
        "consultant"
    ],
    "wof:name":"Fentum,J,",
    "wof:placetype":"venue"
},
  "geometry": {"coordinates":[0.765775,51.679375],"type":"Point"}
}