{
  "type": "Feature",
  "properties": {
    "iso:country":"GB",
    "sg:address":"1 Auburn Avenue, Bredbury",
    "sg:city":"Stockport",
    "sg:classifiers":[
        {
            "category":"Health Services",
            "subcategory":"Doctor",
            "type":"Services"
        }
    ],
    "sg:phone":"+44 161 494 8884",
    "sg:postcode":"SK6 2AH",
    "sg:province":"Cheshire",
    "sg:tags":[
        "practitioners"
    ],
    "wof:name":"M H Armstrong & R S Beardsell",
    "wof:placetype":"venue"
},
  "geometry": {"coordinates":[-2.113557,53.422874],"type":"Point"}
}