{
  "type": "Feature",
  "properties": {
    "addr:full":"Unit C 105 Rosemount Place Aberdeen Aberdeen City AB252YG",
    "addr:housenumber":"unit c 105",
    "addr:postcode":"ab252yg",
    "addr:street":"Rosemount Place",
    "iso:country":"GB",
    "sg:address":"Unit C 105 Rosemount Place",
    "sg:city":"Aberdeen",
    "sg:classifiers":[
        {
            "category":"Home & Garden",
            "subcategory":"Home Furnishings",
            "type":"Retail Goods"
        }
    ],
    "sg:phone":"+44 1224 625552",
    "sg:postcode":"AB252YG",
    "sg:province":"Aberdeen City",
    "sg:tags":[
        "furnishers",
        "planner",
        "kitchen"
    ],
    "wof:name":"Elegant Homes Interiors",
    "wof:placetype":"venue"
},
  "geometry": {"coordinates":[-2.106789,57.15382],"type":"Point"}
}