{
  "type": "Feature",
  "properties": {
    "addr:full":"Bath Street Leamington Spa Warwickshire CV31 3AF",
    "addr:postcode":"cv31 3af",
    "addr:street":"Bath Street",
    "iso:country":"GB",
    "sg:address":"Bath Street",
    "sg:city":"Leamington Spa",
    "sg:classifiers":[
        {
            "category":"Bars & Pubs",
            "type":"Food & Drink"
        }
    ],
    "sg:phone":"+44 1926 425727",
    "sg:postcode":"CV31 3AF",
    "sg:province":"Warwickshire",
    "sg:tags":[
        "pubs",
        "inn"
    ],
    "wof:name":"The Jugg & Jester",
    "wof:placetype":"venue"
},
  "geometry": {"coordinates":[-1.5330439806,52.2855911255],"type":"Point"}
}