{
  "type": "Feature",
  "properties": {
    "addr:full":"23 Hall Gate Doncaster South Yorkshire DN1 3NA",
    "addr:housenumber":"23",
    "addr:postcode":"dn1 3na",
    "addr:street":"Hall Gate",
    "iso:country":"GB",
    "sg:address":"23 Hall Gate",
    "sg:city":"Doncaster",
    "sg:classifiers":[
        {
            "category":"Personal",
            "subcategory":"Beauty Salon",
            "type":"Services"
        }
    ],
    "sg:phone":"+44 1302 360870",
    "sg:postcode":"DN1 3NA",
    "sg:province":"South Yorkshire",
    "sg:tags":[
        "unisex",
        "hairdresser"
    ],
    "wof:name":"The Cutting Co",
    "wof:placetype":"venue"
},
  "geometry": {"coordinates":[-1.1299990416,53.5223693848],"type":"Point"}
}