{
  "type": "Feature",
  "properties": {
    "addr:full":"104 Woodlands Road St Helens Lancashire WA11 9AQ",
    "addr:housenumber":"104",
    "addr:postcode":"wa11 9aq",
    "addr:street":"Woodlands Road",
    "iso:country":"GB",
    "sg:address":"104 Woodlands Road",
    "sg:city":"St Helens",
    "sg:classifiers":[
        {
            "category":"Personal",
            "subcategory":"Beauty Salon",
            "type":"Services"
        }
    ],
    "sg:postcode":"WA11 9AQ",
    "sg:province":"Lancashire",
    "sg:tags":[
        "unisex",
        "hairdresser"
    ],
    "wof:name":"Hair & Co",
    "wof:placetype":"venue"
},
  "geometry": {"coordinates":[-2.723845005,53.4695587158],"type":"Point"}
}