{
  "type": "Feature",
  "properties": {
    "addr:full":"186-188 High Street Scunthorpe Lincolnshire DN15 6EA",
    "addr:housenumber":"186-188",
    "addr:postcode":"dn15 6ea",
    "addr:street":"High Street",
    "iso:country":"GB",
    "sg:address":"186-188 High Street",
    "sg:city":"Scunthorpe",
    "sg:classifiers":[
        {
            "category":"Home & Garden",
            "subcategory":"Home Furnishings",
            "type":"Retail Goods"
        }
    ],
    "sg:phone":"+44 1724 866649",
    "sg:postcode":"DN15 6EA",
    "sg:province":"Lincolnshire",
    "sg:tags":[
        "beds",
        "bedding",
        "blanket"
    ],
    "wof:name":"The Bed Shop",
    "wof:placetype":"venue"
},
  "geometry": {"coordinates":[-0.653157,53.591122],"type":"Point"}
}