{
  "type": "Feature",
  "properties": {
    "addr:full":"Cargo Only, Building 559 Shoreham Rd West Hounslow Greater London TW6 3NQ",
    "addr:housenumber":"559",
    "addr:postcode":"tw6 3nq",
    "addr:street":"Shoreham Rd West",
    "iso:country":"GB",
    "sg:address":"Cargo Only, Building 559 Shoreham Rd West",
    "sg:city":"Hounslow",
    "sg:classifiers":[
        {
            "category":"Freight",
            "type":"Transportation"
        }
    ],
    "sg:phone":"+44 20 8754 9080",
    "sg:postcode":"TW6 3NQ",
    "sg:province":"Greater London",
    "sg:tags":[
        "cargo",
        "handling"
    ],
    "wof:name":"Ethiopian Airlines",
    "wof:placetype":"venue"
},
  "geometry": {"coordinates":[-0.4707100093,51.4624404907],"type":"Point"}
}