{
  "type": "Feature",
  "properties": {
    "iso:country":"GB",
    "sg:address":"70 Chapel Street",
    "sg:city":"Southport",
    "sg:classifiers":[
        {
            "category":"Shopping",
            "subcategory":"Mobile Phones",
            "type":"Retail Goods"
        }
    ],
    "sg:phone":"+44 1704 543232",
    "sg:postcode":"PR8 1BZ",
    "sg:province":"Lancashire",
    "sg:tags":[
        "supplier"
    ],
    "wof:name":"The Link",
    "wof:placetype":"venue"
},
  "geometry": {"coordinates":[-3.002938,53.647552],"type":"Point"}
}