{
  "type": "Feature",
  "properties": {
    "addr:full":"Shop 4 Bridle Road Stafford Staffordshire ST17 0QD",
    "addr:housenumber":"shop 4",
    "addr:postcode":"st17 0qd",
    "addr:street":"Bridle Road",
    "iso:country":"GB",
    "sg:address":"Shop 4 Bridle Road",
    "sg:city":"Stafford",
    "sg:classifiers":[
        {
            "category":"Personal",
            "subcategory":"Beauty Salon",
            "type":"Services"
        }
    ],
    "sg:phone":"+44 1785 661733",
    "sg:postcode":"ST17 0QD",
    "sg:province":"Staffordshire",
    "sg:tags":[
        "unisex",
        "hairdresser"
    ],
    "wof:name":"Francesco Group Holdings",
    "wof:placetype":"venue"
},
  "geometry": {"coordinates":[-2.07653,52.784592],"type":"Point"}
}