{
  "type": "Feature",
  "properties": {
    "iso:country":"GB",
    "sg:address":"Tor View, Rousdown Road",
    "sg:city":"Torquay",
    "sg:classifiers":[
        {
            "category":"Travel",
            "subcategory":"Hotels & Motels",
            "type":"Entertainment"
        }
    ],
    "sg:phone":"+44 1803 606060",
    "sg:postcode":"TQ2 6PB",
    "sg:province":"Devon",
    "sg:tags":[
        "self",
        "catering"
    ],
    "wof:name":"Torview Holiday Flats",
    "wof:placetype":"venue"
},
  "geometry": {"coordinates":[-3.545731,50.463886],"type":"Point"}
}