{
  "type": "Feature",
  "properties": {
    "addr:full":"16 Apollo Studios, Charlton Kings Rd London Greater London NW5 2SB",
    "addr:housenumber":"16",
    "addr:postcode":"nw5 2sb",
    "addr:street":"Charlton Kings Rd",
    "iso:country":"GB",
    "sg:address":"16 Apollo Studios, Charlton Kings Rd",
    "sg:city":"London",
    "sg:classifiers":[
        {
            "category":"Communications",
            "subcategory":"Newspaper",
            "type":"Services"
        }
    ],
    "sg:postcode":"NW5 2SB",
    "sg:province":"Greater London",
    "sg:tags":[
        "magazine"
    ],
    "wof:name":"Kato Communications Ltd",
    "wof:placetype":"venue"
},
  "geometry": {"coordinates":[-0.1319600046,51.5510292053],"type":"Point"}
}