{
  "type": "Feature",
  "properties": {
    "addr:full":"31-33 Cooks Rd Liverpool Merseyside L23 2TB",
    "addr:housenumber":"31-33",
    "addr:postcode":"l23 2tb",
    "addr:street":"Cooks Rd",
    "iso:country":"GB",
    "sg:address":"31-33 Cooks Rd",
    "sg:city":"Liverpool",
    "sg:classifiers":[
        {
            "category":"Food & Beverages",
            "subcategory":"Liquor & Beverages",
            "type":"Retail Goods"
        }
    ],
    "sg:phone":"+44 151 924 3504",
    "sg:postcode":"L23 2TB",
    "sg:province":"Merseyside",
    "sg:tags":[
        "beer",
        "spirit",
        "wines"
    ],
    "wof:name":"Thresher",
    "wof:placetype":"venue"
},
  "geometry": {"coordinates":[-3.0284030437,53.4931297302],"type":"Point"}
}