{
  "type": "Feature",
  "properties": {
    "iso:country":"GB",
    "sg:address":"72 Craven St",
    "sg:city":"Northampton",
    "sg:classifiers":[
        {
            "category":"Building & Trades",
            "subcategory":"Electrical",
            "type":"Services"
        }
    ],
    "sg:phone":"+44 1604 637924",
    "sg:postcode":"NN1 3EZ",
    "sg:province":"Northamptonshire",
    "sg:tags":[
        "consultant",
        "lighting"
    ],
    "wof:name":"General Lighting Services Ltd",
    "wof:placetype":"venue"
},
  "geometry": {"coordinates":[-0.891237,52.243988],"type":"Point"}
}