{
  "type": "Feature",
  "properties": {
    "addr:full":"35 Chapel Street, Stanground Peterborough Cambridgeshire PE2 8JN",
    "addr:housenumber":"35",
    "addr:postcode":"pe2 8jn",
    "addr:street":"Chapel Street",
    "iso:country":"GB",
    "sg:address":"35 Chapel Street, Stanground",
    "sg:city":"Peterborough",
    "sg:classifiers":[
        {
            "category":"Building & Trades",
            "subcategory":"Construction",
            "type":"Services"
        }
    ],
    "sg:phone":"+44 1733 345732",
    "sg:postcode":"PE2 8JN",
    "sg:province":"Cambridgeshire",
    "sg:tags":[
        "builder"
    ],
    "wof:name":"Carter Steve Building Contractor",
    "wof:placetype":"venue"
},
  "geometry": {"coordinates":[-0.226289,52.559364],"type":"Point"}
}