{
  "type": "Feature",
  "properties": {
    "addr:full":"24 Otley Rd, Guiseley Leeds West Yorkshire LS20 8AH",
    "addr:housenumber":"24",
    "addr:postcode":"ls20 8ah",
    "addr:street":"Otley Rd",
    "iso:country":"GB",
    "sg:address":"24 Otley Rd, Guiseley",
    "sg:city":"Leeds",
    "sg:classifiers":[
        {
            "category":"Shopping",
            "subcategory":"News",
            "type":"Retail Goods"
        }
    ],
    "sg:postcode":"LS20 8AH",
    "sg:province":"West Yorkshire",
    "sg:tags":[
        "newsagent"
    ],
    "wof:name":"Davies,Christopher,",
    "wof:placetype":"venue"
},
  "geometry": {"coordinates":[-1.7104439735,53.8731498718],"type":"Point"}
}