{
  "type": "Feature",
  "properties": {
    "addr:full":"Unit 2 Kensington Road, Vauxhal Industrial Estate Canterbury Kent CT1 1QZ",
    "addr:housenumber":"unit 2",
    "addr:postcode":"ct1 1qz",
    "addr:street":"Kensington Road Vauxhal Industrial Estate",
    "iso:country":"GB",
    "sg:address":"Unit 2 Kensington Road, Vauxhal Industrial Estate",
    "sg:city":"Canterbury",
    "sg:classifiers":[
        {
            "category":"Autos & Motor Vehicles",
            "subcategory":"Auto Supplies",
            "type":"Retail Goods"
        }
    ],
    "sg:postcode":"CT1 1QZ",
    "sg:province":"Kent",
    "sg:tags":[
        "towbars"
    ],
    "wof:name":"U K Towbars Ltd.",
    "wof:placetype":"venue"
},
  "geometry": {"coordinates":[1.10179,51.294235],"type":"Point"}
}