{
  "type": "Feature",
  "properties": {
    "iso:country":"GB",
    "sg:address":"2 Loanhead Avenue",
    "sg:city":"Grangemouth",
    "sg:classifiers":[
        {
            "category":"Food & Beverages",
            "subcategory":"Groceries & Convenience Stores",
            "type":"Retail Goods"
        }
    ],
    "sg:phone":"+44 1324 474128",
    "sg:postcode":"FK3 9ED",
    "sg:province":"Falkirk",
    "wof:name":"Mohammed Arshad",
    "wof:placetype":"venue"
},
  "geometry": {"coordinates":[-3.710412,56.009895],"type":"Point"}
}