{
  "type": "Feature",
  "properties": {
    "iso:country":"GB",
    "sg:address":"Unit L, Rose Business Estate, Marlow Bottom",
    "sg:city":"Marlow",
    "sg:classifiers":[
        {
            "category":"Ice Cream",
            "type":"Food & Drink"
        }
    ],
    "sg:phone":"+44 1628 482844",
    "sg:postcode":"SL7 3ND",
    "sg:province":"Berkshire",
    "sg:tags":[
        "mnfr"
    ],
    "wof:name":"Dove Desserts",
    "wof:placetype":"venue"
},
  "geometry": {"coordinates":[-0.77731,51.586899],"type":"Point"}
}