{
  "type": "Feature",
  "properties": {
    "addr:full":"38 Meyrick Rd Willesden Greater London NW10 2EJ",
    "addr:housenumber":"38",
    "addr:postcode":"nw10 2ej",
    "addr:street":"Meyrick Rd",
    "iso:country":"GB",
    "sg:address":"38 Meyrick Rd",
    "sg:city":"Willesden",
    "sg:classifiers":[
        {
            "category":"Health Services",
            "subcategory":"Nursing And Care Facility",
            "type":"Services"
        }
    ],
    "sg:phone":"+44 20 8830 3560",
    "sg:postcode":"NW10 2EJ",
    "sg:province":"Greater London",
    "sg:tags":[
        "agency"
    ],
    "wof:name":"London & General Employment Services",
    "wof:placetype":"venue"
},
  "geometry": {"coordinates":[-0.240019,51.549416],"type":"Point"}
}