{
  "type": "Feature",
  "properties": {
    "addr:full":"Care Of Caldergrove House, Caldergrove, Cambusland Glasgow South Lanarkshire G72 8YA",
    "addr:postcode":"g72 8ya",
    "iso:country":"GB",
    "sg:address":"Care Of Caldergrove House, Caldergrove, Cambusland",
    "sg:city":"Glasgow",
    "sg:classifiers":[
        {
            "category":"Professional",
            "subcategory":"Engineering",
            "type":"Services"
        }
    ],
    "sg:phone":"+44 1698 824442",
    "sg:postcode":"G72 8YA",
    "sg:province":"South Lanarkshire",
    "sg:tags":[
        "civil",
        "engineer"
    ],
    "wof:name":"Advance Contracts Ltd.",
    "wof:placetype":"venue"
},
  "geometry": {"coordinates":[-4.1713118553,55.806842804],"type":"Point"}
}