{
  "type": "Feature",
  "properties": {
    "addr:full":"17 Crosby Road South Liverpool Merseyside L22 1RG",
    "addr:housenumber":"17",
    "addr:postcode":"l22 1rg",
    "addr:street":"Crosby Road South",
    "iso:country":"GB",
    "sg:address":"17 Crosby Road South",
    "sg:city":"Liverpool",
    "sg:classifiers":[
        {
            "category":"Real Estate",
            "subcategory":"Surveying",
            "type":"Services"
        }
    ],
    "sg:phone":"+44 151 928 9500",
    "sg:postcode":"L22 1RG",
    "sg:province":"Merseyside",
    "sg:tags":[
        "surveyor",
        "quantity"
    ],
    "wof:name":"S J Nicholson & Associates",
    "wof:placetype":"venue"
},
  "geometry": {"coordinates":[-3.0199100971,53.4709854126],"type":"Point"}
}