{
  "type": "Feature",
  "properties": {
    "addr:full":"Coldfield Drive, Oakenshaw Redditch Warwickshire B98 7ST",
    "addr:postcode":"b98 7st",
    "addr:street":"Coldfield Drive",
    "iso:country":"GB",
    "sg:address":"Coldfield Drive, Oakenshaw",
    "sg:city":"Redditch",
    "sg:classifiers":[
        {
            "category":"Fast Food",
            "type":"Food & Drink"
        }
    ],
    "sg:phone":"+44 1527 404534",
    "sg:postcode":"B98 7ST",
    "sg:province":"Warwickshire",
    "sg:tags":[
        "away",
        "take"
    ],
    "wof:name":"Mcdonald's Oakenshaw",
    "wof:placetype":"venue"
},
  "geometry": {"coordinates":[-1.9339289665,52.2995300293],"type":"Point"}
}