{
  "type": "Feature",
  "properties": {
    "addr:full":"709 Green Lanes, Winchmore Hill London Greater London N21 3RS",
    "addr:housenumber":"709",
    "addr:postcode":"n21 3rs",
    "addr:street":"Green Lanes",
    "iso:country":"GB",
    "sg:address":"709 Green Lanes, Winchmore Hill",
    "sg:city":"London",
    "sg:classifiers":[
        {
            "category":"Home & Garden",
            "subcategory":"Household Appliances",
            "type":"Retail Goods"
        }
    ],
    "sg:phone":"+44 20 8360 4520",
    "sg:postcode":"N21 3RS",
    "sg:province":"Greater London",
    "sg:tags":[
        "electrical"
    ],
    "wof:name":"Porter Services",
    "wof:placetype":"venue"
},
  "geometry": {"coordinates":[-0.0967769995,51.6305923462],"type":"Point"}
}