{
  "type": "Feature",
  "properties": {
    "iso:country":"GB",
    "sg:address":"21 Craigmead Terrace, Cardenden",
    "sg:city":"Lochgelly",
    "sg:classifiers":[
        {
            "category":"Professional",
            "subcategory":"Advertising",
            "type":"Services"
        },
        {
            "category":"Manufacturing",
            "subcategory":"Signs",
            "type":"Manufacturing & Wholesale Goods"
        }
    ],
    "sg:phone":"+44 1592 721944",
    "sg:postcode":"KY5 0JT",
    "sg:province":"Fife",
    "sg:tags":[
        "writer",
        "signwriters"
    ],
    "wof:name":"Stylistix Signs",
    "wof:placetype":"venue"
},
  "geometry": {"coordinates":[-3.259311,56.1488],"type":"Point"}
}