{
  "type": "Feature",
  "properties": {
    "addr:full":"104 Bute Street Cardiff Cardiff CF10 5AD",
    "addr:housenumber":"104",
    "addr:postcode":"cf10 5ad",
    "addr:street":"Bute Street",
    "iso:country":"GB",
    "sg:address":"104 Bute Street",
    "sg:city":"Cardiff",
    "sg:classifiers":[
        {
            "category":"Personal",
            "subcategory":"Beauty Salon",
            "type":"Services"
        }
    ],
    "sg:postcode":"CF10 5AD",
    "sg:province":"Cardiff",
    "sg:tags":[
        "unisex",
        "hairdresser"
    ],
    "wof:name":"Shadows of Tasha's",
    "wof:placetype":"venue"
},
  "geometry": {"coordinates":[-3.166123,51.465027],"type":"Point"}
}