{
  "type": "Feature",
  "properties": {
    "iso:country":"GB",
    "sg:address":"20 Croft Road",
    "sg:city":"Blyth",
    "sg:classifiers":[
        {
            "category":"Professional",
            "subcategory":"Accounting & Tax Preparation",
            "type":"Services"
        }
    ],
    "sg:phone":"+44 1670 365414",
    "sg:postcode":"NE24 2JL",
    "sg:province":"Northumberland",
    "sg:tags":[
        "accountant"
    ],
    "wof:name":"Norman Gray Accounts",
    "wof:placetype":"venue"
},
  "geometry": {"coordinates":[-1.509047,55.126225],"type":"Point"}
}