{
  "type": "Feature",
  "properties": {
    "addr:full":"44 Elmshurst Gardens Tonbridge Kent TN10 3QU",
    "addr:housenumber":"44",
    "addr:postcode":"tn10 3qu",
    "addr:street":"Elmshurst Gardens",
    "iso:country":"GB",
    "sg:address":"44 Elmshurst Gardens",
    "sg:city":"Tonbridge",
    "sg:classifiers":[
        {
            "category":"Building & Trades",
            "subcategory":"Landscaping Services",
            "type":"Services"
        }
    ],
    "sg:postcode":"TN10 3QU",
    "sg:province":"Kent",
    "sg:tags":[
        "preservation",
        "timber"
    ],
    "wof:name":"Preservatim Ltd.",
    "wof:placetype":"venue"
},
  "geometry": {"coordinates":[0.280577004,51.2197761536],"type":"Point"}
}