{
  "type": "Feature",
  "properties": {
    "iso:country":"GB",
    "sg:address":"350 Alcester Road, Moseley",
    "sg:city":"Birmingham",
    "sg:classifiers":[
        {
            "category":"Retail",
            "subcategory":"Funeral Services",
            "type":"Services"
        }
    ],
    "sg:phone":"+44 121 449 6666",
    "sg:postcode":"B13 8LJ",
    "sg:province":"West Midlands",
    "wof:name":"Ambler Bros",
    "wof:placetype":"venue"
},
  "geometry": {"coordinates":[-1.89267,52.439888],"type":"Point"}
}