{
  "type": "Feature",
  "properties": {
    "iso:country":"GB",
    "sg:address":"Unit 3, Ham Green Farm, Ham Green",
    "sg:city":"Redditch",
    "sg:classifiers":[
        {
            "category":"Building & Trades",
            "subcategory":"Pest Control",
            "type":"Services"
        }
    ],
    "sg:phone":"+44 1527 403031",
    "sg:postcode":"B97 5PR",
    "sg:province":"Warwickshire",
    "sg:tags":[
        "corrosion",
        "prevention"
    ],
    "wof:name":"P.J & A.J Green",
    "wof:placetype":"venue"
},
  "geometry": {"coordinates":[-1.983524,52.271694],"type":"Point"}
}