{
  "type": "Feature",
  "properties": {
    "addr:full":"7-9 Market Place Stoke-on-trent Staffordshire ST6 3AA",
    "addr:housenumber":"7-9",
    "addr:postcode":"st6 3aa",
    "addr:street":"Market Place",
    "iso:country":"GB",
    "sg:address":"7-9 Market Place",
    "sg:city":"Stoke-on-trent",
    "sg:classifiers":[
        {
            "category":"Shopping",
            "subcategory":"News",
            "type":"Retail Goods"
        }
    ],
    "sg:phone":"+44 1782 838340",
    "sg:postcode":"ST6 3AA",
    "sg:province":"Staffordshire",
    "sg:tags":[
        "newsagent"
    ],
    "wof:name":"Brays Newsagents",
    "wof:placetype":"venue"
},
  "geometry": {"coordinates":[-2.197141,53.045521],"type":"Point"}
}