{
  "type": "Feature",
  "properties": {
    "addr:full":"28 Gladeside Road Manchester Greater Manchester M22 9GQ",
    "addr:housenumber":"28",
    "addr:postcode":"m22 9gq",
    "addr:street":"Gladeside Road",
    "iso:country":"GB",
    "sg:address":"28 Gladeside Road",
    "sg:city":"Manchester",
    "sg:classifiers":[
        {
            "category":"Shopping",
            "subcategory":"Florist",
            "type":"Retail Goods"
        }
    ],
    "sg:phone":"+44 161 945 5131",
    "sg:postcode":"M22 9GQ",
    "sg:province":"Greater Manchester",
    "wof:name":"Cheshire Flowers",
    "wof:placetype":"venue"
},
  "geometry": {"coordinates":[-2.261819,53.381554],"type":"Point"}
}