{
  "type": "Feature",
  "properties": {
    "iso:country":"GB",
    "sg:address":"41 Broad Street",
    "sg:city":"Leek",
    "sg:classifiers":[
        {
            "category":"Fast Food",
            "type":"Food & Drink"
        }
    ],
    "sg:phone":"+44 1538 382489",
    "sg:postcode":"ST13 5NX",
    "sg:province":"Staffordshire",
    "sg:tags":[
        "away",
        "take"
    ],
    "wof:name":"Win Lee Chinese Takeaway",
    "wof:placetype":"venue"
},
  "geometry": {"coordinates":[-2.028219,53.1031],"type":"Point"}
}