{
  "type": "Feature",
  "properties": {
    "addr:full":"1-5 The Shambles York North Yorkshire YO1 7LZ",
    "addr:housenumber":"1-5",
    "addr:postcode":"yo1 7lz",
    "addr:street":"The",
    "iso:country":"GB",
    "sg:address":"1-5 The Shambles",
    "sg:city":"York",
    "sg:classifiers":[
        {
            "category":"Real Estate",
            "subcategory":"Real Estate Operator",
            "type":"Services"
        }
    ],
    "sg:phone":"+44 1904 632336",
    "sg:postcode":"YO1 7LZ",
    "sg:province":"North Yorkshire",
    "sg:tags":[
        "letting",
        "agent"
    ],
    "wof:name":"Copleys (Ag) Ltd.",
    "wof:placetype":"venue"
},
  "geometry": {"coordinates":[-1.0799399614,53.959438324],"type":"Point"}
}