{
  "type": "Feature",
  "properties": {
    "addr:full":"Thomas Bennett House, Salford University Business Park Salford Greater Manchester M6 6AS",
    "addr:postcode":"m6 6as",
    "addr:street":"Business Park",
    "iso:country":"GB",
    "sg:address":"Thomas Bennett House, Salford University Business Park",
    "sg:city":"Salford",
    "sg:classifiers":[
        {
            "category":"Professional",
            "subcategory":"Computer Services",
            "type":"Services"
        }
    ],
    "sg:phone":"+44 161 736 1758",
    "sg:postcode":"M6 6AS",
    "sg:province":"Greater Manchester",
    "sg:tags":[
        "system",
        "software"
    ],
    "wof:name":"N R G Software (U K) Ltd.",
    "wof:placetype":"venue"
},
  "geometry": {"coordinates":[-2.274494,53.492367],"type":"Point"}
}