{
  "type": "Feature",
  "properties": {
    "addr:full":"Hodges Farm Pencaitland East Lothian EH34 5BG",
    "addr:postcode":"eh34 5bg",
    "addr:street":"Pencaitland",
    "iso:country":"GB",
    "sg:address":"Hodges Farm",
    "sg:city":"Pencaitland",
    "sg:classifiers":[
        {
            "category":"Farming",
            "subcategory":"Livestock Farm",
            "type":"Manufacturing & Wholesale Goods"
        },
        {
            "category":"Farming",
            "subcategory":"Farm",
            "type":"Manufacturing & Wholesale Goods"
        }
    ],
    "sg:phone":"+44 1875 340221",
    "sg:postcode":"EH34 5BG",
    "sg:province":"East Lothian",
    "sg:tags":[
        "mixed",
        "crop",
        "others"
    ],
    "wof:name":"Hodge,Tom,",
    "wof:placetype":"venue"
},
  "geometry": {"coordinates":[-2.896169,55.910084],"type":"Point"}
}