{
  "type": "Feature",
  "properties": {
    "addr:full":"174 New Hall Lane Preston Lancashire PR1 4DX",
    "addr:housenumber":"174",
    "addr:postcode":"pr1 4dx",
    "addr:street":"New Hall Lane",
    "iso:country":"GB",
    "sg:address":"174 New Hall Lane",
    "sg:city":"Preston",
    "sg:classifiers":[
        {
            "category":"Home & Garden",
            "subcategory":"Household Appliances",
            "type":"Retail Goods"
        }
    ],
    "sg:phone":"+44 1772 798971",
    "sg:postcode":"PR1 4DX",
    "sg:province":"Lancashire",
    "sg:tags":[
        "electrical"
    ],
    "wof:name":"Swan Domestics",
    "wof:placetype":"venue"
},
  "geometry": {"coordinates":[-2.677527,53.762882],"type":"Point"}
}