{
  "type": "Feature",
  "properties": {
    "iso:country":"GB",
    "sg:address":"1-3 Artillery Rd, Lufton Trading Estate, Lufton",
    "sg:city":"Yeovil",
    "sg:classifiers":[
        {
            "category":"Building & Trades",
            "subcategory":"Cleaning & Sanitation",
            "type":"Services"
        },
        {
            "category":"Building & Trades",
            "subcategory":"Pest Control",
            "type":"Services"
        }
    ],
    "sg:phone":"+44 1935 473708",
    "sg:postcode":"BA22 8RP",
    "sg:province":"Dorset",
    "sg:tags":[
        "use",
        "industrial",
        "door",
        "manufacturer"
    ],
    "wof:name":"Wessex Industrial Doors Yeovil Ltd",
    "wof:placetype":"venue"
},
  "geometry": {"coordinates":[-2.678349,50.949089],"type":"Point"}
}