{
  "type": "Feature",
  "properties": {
    "iso:country":"GB",
    "sg:address":"30 Lower Ebor Street",
    "sg:city":"York",
    "sg:classifiers":[
        {
            "category":"Professional",
            "subcategory":"Computer Services",
            "type":"Services"
        }
    ],
    "sg:phone":"+44 1904 626336",
    "sg:postcode":"YO23 1AY",
    "sg:province":"North Yorkshire",
    "sg:tags":[
        "system",
        "software"
    ],
    "wof:name":"Relcon Software",
    "wof:placetype":"venue"
},
  "geometry": {"coordinates":[-1.082092,53.951714],"type":"Point"}
}