{
  "type": "Feature",
  "properties": {
    "iso:country":"GB",
    "sg:address":"11 Eclipse Industrial Estate, Sedgley Road West",
    "sg:city":"Tipton",
    "sg:classifiers":[
        {
            "category":"Shopping Center",
            "type":"Public Place"
        }
    ],
    "sg:phone":"+44 121 522 2094",
    "sg:postcode":"DY4 8AB",
    "sg:province":"West Midlands",
    "sg:tags":[
        "clutch",
        "brake",
        "centre"
    ],
    "wof:name":"A1 Clutches",
    "wof:placetype":"venue"
},
  "geometry": {"coordinates":[-2.070697,52.528137],"type":"Point"}
}