{
  "type": "Feature",
  "properties": {
    "addr:full":"Langley House, Roberttown Lane Liversedge West Yorkshire WF15 7LF",
    "addr:postcode":"wf15 7lf",
    "addr:street":"Roberttown Lane",
    "iso:country":"GB",
    "sg:address":"Langley House, Roberttown Lane",
    "sg:city":"Liversedge",
    "sg:classifiers":[
        {
            "category":"Farming",
            "subcategory":"Farm",
            "type":"Manufacturing & Wholesale Goods"
        }
    ],
    "sg:phone":"+44 1924 405988",
    "sg:postcode":"WF15 7LF",
    "sg:province":"West Yorkshire",
    "sg:tags":[
        "egg",
        "producer"
    ],
    "wof:name":"Half Acre Eggs Ltd.",
    "wof:placetype":"venue"
},
  "geometry": {"coordinates":[-1.7059789896,53.6989860535],"type":"Point"}
}