{
  "type": "Feature",
  "properties": {
    "addr:full":"T.s.l House, Station Rd Edenbridge East Sussex TN8 6HG",
    "addr:postcode":"tn8 6hg",
    "addr:street":"Station Rd",
    "iso:country":"GB",
    "sg:address":"T.s.l House, Station Rd",
    "sg:city":"Edenbridge",
    "sg:classifiers":[
        {
            "category":"Professional",
            "subcategory":"Engineering",
            "type":"Services"
        }
    ],
    "sg:phone":"+44 1732 864819",
    "sg:postcode":"TN8 6HG",
    "sg:province":"East Sussex",
    "sg:tags":[
        "contractor",
        "electrical",
        "engineer"
    ],
    "wof:name":"Turner Saunders Contractors Ltd",
    "wof:placetype":"venue"
},
  "geometry": {"coordinates":[0.0623609982,51.204246521],"type":"Point"}
}