{
  "type": "Feature",
  "properties": {
    "addr:full":"167 Chessington Road, West Ewell Epsom Surrey KT19 9XE",
    "addr:housenumber":"167",
    "addr:postcode":"kt19 9xe",
    "addr:street":"Chessington Road West",
    "iso:country":"GB",
    "sg:address":"167 Chessington Road, West Ewell",
    "sg:city":"Epsom",
    "sg:classifiers":[
        {
            "category":"Taxi",
            "type":"Transportation"
        }
    ],
    "sg:phone":"+44 20 8393 3333",
    "sg:postcode":"KT19 9XE",
    "sg:province":"Surrey",
    "sg:tags":[
        "mini",
        "cab"
    ],
    "wof:name":"Topping Select Car Hire Ltd.",
    "wof:placetype":"venue"
},
  "geometry": {"coordinates":[-0.267589,51.352562],"type":"Point"}
}