{
  "type": "Feature",
  "properties": {
    "addr:full":"Oakdale Blackwood Caerphilly NP12 0DY",
    "addr:postcode":"np12 0dy",
    "iso:country":"GB",
    "sg:address":"Oakdale",
    "sg:city":"Blackwood",
    "sg:classifiers":[
        {
            "category":"Bars & Pubs",
            "type":"Food & Drink"
        }
    ],
    "sg:phone":"+44 1495 225796",
    "sg:postcode":"NP12 0DY",
    "sg:province":"Caerphilly",
    "sg:tags":[
        "pubs",
        "inn"
    ],
    "wof:name":"The Tudor House",
    "wof:placetype":"venue"
},
  "geometry": {"coordinates":[-3.173667,51.677402],"type":"Point"}
}