{
  "type": "Feature",
  "properties": {
    "iso:country":"GB",
    "sg:address":"8 Chalvedon Square, Pitsea",
    "sg:city":"Basildon",
    "sg:classifiers":[
        {
            "category":"Personal",
            "subcategory":"Beauty Salon",
            "type":"Services"
        }
    ],
    "sg:phone":"+44 1268 581583",
    "sg:postcode":"SS13 3QX",
    "sg:province":"Essex",
    "sg:tags":[
        "unisex",
        "hairdresser"
    ],
    "wof:name":"Cutting Edge",
    "wof:placetype":"venue"
},
  "geometry": {"coordinates":[0.500935,51.572239],"type":"Point"}
}