{
  "type": "Feature",
  "properties": {
    "addr:full":"185-187 Northgate Darlington Durham DL1 1UB",
    "addr:housenumber":"185-187",
    "addr:postcode":"dl1 1ub",
    "addr:street":"Northgate",
    "iso:country":"GB",
    "sg:address":"185-187 Northgate",
    "sg:city":"Darlington",
    "sg:classifiers":[
        {
            "category":"Fast Food",
            "type":"Food & Drink"
        }
    ],
    "sg:phone":"+44 1325 483500",
    "sg:postcode":"DL1 1UB",
    "sg:province":"Durham",
    "sg:tags":[
        "away",
        "take"
    ],
    "wof:name":"Northgate Fast Food Ltd.",
    "wof:placetype":"venue"
},
  "geometry": {"coordinates":[-1.5529099703,54.5306472778],"type":"Point"}
}