{
  "type": "Feature",
  "properties": {
    "iso:country":"GB",
    "sg:address":"Glaisdale Dr",
    "sg:city":"Nottingham",
    "sg:classifiers":[
        {
            "category":"Freight",
            "type":"Transportation"
        }
    ],
    "sg:postcode":"NG8 4GY",
    "sg:province":"Nottinghamshire",
    "sg:tags":[
        "haulage",
        "road"
    ],
    "wof:name":"Greenway,Mr & Mrs,",
    "wof:placetype":"venue"
},
  "geometry": {"coordinates":[-1.215989,52.963268],"type":"Point"}
}