{
  "type": "Feature",
  "properties": {
    "addr:full":"4a Parchmore Road Thornton Heath Surrey CR7 8LU",
    "addr:housenumber":"4a",
    "addr:postcode":"cr7 8lu",
    "addr:street":"Parchmore Road",
    "iso:country":"GB",
    "sg:address":"4a Parchmore Road",
    "sg:city":"Thornton Heath",
    "sg:classifiers":[
        {
            "category":"Professional",
            "subcategory":"Printing & Photocopies",
            "type":"Services"
        }
    ],
    "sg:phone":"+44 20 8771 4801",
    "sg:postcode":"CR7 8LU",
    "sg:province":"Surrey",
    "sg:tags":[
        "printer"
    ],
    "wof:name":"Falcon Print Services",
    "wof:placetype":"venue"
},
  "geometry": {"coordinates":[-0.0989670008,51.3997421265],"type":"Point"}
}