{
  "type": "Feature",
  "properties": {
    "iso:country":"GB",
    "sg:address":"Burtons Arcade",
    "sg:city":"Leeds",
    "sg:classifiers":[
        {
            "category":"Shopping",
            "subcategory":"Clothing, Apparel, & Fashions",
            "type":"Retail Goods"
        }
    ],
    "sg:postcode":"LS1 6HQ",
    "sg:province":"West Yorkshire",
    "sg:tags":[
        "menswear"
    ],
    "wof:name":"Cheatle,John,Ltd",
    "wof:placetype":"venue"
},
  "geometry": {"coordinates":[-1.5430999994,53.796787262],"type":"Point"}
}