{
  "type": "Feature",
  "properties": {
    "addr:full":"2 Manor Farm Cottages, Greywell Rd Basingstoke Hampshire RG25 2RQ",
    "addr:housenumber":"2",
    "addr:postcode":"rg25 2rq",
    "addr:street":"Manor Farm Cottages Greywell Rd",
    "iso:country":"GB",
    "sg:address":"2 Manor Farm Cottages, Greywell Rd",
    "sg:city":"Basingstoke",
    "sg:classifiers":[
        {
            "category":"Professional",
            "subcategory":"Printing & Photocopies",
            "type":"Services"
        }
    ],
    "sg:phone":"+44 1256 862502",
    "sg:postcode":"RG25 2RQ",
    "sg:province":"Hampshire",
    "sg:tags":[
        "printer"
    ],
    "wof:name":"Upton Grey Copperplate Engraving",
    "wof:placetype":"venue"
},
  "geometry": {"coordinates":[-1.0013699532,51.2332191467],"type":"Point"}
}