{
  "type": "Feature",
  "properties": {
    "iso:country":"GB",
    "sg:address":"69 Ship St",
    "sg:city":"Brighton",
    "sg:classifiers":[
        {
            "category":"Professional",
            "subcategory":"Lawyer & Legal Services",
            "type":"Services"
        }
    ],
    "sg:phone":"+44 1273 887886",
    "sg:postcode":"BN1 1AE",
    "sg:province":"East Sussex",
    "sg:tags":[
        "advice",
        "counselling"
    ],
    "wof:name":"On The Level",
    "wof:placetype":"venue"
},
  "geometry": {"coordinates":[-0.142047,50.820515],"type":"Point"}
}