{
  "type": "Feature",
  "properties": {
    "addr:full":"7 Station Street Swaffham Norfolk PE37 7LL",
    "addr:housenumber":"7",
    "addr:postcode":"pe37 7ll",
    "addr:street":"Station Street",
    "iso:country":"GB",
    "sg:address":"7 Station Street",
    "sg:city":"Swaffham",
    "sg:classifiers":[
        {
            "category":"Personal",
            "subcategory":"Beauty Salon",
            "type":"Services"
        }
    ],
    "sg:phone":"+44 1760 721237",
    "sg:postcode":"PE37 7LL",
    "sg:province":"Norfolk",
    "sg:tags":[
        "unisex",
        "hairdresser"
    ],
    "wof:name":"Just Hair",
    "wof:placetype":"venue"
},
  "geometry": {"coordinates":[0.689,52.649498],"type":"Point"}
}