{
  "type": "Feature",
  "properties": {
    "iso:country":"GB",
    "sg:address":"Fairfax House, 117 Midland Road",
    "sg:city":"Bedford",
    "sg:classifiers":[
        {
            "category":"Personal",
            "subcategory":"Beauty Salon",
            "type":"Services"
        }
    ],
    "sg:phone":"+44 1234 355619",
    "sg:postcode":"MK40 1DE",
    "sg:province":"Bedfordshire",
    "sg:tags":[
        "lady",
        "hairdresser"
    ],
    "wof:name":"Temples Hair Studio",
    "wof:placetype":"venue"
},
  "geometry": {"coordinates":[-0.474161,52.135677],"type":"Point"}
}