{
  "type": "Feature",
  "properties": {
    "addr:full":"16 St Catherines Rd, Giffnock Glasgow East Renfrewshire G46 6JN",
    "addr:housenumber":"16",
    "addr:postcode":"g46 6jn",
    "addr:street":"St Catherines Rd",
    "iso:country":"GB",
    "sg:address":"16 St Catherines Rd, Giffnock",
    "sg:city":"Glasgow",
    "sg:classifiers":[
        {
            "category":"Real Estate",
            "subcategory":"Surveying",
            "type":"Services"
        }
    ],
    "sg:phone":"+44 141 621 4303",
    "sg:postcode":"G46 6JN",
    "sg:province":"East Renfrewshire",
    "sg:tags":[
        "surveyor",
        "quantity"
    ],
    "wof:name":"Allan Downie Associates",
    "wof:placetype":"venue"
},
  "geometry": {"coordinates":[-4.2928872108,55.8018951416],"type":"Point"}
}