{
  "type": "Feature",
  "properties": {
    "addr:full":"Regency Court Nursing & Residential Home, South Terrace Littlehampton West Sussex BN17 5NZ",
    "addr:postcode":"bn17 5nz",
    "addr:street":"Regency;Terrace",
    "iso:country":"GB",
    "sg:address":"Regency Court Nursing & Residential Home, South Terrace",
    "sg:city":"Littlehampton",
    "sg:classifiers":[
        {
            "category":"Health Services",
            "subcategory":"Nursing And Care Facility",
            "type":"Services"
        }
    ],
    "sg:phone":"+44 1903 736400",
    "sg:postcode":"BN17 5NZ",
    "sg:province":"West Sussex",
    "sg:tags":[
        "home"
    ],
    "wof:name":"Ans Plc",
    "wof:placetype":"venue"
},
  "geometry": {"coordinates":[-0.53189,50.80397],"type":"Point"}
}