{
  "type": "Feature",
  "properties": {
    "iso:country":"GB",
    "sg:address":"Faulkeners End",
    "sg:city":"Harpenden",
    "sg:classifiers":[
        {
            "category":"Farming",
            "subcategory":"Farm",
            "type":"Manufacturing & Wholesale Goods"
        }
    ],
    "sg:postcode":"AL5 3PG",
    "sg:province":"Hertfordshire",
    "sg:tags":[
        "mixed",
        "crop"
    ],
    "wof:name":"Catton,D",
    "wof:placetype":"venue"
},
  "geometry": {"coordinates":[-0.388410002,51.823348999],"type":"Point"}
}