{
  "type": "Feature",
  "properties": {
    "iso:country":"GB",
    "sg:address":"2 St Michaels Road",
    "sg:city":"Leeds",
    "sg:classifiers":[
        {
            "category":"Bars & Pubs",
            "type":"Food & Drink"
        }
    ],
    "sg:phone":"+44 113 275 2123",
    "sg:postcode":"LS6 3AW",
    "sg:province":"West Yorkshire",
    "sg:tags":[
        "pubs",
        "inn"
    ],
    "wof:name":"Skyrack Hotel",
    "wof:placetype":"venue"
},
  "geometry": {"coordinates":[-1.5802079439,53.8193473816],"type":"Point"}
}