{
  "type": "Feature",
  "properties": {
    "addr:full":"752 Ecclesall Road Sheffield Derbyshire S11 8TB",
    "addr:housenumber":"752",
    "addr:postcode":"s11 8tb",
    "addr:street":"Ecclesall Road",
    "iso:country":"GB",
    "sg:address":"752 Ecclesall Road",
    "sg:city":"Sheffield",
    "sg:classifiers":[
        {
            "category":"Shopping",
            "subcategory":"Baby Store",
            "type":"Retail Goods"
        }
    ],
    "sg:phone":"+44 114 267 9645",
    "sg:postcode":"S11 8TB",
    "sg:province":"Derbyshire",
    "sg:tags":[
        "babywear",
        "childrens"
    ],
    "wof:name":"Daisychain",
    "wof:placetype":"venue"
},
  "geometry": {"coordinates":[-1.5072920322,53.3661384583],"type":"Point"}
}