{
  "type": "Feature",
  "properties": {
    "addr:full":"54 Little Heath Road, Chobham Woking Surrey GU24 8RJ",
    "addr:housenumber":"54",
    "addr:postcode":"gu24 8rj",
    "addr:street":"Little Heath Road",
    "iso:country":"GB",
    "sg:address":"54 Little Heath Road, Chobham",
    "sg:city":"Woking",
    "sg:classifiers":[
        {
            "category":"Building & Trades",
            "subcategory":"Landscaping Services",
            "type":"Services"
        }
    ],
    "sg:postcode":"GU24 8RJ",
    "sg:province":"Surrey",
    "sg:tags":[
        "forestry",
        "tree"
    ],
    "wof:name":"Tree Stump Removals",
    "wof:placetype":"venue"
},
  "geometry": {"coordinates":[-0.601609,51.354912],"type":"Point"}
}