{
  "type": "Feature",
  "properties": {
    "addr:full":"St Georges Down, Blackwater Newport Isle of Wight PO30 3BX",
    "addr:postcode":"po30 3bx",
    "addr:street":"St Georges Down Blackwater",
    "iso:country":"GB",
    "sg:address":"St Georges Down, Blackwater",
    "sg:city":"Newport",
    "sg:classifiers":[
        {
            "category":"Utilities",
            "subcategory":"Natural Gas",
            "type":"Services"
        }
    ],
    "sg:phone":"+44 1983 533755",
    "sg:postcode":"PO30 3BX",
    "sg:province":"Isle of Wight",
    "sg:tags":[
        "supplier"
    ],
    "wof:name":"Medina Gases",
    "wof:placetype":"venue"
},
  "geometry": {"coordinates":[-1.287264,50.689732],"type":"Point"}
}