{
  "type": "Feature",
  "properties": {
    "addr:full":"29 Beach Street Deal Kent CT14 6HY",
    "addr:housenumber":"29",
    "addr:postcode":"ct14 6hy",
    "addr:street":"Beach Street Deal",
    "iso:country":"GB",
    "sg:address":"29 Beach Street",
    "sg:city":"Deal",
    "sg:classifiers":[
        {
            "category":"Travel",
            "subcategory":"Hotels & Motels",
            "type":"Entertainment"
        }
    ],
    "sg:phone":"+44 1304 374338",
    "sg:postcode":"CT14 6HY",
    "sg:province":"Kent",
    "wof:name":"The Beachbrow Hotel",
    "wof:placetype":"venue"
},
  "geometry": {"coordinates":[1.404305,51.223488],"type":"Point"}
}