{
  "type": "Feature",
  "properties": {
    "addr:full":"39-41 High Street Denbigh Conwy LL16 3HY",
    "addr:housenumber":"39-41",
    "addr:postcode":"ll16 3hy",
    "addr:street":"High Street",
    "iso:country":"GB",
    "sg:address":"39-41 High Street",
    "sg:city":"Denbigh",
    "sg:classifiers":[
        {
            "category":"Professional",
            "subcategory":"Detective & Security Services",
            "type":"Services"
        }
    ],
    "sg:phone":"+44 1745 814024",
    "sg:postcode":"LL16 3HY",
    "sg:province":"Conwy",
    "sg:tags":[
        "alarm",
        "burglar",
        "system"
    ],
    "wof:name":"S & G Tate Security & Electrical Systems",
    "wof:placetype":"venue"
},
  "geometry": {"coordinates":[-3.4200439453,53.1834259033],"type":"Point"}
}