{
  "type": "Feature",
  "properties": {
    "iso:country":"GB",
    "sg:address":"2a Grosvenor Park Road",
    "sg:city":"London",
    "sg:classifiers":[
        {
            "category":"Shopping",
            "subcategory":"News",
            "type":"Retail Goods"
        }
    ],
    "sg:phone":"+44 20 8520 6673",
    "sg:postcode":"E17 9PG",
    "sg:province":"Greater London",
    "sg:tags":[
        "newsagent"
    ],
    "wof:name":"Lynns",
    "wof:placetype":"venue"
},
  "geometry": {"coordinates":[-0.0129220001,51.5806655884],"type":"Point"}
}