{
  "type": "Feature",
  "properties": {
    "addr:full":"9 Knaresborough Pl London Greater London SW5 0TP",
    "addr:housenumber":"9",
    "addr:postcode":"sw5 0tp",
    "addr:street":"Knaresborough Pl",
    "iso:country":"GB",
    "sg:address":"9 Knaresborough Pl",
    "sg:city":"London",
    "sg:classifiers":[
        {
            "category":"Travel",
            "subcategory":"Hotels & Motels",
            "type":"Entertainment"
        }
    ],
    "sg:phone":"+44 20 7370 3246",
    "sg:postcode":"SW5 0TP",
    "sg:province":"Greater London",
    "wof:name":"Allied Sainif Plc",
    "wof:placetype":"venue"
},
  "geometry": {"coordinates":[-0.191118,51.493904],"type":"Point"}
}