{
  "type": "Feature",
  "properties": {
    "iso:country":"GB",
    "sg:address":"1a Coniston Road, Astley, Tyldesley",
    "sg:city":"Manchester",
    "sg:classifiers":[
        {
            "category":"Health Services",
            "subcategory":"Podiatrist",
            "type":"Services"
        }
    ],
    "sg:phone":"+44 1942 887881",
    "sg:postcode":"M29 7AS",
    "sg:province":"Greater Manchester",
    "sg:tags":[
        "podiatrists",
        "chiropodist"
    ],
    "wof:name":"Sandra Jones",
    "wof:placetype":"venue"
},
  "geometry": {"coordinates":[-2.4632790089,53.5062713623],"type":"Point"}
}