{
  "type": "Feature",
  "properties": {
    "iso:country":"GB",
    "sg:address":"Unit 7, Newland Industrial Estate",
    "sg:city":"Witney",
    "sg:classifiers":[
        {
            "category":"Retail",
            "subcategory":"Photofinishing",
            "type":"Services"
        }
    ],
    "sg:postcode":"OX28 3JH",
    "sg:province":"Oxfordshire",
    "sg:tags":[
        "photographic",
        "processor"
    ],
    "wof:name":"Photolabs",
    "wof:placetype":"venue"
},
  "geometry": {"coordinates":[-1.4775949717,51.7893447876],"type":"Point"}
}