{
  "type": "Feature",
  "properties": {
    "addr:full":"Meersbrook Works, Valley Rd Sheffield Derbyshire S8 9FT",
    "addr:postcode":"s8 9ft",
    "addr:street":"Valley Rd",
    "iso:country":"GB",
    "sg:address":"Meersbrook Works, Valley Rd",
    "sg:city":"Sheffield",
    "sg:classifiers":[
        {
            "category":"Arts & Performance",
            "subcategory":"Theater",
            "type":"Entertainment"
        }
    ],
    "sg:phone":"+44 114 249 3650",
    "sg:postcode":"S8 9FT",
    "sg:province":"Derbyshire",
    "sg:tags":[
        "theatre"
    ],
    "wof:name":"The Performance Project",
    "wof:placetype":"venue"
},
  "geometry": {"coordinates":[-1.4750740528,53.356716156],"type":"Point"}
}