{
  "type": "Feature",
  "properties": {
    "addr:full":"80 Station Road, Hatton Derby Derbyshire DE65 5EL",
    "addr:housenumber":"80",
    "addr:postcode":"de65 5el",
    "addr:street":"Station Road",
    "iso:country":"GB",
    "sg:address":"80 Station Road, Hatton",
    "sg:city":"Derby",
    "sg:classifiers":[
        {
            "category":"Government",
            "subcategory":"Post Office",
            "type":"Public Place"
        }
    ],
    "sg:phone":"+44 1283 812170",
    "sg:postcode":"DE65 5EL",
    "sg:province":"Derbyshire",
    "wof:name":"Hatton Post Office",
    "wof:placetype":"venue"
},
  "geometry": {"coordinates":[-1.680483,52.866959],"type":"Point"}
}