{
  "type": "Feature",
  "properties": {
    "addr:full":"39 Edenhall Road, Quinton Birmingham West Midlands B32 1DB",
    "addr:housenumber":"39",
    "addr:postcode":"b32 1db",
    "addr:street":"Edenhall Road",
    "iso:country":"GB",
    "sg:address":"39 Edenhall Road, Quinton",
    "sg:city":"Birmingham",
    "sg:classifiers":[
        {
            "category":"Building & Trades",
            "subcategory":"Construction",
            "type":"Services"
        }
    ],
    "sg:postcode":"B32 1DB",
    "sg:province":"West Midlands",
    "sg:tags":[
        "joiner",
        "carpenter"
    ],
    "wof:name":"G Riches",
    "wof:placetype":"venue"
},
  "geometry": {"coordinates":[-2.002026,52.461437],"type":"Point"}
}