{
  "type": "Feature",
  "properties": {
    "iso:country":"GB",
    "sg:address":"250 North Road",
    "sg:city":"Darlington",
    "sg:classifiers":[
        {
            "category":"Building & Trades",
            "subcategory":"Plumbing",
            "type":"Services"
        }
    ],
    "sg:phone":"+44 1325 465886",
    "sg:postcode":"DL1 2EN",
    "sg:province":"Durham",
    "sg:tags":[
        "plumber",
        "heating"
    ],
    "wof:name":"Peter Green",
    "wof:placetype":"venue"
},
  "geometry": {"coordinates":[-1.548395,54.543129],"type":"Point"}
}