{
  "type": "Feature",
  "properties": {
    "addr:full":"23 St Mary Street St Andrews Fife KY16 8AZ",
    "addr:housenumber":"23",
    "addr:postcode":"ky16 8az",
    "addr:street":"St Mary Street",
    "iso:country":"GB",
    "sg:address":"23 St Mary Street",
    "sg:city":"St Andrews",
    "sg:classifiers":[
        {
            "category":"Bars & Pubs",
            "type":"Food & Drink"
        }
    ],
    "sg:phone":"+44 1334 472105",
    "sg:postcode":"KY16 8AZ",
    "sg:province":"Fife",
    "sg:tags":[
        "pubs",
        "inn"
    ],
    "wof:name":"The New Inn",
    "wof:placetype":"venue"
},
  "geometry": {"coordinates":[-2.7835071087,56.3348236084],"type":"Point"}
}