{
  "type": "Feature",
  "properties": {
    "addr:full":"Westlea House, Selsley West Stroud Gloucestershire GL5 5LQ",
    "addr:postcode":"gl5 5lq",
    "addr:street":"West",
    "iso:country":"GB",
    "sg:address":"Westlea House, Selsley West",
    "sg:city":"Stroud",
    "sg:classifiers":[
        {
            "category":"Professional",
            "subcategory":"Accounting & Tax Preparation",
            "type":"Services"
        }
    ],
    "sg:phone":"+44 1453 823876",
    "sg:postcode":"GL5 5LQ",
    "sg:province":"Gloucestershire",
    "sg:tags":[
        "accountant"
    ],
    "wof:name":"John M Hayton",
    "wof:placetype":"venue"
},
  "geometry": {"coordinates":[-2.24062,51.734344],"type":"Point"}
}