{
  "type": "Feature",
  "properties": {
    "addr:full":"327-331 London Road, Hadleigh Benfleet Essex SS7 2BT",
    "addr:housenumber":"327-331",
    "addr:postcode":"ss7 2bt",
    "addr:street":"London Road",
    "iso:country":"GB",
    "sg:address":"327-331 London Road, Hadleigh",
    "sg:city":"Benfleet",
    "sg:classifiers":[
        {
            "category":"Autos & Motor Vehicles",
            "subcategory":"Automobile Sales",
            "type":"Retail Goods"
        }
    ],
    "sg:phone":"+44 1702 554586",
    "sg:postcode":"SS7 2BT",
    "sg:province":"Essex",
    "sg:tags":[
        "car",
        "commercial"
    ],
    "wof:name":"Boundary Garage",
    "wof:placetype":"venue"
},
  "geometry": {"coordinates":[0.612922,51.552052],"type":"Point"}
}