{
  "type": "Feature",
  "properties": {
    "addr:full":"Dylan House, Town End Street Godalming Surrey GU7 1BQ",
    "addr:postcode":"gu7 1bq",
    "addr:street":"Town End Street",
    "iso:country":"GB",
    "sg:address":"Dylan House, Town End Street",
    "sg:city":"Godalming",
    "sg:classifiers":[
        {
            "category":"Communications",
            "type":"Services"
        }
    ],
    "sg:postcode":"GU7 1BQ",
    "sg:province":"Surrey",
    "sg:tags":[
        "audio-visual"
    ],
    "wof:name":"Sightline",
    "wof:placetype":"venue"
},
  "geometry": {"coordinates":[-0.6102290154,51.1837348938],"type":"Point"}
}