{
  "type": "Feature",
  "properties": {
    "addr:full":"5 Hen Ys Gol, Forge Rd Crickhowell Monmouthshire NP8 1LU",
    "addr:housenumber":"5;ys",
    "addr:postcode":"np8 1lu",
    "addr:street":"Hen;Forge Rd",
    "iso:country":"GB",
    "sg:address":"5 Hen Ys Gol, Forge Rd",
    "sg:city":"Crickhowell",
    "sg:classifiers":[
        {
            "category":"Building & Trades",
            "subcategory":"Equipment Rental",
            "type":"Services"
        }
    ],
    "sg:phone":"+44 1874 730124",
    "sg:postcode":"NP8 1LU",
    "sg:province":"Monmouthshire",
    "sg:tags":[
        "supply"
    ],
    "wof:name":"Jack Joseph Designs",
    "wof:placetype":"venue"
},
  "geometry": {"coordinates":[-3.138122,51.861626],"type":"Point"}
}