{
  "type": "Feature",
  "properties": {
    "addr:full":"65 Campden Street London Greater London W8 7EL",
    "addr:housenumber":"65",
    "addr:postcode":"w8 7el",
    "addr:street":"Campden Street",
    "iso:country":"GB",
    "sg:address":"65 Campden Street",
    "sg:city":"London",
    "sg:classifiers":[
        {
            "category":"Professional",
            "subcategory":"Management & Consulting",
            "type":"Services"
        }
    ],
    "sg:phone":"+44 20 7221 3606",
    "sg:postcode":"W8 7EL",
    "sg:province":"Greater London",
    "sg:tags":[
        "music"
    ],
    "wof:name":"Olivia Ma Artists Management",
    "wof:placetype":"venue"
},
  "geometry": {"coordinates":[-0.197276,51.506233],"type":"Point"}
}