{
  "type": "Feature",
  "properties": {
    "addr:full":"136 Lee Lane, Horwich Bolton Lancashire BL6 7AF",
    "addr:housenumber":"136",
    "addr:postcode":"bl6 7af",
    "addr:street":"Lee Lane",
    "iso:country":"GB",
    "sg:address":"136 Lee Lane, Horwich",
    "sg:city":"Bolton",
    "sg:classifiers":[
        {
            "category":"Shopping",
            "subcategory":"News",
            "type":"Retail Goods"
        }
    ],
    "sg:phone":"+44 1204 697450",
    "sg:postcode":"BL6 7AF",
    "sg:province":"Lancashire",
    "sg:tags":[
        "newsagent"
    ],
    "wof:name":"Grimshaws",
    "wof:placetype":"venue"
},
  "geometry": {"coordinates":[-2.5497310162,53.6011810303],"type":"Point"}
}