{
  "type": "Feature",
  "properties": {
    "addr:full":"Cherry Tree Cottage, Alltami Road, Alltami Mold Denbighshire CH7 6RW",
    "addr:postcode":"ch7 6rw",
    "addr:street":"Alltami Road",
    "iso:country":"GB",
    "sg:address":"Cherry Tree Cottage, Alltami Road, Alltami",
    "sg:city":"Mold",
    "sg:classifiers":[
        {
            "category":"Autos & Motor Vehicles",
            "subcategory":"Motorcycle Sales",
            "type":"Retail Goods"
        }
    ],
    "sg:phone":"+44 1244 546218",
    "sg:postcode":"CH7 6RW",
    "sg:province":"Denbighshire",
    "sg:tags":[
        "chauffeur",
        "driven",
        "car"
    ],
    "wof:name":"Lewis Chauffeur Services",
    "wof:placetype":"venue"
},
  "geometry": {"coordinates":[-3.0988199711,53.1819992065],"type":"Point"}
}