{
  "type": "Feature",
  "properties": {
    "addr:full":"40 Jodrell Road, Whalley Bridge High Peak Cheshire SK23 7AN",
    "addr:housenumber":"40",
    "addr:postcode":"sk23 7an",
    "addr:street":"Jodrell Road;Peak",
    "iso:country":"GB",
    "sg:address":"40 Jodrell Road, Whalley Bridge",
    "sg:city":"High Peak",
    "sg:classifiers":[
        {
            "category":"Professional",
            "subcategory":"Business Services",
            "type":"Services"
        }
    ],
    "sg:phone":"+44 1663 732709",
    "sg:postcode":"SK23 7AN",
    "sg:province":"Cheshire",
    "sg:tags":[
        "assessment",
        "quality"
    ],
    "wof:name":"Flakeplace Ltd.",
    "wof:placetype":"venue"
},
  "geometry": {"coordinates":[-1.987102,53.33205],"type":"Point"}
}