{
  "type": "Feature",
  "properties": {
    "addr:full":"577 Moseley Road Birmingham West Midlands B12 9BS",
    "addr:housenumber":"577",
    "addr:postcode":"b12 9bs",
    "addr:street":"Moseley Road",
    "iso:country":"GB",
    "sg:address":"577 Moseley Road",
    "sg:city":"Birmingham",
    "sg:classifiers":[
        {
            "category":"Government",
            "subcategory":"Post Office",
            "type":"Public Place"
        }
    ],
    "sg:phone":"+44 121 440 2749",
    "sg:postcode":"B12 9BS",
    "sg:province":"West Midlands",
    "wof:name":"Brighton Road Sub Post Office",
    "wof:placetype":"venue"
},
  "geometry": {"coordinates":[-1.886581,52.455185],"type":"Point"}
}