{
  "type": "Feature",
  "properties": {
    "addr:full":"1 Wendy Avenue Ripon North Yorkshire HG4 1TD",
    "addr:housenumber":"1",
    "addr:postcode":"hg4 1td",
    "addr:street":"Wendy Avenue",
    "iso:country":"GB",
    "sg:address":"1 Wendy Avenue",
    "sg:city":"Ripon",
    "sg:classifiers":[
        {
            "category":"Retail",
            "subcategory":"Repair Shop",
            "type":"Services"
        }
    ],
    "sg:phone":"+44 1765 607448",
    "sg:postcode":"HG4 1TD",
    "sg:province":"North Yorkshire",
    "sg:tags":[
        "maintenance"
    ],
    "wof:name":"Gilliam James Andrew Painting & Decoratoring",
    "wof:placetype":"venue"
},
  "geometry": {"coordinates":[-1.527975,54.127579],"type":"Point"}
}