{
  "type": "Feature",
  "properties": {
    "iso:country":"GB",
    "sg:address":"Southampton Road, Cadnam",
    "sg:city":"Southampton",
    "sg:classifiers":[
        {
            "category":"Travel",
            "subcategory":"Hotels & Motels",
            "type":"Entertainment"
        }
    ],
    "sg:postcode":"SO40 2NQ",
    "sg:province":"Hampshire",
    "sg:tags":[
        "house",
        "guest"
    ],
    "wof:name":"Sylvia J Perkiss",
    "wof:placetype":"venue"
},
  "geometry": {"coordinates":[-1.5740740299,50.9192581177],"type":"Point"}
}