{
  "type": "Feature",
  "properties": {
    "iso:country":"GB",
    "sg:address":"405 Chiswick High Road, Chiswick",
    "sg:city":"London",
    "sg:classifiers":[
        {
            "category":"Taxi",
            "type":"Transportation"
        }
    ],
    "sg:postcode":"W4 4AR",
    "sg:province":"Greater London",
    "sg:tags":[
        "mini",
        "cab"
    ],
    "wof:name":"Coachman Car Service",
    "wof:placetype":"venue"
},
  "geometry": {"coordinates":[-0.276144,51.492176],"type":"Point"}
}