{
  "type": "Feature",
  "properties": {
    "iso:country":"GB",
    "sg:address":"Back Oxford St, Castleford Rd",
    "sg:city":"Normanton",
    "sg:classifiers":[
        {
            "category":"Social Services",
            "subcategory":"Adult Care",
            "type":"Services"
        }
    ],
    "sg:phone":"+44 1924 302530",
    "sg:postcode":"WF6 2DP",
    "sg:province":"West Yorkshire",
    "sg:tags":[
        "day",
        "centre"
    ],
    "wof:name":"Hopetown & Loscoe Centre",
    "wof:placetype":"venue"
},
  "geometry": {"coordinates":[-1.407029,53.702549],"type":"Point"}
}