{
  "type": "Feature",
  "properties": {
    "addr:full":"25 Wood Street Stratford-upon-avon Warwickshire CV37 6JF",
    "addr:housenumber":"25",
    "addr:postcode":"cv37 6jf",
    "addr:street":"Wood Street",
    "iso:country":"GB",
    "sg:address":"25 Wood Street",
    "sg:city":"Stratford-upon-avon",
    "sg:classifiers":[
        {
            "category":"Personal",
            "subcategory":"Beauty Salon",
            "type":"Services"
        },
        {
            "category":"Personal",
            "subcategory":"Barber",
            "type":"Services"
        }
    ],
    "sg:phone":"+44 1789 204335",
    "sg:postcode":"CV37 6JF",
    "sg:province":"Warwickshire",
    "sg:tags":[
        "unisex",
        "hairdresser"
    ],
    "wof:name":"Mark Lindsey",
    "wof:placetype":"venue"
},
  "geometry": {"coordinates":[-1.7091950178,52.1927604675],"type":"Point"}
}