{
  "type": "Feature",
  "properties": {
    "addr:full":"21 New Street Woodbridge Suffolk IP12 1DY",
    "addr:housenumber":"21",
    "addr:postcode":"ip12 1dy",
    "addr:street":"New Street",
    "iso:country":"GB",
    "sg:address":"21 New Street",
    "sg:city":"Woodbridge",
    "sg:classifiers":[
        {
            "category":"Food & Beverages",
            "subcategory":"Bakery",
            "type":"Retail Goods"
        }
    ],
    "sg:phone":"+44 1394 384398",
    "sg:postcode":"IP12 1DY",
    "sg:province":"Suffolk",
    "sg:tags":[
        "shop",
        "baker"
    ],
    "wof:name":"Moss & Son The Bakers",
    "wof:placetype":"venue"
},
  "geometry": {"coordinates":[1.3181,52.093987],"type":"Point"}
}