{
  "type": "Feature",
  "properties": {
    "addr:full":"Lockwood Clo Nottingham Nottinghamshire NG5 9JN",
    "addr:postcode":"ng5 9jn",
    "iso:country":"GB",
    "sg:address":"Lockwood Clo",
    "sg:city":"Nottingham",
    "sg:classifiers":[
        {
            "category":"Home & Garden",
            "subcategory":"Carpets & Floor Coverings",
            "type":"Retail Goods"
        }
    ],
    "sg:phone":"+44 115 967 4366",
    "sg:postcode":"NG5 9JN",
    "sg:province":"Nottinghamshire",
    "sg:tags":[
        "rubber",
        "plastic"
    ],
    "wof:name":"Plastique Ltd",
    "wof:placetype":"venue"
},
  "geometry": {"coordinates":[-1.158769,53.010403],"type":"Point"}
}