{
  "type": "Feature",
  "properties": {
    "addr:full":"132-134 The Broadway London Greater London SW19 1RH",
    "addr:housenumber":"132-134",
    "addr:postcode":"sw19 1rh",
    "addr:street":"The Broadway",
    "iso:country":"GB",
    "sg:address":"132-134 The Broadway",
    "sg:city":"London",
    "sg:classifiers":[
        {
            "category":"Shopping",
            "subcategory":"News",
            "type":"Retail Goods"
        }
    ],
    "sg:postcode":"SW19 1RH",
    "sg:province":"Greater London",
    "sg:tags":[
        "newsagent"
    ],
    "wof:name":"Junction Box Ltd.",
    "wof:placetype":"venue"
},
  "geometry": {"coordinates":[-0.200439,51.419388],"type":"Point"}
}