{
  "type": "Feature",
  "properties": {
    "addr:full":"Britannia House, 6-7 Eastgate Street Stafford Staffordshire ST16 2NQ",
    "addr:housenumber":"6-7",
    "addr:postcode":"st16 2nq",
    "addr:street":"Eastgate Street",
    "iso:country":"GB",
    "sg:address":"Britannia House, 6-7 Eastgate Street",
    "sg:city":"Stafford",
    "sg:classifiers":[
        {
            "category":"Travel",
            "subcategory":"Travel Agent",
            "type":"Entertainment"
        }
    ],
    "sg:phone":"+44 1785 251610",
    "sg:postcode":"ST16 2NQ",
    "sg:province":"Staffordshire",
    "wof:name":"Regent Business Travel",
    "wof:placetype":"venue"
},
  "geometry": {"coordinates":[-2.1151099205,52.8072319031],"type":"Point"}
}