{
  "type": "Feature",
  "properties": {
    "iso:country":"GB",
    "sg:address":"Unit 1 Wellington Place, Off Buckingham Road",
    "sg:city":"Milton Keynes",
    "sg:classifiers":[
        {
            "category":"Autos & Motor Vehicles",
            "subcategory":"Auto Supplies",
            "type":"Retail Goods"
        },
        {
            "category":"Retail",
            "subcategory":"Auto Repair",
            "type":"Services"
        }
    ],
    "sg:phone":"+44 1908 648099",
    "sg:postcode":"MK3 5NA",
    "sg:province":"Buckinghamshire",
    "sg:tags":[
        "windscreen",
        "replacement"
    ],
    "wof:name":"R A C Auto Windscreens",
    "wof:placetype":"venue"
},
  "geometry": {"coordinates":[-0.737611,51.991589],"type":"Point"}
}