{
  "type": "Feature",
  "properties": {
    "iso:country":"GB",
    "sg:address":"Elm Farm, Fishpool Hill",
    "sg:city":"Bristol",
    "sg:classifiers":[
        {
            "category":"Farming",
            "subcategory":"Livestock Farm",
            "type":"Manufacturing & Wholesale Goods"
        }
    ],
    "sg:phone":"+44 117 950 3355",
    "sg:postcode":"BS10 6SW",
    "sg:province":"City of Bristol",
    "sg:tags":[
        "others"
    ],
    "wof:name":"S L Panes & Son",
    "wof:placetype":"venue"
},
  "geometry": {"coordinates":[-2.604879,51.517654],"type":"Point"}
}