{
  "type": "Feature",
  "properties": {
    "addr:full":"33 Chaucer Road Sittingbourne Kent ME10 1EZ",
    "addr:housenumber":"33",
    "addr:postcode":"me10 1ez",
    "addr:street":"Chaucer Road",
    "iso:country":"GB",
    "sg:address":"33 Chaucer Road",
    "sg:city":"Sittingbourne",
    "sg:classifiers":[
        {
            "category":"Shopping",
            "subcategory":"News",
            "type":"Retail Goods"
        }
    ],
    "sg:phone":"+44 1795 472801",
    "sg:postcode":"ME10 1EZ",
    "sg:province":"Kent",
    "sg:tags":[
        "newsagent"
    ],
    "wof:name":"Chaucer News",
    "wof:placetype":"venue"
},
  "geometry": {"coordinates":[0.724856,51.334576],"type":"Point"}
}