{
  "type": "Feature",
  "properties": {
    "addr:full":"4 Somerville Street, Smithills Bolton Lancashire BL1 3LN",
    "addr:housenumber":"4",
    "addr:postcode":"bl1 3ln",
    "addr:street":"Somerville Street",
    "iso:country":"GB",
    "sg:address":"4 Somerville Street, Smithills",
    "sg:city":"Bolton",
    "sg:classifiers":[
        {
            "category":"Building & Trades",
            "subcategory":"Landscaping Services",
            "type":"Services"
        }
    ],
    "sg:phone":"+44 1204 493931",
    "sg:postcode":"BL1 3LN",
    "sg:province":"Lancashire",
    "sg:tags":[
        "gardening"
    ],
    "wof:name":"Nigel Kay Handyman Services",
    "wof:placetype":"venue"
},
  "geometry": {"coordinates":[-2.450422,53.595303],"type":"Point"}
}