{
  "type": "Feature",
  "properties": {
    "addr:full":"Unit 5 Universal Shipyard, Sarisbury Grn Southampton Hampshire SO31 7ZN",
    "addr:housenumber":"unit 5",
    "addr:postcode":"so31 7zn",
    "addr:street":"Sarisbury Grn",
    "iso:country":"GB",
    "sg:address":"Unit 5 Universal Shipyard, Sarisbury Grn",
    "sg:city":"Southampton",
    "sg:classifiers":[
        {
            "category":"Shopping",
            "subcategory":"Bicycles & Sporting Goods",
            "type":"Retail Goods"
        }
    ],
    "sg:phone":"+44 1489 885022",
    "sg:postcode":"SO31 7ZN",
    "sg:province":"Hampshire",
    "sg:tags":[
        "equipment",
        "marine",
        "supply"
    ],
    "wof:name":"Atlantic med Marine Ltd.",
    "wof:placetype":"venue"
},
  "geometry": {"coordinates":[-1.301970005,50.8748207092],"type":"Point"}
}