{
  "type": "Feature",
  "properties": {
    "iso:country":"GB",
    "sg:address":"29 Regent Street",
    "sg:city":"Great Yarmouth",
    "sg:classifiers":[
        {
            "category":"Professional",
            "subcategory":"Lawyer & Legal Services",
            "type":"Services"
        }
    ],
    "sg:phone":"+44 1493 853725",
    "sg:postcode":"NR30 1RR",
    "sg:province":"Norfolk",
    "sg:tags":[
        "solicitor"
    ],
    "wof:name":"Pollok Webb & Gall",
    "wof:placetype":"venue"
},
  "geometry": {"coordinates":[1.72612,52.606564],"type":"Point"}
}