{
  "type": "Feature",
  "properties": {
    "addr:full":"Robert Tresham House, Clipston Market Harborough Leicestershire LE16 9RZ",
    "addr:housenumber":"clipston",
    "addr:postcode":"le16 9rz",
    "iso:country":"GB",
    "sg:address":"Robert Tresham House, Clipston",
    "sg:city":"Market Harborough",
    "sg:classifiers":[
        {
            "category":"Real Estate",
            "subcategory":"Architect",
            "type":"Services"
        }
    ],
    "sg:postcode":"LE16 9RZ",
    "sg:province":"Leicestershire",
    "wof:name":"Jwa Architects Ltd.",
    "wof:placetype":"venue"
},
  "geometry": {"coordinates":[-0.916583,52.4702],"type":"Point"}
}