{
  "type": "Feature",
  "properties": {
    "addr:full":"4 Stanmore Road, Edgbaston Birmingham West Midlands B16 9TA",
    "addr:housenumber":"4",
    "addr:postcode":"b16 9ta",
    "addr:street":"Stanmore Road",
    "iso:country":"GB",
    "sg:address":"4 Stanmore Road, Edgbaston",
    "sg:city":"Birmingham",
    "sg:classifiers":[
        {
            "category":"Travel",
            "subcategory":"Hotels & Motels",
            "type":"Entertainment"
        }
    ],
    "sg:phone":"+44 121 429 2598",
    "sg:postcode":"B16 9TA",
    "sg:province":"West Midlands",
    "wof:name":"Prince Hotel",
    "wof:placetype":"venue"
},
  "geometry": {"coordinates":[-1.9546400309,52.4732017517],"type":"Point"}
}