{
  "type": "Feature",
  "properties": {
    "addr:full":"Unit 3 Lombard Trading Estate, Anchor & Hope Lane, Charlton London Greater London SE7 7SN",
    "addr:housenumber":"unit 3;estate",
    "addr:postcode":"se7 7sn",
    "addr:street":"Trading;Lane",
    "iso:country":"GB",
    "sg:address":"Unit 3 Lombard Trading Estate, Anchor & Hope Lane, Charlton",
    "sg:city":"London",
    "sg:classifiers":[
        {
            "category":"Building & Trades",
            "subcategory":"Construction",
            "type":"Services"
        }
    ],
    "sg:phone":"+44 20 8305 2702",
    "sg:postcode":"SE7 7SN",
    "sg:province":"Greater London",
    "sg:tags":[
        "joinery"
    ],
    "wof:name":"Sun Grace Ltd.",
    "wof:placetype":"venue"
},
  "geometry": {"coordinates":[0.0298500005,51.4909210205],"type":"Point"}
}