{
  "type": "Feature",
  "properties": {
    "iso:country":"GB",
    "sg:address":"Unit 5, Greenwich Industrial Estate",
    "sg:city":"London",
    "sg:classifiers":[
        {
            "category":"Shopping",
            "subcategory":"Stationery & Office Supplies",
            "type":"Retail Goods"
        }
    ],
    "sg:phone":"+44 20 8305 0005",
    "sg:postcode":"SE7 7AW",
    "sg:province":"Greater London",
    "sg:tags":[
        "merchant",
        "paper"
    ],
    "wof:name":"Classic Papers Ltd.",
    "wof:placetype":"venue"
},
  "geometry": {"coordinates":[0.02513,51.4883003235],"type":"Point"}
}