{
  "type": "Feature",
  "properties": {
    "addr:full":"472 Caledonian Road London Greater London N7 8TB",
    "addr:housenumber":"472",
    "addr:postcode":"n7 8tb",
    "addr:street":"Caledonian Road",
    "iso:country":"GB",
    "sg:address":"472 Caledonian Road",
    "sg:city":"London",
    "sg:classifiers":[
        {
            "category":"Shopping",
            "subcategory":"Clothing, Apparel, & Fashions",
            "type":"Retail Goods"
        },
        {
            "category":"Personal",
            "type":"Services"
        }
    ],
    "sg:phone":"+44 20 7607 0718",
    "sg:postcode":"N7 8TB",
    "sg:province":"Greater London",
    "sg:tags":[
        "shop",
        "dressmaker"
    ],
    "wof:name":"Pierre Dresses Ltd.",
    "wof:placetype":"venue"
},
  "geometry": {"coordinates":[-0.117763,51.548759],"type":"Point"}
}