{
  "type": "Feature",
  "properties": {
    "addr:full":"24-26 Peel Street Barnsley South Yorkshire S70 2QX",
    "addr:housenumber":"24-26",
    "addr:postcode":"s70 2qx",
    "addr:street":"Peel Street;Yorkshire",
    "iso:country":"GB",
    "sg:address":"24-26 Peel Street",
    "sg:city":"Barnsley",
    "sg:classifiers":[
        {
            "category":"Insurance",
            "subcategory":"Insurance Agent",
            "type":"Services"
        }
    ],
    "sg:phone":"+44 1226 298585",
    "sg:postcode":"S70 2QX",
    "sg:province":"South Yorkshire",
    "wof:name":"Budget Retail Ltd.",
    "wof:placetype":"venue"
},
  "geometry": {"coordinates":[-1.4843850136,53.5522003174],"type":"Point"}
}