{
  "type": "Feature",
  "properties": {
    "addr:full":"3 Orchard Way, Cranfield Bedford Bedfordshire MK43 0HU",
    "addr:housenumber":"3",
    "addr:postcode":"mk43 0hu",
    "addr:street":"Orchard Way",
    "iso:country":"GB",
    "sg:address":"3 Orchard Way, Cranfield",
    "sg:city":"Bedford",
    "sg:classifiers":[
        {
            "category":"Building & Trades",
            "subcategory":"Construction",
            "type":"Services"
        }
    ],
    "sg:phone":"+44 1234 750788",
    "sg:postcode":"MK43 0HU",
    "sg:province":"Bedfordshire",
    "sg:tags":[
        "dry",
        "lining",
        "plasterers",
        "screeders"
    ],
    "wof:name":"L.I Buckle",
    "wof:placetype":"venue"
},
  "geometry": {"coordinates":[-0.6081879735,52.0696334839],"type":"Point"}
}