{
  "type": "Feature",
  "properties": {
    "addr:full":"65 Duke Street London Greater London W1K 5AJ",
    "addr:housenumber":"65",
    "addr:postcode":"w1k 5aj",
    "addr:street":"Duke Street",
    "iso:country":"GB",
    "sg:address":"65 Duke Street",
    "sg:city":"London",
    "sg:classifiers":[
        {
            "category":"Banks & Credit Unions",
            "subcategory":"Bank",
            "type":"Services"
        }
    ],
    "sg:postcode":"W1K 5AJ",
    "sg:province":"Greater London",
    "wof:name":"Palladian Ltd",
    "wof:placetype":"venue"
},
  "geometry": {"coordinates":[-0.1509560049,51.5138053894],"type":"Point"}
}