{
  "type": "Feature",
  "properties": {
    "addr:full":"53 Almondvale Centre Livingston West Lothian EH54 6NB",
    "addr:housenumber":"53",
    "addr:postcode":"eh54 6nb",
    "addr:street":"Almondvale Centre",
    "iso:country":"GB",
    "sg:address":"53 Almondvale Centre",
    "sg:city":"Livingston",
    "sg:classifiers":[
        {
            "category":"Home & Garden",
            "subcategory":"Furniture",
            "type":"Retail Goods"
        }
    ],
    "sg:phone":"+44 1506 430842",
    "sg:postcode":"EH54 6NB",
    "sg:province":"West Lothian",
    "wof:name":"Rosebys",
    "wof:placetype":"venue"
},
  "geometry": {"coordinates":[-3.5204250813,55.8910865784],"type":"Point"}
}