{
  "type": "Feature",
  "properties": {
    "addr:full":"Unit 2 Wokingham Town Football G, Round Wokingham Berkshire RG40 2NR",
    "addr:housenumber":"unit 2",
    "addr:postcode":"rg40 2nr",
    "iso:country":"GB",
    "sg:address":"Unit 2 Wokingham Town Football G, Round",
    "sg:city":"Wokingham",
    "sg:classifiers":[
        {
            "category":"Military Area",
            "subcategory":"Air Force Base",
            "type":"Public Place"
        }
    ],
    "sg:postcode":"RG40 2NR",
    "sg:province":"Berkshire",
    "sg:tags":[
        "taxi",
        "hire",
        "private"
    ],
    "wof:name":"Point 2 Point Taxis",
    "wof:placetype":"venue"
},
  "geometry": {"coordinates":[-0.834594,51.410801],"type":"Point"}
}