{
  "type": "Feature",
  "properties": {
    "addr:full":"159-161 Bruntsfield Place Edinburgh City of Edinburgh EH10 4DG",
    "addr:housenumber":"159-161",
    "addr:postcode":"eh10 4dg",
    "addr:street":"Bruntsfield Place Edinburgh",
    "iso:country":"GB",
    "sg:address":"159-161 Bruntsfield Place",
    "sg:city":"Edinburgh",
    "sg:classifiers":[
        {
            "category":"Restaurant",
            "type":"Food & Drink"
        }
    ],
    "sg:phone":"+44 131 229 3115",
    "sg:postcode":"EH10 4DG",
    "sg:province":"City of Edinburgh",
    "wof:name":"Montpeliers",
    "wof:placetype":"venue"
},
  "geometry": {"coordinates":[-3.2096319199,55.9358901978],"type":"Point"}
}