{
  "type": "Feature",
  "properties": {
    "iso:country":"GB",
    "sg:address":"Syon Lane",
    "sg:city":"Isleworth",
    "sg:classifiers":[
        {
            "category":"Home & Garden",
            "subcategory":"Hardware",
            "type":"Retail Goods"
        }
    ],
    "sg:phone":"+44 20 8847 3687",
    "sg:postcode":"TW7 5NP",
    "sg:province":"Greater London",
    "sg:tags":[
        "retailer",
        "diy"
    ],
    "wof:name":"Homebase",
    "wof:placetype":"venue"
},
  "geometry": {"coordinates":[-0.335634,51.487083],"type":"Point"}
}