{
  "type": "Feature",
  "properties": {
    "addr:full":"175 High Street London Greater London E17 7BX",
    "addr:housenumber":"175",
    "addr:postcode":"e17 7bx",
    "addr:street":"High Street",
    "iso:country":"GB",
    "sg:address":"175 High Street",
    "sg:city":"London",
    "sg:classifiers":[
        {
            "category":"Shopping",
            "subcategory":"Clothing, Apparel, & Fashions",
            "type":"Retail Goods"
        }
    ],
    "sg:phone":"+44 20 8520 8621",
    "sg:postcode":"E17 7BX",
    "sg:province":"Greater London",
    "sg:tags":[
        "shop"
    ],
    "wof:name":"Goggle Boutique",
    "wof:placetype":"venue"
},
  "geometry": {"coordinates":[-0.0252589993,51.5838928223],"type":"Point"}
}