{
  "type": "Feature",
  "properties": {
    "iso:country":"GB",
    "sg:address":"Station Yard, Station Rd",
    "sg:city":"Knighton",
    "sg:classifiers":[
        {
            "category":"Manufacturing",
            "subcategory":"Petroleum Products",
            "type":"Manufacturing & Wholesale Goods"
        }
    ],
    "sg:phone":"+44 1547 528268",
    "sg:postcode":"LD7 1DT",
    "sg:province":"Shropshire",
    "sg:tags":[
        "double",
        "glazing"
    ],
    "wof:name":"Knighton Home Improvements & Double Glazing",
    "wof:placetype":"venue"
},
  "geometry": {"coordinates":[-3.04771,52.343067],"type":"Point"}
}