{
  "type": "Feature",
  "properties": {
    "addr:full":"Salisbury Road, Totton Southampton Hampshire SO40 3ND",
    "addr:postcode":"so40 3nd",
    "addr:street":"Salisbury Road",
    "iso:country":"GB",
    "sg:address":"Salisbury Road, Totton",
    "sg:city":"Southampton",
    "sg:classifiers":[
        {
            "category":"Bars & Pubs",
            "type":"Food & Drink"
        }
    ],
    "sg:phone":"+44 23 8086 8210",
    "sg:postcode":"SO40 3ND",
    "sg:province":"Hampshire",
    "sg:tags":[
        "pubs",
        "inn"
    ],
    "wof:name":"Testwood Hotel",
    "wof:placetype":"venue"
},
  "geometry": {"coordinates":[-1.491189,50.91991],"type":"Point"}
}