{
  "type": "Feature",
  "properties": {
    "iso:country":"GB",
    "sg:address":"19 Ellenborough Crescent",
    "sg:city":"Weston-super-mare",
    "sg:classifiers":[
        {
            "category":"Travel",
            "subcategory":"Hotels & Motels",
            "type":"Entertainment"
        }
    ],
    "sg:phone":"+44 1934 620832",
    "sg:postcode":"BS23 1XL",
    "sg:province":"Somerset",
    "sg:tags":[
        "self",
        "catering"
    ],
    "wof:name":"Seacrest Holiday Flats",
    "wof:placetype":"venue"
},
  "geometry": {"coordinates":[-2.975548,51.341602],"type":"Point"}
}