{
  "type": "Feature",
  "properties": {
    "addr:full":"2 Hazel Cotts, 42 Redehall Road, Smallfield Horley Surrey RH6 9QL",
    "addr:housenumber":"2;42",
    "addr:postcode":"rh6 9ql",
    "addr:street":"Hazel Cotts;Redehall Road Smallfield",
    "iso:country":"GB",
    "sg:address":"2 Hazel Cotts, 42 Redehall Road, Smallfield",
    "sg:city":"Horley",
    "sg:classifiers":[
        {
            "category":"Building & Trades",
            "subcategory":"Construction",
            "type":"Services"
        }
    ],
    "sg:phone":"+44 1342 842020",
    "sg:postcode":"RH6 9QL",
    "sg:province":"Surrey",
    "sg:tags":[
        "decorator",
        "painter"
    ],
    "wof:name":"D E King",
    "wof:placetype":"venue"
},
  "geometry": {"coordinates":[-0.116141,51.172573],"type":"Point"}
}