{
  "type": "Feature",
  "properties": {
    "iso:country":"GB",
    "sg:address":"9 Victoria Road, Ince Blundell",
    "sg:city":"Liverpool",
    "sg:classifiers":[
        {
            "category":"Retail",
            "subcategory":"Auto Repair",
            "type":"Services"
        }
    ],
    "sg:postcode":"L38 6JE",
    "sg:province":"Merseyside",
    "sg:tags":[
        "car",
        "upholsterer"
    ],
    "wof:name":"Lorankleen",
    "wof:placetype":"venue"
},
  "geometry": {"coordinates":[-3.024662,53.523136],"type":"Point"}
}