{
  "type": "Feature",
  "properties": {
    "addr:full":"232 King Cross Road Halifax West Yorkshire HX1 3JP",
    "addr:housenumber":"232",
    "addr:postcode":"hx1 3jp",
    "addr:street":"King Cross Road",
    "iso:country":"GB",
    "sg:address":"232 King Cross Road",
    "sg:city":"Halifax",
    "sg:classifiers":[
        {
            "category":"Fast Food",
            "type":"Food & Drink"
        }
    ],
    "sg:postcode":"HX1 3JP",
    "sg:province":"West Yorkshire",
    "sg:tags":[
        "away",
        "take"
    ],
    "wof:name":"Pizza King",
    "wof:placetype":"venue"
},
  "geometry": {"coordinates":[-1.8805589676,53.7154998779],"type":"Point"}
}