{
  "type": "Feature",
  "properties": {
    "addr:full":"Coopers Hill Road, Nutfield Redhill Surrey RH1 4HX",
    "addr:postcode":"rh1 4hx",
    "addr:street":"Coopers Hill Road;Redhill",
    "iso:country":"GB",
    "sg:address":"Coopers Hill Road, Nutfield",
    "sg:city":"Redhill",
    "sg:classifiers":[
        {
            "category":"Travel",
            "subcategory":"Hotels & Motels",
            "type":"Entertainment"
        }
    ],
    "sg:postcode":"RH1 4HX",
    "sg:province":"Surrey",
    "sg:tags":[
        "house",
        "guest"
    ],
    "wof:name":"Hillside Cottage",
    "wof:placetype":"venue"
},
  "geometry": {"coordinates":[-0.1244070008,51.2368812561],"type":"Point"}
}