{
  "type": "Feature",
  "properties": {
    "addr:full":"32 Invincible Drive, Armstrong Industrial Park Newcastle Upon Tyne Tyne and Wear NE4 7HX",
    "addr:housenumber":"32",
    "addr:postcode":"ne4 7hx",
    "addr:street":"Invincible Drive",
    "iso:country":"GB",
    "sg:address":"32 Invincible Drive, Armstrong Industrial Park",
    "sg:city":"Newcastle Upon Tyne",
    "sg:classifiers":[
        {
            "category":"Professional",
            "subcategory":"Printing & Photocopies",
            "type":"Services"
        }
    ],
    "sg:phone":"+44 191 273 2864",
    "sg:postcode":"NE4 7HX",
    "sg:province":"Tyne and Wear",
    "sg:tags":[
        "duplicating",
        "copying"
    ],
    "wof:name":"Service Point",
    "wof:placetype":"venue"
},
  "geometry": {"coordinates":[-1.635872,54.961853],"type":"Point"}
}