{
  "type": "Feature",
  "properties": {
    "addr:full":"Meed Ho, 21 John St Bloomsbury Greater London WC1N 2BP",
    "addr:housenumber":"21",
    "addr:postcode":"wc1n 2bp",
    "addr:street":"John St",
    "iso:country":"GB",
    "sg:address":"Meed Ho, 21 John St",
    "sg:city":"Bloomsbury",
    "sg:classifiers":[
        {
            "category":"Communications",
            "subcategory":"Newspaper",
            "type":"Services"
        }
    ],
    "sg:phone":"+44 20 7470 6200",
    "sg:postcode":"WC1N 2BP",
    "sg:province":"Greater London",
    "sg:tags":[
        "magazine"
    ],
    "wof:name":"E M A P Business Communications",
    "wof:placetype":"venue"
},
  "geometry": {"coordinates":[-0.1160100028,51.5227203369],"type":"Point"}
}