{
  "type": "Feature",
  "properties": {
    "addr:full":"T A Centre, Upper Tulse Hill Brixton Greater London SW2 2RS",
    "addr:postcode":"sw2 2rs",
    "addr:street":"Upper Tulse Hill",
    "iso:country":"GB",
    "sg:address":"T A Centre, Upper Tulse Hill",
    "sg:city":"Brixton",
    "sg:classifiers":[
        {
            "category":"Community Center",
            "subcategory":"Youth",
            "type":"Public Place"
        }
    ],
    "sg:phone":"+44 20 8678 7250",
    "sg:postcode":"SW2 2RS",
    "sg:province":"Greater London",
    "sg:tags":[
        "organisation",
        "centre"
    ],
    "wof:name":"50 F (Lambeth) Squadron Atc",
    "wof:placetype":"venue"
},
  "geometry": {"coordinates":[-0.1112489998,51.4445495605],"type":"Point"}
}