{
  "type": "Feature",
  "properties": {
    "addr:full":"Beacon House, Long Acre, Nechells Birmingham West Midlands B7 5JJ",
    "addr:postcode":"b7 5jj",
    "addr:street":"Long Acre",
    "iso:country":"GB",
    "sg:address":"Beacon House, Long Acre, Nechells",
    "sg:city":"Birmingham",
    "sg:classifiers":[
        {
            "category":"Bus Charters",
            "type":"Transportation"
        }
    ],
    "sg:phone":"+44 121 322 2707",
    "sg:postcode":"B7 5JJ",
    "sg:province":"West Midlands",
    "sg:tags":[
        "hire",
        "coach"
    ],
    "wof:name":"Flights Coach Travel",
    "wof:placetype":"venue"
},
  "geometry": {"coordinates":[-1.863964,52.501846],"type":"Point"}
}