{
  "type": "Feature",
  "properties": {
    "iso:country":"GB",
    "sg:address":"44 High Street, Methwold",
    "sg:city":"Thetford",
    "sg:classifiers":[
        {
            "category":"Manufacturing",
            "subcategory":"Tools & Machinery",
            "type":"Manufacturing & Wholesale Goods"
        }
    ],
    "sg:phone":"+44 1366 728043",
    "sg:postcode":"IP26 4NX",
    "sg:province":"Norfolk",
    "sg:tags":[
        "society",
        "friendly"
    ],
    "wof:name":"Lawrence Insurance Services",
    "wof:placetype":"venue"
},
  "geometry": {"coordinates":[0.5205929875,52.4862594604],"type":"Point"}
}