{
  "type": "Feature",
  "properties": {
    "addr:full":"4 Woodleigh Gardens Bristol City of Bristol BS14 9JA",
    "addr:housenumber":"4",
    "addr:postcode":"bs14 9ja",
    "addr:street":"Woodleigh Gardens",
    "iso:country":"GB",
    "sg:address":"4 Woodleigh Gardens",
    "sg:city":"Bristol",
    "sg:classifiers":[
        {
            "category":"Health Services",
            "subcategory":"Clinic",
            "type":"Services"
        },
        {
            "category":"Manufacturing",
            "subcategory":"Textiles",
            "type":"Manufacturing & Wholesale Goods"
        }
    ],
    "sg:postcode":"BS14 9JA",
    "sg:province":"City of Bristol",
    "sg:tags":[
        "merchant",
        "aromatherapy",
        "agent"
    ],
    "wof:name":"Byway Retail Supplies",
    "wof:placetype":"venue"
},
  "geometry": {"coordinates":[-2.5586481094,51.4137763977],"type":"Point"}
}