{
  "type": "Feature",
  "properties": {
    "addr:full":"9 Hylton Riverside Retail Park, East Timber Beach Road Sunderland Tyne and Wear SR5 3XG",
    "addr:housenumber":"9;riverside retail",
    "addr:postcode":"sr5 3xg",
    "addr:street":"Hylton;Park;Timber Beach Road",
    "iso:country":"GB",
    "sg:address":"9 Hylton Riverside Retail Park, East Timber Beach Road",
    "sg:city":"Sunderland",
    "sg:classifiers":[
        {
            "category":"Shopping",
            "subcategory":"Stationery & Office Supplies",
            "type":"Retail Goods"
        }
    ],
    "sg:phone":"+44 191 549 7521",
    "sg:postcode":"SR5 3XG",
    "sg:province":"Tyne and Wear",
    "wof:name":"Staples U K Ltd.",
    "wof:placetype":"venue"
},
  "geometry": {"coordinates":[-1.439208,54.913952],"type":"Point"}
}