{
  "type": "Feature",
  "properties": {
    "iso:country":"GB",
    "sg:address":"57 North Cray Road",
    "sg:city":"Sidcup",
    "sg:classifiers":[
        {
            "category":"Home & Garden",
            "subcategory":"Garden Supply",
            "type":"Retail Goods"
        }
    ],
    "sg:phone":"+44 20 8300 1933",
    "sg:postcode":"DA14 5EU",
    "sg:province":"Kent",
    "sg:tags":[
        "nursery",
        "centre"
    ],
    "wof:name":"Stuarts Nurseries & Garden Centre",
    "wof:placetype":"venue"
},
  "geometry": {"coordinates":[0.138834,51.429497],"type":"Point"}
}