{
  "type": "Feature",
  "properties": {
    "addr:full":"Mayhew Animal Home, Trenmar Gardens London Greater London NW10 6BJ",
    "addr:postcode":"nw10 6bj",
    "addr:street":"Gardens",
    "iso:country":"GB",
    "sg:address":"Mayhew Animal Home, Trenmar Gardens",
    "sg:city":"London",
    "sg:classifiers":[
        {
            "category":"Organizations",
            "subcategory":"Non-profit Organization",
            "type":"Services"
        }
    ],
    "sg:phone":"+44 20 7969 0178",
    "sg:postcode":"NW10 6BJ",
    "sg:province":"Greater London",
    "sg:tags":[
        "organisation",
        "animal",
        "welfare"
    ],
    "wof:name":"Royal Society for the Prevention of Cruelty to Animals",
    "wof:placetype":"venue"
},
  "geometry": {"coordinates":[-0.23291,51.531219],"type":"Point"}
}