{
  "type": "Feature",
  "properties": {
    "addr:full":"2 Town Square, Six Acre Centre, Sale Manchester Cheshire M33 7WZ",
    "addr:housenumber":"2",
    "addr:postcode":"m33 7wz",
    "addr:street":"Town Square Six Acre",
    "iso:country":"GB",
    "sg:address":"2 Town Square, Six Acre Centre, Sale",
    "sg:city":"Manchester",
    "sg:classifiers":[
        {
            "category":"Home & Garden",
            "subcategory":"Hardware",
            "type":"Retail Goods"
        }
    ],
    "sg:phone":"+44 161 905 1525",
    "sg:postcode":"M33 7WZ",
    "sg:province":"Cheshire",
    "sg:tags":[
        "retailer",
        "diy"
    ],
    "wof:name":"Wilkinson Hardware Stores Ltd.",
    "wof:placetype":"venue"
},
  "geometry": {"coordinates":[-2.2488090992,53.4796218872],"type":"Point"}
}