{
  "type": "Feature",
  "properties": {
    "addr:full":"21 Arkwright Rd, Marple Stockport Cheshire SK6 7DB",
    "addr:housenumber":"21",
    "addr:postcode":"sk6 7db",
    "addr:street":"Arkwright Rd",
    "iso:country":"GB",
    "sg:address":"21 Arkwright Rd, Marple",
    "sg:city":"Stockport",
    "sg:classifiers":[
        {
            "category":"Organizations",
            "subcategory":"Non-profit Organization",
            "type":"Services"
        }
    ],
    "sg:phone":"+44 161 449 0391",
    "sg:postcode":"SK6 7DB",
    "sg:province":"Cheshire",
    "sg:tags":[
        "organisation",
        "voluntary",
        "charity"
    ],
    "wof:name":"North East Cheshire Society for Handicapped Adults",
    "wof:placetype":"venue"
},
  "geometry": {"coordinates":[-2.0575819016,53.3993148804],"type":"Point"}
}