{
  "type": "Feature",
  "properties": {
    "iso:country":"GB",
    "sg:address":"Unit 7 The Looe, Reigate Rd",
    "sg:city":"Epsom",
    "sg:classifiers":[
        {
            "category":"Shopping",
            "subcategory":"Computers & Home Electronics",
            "type":"Retail Goods"
        }
    ],
    "sg:postcode":"KT17 3BZ",
    "sg:province":"Surrey",
    "wof:name":"Old Forge and Foundry (The)",
    "wof:placetype":"venue"
},
  "geometry": {"coordinates":[-0.23867,51.333969],"type":"Point"}
}