{
  "type": "Feature",
  "properties": {
    "iso:country":"GB",
    "sg:address":"11 High Street",
    "sg:city":"Leven",
    "sg:classifiers":[
        {
            "category":"Shopping",
            "subcategory":"Gifts & Souvenirs",
            "type":"Retail Goods"
        }
    ],
    "sg:phone":"+44 1333 428270",
    "sg:postcode":"KY8 4ND",
    "sg:province":"Fife",
    "sg:tags":[
        "poster",
        "card"
    ],
    "wof:name":"Sentiments",
    "wof:placetype":"venue"
},
  "geometry": {"coordinates":[-2.995283,56.195374],"type":"Point"}
}