{
  "type": "Feature",
  "properties": {
    "iso:country":"GB",
    "sg:address":"24 Foley Trad Est",
    "sg:city":"Hereford",
    "sg:classifiers":[
        {
            "category":"Retail",
            "subcategory":"Auto Repair",
            "type":"Services"
        }
    ],
    "sg:postcode":"HR1 2SF",
    "sg:province":"Herefordshire",
    "sg:tags":[
        "modification",
        "garage"
    ],
    "wof:name":"Bagley,Keith,",
    "wof:placetype":"venue"
},
  "geometry": {"coordinates":[-2.701537,52.052879],"type":"Point"}
}