{
  "type": "Feature",
  "properties": {
    "addr:full":"Tredegar House, Duffryn Newport East Riding of Yorkshire NP1 8QL",
    "addr:postcode":"8ql",
    "addr:street":"Riding",
    "iso:country":"GB",
    "sg:address":"Tredegar House, Duffryn",
    "sg:city":"Newport",
    "sg:classifiers":[
        {
            "category":"Community Center",
            "type":"Public Place"
        }
    ],
    "sg:phone":"+44 1633 810264",
    "sg:postcode":"NP1 8QL",
    "sg:province":"East Riding of Yorkshire",
    "sg:tags":[
        "recreation",
        "leisure",
        "centre"
    ],
    "wof:name":"Duffryn Community Centre",
    "wof:placetype":"venue"
},
  "geometry": {"coordinates":[-3.052874,51.579769],"type":"Point"}
}