{
  "type": "Feature",
  "properties": {
    "addr:full":"Clout Cottage, Lenham Heath Rd, Sandway Maidstone Kent ME17 2HX",
    "addr:postcode":"me17 2hx",
    "addr:street":"Heath Rd",
    "iso:country":"GB",
    "sg:address":"Clout Cottage, Lenham Heath Rd, Sandway",
    "sg:city":"Maidstone",
    "sg:classifiers":[
        {
            "category":"Manufacturing",
            "subcategory":"Furniture",
            "type":"Manufacturing & Wholesale Goods"
        }
    ],
    "sg:phone":"+44 1622 859036",
    "sg:postcode":"ME17 2HX",
    "sg:province":"Kent",
    "sg:tags":[
        "mnfr",
        "garden",
        "patio"
    ],
    "wof:name":"Pots & Pitchers",
    "wof:placetype":"venue"
},
  "geometry": {"coordinates":[0.740865,51.215012],"type":"Point"}
}