{
  "type": "Feature",
  "properties": {
    "iso:country":"GB",
    "sg:address":"Orchard Cottage, Arkley Lane Arkley",
    "sg:city":"Barnet",
    "sg:classifiers":[
        {
            "category":"Banks & Credit Unions",
            "subcategory":"Investment Brokerage",
            "type":"Services"
        }
    ],
    "sg:postcode":"EN5 3JW",
    "sg:province":"Hertfordshire",
    "sg:tags":[
        "property",
        "broker",
        "commodity"
    ],
    "wof:name":"Blackheath Resources Ltd",
    "wof:placetype":"venue"
},
  "geometry": {"coordinates":[-0.229769,51.648415],"type":"Point"}
}