{
  "type": "Feature",
  "properties": {
    "iso:country":"GB",
    "sg:address":"High Road, Wortwell",
    "sg:city":"Harleston",
    "sg:classifiers":[
        {
            "category":"Recreation",
            "subcategory":"Campground",
            "type":"Entertainment"
        }
    ],
    "sg:postcode":"IP20 0EL",
    "sg:province":"Norfolk",
    "sg:tags":[
        "caravan",
        "park"
    ],
    "wof:name":"Little Lakeland Caravan Park",
    "wof:placetype":"venue"
},
  "geometry": {"coordinates":[1.34717,52.41584],"type":"Point"}
}