{
  "type": "Feature",
  "properties": {
    "addr:full":"The Old Rectory, Church La Newark Lincolnshire NG23 5RB",
    "addr:postcode":"ng23 5rb",
    "addr:street":"La Newark",
    "iso:country":"GB",
    "sg:address":"The Old Rectory, Church La",
    "sg:city":"Newark",
    "sg:classifiers":[
        {
            "category":"Travel",
            "subcategory":"Hotels & Motels",
            "type":"Entertainment"
        }
    ],
    "sg:phone":"+44 1636 707655",
    "sg:postcode":"NG23 5RB",
    "sg:province":"Lincolnshire",
    "sg:tags":[
        "house",
        "guest"
    ],
    "wof:name":"Robin Hood Accommodation",
    "wof:placetype":"venue"
},
  "geometry": {"coordinates":[-0.85817,53.081829],"type":"Point"}
}