{
  "type": "Feature",
  "properties": {
    "addr:full":"Bishops Court, Rectory Lane, Whickham Newcastle-upon-tyne Durham NE16 4PA",
    "addr:postcode":"ne16 4pa",
    "addr:street":"Bishops;Rectory Lane",
    "iso:country":"GB",
    "sg:address":"Bishops Court, Rectory Lane, Whickham",
    "sg:city":"Newcastle-upon-tyne",
    "sg:classifiers":[
        {
            "category":"Real Estate",
            "subcategory":"Architect",
            "type":"Services"
        }
    ],
    "sg:phone":"+44 191 420 3090",
    "sg:postcode":"NE16 4PA",
    "sg:province":"Durham",
    "wof:name":"Nicholson Nairn Architects",
    "wof:placetype":"venue"
},
  "geometry": {"coordinates":[-1.677474,54.943111],"type":"Point"}
}