{
  "type": "Feature",
  "properties": {
    "iso:country":"GB",
    "sg:address":"159 Sloane Street",
    "sg:city":"London",
    "sg:classifiers":[
        {
            "category":"Travel",
            "subcategory":"Travel Agent",
            "type":"Entertainment"
        }
    ],
    "sg:phone":"+44 20 7730 0721",
    "sg:postcode":"SW1X 9BT",
    "sg:province":"Greater London",
    "wof:name":"Cadogan Travel Ltd.",
    "wof:placetype":"venue"
},
  "geometry": {"coordinates":[-0.157958,51.494049],"type":"Point"}
}