{
  "type": "Feature",
  "properties": {
    "addr:full":"71 Gresham Drive, West Hunsbury Northampton Northamptonshire NN4 9SB",
    "addr:housenumber":"71",
    "addr:postcode":"nn4 9sb",
    "addr:street":"Gresham Drive West Hunsbury",
    "iso:country":"GB",
    "sg:address":"71 Gresham Drive, West Hunsbury",
    "sg:city":"Northampton",
    "sg:classifiers":[
        {
            "category":"Building & Trades",
            "subcategory":"Construction",
            "type":"Services"
        }
    ],
    "sg:postcode":"NN4 9SB",
    "sg:province":"Northamptonshire",
    "sg:tags":[
        "builder"
    ],
    "wof:name":"Malcolm H Smith Building Contractor",
    "wof:placetype":"venue"
},
  "geometry": {"coordinates":[-0.93166399,52.2208480835],"type":"Point"}
}