{
  "type": "Feature",
  "properties": {
    "addr:full":"Stubbers Grn Road, Aldridge Walsall Staffordshire WS9 8BN",
    "addr:postcode":"ws9 8bn",
    "addr:street":"Stubbers Grn Road",
    "iso:country":"GB",
    "sg:address":"Stubbers Grn Road, Aldridge",
    "sg:city":"Walsall",
    "sg:classifiers":[
        {
            "category":"Building & Trades",
            "subcategory":"Construction",
            "type":"Services"
        }
    ],
    "sg:phone":"+44 1922 451909",
    "sg:postcode":"WS9 8BN",
    "sg:province":"Staffordshire",
    "sg:tags":[
        "contractor"
    ],
    "wof:name":"Special Formwork Ltd.",
    "wof:placetype":"venue"
},
  "geometry": {"coordinates":[-1.934316,52.611504],"type":"Point"}
}