{
  "type": "Feature",
  "properties": {
    "addr:full":"9 Brunel Gate Andover Hampshire SP10 3SL",
    "addr:housenumber":"9",
    "addr:postcode":"sp10 3sl",
    "addr:street":"Brunel Gate",
    "iso:country":"GB",
    "sg:address":"9 Brunel Gate",
    "sg:city":"Andover",
    "sg:classifiers":[
        {
            "category":"Manufacturing",
            "subcategory":"Wood Products",
            "type":"Manufacturing & Wholesale Goods"
        }
    ],
    "sg:phone":"+44 1264 357511",
    "sg:postcode":"SP10 3SL",
    "sg:province":"Hampshire",
    "sg:tags":[
        "packaging",
        "crate",
        "pallets"
    ],
    "wof:name":"Loveshaw Europe",
    "wof:placetype":"venue"
},
  "geometry": {"coordinates":[-1.514914,51.216911],"type":"Point"}
}