{
  "type": "Feature",
  "properties": {
    "addr:full":"York Street, Audenshaw Manchester Greater Manchester M34 5HW",
    "addr:postcode":"m34 5hw",
    "addr:street":"York Street",
    "iso:country":"GB",
    "sg:address":"York Street, Audenshaw",
    "sg:city":"Manchester",
    "sg:classifiers":[
        {
            "category":"Home & Garden",
            "subcategory":"Building Materials",
            "type":"Retail Goods"
        }
    ],
    "sg:phone":"+44 161 339 0442",
    "sg:postcode":"M34 5HW",
    "sg:province":"Greater Manchester",
    "sg:tags":[
        "insulation",
        "installers"
    ],
    "wof:name":"McVeigh Insulations Ltd.",
    "wof:placetype":"venue"
},
  "geometry": {"coordinates":[-2.1291790009,53.4712753296],"type":"Point"}
}