{
  "type": "Feature",
  "properties": {
    "addr:full":"Braidhaugh Crieff Perth and Kinross PH7 4HP",
    "addr:postcode":"ph7 4hp",
    "iso:country":"GB",
    "sg:address":"Braidhaugh",
    "sg:city":"Crieff",
    "sg:classifiers":[
        {
            "category":"Arena",
            "subcategory":"Sports Club",
            "type":"Entertainment"
        }
    ],
    "sg:phone":"+44 1764 654311",
    "sg:postcode":"PH7 4HP",
    "sg:province":"Perth and Kinross",
    "wof:name":"Crieff Cricket & Rugby Club",
    "wof:placetype":"venue"
},
  "geometry": {"coordinates":[-3.839511,56.372738],"type":"Point"}
}