{
  "type": "Feature",
  "properties": {
    "iso:country":"GB",
    "sg:address":"Main St",
    "sg:city":"Dunfermline",
    "sg:classifiers":[
        {
            "category":"Community Center",
            "type":"Public Place"
        }
    ],
    "sg:phone":"+44 1383 724210",
    "sg:postcode":"KY12 0EN",
    "sg:province":"Fife",
    "sg:tags":[
        "centre"
    ],
    "wof:name":"Townhill Community Leisure Centre",
    "wof:placetype":"venue"
},
  "geometry": {"coordinates":[-3.406794,56.099468],"type":"Point"}
}