{
  "type": "Feature",
  "properties": {
    "iso:country":"GB",
    "sg:address":"214 York Road, Haxby",
    "sg:city":"York",
    "sg:classifiers":[
        {
            "category":"Shopping",
            "subcategory":"Antiques",
            "type":"Retail Goods"
        }
    ],
    "sg:postcode":"YO32 3HA",
    "sg:province":"North Yorkshire",
    "wof:name":"Acorn Antiques",
    "wof:placetype":"venue"
},
  "geometry": {"coordinates":[-1.074092,54.00547],"type":"Point"}
}