{
  "type": "Feature",
  "properties": {
    "addr:full":"19 Belmore Park Ashford Kent TN24 8UW",
    "addr:housenumber":"19",
    "addr:postcode":"tn24 8uw",
    "addr:street":"Belmore Park",
    "iso:country":"GB",
    "sg:address":"19 Belmore Park",
    "sg:city":"Ashford",
    "sg:classifiers":[
        {
            "category":"Professional",
            "subcategory":"Engineering",
            "type":"Services"
        }
    ],
    "sg:phone":"+44 1233 639094",
    "sg:postcode":"TN24 8UW",
    "sg:province":"Kent",
    "sg:tags":[
        "contractor",
        "electrical",
        "engineer"
    ],
    "wof:name":"Crs Electrical Installations",
    "wof:placetype":"venue"
},
  "geometry": {"coordinates":[0.868538,51.154202],"type":"Point"}
}