{
  "type": "Feature",
  "properties": {
    "addr:full":"Fen Road, Owmby By Spital Market Rasen Lincolnshire LN8 2HP",
    "addr:postcode":"ln8 2hp",
    "addr:street":"Fen Road",
    "iso:country":"GB",
    "sg:address":"Fen Road, Owmby By Spital",
    "sg:city":"Market Rasen",
    "sg:classifiers":[
        {
            "category":"Building & Trades",
            "subcategory":"Construction",
            "type":"Services"
        }
    ],
    "sg:phone":"+44 1673 878303",
    "sg:postcode":"LN8 2HP",
    "sg:province":"Lincolnshire",
    "sg:tags":[
        "builder"
    ],
    "sg:website":"http://www.mwcrowe.ltd.uk",
    "wof:name":"M W Crowe Ltd",
    "wof:placetype":"venue"
},
  "geometry": {"coordinates":[-0.4960870147,53.3746566772],"type":"Point"}
}