{
  "type": "Feature",
  "properties": {
    "iso:country":"GB",
    "sg:address":"9 Wallbridge Industrial Estate, Wallbridge",
    "sg:city":"Stroud",
    "sg:classifiers":[
        {
            "category":"Retail",
            "subcategory":"Auto Repair",
            "type":"Services"
        }
    ],
    "sg:phone":"+44 1453 752878",
    "sg:postcode":"GL5 3JU",
    "sg:province":"Gloucestershire",
    "sg:tags":[
        "garage"
    ],
    "wof:name":"Wyatt Engineering Fuel Services",
    "wof:placetype":"venue"
},
  "geometry": {"coordinates":[-2.2219998837,51.7434806824],"type":"Point"}
}