{
  "type": "Feature",
  "properties": {
    "iso:country":"GB",
    "sg:address":"61 Market Street",
    "sg:city":"Ashby-de-la-zouch",
    "sg:classifiers":[
        {
            "category":"Shopping",
            "subcategory":"Department Store",
            "type":"Retail Goods"
        },
        {
            "category":"Shopping",
            "subcategory":"Clothing, Apparel, & Fashions",
            "type":"Retail Goods"
        }
    ],
    "sg:phone":"+44 1530 414924",
    "sg:postcode":"LE65 1AH",
    "sg:province":"Derbyshire",
    "sg:tags":[
        "shop",
        "departmental"
    ],
    "sg:website":"http://www.peacocks.co.uk",
    "wof:name":"Peacocks Stores Ltd",
    "wof:placetype":"venue"
},
  "geometry": {"coordinates":[-1.4733439684,52.7466506958],"type":"Point"}
}