{
  "type": "Feature",
  "properties": {
    "iso:country":"GB",
    "sg:address":"11 Station Hill",
    "sg:city":"Chippenham",
    "sg:classifiers":[
        {
            "category":"Professional",
            "subcategory":"Art Services",
            "type":"Services"
        }
    ],
    "sg:phone":"+44 1249 446220",
    "sg:postcode":"SN15 1EQ",
    "sg:province":"Wiltshire",
    "sg:tags":[
        "picture",
        "framing"
    ],
    "wof:name":"The Picture Shop",
    "wof:placetype":"venue"
},
  "geometry": {"coordinates":[-2.117655,51.46122],"type":"Point"}
}