{
  "type": "Feature",
  "properties": {
    "addr:full":"Lincoln View Worksop Nottinghamshire S80 2NP",
    "addr:postcode":"s80 2np",
    "addr:street":"Lincoln",
    "iso:country":"GB",
    "sg:address":"Lincoln View",
    "sg:city":"Worksop",
    "sg:classifiers":[
        {
            "category":"Retail",
            "subcategory":"Auto Repair",
            "type":"Services"
        }
    ],
    "sg:postcode":"S80 2NP",
    "sg:province":"Nottinghamshire",
    "sg:tags":[
        "modification",
        "garage"
    ],
    "wof:name":"J Wheeldon",
    "wof:placetype":"venue"
},
  "geometry": {"coordinates":[-1.113476038,53.3016929626],"type":"Point"}
}