{
  "type": "Feature",
  "properties": {
    "iso:country":"GB",
    "sg:address":"Red House Farm, Aspall",
    "sg:city":"Stowmarket",
    "sg:classifiers":[
        {
            "category":"Farming",
            "subcategory":"Crops",
            "type":"Manufacturing & Wholesale Goods"
        },
        {
            "category":"Farming",
            "subcategory":"Farm",
            "type":"Manufacturing & Wholesale Goods"
        }
    ],
    "sg:phone":"+44 1728 860599",
    "sg:postcode":"IP14 6NS",
    "sg:province":"Suffolk",
    "sg:tags":[
        "mixed",
        "arable"
    ],
    "wof:name":"C J R FREEMAN & PARTNERS",
    "wof:placetype":"venue"
},
  "geometry": {"coordinates":[1.178910017,52.2426605225],"type":"Point"}
}