{
  "type": "Feature",
  "properties": {
    "addr:full":"91a South St Lancing West Sussex BN15 8AP",
    "addr:housenumber":"91a",
    "addr:postcode":"bn15 8ap",
    "addr:street":"South St",
    "iso:country":"GB",
    "sg:address":"91a South St",
    "sg:city":"Lancing",
    "sg:classifiers":[
        {
            "category":"Communications",
            "subcategory":"Newspaper",
            "type":"Services"
        }
    ],
    "sg:phone":"+44 1903 523000",
    "sg:postcode":"BN15 8AP",
    "sg:province":"West Sussex",
    "sg:tags":[
        "magazine"
    ],
    "wof:name":"Baseline Enterprises",
    "wof:placetype":"venue"
},
  "geometry": {"coordinates":[-0.3234870136,50.8233833313],"type":"Point"}
}