{
  "type": "Feature",
  "properties": {
    "addr:full":"88-90 North Hill London Greater London N6 4RL",
    "addr:housenumber":"88-90",
    "addr:postcode":"n6 4rl",
    "addr:street":"North Hill",
    "iso:country":"GB",
    "sg:address":"88-90 North Hill",
    "sg:city":"London",
    "sg:classifiers":[
        {
            "category":"Real Estate",
            "subcategory":"Real Estate Services",
            "type":"Services"
        },
        {
            "category":"Real Estate",
            "subcategory":"Real Estate Agent",
            "type":"Services"
        }
    ],
    "sg:phone":"+44 20 8340 5050",
    "sg:postcode":"N6 4RL",
    "sg:province":"Greater London",
    "sg:tags":[
        "management"
    ],
    "wof:name":"Christopher A Holder",
    "wof:placetype":"venue"
},
  "geometry": {"coordinates":[-0.155334,51.58078],"type":"Point"}
}