{
  "type": "Feature",
  "properties": {
    "addr:full":"Keeling Hall Road, Foulsham Dereham Norfolk NR20 5PR",
    "addr:postcode":"nr20 5pr",
    "addr:street":"Hall Road;Dereham",
    "iso:country":"GB",
    "sg:address":"Keeling Hall Road, Foulsham",
    "sg:city":"Dereham",
    "sg:classifiers":[
        {
            "category":"Manufacturing",
            "subcategory":"Metals",
            "type":"Manufacturing & Wholesale Goods"
        }
    ],
    "sg:phone":"+44 1362 684105",
    "sg:postcode":"NR20 5PR",
    "sg:province":"Norfolk",
    "sg:tags":[
        "fab",
        "foundry"
    ],
    "wof:name":"Marshall Brass",
    "wof:placetype":"venue"
},
  "geometry": {"coordinates":[1.0100250244,52.7805099487],"type":"Point"}
}