{
  "type": "Feature",
  "properties": {
    "iso:country":"GB",
    "sg:address":"36 The Mall",
    "sg:city":"Grays",
    "sg:classifiers":[
        {
            "category":"Food & Beverages",
            "subcategory":"Meat & Fish",
            "type":"Retail Goods"
        }
    ],
    "sg:postcode":"RM17 6QF",
    "sg:province":"Essex",
    "sg:tags":[
        "butcher"
    ],
    "wof:name":"Meat Express",
    "wof:placetype":"venue"
},
  "geometry": {"coordinates":[0.3455780149,51.4761123657],"type":"Point"}
}