{
  "type": "Feature",
  "properties": {
    "addr:full":"375 City Road London Greater London EC1V 1NB",
    "addr:housenumber":"375",
    "addr:postcode":"ec1v 1nb",
    "addr:street":"City Road",
    "iso:country":"GB",
    "sg:address":"375 City Road",
    "sg:city":"London",
    "sg:classifiers":[
        {
            "category":"Communications",
            "type":"Services"
        }
    ],
    "sg:phone":"+44 20 7837 3000",
    "sg:postcode":"EC1V 1NB",
    "sg:province":"Greater London",
    "sg:tags":[
        "audio-visual"
    ],
    "wof:name":"On Line Editing Ltd.",
    "wof:placetype":"venue"
},
  "geometry": {"coordinates":[-0.088079,51.526711],"type":"Point"}
}