{
  "type": "Feature",
  "properties": {
    "addr:full":"640 Newchurch Road Rossendale Lancashire BB4 9HG",
    "addr:housenumber":"640",
    "addr:postcode":"bb4 9hg",
    "addr:street":"Newchurch Road",
    "iso:country":"GB",
    "sg:address":"640 Newchurch Road",
    "sg:city":"Rossendale",
    "sg:classifiers":[
        {
            "category":"Professional",
            "subcategory":"Business Services",
            "type":"Services"
        }
    ],
    "sg:postcode":"BB4 9HG",
    "sg:province":"Lancashire",
    "sg:tags":[
        "holding"
    ],
    "wof:name":"The Rossendale United Holdings Ltd.  (the)",
    "wof:placetype":"venue"
},
  "geometry": {"coordinates":[-2.2595880032,53.6995582581],"type":"Point"}
}