{
  "type": "Feature",
  "properties": {
    "iso:country":"GB",
    "sg:address":"28-32 King Street",
    "sg:city":"King's Lynn",
    "sg:classifiers":[
        {
            "category":"Professional",
            "subcategory":"Lawyer & Legal Services",
            "type":"Services"
        }
    ],
    "sg:phone":"+44 1553 778100",
    "sg:postcode":"PE30 1HQ",
    "sg:province":"Norfolk",
    "sg:tags":[
        "solicitor"
    ],
    "sg:website":"http://www.mcp-law.co.uk",
    "wof:name":"Metcalfe Copeman & Pettefar",
    "wof:placetype":"venue"
},
  "geometry": {"coordinates":[0.393924,52.755016],"type":"Point"}
}