{
  "type": "Feature",
  "properties": {
    "addr:full":", Llangybi Pwllheli Gwynedd LL53 6DQ",
    "addr:postcode":"ll53 6dq",
    "iso:country":"GB",
    "sg:address":", Llangybi",
    "sg:city":"Pwllheli",
    "sg:classifiers":[
        {
            "category":"Education",
            "subcategory":"School",
            "type":"Public Place"
        }
    ],
    "sg:phone":"+44 1766 810564",
    "sg:postcode":"LL53 6DQ",
    "sg:province":"Gwynedd",
    "sg:tags":[
        "local",
        "authority"
    ],
    "wof:name":"Llangybi Primary School",
    "wof:placetype":"venue"
},
  "geometry": {"coordinates":[-4.4511089325,52.9379310608],"type":"Point"}
}