{
  "type": "Feature",
  "properties": {
    "addr:full":"Unit 4 Barnby Gate Newark Nottinghamshire NG24 1PZ",
    "addr:housenumber":"unit 4",
    "addr:postcode":"ng24 1pz",
    "addr:street":"Barnby Gate",
    "iso:country":"GB",
    "sg:address":"Unit 4 Barnby Gate",
    "sg:city":"Newark",
    "sg:classifiers":[
        {
            "category":"Manufacturing",
            "subcategory":"Petroleum Products",
            "type":"Manufacturing & Wholesale Goods"
        }
    ],
    "sg:phone":"+44 1636 610484",
    "sg:postcode":"NG24 1PZ",
    "sg:province":"Nottinghamshire",
    "sg:tags":[
        "double",
        "glazing"
    ],
    "wof:name":"Heatseal Windows",
    "wof:placetype":"venue"
},
  "geometry": {"coordinates":[-0.80469,53.075035],"type":"Point"}
}