{
  "type": "Feature",
  "properties": {
    "addr:full":"Foss Bank Farm, Strensall Road, Earswick York North Yorkshire YO32 9SW",
    "addr:postcode":"yo32 9sw",
    "addr:street":"Strensall Road",
    "iso:country":"GB",
    "sg:address":"Foss Bank Farm, Strensall Road, Earswick",
    "sg:city":"York",
    "sg:classifiers":[
        {
            "category":"Transit Center",
            "subcategory":"Passenger",
            "type":"Transportation"
        },
        {
            "category":"Retail",
            "subcategory":"Pet Boarding",
            "type":"Services"
        }
    ],
    "sg:phone":"+44 1904 766952",
    "sg:postcode":"YO32 9SW",
    "sg:province":"North Yorkshire",
    "sg:tags":[
        "kennel",
        "catteries"
    ],
    "wof:name":"Foss Bank Kennels",
    "wof:placetype":"venue"
},
  "geometry": {"coordinates":[-1.058049,54.004883],"type":"Point"}
}