{
  "type": "Feature",
  "properties": {
    "iso:country":"GB",
    "sg:address":"Bush House, 72 Prince Street",
    "sg:city":"Bristol",
    "sg:classifiers":[
        {
            "category":"Professional",
            "subcategory":"Lawyer & Legal Services",
            "type":"Services"
        }
    ],
    "sg:phone":"+44 117 917 7777",
    "sg:postcode":"BS99 7JZ",
    "sg:province":"City of Bristol",
    "sg:tags":[
        "solicitor"
    ],
    "wof:name":"Sarah Mumford",
    "wof:placetype":"venue"
},
  "geometry": {"coordinates":[-2.596862,51.449619],"type":"Point"}
}