{
  "type": "Feature",
  "properties": {
    "iso:country":"GB",
    "sg:address":"Lincoln Road, Fenton",
    "sg:city":"Lincoln",
    "sg:classifiers":[
        {
            "category":"Travel",
            "subcategory":"Hotels & Motels",
            "type":"Entertainment"
        }
    ],
    "sg:postcode":"LN1 2EN",
    "sg:province":"Lincolnshire",
    "wof:name":"Trenton Lodge & Restaurant",
    "wof:placetype":"venue"
},
  "geometry": {"coordinates":[-0.7353559732,53.2809524536],"type":"Point"}
}