{
  "type": "Feature",
  "properties": {
    "iso:country":"GB",
    "sg:address":"2 Sycamore Close, Holmes Chapel",
    "sg:city":"Crewe",
    "sg:classifiers":[
        {
            "category":"Utilities",
            "subcategory":"Natural Gas",
            "type":"Services"
        }
    ],
    "sg:phone":"+44 1477 532729",
    "sg:postcode":"CW4 7BT",
    "sg:province":"Cheshire",
    "sg:tags":[
        "control",
        "energy",
        "management",
        "system"
    ],
    "wof:name":"Sycamore Services",
    "wof:placetype":"venue"
},
  "geometry": {"coordinates":[-2.352336,53.201588],"type":"Point"}
}