{
  "type": "Feature",
  "properties": {
    "iso:country":"GB",
    "sg:address":"49 Middle Street North",
    "sg:city":"Driffield",
    "sg:classifiers":[
        {
            "category":"Professional",
            "subcategory":"Art Services",
            "type":"Services"
        },
        {
            "category":"Building & Trades",
            "subcategory":"Construction",
            "type":"Services"
        }
    ],
    "sg:phone":"+44 1377 252266",
    "sg:postcode":"YO25 6SS",
    "sg:province":"East Riding of Yorkshire",
    "sg:tags":[
        "decorator",
        "painter"
    ],
    "wof:name":"E E Dobson & Sons",
    "wof:placetype":"venue"
},
  "geometry": {"coordinates":[-0.4375360012,54.0039558411],"type":"Point"}
}