{
  "type": "Feature",
  "properties": {
    "iso:country":"GB",
    "sg:address":"Spring Grove, Penistone Road, Kirkburton",
    "sg:city":"Huddersfield",
    "sg:classifiers":[
        {
            "category":"Wholesale",
            "subcategory":"Machinery & Supplies",
            "type":"Manufacturing & Wholesale Goods"
        },
        {
            "category":"Manufacturing",
            "subcategory":"Building Materials",
            "type":"Manufacturing & Wholesale Goods"
        }
    ],
    "sg:phone":"+44 1484 601400",
    "sg:postcode":"HD8 0PL",
    "sg:province":"South Yorkshire",
    "sg:tags":[
        "equipment",
        "handling",
        "lifting"
    ],
    "wof:name":"Easilift Loading Systems Ltd",
    "wof:placetype":"venue"
},
  "geometry": {"coordinates":[-1.701374,53.607441],"type":"Point"}
}