{
  "type": "Feature",
  "properties": {
    "iso:country":"GB",
    "sg:address":"Netherwood Farm House",
    "sg:city":"Kilmacolm",
    "sg:classifiers":[
        {
            "category":"Farming",
            "subcategory":"Livestock Farm",
            "type":"Manufacturing & Wholesale Goods"
        }
    ],
    "sg:postcode":"PA13 4SX",
    "sg:province":"Inverclyde",
    "sg:tags":[
        "others"
    ],
    "wof:name":"Mathew Wilson",
    "wof:placetype":"venue"
},
  "geometry": {"coordinates":[-4.6301999092,55.8926010132],"type":"Point"}
}