{
  "type": "Feature",
  "properties": {
    "iso:country":"GB",
    "sg:address":"66 High Road, Byfleet",
    "sg:city":"West Byfleet",
    "sg:classifiers":[
        {
            "category":"Professional",
            "type":"Services"
        }
    ],
    "sg:phone":"+44 1932 352300",
    "sg:postcode":"KT14 7QL",
    "sg:province":"Surrey",
    "sg:tags":[
        "caterer"
    ],
    "wof:name":"Truffles",
    "wof:placetype":"venue"
},
  "geometry": {"coordinates":[-0.476746,51.338737],"type":"Point"}
}