{
  "type": "Feature",
  "properties": {
    "addr:full":"4b Martindale Cannock Staffordshire WS11 2XN",
    "addr:housenumber":"4b",
    "addr:postcode":"ws11 2xn",
    "addr:street":"Martindale",
    "iso:country":"GB",
    "sg:address":"4b Martindale",
    "sg:city":"Cannock",
    "sg:classifiers":[
        {
            "category":"Building & Trades",
            "subcategory":"Construction",
            "type":"Services"
        }
    ],
    "sg:phone":"+44 1543 579303",
    "sg:postcode":"WS11 2XN",
    "sg:province":"Staffordshire",
    "sg:tags":[
        "welder"
    ],
    "wof:name":"Weldall",
    "wof:placetype":"venue"
},
  "geometry": {"coordinates":[-2.012826,52.694427],"type":"Point"}
}