{
  "type": "Feature",
  "properties": {
    "addr:full":"Hilton Main Indstl Est Wolverhampton Staffordshire WV10 7HP",
    "addr:postcode":"wv10 7hp",
    "addr:street":"Indstl Est",
    "iso:country":"GB",
    "sg:address":"Hilton Main Indstl Est",
    "sg:city":"Wolverhampton",
    "sg:classifiers":[
        {
            "category":"Manufacturing",
            "subcategory":"Building Materials",
            "type":"Manufacturing & Wholesale Goods"
        }
    ],
    "sg:postcode":"WV10 7HP",
    "sg:province":"Staffordshire",
    "sg:tags":[
        "concrete",
        "product"
    ],
    "wof:name":"Tarmac Topblock 1996 Ltd",
    "wof:placetype":"venue"
},
  "geometry": {"coordinates":[-2.121669,52.58865],"type":"Point"}
}