{
  "type": "Feature",
  "properties": {
    "addr:full":"40 Chidswell Lane, Chidwell Dewsbury West Yorkshire WF12 7SD",
    "addr:housenumber":"40",
    "addr:postcode":"wf12 7sd",
    "addr:street":"Chidswell Lane",
    "iso:country":"GB",
    "sg:address":"40 Chidswell Lane, Chidwell",
    "sg:city":"Dewsbury",
    "sg:classifiers":[
        {
            "category":"Manufacturing",
            "subcategory":"Building Materials",
            "type":"Manufacturing & Wholesale Goods"
        }
    ],
    "sg:phone":"+44 1924 455459",
    "sg:postcode":"WF12 7SD",
    "sg:province":"West Yorkshire",
    "sg:tags":[
        "tarmac",
        "asphalt"
    ],
    "wof:name":"Construction Dad Ltd.",
    "wof:placetype":"venue"
},
  "geometry": {"coordinates":[-1.599246,53.704704],"type":"Point"}
}