{
  "type": "Feature",
  "properties": {
    "addr:full":"22 The Centre, Rawtenstall Rossendale Lancashire BB4 7QQ",
    "addr:housenumber":"22",
    "addr:postcode":"bb4 7qq",
    "addr:street":"The Centre Rawtenstall",
    "iso:country":"GB",
    "sg:address":"22 The Centre, Rawtenstall",
    "sg:city":"Rossendale",
    "sg:classifiers":[
        {
            "category":"Retail",
            "subcategory":"Photofinishing",
            "type":"Services"
        }
    ],
    "sg:phone":"+44 1706 217986",
    "sg:postcode":"BB4 7QQ",
    "sg:province":"Lancashire",
    "sg:tags":[
        "photographic",
        "processor"
    ],
    "wof:name":"Sketchley Retail Ltd.",
    "wof:placetype":"venue"
},
  "geometry": {"coordinates":[-2.2798690796,53.7003707886],"type":"Point"}
}