{
  "type": "Feature",
  "properties": {
    "iso:country":"GB",
    "sg:address":"3 Albion Street",
    "sg:city":"Castleford",
    "sg:classifiers":[
        {
            "category":"Food & Beverages",
            "subcategory":"Fruits & Vegetables",
            "type":"Retail Goods"
        }
    ],
    "sg:phone":"+44 1977 558278",
    "sg:postcode":"WF10 1EG",
    "sg:province":"West Yorkshire",
    "sg:tags":[
        "greengrocer"
    ],
    "wof:name":"Brian Copley",
    "wof:placetype":"venue"
},
  "geometry": {"coordinates":[-1.356201,53.725662],"type":"Point"}
}