{
  "type": "Feature",
  "properties": {
    "addr:full":"3 St Marys Gate Derby Derbyshire DE1 3JE",
    "addr:housenumber":"3",
    "addr:postcode":"de1 3je",
    "addr:street":"St Marys Gate",
    "iso:country":"GB",
    "sg:address":"3 St Marys Gate",
    "sg:city":"Derby",
    "sg:classifiers":[
        {
            "category":"Professional",
            "subcategory":"Lawyer & Legal Services",
            "type":"Services"
        }
    ],
    "sg:phone":"+44 1332 346018",
    "sg:postcode":"DE1 3JE",
    "sg:province":"Derbyshire",
    "sg:tags":[
        "solicitor"
    ],
    "wof:name":"Robotham & Co",
    "wof:placetype":"venue"
},
  "geometry": {"coordinates":[-1.4712450504,52.9303245544],"type":"Point"}
}