{
  "type": "Feature",
  "properties": {
    "iso:country":"GB",
    "sg:address":"Mount Pleasant Industrial Estate",
    "sg:city":"Oldham",
    "sg:classifiers":[
        {
            "category":"Autos & Motor Vehicles",
            "subcategory":"Auto Supplies",
            "type":"Retail Goods"
        }
    ],
    "sg:postcode":"OL4 1HD",
    "sg:province":"Lancashire",
    "sg:tags":[
        "tyre"
    ],
    "wof:name":"A C Tyres",
    "wof:placetype":"venue"
},
  "geometry": {"coordinates":[-2.0940859318,53.5425186157],"type":"Point"}
}