{
  "type": "Feature",
  "properties": {
    "iso:country":"GB",
    "sg:address":"1 Manor Square",
    "sg:city":"Otley",
    "sg:classifiers":[
        {
            "category":"Autos & Motor Vehicles",
            "subcategory":"Auto Supplies",
            "type":"Retail Goods"
        },
        {
            "category":"Shopping",
            "type":"Retail Goods"
        }
    ],
    "sg:phone":"+44 1943 850358",
    "sg:postcode":"LS21 3AP",
    "sg:province":"North Yorkshire",
    "sg:tags":[
        "car",
        "part",
        "accessory"
    ],
    "wof:name":"Motor World Ltd",
    "wof:placetype":"venue"
},
  "geometry": {"coordinates":[-1.694904,53.906471],"type":"Point"}
}