{
  "type": "Feature",
  "properties": {
    "addr:full":"Royal Way, Alma Barracks Camberley Hampshire GU16 6SX",
    "addr:postcode":"gu16 6sx",
    "addr:street":"Royal Way",
    "iso:country":"GB",
    "sg:address":"Royal Way, Alma Barracks",
    "sg:city":"Camberley",
    "sg:classifiers":[
        {
            "category":"Retail",
            "subcategory":"Repair Shop",
            "type":"Services"
        }
    ],
    "sg:phone":"+44 1252 837892",
    "sg:postcode":"GU16 6SX",
    "sg:province":"Hampshire",
    "sg:tags":[
        "maintenance"
    ],
    "wof:name":"Aqumen Services Ltd.",
    "wof:placetype":"venue"
},
  "geometry": {"coordinates":[-0.7001100183,51.3102416992],"type":"Point"}
}