{
  "type": "Feature",
  "properties": {
    "addr:full":"Fagnall Lane, Winchmore Hill Amersham Buckinghamshire HP7 0PH",
    "addr:postcode":"hp7 0ph",
    "addr:street":"Fagnall Lane",
    "iso:country":"GB",
    "sg:address":"Fagnall Lane, Winchmore Hill",
    "sg:city":"Amersham",
    "sg:classifiers":[
        {
            "category":"Bars & Pubs",
            "type":"Food & Drink"
        }
    ],
    "sg:phone":"+44 1494 722641",
    "sg:postcode":"HP7 0PH",
    "sg:province":"Buckinghamshire",
    "sg:tags":[
        "pubs",
        "inn"
    ],
    "wof:name":"The Potters Arms",
    "wof:placetype":"venue"
},
  "geometry": {"coordinates":[-0.653079,51.645279],"type":"Point"}
}