{
  "type": "Feature",
  "properties": {
    "addr:full":"41 Lower Kings Road Berkhamsted Bedfordshire HP4 2AB",
    "addr:housenumber":"41",
    "addr:postcode":"hp4 2ab",
    "addr:street":"Lower Kings Road",
    "iso:country":"GB",
    "sg:address":"41 Lower Kings Road",
    "sg:city":"Berkhamsted",
    "sg:classifiers":[
        {
            "category":"Wholesale",
            "subcategory":"Books, Periodicals, & Newspapers",
            "type":"Manufacturing & Wholesale Goods"
        }
    ],
    "sg:phone":"+44 1442 878200",
    "sg:postcode":"HP4 2AB",
    "sg:province":"Bedfordshire",
    "sg:tags":[
        "publishing"
    ],
    "wof:name":"Meercats",
    "wof:placetype":"venue"
},
  "geometry": {"coordinates":[-0.5645970106,51.761806488],"type":"Point"}
}