{
  "type": "Feature",
  "properties": {
    "iso:country":"GB",
    "sg:address":"Froghall Farm, Ampthill Road, Steppingley",
    "sg:city":"Bedford",
    "sg:classifiers":[
        {
            "category":"Farming",
            "subcategory":"Farm",
            "type":"Manufacturing & Wholesale Goods"
        }
    ],
    "sg:phone":"+44 1525 712570",
    "sg:postcode":"MK45 1AB",
    "sg:province":"Bedfordshire",
    "sg:tags":[
        "mixed",
        "crop"
    ],
    "wof:name":"W H Jellis",
    "wof:placetype":"venue"
},
  "geometry": {"coordinates":[-0.509524,52.01273],"type":"Point"}
}