{
  "type": "Feature",
  "properties": {
    "addr:full":"230 Cockett Road, Cockett Swansea Swansea SA2 0FN",
    "addr:housenumber":"230",
    "addr:postcode":"sa2 0fn",
    "addr:street":"Cockett Road",
    "iso:country":"GB",
    "sg:address":"230 Cockett Road, Cockett",
    "sg:city":"Swansea",
    "sg:classifiers":[
        {
            "category":"Health Services",
            "subcategory":"Nursing And Care Facility",
            "type":"Services"
        }
    ],
    "sg:phone":"+44 1792 581846",
    "sg:postcode":"SA2 0FN",
    "sg:province":"Swansea",
    "sg:tags":[
        "home"
    ],
    "wof:name":"Glasfryn House Nursing Home",
    "wof:placetype":"venue"
},
  "geometry": {"coordinates":[-3.9813148975,51.6345748901],"type":"Point"}
}