{
  "type": "Feature",
  "properties": {
    "iso:country":"GB",
    "sg:address":"Horseshoe Service Station, London Rd",
    "sg:city":"Etchingham",
    "sg:classifiers":[
        {
            "category":"Autos & Motor Vehicles",
            "subcategory":"Automobile Sales",
            "type":"Retail Goods"
        }
    ],
    "sg:phone":"+44 1580 860444",
    "sg:postcode":"TN19 7QY",
    "sg:province":"East Sussex",
    "sg:tags":[
        "car"
    ],
    "wof:name":"A M Cars",
    "wof:placetype":"venue"
},
  "geometry": {"coordinates":[0.441642,51.00938],"type":"Point"}
}