{
  "type": "Feature",
  "properties": {
    "iso:country":"GB",
    "sg:address":"Station Road, Kennett",
    "sg:city":"Newmarket",
    "sg:classifiers":[
        {
            "category":"Recreation",
            "subcategory":"Amusement Park",
            "type":"Entertainment"
        }
    ],
    "sg:phone":"+44 1638 750335",
    "sg:postcode":"CB8 7QE",
    "sg:province":"Cambridgeshire",
    "sg:tags":[
        "arcade"
    ],
    "wof:name":"Mac Automatics Ltd.",
    "wof:placetype":"venue"
},
  "geometry": {"coordinates":[0.4895389974,52.2823371887],"type":"Point"}
}