{
  "type": "Feature",
  "properties": {
    "addr:full":"110-112 New Road Side, Horsforth Leeds West Yorkshire LS18 4QB",
    "addr:housenumber":"110-112",
    "addr:postcode":"ls18 4qb",
    "addr:street":"New Road Side",
    "iso:country":"GB",
    "sg:address":"110-112 New Road Side, Horsforth",
    "sg:city":"Leeds",
    "sg:classifiers":[
        {
            "category":"Real Estate",
            "subcategory":"Real Estate Agent",
            "type":"Services"
        }
    ],
    "sg:phone":"+44 113 258 3476",
    "sg:postcode":"LS18 4QB",
    "sg:province":"West Yorkshire",
    "sg:website":"http://www.rightmove.co.uk",
    "wof:name":"William H Brown",
    "wof:placetype":"venue"
},
  "geometry": {"coordinates":[-1.639522,53.834335],"type":"Point"}
}