{
  "type": "Feature",
  "properties": {
    "iso:country":"GB",
    "sg:address":"508-510 Fishponds Road, Fishponds",
    "sg:city":"Bristol",
    "sg:classifiers":[
        {
            "category":"Travel",
            "subcategory":"Hotels & Motels",
            "type":"Entertainment"
        }
    ],
    "sg:phone":"+44 117 965 2436",
    "sg:postcode":"BS16 3DT",
    "sg:province":"City of Bristol",
    "sg:tags":[
        "house",
        "guest"
    ],
    "wof:name":"Alcove Guest House",
    "wof:placetype":"venue"
},
  "geometry": {"coordinates":[-2.541626,51.475529],"type":"Point"}
}