{
  "type": "Feature",
  "properties": {
    "addr:full":"Unit 5 North Anston Business Cen, Tre Houghton Road, North Anston Trading Estate Sheffield South Yorkshire S25 4JJ",
    "addr:housenumber":"unit 5",
    "addr:postcode":"s25 4jj",
    "addr:street":"North Anston;Houghton Road North Anston Trading Estate",
    "iso:country":"GB",
    "sg:address":"Unit 5 North Anston Business Cen, Tre Houghton Road, North Anston Trading Estate",
    "sg:city":"Sheffield",
    "sg:classifiers":[
        {
            "category":"Professional",
            "subcategory":"Engineering",
            "type":"Services"
        },
        {
            "category":"Manufacturing",
            "subcategory":"Aerospace",
            "type":"Manufacturing & Wholesale Goods"
        }
    ],
    "sg:phone":"+44 1909 550095",
    "sg:postcode":"S25 4JJ",
    "sg:province":"South Yorkshire",
    "sg:tags":[
        "fitting",
        "aircraft",
        "ge",
        "furnishing",
        "mechanical",
        "engineer"
    ],
    "wof:name":"F M T(U K) Ltd.",
    "wof:placetype":"venue"
},
  "geometry": {"coordinates":[-1.2145240307,53.362121582],"type":"Point"}
}