{
  "type": "Feature",
  "properties": {
    "iso:country":"GB",
    "sg:address":"The Square, Eyam",
    "sg:city":"Hope Valley",
    "sg:classifiers":[
        {
            "category":"Food & Beverages",
            "subcategory":"Meat & Fish",
            "type":"Retail Goods"
        }
    ],
    "sg:phone":"+44 1433 631611",
    "sg:postcode":"S32 5RB",
    "sg:province":"Derbyshire",
    "sg:tags":[
        "butcher"
    ],
    "wof:name":"George Brian Siddall",
    "wof:placetype":"venue"
},
  "geometry": {"coordinates":[-1.6715140343,53.2842483521],"type":"Point"}
}