{
  "type": "Feature",
  "properties": {
    "addr:full":"102 Lyndhurst Ashurst Centre Skelmersdale Lancashire WN8 6UH",
    "addr:housenumber":"102;ashurst",
    "addr:postcode":"wn8 6uh",
    "addr:street":"Lyndhurst;Skelmersdale",
    "iso:country":"GB",
    "sg:address":"102 Lyndhurst Ashurst Centre",
    "sg:city":"Skelmersdale",
    "sg:classifiers":[
        {
            "category":"Shopping",
            "subcategory":"News",
            "type":"Retail Goods"
        }
    ],
    "sg:phone":"+44 1695 51867",
    "sg:postcode":"WN8 6UH",
    "sg:province":"Lancashire",
    "sg:tags":[
        "newsagent"
    ],
    "wof:name":"Martin The Newsagent",
    "wof:placetype":"venue"
},
  "geometry": {"coordinates":[-2.7741389275,53.5634384155],"type":"Point"}
}