{
  "type": "Feature",
  "properties": {
    "iso:country":"GB",
    "sg:address":"58-62 Langley Common Road, Barkham",
    "sg:city":"Wokingham",
    "sg:classifiers":[
        {
            "category":"Autos & Motor Vehicles",
            "subcategory":"Auto Supplies",
            "type":"Retail Goods"
        },
        {
            "category":"Retail",
            "subcategory":"Auto Repair",
            "type":"Services"
        }
    ],
    "sg:phone":"+44 118 978 2102",
    "sg:postcode":"RG40 4TS",
    "sg:province":"Berkshire",
    "sg:tags":[
        "modification",
        "garage",
        "tyre"
    ],
    "wof:name":"Staysure Ltd.",
    "wof:placetype":"venue"
},
  "geometry": {"coordinates":[-0.89843,51.390846],"type":"Point"}
}