{
  "type": "Feature",
  "properties": {
    "addr:full":"Redbury Barn, Ardleigh Colchester Essex CO7 7PQ",
    "addr:postcode":"co7 7pq",
    "addr:street":"Ardleigh",
    "iso:country":"GB",
    "sg:address":"Redbury Barn, Ardleigh",
    "sg:city":"Colchester",
    "sg:classifiers":[
        {
            "category":"Professional",
            "subcategory":"Engineering",
            "type":"Services"
        }
    ],
    "sg:phone":"+44 1206 231791",
    "sg:postcode":"CO7 7PQ",
    "sg:province":"Essex",
    "sg:tags":[
        "consulting",
        "engineer"
    ],
    "wof:name":"Carpenter & Lowe Ltd.",
    "wof:placetype":"venue"
},
  "geometry": {"coordinates":[0.9837970138,51.9258880615],"type":"Point"}
}