{
  "type": "Feature",
  "properties": {
    "addr:full":"10 Ellerby Lane, Runswick Bay Saltburn-by-the-sea North Yorkshire TS13 5HS",
    "addr:housenumber":"10",
    "addr:postcode":"ts13 5hs",
    "addr:street":"Ellerby Lane",
    "iso:country":"GB",
    "sg:address":"10 Ellerby Lane, Runswick Bay",
    "sg:city":"Saltburn-by-the-sea",
    "sg:classifiers":[
        {
            "category":"Professional",
            "subcategory":"Engineering",
            "type":"Services"
        }
    ],
    "sg:phone":"+44 1947 840738",
    "sg:postcode":"TS13 5HS",
    "sg:province":"North Yorkshire",
    "sg:tags":[
        "contractor",
        "electrical",
        "engineer"
    ],
    "wof:name":"Metcalfe Electrical (Yorkshire) Ltd.",
    "wof:placetype":"venue"
},
  "geometry": {"coordinates":[-0.7569389939,54.5327033997],"type":"Point"}
}