{
  "type": "Feature",
  "properties": {
    "iso:country":"GB",
    "sg:address":"20 Mill Road, Thurcaston",
    "sg:city":"Leicester",
    "sg:classifiers":[
        {
            "category":"Professional",
            "subcategory":"Engineering",
            "type":"Services"
        }
    ],
    "sg:phone":"+44 116 237 4853",
    "sg:postcode":"LE7 7JP",
    "sg:province":"Leicestershire",
    "wof:name":"Schell Standards (U K) Ltd.",
    "wof:placetype":"venue"
},
  "geometry": {"coordinates":[-1.161182,52.695232],"type":"Point"}
}