{
  "type": "Feature",
  "properties": {
    "iso:country":"GB",
    "sg:address":"Deepdale, Potton",
    "sg:city":"Sandy",
    "sg:classifiers":[
        {
            "category":"Building & Trades",
            "subcategory":"Landscaping Services",
            "type":"Services"
        }
    ],
    "sg:phone":"+44 1767 261600",
    "sg:postcode":"SG19 2NH",
    "sg:province":"Bedfordshire",
    "sg:tags":[
        "pond",
        "aquarium"
    ],
    "wof:name":"Deepdale Water Gardens",
    "wof:placetype":"venue"
},
  "geometry": {"coordinates":[-0.2161410004,52.1265907288],"type":"Point"}
}