{
  "type": "Feature",
  "properties": {
    "addr:full":"27 Church St Slough Berkshire SL1 1PL",
    "addr:housenumber":"27",
    "addr:postcode":"sl1 1pl",
    "addr:street":"Church St",
    "iso:country":"GB",
    "sg:address":"27 Church St",
    "sg:city":"Slough",
    "sg:classifiers":[
        {
            "category":"Professional",
            "subcategory":"Lawyer & Legal Services",
            "type":"Services"
        }
    ],
    "sg:phone":"+44 1753 522004",
    "sg:postcode":"SL1 1PL",
    "sg:province":"Berkshire",
    "sg:tags":[
        "advice",
        "counselling"
    ],
    "wof:name":"Citizens Advice Bureau",
    "wof:placetype":"venue"
},
  "geometry": {"coordinates":[-0.5935099721,51.507522583],"type":"Point"}
}