{
  "type": "Feature",
  "properties": {
    "iso:country":"GB",
    "sg:address":"17 Holywell Row, Off Worship Street",
    "sg:city":"London",
    "sg:classifiers":[
        {
            "category":"Banks & Credit Unions",
            "subcategory":"Financial Services",
            "type":"Services"
        }
    ],
    "sg:phone":"+44 20 7377 7575",
    "sg:postcode":"EC2A 4XB",
    "sg:province":"Greater London",
    "sg:tags":[
        "consultant"
    ],
    "wof:name":"Weston-Cummins Ltd.",
    "wof:placetype":"venue"
},
  "geometry": {"coordinates":[-0.08255,51.522659],"type":"Point"}
}