{
  "type": "Feature",
  "properties": {
    "addr:full":"Care Of Hinckley Leisure Centre, Coventry Rd Hinckley Leicestershire LE10 0JR",
    "addr:postcode":"le10 0jr",
    "addr:street":"Coventry Rd",
    "iso:country":"GB",
    "sg:address":"Care Of Hinckley Leisure Centre, Coventry Rd",
    "sg:city":"Hinckley",
    "sg:classifiers":[
        {
            "category":"Arena",
            "subcategory":"Sports Club",
            "type":"Entertainment"
        }
    ],
    "sg:phone":"+44 1455 610226",
    "sg:postcode":"LE10 0JR",
    "sg:province":"Leicestershire",
    "wof:name":"Hinckley Sub-Aqua Club",
    "wof:placetype":"venue"
},
  "geometry": {"coordinates":[-1.372754,52.542439],"type":"Point"}
}