{
  "type": "Feature",
  "properties": {
    "addr:full":"59a Nether Hall Road Doncaster South Yorkshire DN1 2PG",
    "addr:housenumber":"59a",
    "addr:postcode":"dn1 2pg",
    "addr:street":"Nether Hall Road",
    "iso:country":"GB",
    "sg:address":"59a Nether Hall Road",
    "sg:city":"Doncaster",
    "sg:classifiers":[
        {
            "category":"Real Estate",
            "subcategory":"Surveying",
            "type":"Services"
        }
    ],
    "sg:postcode":"DN1 2PG",
    "sg:province":"South Yorkshire",
    "sg:tags":[
        "surveyor",
        "valuer"
    ],
    "wof:name":"Turner Kenyon",
    "wof:placetype":"venue"
},
  "geometry": {"coordinates":[-1.1285090446,53.5257415771],"type":"Point"}
}