{
  "type": "Feature",
  "properties": {
    "iso:country":"GB",
    "sg:address":"35 North Upton Lane, Barnwood",
    "sg:city":"Gloucester",
    "sg:classifiers":[
        {
            "category":"Health Services",
            "subcategory":"Nursing And Care Facility",
            "type":"Services"
        }
    ],
    "sg:phone":"+44 1452 616291",
    "sg:postcode":"GL4 3TD",
    "sg:province":"Gloucestershire",
    "sg:tags":[
        "home"
    ],
    "wof:name":"Woodstock Nursing Home",
    "wof:placetype":"venue"
},
  "geometry": {"coordinates":[-2.198761,51.856262],"type":"Point"}
}