{
  "type": "Feature",
  "properties": {
    "addr:full":"104 Burnley Rd Accrington Lancashire BB5 6DW",
    "addr:housenumber":"104",
    "addr:postcode":"bb5 6dw",
    "addr:street":"Burnley Rd",
    "iso:country":"GB",
    "sg:address":"104 Burnley Rd",
    "sg:city":"Accrington",
    "sg:classifiers":[
        {
            "category":"Retail",
            "subcategory":"Laundry & Dry Cleaning",
            "type":"Services"
        }
    ],
    "sg:postcode":"BB5 6DW",
    "sg:province":"Lancashire",
    "sg:tags":[
        "alteration"
    ],
    "wof:name":"King,Carol,",
    "wof:placetype":"venue"
},
  "geometry": {"coordinates":[-2.36033,53.756599],"type":"Point"}
}