{
  "type": "Feature",
  "properties": {
    "addr:full":"Upper Draycott Road Cheddar Somerset BS27 3YL",
    "addr:postcode":"bs27 3yl",
    "addr:street":"Upper Draycott Road",
    "iso:country":"GB",
    "sg:address":"Upper Draycott Road",
    "sg:city":"Cheddar",
    "sg:classifiers":[
        {
            "category":"Farming",
            "subcategory":"Livestock Farm",
            "type":"Manufacturing & Wholesale Goods"
        }
    ],
    "sg:phone":"+44 1934 742202",
    "sg:postcode":"BS27 3YL",
    "sg:province":"Somerset",
    "sg:tags":[
        "others"
    ],
    "wof:name":"J Thorner & Sons",
    "wof:placetype":"venue"
},
  "geometry": {"coordinates":[-2.777659,51.279659],"type":"Point"}
}