{
  "type": "Feature",
  "properties": {
    "addr:full":"52 Cross St, Northam Bideford Devon EX39 1BX",
    "addr:housenumber":"52",
    "addr:postcode":"ex39 1bx",
    "addr:street":"Cross St",
    "iso:country":"GB",
    "sg:address":"52 Cross St, Northam",
    "sg:city":"Bideford",
    "sg:classifiers":[
        {
            "category":"Professional",
            "type":"Services"
        }
    ],
    "sg:phone":"+44 1237 425615",
    "sg:postcode":"EX39 1BX",
    "sg:province":"Devon",
    "sg:tags":[
        "entertainer"
    ],
    "wof:name":"Rachael Storme Promotions",
    "wof:placetype":"venue"
},
  "geometry": {"coordinates":[-4.204259,51.019249],"type":"Point"}
}