{
  "type": "Feature",
  "properties": {
    "addr:full":"106 Bath Road Stroud Gloucestershire GL5 3TJ",
    "addr:housenumber":"106",
    "addr:postcode":"gl5 3tj",
    "addr:street":"Bath Road",
    "iso:country":"GB",
    "sg:address":"106 Bath Road",
    "sg:city":"Stroud",
    "sg:classifiers":[
        {
            "category":"Bars & Pubs",
            "type":"Food & Drink"
        }
    ],
    "sg:phone":"+44 1453 764432",
    "sg:postcode":"GL5 3TJ",
    "sg:province":"Gloucestershire",
    "sg:tags":[
        "pubs",
        "inn"
    ],
    "wof:name":"Fleece Inn",
    "wof:placetype":"venue"
},
  "geometry": {"coordinates":[-2.232653,51.736847],"type":"Point"}
}