{
  "type": "Feature",
  "properties": {
    "iso:country":"GB",
    "sg:address":"Oddingley Lane, Crowle",
    "sg:city":"Worcester",
    "sg:classifiers":[
        {
            "category":"Farming",
            "subcategory":"Livestock Farm",
            "type":"Manufacturing & Wholesale Goods"
        }
    ],
    "sg:postcode":"WR7 4AF",
    "sg:province":"Worcestershire",
    "sg:tags":[
        "others"
    ],
    "wof:name":"J Wilkinson",
    "wof:placetype":"venue"
},
  "geometry": {"coordinates":[-2.114281,52.201859],"type":"Point"}
}