{
  "type": "Feature",
  "properties": {
    "iso:country":"GB",
    "sg:address":"6 The Thoroughfare",
    "sg:city":"Harleston",
    "sg:classifiers":[
        {
            "category":"Professional",
            "subcategory":"Business Services",
            "type":"Services"
        }
    ],
    "sg:phone":"+44 1379 854182",
    "sg:postcode":"IP20 9AX",
    "sg:province":"Norfolk",
    "sg:tags":[
        "distributor",
        "film"
    ],
    "wof:name":"Video Plus Movie Zone",
    "wof:placetype":"venue"
},
  "geometry": {"coordinates":[1.299603,52.402088],"type":"Point"}
}