{
  "type": "Feature",
  "properties": {
    "iso:country":"GB",
    "sg:address":"117 Park Road, New Barnet",
    "sg:city":"Barnet",
    "sg:classifiers":[
        {
            "category":"Travel",
            "subcategory":"Travel Agent",
            "type":"Entertainment"
        }
    ],
    "sg:phone":"+44 20 8441 3019",
    "sg:postcode":"EN4 9QN",
    "sg:province":"Hertfordshire",
    "wof:name":"Am Global Ltd.",
    "wof:placetype":"venue"
},
  "geometry": {"coordinates":[-0.161214,51.647125],"type":"Point"}
}