{
  "type": "Feature",
  "properties": {
    "iso:country":"GB",
    "sg:address":"37 Temple Drive, Swinton",
    "sg:city":"Manchester",
    "sg:classifiers":[
        {
            "category":"Real Estate",
            "subcategory":"Architect",
            "type":"Services"
        }
    ],
    "sg:postcode":"M27 4EA",
    "sg:province":"Greater Manchester",
    "wof:name":"David Young Architect",
    "wof:placetype":"venue"
},
  "geometry": {"coordinates":[-2.3252580166,53.508769989],"type":"Point"}
}