{
  "type": "Feature",
  "properties": {
    "addr:full":"32 Fordhook Avenue London Greater London W5 3LP",
    "addr:housenumber":"32",
    "addr:postcode":"london;w5 3lp",
    "addr:street":"Fordhook Avenue",
    "iso:country":"GB",
    "sg:address":"32 Fordhook Avenue",
    "sg:city":"London",
    "sg:classifiers":[
        {
            "category":"Banks & Credit Unions",
            "subcategory":"Financial Services",
            "type":"Services"
        }
    ],
    "sg:phone":"+44 20 8993 1126",
    "sg:postcode":"W5 3LP",
    "sg:province":"Greater London",
    "sg:tags":[
        "adviser"
    ],
    "wof:name":"Stephen Ward & Co.",
    "wof:placetype":"venue"
},
  "geometry": {"coordinates":[-0.2851159871,51.5112571716],"type":"Point"}
}