{
  "type": "Feature",
  "properties": {
    "iso:country":"GB",
    "sg:address":"12 Market Street",
    "sg:city":"Chipping Norton",
    "sg:classifiers":[
        {
            "category":"Professional",
            "subcategory":"Computer Services",
            "type":"Services"
        }
    ],
    "sg:phone":"+44 1608 645566",
    "sg:postcode":"OX7 5NQ",
    "sg:province":"Gloucestershire",
    "sg:tags":[
        "information"
    ],
    "wof:name":"Cosic Coffee Science Information Centre",
    "wof:placetype":"venue"
},
  "geometry": {"coordinates":[-1.545379,51.942871],"type":"Point"}
}