{
  "type": "Feature",
  "properties": {
    "iso:country":"GB",
    "sg:address":"Unit 105, Mayford Centre, Mayford Grn",
    "sg:city":"Woking",
    "sg:classifiers":[
        {
            "category":"Professional",
            "subcategory":"Engineering",
            "type":"Services"
        },
        {
            "category":"Professional",
            "subcategory":"Management & Consulting",
            "type":"Services"
        }
    ],
    "sg:phone":"+44 1483 755957",
    "sg:postcode":"GU22 0PP",
    "sg:province":"Surrey",
    "sg:tags":[
        "environmental",
        "consultant",
        "engineer"
    ],
    "wof:name":"Pollution Monitors Ltd",
    "wof:placetype":"venue"
},
  "geometry": {"coordinates":[-0.572559,51.296757],"type":"Point"}
}