{
  "type": "Feature",
  "properties": {
    "addr:full":"Gilnow Mill Industrial Estate, Spa Road Bolton Lancashire BL1 4SF",
    "addr:postcode":"bl1 4sf",
    "addr:street":"Gilnow Mill Industrial;Spa Road",
    "iso:country":"GB",
    "sg:address":"Gilnow Mill Industrial Estate, Spa Road",
    "sg:city":"Bolton",
    "sg:classifiers":[
        {
            "category":"Retail",
            "subcategory":"Repair Shop",
            "type":"Services"
        }
    ],
    "sg:phone":"+44 1204 371841",
    "sg:postcode":"BL1 4SF",
    "sg:province":"Lancashire",
    "sg:tags":[
        "furniture"
    ],
    "wof:name":"David Wood & Son",
    "wof:placetype":"venue"
},
  "geometry": {"coordinates":[-2.421749,53.581356],"type":"Point"}
}