{
  "type": "Feature",
  "properties": {
    "iso:country":"GB",
    "sg:address":"28 Orwell Close, Norton",
    "sg:city":"Stourbridge",
    "sg:classifiers":[
        {
            "category":"Building & Trades",
            "subcategory":"Construction",
            "type":"Services"
        }
    ],
    "sg:phone":"+44 1384 375169",
    "sg:postcode":"DY8 3JS",
    "sg:province":"Staffordshire",
    "sg:tags":[
        "bricklayer",
        "bricklaying"
    ],
    "wof:name":"Albert G Rutter",
    "wof:placetype":"venue"
},
  "geometry": {"coordinates":[-2.1696960926,52.4506912231],"type":"Point"}
}