{
  "type": "Feature",
  "properties": {
    "addr:full":"St Nicholas House, 71 Oaston Road Nuneaton Leicestershire CV11 6LA",
    "addr:housenumber":"71",
    "addr:postcode":"cv11 6la",
    "addr:street":"Oaston Road",
    "iso:country":"GB",
    "sg:address":"St Nicholas House, 71 Oaston Road",
    "sg:city":"Nuneaton",
    "sg:classifiers":[
        {
            "category":"Banks & Credit Unions",
            "subcategory":"Bank",
            "type":"Services"
        }
    ],
    "sg:postcode":"CV11 6LA",
    "sg:province":"Leicestershire",
    "sg:tags":[
        "stocktaking",
        "inventory"
    ],
    "wof:name":"David Smart",
    "wof:placetype":"venue"
},
  "geometry": {"coordinates":[-1.4559550285,52.5247459412],"type":"Point"}
}