{
  "type": "Feature",
  "properties": {
    "addr:full":"13 Cold Harbour, Isle Of Dogs London Greater London E14 9NS",
    "addr:housenumber":"13",
    "addr:postcode":"e14 9ns",
    "addr:street":"Cold Harbour",
    "iso:country":"GB",
    "sg:address":"13 Cold Harbour, Isle Of Dogs",
    "sg:city":"London",
    "sg:classifiers":[
        {
            "category":"Real Estate",
            "subcategory":"Architect",
            "type":"Services"
        }
    ],
    "sg:postcode":"E14 9NS",
    "sg:province":"Greater London",
    "wof:name":"Evo Archo Ltd",
    "wof:placetype":"venue"
},
  "geometry": {"coordinates":[-0.007418,51.50288],"type":"Point"}
}