{
  "type": "Feature",
  "properties": {
    "iso:country":"GB",
    "sg:address":"42g Eaton Square",
    "sg:city":"London",
    "sg:classifiers":[
        {
            "category":"Arts & Performance",
            "subcategory":"Art Gallery",
            "type":"Entertainment"
        }
    ],
    "sg:phone":"+44 20 7235 2276",
    "sg:postcode":"SW1W 9BD",
    "sg:province":"Greater London",
    "wof:name":"Hildegard Fritz-Denneville (Fine Arts) Ltd.",
    "wof:placetype":"venue"
},
  "geometry": {"coordinates":[-0.151714,51.495071],"type":"Point"}
}