{
  "type": "Feature",
  "properties": {
    "iso:country":"GB",
    "sg:address":"106 Glebe St",
    "sg:city":"Penarth",
    "sg:classifiers":[
        {
            "category":"Food & Beverages",
            "subcategory":"Bakery",
            "type":"Retail Goods"
        }
    ],
    "sg:phone":"+44 29 2025 0757",
    "sg:postcode":"CF64 1ED",
    "sg:province":"The Vale of Glamorgan",
    "sg:tags":[
        "baker"
    ],
    "wof:name":"Humphreys Cottage Bakery",
    "wof:placetype":"venue"
},
  "geometry": {"coordinates":[-3.174371,51.439976],"type":"Point"}
}