{
  "type": "Feature",
  "properties": {
    "iso:country":"GB",
    "sg:address":"18 First Avenue, Westfield Trading Estate, Midsomer Norton",
    "sg:city":"Bath",
    "sg:classifiers":[
        {
            "category":"Home & Garden",
            "subcategory":"Building Materials",
            "type":"Retail Goods"
        }
    ],
    "sg:postcode":"BA3 4BS",
    "sg:province":"Somerset",
    "sg:tags":[
        "plaster",
        "ware"
    ],
    "wof:name":"Feature Ceilings",
    "wof:placetype":"venue"
},
  "geometry": {"coordinates":[-2.4699749947,51.2799453735],"type":"Point"}
}