{
  "type": "Feature",
  "properties": {
    "iso:country":"GB",
    "sg:address":"1 Wootton Hill Farm",
    "sg:city":"Northampton",
    "sg:classifiers":[
        {
            "category":"Professional",
            "subcategory":"Accounting & Tax Preparation",
            "type":"Services"
        }
    ],
    "sg:phone":"+44 1604 763835",
    "sg:postcode":"NN4 9JJ",
    "sg:province":"Northamptonshire",
    "sg:tags":[
        "accountant"
    ],
    "wof:name":"Norman Chant Accountancy Services",
    "wof:placetype":"venue"
},
  "geometry": {"coordinates":[-0.9207149744,52.2146072388],"type":"Point"}
}