{
  "type": "Feature",
  "properties": {
    "iso:country":"GB",
    "sg:address":"47 Chester Street",
    "sg:city":"Wrexham",
    "sg:classifiers":[
        {
            "category":"Shopping",
            "subcategory":"Optician",
            "type":"Retail Goods"
        }
    ],
    "sg:postcode":"LL13 8BA",
    "sg:province":"Wrexham",
    "wof:name":"Jbr1910 Ltd.",
    "wof:placetype":"venue"
},
  "geometry": {"coordinates":[-2.9914050102,53.0465164185],"type":"Point"}
}