{
  "type": "Feature",
  "properties": {
    "addr:full":"205 Creynolds Lane, Shirley Solihull West Midlands B90 4ES",
    "addr:housenumber":"205",
    "addr:postcode":"b90 4es",
    "addr:street":"Creynolds Lane",
    "iso:country":"GB",
    "sg:address":"205 Creynolds Lane, Shirley",
    "sg:city":"Solihull",
    "sg:classifiers":[
        {
            "category":"Professional",
            "subcategory":"Testing Lab",
            "type":"Services"
        },
        {
            "category":"Professional",
            "subcategory":"Art Services",
            "type":"Services"
        }
    ],
    "sg:phone":"+44 121 733 6152",
    "sg:postcode":"B90 4ES",
    "sg:province":"West Midlands",
    "sg:tags":[
        "inspection",
        "consultant",
        "design",
        "calibration"
    ],
    "wof:name":"Pro-Test Panels                     Horsell Design",
    "wof:placetype":"venue"
},
  "geometry": {"coordinates":[-1.810634,52.377895],"type":"Point"}
}