{
  "type": "Feature",
  "properties": {
    "addr:full":"Royal Lane, Hillingdon Hayes Greater London UB3 3QP",
    "addr:postcode":"ub3 3qp",
    "addr:street":"Royal Lane",
    "iso:country":"GB",
    "sg:address":"Royal Lane, Hillingdon",
    "sg:city":"Hayes",
    "sg:classifiers":[
        {
            "category":"Organizations",
            "subcategory":"Membership Organization",
            "type":"Services"
        }
    ],
    "sg:phone":"+44 1895 448229",
    "sg:postcode":"UB3 3QP",
    "sg:province":"Greater London",
    "sg:tags":[
        "club"
    ],
    "wof:name":"The Hillingdon Irish Society",
    "wof:placetype":"venue"
},
  "geometry": {"coordinates":[-0.4247559905,51.5015525818],"type":"Point"}
}