{
  "type": "Feature",
  "properties": {
    "iso:country":"GB",
    "sg:address":"12a High St",
    "sg:city":"Biggleswade",
    "sg:classifiers":[
        {
            "category":"Restaurant",
            "type":"Food & Drink"
        }
    ],
    "sg:phone":"+44 1767 313971",
    "sg:postcode":"SG18 0JL",
    "sg:province":"Bedfordshire",
    "wof:name":"Golden Grill",
    "wof:placetype":"venue"
},
  "geometry": {"coordinates":[-0.265084,52.086876],"type":"Point"}
}