{
  "type": "Feature",
  "properties": {
    "addr:full":"32 Crediton Road Okehampton Devon EX20 1NU",
    "addr:housenumber":"32",
    "addr:postcode":"ex20 1nu",
    "addr:street":"Crediton Road",
    "iso:country":"GB",
    "sg:address":"32 Crediton Road",
    "sg:city":"Okehampton",
    "sg:classifiers":[
        {
            "category":"Personal",
            "subcategory":"Beauty Salon",
            "type":"Services"
        }
    ],
    "sg:phone":"+44 1837 52360",
    "sg:postcode":"EX20 1NU",
    "sg:province":"Devon",
    "sg:tags":[
        "unisex",
        "hairdresser"
    ],
    "wof:name":"Gillian's Hairstylist",
    "wof:placetype":"venue"
},
  "geometry": {"coordinates":[-3.996138,50.741013],"type":"Point"}
}