{
  "type": "Feature",
  "properties": {
    "addr:full":"Care Of Kwik Save, Alvescot Rd Carterton Gloucestershire OX18 3JL",
    "addr:postcode":"ox18 3jl",
    "addr:street":"Alvescot Rd",
    "iso:country":"GB",
    "sg:address":"Care Of Kwik Save, Alvescot Rd",
    "sg:city":"Carterton",
    "sg:classifiers":[
        {
            "category":"Food & Beverages",
            "subcategory":"Fruits & Vegetables",
            "type":"Retail Goods"
        }
    ],
    "sg:postcode":"OX18 3JL",
    "sg:province":"Gloucestershire",
    "sg:tags":[
        "greengrocer"
    ],
    "wof:name":"Hurst Parnell",
    "wof:placetype":"venue"
},
  "geometry": {"coordinates":[-1.5903840065,51.7606239319],"type":"Point"}
}