{
  "type": "Feature",
  "properties": {
    "addr:full":"Stotfold Moor Farm, Elwick Hartlepool Durham TS27 3EY",
    "addr:postcode":"ts27 3ey",
    "addr:street":"Stotfold Moor",
    "iso:country":"GB",
    "sg:address":"Stotfold Moor Farm, Elwick",
    "sg:city":"Hartlepool",
    "sg:classifiers":[
        {
            "category":"Home & Garden",
            "subcategory":"Garden Supply",
            "type":"Retail Goods"
        }
    ],
    "sg:phone":"+44 1429 273444",
    "sg:postcode":"TS27 3EY",
    "sg:province":"Durham",
    "sg:tags":[
        "bulb",
        "grower"
    ],
    "wof:name":"H & P Hutchinson",
    "wof:placetype":"venue"
},
  "geometry": {"coordinates":[-1.2955089808,54.6837768555],"type":"Point"}
}