{
  "type": "Feature",
  "properties": {
    "addr:full":"Council Depot, Wade Road Basingstoke Hampshire RG24 8PL",
    "addr:postcode":"rg24 8pl",
    "addr:street":"Wade Road",
    "iso:country":"GB",
    "sg:address":"Council Depot, Wade Road",
    "sg:city":"Basingstoke",
    "sg:classifiers":[
        {
            "category":"Utilities",
            "subcategory":"Refuse",
            "type":"Services"
        }
    ],
    "sg:phone":"+44 1252 311931",
    "sg:postcode":"RG24 8PL",
    "sg:province":"Hampshire",
    "sg:tags":[
        "skip",
        "hire"
    ],
    "wof:name":"Acorn Skip Hire",
    "wof:placetype":"venue"
},
  "geometry": {"coordinates":[-1.06693995,51.2802391052],"type":"Point"}
}