{
  "type": "Feature",
  "properties": {
    "addr:full":"Po Box 573 Addlestone Surrey KT15 1WT",
    "addr:housenumber":"po",
    "addr:postcode":"kt15 1wt",
    "addr:street":"Box 573",
    "iso:country":"GB",
    "sg:address":"Po Box 573",
    "sg:city":"Addlestone",
    "sg:classifiers":[
        {
            "category":"Building & Trades",
            "subcategory":"Construction",
            "type":"Services"
        }
    ],
    "sg:phone":"+44 1932 851950",
    "sg:postcode":"KT15 1WT",
    "sg:province":"Surrey",
    "sg:tags":[
        "builder"
    ],
    "wof:name":"Stedman Contracting Ltd.",
    "wof:placetype":"venue"
},
  "geometry": {"coordinates":[-0.505749,51.364342],"type":"Point"}
}