{
  "type": "Feature",
  "properties": {
    "addr:full":"53 Port Street Evesham Gloucestershire WR11 3LF",
    "addr:housenumber":"53",
    "addr:postcode":"wr11 3lf",
    "addr:street":"Port Street",
    "iso:country":"GB",
    "sg:address":"53 Port Street",
    "sg:city":"Evesham",
    "sg:classifiers":[
        {
            "category":"Home & Garden",
            "subcategory":"Household Appliances",
            "type":"Retail Goods"
        }
    ],
    "sg:phone":"+44 1386 421608",
    "sg:postcode":"WR11 3LF",
    "sg:province":"Gloucestershire",
    "sg:tags":[
        "electrical",
        "domestic"
    ],
    "wof:name":"Direct Appliances",
    "wof:placetype":"venue"
},
  "geometry": {"coordinates":[-1.9390749931,52.0908241272],"type":"Point"}
}