{
  "type": "Feature",
  "properties": {
    "addr:full":"48 Park Way Havant Hampshire PO9 1HH",
    "addr:housenumber":"48",
    "addr:postcode":"po9 1hh",
    "addr:street":"Park Way",
    "iso:country":"GB",
    "sg:address":"48 Park Way",
    "sg:city":"Havant",
    "sg:classifiers":[
        {
            "category":"Bus Charters",
            "type":"Transportation"
        },
        {
            "category":"Travel",
            "subcategory":"Travel Agent",
            "type":"Entertainment"
        }
    ],
    "sg:phone":"+44 23 9249 9122",
    "sg:postcode":"PO9 1HH",
    "sg:province":"Hampshire",
    "sg:tags":[
        "hire",
        "coach",
        "agency",
        "activity"
    ],
    "wof:name":"Normans Coaches",
    "wof:placetype":"venue"
},
  "geometry": {"coordinates":[-0.9885489941,50.8531837463],"type":"Point"}
}