{
  "type": "Feature",
  "properties": {
    "iso:country":"GB",
    "sg:address":"8 Duke St",
    "sg:city":"Cardiff",
    "sg:classifiers":[
        {
            "category":"Shopping",
            "subcategory":"Computers & Home Electronics",
            "type":"Retail Goods"
        }
    ],
    "sg:phone":"+44 29 2022 8020",
    "sg:postcode":"CF1 2AY",
    "sg:province":"Cardiff",
    "sg:tags":[
        "hi-fi",
        "centre"
    ],
    "wof:name":"Cardiff Sony Centre",
    "wof:placetype":"venue"
},
  "geometry": {"coordinates":[-3.179134,51.481617],"type":"Point"}
}