{
  "type": "Feature",
  "properties": {
    "addr:full":"9 Paddock Close, South Wonston Winchester Hampshire SO21 3EQ",
    "addr:housenumber":"9",
    "addr:postcode":"so21 3eq",
    "addr:street":"Paddock Close South",
    "iso:country":"GB",
    "sg:address":"9 Paddock Close, South Wonston",
    "sg:city":"Winchester",
    "sg:classifiers":[
        {
            "category":"Professional",
            "type":"Services"
        }
    ],
    "sg:phone":"+44 1962 885551",
    "sg:postcode":"SO21 3EQ",
    "sg:province":"Hampshire",
    "sg:tags":[
        "repair",
        "tech",
        "maintenance"
    ],
    "wof:name":"Steven Russell Technology Ltd.",
    "wof:placetype":"venue"
},
  "geometry": {"coordinates":[-1.3210810423,51.1525421143],"type":"Point"}
}