{
  "type": "Feature",
  "properties": {
    "iso:country":"GB",
    "sg:address":"9 Melville Street",
    "sg:city":"Ryde",
    "sg:classifiers":[
        {
            "category":"Health Services",
            "subcategory":"Dentist",
            "type":"Services"
        }
    ],
    "sg:phone":"+44 1983 563700",
    "sg:postcode":"PO33 2AE",
    "sg:province":"Isle of Wight",
    "wof:name":"F D Shamash",
    "wof:placetype":"venue"
},
  "geometry": {"coordinates":[-1.159857,50.729626],"type":"Point"}
}