{
  "type": "Feature",
  "properties": {
    "addr:full":"Bentworth Road London Greater London W12 7AJ",
    "addr:postcode":"w12 7aj",
    "addr:street":"Bentworth Road",
    "iso:country":"GB",
    "sg:address":"Bentworth Road",
    "sg:city":"London",
    "sg:classifiers":[
        {
            "category":"Education",
            "subcategory":"Preschool",
            "type":"Public Place"
        },
        {
            "category":"Education",
            "subcategory":"School",
            "type":"Public Place"
        },
        {
            "category":"Government",
            "subcategory":"Office",
            "type":"Public Place"
        }
    ],
    "sg:phone":"+44 20 8746 0144",
    "sg:postcode":"W12 7AJ",
    "sg:province":"Greater London",
    "sg:tags":[
        "playgroups",
        "pre-school",
        "local",
        "authority"
    ],
    "wof:name":"Bentworth Playcentre",
    "wof:placetype":"venue"
},
  "geometry": {"coordinates":[-0.2300219983,51.5156021118],"type":"Point"}
}