{
  "type": "Feature",
  "properties": {
    "iso:country":"GB",
    "sg:address":"2 Bramble Court, Penwortham",
    "sg:city":"Preston",
    "sg:classifiers":[
        {
            "category":"Professional",
            "type":"Services"
        }
    ],
    "sg:phone":"+44 1772 741739",
    "sg:postcode":"PR1 9EW",
    "sg:province":"Lancashire",
    "sg:tags":[
        "repair",
        "tech",
        "maintenance"
    ],
    "wof:name":"G L S Technology",
    "wof:placetype":"venue"
},
  "geometry": {"coordinates":[-2.713471,53.733742],"type":"Point"}
}