{
  "type": "Feature",
  "properties": {
    "addr:full":"28 Milford Place, Heaton Bradford West Yorkshire BD9 4RU",
    "addr:housenumber":"28",
    "addr:postcode":"yorkshire bd9 4ru",
    "addr:street":"Milford Place",
    "iso:country":"GB",
    "sg:address":"28 Milford Place, Heaton",
    "sg:city":"Bradford",
    "sg:classifiers":[
        {
            "category":"Building & Trades",
            "subcategory":"Construction",
            "type":"Services"
        }
    ],
    "sg:postcode":"BD9 4RU",
    "sg:province":"West Yorkshire",
    "sg:tags":[
        "joiner",
        "carpenter"
    ],
    "wof:name":"Richard Hillier",
    "wof:placetype":"venue"
},
  "geometry": {"coordinates":[-1.781574,53.812569],"type":"Point"}
}