{
  "type": "Feature",
  "properties": {
    "iso:country":"GB",
    "sg:address":"55 Fort Street",
    "sg:city":"Ayr",
    "sg:classifiers":[
        {
            "category":"Shopping",
            "subcategory":"Crafts & Fabrics",
            "type":"Retail Goods"
        }
    ],
    "sg:phone":"+44 1292 261841",
    "sg:postcode":"KA7 1DH",
    "sg:province":"South Ayrshire",
    "sg:tags":[
        "shop",
        "needlecraft",
        "wool",
        "retailer"
    ],
    "wof:name":"The Sewing Basket",
    "wof:placetype":"venue"
},
  "geometry": {"coordinates":[-4.635048,55.462219],"type":"Point"}
}