{
  "type": "Feature",
  "properties": {
    "addr:full":"Carl Court Rest Home, Guestland Road Torquay Devon TQ1 3NN",
    "addr:postcode":"tq1 3nn",
    "addr:street":"Carl Court;Guestland Road",
    "iso:country":"GB",
    "sg:address":"Carl Court Rest Home, Guestland Road",
    "sg:city":"Torquay",
    "sg:classifiers":[
        {
            "category":"Health Services",
            "subcategory":"Nursing And Care Facility",
            "type":"Services"
        },
        {
            "category":"Social Services",
            "subcategory":"Retirement Home",
            "type":"Services"
        }
    ],
    "sg:phone":"+44 1803 329203",
    "sg:postcode":"TQ1 3NN",
    "sg:province":"Devon",
    "sg:tags":[
        "residential"
    ],
    "wof:name":"Carl Court Rest Home",
    "wof:placetype":"venue"
},
  "geometry": {"coordinates":[-3.5216140747,50.4790763855],"type":"Point"}
}