{
  "type": "Feature",
  "properties": {
    "addr:full":"37 Clarence Street Southend On Sea Essex SS1 1BH",
    "addr:housenumber":"37",
    "addr:postcode":"ss1 1bh",
    "addr:street":"Clarence Street",
    "iso:country":"GB",
    "sg:address":"37 Clarence Street",
    "sg:city":"Southend On Sea",
    "sg:classifiers":[
        {
            "category":"Health Services",
            "subcategory":"Doctor",
            "type":"Services"
        }
    ],
    "sg:phone":"+44 1702 394384",
    "sg:postcode":"SS1 1BH",
    "sg:province":"Essex",
    "sg:tags":[
        "practitioners"
    ],
    "wof:name":"New Life Hypnotherapy",
    "wof:placetype":"venue"
},
  "geometry": {"coordinates":[0.712128,51.535561],"type":"Point"}
}