{
  "type": "Feature",
  "properties": {
    "iso:country":"GB",
    "sg:address":"43 Dilhorne Road, Cheadle",
    "sg:city":"Stoke-on-trent",
    "sg:classifiers":[
        {
            "category":"Retail",
            "subcategory":"Driving School",
            "type":"Services"
        }
    ],
    "sg:postcode":"ST10 1PT",
    "sg:province":"Staffordshire",
    "wof:name":"Top Gear School of Motoring",
    "wof:placetype":"venue"
},
  "geometry": {"coordinates":[-2.003369,52.985081],"type":"Point"}
}