{
  "type": "Feature",
  "properties": {
    "iso:country":"GB",
    "sg:address":"315 Preston Old Road",
    "sg:city":"Blackburn",
    "sg:classifiers":[
        {
            "category":"Building & Trades",
            "subcategory":"Landscaping Services",
            "type":"Services"
        }
    ],
    "sg:phone":"+44 1254 202286",
    "sg:postcode":"BB2 2TX",
    "sg:province":"Lancashire",
    "sg:tags":[
        "gardening"
    ],
    "wof:name":"John Edwards",
    "wof:placetype":"venue"
},
  "geometry": {"coordinates":[-2.516572,53.736389],"type":"Point"}
}