{
  "type": "Feature",
  "properties": {
    "iso:country":"GB",
    "sg:address":"1/5 Bond Street",
    "sg:city":"London",
    "sg:classifiers":[
        {
            "category":"Banks & Credit Unions",
            "subcategory":"Bank",
            "type":"Services"
        }
    ],
    "sg:phone":"+44 845 601 0110",
    "sg:postcode":"W5 5AR",
    "sg:province":"Greater London",
    "wof:name":"Halifax Plc",
    "wof:placetype":"venue"
},
  "geometry": {"coordinates":[-0.306339,51.512676],"type":"Point"}
}