{
  "type": "Feature",
  "properties": {
    "iso:country":"GB",
    "sg:address":"63 Ashdown Drive",
    "sg:city":"Borehamwood",
    "sg:classifiers":[
        {
            "category":"Professional",
            "subcategory":"Computer Services",
            "type":"Services"
        }
    ],
    "sg:postcode":"WD6 4NA",
    "sg:province":"Hertfordshire",
    "sg:tags":[
        "system",
        "software"
    ],
    "wof:name":"Logicsoft Ltd",
    "wof:placetype":"venue"
},
  "geometry": {"coordinates":[-0.288306,51.661095],"type":"Point"}
}