{
  "type": "Feature",
  "properties": {
    "iso:country":"GB",
    "sg:address":"4 Canal Street, Droylsden",
    "sg:city":"Manchester",
    "sg:classifiers":[
        {
            "category":"Professional",
            "subcategory":"Accounting & Tax Preparation",
            "type":"Services"
        }
    ],
    "sg:postcode":"M43 7UN",
    "sg:province":"Greater Manchester",
    "sg:tags":[
        "accountant"
    ],
    "wof:name":"A K Connor & Co",
    "wof:placetype":"venue"
},
  "geometry": {"coordinates":[-2.146244,53.478767],"type":"Point"}
}