{
  "type": "Feature",
  "properties": {
    "iso:country":"GB",
    "sg:address":"Care Of David Baxter Centre, 63 North Seventh St",
    "sg:city":"Milton Keynes",
    "sg:classifiers":[
        {
            "category":"Professional",
            "subcategory":"Lawyer & Legal Services",
            "type":"Services"
        }
    ],
    "sg:phone":"+44 1908 691969",
    "sg:postcode":"MK9 2DP",
    "sg:province":"Buckinghamshire",
    "sg:tags":[
        "advice",
        "counselling"
    ],
    "wof:name":"Milton Keynes Rape Crisis Centre",
    "wof:placetype":"venue"
},
  "geometry": {"coordinates":[-0.76383,52.042728],"type":"Point"}
}