{
  "type": "Feature",
  "properties": {
    "iso:country":"GB",
    "sg:address":"18 Mossbury Road",
    "sg:city":"London",
    "sg:classifiers":[
        {
            "category":"Travel",
            "subcategory":"Travel Agent",
            "type":"Entertainment"
        }
    ],
    "sg:postcode":"SW11 2PB",
    "sg:province":"Greater London",
    "wof:name":"International Travel Destinations Ltd.",
    "wof:placetype":"venue"
},
  "geometry": {"coordinates":[-0.167055,51.464161],"type":"Point"}
}