{
  "type": "Feature",
  "properties": {
    "iso:country":"GB",
    "sg:address":"1a High Street",
    "sg:city":"Downham Market",
    "sg:classifiers":[
        {
            "category":"Wholesale",
            "subcategory":"Groceries",
            "type":"Manufacturing & Wholesale Goods"
        }
    ],
    "sg:phone":"+44 1366 388472",
    "sg:postcode":"PE38 9DA",
    "sg:province":"Cambridgeshire",
    "sg:tags":[
        "food",
        "supplier",
        "drink"
    ],
    "wof:name":"Tinco",
    "wof:placetype":"venue"
},
  "geometry": {"coordinates":[0.378004,52.602341],"type":"Point"}
}