{
  "type": "Feature",
  "properties": {
    "addr:full":"14 Robinsfield Hemel Hempstead Hertfordshire HP1 1RW",
    "addr:housenumber":"14",
    "addr:postcode":"hp1 1rw",
    "addr:street":"Robinsfield Hemel Hempstead",
    "iso:country":"GB",
    "sg:address":"14 Robinsfield",
    "sg:city":"Hemel Hempstead",
    "sg:classifiers":[
        {
            "category":"Health Services",
            "subcategory":"Doctor",
            "type":"Services"
        },
        {
            "category":"Health Services",
            "subcategory":"Clinic",
            "type":"Services"
        }
    ],
    "sg:phone":"+44 1442 263199",
    "sg:postcode":"HP1 1RW",
    "sg:province":"Hertfordshire",
    "sg:tags":[
        "medical"
    ],
    "wof:name":"Marshcouch",
    "wof:placetype":"venue"
},
  "geometry": {"coordinates":[-0.490237,51.753582],"type":"Point"}
}