{
  "type": "Feature",
  "properties": {
    "addr:full":"159 White Hart Lane, Barnes London Greater London SW13 0JP",
    "addr:housenumber":"159",
    "addr:postcode":"sw13 0jp",
    "addr:street":"White Hart Lane",
    "iso:country":"GB",
    "sg:address":"159 White Hart Lane, Barnes",
    "sg:city":"London",
    "sg:classifiers":[
        {
            "category":"Personal",
            "subcategory":"Beauty Salon",
            "type":"Services"
        }
    ],
    "sg:phone":"+44 20 8876 5012",
    "sg:postcode":"SW13 0JP",
    "sg:province":"Greater London",
    "wof:name":"Profile",
    "wof:placetype":"venue"
},
  "geometry": {"coordinates":[-0.253343,51.466549],"type":"Point"}
}