{
  "type": "Feature",
  "properties": {
    "iso:country":"GB",
    "sg:address":"3 Bishops Walk, Forthampton",
    "sg:city":"Gloucester",
    "sg:classifiers":[
        {
            "category":"Banks & Credit Unions",
            "subcategory":"Bureau De Change",
            "type":"Services"
        },
        {
            "category":"Park",
            "subcategory":"Town Common",
            "type":"Public Place"
        }
    ],
    "sg:phone":"+44 1684 297463",
    "sg:postcode":"GL19 4QF",
    "sg:province":"Gloucestershire",
    "sg:tags":[
        "consultant",
        "planning",
        "city"
    ],
    "wof:name":"Neil Hadley & Associates",
    "wof:placetype":"venue"
},
  "geometry": {"coordinates":[-2.209526,51.991806],"type":"Point"}
}