{
  "type": "Feature",
  "properties": {
    "addr:full":"34 Princess Victoria Rd Bristol City of Bristol BS8 4BZ",
    "addr:housenumber":"34",
    "addr:postcode":"bs8 4bz",
    "addr:street":"Princess Victoria Rd",
    "iso:country":"GB",
    "sg:address":"34 Princess Victoria Rd",
    "sg:city":"Bristol",
    "sg:classifiers":[
        {
            "category":"Shopping",
            "subcategory":"Thrift Store",
            "type":"Retail Goods"
        }
    ],
    "sg:phone":"+44 117 973 1459",
    "sg:postcode":"BS8 4BZ",
    "sg:province":"City of Bristol",
    "sg:tags":[
        "shop",
        "charity"
    ],
    "wof:name":"The Sue Ryder Foundation",
    "wof:placetype":"venue"
},
  "geometry": {"coordinates":[-2.6208999157,51.4545249939],"type":"Point"}
}