{
  "type": "Feature",
  "properties": {
    "addr:full":"Cecil Street, The Butts Walsall West Midlands WS4 2AY",
    "addr:postcode":"ws4 2ay",
    "addr:street":"Cecil Street The Butts",
    "iso:country":"GB",
    "sg:address":"Cecil Street, The Butts",
    "sg:city":"Walsall",
    "sg:classifiers":[
        {
            "category":"Farming",
            "subcategory":"Nursery",
            "type":"Manufacturing & Wholesale Goods"
        }
    ],
    "sg:postcode":"WS4 2AY",
    "sg:province":"West Midlands",
    "sg:tags":[
        "creche"
    ],
    "wof:name":"Butt Babes Nursery",
    "wof:placetype":"venue"
},
  "geometry": {"coordinates":[-1.978022,52.592632],"type":"Point"}
}