{
  "type": "Feature",
  "properties": {
    "addr:full":"672 North Row, Central Milton Keynes Milton Keynes Buckinghamshire MK9 3AP",
    "addr:housenumber":"672",
    "addr:postcode":"mk9 3ap",
    "addr:street":"North Row",
    "iso:country":"GB",
    "sg:address":"672 North Row, Central Milton Keynes",
    "sg:city":"Milton Keynes",
    "sg:classifiers":[
        {
            "category":"Professional",
            "subcategory":"Employment Agencies",
            "type":"Services"
        }
    ],
    "sg:phone":"+44 1908 200891",
    "sg:postcode":"MK9 3AP",
    "sg:province":"Buckinghamshire",
    "sg:tags":[
        "consultant"
    ],
    "wof:name":"Parkhouse Personnel Ltd.",
    "wof:placetype":"venue"
},
  "geometry": {"coordinates":[-0.758545,52.045559],"type":"Point"}
}