{
  "type": "Feature",
  "properties": {
    "iso:country":"GB",
    "sg:address":"3 Saxon Park",
    "sg:city":"Corby",
    "sg:classifiers":[
        {
            "category":"Home & Garden",
            "subcategory":"Home Furnishings",
            "type":"Retail Goods"
        },
        {
            "category":"Home & Garden",
            "subcategory":"Building Materials",
            "type":"Retail Goods"
        }
    ],
    "sg:phone":"+44 1536 744024",
    "sg:postcode":"NN18 9EY",
    "sg:province":"Northamptonshire",
    "sg:tags":[
        "installers",
        "planner",
        "kitchen",
        "furnishers"
    ],
    "wof:name":"In Touch Interiors",
    "wof:placetype":"venue"
},
  "geometry": {"coordinates":[-0.736875,52.46455],"type":"Point"}
}