{
  "type": "Feature",
  "properties": {
    "addr:full":"Harvey Road Birmingham West Midlands B26 1TD",
    "addr:postcode":"b26 1td",
    "addr:street":"Harvey Road",
    "iso:country":"GB",
    "sg:address":"Harvey Road",
    "sg:city":"Birmingham",
    "sg:classifiers":[
        {
            "category":"Education",
            "subcategory":"School",
            "type":"Public Place"
        }
    ],
    "sg:phone":"+44 121 783 3235",
    "sg:postcode":"B26 1TD",
    "sg:province":"West Midlands",
    "sg:tags":[
        "local",
        "authority"
    ],
    "wof:name":"Yardley Infant School",
    "wof:placetype":"venue"
},
  "geometry": {"coordinates":[-1.809092,52.464943],"type":"Point"}
}