{
  "type": "Feature",
  "properties": {
    "addr:full":"Newells Lane, Maplehurst Horsham West Sussex RH13 6LN",
    "addr:postcode":"rh13 6ln",
    "addr:street":"Newells Lane",
    "iso:country":"GB",
    "sg:address":"Newells Lane, Maplehurst",
    "sg:city":"Horsham",
    "sg:classifiers":[
        {
            "category":"Farming",
            "subcategory":"Poultry Farm",
            "type":"Manufacturing & Wholesale Goods"
        }
    ],
    "sg:postcode":"RH13 6LN",
    "sg:province":"West Sussex",
    "sg:tags":[
        "game"
    ],
    "wof:name":"Windyridge Farm",
    "wof:placetype":"venue"
},
  "geometry": {"coordinates":[-0.3064750135,51.0081672668],"type":"Point"}
}