{
  "type": "Feature",
  "properties": {
    "addr:full":"36 Holloway Circus, Queensway Birmingham West Midlands B1 1BA",
    "addr:housenumber":"36",
    "addr:postcode":"b1 1ba",
    "addr:street":"Holloway Circus Queensway",
    "iso:country":"GB",
    "sg:address":"36 Holloway Circus, Queensway",
    "sg:city":"Birmingham",
    "sg:classifiers":[
        {
            "category":"Real Estate",
            "subcategory":"Real Estate Operator",
            "type":"Services"
        }
    ],
    "sg:phone":"+44 121 643 1367",
    "sg:postcode":"B1 1BA",
    "sg:province":"West Midlands",
    "sg:tags":[
        "letting",
        "agent"
    ],
    "wof:name":"Willow Estates",
    "wof:placetype":"venue"
},
  "geometry": {"coordinates":[-1.900014,52.474762],"type":"Point"}
}