{
  "type": "Feature",
  "properties": {
    "addr:full":"32 Caskgate Street Gainsborough Lincolnshire DN21 2DL",
    "addr:housenumber":"32",
    "addr:postcode":"dn21 2dl",
    "addr:street":"Caskgate Street",
    "iso:country":"GB",
    "sg:address":"32 Caskgate Street",
    "sg:city":"Gainsborough",
    "sg:classifiers":[
        {
            "category":"Autos & Motor Vehicles",
            "subcategory":"Auto Supplies",
            "type":"Retail Goods"
        }
    ],
    "sg:phone":"+44 1427 613897",
    "sg:postcode":"DN21 2DL",
    "sg:province":"Lincolnshire",
    "sg:tags":[
        "component"
    ],
    "wof:name":"Autocom Units Ltd.",
    "wof:placetype":"venue"
},
  "geometry": {"coordinates":[-0.7774900198,53.3982963562],"type":"Point"}
}