{
  "type": "Feature",
  "properties": {
    "addr:full":"Copper View Newtown Powys SY16 4PD",
    "addr:postcode":"sy16 4pd",
    "addr:street":"Copper View",
    "iso:country":"GB",
    "sg:address":"Copper View",
    "sg:city":"Newtown",
    "sg:classifiers":[
        {
            "category":"Professional",
            "subcategory":"Engineering",
            "type":"Services"
        }
    ],
    "sg:phone":"+44 1686 670291",
    "sg:postcode":"SY16 4PD",
    "sg:province":"Powys",
    "sg:tags":[
        "precision",
        "engineer"
    ],
    "wof:name":"D P Pryce Precision Engineering",
    "wof:placetype":"venue"
},
  "geometry": {"coordinates":[-3.314612,52.512775],"type":"Point"}
}