{
  "type": "Feature",
  "properties": {
    "addr:full":"Artafallie Farm, North Kessock Inverness Highland IV1 3ZD",
    "addr:postcode":"iv1 3zd",
    "addr:street":"North Kessock",
    "iso:country":"GB",
    "sg:address":"Artafallie Farm, North Kessock",
    "sg:city":"Inverness",
    "sg:classifiers":[
        {
            "category":"Farming",
            "subcategory":"Livestock Farm",
            "type":"Manufacturing & Wholesale Goods"
        }
    ],
    "sg:phone":"+44 1463 731586",
    "sg:postcode":"IV1 3ZD",
    "sg:province":"Highland",
    "sg:tags":[
        "others"
    ],
    "wof:name":"H & I Livestock Ltd.",
    "wof:placetype":"venue"
},
  "geometry": {"coordinates":[-4.2624588013,57.5065155029],"type":"Point"}
}