{
  "type": "Feature",
  "properties": {
    "addr:full":"2 Springwell Rd Durham Durham DH1 4LR",
    "addr:housenumber":"2",
    "addr:postcode":"dh1 4lr",
    "addr:street":"Springwell Rd",
    "iso:country":"GB",
    "sg:address":"2 Springwell Rd",
    "sg:city":"Durham",
    "sg:classifiers":[
        {
            "category":"Health Services",
            "subcategory":"Doctor",
            "type":"Services"
        }
    ],
    "sg:phone":"+44 191 386 2852",
    "sg:postcode":"DH1 4LR",
    "sg:province":"Durham",
    "sg:tags":[
        "practitioners"
    ],
    "wof:name":"Green, M R",
    "wof:placetype":"venue"
},
  "geometry": {"coordinates":[-1.593358,54.784588],"type":"Point"}
}