{
  "type": "Feature",
  "properties": {
    "iso:country":"GB",
    "sg:address":"Fell View Garage",
    "sg:city":"Brampton",
    "sg:classifiers":[
        {
            "category":"Retail",
            "subcategory":"Auto Repair",
            "type":"Services"
        }
    ],
    "sg:phone":"+44 16977 46244",
    "sg:postcode":"CA8 2NJ",
    "sg:province":"Cumbria",
    "sg:tags":[
        "modification",
        "garage"
    ],
    "wof:name":"Fergusons",
    "wof:placetype":"venue"
},
  "geometry": {"coordinates":[-2.7372810841,54.9422798157],"type":"Point"}
}