{
  "type": "Feature",
  "properties": {
    "addr:full":"Unit 4, 49 Brimington Rd North Chesterfield Derbyshire S41 9BE",
    "addr:housenumber":"unit;49",
    "addr:postcode":"s41 9be",
    "addr:street":"Brimington Rd",
    "iso:country":"GB",
    "sg:address":"Unit 4, 49 Brimington Rd North",
    "sg:city":"Chesterfield",
    "sg:classifiers":[
        {
            "category":"Building & Trades",
            "subcategory":"Cleaning & Sanitation",
            "type":"Services"
        }
    ],
    "sg:phone":"+44 1246 268825",
    "sg:postcode":"S41 9BE",
    "sg:province":"Derbyshire",
    "sg:tags":[
        "blast"
    ],
    "wof:name":"Monsal Decor",
    "wof:placetype":"venue"
},
  "geometry": {"coordinates":[-1.4182590246,53.2584228516],"type":"Point"}
}