{
  "type": "Feature",
  "properties": {
    "addr:full":"117-119 Warwick Street Leamington Spa Warwickshire CV32 4QZ",
    "addr:housenumber":"117-119",
    "addr:postcode":"cv32 4qz",
    "addr:street":"Warwick Street",
    "iso:country":"GB",
    "sg:address":"117-119 Warwick Street",
    "sg:city":"Leamington Spa",
    "sg:classifiers":[
        {
            "category":"Home & Garden",
            "subcategory":"Furniture",
            "type":"Retail Goods"
        }
    ],
    "sg:phone":"+44 1926 428326",
    "sg:postcode":"CV32 4QZ",
    "sg:province":"Warwickshire",
    "wof:name":"Bentleys of Leamington Spa",
    "wof:placetype":"venue"
},
  "geometry": {"coordinates":[-1.5317369699,52.2923202515],"type":"Point"}
}