{
  "type": "Feature",
  "properties": {
    "addr:full":"19 William Smith Close, Churchill Chipping Norton Gloucestershire OX7 6QS",
    "addr:housenumber":"19",
    "addr:postcode":"ox7 6qs",
    "addr:street":"William Smith Close",
    "iso:country":"GB",
    "sg:address":"19 William Smith Close, Churchill",
    "sg:city":"Chipping Norton",
    "sg:classifiers":[
        {
            "category":"Professional",
            "subcategory":"Management & Consulting",
            "type":"Services"
        },
        {
            "category":"Professional",
            "subcategory":"Computer Services",
            "type":"Services"
        }
    ],
    "sg:phone":"+44 1608 658172",
    "sg:postcode":"OX7 6QS",
    "sg:province":"Gloucestershire",
    "sg:tags":[
        "consultant",
        "business",
        "information"
    ],
    "wof:name":"Rs2j Consulting Ltd",
    "wof:placetype":"venue"
},
  "geometry": {"coordinates":[-1.592474,51.912815],"type":"Point"}
}