{
  "type": "Feature",
  "properties": {
    "addr:full":"Silverburn Pl Aberdeen Aberdeen City AB23 8EG",
    "addr:postcode":"ab23 8eg",
    "addr:street":"Silverburn Pl",
    "iso:country":"GB",
    "sg:address":"Silverburn Pl",
    "sg:city":"Aberdeen",
    "sg:classifiers":[
        {
            "category":"Mining & Drilling",
            "type":"Manufacturing & Wholesale Goods"
        }
    ],
    "sg:phone":"+44 1224 703123",
    "sg:postcode":"AB23 8EG",
    "sg:province":"Aberdeen City",
    "sg:tags":[
        "contractor"
    ],
    "wof:name":"Martin Decker Totco",
    "wof:placetype":"venue"
},
  "geometry": {"coordinates":[-2.0730888844,57.225818634],"type":"Point"}
}