{
  "type": "Feature",
  "properties": {
    "iso:country":"GB",
    "sg:address":"Unit 6, Rose Acres, Astley",
    "sg:city":"Stourport On Severn",
    "sg:classifiers":[
        {
            "category":"Building & Trades",
            "subcategory":"Construction",
            "type":"Services"
        }
    ],
    "sg:phone":"+44 1299 879997",
    "sg:postcode":"DY13 0RG",
    "sg:province":"Worcestershire",
    "sg:tags":[
        "glazier"
    ],
    "wof:name":"Belus Glass & Windows",
    "wof:placetype":"venue"
},
  "geometry": {"coordinates":[-2.314414,52.306648],"type":"Point"}
}