{
  "type": "Feature",
  "properties": {
    "iso:country":"GB",
    "sg:address":"73 Cotterhill Lane, Brimington",
    "sg:city":"Chesterfield",
    "sg:classifiers":[
        {
            "category":"Home & Garden",
            "subcategory":"Home Furnishings",
            "type":"Retail Goods"
        }
    ],
    "sg:phone":"+44 1246 230449",
    "sg:postcode":"S43 1NL",
    "sg:province":"Derbyshire",
    "sg:tags":[
        "furnishers",
        "planner",
        "kitchen"
    ],
    "wof:name":"Hartfields",
    "wof:placetype":"venue"
},
  "geometry": {"coordinates":[-1.395686,53.255455],"type":"Point"}
}