{
  "type": "Feature",
  "properties": {
    "iso:country":"GB",
    "sg:address":"Barlborough",
    "sg:city":"Chesterfield",
    "sg:classifiers":[
        {
            "category":"Bars & Pubs",
            "type":"Food & Drink"
        }
    ],
    "sg:phone":"+44 1246 810327",
    "sg:postcode":"S43 4TH",
    "sg:province":"Derbyshire",
    "sg:tags":[
        "pubs",
        "inn"
    ],
    "wof:name":"Pebley Inn",
    "wof:placetype":"venue"
},
  "geometry": {"coordinates":[-1.28132,53.308441],"type":"Point"}
}