{
  "type": "Feature",
  "properties": {
    "iso:country":"GB",
    "sg:address":"21 Maple Way, Headley Down",
    "sg:city":"Bordon",
    "sg:classifiers":[
        {
            "category":"Utilities",
            "subcategory":"Refuse",
            "type":"Services"
        }
    ],
    "sg:phone":"+44 1428 713437",
    "sg:postcode":"GU35 8AU",
    "sg:province":"Hampshire",
    "sg:tags":[
        "skip",
        "hire"
    ],
    "wof:name":"Garden & Household Clearance",
    "wof:placetype":"venue"
},
  "geometry": {"coordinates":[-0.80201298,51.1228523254],"type":"Point"}
}