{
  "type": "Feature",
  "properties": {
    "addr:full":"59 Turnham Green Terrace London Greater London W4 1RP",
    "addr:housenumber":"59",
    "addr:postcode":"w4 1rp",
    "addr:street":"Turnham Green Terrace",
    "iso:country":"GB",
    "sg:address":"59 Turnham Green Terrace",
    "sg:city":"London",
    "sg:classifiers":[
        {
            "category":"Personal",
            "subcategory":"Beauty Salon",
            "type":"Services"
        },
        {
            "category":"Professional",
            "subcategory":"Management & Consulting",
            "type":"Services"
        }
    ],
    "sg:phone":"+44 20 8995 7360",
    "sg:postcode":"W4 1RP",
    "sg:province":"Greater London",
    "sg:tags":[
        "consultant",
        "specialist"
    ],
    "wof:name":"Chrysalis Beauty Salon",
    "wof:placetype":"venue"
},
  "geometry": {"coordinates":[-0.255539,51.494358],"type":"Point"}
}