{
  "type": "Feature",
  "properties": {
    "iso:country":"GB",
    "sg:address":"8 Star Lane",
    "sg:city":"Dunmow",
    "sg:classifiers":[
        {
            "category":"Utilities",
            "type":"Services"
        }
    ],
    "sg:phone":"+44 870 904 6868",
    "sg:postcode":"CM6 1AY",
    "sg:province":"Essex",
    "sg:tags":[
        "internet"
    ],
    "wof:name":"68 Creative Solutions",
    "wof:placetype":"venue"
},
  "geometry": {"coordinates":[0.361707,51.874249],"type":"Point"}
}