{
  "type": "Feature",
  "properties": {
    "addr:full":"Shear Way, Burmarsh Romney Marsh Kent TN29 0JJ",
    "addr:postcode":"tn29 0jj",
    "addr:street":"Shear Way",
    "iso:country":"GB",
    "sg:address":"Shear Way, Burmarsh",
    "sg:city":"Romney Marsh",
    "sg:classifiers":[
        {
            "category":"Bars & Pubs",
            "type":"Food & Drink"
        }
    ],
    "sg:phone":"+44 1303 872336",
    "sg:postcode":"TN29 0JJ",
    "sg:province":"Kent",
    "sg:tags":[
        "pubs",
        "inn"
    ],
    "wof:name":"The Shepherd & Crook Inn",
    "wof:placetype":"venue"
},
  "geometry": {"coordinates":[0.9226999879,51.0038833618],"type":"Point"}
}