{
  "type": "Feature",
  "properties": {
    "addr:full":"Wensley Drive Leeds West Yorkshire LS7 2LT",
    "addr:postcode":"ls7 2lt",
    "addr:street":"Wensley Drive",
    "iso:country":"GB",
    "sg:address":"Wensley Drive",
    "sg:city":"Leeds",
    "sg:classifiers":[
        {
            "category":"Retail",
            "subcategory":"Driving School",
            "type":"Services"
        }
    ],
    "sg:phone":"+44 113 269 3533",
    "sg:postcode":"LS7 2LT",
    "sg:province":"West Yorkshire",
    "wof:name":"Ken Harrison",
    "wof:placetype":"venue"
},
  "geometry": {"coordinates":[-1.5454590321,53.8312416077],"type":"Point"}
}