{
  "type": "Feature",
  "properties": {
    "addr:full":"Century House, 2 Turf Lane, Chadderton Oldham Lancashire OL9 8HL",
    "addr:housenumber":"2",
    "addr:postcode":"ol9 8hl",
    "addr:street":"Turf Lane",
    "iso:country":"GB",
    "sg:address":"Century House, 2 Turf Lane, Chadderton",
    "sg:city":"Oldham",
    "sg:classifiers":[
        {
            "category":"Communications",
            "subcategory":"Newspaper",
            "type":"Services"
        }
    ],
    "sg:phone":"+44 161 287 3773",
    "sg:postcode":"OL9 8HL",
    "sg:province":"Lancashire",
    "sg:tags":[
        "magazine"
    ],
    "wof:name":"City Centinel",
    "wof:placetype":"venue"
},
  "geometry": {"coordinates":[-2.148654,53.525284],"type":"Point"}
}