{
  "type": "Feature",
  "properties": {
    "iso:country":"GB",
    "sg:address":"18 St. Johns Chambers, Ashwell St",
    "sg:city":"Leicester",
    "sg:classifiers":[
        {
            "category":"Health Services",
            "subcategory":"Health Practitioner",
            "type":"Services"
        }
    ],
    "sg:phone":"+44 116 254 5451",
    "sg:postcode":"LE1 6JJ",
    "sg:province":"Leicestershire",
    "sg:tags":[
        "physiotherapist"
    ],
    "wof:name":"J V Hurd",
    "wof:placetype":"venue"
},
  "geometry": {"coordinates":[-1.140365,52.637886],"type":"Point"}
}