{
  "type": "Feature",
  "properties": {
    "addr:full":"11-15 St Mary At Hill London Greater London EC3R 8EE",
    "addr:housenumber":"11-15",
    "addr:postcode":"ec3r 8ee",
    "addr:street":"St;At Hill",
    "iso:country":"GB",
    "sg:address":"11-15 St Mary At Hill",
    "sg:city":"London",
    "sg:classifiers":[
        {
            "category":"Professional",
            "subcategory":"Business Services",
            "type":"Services"
        }
    ],
    "sg:phone":"+44 20 7929 2130",
    "sg:postcode":"EC3R 8EE",
    "sg:province":"Greater London",
    "sg:tags":[
        "import",
        "export",
        "agent"
    ],
    "wof:name":"S B S Trade & Finance International Ltd.",
    "wof:placetype":"venue"
},
  "geometry": {"coordinates":[-0.0157869998,51.5836715698],"type":"Point"}
}