{
  "type": "Feature",
  "properties": {
    "iso:country":"GB",
    "sg:address":"2 Wheatfield Rd",
    "sg:city":"Ayr",
    "sg:classifiers":[
        {
            "category":"Professional",
            "type":"Services"
        }
    ],
    "sg:phone":"+44 1292 287142",
    "sg:postcode":"KA7 2XB",
    "sg:province":"South Ayrshire",
    "sg:tags":[
        "reflexologists"
    ],
    "wof:name":"Scottish School of Reflexology",
    "wof:placetype":"venue"
},
  "geometry": {"coordinates":[-4.6289458275,55.4506416321],"type":"Point"}
}