{
  "type": "Feature",
  "properties": {
    "addr:full":"72 High St Esher Surrey KT10 9QS",
    "addr:housenumber":"72",
    "addr:postcode":"kt10 9qs",
    "addr:street":"High St",
    "iso:country":"GB",
    "sg:address":"72 High St",
    "sg:city":"Esher",
    "sg:classifiers":[
        {
            "category":"Professional",
            "subcategory":"Management & Consulting",
            "type":"Services"
        }
    ],
    "sg:phone":"+44 1372 463555",
    "sg:postcode":"KT10 9QS",
    "sg:province":"Surrey",
    "sg:tags":[
        "consultant",
        "specialist"
    ],
    "wof:name":"Pamela Stevens Beauty Clinic",
    "wof:placetype":"venue"
},
  "geometry": {"coordinates":[-0.366264,51.369305],"type":"Point"}
}