{
  "type": "Feature",
  "properties": {
    "iso:country":"GB",
    "sg:address":"Broadway",
    "sg:city":"Bridgwater",
    "sg:classifiers":[
        {
            "category":"Home & Garden",
            "subcategory":"Garden Supply",
            "type":"Retail Goods"
        }
    ],
    "sg:phone":"+44 1278 422897",
    "sg:postcode":"TA6 3LN",
    "sg:province":"Somerset",
    "sg:tags":[
        "nursery",
        "centre"
    ],
    "wof:name":"Trinity Nursery",
    "wof:placetype":"venue"
},
  "geometry": {"coordinates":[-3.008969,51.127129],"type":"Point"}
}