{
  "type": "Feature",
  "properties": {
    "addr:full":"Unit 3 Aire & Calder Industrial Park, Lock Lane Castleford West Yorkshire WF10 2JA",
    "addr:housenumber":"unit 3",
    "addr:postcode":"wf10 2ja",
    "addr:street":"&;Industrial Park Lock Lane",
    "iso:country":"GB",
    "sg:address":"Unit 3 Aire & Calder Industrial Park, Lock Lane",
    "sg:city":"Castleford",
    "sg:classifiers":[
        {
            "category":"Retail",
            "subcategory":"Emissions Testing",
            "type":"Services"
        },
        {
            "category":"Autos & Motor Vehicles",
            "subcategory":"Automobile Sales",
            "type":"Retail Goods"
        }
    ],
    "sg:phone":"+44 1977 518484",
    "sg:postcode":"WF10 2JA",
    "sg:province":"West Yorkshire",
    "sg:tags":[
        "car",
        "mot"
    ],
    "wof:name":"Pildacre Car Sales",
    "wof:placetype":"venue"
},
  "geometry": {"coordinates":[-1.3486800194,53.7281417847],"type":"Point"}
}