{
  "type": "Feature",
  "properties": {
    "addr:full":"116 High Street Hounslow Greater London TW3 1NA",
    "addr:housenumber":"116",
    "addr:postcode":"tw3 1na",
    "addr:street":"High Street",
    "iso:country":"GB",
    "sg:address":"116 High Street",
    "sg:city":"Hounslow",
    "sg:classifiers":[
        {
            "category":"Shopping",
            "subcategory":"Gifts & Souvenirs",
            "type":"Retail Goods"
        }
    ],
    "sg:phone":"+44 20 8577 1443",
    "sg:postcode":"TW3 1NA",
    "sg:province":"Greater London",
    "sg:tags":[
        "poster",
        "card"
    ],
    "wof:name":"Hall of Cards",
    "wof:placetype":"venue"
},
  "geometry": {"coordinates":[-0.359329,51.469631],"type":"Point"}
}