{
  "type": "Feature",
  "properties": {
    "addr:full":"32 Hill St, Totterdown Bristol City of Bristol BS3 4TW",
    "addr:housenumber":"32",
    "addr:postcode":"bs3 4tw",
    "addr:street":"Hill St",
    "iso:country":"GB",
    "sg:address":"32 Hill St, Totterdown",
    "sg:city":"Bristol",
    "sg:classifiers":[
        {
            "category":"Professional",
            "subcategory":"Accounting & Tax Preparation",
            "type":"Services"
        }
    ],
    "sg:phone":"+44 117 971 7435",
    "sg:postcode":"BS3 4TW",
    "sg:province":"City of Bristol",
    "sg:tags":[
        "accountant"
    ],
    "wof:name":"Linkom Voluntary Sector Accounting",
    "wof:placetype":"venue"
},
  "geometry": {"coordinates":[-2.582547,51.443195],"type":"Point"}
}