{
  "type": "Feature",
  "properties": {
    "addr:full":"139 Hainton Av Grimsby Lincolnshire DN32 9LF",
    "addr:housenumber":"139",
    "addr:postcode":"dn32 9lf",
    "addr:street":"Av Grimsby",
    "iso:country":"GB",
    "sg:address":"139 Hainton Av",
    "sg:city":"Grimsby",
    "sg:classifiers":[
        {
            "category":"Professional",
            "subcategory":"Computer Services",
            "type":"Services"
        }
    ],
    "sg:phone":"+44 1472 232023",
    "sg:postcode":"DN32 9LF",
    "sg:province":"Lincolnshire",
    "sg:tags":[
        "system",
        "software"
    ],
    "wof:name":"Business Point Associates",
    "wof:placetype":"venue"
},
  "geometry": {"coordinates":[-0.075636,53.563202],"type":"Point"}
}