{
  "type": "Feature",
  "properties": {
    "addr:full":"Collum Avenue Scunthorpe Lincolnshire DN16 2TF",
    "addr:postcode":"dn16 2tf",
    "addr:street":"Collum Avenue",
    "iso:country":"GB",
    "sg:address":"Collum Avenue",
    "sg:city":"Scunthorpe",
    "sg:classifiers":[
        {
            "category":"Education",
            "subcategory":"School",
            "type":"Public Place"
        },
        {
            "category":"Government",
            "subcategory":"Office",
            "type":"Public Place"
        }
    ],
    "sg:phone":"+44 1724 861371",
    "sg:postcode":"DN16 2TF",
    "sg:province":"Lincolnshire",
    "sg:tags":[
        "local",
        "authority"
    ],
    "wof:name":"St Bede's School",
    "wof:placetype":"venue"
},
  "geometry": {"coordinates":[-0.6438090205,53.5743865967],"type":"Point"}
}