{
  "type": "Feature",
  "properties": {
    "addr:full":"130 Chalton Lane, Clanfield Waterlooville Hampshire PO8 0RJ",
    "addr:housenumber":"130",
    "addr:postcode":"po8 0rj",
    "addr:street":"Chalton Lane",
    "iso:country":"GB",
    "sg:address":"130 Chalton Lane, Clanfield",
    "sg:city":"Waterlooville",
    "sg:classifiers":[
        {
            "category":"Building & Trades",
            "subcategory":"Construction",
            "type":"Services"
        }
    ],
    "sg:postcode":"PO8 0RJ",
    "sg:province":"Hampshire",
    "sg:tags":[
        "joiner",
        "carpenter"
    ],
    "wof:name":"Len Scott",
    "wof:placetype":"venue"
},
  "geometry": {"coordinates":[-1.0074369907,50.9468078613],"type":"Point"}
}