{
  "type": "Feature",
  "properties": {
    "iso:country":"GB",
    "sg:address":"3a Granary Lane, Littleport",
    "sg:city":"Ely",
    "sg:classifiers":[
        {
            "category":"Professional",
            "subcategory":"Engineering",
            "type":"Services"
        }
    ],
    "sg:phone":"+44 1353 860343",
    "sg:postcode":"CB6 1PQ",
    "sg:province":"Cambridgeshire",
    "sg:tags":[
        "contractor",
        "electrical",
        "engineer"
    ],
    "wof:name":"A Tassell",
    "wof:placetype":"venue"
},
  "geometry": {"coordinates":[0.3071250021,52.4572486877],"type":"Point"}
}