{
  "type": "Feature",
  "properties": {
    "iso:country":"GB",
    "sg:address":"Warren Close",
    "sg:city":"Brandon",
    "sg:classifiers":[
        {
            "category":"Community Center",
            "type":"Public Place"
        }
    ],
    "sg:phone":"+44 1842 810161",
    "sg:postcode":"IP27 0EE",
    "sg:province":"Norfolk",
    "sg:tags":[
        "centre"
    ],
    "wof:name":"BRANDON COMMUNITY CENTRE",
    "wof:placetype":"venue"
},
  "geometry": {"coordinates":[0.6259639859,52.4447250366],"type":"Point"}
}