{
  "type": "Feature",
  "properties": {
    "addr:full":"92-100 London Road Liverpool Merseyside L3 5NL",
    "addr:housenumber":"92-100",
    "addr:postcode":"l3 5nl",
    "addr:street":"London Road",
    "iso:country":"GB",
    "sg:address":"92-100 London Road",
    "sg:city":"Liverpool",
    "sg:classifiers":[
        {
            "category":"Education",
            "subcategory":"College",
            "type":"Public Place"
        },
        {
            "category":"Education",
            "subcategory":"University",
            "type":"Public Place"
        }
    ],
    "sg:phone":"+44 151 709 0701",
    "sg:postcode":"L3 5NL",
    "sg:province":"Merseyside",
    "sg:tags":[
        "school",
        "outfitter"
    ],
    "wof:name":"Laser Schoolwear Ltd",
    "wof:placetype":"venue"
},
  "geometry": {"coordinates":[-2.9720430374,53.4094200134],"type":"Point"}
}