{
  "type": "Feature",
  "properties": {
    "addr:full":"The Old Smithy, Llanwnda Caernarfon Gwynedd LL54 5SD",
    "addr:postcode":"ll54 5sd",
    "iso:country":"GB",
    "sg:address":"The Old Smithy, Llanwnda",
    "sg:city":"Caernarfon",
    "sg:classifiers":[
        {
            "category":"Home & Garden",
            "subcategory":"Home Furnishings",
            "type":"Retail Goods"
        }
    ],
    "sg:phone":"+44 1286 831277",
    "sg:postcode":"LL54 5SD",
    "sg:province":"Gwynedd",
    "sg:tags":[
        "homefurnishings"
    ],
    "wof:name":"Forget Me Knot Furniture",
    "wof:placetype":"venue"
},
  "geometry": {"coordinates":[-4.2777280807,53.1001281738],"type":"Point"}
}