{
  "type": "Feature",
  "properties": {
    "addr:full":"Weeley Garage, 1 Colchester Road, Weeley Clacton On Sea Essex CO16 9JT",
    "addr:housenumber":"1",
    "addr:postcode":"co16 9jt",
    "addr:street":"Colchester Road;Sea",
    "iso:country":"GB",
    "sg:address":"Weeley Garage, 1 Colchester Road, Weeley",
    "sg:city":"Clacton On Sea",
    "sg:classifiers":[
        {
            "category":"Autos & Motor Vehicles",
            "subcategory":"Automobile Sales",
            "type":"Retail Goods"
        }
    ],
    "sg:phone":"+44 1255 831384",
    "sg:postcode":"CO16 9JT",
    "sg:province":"Essex",
    "sg:tags":[
        "car"
    ],
    "wof:name":"Albany Car Sales",
    "wof:placetype":"venue"
},
  "geometry": {"coordinates":[1.1130330563,51.8573226929],"type":"Point"}
}