{
  "type": "Feature",
  "properties": {
    "addr:full":"9b Guthrie Street Dundee Dundee City DD1 5DR",
    "addr:housenumber":"9b",
    "addr:postcode":"dd1 5dr",
    "addr:street":"Guthrie Street",
    "iso:country":"GB",
    "sg:address":"9b Guthrie Street",
    "sg:city":"Dundee",
    "sg:classifiers":[
        {
            "category":"Home & Garden",
            "subcategory":"Furniture",
            "type":"Retail Goods"
        }
    ],
    "sg:postcode":"DD1 5DR",
    "sg:province":"Dundee City",
    "wof:name":"A A D Furniture Centre",
    "wof:placetype":"venue"
},
  "geometry": {"coordinates":[-2.980149,56.461266],"type":"Point"}
}