{
  "type": "Feature",
  "properties": {
    "addr:full":"Leicester House Ewe Lamb Lane, Beeston Nottingham Nottinghamshire NG9 3LS",
    "addr:postcode":"ng9 3ls",
    "addr:street":"Lamb Lane",
    "iso:country":"GB",
    "sg:address":"Leicester House Ewe Lamb Lane, Beeston",
    "sg:city":"Nottingham",
    "sg:classifiers":[
        {
            "category":"Social Services",
            "subcategory":"Retirement Home",
            "type":"Services"
        },
        {
            "category":"Organizations",
            "subcategory":"Community Association",
            "type":"Services"
        }
    ],
    "sg:phone":"+44 115 939 0881",
    "sg:postcode":"NG9 3LS",
    "sg:province":"Nottinghamshire",
    "sg:tags":[
        "society",
        "housing",
        "sheltered",
        "accommodation"
    ],
    "wof:name":"Leicester Housing Association Ltd.",
    "wof:placetype":"venue"
},
  "geometry": {"coordinates":[-1.2609659433,52.9393920898],"type":"Point"}
}