{
  "type": "Feature",
  "properties": {
    "addr:full":"11 Newgate Street Morpeth Northumberland NE61 1AL",
    "addr:housenumber":"11",
    "addr:postcode":"ne61 1al",
    "addr:street":"Newgate Street",
    "iso:country":"GB",
    "sg:address":"11 Newgate Street",
    "sg:city":"Morpeth",
    "sg:classifiers":[
        {
            "category":"Shopping",
            "subcategory":"Optician",
            "type":"Retail Goods"
        }
    ],
    "sg:phone":"+44 1670 511797",
    "sg:postcode":"NE61 1AL",
    "sg:province":"Northumberland",
    "sg:tags":[
        "dispensing"
    ],
    "wof:name":"Specs Galore Ltd.",
    "wof:placetype":"venue"
},
  "geometry": {"coordinates":[-1.690951,55.167946],"type":"Point"}
}