{
  "type": "Feature",
  "properties": {
    "iso:country":"GB",
    "sg:address":"Foundation Ho, Lower Church St",
    "sg:city":"High Wycombe",
    "sg:classifiers":[
        {
            "category":"Utilities",
            "subcategory":"Telephone",
            "type":"Services"
        }
    ],
    "sg:phone":"+44 1494 485021",
    "sg:postcode":"HP14 3TG",
    "sg:province":"Buckinghamshire",
    "sg:tags":[
        "telecommunication"
    ],
    "wof:name":"Vocality",
    "wof:placetype":"venue"
},
  "geometry": {"coordinates":[-0.804014,51.644611],"type":"Point"}
}