{
  "type": "Feature",
  "properties": {
    "addr:full":"Hill Farm, Irthlingborough Road, Little Addington Kettering Northamptonshire NN14 4AS",
    "addr:postcode":"nn14 4as",
    "addr:street":"Hill;Irthlingborough Road",
    "iso:country":"GB",
    "sg:address":"Hill Farm, Irthlingborough Road, Little Addington",
    "sg:city":"Kettering",
    "sg:classifiers":[
        {
            "category":"Freight",
            "type":"Transportation"
        }
    ],
    "sg:phone":"+44 1933 653731",
    "sg:postcode":"NN14 4AS",
    "sg:province":"Northamptonshire",
    "sg:tags":[
        "haulage",
        "road"
    ],
    "wof:name":"A R Williams Haulage",
    "wof:placetype":"venue"
},
  "geometry": {"coordinates":[-0.5897089839,52.3546485901],"type":"Point"}
}