{
  "type": "Feature",
  "properties": {
    "addr:full":"Global Care House, Dugdale Road Coventry Warwickshire CV6 1PB",
    "addr:postcode":"cv6 1pb",
    "addr:street":"Dugdale Road",
    "iso:country":"GB",
    "sg:address":"Global Care House, Dugdale Road",
    "sg:city":"Coventry",
    "sg:classifiers":[
        {
            "category":"Organizations",
            "subcategory":"Non-profit Organization",
            "type":"Services"
        }
    ],
    "sg:phone":"+44 24 7660 1800",
    "sg:postcode":"CV6 1PB",
    "sg:province":"Warwickshire",
    "sg:tags":[
        "charitable",
        "organisation",
        "voluntary",
        "charity"
    ],
    "wof:name":"Global Care",
    "wof:placetype":"venue"
},
  "geometry": {"coordinates":[-1.5231850147,52.4220085144],"type":"Point"}
}