{
  "type": "Feature",
  "properties": {
    "iso:country":"GB",
    "sg:address":"Ganders House, Ganders Park, Main Rd, Kingsley",
    "sg:city":"Bordon",
    "sg:classifiers":[
        {
            "category":"Professional",
            "subcategory":"Computer Services",
            "type":"Services"
        }
    ],
    "sg:phone":"+44 1420 477764",
    "sg:postcode":"GU35 9LU",
    "sg:province":"Hampshire",
    "sg:tags":[
        "system",
        "software"
    ],
    "wof:name":"Four Front Ltd",
    "wof:placetype":"venue"
},
  "geometry": {"coordinates":[-0.865114,51.108856],"type":"Point"}
}