{
  "type": "Feature",
  "properties": {
    "addr:full":"Unit 17 Cavendish Mews, Off Grosvenor Road Aldershot Hampshire GU11 3EH",
    "addr:housenumber":"unit 17",
    "addr:postcode":"gu11 3eh",
    "addr:street":"Cavendish Mews Off Grosvenor Road",
    "iso:country":"GB",
    "sg:address":"Unit 17 Cavendish Mews, Off Grosvenor Road",
    "sg:city":"Aldershot",
    "sg:classifiers":[
        {
            "category":"Autos & Motor Vehicles",
            "subcategory":"Motorcycle Sales",
            "type":"Retail Goods"
        }
    ],
    "sg:phone":"+44 1252 316412",
    "sg:postcode":"GU11 3EH",
    "sg:province":"Hampshire",
    "sg:tags":[
        "outboard"
    ],
    "wof:name":"Streamlined Propeller Repairs",
    "wof:placetype":"venue"
},
  "geometry": {"coordinates":[-0.7659389973,51.2451133728],"type":"Point"}
}