{
  "type": "Feature",
  "properties": {
    "addr:full":"11 Cressida Chase Bracknell Berkshire RG42 3UD",
    "addr:housenumber":"11",
    "addr:postcode":"rg42 3ud",
    "addr:street":"Cressida Chase",
    "iso:country":"GB",
    "sg:address":"11 Cressida Chase",
    "sg:city":"Bracknell",
    "sg:classifiers":[
        {
            "category":"Home & Garden",
            "subcategory":"Carpets & Floor Coverings",
            "type":"Retail Goods"
        }
    ],
    "sg:phone":"+44 1344 861573",
    "sg:postcode":"RG42 3UD",
    "sg:province":"Berkshire",
    "sg:tags":[
        "carpets",
        "rug",
        "matting"
    ],
    "wof:name":"Bracknell Carpet Co",
    "wof:placetype":"venue"
},
  "geometry": {"coordinates":[-0.728742,51.422436],"type":"Point"}
}