{
  "type": "Feature",
  "properties": {
    "iso:country":"GB",
    "sg:address":"The Martello Tower, Leyland Rd",
    "sg:city":"Pevensey",
    "sg:classifiers":[
        {
            "category":"Shopping",
            "subcategory":"Pharmacy",
            "type":"Retail Goods"
        }
    ],
    "sg:phone":"+44 1323 763322",
    "sg:postcode":"BN24 6HT",
    "sg:province":"East Sussex",
    "sg:tags":[
        "medicine",
        "therapy"
    ],
    "wof:name":"Clair Lucas",
    "wof:placetype":"venue"
},
  "geometry": {"coordinates":[0.335995,50.800983],"type":"Point"}
}