{
  "type": "Feature",
  "properties": {
    "iso:country":"GB",
    "sg:address":"72 Church Street",
    "sg:city":"Tewkesbury",
    "sg:classifiers":[
        {
            "category":"Professional",
            "subcategory":"Art Services",
            "type":"Services"
        }
    ],
    "sg:phone":"+44 1684 298719",
    "sg:postcode":"GL20 5RX",
    "sg:province":"Gloucestershire",
    "sg:tags":[
        "framing"
    ],
    "wof:name":"Grosvenor Products",
    "wof:placetype":"venue"
},
  "geometry": {"coordinates":[-2.160238,51.991417],"type":"Point"}
}