{
  "type": "Feature",
  "properties": {
    "iso:country":"GB",
    "sg:address":", Corton Denham",
    "sg:city":"Sherborne",
    "sg:classifiers":[
        {
            "category":"Bars & Pubs",
            "type":"Food & Drink"
        },
        {
            "category":"Community Center",
            "subcategory":"Social",
            "type":"Public Place"
        }
    ],
    "sg:phone":"+44 1963 220317",
    "sg:postcode":"DT9 4LR",
    "sg:province":"Dorset",
    "sg:tags":[
        "pubs",
        "house",
        "inn",
        "activity"
    ],
    "wof:name":"The Queens Arms Inn",
    "wof:placetype":"venue"
},
  "geometry": {"coordinates":[-2.514139,50.971699],"type":"Point"}
}