{
  "type": "Feature",
  "properties": {
    "iso:country":"GB",
    "sg:address":"Beech Croft, New Road, Catfield",
    "sg:city":"Great Yarmouth",
    "sg:classifiers":[
        {
            "category":"Farming",
            "subcategory":"Farm",
            "type":"Manufacturing & Wholesale Goods"
        }
    ],
    "sg:phone":"+44 1692 580391",
    "sg:postcode":"NR29 5BW",
    "sg:province":"Norfolk",
    "sg:tags":[
        "mixed",
        "crop"
    ],
    "wof:name":"Nigel J B Gardiner",
    "wof:placetype":"venue"
},
  "geometry": {"coordinates":[1.53985,52.741154],"type":"Point"}
}