{
  "type": "Feature",
  "properties": {
    "iso:country":"GB",
    "sg:address":"67 Brasenose Road",
    "sg:city":"Bootle",
    "sg:classifiers":[
        {
            "category":"Manufacturing",
            "subcategory":"Motor Vehicles & Parts",
            "type":"Manufacturing & Wholesale Goods"
        }
    ],
    "sg:phone":"+44 151 933 6290",
    "sg:postcode":"L20 8HE",
    "sg:province":"Merseyside",
    "sg:tags":[
        "bearing"
    ],
    "wof:name":"Bsl",
    "wof:placetype":"venue"
},
  "geometry": {"coordinates":[-2.995105,53.442226],"type":"Point"}
}