{
  "type": "Feature",
  "properties": {
    "addr:full":"Coronation Way Kidderminster Staffordshire DY10 3AU",
    "addr:postcode":"dy10 3au",
    "addr:street":"Coronation Way",
    "iso:country":"GB",
    "sg:address":"Coronation Way",
    "sg:city":"Kidderminster",
    "sg:classifiers":[
        {
            "category":"Bars & Pubs",
            "type":"Food & Drink"
        },
        {
            "category":"Community Center",
            "subcategory":"Social",
            "type":"Public Place"
        }
    ],
    "sg:phone":"+44 1562 824720",
    "sg:postcode":"DY10 3AU",
    "sg:province":"Staffordshire",
    "sg:tags":[
        "pubs",
        "house",
        "inn",
        "activity"
    ],
    "wof:name":"COMBERTON ARMS",
    "wof:placetype":"venue"
},
  "geometry": {"coordinates":[-2.226109,52.384491],"type":"Point"}
}