{
  "type": "Feature",
  "properties": {
    "addr:full":"Unit 20, Bells Industrial Estate Newcastle-upon-tyne Northumberland NE15 6UX",
    "addr:housenumber":"unit 20",
    "addr:postcode":"ne15 6ux",
    "addr:street":"Bells Industrial Estate",
    "iso:country":"GB",
    "sg:address":"Unit 20, Bells Industrial Estate",
    "sg:city":"Newcastle-upon-tyne",
    "sg:classifiers":[
        {
            "category":"Government",
            "subcategory":"Department Of Motor Vehicles",
            "type":"Public Place"
        }
    ],
    "sg:phone":"+44 191 264 5655",
    "sg:postcode":"NE15 6UX",
    "sg:province":"Northumberland",
    "sg:tags":[
        "machine",
        "industrial",
        "sewing"
    ],
    "wof:name":"Protector Cover Ltd.",
    "wof:placetype":"venue"
},
  "geometry": {"coordinates":[-1.7002190351,54.973690033],"type":"Point"}
}