{
  "type": "Feature",
  "properties": {
    "iso:country":"GB",
    "sg:address":"13 Burnside Avenue",
    "sg:city":"Port Glasgow",
    "sg:classifiers":[
        {
            "category":"Food & Beverages",
            "subcategory":"Meat & Fish",
            "type":"Retail Goods"
        }
    ],
    "sg:phone":"+44 1475 704458",
    "sg:postcode":"PA14 6PN",
    "sg:province":"Inverclyde",
    "sg:tags":[
        "chip"
    ],
    "wof:name":"Andrew Nolan",
    "wof:placetype":"venue"
},
  "geometry": {"coordinates":[-4.6136789322,55.9300003052],"type":"Point"}
}