{
  "type": "Feature",
  "properties": {
    "iso:country":"GB",
    "sg:address":"Leeway Industrial Estate",
    "sg:city":"Newport",
    "sg:classifiers":[
        {
            "category":"Autos & Motor Vehicles",
            "subcategory":"Automobile Sales",
            "type":"Retail Goods"
        }
    ],
    "sg:phone":"+44 1633 290929",
    "sg:postcode":"NP19 4SL",
    "sg:province":"Newport",
    "sg:tags":[
        "commercial"
    ],
    "wof:name":"Volvo Truck & Bus (South)",
    "wof:placetype":"venue"
},
  "geometry": {"coordinates":[-2.948897,51.574764],"type":"Point"}
}