{
  "type": "Feature",
  "properties": {
    "iso:country":"GB",
    "sg:address":"38 High Street",
    "sg:city":"Southall",
    "sg:classifiers":[
        {
            "category":"Shopping",
            "subcategory":"Comic Books",
            "type":"Retail Goods"
        }
    ],
    "sg:postcode":"UB1 3DA",
    "sg:province":"Greater London",
    "sg:tags":[
        "jeweller"
    ],
    "wof:name":"Kanda Jewellers",
    "wof:placetype":"venue"
},
  "geometry": {"coordinates":[-0.374829,51.511086],"type":"Point"}
}