{
  "type": "Feature",
  "properties": {
    "iso:country":"GB",
    "sg:address":"Kings Way, Thurnscoe",
    "sg:city":"Rotherham",
    "sg:classifiers":[
        {
            "category":"Organizations",
            "subcategory":"Membership Organization",
            "type":"Services"
        }
    ],
    "sg:phone":"+44 1709 892136",
    "sg:postcode":"S63 0TQ",
    "sg:province":"South Yorkshire",
    "sg:tags":[
        "club",
        "social"
    ],
    "wof:name":"Thurnscoe Ex Service Mens Club",
    "wof:placetype":"venue"
},
  "geometry": {"coordinates":[-1.3148440123,53.5463752747],"type":"Point"}
}