{
  "type": "Feature",
  "properties": {
    "addr:full":"40 High Street Bagshot Berkshire GU19 5AZ",
    "addr:housenumber":"40",
    "addr:postcode":"gu19 5az",
    "addr:street":"High Street",
    "iso:country":"GB",
    "sg:address":"40 High Street",
    "sg:city":"Bagshot",
    "sg:classifiers":[
        {
            "category":"Retail",
            "subcategory":"Laundry & Dry Cleaning",
            "type":"Services"
        }
    ],
    "sg:phone":"+44 1276 453993",
    "sg:postcode":"GU19 5AZ",
    "sg:province":"Berkshire",
    "sg:tags":[
        "alteration"
    ],
    "wof:name":"Tudor Dry Cleaners",
    "wof:placetype":"venue"
},
  "geometry": {"coordinates":[-0.6928970218,51.3612327576],"type":"Point"}
}