{
  "type": "Feature",
  "properties": {
    "addr:full":"67 Leagrave Road Luton Bedfordshire LU4 8HT",
    "addr:housenumber":"67",
    "addr:postcode":"lu4 8ht",
    "addr:street":"Leagrave Road",
    "iso:country":"GB",
    "sg:address":"67 Leagrave Road",
    "sg:city":"Luton",
    "sg:classifiers":[
        {
            "category":"Fast Food",
            "type":"Food & Drink"
        }
    ],
    "sg:phone":"+44 1582 453429",
    "sg:postcode":"LU4 8HT",
    "sg:province":"Bedfordshire",
    "sg:tags":[
        "away",
        "take"
    ],
    "wof:name":"Scrumptious Euro-Carribean Takeaways",
    "wof:placetype":"venue"
},
  "geometry": {"coordinates":[-0.431999,51.888062],"type":"Point"}
}