{
  "type": "Feature",
  "properties": {
    "addr:full":"3 David Street Carlisle Cumbria CA1 2LR",
    "addr:housenumber":"3",
    "addr:postcode":"ca1 2lr",
    "addr:street":"David Street",
    "iso:country":"GB",
    "sg:address":"3 David Street",
    "sg:city":"Carlisle",
    "sg:classifiers":[
        {
            "category":"Retail",
            "subcategory":"Auto Repair",
            "type":"Services"
        }
    ],
    "sg:phone":"+44 1228 531794",
    "sg:postcode":"CA1 2LR",
    "sg:province":"Cumbria",
    "sg:tags":[
        "modification",
        "garage",
        "related"
    ],
    "wof:name":"David Street Garage",
    "wof:placetype":"venue"
},
  "geometry": {"coordinates":[-2.921954,54.887066],"type":"Point"}
}