{
  "type": "Feature",
  "properties": {
    "addr:full":"22 Church Street Callington Cornwall PL17 7AR",
    "addr:housenumber":"22",
    "addr:postcode":"pl17 7ar",
    "addr:street":"Church Street",
    "iso:country":"GB",
    "sg:address":"22 Church Street",
    "sg:city":"Callington",
    "sg:classifiers":[
        {
            "category":"Professional",
            "subcategory":"Business Services",
            "type":"Services"
        }
    ],
    "sg:phone":"+44 1579 384066",
    "sg:postcode":"PL17 7AR",
    "sg:province":"Cornwall",
    "sg:tags":[
        "bookmaker"
    ],
    "wof:name":"Callington Bookmakers",
    "wof:placetype":"venue"
},
  "geometry": {"coordinates":[-4.3158359528,50.5034065247],"type":"Point"}
}