{
  "type": "Feature",
  "properties": {
    "addr:full":"Park Ho, Parkhill Rd Bexley Kent DA5 1HT",
    "addr:postcode":"da5 1ht",
    "addr:street":"Park;Parkhill Rd",
    "iso:country":"GB",
    "sg:address":"Park Ho, Parkhill Rd",
    "sg:city":"Bexley",
    "sg:classifiers":[
        {
            "category":"Professional",
            "subcategory":"Lawyer & Legal Services",
            "type":"Services"
        }
    ],
    "sg:phone":"+44 1322 553424",
    "sg:postcode":"DA5 1HT",
    "sg:province":"Kent",
    "sg:tags":[
        "solicitor"
    ],
    "wof:name":"Lea Brewer & Co",
    "wof:placetype":"venue"
},
  "geometry": {"coordinates":[0.1390630007,51.4434928894],"type":"Point"}
}