{
  "type": "Feature",
  "properties": {
    "addr:full":"14a Woodsure Mead, Wootton Bassett Swindon Wiltshire SN4 8RB",
    "addr:housenumber":"14a",
    "addr:postcode":"sn4 8rb",
    "addr:street":"Woodsure Mead",
    "iso:country":"GB",
    "sg:address":"14a Woodsure Mead, Wootton Bassett",
    "sg:city":"Swindon",
    "sg:classifiers":[
        {
            "category":"Building & Trades",
            "subcategory":"Construction",
            "type":"Services"
        }
    ],
    "sg:phone":"+44 1793 854228",
    "sg:postcode":"SN4 8RB",
    "sg:province":"Wiltshire",
    "sg:tags":[
        "joiner",
        "carpenter"
    ],
    "wof:name":"C E Dunn",
    "wof:placetype":"venue"
},
  "geometry": {"coordinates":[-1.88509,51.542339],"type":"Point"}
}