{
  "type": "Feature",
  "properties": {
    "iso:country":"GB",
    "sg:address":"68 East Avenue",
    "sg:city":"Hayes",
    "sg:classifiers":[
        {
            "category":"Banks & Credit Unions",
            "subcategory":"Financial Services",
            "type":"Services"
        }
    ],
    "sg:phone":"+44 1895 460944",
    "sg:postcode":"UB3 2HP",
    "sg:province":"Greater London",
    "sg:tags":[
        "claim",
        "assessor"
    ],
    "wof:name":"Phillips & Bond",
    "wof:placetype":"venue"
},
  "geometry": {"coordinates":[-0.416176,51.509293],"type":"Point"}
}