{
  "type": "Feature",
  "properties": {
    "addr:full":"Hopkins Lane Newton Abbot Devon TQ12 2EL",
    "addr:postcode":"tq12 2el",
    "addr:street":"Hopkins Lane",
    "iso:country":"GB",
    "sg:address":"Hopkins Lane",
    "sg:city":"Newton Abbot",
    "sg:classifiers":[
        {
            "category":"Shopping",
            "subcategory":"Stationery & Office Supplies",
            "type":"Retail Goods"
        }
    ],
    "sg:phone":"+44 1626 364766",
    "sg:postcode":"TQ12 2EL",
    "sg:province":"Devon",
    "sg:tags":[
        "recording",
        "machine",
        "time"
    ],
    "wof:name":"D J Offord",
    "wof:placetype":"venue"
},
  "geometry": {"coordinates":[-3.6088221073,50.5303421021],"type":"Point"}
}