{
  "type": "Feature",
  "properties": {
    "iso:country":"GB",
    "sg:address":"Bath Road, Thatcham",
    "sg:city":"Newbury",
    "sg:classifiers":[
        {
            "category":"Home & Garden",
            "subcategory":"Garden Supply",
            "type":"Retail Goods"
        }
    ],
    "sg:phone":"+44 1635 873700",
    "sg:postcode":"RG18 3AN",
    "sg:province":"Berkshire",
    "sg:tags":[
        "nursery",
        "centre"
    ],
    "wof:name":"The Country Gardener Ltd.",
    "wof:placetype":"venue"
},
  "geometry": {"coordinates":[-1.263599,51.403831],"type":"Point"}
}