{
  "type": "Feature",
  "properties": {
    "iso:country":"GB",
    "sg:address":"Solar House",
    "sg:city":"Stevenage",
    "sg:classifiers":[
        {
            "category":"Professional",
            "type":"Services"
        }
    ],
    "sg:postcode":"SG1 2UA",
    "sg:province":"Hertfordshire",
    "sg:tags":[
        "caterer"
    ],
    "wof:name":"Gardner Merchant Ltd.",
    "wof:placetype":"venue"
},
  "geometry": {"coordinates":[-0.1886799932,51.9056091309],"type":"Point"}
}