{
  "type": "Feature",
  "properties": {
    "addr:full":"Sterling House, 35 High Street Ascot Berkshire SL5 7HG",
    "addr:housenumber":"35",
    "addr:postcode":"sl5 7hg",
    "addr:street":"High Street",
    "iso:country":"GB",
    "sg:address":"Sterling House, 35 High Street",
    "sg:city":"Ascot",
    "sg:classifiers":[
        {
            "category":"Professional",
            "subcategory":"Management & Consulting",
            "type":"Services"
        },
        {
            "category":"Real Estate",
            "subcategory":"Real Estate Agent",
            "type":"Services"
        }
    ],
    "sg:phone":"+44 1344 872889",
    "sg:postcode":"SL5 7HG",
    "sg:province":"Berkshire",
    "sg:tags":[
        "project"
    ],
    "wof:name":"Meedhurst Properties Ltd",
    "wof:placetype":"venue"
},
  "geometry": {"coordinates":[-0.673971,51.410824],"type":"Point"}
}