{
  "type": "Feature",
  "properties": {
    "addr:full":"22 Chestnut Drive Malvern Herefordshire WR14 4AS",
    "addr:housenumber":"22",
    "addr:postcode":"wr14 4as",
    "addr:street":"Chestnut Drive;Herefordshire",
    "iso:country":"GB",
    "sg:address":"22 Chestnut Drive",
    "sg:city":"Malvern",
    "sg:classifiers":[
        {
            "category":"Shopping",
            "subcategory":"Photographic Equipment",
            "type":"Retail Goods"
        }
    ],
    "sg:phone":"+44 1684 564073",
    "sg:postcode":"WR14 4AS",
    "sg:province":"Herefordshire",
    "wof:name":"Alan Hayman Photography",
    "wof:placetype":"venue"
},
  "geometry": {"coordinates":[-2.3264729977,52.0935058594],"type":"Point"}
}