{
  "type": "Feature",
  "properties": {
    "addr:full":"19 Coronation Street Macclesfield Cheshire SK11 7PQ",
    "addr:housenumber":"19",
    "addr:postcode":"sk11 7pq",
    "addr:street":"Coronation Street",
    "iso:country":"GB",
    "sg:address":"19 Coronation Street",
    "sg:city":"Macclesfield",
    "sg:classifiers":[
        {
            "category":"Retail",
            "subcategory":"Storage",
            "type":"Services"
        }
    ],
    "sg:phone":"+44 1625 422225",
    "sg:postcode":"SK11 7PQ",
    "sg:province":"Cheshire",
    "sg:tags":[
        "household",
        "removal"
    ],
    "wof:name":"Mick's Mini Transport",
    "wof:placetype":"venue"
},
  "geometry": {"coordinates":[-2.121451,53.250965],"type":"Point"}
}