{
  "type": "Feature",
  "properties": {
    "addr:full":"Queens Square, Bowness-on-windermersquare Windermere Cumbria LA23 3BY",
    "addr:postcode":"la23 3by",
    "addr:street":"Queens;Bowness-On-Windermersquare",
    "iso:country":"GB",
    "sg:address":"Queens Square, Bowness-on-windermersquare",
    "sg:city":"Windermere",
    "sg:classifiers":[
        {
            "category":"Fast Food",
            "type":"Food & Drink"
        }
    ],
    "sg:phone":"+44 15394 43535",
    "sg:postcode":"LA23 3BY",
    "sg:province":"Cumbria",
    "sg:tags":[
        "away",
        "take"
    ],
    "wof:name":"Stefans Cafe Bisto",
    "wof:placetype":"venue"
},
  "geometry": {"coordinates":[-2.922436,54.362869],"type":"Point"}
}