{
  "type": "Feature",
  "properties": {
    "addr:full":"42 Nunnery Fields Canterbury Kent CT1 3JT",
    "addr:housenumber":"42",
    "addr:postcode":"ct1 3jt",
    "addr:street":"Nunnery Fields",
    "iso:country":"GB",
    "sg:address":"42 Nunnery Fields",
    "sg:city":"Canterbury",
    "sg:classifiers":[
        {
            "category":"Travel",
            "subcategory":"Hotels & Motels",
            "type":"Entertainment"
        }
    ],
    "sg:phone":"+44 1227 464905",
    "sg:postcode":"CT1 3JT",
    "sg:province":"Kent",
    "sg:tags":[
        "house",
        "guest"
    ],
    "wof:name":"Guildford Lodge Guest House",
    "wof:placetype":"venue"
},
  "geometry": {"coordinates":[1.082221,51.271351],"type":"Point"}
}