{
  "type": "Feature",
  "properties": {
    "iso:country":"GB",
    "sg:address":"Unit 6 Knightsridge Indust Est, Knightsridge East",
    "sg:city":"Livingston",
    "sg:classifiers":[
        {
            "category":"Professional",
            "type":"Services"
        }
    ],
    "sg:phone":"+44 1506 436333",
    "sg:postcode":"EH54 8RA",
    "sg:province":"West Lothian",
    "sg:tags":[
        "repair",
        "tech",
        "maintenance"
    ],
    "wof:name":"Four Front Services",
    "wof:placetype":"venue"
},
  "geometry": {"coordinates":[-3.5310239792,55.9052238464],"type":"Point"}
}