{
  "type": "Feature",
  "properties": {
    "addr:full":"6 Long Eaton Drive Bristol City of Bristol BS14 9AP",
    "addr:housenumber":"6",
    "addr:postcode":"bs14 9ap",
    "addr:street":"Long Eaton Drive",
    "iso:country":"GB",
    "sg:address":"6 Long Eaton Drive",
    "sg:city":"Bristol",
    "sg:classifiers":[
        {
            "category":"Social Services",
            "subcategory":"Job Training",
            "type":"Services"
        }
    ],
    "sg:phone":"+44 1275 835365",
    "sg:postcode":"BS14 9AP",
    "sg:province":"City of Bristol",
    "sg:tags":[
        "draughtsman",
        "drawing"
    ],
    "wof:name":"Home Extensions",
    "wof:placetype":"venue"
},
  "geometry": {"coordinates":[-2.5636470318,51.423034668],"type":"Point"}
}