{
  "type": "Feature",
  "properties": {
    "iso:country":"GB",
    "sg:address":"Freeth Terrace, North Clifton",
    "sg:city":"Newark",
    "sg:classifiers":[
        {
            "category":"Government",
            "subcategory":"Post Office",
            "type":"Public Place"
        }
    ],
    "sg:phone":"+44 1777 228223",
    "sg:postcode":"NG23 7AX",
    "sg:province":"Lincolnshire",
    "wof:name":"North Clifton Post Office",
    "wof:placetype":"venue"
},
  "geometry": {"coordinates":[-0.765945,53.240177],"type":"Point"}
}