{
  "type": "Feature",
  "properties": {
    "addr:full":"56 Jesmond Road West Newcastle-upon-tyne Tyne and Wear NE2 4PQ",
    "addr:housenumber":"56",
    "addr:postcode":"ne2 4pq",
    "addr:street":"Jesmond Road West",
    "iso:country":"GB",
    "sg:address":"56 Jesmond Road West",
    "sg:city":"Newcastle-upon-tyne",
    "sg:classifiers":[
        {
            "category":"Professional",
            "subcategory":"Management & Consulting",
            "type":"Services"
        },
        {
            "category":"Organizations",
            "subcategory":"Community Association",
            "type":"Services"
        }
    ],
    "sg:phone":"+44 191 281 8833",
    "sg:postcode":"NE2 4PQ",
    "sg:province":"Tyne and Wear",
    "sg:tags":[
        "consultant",
        "relation",
        "public"
    ],
    "wof:name":"Bradley O'Mahoney Public Relations",
    "wof:placetype":"venue"
},
  "geometry": {"coordinates":[-1.609134,54.981102],"type":"Point"}
}