{
  "type": "Feature",
  "properties": {
    "addr:full":"Great Holland Hall, Church Lane, Great Holland Frinton-on-sea Essex CO13 0JS",
    "addr:postcode":"co13 0js",
    "addr:street":"Church Lane",
    "iso:country":"GB",
    "sg:address":"Great Holland Hall, Church Lane, Great Holland",
    "sg:city":"Frinton-on-sea",
    "sg:classifiers":[
        {
            "category":"Farming",
            "subcategory":"Livestock Farm",
            "type":"Manufacturing & Wholesale Goods"
        }
    ],
    "sg:phone":"+44 1255 678210",
    "sg:postcode":"CO13 0JS",
    "sg:province":"Essex",
    "sg:tags":[
        "others"
    ],
    "wof:name":"Frinton Farm Partners",
    "wof:placetype":"venue"
},
  "geometry": {"coordinates":[1.21214,51.828468],"type":"Point"}
}