{
  "type": "Feature",
  "properties": {
    "addr:full":"11 Yew Tree Walk Purley Surrey CR8 1HD",
    "addr:housenumber":"11",
    "addr:postcode":"cr8 1hd",
    "addr:street":"Yew Tree Walk",
    "iso:country":"GB",
    "sg:address":"11 Yew Tree Walk",
    "sg:city":"Purley",
    "sg:classifiers":[
        {
            "category":"Building & Trades",
            "subcategory":"Plumbing",
            "type":"Services"
        },
        {
            "category":"Arts & Performance",
            "subcategory":"Music",
            "type":"Entertainment"
        }
    ],
    "sg:phone":"+44 20 8660 6952",
    "sg:postcode":"CR8 1HD",
    "sg:province":"Surrey",
    "sg:tags":[
        "mobile",
        "heating",
        "disco"
    ],
    "wof:name":"K M Plumbing Services",
    "wof:placetype":"venue"
},
  "geometry": {"coordinates":[-0.104069002,51.3423271179],"type":"Point"}
}