{
  "type": "Feature",
  "properties": {
    "addr:full":"Unit 70-83 In Shops, High St Chatham Kent ME4 4BP",
    "addr:housenumber":"unit 70-83",
    "addr:postcode":"me4 4bp",
    "addr:street":"High St",
    "iso:country":"GB",
    "sg:address":"Unit 70-83 In Shops, High St",
    "sg:city":"Chatham",
    "sg:classifiers":[
        {
            "category":"Shopping",
            "subcategory":"Department Store",
            "type":"Retail Goods"
        }
    ],
    "sg:postcode":"ME4 4BP",
    "sg:province":"Kent",
    "wof:name":"Patel,Pravin K,",
    "wof:placetype":"venue"
},
  "geometry": {"coordinates":[0.5224400163,51.3818893433],"type":"Point"}
}