{
  "type": "Feature",
  "properties": {
    "addr:full":"44 Greenways Norwich Norfolk NR4 6PE",
    "addr:housenumber":"44",
    "addr:postcode":"nr4 6pe",
    "addr:street":"Greenways Norwich Norfolk",
    "iso:country":"GB",
    "sg:address":"44 Greenways",
    "sg:city":"Norwich",
    "sg:classifiers":[
        {
            "category":"Building & Trades",
            "subcategory":"Construction",
            "type":"Services"
        }
    ],
    "sg:phone":"+44 1603 452493",
    "sg:postcode":"NR4 6PE",
    "sg:province":"Norfolk",
    "sg:tags":[
        "roofing"
    ],
    "wof:name":"Walker Roofing (Norwich) Ltd.",
    "wof:placetype":"venue"
},
  "geometry": {"coordinates":[1.2579679489,52.6083488464],"type":"Point"}
}