{
  "type": "Feature",
  "properties": {
    "iso:country":"GB",
    "sg:address":"53 Vennal Street",
    "sg:city":"Dalry",
    "sg:classifiers":[
        {
            "category":"Farming",
            "subcategory":"Nursery",
            "type":"Manufacturing & Wholesale Goods"
        },
        {
            "category":"Education",
            "subcategory":"Preschool",
            "type":"Public Place"
        }
    ],
    "sg:phone":"+44 1294 832200",
    "sg:postcode":"KA24 4AG",
    "sg:province":"North Ayrshire",
    "sg:tags":[
        "school",
        "creche"
    ],
    "wof:name":"Dalry Nursery School",
    "wof:placetype":"venue"
},
  "geometry": {"coordinates":[-4.724252224,55.7061805725],"type":"Point"}
}