{
  "type": "Feature",
  "properties": {
    "addr:full":"33 Parsons Grn Lane London Greater London SW6 4HH",
    "addr:housenumber":"33",
    "addr:postcode":"sw6 4hh",
    "addr:street":"Parsons Grn Lane",
    "iso:country":"GB",
    "sg:address":"33 Parsons Grn Lane",
    "sg:city":"London",
    "sg:classifiers":[
        {
            "category":"Retail",
            "subcategory":"Auto Repair",
            "type":"Services"
        }
    ],
    "sg:phone":"+44 20 7471 4852",
    "sg:postcode":"SW6 4HH",
    "sg:province":"Greater London",
    "sg:tags":[
        "bathroom",
        "fixture"
    ],
    "wof:name":"Jacob Delafon",
    "wof:placetype":"venue"
},
  "geometry": {"coordinates":[-0.200643003,51.4761886597],"type":"Point"}
}