{
  "type": "Feature",
  "properties": {
    "iso:country":"GB",
    "sg:address":"219 Dean St Telford Centre, Town Centre",
    "sg:city":"Telford",
    "sg:classifiers":[
        {
            "category":"Shopping",
            "subcategory":"Books",
            "type":"Retail Goods"
        }
    ],
    "sg:phone":"+44 1952 299454",
    "sg:postcode":"TF3 4BT",
    "sg:province":"Shropshire",
    "sg:tags":[
        "bookseller"
    ],
    "wof:name":"Peters Bookshop",
    "wof:placetype":"venue"
},
  "geometry": {"coordinates":[-2.444159,52.673939],"type":"Point"}
}