{
  "type": "Feature",
  "properties": {
    "iso:country":"GB",
    "sg:address":"70-72 Upper Orwell Street",
    "sg:city":"Ipswich",
    "sg:classifiers":[
        {
            "category":"Shopping",
            "subcategory":"Department Store",
            "type":"Retail Goods"
        },
        {
            "category":"Food & Beverages",
            "subcategory":"Supermarket",
            "type":"Retail Goods"
        }
    ],
    "sg:postcode":"IP4 1HR",
    "sg:province":"Suffolk",
    "wof:name":"Oriental Supplies",
    "wof:placetype":"venue"
},
  "geometry": {"coordinates":[1.15931,52.055653],"type":"Point"}
}