{
  "type": "Feature",
  "properties": {
    "iso:country":"GB",
    "sg:address":"Laddus Farm, Laddus Drove, Friday Bridge",
    "sg:city":"Wisbech",
    "sg:classifiers":[
        {
            "category":"Farming",
            "subcategory":"Livestock Farm",
            "type":"Manufacturing & Wholesale Goods"
        }
    ],
    "sg:phone":"+44 1945 860247",
    "sg:postcode":"PE14 0LJ",
    "sg:province":"Cambridgeshire",
    "sg:tags":[
        "others"
    ],
    "wof:name":"A G Scott & Son",
    "wof:placetype":"venue"
},
  "geometry": {"coordinates":[0.1640899926,52.6210594177],"type":"Point"}
}