{
  "type": "Feature",
  "properties": {
    "iso:country":"GB",
    "sg:address":"Auction Mart,",
    "sg:city":"Leyburn",
    "sg:classifiers":[
        {
            "category":"Professional",
            "type":"Services"
        }
    ],
    "sg:phone":"+44 1765 689216",
    "sg:postcode":"HG4 4DB",
    "sg:province":"North Yorkshire",
    "sg:tags":[
        "auctioneer"
    ],
    "wof:name":"Masham Farmer's Live Stock Mart Company",
    "wof:placetype":"venue"
},
  "geometry": {"coordinates":[-1.6643489599,54.2239685059],"type":"Point"}
}