{
  "type": "Feature",
  "properties": {
    "addr:full":"3 Richmond Street Herne Bay Kent CT6 5LR",
    "addr:housenumber":"3",
    "addr:postcode":"ct6 5lr",
    "addr:street":"Richmond Street",
    "iso:country":"GB",
    "sg:address":"3 Richmond Street",
    "sg:city":"Herne Bay",
    "sg:classifiers":[
        {
            "category":"Bars & Pubs",
            "type":"Food & Drink"
        }
    ],
    "sg:phone":"+44 1227 361583",
    "sg:postcode":"CT6 5LR",
    "sg:province":"Kent",
    "sg:tags":[
        "pubs",
        "inn"
    ],
    "wof:name":"The Richmond Inn",
    "wof:placetype":"venue"
},
  "geometry": {"coordinates":[1.124054,51.37207],"type":"Point"}
}