{
  "type": "Feature",
  "properties": {
    "addr:full":"333 Morville Street London Greater London E3 2DD",
    "addr:housenumber":"333",
    "addr:postcode":"e3 2dd",
    "addr:street":"Morville Street",
    "iso:country":"GB",
    "sg:address":"333 Morville Street",
    "sg:city":"London",
    "sg:classifiers":[
        {
            "category":"Health Services",
            "subcategory":"Nursing And Care Facility",
            "type":"Services"
        }
    ],
    "sg:phone":"+44 20 8983 0366",
    "sg:postcode":"E3 2DD",
    "sg:province":"Greater London",
    "sg:tags":[
        "home"
    ],
    "wof:name":"Tower Hamlets Housing Action Trust",
    "wof:placetype":"venue"
},
  "geometry": {"coordinates":[-0.0253839996,51.5320739746],"type":"Point"}
}