{
  "type": "Feature",
  "properties": {
    "addr:full":"6 Richmond House, George Street, Thornaby Stockton On Tees Durham TS17 6DE",
    "addr:housenumber":"6;house",
    "addr:postcode":"ts17 6de",
    "addr:street":"George Street;On",
    "iso:country":"GB",
    "sg:address":"6 Richmond House, George Street, Thornaby",
    "sg:city":"Stockton On Tees",
    "sg:classifiers":[
        {
            "category":"Shopping",
            "subcategory":"Department Store",
            "type":"Retail Goods"
        }
    ],
    "sg:phone":"+44 1642 606914",
    "sg:postcode":"TS17 6DE",
    "sg:province":"Durham",
    "wof:name":"Tupperware",
    "wof:placetype":"venue"
},
  "geometry": {"coordinates":[-1.3043899536,54.5562400818],"type":"Point"}
}