{
  "type": "Feature",
  "properties": {
    "addr:full":"9 Victoria Gardens Castle Cary Somerset BA7 7DJ",
    "addr:housenumber":"9",
    "addr:postcode":"ba7 7dj",
    "addr:street":"Victoria Gardens",
    "iso:country":"GB",
    "sg:address":"9 Victoria Gardens",
    "sg:city":"Castle Cary",
    "sg:classifiers":[
        {
            "category":"Shopping",
            "subcategory":"Musical Instruments",
            "type":"Retail Goods"
        }
    ],
    "sg:phone":"+44 1963 351134",
    "sg:postcode":"BA7 7DJ",
    "sg:province":"Somerset",
    "wof:name":"Gary Mills Woodwind & Brass Instrument Repairs",
    "wof:placetype":"venue"
},
  "geometry": {"coordinates":[-2.5180490017,51.0915145874],"type":"Point"}
}