{
  "type": "Feature",
  "properties": {
    "addr:full":"Walsyde, Latton Swindon Gloucestershire SN6 6DP",
    "addr:housenumber":"latton",
    "addr:postcode":"sn6 6dp",
    "iso:country":"GB",
    "sg:address":"Walsyde, Latton",
    "sg:city":"Swindon",
    "sg:classifiers":[
        {
            "category":"Real Estate",
            "subcategory":"Real Estate Operator",
            "type":"Services"
        }
    ],
    "sg:phone":"+44 1793 750505",
    "sg:postcode":"SN6 6DP",
    "sg:province":"Gloucestershire",
    "sg:tags":[
        "letting",
        "agent"
    ],
    "wof:name":"All Seasons Property Management",
    "wof:placetype":"venue"
},
  "geometry": {"coordinates":[-1.871114,51.659306],"type":"Point"}
}