{
  "type": "Feature",
  "properties": {
    "iso:country":"GB",
    "sg:address":"18 High Street",
    "sg:city":"Nottingham",
    "sg:classifiers":[
        {
            "category":"Retail",
            "subcategory":"Funeral Services",
            "type":"Services"
        },
        {
            "category":"Building & Trades",
            "subcategory":"Construction",
            "type":"Services"
        }
    ],
    "sg:postcode":"NG13 0AA",
    "sg:province":"Leicestershire",
    "sg:tags":[
        "builder"
    ],
    "wof:name":"J Norris & Son",
    "wof:placetype":"venue"
},
  "geometry": {"coordinates":[-0.805015,52.941635],"type":"Point"}
}