{
  "type": "Feature",
  "properties": {
    "addr:full":"The Louisa Centre, Front St Stanley Durham DH9 0TE",
    "addr:postcode":"dh9 0te",
    "addr:street":"Front St",
    "iso:country":"GB",
    "sg:address":"The Louisa Centre, Front St",
    "sg:city":"Stanley",
    "sg:classifiers":[
        {
            "category":"Organizations",
            "subcategory":"Non-profit Organization",
            "type":"Services"
        }
    ],
    "sg:phone":"+44 1207 218854",
    "sg:postcode":"DH9 0TE",
    "sg:province":"Durham",
    "sg:tags":[
        "organisation",
        "voluntary",
        "charity"
    ],
    "wof:name":"Derwentside Volunteer Bureau",
    "wof:placetype":"venue"
},
  "geometry": {"coordinates":[-1.690338,54.872379],"type":"Point"}
}