{
  "type": "Feature",
  "properties": {
    "iso:country":"GB",
    "sg:address":"39-41 Acklam Road",
    "sg:city":"London",
    "sg:classifiers":[
        {
            "category":"Farming",
            "subcategory":"Nursery",
            "type":"Manufacturing & Wholesale Goods"
        }
    ],
    "sg:phone":"+44 20 8968 5833",
    "sg:postcode":"W10 5YU",
    "sg:province":"Greater London",
    "sg:tags":[
        "creche"
    ],
    "wof:name":"Swinbrook Nursery Centre",
    "wof:placetype":"venue"
},
  "geometry": {"coordinates":[-0.206295,51.519722],"type":"Point"}
}