{
  "type": "Feature",
  "properties": {
    "addr:full":"3 Westminster House, Thorley St, Failsworth Manchester Lancashire M35 9PA",
    "addr:housenumber":"3",
    "addr:postcode":"m35 9pa",
    "addr:street":"Westminster House Thorley St",
    "iso:country":"GB",
    "sg:address":"3 Westminster House, Thorley St, Failsworth",
    "sg:city":"Manchester",
    "sg:classifiers":[
        {
            "category":"Utilities",
            "subcategory":"Natural Gas",
            "type":"Services"
        }
    ],
    "sg:phone":"+44 161 688 6444",
    "sg:postcode":"M35 9PA",
    "sg:province":"Lancashire",
    "sg:tags":[
        "control",
        "energy",
        "management",
        "system"
    ],
    "wof:name":"Complete Heating Services",
    "wof:placetype":"venue"
},
  "geometry": {"coordinates":[-2.1547000408,53.5108184814],"type":"Point"}
}