{
  "type": "Feature",
  "properties": {
    "iso:country":"GB",
    "sg:address":"430 Buxton Rd",
    "sg:city":"Stockport",
    "sg:classifiers":[
        {
            "category":"Health Services",
            "subcategory":"Doctor",
            "type":"Services"
        }
    ],
    "sg:phone":"+44 161 456 5205",
    "sg:postcode":"SK2 7JQ",
    "sg:province":"Cheshire",
    "sg:tags":[
        "practitioners"
    ],
    "wof:name":"Sanville, P",
    "wof:placetype":"venue"
},
  "geometry": {"coordinates":[-2.131289959,53.3863067627],"type":"Point"}
}