{
  "type": "Feature",
  "properties": {
    "iso:country":"GB",
    "sg:address":"Grey House, Burford Road, Filkins",
    "sg:city":"Lechlade",
    "sg:classifiers":[
        {
            "category":"Professional",
            "subcategory":"Business Services",
            "type":"Services"
        }
    ],
    "sg:phone":"+44 1367 860900",
    "sg:postcode":"GL7 3JW",
    "sg:province":"Gloucestershire",
    "sg:tags":[
        "information"
    ],
    "wof:name":"Apogeion",
    "wof:placetype":"venue"
},
  "geometry": {"coordinates":[-1.691909,51.694077],"type":"Point"}
}