{
  "type": "Feature",
  "properties": {
    "iso:country":"GB",
    "sg:address":"4a Station Street",
    "sg:city":"Lewes",
    "sg:classifiers":[
        {
            "category":"Shopping",
            "subcategory":"Department Store",
            "type":"Retail Goods"
        },
        {
            "category":"Shopping",
            "subcategory":"Music",
            "type":"Retail Goods"
        }
    ],
    "sg:phone":"+44 1273 483983",
    "sg:postcode":"BN7 2DA",
    "sg:province":"East Sussex",
    "sg:tags":[
        "record",
        "tape",
        "cd"
    ],
    "wof:name":"Rik's Compact Discs",
    "wof:placetype":"venue"
},
  "geometry": {"coordinates":[0.0109019997,50.8728065491],"type":"Point"}
}