{
  "type": "Feature",
  "properties": {
    "addr:full":"6 The Malthouse, Brewery Walk Worcester Worcestershire WR1 3HY",
    "addr:housenumber":"6",
    "addr:postcode":"wr1 3hy",
    "addr:street":"The;Brewery Walk",
    "iso:country":"GB",
    "sg:address":"6 The Malthouse, Brewery Walk",
    "sg:city":"Worcester",
    "sg:classifiers":[
        {
            "category":"Freight",
            "type":"Transportation"
        }
    ],
    "sg:postcode":"WR1 3HY",
    "sg:province":"Worcestershire",
    "sg:tags":[
        "haulage",
        "road"
    ],
    "wof:name":"Higgins,Paul A,",
    "wof:placetype":"venue"
},
  "geometry": {"coordinates":[-2.2278800011,52.1970176697],"type":"Point"}
}