{
  "type": "Feature",
  "properties": {
    "addr:full":"Unit 2 Howard Plant Industrial Estate Bournemouth Dorset BH11 9DU",
    "addr:housenumber":"unit 2",
    "addr:postcode":"bh11 9du",
    "addr:street":"Howard;Estate",
    "iso:country":"GB",
    "sg:address":"Unit 2 Howard Plant Industrial Estate",
    "sg:city":"Bournemouth",
    "sg:classifiers":[
        {
            "category":"Parking",
            "type":"Transportation"
        }
    ],
    "sg:postcode":"BH11 9DU",
    "sg:province":"Dorset",
    "sg:tags":[
        "car",
        "valet"
    ],
    "wof:name":"Cars International",
    "wof:placetype":"venue"
},
  "geometry": {"coordinates":[-1.92432,50.758389],"type":"Point"}
}