{
  "type": "Feature",
  "properties": {
    "iso:country":"GB",
    "sg:address":"The Workshop",
    "sg:city":"Kirkwall",
    "sg:classifiers":[
        {
            "category":"Retail",
            "subcategory":"Auto Rental",
            "type":"Services"
        }
    ],
    "sg:phone":"+44 1856 872063",
    "sg:postcode":"KW15 1GS",
    "sg:province":"Orkney Islands",
    "sg:tags":[
        "car",
        "hire",
        "truck"
    ],
    "wof:name":"Rainbow Private Car Hire",
    "wof:placetype":"venue"
},
  "geometry": {"coordinates":[-2.9604189396,58.9817314148],"type":"Point"}
}