{
  "type": "Feature",
  "properties": {
    "addr:full":"48 The Boulevard, Tunstall Stoke-on-trent Staffordshire ST6 6BD",
    "addr:housenumber":"48",
    "addr:postcode":"staffordshire st6 6bd",
    "addr:street":"The Boulevard",
    "iso:country":"GB",
    "sg:address":"48 The Boulevard, Tunstall",
    "sg:city":"Stoke-on-trent",
    "sg:classifiers":[
        {
            "category":"Home & Garden",
            "subcategory":"Household Appliances",
            "type":"Retail Goods"
        }
    ],
    "sg:phone":"+44 1782 811016",
    "sg:postcode":"ST6 6BD",
    "sg:province":"Staffordshire",
    "sg:tags":[
        "electrical"
    ],
    "wof:name":"Nationwide Electronic Service Network Ltd.",
    "wof:placetype":"venue"
},
  "geometry": {"coordinates":[-2.2066309452,53.05884552],"type":"Point"}
}