{
  "type": "Feature",
  "properties": {
    "iso:country":"GB",
    "sg:address":"28 Corporation Rd",
    "sg:city":"Carlisle",
    "sg:classifiers":[
        {
            "category":"Government",
            "subcategory":"Customs House",
            "type":"Public Place"
        }
    ],
    "sg:phone":"+44 1228 818808",
    "sg:postcode":"CA3 8XB",
    "sg:province":"Cumbria",
    "sg:tags":[
        "clearance"
    ],
    "wof:name":"The House Clearance Centre",
    "wof:placetype":"venue"
},
  "geometry": {"coordinates":[-2.936806,54.897743],"type":"Point"}
}