{
  "type": "Feature",
  "properties": {
    "addr:full":"Weasenham Ct, Weasenham La Wisbech Cambridgeshire PE13 2RD",
    "addr:postcode":"pe13 2rd",
    "addr:street":"Weasenham Ct;La Wisbech",
    "iso:country":"GB",
    "sg:address":"Weasenham Ct, Weasenham La",
    "sg:city":"Wisbech",
    "sg:classifiers":[
        {
            "category":"Retail",
            "subcategory":"Auto Rental",
            "type":"Services"
        }
    ],
    "sg:postcode":"PE13 2RD",
    "sg:province":"Cambridgeshire",
    "sg:tags":[
        "truck",
        "hire",
        "van",
        "car"
    ],
    "wof:name":"Noel-Storr,H,",
    "wof:placetype":"venue"
},
  "geometry": {"coordinates":[0.1682450026,52.6545562744],"type":"Point"}
}