{
  "type": "Feature",
  "properties": {
    "addr:full":"Unit 2 Park Court, Park Road Wellingborough Northamptonshire NN8 4PW",
    "addr:housenumber":"unit 2",
    "addr:postcode":"nn8 4pw",
    "addr:street":"Park Court Park Road",
    "iso:country":"GB",
    "sg:address":"Unit 2 Park Court, Park Road",
    "sg:city":"Wellingborough",
    "sg:classifiers":[
        {
            "category":"Building & Trades",
            "subcategory":"Construction",
            "type":"Services"
        }
    ],
    "sg:phone":"+44 1933 275010",
    "sg:postcode":"NN8 4PW",
    "sg:province":"Northamptonshire",
    "sg:tags":[
        "decorator",
        "painter"
    ],
    "wof:name":"Redwater Ltd.",
    "wof:placetype":"venue"
},
  "geometry": {"coordinates":[-0.6929240227,52.3043708801],"type":"Point"}
}