{
  "type": "Feature",
  "properties": {
    "addr:full":"185a Torridon Rd, Catford Catford Greater London SE6 1RG",
    "addr:housenumber":"185a",
    "addr:postcode":"se6 1rg",
    "addr:street":"Torridon Rd",
    "iso:country":"GB",
    "sg:address":"185a Torridon Rd, Catford",
    "sg:city":"Catford",
    "sg:classifiers":[
        {
            "category":"Health Services",
            "subcategory":"Clinic",
            "type":"Services"
        }
    ],
    "sg:phone":"+44 20 8480 9905",
    "sg:postcode":"SE6 1RG",
    "sg:province":"Greater London",
    "sg:tags":[
        "private"
    ],
    "wof:name":"Torridon Complementary Therapy Clinic",
    "wof:placetype":"venue"
},
  "geometry": {"coordinates":[-0.001739,51.4400367737],"type":"Point"}
}