{
  "type": "Feature",
  "properties": {
    "addr:full":"1 Thames Lock, Dock Road Brentford Greater London TW8 8AG",
    "addr:housenumber":"1;lock",
    "addr:postcode":"tw8 8ag",
    "addr:street":"Thames;Dock Road",
    "iso:country":"GB",
    "sg:address":"1 Thames Lock, Dock Road",
    "sg:city":"Brentford",
    "sg:classifiers":[
        {
            "category":"Marine",
            "type":"Transportation"
        }
    ],
    "sg:phone":"+44 20 8568 2779",
    "sg:postcode":"TW8 8AG",
    "sg:province":"Greater London",
    "sg:tags":[
        "inland",
        "waterway",
        "river"
    ],
    "wof:name":"British Waterways",
    "wof:placetype":"venue"
},
  "geometry": {"coordinates":[-0.3067240119,51.4841346741],"type":"Point"}
}