{
  "type": "Feature",
  "properties": {
    "addr:full":"15 South St Romford Essex RM1 1NJ",
    "addr:housenumber":"15",
    "addr:postcode":"rm1 1nj",
    "addr:street":"South St",
    "iso:country":"GB",
    "sg:address":"15 South St",
    "sg:city":"Romford",
    "sg:classifiers":[
        {
            "category":"Shopping",
            "subcategory":"Clothing, Apparel, & Fashions",
            "type":"Retail Goods"
        }
    ],
    "sg:phone":"+44 1708 766237",
    "sg:postcode":"RM1 1NJ",
    "sg:province":"Essex",
    "sg:tags":[
        "menswear"
    ],
    "wof:name":"Burton Menswear",
    "wof:placetype":"venue"
},
  "geometry": {"coordinates":[0.180779,51.578239],"type":"Point"}
}