{
  "type": "Feature",
  "properties": {
    "iso:country":"GB",
    "sg:address":"Harbour Street",
    "sg:city":"Tarbert",
    "sg:classifiers":[
        {
            "category":"Bars & Pubs",
            "type":"Food & Drink"
        },
        {
            "category":"Community Center",
            "subcategory":"Social",
            "type":"Public Place"
        }
    ],
    "sg:phone":"+44 1880 820263",
    "sg:postcode":"PA29 6UB",
    "sg:province":"Argyll and Bute",
    "sg:tags":[
        "pubs",
        "house",
        "inn",
        "activity"
    ],
    "wof:name":"The Corner House",
    "wof:placetype":"venue"
},
  "geometry": {"coordinates":[-5.414919,55.863392],"type":"Point"}
}