{
  "type": "Feature",
  "properties": {
    "iso:country":"GB",
    "sg:address":"20 Marian Square",
    "sg:city":"Bootle",
    "sg:classifiers":[
        {
            "category":"Personal",
            "subcategory":"Beauty Salon",
            "type":"Services"
        },
        {
            "category":"Personal",
            "subcategory":"Barber",
            "type":"Services"
        }
    ],
    "sg:phone":"+44 151 530 1939",
    "sg:postcode":"L30 5QA",
    "sg:province":"Merseyside",
    "sg:tags":[
        "unisex",
        "hairdresser"
    ],
    "wof:name":"Lynn Michaels",
    "wof:placetype":"venue"
},
  "geometry": {"coordinates":[-2.971981,53.487915],"type":"Point"}
}