{
  "type": "Feature",
  "properties": {
    "addr:full":"Elwartlaw Farm, Greenlaw Duns Scottish Borders TD10 6UH",
    "addr:postcode":"td10 6uh",
    "addr:street":"Greenlaw",
    "iso:country":"GB",
    "sg:address":"Elwartlaw Farm, Greenlaw",
    "sg:city":"Duns",
    "sg:classifiers":[
        {
            "category":"Farming",
            "subcategory":"Farm",
            "type":"Manufacturing & Wholesale Goods"
        }
    ],
    "sg:phone":"+44 1361 810212",
    "sg:postcode":"TD10 6UH",
    "sg:province":"Scottish Borders",
    "sg:tags":[
        "mixed",
        "crop"
    ],
    "wof:name":"WILLIAM WHITE & SONS",
    "wof:placetype":"venue"
},
  "geometry": {"coordinates":[-2.462528944,55.7065162659],"type":"Point"}
}