{
  "type": "Feature",
  "properties": {
    "addr:full":"4 Bank Buildings Cranleigh Surrey GU6 8BB",
    "addr:housenumber":"4",
    "addr:postcode":"gu6 8bb",
    "addr:street":"Bank Buildings",
    "iso:country":"GB",
    "sg:address":"4 Bank Buildings",
    "sg:city":"Cranleigh",
    "sg:classifiers":[
        {
            "category":"Fast Food",
            "type":"Food & Drink"
        }
    ],
    "sg:phone":"+44 1483 275233",
    "sg:postcode":"GU6 8BB",
    "sg:province":"Surrey",
    "sg:tags":[
        "away",
        "meal",
        "outlet",
        "take"
    ],
    "wof:name":"New Lotus House",
    "wof:placetype":"venue"
},
  "geometry": {"coordinates":[-0.482998997,51.1415405273],"type":"Point"}
}