{
  "type": "Feature",
  "properties": {
    "iso:country":"GB",
    "sg:address":"Unit 10a, Penshaw Way",
    "sg:city":"Houghton-le-spring",
    "sg:classifiers":[
        {
            "category":"Building & Trades",
            "subcategory":"Construction",
            "type":"Services"
        }
    ],
    "sg:phone":"+44 191 385 8045",
    "sg:postcode":"DH4 6JW",
    "sg:province":"Durham",
    "sg:tags":[
        "decorator",
        "painter"
    ],
    "wof:name":"Dunholme Decorators Ltd.",
    "wof:placetype":"venue"
},
  "geometry": {"coordinates":[-1.487226963,54.8792572021],"type":"Point"}
}