{
  "type": "Feature",
  "properties": {
    "addr:full":"Harvest House, 127 Whitton Street Northwich Cheshire CW9 6PL",
    "addr:housenumber":"127",
    "addr:postcode":"cw9 6pl",
    "addr:street":"Whitton Street",
    "iso:country":"GB",
    "sg:address":"Harvest House, 127 Whitton Street",
    "sg:city":"Northwich",
    "sg:classifiers":[
        {
            "category":"Shopping",
            "subcategory":"Pets & Pet Supplies",
            "type":"Retail Goods"
        }
    ],
    "sg:phone":"+44 1606 40040",
    "sg:postcode":"CW9 6PL",
    "sg:province":"Cheshire",
    "sg:tags":[
        "food"
    ],
    "wof:name":"Davies Feeds",
    "wof:placetype":"venue"
},
  "geometry": {"coordinates":[-2.503409,53.294182],"type":"Point"}
}