{
  "type": "Feature",
  "properties": {
    "iso:country":"GB",
    "sg:address":"14 Blenheim Rd",
    "sg:city":"Deal",
    "sg:classifiers":[
        {
            "category":"Place Of Worship",
            "type":"Public Place"
        },
        {
            "category":"Organizations",
            "subcategory":"Religious Organization",
            "type":"Services"
        }
    ],
    "sg:phone":"+44 1304 374399",
    "sg:postcode":"CT14 7DB",
    "sg:province":"Kent",
    "sg:tags":[
        "organisation"
    ],
    "wof:name":"St Thomas Of Canterbury R C Church",
    "wof:placetype":"venue"
},
  "geometry": {"coordinates":[1.4001369476,51.2214660645],"type":"Point"}
}