{
  "type": "Feature",
  "properties": {
    "iso:country":"GB",
    "sg:address":"Jubilee Rd",
    "sg:city":"Nottingham",
    "sg:classifiers":[
        {
            "category":"Government",
            "subcategory":"Fire Station",
            "type":"Public Place"
        }
    ],
    "sg:phone":"+44 115 967 0155",
    "sg:postcode":"NG5 6JR",
    "sg:province":"Nottinghamshire",
    "wof:name":"Arnold Fire Station",
    "wof:placetype":"venue"
},
  "geometry": {"coordinates":[-1.136199,52.996578],"type":"Point"}
}