{
  "type": "Feature",
  "properties": {
    "iso:country":"GB",
    "sg:address":"327 Lillie Road, Fulham",
    "sg:city":"London",
    "sg:classifiers":[
        {
            "category":"Professional",
            "subcategory":"Art Services",
            "type":"Services"
        }
    ],
    "sg:phone":"+44 20 7381 6433",
    "sg:postcode":"SW6 7NR",
    "sg:province":"Greater London",
    "sg:tags":[
        "consultant",
        "design"
    ],
    "wof:name":"Seymour-Powell Ltd.",
    "wof:placetype":"venue"
},
  "geometry": {"coordinates":[-0.2138549984,51.4825515747],"type":"Point"}
}