{
  "type": "Feature",
  "properties": {
    "addr:full":"244 Holdenhurst Road Bournemouth Dorset BH8 8AZ",
    "addr:housenumber":"244",
    "addr:postcode":"bh8 8az",
    "addr:street":"Holdenhurst Road",
    "iso:country":"GB",
    "sg:address":"244 Holdenhurst Road",
    "sg:city":"Bournemouth",
    "sg:classifiers":[
        {
            "category":"Professional",
            "subcategory":"Employment Agencies",
            "type":"Services"
        }
    ],
    "sg:phone":"+44 1202 557734",
    "sg:postcode":"BH8 8AZ",
    "sg:province":"Dorset",
    "sg:tags":[
        "career",
        "guidance"
    ],
    "wof:name":"Army Careers Information Office",
    "wof:placetype":"venue"
},
  "geometry": {"coordinates":[-1.8575700521,50.7292404175],"type":"Point"}
}