{
  "type": "Feature",
  "properties": {
    "iso:country":"GB",
    "sg:address":"116 High Street, Barwell",
    "sg:city":"Leicester",
    "sg:classifiers":[
        {
            "category":"Professional",
            "subcategory":"Engineering",
            "type":"Services"
        }
    ],
    "sg:postcode":"LE9 8DR",
    "sg:province":"Leicestershire",
    "sg:tags":[
        "precision",
        "engineer"
    ],
    "wof:name":"R D Carnall & Co.",
    "wof:placetype":"venue"
},
  "geometry": {"coordinates":[-1.3485519886,52.5653343201],"type":"Point"}
}