{
  "type": "Feature",
  "properties": {
    "addr:full":"Essex Antique Centre, Priory St Colchester Essex CO1 2PY",
    "addr:postcode":"co1 2py",
    "addr:street":"Priory St",
    "iso:country":"GB",
    "sg:address":"Essex Antique Centre, Priory St",
    "sg:city":"Colchester",
    "sg:classifiers":[
        {
            "category":"Home & Garden",
            "subcategory":"Furniture",
            "type":"Retail Goods"
        }
    ],
    "sg:postcode":"CO1 2PY",
    "sg:province":"Essex",
    "wof:name":"Crick,A,",
    "wof:placetype":"venue"
},
  "geometry": {"coordinates":[0.9053900242,51.8877487183],"type":"Point"}
}