{
  "type": "Feature",
  "properties": {
    "iso:country":"GB",
    "sg:address":"78 Promenade",
    "sg:city":"Cheltenham",
    "sg:classifiers":[
        {
            "category":"Shopping",
            "subcategory":"Comic Books",
            "type":"Retail Goods"
        }
    ],
    "sg:phone":"+44 1242 528526",
    "sg:postcode":"GL50 1NB",
    "sg:province":"Gloucestershire",
    "sg:tags":[
        "jeweller"
    ],
    "wof:name":"Goldsmiths",
    "wof:placetype":"venue"
},
  "geometry": {"coordinates":[-2.0770640373,51.8990020752],"type":"Point"}
}