{
  "type": "Feature",
  "properties": {
    "iso:country":"GB",
    "sg:address":"Rear Of 8 Grove Rd",
    "sg:city":"Bridgend",
    "sg:classifiers":[
        {
            "category":"Manufacturing",
            "subcategory":"Glass & Minerals",
            "type":"Manufacturing & Wholesale Goods"
        }
    ],
    "sg:phone":"+44 1656 652339",
    "sg:postcode":"CF31 3EF",
    "sg:province":"Bridgend",
    "sg:tags":[
        "mnfrs",
        "fibre"
    ],
    "wof:name":"Fibretech",
    "wof:placetype":"venue"
},
  "geometry": {"coordinates":[-3.5399138927,51.5031890869],"type":"Point"}
}