{
  "type": "Feature",
  "properties": {
    "addr:full":"Melbourne Lodge, Walcote Lutterworth Leicestershire LE17 4JT",
    "addr:postcode":"le17 4jt",
    "addr:street":"Walcote",
    "iso:country":"GB",
    "sg:address":"Melbourne Lodge, Walcote",
    "sg:city":"Lutterworth",
    "sg:classifiers":[
        {
            "category":"Farming",
            "subcategory":"Livestock Farm",
            "type":"Manufacturing & Wholesale Goods"
        }
    ],
    "sg:postcode":"LE17 4JT",
    "sg:province":"Leicestershire",
    "sg:tags":[
        "others"
    ],
    "wof:name":"P F Towers",
    "wof:placetype":"venue"
},
  "geometry": {"coordinates":[-1.199624,52.456299],"type":"Point"}
}