{
  "type": "Feature",
  "properties": {
    "iso:country":"GB",
    "sg:address":"18b Albert Street",
    "sg:city":"Aberdeen",
    "sg:classifiers":[
        {
            "category":"Professional",
            "subcategory":"Engineering",
            "type":"Services"
        }
    ],
    "sg:postcode":"AB25 1XQ",
    "sg:province":"Aberdeen City",
    "sg:tags":[
        "engineer"
    ],
    "wof:name":"Glendee Engineering Ltd.",
    "wof:placetype":"venue"
},
  "geometry": {"coordinates":[-2.117205,57.144928],"type":"Point"}
}