{
  "type": "Feature",
  "properties": {
    "addr:full":"18 Twyford Business Centre, London Road Bishops Stortford Essex CM23 3YT",
    "addr:housenumber":"18",
    "addr:postcode":"cm23 3yt",
    "addr:street":"Twyford Business Centre London Road",
    "iso:country":"GB",
    "sg:address":"18 Twyford Business Centre, London Road",
    "sg:city":"Bishops Stortford",
    "sg:classifiers":[
        {
            "category":"Shopping",
            "subcategory":"Party Supplies",
            "type":"Retail Goods"
        }
    ],
    "sg:phone":"+44 1279 653821",
    "sg:postcode":"CM23 3YT",
    "sg:province":"Essex",
    "sg:tags":[
        "novelty"
    ],
    "wof:name":"A W Jan Ltd.",
    "wof:placetype":"venue"
},
  "geometry": {"coordinates":[0.1645089984,51.8585166931],"type":"Point"}
}