{
  "type": "Feature",
  "properties": {
    "addr:full":"Pembridge Studios, 27a Pembridge Villas London Greater London W11 3EP",
    "addr:housenumber":"27a",
    "addr:postcode":"w11 3ep",
    "addr:street":"Pembridge Villas",
    "iso:country":"GB",
    "sg:address":"Pembridge Studios, 27a Pembridge Villas",
    "sg:city":"London",
    "sg:classifiers":[
        {
            "category":"Professional",
            "subcategory":"Employment Agencies",
            "type":"Services"
        }
    ],
    "sg:postcode":"W11 3EP",
    "sg:province":"Greater London",
    "sg:tags":[
        "modelling"
    ],
    "wof:name":"Bookings Men",
    "wof:placetype":"venue"
},
  "geometry": {"coordinates":[-0.1975499988,51.5124015808],"type":"Point"}
}