{
  "type": "Feature",
  "properties": {
    "iso:country":"GB",
    "sg:address":"30 Holland Park Drive",
    "sg:city":"Jarrow",
    "sg:classifiers":[
        {
            "category":"Professional",
            "subcategory":"Detective & Security Services",
            "type":"Services"
        },
        {
            "category":"Building & Trades",
            "subcategory":"Locksmith",
            "type":"Services"
        }
    ],
    "sg:phone":"+44 191 536 2266",
    "sg:postcode":"NE32 4LL",
    "sg:province":"Tyne and Wear",
    "wof:name":"Bridge Master Locksmiths",
    "wof:placetype":"venue"
},
  "geometry": {"coordinates":[-1.473452,54.958122],"type":"Point"}
}