{
  "type": "Feature",
  "properties": {
    "addr:full":"21 Warburton Road London Greater London E8 3RT",
    "addr:housenumber":"21",
    "addr:postcode":"e8 3rt",
    "addr:street":"Warburton Road",
    "iso:country":"GB",
    "sg:address":"21 Warburton Road",
    "sg:city":"London",
    "sg:classifiers":[
        {
            "category":"Professional",
            "subcategory":"Printing & Photocopies",
            "type":"Services"
        }
    ],
    "sg:postcode":"E8 3RT",
    "sg:province":"Greater London",
    "sg:tags":[
        "computer",
        "tag",
        "label"
    ],
    "wof:name":"Rowheath Ltd.",
    "wof:placetype":"venue"
},
  "geometry": {"coordinates":[-0.058264,51.538761],"type":"Point"}
}