{
  "type": "Feature",
  "properties": {
    "addr:full":"Enterprise Way, Flitwick Bedford Bedfordshire MK45 5BS",
    "addr:postcode":"mk45 5bs",
    "addr:street":"Enterprise Way",
    "iso:country":"GB",
    "sg:address":"Enterprise Way, Flitwick",
    "sg:city":"Bedford",
    "sg:classifiers":[
        {
            "category":"Shopping",
            "subcategory":"Computers & Home Electronics",
            "type":"Retail Goods"
        }
    ],
    "sg:phone":"+44 1525 713771",
    "sg:postcode":"MK45 5BS",
    "sg:province":"Bedfordshire",
    "wof:name":"Yeoman Upholstery Plc",
    "wof:placetype":"venue"
},
  "geometry": {"coordinates":[-0.4862549901,52.00806427],"type":"Point"}
}