{
  "type": "Feature",
  "properties": {
    "addr:full":"44 Downs Road Coulsdon Surrey CR5 1AA",
    "addr:housenumber":"44",
    "addr:postcode":"cr5 1aa",
    "addr:street":"Downs Road",
    "iso:country":"GB",
    "sg:address":"44 Downs Road",
    "sg:city":"Coulsdon",
    "sg:classifiers":[
        {
            "category":"Professional",
            "subcategory":"Business Services",
            "type":"Services"
        }
    ],
    "sg:phone":"+44 20 8681 8339",
    "sg:postcode":"CR5 1AA",
    "sg:province":"Surrey",
    "sg:tags":[
        "import",
        "export",
        "agent"
    ],
    "wof:name":"Rowtel Communications",
    "wof:placetype":"venue"
},
  "geometry": {"coordinates":[-0.136994,51.312992],"type":"Point"}
}