{
  "type": "Feature",
  "properties": {
    "iso:country":"GB",
    "sg:address":"16 Bridge Street",
    "sg:city":"Hungerford",
    "sg:classifiers":[
        {
            "category":"Personal",
            "subcategory":"Beauty Salon",
            "type":"Services"
        }
    ],
    "sg:phone":"+44 1488 681944",
    "sg:postcode":"RG17 0EG",
    "sg:province":"Berkshire",
    "sg:tags":[
        "unisex",
        "hairdresser"
    ],
    "wof:name":"Ad-Hoc Hair Design",
    "wof:placetype":"venue"
},
  "geometry": {"coordinates":[-1.5139199495,51.4169616699],"type":"Point"}
}