{
  "type": "Feature",
  "properties": {
    "iso:country":"GB",
    "sg:address":"Ashwicke Hall, Marshfield",
    "sg:city":"Chippenham",
    "sg:classifiers":[
        {
            "category":"Education",
            "subcategory":"School",
            "type":"Public Place"
        }
    ],
    "sg:phone":"+44 1225 891841",
    "sg:postcode":"SN14 8AG",
    "sg:province":"Gloucestershire",
    "sg:tags":[
        "independent",
        "preparatory"
    ],
    "wof:name":"Ashwicke Hall School Ltd",
    "wof:placetype":"venue"
},
  "geometry": {"coordinates":[-2.3099548817,51.4440994263],"type":"Point"}
}