{
  "type": "Feature",
  "properties": {
    "addr:full":"Belgrave Commercial Centre, 160 Belgrave Road Leicester Leicestershire LE4 5AU",
    "addr:housenumber":"160",
    "addr:postcode":"le4 5au",
    "addr:street":"Belgrave Road",
    "iso:country":"GB",
    "sg:address":"Belgrave Commercial Centre, 160 Belgrave Road",
    "sg:city":"Leicester",
    "sg:classifiers":[
        {
            "category":"Manufacturing",
            "subcategory":"Apparel",
            "type":"Manufacturing & Wholesale Goods"
        }
    ],
    "sg:postcode":"LE4 5AU",
    "sg:province":"Leicestershire",
    "sg:tags":[
        "garment",
        "designer"
    ],
    "wof:name":"Indikal",
    "wof:placetype":"venue"
},
  "geometry": {"coordinates":[-1.1223640442,52.6550636292],"type":"Point"}
}