{
  "type": "Feature",
  "properties": {
    "iso:country":"GB",
    "sg:address":"24 Church Lane, Eaton Bray",
    "sg:city":"Dunstable",
    "sg:classifiers":[
        {
            "category":"Manufacturing",
            "subcategory":"Wood Products",
            "type":"Manufacturing & Wholesale Goods"
        }
    ],
    "sg:phone":"+44 1525 220477",
    "sg:postcode":"LU6 2DJ",
    "sg:province":"Bedfordshire",
    "sg:tags":[
        "sawmill",
        "shaving"
    ],
    "wof:name":"M Grundy",
    "wof:placetype":"venue"
},
  "geometry": {"coordinates":[-0.590843,51.875256],"type":"Point"}
}