{
  "type": "Feature",
  "properties": {
    "iso:country":"GB",
    "sg:address":"7 High St, Downe",
    "sg:city":"Orpington",
    "sg:classifiers":[
        {
            "category":"Bakery",
            "type":"Food & Drink"
        }
    ],
    "sg:phone":"+44 1689 862077",
    "sg:postcode":"BR6 7US",
    "sg:province":"Kent",
    "sg:tags":[
        "cake",
        "maker"
    ],
    "wof:name":"The Tea Cosy",
    "wof:placetype":"venue"
},
  "geometry": {"coordinates":[0.053663,51.336918],"type":"Point"}
}