{
  "type": "Feature",
  "properties": {
    "addr:full":"Unit 18, Old Union Mill, 17-33 Grosvenor St West Birmingham West Midlands B16 8HW",
    "addr:housenumber":"unit 18;17-33",
    "addr:postcode":"b16 8hw",
    "addr:street":"Old Union;Grosvenor St West",
    "iso:country":"GB",
    "sg:address":"Unit 18, Old Union Mill, 17-33 Grosvenor St West",
    "sg:city":"Birmingham",
    "sg:classifiers":[
        {
            "category":"Communications",
            "subcategory":"Film & Video Production",
            "type":"Services"
        }
    ],
    "sg:postcode":"B16 8HW",
    "sg:province":"West Midlands",
    "sg:tags":[
        "illustrator",
        "artist"
    ],
    "wof:name":"Andrew C I Benfield",
    "wof:placetype":"venue"
},
  "geometry": {"coordinates":[-1.908604,52.478596],"type":"Point"}
}