{
  "type": "Feature",
  "properties": {
    "addr:full":"Church Rd Wylam Northumberland NE41 8AP",
    "addr:postcode":"ne41 8ap",
    "addr:street":"Church Rd",
    "iso:country":"GB",
    "sg:address":"Church Rd",
    "sg:city":"Wylam",
    "sg:classifiers":[
        {
            "category":"Community Center",
            "type":"Public Place"
        }
    ],
    "sg:phone":"+44 1661 852498",
    "sg:postcode":"NE41 8AP",
    "sg:province":"Northumberland",
    "sg:tags":[
        "centre"
    ],
    "wof:name":"Wylam Institute Community Association",
    "wof:placetype":"venue"
},
  "geometry": {"coordinates":[-1.8245060444,54.9779968262],"type":"Point"}
}