{
  "type": "Feature",
  "properties": {
    "addr:full":"41 Birch Road East Industrial Estate, Birch Road East Birmingham West Midlands B6 7DA",
    "addr:housenumber":"41",
    "addr:postcode":"b6 7da",
    "addr:street":"Birch Road East;Estate Birch Road East",
    "iso:country":"GB",
    "sg:address":"41 Birch Road East Industrial Estate, Birch Road East",
    "sg:city":"Birmingham",
    "sg:classifiers":[
        {
            "category":"Building & Trades",
            "subcategory":"Construction",
            "type":"Services"
        }
    ],
    "sg:phone":"+44 121 326 7181",
    "sg:postcode":"B6 7DA",
    "sg:province":"West Midlands",
    "sg:tags":[
        "roofing"
    ],
    "wof:name":"Imperial Residential Lettings Ltd.",
    "wof:placetype":"venue"
},
  "geometry": {"coordinates":[-1.877509,52.516449],"type":"Point"}
}