{
  "type": "Feature",
  "properties": {
    "addr:full":"Hadzor La Droitwich Worcestershire WR9 7DR",
    "addr:postcode":"wr9 7dr",
    "addr:street":"La Droitwich",
    "iso:country":"GB",
    "sg:address":"Hadzor La",
    "sg:city":"Droitwich",
    "sg:classifiers":[
        {
            "category":"Place Of Worship",
            "type":"Public Place"
        }
    ],
    "sg:phone":"+44 1527 63096",
    "sg:postcode":"WR9 7DR",
    "sg:province":"Worcestershire",
    "wof:name":"St Richard & St Hubert Church",
    "wof:placetype":"venue"
},
  "geometry": {"coordinates":[-2.128309,52.259289],"type":"Point"}
}