{
  "type": "Feature",
  "properties": {
    "addr:full":"Kent Avenue Dagenham Essex RM9 6SA",
    "addr:postcode":"rm9 6sa",
    "addr:street":"Kent Avenue",
    "iso:country":"GB",
    "sg:address":"Kent Avenue",
    "sg:city":"Dagenham",
    "sg:classifiers":[
        {
            "category":"Professional",
            "subcategory":"Business Services",
            "type":"Services"
        }
    ],
    "sg:phone":"+44 20 8984 9335",
    "sg:postcode":"RM9 6SA",
    "sg:province":"Essex",
    "sg:tags":[
        "shop",
        "cleaning"
    ],
    "wof:name":"Hamton Environmental Services Ltd.",
    "wof:placetype":"venue"
},
  "geometry": {"coordinates":[0.1505320072,51.517993927],"type":"Point"}
}