{
  "type": "Feature",
  "properties": {
    "addr:full":"Suite 13 Concord Ho, Speculation Pl Washington Tyne and Wear NE37 2AS",
    "addr:postcode":"ne37 2as",
    "addr:street":"Suite 13;Speculation Pl",
    "iso:country":"GB",
    "sg:address":"Suite 13 Concord Ho, Speculation Pl",
    "sg:city":"Washington",
    "sg:classifiers":[
        {
            "category":"Wholesale",
            "subcategory":"Music Publishers",
            "type":"Manufacturing & Wholesale Goods"
        }
    ],
    "sg:phone":"+44 191 419 0506",
    "sg:postcode":"NE37 2AS",
    "sg:province":"Tyne and Wear",
    "sg:tags":[
        "record"
    ],
    "wof:name":"Transmit Records",
    "wof:placetype":"venue"
},
  "geometry": {"coordinates":[-1.51994,54.91206],"type":"Point"}
}