{
  "type": "Feature",
  "properties": {
    "addr:full":"25a West Road Newcastle-upon-tyne Tyne and Wear NE4 9PU",
    "addr:housenumber":"25a",
    "addr:postcode":"ne4 9pu",
    "addr:street":"West Road",
    "iso:country":"GB",
    "sg:address":"25a West Road",
    "sg:city":"Newcastle-upon-tyne",
    "sg:classifiers":[
        {
            "category":"Food & Beverages",
            "subcategory":"Meat & Fish",
            "type":"Retail Goods"
        }
    ],
    "sg:phone":"+44 191 273 5140",
    "sg:postcode":"NE4 9PU",
    "sg:province":"Tyne and Wear",
    "sg:tags":[
        "butcher"
    ],
    "wof:name":"Family Butcher",
    "wof:placetype":"venue"
},
  "geometry": {"coordinates":[-1.655041,54.975777],"type":"Point"}
}