{
  "type": "Feature",
  "properties": {
    "iso:country":"GB",
    "sg:address":"43a North Moor Rd, Huntington",
    "sg:city":"York",
    "sg:classifiers":[
        {
            "category":"Shopping",
            "subcategory":"News",
            "type":"Retail Goods"
        }
    ],
    "sg:phone":"+44 1904 768406",
    "sg:postcode":"YO32 9QN",
    "sg:province":"North Yorkshire",
    "sg:tags":[
        "newsagent"
    ],
    "wof:name":"Porters News",
    "wof:placetype":"venue"
},
  "geometry": {"coordinates":[-1.057279,53.9972],"type":"Point"}
}