{
  "type": "Feature",
  "properties": {
    "iso:country":"GB",
    "sg:address":"13 Portland Road",
    "sg:city":"Walsall",
    "sg:classifiers":[
        {
            "category":"Professional",
            "subcategory":"Art Services",
            "type":"Services"
        }
    ],
    "sg:phone":"+44 1922 456067",
    "sg:postcode":"WS9 8NS",
    "sg:province":"Staffordshire",
    "sg:tags":[
        "photographer"
    ],
    "wof:name":"Jonathon Brooks Photography",
    "wof:placetype":"venue"
},
  "geometry": {"coordinates":[-1.9178960323,52.6027297974],"type":"Point"}
}