{
  "type": "Feature",
  "properties": {
    "addr:full":"110 Station Rd Hampton Greater London TW12 2AS",
    "addr:housenumber":"110",
    "addr:postcode":"tw12 2as",
    "addr:street":"Station Rd",
    "iso:country":"GB",
    "sg:address":"110 Station Rd",
    "sg:city":"Hampton",
    "sg:classifiers":[
        {
            "category":"Place Of Worship",
            "type":"Public Place"
        }
    ],
    "sg:phone":"+44 20 8979 3596",
    "sg:postcode":"TW12 2AS",
    "sg:province":"Greater London",
    "wof:name":"St Theodore Of Canterbury",
    "wof:placetype":"venue"
},
  "geometry": {"coordinates":[-0.368595,51.415642],"type":"Point"}
}