{
  "type": "Feature",
  "properties": {
    "iso:country":"GB",
    "sg:address":"154 Victoria Rise",
    "sg:city":"London",
    "sg:classifiers":[
        {
            "category":"Organizations",
            "subcategory":"Membership Organization",
            "type":"Services"
        }
    ],
    "sg:phone":"+44 20 7622 8448",
    "sg:postcode":"SW4 0NW",
    "sg:province":"Greater London",
    "sg:tags":[
        "club"
    ],
    "wof:name":"The Royal British Legion",
    "wof:placetype":"venue"
},
  "geometry": {"coordinates":[-0.1489100009,51.4662704468],"type":"Point"}
}