{
  "type": "Feature",
  "properties": {
    "addr:full":"Hailsham Rd Heathfield East Sussex TN21 8AE",
    "addr:postcode":"tn21 8ae",
    "addr:street":"Hailsham Rd",
    "iso:country":"GB",
    "sg:address":"Hailsham Rd",
    "sg:city":"Heathfield",
    "sg:classifiers":[
        {
            "category":"Food & Beverages",
            "subcategory":"Specialty",
            "type":"Retail Goods"
        }
    ],
    "sg:phone":"+44 1435 865959",
    "sg:postcode":"TN21 8AE",
    "sg:province":"East Sussex",
    "sg:tags":[
        "product",
        "health"
    ],
    "wof:name":"Bio Nutrition",
    "wof:placetype":"venue"
},
  "geometry": {"coordinates":[0.2561269999,50.966129303],"type":"Point"}
}