{
  "type": "Feature",
  "properties": {
    "iso:country":"GB",
    "sg:address":"10 Greycoat Pl",
    "sg:city":"Westminster",
    "sg:classifiers":[
        {
            "category":"Professional",
            "subcategory":"Employment Agencies",
            "type":"Services"
        }
    ],
    "sg:phone":"+44 20 7976 7272",
    "sg:postcode":"SW1P 1SB",
    "sg:province":"Greater London",
    "sg:tags":[
        "consultant"
    ],
    "wof:name":"Interpro Solutions Ltd",
    "wof:placetype":"venue"
},
  "geometry": {"coordinates":[-0.134721,51.496368],"type":"Point"}
}