{
  "type": "Feature",
  "properties": {
    "iso:country":"GB",
    "sg:address":"Stephenson Road, Churcfield Industrial Estate",
    "sg:city":"Salisbury",
    "sg:classifiers":[
        {
            "category":"Building & Trades",
            "subcategory":"Plumbing",
            "type":"Services"
        }
    ],
    "sg:phone":"+44 1722 413131",
    "sg:postcode":"SP2 7NP",
    "sg:province":"Wiltshire",
    "sg:tags":[
        "merchant",
        "plumbers'"
    ],
    "wof:name":"Plumb Center",
    "wof:placetype":"venue"
},
  "geometry": {"coordinates":[-1.8117649555,51.069229126],"type":"Point"}
}