{
  "type": "Feature",
  "properties": {
    "iso:country":"GB",
    "sg:address":"144 Wisley Way",
    "sg:city":"Birmingham",
    "sg:classifiers":[
        {
            "category":"Building & Trades",
            "subcategory":"Construction",
            "type":"Services"
        }
    ],
    "sg:postcode":"B32 2JX",
    "sg:province":"West Midlands",
    "sg:tags":[
        "glass",
        "replacement"
    ],
    "wof:name":"Alan Firkin",
    "wof:placetype":"venue"
},
  "geometry": {"coordinates":[-1.975746,52.456181],"type":"Point"}
}