{
  "type": "Feature",
  "properties": {
    "addr:full":"Sports And Community Centre, Park Road, Cosby Leicester Leicestershire LE9 1RN",
    "addr:postcode":"le9 1rn",
    "addr:street":"Park Road",
    "iso:country":"GB",
    "sg:address":"Sports And Community Centre, Park Road, Cosby",
    "sg:city":"Leicester",
    "sg:classifiers":[
        {
            "category":"Community Center",
            "type":"Public Place"
        }
    ],
    "sg:phone":"+44 116 284 9244",
    "sg:postcode":"LE9 1RN",
    "sg:province":"Leicestershire",
    "sg:tags":[
        "centre"
    ],
    "wof:name":"Cosby Village Hall",
    "wof:placetype":"venue"
},
  "geometry": {"coordinates":[-1.194663,52.551392],"type":"Point"}
}