{
  "type": "Feature",
  "properties": {
    "addr:full":"12 Goose Acre Chesham Buckinghamshire HP5 1YG",
    "addr:housenumber":"12",
    "addr:postcode":"hp5 1yg",
    "addr:street":"Goose Acre",
    "iso:country":"GB",
    "sg:address":"12 Goose Acre",
    "sg:city":"Chesham",
    "sg:classifiers":[
        {
            "category":"Building & Trades",
            "subcategory":"Construction",
            "type":"Services"
        }
    ],
    "sg:postcode":"HP5 1YG",
    "sg:province":"Buckinghamshire",
    "sg:tags":[
        "decorator",
        "painter"
    ],
    "wof:name":"Harry Tuszynski",
    "wof:placetype":"venue"
},
  "geometry": {"coordinates":[-0.582677,51.709187],"type":"Point"}
}