{
  "type": "Feature",
  "properties": {
    "iso:country":"GB",
    "sg:address":"Birchmeade, 14 Woodale Close",
    "sg:city":"Warrington",
    "sg:classifiers":[
        {
            "category":"Communications",
            "type":"Services"
        }
    ],
    "sg:postcode":"WA5 3GL",
    "sg:province":"Cheshire",
    "sg:tags":[
        "data",
        "network"
    ],
    "wof:name":"Advanced Network Solutions (Northern) Ltd.",
    "wof:placetype":"venue"
},
  "geometry": {"coordinates":[-2.6565,53.398319],"type":"Point"}
}