{
  "type": "Feature",
  "properties": {
    "iso:country":"GB",
    "sg:address":"91-93 Etnam Street",
    "sg:city":"Leominster",
    "sg:classifiers":[
        {
            "category":"Home & Garden",
            "subcategory":"Hardware",
            "type":"Retail Goods"
        }
    ],
    "sg:postcode":"HR6 8AF",
    "sg:province":"Herefordshire",
    "sg:tags":[
        "lawnmowers",
        "machinery"
    ],
    "wof:name":"Wilsons",
    "wof:placetype":"venue"
},
  "geometry": {"coordinates":[-2.733786,52.22654],"type":"Point"}
}