{
  "type": "Feature",
  "properties": {
    "addr:full":"22 Main Street, Cowie Stirling Falkirk FK7 7BL",
    "addr:housenumber":"22",
    "addr:postcode":"fk7 7bl",
    "addr:street":"Main Street",
    "iso:country":"GB",
    "sg:address":"22 Main Street, Cowie",
    "sg:city":"Stirling",
    "sg:classifiers":[
        {
            "category":"Personal",
            "subcategory":"Beauty Salon",
            "type":"Services"
        }
    ],
    "sg:phone":"+44 1786 811996",
    "sg:postcode":"FK7 7BL",
    "sg:province":"Falkirk",
    "sg:tags":[
        "unisex",
        "hairdresser"
    ],
    "wof:name":"Heather's",
    "wof:placetype":"venue"
},
  "geometry": {"coordinates":[-3.8695309162,56.0819206238],"type":"Point"}
}