{
  "type": "Feature",
  "properties": {
    "addr:full":"The Yard, Lake Lane, Barnham Bognor Regis West Sussex PO22 0AE",
    "addr:postcode":"po22 0ae",
    "addr:street":"Lake Lane",
    "iso:country":"GB",
    "sg:address":"The Yard, Lake Lane, Barnham",
    "sg:city":"Bognor Regis",
    "sg:classifiers":[
        {
            "category":"Manufacturing",
            "subcategory":"Lumber",
            "type":"Manufacturing & Wholesale Goods"
        }
    ],
    "sg:postcode":"PO22 0AE",
    "sg:province":"West Sussex",
    "sg:tags":[
        "importer",
        "merchants",
        "agent",
        "timber"
    ],
    "wof:name":"Howard Materials",
    "wof:placetype":"venue"
},
  "geometry": {"coordinates":[-0.6241639853,50.833278656],"type":"Point"}
}