{
  "type": "Feature",
  "properties": {
    "addr:full":"1 Mina Road London Greater London SE17 2QS",
    "addr:housenumber":"1",
    "addr:postcode":"se17 2qs",
    "addr:street":"Mina Road",
    "iso:country":"GB",
    "sg:address":"1 Mina Road",
    "sg:city":"London",
    "sg:classifiers":[
        {
            "category":"Retail",
            "subcategory":"Auto Repair",
            "type":"Services"
        }
    ],
    "sg:phone":"+44 20 7703 6839",
    "sg:postcode":"SE17 2QS",
    "sg:province":"Greater London",
    "sg:tags":[
        "modification",
        "garage"
    ],
    "wof:name":"Albany Garage",
    "wof:placetype":"venue"
},
  "geometry": {"coordinates":[-0.078505002,51.4882354736],"type":"Point"}
}