{
  "type": "Feature",
  "properties": {
    "addr:full":"Palm Street, Old Town Barnsley South Yorkshire S75 2SU",
    "addr:postcode":"s75 2su",
    "addr:street":"Palm Street;Yorkshire",
    "iso:country":"GB",
    "sg:address":"Palm Street, Old Town",
    "sg:city":"Barnsley",
    "sg:classifiers":[
        {
            "category":"Bars & Pubs",
            "type":"Food & Drink"
        }
    ],
    "sg:phone":"+44 1226 282339",
    "sg:postcode":"S75 2SU",
    "sg:province":"South Yorkshire",
    "sg:tags":[
        "pubs",
        "inn"
    ],
    "wof:name":"Inntrepreneur Pub Co.",
    "wof:placetype":"venue"
},
  "geometry": {"coordinates":[-1.494968,53.559315],"type":"Point"}
}