{
  "type": "Feature",
  "properties": {
    "addr:full":"39 Front St West Wingate Durham TS28 5AA",
    "addr:housenumber":"39",
    "addr:postcode":"ts28 5aa",
    "addr:street":"Front St;Wingate",
    "iso:country":"GB",
    "sg:address":"39 Front St West",
    "sg:city":"Wingate",
    "sg:classifiers":[
        {
            "category":"Shopping",
            "subcategory":"Department Store",
            "type":"Retail Goods"
        }
    ],
    "sg:postcode":"TS28 5AA",
    "sg:province":"Durham",
    "wof:name":"Hockaday,Joseph H,",
    "wof:placetype":"venue"
},
  "geometry": {"coordinates":[-1.380794,54.727718],"type":"Point"}
}