{
  "type": "Feature",
  "properties": {
    "addr:full":"62 Church Street, Whittington Lichfield Staffordshire WS14 9JX",
    "addr:housenumber":"62",
    "addr:postcode":"ws14 9jx",
    "addr:street":"Church Street",
    "iso:country":"GB",
    "sg:address":"62 Church Street, Whittington",
    "sg:city":"Lichfield",
    "sg:classifiers":[
        {
            "category":"Professional",
            "subcategory":"Accounting & Tax Preparation",
            "type":"Services"
        }
    ],
    "sg:postcode":"WS14 9JX",
    "sg:province":"Staffordshire",
    "sg:tags":[
        "accountant"
    ],
    "wof:name":"Malcolm N Wigley & Co",
    "wof:placetype":"venue"
},
  "geometry": {"coordinates":[-1.7680779696,52.672870636],"type":"Point"}
}