{
  "type": "Feature",
  "properties": {
    "addr:full":"5-6 Hurlands Business Centre Farnham Surrey GU9 9JE",
    "addr:housenumber":"5-6",
    "addr:postcode":"gu9 9je",
    "addr:street":"Hurlands Business Centre Farnham",
    "iso:country":"GB",
    "sg:address":"5-6 Hurlands Business Centre",
    "sg:city":"Farnham",
    "sg:classifiers":[
        {
            "category":"Shopping",
            "subcategory":"Clothing, Apparel, & Fashions",
            "type":"Retail Goods"
        }
    ],
    "sg:phone":"+44 1252 717616",
    "sg:postcode":"GU9 9JE",
    "sg:province":"Surrey",
    "sg:tags":[
        "workwear",
        "protective"
    ],
    "wof:name":"Shield Medicare Ltd.",
    "wof:placetype":"venue"
},
  "geometry": {"coordinates":[-0.7714759707,51.2231025696],"type":"Point"}
}