{
  "type": "Feature",
  "properties": {
    "addr:full":"Chippenham Drive Milton Keynes Buckinghamshire MK10 0AN",
    "addr:postcode":"mk10 0an",
    "addr:street":"Chippenham Drive",
    "iso:country":"GB",
    "sg:address":"Chippenham Drive",
    "sg:city":"Milton Keynes",
    "sg:classifiers":[
        {
            "category":"Building & Trades",
            "subcategory":"Electrical",
            "type":"Services"
        }
    ],
    "sg:phone":"+44 1908 282044",
    "sg:postcode":"MK10 0AN",
    "sg:province":"Buckinghamshire",
    "sg:tags":[
        "consultant",
        "lighting"
    ],
    "wof:name":"Anocoil Ltd",
    "wof:placetype":"venue"
},
  "geometry": {"coordinates":[-0.6924009919,52.038192749],"type":"Point"}
}