{
  "type": "Feature",
  "properties": {
    "addr:full":"Village Farm, Thornton Watlass Ripon North Yorkshire HG4 4AH",
    "addr:housenumber":"thornton watlass",
    "addr:postcode":"hg4 4ah",
    "iso:country":"GB",
    "sg:address":"Village Farm, Thornton Watlass",
    "sg:city":"Ripon",
    "sg:classifiers":[
        {
            "category":"Farming",
            "subcategory":"Dairy Farm",
            "type":"Manufacturing & Wholesale Goods"
        }
    ],
    "sg:phone":"+44 1677 422896",
    "sg:postcode":"HG4 4AH",
    "sg:province":"North Yorkshire",
    "sg:tags":[
        "farmer"
    ],
    "wof:name":"D R Allison",
    "wof:placetype":"venue"
},
  "geometry": {"coordinates":[-1.640619,54.264591],"type":"Point"}
}