{
  "type": "Feature",
  "properties": {
    "addr:full":"Bell Street Wolverhampton West Midlands WV1 3PR",
    "addr:postcode":"wv1 3pr",
    "addr:street":"Bell Street",
    "iso:country":"GB",
    "sg:address":"Bell Street",
    "sg:city":"Wolverhampton",
    "sg:classifiers":[
        {
            "category":"Commercial Area",
            "type":"Public Place"
        }
    ],
    "sg:phone":"+44 1902 425654",
    "sg:postcode":"WV1 3PR",
    "sg:province":"West Midlands",
    "sg:tags":[
        "shop",
        "centre"
    ],
    "wof:name":"Wulfrun Centre",
    "wof:placetype":"venue"
},
  "geometry": {"coordinates":[-2.1290409565,52.5838470459],"type":"Point"}
}