{
  "type": "Feature",
  "properties": {
    "addr:full":"Unit 14, Bridgend Works, Bridgend Stonehouse Gloucestershire GL10 2BA",
    "addr:housenumber":"unit 14",
    "addr:postcode":"stonehouse;gl10 2ba",
    "iso:country":"GB",
    "sg:address":"Unit 14, Bridgend Works, Bridgend",
    "sg:city":"Stonehouse",
    "sg:classifiers":[
        {
            "category":"Professional",
            "type":"Services"
        },
        {
            "category":"Building & Trades",
            "subcategory":"Cleaning & Sanitation",
            "type":"Services"
        }
    ],
    "sg:phone":"+44 1453 821101",
    "sg:postcode":"GL10 2BA",
    "sg:province":"Gloucestershire",
    "sg:tags":[
        "dry",
        "control",
        "damp",
        "rot",
        "preservation"
    ],
    "wof:name":"Frampton Consultants Ltd.",
    "wof:placetype":"venue"
},
  "geometry": {"coordinates":[-2.2861390114,51.7396202087],"type":"Point"}
}