{
  "type": "Feature",
  "properties": {
    "iso:country":"GB",
    "sg:address":"23 New Mount Street",
    "sg:city":"Manchester",
    "sg:classifiers":[
        {
            "category":"Professional",
            "subcategory":"Employment Agencies",
            "type":"Services"
        }
    ],
    "sg:phone":"+44 161 839 3151",
    "sg:postcode":"M4 4DE",
    "sg:province":"Greater Manchester",
    "sg:tags":[
        "consultant"
    ],
    "wof:name":"First Logistics Ltd.",
    "wof:placetype":"venue"
},
  "geometry": {"coordinates":[-2.2354021072,53.4882545471],"type":"Point"}
}