{
  "type": "Feature",
  "properties": {
    "addr:full":"Alexander House, Fleming Way Swindon Wiltshire SN1 2NG",
    "addr:postcode":"sn1 2ng",
    "addr:street":"Fleming Way",
    "iso:country":"GB",
    "sg:address":"Alexander House, Fleming Way",
    "sg:city":"Swindon",
    "sg:classifiers":[
        {
            "category":"Building & Trades",
            "subcategory":"Cleaning & Sanitation",
            "type":"Services"
        }
    ],
    "sg:phone":"+44 1793 705133",
    "sg:postcode":"SN1 2NG",
    "sg:province":"Wiltshire",
    "sg:tags":[
        "commercial"
    ],
    "wof:name":"J P S Services",
    "wof:placetype":"venue"
},
  "geometry": {"coordinates":[-1.776415,51.562897],"type":"Point"}
}