{
  "type": "Feature",
  "properties": {
    "addr:full":"High Street, Saul Gloucester Gloucestershire GL2 7LW",
    "addr:postcode":"gl2 7lw",
    "addr:street":"High Street",
    "iso:country":"GB",
    "sg:address":"High Street, Saul",
    "sg:city":"Gloucester",
    "sg:classifiers":[
        {
            "category":"Education",
            "subcategory":"School",
            "type":"Public Place"
        }
    ],
    "sg:phone":"+44 1452 740337",
    "sg:postcode":"GL2 7LW",
    "sg:province":"Gloucestershire",
    "sg:tags":[
        "local",
        "authority"
    ],
    "wof:name":"Gloucestershire County Council",
    "wof:placetype":"venue"
},
  "geometry": {"coordinates":[-2.366349,51.782124],"type":"Point"}
}