{
  "type": "Feature",
  "properties": {
    "iso:country":"GB",
    "sg:address":"Old Severalls Rd",
    "sg:city":"Thetford",
    "sg:classifiers":[
        {
            "category":"Building & Trades",
            "subcategory":"Landscaping Services",
            "type":"Services"
        }
    ],
    "sg:phone":"+44 1366 728153",
    "sg:postcode":"IP26 4QR",
    "sg:province":"Norfolk",
    "sg:tags":[
        "horticultural",
        "consultant"
    ],
    "wof:name":"E.B.L",
    "wof:placetype":"venue"
},
  "geometry": {"coordinates":[0.5231320262,52.5269927979],"type":"Point"}
}