{
  "type": "Feature",
  "properties": {
    "addr:full":"18 Albion Parade, Wall Heath Brierley Hill Staffordshire DY6 0NP",
    "addr:housenumber":"18",
    "addr:postcode":"dy6 0np",
    "addr:street":"Albion Parade Wall Heath",
    "iso:country":"GB",
    "sg:address":"18 Albion Parade, Wall Heath",
    "sg:city":"Brierley Hill",
    "sg:classifiers":[
        {
            "category":"Fast Food",
            "type":"Food & Drink"
        }
    ],
    "sg:phone":"+44 1384 400606",
    "sg:postcode":"DY6 0NP",
    "sg:province":"Staffordshire",
    "sg:tags":[
        "away",
        "meal",
        "outlet",
        "take"
    ],
    "wof:name":"Roberto's Dial A Pizza",
    "wof:placetype":"venue"
},
  "geometry": {"coordinates":[-2.179764,52.507652],"type":"Point"}
}