{
  "type": "Feature",
  "properties": {
    "addr:full":"33 Innerwood Rd Kilwinning East Ayrshire KA13 7DX",
    "addr:housenumber":"33",
    "addr:postcode":"ka13 7dx",
    "addr:street":"Innerwood Rd",
    "iso:country":"GB",
    "sg:address":"33 Innerwood Rd",
    "sg:city":"Kilwinning",
    "sg:classifiers":[
        {
            "category":"Retail",
            "subcategory":"Repair Shop",
            "type":"Services"
        }
    ],
    "sg:phone":"+44 1294 551957",
    "sg:postcode":"KA13 7DX",
    "sg:province":"East Ayrshire",
    "sg:tags":[
        "radio",
        "television",
        "video"
    ],
    "wof:name":"Scotland Tomorrow Electronics",
    "wof:placetype":"venue"
},
  "geometry": {"coordinates":[-4.701065,55.660839],"type":"Point"}
}