{
  "type": "Feature",
  "properties": {
    "addr:full":"7 Hylton Rd Worcester Worcestershire WR2 5JN",
    "addr:housenumber":"7",
    "addr:postcode":"wr2 5jn",
    "addr:street":"Hylton Rd",
    "iso:country":"GB",
    "sg:address":"7 Hylton Rd",
    "sg:city":"Worcester",
    "sg:classifiers":[
        {
            "category":"Retail",
            "subcategory":"Auto Repair",
            "type":"Services"
        }
    ],
    "sg:phone":"+44 1905 422931",
    "sg:postcode":"WR2 5JN",
    "sg:province":"Worcestershire",
    "sg:tags":[
        "modification",
        "garage"
    ],
    "wof:name":"Hylton Road Garage",
    "wof:placetype":"venue"
},
  "geometry": {"coordinates":[-2.234128952,52.1955604553],"type":"Point"}
}