{
  "type": "Feature",
  "properties": {
    "addr:full":"Long St Manchester Greater Manchester M24 6UZ",
    "addr:postcode":"m24 6uz",
    "addr:street":"Long St",
    "iso:country":"GB",
    "sg:address":"Long St",
    "sg:city":"Manchester",
    "sg:classifiers":[
        {
            "category":"Place Of Worship",
            "type":"Public Place"
        }
    ],
    "sg:phone":"+44 161 643 3285",
    "sg:postcode":"M24 6UZ",
    "sg:province":"Greater Manchester",
    "wof:name":"Long Street Methodist Church",
    "wof:placetype":"venue"
},
  "geometry": {"coordinates":[-2.196854,53.554272],"type":"Point"}
}