{
  "type": "Feature",
  "properties": {
    "iso:country":"GB",
    "sg:address":"62 Links Rd",
    "sg:city":"Saltcoats",
    "sg:classifiers":[
        {
            "category":"Taxi",
            "type":"Transportation"
        },
        {
            "category":"Communications",
            "type":"Services"
        },
        {
            "category":"Military Area",
            "subcategory":"Air Force Base",
            "type":"Public Place"
        }
    ],
    "sg:postcode":"KA21 6BH",
    "sg:province":"North Ayrshire",
    "sg:tags":[
        "mini",
        "hire",
        "audio-visual",
        "private",
        "cab"
    ],
    "wof:name":"Macdowall,James,",
    "wof:placetype":"venue"
},
  "geometry": {"coordinates":[-4.7895932198,55.6449737549],"type":"Point"}
}