{
  "type": "Feature",
  "properties": {
    "addr:full":"89 Lyham Road London Greater London SW2 5DD",
    "addr:housenumber":"89",
    "addr:postcode":"sw2 5dd",
    "addr:street":"Lyham Road",
    "iso:country":"GB",
    "sg:address":"89 Lyham Road",
    "sg:city":"London",
    "sg:classifiers":[
        {
            "category":"Bars & Pubs",
            "type":"Food & Drink"
        }
    ],
    "sg:phone":"+44 20 8671 8914",
    "sg:postcode":"SW2 5DD",
    "sg:province":"Greater London",
    "sg:tags":[
        "pubs",
        "inn"
    ],
    "wof:name":"Duke of Cornwall",
    "wof:placetype":"venue"
},
  "geometry": {"coordinates":[-0.1277090013,51.4554214478],"type":"Point"}
}