{
  "type": "Feature",
  "properties": {
    "iso:country":"GB",
    "sg:address":"28 High Street",
    "sg:city":"Sheerness",
    "sg:classifiers":[
        {
            "category":"Real Estate",
            "subcategory":"Developer",
            "type":"Services"
        }
    ],
    "sg:phone":"+44 1795 666467",
    "sg:postcode":"ME12 1NL",
    "sg:province":"Kent",
    "sg:tags":[
        "property"
    ],
    "wof:name":"Kingsdale Homes Ltd.",
    "wof:placetype":"venue"
},
  "geometry": {"coordinates":[0.760562,51.440792],"type":"Point"}
}