{
  "type": "Feature",
  "properties": {
    "addr:full":"4 Glendon Court, Moorside Oldham Lancashire OL1 4SE",
    "addr:housenumber":"4",
    "addr:postcode":"ol1 4se",
    "addr:street":"Glendon Court",
    "iso:country":"GB",
    "sg:address":"4 Glendon Court, Moorside",
    "sg:city":"Oldham",
    "sg:classifiers":[
        {
            "category":"Building & Trades",
            "subcategory":"Construction",
            "type":"Services"
        }
    ],
    "sg:phone":"+44 161 626 3024",
    "sg:postcode":"OL1 4SE",
    "sg:province":"Lancashire",
    "sg:tags":[
        "flooring"
    ],
    "wof:name":"Howarth Flooring Contractors",
    "wof:placetype":"venue"
},
  "geometry": {"coordinates":[-2.075004,53.56469],"type":"Point"}
}