{
  "type": "Feature",
  "properties": {
    "addr:full":"7-10 Albert Square Great Yarmouth Norfolk NR30 3JH",
    "addr:housenumber":"7-10",
    "addr:postcode":"nr30 3jh",
    "addr:street":"Albert Square Great",
    "iso:country":"GB",
    "sg:address":"7-10 Albert Square",
    "sg:city":"Great Yarmouth",
    "sg:classifiers":[
        {
            "category":"Travel",
            "subcategory":"Hotels & Motels",
            "type":"Entertainment"
        }
    ],
    "sg:postcode":"NR30 3JH",
    "sg:province":"Norfolk",
    "wof:name":"St George Hotel",
    "wof:placetype":"venue"
},
  "geometry": {"coordinates":[1.7342120409,52.5998649597],"type":"Point"}
}