{
  "type": "Feature",
  "properties": {
    "addr:full":"Unit 1, Kerstein Mansions Assam St Whitechapel Greater London E1 7QT",
    "addr:housenumber":"unit 1 kerstein",
    "addr:postcode":"e1 7qt",
    "addr:street":"Assam St",
    "iso:country":"GB",
    "sg:address":"Unit 1, Kerstein Mansions Assam St",
    "sg:city":"Whitechapel",
    "sg:classifiers":[
        {
            "category":"Utilities",
            "type":"Services"
        }
    ],
    "sg:phone":"+44 20 7377 1920",
    "sg:postcode":"E1 7QT",
    "sg:province":"Greater London",
    "sg:tags":[
        "internet"
    ],
    "wof:name":"Webterior Multimedia Arts",
    "wof:placetype":"venue"
},
  "geometry": {"coordinates":[-0.0685200021,51.5151901245],"type":"Point"}
}