{
  "type": "Feature",
  "properties": {
    "addr:full":"Woodbridge Industrial Estate Sleaford Lincolnshire NG34 7TS",
    "addr:housenumber":"estate",
    "addr:postcode":"ng34 7ts",
    "iso:country":"GB",
    "sg:address":"Woodbridge Industrial Estate",
    "sg:city":"Sleaford",
    "sg:classifiers":[
        {
            "category":"Retail",
            "subcategory":"Auto Repair",
            "type":"Services"
        }
    ],
    "sg:phone":"+44 1529 302793",
    "sg:postcode":"NG34 7TS",
    "sg:province":"Lincolnshire",
    "sg:tags":[
        "modification",
        "garage"
    ],
    "wof:name":"Olive & Nicholson",
    "wof:placetype":"venue"
},
  "geometry": {"coordinates":[-0.3965060115,53.0061645508],"type":"Point"}
}