{
  "type": "Feature",
  "properties": {
    "addr:full":"Lodge Road Redditch Warwickshire B98 7BS",
    "addr:postcode":"b98 7bs",
    "addr:street":"Lodge Road",
    "iso:country":"GB",
    "sg:address":"Lodge Road",
    "sg:city":"Redditch",
    "sg:classifiers":[
        {
            "category":"Personal",
            "type":"Services"
        }
    ],
    "sg:phone":"+44 1527 64449",
    "sg:postcode":"B98 7BS",
    "sg:province":"Warwickshire",
    "sg:tags":[
        "delivery"
    ],
    "wof:name":"A 1 Taxis",
    "wof:placetype":"venue"
},
  "geometry": {"coordinates":[-1.937072,52.304081],"type":"Point"}
}