{
  "type": "Feature",
  "properties": {
    "iso:country":"GB",
    "sg:address":"12 Clos Hector, Pengam Grn",
    "sg:city":"Cardiff",
    "sg:classifiers":[
        {
            "category":"Retail",
            "subcategory":"Driving School",
            "type":"Services"
        }
    ],
    "sg:postcode":"CF24 2HL",
    "sg:province":"Cardiff",
    "wof:name":"R S M Drving School",
    "wof:placetype":"venue"
},
  "geometry": {"coordinates":[-3.131584,51.489342],"type":"Point"}
}