{
  "type": "Feature",
  "properties": {
    "addr:full":"Unit 1 Quarry Road Aberdeen Aberdeen City AB16 5UU",
    "addr:housenumber":"unit 1",
    "addr:postcode":"ab16 5uu",
    "addr:street":"Quarry Road",
    "iso:country":"GB",
    "sg:address":"Unit 1 Quarry Road",
    "sg:city":"Aberdeen",
    "sg:classifiers":[
        {
            "category":"Building & Trades",
            "subcategory":"Construction",
            "type":"Services"
        }
    ],
    "sg:phone":"+44 1224 692000",
    "sg:postcode":"AB16 5UU",
    "sg:province":"Aberdeen City",
    "sg:tags":[
        "roofing",
        "contracting"
    ],
    "wof:name":"S I G Roofing Supplies Ltd.",
    "wof:placetype":"venue"
},
  "geometry": {"coordinates":[-2.159334,57.165852],"type":"Point"}
}