{
  "type": "Feature",
  "properties": {
    "iso:country":"GB",
    "sg:address":"146 Bradwell Common Boulevard, Bradwell Common",
    "sg:city":"Milton Keynes",
    "sg:classifiers":[
        {
            "category":"Professional",
            "subcategory":"Management & Consulting",
            "type":"Services"
        }
    ],
    "sg:phone":"+44 1908 676174",
    "sg:postcode":"MK13 8BE",
    "sg:province":"Buckinghamshire",
    "sg:tags":[
        "consultant",
        "business"
    ],
    "wof:name":"Scorpio Consultants Uk Ltd.",
    "wof:placetype":"venue"
},
  "geometry": {"coordinates":[-0.769604,52.044563],"type":"Point"}
}