{
  "type": "Feature",
  "properties": {
    "iso:country":"GB",
    "sg:address":"Sales 8 Lawrence Industrial Estate, Lawrence Way",
    "sg:city":"Dunstable",
    "sg:classifiers":[
        {
            "category":"Home & Garden",
            "subcategory":"Hardware",
            "type":"Retail Goods"
        }
    ],
    "sg:phone":"+44 1582 475777",
    "sg:postcode":"LU6 1BD",
    "sg:province":"Bedfordshire",
    "sg:tags":[
        "product",
        "wire",
        "electrical"
    ],
    "wof:name":"Von Roll Isola Ltd.",
    "wof:placetype":"venue"
},
  "geometry": {"coordinates":[-0.520663,51.885803],"type":"Point"}
}