{
  "type": "Feature",
  "properties": {
    "addr:full":"142 Vauxhall Street Plymouth Devon PL4 0DF",
    "addr:housenumber":"142",
    "addr:postcode":"pl4 0df",
    "addr:street":"Vauxhall Street",
    "iso:country":"GB",
    "sg:address":"142 Vauxhall Street",
    "sg:city":"Plymouth",
    "sg:classifiers":[
        {
            "category":"Organizations",
            "subcategory":"Membership Organization",
            "type":"Services"
        }
    ],
    "sg:phone":"+44 1752 290837",
    "sg:postcode":"PL4 0DF",
    "sg:province":"Devon",
    "sg:tags":[
        "club"
    ],
    "wof:name":"Eddysune S A S C Sharkys",
    "wof:placetype":"venue"
},
  "geometry": {"coordinates":[-4.135035,50.370331],"type":"Point"}
}