{
  "type": "Feature",
  "properties": {
    "addr:full":"71 Southgate Elland West Yorkshire HX5 0DQ",
    "addr:housenumber":"71",
    "addr:postcode":"hx5 0dq",
    "addr:street":"Southgate Elland West",
    "iso:country":"GB",
    "sg:address":"71 Southgate",
    "sg:city":"Elland",
    "sg:classifiers":[
        {
            "category":"Shopping",
            "subcategory":"Catalog Store",
            "type":"Retail Goods"
        }
    ],
    "sg:postcode":"HX5 0DQ",
    "sg:province":"West Yorkshire",
    "sg:tags":[
        "catalogue",
        "showroom"
    ],
    "wof:name":"Ex Catalogue Shop",
    "wof:placetype":"venue"
},
  "geometry": {"coordinates":[-1.8368320465,53.6851234436],"type":"Point"}
}