{
  "type": "Feature",
  "properties": {
    "addr:full":"104 Ashton Road, Denton Manchester Greater Manchester M34 3JE",
    "addr:housenumber":"104",
    "addr:postcode":"m34 3je",
    "addr:street":"Ashton Road",
    "iso:country":"GB",
    "sg:address":"104 Ashton Road, Denton",
    "sg:city":"Manchester",
    "sg:classifiers":[
        {
            "category":"Retail",
            "subcategory":"Veterinary Services",
            "type":"Services"
        }
    ],
    "sg:phone":"+44 161 336 5062",
    "sg:postcode":"M34 3JE",
    "sg:province":"Greater Manchester",
    "sg:tags":[
        "surgeon",
        "activity"
    ],
    "wof:name":"Abbey Wood Veterinary Centre",
    "wof:placetype":"venue"
},
  "geometry": {"coordinates":[-2.1155979633,53.4598426819],"type":"Point"}
}