{
  "type": "Feature",
  "properties": {
    "addr:full":"Minsthorpe Lane, South Elmsall Pontefract West Yorkshire WF9 2PH",
    "addr:postcode":"wf9 2ph",
    "addr:street":"Minsthorpe Lane;Pontefract West",
    "iso:country":"GB",
    "sg:address":"Minsthorpe Lane, South Elmsall",
    "sg:city":"Pontefract",
    "sg:classifiers":[
        {
            "category":"Autos & Motor Vehicles",
            "subcategory":"Fuel & Gas Station",
            "type":"Retail Goods"
        }
    ],
    "sg:phone":"+44 1977 642376",
    "sg:postcode":"WF9 2PH",
    "sg:province":"West Yorkshire",
    "sg:tags":[
        "petrol",
        "filling"
    ],
    "wof:name":"Save Service Station",
    "wof:placetype":"venue"
},
  "geometry": {"coordinates":[-1.294794,53.59959],"type":"Point"}
}