{
  "type": "Feature",
  "properties": {
    "addr:full":"335 High Road Romford Essex IG1 1TE",
    "addr:housenumber":"335",
    "addr:postcode":"ig1 1te",
    "addr:street":"High Road",
    "iso:country":"GB",
    "sg:address":"335 High Road",
    "sg:city":"Romford",
    "sg:classifiers":[
        {
            "category":"Real Estate",
            "subcategory":"Real Estate Operator",
            "type":"Services"
        },
        {
            "category":"Professional",
            "subcategory":"Business Services",
            "type":"Services"
        }
    ],
    "sg:phone":"+44 20 8478 0600",
    "sg:postcode":"IG1 1TE",
    "sg:province":"Essex",
    "sg:tags":[
        "letting",
        "accomodation",
        "agent"
    ],
    "wof:name":"Crescent Property Services Ltd.",
    "wof:placetype":"venue"
},
  "geometry": {"coordinates":[0.1471139938,51.5730552673],"type":"Point"}
}