{
  "type": "Feature",
  "properties": {
    "addr:full":"79 St Johns Wood High Street London Greater London NW8 7NL",
    "addr:housenumber":"79",
    "addr:postcode":"nw8 7nl",
    "addr:street":"St Johns Wood High Street",
    "iso:country":"GB",
    "sg:address":"79 St Johns Wood High Street",
    "sg:city":"London",
    "sg:classifiers":[
        {
            "category":"Cafe",
            "type":"Food & Drink"
        }
    ],
    "sg:phone":"+44 20 7586 4365",
    "sg:postcode":"NW8 7NL",
    "sg:province":"Greater London",
    "sg:tags":[
        "tea",
        "room"
    ],
    "wof:name":"Seattle Coffee Co",
    "wof:placetype":"venue"
},
  "geometry": {"coordinates":[-0.171389,51.533867],"type":"Point"}
}