{
  "type": "Feature",
  "properties": {
    "addr:full":"3 Ellison St Hebburn Tyne and Wear NE31 1BP",
    "addr:housenumber":"3",
    "addr:postcode":"ne31 1bp",
    "addr:street":"Ellison St",
    "iso:country":"GB",
    "sg:address":"3 Ellison St",
    "sg:city":"Hebburn",
    "sg:classifiers":[
        {
            "category":"Shopping",
            "subcategory":"Florist",
            "type":"Retail Goods"
        }
    ],
    "sg:postcode":"NE31 1BP",
    "sg:province":"Tyne and Wear",
    "wof:name":"Aston,Michael,",
    "wof:placetype":"venue"
},
  "geometry": {"coordinates":[-1.5207229853,54.9784317017],"type":"Point"}
}