{
  "type": "Feature",
  "properties": {
    "addr:full":"9 Little Portland St West End Hampshire W1N 6LT",
    "addr:housenumber":"9",
    "addr:postcode":"6lt",
    "addr:street":"Little Portland St",
    "iso:country":"GB",
    "sg:address":"9 Little Portland St",
    "sg:city":"West End",
    "sg:classifiers":[
        {
            "category":"Shopping",
            "subcategory":"Clothing, Apparel, & Fashions",
            "type":"Retail Goods"
        }
    ],
    "sg:phone":"+44 20 7436 1722",
    "sg:postcode":"W1N 6LT",
    "sg:province":"Hampshire",
    "sg:tags":[
        "clothing",
        "fabric"
    ],
    "wof:name":"Civvy Clothing Co",
    "wof:placetype":"venue"
},
  "geometry": {"coordinates":[-0.141869,51.517189],"type":"Point"}
}