{
  "type": "Feature",
  "properties": {
    "iso:country":"GB",
    "sg:address":"Accountability, 340 High St",
    "sg:city":"Dorking",
    "sg:classifiers":[
        {
            "category":"Conference Center",
            "type":"Public Place"
        }
    ],
    "sg:phone":"+44 1306 741131",
    "sg:postcode":"RH4 1QX",
    "sg:province":"Surrey",
    "wof:name":"Business Communications International Lt",
    "wof:placetype":"venue"
},
  "geometry": {"coordinates":[-0.328814,51.233341],"type":"Point"}
}