{
  "type": "Feature",
  "properties": {
    "addr:full":"Asset House, Penarth Rd Cardiff Cardiff CF10 5RA",
    "addr:postcode":"cf10 5ra",
    "addr:street":"Penarth Rd",
    "iso:country":"GB",
    "sg:address":"Asset House, Penarth Rd",
    "sg:city":"Cardiff",
    "sg:classifiers":[
        {
            "category":"Food & Beverages",
            "subcategory":"Specialty",
            "type":"Retail Goods"
        }
    ],
    "sg:phone":"+44 29 2039 8080",
    "sg:postcode":"CF10 5RA",
    "sg:province":"Cardiff",
    "sg:tags":[
        "dietetic",
        "homogenised"
    ],
    "wof:name":"Aloe Vera Marketing Bureau",
    "wof:placetype":"venue"
},
  "geometry": {"coordinates":[-3.1783189774,51.473739624],"type":"Point"}
}