{
  "type": "Feature",
  "properties": {
    "iso:country":"GB",
    "sg:address":"20 The Parks, Newton Willows",
    "sg:city":"St Helens",
    "sg:classifiers":[
        {
            "category":"Building & Trades",
            "subcategory":"Construction",
            "type":"Services"
        }
    ],
    "sg:phone":"+44 1942 720000",
    "sg:postcode":"WA12 0JQ",
    "sg:province":"Cheshire",
    "sg:tags":[
        "builder"
    ],
    "wof:name":"Allen Trustee Ltd.",
    "wof:placetype":"venue"
},
  "geometry": {"coordinates":[-2.63921,53.47953],"type":"Point"}
}