{
  "type": "Feature",
  "properties": {
    "addr:full":"Cocklebury Road Chippenham Wiltshire SN15 3QF",
    "addr:postcode":"sn15 3qf",
    "addr:street":"Cocklebury Road",
    "iso:country":"GB",
    "sg:address":"Cocklebury Road",
    "sg:city":"Chippenham",
    "sg:classifiers":[
        {
            "category":"Autos & Motor Vehicles",
            "subcategory":"Auto Supplies",
            "type":"Retail Goods"
        }
    ],
    "sg:phone":"+44 1249 653541",
    "sg:postcode":"SN15 3QF",
    "sg:province":"Wiltshire",
    "sg:tags":[
        "tyre"
    ],
    "wof:name":"A T S",
    "wof:placetype":"venue"
},
  "geometry": {"coordinates":[-2.106654,51.463245],"type":"Point"}
}