{
  "type": "Feature",
  "properties": {
    "addr:full":"35 North Cray Road Bexley Kent DA5 3NE",
    "addr:housenumber":"35",
    "addr:postcode":"da5 3ne",
    "addr:street":"North Cray Road",
    "iso:country":"GB",
    "sg:address":"35 North Cray Road",
    "sg:city":"Bexley",
    "sg:classifiers":[
        {
            "category":"Bars & Pubs",
            "type":"Food & Drink"
        },
        {
            "category":"Travel",
            "subcategory":"Hotels & Motels",
            "type":"Entertainment"
        }
    ],
    "sg:phone":"+44 1322 523675",
    "sg:postcode":"DA5 3NE",
    "sg:province":"Kent",
    "sg:tags":[
        "pubs",
        "house",
        "inn",
        "guest"
    ],
    "wof:name":"Coach & Horses",
    "wof:placetype":"venue"
},
  "geometry": {"coordinates":[0.150562,51.437035],"type":"Point"}
}