{
  "type": "Feature",
  "properties": {
    "addr:full":"8 Drew Road Stourbridge West Midlands DY9 0UZ",
    "addr:housenumber":"8",
    "addr:postcode":"dy9 0uz",
    "addr:street":"Drew Road",
    "iso:country":"GB",
    "sg:address":"8 Drew Road",
    "sg:city":"Stourbridge",
    "sg:classifiers":[
        {
            "category":"Home & Garden",
            "subcategory":"Home Furnishings",
            "type":"Retail Goods"
        }
    ],
    "sg:phone":"+44 1384 370251",
    "sg:postcode":"DY9 0UZ",
    "sg:province":"West Midlands",
    "sg:tags":[
        "decorative",
        "glass",
        "mirror"
    ],
    "wof:name":"Connex International",
    "wof:placetype":"venue"
},
  "geometry": {"coordinates":[-2.1199901104,52.4460449219],"type":"Point"}
}