{
  "type": "Feature",
  "properties": {
    "addr:full":"Unit 8 The Street Industrial Estate, Heybridge Maldon Essex CM9 4XB",
    "addr:housenumber":"unit 8",
    "addr:postcode":"cm9 4xb",
    "addr:street":"The Street Industrial",
    "iso:country":"GB",
    "sg:address":"Unit 8 The Street Industrial Estate, Heybridge",
    "sg:city":"Maldon",
    "sg:classifiers":[
        {
            "category":"Autos & Motor Vehicles",
            "subcategory":"Fuel & Gas Station",
            "type":"Retail Goods"
        },
        {
            "category":"Professional",
            "subcategory":"Engineering",
            "type":"Services"
        }
    ],
    "sg:phone":"+44 1621 843404",
    "sg:postcode":"CM9 4XB",
    "sg:province":"Essex",
    "sg:tags":[
        "manufacturer"
    ],
    "sg:website":"http://www.bwcutters.com",
    "wof:name":"Blackman & White Ltd",
    "wof:placetype":"venue"
},
  "geometry": {"coordinates":[0.692628,51.740593],"type":"Point"}
}