{
  "type": "Feature",
  "properties": {
    "iso:country":"GB",
    "sg:address":"11 Balmellie Street",
    "sg:city":"Turriff",
    "sg:classifiers":[
        {
            "category":"Home & Garden",
            "subcategory":"Hardware",
            "type":"Retail Goods"
        }
    ],
    "sg:postcode":"AB53 4DW",
    "sg:province":"Aberdeenshire",
    "sg:tags":[
        "retailer",
        "diy"
    ],
    "wof:name":"L J Beedie's Hardware",
    "wof:placetype":"venue"
},
  "geometry": {"coordinates":[-2.4591469765,57.5373649597],"type":"Point"}
}