{
  "type": "Feature",
  "properties": {
    "addr:full":"5 Bulls Head Yd Alcester Warwickshire B49 5BX",
    "addr:housenumber":"5",
    "addr:postcode":"b49 5bx",
    "addr:street":"Yd",
    "iso:country":"GB",
    "sg:address":"5 Bulls Head Yd",
    "sg:city":"Alcester",
    "sg:classifiers":[
        {
            "category":"Professional",
            "subcategory":"Business Services",
            "type":"Services"
        },
        {
            "category":"Shopping",
            "subcategory":"Pets & Pet Supplies",
            "type":"Retail Goods"
        }
    ],
    "sg:postcode":"B49 5BX",
    "sg:province":"Warwickshire",
    "sg:tags":[
        "import",
        "export",
        "agent"
    ],
    "wof:name":"Dill,Michael,",
    "wof:placetype":"venue"
},
  "geometry": {"coordinates":[-1.860992,52.221798],"type":"Point"}
}