{
  "type": "Feature",
  "properties": {
    "iso:country":"GB",
    "sg:address":"1 Ringtail Road, Burscough Industrial Estate",
    "sg:city":"Ormskirk",
    "sg:classifiers":[
        {
            "category":"Retail",
            "subcategory":"Storage",
            "type":"Services"
        }
    ],
    "sg:postcode":"L40 8JT",
    "sg:province":"Lancashire",
    "sg:tags":[
        "household",
        "removal"
    ],
    "wof:name":"John Thompson & Son",
    "wof:placetype":"venue"
},
  "geometry": {"coordinates":[-2.8645141125,53.5979766846],"type":"Point"}
}