{
  "type": "Feature",
  "properties": {
    "addr:full":"Second Avenue, Trafford Park Manchester Cheshire M17 1EE",
    "addr:postcode":"m17 1ee",
    "addr:street":"Second Avenue Trafford",
    "iso:country":"GB",
    "sg:address":"Second Avenue, Trafford Park",
    "sg:city":"Manchester",
    "sg:classifiers":[
        {
            "category":"Freight",
            "type":"Transportation"
        }
    ],
    "sg:postcode":"M17 1EE",
    "sg:province":"Cheshire",
    "sg:tags":[
        "haulage",
        "road"
    ],
    "wof:name":"Harrison Transport",
    "wof:placetype":"venue"
},
  "geometry": {"coordinates":[-2.3083589077,53.4681396484],"type":"Point"}
}