{
  "type": "Feature",
  "properties": {
    "addr:full":"228 High Road London Greater London NW10 2NX",
    "addr:housenumber":"228",
    "addr:postcode":"nw10 2nx",
    "addr:street":"High Road",
    "iso:country":"GB",
    "sg:address":"228 High Road",
    "sg:city":"London",
    "sg:classifiers":[
        {
            "category":"Fast Food",
            "type":"Food & Drink"
        },
        {
            "category":"Restaurant",
            "type":"Food & Drink"
        }
    ],
    "sg:phone":"+44 20 8830 0772",
    "sg:postcode":"NW10 2NX",
    "sg:province":"Greater London",
    "sg:tags":[
        "away",
        "indian",
        "take"
    ],
    "wof:name":"Willesden Curry House",
    "wof:placetype":"venue"
},
  "geometry": {"coordinates":[-0.236816,51.548054],"type":"Point"}
}