{
  "type": "Feature",
  "properties": {
    "addr:full":"122 Doncaster Road Scunthorpe Lincolnshire DN15 7DN",
    "addr:housenumber":"122",
    "addr:postcode":"dn15 7dn",
    "addr:street":"Doncaster Road",
    "iso:country":"GB",
    "sg:address":"122 Doncaster Road",
    "sg:city":"Scunthorpe",
    "sg:classifiers":[
        {
            "category":"Building & Trades",
            "subcategory":"Construction",
            "type":"Services"
        }
    ],
    "sg:phone":"+44 1724 841379",
    "sg:postcode":"DN15 7DN",
    "sg:province":"Lincolnshire",
    "sg:tags":[
        "roofing"
    ],
    "wof:name":"R W  Downie",
    "wof:placetype":"venue"
},
  "geometry": {"coordinates":[-0.6701490283,53.5902366638],"type":"Point"}
}