{
  "type": "Feature",
  "properties": {
    "addr:full":"Mulberry Street Ashton Under Lyne Greater Manchester OL6 6EY",
    "addr:postcode":"ol6 6ey",
    "addr:street":"Mulberry Street;Under Lyne",
    "iso:country":"GB",
    "sg:address":"Mulberry Street",
    "sg:city":"Ashton Under Lyne",
    "sg:classifiers":[
        {
            "category":"Education",
            "subcategory":"Library",
            "type":"Public Place"
        }
    ],
    "sg:phone":"+44 161 330 2151",
    "sg:postcode":"OL6 6EY",
    "sg:province":"Greater Manchester",
    "sg:tags":[
        "book"
    ],
    "wof:name":"Tameside Central Library",
    "wof:placetype":"venue"
},
  "geometry": {"coordinates":[-2.0896539688,53.4894714355],"type":"Point"}
}