{
  "type": "Feature",
  "properties": {
    "iso:country":"GB",
    "sg:address":"101-103 Brixton Hill, Brixton",
    "sg:city":"London",
    "sg:classifiers":[
        {
            "category":"Shopping",
            "subcategory":"Discount & Variety Stores",
            "type":"Retail Goods"
        }
    ],
    "sg:phone":"+44 20 8674 0121",
    "sg:postcode":"SW2 1AA",
    "sg:province":"Greater London",
    "sg:tags":[
        "surplus"
    ],
    "wof:name":"M Urban (Trading) Ltd.",
    "wof:placetype":"venue"
},
  "geometry": {"coordinates":[-0.11972,51.454479],"type":"Point"}
}