{
  "type": "Feature",
  "properties": {
    "addr:full":"Two Pools Farm, Wotton Road, Iron Acton Bristol Gloucestershire BS37 9XD",
    "addr:postcode":"bs37 9xd",
    "addr:street":"Wotton Road",
    "iso:country":"GB",
    "sg:address":"Two Pools Farm, Wotton Road, Iron Acton",
    "sg:city":"Bristol",
    "sg:classifiers":[
        {
            "category":"Farming",
            "subcategory":"Farm",
            "type":"Manufacturing & Wholesale Goods"
        }
    ],
    "sg:phone":"+44 1454 228571",
    "sg:postcode":"BS37 9XD",
    "sg:province":"Gloucestershire",
    "sg:tags":[
        "egg",
        "producer"
    ],
    "wof:name":"P E King (Bristol) Ltd.",
    "wof:placetype":"venue"
},
  "geometry": {"coordinates":[-2.460513,51.550182],"type":"Point"}
}