{
  "type": "Feature",
  "properties": {
    "addr:full":"The Workshop Gallery Tomatin Highland IV13 7XY",
    "addr:postcode":"iv13 7xy",
    "iso:country":"GB",
    "sg:address":"The Workshop Gallery",
    "sg:city":"Tomatin",
    "sg:classifiers":[
        {
            "category":"Professional",
            "subcategory":"Art Services",
            "type":"Services"
        }
    ],
    "sg:phone":"+44 1808 511377",
    "sg:postcode":"IV13 7XY",
    "sg:province":"Highland",
    "sg:tags":[
        "framing"
    ],
    "wof:name":"Alan & Pamela Hardwick",
    "wof:placetype":"venue"
},
  "geometry": {"coordinates":[-3.9909079075,57.3342590332],"type":"Point"}
}