{
  "type": "Feature",
  "properties": {
    "addr:full":"33 Wilkinson Way, Chiswick London Greater London W4 5XD",
    "addr:housenumber":"33",
    "addr:postcode":"w4 5xd",
    "addr:street":"Wilkinson Way",
    "iso:country":"GB",
    "sg:address":"33 Wilkinson Way, Chiswick",
    "sg:city":"London",
    "sg:classifiers":[
        {
            "category":"Retail",
            "subcategory":"Driving School",
            "type":"Services"
        }
    ],
    "sg:phone":"+44 20 8995 2584",
    "sg:postcode":"W4 5XD",
    "sg:province":"Greater London",
    "wof:name":"Lynx Driving School",
    "wof:placetype":"venue"
},
  "geometry": {"coordinates":[-0.2641769946,51.5034103394],"type":"Point"}
}