{
  "type": "Feature",
  "properties": {
    "addr:full":"49 Oxford Street Weston-super-mare Somerset BS23 1TN",
    "addr:housenumber":"49",
    "addr:postcode":"bs23 1tn",
    "addr:street":"Oxford Street",
    "iso:country":"GB",
    "sg:address":"49 Oxford Street",
    "sg:city":"Weston-super-mare",
    "sg:classifiers":[
        {
            "category":"Bars & Pubs",
            "subcategory":"Nightclub",
            "type":"Food & Drink"
        }
    ],
    "sg:phone":"+44 1934 633673",
    "sg:postcode":"BS23 1TN",
    "sg:province":"Somerset",
    "sg:tags":[
        "club",
        "night"
    ],
    "wof:name":"The Lodge",
    "wof:placetype":"venue"
},
  "geometry": {"coordinates":[-2.977249,51.346321],"type":"Point"}
}