{
  "type": "Feature",
  "properties": {
    "iso:country":"GB",
    "sg:address":"Nailcote Farm, Nailcote Lane",
    "sg:city":"Coventry",
    "sg:classifiers":[
        {
            "category":"Home & Garden",
            "subcategory":"Garden Supply",
            "type":"Retail Goods"
        }
    ],
    "sg:phone":"+44 24 7646 4479",
    "sg:postcode":"CV7 7DE",
    "sg:province":"Warwickshire",
    "sg:tags":[
        "bulb",
        "grower"
    ],
    "wof:name":"J Cooper & Sons",
    "wof:placetype":"venue"
},
  "geometry": {"coordinates":[-1.61342,52.393318],"type":"Point"}
}