{
  "type": "Feature",
  "properties": {
    "iso:country":"GB",
    "sg:address":"Building 86",
    "sg:city":"Bicester",
    "sg:classifiers":[
        {
            "category":"Retail",
            "subcategory":"Event Space",
            "type":"Services"
        }
    ],
    "sg:postcode":"OX25 5HD",
    "sg:province":"Oxfordshire",
    "sg:tags":[
        "exhibition",
        "organiser"
    ],
    "wof:name":"Button Eventures",
    "wof:placetype":"venue"
},
  "geometry": {"coordinates":[-1.276417,51.928688],"type":"Point"}
}