{
  "type": "Feature",
  "properties": {
    "iso:country":"GB",
    "sg:address":"P O Box 152",
    "sg:city":"Kidderminster",
    "sg:classifiers":[
        {
            "category":"Professional",
            "subcategory":"Lawyer & Legal Services",
            "type":"Services"
        }
    ],
    "sg:phone":"+44 1299 828200",
    "sg:postcode":"DY11 7YY",
    "sg:province":"Staffordshire",
    "sg:tags":[
        "advice",
        "counselling"
    ],
    "wof:name":"Wyre Forest Womens Aid",
    "wof:placetype":"venue"
},
  "geometry": {"coordinates":[-2.2365291119,52.3361816406],"type":"Point"}
}