{
  "type": "Feature",
  "properties": {
    "addr:full":"69 Main Street, New Deer Turriff Aberdeenshire AB53 6SY",
    "addr:housenumber":"69",
    "addr:postcode":"ab53 6sy",
    "addr:street":"Main Street",
    "iso:country":"GB",
    "sg:address":"69 Main Street, New Deer",
    "sg:city":"Turriff",
    "sg:classifiers":[
        {
            "category":"Food & Beverages",
            "subcategory":"Bakery",
            "type":"Retail Goods"
        }
    ],
    "sg:phone":"+44 1771 644288",
    "sg:postcode":"AB53 6SY",
    "sg:province":"Aberdeenshire",
    "sg:tags":[
        "shop",
        "baker"
    ],
    "wof:name":"Kindness Bakers Ltd.",
    "wof:placetype":"venue"
},
  "geometry": {"coordinates":[-2.195147,57.51405],"type":"Point"}
}