{
  "type": "Feature",
  "properties": {
    "iso:country":"GB",
    "sg:address":"52 Dorchester Way",
    "sg:city":"Harrow",
    "sg:classifiers":[
        {
            "category":"Bars & Pubs",
            "subcategory":"Sports Bar",
            "type":"Food & Drink"
        },
        {
            "category":"Professional",
            "type":"Services"
        }
    ],
    "sg:phone":"+44 20 8204 0629",
    "sg:postcode":"HA3 9RE",
    "sg:province":"Greater London",
    "sg:tags":[
        "reflexology",
        "therapist",
        "reflexologists"
    ],
    "wof:name":"REKHA SHAH",
    "wof:placetype":"venue"
},
  "geometry": {"coordinates":[-0.286747,51.582027],"type":"Point"}
}