{
  "type": "Feature",
  "properties": {
    "iso:country":"GB",
    "sg:address":"Wyndley Garden Centre",
    "sg:city":"Sutton Coldfield",
    "sg:classifiers":[
        {
            "category":"Home & Garden",
            "subcategory":"Home Furnishings",
            "type":"Retail Goods"
        }
    ],
    "sg:postcode":"B74 4HA",
    "sg:province":"Staffordshire",
    "sg:tags":[
        "mantelpiece",
        "fireplace"
    ],
    "wof:name":"Flames",
    "wof:placetype":"venue"
},
  "geometry": {"coordinates":[-1.838632,52.605846],"type":"Point"}
}