{
  "type": "Feature",
  "properties": {
    "iso:country":"GB",
    "sg:address":"Field Rose, Springwood Lane",
    "sg:city":"Bungay",
    "sg:classifiers":[
        {
            "category":"Building & Trades",
            "subcategory":"Plumbing",
            "type":"Services"
        }
    ],
    "sg:phone":"+44 1508 482559",
    "sg:postcode":"NR35 2NF",
    "sg:province":"Norfolk",
    "sg:tags":[
        "heating"
    ],
    "wof:name":"B K M Plumbing & Heating",
    "wof:placetype":"venue"
},
  "geometry": {"coordinates":[1.443709,52.44997],"type":"Point"}
}