{
  "type": "Feature",
  "properties": {
    "addr:full":"127-129 Alaska Street London Greater London SE1 8XE",
    "addr:housenumber":"127-129",
    "addr:postcode":"se1 8xe",
    "addr:street":"Alaska Street",
    "iso:country":"GB",
    "sg:address":"127-129 Alaska Street",
    "sg:city":"London",
    "sg:classifiers":[
        {
            "category":"Communications",
            "subcategory":"Film & Video Production",
            "type":"Services"
        }
    ],
    "sg:phone":"+44 20 7928 7440",
    "sg:postcode":"SE1 8XE",
    "sg:province":"Greater London",
    "sg:tags":[
        "recording",
        "studio"
    ],
    "wof:name":"Alaska Street Studios",
    "wof:placetype":"venue"
},
  "geometry": {"coordinates":[-0.1111340001,51.5040359497],"type":"Point"}
}