{
  "type": "Feature",
  "properties": {
    "iso:country":"GB",
    "sg:address":"1 Park Road",
    "sg:city":"Bonnyrigg",
    "sg:classifiers":[
        {
            "category":"Freight",
            "type":"Transportation"
        }
    ],
    "sg:phone":"+44 131 663 9183",
    "sg:postcode":"EH19 2AW",
    "sg:province":"Midlothian",
    "sg:tags":[
        "haulage",
        "transport",
        "road"
    ],
    "wof:name":"H B G International Ltd.",
    "wof:placetype":"venue"
},
  "geometry": {"coordinates":[-3.107735,55.876717],"type":"Point"}
}