{
  "type": "Feature",
  "properties": {
    "addr:full":"21 The Oval Stevenage Hertfordshire SG1 5RD",
    "addr:housenumber":"21",
    "addr:postcode":"sg1 5rd",
    "addr:street":"The Oval",
    "iso:country":"GB",
    "sg:address":"21 The Oval",
    "sg:city":"Stevenage",
    "sg:classifiers":[
        {
            "category":"Shopping",
            "subcategory":"Florist",
            "type":"Retail Goods"
        }
    ],
    "sg:phone":"+44 1438 359608",
    "sg:postcode":"SG1 5RD",
    "sg:province":"Hertfordshire",
    "wof:name":"Buds'n'blooms",
    "wof:placetype":"venue"
},
  "geometry": {"coordinates":[-0.179714,51.917938],"type":"Point"}
}