{
  "type": "Feature",
  "properties": {
    "addr:full":"27 Northburn Avenue Aberdeen Aberdeen City AB15 6AH",
    "addr:housenumber":"27",
    "addr:postcode":"ab15 6ah",
    "addr:street":"Northburn Avenue",
    "iso:country":"GB",
    "sg:address":"27 Northburn Avenue",
    "sg:city":"Aberdeen",
    "sg:classifiers":[
        {
            "category":"Health Services",
            "subcategory":"Clinic",
            "type":"Services"
        }
    ],
    "sg:phone":"+44 1224 315124",
    "sg:postcode":"AB15 6AH",
    "sg:province":"Aberdeen City",
    "sg:tags":[
        "aromatherapy"
    ],
    "wof:name":"The Aromatherapy Clinic",
    "wof:placetype":"venue"
},
  "geometry": {"coordinates":[-2.157446,57.142231],"type":"Point"}
}