{
  "type": "Feature",
  "properties": {
    "iso:country":"GB",
    "sg:address":"Unit 6 Stonegravels Lane",
    "sg:city":"Chesterfield",
    "sg:classifiers":[
        {
            "category":"Home & Garden",
            "subcategory":"Home Furnishings",
            "type":"Retail Goods"
        }
    ],
    "sg:phone":"+44 1246 211303",
    "sg:postcode":"S41 7LF",
    "sg:province":"Derbyshire",
    "sg:tags":[
        "tube",
        "fitting",
        "stockist"
    ],
    "wof:name":"Proteus Fittings Ltd.",
    "wof:placetype":"venue"
},
  "geometry": {"coordinates":[-1.423564,53.247501],"type":"Point"}
}