{
  "type": "Feature",
  "properties": {
    "iso:country":"GB",
    "sg:address":"Scotsmans Lodge, Stamford Road",
    "sg:city":"Peterborough",
    "sg:classifiers":[
        {
            "category":"Farming",
            "subcategory":"Farm",
            "type":"Manufacturing & Wholesale Goods"
        }
    ],
    "sg:postcode":"PE6 7EL",
    "sg:province":"Cambridgeshire",
    "sg:tags":[
        "mixed",
        "crop"
    ],
    "wof:name":"F E Morton",
    "wof:placetype":"venue"
},
  "geometry": {"coordinates":[-0.34985,52.613609],"type":"Point"}
}