{
  "type": "Feature",
  "properties": {
    "addr:full":"878 Newport Road, Rumney Cardiff Caerphilly CF3 4LJ",
    "addr:housenumber":"878",
    "addr:postcode":"cf3 4lj",
    "addr:street":"Newport Road",
    "iso:country":"GB",
    "sg:address":"878 Newport Road, Rumney",
    "sg:city":"Cardiff",
    "sg:classifiers":[
        {
            "category":"Building & Trades",
            "subcategory":"Construction",
            "type":"Services"
        }
    ],
    "sg:postcode":"CF3 4LJ",
    "sg:province":"Caerphilly",
    "sg:tags":[
        "builder"
    ],
    "wof:name":"M J O R",
    "wof:placetype":"venue"
},
  "geometry": {"coordinates":[-3.127083,51.511513],"type":"Point"}
}