{
  "type": "Feature",
  "properties": {
    "iso:country":"GB",
    "sg:address":"Farraline Park",
    "sg:city":"Inverness",
    "sg:classifiers":[
        {
            "category":"Education",
            "subcategory":"Library",
            "type":"Public Place"
        },
        {
            "category":"Government",
            "subcategory":"Office",
            "type":"Public Place"
        }
    ],
    "sg:phone":"+44 1463 236463",
    "sg:postcode":"IV1 1NH",
    "sg:province":"Highland",
    "sg:tags":[
        "book",
        "local"
    ],
    "wof:name":"Inverness Library",
    "wof:placetype":"venue"
},
  "geometry": {"coordinates":[-4.22453,57.481121],"type":"Point"}
}