{
  "type": "Feature",
  "properties": {
    "addr:full":"13 Cockburn Street Falkirk Falkirk FK1 1DJ",
    "addr:housenumber":"13",
    "addr:postcode":"fk1 1dj",
    "addr:street":"Cockburn Street",
    "iso:country":"GB",
    "sg:address":"13 Cockburn Street",
    "sg:city":"Falkirk",
    "sg:classifiers":[
        {
            "category":"Professional",
            "subcategory":"Lawyer & Legal Services",
            "type":"Services"
        }
    ],
    "sg:phone":"+44 1324 635035",
    "sg:postcode":"FK1 1DJ",
    "sg:province":"Falkirk",
    "sg:tags":[
        "solicitor"
    ],
    "wof:name":"Brophy & Co",
    "wof:placetype":"venue"
},
  "geometry": {"coordinates":[-3.7880690098,56.0000953674],"type":"Point"}
}