{
  "type": "Feature",
  "properties": {
    "addr:full":"Unit G West Line Indust Est Chester Le Street Durham DH2 1AU",
    "addr:housenumber":"unit g",
    "addr:postcode":"dh2 1au",
    "addr:street":"West Line Indust Est;Le Street",
    "iso:country":"GB",
    "sg:address":"Unit G West Line Indust Est",
    "sg:city":"Chester Le Street",
    "sg:classifiers":[
        {
            "category":"Home & Garden",
            "subcategory":"Building Materials",
            "type":"Retail Goods"
        }
    ],
    "sg:phone":"+44 191 410 9080",
    "sg:postcode":"DH2 1AU",
    "sg:province":"Durham",
    "sg:tags":[
        "fencing"
    ],
    "wof:name":"Brian Hull",
    "wof:placetype":"venue"
},
  "geometry": {"coordinates":[-1.5868099928,54.8874015808],"type":"Point"}
}