{
  "type": "Feature",
  "properties": {
    "addr:full":"4 Selhurst Road London Greater London SE25 5QF",
    "addr:housenumber":"4",
    "addr:postcode":"se25 5qf",
    "addr:street":"Selhurst Road",
    "iso:country":"GB",
    "sg:address":"4 Selhurst Road",
    "sg:city":"London",
    "sg:classifiers":[
        {
            "category":"Military Area",
            "subcategory":"Air Force Base",
            "type":"Public Place"
        }
    ],
    "sg:postcode":"SE25 5QF",
    "sg:province":"Greater London",
    "sg:tags":[
        "mnfr",
        "trimming",
        "trimmer"
    ],
    "wof:name":"Sewing Accessories Wholesale",
    "wof:placetype":"venue"
},
  "geometry": {"coordinates":[-0.0900330022,51.3890686035],"type":"Point"}
}