{
  "type": "Feature",
  "properties": {
    "iso:country":"GB",
    "sg:address":"11 Crosland Industrial Estate, Stockport Road West, Bredbury",
    "sg:city":"Stockport",
    "sg:classifiers":[
        {
            "category":"Food & Beverages",
            "subcategory":"Liquor & Beverages",
            "type":"Retail Goods"
        },
        {
            "category":"Military Area",
            "subcategory":"Air Force Base",
            "type":"Public Place"
        }
    ],
    "sg:phone":"+44 161 494 0070",
    "sg:postcode":"SK6 2BR",
    "sg:province":"Cheshire",
    "sg:tags":[
        "wholesale",
        "beer",
        "wine",
        "spirit",
        "wines"
    ],
    "wof:name":"H B Clark Stockport Wholesale",
    "wof:placetype":"venue"
},
  "geometry": {"coordinates":[-2.122762,53.42065],"type":"Point"}
}