{
  "type": "Feature",
  "properties": {
    "addr:full":"11 Olympia Arcade, East Kilbride Glasgow South Lanarkshire G74 1LZ",
    "addr:housenumber":"11",
    "addr:postcode":"g74 1lz",
    "addr:street":"Olympia Arcade",
    "iso:country":"GB",
    "sg:address":"11 Olympia Arcade, East Kilbride",
    "sg:city":"Glasgow",
    "sg:classifiers":[
        {
            "category":"Shopping",
            "subcategory":"Clothing, Apparel, & Fashions",
            "type":"Retail Goods"
        }
    ],
    "sg:phone":"+44 1355 264369",
    "sg:postcode":"G74 1LZ",
    "sg:province":"South Lanarkshire",
    "sg:tags":[
        "shop"
    ],
    "wof:name":"Optchannel Ltd.",
    "wof:placetype":"venue"
},
  "geometry": {"coordinates":[-4.1746997833,55.7592010498],"type":"Point"}
}