{
  "type": "Feature",
  "properties": {
    "iso:country":"GB",
    "sg:address":"10 Birchwood Pde, Woodside Dr",
    "sg:city":"Dartford",
    "sg:classifiers":[
        {
            "category":"Shopping",
            "subcategory":"Department Store",
            "type":"Retail Goods"
        }
    ],
    "sg:phone":"+44 1322 558036",
    "sg:postcode":"DA2 7NJ",
    "sg:province":"Kent",
    "wof:name":"Mindi's Stores",
    "wof:placetype":"venue"
},
  "geometry": {"coordinates":[0.179895,51.427055],"type":"Point"}
}