{
  "type": "Feature",
  "properties": {
    "addr:full":"Milton Common Thame Buckinghamshire OX9 2NU",
    "addr:postcode":"ox9 2nu",
    "addr:street":"Milton",
    "iso:country":"GB",
    "sg:address":"Milton Common",
    "sg:city":"Thame",
    "sg:classifiers":[
        {
            "category":"Autos & Motor Vehicles",
            "subcategory":"Motorcycle Sales",
            "type":"Retail Goods"
        }
    ],
    "sg:phone":"+44 1844 279701",
    "sg:postcode":"OX9 2NU",
    "sg:province":"Buckinghamshire",
    "wof:name":"Hughenden M40 Ltd.",
    "wof:placetype":"venue"
},
  "geometry": {"coordinates":[-1.0518699884,51.7239112854],"type":"Point"}
}