{
  "type": "Feature",
  "properties": {
    "addr:full":"Chatley Farm, Tellisford Lane, Norton St Philip Bath Somerset BA2 7NJ",
    "addr:postcode":"ba2 7nj",
    "addr:street":"Tellisford Lane",
    "iso:country":"GB",
    "sg:address":"Chatley Farm, Tellisford Lane, Norton St Philip",
    "sg:city":"Bath",
    "sg:classifiers":[
        {
            "category":"Home & Garden",
            "subcategory":"Garden Supply",
            "type":"Retail Goods"
        },
        {
            "category":"Farming",
            "subcategory":"Farm",
            "type":"Manufacturing & Wholesale Goods"
        }
    ],
    "sg:phone":"+44 1373 830287",
    "sg:postcode":"BA2 7NJ",
    "sg:province":"Somerset",
    "sg:tags":[
        "mixed",
        "bulb",
        "crop",
        "grower"
    ],
    "wof:name":"P J Pobjoy & Son",
    "wof:placetype":"venue"
},
  "geometry": {"coordinates":[-2.324846983,51.3012466431],"type":"Point"}
}