{
  "type": "Feature",
  "properties": {
    "iso:country":"GB",
    "sg:address":"Ashdown Park, Wych Cross",
    "sg:city":"Forest Row",
    "sg:classifiers":[
        {
            "category":"Travel",
            "subcategory":"Hotels & Motels",
            "type":"Entertainment"
        }
    ],
    "sg:phone":"+44 1342 824988",
    "sg:postcode":"RH18 5JR",
    "sg:province":"East Sussex",
    "wof:name":"Ashdown Park (Sussex) Ltd.",
    "wof:placetype":"venue"
},
  "geometry": {"coordinates":[0.033261,51.098259],"type":"Point"}
}