{
  "type": "Feature",
  "properties": {
    "iso:country":"GB",
    "sg:address":"16 Careks Pole Close, Malpas",
    "sg:city":"Truro",
    "sg:classifiers":[
        {
            "category":"Military Area",
            "subcategory":"Air Force Base",
            "type":"Public Place"
        }
    ],
    "sg:phone":"+44 1872 263635",
    "sg:postcode":"TR1 1QZ",
    "sg:province":"Cornwall",
    "sg:tags":[
        "taxi",
        "hire",
        "private"
    ],
    "wof:name":"A to B Taxis",
    "wof:placetype":"venue"
},
  "geometry": {"coordinates":[-5.026821,50.243614],"type":"Point"}
}