{
  "type": "Feature",
  "properties": {
    "iso:country":"GB",
    "sg:address":"127-133 High Street",
    "sg:city":"Hornchurch",
    "sg:classifiers":[
        {
            "category":"Recreation",
            "type":"Entertainment"
        }
    ],
    "sg:phone":"+44 1708 443966",
    "sg:postcode":"RM11 1TX",
    "sg:province":"Essex",
    "sg:tags":[
        "snooker",
        "billiards",
        "pool"
    ],
    "wof:name":"Knights Snooker Ltd.",
    "wof:placetype":"venue"
},
  "geometry": {"coordinates":[0.2198649943,51.5625534058],"type":"Point"}
}