{
  "type": "Feature",
  "properties": {
    "addr:full":"Cedars Farm, Rushton Rd Kettering Northamptonshire NN14 2QD",
    "addr:postcode":"nn14 2qd",
    "addr:street":"Rushton Rd",
    "iso:country":"GB",
    "sg:address":"Cedars Farm, Rushton Rd",
    "sg:city":"Kettering",
    "sg:classifiers":[
        {
            "category":"Professional",
            "subcategory":"Employment Agencies",
            "type":"Services"
        }
    ],
    "sg:phone":"+44 1536 760550",
    "sg:postcode":"NN14 2QD",
    "sg:province":"Northamptonshire",
    "sg:tags":[
        "agricultural",
        "advice"
    ],
    "wof:name":"Tuffbrand Livestock Equipment",
    "wof:placetype":"venue"
},
  "geometry": {"coordinates":[-0.80996,52.443008],"type":"Point"}
}