{
  "type": "Feature",
  "properties": {
    "iso:country":"GB",
    "sg:address":"Unit 6, Greenlea Park, Prince Georges Road",
    "sg:city":"London",
    "sg:classifiers":[
        {
            "category":"Professional",
            "subcategory":"Engineering",
            "type":"Services"
        },
        {
            "category":"Banks & Credit Unions",
            "subcategory":"Bank",
            "type":"Services"
        }
    ],
    "sg:phone":"+44 20 8640 1982",
    "sg:postcode":"SW19 2JD",
    "sg:province":"Greater London",
    "sg:tags":[
        "belt",
        "mechanical",
        "conveyor",
        "engineer"
    ],
    "wof:name":"Specialised Unit Handling Ltd.",
    "wof:placetype":"venue"
},
  "geometry": {"coordinates":[-0.1746799946,51.4146118164],"type":"Point"}
}