{
  "type": "Feature",
  "properties": {
    "addr:full":"1 Observatory View Hailsham East Sussex BN27 2HQ",
    "addr:housenumber":"1",
    "addr:postcode":"bn27 2hq",
    "addr:street":"Observatory View",
    "iso:country":"GB",
    "sg:address":"1 Observatory View",
    "sg:city":"Hailsham",
    "sg:classifiers":[
        {
            "category":"Retail",
            "subcategory":"Auto Repair",
            "type":"Services"
        }
    ],
    "sg:phone":"+44 1323 846934",
    "sg:postcode":"BN27 2HQ",
    "sg:province":"East Sussex",
    "sg:tags":[
        "modification",
        "garage"
    ],
    "wof:name":"Kevin Cars",
    "wof:placetype":"venue"
},
  "geometry": {"coordinates":[0.269792,50.858315],"type":"Point"}
}