{
  "type": "Feature",
  "properties": {
    "iso:country":"GB",
    "sg:address":"6 Queen Victoria Street",
    "sg:city":"Reading",
    "sg:classifiers":[
        {
            "category":"Shopping",
            "subcategory":"Hobbies, Toys, & Games",
            "type":"Retail Goods"
        }
    ],
    "sg:phone":"+44 118 958 1107",
    "sg:postcode":"RG1 1TQ",
    "sg:province":"Berkshire",
    "sg:tags":[
        "computer"
    ],
    "wof:name":"Gamestation",
    "wof:placetype":"venue"
},
  "geometry": {"coordinates":[-0.97191,51.456482],"type":"Point"}
}