{
  "type": "Feature",
  "properties": {
    "iso:country":"GB",
    "sg:address":"37 Devonshire Road",
    "sg:city":"Bexhill-on-sea",
    "sg:classifiers":[
        {
            "category":"Home & Garden",
            "subcategory":"Furniture",
            "type":"Retail Goods"
        }
    ],
    "sg:phone":"+44 1424 211188",
    "sg:postcode":"TN40 1BD",
    "sg:province":"East Sussex",
    "wof:name":"Stocks Quality Furniture",
    "wof:placetype":"venue"
},
  "geometry": {"coordinates":[0.474058,50.838783],"type":"Point"}
}