{
  "type": "Feature",
  "properties": {
    "addr:full":"37 Devonshire Road Bexhill-on-sea East Sussex TN40 1BD",
    "addr:housenumber":"37",
    "addr:postcode":"tn40 1bd",
    "addr:street":"Devonshire Road",
    "iso:country":"GB",
    "sg:address":"37 Devonshire Road",
    "sg:city":"Bexhill-on-sea",
    "sg:classifiers":[
        {
            "category":"Home & Garden",
            "subcategory":"Furniture",
            "type":"Retail Goods"
        }
    ],
    "sg:phone":"+44 1424 211188",
    "sg:postcode":"TN40 1BD",
    "sg:province":"East Sussex",
    "wof:name":"Stocks Quality Furniture",
    "wof:placetype":"venue"
},
  "geometry": {"coordinates":[0.474058,50.838783],"type":"Point"}
}