{
  "type": "Feature",
  "properties": {
    "addr:full":"Grafton Market, Burgess Street Leominster Herefordshire HR6 8DE",
    "addr:postcode":"hr6 8de",
    "addr:street":"Burgess Street",
    "iso:country":"GB",
    "sg:address":"Grafton Market, Burgess Street",
    "sg:city":"Leominster",
    "sg:classifiers":[
        {
            "category":"Food & Beverages",
            "subcategory":"Fruits & Vegetables",
            "type":"Retail Goods"
        }
    ],
    "sg:postcode":"HR6 8DE",
    "sg:province":"Herefordshire",
    "sg:tags":[
        "greengrocer"
    ],
    "wof:name":"Daves Fresh Fruit & Veg",
    "wof:placetype":"venue"
},
  "geometry": {"coordinates":[-2.743553,52.227077],"type":"Point"}
}