{
  "type": "Feature",
  "properties": {
    "iso:country":"GB",
    "sg:address":"39 Willoughby Avenue",
    "sg:city":"Thornton-cleveleys",
    "sg:classifiers":[
        {
            "category":"Shopping",
            "subcategory":"Beauty & Cosmetics",
            "type":"Retail Goods"
        }
    ],
    "sg:postcode":"FY5 2BW",
    "sg:province":"Lancashire",
    "sg:tags":[
        "wig",
        "hairpiece"
    ],
    "wof:name":"Janice Hague",
    "wof:placetype":"venue"
},
  "geometry": {"coordinates":[-3.036044,53.878944],"type":"Point"}
}