{
  "type": "Feature",
  "properties": {
    "addr:full":"12 Blackhill Drive, Carlton Nottingham Nottinghamshire NG4 3FT",
    "addr:housenumber":"12",
    "addr:postcode":"ng4 3ft",
    "addr:street":"Blackhill Drive",
    "iso:country":"GB",
    "sg:address":"12 Blackhill Drive, Carlton",
    "sg:city":"Nottingham",
    "sg:classifiers":[
        {
            "category":"Home & Garden",
            "subcategory":"Home Furnishings",
            "type":"Retail Goods"
        },
        {
            "category":"Organizations",
            "subcategory":"Community Association",
            "type":"Services"
        }
    ],
    "sg:phone":"+44 115 940 0083",
    "sg:postcode":"NG4 3FT",
    "sg:province":"Nottinghamshire",
    "sg:tags":[
        "shelving",
        "installers",
        "system",
        "supplier",
        "diy",
        "racking"
    ],
    "wof:name":"Nottingham Used Pallets Racking Co",
    "wof:placetype":"venue"
},
  "geometry": {"coordinates":[-1.080928,52.971291],"type":"Point"}
}