{
  "type": "Feature",
  "properties": {
    "addr:full":"Ash Garth, Churchbrough Kirkby Stephen Cumbria CA17 4EJ",
    "addr:postcode":"ca17 4ej",
    "addr:street":"Ash;Churchbrough",
    "iso:country":"GB",
    "sg:address":"Ash Garth, Churchbrough",
    "sg:city":"Kirkby Stephen",
    "sg:classifiers":[
        {
            "category":"Building & Trades",
            "subcategory":"Construction",
            "type":"Services"
        }
    ],
    "sg:phone":"+44 17683 41839",
    "sg:postcode":"CA17 4EJ",
    "sg:province":"Cumbria",
    "sg:tags":[
        "builder"
    ],
    "wof:name":"S M Wilkinson (Builder)",
    "wof:placetype":"venue"
},
  "geometry": {"coordinates":[-2.3486230373,54.4727172852],"type":"Point"}
}