{
  "type": "Feature",
  "properties": {
    "iso:country":"GB",
    "sg:address":"21 Layton Road",
    "sg:city":"Poole",
    "sg:classifiers":[
        {
            "category":"Home & Garden",
            "subcategory":"Home Furnishings",
            "type":"Retail Goods"
        }
    ],
    "sg:postcode":"BH12 2BH",
    "sg:province":"Dorset",
    "sg:tags":[
        "blind",
        "curtain",
        "fitting"
    ],
    "wof:name":"Chris the Curtain Trackman",
    "wof:placetype":"venue"
},
  "geometry": {"coordinates":[-1.932303,50.729301],"type":"Point"}
}