{
  "type": "Feature",
  "properties": {
    "iso:country":"GB",
    "sg:address":"Sub Branch, 218 Heaton Moor Rd",
    "sg:city":"Stockport",
    "sg:classifiers":[
        {
            "category":"Banks & Credit Unions",
            "subcategory":"Bank",
            "type":"Services"
        }
    ],
    "sg:phone":"+44 161 432 9449",
    "sg:postcode":"SK4 4DU",
    "sg:province":"Cheshire",
    "wof:name":"NatWest",
    "wof:placetype":"venue"
},
  "geometry": {"coordinates":[-2.1893999577,53.4176216125],"type":"Point"}
}