{
  "type": "Feature",
  "properties": {
    "iso:country":"GB",
    "sg:address":"69 Bell Street",
    "sg:city":"Reigate",
    "sg:classifiers":[
        {
            "category":"Retail",
            "subcategory":"Laundry & Dry Cleaning",
            "type":"Services"
        }
    ],
    "sg:phone":"+44 1737 246099",
    "sg:postcode":"RH2 7AQ",
    "sg:province":"Surrey",
    "sg:tags":[
        "launderette"
    ],
    "wof:name":"J Bader(Cleaners)Ltd.",
    "wof:placetype":"venue"
},
  "geometry": {"coordinates":[-0.204457,51.235573],"type":"Point"}
}