{
  "type": "Feature",
  "properties": {
    "iso:country":"GB",
    "sg:address":"Oakfields, Wreath Lane",
    "sg:city":"Chard",
    "sg:classifiers":[
        {
            "category":"Building & Trades",
            "subcategory":"Construction",
            "type":"Services"
        }
    ],
    "sg:phone":"+44 1460 67147",
    "sg:postcode":"TA20 4DT",
    "sg:province":"Devon",
    "sg:tags":[
        "builder"
    ],
    "wof:name":"C & T Builders",
    "wof:placetype":"venue"
},
  "geometry": {"coordinates":[-2.9346139431,50.8380584717],"type":"Point"}
}