{
  "type": "Feature",
  "properties": {
    "addr:full":"Victoria Street Blackpool Lancashire FY1 4RJ",
    "addr:postcode":"fy1 4rj",
    "addr:street":"Victoria Street",
    "iso:country":"GB",
    "sg:address":"Victoria Street",
    "sg:city":"Blackpool",
    "sg:classifiers":[
        {
            "category":"Shopping",
            "type":"Retail Goods"
        }
    ],
    "sg:phone":"+44 1253 295089",
    "sg:postcode":"FY1 4RJ",
    "sg:province":"Lancashire",
    "sg:tags":[
        "part",
        "accessory"
    ],
    "wof:name":"The Wholesale Warehouse",
    "wof:placetype":"venue"
},
  "geometry": {"coordinates":[-3.054164,53.816704],"type":"Point"}
}