{
  "type": "Feature",
  "properties": {
    "iso:country":"GB",
    "sg:address":"Burn Street",
    "sg:city":"Bolton",
    "sg:classifiers":[
        {
            "category":"Manufacturing",
            "subcategory":"Textiles",
            "type":"Manufacturing & Wholesale Goods"
        }
    ],
    "sg:postcode":"BL3 6DA",
    "sg:province":"Lancashire",
    "sg:tags":[
        "knitwear"
    ],
    "wof:name":"Burn Street Mill Co",
    "wof:placetype":"venue"
},
  "geometry": {"coordinates":[-2.427766,53.573017],"type":"Point"}
}