{
  "type": "Feature",
  "properties": {
    "iso:country":"GB",
    "sg:address":"221 Union Road, Oswaldtwistle",
    "sg:city":"Accrington",
    "sg:classifiers":[
        {
            "category":"Building & Trades",
            "subcategory":"Equipment Rental",
            "type":"Services"
        }
    ],
    "sg:phone":"+44 1254 391320",
    "sg:postcode":"BB5 3HU",
    "sg:province":"Lancashire",
    "sg:tags":[
        "hire",
        "centre"
    ],
    "wof:name":"Ossy Tool Hire Ltd.",
    "wof:placetype":"venue"
},
  "geometry": {"coordinates":[-2.395596,53.743603],"type":"Point"}
}