{
  "type": "Feature",
  "properties": {
    "addr:full":"71 Bank Hey Street Blackpool Lancashire FY1 4TH",
    "addr:housenumber":"71",
    "addr:postcode":"fy1 4th",
    "addr:street":"Bank Hey Street",
    "iso:country":"GB",
    "sg:address":"71 Bank Hey Street",
    "sg:city":"Blackpool",
    "sg:classifiers":[
        {
            "category":"Shopping",
            "subcategory":"Clothing, Apparel, & Fashions",
            "type":"Retail Goods"
        }
    ],
    "sg:phone":"+44 1253 622528",
    "sg:postcode":"FY1 4TH",
    "sg:province":"Lancashire",
    "sg:tags":[
        "shop"
    ],
    "wof:name":"Alexon International Ltd.",
    "wof:placetype":"venue"
},
  "geometry": {"coordinates":[-3.054777,53.815033],"type":"Point"}
}