{
  "type": "Feature",
  "properties": {
    "addr:full":"4-5 Lindsay Road Edinburgh City of Edinburgh EH6 4DT",
    "addr:housenumber":"4-5",
    "addr:postcode":"eh6 4dt",
    "addr:street":"Lindsay Road",
    "iso:country":"GB",
    "sg:address":"4-5 Lindsay Road",
    "sg:city":"Edinburgh",
    "sg:classifiers":[
        {
            "category":"Professional",
            "subcategory":"Art Services",
            "type":"Services"
        }
    ],
    "sg:phone":"+44 131 553 6663",
    "sg:postcode":"EH6 4DT",
    "sg:province":"City of Edinburgh",
    "sg:tags":[
        "decorating",
        "painting"
    ],
    "wof:name":"Leyland Decorating Trade Centre",
    "wof:placetype":"venue"
},
  "geometry": {"coordinates":[-3.184526,55.979134],"type":"Point"}
}