{
  "type": "Feature",
  "properties": {
    "iso:country":"GB",
    "sg:address":"342-343 Dukes Walk, Chequers Centre",
    "sg:city":"Maidstone",
    "sg:classifiers":[
        {
            "category":"Shopping",
            "subcategory":"Luggage & Leather Goods",
            "type":"Retail Goods"
        }
    ],
    "sg:phone":"+44 1622 672333",
    "sg:postcode":"ME15 6AS",
    "sg:province":"Kent",
    "sg:tags":[
        "shop",
        "leathergoods"
    ],
    "wof:name":"M & J Travel Goods",
    "wof:placetype":"venue"
},
  "geometry": {"coordinates":[0.5253,51.272579],"type":"Point"}
}