{
  "type": "Feature",
  "properties": {
    "addr:full":"Snowdrop Farm, Jekil's Bank, Holbeach St Johns Spalding Cambridgeshire PE12 8SG",
    "addr:postcode":"pe12 8sg",
    "addr:street":"Holbeach St;Spalding",
    "iso:country":"GB",
    "sg:address":"Snowdrop Farm, Jekil's Bank, Holbeach St Johns",
    "sg:city":"Spalding",
    "sg:classifiers":[
        {
            "category":"Home & Garden",
            "subcategory":"Garden Supply",
            "type":"Retail Goods"
        },
        {
            "category":"Farming",
            "subcategory":"Crops",
            "type":"Manufacturing & Wholesale Goods"
        },
        {
            "category":"Farming",
            "subcategory":"Farm",
            "type":"Manufacturing & Wholesale Goods"
        }
    ],
    "sg:phone":"+44 1406 540346",
    "sg:postcode":"PE12 8SG",
    "sg:province":"Cambridgeshire",
    "sg:tags":[
        "mixed",
        "bulb",
        "arable",
        "grower"
    ],
    "wof:name":"F Laming & Son",
    "wof:placetype":"venue"
},
  "geometry": {"coordinates":[0.0183099993,52.7499694824],"type":"Point"}
}