{
  "type": "Feature",
  "properties": {
    "iso:country":"GB",
    "sg:address":"950 North Circular Rd",
    "sg:city":"Cricklewood",
    "sg:classifiers":[
        {
            "category":"Home & Garden",
            "subcategory":"Furniture",
            "type":"Retail Goods"
        }
    ],
    "sg:phone":"+44 20 8208 0055",
    "sg:postcode":"NW2 7JR",
    "sg:province":"Greater London",
    "wof:name":"World Of Leather",
    "wof:placetype":"venue"
},
  "geometry": {"coordinates":[-0.2397000045,51.5691108704],"type":"Point"}
}