{
  "type": "Feature",
  "properties": {
    "addr:full":"11 Hume Street Clydebank East Dunbartonshire G81 1XL",
    "addr:housenumber":"11",
    "addr:postcode":"g81 1xl",
    "addr:street":"Hume Street",
    "iso:country":"GB",
    "sg:address":"11 Hume Street",
    "sg:city":"Clydebank",
    "sg:classifiers":[
        {
            "category":"Sports & Exercise",
            "subcategory":"Sports Center",
            "type":"Entertainment"
        },
        {
            "category":"Arts & Performance",
            "subcategory":"Theater",
            "type":"Entertainment"
        }
    ],
    "sg:phone":"+44 141 951 1554",
    "sg:postcode":"G81 1XL",
    "sg:province":"East Dunbartonshire",
    "sg:tags":[
        "rehearsal",
        "studio",
        "facility"
    ],
    "wof:name":"Red Eye Studios",
    "wof:placetype":"venue"
},
  "geometry": {"coordinates":[-4.403385,55.900204],"type":"Point"}
}