{
  "type": "Feature",
  "properties": {
    "addr:full":"7 Paddock Mt Telford Shropshire TF4 3PR",
    "addr:housenumber":"7",
    "addr:postcode":"tf4 3pr",
    "addr:street":"Paddock Mt",
    "iso:country":"GB",
    "sg:address":"7 Paddock Mt",
    "sg:city":"Telford",
    "sg:classifiers":[
        {
            "category":"Professional",
            "subcategory":"Art Services",
            "type":"Services"
        }
    ],
    "sg:postcode":"TF4 3PR",
    "sg:province":"Shropshire",
    "sg:tags":[
        "photographer"
    ],
    "wof:name":"Finlay,Bernard,",
    "wof:placetype":"venue"
},
  "geometry": {"coordinates":[-2.46289,52.66021],"type":"Point"}
}