{
  "type": "Feature",
  "properties": {
    "addr:full":"15 Salvia Close Clacton-on-sea Essex CO16 7BZ",
    "addr:housenumber":"15",
    "addr:postcode":"co16 7bz",
    "addr:street":"Salvia Close",
    "iso:country":"GB",
    "sg:address":"15 Salvia Close",
    "sg:city":"Clacton-on-sea",
    "sg:classifiers":[
        {
            "category":"Shopping",
            "subcategory":"Computers & Home Electronics",
            "type":"Retail Goods"
        }
    ],
    "sg:postcode":"CO16 7BZ",
    "sg:province":"Essex",
    "sg:tags":[
        "aerial",
        "television",
        "radio"
    ],
    "wof:name":"Thompson L A & Son Satellite & Aerial Services",
    "wof:placetype":"venue"
},
  "geometry": {"coordinates":[1.1362119913,51.7990684509],"type":"Point"}
}