{
  "type": "Feature",
  "properties": {
    "iso:country":"GB",
    "sg:address":"St Mary's Crescent",
    "sg:city":"Isleworth",
    "sg:classifiers":[
        {
            "category":"Education",
            "subcategory":"Library",
            "type":"Public Place"
        }
    ],
    "sg:phone":"+44 20 8560 4295",
    "sg:postcode":"TW7 4NB",
    "sg:province":"Greater London",
    "sg:tags":[
        "book"
    ],
    "wof:name":"Osterley Public Library",
    "wof:placetype":"venue"
},
  "geometry": {"coordinates":[-0.327328,51.468582],"type":"Point"}
}