{
  "type": "Feature",
  "properties": {
    "addr:full":"Civic Centre Harrow Greater London HA1 2UL",
    "addr:postcode":"ha1 2ul",
    "iso:country":"GB",
    "sg:address":"Civic Centre",
    "sg:city":"Harrow",
    "sg:classifiers":[
        {
            "category":"Social Services",
            "type":"Services"
        }
    ],
    "sg:phone":"+44 20 8861 3242",
    "sg:postcode":"HA1 2UL",
    "sg:province":"Greater London",
    "sg:tags":[
        "disability"
    ],
    "wof:name":"Harrow Helpline Alarms",
    "wof:placetype":"venue"
},
  "geometry": {"coordinates":[-0.336082,51.578785],"type":"Point"}
}