{
  "type": "Feature",
  "properties": {
    "iso:country":"GB",
    "sg:address":"63 Thorburn Rd",
    "sg:city":"Northampton",
    "sg:classifiers":[
        {
            "category":"Professional",
            "type":"Services"
        }
    ],
    "sg:phone":"+44 1604 470507",
    "sg:postcode":"NN3 3DA",
    "sg:province":"Northamptonshire",
    "sg:tags":[
        "shopfitters"
    ],
    "wof:name":"A N Displays",
    "wof:placetype":"venue"
},
  "geometry": {"coordinates":[-0.8422939777,52.2462501526],"type":"Point"}
}