{
  "type": "Feature",
  "properties": {
    "addr:full":"1 Sussex Rd Worthing West Sussex BN11 1DS",
    "addr:housenumber":"1",
    "addr:postcode":"bn11 1ds",
    "addr:street":"Sussex Rd",
    "iso:country":"GB",
    "sg:address":"1 Sussex Rd",
    "sg:city":"Worthing",
    "sg:classifiers":[
        {
            "category":"Communications",
            "type":"Services"
        }
    ],
    "sg:phone":"+44 1903 230320",
    "sg:postcode":"BN11 1DS",
    "sg:province":"West Sussex",
    "sg:tags":[
        "audio-visual"
    ],
    "wof:name":"Rare Earth Production Co",
    "wof:placetype":"venue"
},
  "geometry": {"coordinates":[-0.370069,50.816513],"type":"Point"}
}