{
  "type": "Feature",
  "properties": {
    "addr:full":"Thornley Lane North, Denton Manchester Greater Manchester M34 2FF",
    "addr:postcode":"m34 2ff",
    "addr:street":"Thornley Lane North",
    "iso:country":"GB",
    "sg:address":"Thornley Lane North, Denton",
    "sg:city":"Manchester",
    "sg:classifiers":[
        {
            "category":"Retail",
            "subcategory":"Auto Repair",
            "type":"Services"
        }
    ],
    "sg:phone":"+44 161 223 6400",
    "sg:postcode":"M34 2FF",
    "sg:province":"Greater Manchester",
    "sg:tags":[
        "modification",
        "garage"
    ],
    "wof:name":"Crescent Service Station",
    "wof:placetype":"venue"
},
  "geometry": {"coordinates":[-2.147449,53.446266],"type":"Point"}
}