{
  "type": "Feature",
  "properties": {
    "iso:country":"GB",
    "sg:address":"Altrincham Road, Styal",
    "sg:city":"Wilmslow",
    "sg:classifiers":[
        {
            "category":"Arena",
            "subcategory":"Sports Club",
            "type":"Entertainment"
        }
    ],
    "sg:phone":"+44 1625 529303",
    "sg:postcode":"SK9 4JE",
    "sg:province":"Cheshire",
    "wof:name":"Styal Sports & Social Club",
    "wof:placetype":"venue"
},
  "geometry": {"coordinates":[-2.244332,53.352428],"type":"Point"}
}