{
  "type": "Feature",
  "properties": {
    "iso:country":"GB",
    "sg:address":"Staddon",
    "sg:city":"Plymouth",
    "sg:classifiers":[
        {
            "category":"Professional",
            "subcategory":"Art Services",
            "type":"Services"
        }
    ],
    "sg:phone":"+44 1752 839332",
    "sg:postcode":"PL7 5HB",
    "sg:province":"Devon",
    "sg:tags":[
        "glass",
        "engraver"
    ],
    "wof:name":"M B Harris",
    "wof:placetype":"venue"
},
  "geometry": {"coordinates":[-4.026444,50.409462],"type":"Point"}
}