{
  "type": "Feature",
  "properties": {
    "iso:country":"GB",
    "sg:address":"Mounts Bay Ho, Churchtown",
    "sg:city":"Helston",
    "sg:classifiers":[
        {
            "category":"Banks & Credit Unions",
            "subcategory":"Financial Services",
            "type":"Services"
        }
    ],
    "sg:phone":"+44 1326 240030",
    "sg:postcode":"TR12 7BZ",
    "sg:province":"Cornwall",
    "sg:tags":[
        "consultant"
    ],
    "wof:name":"R W Blott",
    "wof:placetype":"venue"
},
  "geometry": {"coordinates":[-5.199324131,49.9687690735],"type":"Point"}
}