{
  "type": "Feature",
  "properties": {
    "addr:full":"68 Oakdene Crescent Nuneaton Leicestershire CV10 0DU",
    "addr:housenumber":"68",
    "addr:postcode":"cv10 0du",
    "addr:street":"Oakdene Crescent",
    "iso:country":"GB",
    "sg:address":"68 Oakdene Crescent",
    "sg:city":"Nuneaton",
    "sg:classifiers":[
        {
            "category":"Professional",
            "subcategory":"Engineering",
            "type":"Services"
        }
    ],
    "sg:phone":"+44 24 7634 8100",
    "sg:postcode":"CV10 0DU",
    "sg:province":"Leicestershire",
    "sg:tags":[
        "contractor",
        "electrical",
        "engineer"
    ],
    "wof:name":"Parker Bros",
    "wof:placetype":"venue"
},
  "geometry": {"coordinates":[-1.4631010294,52.5362892151],"type":"Point"}
}