{
  "type": "Feature",
  "properties": {
    "addr:full":"Carpiginiani House, Coldnose Rd, Rowtherwas Hereford Herefordshire HR2 6JL",
    "addr:postcode":"hr2 6jl",
    "addr:street":"Coldnose Rd",
    "iso:country":"GB",
    "sg:address":"Carpiginiani House, Coldnose Rd, Rowtherwas",
    "sg:city":"Hereford",
    "sg:classifiers":[
        {
            "category":"Ice Cream",
            "type":"Food & Drink"
        }
    ],
    "sg:phone":"+44 1432 351009",
    "sg:postcode":"HR2 6JL",
    "sg:province":"Herefordshire",
    "wof:name":"Ingrams Co Ltd",
    "wof:placetype":"venue"
},
  "geometry": {"coordinates":[-2.6803290844,52.0361633301],"type":"Point"}
}