{
  "type": "Feature",
  "properties": {
    "iso:country":"GB",
    "sg:address":"40 Barratt Rd",
    "sg:city":"Northampton",
    "sg:classifiers":[
        {
            "category":"Manufacturing",
            "subcategory":"Furniture",
            "type":"Manufacturing & Wholesale Goods"
        }
    ],
    "sg:phone":"+44 1604 250350",
    "sg:postcode":"NN1 3RJ",
    "sg:province":"Northamptonshire",
    "sg:tags":[
        "mnfr",
        "garden",
        "patio"
    ],
    "wof:name":"Tft Garden Furniture",
    "wof:placetype":"venue"
},
  "geometry": {"coordinates":[-0.895284,52.23394],"type":"Point"}
}