{
  "type": "Feature",
  "properties": {
    "addr:full":"130 Hamilton Avenue Surbiton Surrey KT6 7PZ",
    "addr:housenumber":"130",
    "addr:postcode":"kt6 7pz",
    "addr:street":"Hamilton Avenue",
    "iso:country":"GB",
    "sg:address":"130 Hamilton Avenue",
    "sg:city":"Surbiton",
    "sg:classifiers":[
        {
            "category":"Building & Trades",
            "subcategory":"Construction",
            "type":"Services"
        }
    ],
    "sg:postcode":"KT6 7PZ",
    "sg:province":"Surrey",
    "sg:tags":[
        "builder"
    ],
    "wof:name":"Francis Property Services",
    "wof:placetype":"venue"
},
  "geometry": {"coordinates":[-0.282868,51.37944],"type":"Point"}
}