{
  "type": "Feature",
  "properties": {
    "addr:full":"11 Campbell Street Northampton Northamptonshire NN1 3DS",
    "addr:housenumber":"11",
    "addr:postcode":"nn1 3ds",
    "addr:street":"Campbell Street",
    "iso:country":"GB",
    "sg:address":"11 Campbell Street",
    "sg:city":"Northampton",
    "sg:classifiers":[
        {
            "category":"Autos & Motor Vehicles",
            "subcategory":"Auto Supplies",
            "type":"Retail Goods"
        }
    ],
    "sg:phone":"+44 1604 622852",
    "sg:postcode":"NN1 3DS",
    "sg:province":"Northamptonshire",
    "sg:tags":[
        "tyre"
    ],
    "wof:name":"Hi-Q Tyre Services",
    "wof:placetype":"venue"
},
  "geometry": {"coordinates":[-0.897620976,52.2427787781],"type":"Point"}
}