{
  "type": "Feature",
  "properties": {
    "iso:country":"GB",
    "sg:address":"12 The Range, Langham",
    "sg:city":"Oakham",
    "sg:classifiers":[
        {
            "category":"Professional",
            "subcategory":"Accounting & Tax Preparation",
            "type":"Services"
        }
    ],
    "sg:postcode":"LE15 7EB",
    "sg:province":"Leicestershire",
    "sg:tags":[
        "accountant"
    ],
    "wof:name":"Keith McMorran",
    "wof:placetype":"venue"
},
  "geometry": {"coordinates":[-0.758631,52.690636],"type":"Point"}
}