{
  "type": "Feature",
  "properties": {
    "iso:country":"GB",
    "sg:address":"55 Willington Rd",
    "sg:city":"London",
    "sg:classifiers":[
        {
            "category":"Community Center",
            "subcategory":"Youth",
            "type":"Public Place"
        }
    ],
    "sg:phone":"+44 20 7737 0499",
    "sg:postcode":"SW9 9NB",
    "sg:province":"Greater London",
    "sg:tags":[
        "organisation",
        "centre"
    ],
    "wof:name":"Lambeth Council (Mayor & Burgessess Of)",
    "wof:placetype":"venue"
},
  "geometry": {"coordinates":[-0.125145,51.46368],"type":"Point"}
}