{
  "type": "Feature",
  "properties": {
    "addr:full":"81 Albert Rd Epsom Surrey KT17 4EQ",
    "addr:housenumber":"81",
    "addr:postcode":"kt17 4eq",
    "addr:street":"Albert Rd",
    "iso:country":"GB",
    "sg:address":"81 Albert Rd",
    "sg:city":"Epsom",
    "sg:classifiers":[
        {
            "category":"Home & Garden",
            "subcategory":"Household Appliances",
            "type":"Retail Goods"
        }
    ],
    "sg:phone":"+44 1372 742644",
    "sg:postcode":"KT17 4EQ",
    "sg:province":"Surrey",
    "sg:tags":[
        "electrical"
    ],
    "wof:name":"Babworth",
    "wof:placetype":"venue"
},
  "geometry": {"coordinates":[-0.25542,51.331516],"type":"Point"}
}