{
  "type": "Feature",
  "properties": {
    "iso:country":"GB",
    "sg:address":"Essex Works, 30 Kenway",
    "sg:city":"Southend-on-sea",
    "sg:classifiers":[
        {
            "category":"Manufacturing",
            "subcategory":"Rubber & Plastics",
            "type":"Manufacturing & Wholesale Goods"
        }
    ],
    "sg:postcode":"SS2 5DX",
    "sg:province":"Essex",
    "sg:tags":[
        "injection",
        "moulding"
    ],
    "wof:name":"Rosti (Southend) Ltd.",
    "wof:placetype":"venue"
},
  "geometry": {"coordinates":[0.7127,51.54771],"type":"Point"}
}