{
  "type": "Feature",
  "properties": {
    "addr:full":"100 Blackfen Road Sidcup Kent DA15 8SW",
    "addr:housenumber":"100",
    "addr:postcode":"da15 8sw",
    "addr:street":"Blackfen Road",
    "iso:country":"GB",
    "sg:address":"100 Blackfen Road",
    "sg:city":"Sidcup",
    "sg:classifiers":[
        {
            "category":"Building & Trades",
            "subcategory":"Construction",
            "type":"Services"
        }
    ],
    "sg:phone":"+44 20 8859 2716",
    "sg:postcode":"DA15 8SW",
    "sg:province":"Kent",
    "sg:tags":[
        "roofing",
        "contracting"
    ],
    "wof:name":"Specified Asphalt Co",
    "wof:placetype":"venue"
},
  "geometry": {"coordinates":[0.0930150002,51.451625824],"type":"Point"}
}