{
  "type": "Feature",
  "properties": {
    "iso:country":"GB",
    "sg:address":"11 Conquest Close",
    "sg:city":"Hitchin",
    "sg:classifiers":[
        {
            "category":"Building & Trades",
            "subcategory":"Plumbing",
            "type":"Services"
        }
    ],
    "sg:phone":"+44 1462 452311",
    "sg:postcode":"SG4 9DP",
    "sg:province":"Hertfordshire",
    "sg:tags":[
        "central",
        "heating"
    ],
    "wof:name":"Roger Hart",
    "wof:placetype":"venue"
},
  "geometry": {"coordinates":[-0.27135,51.940201],"type":"Point"}
}