{
  "type": "Feature",
  "properties": {
    "iso:country":"GB",
    "sg:address":"Japanica Lane, V10 Brickhill Street, Willen Park",
    "sg:city":"Milton Keynes",
    "sg:classifiers":[
        {
            "category":"Education",
            "subcategory":"School",
            "type":"Public Place"
        }
    ],
    "sg:phone":"+44 1908 690100",
    "sg:postcode":"MK15 9JX",
    "sg:province":"Buckinghamshire",
    "sg:tags":[
        "independent",
        "preparatory"
    ],
    "wof:name":"Gyosei International School",
    "wof:placetype":"venue"
},
  "geometry": {"coordinates":[-0.730593,52.06068],"type":"Point"}
}