{
  "type": "Feature",
  "properties": {
    "addr:full":"101 Mount Pleasant Redditch Warwickshire B97 4JE",
    "addr:housenumber":"101",
    "addr:postcode":"b97 4je",
    "addr:street":"Mount Pleasant",
    "iso:country":"GB",
    "sg:address":"101 Mount Pleasant",
    "sg:city":"Redditch",
    "sg:classifiers":[
        {
            "category":"Travel",
            "subcategory":"Hotels & Motels",
            "type":"Entertainment"
        },
        {
            "category":"Restaurant",
            "type":"Food & Drink"
        }
    ],
    "sg:phone":"+44 1527 544411",
    "sg:postcode":"B97 4JE",
    "sg:province":"Warwickshire",
    "wof:name":"Montville Hotel & Restaurant",
    "wof:placetype":"venue"
},
  "geometry": {"coordinates":[-1.94348,52.300468],"type":"Point"}
}