{
  "type": "Feature",
  "properties": {
    "iso:country":"GB",
    "sg:address":"Trevenson Road, Pool",
    "sg:city":"Redruth",
    "sg:classifiers":[
        {
            "category":"Utilities",
            "subcategory":"Natural Gas",
            "type":"Services"
        }
    ],
    "sg:phone":"+44 1209 719151",
    "sg:postcode":"TR15 3PW",
    "sg:province":"Cornwall",
    "sg:tags":[
        "supplier"
    ],
    "wof:name":"Boc Gases",
    "wof:placetype":"venue"
},
  "geometry": {"coordinates":[-5.266689,50.228035],"type":"Point"}
}