{
  "type": "Feature",
  "properties": {
    "addr:full":"Rear Of 16 Northcote Street Stockton-on-tees Durham TS18 3JB",
    "addr:housenumber":"rear of 16",
    "addr:postcode":"ts18 3jb",
    "addr:street":"Northcote Street",
    "iso:country":"GB",
    "sg:address":"Rear Of 16 Northcote Street",
    "sg:city":"Stockton-on-tees",
    "sg:classifiers":[
        {
            "category":"Building & Trades",
            "subcategory":"Construction",
            "type":"Services"
        }
    ],
    "sg:phone":"+44 1642 604561",
    "sg:postcode":"TS18 3JB",
    "sg:province":"Durham",
    "sg:tags":[
        "joiner",
        "carpenter"
    ],
    "wof:name":"D & R Joinery",
    "wof:placetype":"venue"
},
  "geometry": {"coordinates":[-1.3198699951,54.5579414368],"type":"Point"}
}