{
  "type": "Feature",
  "properties": {
    "iso:country":"GB",
    "sg:address":"Vicarage, 57 New House La",
    "sg:city":"Gravesend",
    "sg:classifiers":[
        {
            "category":"Place Of Worship",
            "type":"Public Place"
        }
    ],
    "sg:phone":"+44 1474 352162",
    "sg:postcode":"DA11 7HJ",
    "sg:province":"Kent",
    "wof:name":"St Marys Church",
    "wof:placetype":"venue"
},
  "geometry": {"coordinates":[0.364606,51.432827],"type":"Point"}
}