{
  "type": "Feature",
  "properties": {
    "iso:country":"GB",
    "sg:address":"Rock Avenue",
    "sg:city":"Lynton",
    "sg:classifiers":[
        {
            "category":"Arena",
            "subcategory":"Sports Club",
            "type":"Entertainment"
        }
    ],
    "sg:phone":"+44 1598 753509",
    "sg:postcode":"EX35 6DL",
    "sg:province":"Devon",
    "wof:name":"The Lynton & Lynmouth Bowls Club",
    "wof:placetype":"venue"
},
  "geometry": {"coordinates":[-3.841502,51.228615],"type":"Point"}
}