{
  "type": "Feature",
  "properties": {
    "addr:full":"12 London Rd Staines Berkshire TW18 4BP",
    "addr:housenumber":"12",
    "addr:postcode":"tw18 4bp",
    "addr:street":"London Rd",
    "iso:country":"GB",
    "sg:address":"12 London Rd",
    "sg:city":"Staines",
    "sg:classifiers":[
        {
            "category":"Professional",
            "subcategory":"Printing & Photocopies",
            "type":"Services"
        }
    ],
    "sg:phone":"+44 1784 456176",
    "sg:postcode":"TW18 4BP",
    "sg:province":"Berkshire",
    "sg:tags":[
        "duplicating",
        "copying"
    ],
    "wof:name":"Used Office Machine Co",
    "wof:placetype":"venue"
},
  "geometry": {"coordinates":[-0.505351007,51.4352798462],"type":"Point"}
}