{
  "type": "Feature",
  "properties": {
    "addr:full":"107 Bromley Road Colchester Essex CO4 3JG",
    "addr:housenumber":"107",
    "addr:postcode":"co4 3jg",
    "addr:street":"Bromley Road Colchester",
    "iso:country":"GB",
    "sg:address":"107 Bromley Road",
    "sg:city":"Colchester",
    "sg:classifiers":[
        {
            "category":"Building & Trades",
            "subcategory":"Landscaping Services",
            "type":"Services"
        }
    ],
    "sg:phone":"+44 1206 799000",
    "sg:postcode":"CO4 3JG",
    "sg:province":"Essex",
    "sg:tags":[
        "contractor"
    ],
    "wof:name":"The Garden by Design Ltd.",
    "wof:placetype":"venue"
},
  "geometry": {"coordinates":[0.948083,51.897007],"type":"Point"}
}