{
  "type": "Feature",
  "properties": {
    "addr:full":"23 Finkle Street, Thorne Doncaster East Riding of Yorkshire DN8 5DE",
    "addr:housenumber":"23",
    "addr:postcode":"dn8 5de",
    "addr:street":"Finkle Street;Riding",
    "iso:country":"GB",
    "sg:address":"23 Finkle Street, Thorne",
    "sg:city":"Doncaster",
    "sg:classifiers":[
        {
            "category":"Health Services",
            "subcategory":"Optometrist",
            "type":"Services"
        }
    ],
    "sg:phone":"+44 1405 812209",
    "sg:postcode":"DN8 5DE",
    "sg:province":"East Riding of Yorkshire",
    "sg:tags":[
        "optician"
    ],
    "wof:name":"Bell Brothers (Opticians) Ltd.",
    "wof:placetype":"venue"
},
  "geometry": {"coordinates":[-0.962111,53.61105],"type":"Point"}
}