{
  "type": "Feature",
  "properties": {
    "iso:country":"GB",
    "sg:address":"20-24 Chatley Street",
    "sg:city":"Manchester",
    "sg:classifiers":[
        {
            "category":"Wholesale",
            "subcategory":"Non-durable Goods",
            "type":"Manufacturing & Wholesale Goods"
        }
    ],
    "sg:phone":"+44 161 832 9682",
    "sg:postcode":"M3 1HX",
    "sg:province":"Greater Manchester",
    "sg:tags":[
        "carry",
        "wholesaler",
        "cash"
    ],
    "wof:name":"Ashraf & Sons Ltd.",
    "wof:placetype":"venue"
},
  "geometry": {"coordinates":[-2.241859,53.49268],"type":"Point"}
}