{
  "type": "Feature",
  "properties": {
    "iso:country":"GB",
    "sg:address":"Tipton College, Alexandra Road",
    "sg:city":"Tipton",
    "sg:classifiers":[
        {
            "category":"Education",
            "subcategory":"Special Training",
            "type":"Public Place"
        }
    ],
    "sg:postcode":"DY4 8TQ",
    "sg:province":"West Midlands",
    "sg:tags":[
        "product",
        "centre"
    ],
    "wof:name":"K C T",
    "wof:placetype":"venue"
},
  "geometry": {"coordinates":[-2.070697,52.528137],"type":"Point"}
}