{
  "type": "Feature",
  "properties": {
    "iso:country":"GB",
    "sg:address":"235-237 Finchley Road",
    "sg:city":"London",
    "sg:classifiers":[
        {
            "category":"Real Estate",
            "subcategory":"Real Estate Agent",
            "type":"Services"
        }
    ],
    "sg:phone":"+44 20 7435 7988",
    "sg:postcode":"NW3 6LS",
    "sg:province":"Greater London",
    "wof:name":"Allman Field & Co Estate Agents",
    "wof:placetype":"venue"
},
  "geometry": {"coordinates":[-0.180161,51.547318],"type":"Point"}
}