{
  "type": "Feature",
  "properties": {
    "addr:full":"Winton House Windsor Berkshire SL4 5AZ",
    "addr:postcode":"sl4 5az",
    "iso:country":"GB",
    "sg:address":"Winton House",
    "sg:city":"Windsor",
    "sg:classifiers":[
        {
            "category":"Organizations",
            "subcategory":"Community Association",
            "type":"Services"
        }
    ],
    "sg:phone":"+44 1753 856466",
    "sg:postcode":"SL4 5AZ",
    "sg:province":"Berkshire",
    "sg:tags":[
        "society",
        "housing"
    ],
    "wof:name":"The Abbeyfield (Maidenhead) Society Ltd.",
    "wof:placetype":"venue"
},
  "geometry": {"coordinates":[-0.655723989,51.4839935303],"type":"Point"}
}