{
  "type": "Feature",
  "properties": {
    "iso:country":"GB",
    "sg:address":"Queens Street",
    "sg:city":"Burnley",
    "sg:classifiers":[
        {
            "category":"Shopping",
            "subcategory":"Bicycles & Sporting Goods",
            "type":"Retail Goods"
        }
    ],
    "sg:phone":"+44 1282 438855",
    "sg:postcode":"BB11 1AT",
    "sg:province":"Lancashire",
    "sg:tags":[
        "shop",
        "cycle",
        "accessory"
    ],
    "wof:name":"On Yer Bike Cycles",
    "wof:placetype":"venue"
},
  "geometry": {"coordinates":[-2.2438089848,53.7880096436],"type":"Point"}
}