{
  "type": "Feature",
  "properties": {
    "iso:country":"GB",
    "sg:address":"18 Davenham Road",
    "sg:city":"Liverpool",
    "sg:classifiers":[
        {
            "category":"Building & Trades",
            "subcategory":"Construction",
            "type":"Services"
        }
    ],
    "sg:postcode":"L37 3NS",
    "sg:province":"Lancashire",
    "sg:tags":[
        "dry",
        "lining",
        "plasterers",
        "screeders"
    ],
    "wof:name":"W M Plastering & Property Maintenance",
    "wof:placetype":"venue"
},
  "geometry": {"coordinates":[-3.0583820343,53.5589027405],"type":"Point"}
}