{
  "type": "Feature",
  "properties": {
    "addr:full":"67 Cathcart Street Greenock Inverclyde PA15 1DE",
    "addr:housenumber":"67",
    "addr:postcode":"pa15 1de",
    "addr:street":"Cathcart Street Greenock",
    "iso:country":"GB",
    "sg:address":"67 Cathcart Street",
    "sg:city":"Greenock",
    "sg:classifiers":[
        {
            "category":"Shopping",
            "subcategory":"Crafts & Fabrics",
            "type":"Retail Goods"
        }
    ],
    "sg:phone":"+44 1475 726148",
    "sg:postcode":"PA15 1DE",
    "sg:province":"Inverclyde",
    "sg:tags":[
        "shop",
        "retailer"
    ],
    "wof:name":"Material Things",
    "wof:placetype":"venue"
},
  "geometry": {"coordinates":[-4.753057003,55.9466056824],"type":"Point"}
}