{
  "type": "Feature",
  "properties": {
    "addr:full":"Suite 5 The Office Bliock, The Common Cranleigh Surrey GU6 8RZ",
    "addr:housenumber":"suite 5 the office bliock",
    "addr:postcode":"gu6 8rz",
    "addr:street":"The Common",
    "iso:country":"GB",
    "sg:address":"Suite 5 The Office Bliock, The Common",
    "sg:city":"Cranleigh",
    "sg:classifiers":[
        {
            "category":"Professional",
            "subcategory":"Accounting & Tax Preparation",
            "type":"Services"
        }
    ],
    "sg:postcode":"GU6 8RZ",
    "sg:province":"Surrey",
    "sg:tags":[
        "accountant"
    ],
    "wof:name":"Bookline Management Ltd.",
    "wof:placetype":"venue"
},
  "geometry": {"coordinates":[-0.5160350204,51.1364707947],"type":"Point"}
}