{
  "type": "Feature",
  "properties": {
    "addr:full":"Unit 89, Laurence Leyland Complex, Irthlingborough Rd Wellingborough Northamptonshire NN8 1RT",
    "addr:housenumber":"unit 89",
    "addr:postcode":"nn8 1rt",
    "addr:street":"Laurence Leyland;Irthlingborough Rd",
    "iso:country":"GB",
    "sg:address":"Unit 89, Laurence Leyland Complex, Irthlingborough Rd",
    "sg:city":"Wellingborough",
    "sg:classifiers":[
        {
            "category":"Government",
            "subcategory":"Post Office",
            "type":"Public Place"
        }
    ],
    "sg:phone":"+44 1933 274107",
    "sg:postcode":"NN8 1RT",
    "sg:province":"Northamptonshire",
    "sg:tags":[
        "messenger",
        "courier"
    ],
    "wof:name":"Park Express Couriers",
    "wof:placetype":"venue"
},
  "geometry": {"coordinates":[-0.6962959766,52.3024215698],"type":"Point"}
}