{
  "type": "Feature",
  "properties": {
    "addr:full":"Unit 16 Hurlbutt Road, Heathcote Industrial Estate Warwick Warwickshire CV34 6TD",
    "addr:housenumber":"unit 16",
    "addr:postcode":"cv34 6td",
    "addr:street":"Hurlbutt Road;Industrial Estate",
    "iso:country":"GB",
    "sg:address":"Unit 16 Hurlbutt Road, Heathcote Industrial Estate",
    "sg:city":"Warwick",
    "sg:classifiers":[
        {
            "category":"Park",
            "subcategory":"Town Common",
            "type":"Public Place"
        }
    ],
    "sg:postcode":"CV34 6TD",
    "sg:province":"Warwickshire",
    "sg:tags":[
        "funfair"
    ],
    "wof:name":"Amusement Park Spares Ltd.",
    "wof:placetype":"venue"
},
  "geometry": {"coordinates":[-1.555054,52.271648],"type":"Point"}
}