{
  "type": "Feature",
  "properties": {
    "iso:country":"GB",
    "sg:address":"Studio 23 86-96 Garratt Lane",
    "sg:city":"London",
    "sg:classifiers":[
        {
            "category":"Shopping",
            "subcategory":"Antiques",
            "type":"Retail Goods"
        }
    ],
    "sg:phone":"+44 20 8870 8060",
    "sg:postcode":"SW18 4DJ",
    "sg:province":"Greater London",
    "wof:name":"Dominic Schuster Gilding & Restoration",
    "wof:placetype":"venue"
},
  "geometry": {"coordinates":[-0.19092,51.452389],"type":"Point"}
}