{
  "type": "Feature",
  "properties": {
    "addr:full":"14-16 Market St Lewes East Sussex BN7 2NB",
    "addr:housenumber":"14-16",
    "addr:postcode":"bn7 2nb",
    "addr:street":"Market St",
    "iso:country":"GB",
    "sg:address":"14-16 Market St",
    "sg:city":"Lewes",
    "sg:classifiers":[
        {
            "category":"Professional",
            "type":"Services"
        }
    ],
    "sg:postcode":"BN7 2NB",
    "sg:province":"East Sussex",
    "sg:tags":[
        "directory",
        "pub"
    ],
    "wof:name":"Market Printers",
    "wof:placetype":"venue"
},
  "geometry": {"coordinates":[0.0113810003,50.8742828369],"type":"Point"}
}