{
  "type": "Feature",
  "properties": {
    "addr:full":"Fort Pitt Hill Chatham Kent ME4 6TJ",
    "addr:postcode":"me4 6tj",
    "addr:street":"Pitt Hill",
    "iso:country":"GB",
    "sg:address":"Fort Pitt Hill",
    "sg:city":"Chatham",
    "sg:classifiers":[
        {
            "category":"Education",
            "subcategory":"School",
            "type":"Public Place"
        },
        {
            "category":"Government",
            "subcategory":"Office",
            "type":"Public Place"
        }
    ],
    "sg:phone":"+44 1634 842359",
    "sg:postcode":"ME4 6TJ",
    "sg:province":"Kent",
    "sg:tags":[
        "local",
        "authority"
    ],
    "wof:name":"Fort Pitt Grammar School For Girls",
    "wof:placetype":"venue"
},
  "geometry": {"coordinates":[0.5180799961,51.3807868958],"type":"Point"}
}