{
  "type": "Feature",
  "properties": {
    "addr:full":"1 Church Sq, Lenton Nottingham Nottinghamshire NG7 1SL",
    "addr:housenumber":"1",
    "addr:postcode":"ng7 1sl",
    "addr:street":"Church Sq",
    "iso:country":"GB",
    "sg:address":"1 Church Sq, Lenton",
    "sg:city":"Nottingham",
    "sg:classifiers":[
        {
            "category":"Shopping",
            "subcategory":"News",
            "type":"Retail Goods"
        }
    ],
    "sg:postcode":"NG7 1SL",
    "sg:province":"Nottinghamshire",
    "sg:tags":[
        "newsagent"
    ],
    "wof:name":"Roper,Keith,",
    "wof:placetype":"venue"
},
  "geometry": {"coordinates":[-1.1716840267,52.9489555359],"type":"Point"}
}