{
  "type": "Feature",
  "properties": {
    "addr:full":"202 High Road Leytonstone London Greater London E11 3HU",
    "addr:housenumber":"202",
    "addr:postcode":"e11 3hu",
    "addr:street":"High Road",
    "iso:country":"GB",
    "sg:address":"202 High Road Leytonstone",
    "sg:city":"London",
    "sg:classifiers":[
        {
            "category":"Fast Food",
            "type":"Food & Drink"
        },
        {
            "category":"Restaurant",
            "type":"Food & Drink"
        }
    ],
    "sg:phone":"+44 20 8534 2825",
    "sg:postcode":"E11 3HU",
    "sg:province":"Greater London",
    "sg:tags":[
        "away",
        "take"
    ],
    "wof:name":"Lee Kwai Yau Restaurant",
    "wof:placetype":"venue"
},
  "geometry": {"coordinates":[0.00532,51.5534896851],"type":"Point"}
}