{
  "type": "Feature",
  "properties": {
    "iso:country":"GB",
    "sg:address":"77 Silverdale Road, Beverley High Road",
    "sg:city":"Hull",
    "sg:classifiers":[
        {
            "category":"Travel",
            "subcategory":"Travel Agent",
            "type":"Entertainment"
        }
    ],
    "sg:postcode":"HU6 7HF",
    "sg:province":"East Riding of Yorkshire",
    "wof:name":"Citytravels Ltd.",
    "wof:placetype":"venue"
},
  "geometry": {"coordinates":[-0.351625,53.779766],"type":"Point"}
}