{
  "type": "Feature",
  "properties": {
    "iso:country":"GB",
    "sg:address":"The Siston Centre, Station Rd",
    "sg:city":"Bristol",
    "sg:classifiers":[
        {
            "category":"Professional",
            "subcategory":"Detective & Security Services",
            "type":"Services"
        }
    ],
    "sg:phone":"+44 117 918 1000",
    "sg:postcode":"BS15 4GQ",
    "sg:province":"City of Bristol",
    "sg:tags":[
        "equipment"
    ],
    "wof:name":"Alfia Services Ltd",
    "wof:placetype":"venue"
},
  "geometry": {"coordinates":[-2.591429,51.453667],"type":"Point"}
}