{
  "type": "Feature",
  "properties": {
    "iso:country":"GB",
    "sg:address":"5 Mansel Street",
    "sg:city":"Swansea",
    "sg:classifiers":[
        {
            "category":"Banks & Credit Unions",
            "subcategory":"Bank",
            "type":"Services"
        }
    ],
    "sg:phone":"+44 1792 466311",
    "sg:postcode":"SA1 5SF",
    "sg:province":"Neath Port Talbot",
    "sg:tags":[
        "broker",
        "mortgage"
    ],
    "wof:name":"The Mortgage Helpline",
    "wof:placetype":"venue"
},
  "geometry": {"coordinates":[-3.9479620457,51.6210289001],"type":"Point"}
}