{
  "type": "Feature",
  "properties": {
    "iso:country":"GB",
    "sg:address":"Lutomer House Business Centre, 100 Prestons Road",
    "sg:city":"London",
    "sg:classifiers":[
        {
            "category":"Education",
            "subcategory":"Special Training",
            "type":"Public Place"
        },
        {
            "category":"Shopping",
            "subcategory":"Pharmacy",
            "type":"Retail Goods"
        }
    ],
    "sg:phone":"+44 20 7987 1227",
    "sg:postcode":"E14 9SB",
    "sg:province":"Greater London",
    "sg:tags":[
        "aid",
        "medical",
        "first"
    ],
    "wof:name":"Simpson Training Service",
    "wof:placetype":"venue"
},
  "geometry": {"coordinates":[-0.01161,51.502789],"type":"Point"}
}