{
  "type": "Feature",
  "properties": {
    "iso:country":"GB",
    "sg:address":"19 Bedford Avenue",
    "sg:city":"Amersham",
    "sg:classifiers":[
        {
            "category":"Professional",
            "subcategory":"Management & Consulting",
            "type":"Services"
        }
    ],
    "sg:phone":"+44 1494 766144",
    "sg:postcode":"HP6 6PT",
    "sg:province":"Buckinghamshire",
    "sg:tags":[
        "marketing",
        "consultant"
    ],
    "wof:name":"A M C O",
    "wof:placetype":"venue"
},
  "geometry": {"coordinates":[-0.561968,51.668945],"type":"Point"}
}