{
  "type": "Feature",
  "properties": {
    "iso:country":"GB",
    "sg:address":"St Stephens Church Hall, 37 Waterloo Road",
    "sg:city":"Tonbridge",
    "sg:classifiers":[
        {
            "category":"Education",
            "subcategory":"Preschool",
            "type":"Public Place"
        }
    ],
    "sg:phone":"+44 1732 363642",
    "sg:postcode":"TN9 2SW",
    "sg:province":"Kent",
    "sg:tags":[
        "pre-school",
        "playgroups"
    ],
    "wof:name":"St.Stephens Preschool Playgroup",
    "wof:placetype":"venue"
},
  "geometry": {"coordinates":[0.27634,51.199829],"type":"Point"}
}