{
  "type": "Feature",
  "properties": {
    "iso:country":"GB",
    "sg:address":"30 York Avenue",
    "sg:city":"Hunstanton",
    "sg:classifiers":[
        {
            "category":"Education",
            "subcategory":"School",
            "type":"Public Place"
        }
    ],
    "sg:phone":"+44 1485 534845",
    "sg:postcode":"PE36 6BU",
    "sg:province":"Norfolk",
    "sg:tags":[
        "private",
        "tuition"
    ],
    "wof:name":"Max Dolby",
    "wof:placetype":"venue"
},
  "geometry": {"coordinates":[0.4936760068,52.9434814453],"type":"Point"}
}