{
  "type": "Feature",
  "properties": {
    "addr:full":"Unit 13-15, Honeyborough Industrial Estate, Neyland Milford Haven Pembrokeshire SA73 1SE",
    "addr:housenumber":"unit 13-15",
    "addr:postcode":"sa73 1se",
    "addr:street":"Honeyborough Industrial Estate",
    "iso:country":"GB",
    "sg:address":"Unit 13-15, Honeyborough Industrial Estate, Neyland",
    "sg:city":"Milford Haven",
    "sg:classifiers":[
        {
            "category":"Manufacturing",
            "subcategory":"Wood Products",
            "type":"Manufacturing & Wholesale Goods"
        },
        {
            "category":"Home & Garden",
            "subcategory":"Home Furnishings",
            "type":"Retail Goods"
        }
    ],
    "sg:phone":"+44 1646 602324",
    "sg:postcode":"SA73 1SE",
    "sg:province":"Pembrokeshire",
    "sg:tags":[
        "joinery",
        "manufacturer",
        "planner",
        "kitchen",
        "furnishers"
    ],
    "wof:name":"Howdens Joinery",
    "wof:placetype":"venue"
},
  "geometry": {"coordinates":[-5.027044,51.716808],"type":"Point"}
}