{
  "type": "Feature",
  "properties": {
    "addr:full":"5 Bourne Mill Industrial Estate, Guildford Rd Farnham Surrey GU9 9PS",
    "addr:housenumber":"5",
    "addr:postcode":"gu9 9ps",
    "addr:street":"Bourne Mill Industrial Estate Guildford Rd",
    "iso:country":"GB",
    "sg:address":"5 Bourne Mill Industrial Estate, Guildford Rd",
    "sg:city":"Farnham",
    "sg:classifiers":[
        {
            "category":"Professional",
            "subcategory":"Printing & Photocopies",
            "type":"Services"
        }
    ],
    "sg:phone":"+44 1252 737222",
    "sg:postcode":"GU9 9PS",
    "sg:province":"Surrey",
    "sg:tags":[
        "printer"
    ],
    "wof:name":"A3 Litho Ltd",
    "wof:placetype":"venue"
},
  "geometry": {"coordinates":[-0.8008369803,51.2143211365],"type":"Point"}
}