{
  "type": "Feature",
  "properties": {
    "iso:country":"GB",
    "sg:address":"155 Highgate",
    "sg:city":"Kendal",
    "sg:classifiers":[
        {
            "category":"Travel",
            "subcategory":"Hotels & Motels",
            "type":"Entertainment"
        }
    ],
    "sg:phone":"+44 1539 724023",
    "sg:postcode":"LA9 4EN",
    "sg:province":"Cumbria",
    "wof:name":"Kendal Bowman Hotel",
    "wof:placetype":"venue"
},
  "geometry": {"coordinates":[-2.747078,54.323978],"type":"Point"}
}