{
  "type": "Feature",
  "properties": {
    "iso:country":"GB",
    "sg:address":"C, O 15 Conisborough, Berkeley",
    "sg:city":"Worcester",
    "sg:classifiers":[
        {
            "category":"Education",
            "subcategory":"Dance Studio",
            "type":"Public Place"
        }
    ],
    "sg:phone":"+44 1905 23164",
    "sg:postcode":"WR4 0DH",
    "sg:province":"Worcestershire",
    "sg:tags":[
        "ballet",
        "school"
    ],
    "wof:name":"Crescents Ballet School",
    "wof:placetype":"venue"
},
  "geometry": {"coordinates":[-2.17329,52.210312],"type":"Point"}
}