{
  "type": "Feature",
  "properties": {
    "addr:full":"High St Rhymney Blaenau Gwent NP2 5LP",
    "addr:postcode":"np2 5lp",
    "addr:street":"High St",
    "iso:country":"GB",
    "sg:address":"High St",
    "sg:city":"Rhymney",
    "sg:classifiers":[
        {
            "category":"Social Services",
            "subcategory":"Adult Care",
            "type":"Services"
        }
    ],
    "sg:phone":"+44 1685 840905",
    "sg:postcode":"NP2 5LP",
    "sg:province":"Blaenau Gwent",
    "sg:tags":[
        "day",
        "centre"
    ],
    "wof:name":"Hafod Deg Day Centre",
    "wof:placetype":"venue"
},
  "geometry": {"coordinates":[-3.286039114,51.7609100342],"type":"Point"}
}