{
  "type": "Feature",
  "properties": {
    "iso:country":"GB",
    "sg:address":"Unit 4 Station Yard Business Park",
    "sg:city":"Teignmouth",
    "sg:classifiers":[
        {
            "category":"Home & Garden",
            "subcategory":"Hardware",
            "type":"Retail Goods"
        }
    ],
    "sg:postcode":"TQ14 8QJ",
    "sg:province":"Devon",
    "sg:tags":[
        "paint"
    ],
    "wof:name":"Westcountry Finishes Ltd.",
    "wof:placetype":"venue"
},
  "geometry": {"coordinates":[-3.4950149059,50.5489425659],"type":"Point"}
}