{
  "type": "Feature",
  "properties": {
    "iso:country":"GB",
    "sg:address":"2 Church Lane, Bulphan",
    "sg:city":"Upminster",
    "sg:classifiers":[
        {
            "category":"Building & Trades",
            "subcategory":"Construction",
            "type":"Services"
        }
    ],
    "sg:postcode":"RM14 3TU",
    "sg:province":"Essex",
    "sg:tags":[
        "dry",
        "lining",
        "plasterers",
        "screeders"
    ],
    "wof:name":"M G Flooring Contractors",
    "wof:placetype":"venue"
},
  "geometry": {"coordinates":[0.359977,51.547379],"type":"Point"}
}