{
  "type": "Feature",
  "properties": {
    "iso:country":"GB",
    "sg:address":"Rockbridge Park",
    "sg:city":"Presteigne",
    "sg:classifiers":[
        {
            "category":"Recreation",
            "subcategory":"Campground",
            "type":"Entertainment"
        }
    ],
    "sg:phone":"+44 1547 560300",
    "sg:postcode":"LD8 2NF",
    "sg:province":"Herefordshire",
    "sg:tags":[
        "site",
        "camping"
    ],
    "wof:name":"R M & L G  Deakins",
    "wof:placetype":"venue"
},
  "geometry": {"coordinates":[-3.0044538975,52.2702064514],"type":"Point"}
}