{
  "type": "Feature",
  "properties": {
    "iso:country":"GB",
    "sg:address":"River Park Avenue",
    "sg:city":"Staines",
    "sg:classifiers":[
        {
            "category":"Manufacturing",
            "subcategory":"Apparel",
            "type":"Manufacturing & Wholesale Goods"
        }
    ],
    "sg:phone":"+44 1784 496000",
    "sg:postcode":"TW18 3EN",
    "sg:province":"Berkshire",
    "sg:tags":[
        "mnfr",
        "footwear"
    ],
    "wof:name":"Timberland (U K) Ltd.",
    "wof:placetype":"venue"
},
  "geometry": {"coordinates":[-0.523164,51.434368],"type":"Point"}
}