{
  "type": "Feature",
  "properties": {
    "iso:country":"GB",
    "sg:address":"82 Pinner Road",
    "sg:city":"Watford",
    "sg:classifiers":[
        {
            "category":"Social Services",
            "subcategory":"Retirement Home",
            "type":"Services"
        }
    ],
    "sg:phone":"+44 1923 245466",
    "sg:postcode":"WD19 4EH",
    "sg:province":"Hertfordshire",
    "sg:tags":[
        "residential",
        "care"
    ],
    "wof:name":"Watford Mencap Hillside Residential Home",
    "wof:placetype":"venue"
},
  "geometry": {"coordinates":[-0.383083,51.643505],"type":"Point"}
}