{
  "type": "Feature",
  "properties": {
    "addr:full":"Eden Nurseries, Spikes Lane Off (a14) Stowmarket Suffolk IP14 3QD",
    "addr:housenumber":"a14",
    "addr:postcode":"ip14 3qd",
    "addr:street":"Spikes Lane Off",
    "iso:country":"GB",
    "sg:address":"Eden Nurseries, Spikes Lane Off (a14)",
    "sg:city":"Stowmarket",
    "sg:classifiers":[
        {
            "category":"Home & Garden",
            "subcategory":"Garden Supply",
            "type":"Retail Goods"
        }
    ],
    "sg:phone":"+44 1449 612559",
    "sg:postcode":"IP14 3QD",
    "sg:province":"Suffolk",
    "sg:tags":[
        "nursery",
        "centre"
    ],
    "wof:name":"J NAREY & SONS",
    "wof:placetype":"venue"
},
  "geometry": {"coordinates":[0.996769011,52.1886253357],"type":"Point"}
}