{
  "type": "Feature",
  "properties": {
    "addr:full":"262 West Green Road London Greater London N15 3QR",
    "addr:housenumber":"262",
    "addr:postcode":"n15 3qr",
    "addr:street":"West Green Road",
    "iso:country":"GB",
    "sg:address":"262 West Green Road",
    "sg:city":"London",
    "sg:classifiers":[
        {
            "category":"Fast Food",
            "type":"Food & Drink"
        }
    ],
    "sg:phone":"+44 20 8888 3311",
    "sg:postcode":"N15 3QR",
    "sg:province":"Greater London",
    "sg:tags":[
        "away",
        "take"
    ],
    "wof:name":"Champion Kebab",
    "wof:placetype":"venue"
},
  "geometry": {"coordinates":[-0.089534,51.586456],"type":"Point"}
}