{
  "type": "Feature",
  "properties": {
    "addr:full":"C/o Suite Centre, Unit 2 Aldermoor Way, Longwell Grn Bristol Gloucestershire BS30 7DA",
    "addr:housenumber":"/ o suite centre unit 2",
    "addr:postcode":"bs30 7da",
    "addr:street":"C;Aldermoor Way Longwell Grn",
    "iso:country":"GB",
    "sg:address":"C/o Suite Centre, Unit 2 Aldermoor Way, Longwell Grn",
    "sg:city":"Bristol",
    "sg:classifiers":[
        {
            "category":"Home & Garden",
            "subcategory":"Home Furnishings",
            "type":"Retail Goods"
        }
    ],
    "sg:phone":"+44 117 947 7659",
    "sg:postcode":"BS30 7DA",
    "sg:province":"Gloucestershire",
    "sg:tags":[
        "beds",
        "bedding",
        "blanket"
    ],
    "wof:name":"Bensons Bed Centres Ltd.",
    "wof:placetype":"venue"
},
  "geometry": {"coordinates":[-2.49809,51.445099],"type":"Point"}
}