{
  "type": "Feature",
  "properties": {
    "iso:country":"GB",
    "sg:address":"Unit 6, Whitfield & Brown Business Centre",
    "sg:city":"Widnes",
    "sg:classifiers":[
        {
            "category":"Home & Garden",
            "subcategory":"Hardware",
            "type":"Retail Goods"
        }
    ],
    "sg:phone":"+44 151 420 5050",
    "sg:postcode":"WA8 0RA",
    "sg:province":"Cheshire",
    "sg:tags":[
        "heat",
        "mech",
        "exchanger"
    ],
    "wof:name":"D R S Heat Transfer",
    "wof:placetype":"venue"
},
  "geometry": {"coordinates":[-2.73509,53.353901],"type":"Point"}
}