{
  "type": "Feature",
  "properties": {
    "iso:country":"GB",
    "sg:address":"Jubilee House, 113 Laughton Road, Dinnington",
    "sg:city":"Sheffield",
    "sg:classifiers":[
        {
            "category":"Wholesale",
            "subcategory":"Construction Materials",
            "type":"Manufacturing & Wholesale Goods"
        }
    ],
    "sg:phone":"+44 1909 568335",
    "sg:postcode":"S25 2PP",
    "sg:province":"South Yorkshire",
    "sg:tags":[
        "refractory"
    ],
    "wof:name":"Sheffield Refractories Ltd.",
    "wof:placetype":"venue"
},
  "geometry": {"coordinates":[-1.209074,53.370575],"type":"Point"}
}