{
  "type": "Feature",
  "properties": {
    "iso:country":"GB",
    "sg:address":"306 Kilburn High Road",
    "sg:city":"London",
    "sg:classifiers":[
        {
            "category":"Autos & Motor Vehicles",
            "subcategory":"Auto Supplies",
            "type":"Retail Goods"
        }
    ],
    "sg:phone":"+44 20 7624 8082",
    "sg:postcode":"NW6 2DB",
    "sg:province":"Greater London",
    "sg:tags":[
        "religious",
        "furnishing"
    ],
    "wof:name":"Lady Fatima",
    "wof:placetype":"venue"
},
  "geometry": {"coordinates":[-0.200148,51.543808],"type":"Point"}
}