{
  "type": "Feature",
  "properties": {
    "addr:full":"154 The Street Littlehampton West Sussex BN16 3TF",
    "addr:housenumber":"154",
    "addr:postcode":"bn16 3tf",
    "addr:street":"The Street",
    "iso:country":"GB",
    "sg:address":"154 The Street",
    "sg:city":"Littlehampton",
    "sg:classifiers":[
        {
            "category":"Banks & Credit Unions",
            "subcategory":"Bank",
            "type":"Services"
        }
    ],
    "sg:phone":"+44 1903 693123",
    "sg:postcode":"BN16 3TF",
    "sg:province":"West Sussex",
    "wof:name":"NatWest",
    "wof:placetype":"venue"
},
  "geometry": {"coordinates":[-0.5055050254,50.8103981018],"type":"Point"}
}