{
  "type": "Feature",
  "properties": {
    "iso:country":"GB",
    "sg:address":"19 Layer Rd",
    "sg:city":"Colchester",
    "sg:classifiers":[
        {
            "category":"Health Services",
            "subcategory":"Health Practitioner",
            "type":"Services"
        }
    ],
    "sg:phone":"+44 1206 542580",
    "sg:postcode":"CO2 7HT",
    "sg:province":"Essex",
    "sg:tags":[
        "physiotherapist"
    ],
    "wof:name":"A M Hunt",
    "wof:placetype":"venue"
},
  "geometry": {"coordinates":[0.884951,51.878654],"type":"Point"}
}