{
  "type": "Feature",
  "properties": {
    "addr:full":"262 Union Street Aberdeen Aberdeen City AB10 1TP",
    "addr:housenumber":"262",
    "addr:postcode":"ab10 1tp",
    "addr:street":"Union Street",
    "iso:country":"GB",
    "sg:address":"262 Union Street",
    "sg:city":"Aberdeen",
    "sg:classifiers":[
        {
            "category":"Banks & Credit Unions",
            "subcategory":"Bank",
            "type":"Services"
        }
    ],
    "sg:phone":"+44 20 7726 1000",
    "sg:postcode":"AB10 1TP",
    "sg:province":"Aberdeen City",
    "wof:name":"National Westminster Bank Plc",
    "wof:placetype":"venue"
},
  "geometry": {"coordinates":[-2.108693,57.143955],"type":"Point"}
}