{
  "type": "Feature",
  "properties": {
    "addr:full":"19-21 Wellgate Clitheroe Lancashire BB7 2DP",
    "addr:housenumber":"19-21",
    "addr:postcode":"bb7 2dp",
    "addr:street":"Wellgate Clitheroe",
    "iso:country":"GB",
    "sg:address":"19-21 Wellgate",
    "sg:city":"Clitheroe",
    "sg:classifiers":[
        {
            "category":"Restaurant",
            "type":"Food & Drink"
        }
    ],
    "sg:phone":"+44 1200 424544",
    "sg:postcode":"BB7 2DP",
    "sg:province":"Lancashire",
    "sg:tags":[
        "-",
        "oriental",
        "chinese"
    ],
    "wof:name":"The Clover Restaurant",
    "wof:placetype":"venue"
},
  "geometry": {"coordinates":[-2.39018,53.87291],"type":"Point"}
}