{
  "type": "Feature",
  "properties": {
    "addr:full":"12 Church Street Atherstone Leicestershire CV9 1RN",
    "addr:housenumber":"12",
    "addr:postcode":"cv9 1rn",
    "addr:street":"Church Street",
    "iso:country":"GB",
    "sg:address":"12 Church Street",
    "sg:city":"Atherstone",
    "sg:classifiers":[
        {
            "category":"Real Estate",
            "subcategory":"Real Estate Agent",
            "type":"Services"
        }
    ],
    "sg:phone":"+44 1827 718021",
    "sg:postcode":"CV9 1RN",
    "sg:province":"Leicestershire",
    "sg:website":"http://www.howkinsandharrison.co.uk",
    "wof:name":"Howkins & Harrison",
    "wof:placetype":"venue"
},
  "geometry": {"coordinates":[-1.547253,52.577728],"type":"Point"}
}