{
  "type": "Feature",
  "properties": {
    "iso:country":"GB",
    "sg:address":"Greens Farm, Norwood End",
    "sg:city":"Ongar",
    "sg:classifiers":[
        {
            "category":"Farming",
            "subcategory":"Farm",
            "type":"Manufacturing & Wholesale Goods"
        }
    ],
    "sg:phone":"+44 1277 899241",
    "sg:postcode":"CM5 0RL",
    "sg:province":"Essex",
    "sg:tags":[
        "mixed",
        "crop"
    ],
    "wof:name":"T W East",
    "wof:placetype":"venue"
},
  "geometry": {"coordinates":[0.24517,51.706131],"type":"Point"}
}