{
  "type": "Feature",
  "properties": {
    "iso:country":"GB",
    "sg:address":"Unit 1 Elizabeth House Bradley Street",
    "sg:city":"Castleford",
    "sg:classifiers":[
        {
            "category":"Home & Garden",
            "subcategory":"Home Furnishings",
            "type":"Retail Goods"
        }
    ],
    "sg:phone":"+44 1977 552200",
    "sg:postcode":"WF10 1HR",
    "sg:province":"West Yorkshire",
    "sg:tags":[
        "furnishers",
        "planner",
        "kitchen"
    ],
    "wof:name":"Heritage (Kitchens & Bedrooms) Ltd.",
    "wof:placetype":"venue"
},
  "geometry": {"coordinates":[-1.3532990217,53.7267112732],"type":"Point"}
}