{
  "type": "Feature",
  "properties": {
    "iso:country":"GB",
    "sg:address":"28 Front Street, Chirton",
    "sg:city":"North Shields",
    "sg:classifiers":[
        {
            "category":"Government",
            "subcategory":"Post Office",
            "type":"Public Place"
        }
    ],
    "sg:phone":"+44 191 257 5249",
    "sg:postcode":"NE29 7QW",
    "sg:province":"Tyne and Wear",
    "wof:name":"Chirton Post Office",
    "wof:placetype":"venue"
},
  "geometry": {"coordinates":[-1.463183,55.007877],"type":"Point"}
}