{
  "type": "Feature",
  "properties": {
    "addr:full":"Stephenson Road, Speedwell Industrial Estate, Staveley Chesterfield Derbyshire S43 3JN",
    "addr:postcode":"s43 3jn",
    "addr:street":"Stephenson Road;Industrial Estate",
    "iso:country":"GB",
    "sg:address":"Stephenson Road, Speedwell Industrial Estate, Staveley",
    "sg:city":"Chesterfield",
    "sg:classifiers":[
        {
            "category":"Wholesale",
            "subcategory":"Office Equipment",
            "type":"Manufacturing & Wholesale Goods"
        },
        {
            "category":"Building & Trades",
            "subcategory":"Cleaning & Sanitation",
            "type":"Services"
        }
    ],
    "sg:phone":"+44 1246 471147",
    "sg:postcode":"S43 3JN",
    "sg:province":"Derbyshire",
    "sg:tags":[
        "commercial"
    ],
    "wof:name":"Morclean",
    "wof:placetype":"venue"
},
  "geometry": {"coordinates":[-1.350919,53.264126],"type":"Point"}
}