{
  "type": "Feature",
  "properties": {
    "iso:country":"GB",
    "sg:address":"Dental Surgery, 268a Old Kent Rd",
    "sg:city":"Southwark",
    "sg:classifiers":[
        {
            "category":"Health Services",
            "subcategory":"Dentist",
            "type":"Services"
        }
    ],
    "sg:phone":"+44 20 7703 3697",
    "sg:postcode":"SE1 5UB",
    "sg:province":"Greater London",
    "wof:name":"Dr Azar",
    "wof:placetype":"venue"
},
  "geometry": {"coordinates":[-0.095995,51.499653],"type":"Point"}
}