{
  "type": "Feature",
  "properties": {
    "addr:full":"3 Stanley Close, Pulloxhill Bedford Bedfordshire MK45 5HS",
    "addr:housenumber":"3",
    "addr:postcode":"mk45 5hs",
    "addr:street":"Stanley Close",
    "iso:country":"GB",
    "sg:address":"3 Stanley Close, Pulloxhill",
    "sg:city":"Bedford",
    "sg:classifiers":[
        {
            "category":"Shopping",
            "subcategory":"Antiques",
            "type":"Retail Goods"
        }
    ],
    "sg:postcode":"MK45 5HS",
    "sg:province":"Bedfordshire",
    "wof:name":"Mary Collins (Furniture) Limited",
    "wof:placetype":"venue"
},
  "geometry": {"coordinates":[-0.4564880133,51.9914245605],"type":"Point"}
}