{
  "type": "Feature",
  "properties": {
    "addr:full":"31 Winton Road Reading Berkshire RG2 8HJ",
    "addr:housenumber":"31",
    "addr:postcode":"rg2 8hj",
    "addr:street":"Winton Road",
    "iso:country":"GB",
    "sg:address":"31 Winton Road",
    "sg:city":"Reading",
    "sg:classifiers":[
        {
            "category":"Professional",
            "subcategory":"Art Services",
            "type":"Services"
        }
    ],
    "sg:phone":"+44 118 987 5875",
    "sg:postcode":"RG2 8HJ",
    "sg:province":"Berkshire",
    "sg:tags":[
        "graphic",
        "designer"
    ],
    "wof:name":"875 Design Ltd.",
    "wof:placetype":"venue"
},
  "geometry": {"coordinates":[-0.9626899958,51.4197921753],"type":"Point"}
}