{
  "type": "Feature",
  "properties": {
    "iso:country":"GB",
    "sg:address":"49 Byres Road",
    "sg:city":"Glasgow",
    "sg:classifiers":[
        {
            "category":"Deli",
            "type":"Food & Drink"
        }
    ],
    "sg:postcode":"G11 5RG",
    "sg:province":"Glasgow City",
    "sg:tags":[
        "delicatessen"
    ],
    "wof:name":"Byres Market",
    "wof:placetype":"venue"
},
  "geometry": {"coordinates":[-4.2986268997,55.8714981079],"type":"Point"}
}