{
  "type": "Feature",
  "properties": {
    "iso:country":"GB",
    "sg:address":"7 Easton Place",
    "sg:city":"Coatbridge",
    "sg:classifiers":[
        {
            "category":"Cafe",
            "type":"Food & Drink"
        }
    ],
    "sg:phone":"+44 1236 606357",
    "sg:postcode":"ML5 4EW",
    "sg:province":"North Lanarkshire",
    "sg:tags":[
        "tea",
        "room"
    ],
    "wof:name":"The Coffee Shop",
    "wof:placetype":"venue"
},
  "geometry": {"coordinates":[-4.019565,55.853718],"type":"Point"}
}