{
  "type": "Feature",
  "properties": {
    "addr:full":"154 Wickham Road Croydon Surrey CR0 8BF",
    "addr:housenumber":"154",
    "addr:postcode":"cr0 8bf",
    "addr:street":"Wickham Road",
    "iso:country":"GB",
    "sg:address":"154 Wickham Road",
    "sg:city":"Croydon",
    "sg:classifiers":[
        {
            "category":"Shopping",
            "subcategory":"Bicycles & Sporting Goods",
            "type":"Retail Goods"
        }
    ],
    "sg:phone":"+44 20 8654 5046",
    "sg:postcode":"CR0 8BF",
    "sg:province":"Surrey",
    "sg:tags":[
        "cycle",
        "accessory"
    ],
    "wof:name":"Toplis Engineering Enterprises Ltd.",
    "wof:placetype":"venue"
},
  "geometry": {"coordinates":[-0.050811,51.374336],"type":"Point"}
}