{
  "type": "Feature",
  "properties": {
    "iso:country":"GB",
    "sg:address":"65-67 Stubby Lane, Wednesfield",
    "sg:city":"Wolverhampton",
    "sg:classifiers":[
        {
            "category":"Food & Beverages",
            "subcategory":"Supermarket",
            "type":"Retail Goods"
        }
    ],
    "sg:phone":"+44 1902 634257",
    "sg:postcode":"WV11 3NL",
    "sg:province":"Staffordshire",
    "wof:name":"Money Saver Discounts",
    "wof:placetype":"venue"
},
  "geometry": {"coordinates":[-2.059855,52.604259],"type":"Point"}
}