{
  "type": "Feature",
  "properties": {
    "addr:full":"Sandeyne Higher Shady Lane, Bromley Cross Bolton Lancashire BL7 9AQ",
    "addr:postcode":"bl7 9aq",
    "addr:street":"Higher Shady Lane",
    "iso:country":"GB",
    "sg:address":"Sandeyne Higher Shady Lane, Bromley Cross",
    "sg:city":"Bolton",
    "sg:classifiers":[
        {
            "category":"Home & Garden",
            "subcategory":"Hardware",
            "type":"Retail Goods"
        }
    ],
    "sg:phone":"+44 1204 307904",
    "sg:postcode":"BL7 9AQ",
    "sg:province":"Lancashire",
    "sg:tags":[
        "retailer",
        "diy"
    ],
    "wof:name":"D Green",
    "wof:placetype":"venue"
},
  "geometry": {"coordinates":[-2.410882,53.614738],"type":"Point"}
}