{
  "type": "Feature",
  "properties": {
    "addr:full":"180 Hall Lane Upminster Essex RM14 1AT",
    "addr:housenumber":"180",
    "addr:postcode":"rm14 1at",
    "addr:street":"Hall Lane",
    "iso:country":"GB",
    "sg:address":"180 Hall Lane",
    "sg:city":"Upminster",
    "sg:classifiers":[
        {
            "category":"Building & Trades",
            "subcategory":"Construction",
            "type":"Services"
        }
    ],
    "sg:phone":"+44 1708 228840",
    "sg:postcode":"RM14 1AT",
    "sg:province":"Essex",
    "sg:tags":[
        "decorator",
        "painter"
    ],
    "wof:name":"D J Davies Decorators",
    "wof:placetype":"venue"
},
  "geometry": {"coordinates":[0.2569800019,51.5723838806],"type":"Point"}
}