{
  "type": "Feature",
  "properties": {
    "addr:full":"3 Lyncroft Lees, Scraptoft Leicester Leicestershire LE7 9UW",
    "addr:housenumber":"3",
    "addr:postcode":"le7 9uw",
    "addr:street":"Lyncroft Lees",
    "iso:country":"GB",
    "sg:address":"3 Lyncroft Lees, Scraptoft",
    "sg:city":"Leicester",
    "sg:classifiers":[
        {
            "category":"Professional",
            "type":"Services"
        },
        {
            "category":"Professional",
            "subcategory":"Computer Services",
            "type":"Services"
        }
    ],
    "sg:postcode":"LE7 9UW",
    "sg:province":"Leicestershire",
    "sg:tags":[
        "system",
        "shopfitters",
        "software"
    ],
    "wof:name":"B S Systems",
    "wof:placetype":"venue"
},
  "geometry": {"coordinates":[-1.0454230309,52.6435241699],"type":"Point"}
}