{
  "type": "Feature",
  "properties": {
    "addr:full":"Berry Lane Basildon Essex SS16 6AZ",
    "addr:postcode":"ss16 6az",
    "addr:street":"Berry Lane",
    "iso:country":"GB",
    "sg:address":"Berry Lane",
    "sg:city":"Basildon",
    "sg:classifiers":[
        {
            "category":"Education",
            "subcategory":"School",
            "type":"Public Place"
        }
    ],
    "sg:phone":"+44 1268 412888",
    "sg:postcode":"SS16 6AZ",
    "sg:province":"Essex",
    "sg:tags":[
        "local",
        "authority"
    ],
    "wof:name":"Lincewood Primary School",
    "wof:placetype":"venue"
},
  "geometry": {"coordinates":[0.419517,51.563503],"type":"Point"}
}