{
  "type": "Feature",
  "properties": {
    "addr:full":"Breakers Yard, Moat Farm, Theberton Leiston Suffolk IP16 4RS",
    "addr:housenumber":"theberton leiston",
    "addr:postcode":"ip16 4rs",
    "addr:street":"Moat",
    "iso:country":"GB",
    "sg:address":"Breakers Yard, Moat Farm, Theberton",
    "sg:city":"Leiston",
    "sg:classifiers":[
        {
            "category":"Wholesale",
            "subcategory":"Scrap",
            "type":"Manufacturing & Wholesale Goods"
        }
    ],
    "sg:phone":"+44 1728 833886",
    "sg:postcode":"IP16 4RS",
    "sg:province":"Suffolk",
    "sg:tags":[
        "car",
        "breaker",
        "dismantlers"
    ],
    "wof:name":"J.B Motors",
    "wof:placetype":"venue"
},
  "geometry": {"coordinates":[1.574834,52.204872],"type":"Point"}
}