{
  "type": "Feature",
  "properties": {
    "addr:full":"57 Yew Ct, Marigold Way Chingford Greater London E4 8RJ",
    "addr:housenumber":"57",
    "addr:postcode":"e4 8rj",
    "addr:street":"Yew Ct Marigold Way",
    "iso:country":"GB",
    "sg:address":"57 Yew Ct, Marigold Way",
    "sg:city":"Chingford",
    "sg:classifiers":[
        {
            "category":"Building & Trades",
            "subcategory":"Construction",
            "type":"Services"
        }
    ],
    "sg:phone":"+44 20 8531 0227",
    "sg:postcode":"E4 8RJ",
    "sg:province":"Greater London",
    "sg:tags":[
        "roofing"
    ],
    "wof:name":"M A Lambert",
    "wof:placetype":"venue"
},
  "geometry": {"coordinates":[-0.02268,51.61644],"type":"Point"}
}