{
  "type": "Feature",
  "properties": {
    "iso:country":"GB",
    "sg:address":"237 Cannon Hill Lane",
    "sg:city":"London",
    "sg:classifiers":[
        {
            "category":"Health Services",
            "subcategory":"Dentist",
            "type":"Services"
        }
    ],
    "sg:postcode":"SW20 9DB",
    "sg:province":"Greater London",
    "sg:tags":[
        "technician",
        "instrument",
        "dental"
    ],
    "wof:name":"Ceramtech Ltd",
    "wof:placetype":"venue"
},
  "geometry": {"coordinates":[-0.2173389941,51.4007720947],"type":"Point"}
}