{
  "type": "Feature",
  "properties": {
    "addr:full":"Kingstown Broadway Carlisle Cumbria CA3 0HA",
    "addr:postcode":"ca3 0ha",
    "addr:street":"Kingstown Broadway",
    "iso:country":"GB",
    "sg:address":"Kingstown Broadway",
    "sg:city":"Carlisle",
    "sg:classifiers":[
        {
            "category":"Government",
            "subcategory":"Post Office",
            "type":"Public Place"
        }
    ],
    "sg:phone":"+44 1228 590020",
    "sg:postcode":"CA3 0HA",
    "sg:province":"Cumbria",
    "sg:tags":[
        "organisation",
        "soc",
        "research"
    ],
    "wof:name":"Scotia Pharmacuticals Ltd",
    "wof:placetype":"venue"
},
  "geometry": {"coordinates":[-2.9493589401,54.9274559021],"type":"Point"}
}