{
  "type": "Feature",
  "properties": {
    "addr:full":"1 Links Road North Tayport Fife DD6 9EB",
    "addr:housenumber":"1",
    "addr:postcode":"dd6 9eb",
    "addr:street":"Links Road North",
    "iso:country":"GB",
    "sg:address":"1 Links Road North",
    "sg:city":"Tayport",
    "sg:classifiers":[
        {
            "category":"Food & Beverages",
            "subcategory":"Fruits & Vegetables",
            "type":"Retail Goods"
        }
    ],
    "sg:phone":"+44 1382 552258",
    "sg:postcode":"DD6 9EB",
    "sg:province":"Fife",
    "sg:tags":[
        "greengrocer"
    ],
    "wof:name":"Andrew Auld",
    "wof:placetype":"venue"
},
  "geometry": {"coordinates":[-2.8694601059,56.4412002563],"type":"Point"}
}