{
  "type": "Feature",
  "properties": {
    "addr:full":"282 Worton Rd Isleworth Greater London TW7 6EE",
    "addr:housenumber":"282",
    "addr:postcode":"tw7 6ee",
    "addr:street":"Worton Rd",
    "iso:country":"GB",
    "sg:address":"282 Worton Rd",
    "sg:city":"Isleworth",
    "sg:classifiers":[
        {
            "category":"Autos & Motor Vehicles",
            "subcategory":"Auto Supplies",
            "type":"Retail Goods"
        }
    ],
    "sg:phone":"+44 20 8568 4636",
    "sg:postcode":"TW7 6EE",
    "sg:province":"Greater London",
    "sg:tags":[
        "component"
    ],
    "wof:name":"Autela",
    "wof:placetype":"venue"
},
  "geometry": {"coordinates":[-0.3323079944,51.4676475525],"type":"Point"}
}