{
  "type": "Feature",
  "properties": {
    "addr:full":"286 Windsor Road Maidenhead Berkshire SL6 2DT",
    "addr:housenumber":"286",
    "addr:postcode":"sl6 2dt",
    "addr:street":"Windsor Road",
    "iso:country":"GB",
    "sg:address":"286 Windsor Road",
    "sg:city":"Maidenhead",
    "sg:classifiers":[
        {
            "category":"Manufacturing",
            "subcategory":"Metals",
            "type":"Manufacturing & Wholesale Goods"
        },
        {
            "category":"Manufacturing",
            "subcategory":"Furniture",
            "type":"Manufacturing & Wholesale Goods"
        }
    ],
    "sg:phone":"+44 1628 623655",
    "sg:postcode":"SL6 2DT",
    "sg:province":"Berkshire",
    "sg:tags":[
        "polishing",
        "heat",
        "-",
        "treatment",
        "french"
    ],
    "wof:name":"J W Mundy & Son",
    "wof:placetype":"venue"
},
  "geometry": {"coordinates":[-0.7047989964,51.5001792908],"type":"Point"}
}