{
  "type": "Feature",
  "properties": {
    "addr:full":"Unit 17, Almners Farm Chertsey Surrey KT16 0BH",
    "addr:housenumber":"unit 17 almners farm chertsey",
    "addr:postcode":"kt16 0bh",
    "iso:country":"GB",
    "sg:address":"Unit 17, Almners Farm",
    "sg:city":"Chertsey",
    "sg:classifiers":[
        {
            "category":"Building & Trades",
            "subcategory":"Construction",
            "type":"Services"
        }
    ],
    "sg:postcode":"KT16 0BH",
    "sg:province":"Surrey",
    "sg:tags":[
        "builder"
    ],
    "wof:name":"J Fitzpatrick Builders",
    "wof:placetype":"venue"
},
  "geometry": {"coordinates":[-0.528912,51.38979],"type":"Point"}
}