{
  "type": "Feature",
  "properties": {
    "addr:full":"Enterprise House, Station Approach West Byfleet Surrey KT14 6NE",
    "addr:postcode":"kt14 6ne",
    "addr:street":"Station Approach West Byfleet",
    "iso:country":"GB",
    "sg:address":"Enterprise House, Station Approach",
    "sg:city":"West Byfleet",
    "sg:classifiers":[
        {
            "category":"Health Services",
            "subcategory":"Clinic",
            "type":"Services"
        }
    ],
    "sg:phone":"+44 1932 341122",
    "sg:postcode":"KT14 6NE",
    "sg:province":"Surrey",
    "sg:tags":[
        "medical"
    ],
    "wof:name":"Pari Medical Ltd.",
    "wof:placetype":"venue"
},
  "geometry": {"coordinates":[-0.505012,51.339165],"type":"Point"}
}