{
  "type": "Feature",
  "properties": {
    "addr:full":"Unit 8 Lea Park Industrial Estate, Millicent Road London Greater London E10 7LG",
    "addr:housenumber":"unit 8",
    "addr:postcode":"e10 7lg",
    "addr:street":"Lea Park Industrial;Millicent Road",
    "iso:country":"GB",
    "sg:address":"Unit 8 Lea Park Industrial Estate, Millicent Road",
    "sg:city":"London",
    "sg:classifiers":[
        {
            "category":"Shopping",
            "subcategory":"Clothing, Apparel, & Fashions",
            "type":"Retail Goods"
        }
    ],
    "sg:phone":"+44 20 8558 3286",
    "sg:postcode":"E10 7LG",
    "sg:province":"Greater London",
    "sg:tags":[
        "clothing",
        "fabric"
    ],
    "wof:name":"Todd & Reed",
    "wof:placetype":"venue"
},
  "geometry": {"coordinates":[-0.02593,51.568981],"type":"Point"}
}