{
  "type": "Feature",
  "properties": {
    "addr:full":"71 Upper Hale Road Farnham Surrey GU9 0PA",
    "addr:housenumber":"71",
    "addr:postcode":"gu9 0pa",
    "addr:street":"Upper Hale Road",
    "iso:country":"GB",
    "sg:address":"71 Upper Hale Road",
    "sg:city":"Farnham",
    "sg:classifiers":[
        {
            "category":"Personal",
            "subcategory":"Barber",
            "type":"Services"
        }
    ],
    "sg:phone":"+44 1252 717376",
    "sg:postcode":"GU9 0PA",
    "sg:province":"Surrey",
    "sg:tags":[
        "men's",
        "hairdresser"
    ],
    "wof:name":"Sweeney Todds Barbers",
    "wof:placetype":"venue"
},
  "geometry": {"coordinates":[-0.791802,51.232418],"type":"Point"}
}