{
  "type": "Feature",
  "properties": {
    "iso:country":"GB",
    "sg:address":"30 Brook Hill, Little Waltham",
    "sg:city":"Chelmsford",
    "sg:classifiers":[
        {
            "category":"Health Services",
            "subcategory":"Doctor",
            "type":"Services"
        }
    ],
    "sg:phone":"+44 1245 360253",
    "sg:postcode":"CM3 3LL",
    "sg:province":"Essex",
    "sg:tags":[
        "practitioners"
    ],
    "wof:name":"West Essex Health Authority",
    "wof:placetype":"venue"
},
  "geometry": {"coordinates":[0.477652,51.78756],"type":"Point"}
}