{
  "type": "Feature",
  "properties": {
    "iso:country":"GB",
    "sg:address":"14 Commercial Road",
    "sg:city":"Hereford",
    "sg:classifiers":[
        {
            "category":"Insurance",
            "subcategory":"Insurance Agent",
            "type":"Services"
        }
    ],
    "sg:phone":"+44 1432 266990",
    "sg:postcode":"HR1 2BE",
    "sg:province":"Herefordshire",
    "sg:tags":[
        "broker"
    ],
    "wof:name":"Clarke Roxburgh Insurance Brokers Ltd.",
    "wof:placetype":"venue"
},
  "geometry": {"coordinates":[-2.711638,52.058167],"type":"Point"}
}