{
  "type": "Feature",
  "properties": {
    "addr:full":"80 North End Croydon Surrey CR0 1UJ",
    "addr:housenumber":"80",
    "addr:postcode":"cr0 1uj",
    "addr:street":"North End",
    "iso:country":"GB",
    "sg:address":"80 North End",
    "sg:city":"Croydon",
    "sg:classifiers":[
        {
            "category":"Health Services",
            "subcategory":"Dentist",
            "type":"Services"
        }
    ],
    "sg:postcode":"CR0 1UJ",
    "sg:province":"Surrey",
    "sg:tags":[
        "technician",
        "dental"
    ],
    "wof:name":"Hewitt & McBurney",
    "wof:placetype":"venue"
},
  "geometry": {"coordinates":[-0.1013849974,51.376247406],"type":"Point"}
}