{
  "type": "Feature",
  "properties": {
    "addr:full":"3 Wellmeadow St Paisley Renfrewshire PA1 2EF",
    "addr:housenumber":"3",
    "addr:postcode":"pa1 2ef",
    "addr:street":"Wellmeadow St",
    "iso:country":"GB",
    "sg:address":"3 Wellmeadow St",
    "sg:city":"Paisley",
    "sg:classifiers":[
        {
            "category":"Bars & Pubs",
            "type":"Food & Drink"
        }
    ],
    "sg:phone":"+44 141 887 9955",
    "sg:postcode":"PA1 2EF",
    "sg:province":"Renfrewshire",
    "sg:tags":[
        "pubs",
        "inn"
    ],
    "wof:name":"Bowlers Tavern The",
    "wof:placetype":"venue"
},
  "geometry": {"coordinates":[-4.4331030846,55.8441772461],"type":"Point"}
}