{
  "type": "Feature",
  "properties": {
    "addr:full":"22 Fernlea Av Herne Bay Kent CT6 8UG",
    "addr:housenumber":"22",
    "addr:postcode":"ct6 8ug",
    "addr:street":"Fernlea Av Herne Bay",
    "iso:country":"GB",
    "sg:address":"22 Fernlea Av",
    "sg:city":"Herne Bay",
    "sg:classifiers":[
        {
            "category":"Professional",
            "subcategory":"Lawyer & Legal Services",
            "type":"Services"
        }
    ],
    "sg:phone":"+44 1227 362220",
    "sg:postcode":"CT6 8UG",
    "sg:province":"Kent",
    "sg:tags":[
        "advice",
        "counselling"
    ],
    "wof:name":"C C A C T",
    "wof:placetype":"venue"
},
  "geometry": {"coordinates":[1.1172169447,51.3671722412],"type":"Point"}
}