{
  "type": "Feature",
  "properties": {
    "addr:full":"Moncur Road Kilwinning East Ayrshire KA13 7LD",
    "addr:postcode":"ka13 7ld",
    "addr:street":"Moncur Road",
    "iso:country":"GB",
    "sg:address":"Moncur Road",
    "sg:city":"Kilwinning",
    "sg:classifiers":[
        {
            "category":"Arena",
            "subcategory":"Sports Club",
            "type":"Entertainment"
        }
    ],
    "sg:phone":"+44 1294 550319",
    "sg:postcode":"KA13 7LD",
    "sg:province":"East Ayrshire",
    "wof:name":"Corsehill Bowling Club",
    "wof:placetype":"venue"
},
  "geometry": {"coordinates":[-4.6817388535,55.6543197632],"type":"Point"}
}