{
  "type": "Feature",
  "properties": {
    "iso:country":"GB",
    "sg:address":"Pine Hurst, Hawley Drive",
    "sg:city":"Altrincham",
    "sg:classifiers":[
        {
            "category":"Professional",
            "subcategory":"Printing & Photocopies",
            "type":"Services"
        }
    ],
    "sg:phone":"+44 161 904 8844",
    "sg:postcode":"WA15 0DP",
    "sg:province":"Cheshire",
    "sg:tags":[
        "duplicating",
        "copying"
    ],
    "wof:name":"R B T Service Direct Ltd.",
    "wof:placetype":"venue"
},
  "geometry": {"coordinates":[-2.32187,53.366829],"type":"Point"}
}