{
  "type": "Feature",
  "properties": {
    "addr:full":"23 Maxwell Rd Northwood Greater London HA6 2XX",
    "addr:housenumber":"23",
    "addr:postcode":"ha6 2xx",
    "addr:street":"Maxwell Rd",
    "iso:country":"GB",
    "sg:address":"23 Maxwell Rd",
    "sg:city":"Northwood",
    "sg:classifiers":[
        {
            "category":"Food & Beverages",
            "subcategory":"Bakery",
            "type":"Retail Goods"
        }
    ],
    "sg:postcode":"HA6 2XX",
    "sg:province":"Greater London",
    "sg:tags":[
        "baker"
    ],
    "wof:name":"Wenzel's the Bakers",
    "wof:placetype":"venue"
},
  "geometry": {"coordinates":[-0.425256,51.61113],"type":"Point"}
}