{
  "type": "Feature",
  "properties": {
    "iso:country":"GB",
    "sg:address":"Munro House, Duke Street",
    "sg:city":"Leeds",
    "sg:classifiers":[
        {
            "category":"Autos & Motor Vehicles",
            "subcategory":"Automobile Sales",
            "type":"Retail Goods"
        },
        {
            "category":"Communications",
            "subcategory":"Newspaper",
            "type":"Services"
        }
    ],
    "sg:phone":"+44 113 246 2400",
    "sg:postcode":"LS9 8AL",
    "sg:province":"West Yorkshire",
    "sg:tags":[
        "car",
        "magazine"
    ],
    "sg:website":"http://www.diamondfreeads.co.uk",
    "wof:name":"Yorkshire Auto Trader",
    "wof:placetype":"venue"
},
  "geometry": {"coordinates":[-1.5339109898,53.7959861755],"type":"Point"}
}