{
  "type": "Feature",
  "properties": {
    "addr:full":"C/o H M Whittle (holdings) Ltd, Cuerden Way Cuerden Preston Lancashire PR5 6BP",
    "addr:postcode":"pr5 6bp",
    "addr:street":"C;Cuerden Way",
    "iso:country":"GB",
    "sg:address":"C/o H M Whittle (holdings) Ltd, Cuerden Way Cuerden",
    "sg:city":"Preston",
    "sg:classifiers":[
        {
            "category":"Building & Trades",
            "subcategory":"Construction",
            "type":"Services"
        }
    ],
    "sg:postcode":"PR5 6BP",
    "sg:province":"Lancashire",
    "sg:tags":[
        "joinery"
    ],
    "wof:name":"D  Whittle & Sons (Joiners) Ltd.",
    "wof:placetype":"venue"
},
  "geometry": {"coordinates":[-2.660599947,53.7260284424],"type":"Point"}
}