{
  "type": "Feature",
  "properties": {
    "addr:full":"East Hill House, 76 High Street Colchester Essex CO1 1UF",
    "addr:housenumber":"76",
    "addr:postcode":"co1 1uf",
    "addr:street":"High Street",
    "iso:country":"GB",
    "sg:address":"East Hill House, 76 High Street",
    "sg:city":"Colchester",
    "sg:classifiers":[
        {
            "category":"Farming",
            "subcategory":"Nursery",
            "type":"Manufacturing & Wholesale Goods"
        },
        {
            "category":"Government",
            "subcategory":"Office",
            "type":"Public Place"
        }
    ],
    "sg:phone":"+44 1206 572558",
    "sg:postcode":"CO1 1UF",
    "sg:province":"Essex",
    "sg:tags":[
        "local",
        "creche"
    ],
    "wof:name":"The Mulberry Tree Day Nursery",
    "wof:placetype":"venue"
},
  "geometry": {"coordinates":[0.9064469934,51.8897972107],"type":"Point"}
}