{
  "type": "Feature",
  "properties": {
    "iso:country":"GB",
    "sg:address":"20 Newton Street",
    "sg:city":"Glasgow",
    "sg:classifiers":[
        {
            "category":"Professional",
            "subcategory":"Art Services",
            "type":"Services"
        }
    ],
    "sg:phone":"+44 141 226 3888",
    "sg:postcode":"G3 8BS",
    "sg:province":"Glasgow City",
    "sg:tags":[
        "photographer"
    ],
    "wof:name":"Nisbet & Wylie Photography",
    "wof:placetype":"venue"
},
  "geometry": {"coordinates":[-4.2699990273,55.8625602722],"type":"Point"}
}