{
  "type": "Feature",
  "properties": {
    "iso:country":"GB",
    "sg:address":"60 The Hoo",
    "sg:city":"Harlow",
    "sg:classifiers":[
        {
            "category":"Home & Garden",
            "subcategory":"Building Materials",
            "type":"Retail Goods"
        },
        {
            "category":"Building & Trades",
            "subcategory":"Construction",
            "type":"Services"
        }
    ],
    "sg:phone":"+44 1279 438354",
    "sg:postcode":"CM17 0HR",
    "sg:province":"Essex",
    "sg:tags":[
        "fencing",
        "contractor"
    ],
    "wof:name":"C R Ellis",
    "wof:placetype":"venue"
},
  "geometry": {"coordinates":[0.1347559988,51.7904014587],"type":"Point"}
}