{
  "type": "Feature",
  "properties": {
    "addr:full":"Deegans Yard, 38 Crossway Raynes Park Greater London SW20 9JA",
    "addr:housenumber":"38",
    "addr:postcode":"sw20 9ja",
    "addr:street":"Deegans;Crossway",
    "iso:country":"GB",
    "sg:address":"Deegans Yard, 38 Crossway",
    "sg:city":"Raynes Park",
    "sg:classifiers":[
        {
            "category":"Retail",
            "subcategory":"Auto Repair",
            "type":"Services"
        }
    ],
    "sg:phone":"+44 20 8395 4447",
    "sg:postcode":"SW20 9JA",
    "sg:province":"Greater London",
    "sg:tags":[
        "modification",
        "garage"
    ],
    "wof:name":"Kingston Workshop",
    "wof:placetype":"venue"
},
  "geometry": {"coordinates":[-0.2265190035,51.4110946655],"type":"Point"}
}