{
  "type": "Feature",
  "properties": {
    "addr:full":"Unit 18 The Old Town Hall, Effingham St Rotherham South Yorkshire S65 1AJ",
    "addr:housenumber":"unit 18",
    "addr:postcode":"s65 1aj",
    "addr:street":"The;Effingham St",
    "iso:country":"GB",
    "sg:address":"Unit 18 The Old Town Hall, Effingham St",
    "sg:city":"Rotherham",
    "sg:classifiers":[
        {
            "category":"Home & Garden",
            "subcategory":"Home Furnishings",
            "type":"Retail Goods"
        }
    ],
    "sg:phone":"+44 1709 515656",
    "sg:postcode":"S65 1AJ",
    "sg:province":"South Yorkshire",
    "sg:tags":[
        "candle"
    ],
    "wof:name":"Wicks End",
    "wof:placetype":"venue"
},
  "geometry": {"coordinates":[-1.35574,53.431862],"type":"Point"}
}