{
  "type": "Feature",
  "properties": {
    "addr:full":"1 Mole Place Oxford Oxfordshire OX4 7SD",
    "addr:housenumber":"1",
    "addr:postcode":"ox4 7sd",
    "addr:street":"Mole Place",
    "iso:country":"GB",
    "sg:address":"1 Mole Place",
    "sg:city":"Oxford",
    "sg:classifiers":[
        {
            "category":"Education",
            "subcategory":"Special Training",
            "type":"Public Place"
        }
    ],
    "sg:phone":"+44 1865 776691",
    "sg:postcode":"OX4 7SD",
    "sg:province":"Oxfordshire",
    "sg:tags":[
        "product",
        "centre"
    ],
    "wof:name":"Celebrating Identity Training and Consultancy",
    "wof:placetype":"venue"
},
  "geometry": {"coordinates":[-1.1907629967,51.716178894],"type":"Point"}
}