{
  "type": "Feature",
  "properties": {
    "addr:full":"6 Rayment Avenue Canvey Island Essex SS8 7JU",
    "addr:housenumber":"6",
    "addr:postcode":"ss8 7ju",
    "addr:street":"Rayment Avenue",
    "iso:country":"GB",
    "sg:address":"6 Rayment Avenue",
    "sg:city":"Canvey Island",
    "sg:classifiers":[
        {
            "category":"Professional",
            "type":"Services"
        }
    ],
    "sg:phone":"+44 1268 683260",
    "sg:postcode":"SS8 7JU",
    "sg:province":"Essex",
    "sg:tags":[
        "entertainer"
    ],
    "wof:name":"W.G Capser",
    "wof:placetype":"venue"
},
  "geometry": {"coordinates":[0.602688,51.518097],"type":"Point"}
}