{
  "type": "Feature",
  "properties": {
    "addr:full":"Unit C3 Deal Kent CT14 6PJ",
    "addr:postcode":"ct14 6pj",
    "iso:country":"GB",
    "sg:address":"Unit C3",
    "sg:city":"Deal",
    "sg:classifiers":[
        {
            "category":"Sports & Exercise",
            "subcategory":"Tennis Court",
            "type":"Entertainment"
        }
    ],
    "sg:phone":"+44 1304 381852",
    "sg:postcode":"CT14 6PJ",
    "sg:province":"Kent",
    "sg:tags":[
        "breakdown",
        "recovery"
    ],
    "wof:name":"Knights Recovery & Transportation Services",
    "wof:placetype":"venue"
},
  "geometry": {"coordinates":[1.4032349586,51.2231292725],"type":"Point"}
}