{
  "type": "Feature",
  "properties": {
    "addr:full":"21 Grebe Clo Birmingham West Midlands B23 7RW",
    "addr:housenumber":"21",
    "addr:postcode":"b23 7rw",
    "addr:street":"Grebe Clo",
    "iso:country":"GB",
    "sg:address":"21 Grebe Clo",
    "sg:city":"Birmingham",
    "sg:classifiers":[
        {
            "category":"Professional",
            "subcategory":"Computer Services",
            "type":"Services"
        }
    ],
    "sg:phone":"+44 121 344 4396",
    "sg:postcode":"B23 7RW",
    "sg:province":"West Midlands",
    "sg:tags":[
        "system",
        "software"
    ],
    "wof:name":"Texwipe UK",
    "wof:placetype":"venue"
},
  "geometry": {"coordinates":[-1.872344,52.51939],"type":"Point"}
}