{
  "type": "Feature",
  "properties": {
    "iso:country":"GB",
    "sg:address":"178 Beechwood Avenue",
    "sg:city":"Coventry",
    "sg:classifiers":[
        {
            "category":"Professional",
            "subcategory":"Management & Consulting",
            "type":"Services"
        }
    ],
    "sg:phone":"+44 24 7667 3765",
    "sg:postcode":"CV5 6FW",
    "sg:province":"West Midlands",
    "sg:tags":[
        "consultant",
        "business"
    ],
    "wof:name":"PACCTS",
    "wof:placetype":"venue"
},
  "geometry": {"coordinates":[-1.537661,52.399189],"type":"Point"}
}