{
  "type": "Feature",
  "properties": {
    "addr:full":"The Homestead, Temple La, Copmanthorpe York North Yorkshire YO23 3TD",
    "addr:postcode":"yo23 3td",
    "addr:street":"Copmanthorpe",
    "iso:country":"GB",
    "sg:address":"The Homestead, Temple La, Copmanthorpe",
    "sg:city":"York",
    "sg:classifiers":[
        {
            "category":"Building & Trades",
            "subcategory":"Construction",
            "type":"Services"
        }
    ],
    "sg:postcode":"YO23 3TD",
    "sg:province":"North Yorkshire",
    "sg:tags":[
        "builder"
    ],
    "wof:name":"Parkinson,F,Ltd",
    "wof:placetype":"venue"
},
  "geometry": {"coordinates":[-1.142071,53.913673],"type":"Point"}
}