{
  "type": "Feature",
  "properties": {
    "addr:full":"148-152 Old Dalmarnock Road Glasgow Glasgow City G40 4LH",
    "addr:housenumber":"148-152",
    "addr:postcode":"g40 4lh",
    "addr:street":"Old Dalmarnock Road",
    "iso:country":"GB",
    "sg:address":"148-152 Old Dalmarnock Road",
    "sg:city":"Glasgow",
    "sg:classifiers":[
        {
            "category":"Bars & Pubs",
            "type":"Food & Drink"
        },
        {
            "category":"Community Center",
            "subcategory":"Social",
            "type":"Public Place"
        }
    ],
    "sg:phone":"+44 141 554 7027",
    "sg:postcode":"G40 4LH",
    "sg:province":"Glasgow City",
    "sg:tags":[
        "pubs",
        "house",
        "inn",
        "activity"
    ],
    "wof:name":"The Hayfield Bar",
    "wof:placetype":"venue"
},
  "geometry": {"coordinates":[-4.2200460434,55.844165802],"type":"Point"}
}