{
  "type": "Feature",
  "properties": {
    "addr:full":"20 London Road Horsham West Sussex RH12 1AY",
    "addr:housenumber":"20",
    "addr:postcode":"rh12 1ay",
    "addr:street":"London Road",
    "iso:country":"GB",
    "sg:address":"20 London Road",
    "sg:city":"Horsham",
    "sg:classifiers":[
        {
            "category":"Professional",
            "subcategory":"Accounting & Tax Preparation",
            "type":"Services"
        }
    ],
    "sg:postcode":"RH12 1AY",
    "sg:province":"West Sussex",
    "sg:tags":[
        "accountant"
    ],
    "wof:name":"William Maxwell & Co",
    "wof:placetype":"venue"
},
  "geometry": {"coordinates":[-0.3282920122,51.0643348694],"type":"Point"}
}