{
  "type": "Feature",
  "properties": {
    "addr:full":"17 Chapel Yard, Albert Street Holt Norfolk NR25 6HG",
    "addr:housenumber":"17",
    "addr:postcode":"nr25 6hg",
    "addr:street":"Chapel Yard Albert Street",
    "iso:country":"GB",
    "sg:address":"17 Chapel Yard, Albert Street",
    "sg:city":"Holt",
    "sg:classifiers":[
        {
            "category":"Shopping",
            "subcategory":"Antiques",
            "type":"Retail Goods"
        }
    ],
    "sg:postcode":"NR25 6HG",
    "sg:province":"Norfolk",
    "wof:name":"MAURA HENRY ANTIQUES",
    "wof:placetype":"venue"
},
  "geometry": {"coordinates":[1.0899460316,52.9030570984],"type":"Point"}
}