{
  "type": "Feature",
  "properties": {
    "iso:country":"GB",
    "sg:address":"Birch Tree Centre, Winstanley Park",
    "sg:city":"Wigan",
    "sg:classifiers":[
        {
            "category":"Wholesale",
            "subcategory":"Sporting Goods",
            "type":"Manufacturing & Wholesale Goods"
        },
        {
            "category":"Sports & Exercise",
            "subcategory":"Golf",
            "type":"Entertainment"
        }
    ],
    "sg:postcode":"WN3 6BE",
    "sg:province":"Lancashire",
    "sg:tags":[
        "mnfr",
        "equipment"
    ],
    "wof:name":"M I S Northwest",
    "wof:placetype":"venue"
},
  "geometry": {"coordinates":[-2.676546,53.521503],"type":"Point"}
}