{
  "type": "Feature",
  "properties": {
    "iso:country":"GB",
    "sg:address":"35 Tees Drive",
    "sg:city":"Romford",
    "sg:classifiers":[
        {
            "category":"Building & Trades",
            "subcategory":"Construction",
            "type":"Services"
        }
    ],
    "sg:postcode":"RM3 9AH",
    "sg:province":"Essex",
    "sg:tags":[
        "builder"
    ],
    "wof:name":"Inflex Ltd.",
    "wof:placetype":"venue"
},
  "geometry": {"coordinates":[0.2225860059,51.6149215698],"type":"Point"}
}