{
  "type": "Feature",
  "properties": {
    "addr:full":"Greenbank, Main Street Killin Perth and Kinross FK21 8UT",
    "addr:postcode":"fk21 8ut",
    "addr:street":"Main Street",
    "iso:country":"GB",
    "sg:address":"Greenbank, Main Street",
    "sg:city":"Killin",
    "sg:classifiers":[
        {
            "category":"Professional",
            "subcategory":"Art Services",
            "type":"Services"
        },
        {
            "category":"Building & Trades",
            "subcategory":"Construction",
            "type":"Services"
        }
    ],
    "sg:phone":"+44 1567 820462",
    "sg:postcode":"FK21 8UT",
    "sg:province":"Perth and Kinross",
    "sg:tags":[
        "decorator",
        "painter"
    ],
    "wof:name":"Grant & Welsh",
    "wof:placetype":"venue"
},
  "geometry": {"coordinates":[-4.3176631927,56.4681739807],"type":"Point"}
}