{
  "type": "Feature",
  "properties": {
    "iso:country":"GB",
    "sg:address":"808/810 Pershore Road, Selly Park",
    "sg:city":"Birmingham",
    "sg:classifiers":[
        {
            "category":"Shopping",
            "subcategory":"Pharmacy",
            "type":"Retail Goods"
        }
    ],
    "sg:postcode":"B29 7LS",
    "sg:province":"West Midlands",
    "sg:tags":[
        "pharmacist",
        "chemist"
    ],
    "wof:name":"Noble's Chemist",
    "wof:placetype":"venue"
},
  "geometry": {"coordinates":[-1.9153120518,52.441318512],"type":"Point"}
}