{
  "type": "Feature",
  "properties": {
    "iso:country":"GB",
    "sg:address":"7 Poplar Rd",
    "sg:city":"Sudbury",
    "sg:classifiers":[
        {
            "category":"Shopping",
            "subcategory":"Pharmacy",
            "type":"Retail Goods"
        }
    ],
    "sg:phone":"+44 1787 375804",
    "sg:postcode":"CO10 0LH",
    "sg:province":"Essex",
    "sg:tags":[
        "pharmacist",
        "chemist"
    ],
    "wof:name":"Great Cornard Pharmacy",
    "wof:placetype":"venue"
},
  "geometry": {"coordinates":[0.748774,52.034351],"type":"Point"}
}