{
  "type": "Feature",
  "properties": {
    "addr:full":"12 The Precinct, West Meads Bognor Regis West Sussex PO21 5SB",
    "addr:housenumber":"12",
    "addr:postcode":"po21 5sb",
    "addr:street":"The Precinct West Meads",
    "iso:country":"GB",
    "sg:address":"12 The Precinct, West Meads",
    "sg:city":"Bognor Regis",
    "sg:classifiers":[
        {
            "category":"Personal",
            "subcategory":"Beauty Salon",
            "type":"Services"
        },
        {
            "category":"Personal",
            "subcategory":"Barber",
            "type":"Services"
        }
    ],
    "sg:phone":"+44 1243 864817",
    "sg:postcode":"PO21 5SB",
    "sg:province":"West Sussex",
    "sg:tags":[
        "unisex",
        "hairdresser"
    ],
    "wof:name":"Hair Flair",
    "wof:placetype":"venue"
},
  "geometry": {"coordinates":[-0.7010369897,50.7878837585],"type":"Point"}
}