{
  "type": "Feature",
  "properties": {
    "addr:full":"Bankhead Road, Rutherglen Glasgow Glasgow City G73 2BQ",
    "addr:postcode":"g73 2bq",
    "addr:street":"Bankhead Road",
    "iso:country":"GB",
    "sg:address":"Bankhead Road, Rutherglen",
    "sg:city":"Glasgow",
    "sg:classifiers":[
        {
            "category":"Education",
            "subcategory":"School",
            "type":"Public Place"
        },
        {
            "category":"Government",
            "subcategory":"Office",
            "type":"Public Place"
        }
    ],
    "sg:phone":"+44 141 647 6967",
    "sg:postcode":"G73 2BQ",
    "sg:province":"Glasgow City",
    "sg:tags":[
        "local",
        "authority"
    ],
    "wof:name":"Bankhead Primary School",
    "wof:placetype":"venue"
},
  "geometry": {"coordinates":[-4.211459,55.828495],"type":"Point"}
}