{
  "type": "Feature",
  "properties": {
    "addr:full":"Taliesin, Earlswood Chepstow Gloucestershire NP16 6AN",
    "addr:postcode":"np16 6an",
    "iso:country":"GB",
    "sg:address":"Taliesin, Earlswood",
    "sg:city":"Chepstow",
    "sg:classifiers":[
        {
            "category":"Real Estate",
            "subcategory":"Architect",
            "type":"Services"
        }
    ],
    "sg:phone":"+44 1291 641275",
    "sg:postcode":"NP16 6AN",
    "sg:province":"Gloucestershire",
    "wof:name":"Robert Lutken",
    "wof:placetype":"venue"
},
  "geometry": {"coordinates":[-2.8076241016,51.6575126648],"type":"Point"}
}