{
  "type": "Feature",
  "properties": {
    "addr:full":"70-72 Wardle Road Sale Cheshire M33 3DH",
    "addr:housenumber":"70-72",
    "addr:postcode":"m33 3dh",
    "addr:street":"Wardle Road",
    "iso:country":"GB",
    "sg:address":"70-72 Wardle Road",
    "sg:city":"Sale",
    "sg:classifiers":[
        {
            "category":"Retail",
            "subcategory":"Auto Repair",
            "type":"Services"
        }
    ],
    "sg:postcode":"M33 3DH",
    "sg:province":"Cheshire",
    "sg:tags":[
        "modification",
        "garage"
    ],
    "wof:name":"Brooklands Auto Services Ltd.",
    "wof:placetype":"venue"
},
  "geometry": {"coordinates":[-2.318886,53.417816],"type":"Point"}
}