{
  "type": "Feature",
  "properties": {
    "addr:full":"7 Station Rd Prescot Merseyside L34 5SN",
    "addr:housenumber":"7",
    "addr:postcode":"l34 5sn",
    "addr:street":"Station Rd",
    "iso:country":"GB",
    "sg:address":"7 Station Rd",
    "sg:city":"Prescot",
    "sg:classifiers":[
        {
            "category":"Professional",
            "subcategory":"Printing & Photocopies",
            "type":"Services"
        }
    ],
    "sg:phone":"+44 151 426 6756",
    "sg:postcode":"L34 5SN",
    "sg:province":"Merseyside",
    "sg:tags":[
        "printer"
    ],
    "wof:name":"Instant Print",
    "wof:placetype":"venue"
},
  "geometry": {"coordinates":[-2.801654,53.42765],"type":"Point"}
}