{
  "type": "Feature",
  "properties": {
    "addr:full":"121 Woodhouse St Leeds West Yorkshire LS6 2PY",
    "addr:housenumber":"121",
    "addr:postcode":"ls6 2py",
    "addr:street":"Woodhouse St",
    "iso:country":"GB",
    "sg:address":"121 Woodhouse St",
    "sg:city":"Leeds",
    "sg:classifiers":[
        {
            "category":"Bars & Pubs",
            "type":"Food & Drink"
        }
    ],
    "sg:postcode":"LS6 2PY",
    "sg:province":"West Yorkshire",
    "sg:tags":[
        "pubs",
        "inn"
    ],
    "wof:name":"Beer Exchange (The)",
    "wof:placetype":"venue"
},
  "geometry": {"coordinates":[-1.549719,53.812366],"type":"Point"}
}