{
  "type": "Feature",
  "properties": {
    "iso:country":"GB",
    "sg:address":"Eastbury Rd, Oxhey",
    "sg:city":"Watford",
    "sg:classifiers":[
        {
            "category":"Arena",
            "subcategory":"Sports Club",
            "type":"Entertainment"
        }
    ],
    "sg:phone":"+44 1923 230534",
    "sg:postcode":"WD1 4PX",
    "sg:province":"Hertfordshire",
    "wof:name":"Bushey Cricket Club",
    "wof:placetype":"venue"
},
  "geometry": {"coordinates":[-0.3797,51.637901],"type":"Point"}
}