{
  "type": "Feature",
  "properties": {
    "addr:full":"Unit 4 Lion Park Avenue Chessington Surrey KT9 1ST",
    "addr:housenumber":"unit 4",
    "addr:postcode":"kt9 1st",
    "addr:street":"Lion Park Avenue",
    "iso:country":"GB",
    "sg:address":"Unit 4 Lion Park Avenue",
    "sg:city":"Chessington",
    "sg:classifiers":[
        {
            "category":"Utilities",
            "subcategory":"Telephone",
            "type":"Services"
        }
    ],
    "sg:phone":"+44 20 8974 2986",
    "sg:postcode":"KT9 1ST",
    "sg:province":"Surrey",
    "sg:tags":[
        "telecommunication"
    ],
    "wof:name":"Damovo U K Ltd.",
    "wof:placetype":"venue"
},
  "geometry": {"coordinates":[-0.2871879935,51.3684692383],"type":"Point"}
}