{
  "type": "Feature",
  "properties": {
    "addr:full":"Kimson House, Plot 4 Cwrt Liechryd Rhymney Blaenau Gwent NP2 5QF",
    "addr:housenumber":"plot",
    "addr:postcode":"np2 5qf",
    "addr:street":"Cwrt",
    "iso:country":"GB",
    "sg:address":"Kimson House, Plot 4 Cwrt Liechryd",
    "sg:city":"Rhymney",
    "sg:classifiers":[
        {
            "category":"Autos & Motor Vehicles",
            "subcategory":"Automobile Sales",
            "type":"Retail Goods"
        }
    ],
    "sg:phone":"+44 1685 844222",
    "sg:postcode":"NP2 5QF",
    "sg:province":"Blaenau Gwent",
    "sg:tags":[
        "car"
    ],
    "wof:name":"Rhymney Bridge 4x4",
    "wof:placetype":"venue"
},
  "geometry": {"coordinates":[-3.2876899242,51.7635192871],"type":"Point"}
}