{
  "type": "Feature",
  "properties": {
    "addr:full":"Stratton Business Park Biggleswade Bedfordshire SG18 8QB",
    "addr:postcode":"sg18 8qb",
    "addr:street":"Bedfordshire",
    "iso:country":"GB",
    "sg:address":"Stratton Business Park",
    "sg:city":"Biggleswade",
    "sg:classifiers":[
        {
            "category":"Building & Trades",
            "subcategory":"Cleaning & Sanitation",
            "type":"Services"
        }
    ],
    "sg:phone":"+44 1767 601222",
    "sg:postcode":"SG18 8QB",
    "sg:province":"Bedfordshire",
    "sg:tags":[
        "door",
        "manufacturer"
    ],
    "wof:name":"Esavian Ltd.",
    "wof:placetype":"venue"
},
  "geometry": {"coordinates":[-0.242149,52.075031],"type":"Point"}
}