{
  "type": "Feature",
  "properties": {
    "addr:full":"14 King Edward Road Deal Kent CT14 6QL",
    "addr:housenumber":"14",
    "addr:postcode":"ct14 6ql",
    "addr:street":"King Edward Road Deal",
    "iso:country":"GB",
    "sg:address":"14 King Edward Road",
    "sg:city":"Deal",
    "sg:classifiers":[
        {
            "category":"Shopping",
            "subcategory":"News",
            "type":"Retail Goods"
        }
    ],
    "sg:phone":"+44 1304 375876",
    "sg:postcode":"CT14 6QL",
    "sg:province":"Kent",
    "sg:tags":[
        "newsagent"
    ],
    "wof:name":"Lamb's Newsagents",
    "wof:placetype":"venue"
},
  "geometry": {"coordinates":[1.4011750221,51.2354850769],"type":"Point"}
}