{
  "type": "Feature",
  "properties": {
    "addr:full":"133 Roe La Southport Lancashire PR9 7PW",
    "addr:housenumber":"133",
    "addr:postcode":"pr9 7pw",
    "addr:street":"Roe La Southport",
    "iso:country":"GB",
    "sg:address":"133 Roe La",
    "sg:city":"Southport",
    "sg:classifiers":[
        {
            "category":"Health Services",
            "subcategory":"Dentist",
            "type":"Services"
        }
    ],
    "sg:phone":"+44 1704 227041",
    "sg:postcode":"PR9 7PW",
    "sg:province":"Lancashire",
    "wof:name":"T M Baker",
    "wof:placetype":"venue"
},
  "geometry": {"coordinates":[-2.9665899277,53.6542396545],"type":"Point"}
}