{
  "type": "Feature",
  "properties": {
    "iso:country":"GB",
    "sg:address":"35 Church Street",
    "sg:city":"Leighton Buzzard",
    "sg:classifiers":[
        {
            "category":"Personal",
            "subcategory":"Beauty Salon",
            "type":"Services"
        }
    ],
    "sg:phone":"+44 1525 370167",
    "sg:postcode":"LU7 1BP",
    "sg:province":"Bedfordshire",
    "sg:tags":[
        "unisex",
        "hairdresser"
    ],
    "wof:name":"Reflections",
    "wof:placetype":"venue"
},
  "geometry": {"coordinates":[-0.660421,51.920982],"type":"Point"}
}