{
  "type": "Feature",
  "properties": {
    "addr:full":"Holmlands Bldgs, Tunstall Rd Sunderland Tyne and Wear SR2 7RR",
    "addr:postcode":"sr2 7rr",
    "addr:street":"Tunstall Rd",
    "iso:country":"GB",
    "sg:address":"Holmlands Bldgs, Tunstall Rd",
    "sg:city":"Sunderland",
    "sg:classifiers":[
        {
            "category":"Personal",
            "subcategory":"Beauty Salon",
            "type":"Services"
        }
    ],
    "sg:postcode":"SR2 7RR",
    "sg:province":"Tyne and Wear",
    "wof:name":"Rawding,Maxine,",
    "wof:placetype":"venue"
},
  "geometry": {"coordinates":[-1.38926,54.895031],"type":"Point"}
}