{
  "type": "Feature",
  "properties": {
    "addr:full":"Crofts Gear Works, Thornbury Road Bradford West Yorkshire BD3 8HJ",
    "addr:postcode":"bd3 8hj",
    "addr:street":"Crofts;Thornbury Road",
    "iso:country":"GB",
    "sg:address":"Crofts Gear Works, Thornbury Road",
    "sg:city":"Bradford",
    "sg:classifiers":[
        {
            "category":"Professional",
            "subcategory":"Engineering",
            "type":"Services"
        }
    ],
    "sg:phone":"+44 1274 662161",
    "sg:postcode":"BD3 8HJ",
    "sg:province":"West Yorkshire",
    "wof:name":"Renold Hydraulics & Varietors",
    "wof:placetype":"venue"
},
  "geometry": {"coordinates":[-1.7173800468,53.7966995239],"type":"Point"}
}