{
  "type": "Feature",
  "properties": {
    "addr:full":"50 Guildford Rd Worthing West Sussex BN14 7LL",
    "addr:housenumber":"50",
    "addr:postcode":"bn14 7ll",
    "addr:street":"Guildford Rd",
    "iso:country":"GB",
    "sg:address":"50 Guildford Rd",
    "sg:city":"Worthing",
    "sg:classifiers":[
        {
            "category":"Professional",
            "subcategory":"Printing & Photocopies",
            "type":"Services"
        }
    ],
    "sg:phone":"+44 1903 201430",
    "sg:postcode":"BN14 7LL",
    "sg:province":"West Sussex",
    "sg:tags":[
        "embroiderer"
    ],
    "wof:name":"Initial Designs",
    "wof:placetype":"venue"
},
  "geometry": {"coordinates":[-0.389356,50.819412],"type":"Point"}
}