{
  "type": "Feature",
  "properties": {
    "addr:full":"King Street Market Rasen Lincolnshire LN8 3BB",
    "addr:postcode":"ln8 3bb",
    "addr:street":"King Street",
    "iso:country":"GB",
    "sg:address":"King Street",
    "sg:city":"Market Rasen",
    "sg:classifiers":[
        {
            "category":"Place Of Worship",
            "type":"Public Place"
        }
    ],
    "sg:phone":"+44 1673 842455",
    "sg:postcode":"LN8 3BB",
    "sg:province":"Lincolnshire",
    "wof:name":"Holyrood Catholic Church",
    "wof:placetype":"venue"
},
  "geometry": {"coordinates":[-0.33841,53.387928],"type":"Point"}
}