{
  "type": "Feature",
  "properties": {
    "addr:full":"137 Lozells Rd Birmingham West Midlands B19 2TP",
    "addr:housenumber":"137",
    "addr:postcode":"b19 2tp",
    "addr:street":"Lozells Rd",
    "iso:country":"GB",
    "sg:address":"137 Lozells Rd",
    "sg:city":"Birmingham",
    "sg:classifiers":[
        {
            "category":"Shopping",
            "subcategory":"Department Store",
            "type":"Retail Goods"
        }
    ],
    "sg:phone":"+44 121 554 8048",
    "sg:postcode":"B19 2TP",
    "sg:province":"West Midlands",
    "wof:name":"DLB Supermarket",
    "wof:placetype":"venue"
},
  "geometry": {"coordinates":[-1.9078739882,52.5030288696],"type":"Point"}
}