{
  "type": "Feature",
  "properties": {
    "addr:full":"Spectrum House, Lower Oakham Way Mansfield Nottinghamshire NG18 5BY",
    "addr:postcode":"ng18 5by",
    "addr:street":"Lower Oakham Way",
    "iso:country":"GB",
    "sg:address":"Spectrum House, Lower Oakham Way",
    "sg:city":"Mansfield",
    "sg:classifiers":[
        {
            "category":"Building & Trades",
            "subcategory":"Cleaning & Sanitation",
            "type":"Services"
        },
        {
            "category":"Insurance",
            "subcategory":"Hazard Insurance",
            "type":"Services"
        },
        {
            "category":"Home & Garden",
            "subcategory":"Carpets & Floor Coverings",
            "type":"Retail Goods"
        }
    ],
    "sg:phone":"+44 1623 422488",
    "sg:postcode":"NG18 5BY",
    "sg:province":"Nottinghamshire",
    "sg:tags":[
        "fire",
        "cleaner",
        "upholstery",
        "water",
        "damage"
    ],
    "wof:name":"Rainbow International",
    "wof:placetype":"venue"
},
  "geometry": {"coordinates":[-1.215774,53.128422],"type":"Point"}
}