{
  "type": "Feature",
  "properties": {
    "iso:country":"GB",
    "sg:address":"Beck Road",
    "sg:city":"Sheffield",
    "sg:classifiers":[
        {
            "category":"Education",
            "subcategory":"School",
            "type":"Public Place"
        },
        {
            "category":"Government",
            "subcategory":"Office",
            "type":"Public Place"
        }
    ],
    "sg:phone":"+44 114 246 7536",
    "sg:postcode":"S5 0GG",
    "sg:province":"South Yorkshire",
    "sg:tags":[
        "local",
        "authority"
    ],
    "wof:name":"Beck Primary School",
    "wof:placetype":"venue"
},
  "geometry": {"coordinates":[-1.444832,53.435211],"type":"Point"}
}