{
  "type": "Feature",
  "properties": {
    "iso:country":"GB",
    "sg:address":"Estuary Ho, 196 Ballards Rd",
    "sg:city":"Dagenham",
    "sg:classifiers":[
        {
            "category":"Professional",
            "subcategory":"Computer Services",
            "type":"Services"
        }
    ],
    "sg:postcode":"RM10 9AB",
    "sg:province":"Essex",
    "sg:tags":[
        "consultant",
        "system",
        "software"
    ],
    "wof:name":"Eastfield Computer Academy",
    "wof:placetype":"venue"
},
  "geometry": {"coordinates":[0.147961,51.541618],"type":"Point"}
}