{
  "type": "Feature",
  "properties": {
    "iso:country":"GB",
    "sg:address":"128 Kentish Town Road",
    "sg:city":"London",
    "sg:classifiers":[
        {
            "category":"Home & Garden",
            "subcategory":"Household Appliances",
            "type":"Retail Goods"
        }
    ],
    "sg:phone":"+44 20 7485 1841",
    "sg:postcode":"NW1 9QB",
    "sg:province":"Greater London",
    "sg:tags":[
        "domestic",
        "centre"
    ],
    "wof:name":"B A R Electrical",
    "wof:placetype":"venue"
},
  "geometry": {"coordinates":[-0.141506,51.545895],"type":"Point"}
}