{
  "type": "Feature",
  "properties": {
    "iso:country":"GB",
    "sg:address":"3rd Floor, Warwick House",
    "sg:city":"London",
    "sg:classifiers":[
        {
            "category":"Real Estate",
            "subcategory":"Architect",
            "type":"Services"
        }
    ],
    "sg:phone":"+44 20 7246 2970",
    "sg:postcode":"EC4R 1EB",
    "sg:province":"Greater London",
    "wof:name":"Insight Architecture Ltd.",
    "wof:placetype":"venue"
},
  "geometry": {"coordinates":[-0.09265,51.511559],"type":"Point"}
}