{
  "type": "Feature",
  "properties": {
    "iso:country":"GB",
    "sg:address":"Unit 9 Sedgway Business Park, Common Road",
    "sg:city":"Ely",
    "sg:classifiers":[
        {
            "category":"Communications",
            "type":"Services"
        }
    ],
    "sg:phone":"+44 1353 668976",
    "sg:postcode":"CB6 2HY",
    "sg:province":"Cambridgeshire",
    "sg:tags":[
        "data",
        "network"
    ],
    "wof:name":"Network Solutions",
    "wof:placetype":"venue"
},
  "geometry": {"coordinates":[0.2062799931,52.3877487183],"type":"Point"}
}