{
  "type": "Feature",
  "properties": {
    "addr:full":"Unit 6, Viewfield Park, Viewfield Larkhall South Lanarkshire ML9 2PD",
    "addr:housenumber":"unit 6",
    "addr:postcode":"ml9 2pd",
    "addr:street":"Viewfield Park",
    "iso:country":"GB",
    "sg:address":"Unit 6, Viewfield Park, Viewfield",
    "sg:city":"Larkhall",
    "sg:classifiers":[
        {
            "category":"Freight",
            "type":"Transportation"
        }
    ],
    "sg:phone":"+44 1236 425566",
    "sg:postcode":"ML9 2PD",
    "sg:province":"South Lanarkshire",
    "sg:tags":[
        "haulage",
        "road"
    ],
    "wof:name":"Norfolkline Ltd",
    "wof:placetype":"venue"
},
  "geometry": {"coordinates":[-3.9636490345,55.7222900391],"type":"Point"}
}