{
  "type": "Feature",
  "properties": {
    "addr:full":"Burdon Terrace Bedlington Northumberland NE22 6DA",
    "addr:postcode":"ne22 6da",
    "addr:street":"Burdon Terrace",
    "iso:country":"GB",
    "sg:address":"Burdon Terrace",
    "sg:city":"Bedlington",
    "sg:classifiers":[
        {
            "category":"Bars & Pubs",
            "type":"Food & Drink"
        }
    ],
    "sg:phone":"+44 1670 822214",
    "sg:postcode":"NE22 6DA",
    "sg:province":"Northumberland",
    "sg:tags":[
        "pubs",
        "inn"
    ],
    "wof:name":"Whitbread Hotel Co. Ltd.",
    "wof:placetype":"venue"
},
  "geometry": {"coordinates":[-1.6016470194,55.1321144104],"type":"Point"}
}