{
  "type": "Feature",
  "properties": {
    "iso:country":"GB",
    "sg:address":"High Street, New Rattray",
    "sg:city":"Blairgowrie",
    "sg:classifiers":[
        {
            "category":"Food & Beverages",
            "subcategory":"Bakery",
            "type":"Retail Goods"
        }
    ],
    "sg:postcode":"PH10 7BT",
    "sg:province":"Perth and Kinross",
    "sg:tags":[
        "confectionery"
    ],
    "wof:name":"Crichton  R & Son",
    "wof:placetype":"venue"
},
  "geometry": {"coordinates":[-3.322854,56.596321],"type":"Point"}
}