{
  "type": "Feature",
  "properties": {
    "addr:full":"56 Windsor Road Penarth The Vale of Glamorgan CF64 1JJ",
    "addr:housenumber":"56",
    "addr:postcode":"cf64 1jj",
    "addr:street":"Windsor Road;Vale",
    "iso:country":"GB",
    "sg:address":"56 Windsor Road",
    "sg:city":"Penarth",
    "sg:classifiers":[
        {
            "category":"Retail",
            "subcategory":"Auto Repair",
            "type":"Services"
        }
    ],
    "sg:phone":"+44 29 2070 3026",
    "sg:postcode":"CF64 1JJ",
    "sg:province":"The Vale of Glamorgan",
    "sg:tags":[
        "modification",
        "garage"
    ],
    "wof:name":"Monty Smith (Penarth) Ltd.",
    "wof:placetype":"venue"
},
  "geometry": {"coordinates":[-3.1773149967,51.4396286011],"type":"Point"}
}