{
  "type": "Feature",
  "properties": {
    "iso:country":"GB",
    "sg:address":"Inglenook Cottage, Heath Road",
    "sg:city":"Whitchurch",
    "sg:classifiers":[
        {
            "category":"Food & Beverages",
            "subcategory":"Specialty",
            "type":"Retail Goods"
        }
    ],
    "sg:postcode":"SY13 2AE",
    "sg:province":"Cheshire",
    "sg:tags":[
        "product",
        "health"
    ],
    "wof:name":"Healthcare International",
    "wof:placetype":"venue"
},
  "geometry": {"coordinates":[-2.685209,52.970558],"type":"Point"}
}