{
  "type": "Feature",
  "properties": {
    "addr:full":"104-106 Kings Avenue, Holland On Sea Clacton-on-sea Essex CO15 5EP",
    "addr:housenumber":"104-106",
    "addr:postcode":"co15 5ep",
    "addr:street":"Kings Avenue",
    "iso:country":"GB",
    "sg:address":"104-106 Kings Avenue, Holland On Sea",
    "sg:city":"Clacton-on-sea",
    "sg:classifiers":[
        {
            "category":"Professional",
            "subcategory":"Lawyer & Legal Services",
            "type":"Services"
        }
    ],
    "sg:phone":"+44 1255 815888",
    "sg:postcode":"CO15 5EP",
    "sg:province":"Essex",
    "sg:tags":[
        "solicitor"
    ],
    "wof:name":"Alistair Keeble Solicitors",
    "wof:placetype":"venue"
},
  "geometry": {"coordinates":[1.1819390059,51.8027229309],"type":"Point"}
}