{
  "type": "Feature",
  "properties": {
    "addr:full":"2 Harrow Lane Maidenhead Berkshire SL6 7PE",
    "addr:housenumber":"2",
    "addr:postcode":"sl6 7pe",
    "addr:street":"Harrow Lane",
    "iso:country":"GB",
    "sg:address":"2 Harrow Lane",
    "sg:city":"Maidenhead",
    "sg:classifiers":[
        {
            "category":"Bars & Pubs",
            "type":"Food & Drink"
        }
    ],
    "sg:phone":"+44 1628 623033",
    "sg:postcode":"SL6 7PE",
    "sg:province":"Berkshire",
    "sg:tags":[
        "pubs",
        "inn"
    ],
    "wof:name":"The Farmers Boy",
    "wof:placetype":"venue"
},
  "geometry": {"coordinates":[-0.725604,51.533237],"type":"Point"}
}