{
  "type": "Feature",
  "properties": {
    "addr:full":"Morgan Arcade Chambers, 33 St Mary Street Cardiff Cardiff CF10 1AF",
    "addr:housenumber":"33",
    "addr:postcode":"cf10 1af",
    "addr:street":"St Mary Street",
    "iso:country":"GB",
    "sg:address":"Morgan Arcade Chambers, 33 St Mary Street",
    "sg:city":"Cardiff",
    "sg:classifiers":[
        {
            "category":"Professional",
            "subcategory":"Lawyer & Legal Services",
            "type":"Services"
        },
        {
            "category":"Professional",
            "subcategory":"Business Services",
            "type":"Services"
        }
    ],
    "sg:phone":"+44 29 2022 9526",
    "sg:postcode":"CF10 1AF",
    "sg:province":"Cardiff",
    "sg:tags":[
        "patent",
        "mark",
        "agent",
        "trade"
    ],
    "wof:name":"Wynne-Jones Laine & James",
    "wof:placetype":"venue"
},
  "geometry": {"coordinates":[-3.180669,51.481258],"type":"Point"}
}