{
  "type": "Feature",
  "properties": {
    "iso:country":"GB",
    "sg:address":"89 Week St",
    "sg:city":"Maidstone",
    "sg:classifiers":[
        {
            "category":"Shopping",
            "subcategory":"Pharmacy",
            "type":"Retail Goods"
        }
    ],
    "sg:phone":"+44 1622 687868",
    "sg:postcode":"ME14 1QX",
    "sg:province":"Kent",
    "sg:tags":[
        "medicine",
        "therapy"
    ],
    "wof:name":"Herbmedic",
    "wof:placetype":"venue"
},
  "geometry": {"coordinates":[0.52188,51.276535],"type":"Point"}
}