{
  "type": "Feature",
  "properties": {
    "addr:full":"71 Novers Hill, Knowle Bristol City of Bristol BS4 1QX",
    "addr:housenumber":"71",
    "addr:postcode":"bs4 1qx",
    "addr:street":"Novers Hill",
    "iso:country":"GB",
    "sg:address":"71 Novers Hill, Knowle",
    "sg:city":"Bristol",
    "sg:classifiers":[
        {
            "category":"Manufacturing",
            "subcategory":"Signs",
            "type":"Manufacturing & Wholesale Goods"
        }
    ],
    "sg:phone":"+44 117 963 3432",
    "sg:postcode":"BS4 1QX",
    "sg:province":"City of Bristol",
    "sg:tags":[
        "writer"
    ],
    "wof:name":"Gerald Ellis",
    "wof:placetype":"venue"
},
  "geometry": {"coordinates":[-2.5993978977,51.4262199402],"type":"Point"}
}