{
  "type": "Feature",
  "properties": {
    "iso:country":"GB",
    "sg:address":"Unit 1, Trench Lock 3",
    "sg:city":"Telford",
    "sg:classifiers":[
        {
            "category":"Professional",
            "type":"Services"
        },
        {
            "category":"Shopping",
            "subcategory":"News",
            "type":"Retail Goods"
        }
    ],
    "sg:phone":"+44 1952 255111",
    "sg:postcode":"TF1 4ST",
    "sg:province":"Shropshire",
    "sg:tags":[
        "newsagent",
        "caterer"
    ],
    "wof:name":"Hammonds Catering",
    "wof:placetype":"venue"
},
  "geometry": {"coordinates":[-2.467239,52.707497],"type":"Point"}
}