{
  "type": "Feature",
  "properties": {
    "addr:full":"45 Parkways Gro Leeds West Yorkshire LS26 8TP",
    "addr:postcode":"ls26 8tp",
    "addr:street":"45 Parkways",
    "iso:country":"GB",
    "sg:address":"45 Parkways Gro",
    "sg:city":"Leeds",
    "sg:classifiers":[
        {
            "category":"Building & Trades",
            "subcategory":"Construction",
            "type":"Services"
        }
    ],
    "sg:phone":"+44 113 282 6830",
    "sg:postcode":"LS26 8TP",
    "sg:province":"West Yorkshire",
    "sg:tags":[
        "platform",
        "work",
        "scaffolding"
    ],
    "wof:name":"Rothwell Scaffolding",
    "wof:placetype":"venue"
},
  "geometry": {"coordinates":[-1.4556219578,53.7506332397],"type":"Point"}
}