{
  "type": "Feature",
  "properties": {
    "iso:country":"GB",
    "sg:address":"192 Solihull Rd, Shirley",
    "sg:city":"Solihull",
    "sg:classifiers":[
        {
            "category":"Professional",
            "subcategory":"Business Services",
            "type":"Services"
        }
    ],
    "sg:postcode":"B90 3LG",
    "sg:province":"West Midlands",
    "sg:tags":[
        "agent",
        "manufacturers'"
    ],
    "wof:name":"Smith,Derek,",
    "wof:placetype":"venue"
},
  "geometry": {"coordinates":[-1.8107270002,52.4131622314],"type":"Point"}
}