{
  "type": "Feature",
  "properties": {
    "iso:country":"GB",
    "sg:address":"122 High Street, Cuminestown",
    "sg:city":"Turriff",
    "sg:classifiers":[
        {
            "category":"Bus Charters",
            "type":"Transportation"
        },
        {
            "category":"Military Area",
            "subcategory":"Air Force Base",
            "type":"Public Place"
        }
    ],
    "sg:phone":"+44 1888 544362",
    "sg:postcode":"AB53 5YH",
    "sg:province":"Aberdeenshire",
    "sg:tags":[
        "taxi",
        "hire",
        "coach",
        "private"
    ],
    "wof:name":"W & G TAXIS",
    "wof:placetype":"venue"
},
  "geometry": {"coordinates":[-2.3220009804,57.5440559387],"type":"Point"}
}