{
  "type": "Feature",
  "properties": {
    "addr:full":"Flat 89 King House, Du Cane Road London Greater London W12 0UD",
    "addr:housenumber":"flat 89",
    "addr:postcode":"road;w12 0ud",
    "addr:street":"King House Du Cane",
    "iso:country":"GB",
    "sg:address":"Flat 89 King House, Du Cane Road",
    "sg:city":"London",
    "sg:classifiers":[
        {
            "category":"Health Services",
            "subcategory":"Nursing And Care Facility",
            "type":"Services"
        },
        {
            "category":"Organizations",
            "subcategory":"Community Association",
            "type":"Services"
        }
    ],
    "sg:phone":"+44 20 8735 4990",
    "sg:postcode":"W12 0UD",
    "sg:province":"Greater London",
    "sg:tags":[
        "residential",
        "housing",
        "society"
    ],
    "wof:name":"Ducane Housing Association Ltd",
    "wof:placetype":"venue"
},
  "geometry": {"coordinates":[-0.2336699963,51.5161590576],"type":"Point"}
}