{
  "type": "Feature",
  "properties": {
    "iso:country":"GB",
    "sg:address":"Unit 26 Strathclyde Business Cntr, 20 Pottery Street",
    "sg:city":"Greenock",
    "sg:classifiers":[
        {
            "category":"Education",
            "subcategory":"Special Training",
            "type":"Public Place"
        }
    ],
    "sg:phone":"+44 1475 741348",
    "sg:postcode":"PA15 2UH",
    "sg:province":"Inverclyde",
    "sg:tags":[
        "product",
        "centre"
    ],
    "wof:name":"Spring Skills",
    "wof:placetype":"venue"
},
  "geometry": {"coordinates":[-4.724529,55.941662],"type":"Point"}
}