{
  "type": "Feature",
  "properties": {
    "iso:country":"GB",
    "sg:address":"13 North St",
    "sg:city":"Chichester",
    "sg:classifiers":[
        {
            "category":"Communications",
            "subcategory":"Film & Video Production",
            "type":"Services"
        }
    ],
    "sg:phone":"+44 1243 785630",
    "sg:postcode":"PO19 1LB",
    "sg:province":"West Sussex",
    "sg:tags":[
        "tv"
    ],
    "wof:name":"Granada Home Technology",
    "wof:placetype":"venue"
},
  "geometry": {"coordinates":[-0.778925,50.837143],"type":"Point"}
}