{
  "type": "Feature",
  "properties": {
    "iso:country":"GB",
    "sg:address":"4 Ashcombe Terr, Oatfield Rd",
    "sg:city":"Tadworth",
    "sg:classifiers":[
        {
            "category":"Professional",
            "subcategory":"Engineering",
            "type":"Services"
        }
    ],
    "sg:postcode":"KT20 5EW",
    "sg:province":"Surrey",
    "sg:tags":[
        "civil",
        "engineer"
    ],
    "wof:name":"P G McCarthy",
    "wof:placetype":"venue"
},
  "geometry": {"coordinates":[-0.2408290058,51.2995147705],"type":"Point"}
}