{
  "type": "Feature",
  "properties": {
    "addr:full":", Modbury Ivybridge Devon PL21 0SB",
    "addr:postcode":"pl21 0sb",
    "iso:country":"GB",
    "sg:address":", Modbury",
    "sg:city":"Ivybridge",
    "sg:classifiers":[
        {
            "category":"Recreation",
            "subcategory":"Campground",
            "type":"Entertainment"
        }
    ],
    "sg:phone":"+44 1548 830542",
    "sg:postcode":"PL21 0SB",
    "sg:province":"Devon",
    "sg:tags":[
        "caravan",
        "park"
    ],
    "wof:name":"Pennymoor Camping & Caravan Park",
    "wof:placetype":"venue"
},
  "geometry": {"coordinates":[-3.8962869644,50.3772201538],"type":"Point"}
}