{
  "type": "Feature",
  "properties": {
    "iso:country":"GB",
    "sg:address":"618 Harrogate Road",
    "sg:city":"Leeds",
    "sg:classifiers":[
        {
            "category":"Bars & Pubs",
            "type":"Food & Drink"
        }
    ],
    "sg:phone":"+44 113 237 0100",
    "sg:postcode":"LS17 8EH",
    "sg:province":"North Yorkshire",
    "sg:tags":[
        "pubs",
        "inn"
    ],
    "wof:name":"The Lord Darcy",
    "wof:placetype":"venue"
},
  "geometry": {"coordinates":[-1.530266,53.8564],"type":"Point"}
}