{
  "type": "Feature",
  "properties": {
    "iso:country":"GB",
    "sg:address":"36 Cinque Ports Street",
    "sg:city":"Rye",
    "sg:classifiers":[
        {
            "category":"Personal",
            "subcategory":"Beauty Salon",
            "type":"Services"
        },
        {
            "category":"Health Services",
            "subcategory":"Health Practitioner",
            "type":"Services"
        }
    ],
    "sg:postcode":"TN31 7AN",
    "sg:province":"East Sussex",
    "sg:tags":[
        "unisex",
        "homoeopathic",
        "hairdresser"
    ],
    "wof:name":"The Ria Retreat",
    "wof:placetype":"venue"
},
  "geometry": {"coordinates":[0.7336230278,50.9523544312],"type":"Point"}
}