{
  "type": "Feature",
  "properties": {
    "iso:country":"GB",
    "sg:address":"8 Dryden Avenue",
    "sg:city":"Bicester",
    "sg:classifiers":[
        {
            "category":"Professional",
            "subcategory":"Computer Services",
            "type":"Services"
        }
    ],
    "sg:postcode":"OX26 2NJ",
    "sg:province":"Oxfordshire",
    "sg:tags":[
        "system",
        "software"
    ],
    "wof:name":"S J A  Enterprises Ltd.",
    "wof:placetype":"venue"
},
  "geometry": {"coordinates":[-1.173824,51.907288],"type":"Point"}
}