{
  "type": "Feature",
  "properties": {
    "iso:country":"GB",
    "sg:address":"235 Broad Street",
    "sg:city":"Crewe",
    "sg:classifiers":[
        {
            "category":"Cinema",
            "subcategory":"Movie Rental",
            "type":"Entertainment"
        }
    ],
    "sg:phone":"+44 1270 214737",
    "sg:postcode":"CW1 4JJ",
    "sg:province":"Cheshire",
    "sg:tags":[
        "video",
        "library"
    ],
    "wof:name":"The Video Zone",
    "wof:placetype":"venue"
},
  "geometry": {"coordinates":[-2.441523,53.110584],"type":"Point"}
}