{
  "type": "Feature",
  "properties": {
    "addr:full":"471 Northumberland Avenue Reading Berkshire RG2 8LZ",
    "addr:housenumber":"471",
    "addr:postcode":"rg2 8lz",
    "addr:street":"Northumberland Avenue",
    "iso:country":"GB",
    "sg:address":"471 Northumberland Avenue",
    "sg:city":"Reading",
    "sg:classifiers":[
        {
            "category":"Fast Food",
            "type":"Food & Drink"
        }
    ],
    "sg:phone":"+44 118 987 6644",
    "sg:postcode":"RG2 8LZ",
    "sg:province":"Berkshire",
    "sg:tags":[
        "away",
        "meal",
        "outlet",
        "take"
    ],
    "wof:name":"Kings Garden Takeaway",
    "wof:placetype":"venue"
},
  "geometry": {"coordinates":[-0.9590950012,51.4230728149],"type":"Point"}
}