{
  "type": "Feature",
  "properties": {
    "addr:full":"117 Trafalgar Rd Greenwich Greater London SE10 9TX",
    "addr:housenumber":"117",
    "addr:postcode":"se10 9tx",
    "addr:street":"Trafalgar Rd",
    "iso:country":"GB",
    "sg:address":"117 Trafalgar Rd",
    "sg:city":"Greenwich",
    "sg:classifiers":[
        {
            "category":"Professional",
            "type":"Services"
        }
    ],
    "sg:phone":"+44 20 8480 8553",
    "sg:postcode":"SE10 9TX",
    "sg:province":"Greater London",
    "sg:tags":[
        "repair",
        "tech",
        "maintenance"
    ],
    "wof:name":"Nano Tech Computers",
    "wof:placetype":"venue"
},
  "geometry": {"coordinates":[0.0031039999,51.484703064],"type":"Point"}
}