{
  "type": "Feature",
  "properties": {
    "iso:country":"GB",
    "sg:address":"64b Dukesway, Teesside Indust Estate",
    "sg:city":"Stockton On Tees",
    "sg:classifiers":[
        {
            "category":"Professional",
            "subcategory":"Engineering",
            "type":"Services"
        }
    ],
    "sg:phone":"+44 1642 751399",
    "sg:postcode":"TS17 9LT",
    "sg:province":"Durham",
    "sg:tags":[
        "contractor",
        "electrical",
        "engineer"
    ],
    "wof:name":"C I S Cable Installation Services",
    "wof:placetype":"venue"
},
  "geometry": {"coordinates":[-1.292764,54.51828],"type":"Point"}
}