{
  "type": "Feature",
  "properties": {
    "addr:full":"Princess St Stoke On Trent Staffordshire ST8 6JN",
    "addr:postcode":"st8 6jn",
    "addr:street":"Princess St",
    "iso:country":"GB",
    "sg:address":"Princess St",
    "sg:city":"Stoke On Trent",
    "sg:classifiers":[
        {
            "category":"Health Services",
            "subcategory":"Clinic",
            "type":"Services"
        }
    ],
    "sg:phone":"+44 1782 427800",
    "sg:postcode":"ST8 6JN",
    "sg:province":"Staffordshire",
    "sg:tags":[
        "nh"
    ],
    "wof:name":"Biddulph Community Health Centre",
    "wof:placetype":"venue"
},
  "geometry": {"coordinates":[-2.1710920334,53.1134414673],"type":"Point"}
}