{
  "type": "Feature",
  "properties": {
    "addr:full":"1325 Duke Street Glasgow Glasgow City G31 5PN",
    "addr:housenumber":"1325",
    "addr:postcode":"g31 5pn",
    "addr:street":"Duke Street",
    "iso:country":"GB",
    "sg:address":"1325 Duke Street",
    "sg:city":"Glasgow",
    "sg:classifiers":[
        {
            "category":"Bars & Pubs",
            "type":"Food & Drink"
        }
    ],
    "sg:phone":"+44 141 556 1381",
    "sg:postcode":"G31 5PN",
    "sg:province":"Glasgow City",
    "sg:tags":[
        "pubs",
        "inn"
    ],
    "wof:name":"The Pippin Bar",
    "wof:placetype":"venue"
},
  "geometry": {"coordinates":[-4.2014188766,55.8568916321],"type":"Point"}
}