{
  "type": "Feature",
  "properties": {
    "iso:country":"GB",
    "sg:address":"47 Holmlea Road, Goring",
    "sg:city":"Reading",
    "sg:classifiers":[
        {
            "category":"Professional",
            "subcategory":"Computer Services",
            "type":"Services"
        }
    ],
    "sg:phone":"+44 1491 872812",
    "sg:postcode":"RG8 9EX",
    "sg:province":"Berkshire",
    "sg:tags":[
        "system",
        "software"
    ],
    "wof:name":"Vertex Systems Ltd.",
    "wof:placetype":"venue"
},
  "geometry": {"coordinates":[-1.1335450411,51.5186767578],"type":"Point"}
}