{
  "type": "Feature",
  "properties": {
    "addr:full":"94 Broad St Birmingham West Midlands B15 1AU",
    "addr:housenumber":"94",
    "addr:postcode":"b15 1au",
    "addr:street":"Broad St",
    "iso:country":"GB",
    "sg:address":"94 Broad St",
    "sg:city":"Birmingham",
    "sg:classifiers":[
        {
            "category":"Professional",
            "subcategory":"Lawyer & Legal Services",
            "type":"Services"
        }
    ],
    "sg:postcode":"B15 1AU",
    "sg:province":"West Midlands",
    "sg:tags":[
        "solicitor"
    ],
    "wof:name":"Bickley Wheatley & Co",
    "wof:placetype":"venue"
},
  "geometry": {"coordinates":[-1.9144999981,52.4752006531],"type":"Point"}
}