{
  "type": "Feature",
  "properties": {
    "iso:country":"GB",
    "sg:address":"94 Broad St",
    "sg:city":"Birmingham",
    "sg:classifiers":[
        {
            "category":"Professional",
            "subcategory":"Lawyer & Legal Services",
            "type":"Services"
        }
    ],
    "sg:postcode":"B15 1AU",
    "sg:province":"West Midlands",
    "sg:tags":[
        "solicitor"
    ],
    "wof:name":"Bickley Wheatley & Co",
    "wof:placetype":"venue"
},
  "geometry": {"coordinates":[-1.9144999981,52.4752006531],"type":"Point"}
}