{
  "type": "Feature",
  "properties": {
    "iso:country":"GB",
    "sg:address":"3 Carisbrooke Drive",
    "sg:city":"Southampton",
    "sg:classifiers":[
        {
            "category":"Building & Trades",
            "subcategory":"Construction",
            "type":"Services"
        }
    ],
    "sg:postcode":"SO19 7BE",
    "sg:province":"Hampshire",
    "sg:tags":[
        "decorator",
        "painter"
    ],
    "wof:name":"I C D",
    "wof:placetype":"venue"
},
  "geometry": {"coordinates":[-1.362868,50.911499],"type":"Point"}
}