{
  "type": "Feature",
  "properties": {
    "addr:full":"19 Peghouse Rise Stroud Gloucestershire GL5 1RU",
    "addr:housenumber":"19",
    "addr:postcode":"gl5 1ru",
    "addr:street":"Peghouse Rise",
    "iso:country":"GB",
    "sg:address":"19 Peghouse Rise",
    "sg:city":"Stroud",
    "sg:classifiers":[
        {
            "category":"Professional",
            "subcategory":"Secretarial Services",
            "type":"Services"
        },
        {
            "category":"Taxi",
            "type":"Transportation"
        },
        {
            "category":"Home & Garden",
            "subcategory":"Carpets & Floor Coverings",
            "type":"Retail Goods"
        }
    ],
    "sg:phone":"+44 1453 766917",
    "sg:postcode":"GL5 1RU",
    "sg:province":"Gloucestershire",
    "sg:tags":[
        "cleaner",
        "hire",
        "upholstery",
        "private",
        "vehicle"
    ],
    "wof:name":"David Chandler",
    "wof:placetype":"venue"
},
  "geometry": {"coordinates":[-2.204295,51.752495],"type":"Point"}
}