{
  "type": "Feature",
  "properties": {
    "addr:full":"57 Cheapside Luton Bedfordshire LU1 2HN",
    "addr:housenumber":"57",
    "addr:postcode":"lu1 2hn",
    "addr:street":"Cheapside",
    "iso:country":"GB",
    "sg:address":"57 Cheapside",
    "sg:city":"Luton",
    "sg:classifiers":[
        {
            "category":"Professional",
            "subcategory":"Art Services",
            "type":"Services"
        }
    ],
    "sg:phone":"+44 1582 723135",
    "sg:postcode":"LU1 2HN",
    "sg:province":"Bedfordshire",
    "sg:tags":[
        "photographer"
    ],
    "wof:name":"Glen Smith Studios",
    "wof:placetype":"venue"
},
  "geometry": {"coordinates":[-0.4139589965,51.8807067871],"type":"Point"}
}