{
  "type": "Feature",
  "properties": {
    "addr:full":"128 Meads Lane Ilford Essex IG3 8PE",
    "addr:housenumber":"128",
    "addr:postcode":"ig3 8pe",
    "addr:street":"Meads Lane",
    "iso:country":"GB",
    "sg:address":"128 Meads Lane",
    "sg:city":"Ilford",
    "sg:classifiers":[
        {
            "category":"Health Services",
            "subcategory":"Health Practitioner",
            "type":"Services"
        }
    ],
    "sg:postcode":"IG3 8PE",
    "sg:province":"Essex",
    "sg:tags":[
        "psychotherapist"
    ],
    "wof:name":"Sharon Gilbert",
    "wof:placetype":"venue"
},
  "geometry": {"coordinates":[0.1005470008,51.5709114075],"type":"Point"}
}