{
  "type": "Feature",
  "properties": {
    "addr:full":"Unit 2 Lighterage Hill, Newham Industrial Estate Truro Cornwall TR1 2DP",
    "addr:housenumber":"unit 2",
    "addr:postcode":"tr1 2dp",
    "addr:street":"Lighterage Hill;Industrial Estate",
    "iso:country":"GB",
    "sg:address":"Unit 2 Lighterage Hill, Newham Industrial Estate",
    "sg:city":"Truro",
    "sg:classifiers":[
        {
            "category":"Retail",
            "subcategory":"Auto Repair",
            "type":"Services"
        }
    ],
    "sg:postcode":"TR1 2DP",
    "sg:province":"Cornwall",
    "sg:tags":[
        "modification",
        "garage"
    ],
    "wof:name":"City M O T's",
    "wof:placetype":"venue"
},
  "geometry": {"coordinates":[-5.043885231,50.2520446777],"type":"Point"}
}