{
  "type": "Feature",
  "properties": {
    "iso:country":"GB",
    "sg:address":"16 Colchester Road, Easington",
    "sg:city":"Saltburn-by-the-sea",
    "sg:classifiers":[
        {
            "category":"Building & Trades",
            "subcategory":"Construction",
            "type":"Services"
        }
    ],
    "sg:postcode":"TS13 4NG",
    "sg:province":"North Yorkshire",
    "sg:tags":[
        "joiner",
        "carpenter"
    ],
    "wof:name":"Alfred R Fox",
    "wof:placetype":"venue"
},
  "geometry": {"coordinates":[-0.8532519937,54.5540161133],"type":"Point"}
}