{
  "type": "Feature",
  "properties": {
    "iso:country":"GB",
    "sg:address":"8 Highland Court, Bryncethin",
    "sg:city":"Bridgend",
    "sg:classifiers":[
        {
            "category":"Professional",
            "subcategory":"Business Services",
            "type":"Services"
        }
    ],
    "sg:phone":"+44 1656 720001",
    "sg:postcode":"CF32 9US",
    "sg:province":"Bridgend",
    "wof:name":"K J Business Solutions",
    "wof:placetype":"venue"
},
  "geometry": {"coordinates":[-3.567839,51.549538],"type":"Point"}
}