{
  "type": "Feature",
  "properties": {
    "addr:full":"2 Polton Street Bonnyrigg Midlothian EH19 3HA",
    "addr:housenumber":"2",
    "addr:postcode":"eh19 3ha",
    "addr:street":"Polton Street",
    "iso:country":"GB",
    "sg:address":"2 Polton Street",
    "sg:city":"Bonnyrigg",
    "sg:classifiers":[
        {
            "category":"Banks & Credit Unions",
            "subcategory":"Financial Services",
            "type":"Services"
        }
    ],
    "sg:phone":"+44 131 654 1497",
    "sg:postcode":"EH19 3HA",
    "sg:province":"Midlothian",
    "sg:tags":[
        "consultant"
    ],
    "wof:name":"Wilson Tupholme Ltd",
    "wof:placetype":"venue"
},
  "geometry": {"coordinates":[-3.1056780815,55.8748321533],"type":"Point"}
}