{
  "type": "Feature",
  "properties": {
    "addr:full":"41 Glamis Road Forfar Angus DD8 1DH",
    "addr:housenumber":"41",
    "addr:postcode":"dd8 1dh",
    "addr:street":"Glamis Road",
    "iso:country":"GB",
    "sg:address":"41 Glamis Road",
    "sg:city":"Forfar",
    "sg:classifiers":[
        {
            "category":"Recreation",
            "subcategory":"Dog Park",
            "type":"Entertainment"
        },
        {
            "category":"Retail",
            "subcategory":"Animal Services",
            "type":"Services"
        }
    ],
    "sg:phone":"+44 1307 469009",
    "sg:postcode":"DD8 1DH",
    "sg:province":"Angus",
    "sg:tags":[
        "grooming",
        "clipping"
    ],
    "wof:name":"Canine Clippers",
    "wof:placetype":"venue"
},
  "geometry": {"coordinates":[-2.8969480991,56.6411476135],"type":"Point"}
}