{
  "type": "Feature",
  "properties": {
    "addr:full":"Blythe Street Tamworth Staffordshire B77 2AB",
    "addr:postcode":"b77 2ab",
    "addr:street":"Blythe Street",
    "iso:country":"GB",
    "sg:address":"Blythe Street",
    "sg:city":"Tamworth",
    "sg:classifiers":[
        {
            "category":"Retail",
            "subcategory":"Storage",
            "type":"Services"
        }
    ],
    "sg:phone":"+44 1827 50426",
    "sg:postcode":"B77 2AB",
    "sg:province":"Staffordshire",
    "sg:tags":[
        "cold",
        "activity",
        "domestic",
        "removal"
    ],
    "wof:name":"Johnson Brothers",
    "wof:placetype":"venue"
},
  "geometry": {"coordinates":[-1.684384,52.629295],"type":"Point"}
}