{
  "type": "Feature",
  "properties": {
    "iso:country":"GB",
    "sg:address":"17a Waverley Road",
    "sg:city":"St Albans",
    "sg:classifiers":[
        {
            "category":"Manufacturing",
            "subcategory":"Wood Products",
            "type":"Manufacturing & Wholesale Goods"
        },
        {
            "category":"Home & Garden",
            "subcategory":"Home Furnishings",
            "type":"Retail Goods"
        },
        {
            "category":"Home & Garden",
            "subcategory":"Building Materials",
            "type":"Retail Goods"
        }
    ],
    "sg:phone":"+44 1727 850921",
    "sg:postcode":"AL3 5PH",
    "sg:province":"Hertfordshire",
    "sg:tags":[
        "planner",
        "installers",
        "furnishers",
        "kitchen",
        "sawmill",
        "shaving"
    ],
    "wof:name":"A E & I E Holsey",
    "wof:placetype":"venue"
},
  "geometry": {"coordinates":[-0.338021,51.759468],"type":"Point"}
}