{
  "type": "Feature",
  "properties": {
    "iso:country":"GB",
    "sg:address":"124 Victoria Rd",
    "sg:city":"Lower Edmonton",
    "sg:classifiers":[
        {
            "category":"Retail",
            "subcategory":"Veterinary Services",
            "type":"Services"
        },
        {
            "category":"Organizations",
            "subcategory":"Non-profit Organization",
            "type":"Services"
        }
    ],
    "sg:phone":"+44 20 8807 3113",
    "sg:postcode":"N9 9SS",
    "sg:province":"Greater London",
    "sg:tags":[
        "organisation",
        "welfare",
        "animal",
        "activity"
    ],
    "wof:name":"Chace Veterinary Group",
    "wof:placetype":"venue"
},
  "geometry": {"coordinates":[-0.066105,51.621307],"type":"Point"}
}