{
  "type": "Feature",
  "properties": {
    "addr:full":"73 Moor End Road, Mellor Stockport Cheshire SK6 5PT",
    "addr:housenumber":"73",
    "addr:postcode":"sk6 5pt",
    "addr:street":"Moor End Road",
    "iso:country":"GB",
    "sg:address":"73 Moor End Road, Mellor",
    "sg:city":"Stockport",
    "sg:classifiers":[
        {
            "category":"Bars & Pubs",
            "type":"Food & Drink"
        }
    ],
    "sg:phone":"+44 161 449 7826",
    "sg:postcode":"SK6 5PT",
    "sg:province":"Cheshire",
    "sg:tags":[
        "pubs",
        "inn"
    ],
    "wof:name":"Oddfellows Arms",
    "wof:placetype":"venue"
},
  "geometry": {"coordinates":[-2.017152,53.393845],"type":"Point"}
}