{
  "type": "Feature",
  "properties": {
    "addr:full":"189-191 Cranbrook Road Ilford Essex IG1 4TA",
    "addr:housenumber":"189-191",
    "addr:postcode":"ig1 4ta",
    "addr:street":"Cranbrook Road",
    "iso:country":"GB",
    "sg:address":"189-191 Cranbrook Road",
    "sg:city":"Ilford",
    "sg:classifiers":[
        {
            "category":"Real Estate",
            "subcategory":"Real Estate Agent",
            "type":"Services"
        }
    ],
    "sg:phone":"+44 20 8518 0044",
    "sg:postcode":"IG1 4TA",
    "sg:province":"Essex",
    "wof:name":"Douglas Allen Spiro",
    "wof:placetype":"venue"
},
  "geometry": {"coordinates":[0.0655540004,51.5669822693],"type":"Point"}
}