{
  "type": "Feature",
  "properties": {
    "addr:full":"22 The Oval Hereford Herefordshire HR2 7HG",
    "addr:housenumber":"22",
    "addr:postcode":"hr2 7hg",
    "addr:street":"The Oval",
    "iso:country":"GB",
    "sg:address":"22 The Oval",
    "sg:city":"Hereford",
    "sg:classifiers":[
        {
            "category":"Shopping",
            "subcategory":"Pets & Pet Supplies",
            "type":"Retail Goods"
        }
    ],
    "sg:phone":"+44 1432 371082",
    "sg:postcode":"HR2 7HG",
    "sg:province":"Herefordshire",
    "wof:name":"Yum Yum Pet Foods",
    "wof:placetype":"venue"
},
  "geometry": {"coordinates":[-2.7304,52.043037],"type":"Point"}
}