{
  "type": "Feature",
  "properties": {
    "addr:full":"10 Cinnamon Row London Greater London SW11 3TW",
    "addr:housenumber":"10",
    "addr:postcode":"sw11 3tw",
    "addr:street":"Cinnamon Row",
    "iso:country":"GB",
    "sg:address":"10 Cinnamon Row",
    "sg:city":"London",
    "sg:classifiers":[
        {
            "category":"Professional",
            "subcategory":"Management & Consulting",
            "type":"Services"
        }
    ],
    "sg:phone":"+44 20 7801 1380",
    "sg:postcode":"SW11 3TW",
    "sg:province":"Greater London",
    "sg:tags":[
        "consultant",
        "business"
    ],
    "wof:name":"Stephen White",
    "wof:placetype":"venue"
},
  "geometry": {"coordinates":[-0.18075,51.466839],"type":"Point"}
}