{
  "type": "Feature",
  "properties": {
    "iso:country":"GB",
    "sg:address":"207 Crookes Valley Road",
    "sg:city":"Sheffield",
    "sg:classifiers":[
        {
            "category":"Food & Beverages",
            "subcategory":"Specialty",
            "type":"Retail Goods"
        },
        {
            "category":"Food & Beverages",
            "subcategory":"Groceries & Convenience Stores",
            "type":"Retail Goods"
        }
    ],
    "sg:phone":"+44 114 268 1662",
    "sg:postcode":"S10 1BA",
    "sg:province":"South Yorkshire",
    "sg:tags":[
        "product",
        "health"
    ],
    "wof:name":"SHEFFIELD WHOLEFOODS LTD",
    "wof:placetype":"venue"
},
  "geometry": {"coordinates":[-1.49356,53.385082],"type":"Point"}
}