{
  "type": "Feature",
  "properties": {
    "iso:country":"GB",
    "sg:address":"6 Shaw Street",
    "sg:city":"Worcester",
    "sg:classifiers":[
        {
            "category":"Manufacturing",
            "subcategory":"Tools & Machinery",
            "type":"Manufacturing & Wholesale Goods"
        }
    ],
    "sg:phone":"+44 1905 26809",
    "sg:postcode":"WR1 3QQ",
    "sg:province":"Worcestershire",
    "sg:tags":[
        "society",
        "friendly"
    ],
    "wof:name":"Town & Country Insurance Services",
    "wof:placetype":"venue"
},
  "geometry": {"coordinates":[-2.2229290009,52.1942825317],"type":"Point"}
}