{
  "type": "Feature",
  "properties": {
    "iso:country":"GB",
    "sg:address":"25 Wellis Gardens",
    "sg:city":"Margate",
    "sg:classifiers":[
        {
            "category":"Building & Trades",
            "subcategory":"Plumbing",
            "type":"Services"
        }
    ],
    "sg:phone":"+44 1843 295808",
    "sg:postcode":"CT9 5RG",
    "sg:province":"Kent",
    "sg:tags":[
        "heating"
    ],
    "wof:name":"R Hazel Heating Contractor",
    "wof:placetype":"venue"
},
  "geometry": {"coordinates":[1.367104,51.381508],"type":"Point"}
}