{
  "type": "Feature",
  "properties": {
    "addr:full":"Dresden House, 1 & 2 College Street Lampeter Carmarthenshire SA48 7DY",
    "addr:housenumber":"1 & 2",
    "addr:postcode":"sa48 7dy",
    "addr:street":"College Street",
    "iso:country":"GB",
    "sg:address":"Dresden House, 1 & 2 College Street",
    "sg:city":"Lampeter",
    "sg:classifiers":[
        {
            "category":"Retail",
            "subcategory":"Funeral Services",
            "type":"Services"
        }
    ],
    "sg:phone":"+44 1570 422673",
    "sg:postcode":"SA48 7DY",
    "sg:province":"Carmarthenshire",
    "wof:name":"Gwylym C Price & Son & Daughters",
    "wof:placetype":"venue"
},
  "geometry": {"coordinates":[-4.0785331726,52.1132888794],"type":"Point"}
}