{
  "type": "Feature",
  "properties": {
    "addr:full":"69 Lythe Fell Ave, Halton Lancaster Lancashire LA2 6NL",
    "addr:housenumber":"69",
    "addr:postcode":"la2 6nl",
    "addr:street":"Lythe Fell Ave",
    "iso:country":"GB",
    "sg:address":"69 Lythe Fell Ave, Halton",
    "sg:city":"Lancaster",
    "sg:classifiers":[
        {
            "category":"Professional",
            "subcategory":"Engineering",
            "type":"Services"
        }
    ],
    "sg:postcode":"LA2 6NL",
    "sg:province":"Lancashire",
    "sg:tags":[
        "contractor",
        "electrical",
        "engineer"
    ],
    "wof:name":"Atkinson,Kenneth,",
    "wof:placetype":"venue"
},
  "geometry": {"coordinates":[-2.751809,54.079861],"type":"Point"}
}