{
  "type": "Feature",
  "properties": {
    "addr:full":"Managers Office, Mount Row Stafford Staffordshire ST16 2AD",
    "addr:postcode":"st16 2ad",
    "addr:street":"Mount Row",
    "iso:country":"GB",
    "sg:address":"Managers Office, Mount Row",
    "sg:city":"Stafford",
    "sg:classifiers":[
        {
            "category":"Commercial Area",
            "type":"Public Place"
        }
    ],
    "sg:phone":"+44 1785 245958",
    "sg:postcode":"ST16 2AD",
    "sg:province":"Staffordshire",
    "sg:tags":[
        "shop",
        "centre"
    ],
    "wof:name":"Sheridan Centre",
    "wof:placetype":"venue"
},
  "geometry": {"coordinates":[-2.121768,52.803959],"type":"Point"}
}