{
  "type": "Feature",
  "properties": {
    "addr:full":"139-141 Hanworth Road Hounslow Greater London TW3 3TN",
    "addr:postcode":"139-141;tw3 3tn",
    "addr:street":"Hanworth Road",
    "iso:country":"GB",
    "sg:address":"139-141 Hanworth Road",
    "sg:city":"Hounslow",
    "sg:classifiers":[
        {
            "category":"Manufacturing",
            "subcategory":"Tools & Machinery",
            "type":"Manufacturing & Wholesale Goods"
        }
    ],
    "sg:phone":"+44 20 8570 8749",
    "sg:postcode":"TW3 3TN",
    "sg:province":"Greater London",
    "wof:name":"J Tyson & Co.",
    "wof:placetype":"venue"
},
  "geometry": {"coordinates":[-0.3631780148,51.4663734436],"type":"Point"}
}