{
  "type": "Feature",
  "properties": {
    "addr:full":"61 Dunnikier Rd Kirkcaldy Fife KY1 2RL",
    "addr:housenumber":"61",
    "addr:postcode":"ky1 2rl",
    "addr:street":"Dunnikier Rd",
    "iso:country":"GB",
    "sg:address":"61 Dunnikier Rd",
    "sg:city":"Kirkcaldy",
    "sg:classifiers":[
        {
            "category":"Manufacturing",
            "subcategory":"Petroleum Products",
            "type":"Manufacturing & Wholesale Goods"
        }
    ],
    "sg:phone":"+44 1592 641818",
    "sg:postcode":"KY1 2RL",
    "sg:province":"Fife",
    "sg:tags":[
        "double",
        "glazing"
    ],
    "wof:name":"Saveheat Quality Windows",
    "wof:placetype":"venue"
},
  "geometry": {"coordinates":[-3.156372,56.11771],"type":"Point"}
}