{
  "type": "Feature",
  "properties": {
    "iso:country":"GB",
    "sg:address":"Hawling",
    "sg:city":"Cheltenham",
    "sg:classifiers":[
        {
            "category":"Place Of Worship",
            "type":"Public Place"
        }
    ],
    "sg:phone":"+44 1242 512271",
    "sg:postcode":"GL54 5SZ",
    "sg:province":"Gloucestershire",
    "wof:name":"Hawling Methodist Church",
    "wof:placetype":"venue"
},
  "geometry": {"coordinates":[-1.90431,51.905048],"type":"Point"}
}