{
  "type": "Feature",
  "properties": {
    "addr:full":"150 Fonthill Road London Greater London N4 3HP",
    "addr:housenumber":"150",
    "addr:postcode":"n4 3hp",
    "addr:street":"Fonthill Road",
    "iso:country":"GB",
    "sg:address":"150 Fonthill Road",
    "sg:city":"London",
    "sg:classifiers":[
        {
            "category":"Shopping",
            "subcategory":"Clothing, Apparel, & Fashions",
            "type":"Retail Goods"
        }
    ],
    "sg:phone":"+44 20 7263 9761",
    "sg:postcode":"N4 3HP",
    "sg:province":"Greater London",
    "sg:tags":[
        "clothing"
    ],
    "wof:name":"Flickers Ladies Clothing",
    "wof:placetype":"venue"
},
  "geometry": {"coordinates":[-0.1082419977,51.5635108948],"type":"Point"}
}