{
  "type": "Feature",
  "properties": {
    "addr:full":"129 Southans Road Bromley Kent BR2 9QT",
    "addr:housenumber":"129",
    "addr:postcode":"br2 9qt",
    "addr:street":"Southans Road",
    "iso:country":"GB",
    "sg:address":"129 Southans Road",
    "sg:city":"Bromley",
    "sg:classifiers":[
        {
            "category":"Organizations",
            "subcategory":"Non-profit Organization",
            "type":"Services"
        }
    ],
    "sg:phone":"+44 20 8464 2897",
    "sg:postcode":"BR2 9QT",
    "sg:province":"Kent",
    "sg:tags":[
        "organisation",
        "voluntary",
        "charity"
    ],
    "wof:name":"Bromley Autistic Trust",
    "wof:placetype":"venue"
},
  "geometry": {"coordinates":[0.0092399996,51.3888511658],"type":"Point"}
}