{
  "type": "Feature",
  "properties": {
    "addr:full":"Garthdee Road, Cults Aberdeen Aberdeen City AB15 9FX",
    "addr:postcode":"ab15 9fx",
    "addr:street":"Garthdee Road",
    "iso:country":"GB",
    "sg:address":"Garthdee Road, Cults",
    "sg:city":"Aberdeen",
    "sg:classifiers":[
        {
            "category":"Travel",
            "subcategory":"Hotels & Motels",
            "type":"Entertainment"
        }
    ],
    "sg:phone":"+44 1224 868951",
    "sg:postcode":"AB15 9FX",
    "sg:province":"Aberdeen City",
    "wof:name":"c/o Norwood Hall Hotel",
    "wof:placetype":"venue"
},
  "geometry": {"coordinates":[-2.1773099899,57.1174468994],"type":"Point"}
}