{
  "type": "Feature",
  "properties": {
    "addr:full":"35 King Street West Manchester Greater Manchester M3 2PW",
    "addr:housenumber":"35",
    "addr:postcode":"m3 2pw",
    "addr:street":"King Street",
    "iso:country":"GB",
    "sg:address":"35 King Street West",
    "sg:city":"Manchester",
    "sg:classifiers":[
        {
            "category":"Shopping",
            "subcategory":"Clothing, Apparel, & Fashions",
            "type":"Retail Goods"
        },
        {
            "category":"Banks & Credit Unions",
            "subcategory":"Investment Brokerage",
            "type":"Services"
        }
    ],
    "sg:phone":"+44 161 832 3670",
    "sg:postcode":"M3 2PW",
    "sg:province":"Greater Manchester",
    "sg:tags":[
        "agency",
        "dress",
        "dresswear"
    ],
    "wof:name":"Elite Dress Agency",
    "wof:placetype":"venue"
},
  "geometry": {"coordinates":[-2.2492148876,53.4816741943],"type":"Point"}
}