{
  "type": "Feature",
  "properties": {
    "iso:country":"GB",
    "sg:address":"45 Latimer Road",
    "sg:city":"Darlington",
    "sg:classifiers":[
        {
            "category":"Home & Garden",
            "subcategory":"Carpets & Floor Coverings",
            "type":"Retail Goods"
        }
    ],
    "sg:postcode":"DL1 2AE",
    "sg:province":"Durham",
    "sg:tags":[
        "cleaner",
        "upholstery"
    ],
    "wof:name":"Extractaclean",
    "wof:placetype":"venue"
},
  "geometry": {"coordinates":[-1.530292,54.538151],"type":"Point"}
}