{
  "type": "Feature",
  "properties": {
    "addr:full":"Princess Of Wales Court, Seaway Drive, Seaway Parade Industrial Estate Port Talbot Neath Port Talbot SA12 7BT",
    "addr:housenumber":"talbot",
    "addr:postcode":"sa12 7bt",
    "addr:street":"Wales Court Seaway Drive Seaway Parade Industrial Estate",
    "iso:country":"GB",
    "sg:address":"Princess Of Wales Court, Seaway Drive, Seaway Parade Industrial Estate",
    "sg:city":"Port Talbot",
    "sg:classifiers":[
        {
            "category":"Home & Garden",
            "subcategory":"Hardware",
            "type":"Retail Goods"
        },
        {
            "category":"Building & Trades",
            "subcategory":"Equipment Rental",
            "type":"Services"
        }
    ],
    "sg:phone":"+44 1639 821414",
    "sg:postcode":"SA12 7BT",
    "sg:province":"Neath Port Talbot",
    "sg:tags":[
        "tool",
        "hire",
        "generator"
    ],
    "wof:name":"Aggreko Generators Ltd",
    "wof:placetype":"venue"
},
  "geometry": {"coordinates":[-3.811384,51.614803],"type":"Point"}
}