{
  "type": "Feature",
  "properties": {
    "iso:country":"GB",
    "sg:address":"37 Station Rd",
    "sg:city":"Hinckley",
    "sg:classifiers":[
        {
            "category":"Health Services",
            "subcategory":"Health Practitioner",
            "type":"Services"
        }
    ],
    "sg:phone":"+44 1455 233484",
    "sg:postcode":"LE10 1AP",
    "sg:province":"Leicestershire",
    "sg:tags":[
        "osteopath"
    ],
    "wof:name":"J M Lloyd-Paine",
    "wof:placetype":"venue"
},
  "geometry": {"coordinates":[-1.3725550175,52.5379905701],"type":"Point"}
}