{
  "type": "Feature",
  "properties": {
    "addr:full":"12a Princess Way Camberley Berkshire GU15 3SP",
    "addr:housenumber":"12a",
    "addr:postcode":"gu15 3sp",
    "addr:street":"Princess Way",
    "iso:country":"GB",
    "sg:address":"12a Princess Way",
    "sg:city":"Camberley",
    "sg:classifiers":[
        {
            "category":"Professional",
            "subcategory":"Employment Agencies",
            "type":"Services"
        }
    ],
    "sg:phone":"+44 1276 21188",
    "sg:postcode":"GU15 3SP",
    "sg:province":"Berkshire",
    "sg:tags":[
        "career",
        "guidance"
    ],
    "wof:name":"Independent Schools Careers Organisation",
    "wof:placetype":"venue"
},
  "geometry": {"coordinates":[-0.7445170283,51.3376693726],"type":"Point"}
}