{
  "type": "Feature",
  "properties": {
    "addr:full":"11 Romwood Avenue, Swinton Mexborough South Yorkshire S64 8DX",
    "addr:housenumber":"11",
    "addr:postcode":"s64 8dx",
    "addr:street":"Romwood Avenue",
    "iso:country":"GB",
    "sg:address":"11 Romwood Avenue, Swinton",
    "sg:city":"Mexborough",
    "sg:classifiers":[
        {
            "category":"Personal",
            "type":"Services"
        }
    ],
    "sg:phone":"+44 1709 873753",
    "sg:postcode":"S64 8DX",
    "sg:province":"South Yorkshire",
    "sg:tags":[
        "dressmaker"
    ],
    "wof:name":"Marceline Dancewear",
    "wof:placetype":"venue"
},
  "geometry": {"coordinates":[-1.332163,53.487656],"type":"Point"}
}