{
  "type": "Feature",
  "properties": {
    "addr:full":"31 High Street, Over Cambridge Cambridgeshire CB4 5NB",
    "addr:housenumber":"31",
    "addr:postcode":"cb4 5nb",
    "addr:street":"High Street Over",
    "iso:country":"GB",
    "sg:address":"31 High Street, Over",
    "sg:city":"Cambridge",
    "sg:classifiers":[
        {
            "category":"Bars & Pubs",
            "type":"Food & Drink"
        }
    ],
    "sg:phone":"+44 1954 230300",
    "sg:postcode":"CB4 5NB",
    "sg:province":"Cambridgeshire",
    "sg:tags":[
        "pubs",
        "inn"
    ],
    "wof:name":"Mr P Holmes",
    "wof:placetype":"venue"
},
  "geometry": {"coordinates":[0.047066,52.279163],"type":"Point"}
}