{
  "type": "Feature",
  "properties": {
    "addr:full":"The Old Canning Factory, Wellmore, Porthleven Helston Cornwall TR13 9JP",
    "addr:postcode":"tr13 9jp",
    "addr:street":"Wellmore",
    "iso:country":"GB",
    "sg:address":"The Old Canning Factory, Wellmore, Porthleven",
    "sg:city":"Helston",
    "sg:classifiers":[
        {
            "category":"Home & Garden",
            "subcategory":"Building Materials",
            "type":"Retail Goods"
        }
    ],
    "sg:phone":"+44 1326 562280",
    "sg:postcode":"TR13 9JP",
    "sg:province":"Cornwall",
    "sg:tags":[
        "ironwork",
        "diy",
        "wrought"
    ],
    "wof:name":"Harbourside Forge",
    "wof:placetype":"venue"
},
  "geometry": {"coordinates":[-5.313275,50.086704],"type":"Point"}
}