{
  "type": "Feature",
  "properties": {
    "addr:full":"9 Kellas Avenue Lossiemouth Moray IV31 6JG",
    "addr:housenumber":"9",
    "addr:postcode":"iv31 6jg",
    "addr:street":"Kellas Avenue",
    "iso:country":"GB",
    "sg:address":"9 Kellas Avenue",
    "sg:city":"Lossiemouth",
    "sg:classifiers":[
        {
            "category":"Building & Trades",
            "subcategory":"Plumbing",
            "type":"Services"
        }
    ],
    "sg:postcode":"IV31 6JG",
    "sg:province":"Moray",
    "sg:tags":[
        "heating"
    ],
    "wof:name":"Ian Sim",
    "wof:placetype":"venue"
},
  "geometry": {"coordinates":[-3.2850680351,57.7142562866],"type":"Point"}
}