{
  "type": "Feature",
  "properties": {
    "iso:country":"GB",
    "sg:address":"Barras Garth Industrial Estate, Barras Garth Road, Wortley",
    "sg:city":"Leeds",
    "sg:classifiers":[
        {
            "category":"Manufacturing",
            "subcategory":"Rubber & Plastics",
            "type":"Manufacturing & Wholesale Goods"
        }
    ],
    "sg:phone":"+44 113 263 4330",
    "sg:postcode":"LS12 4JW",
    "sg:province":"West Yorkshire",
    "sg:tags":[
        "product"
    ],
    "wof:name":"Arrow Film Converters",
    "wof:placetype":"venue"
},
  "geometry": {"coordinates":[-1.59391,53.791531],"type":"Point"}
}