{
  "type": "Feature",
  "properties": {
    "iso:country":"GB",
    "sg:address":"26 Southern Road, Southbourne",
    "sg:city":"Bournemouth",
    "sg:classifiers":[
        {
            "category":"Travel",
            "subcategory":"Hotels & Motels",
            "type":"Entertainment"
        }
    ],
    "sg:phone":"+44 1202 428653",
    "sg:postcode":"BH6 3SS",
    "sg:province":"Dorset",
    "wof:name":"Pennington Private Hotel",
    "wof:placetype":"venue"
},
  "geometry": {"coordinates":[-1.815807,50.723026],"type":"Point"}
}