{
  "type": "Feature",
  "properties": {
    "addr:full":"Unit 4, Tribune Drive Sittingbourne Kent ME10 2PG",
    "addr:housenumber":"unit 4",
    "addr:postcode":"me10 2pg",
    "addr:street":"Tribune Drive",
    "iso:country":"GB",
    "sg:address":"Unit 4, Tribune Drive",
    "sg:city":"Sittingbourne",
    "sg:classifiers":[
        {
            "category":"Manufacturing",
            "subcategory":"Rubber & Plastics",
            "type":"Manufacturing & Wholesale Goods"
        }
    ],
    "sg:phone":"+44 1795 477341",
    "sg:postcode":"ME10 2PG",
    "sg:province":"Kent",
    "sg:tags":[
        "product"
    ],
    "wof:name":"B & R Plastics",
    "wof:placetype":"venue"
},
  "geometry": {"coordinates":[0.7379230261,51.3518295288],"type":"Point"}
}