{
  "type": "Feature",
  "properties": {
    "iso:country":"GB",
    "sg:address":"20 Bengarth Road",
    "sg:city":"Northolt",
    "sg:classifiers":[
        {
            "category":"Home & Garden",
            "subcategory":"Home Furnishings",
            "type":"Retail Goods"
        }
    ],
    "sg:phone":"+44 20 8842 1820",
    "sg:postcode":"UB5 5LG",
    "sg:province":"Greater London",
    "sg:tags":[
        "furnishers",
        "planner",
        "kitchen"
    ],
    "wof:name":"D L Kettle",
    "wof:placetype":"venue"
},
  "geometry": {"coordinates":[-0.38557,51.541023],"type":"Point"}
}