{
  "type": "Feature",
  "properties": {
    "iso:country":"GB",
    "sg:address":"8 Apedale Rd, Wood Lane",
    "sg:city":"Stoke On Trent",
    "sg:classifiers":[
        {
            "category":"Building & Trades",
            "subcategory":"Plumbing",
            "type":"Services"
        }
    ],
    "sg:phone":"+44 1782 721019",
    "sg:postcode":"ST7 8PH",
    "sg:province":"Cheshire",
    "sg:tags":[
        "heating"
    ],
    "wof:name":"Alan Goodwin",
    "wof:placetype":"venue"
},
  "geometry": {"coordinates":[-2.28577,53.046288],"type":"Point"}
}