{
  "type": "Feature",
  "properties": {
    "addr:full":"2 Riverbank, Warwick Morpeth Northumberland NE65 0UZ",
    "addr:housenumber":"2",
    "addr:postcode":"ne65 0uz",
    "addr:street":"Riverbank",
    "iso:country":"GB",
    "sg:address":"2 Riverbank, Warwick",
    "sg:city":"Morpeth",
    "sg:classifiers":[
        {
            "category":"Building & Trades",
            "subcategory":"Construction",
            "type":"Services"
        }
    ],
    "sg:postcode":"NE65 0UZ",
    "sg:province":"Northumberland",
    "sg:tags":[
        "builder"
    ],
    "wof:name":"Easton,Ron,Builders",
    "wof:placetype":"venue"
},
  "geometry": {"coordinates":[-1.591809,55.333733],"type":"Point"}
}