{
  "type": "Feature",
  "properties": {
    "iso:country":"GB",
    "sg:address":"2 Riverbank, Warwick",
    "sg:city":"Morpeth",
    "sg:classifiers":[
        {
            "category":"Building & Trades",
            "subcategory":"Construction",
            "type":"Services"
        }
    ],
    "sg:postcode":"NE65 0UZ",
    "sg:province":"Northumberland",
    "sg:tags":[
        "builder"
    ],
    "wof:name":"Easton,Ron,Builders",
    "wof:placetype":"venue"
},
  "geometry": {"coordinates":[-1.591809,55.333733],"type":"Point"}
}