{
  "type": "Feature",
  "properties": {
    "addr:full":"1 Wigton Road London Greater London E17 5HU",
    "addr:housenumber":"1",
    "addr:postcode":"e17 5hu",
    "addr:street":"Wigton Road",
    "iso:country":"GB",
    "sg:address":"1 Wigton Road",
    "sg:city":"London",
    "sg:classifiers":[
        {
            "category":"Education",
            "subcategory":"School",
            "type":"Public Place"
        }
    ],
    "sg:phone":"+44 20 8527 3157",
    "sg:postcode":"E17 5HU",
    "sg:province":"Greater London",
    "sg:tags":[
        "local",
        "authority"
    ],
    "wof:name":"Roger Ascham Primary School",
    "wof:placetype":"venue"
},
  "geometry": {"coordinates":[-0.026687,51.598755],"type":"Point"}
}