{
  "type": "Feature",
  "properties": {
    "addr:full":"Beech Hill, Hadley Wood Barnet Hertfordshire EN4 0JJ",
    "addr:postcode":"en4 0jj",
    "iso:country":"GB",
    "sg:address":"Beech Hill, Hadley Wood",
    "sg:city":"Barnet",
    "sg:classifiers":[
        {
            "category":"Sports & Exercise",
            "subcategory":"Golf",
            "type":"Entertainment"
        }
    ],
    "sg:phone":"+44 20 8449 4328",
    "sg:postcode":"EN4 0JJ",
    "sg:province":"Hertfordshire",
    "sg:tags":[
        "club",
        "course"
    ],
    "wof:name":"Hadley Wood Golf Club Ltd.",
    "wof:placetype":"venue"
},
  "geometry": {"coordinates":[-0.1575639993,51.6674041748],"type":"Point"}
}