{
  "type": "Feature",
  "properties": {
    "addr:full":"Unit 1, Shires Road Brackley Buckinghamshire NN13 7EZ",
    "addr:housenumber":"unit 1",
    "addr:postcode":"nn13 7ez",
    "addr:street":"Shires Road",
    "iso:country":"GB",
    "sg:address":"Unit 1, Shires Road",
    "sg:city":"Brackley",
    "sg:classifiers":[
        {
            "category":"Structure",
            "subcategory":"Warehouse",
            "type":"Public Place"
        }
    ],
    "sg:phone":"+44 1280 700944",
    "sg:postcode":"NN13 7EZ",
    "sg:province":"Buckinghamshire",
    "wof:name":"B & S Warehousing",
    "wof:placetype":"venue"
},
  "geometry": {"coordinates":[-1.138234,52.02523],"type":"Point"}
}