{
  "type": "Feature",
  "properties": {
    "addr:full":"140 Wardour Street London Greater London W1F 8ZT",
    "addr:housenumber":"140",
    "addr:postcode":"w1f 8zt",
    "addr:street":"Wardour Street",
    "iso:country":"GB",
    "sg:address":"140 Wardour Street",
    "sg:city":"London",
    "sg:classifiers":[
        {
            "category":"Communications",
            "type":"Services"
        }
    ],
    "sg:phone":"+44 20 7432 6800",
    "sg:postcode":"W1F 8ZT",
    "sg:province":"Greater London",
    "sg:tags":[
        "audio-visual"
    ],
    "wof:name":"Radical Media",
    "wof:placetype":"venue"
},
  "geometry": {"coordinates":[-0.134754,51.514736],"type":"Point"}
}