{
  "type": "Feature",
  "properties": {
    "iso:country":"GB",
    "sg:address":"Llandrindod Wells County Primary, School, Cefnllys Lane",
    "sg:city":"Llandrindod Wells",
    "sg:classifiers":[
        {
            "category":"Community Center",
            "subcategory":"Youth",
            "type":"Public Place"
        }
    ],
    "sg:postcode":"LD1 5WA",
    "sg:province":"Powys",
    "sg:tags":[
        "organisation",
        "centre"
    ],
    "wof:name":"Chwarae Da Playcare",
    "wof:placetype":"venue"
},
  "geometry": {"coordinates":[-3.377029,52.24575],"type":"Point"}
}