{
  "type": "Feature",
  "properties": {
    "addr:full":"40 Holmesdale Road Reigate Surrey RH2 0YZ",
    "addr:housenumber":"40",
    "addr:postcode":"rh2 0yz",
    "addr:street":"Holmesdale Road",
    "iso:country":"GB",
    "sg:address":"40 Holmesdale Road",
    "sg:city":"Reigate",
    "sg:classifiers":[
        {
            "category":"Home & Garden",
            "subcategory":"Household Appliances",
            "type":"Retail Goods"
        }
    ],
    "sg:postcode":"RH2 0YZ",
    "sg:province":"Surrey",
    "sg:tags":[
        "cleaner",
        "vacuum"
    ],
    "wof:name":"Gotland Ltd.",
    "wof:placetype":"venue"
},
  "geometry": {"coordinates":[-0.200319007,51.2415390015],"type":"Point"}
}