{
  "type": "Feature",
  "properties": {
    "addr:full":"Tsuite 18, Carna Court, 145 Kew Road Richmond Greater London TW9 2PN",
    "addr:housenumber":"18;145",
    "addr:postcode":"tw9 2pn",
    "addr:street":"Tsuite;Kew Road",
    "iso:country":"GB",
    "sg:address":"Tsuite 18, Carna Court, 145 Kew Road",
    "sg:city":"Richmond",
    "sg:classifiers":[
        {
            "category":"Organizations",
            "subcategory":"Community Association",
            "type":"Services"
        }
    ],
    "sg:phone":"+44 20 8332 2337",
    "sg:postcode":"TW9 2PN",
    "sg:province":"Greater London",
    "sg:tags":[
        "relation",
        "public"
    ],
    "wof:name":"Eye Communications",
    "wof:placetype":"venue"
},
  "geometry": {"coordinates":[-0.3027839959,51.462348938],"type":"Point"}
}