{
  "type": "Feature",
  "properties": {
    "addr:full":"Coverwood, Peaslake Road Cranleigh Surrey GU6 7NT",
    "addr:postcode":"gu6 7nt",
    "addr:street":"Peaslake Road",
    "iso:country":"GB",
    "sg:address":"Coverwood, Peaslake Road",
    "sg:city":"Cranleigh",
    "sg:classifiers":[
        {
            "category":"Farming",
            "subcategory":"Livestock Farm",
            "type":"Manufacturing & Wholesale Goods"
        }
    ],
    "sg:postcode":"GU6 7NT",
    "sg:province":"Surrey",
    "sg:tags":[
        "others"
    ],
    "wof:name":"Coverwood Poll Herefords",
    "wof:placetype":"venue"
},
  "geometry": {"coordinates":[-0.482998997,51.1415405273],"type":"Point"}
}