{
  "type": "Feature",
  "properties": {
    "iso:country":"GB",
    "sg:address":"11 Crookeder Clo",
    "sg:city":"Plymouth",
    "sg:classifiers":[
        {
            "category":"Arts & Performance",
            "subcategory":"Music",
            "type":"Entertainment"
        }
    ],
    "sg:postcode":"PL9 9TR",
    "sg:province":"Devon",
    "sg:tags":[
        "mobile",
        "disco"
    ],
    "wof:name":"Lamatrast,Steven,",
    "wof:placetype":"venue"
},
  "geometry": {"coordinates":[-4.0772309303,50.3524856567],"type":"Point"}
}