{
  "type": "Feature",
  "properties": {
    "addr:full":"Lynn Street Swaffham Norfolk PE37 7AU",
    "addr:postcode":"pe37 7au",
    "addr:street":"Lynn Street",
    "iso:country":"GB",
    "sg:address":"Lynn Street",
    "sg:city":"Swaffham",
    "sg:classifiers":[
        {
            "category":"Food & Beverages",
            "subcategory":"Supermarket",
            "type":"Retail Goods"
        }
    ],
    "sg:phone":"+44 1760 724934",
    "sg:postcode":"PE37 7AU",
    "sg:province":"Norfolk",
    "wof:name":"Budgens Stores Ltd",
    "wof:placetype":"venue"
},
  "geometry": {"coordinates":[0.6848229766,52.6494140625],"type":"Point"}
}