{
  "type": "Feature",
  "properties": {
    "addr:full":"15 Main Street, Nailstone Nuneaton Leicestershire CV13 0QE",
    "addr:housenumber":"15",
    "addr:postcode":"cv13 0qe",
    "addr:street":"Main Street",
    "iso:country":"GB",
    "sg:address":"15 Main Street, Nailstone",
    "sg:city":"Nuneaton",
    "sg:classifiers":[
        {
            "category":"Shopping",
            "subcategory":"Department Store",
            "type":"Retail Goods"
        }
    ],
    "sg:phone":"+44 1530 263978",
    "sg:postcode":"CV13 0QE",
    "sg:province":"Leicestershire",
    "wof:name":"Nailstone Post Office & General Store",
    "wof:placetype":"venue"
},
  "geometry": {"coordinates":[-1.3683079481,52.6480445862],"type":"Point"}
}