{
  "type": "Feature",
  "properties": {
    "addr:full":"151 Soothill Lane Batley West Yorkshire WF17 6HW",
    "addr:housenumber":"151",
    "addr:postcode":"wf17 6hw",
    "addr:street":"Soothill Lane",
    "iso:country":"GB",
    "sg:address":"151 Soothill Lane",
    "sg:city":"Batley",
    "sg:classifiers":[
        {
            "category":"Organizations",
            "subcategory":"Membership Organization",
            "type":"Services"
        }
    ],
    "sg:phone":"+44 1924 477974",
    "sg:postcode":"WF17 6HW",
    "sg:province":"West Yorkshire",
    "sg:tags":[
        "club",
        "social"
    ],
    "wof:name":"Soothill Working Mens Club",
    "wof:placetype":"venue"
},
  "geometry": {"coordinates":[-1.6149519682,53.7138366699],"type":"Point"}
}