{
  "type": "Feature",
  "properties": {
    "addr:full":"Southview Court Woking Surrey GU22 7RR",
    "addr:postcode":"gu22 7rr",
    "addr:street":"Southview Court",
    "iso:country":"GB",
    "sg:address":"Southview Court",
    "sg:city":"Woking",
    "sg:classifiers":[
        {
            "category":"Health Services",
            "subcategory":"Doctor",
            "type":"Services"
        },
        {
            "category":"Health Services",
            "subcategory":"Clinic",
            "type":"Services"
        }
    ],
    "sg:phone":"+44 1483 763186",
    "sg:postcode":"GU22 7RR",
    "sg:province":"Surrey",
    "sg:tags":[
        "nh",
        "practitioners"
    ],
    "wof:name":"South View Surgery",
    "wof:placetype":"venue"
},
  "geometry": {"coordinates":[-0.5600630045,51.3135108948],"type":"Point"}
}