{
  "type": "Feature",
  "properties": {
    "iso:country":"GB",
    "sg:address":"6 Trengothal Court, Mill Road, Whitfield",
    "sg:city":"Brackley",
    "sg:classifiers":[
        {
            "category":"Professional",
            "subcategory":"Business Services",
            "type":"Services"
        }
    ],
    "sg:phone":"+44 1280 850054",
    "sg:postcode":"NN13 5TQ",
    "sg:province":"Buckinghamshire",
    "sg:tags":[
        "hospitality",
        "corporate"
    ],
    "wof:name":"Eventz 2000 Corporate Events",
    "wof:placetype":"venue"
},
  "geometry": {"coordinates":[-1.114154,52.050636],"type":"Point"}
}