{
  "type": "Feature",
  "properties": {
    "addr:full":"27 Clare Street Cardiff Cardiff CF11 6BD",
    "addr:housenumber":"27",
    "addr:postcode":"cf11 6bd",
    "addr:street":"Clare Street",
    "iso:country":"GB",
    "sg:address":"27 Clare Street",
    "sg:city":"Cardiff",
    "sg:classifiers":[
        {
            "category":"Utilities",
            "subcategory":"Refuse",
            "type":"Services"
        }
    ],
    "sg:phone":"+44 29 2038 7385",
    "sg:postcode":"CF11 6BD",
    "sg:province":"Cardiff",
    "sg:tags":[
        "disposal",
        "waste"
    ],
    "wof:name":"Roberts Transport",
    "wof:placetype":"venue"
},
  "geometry": {"coordinates":[-3.1883280277,51.4776420593],"type":"Point"}
}