{
  "type": "Feature",
  "properties": {
    "addr:full":"Upper Street, Kingsdown Deal Kent CT14 8DJ",
    "addr:postcode":"ct14 8dj",
    "addr:street":"Upper Street",
    "iso:country":"GB",
    "sg:address":"Upper Street, Kingsdown",
    "sg:city":"Deal",
    "sg:classifiers":[
        {
            "category":"Food & Beverages",
            "subcategory":"Meat & Fish",
            "type":"Retail Goods"
        }
    ],
    "sg:phone":"+44 1304 375670",
    "sg:postcode":"CT14 8DJ",
    "sg:province":"Kent",
    "sg:tags":[
        "butcher"
    ],
    "wof:name":"A Doyle & Sons",
    "wof:placetype":"venue"
},
  "geometry": {"coordinates":[1.395317,51.184967],"type":"Point"}
}