{
  "type": "Feature",
  "properties": {
    "addr:full":"30 Cold Bath Road Harrogate North Yorkshire HG2 0NA",
    "addr:housenumber":"30",
    "addr:postcode":"hg2 0na",
    "addr:street":"Cold Bath Road",
    "iso:country":"GB",
    "sg:address":"30 Cold Bath Road",
    "sg:city":"Harrogate",
    "sg:classifiers":[
        {
            "category":"Bars & Pubs",
            "type":"Food & Drink"
        }
    ],
    "sg:phone":"+44 1423 560437",
    "sg:postcode":"HG2 0NA",
    "sg:province":"North Yorkshire",
    "sg:tags":[
        "pubs",
        "inn"
    ],
    "wof:name":"The Slip Inn",
    "wof:placetype":"venue"
},
  "geometry": {"coordinates":[-1.5475939512,53.9904975891],"type":"Point"}
}