{
  "type": "Feature",
  "properties": {
    "iso:country":"GB",
    "sg:address":"82 Sandringham Rd",
    "sg:city":"Swindon",
    "sg:classifiers":[
        {
            "category":"Retail",
            "subcategory":"Driving School",
            "type":"Services"
        }
    ],
    "sg:phone":"+44 1793 529827",
    "sg:postcode":"SN3 1JD",
    "sg:province":"Wiltshire",
    "wof:name":"Lawns School of Motoring",
    "wof:placetype":"venue"
},
  "geometry": {"coordinates":[-1.757699,51.54747],"type":"Point"}
}