{
  "type": "Feature",
  "properties": {
    "iso:country":"GB",
    "sg:address":"502 Lytham Road",
    "sg:city":"Blackpool",
    "sg:classifiers":[
        {
            "category":"Social Services",
            "subcategory":"Retirement Home",
            "type":"Services"
        }
    ],
    "sg:postcode":"FY4 1JH",
    "sg:province":"Lancashire",
    "sg:tags":[
        "residential",
        "care"
    ],
    "wof:name":"Burrows Lea Rest Home",
    "wof:placetype":"venue"
},
  "geometry": {"coordinates":[-3.0478680134,53.788520813],"type":"Point"}
}