{
  "type": "Feature",
  "properties": {
    "addr:full":"6 Cambrian St Manchester Greater Manchester M11 3FY",
    "addr:housenumber":"6",
    "addr:postcode":"m11 3fy",
    "addr:street":"Cambrian St",
    "iso:country":"GB",
    "sg:address":"6 Cambrian St",
    "sg:city":"Manchester",
    "sg:classifiers":[
        {
            "category":"Professional",
            "subcategory":"Detective & Security Services",
            "type":"Services"
        }
    ],
    "sg:phone":"+44 161 273 8835",
    "sg:postcode":"M11 3FY",
    "sg:province":"Greater Manchester",
    "wof:name":"Corporate Services Ltd",
    "wof:placetype":"venue"
},
  "geometry": {"coordinates":[-2.2087171078,53.4836006165],"type":"Point"}
}