{
  "type": "Feature",
  "properties": {
    "addr:full":"136 Main St, Swithland Loughborough Leicestershire LE12 8TJ",
    "addr:housenumber":"136",
    "addr:postcode":"le12 8tj",
    "addr:street":"Main St",
    "iso:country":"GB",
    "sg:address":"136 Main St, Swithland",
    "sg:city":"Loughborough",
    "sg:classifiers":[
        {
            "category":"Professional",
            "subcategory":"Management & Consulting",
            "type":"Services"
        }
    ],
    "sg:postcode":"LE12 8TJ",
    "sg:province":"Leicestershire",
    "sg:tags":[
        "consultant",
        "specialist"
    ],
    "wof:name":"Health & Body",
    "wof:placetype":"venue"
},
  "geometry": {"coordinates":[-1.186467,52.712631],"type":"Point"}
}