{
  "type": "Feature",
  "properties": {
    "addr:full":"Ramsley Hill, South Zeal Okehampton Devon EX20 2PD",
    "addr:postcode":"ex20 2pd",
    "addr:street":"Ramsley Hill South Zeal",
    "iso:country":"GB",
    "sg:address":"Ramsley Hill, South Zeal",
    "sg:city":"Okehampton",
    "sg:classifiers":[
        {
            "category":"Bars & Pubs",
            "type":"Food & Drink"
        }
    ],
    "sg:phone":"+44 1837 840215",
    "sg:postcode":"EX20 2PD",
    "sg:province":"Devon",
    "sg:tags":[
        "pubs",
        "inn"
    ],
    "wof:name":"The Rising Sun Inn",
    "wof:placetype":"venue"
},
  "geometry": {"coordinates":[-3.9121370316,50.7222480774],"type":"Point"}
}