{
  "type": "Feature",
  "properties": {
    "iso:country":"GB",
    "sg:address":"408 Kenton Lane, Belmont Circle",
    "sg:city":"Harrow",
    "sg:classifiers":[
        {
            "category":"Retail",
            "subcategory":"Laundry & Dry Cleaning",
            "type":"Services"
        }
    ],
    "sg:phone":"+44 20 8907 3702",
    "sg:postcode":"HA3 8RQ",
    "sg:province":"Greater London",
    "sg:tags":[
        "launderette"
    ],
    "wof:name":"The Washing Well",
    "wof:placetype":"venue"
},
  "geometry": {"coordinates":[-0.316965,51.600929],"type":"Point"}
}