{
  "type": "Feature",
  "properties": {
    "addr:full":"3 The Centre, Opposite Town Hall Weston-super-mare Somerset BS23 1US",
    "addr:housenumber":"3",
    "addr:postcode":"bs23 1us",
    "addr:street":"The Centre Opposite Town Hall",
    "iso:country":"GB",
    "sg:address":"3 The Centre, Opposite Town Hall",
    "sg:city":"Weston-super-mare",
    "sg:classifiers":[
        {
            "category":"Food & Beverages",
            "subcategory":"Bakery",
            "type":"Retail Goods"
        }
    ],
    "sg:phone":"+44 1934 414444",
    "sg:postcode":"BS23 1US",
    "sg:province":"Somerset",
    "sg:tags":[
        "pizza"
    ],
    "wof:name":"Perfect Pizza",
    "wof:placetype":"venue"
},
  "geometry": {"coordinates":[-2.9771840572,51.3461914062],"type":"Point"}
}