{
  "type": "Feature",
  "properties": {
    "addr:full":"Flat 12 Braemar, Kersfield Road London Greater London SW15 3HG",
    "addr:housenumber":"flat 12",
    "addr:postcode":"sw15 3hg",
    "addr:street":"Kersfield Road",
    "iso:country":"GB",
    "sg:address":"Flat 12 Braemar, Kersfield Road",
    "sg:city":"London",
    "sg:classifiers":[
        {
            "category":"Banks & Credit Unions",
            "subcategory":"Financial Services",
            "type":"Services"
        }
    ],
    "sg:postcode":"SW15 3HG",
    "sg:province":"Greater London",
    "sg:tags":[
        "consultant"
    ],
    "wof:name":"Cedarberg Warriors Ltd",
    "wof:placetype":"venue"
},
  "geometry": {"coordinates":[-0.2193699926,51.4523506165],"type":"Point"}
}