{
  "type": "Feature",
  "properties": {
    "addr:full":"49 Fields Road Stoke-on-trent Cheshire ST7 2NA",
    "addr:housenumber":"49",
    "addr:postcode":"st7 2na",
    "addr:street":"Fields Road",
    "iso:country":"GB",
    "sg:address":"49 Fields Road",
    "sg:city":"Stoke-on-trent",
    "sg:classifiers":[
        {
            "category":"Real Estate",
            "subcategory":"Real Estate Agent",
            "type":"Services"
        }
    ],
    "sg:phone":"+44 7989 563683",
    "sg:postcode":"ST7 2NA",
    "sg:province":"Cheshire",
    "wof:name":"Claymoss Properties Ltd.",
    "wof:placetype":"venue"
},
  "geometry": {"coordinates":[-2.299006,53.094986],"type":"Point"}
}