{
  "type": "Feature",
  "properties": {
    "addr:full":"21 Middlewood King's Lynn Norfolk PE30 4RS",
    "addr:housenumber":"21",
    "addr:postcode":"pe30 4rs",
    "addr:street":"Middlewood;Lynn",
    "iso:country":"GB",
    "sg:address":"21 Middlewood",
    "sg:city":"King's Lynn",
    "sg:classifiers":[
        {
            "category":"Building & Trades",
            "subcategory":"Construction",
            "type":"Services"
        }
    ],
    "sg:postcode":"PE30 4RS",
    "sg:province":"Norfolk",
    "sg:tags":[
        "roofing"
    ],
    "wof:name":"Colin Simmonds",
    "wof:placetype":"venue"
},
  "geometry": {"coordinates":[0.43607,52.7514],"type":"Point"}
}