{
  "type": "Feature",
  "properties": {
    "addr:full":"Salterforth Lane, Salterforth Barnoldswick Lancashire BB18 5TT",
    "addr:postcode":"bb18 5tt",
    "addr:street":"Salterforth Lane",
    "iso:country":"GB",
    "sg:address":"Salterforth Lane, Salterforth",
    "sg:city":"Barnoldswick",
    "sg:classifiers":[
        {
            "category":"Bars & Pubs",
            "type":"Food & Drink"
        }
    ],
    "sg:phone":"+44 1282 813186",
    "sg:postcode":"BB18 5TT",
    "sg:province":"Lancashire",
    "sg:tags":[
        "pubs",
        "inn"
    ],
    "wof:name":"The Anchor Inn",
    "wof:placetype":"venue"
},
  "geometry": {"coordinates":[-2.1882588863,53.9174118042],"type":"Point"}
}