{
  "type": "Feature",
  "properties": {
    "addr:full":"2 Taylor Avenue Rochdale Lancashire OL11 5YL",
    "addr:housenumber":"2",
    "addr:postcode":"ol11 5yl",
    "addr:street":"Taylor Avenue",
    "iso:country":"GB",
    "sg:address":"2 Taylor Avenue",
    "sg:city":"Rochdale",
    "sg:classifiers":[
        {
            "category":"Building & Trades",
            "subcategory":"Landscaping Services",
            "type":"Services"
        }
    ],
    "sg:phone":"+44 1706 650107",
    "sg:postcode":"OL11 5YL",
    "sg:province":"Lancashire",
    "sg:tags":[
        "forestry",
        "tree"
    ],
    "wof:name":"Briarfield Tree Services",
    "wof:placetype":"venue"
},
  "geometry": {"coordinates":[-2.201971,53.620655],"type":"Point"}
}