{
  "type": "Feature",
  "properties": {
    "addr:full":"3 Elm Drive Market Harborough Leicestershire LE16 9DS",
    "addr:housenumber":"3",
    "addr:postcode":"le16 9ds",
    "addr:street":"Elm Drive",
    "iso:country":"GB",
    "sg:address":"3 Elm Drive",
    "sg:city":"Market Harborough",
    "sg:classifiers":[
        {
            "category":"Home & Garden",
            "subcategory":"Home Furnishings",
            "type":"Retail Goods"
        }
    ],
    "sg:postcode":"LE16 9DS",
    "sg:province":"Leicestershire",
    "sg:tags":[
        "blind",
        "curtain",
        "fitting"
    ],
    "wof:name":"Valerie & Alan Ward",
    "wof:placetype":"venue"
},
  "geometry": {"coordinates":[-0.9341040254,52.4745597839],"type":"Point"}
}