{
  "type": "Feature",
  "properties": {
    "iso:country":"GB",
    "sg:address":"89 Leeming La South, Mansfield Woodhouse",
    "sg:city":"Mansfield",
    "sg:classifiers":[
        {
            "category":"Retail",
            "subcategory":"Repair Shop",
            "type":"Services"
        }
    ],
    "sg:postcode":"NG19 9BD",
    "sg:province":"Derbyshire",
    "sg:tags":[
        "upholsterer"
    ],
    "wof:name":"Harrow,D L,",
    "wof:placetype":"venue"
},
  "geometry": {"coordinates":[-1.184112,53.164791],"type":"Point"}
}