{
  "type": "Feature",
  "properties": {
    "addr:full":"185 Earlham Gro London Greater London E7 9AP",
    "addr:housenumber":"185",
    "addr:postcode":"e7 9ap",
    "addr:street":"Earlham Gro",
    "iso:country":"GB",
    "sg:address":"185 Earlham Gro",
    "sg:city":"London",
    "sg:classifiers":[
        {
            "category":"Sports & Exercise",
            "subcategory":"Athletic Track",
            "type":"Entertainment"
        }
    ],
    "sg:phone":"+44 20 8221 1515",
    "sg:postcode":"E7 9AP",
    "sg:province":"Greater London",
    "sg:tags":[
        "bags",
        "accessory",
        "belt"
    ],
    "wof:name":"Super Belts",
    "wof:placetype":"venue"
},
  "geometry": {"coordinates":[0.0204499997,51.5480918884],"type":"Point"}
}