{
  "type": "Feature",
  "properties": {
    "addr:full":"Mitchell Point Ensign Way, Hamble Southampton Hampshire SO31 4RF",
    "addr:postcode":"so31 4rf",
    "addr:street":"Mitchell;Ensign Way",
    "iso:country":"GB",
    "sg:address":"Mitchell Point Ensign Way, Hamble",
    "sg:city":"Southampton",
    "sg:classifiers":[
        {
            "category":"Shopping",
            "type":"Retail Goods"
        }
    ],
    "sg:phone":"+44 23 8045 7272",
    "sg:postcode":"SO31 4RF",
    "sg:province":"Hampshire",
    "sg:tags":[
        "equipment",
        "clothing",
        "safety"
    ],
    "wof:name":"Craftsafe Marketing Ltd",
    "wof:placetype":"venue"
},
  "geometry": {"coordinates":[-1.327141,50.857323],"type":"Point"}
}