{
  "type": "Feature",
  "properties": {
    "addr:full":"3 Oxford Court, St James Road Brackley Buckinghamshire NN13 7XY",
    "addr:housenumber":"3",
    "addr:postcode":"nn13 7xy",
    "addr:street":"Oxford Court St James Road",
    "iso:country":"GB",
    "sg:address":"3 Oxford Court, St James Road",
    "sg:city":"Brackley",
    "sg:classifiers":[
        {
            "category":"Wholesale",
            "subcategory":"Office Equipment",
            "type":"Manufacturing & Wholesale Goods"
        },
        {
            "category":"Manufacturing",
            "subcategory":"Tools & Machinery",
            "type":"Manufacturing & Wholesale Goods"
        }
    ],
    "sg:phone":"+44 1527 514198",
    "sg:postcode":"NN13 7XY",
    "sg:province":"Buckinghamshire",
    "sg:tags":[
        "merchant",
        "register",
        "cash",
        "accessory"
    ],
    "wof:name":"Intelligent Business Services Ltd.",
    "wof:placetype":"venue"
},
  "geometry": {"coordinates":[-1.1492660046,52.0273208618],"type":"Point"}
}