{
  "type": "Feature",
  "properties": {
    "iso:country":"GB",
    "sg:address":"6 Wallpark Close, Newnham Industrial Estate, Plympton",
    "sg:city":"Plymouth",
    "sg:classifiers":[
        {
            "category":"Retail",
            "subcategory":"Auto Repair",
            "type":"Services"
        }
    ],
    "sg:phone":"+44 1752 338864",
    "sg:postcode":"PL7 4JL",
    "sg:province":"Devon",
    "sg:tags":[
        "body",
        "car",
        "repairer"
    ],
    "wof:name":"Newnham Body Repairs",
    "wof:placetype":"venue"
},
  "geometry": {"coordinates":[-4.0452880859,50.3966903687],"type":"Point"}
}