{
  "type": "Feature",
  "properties": {
    "iso:country":"GB",
    "sg:address":"152a Murray Road",
    "sg:city":"Rugby",
    "sg:classifiers":[
        {
            "category":"Shopping",
            "subcategory":"Department Store",
            "type":"Retail Goods"
        },
        {
            "category":"Home & Garden",
            "subcategory":"Carpets & Floor Coverings",
            "type":"Retail Goods"
        }
    ],
    "sg:postcode":"CV21 3JR",
    "sg:province":"Warwickshire",
    "sg:tags":[
        "carpets",
        "rug",
        "matting"
    ],
    "wof:name":"The Carpet Place",
    "wof:placetype":"venue"
},
  "geometry": {"coordinates":[-1.2520170212,52.3760223389],"type":"Point"}
}