{
  "type": "Feature",
  "properties": {
    "iso:country":"GB",
    "sg:address":"Units 4, & 5 Millwey Rise Ind Est",
    "sg:city":"Axminster",
    "sg:classifiers":[
        {
            "category":"Wholesale",
            "subcategory":"Non-durable Goods",
            "type":"Manufacturing & Wholesale Goods"
        }
    ],
    "sg:phone":"+44 1297 631249",
    "sg:postcode":"EX13 5HU",
    "sg:province":"Devon",
    "sg:tags":[
        "carry",
        "cash"
    ],
    "wof:name":"Warehouse 5",
    "wof:placetype":"venue"
},
  "geometry": {"coordinates":[-2.9865159988,50.7860641479],"type":"Point"}
}