{
  "type": "Feature",
  "properties": {
    "addr:full":"Unit 6, Parsons Estate, District 2 Washington Tyne and Wear NE37 1HB",
    "addr:housenumber":"unit 6",
    "addr:postcode":"tyne and;ne37 1hb",
    "addr:street":"Parsons Estate",
    "iso:country":"GB",
    "sg:address":"Unit 6, Parsons Estate, District 2",
    "sg:city":"Washington",
    "sg:classifiers":[
        {
            "category":"Home & Garden",
            "subcategory":"Household Appliances",
            "type":"Retail Goods"
        }
    ],
    "sg:phone":"+44 191 416 4575",
    "sg:postcode":"NE37 1HB",
    "sg:province":"Tyne and Wear",
    "sg:tags":[
        "refrigeration",
        "air conditioning"
    ],
    "wof:name":"Tyne Tees Forth Air Conditioning & Refrigeration Co. Ltd.",
    "wof:placetype":"venue"
},
  "geometry": {"coordinates":[-1.5381720066,54.9093399048],"type":"Point"}
}