{
  "type": "Feature",
  "properties": {
    "iso:country":"GB",
    "sg:address":"148 Overland Road, Mumbles",
    "sg:city":"Swansea",
    "sg:classifiers":[
        {
            "category":"Education",
            "subcategory":"School",
            "type":"Public Place"
        }
    ],
    "sg:postcode":"SA3 4EU",
    "sg:province":"Swansea",
    "sg:tags":[
        "local",
        "authority"
    ],
    "wof:name":"Schoolart Ltd",
    "wof:placetype":"venue"
},
  "geometry": {"coordinates":[-3.9966480732,51.5724868774],"type":"Point"}
}