{
  "type": "Feature",
  "properties": {
    "addr:full":"4 Westgate Guisborough North Yorkshire TS14 6BA",
    "addr:housenumber":"4",
    "addr:postcode":"ts14 6ba",
    "addr:street":"Westgate Guisborough",
    "iso:country":"GB",
    "sg:address":"4 Westgate",
    "sg:city":"Guisborough",
    "sg:classifiers":[
        {
            "category":"Food & Beverages",
            "subcategory":"Fruits & Vegetables",
            "type":"Retail Goods"
        }
    ],
    "sg:postcode":"TS14 6BA",
    "sg:province":"North Yorkshire",
    "sg:tags":[
        "greengrocer"
    ],
    "wof:name":"Bell's Fruiterers",
    "wof:placetype":"venue"
},
  "geometry": {"coordinates":[-1.0520720482,54.5358047485],"type":"Point"}
}