{
  "type": "Feature",
  "properties": {
    "iso:country":"GB",
    "sg:address":"427 Cronton Road, Cronton",
    "sg:city":"Widnes",
    "sg:classifiers":[
        {
            "category":"Bars & Pubs",
            "type":"Food & Drink"
        }
    ],
    "sg:phone":"+44 151 424 2965",
    "sg:postcode":"WA8 5QG",
    "sg:province":"Cheshire",
    "sg:tags":[
        "pubs",
        "inn"
    ],
    "wof:name":"Greenalls Management Ltd.",
    "wof:placetype":"venue"
},
  "geometry": {"coordinates":[-2.761776,53.389137],"type":"Point"}
}