{
  "type": "Feature",
  "properties": {
    "addr:full":"Porterswood House, Porters Wood St Albans Hertfordshire AL3 6PQ",
    "addr:postcode":"al3 6pq",
    "iso:country":"GB",
    "sg:address":"Porterswood House, Porters Wood",
    "sg:city":"St Albans",
    "sg:classifiers":[
        {
            "category":"Professional",
            "subcategory":"Engineering",
            "type":"Services"
        }
    ],
    "sg:phone":"+44 1727 833261",
    "sg:postcode":"AL3 6PQ",
    "sg:province":"Hertfordshire",
    "sg:tags":[
        "consulting",
        "engineer"
    ],
    "wof:name":"STATS Limited",
    "wof:placetype":"venue"
},
  "geometry": {"coordinates":[-0.327337,51.770679],"type":"Point"}
}