{
  "type": "Feature",
  "properties": {
    "addr:full":"12 Alder Glade, Burghfield Common Reading Berkshire RG7 3HW",
    "addr:housenumber":"12",
    "addr:postcode":"rg7 3hw",
    "addr:street":"Alder Glade",
    "iso:country":"GB",
    "sg:address":"12 Alder Glade, Burghfield Common",
    "sg:city":"Reading",
    "sg:classifiers":[
        {
            "category":"Wholesale",
            "subcategory":"Machinery & Supplies",
            "type":"Manufacturing & Wholesale Goods"
        },
        {
            "category":"Wholesale",
            "subcategory":"Plants",
            "type":"Manufacturing & Wholesale Goods"
        }
    ],
    "sg:phone":"+44 118 983 6383",
    "sg:postcode":"RG7 3HW",
    "sg:province":"Berkshire",
    "sg:tags":[
        "hydraulic"
    ],
    "wof:name":"POWERPLUS SYSTEMS LTD",
    "wof:placetype":"venue"
},
  "geometry": {"coordinates":[-1.0714310408,51.3999443054],"type":"Point"}
}