{
  "type": "Feature",
  "properties": {
    "addr:full":"Grimston Rd, South Wootton King's Lynn Norfolk PE30 3HU",
    "addr:postcode":"pe30 3hu",
    "addr:street":"Grimston Rd;Lynn",
    "iso:country":"GB",
    "sg:address":"Grimston Rd, South Wootton",
    "sg:city":"King's Lynn",
    "sg:classifiers":[
        {
            "category":"Social Services",
            "subcategory":"Adult Care",
            "type":"Services"
        },
        {
            "category":"Organizations",
            "subcategory":"Community Association",
            "type":"Services"
        },
        {
            "category":"Government",
            "subcategory":"Office",
            "type":"Public Place"
        }
    ],
    "sg:phone":"+44 1553 672753",
    "sg:postcode":"PE30 3HU",
    "sg:province":"Norfolk",
    "sg:tags":[
        "associations",
        "centre",
        "housing",
        "co-operatives",
        "trust",
        "local",
        "day",
        "societies"
    ],
    "wof:name":"NORFOLK COUNTY COUNCIL",
    "wof:placetype":"venue"
},
  "geometry": {"coordinates":[0.4413399994,52.7739715576],"type":"Point"}
}