{
  "type": "Feature",
  "properties": {
    "addr:full":"1 Bridge House, Skipton Road, Steeton Keighley North Yorkshire BD20 6NR",
    "addr:housenumber":"1;house",
    "addr:postcode":"bd20 6nr",
    "addr:street":"Skipton Road",
    "iso:country":"GB",
    "sg:address":"1 Bridge House, Skipton Road, Steeton",
    "sg:city":"Keighley",
    "sg:classifiers":[
        {
            "category":"Farming",
            "subcategory":"Nursery",
            "type":"Manufacturing & Wholesale Goods"
        },
        {
            "category":"Education",
            "subcategory":"Preschool",
            "type":"Public Place"
        }
    ],
    "sg:phone":"+44 1535 657800",
    "sg:postcode":"BD20 6NR",
    "sg:province":"North Yorkshire",
    "sg:tags":[
        "school",
        "creche"
    ],
    "wof:name":"Bridge House Nursery",
    "wof:placetype":"venue"
},
  "geometry": {"coordinates":[-1.949194,53.895851],"type":"Point"}
}