{
  "type": "Feature",
  "properties": {
    "addr:full":"Barn Close, Combe Raleigh Honiton Devon EX14 4SG",
    "addr:postcode":"ex14 4sg",
    "addr:street":"Barn Close",
    "iso:country":"GB",
    "sg:address":"Barn Close, Combe Raleigh",
    "sg:city":"Honiton",
    "sg:classifiers":[
        {
            "category":"Transit Center",
            "subcategory":"Passenger",
            "type":"Transportation"
        },
        {
            "category":"Retail",
            "subcategory":"Pet Boarding",
            "type":"Services"
        }
    ],
    "sg:phone":"+44 1404 42505",
    "sg:postcode":"EX14 4SG",
    "sg:province":"Devon",
    "sg:tags":[
        "kennel",
        "catteries"
    ],
    "wof:name":"Barn Close Kennels & Catteries",
    "wof:placetype":"venue"
},
  "geometry": {"coordinates":[-3.196906,50.797386],"type":"Point"}
}