{
  "type": "Feature",
  "properties": {
    "iso:country":"GB",
    "sg:address":"29 Market St",
    "sg:city":"Leicester",
    "sg:classifiers":[
        {
            "category":"Bars & Pubs",
            "type":"Food & Drink"
        }
    ],
    "sg:phone":"+44 116 255 6877",
    "sg:postcode":"LE1 6DN",
    "sg:province":"Leicestershire",
    "sg:tags":[
        "pubs",
        "inn"
    ],
    "wof:name":"Wilkies Continental Bar",
    "wof:placetype":"venue"
},
  "geometry": {"coordinates":[-1.133022,52.632591],"type":"Point"}
}