{
  "type": "Feature",
  "properties": {
    "addr:full":"2 Queens Square Poulton-le-fylde Lancashire FY6 7BN",
    "addr:housenumber":"2",
    "addr:postcode":"fy6 7bn",
    "addr:street":"Queens Square Poulton-Le-Fylde",
    "iso:country":"GB",
    "sg:address":"2 Queens Square",
    "sg:city":"Poulton-le-fylde",
    "sg:classifiers":[
        {
            "category":"Banks & Credit Unions",
            "subcategory":"Bank",
            "type":"Services"
        },
        {
            "category":"Real Estate",
            "subcategory":"Real Estate Agent",
            "type":"Services"
        }
    ],
    "sg:phone":"+44 1253 894894",
    "sg:postcode":"FY6 7BN",
    "sg:province":"Lancashire",
    "sg:tags":[
        "broker",
        "mortgage"
    ],
    "wof:name":"T A Hargreaves & Co Estate Agents",
    "wof:placetype":"venue"
},
  "geometry": {"coordinates":[-2.991822,53.84621],"type":"Point"}
}