{
  "type": "Feature",
  "properties": {
    "addr:full":"487 Scott Hall Rd Leeds West Yorkshire LS7 2EF",
    "addr:housenumber":"487",
    "addr:postcode":"ls7 2ef",
    "addr:street":"Scott Hall Rd",
    "iso:country":"GB",
    "sg:address":"487 Scott Hall Rd",
    "sg:city":"Leeds",
    "sg:classifiers":[
        {
            "category":"Manufacturing",
            "subcategory":"Petroleum Products",
            "type":"Manufacturing & Wholesale Goods"
        }
    ],
    "sg:postcode":"LS7 2EF",
    "sg:province":"West Yorkshire",
    "sg:tags":[
        "double",
        "glazing"
    ],
    "wof:name":"Jeffers,Percy,",
    "wof:placetype":"venue"
},
  "geometry": {"coordinates":[-1.546519,53.825298],"type":"Point"}
}