{
  "type": "Feature",
  "properties": {
    "iso:country":"GB",
    "sg:address":"1 Craigcrook Rd",
    "sg:city":"Edinburgh",
    "sg:classifiers":[
        {
            "category":"Food & Beverages",
            "subcategory":"Liquor & Beverages",
            "type":"Retail Goods"
        }
    ],
    "sg:phone":"+44 131 315 4225",
    "sg:postcode":"EH4 3NQ",
    "sg:province":"City of Edinburgh",
    "sg:tags":[
        "beer",
        "spirit",
        "wines"
    ],
    "wof:name":"Victoria Wine",
    "wof:placetype":"venue"
},
  "geometry": {"coordinates":[-3.250844,55.95805],"type":"Point"}
}