{
  "type": "Feature",
  "properties": {
    "addr:full":"Spenser Rd Harpenden Hertfordshire AL5 5NN",
    "addr:postcode":"al5 5nn",
    "addr:street":"Spenser Rd",
    "iso:country":"GB",
    "sg:address":"Spenser Rd",
    "sg:city":"Harpenden",
    "sg:classifiers":[
        {
            "category":"Arena",
            "subcategory":"Sports Club",
            "type":"Entertainment"
        }
    ],
    "sg:postcode":"AL5 5NN",
    "sg:province":"Hertfordshire",
    "wof:name":"Harpenden Bowling Club",
    "wof:placetype":"venue"
},
  "geometry": {"coordinates":[-0.346514,51.813454],"type":"Point"}
}