{
  "type": "Feature",
  "properties": {
    "addr:full":"36 New Street, Barbican Plymouth Devon PL1 2NA",
    "addr:housenumber":"36",
    "addr:postcode":"pl1 2na",
    "addr:street":"New Street",
    "iso:country":"GB",
    "sg:address":"36 New Street, Barbican",
    "sg:city":"Plymouth",
    "sg:classifiers":[
        {
            "category":"Cafe",
            "type":"Food & Drink"
        }
    ],
    "sg:postcode":"PL1 2NA",
    "sg:province":"Devon",
    "sg:tags":[
        "tea",
        "room"
    ],
    "wof:name":"Tudor Rose Tearooms",
    "wof:placetype":"venue"
},
  "geometry": {"coordinates":[-4.135111,50.366791],"type":"Point"}
}