{
  "type": "Feature",
  "properties": {
    "addr:full":"High Street Bordon Hampshire GU35 0AU",
    "addr:postcode":"gu35 0au",
    "addr:street":"High Street",
    "iso:country":"GB",
    "sg:address":"High Street",
    "sg:city":"Bordon",
    "sg:classifiers":[
        {
            "category":"Farming",
            "subcategory":"Nursery",
            "type":"Manufacturing & Wholesale Goods"
        },
        {
            "category":"Organizations",
            "subcategory":"Non-profit Organization",
            "type":"Services"
        }
    ],
    "sg:phone":"+44 1420 476402",
    "sg:postcode":"GU35 0AU",
    "sg:province":"Hampshire",
    "sg:tags":[
        "charitable",
        "organisation",
        "creche",
        "charity"
    ],
    "wof:name":"Cygnets Centre Day Nursery Ltd.",
    "wof:placetype":"venue"
},
  "geometry": {"coordinates":[-0.863704,51.11134],"type":"Point"}
}