{
  "type": "Feature",
  "properties": {
    "addr:full":"Gnoll Chambers, 4-8 Gnoll Park Road Neath Neath Port Talbot SA11 3PT",
    "addr:housenumber":"4-8",
    "addr:postcode":"sa11 3pt",
    "addr:street":"Gnoll Park Road",
    "iso:country":"GB",
    "sg:address":"Gnoll Chambers, 4-8 Gnoll Park Road",
    "sg:city":"Neath",
    "sg:classifiers":[
        {
            "category":"Professional",
            "subcategory":"Lawyer & Legal Services",
            "type":"Services"
        }
    ],
    "sg:phone":"+44 1639 643674",
    "sg:postcode":"SA11 3PT",
    "sg:province":"Neath Port Talbot",
    "sg:tags":[
        "solicitor"
    ],
    "wof:name":"Hutchinson Morris & Harret",
    "wof:placetype":"venue"
},
  "geometry": {"coordinates":[-3.7998130322,51.6627120972],"type":"Point"}
}