{
  "type": "Feature",
  "properties": {
    "addr:full":"Rose Lane, Chadwell Heath Romford Essex RM6 5NJ",
    "addr:postcode":"rm6 5nj",
    "addr:street":"Rose Lane",
    "iso:country":"GB",
    "sg:address":"Rose Lane, Chadwell Heath",
    "sg:city":"Romford",
    "sg:classifiers":[
        {
            "category":"Social Services",
            "subcategory":"Adult Care",
            "type":"Services"
        }
    ],
    "sg:phone":"+44 20 8597 1525",
    "sg:postcode":"RM6 5NJ",
    "sg:province":"Essex",
    "sg:tags":[
        "day",
        "centre"
    ],
    "wof:name":"Rose Lane Social Centre",
    "wof:placetype":"venue"
},
  "geometry": {"coordinates":[0.133949995,51.5879402161],"type":"Point"}
}