{
  "type": "Feature",
  "properties": {
    "addr:full":"8 Valley Cres Wokingham Berkshire RG41 1NP",
    "addr:housenumber":"8",
    "addr:postcode":"rg41 1np",
    "addr:street":"Valley Cres",
    "iso:country":"GB",
    "sg:address":"8 Valley Cres",
    "sg:city":"Wokingham",
    "sg:classifiers":[
        {
            "category":"Building & Trades",
            "subcategory":"Plumbing",
            "type":"Services"
        }
    ],
    "sg:phone":"+44 118 978 0429",
    "sg:postcode":"RG41 1NP",
    "sg:province":"Berkshire",
    "sg:tags":[
        "heating"
    ],
    "wof:name":"Michael Arnold",
    "wof:placetype":"venue"
},
  "geometry": {"coordinates":[-0.847057,51.419018],"type":"Point"}
}