{
  "type": "Feature",
  "properties": {
    "addr:full":"Foxfield Bideford Devon EX39 6HF",
    "addr:postcode":"ex39 6hf",
    "iso:country":"GB",
    "sg:address":"Foxfield",
    "sg:city":"Bideford",
    "sg:classifiers":[
        {
            "category":"Utilities",
            "subcategory":"Sewage",
            "type":"Services"
        }
    ],
    "sg:phone":"+44 1288 331561",
    "sg:postcode":"EX39 6HF",
    "sg:province":"Devon",
    "sg:tags":[
        "disposal"
    ],
    "wof:name":"Cleanwater",
    "wof:placetype":"venue"
},
  "geometry": {"coordinates":[-4.4804987907,50.9833717346],"type":"Point"}
}