{
  "type": "Feature",
  "properties": {
    "iso:country":"GB",
    "sg:address":"Blaenbedan Fach, Plwmp,",
    "sg:city":"Llandyssul",
    "sg:classifiers":[
        {
            "category":"Military Area",
            "subcategory":"Army Base",
            "type":"Public Place"
        },
        {
            "category":"Freight",
            "type":"Transportation"
        }
    ],
    "sg:postcode":"SA44 6HX",
    "sg:province":"Carmarthenshire",
    "sg:tags":[
        "haulage",
        "livestock",
        "road"
    ],
    "wof:name":"Patterson,David,",
    "wof:placetype":"venue"
},
  "geometry": {"coordinates":[-4.384364,52.146732],"type":"Point"}
}