{
  "type": "Feature",
  "properties": {
    "addr:full":"Crook Log Bexleyheath Kent DA6 8EQ",
    "addr:postcode":"da6 8eq",
    "iso:country":"GB",
    "sg:address":"Crook Log",
    "sg:city":"Bexleyheath",
    "sg:classifiers":[
        {
            "category":"Government",
            "subcategory":"Office",
            "type":"Public Place"
        },
        {
            "category":"Sports & Exercise",
            "subcategory":"Swimming Pool",
            "type":"Entertainment"
        }
    ],
    "sg:phone":"+44 20 8303 5781",
    "sg:postcode":"DA6 8EQ",
    "sg:province":"Kent",
    "sg:tags":[
        "operation",
        "local"
    ],
    "wof:name":"Splashworld Swimming Centre",
    "wof:placetype":"venue"
},
  "geometry": {"coordinates":[0.1248689964,51.4595794678],"type":"Point"}
}