{
  "type": "Feature",
  "properties": {
    "addr:full":"Semer House, Semer Ipswich Suffolk IP7 6JB",
    "addr:postcode":"ip7 6jb",
    "addr:street":"Semer",
    "iso:country":"GB",
    "sg:address":"Semer House, Semer",
    "sg:city":"Ipswich",
    "sg:classifiers":[
        {
            "category":"Real Estate",
            "subcategory":"Real Estate Agent",
            "type":"Services"
        }
    ],
    "sg:postcode":"IP7 6JB",
    "sg:province":"Suffolk",
    "wof:name":"Poligrove Estates Ltd.",
    "wof:placetype":"venue"
},
  "geometry": {"coordinates":[0.9202659726,52.0828514099],"type":"Point"}
}