{
  "type": "Feature",
  "properties": {
    "addr:full":"101 Highfield Road Blackpool Lancashire FY4 2JE",
    "addr:housenumber":"101",
    "addr:postcode":"fy4 2je",
    "addr:street":"Highfield Road",
    "iso:country":"GB",
    "sg:address":"101 Highfield Road",
    "sg:city":"Blackpool",
    "sg:classifiers":[
        {
            "category":"Cinema",
            "subcategory":"Movie Rental",
            "type":"Entertainment"
        }
    ],
    "sg:phone":"+44 1253 348618",
    "sg:postcode":"FY4 2JE",
    "sg:province":"Lancashire",
    "sg:tags":[
        "video",
        "library"
    ],
    "wof:name":"Flickers Video",
    "wof:placetype":"venue"
},
  "geometry": {"coordinates":[-3.0429360867,53.7859954834],"type":"Point"}
}