{
  "type": "Feature",
  "properties": {
    "iso:country":"GB",
    "sg:address":"Truro Baptist Church, Chapel Hill",
    "sg:city":"Truro",
    "sg:classifiers":[
        {
            "category":"Education",
            "subcategory":"Preschool",
            "type":"Public Place"
        }
    ],
    "sg:phone":"+44 1872 263799",
    "sg:postcode":"TR1 3BD",
    "sg:province":"Cornwall",
    "sg:tags":[
        "pre-school",
        "playgroups"
    ],
    "wof:name":"The Pottery Playgroup",
    "wof:placetype":"venue"
},
  "geometry": {"coordinates":[-5.053631,50.26524],"type":"Point"}
}