{
  "type": "Feature",
  "properties": {
    "addr:full":"117 The Bdwy Leigh-on-sea Essex SS9 1PG",
    "addr:housenumber":"117",
    "addr:postcode":"ss9 1pg",
    "addr:street":"The Bdwy",
    "iso:country":"GB",
    "sg:address":"117 The Bdwy",
    "sg:city":"Leigh-on-sea",
    "sg:classifiers":[
        {
            "category":"Shopping",
            "subcategory":"Used Merchandise",
            "type":"Retail Goods"
        }
    ],
    "sg:phone":"+44 1702 74156",
    "sg:postcode":"SS9 1PG",
    "sg:province":"Essex",
    "sg:tags":[
        "shop",
        "second-hand"
    ],
    "wof:name":"Broadway Fayre",
    "wof:placetype":"venue"
},
  "geometry": {"coordinates":[0.6509950161,51.5484809875],"type":"Point"}
}