{
  "type": "Feature",
  "properties": {
    "addr:full":"Room 31 College Business Centre, The College Derby Derbyshire DE22 3WZ",
    "addr:housenumber":"31",
    "addr:postcode":"de22 3wz",
    "addr:street":"College Business Centre The",
    "iso:country":"GB",
    "sg:address":"Room 31 College Business Centre, The College",
    "sg:city":"Derby",
    "sg:classifiers":[
        {
            "category":"Professional",
            "subcategory":"Management & Consulting",
            "type":"Services"
        },
        {
            "category":"Professional",
            "subcategory":"Computer Services",
            "type":"Services"
        }
    ],
    "sg:phone":"+44 1604 660500",
    "sg:postcode":"DE22 3WZ",
    "sg:province":"Derbyshire",
    "sg:tags":[
        "consultant",
        "business"
    ],
    "wof:name":"Solstice Consulting Ltd.",
    "wof:placetype":"venue"
},
  "geometry": {"coordinates":[-1.4932800531,52.919719696],"type":"Point"}
}