{
  "type": "Feature",
  "properties": {
    "addr:full":"High Street, Arnold Nottingham Nottinghamshire NG5 7EE",
    "addr:postcode":"ng5 7ee",
    "addr:street":"High Street",
    "iso:country":"GB",
    "sg:address":"High Street, Arnold",
    "sg:city":"Nottingham",
    "sg:classifiers":[
        {
            "category":"Community Center",
            "type":"Public Place"
        },
        {
            "category":"Government",
            "subcategory":"Office",
            "type":"Public Place"
        }
    ],
    "sg:phone":"+44 115 967 0114",
    "sg:postcode":"NG5 7EE",
    "sg:province":"Nottinghamshire",
    "sg:tags":[
        "recreation",
        "local",
        "leisure",
        "centre"
    ],
    "wof:name":"Arnold Leisure Centre",
    "wof:placetype":"venue"
},
  "geometry": {"coordinates":[-1.1295529604,53.0027389526],"type":"Point"}
}