{
  "type": "Feature",
  "properties": {
    "addr:full":"36 Chapel Market, Islington London Greater London N1 9EN",
    "addr:housenumber":"36",
    "addr:postcode":"n1 9en",
    "addr:street":"Chapel Market",
    "iso:country":"GB",
    "sg:address":"36 Chapel Market, Islington",
    "sg:city":"London",
    "sg:classifiers":[
        {
            "category":"Professional",
            "subcategory":"Computer Services",
            "type":"Services"
        }
    ],
    "sg:phone":"+44 20 7833 2633",
    "sg:postcode":"N1 9EN",
    "sg:province":"Greater London",
    "sg:tags":[
        "consultant"
    ],
    "wof:name":"Ashpark Computer Consultants Ltd.",
    "wof:placetype":"venue"
},
  "geometry": {"coordinates":[-0.1079140007,51.5335922241],"type":"Point"}
}