{
  "type": "Feature",
  "properties": {
    "addr:full":"Unit 3 & 4 Kelvin Ct, Kelvin Rd Wallasey Merseyside L44 7JW",
    "addr:housenumber":"unit 3 & 4",
    "addr:postcode":"l44 7jw",
    "addr:street":"Kelvin Ct Kelvin Rd",
    "iso:country":"GB",
    "sg:address":"Unit 3 & 4 Kelvin Ct, Kelvin Rd",
    "sg:city":"Wallasey",
    "sg:classifiers":[
        {
            "category":"Professional",
            "subcategory":"Printing & Photocopies",
            "type":"Services"
        }
    ],
    "sg:phone":"+44 151 691 1995",
    "sg:postcode":"L44 7JW",
    "sg:province":"Merseyside",
    "sg:tags":[
        "print",
        "finisher"
    ],
    "wof:name":"K & K Print Finishing",
    "wof:placetype":"venue"
},
  "geometry": {"coordinates":[-3.023506,53.406502],"type":"Point"}
}