{
  "type": "Feature",
  "properties": {
    "addr:full":"Curzon House, Brigade Street Bolton Lancashire BL1 4RP",
    "addr:postcode":"bl1 4rp",
    "addr:street":"Brigade Street",
    "iso:country":"GB",
    "sg:address":"Curzon House, Brigade Street",
    "sg:city":"Bolton",
    "sg:classifiers":[
        {
            "category":"Recreation",
            "subcategory":"Amusement Park",
            "type":"Entertainment"
        }
    ],
    "sg:phone":"+44 1204 387377",
    "sg:postcode":"BL1 4RP",
    "sg:province":"Lancashire",
    "sg:tags":[
        "arcade"
    ],
    "wof:name":"Slotamatics (Bolton) Ltd.",
    "wof:placetype":"venue"
},
  "geometry": {"coordinates":[-2.4503591061,53.5775108337],"type":"Point"}
}