{
  "type": "Feature",
  "properties": {
    "addr:full":"8 Ednam Road Dudley West Midlands DY1 1HL",
    "addr:housenumber":"8",
    "addr:postcode":"dy1 1hl",
    "addr:street":"Ednam Road",
    "iso:country":"GB",
    "sg:address":"8 Ednam Road",
    "sg:city":"Dudley",
    "sg:classifiers":[
        {
            "category":"Social Services",
            "type":"Services"
        },
        {
            "category":"Government",
            "subcategory":"Office",
            "type":"Public Place"
        }
    ],
    "sg:phone":"+44 1384 815880",
    "sg:postcode":"DY1 1HL",
    "sg:province":"West Midlands",
    "sg:tags":[
        "local"
    ],
    "wof:name":"Children's Disability Resource Service",
    "wof:placetype":"venue"
},
  "geometry": {"coordinates":[-2.0860159397,52.5119590759],"type":"Point"}
}