{
  "type": "Feature",
  "properties": {
    "iso:country":"GB",
    "sg:address":"4 Grange Parade, Grange Road",
    "sg:city":"Billericay",
    "sg:classifiers":[
        {
            "category":"Retail",
            "subcategory":"Laundry & Dry Cleaning",
            "type":"Services"
        }
    ],
    "sg:phone":"+44 1277 632330",
    "sg:postcode":"CM11 2RF",
    "sg:province":"Essex",
    "sg:tags":[
        "cleaner",
        "alteration"
    ],
    "wof:name":"The Original Touch of Class",
    "wof:placetype":"venue"
},
  "geometry": {"coordinates":[0.430359,51.61388],"type":"Point"}
}