{
  "type": "Feature",
  "properties": {
    "iso:country":"GB",
    "sg:address":"13 Ludgate Close, Waltham",
    "sg:city":"Grimsby",
    "sg:classifiers":[
        {
            "category":"Building & Trades",
            "subcategory":"Plumbing",
            "type":"Services"
        }
    ],
    "sg:phone":"+44 1673 828774",
    "sg:postcode":"DN37 0LX",
    "sg:province":"Lincolnshire",
    "sg:tags":[
        "heating"
    ],
    "wof:name":"D & B Giles Ltd.",
    "wof:placetype":"venue"
},
  "geometry": {"coordinates":[-0.101915,53.517891],"type":"Point"}
}