{
  "type": "Feature",
  "properties": {
    "addr:full":"14 Kingsland Newcastle Upon Tyne Tyne and Wear NE2 3AL",
    "addr:housenumber":"14",
    "addr:postcode":"ne2 3al",
    "addr:street":"Kingsland",
    "iso:country":"GB",
    "sg:address":"14 Kingsland",
    "sg:city":"Newcastle Upon Tyne",
    "sg:classifiers":[
        {
            "category":"Health Services",
            "subcategory":"Health Practitioner",
            "type":"Services"
        }
    ],
    "sg:phone":"+44 191 281 8032",
    "sg:postcode":"NE2 3AL",
    "sg:province":"Tyne and Wear",
    "sg:tags":[
        "technique",
        "alexander"
    ],
    "wof:name":"M Marcus",
    "wof:placetype":"venue"
},
  "geometry": {"coordinates":[-1.607591033,54.9866905212],"type":"Point"}
}