{
  "type": "Feature",
  "properties": {
    "addr:full":"11 Cottage Street Macclesfield Cheshire SK11 8DZ",
    "addr:housenumber":"11",
    "addr:postcode":"sk11 8dz",
    "addr:street":"Cottage Street",
    "iso:country":"GB",
    "sg:address":"11 Cottage Street",
    "sg:city":"Macclesfield",
    "sg:classifiers":[
        {
            "category":"Building & Trades",
            "subcategory":"Construction",
            "type":"Services"
        }
    ],
    "sg:phone":"+44 1625 261640",
    "sg:postcode":"SK11 8DZ",
    "sg:province":"Cheshire",
    "sg:tags":[
        "decorator",
        "painter"
    ],
    "wof:name":"Jeremy Allan Fellows",
    "wof:placetype":"venue"
},
  "geometry": {"coordinates":[-2.1358730793,53.258354187],"type":"Point"}
}