{
  "type": "Feature",
  "properties": {
    "addr:full":"31 Grove Terrace, Highgate Road London Greater London NW5 1PL",
    "addr:housenumber":"31",
    "addr:postcode":"nw5 1pl",
    "addr:street":"Grove Terrace Highgate Road",
    "iso:country":"GB",
    "sg:address":"31 Grove Terrace, Highgate Road",
    "sg:city":"London",
    "sg:classifiers":[
        {
            "category":"Professional",
            "subcategory":"Art Services",
            "type":"Services"
        }
    ],
    "sg:phone":"+44 20 7267 3755",
    "sg:postcode":"NW5 1PL",
    "sg:province":"Greater London",
    "sg:tags":[
        "photographer"
    ],
    "wof:name":"Parliament Hill Studios",
    "wof:placetype":"venue"
},
  "geometry": {"coordinates":[-0.1483740062,51.558631897],"type":"Point"}
}