{
  "type": "Feature",
  "properties": {
    "iso:country":"GB",
    "sg:address":"Tythe Barn, Mottisfont",
    "sg:city":"Romsey",
    "sg:classifiers":[
        {
            "category":"Home & Garden",
            "subcategory":"Home Furnishings",
            "type":"Retail Goods"
        }
    ],
    "sg:phone":"+44 1794 342330",
    "sg:postcode":"SO51 0LP",
    "sg:province":"Hampshire",
    "sg:tags":[
        "wall",
        "wallpaper",
        "covering"
    ],
    "wof:name":"Period Doors & Interiors",
    "wof:placetype":"venue"
},
  "geometry": {"coordinates":[-1.5487430096,51.0394020081],"type":"Point"}
}