{
  "type": "Feature",
  "properties": {
    "iso:country":"GB",
    "sg:address":"Norfolk House",
    "sg:city":"Uckfield",
    "sg:classifiers":[
        {
            "category":"Real Estate",
            "subcategory":"Surveying",
            "type":"Services"
        }
    ],
    "sg:phone":"+44 1825 768319",
    "sg:postcode":"TN22 1EP",
    "sg:province":"East Sussex",
    "sg:tags":[
        "surveyor",
        "land"
    ],
    "wof:name":"Aworth Land Surveys Ltd.",
    "wof:placetype":"venue"
},
  "geometry": {"coordinates":[0.09665,50.971813],"type":"Point"}
}