{
  "type": "Feature",
  "properties": {
    "iso:country":"GB",
    "sg:address":"Christy's Lane",
    "sg:city":"Shaftesbury",
    "sg:classifiers":[
        {
            "category":"Professional",
            "type":"Services"
        }
    ],
    "sg:phone":"+44 1747 851585",
    "sg:postcode":"SP7 8PH",
    "sg:province":"Dorset",
    "sg:tags":[
        "linen",
        "hire"
    ],
    "wof:name":"Stalbridge Linen Services Ltd.",
    "wof:placetype":"venue"
},
  "geometry": {"coordinates":[-2.19064,51.007561],"type":"Point"}
}