{
  "type": "Feature",
  "properties": {
    "iso:country":"GB",
    "sg:address":"5-7 Burwash Road",
    "sg:city":"Hove",
    "sg:classifiers":[
        {
            "category":"Government",
            "subcategory":"Fire Station",
            "type":"Public Place"
        }
    ],
    "sg:postcode":"BN3 8GP",
    "sg:province":"East Sussex",
    "sg:tags":[
        "w'sale",
        "lighting"
    ],
    "wof:name":"S E L S Ltd.",
    "wof:placetype":"venue"
},
  "geometry": {"coordinates":[-0.187766999,50.8517494202],"type":"Point"}
}