{
  "type": "Feature",
  "properties": {
    "iso:country":"GB",
    "sg:address":"364 Dover Rd, Walmer",
    "sg:city":"Deal",
    "sg:classifiers":[
        {
            "category":"Autos & Motor Vehicles",
            "subcategory":"Auto Supplies",
            "type":"Retail Goods"
        }
    ],
    "sg:phone":"+44 1304 374037",
    "sg:postcode":"CT14 7NX",
    "sg:province":"Kent",
    "sg:tags":[
        "tyre"
    ],
    "wof:name":"Hi-q Tyreservices",
    "wof:placetype":"venue"
},
  "geometry": {"coordinates":[1.387998,51.199875],"type":"Point"}
}