{
  "type": "Feature",
  "properties": {
    "addr:full":"76 Winchester Avenue Upminster Essex RM14 3LR",
    "addr:housenumber":"76",
    "addr:postcode":"rm14 3lr",
    "addr:street":"Winchester Avenue",
    "iso:country":"GB",
    "sg:address":"76 Winchester Avenue",
    "sg:city":"Upminster",
    "sg:classifiers":[
        {
            "category":"Professional",
            "subcategory":"Engineering",
            "type":"Services"
        }
    ],
    "sg:phone":"+44 1708 223773",
    "sg:postcode":"RM14 3LR",
    "sg:province":"Essex",
    "sg:tags":[
        "contractor",
        "electrical",
        "engineer"
    ],
    "wof:name":"J M Henderson",
    "wof:placetype":"venue"
},
  "geometry": {"coordinates":[0.273721,51.5606],"type":"Point"}
}