{
  "type": "Feature",
  "properties": {
    "iso:country":"GB",
    "sg:address":"179 Hoe Street",
    "sg:city":"London",
    "sg:classifiers":[
        {
            "category":"Real Estate",
            "subcategory":"Real Estate Agent",
            "type":"Services"
        }
    ],
    "sg:phone":"+44 20 8520 0077",
    "sg:postcode":"E17 3AP",
    "sg:province":"Greater London",
    "wof:name":"Central Estate Agents (Walthamstow) Ltd.",
    "wof:placetype":"venue"
},
  "geometry": {"coordinates":[-0.0189399999,51.5840187073],"type":"Point"}
}