{
  "type": "Feature",
  "properties": {
    "addr:full":"New Premier House, 150 Southampton Row London Greater London WC1B 5AL",
    "addr:housenumber":"150",
    "addr:postcode":"wc1b 5al",
    "addr:street":"Southampton Row",
    "iso:country":"GB",
    "sg:address":"New Premier House, 150 Southampton Row",
    "sg:city":"London",
    "sg:classifiers":[
        {
            "category":"Banks & Credit Unions",
            "subcategory":"Investment Brokerage",
            "type":"Services"
        }
    ],
    "sg:phone":"+44 20 7278 3221",
    "sg:postcode":"WC1B 5AL",
    "sg:province":"Greater London",
    "sg:tags":[
        "pension"
    ],
    "wof:name":"P N P F Trust Co. Ltd.",
    "wof:placetype":"venue"
},
  "geometry": {"coordinates":[-0.086025998,51.4784622192],"type":"Point"}
}