{
  "type": "Feature",
  "properties": {
    "addr:full":"390 Boldmere Road Sutton Coldfield West Midlands B73 5EZ",
    "addr:housenumber":"390",
    "addr:postcode":"b73 5ez",
    "addr:street":"Boldmere Road",
    "iso:country":"GB",
    "sg:address":"390 Boldmere Road",
    "sg:city":"Sutton Coldfield",
    "sg:classifiers":[
        {
            "category":"Professional",
            "subcategory":"Lawyer & Legal Services",
            "type":"Services"
        }
    ],
    "sg:phone":"+44 121 382 5550",
    "sg:postcode":"B73 5EZ",
    "sg:province":"West Midlands",
    "sg:tags":[
        "solicitor"
    ],
    "wof:name":"ANTHONY LEA & CO",
    "wof:placetype":"venue"
},
  "geometry": {"coordinates":[-1.836096,52.536991],"type":"Point"}
}