{
  "type": "Feature",
  "properties": {
    "iso:country":"GB",
    "sg:address":"20 Crockwell Street",
    "sg:city":"Bodmin",
    "sg:classifiers":[
        {
            "category":"Professional",
            "subcategory":"Accounting & Tax Preparation",
            "type":"Services"
        }
    ],
    "sg:postcode":"PL31 2DS",
    "sg:province":"Cornwall",
    "sg:tags":[
        "accountant"
    ],
    "wof:name":"P A Miller & Co",
    "wof:placetype":"venue"
},
  "geometry": {"coordinates":[-4.719043,50.471832],"type":"Point"}
}