{
  "type": "Feature",
  "properties": {
    "iso:country":"GB",
    "sg:address":"76 Cambridge Road",
    "sg:city":"St Helens",
    "sg:classifiers":[
        {
            "category":"Personal",
            "subcategory":"Beauty Salon",
            "type":"Services"
        }
    ],
    "sg:phone":"+44 1744 611644",
    "sg:postcode":"WA10 4HD",
    "sg:province":"Merseyside",
    "sg:tags":[
        "unisex",
        "hairdresser"
    ],
    "wof:name":"Cambridge 76",
    "wof:placetype":"venue"
},
  "geometry": {"coordinates":[-2.7530360222,53.4549865723],"type":"Point"}
}