{
  "type": "Feature",
  "properties": {
    "addr:full":"Helix House, 50 Kimpton Road Luton Bedfordshire LU2 0NB",
    "addr:housenumber":"50",
    "addr:postcode":"lu2 0nb",
    "addr:street":"Kimpton Road",
    "iso:country":"GB",
    "sg:address":"Helix House, 50 Kimpton Road",
    "sg:city":"Luton",
    "sg:classifiers":[
        {
            "category":"Autos & Motor Vehicles",
            "subcategory":"Auto Supplies",
            "type":"Retail Goods"
        }
    ],
    "sg:phone":"+44 1582 482900",
    "sg:postcode":"LU2 0NB",
    "sg:province":"Bedfordshire",
    "sg:tags":[
        "car",
        "component"
    ],
    "wof:name":"Peguform U K Ltd.",
    "wof:placetype":"venue"
},
  "geometry": {"coordinates":[-0.394739002,51.8738517761],"type":"Point"}
}