{
  "type": "Feature",
  "properties": {
    "iso:country":"GB",
    "sg:address":"Castle St",
    "sg:city":"Beaumaris",
    "sg:classifiers":[
        {
            "category":"Museum",
            "subcategory":"Art Museum",
            "type":"Entertainment"
        }
    ],
    "sg:phone":"+44 1248 811691",
    "sg:postcode":"LL58 8AP",
    "sg:province":"Isle of Anglesey",
    "sg:tags":[
        "gallery"
    ],
    "wof:name":"The Old Court House",
    "wof:placetype":"venue"
},
  "geometry": {"coordinates":[-4.0909957886,53.2638893127],"type":"Point"}
}