{
  "type": "Feature",
  "properties": {
    "addr:full":"11 Beam Street Nantwich Cheshire CW5 5NA",
    "addr:housenumber":"11",
    "addr:postcode":"cw5 5na",
    "addr:street":"Beam Street",
    "iso:country":"GB",
    "sg:address":"11 Beam Street",
    "sg:city":"Nantwich",
    "sg:classifiers":[
        {
            "category":"Shopping",
            "subcategory":"Clothing, Apparel, & Fashions",
            "type":"Retail Goods"
        },
        {
            "category":"Shopping",
            "subcategory":"Baby Store",
            "type":"Retail Goods"
        }
    ],
    "sg:phone":"+44 1270 628036",
    "sg:postcode":"CW5 5NA",
    "sg:province":"Cheshire",
    "sg:tags":[
        "child",
        "childrens",
        "babywear"
    ],
    "sg:website":"http://www.ethelaustin.co.uk",
    "wof:name":"Ethel Austin Ltd",
    "wof:placetype":"venue"
},
  "geometry": {"coordinates":[-2.5221459866,53.0685348511],"type":"Point"}
}