{
  "type": "Feature",
  "properties": {
    "addr:full":"Pankridge Street, Crondall Farnham Hampshire GU10 5QU",
    "addr:postcode":"gu10 5qu",
    "addr:street":"Pankridge Street",
    "iso:country":"GB",
    "sg:address":"Pankridge Street, Crondall",
    "sg:city":"Farnham",
    "sg:classifiers":[
        {
            "category":"Bars & Pubs",
            "type":"Food & Drink"
        }
    ],
    "sg:phone":"+44 1252 850418",
    "sg:postcode":"GU10 5QU",
    "sg:province":"Hampshire",
    "sg:tags":[
        "pubs",
        "inn"
    ],
    "wof:name":"The Hampshire Arms",
    "wof:placetype":"venue"
},
  "geometry": {"coordinates":[-0.8592759967,51.2392311096],"type":"Point"}
}