{
  "type": "Feature",
  "properties": {
    "addr:full":"30 Cove Rd Bournemouth Dorset BH10 4BN",
    "addr:housenumber":"30",
    "addr:postcode":"bh10 4bn",
    "addr:street":"Cove Rd",
    "iso:country":"GB",
    "sg:address":"30 Cove Rd",
    "sg:city":"Bournemouth",
    "sg:classifiers":[
        {
            "category":"Retail",
            "subcategory":"Driving School",
            "type":"Services"
        }
    ],
    "sg:phone":"+44 1202 518780",
    "sg:postcode":"BH10 4BN",
    "sg:province":"Dorset",
    "wof:name":"Mornys School Of Motoring",
    "wof:placetype":"venue"
},
  "geometry": {"coordinates":[-1.9005429745,50.7514686584],"type":"Point"}
}