{
  "type": "Feature",
  "properties": {
    "addr:full":"Public Hall, Lady Street Kidwelly Carmarthenshire SA17 4UD",
    "addr:postcode":"sa17 4ud",
    "addr:street":"Lady Street",
    "iso:country":"GB",
    "sg:address":"Public Hall, Lady Street",
    "sg:city":"Kidwelly",
    "sg:classifiers":[
        {
            "category":"Education",
            "subcategory":"Library",
            "type":"Public Place"
        }
    ],
    "sg:phone":"+44 1554 891501",
    "sg:postcode":"SA17 4UD",
    "sg:province":"Carmarthenshire",
    "sg:tags":[
        "book"
    ],
    "wof:name":"Kidwelly Library",
    "wof:placetype":"venue"
},
  "geometry": {"coordinates":[-4.3034381866,51.7365188599],"type":"Point"}
}