{
  "type": "Feature",
  "properties": {
    "addr:full":"The Barn Totnes Devon TQ9 7JG",
    "addr:postcode":"tq9 7jg",
    "iso:country":"GB",
    "sg:address":"The Barn",
    "sg:city":"Totnes",
    "sg:classifiers":[
        {
            "category":"Taxi",
            "type":"Transportation"
        }
    ],
    "sg:phone":"+44 1803 868686",
    "sg:postcode":"TQ9 7JG",
    "sg:province":"Devon",
    "sg:tags":[
        "mini",
        "cab"
    ],
    "wof:name":"Castle Cabs of Totnes",
    "wof:placetype":"venue"
},
  "geometry": {"coordinates":[-3.688092947,50.4341468811],"type":"Point"}
}