{
  "type": "Feature",
  "properties": {
    "addr:full":"150 London Road St Albans Hertfordshire AL1 1PQ",
    "addr:housenumber":"150",
    "addr:postcode":"al1 1pq",
    "addr:street":"London Road",
    "iso:country":"GB",
    "sg:address":"150 London Road",
    "sg:city":"St Albans",
    "sg:classifiers":[
        {
            "category":"Food & Beverages",
            "subcategory":"Bakery",
            "type":"Retail Goods"
        }
    ],
    "sg:postcode":"AL1 1PQ",
    "sg:province":"Hertfordshire",
    "sg:tags":[
        "pizza"
    ],
    "wof:name":"H & H Pizza",
    "wof:placetype":"venue"
},
  "geometry": {"coordinates":[-0.3331010044,51.7483253479],"type":"Point"}
}