{
  "type": "Feature",
  "properties": {
    "addr:full":"Nutts Lane Ind Est, Coventry Rd Hinckley Leicestershire LE10 3EJ",
    "addr:postcode":"le10 3ej",
    "addr:street":"Nutts Lane;Est Coventry Rd",
    "iso:country":"GB",
    "sg:address":"Nutts Lane Ind Est, Coventry Rd",
    "sg:city":"Hinckley",
    "sg:classifiers":[
        {
            "category":"Manufacturing",
            "subcategory":"Metals",
            "type":"Manufacturing & Wholesale Goods"
        }
    ],
    "sg:phone":"+44 1455 618632",
    "sg:postcode":"LE10 3EJ",
    "sg:province":"Leicestershire",
    "sg:tags":[
        "fabricator",
        "aluminium"
    ],
    "wof:name":"Founders Architectural Ltd",
    "wof:placetype":"venue"
},
  "geometry": {"coordinates":[-1.397019,52.531414],"type":"Point"}
}