{
  "type": "Feature",
  "properties": {
    "addr:full":"Church Hill Bungalow Peterborough Cambridgeshire PE8 5PG",
    "addr:postcode":"pe8 5pg",
    "addr:street":"Peterborough",
    "iso:country":"GB",
    "sg:address":"Church Hill Bungalow",
    "sg:city":"Peterborough",
    "sg:classifiers":[
        {
            "category":"Place Of Worship",
            "type":"Public Place"
        }
    ],
    "sg:phone":"+44 1832 272374",
    "sg:postcode":"PE8 5PG",
    "sg:province":"Cambridgeshire",
    "wof:name":"St Andrews Church",
    "wof:placetype":"venue"
},
  "geometry": {"coordinates":[-0.4563739896,52.451915741],"type":"Point"}
}