{
  "type": "Feature",
  "properties": {
    "addr:full":"33 Botley Road Oxford Oxfordshire OX2 0BN",
    "addr:housenumber":"33",
    "addr:postcode":"ox2 0bn",
    "addr:street":"Botley Road",
    "iso:country":"GB",
    "sg:address":"33 Botley Road",
    "sg:city":"Oxford",
    "sg:classifiers":[
        {
            "category":"Real Estate",
            "subcategory":"Real Estate Agent",
            "type":"Services"
        }
    ],
    "sg:phone":"+44 1865 246502",
    "sg:postcode":"OX2 0BN",
    "sg:province":"Oxfordshire",
    "wof:name":"Pearce Alder & Co.",
    "wof:placetype":"venue"
},
  "geometry": {"coordinates":[-1.276366,51.752251],"type":"Point"}
}