{
  "type": "Feature",
  "properties": {
    "iso:country":"GB",
    "sg:address":"Malling House",
    "sg:city":"West Malling",
    "sg:classifiers":[
        {
            "category":"Banks & Credit Unions",
            "subcategory":"Financial Services",
            "type":"Services"
        }
    ],
    "sg:postcode":"ME19 6QL",
    "sg:province":"Kent",
    "sg:tags":[
        "consultant"
    ],
    "wof:name":"Omni Leasing Ltd.",
    "wof:placetype":"venue"
},
  "geometry": {"coordinates":[0.41294,51.293709],"type":"Point"}
}