{
  "type": "Feature",
  "properties": {
    "iso:country":"GB",
    "sg:address":"214 George Street",
    "sg:city":"Aberdeen",
    "sg:classifiers":[
        {
            "category":"Fast Food",
            "type":"Food & Drink"
        }
    ],
    "sg:phone":"+44 1224 634700",
    "sg:postcode":"AB25 1BS",
    "sg:province":"Aberdeen City",
    "sg:tags":[
        "away",
        "take"
    ],
    "wof:name":"Crustys Sandwich & Salad Bar",
    "wof:placetype":"venue"
},
  "geometry": {"coordinates":[-2.1021990776,57.1509819031],"type":"Point"}
}