{
  "type": "Feature",
  "properties": {
    "addr:full":"7 Cheapside Liverpool Merseyside L2 2DY",
    "addr:housenumber":"7",
    "addr:postcode":"l2 2dy",
    "addr:street":"Cheapside",
    "iso:country":"GB",
    "sg:address":"7 Cheapside",
    "sg:city":"Liverpool",
    "sg:classifiers":[
        {
            "category":"Bars & Pubs",
            "type":"Food & Drink"
        },
        {
            "category":"Community Center",
            "subcategory":"Social",
            "type":"Public Place"
        }
    ],
    "sg:phone":"+44 151 231 6851",
    "sg:postcode":"L2 2DY",
    "sg:province":"Merseyside",
    "sg:tags":[
        "pubs",
        "house",
        "inn",
        "activity"
    ],
    "wof:name":"Rose & Crown",
    "wof:placetype":"venue"
},
  "geometry": {"coordinates":[-2.9871139526,53.4088439941],"type":"Point"}
}