{
  "type": "Feature",
  "properties": {
    "iso:country":"GB",
    "sg:address":"3 Roffords, Goldsworth Park",
    "sg:city":"Woking",
    "sg:classifiers":[
        {
            "category":"Taxi",
            "type":"Transportation"
        },
        {
            "category":"Military Area",
            "subcategory":"Air Force Base",
            "type":"Public Place"
        }
    ],
    "sg:phone":"+44 1483 770999",
    "sg:postcode":"GU21 3BH",
    "sg:province":"Surrey",
    "sg:tags":[
        "hire",
        "private"
    ],
    "wof:name":"A J's Private Hire",
    "wof:placetype":"venue"
},
  "geometry": {"coordinates":[-0.5585500002,51.3220748901],"type":"Point"}
}