{
  "type": "Feature",
  "properties": {
    "iso:country":"GB",
    "sg:address":"2 Holmewood Road",
    "sg:city":"Tunbridge Wells",
    "sg:classifiers":[
        {
            "category":"Building & Trades",
            "subcategory":"Construction",
            "type":"Services"
        }
    ],
    "sg:phone":"+44 1892 527143",
    "sg:postcode":"TN4 9HA",
    "sg:province":"Kent",
    "sg:tags":[
        "decorator",
        "painter"
    ],
    "wof:name":"G L M",
    "wof:placetype":"venue"
},
  "geometry": {"coordinates":[0.2756749988,51.1481399536],"type":"Point"}
}