{
  "type": "Feature",
  "properties": {
    "addr:full":"Seggimore Farm, Bishop Norton Rd, Glentham Market Rasen Lincolnshire LN8 2EU",
    "addr:postcode":"ln8 2eu",
    "addr:street":"Bishop Norton Rd;Rasen",
    "iso:country":"GB",
    "sg:address":"Seggimore Farm, Bishop Norton Rd, Glentham",
    "sg:city":"Market Rasen",
    "sg:classifiers":[
        {
            "category":"Farming",
            "subcategory":"Farm",
            "type":"Manufacturing & Wholesale Goods"
        }
    ],
    "sg:postcode":"LN8 2EU",
    "sg:province":"Lincolnshire",
    "sg:tags":[
        "mixed",
        "crop"
    ],
    "wof:name":"Green,J R,& Sons",
    "wof:placetype":"venue"
},
  "geometry": {"coordinates":[-0.4965260029,53.4045372009],"type":"Point"}
}