{
  "type": "Feature",
  "properties": {
    "addr:full":"6 Flempton Rd Leyton Greater London E10 7NH",
    "addr:housenumber":"6",
    "addr:postcode":"e10 7nh",
    "addr:street":"Flempton Rd",
    "iso:country":"GB",
    "sg:address":"6 Flempton Rd",
    "sg:city":"Leyton",
    "sg:classifiers":[
        {
            "category":"Building & Trades",
            "subcategory":"Plumbing",
            "type":"Services"
        }
    ],
    "sg:phone":"+44 20 8556 0151",
    "sg:postcode":"E10 7NH",
    "sg:province":"Greater London",
    "sg:tags":[
        "heating"
    ],
    "wof:name":"J F Hassett & Sons",
    "wof:placetype":"venue"
},
  "geometry": {"coordinates":[-0.0316269994,51.5684013367],"type":"Point"}
}