{
  "type": "Feature",
  "properties": {
    "addr:full":"53 Pool Street Caernarfon Gwynedd LL55 2AE",
    "addr:housenumber":"53",
    "addr:postcode":"ll55 2ae",
    "addr:street":"Pool Street",
    "iso:country":"GB",
    "sg:address":"53 Pool Street",
    "sg:city":"Caernarfon",
    "sg:classifiers":[
        {
            "category":"Shopping",
            "subcategory":"Clothing, Apparel, & Fashions",
            "type":"Retail Goods"
        }
    ],
    "sg:phone":"+44 1286 675741",
    "sg:postcode":"LL55 2AE",
    "sg:province":"Gwynedd",
    "sg:tags":[
        "lingerie",
        "hosiery"
    ],
    "wof:name":"Siopllinos",
    "wof:placetype":"venue"
},
  "geometry": {"coordinates":[-4.2737569809,53.1395950317],"type":"Point"}
}