{
  "type": "Feature",
  "properties": {
    "iso:country":"GB",
    "sg:address":"6 Alder Close",
    "sg:city":"Bishops Stortford",
    "sg:classifiers":[
        {
            "category":"Building & Trades",
            "subcategory":"Plumbing",
            "type":"Services"
        }
    ],
    "sg:phone":"+44 1279 506236",
    "sg:postcode":"CM23 4JX",
    "sg:province":"Essex",
    "sg:tags":[
        "central",
        "installation",
        "system",
        "servicing",
        "heating"
    ],
    "wof:name":"Malcolm Chalk",
    "wof:placetype":"venue"
},
  "geometry": {"coordinates":[0.1414739937,51.8575248718],"type":"Point"}
}