{
  "type": "Feature",
  "properties": {
    "addr:full":"209-210 Western Interntnl Market, Hayes Road Southall Greater London UB2 5XH",
    "addr:housenumber":"209-210",
    "addr:postcode":"ub2 5xh",
    "addr:street":"Western Interntnl;Hayes Road",
    "iso:country":"GB",
    "sg:address":"209-210 Western Interntnl Market, Hayes Road",
    "sg:city":"Southall",
    "sg:classifiers":[
        {
            "category":"Building & Trades",
            "subcategory":"Construction",
            "type":"Services"
        }
    ],
    "sg:phone":"+44 20 8561 8211",
    "sg:postcode":"UB2 5XH",
    "sg:province":"Greater London",
    "sg:tags":[
        "fork",
        "lift",
        "truck"
    ],
    "wof:name":"Stackatruck",
    "wof:placetype":"venue"
},
  "geometry": {"coordinates":[-0.40435,51.495548],"type":"Point"}
}