{
  "type": "Feature",
  "properties": {
    "addr:full":"Old Estate Office, Harleyford Estate, Henley Road Marlow Berkshire SL7 2DX",
    "addr:postcode":"sl7 2dx",
    "addr:street":"Harleyford Estate Henley Road",
    "iso:country":"GB",
    "sg:address":"Old Estate Office, Harleyford Estate, Henley Road",
    "sg:city":"Marlow",
    "sg:classifiers":[
        {
            "category":"Professional",
            "subcategory":"Computer Services",
            "type":"Services"
        }
    ],
    "sg:phone":"+44 1628 483322",
    "sg:postcode":"SL7 2DX",
    "sg:province":"Berkshire",
    "sg:tags":[
        "system",
        "software"
    ],
    "wof:name":"Deltascheme Ltd.",
    "wof:placetype":"venue"
},
  "geometry": {"coordinates":[-0.776189,51.573067],"type":"Point"}
}