{
  "type": "Feature",
  "properties": {
    "iso:country":"GB",
    "sg:address":"Unit 3 Plumb Units East Lane, Stainforth",
    "sg:city":"Doncaster",
    "sg:classifiers":[
        {
            "category":"Manufacturing",
            "subcategory":"Metals",
            "type":"Manufacturing & Wholesale Goods"
        }
    ],
    "sg:postcode":"DN7 5HF",
    "sg:province":"South Yorkshire",
    "sg:tags":[
        "steel",
        "fabricator",
        "erectors"
    ],
    "wof:name":"Brabbs Fabrication",
    "wof:placetype":"venue"
},
  "geometry": {"coordinates":[-1.030399,53.595074],"type":"Point"}
}