{
  "type": "Feature",
  "properties": {
    "addr:full":"17-19 Water Street, Radcliffe Manchester Greater Manchester M26 3DE",
    "addr:housenumber":"17-19",
    "addr:postcode":"m26 3de",
    "addr:street":"Water Street",
    "iso:country":"GB",
    "sg:address":"17-19 Water Street, Radcliffe",
    "sg:city":"Manchester",
    "sg:classifiers":[
        {
            "category":"Food & Beverages",
            "subcategory":"Meat & Fish",
            "type":"Retail Goods"
        }
    ],
    "sg:phone":"+44 161 724 0633",
    "sg:postcode":"M26 3DE",
    "sg:province":"Greater Manchester",
    "sg:tags":[
        "chip"
    ],
    "wof:name":"Boston Chinese Takeaway",
    "wof:placetype":"venue"
},
  "geometry": {"coordinates":[-2.3295240402,53.563293457],"type":"Point"}
}