{
  "type": "Feature",
  "properties": {
    "addr:full":"18 Crown Rd, St Margarets Twickenham Greater London TW1 3EE",
    "addr:housenumber":"18",
    "addr:postcode":"tw1 3ee",
    "addr:street":"Crown Rd",
    "iso:country":"GB",
    "sg:address":"18 Crown Rd, St Margarets",
    "sg:city":"Twickenham",
    "sg:classifiers":[
        {
            "category":"Shopping",
            "subcategory":"Discount & Variety Stores",
            "type":"Retail Goods"
        }
    ],
    "sg:postcode":"TW1 3EE",
    "sg:province":"Greater London",
    "sg:tags":[
        "shop",
        "model"
    ],
    "wof:name":"Plumber,Joy,",
    "wof:placetype":"venue"
},
  "geometry": {"coordinates":[-0.319528,51.454418],"type":"Point"}
}