{
  "type": "Feature",
  "properties": {
    "iso:country":"GB",
    "sg:address":"Prestwood Road, Heathtown",
    "sg:city":"Wolverhampton",
    "sg:classifiers":[
        {
            "category":"Home & Garden",
            "subcategory":"Hardware",
            "type":"Retail Goods"
        }
    ],
    "sg:phone":"+44 1902 728809",
    "sg:postcode":"WV11 1RA",
    "sg:province":"Staffordshire",
    "sg:tags":[
        "retailer",
        "diy"
    ],
    "wof:name":"Malcolm's D I Y",
    "wof:placetype":"venue"
},
  "geometry": {"coordinates":[-2.098609,52.603466],"type":"Point"}
}