{
  "type": "Feature",
  "properties": {
    "addr:full":"8 High Street Arc Cardiff Cardiff CF1 2BB",
    "addr:housenumber":"8",
    "addr:postcode":"cf1 2bb",
    "addr:street":"High Street Arc",
    "iso:country":"GB",
    "sg:address":"8 High Street Arc",
    "sg:city":"Cardiff",
    "sg:classifiers":[
        {
            "category":"Shopping",
            "subcategory":"Used Merchandise",
            "type":"Retail Goods"
        }
    ],
    "sg:phone":"+44 29 2030 4499",
    "sg:postcode":"CF1 2BB",
    "sg:province":"Cardiff",
    "sg:tags":[
        "shop",
        "second-hand"
    ],
    "wof:name":"High Street Xchange",
    "wof:placetype":"venue"
},
  "geometry": {"coordinates":[-3.1793129444,51.4808158875],"type":"Point"}
}