{
  "type": "Feature",
  "properties": {
    "addr:full":"10 Pin Mill Close Ipswich Suffolk IP2 9RU",
    "addr:housenumber":"10",
    "addr:postcode":"ip2 9ru",
    "addr:street":"Pin Mill Close",
    "iso:country":"GB",
    "sg:address":"10 Pin Mill Close",
    "sg:city":"Ipswich",
    "sg:classifiers":[
        {
            "category":"Utilities",
            "type":"Services"
        }
    ],
    "sg:phone":"+44 1473 683814",
    "sg:postcode":"IP2 9RU",
    "sg:province":"Suffolk",
    "sg:tags":[
        "internet"
    ],
    "wof:name":"Propoganda Web Designers & Builders",
    "wof:placetype":"venue"
},
  "geometry": {"coordinates":[1.1102279425,52.0379524231],"type":"Point"}
}