{
  "type": "Feature",
  "properties": {
    "iso:country":"GB",
    "sg:address":"48-49 Albion Terrace, Lynemouth",
    "sg:city":"Morpeth",
    "sg:classifiers":[
        {
            "category":"Shopping",
            "subcategory":"News",
            "type":"Retail Goods"
        }
    ],
    "sg:phone":"+44 1670 860310",
    "sg:postcode":"NE61 5TA",
    "sg:province":"Northumberland",
    "sg:tags":[
        "newsagent"
    ],
    "wof:name":"M & I Cullen",
    "wof:placetype":"venue"
},
  "geometry": {"coordinates":[-1.542534,55.213989],"type":"Point"}
}