{
  "type": "Feature",
  "properties": {
    "iso:country":"GB",
    "sg:address":"30 Mount View Rd",
    "sg:city":"London",
    "sg:classifiers":[
        {
            "category":"Professional",
            "subcategory":"Accounting & Tax Preparation",
            "type":"Services"
        }
    ],
    "sg:postcode":"E4 7EF",
    "sg:province":"Greater London",
    "sg:tags":[
        "accountant"
    ],
    "wof:name":"Turner,Derrick,",
    "wof:placetype":"venue"
},
  "geometry": {"coordinates":[0.00072,51.6329345703],"type":"Point"}
}