{
  "type": "Feature",
  "properties": {
    "addr:full":"30 Marine Parade Eastbourne East Sussex BN22 7AY",
    "addr:housenumber":"30",
    "addr:postcode":"bn22 7ay",
    "addr:street":"Marine Parade",
    "iso:country":"GB",
    "sg:address":"30 Marine Parade",
    "sg:city":"Eastbourne",
    "sg:classifiers":[
        {
            "category":"Fast Food",
            "type":"Food & Drink"
        },
        {
            "category":"Ice Cream",
            "type":"Food & Drink"
        }
    ],
    "sg:phone":"+44 1323 722128",
    "sg:postcode":"BN22 7AY",
    "sg:province":"East Sussex",
    "sg:tags":[
        "shop",
        "mobile",
        "away",
        "parlour",
        "take"
    ],
    "wof:name":"Fusciardi Ice Cream Parlour",
    "wof:placetype":"venue"
},
  "geometry": {"coordinates":[0.294667,50.76944],"type":"Point"}
}