{
  "type": "Feature",
  "properties": {
    "addr:full":"31 Kings Road West Swanage Dorset BH19 1HF",
    "addr:housenumber":"31",
    "addr:postcode":"bh19 1hf",
    "addr:street":"Kings Road West",
    "iso:country":"GB",
    "sg:address":"31 Kings Road West",
    "sg:city":"Swanage",
    "sg:classifiers":[
        {
            "category":"Travel",
            "subcategory":"Hotels & Motels",
            "type":"Entertainment"
        }
    ],
    "sg:phone":"+44 1929 422064",
    "sg:postcode":"BH19 1HF",
    "sg:province":"Dorset",
    "sg:tags":[
        "house",
        "guest"
    ],
    "wof:name":"ST MICHAELS GUEST HOUSE",
    "wof:placetype":"venue"
},
  "geometry": {"coordinates":[-1.9599620104,50.6092681885],"type":"Point"}
}