{
  "type": "Feature",
  "properties": {
    "addr:full":"Tyddyn-y-fron Abergele Conwy LL22 8PL",
    "addr:postcode":"ll22 8pl",
    "addr:street":"Tyddyn-Y-Fron",
    "iso:country":"GB",
    "sg:address":"Tyddyn-y-fron",
    "sg:city":"Abergele",
    "sg:classifiers":[
        {
            "category":"Building & Trades",
            "subcategory":"Equipment Rental",
            "type":"Services"
        }
    ],
    "sg:postcode":"LL22 8PL",
    "sg:province":"Conwy",
    "sg:tags":[
        "plant",
        "machinery"
    ],
    "wof:name":"David J Williams",
    "wof:placetype":"venue"
},
  "geometry": {"coordinates":[-3.5811440945,53.2843551636],"type":"Point"}
}