{
  "type": "Feature",
  "properties": {
    "addr:full":"9 Whincroft Close Ferndown Dorset BH22 9LW",
    "addr:housenumber":"9",
    "addr:postcode":"bh22 9lw",
    "addr:street":"Whincroft Close",
    "iso:country":"GB",
    "sg:address":"9 Whincroft Close",
    "sg:city":"Ferndown",
    "sg:classifiers":[
        {
            "category":"Professional",
            "subcategory":"Engineering",
            "type":"Services"
        }
    ],
    "sg:postcode":"BH22 9LW",
    "sg:province":"Dorset",
    "sg:tags":[
        "gas",
        "engineer"
    ],
    "wof:name":"Copperfield Heating & Plumbing",
    "wof:placetype":"venue"
},
  "geometry": {"coordinates":[-1.8841290474,50.8093795776],"type":"Point"}
}