{
  "type": "Feature",
  "properties": {
    "iso:country":"GB",
    "sg:address":"Pitcoudie Surgery",
    "sg:city":"Glenrothes",
    "sg:classifiers":[
        {
            "category":"Health Services",
            "subcategory":"Doctor",
            "type":"Services"
        }
    ],
    "sg:phone":"+44 1592 620062",
    "sg:postcode":"KY7 6SX",
    "sg:province":"Fife",
    "sg:tags":[
        "practitioners"
    ],
    "wof:name":"North Glen Medical Practice",
    "wof:placetype":"venue"
},
  "geometry": {"coordinates":[-3.1470079422,56.2060699463],"type":"Point"}
}