{
  "type": "Feature",
  "properties": {
    "addr:full":"626 Holloway Road London Greater London N19 3PA",
    "addr:housenumber":"626",
    "addr:postcode":"n19 3pa",
    "addr:street":"Holloway Road",
    "iso:country":"GB",
    "sg:address":"626 Holloway Road",
    "sg:city":"London",
    "sg:classifiers":[
        {
            "category":"Food & Beverages",
            "subcategory":"Liquor & Beverages",
            "type":"Retail Goods"
        }
    ],
    "sg:phone":"+44 20 7263 6969",
    "sg:postcode":"N19 3PA",
    "sg:province":"Greater London",
    "sg:tags":[
        "beer",
        "wine",
        "spirit",
        "wines"
    ],
    "wof:name":"Wine Gate",
    "wof:placetype":"venue"
},
  "geometry": {"coordinates":[-0.125086993,51.5619888306],"type":"Point"}
}