{
  "type": "Feature",
  "properties": {
    "addr:full":"Bonlea Trading Est Stockton On Tees Durham TS17 7AQ",
    "addr:postcode":"ts17 7aq",
    "iso:country":"GB",
    "sg:address":"Bonlea Trading Est",
    "sg:city":"Stockton On Tees",
    "sg:classifiers":[
        {
            "category":"Home & Garden",
            "subcategory":"Building Materials",
            "type":"Retail Goods"
        }
    ],
    "sg:phone":"+44 1642 675747",
    "sg:postcode":"TS17 7AQ",
    "sg:province":"Durham",
    "sg:tags":[
        "ready",
        "mixed",
        "concrete"
    ],
    "wof:name":"Tilcon Ltd",
    "wof:placetype":"venue"
},
  "geometry": {"coordinates":[-1.296614,54.557217],"type":"Point"}
}