{
  "type": "Feature",
  "properties": {
    "addr:full":"5 Padmoor La, Upton Gainsborough Lincolnshire DN21 5NH",
    "addr:housenumber":"5",
    "addr:postcode":"dn21 5nh",
    "addr:street":"Padmoor La Upton",
    "iso:country":"GB",
    "sg:address":"5 Padmoor La, Upton",
    "sg:city":"Gainsborough",
    "sg:classifiers":[
        {
            "category":"Communications",
            "subcategory":"Film & Video Production",
            "type":"Services"
        }
    ],
    "sg:postcode":"DN21 5NH",
    "sg:province":"Lincolnshire",
    "sg:tags":[
        "illustrator",
        "artist"
    ],
    "wof:name":"Broadcanvas Design",
    "wof:placetype":"venue"
},
  "geometry": {"coordinates":[-0.6975769997,53.3707237244],"type":"Point"}
}