{
  "type": "Feature",
  "properties": {
    "addr:full":"Pier Road, Scarinish Scarinish Argyll and Bute PA77 6TN",
    "addr:postcode":"pa77 6tn",
    "addr:street":"Pier Road;Scarinish",
    "iso:country":"GB",
    "sg:address":"Pier Road, Scarinish",
    "sg:city":"Scarinish",
    "sg:classifiers":[
        {
            "category":"Home & Garden",
            "subcategory":"Household Appliances",
            "type":"Retail Goods"
        },
        {
            "category":"Retail",
            "subcategory":"Event Space",
            "type":"Services"
        }
    ],
    "sg:phone":"+44 1879 220338",
    "sg:postcode":"PA77 6TN",
    "sg:province":"Argyll and Bute",
    "sg:tags":[
        "electrical",
        "product",
        "domestic",
        "sales"
    ],
    "wof:name":"Scottish Hydro Electric plc",
    "wof:placetype":"venue"
},
  "geometry": {"coordinates":[-6.801991,56.505669],"type":"Point"}
}