{
  "type": "Feature",
  "properties": {
    "iso:country":"GB",
    "sg:address":"15 Leathermarket St",
    "sg:city":"Southwark",
    "sg:classifiers":[
        {
            "category":"Bars & Pubs",
            "type":"Food & Drink"
        }
    ],
    "sg:phone":"+44 20 7407 0295",
    "sg:postcode":"SE1 3HN",
    "sg:province":"Greater London",
    "sg:tags":[
        "pubs",
        "inn"
    ],
    "wof:name":"Jugglers Arms The",
    "wof:placetype":"venue"
},
  "geometry": {"coordinates":[-0.0823390037,51.5003433228],"type":"Point"}
}