{
  "type": "Feature",
  "properties": {
    "iso:country":"GB",
    "sg:address":"322 Great Western Road",
    "sg:city":"Aberdeen",
    "sg:classifiers":[
        {
            "category":"Shopping",
            "subcategory":"Antiques",
            "type":"Retail Goods"
        }
    ],
    "sg:phone":"+44 1224 593547",
    "sg:postcode":"AB10 6PL",
    "sg:province":"Aberdeen City",
    "wof:name":"Atholl Antiques",
    "wof:placetype":"venue"
},
  "geometry": {"coordinates":[-2.12645,57.13509],"type":"Point"}
}