{
  "type": "Feature",
  "properties": {
    "addr:full":"Goathland Whitby North Yorkshire YO22 5AN",
    "addr:postcode":"yo22 5an",
    "addr:street":"Goathland",
    "iso:country":"GB",
    "sg:address":"Goathland",
    "sg:city":"Whitby",
    "sg:classifiers":[
        {
            "category":"Travel",
            "subcategory":"Hotels & Motels",
            "type":"Entertainment"
        }
    ],
    "sg:phone":"+44 1947 896486",
    "sg:postcode":"YO22 5AN",
    "sg:province":"North Yorkshire",
    "wof:name":"Mallyan Spout Hotel",
    "wof:placetype":"venue"
},
  "geometry": {"coordinates":[-0.7235900164,54.397228241],"type":"Point"}
}