{
  "type": "Feature",
  "properties": {
    "addr:full":"Northfields Avenue London Greater London W5 1AB",
    "addr:postcode":"w5 1ab",
    "addr:street":"Northfields Avenue",
    "iso:country":"GB",
    "sg:address":"Northfields Avenue",
    "sg:city":"London",
    "sg:classifiers":[
        {
            "category":"Taxi",
            "type":"Transportation"
        }
    ],
    "sg:phone":"+44 20 8566 4000",
    "sg:postcode":"W5 1AB",
    "sg:province":"Greater London",
    "sg:tags":[
        "mini",
        "cab"
    ],
    "wof:name":"Premium Radio Cars",
    "wof:placetype":"venue"
},
  "geometry": {"coordinates":[-0.314234,51.498695],"type":"Point"}
}