{
  "type": "Feature",
  "properties": {
    "addr:full":"82 Aurs Rd Glasgow East Ayrshire G78 2NU",
    "addr:housenumber":"82",
    "addr:postcode":"g78 2nu",
    "addr:street":"Aurs Rd",
    "iso:country":"GB",
    "sg:address":"82 Aurs Rd",
    "sg:city":"Glasgow",
    "sg:classifiers":[
        {
            "category":"Health Services",
            "subcategory":"Health Practitioner",
            "type":"Services"
        }
    ],
    "sg:phone":"+44 141 876 0923",
    "sg:postcode":"G78 2NU",
    "sg:province":"East Ayrshire",
    "sg:tags":[
        "hypnotherapists"
    ],
    "wof:name":"John Donlin",
    "wof:placetype":"venue"
},
  "geometry": {"coordinates":[-4.378409,55.798931],"type":"Point"}
}