{
  "type": "Feature",
  "properties": {
    "addr:full":"Security House, Campbell Street, Farnworth Bolton Lancashire BL4 7NF",
    "addr:postcode":"bl4 7nf",
    "addr:street":"Campbell Street",
    "iso:country":"GB",
    "sg:address":"Security House, Campbell Street, Farnworth",
    "sg:city":"Bolton",
    "sg:classifiers":[
        {
            "category":"Professional",
            "subcategory":"Engineering",
            "type":"Services"
        }
    ],
    "sg:phone":"+44 1204 577721",
    "sg:postcode":"BL4 7NF",
    "sg:province":"Lancashire",
    "sg:tags":[
        "instrumentation",
        "engineer"
    ],
    "wof:name":"Arena Instrumentation",
    "wof:placetype":"venue"
},
  "geometry": {"coordinates":[-2.407834,53.554764],"type":"Point"}
}