{
  "type": "Feature",
  "properties": {
    "addr:full":"320 Uxbridge Road, Acton Hill London Greater London W3 9QP",
    "addr:housenumber":"320",
    "addr:postcode":"w3 9qp",
    "addr:street":"Uxbridge Road Acton Hill",
    "iso:country":"GB",
    "sg:address":"320 Uxbridge Road, Acton Hill",
    "sg:city":"London",
    "sg:classifiers":[
        {
            "category":"Real Estate",
            "subcategory":"Real Estate Agent",
            "type":"Services"
        }
    ],
    "sg:postcode":"W3 9QP",
    "sg:province":"Greater London",
    "wof:name":"Sunshaft Properties Ltd",
    "wof:placetype":"venue"
},
  "geometry": {"coordinates":[-0.277588,51.50845],"type":"Point"}
}