{
  "type": "Feature",
  "properties": {
    "addr:full":"36 Wigmore St London Greater London W1U 2BP",
    "addr:housenumber":"36",
    "addr:postcode":"w1u 2bp",
    "addr:street":"Wigmore St",
    "iso:country":"GB",
    "sg:address":"36 Wigmore St",
    "sg:city":"London",
    "sg:classifiers":[
        {
            "category":"Arts & Performance",
            "subcategory":"Theater",
            "type":"Entertainment"
        }
    ],
    "sg:phone":"+44 20 7935 2141",
    "sg:postcode":"W1U 2BP",
    "sg:province":"Greater London",
    "sg:tags":[
        "hall",
        "theatre",
        "concert"
    ],
    "wof:name":"Wigmore Hall",
    "wof:placetype":"venue"
},
  "geometry": {"coordinates":[-0.1475190073,51.5165901184],"type":"Point"}
}