{
  "type": "Feature",
  "properties": {
    "addr:full":"31 Market Street Haddington East Lothian EH41 3JE",
    "addr:housenumber":"31",
    "addr:postcode":"eh41 3je",
    "addr:street":"Market Street",
    "iso:country":"GB",
    "sg:address":"31 Market Street",
    "sg:city":"Haddington",
    "sg:classifiers":[
        {
            "category":"Retail",
            "subcategory":"Photofinishing",
            "type":"Services"
        },
        {
            "category":"Retail",
            "subcategory":"Laundry & Dry Cleaning",
            "type":"Services"
        }
    ],
    "sg:phone":"+44 1620 824893",
    "sg:postcode":"EH41 3JE",
    "sg:province":"East Lothian",
    "sg:tags":[
        "photographic",
        "alteration",
        "processor"
    ],
    "wof:name":"Klick Munro Cleaners",
    "wof:placetype":"venue"
},
  "geometry": {"coordinates":[-2.778990984,55.955947876],"type":"Point"}
}