{
  "type": "Feature",
  "properties": {
    "iso:country":"GB",
    "sg:address":"Mill Lodge",
    "sg:city":"Rye",
    "sg:classifiers":[
        {
            "category":"Manufacturing",
            "subcategory":"Wood Products",
            "type":"Manufacturing & Wholesale Goods"
        }
    ],
    "sg:phone":"+44 1424 882158",
    "sg:postcode":"TN31 6AY",
    "sg:province":"East Sussex",
    "sg:tags":[
        "maker",
        "cabinet"
    ],
    "wof:name":"Baldwins Rye",
    "wof:placetype":"venue"
},
  "geometry": {"coordinates":[0.7356520295,50.9517288208],"type":"Point"}
}