{
  "type": "Feature",
  "properties": {
    "iso:country":"GB",
    "sg:address":"Vale Forge, North Road",
    "sg:city":"Cowbridge",
    "sg:classifiers":[
        {
            "category":"Professional",
            "subcategory":"Accounting & Tax Preparation",
            "type":"Services"
        }
    ],
    "sg:postcode":"CF71 7DF",
    "sg:province":"The Vale of Glamorgan",
    "sg:tags":[
        "accountant"
    ],
    "wof:name":"Allan R Thomas & Co",
    "wof:placetype":"venue"
},
  "geometry": {"coordinates":[-3.450425,51.462391],"type":"Point"}
}