{
  "type": "Feature",
  "properties": {
    "addr:full":"13 Grange Crescent, Stockton Road Sunderland Tyne and Wear SR2 7BN",
    "addr:housenumber":"13",
    "addr:postcode":"sr2 7bn",
    "addr:street":"Grange Crescent Stockton Road",
    "iso:country":"GB",
    "sg:address":"13 Grange Crescent, Stockton Road",
    "sg:city":"Sunderland",
    "sg:classifiers":[
        {
            "category":"Organizations",
            "subcategory":"Non-profit Organization",
            "type":"Services"
        }
    ],
    "sg:phone":"+44 191 567 7177",
    "sg:postcode":"SR2 7BN",
    "sg:province":"Tyne and Wear",
    "sg:tags":[
        "organisation",
        "voluntary",
        "charity"
    ],
    "wof:name":"The Samaritans",
    "wof:placetype":"venue"
},
  "geometry": {"coordinates":[-1.3847409487,54.9004669189],"type":"Point"}
}