{
  "type": "Feature",
  "properties": {
    "addr:full":"Harold Ho, 73 High St Waltham Cross Essex EN8 7AF",
    "addr:housenumber":"73",
    "addr:postcode":"en8 7af",
    "addr:street":"High St",
    "iso:country":"GB",
    "sg:address":"Harold Ho, 73 High St",
    "sg:city":"Waltham Cross",
    "sg:classifiers":[
        {
            "category":"Professional",
            "subcategory":"Management & Consulting",
            "type":"Services"
        },
        {
            "category":"Professional",
            "subcategory":"Advertising",
            "type":"Services"
        }
    ],
    "sg:postcode":"EN8 7AF",
    "sg:province":"Essex",
    "sg:tags":[
        "consultant",
        "promotion",
        "agency",
        "direct",
        "sale"
    ],
    "wof:name":"Supreme Selections (London) Ltd",
    "wof:placetype":"venue"
},
  "geometry": {"coordinates":[-0.0338140018,51.6905097961],"type":"Point"}
}