{
  "type": "Feature",
  "properties": {
    "addr:full":"884 Warwick Road Birmingham West Midlands B11 2ES",
    "addr:housenumber":"884",
    "addr:postcode":"b11 2es",
    "addr:street":"Warwick Road",
    "iso:country":"GB",
    "sg:address":"884 Warwick Road",
    "sg:city":"Birmingham",
    "sg:classifiers":[
        {
            "category":"Autos & Motor Vehicles",
            "subcategory":"Automobile Sales",
            "type":"Retail Goods"
        }
    ],
    "sg:phone":"+44 121 765 4321",
    "sg:postcode":"B11 2ES",
    "sg:province":"West Midlands",
    "sg:tags":[
        "car"
    ],
    "wof:name":"Colliers",
    "wof:placetype":"venue"
},
  "geometry": {"coordinates":[-1.836375,52.452694],"type":"Point"}
}