{
  "type": "Feature",
  "properties": {
    "addr:full":"4 Atholl Crescent Perth Perth and Kinross PH1 5NG",
    "addr:housenumber":"4",
    "addr:postcode":"ph1 5ng",
    "addr:street":"Atholl Crescent",
    "iso:country":"GB",
    "sg:address":"4 Atholl Crescent",
    "sg:city":"Perth",
    "sg:classifiers":[
        {
            "category":"Building & Trades",
            "subcategory":"Construction",
            "type":"Services"
        }
    ],
    "sg:phone":"+44 1828 628757",
    "sg:postcode":"PH1 5NG",
    "sg:province":"Perth and Kinross",
    "sg:tags":[
        "builder"
    ],
    "wof:name":"Lornton Homes Ltd.",
    "wof:placetype":"venue"
},
  "geometry": {"coordinates":[-3.432929,56.399597],"type":"Point"}
}