{
  "type": "Feature",
  "properties": {
    "iso:country":"GB",
    "sg:address":"25 Cricklade St",
    "sg:city":"Cirencester",
    "sg:classifiers":[
        {
            "category":"Travel",
            "subcategory":"Travel Agent",
            "type":"Entertainment"
        }
    ],
    "sg:phone":"+44 1285 661100",
    "sg:postcode":"GL7 1HY",
    "sg:province":"Gloucestershire",
    "wof:name":"Thomas Cook Travel",
    "wof:placetype":"venue"
},
  "geometry": {"coordinates":[-1.967808,51.716415],"type":"Point"}
}