{
  "type": "Feature",
  "properties": {
    "addr:full":"Hamilton Careers Office, 23 Windmill Rd Hamilton South Lanarkshire ML3 6LX",
    "addr:housenumber":"23",
    "addr:postcode":"ml3 6lx",
    "addr:street":"Windmill Rd",
    "iso:country":"GB",
    "sg:address":"Hamilton Careers Office, 23 Windmill Rd",
    "sg:city":"Hamilton",
    "sg:classifiers":[
        {
            "category":"Government",
            "subcategory":"Office",
            "type":"Public Place"
        }
    ],
    "sg:phone":"+44 1698 337484",
    "sg:postcode":"ML3 6LX",
    "sg:province":"South Lanarkshire",
    "sg:tags":[
        "local"
    ],
    "wof:name":"South Lanarkshire Council",
    "wof:placetype":"venue"
},
  "geometry": {"coordinates":[-4.0528907776,55.7773208618],"type":"Point"}
}