{
  "type": "Feature",
  "properties": {
    "addr:full":"4-5 Station Parade Eastbourne East Sussex BN21 1BE",
    "addr:housenumber":"4-5",
    "addr:postcode":"bn21 1be",
    "addr:street":"Station Parade",
    "iso:country":"GB",
    "sg:address":"4-5 Station Parade",
    "sg:city":"Eastbourne",
    "sg:classifiers":[
        {
            "category":"Real Estate",
            "subcategory":"Surveying",
            "type":"Services"
        }
    ],
    "sg:phone":"+44 1323 738856",
    "sg:postcode":"BN21 1BE",
    "sg:province":"East Sussex",
    "sg:tags":[
        "surveyor",
        "quantity"
    ],
    "wof:name":"Michael Chesson Associates",
    "wof:placetype":"venue"
},
  "geometry": {"coordinates":[0.27928,50.769569],"type":"Point"}
}