{
  "type": "Feature",
  "properties": {
    "iso:country":"GB",
    "sg:address":"Unit 112, Bradley Fold Trading Estate",
    "sg:city":"Bolton",
    "sg:classifiers":[
        {
            "category":"Professional",
            "subcategory":"Computer Services",
            "type":"Services"
        }
    ],
    "sg:phone":"+44 1204 399329",
    "sg:postcode":"BL2 6RT",
    "sg:province":"Lancashire",
    "sg:tags":[
        "system",
        "software"
    ],
    "wof:name":"Software Solutions",
    "wof:placetype":"venue"
},
  "geometry": {"coordinates":[-2.36941,53.572121],"type":"Point"}
}