{
  "type": "Feature",
  "properties": {
    "addr:full":"61 New Kings Road London Greater London SW6 4SE",
    "addr:housenumber":"61",
    "addr:postcode":"sw6 4se",
    "addr:street":"New Kings Road",
    "iso:country":"GB",
    "sg:address":"61 New Kings Road",
    "sg:city":"London",
    "sg:classifiers":[
        {
            "category":"Real Estate",
            "subcategory":"Surveying",
            "type":"Services"
        }
    ],
    "sg:phone":"+44 20 7371 0575",
    "sg:postcode":"SW6 4SE",
    "sg:province":"Greater London",
    "sg:tags":[
        "building",
        "surveyor"
    ],
    "wof:name":"Clive Marjoram",
    "wof:placetype":"venue"
},
  "geometry": {"coordinates":[-0.192729,51.476246],"type":"Point"}
}