{
  "type": "Feature",
  "properties": {
    "addr:full":"Northern House, Station App Hitchin Hertfordshire SG4 9UW",
    "addr:postcode":"sg4 9uw",
    "iso:country":"GB",
    "sg:address":"Northern House, Station App",
    "sg:city":"Hitchin",
    "sg:classifiers":[
        {
            "category":"Professional",
            "subcategory":"Engineering",
            "type":"Services"
        }
    ],
    "sg:phone":"+44 1462 452414",
    "sg:postcode":"SG4 9UW",
    "sg:province":"Hertfordshire",
    "sg:tags":[
        "precision",
        "engineer"
    ],
    "wof:name":"C & C Industries",
    "wof:placetype":"venue"
},
  "geometry": {"coordinates":[-0.2648839951,51.9532814026],"type":"Point"}
}