{
  "type": "Feature",
  "properties": {
    "iso:country":"GB",
    "sg:address":"Orchard House, Hill Farm Lane, Duns Tew",
    "sg:city":"Bicester",
    "sg:classifiers":[
        {
            "category":"Building & Trades",
            "subcategory":"Construction",
            "type":"Services"
        }
    ],
    "sg:phone":"+44 1869 340333",
    "sg:postcode":"OX25 6JH",
    "sg:province":"Oxfordshire",
    "sg:tags":[
        "heating",
        "contractor"
    ],
    "wof:name":"Cherwell Heating Ltd",
    "wof:placetype":"venue"
},
  "geometry": {"coordinates":[-1.333567,51.954403],"type":"Point"}
}