{
  "type": "Feature",
  "properties": {
    "iso:country":"GB",
    "sg:address":"Melvin Hall",
    "sg:city":"Dalkeith",
    "sg:classifiers":[
        {
            "category":"Farming",
            "subcategory":"Livestock Farm",
            "type":"Manufacturing & Wholesale Goods"
        },
        {
            "category":"Farming",
            "subcategory":"Farm",
            "type":"Manufacturing & Wholesale Goods"
        }
    ],
    "sg:phone":"+44 1875 320284",
    "sg:postcode":"EH22 2PD",
    "sg:province":"City of Edinburgh",
    "sg:tags":[
        "mixed",
        "others"
    ],
    "wof:name":"ANDREW BRUCE HASTIE",
    "wof:placetype":"venue"
},
  "geometry": {"coordinates":[-3.068613,55.892879],"type":"Point"}
}