{
  "type": "Feature",
  "properties": {
    "addr:full":"1st Floor, 176 Seven Sisters Rd London Greater London N7 7PX",
    "addr:housenumber":"176",
    "addr:postcode":"n7 7px",
    "addr:street":"Seven Sisters Rd",
    "iso:country":"GB",
    "sg:address":"1st Floor, 176 Seven Sisters Rd",
    "sg:city":"London",
    "sg:classifiers":[
        {
            "category":"Shopping",
            "subcategory":"Clothing, Apparel, & Fashions",
            "type":"Retail Goods"
        }
    ],
    "sg:postcode":"N7 7PX",
    "sg:province":"Greater London",
    "sg:tags":[
        "clothing"
    ],
    "wof:name":"Xeni Ltd",
    "wof:placetype":"venue"
},
  "geometry": {"coordinates":[-0.1109019965,51.561882019],"type":"Point"}
}