{
  "type": "Feature",
  "properties": {
    "addr:full":"44 Lanshaw Crescent Leeds West Yorkshire LS10 3NN",
    "addr:housenumber":"44",
    "addr:postcode":"ls10 3nn",
    "addr:street":"Lanshaw Crescent",
    "iso:country":"GB",
    "sg:address":"44 Lanshaw Crescent",
    "sg:city":"Leeds",
    "sg:classifiers":[
        {
            "category":"Social Services",
            "subcategory":"Child Care",
            "type":"Services"
        }
    ],
    "sg:phone":"+44 113 271 6669",
    "sg:postcode":"LS10 3NN",
    "sg:province":"West Yorkshire",
    "sg:tags":[
        "children's",
        "home"
    ],
    "wof:name":"Catholic Care",
    "wof:placetype":"venue"
},
  "geometry": {"coordinates":[-1.5304969549,53.7511978149],"type":"Point"}
}