{
  "type": "Feature",
  "properties": {
    "iso:country":"GB",
    "sg:address":"Church St, Garstang",
    "sg:city":"Preston",
    "sg:classifiers":[
        {
            "category":"Government",
            "subcategory":"City Hall",
            "type":"Public Place"
        }
    ],
    "sg:phone":"+44 1995 603850",
    "sg:postcode":"PR3 1PA",
    "sg:province":"Lancashire",
    "wof:name":"Garstang Masonic Hall",
    "wof:placetype":"venue"
},
  "geometry": {"coordinates":[-2.777166,53.898964],"type":"Point"}
}