{
  "type": "Feature",
  "properties": {
    "addr:full":"32 High Street Wickford Essex SS12 9AZ",
    "addr:housenumber":"32",
    "addr:postcode":"ss12 9az",
    "addr:street":"High Street",
    "iso:country":"GB",
    "sg:address":"32 High Street",
    "sg:city":"Wickford",
    "sg:classifiers":[
        {
            "category":"Shopping",
            "subcategory":"Thrift Store",
            "type":"Retail Goods"
        }
    ],
    "sg:phone":"+44 1268 573977",
    "sg:postcode":"SS12 9AZ",
    "sg:province":"Essex",
    "sg:tags":[
        "shop",
        "charity"
    ],
    "wof:name":"St.Lukes Hospice Shop",
    "wof:placetype":"venue"
},
  "geometry": {"coordinates":[0.5207650065,51.6125640869],"type":"Point"}
}