{
  "type": "Feature",
  "properties": {
    "iso:country":"GB",
    "sg:address":"Town Farm, Campton Road, Gravenhurst",
    "sg:city":"Bedford",
    "sg:classifiers":[
        {
            "category":"Manufacturing",
            "subcategory":"Rubber & Plastics",
            "type":"Manufacturing & Wholesale Goods"
        }
    ],
    "sg:phone":"+44 1462 711797",
    "sg:postcode":"MK45 4JB",
    "sg:province":"Bedfordshire",
    "sg:tags":[
        "injection",
        "moulding"
    ],
    "wof:name":"Kentone Plastics Ltd.",
    "wof:placetype":"venue"
},
  "geometry": {"coordinates":[-0.37765,52.012108],"type":"Point"}
}