{
  "type": "Feature",
  "properties": {
    "iso:country":"GB",
    "sg:address":"Malverleys, East End",
    "sg:city":"Newbury",
    "sg:classifiers":[
        {
            "category":"Professional",
            "subcategory":"Management & Consulting",
            "type":"Services"
        }
    ],
    "sg:postcode":"RG20 0AA",
    "sg:province":"Berkshire",
    "sg:tags":[
        "consultant",
        "business"
    ],
    "wof:name":"Morgan,Paul,Consultants",
    "wof:placetype":"venue"
},
  "geometry": {"coordinates":[-1.405299,51.349724],"type":"Point"}
}