{
  "type": "Feature",
  "properties": {
    "addr:full":"7 Milrig Road, Rutherglen Glasgow Glasgow City G73 2NQ",
    "addr:housenumber":"7",
    "addr:postcode":"g73 2nq",
    "addr:street":"Milrig Road",
    "iso:country":"GB",
    "sg:address":"7 Milrig Road, Rutherglen",
    "sg:city":"Glasgow",
    "sg:classifiers":[
        {
            "category":"Communications",
            "type":"Services"
        }
    ],
    "sg:phone":"+44 141 647 2838",
    "sg:postcode":"G73 2NQ",
    "sg:province":"Glasgow City",
    "sg:tags":[
        "system",
        "music",
        "public",
        "address"
    ],
    "wof:name":"Gerry Bayne",
    "wof:placetype":"venue"
},
  "geometry": {"coordinates":[-4.2179179192,55.822807312],"type":"Point"}
}