{
  "type": "Feature",
  "properties": {
    "addr:full":"102 St Johns Road, Corstorphine Edinburgh City of Edinburgh EH12 8AT",
    "addr:housenumber":"102",
    "addr:postcode":"eh12 8at",
    "addr:street":"St Johns Road",
    "iso:country":"GB",
    "sg:address":"102 St Johns Road, Corstorphine",
    "sg:city":"Edinburgh",
    "sg:classifiers":[
        {
            "category":"Personal",
            "subcategory":"Beauty Salon",
            "type":"Services"
        }
    ],
    "sg:phone":"+44 131 334 7726",
    "sg:postcode":"EH12 8AT",
    "sg:province":"City of Edinburgh",
    "sg:tags":[
        "ladies",
        "lady",
        "hairdresser"
    ],
    "wof:name":"Salon Hair Fashions",
    "wof:placetype":"venue"
},
  "geometry": {"coordinates":[-3.2830491066,55.9429206848],"type":"Point"}
}