{
  "type": "Feature",
  "properties": {
    "iso:country":"GB",
    "sg:address":"7 Queenswood Road, Becketts Park",
    "sg:city":"Leeds",
    "sg:classifiers":[
        {
            "category":"Building & Trades",
            "subcategory":"Construction",
            "type":"Services"
        }
    ],
    "sg:postcode":"LS6 3NH",
    "sg:province":"West Yorkshire",
    "sg:tags":[
        "roofing"
    ],
    "wof:name":"Peter Pounder",
    "wof:placetype":"venue"
},
  "geometry": {"coordinates":[-1.5937,53.820358],"type":"Point"}
}