{
  "type": "Feature",
  "properties": {
    "addr:full":"Little Petherick Wadebridge Cornwall PL27 7SH",
    "addr:postcode":"pl27 7sh",
    "iso:country":"GB",
    "sg:address":"Little Petherick",
    "sg:city":"Wadebridge",
    "sg:classifiers":[
        {
            "category":"Farming",
            "subcategory":"Dairy Farm",
            "type":"Manufacturing & Wholesale Goods"
        }
    ],
    "sg:phone":"+44 1841 540392",
    "sg:postcode":"PL27 7SH",
    "sg:province":"Cornwall",
    "wof:name":"Matthews Farms Ltd.",
    "wof:placetype":"venue"
},
  "geometry": {"coordinates":[-4.8380241394,50.5181884766],"type":"Point"}
}