{
  "type": "Feature",
  "properties": {
    "addr:full":"35 Somerset Road, Histon Cambridge Cambridgeshire CB4 9JS",
    "addr:housenumber":"35",
    "addr:postcode":"cb4 9js",
    "addr:street":"Somerset Road",
    "iso:country":"GB",
    "sg:address":"35 Somerset Road, Histon",
    "sg:city":"Cambridge",
    "sg:classifiers":[
        {
            "category":"Building & Trades",
            "subcategory":"Construction",
            "type":"Services"
        }
    ],
    "sg:phone":"+44 1223 572242",
    "sg:postcode":"CB4 9JS",
    "sg:province":"Cambridgeshire",
    "sg:tags":[
        "builder"
    ],
    "wof:name":"Walker D A & Associates Property Maintenance",
    "wof:placetype":"venue"
},
  "geometry": {"coordinates":[0.100724,52.250343],"type":"Point"}
}