{
  "type": "Feature",
  "properties": {
    "addr:full":"Restormel Estate Lostwithiel Cornwall PL22 0HG",
    "addr:housenumber":"lostwithiel",
    "addr:postcode":"pl22 0hg",
    "iso:country":"GB",
    "sg:address":"Restormel Estate",
    "sg:city":"Lostwithiel",
    "sg:classifiers":[
        {
            "category":"Farming",
            "subcategory":"Nursery",
            "type":"Manufacturing & Wholesale Goods"
        }
    ],
    "sg:phone":"+44 1208 873870",
    "sg:postcode":"PL22 0HG",
    "sg:province":"Cornwall",
    "sg:tags":[
        "creche"
    ],
    "wof:name":"H & S Maymen",
    "wof:placetype":"venue"
},
  "geometry": {"coordinates":[-4.669903,50.408272],"type":"Point"}
}