{
  "type": "Feature",
  "properties": {
    "addr:full":"34 St Helens Road Swansea Neath Port Talbot SA1 4AY",
    "addr:housenumber":"34",
    "addr:postcode":"sa1 4ay",
    "addr:street":"St Helens Road",
    "iso:country":"GB",
    "sg:address":"34 St Helens Road",
    "sg:city":"Swansea",
    "sg:classifiers":[
        {
            "category":"Professional",
            "subcategory":"Printing & Photocopies",
            "type":"Services"
        }
    ],
    "sg:phone":"+44 1792 466333",
    "sg:postcode":"SA1 4AY",
    "sg:province":"Neath Port Talbot",
    "sg:tags":[
        "printer"
    ],
    "wof:name":"Prontaprint",
    "wof:placetype":"venue"
},
  "geometry": {"coordinates":[-3.953299,51.617798],"type":"Point"}
}