{
  "type": "Feature",
  "properties": {
    "addr:full":"Lord Roberts Workshop, 6 Western Corner Edinburgh City of Edinburgh EH12 5NE",
    "addr:housenumber":"6",
    "addr:postcode":"eh12 5ne",
    "addr:street":"Western Corner",
    "iso:country":"GB",
    "sg:address":"Lord Roberts Workshop, 6 Western Corner",
    "sg:city":"Edinburgh",
    "sg:classifiers":[
        {
            "category":"Shopping",
            "subcategory":"Crafts & Fabrics",
            "type":"Retail Goods"
        }
    ],
    "sg:phone":"+44 131 337 6951",
    "sg:postcode":"EH12 5NE",
    "sg:province":"City of Edinburgh",
    "sg:tags":[
        "brush"
    ],
    "wof:name":"Forces Help Society & Lord Roberts Works",
    "wof:placetype":"venue"
},
  "geometry": {"coordinates":[-3.232229948,55.9437103271],"type":"Point"}
}