{
  "type": "Feature",
  "properties": {
    "iso:country":"GB",
    "sg:address":"6a Milburn Road",
    "sg:city":"Ashington",
    "sg:classifiers":[
        {
            "category":"Food & Beverages",
            "subcategory":"Groceries & Convenience Stores",
            "type":"Retail Goods"
        }
    ],
    "sg:phone":"+44 1670 814530",
    "sg:postcode":"NE63 0HD",
    "sg:province":"Northumberland",
    "wof:name":"G S Discount Centre",
    "wof:placetype":"venue"
},
  "geometry": {"coordinates":[-1.565108,55.17923],"type":"Point"}
}