{
  "type": "Feature",
  "properties": {
    "iso:country":"GB",
    "sg:address":"6 The Square, Ironbridge",
    "sg:city":"Telford",
    "sg:classifiers":[
        {
            "category":"Government",
            "subcategory":"Post Office",
            "type":"Public Place"
        }
    ],
    "sg:phone":"+44 1952 432672",
    "sg:postcode":"TF8 7AQ",
    "sg:province":"Shropshire",
    "wof:name":"Ironbridge Sub Post Office",
    "wof:placetype":"venue"
},
  "geometry": {"coordinates":[-2.484703,52.627911],"type":"Point"}
}