{
  "type": "Feature",
  "properties": {
    "addr:full":"Wildmoor Lane Chester Cheshire CH3 7LJ",
    "addr:postcode":"ch3 7lj",
    "addr:street":"Wildmoor Lane",
    "iso:country":"GB",
    "sg:address":"Wildmoor Lane",
    "sg:city":"Chester",
    "sg:classifiers":[
        {
            "category":"Home & Garden",
            "subcategory":"Garden Supply",
            "type":"Retail Goods"
        }
    ],
    "sg:phone":"+44 1244 301510",
    "sg:postcode":"CH3 7LJ",
    "sg:province":"Cheshire",
    "sg:tags":[
        "nursery",
        "centre"
    ],
    "wof:name":"Barrow Nurseries",
    "wof:placetype":"venue"
},
  "geometry": {"coordinates":[-2.7687199116,53.2096481323],"type":"Point"}
}