{
  "type": "Feature",
  "properties": {
    "addr:full":"41 Glasgow Road Stirling Falkirk FK7 0PA",
    "addr:housenumber":"41",
    "addr:postcode":"fk7 0pa",
    "addr:street":"Glasgow Road",
    "iso:country":"GB",
    "sg:address":"41 Glasgow Road",
    "sg:city":"Stirling",
    "sg:classifiers":[
        {
            "category":"Fast Food",
            "type":"Food & Drink"
        }
    ],
    "sg:postcode":"FK7 0PA",
    "sg:province":"Falkirk",
    "sg:tags":[
        "away",
        "take"
    ],
    "wof:name":"Flying Dragon Restaurant",
    "wof:placetype":"venue"
},
  "geometry": {"coordinates":[-3.937285,56.099121],"type":"Point"}
}