{
  "type": "Feature",
  "properties": {
    "addr:full":"159 King Street Ramsgate Kent CT11 8PN",
    "addr:housenumber":"159",
    "addr:postcode":"ct11 8pn",
    "addr:street":"King Street Ramsgate",
    "iso:country":"GB",
    "sg:address":"159 King Street",
    "sg:city":"Ramsgate",
    "sg:classifiers":[
        {
            "category":"Cafe",
            "type":"Food & Drink"
        }
    ],
    "sg:phone":"+44 1843 853301",
    "sg:postcode":"CT11 8PN",
    "sg:province":"Kent",
    "sg:tags":[
        "tea",
        "room"
    ],
    "wof:name":"King Street Cafe",
    "wof:placetype":"venue"
},
  "geometry": {"coordinates":[1.4230799675,51.3374595642],"type":"Point"}
}