{
  "type": "Feature",
  "properties": {
    "addr:full":"3 Broad St Penryn Cornwall TR10 8JL",
    "addr:housenumber":"3",
    "addr:postcode":"tr10 8jl",
    "addr:street":"Broad St",
    "iso:country":"GB",
    "sg:address":"3 Broad St",
    "sg:city":"Penryn",
    "sg:classifiers":[
        {
            "category":"Bars & Pubs",
            "type":"Food & Drink"
        }
    ],
    "sg:phone":"+44 1326 372336",
    "sg:postcode":"TR10 8JL",
    "sg:province":"Cornwall",
    "sg:tags":[
        "pubs",
        "inn"
    ],
    "wof:name":"Lake Inns & Leisure Ltd",
    "wof:placetype":"venue"
},
  "geometry": {"coordinates":[-5.1014699936,50.1678466797],"type":"Point"}
}