{
  "type": "Feature",
  "properties": {
    "iso:country":"GB",
    "sg:address":"Mason Buildings, 28 Exchange St East",
    "sg:city":"Liverpool",
    "sg:classifiers":[
        {
            "category":"Professional",
            "subcategory":"Advertising",
            "type":"Services"
        }
    ],
    "sg:postcode":"L2 3PH",
    "sg:province":"Merseyside",
    "sg:tags":[
        "outdoor"
    ],
    "wof:name":"Maurice Stam Ltd.",
    "wof:placetype":"venue"
},
  "geometry": {"coordinates":[-2.99064,53.40749],"type":"Point"}
}