{
  "type": "Feature",
  "properties": {
    "iso:country":"GB",
    "sg:address":"Old Station Yard, South Quay",
    "sg:city":"Padstow",
    "sg:classifiers":[
        {
            "category":"Manufacturing",
            "subcategory":"Jewelry",
            "type":"Manufacturing & Wholesale Goods"
        }
    ],
    "sg:postcode":"PL28 8BW",
    "sg:province":"Cornwall",
    "sg:tags":[
        "repair",
        "jewellery"
    ],
    "wof:name":"Piran Pewter Co.",
    "wof:placetype":"venue"
},
  "geometry": {"coordinates":[-4.941839,50.537365],"type":"Point"}
}