{
  "type": "Feature",
  "properties": {
    "iso:country":"GB",
    "sg:address":"298 Romford Road",
    "sg:city":"London",
    "sg:classifiers":[
        {
            "category":"Health Services",
            "subcategory":"Dentist",
            "type":"Services"
        }
    ],
    "sg:phone":"+44 20 8534 4889",
    "sg:postcode":"E7 9HD",
    "sg:province":"Greater London",
    "wof:name":"Vincent K Chia",
    "wof:placetype":"venue"
},
  "geometry": {"coordinates":[0.0236900002,51.5463104248],"type":"Point"}
}