{
  "type": "Feature",
  "properties": {
    "iso:country":"GB",
    "sg:address":"Pickwick Ho, Chosen View Rd",
    "sg:city":"Cheltenham",
    "sg:classifiers":[
        {
            "category":"Professional",
            "subcategory":"Management & Consulting",
            "type":"Services"
        }
    ],
    "sg:phone":"+44 1242 256464",
    "sg:postcode":"GL51 9LT",
    "sg:province":"Gloucestershire",
    "sg:tags":[
        "consultant",
        "business"
    ],
    "wof:name":"E B A Cost Reduction Analysis Ltd",
    "wof:placetype":"venue"
},
  "geometry": {"coordinates":[-2.092718,51.916916],"type":"Point"}
}