{
  "type": "Feature",
  "properties": {
    "iso:country":"GB",
    "sg:address":"Unit A4 Little Wood Drive",
    "sg:city":"Cleckheaton",
    "sg:classifiers":[
        {
            "category":"Freight",
            "type":"Transportation"
        }
    ],
    "sg:phone":"+44 1274 861100",
    "sg:postcode":"BD19 4TQ",
    "sg:province":"West Yorkshire",
    "sg:tags":[
        "forwarders"
    ],
    "wof:name":"Bowler International",
    "wof:placetype":"venue"
},
  "geometry": {"coordinates":[-1.719225049,53.7376670837],"type":"Point"}
}