{
  "type": "Feature",
  "properties": {
    "iso:country":"GB",
    "sg:address":"3 Leicester Rd",
    "sg:city":"Manchester",
    "sg:classifiers":[
        {
            "category":"Wholesale",
            "subcategory":"Scrap",
            "type":"Manufacturing & Wholesale Goods"
        }
    ],
    "sg:phone":"+44 161 681 8188",
    "sg:postcode":"M35 0GW",
    "sg:province":"Lancashire",
    "sg:tags":[
        "waste",
        "metal"
    ],
    "wof:name":"S Brooks",
    "wof:placetype":"venue"
},
  "geometry": {"coordinates":[-2.1499829292,53.5030670166],"type":"Point"}
}