{
  "type": "Feature",
  "properties": {
    "iso:country":"GB",
    "sg:address":"62 Old Church Street",
    "sg:city":"London",
    "sg:classifiers":[
        {
            "category":"Arts & Performance",
            "subcategory":"Art Gallery",
            "type":"Entertainment"
        }
    ],
    "sg:phone":"+44 20 7352 8686",
    "sg:postcode":"SW3 6DP",
    "sg:province":"Greater London",
    "wof:name":"Carlyle Gallery",
    "wof:placetype":"venue"
},
  "geometry": {"coordinates":[-0.172948,51.486099],"type":"Point"}
}