{
  "type": "Feature",
  "properties": {
    "addr:full":"Dells Farm, Dells Common High Wycombe Buckinghamshire HP14 3UR",
    "addr:postcode":"high;hp14 3ur",
    "addr:street":"Dells Common",
    "iso:country":"GB",
    "sg:address":"Dells Farm, Dells Common",
    "sg:city":"High Wycombe",
    "sg:classifiers":[
        {
            "category":"Manufacturing",
            "subcategory":"Wood Products",
            "type":"Manufacturing & Wholesale Goods"
        }
    ],
    "sg:phone":"+44 1494 883160",
    "sg:postcode":"HP14 3UR",
    "sg:province":"Buckinghamshire",
    "sg:tags":[
        "craftsman"
    ],
    "wof:name":"Woodcraft Toys",
    "wof:placetype":"venue"
},
  "geometry": {"coordinates":[-0.8040140271,51.6446113586],"type":"Point"}
}