{
  "type": "Feature",
  "properties": {
    "iso:country":"GB",
    "sg:address":"1 Green Rd",
    "sg:city":"Kidlington",
    "sg:classifiers":[
        {
            "category":"Organizations",
            "subcategory":"Membership Organization",
            "type":"Services"
        }
    ],
    "sg:postcode":"OX5 2EU",
    "sg:province":"Buckinghamshire",
    "sg:tags":[
        "club"
    ],
    "wof:name":"Kidlington Green Social Club",
    "wof:placetype":"venue"
},
  "geometry": {"coordinates":[-1.2846250534,51.8204269409],"type":"Point"}
}