{
  "type": "Feature",
  "properties": {
    "iso:country":"GB",
    "sg:address":"274 Hob Moor Rd",
    "sg:city":"Birmingham",
    "sg:classifiers":[
        {
            "category":"Wholesale",
            "subcategory":"Office Equipment",
            "type":"Manufacturing & Wholesale Goods"
        }
    ],
    "sg:phone":"+44 121 783 9201",
    "sg:postcode":"B10 9HH",
    "sg:province":"West Midlands",
    "sg:tags":[
        "partition",
        "cubicle"
    ],
    "wof:name":"R N P S",
    "wof:placetype":"venue"
},
  "geometry": {"coordinates":[-1.830918,52.471561],"type":"Point"}
}