{
  "type": "Feature",
  "properties": {
    "addr:full":"14a Higher Rads End, Eversholt Milton Keynes Bedfordshire MK17 9ED",
    "addr:housenumber":"14a;rads",
    "addr:postcode":"mk17 9ed",
    "addr:street":"Higher;End",
    "iso:country":"GB",
    "sg:address":"14a Higher Rads End, Eversholt",
    "sg:city":"Milton Keynes",
    "sg:classifiers":[
        {
            "category":"Building & Trades",
            "subcategory":"Construction",
            "type":"Services"
        }
    ],
    "sg:phone":"+44 1525 280870",
    "sg:postcode":"MK17 9ED",
    "sg:province":"Bedfordshire",
    "sg:tags":[
        "metering"
    ],
    "wof:name":"Draeger Ltd",
    "wof:placetype":"venue"
},
  "geometry": {"coordinates":[-0.5578629971,51.9850540161],"type":"Point"}
}