{
  "type": "Feature",
  "properties": {
    "addr:full":"Bellevue Farm Helston Cornwall TR13 0DX",
    "addr:housenumber":"helston",
    "addr:postcode":"tr13 0dx",
    "iso:country":"GB",
    "sg:address":"Bellevue Farm",
    "sg:city":"Helston",
    "sg:classifiers":[
        {
            "category":"Home & Garden",
            "subcategory":"Building Materials",
            "type":"Retail Goods"
        }
    ],
    "sg:phone":"+44 1209 860448",
    "sg:postcode":"TR13 0DX",
    "sg:province":"Cornwall",
    "sg:tags":[
        "ironwork",
        "diy",
        "wrought"
    ],
    "wof:name":"Ian Nicholls",
    "wof:placetype":"venue"
},
  "geometry": {"coordinates":[-5.2669591904,50.1058197021],"type":"Point"}
}