{
  "type": "Feature",
  "properties": {
    "addr:full":"46 Colsterdale Close Billingham Durham TS23 3HD",
    "addr:housenumber":"46",
    "addr:postcode":"ts23 3hd",
    "addr:street":"Colsterdale Close",
    "iso:country":"GB",
    "sg:address":"46 Colsterdale Close",
    "sg:city":"Billingham",
    "sg:classifiers":[
        {
            "category":"Professional",
            "subcategory":"Detective & Security Services",
            "type":"Services"
        }
    ],
    "sg:postcode":"TS23 3HD",
    "sg:province":"Durham",
    "sg:tags":[
        "car"
    ],
    "wof:name":"Sertec Ltd",
    "wof:placetype":"venue"
},
  "geometry": {"coordinates":[-1.285426,54.618423],"type":"Point"}
}