{
  "type": "Feature",
  "properties": {
    "addr:full":"Womens Section, 42 Kings Rd Fleet Hampshire GU51 3AQ",
    "addr:housenumber":"42",
    "addr:postcode":"gu51 3aq",
    "addr:street":"Section;Kings Rd",
    "iso:country":"GB",
    "sg:address":"Womens Section, 42 Kings Rd",
    "sg:city":"Fleet",
    "sg:classifiers":[
        {
            "category":"Organizations",
            "subcategory":"Non-profit Organization",
            "type":"Services"
        }
    ],
    "sg:postcode":"GU51 3AQ",
    "sg:province":"Hampshire",
    "sg:tags":[
        "organisation",
        "voluntary",
        "charity"
    ],
    "wof:name":"Royal British Legion (The)",
    "wof:placetype":"venue"
},
  "geometry": {"coordinates":[-0.83121,51.28183],"type":"Point"}
}