{
  "type": "Feature",
  "properties": {
    "addr:full":"272 South Coast Rd Peacehaven East Sussex BN10 7PD",
    "addr:housenumber":"272",
    "addr:postcode":"bn10 7pd",
    "addr:street":"South Coast Rd",
    "iso:country":"GB",
    "sg:address":"272 South Coast Rd",
    "sg:city":"Peacehaven",
    "sg:classifiers":[
        {
            "category":"Building & Trades",
            "subcategory":"Plumbing",
            "type":"Services"
        }
    ],
    "sg:phone":"+44 1273 588123",
    "sg:postcode":"BN10 7PD",
    "sg:province":"East Sussex",
    "sg:tags":[
        "heating"
    ],
    "wof:name":"Crusader Boilers",
    "wof:placetype":"venue"
},
  "geometry": {"coordinates":[-0.0059159999,50.7924041748],"type":"Point"}
}