{
  "type": "Feature",
  "properties": {
    "addr:full":"27 Knifesmithgate Chesterfield Derbyshire S40 1RL",
    "addr:housenumber":"27",
    "addr:postcode":"s40 1rl",
    "addr:street":"Knifesmithgate",
    "iso:country":"GB",
    "sg:address":"27 Knifesmithgate",
    "sg:city":"Chesterfield",
    "sg:classifiers":[
        {
            "category":"Shopping",
            "subcategory":"Department Store",
            "type":"Retail Goods"
        }
    ],
    "sg:postcode":"S40 1RL",
    "sg:province":"Derbyshire",
    "wof:name":"Voila",
    "wof:placetype":"venue"
},
  "geometry": {"coordinates":[-1.4272840023,53.2363548279],"type":"Point"}
}