{
  "type": "Feature",
  "properties": {
    "iso:country":"GB",
    "sg:address":"Fair View, Belnie Lane",
    "sg:city":"Spalding",
    "sg:classifiers":[
        {
            "category":"Home & Garden",
            "subcategory":"Garden Supply",
            "type":"Retail Goods"
        }
    ],
    "sg:phone":"+44 1775 840221",
    "sg:postcode":"PE11 4HN",
    "sg:province":"Lincolnshire",
    "sg:tags":[
        "bulb",
        "grower"
    ],
    "wof:name":"D & J B Spinks",
    "wof:placetype":"venue"
},
  "geometry": {"coordinates":[-0.151488,52.788342],"type":"Point"}
}