{
  "type": "Feature",
  "properties": {
    "addr:full":"Higher Chilton Farm, Cadeleigh Tiverton Devon EX16 8RT",
    "addr:housenumber":"cadeleigh",
    "addr:postcode":"devon ex16 8rt",
    "iso:country":"GB",
    "sg:address":"Higher Chilton Farm, Cadeleigh",
    "sg:city":"Tiverton",
    "sg:classifiers":[
        {
            "category":"Farming",
            "subcategory":"Farm",
            "type":"Manufacturing & Wholesale Goods"
        }
    ],
    "sg:phone":"+44 1884 855510",
    "sg:postcode":"EX16 8RT",
    "sg:province":"Devon",
    "sg:tags":[
        "mixed",
        "crop"
    ],
    "wof:name":"Christopher John Westlake",
    "wof:placetype":"venue"
},
  "geometry": {"coordinates":[-3.5441439152,50.8611831665],"type":"Point"}
}