{
  "type": "Feature",
  "properties": {
    "iso:country":"GB",
    "sg:address":"Ensign House 6, Navigation Business Village",
    "sg:city":"Preston",
    "sg:classifiers":[
        {
            "category":"Real Estate",
            "subcategory":"Surveying",
            "type":"Services"
        }
    ],
    "sg:phone":"+44 1772 722288",
    "sg:postcode":"PR2 2YP",
    "sg:province":"Lancashire",
    "sg:tags":[
        "surveyor",
        "quantity"
    ],
    "wof:name":"Thornber & Walker Ltd",
    "wof:placetype":"venue"
},
  "geometry": {"coordinates":[-2.744316,53.761452],"type":"Point"}
}