{
  "type": "Feature",
  "properties": {
    "iso:country":"GB",
    "sg:address":"37 Thorpe Road, Chacombe",
    "sg:city":"Banbury",
    "sg:classifiers":[
        {
            "category":"Education",
            "subcategory":"School",
            "type":"Public Place"
        }
    ],
    "sg:phone":"+44 1295 710835",
    "sg:postcode":"OX17 2JA",
    "sg:province":"Northamptonshire",
    "sg:tags":[
        "local",
        "authority"
    ],
    "wof:name":"C Chacombe of E Primary School",
    "wof:placetype":"venue"
},
  "geometry": {"coordinates":[-1.2790490389,52.0906219482],"type":"Point"}
}