{
  "type": "Feature",
  "properties": {
    "iso:country":"GB",
    "sg:address":"377 Washway Rd",
    "sg:city":"Sale",
    "sg:classifiers":[
        {
            "category":"Shopping",
            "subcategory":"Pets & Pet Supplies",
            "type":"Retail Goods"
        }
    ],
    "sg:phone":"+44 161 283 8306",
    "sg:postcode":"M33 4FJ",
    "sg:province":"Cheshire",
    "sg:tags":[
        "food"
    ],
    "wof:name":"Oscar Pet Foods",
    "wof:placetype":"venue"
},
  "geometry": {"coordinates":[-2.344013,53.408939],"type":"Point"}
}