{
  "type": "Feature",
  "properties": {
    "addr:full":"15 Park Avenue Bedlington Northumberland NE22 7EJ",
    "addr:housenumber":"15",
    "addr:postcode":"ne22 7ej",
    "addr:street":"Park Avenue",
    "iso:country":"GB",
    "sg:address":"15 Park Avenue",
    "sg:city":"Bedlington",
    "sg:classifiers":[
        {
            "category":"Personal",
            "subcategory":"Beauty Salon",
            "type":"Services"
        },
        {
            "category":"Personal",
            "subcategory":"Barber",
            "type":"Services"
        }
    ],
    "sg:phone":"+44 1670 530117",
    "sg:postcode":"NE22 7EJ",
    "sg:province":"Northumberland",
    "sg:tags":[
        "unisex",
        "hairdresser"
    ],
    "wof:name":"Liz's Hairdressers",
    "wof:placetype":"venue"
},
  "geometry": {"coordinates":[-1.5612009764,55.1429977417],"type":"Point"}
}