{
  "type": "Feature",
  "properties": {
    "iso:country":"GB",
    "sg:address":"1008 Cathcart Rd",
    "sg:city":"Glasgow",
    "sg:classifiers":[
        {
            "category":"Professional",
            "subcategory":"Employment Agencies",
            "type":"Services"
        }
    ],
    "sg:phone":"+44 141 636 5999",
    "sg:postcode":"G42 9XL",
    "sg:province":"Glasgow City",
    "sg:tags":[
        "career",
        "guidance"
    ],
    "wof:name":"Cathcart Job Club",
    "wof:placetype":"venue"
},
  "geometry": {"coordinates":[-4.2596058846,55.8277664185],"type":"Point"}
}