{
  "type": "Feature",
  "properties": {
    "addr:full":"16 Harley Place Saltcoats North Ayrshire KA21 5TE",
    "addr:housenumber":"16",
    "addr:postcode":"ka21 5te",
    "addr:street":"Harley Place",
    "iso:country":"GB",
    "sg:address":"16 Harley Place",
    "sg:city":"Saltcoats",
    "sg:classifiers":[
        {
            "category":"Social Services",
            "subcategory":"Child Care",
            "type":"Services"
        },
        {
            "category":"Government",
            "subcategory":"Office",
            "type":"Public Place"
        }
    ],
    "sg:phone":"+44 1294 466497",
    "sg:postcode":"KA21 5TE",
    "sg:province":"North Ayrshire",
    "sg:tags":[
        "home",
        "local",
        "children's"
    ],
    "wof:name":"Harley Place Children's Home",
    "wof:placetype":"venue"
},
  "geometry": {"coordinates":[-4.7910838127,55.6398353577],"type":"Point"}
}