{
  "type": "Feature",
  "properties": {
    "iso:country":"GB",
    "sg:address":"Pope Iron Road",
    "sg:city":"Worcester",
    "sg:classifiers":[
        {
            "category":"Manufacturing",
            "subcategory":"Tools & Machinery",
            "type":"Manufacturing & Wholesale Goods"
        }
    ],
    "sg:postcode":"WR1 3HP",
    "sg:province":"Worcestershire",
    "sg:tags":[
        "design",
        "maker"
    ],
    "wof:name":"A R Tyler (Toolmakers)",
    "wof:placetype":"venue"
},
  "geometry": {"coordinates":[-2.2324841022,52.205406189],"type":"Point"}
}