{
  "type": "Feature",
  "properties": {
    "iso:country":"GB",
    "sg:address":"80 Brondesbury Road",
    "sg:city":"London",
    "sg:classifiers":[
        {
            "category":"Communications",
            "type":"Services"
        }
    ],
    "sg:phone":"+44 20 7328 4550",
    "sg:postcode":"NW6 6RX",
    "sg:province":"Greater London",
    "sg:tags":[
        "audio-visual"
    ],
    "wof:name":"Penumbra Productions Ltd.",
    "wof:placetype":"venue"
},
  "geometry": {"coordinates":[-0.200631,51.535858],"type":"Point"}
}