{
  "type": "Feature",
  "properties": {
    "iso:country":"GB",
    "sg:address":"98 Churchfields Road",
    "sg:city":"Beckenham",
    "sg:classifiers":[
        {
            "category":"Building & Trades",
            "subcategory":"Construction",
            "type":"Services"
        }
    ],
    "sg:phone":"+44 20 8658 8555",
    "sg:postcode":"BR3 4QZ",
    "sg:province":"Kent",
    "sg:tags":[
        "builder"
    ],
    "wof:name":"D & P Contracting Co. (London) Ltd.",
    "wof:placetype":"venue"
},
  "geometry": {"coordinates":[-0.046897,51.405605],"type":"Point"}
}