{
  "type": "Feature",
  "properties": {
    "addr:full":"3-5 Tithebarn Street Poulton-le-fylde Lancashire FY6 7BX",
    "addr:housenumber":"3-5",
    "addr:postcode":"fy6 7bx",
    "addr:street":"Tithebarn Street Poulton-Le-Fylde",
    "iso:country":"GB",
    "sg:address":"3-5 Tithebarn Street",
    "sg:city":"Poulton-le-fylde",
    "sg:classifiers":[
        {
            "category":"Fast Food",
            "type":"Food & Drink"
        },
        {
            "category":"Restaurant",
            "type":"Food & Drink"
        }
    ],
    "sg:phone":"+44 1253 891019",
    "sg:postcode":"FY6 7BX",
    "sg:province":"Lancashire",
    "sg:tags":[
        "away",
        "take"
    ],
    "wof:name":"Pikeys",
    "wof:placetype":"venue"
},
  "geometry": {"coordinates":[-2.993339,53.847622],"type":"Point"}
}