{
  "type": "Feature",
  "properties": {
    "iso:country":"GB",
    "sg:address":"Lockwood Road",
    "sg:city":"Huddersfield",
    "sg:classifiers":[
        {
            "category":"Autos & Motor Vehicles",
            "subcategory":"Auto Supplies",
            "type":"Retail Goods"
        }
    ],
    "sg:phone":"+44 1484 532448",
    "sg:postcode":"HD1 3PL",
    "sg:province":"West Yorkshire",
    "sg:tags":[
        "exhaust",
        "absorber",
        "shock"
    ],
    "wof:name":"Kwik-Fit",
    "wof:placetype":"venue"
},
  "geometry": {"coordinates":[-1.788109,53.638535],"type":"Point"}
}