{
  "type": "Feature",
  "properties": {
    "iso:country":"GB",
    "sg:address":"151 Wickham Road, Shirley",
    "sg:city":"Croydon",
    "sg:classifiers":[
        {
            "category":"Banks & Credit Unions",
            "subcategory":"Investment Brokerage",
            "type":"Services"
        }
    ],
    "sg:phone":"+44 20 8654 7755",
    "sg:postcode":"CR0 8TE",
    "sg:province":"Surrey",
    "wof:name":"Lyndendown Ltd.",
    "wof:placetype":"venue"
},
  "geometry": {"coordinates":[-0.0496079996,51.3746757507],"type":"Point"}
}