{
  "type": "Feature",
  "properties": {
    "addr:full":"92-95 St Nicholas Market, St Nicholas Street Bristol City of Bristol BS1 1LJ",
    "addr:housenumber":"92-95",
    "addr:postcode":"bs1 1lj",
    "addr:street":"St;Market St Nicholas Street",
    "iso:country":"GB",
    "sg:address":"92-95 St Nicholas Market, St Nicholas Street",
    "sg:city":"Bristol",
    "sg:classifiers":[
        {
            "category":"Cafe",
            "type":"Food & Drink"
        }
    ],
    "sg:phone":"+44 117 927 7444",
    "sg:postcode":"BS1 1LJ",
    "sg:province":"City of Bristol",
    "sg:tags":[
        "tea",
        "room"
    ],
    "wof:name":"Zaks Sandwich Bar",
    "wof:placetype":"venue"
},
  "geometry": {"coordinates":[-2.5934140682,51.4540100098],"type":"Point"}
}