{
  "type": "Feature",
  "properties": {
    "iso:country":"GB",
    "sg:address":"Manor Farm Industrial Estate, Manningford",
    "sg:city":"Pewsey",
    "sg:classifiers":[
        {
            "category":"Manufacturing",
            "subcategory":"Wood Products",
            "type":"Manufacturing & Wholesale Goods"
        }
    ],
    "sg:phone":"+44 1980 630980",
    "sg:postcode":"SN9 6JP",
    "sg:province":"Wiltshire",
    "sg:tags":[
        "woodturning"
    ],
    "wof:name":"Alan Davies Woodturners",
    "wof:placetype":"venue"
},
  "geometry": {"coordinates":[-1.762319,51.340286],"type":"Point"}
}