{
  "type": "Feature",
  "properties": {
    "iso:country":"GB",
    "sg:address":"Torcross, Tuesley Lane",
    "sg:city":"Godalming",
    "sg:classifiers":[
        {
            "category":"Professional",
            "subcategory":"Management & Consulting",
            "type":"Services"
        }
    ],
    "sg:phone":"+44 1483 417882",
    "sg:postcode":"GU7 1SE",
    "sg:province":"Surrey",
    "sg:tags":[
        "consultant",
        "business"
    ],
    "wof:name":"Anthony Slater Associates",
    "wof:placetype":"venue"
},
  "geometry": {"coordinates":[-0.618384,51.183956],"type":"Point"}
}