{
  "type": "Feature",
  "properties": {
    "addr:full":"Flat 2 Aston House Woking Surrey GU23 6EW",
    "addr:housenumber":"2",
    "addr:postcode":"gu23 6ew",
    "addr:street":"Aston House",
    "iso:country":"GB",
    "sg:address":"Flat 2 Aston House",
    "sg:city":"Woking",
    "sg:classifiers":[
        {
            "category":"Professional",
            "subcategory":"Accounting & Tax Preparation",
            "type":"Services"
        }
    ],
    "sg:postcode":"GU23 6EW",
    "sg:province":"Surrey",
    "sg:tags":[
        "accountant"
    ],
    "wof:name":"M  R  Buckell Design Ltd.",
    "wof:placetype":"venue"
},
  "geometry": {"coordinates":[-0.502030015,51.2927894592],"type":"Point"}
}