{
  "type": "Feature",
  "properties": {
    "addr:full":"77 High Street, Eton Windsor Berkshire SL4 6AF",
    "addr:housenumber":"77",
    "addr:postcode":"sl4 6af",
    "addr:street":"High Street",
    "iso:country":"GB",
    "sg:address":"77 High Street, Eton",
    "sg:city":"Windsor",
    "sg:classifiers":[
        {
            "category":"Bars & Pubs",
            "type":"Food & Drink"
        }
    ],
    "sg:phone":"+44 1753 861797",
    "sg:postcode":"SL4 6AF",
    "sg:province":"Berkshire",
    "sg:tags":[
        "pubs",
        "inn"
    ],
    "wof:name":"Whitbread Group Plc",
    "wof:placetype":"venue"
},
  "geometry": {"coordinates":[-0.6087470055,51.4862060547],"type":"Point"}
}