{
  "type": "Feature",
  "properties": {
    "addr:full":"82 South Road Southall Greater London UB1 1RD",
    "addr:housenumber":"82",
    "addr:postcode":"ub1 1rd",
    "addr:street":"South Road",
    "iso:country":"GB",
    "sg:address":"82 South Road",
    "sg:city":"Southall",
    "sg:classifiers":[
        {
            "category":"Travel",
            "subcategory":"Travel Agent",
            "type":"Entertainment"
        }
    ],
    "sg:phone":"+44 20 8843 1604",
    "sg:postcode":"UB1 1RD",
    "sg:province":"Greater London",
    "wof:name":"Pamzee Airlines Centre",
    "wof:placetype":"venue"
},
  "geometry": {"coordinates":[-0.3778649867,51.5082321167],"type":"Point"}
}