{
  "type": "Feature",
  "properties": {
    "addr:full":"21 Jamaica Street Dundee Dundee City DD3 7EL",
    "addr:housenumber":"21",
    "addr:postcode":"dd3 7el",
    "addr:street":"Jamaica Street",
    "iso:country":"GB",
    "sg:address":"21 Jamaica Street",
    "sg:city":"Dundee",
    "sg:classifiers":[
        {
            "category":"Organizations",
            "subcategory":"Membership Organization",
            "type":"Services"
        }
    ],
    "sg:postcode":"DD3 7EL",
    "sg:province":"Dundee City",
    "sg:tags":[
        "club"
    ],
    "wof:name":"Dundee Labour Club",
    "wof:placetype":"venue"
},
  "geometry": {"coordinates":[-2.970732,56.469479],"type":"Point"}
}