{
  "type": "Feature",
  "properties": {
    "iso:country":"GB",
    "sg:address":"Richmond Road",
    "sg:city":"Leicester",
    "sg:classifiers":[
        {
            "category":"Education",
            "subcategory":"Library",
            "type":"Public Place"
        }
    ],
    "sg:phone":"+44 116 283 2540",
    "sg:postcode":"LE2 8BB",
    "sg:province":"Leicestershire",
    "sg:tags":[
        "book"
    ],
    "wof:name":"Aylestone Library",
    "wof:placetype":"venue"
},
  "geometry": {"coordinates":[-1.140471,52.611801],"type":"Point"}
}