{
  "type": "Feature",
  "properties": {
    "addr:full":"Cathedral Road Derby Derbyshire DE1 3PA",
    "addr:postcode":"de1 3pa",
    "addr:street":"Cathedral Road",
    "iso:country":"GB",
    "sg:address":"Cathedral Road",
    "sg:city":"Derby",
    "sg:classifiers":[
        {
            "category":"Community Center",
            "type":"Public Place"
        },
        {
            "category":"Government",
            "subcategory":"Office",
            "type":"Public Place"
        }
    ],
    "sg:phone":"+44 1332 716620",
    "sg:postcode":"DE1 3PA",
    "sg:province":"Derbyshire",
    "sg:tags":[
        "recreation",
        "local",
        "leisure",
        "centre"
    ],
    "wof:name":"Queen's Leisure Centre",
    "wof:placetype":"venue"
},
  "geometry": {"coordinates":[-1.4803789854,52.9251403809],"type":"Point"}
}