{
  "type": "Feature",
  "properties": {
    "iso:country":"GB",
    "sg:address":"Unit 35f Dukesway, Teesside Indust Est",
    "sg:city":"Stockton On Tees",
    "sg:classifiers":[
        {
            "category":"Building & Trades",
            "subcategory":"Pest Control",
            "type":"Services"
        }
    ],
    "sg:phone":"+44 1642 765225",
    "sg:postcode":"TS17 9LT",
    "sg:province":"Durham",
    "sg:tags":[
        "vermin"
    ],
    "wof:name":"Rentokil",
    "wof:placetype":"venue"
},
  "geometry": {"coordinates":[-1.292764,54.51828],"type":"Point"}
}