{
  "type": "Feature",
  "properties": {
    "iso:country":"GB",
    "sg:address":"21 Morland Rd",
    "sg:city":"Stoke On Trent",
    "sg:classifiers":[
        {
            "category":"Shopping",
            "subcategory":"Clothing, Apparel, & Fashions",
            "type":"Retail Goods"
        }
    ],
    "sg:phone":"+44 1782 836331",
    "sg:postcode":"ST6 1DS",
    "sg:province":"Staffordshire",
    "sg:tags":[
        "dresswear"
    ],
    "wof:name":"4 U Dress Agency",
    "wof:placetype":"venue"
},
  "geometry": {"coordinates":[-2.195111,53.046223],"type":"Point"}
}