{
  "type": "Feature",
  "properties": {
    "addr:full":"74 Kyleakin Rd Glasgow East Renfrewshire G46 8DH",
    "addr:housenumber":"74",
    "addr:postcode":"g46 8dh",
    "addr:street":"Kyleakin Rd",
    "iso:country":"GB",
    "sg:address":"74 Kyleakin Rd",
    "sg:city":"Glasgow",
    "sg:classifiers":[
        {
            "category":"Health Services",
            "subcategory":"Doctor",
            "type":"Services"
        }
    ],
    "sg:phone":"+44 141 638 1464",
    "sg:postcode":"G46 8DH",
    "sg:province":"East Renfrewshire",
    "sg:tags":[
        "practitioners"
    ],
    "wof:name":"Bhatti, R",
    "wof:placetype":"venue"
},
  "geometry": {"coordinates":[-4.3307352066,55.8068618774],"type":"Point"}
}