{
  "type": "Feature",
  "properties": {
    "addr:full":"Britannia Wharf, Marine Pde Southampton Hampshire SO14 5JP",
    "addr:postcode":"so14 5jp",
    "iso:country":"GB",
    "sg:address":"Britannia Wharf, Marine Pde",
    "sg:city":"Southampton",
    "sg:classifiers":[
        {
            "category":"Manufacturing",
            "subcategory":"Building Materials",
            "type":"Manufacturing & Wholesale Goods"
        }
    ],
    "sg:phone":"+44 23 8021 1328",
    "sg:postcode":"SO14 5JP",
    "sg:province":"Hampshire",
    "sg:tags":[
        "concrete",
        "product"
    ],
    "wof:name":"A R C Conbloc",
    "wof:placetype":"venue"
},
  "geometry": {"coordinates":[-1.3897639513,50.9069366455],"type":"Point"}
}