{
  "type": "Feature",
  "properties": {
    "addr:full":"Laddin Farm, Little Marcle Ledbury Gloucestershire HR8 2LB",
    "addr:housenumber":"marcle",
    "addr:postcode":"hr8 2lb",
    "iso:country":"GB",
    "sg:address":"Laddin Farm, Little Marcle",
    "sg:city":"Ledbury",
    "sg:classifiers":[
        {
            "category":"Farming",
            "subcategory":"Farm",
            "type":"Manufacturing & Wholesale Goods"
        }
    ],
    "sg:postcode":"HR8 2LB",
    "sg:province":"Gloucestershire",
    "sg:tags":[
        "mixed",
        "crop"
    ],
    "wof:name":"R G & P R Blandford & Sons",
    "wof:placetype":"venue"
},
  "geometry": {"coordinates":[-2.482364,52.026787],"type":"Point"}
}