{
  "type": "Feature",
  "properties": {
    "iso:country":"GB",
    "sg:address":"15 West St",
    "sg:city":"Carshalton",
    "sg:classifiers":[
        {
            "category":"Health Services",
            "subcategory":"Health Practitioner",
            "type":"Services"
        }
    ],
    "sg:phone":"+44 20 8647 5105",
    "sg:postcode":"SM5 2PT",
    "sg:province":"Surrey",
    "sg:tags":[
        "osteopath"
    ],
    "wof:name":"Courtney Philip & Jennifer Foster & Anla Mula & Howard McIntosh & Trevor Strutt",
    "wof:placetype":"venue"
},
  "geometry": {"coordinates":[-0.1672659963,51.3662910461],"type":"Point"}
}