{
  "type": "Feature",
  "properties": {
    "addr:full":"13 Ranulf Close Harlow Essex CM17 0GX",
    "addr:housenumber":"13",
    "addr:postcode":"cm17 0gx",
    "addr:street":"Ranulf Close",
    "iso:country":"GB",
    "sg:address":"13 Ranulf Close",
    "sg:city":"Harlow",
    "sg:classifiers":[
        {
            "category":"Professional",
            "subcategory":"Management & Consulting",
            "type":"Services"
        }
    ],
    "sg:postcode":"CM17 0GX",
    "sg:province":"Essex",
    "sg:tags":[
        "marketing",
        "consultant"
    ],
    "wof:name":"Practical Marketing",
    "wof:placetype":"venue"
},
  "geometry": {"coordinates":[0.1345230043,51.7927780151],"type":"Point"}
}