{
  "type": "Feature",
  "properties": {
    "addr:full":"Station Road, Kirton Boston Lincolnshire PE20 1LQ",
    "addr:postcode":"pe20 1lq",
    "addr:street":"Station Road",
    "iso:country":"GB",
    "sg:address":"Station Road, Kirton",
    "sg:city":"Boston",
    "sg:classifiers":[
        {
            "category":"Autos & Motor Vehicles",
            "subcategory":"Automobile Sales",
            "type":"Retail Goods"
        }
    ],
    "sg:phone":"+44 1205 722400",
    "sg:postcode":"PE20 1LQ",
    "sg:province":"Lincolnshire",
    "sg:tags":[
        "car"
    ],
    "wof:name":"Lewis & Kime Ltd.",
    "wof:placetype":"venue"
},
  "geometry": {"coordinates":[-0.0571379997,52.9280471802],"type":"Point"}
}