{
  "type": "Feature",
  "properties": {
    "iso:country":"GB",
    "sg:address":"23 Marmion Road",
    "sg:city":"Southsea",
    "sg:classifiers":[
        {
            "category":"Coffee & Tea",
            "type":"Food & Drink"
        }
    ],
    "sg:phone":"+44 23 9282 5651",
    "sg:postcode":"PO5 2AT",
    "sg:province":"Hampshire",
    "wof:name":"E J Brewer & Son Ltd.",
    "wof:placetype":"venue"
},
  "geometry": {"coordinates":[-1.087095,50.786453],"type":"Point"}
}