{
  "type": "Feature",
  "properties": {
    "iso:country":"GB",
    "sg:address":"19 Manor Square",
    "sg:city":"Otley",
    "sg:classifiers":[
        {
            "category":"Shopping",
            "subcategory":"Books",
            "type":"Retail Goods"
        }
    ],
    "sg:phone":"+44 1943 466599",
    "sg:postcode":"LS21 3AP",
    "sg:province":"North Yorkshire",
    "sg:tags":[
        "second-hand"
    ],
    "wof:name":"Chevin Books",
    "wof:placetype":"venue"
},
  "geometry": {"coordinates":[-1.694904,53.906471],"type":"Point"}
}