{
  "type": "Feature",
  "properties": {
    "iso:country":"GB",
    "sg:address":"19-21 Upper Parliament Street",
    "sg:city":"Nottingham",
    "sg:classifiers":[
        {
            "category":"Home & Garden",
            "subcategory":"Furniture",
            "type":"Retail Goods"
        }
    ],
    "sg:phone":"+44 115 959 9100",
    "sg:postcode":"NG1 2AP",
    "sg:province":"Nottinghamshire",
    "wof:name":"The Iron Bed Co",
    "wof:placetype":"venue"
},
  "geometry": {"coordinates":[-1.1487090588,52.9550895691],"type":"Point"}
}