{
  "type": "Feature",
  "properties": {
    "iso:country":"GB",
    "sg:address":"The Manor",
    "sg:city":"Marlborough",
    "sg:classifiers":[
        {
            "category":"Farming",
            "subcategory":"Livestock Farm",
            "type":"Manufacturing & Wholesale Goods"
        }
    ],
    "sg:phone":"+44 1672 870266",
    "sg:postcode":"SN8 3SP",
    "sg:province":"Berkshire",
    "sg:tags":[
        "others"
    ],
    "wof:name":"P D L Lemon",
    "wof:placetype":"venue"
},
  "geometry": {"coordinates":[-1.635629,51.35598],"type":"Point"}
}