{
  "type": "Feature",
  "properties": {
    "addr:full":"Cumbria Peat Works, Kirkbride Wigton Cumbria CA7 5LF",
    "addr:postcode":"ca7 5lf",
    "addr:street":"Kirkbride",
    "iso:country":"GB",
    "sg:address":"Cumbria Peat Works, Kirkbride",
    "sg:city":"Wigton",
    "sg:classifiers":[
        {
            "category":"Building & Trades",
            "subcategory":"Landscaping Services",
            "type":"Services"
        }
    ],
    "sg:phone":"+44 16973 51881",
    "sg:postcode":"CA7 5LF",
    "sg:province":"Cumbria",
    "sg:tags":[
        "horticultural",
        "consultant"
    ],
    "wof:name":"Levington Horticulture Ltd.",
    "wof:placetype":"venue"
},
  "geometry": {"coordinates":[-3.204128027,54.9022445679],"type":"Point"}
}