{
  "type": "Feature",
  "properties": {
    "addr:full":"Boat Road Newport-on-tay Fife DD6 8EY",
    "addr:postcode":"dd6 8ey",
    "addr:street":"Boat Road",
    "iso:country":"GB",
    "sg:address":"Boat Road",
    "sg:city":"Newport-on-tay",
    "sg:classifiers":[
        {
            "category":"Bars & Pubs",
            "type":"Food & Drink"
        }
    ],
    "sg:phone":"+44 1382 541274",
    "sg:postcode":"DD6 8EY",
    "sg:province":"Fife",
    "sg:tags":[
        "pubs",
        "inn"
    ],
    "wof:name":"O Brig Tay",
    "wof:placetype":"venue"
},
  "geometry": {"coordinates":[-2.943086,56.438408],"type":"Point"}
}