{
  "type": "Feature",
  "properties": {
    "addr:full":"94 Berwick Street London Greater London W1F 0QF",
    "addr:housenumber":"94",
    "addr:postcode":"w1f 0qf",
    "addr:street":"Berwick Street",
    "iso:country":"GB",
    "sg:address":"94 Berwick Street",
    "sg:city":"London",
    "sg:classifiers":[
        {
            "category":"Shopping",
            "subcategory":"Music",
            "type":"Retail Goods"
        }
    ],
    "sg:phone":"+44 20 7287 8385",
    "sg:postcode":"W1F 0QF",
    "sg:province":"Greater London",
    "sg:tags":[
        "record",
        "tape",
        "cd"
    ],
    "wof:name":"Sister Ray",
    "wof:placetype":"venue"
},
  "geometry": {"coordinates":[-0.134545,51.512871],"type":"Point"}
}