{
  "type": "Feature",
  "properties": {
    "addr:full":"2 King St, Beeston Nottingham Nottinghamshire NG9 2DL",
    "addr:housenumber":"2",
    "addr:postcode":"ng9 2dl",
    "addr:street":"King St",
    "iso:country":"GB",
    "sg:address":"2 King St, Beeston",
    "sg:city":"Nottingham",
    "sg:classifiers":[
        {
            "category":"Building & Trades",
            "subcategory":"Construction",
            "type":"Services"
        }
    ],
    "sg:postcode":"NG9 2DL",
    "sg:province":"Nottinghamshire",
    "sg:tags":[
        "builder"
    ],
    "wof:name":"Goodband,John,",
    "wof:placetype":"venue"
},
  "geometry": {"coordinates":[-1.20928,52.926292],"type":"Point"}
}