{
  "type": "Feature",
  "properties": {
    "addr:full":"Dark Lane Harpenden Hertfordshire AL5 1QD",
    "addr:postcode":"al5 1qd",
    "addr:street":"Dark Lane",
    "iso:country":"GB",
    "sg:address":"Dark Lane",
    "sg:city":"Harpenden",
    "sg:classifiers":[
        {
            "category":"Education",
            "subcategory":"School",
            "type":"Public Place"
        }
    ],
    "sg:phone":"+44 1582 761849",
    "sg:postcode":"AL5 1QD",
    "sg:province":"Hertfordshire",
    "sg:tags":[
        "local",
        "authority"
    ],
    "wof:name":"The Grove Infants & Nursery School",
    "wof:placetype":"venue"
},
  "geometry": {"coordinates":[-0.338059,51.808239],"type":"Point"}
}