{
  "type": "Feature",
  "properties": {
    "addr:full":"19 School Lane, Hollins Green Warrington Cheshire WA3 6LJ",
    "addr:housenumber":"19",
    "addr:postcode":"wa3 6lj",
    "addr:street":"School Lane",
    "iso:country":"GB",
    "sg:address":"19 School Lane, Hollins Green",
    "sg:city":"Warrington",
    "sg:classifiers":[
        {
            "category":"Shopping",
            "type":"Retail Goods"
        }
    ],
    "sg:phone":"+44 161 776 0777",
    "sg:postcode":"WA3 6LJ",
    "sg:province":"Cheshire",
    "sg:tags":[
        "part",
        "accessory"
    ],
    "wof:name":"Awesome Gti Store",
    "wof:placetype":"venue"
},
  "geometry": {"coordinates":[-2.4588410854,53.4156341553],"type":"Point"}
}