{
  "type": "Feature",
  "properties": {
    "addr:full":"40 The Grove Bristol City of Bristol BS1 4RB",
    "addr:housenumber":"40",
    "addr:postcode":"bs1 4rb",
    "addr:street":"The Grove",
    "iso:country":"GB",
    "sg:address":"40 The Grove",
    "sg:city":"Bristol",
    "sg:classifiers":[
        {
            "category":"Shopping",
            "subcategory":"Bicycles & Sporting Goods",
            "type":"Retail Goods"
        },
        {
            "category":"Cafe",
            "type":"Food & Drink"
        }
    ],
    "sg:phone":"+44 117 929 2151",
    "sg:postcode":"BS1 4RB",
    "sg:province":"City of Bristol",
    "sg:tags":[
        "tea",
        "cycle",
        "room",
        "accessory"
    ],
    "wof:name":"Mud Dock Cycle Works & Cafe",
    "wof:placetype":"venue"
},
  "geometry": {"coordinates":[-2.5938150883,51.44947052],"type":"Point"}
}