{
  "type": "Feature",
  "properties": {
    "addr:full":"1530 London Rd Leigh On Sea Essex SS9 2QG",
    "addr:housenumber":"1530",
    "addr:postcode":"ss9 2qg",
    "addr:street":"London Rd",
    "iso:country":"GB",
    "sg:address":"1530 London Rd",
    "sg:city":"Leigh On Sea",
    "sg:classifiers":[
        {
            "category":"Manufacturing",
            "subcategory":"Petroleum Products",
            "type":"Manufacturing & Wholesale Goods"
        }
    ],
    "sg:phone":"+44 1702 470740",
    "sg:postcode":"SS9 2QG",
    "sg:province":"Essex",
    "sg:tags":[
        "double",
        "glazing"
    ],
    "wof:name":"Victoria Windows & Conservatories",
    "wof:placetype":"venue"
},
  "geometry": {"coordinates":[0.63052,51.548321],"type":"Point"}
}