{
  "type": "Feature",
  "properties": {
    "addr:full":"23 Hay Street Elgin Moray IV30 1NH",
    "addr:housenumber":"23",
    "addr:postcode":"iv30 1nh",
    "addr:street":"Hay Street",
    "iso:country":"GB",
    "sg:address":"23 Hay Street",
    "sg:city":"Elgin",
    "sg:classifiers":[
        {
            "category":"Insurance",
            "subcategory":"Insurance Agent",
            "type":"Services"
        }
    ],
    "sg:phone":"+44 1343 547761",
    "sg:postcode":"IV30 1NH",
    "sg:province":"Moray",
    "sg:tags":[
        "broker"
    ],
    "wof:name":"George S Hay & Co",
    "wof:placetype":"venue"
},
  "geometry": {"coordinates":[-3.316289,57.644142],"type":"Point"}
}