{
  "type": "Feature",
  "properties": {
    "iso:country":"GB",
    "sg:address":"2 Crescent Ct, Brook St",
    "sg:city":"Ilkley",
    "sg:classifiers":[
        {
            "category":"Shopping",
            "subcategory":"Hobbies, Toys, & Games",
            "type":"Retail Goods"
        }
    ],
    "sg:phone":"+44 1943 608600",
    "sg:postcode":"LS29 8DE",
    "sg:province":"North Yorkshire",
    "sg:tags":[
        "shop",
        "toy"
    ],
    "wof:name":"The Toy Box",
    "wof:placetype":"venue"
},
  "geometry": {"coordinates":[-1.8217589855,53.9261550903],"type":"Point"}
}