{
  "type": "Feature",
  "properties": {
    "addr:full":"72 Barton Rd Luton Bedfordshire LU3 2BB",
    "addr:housenumber":"72",
    "addr:postcode":"lu3 2bb",
    "addr:street":"Barton Rd",
    "iso:country":"GB",
    "sg:address":"72 Barton Rd",
    "sg:city":"Luton",
    "sg:classifiers":[
        {
            "category":"Freight",
            "type":"Transportation"
        },
        {
            "category":"Government",
            "subcategory":"Post Office",
            "type":"Public Place"
        }
    ],
    "sg:postcode":"LU3 2BB",
    "sg:province":"Bedfordshire",
    "sg:tags":[
        "haulage",
        "messenger",
        "courier",
        "road"
    ],
    "wof:name":"Newham,Colin,",
    "wof:placetype":"venue"
},
  "geometry": {"coordinates":[-0.4259040058,51.9152145386],"type":"Point"}
}