{
  "type": "Feature",
  "properties": {
    "addr:full":"193-207 High Rd Ilford Essex IG1 1LZ",
    "addr:housenumber":"193-207",
    "addr:postcode":"ig1 1lz",
    "addr:street":"High Rd",
    "iso:country":"GB",
    "sg:address":"193-207 High Rd",
    "sg:city":"Ilford",
    "sg:classifiers":[
        {
            "category":"Home & Garden",
            "subcategory":"Home Furnishings",
            "type":"Retail Goods"
        }
    ],
    "sg:phone":"+44 20 8478 4160",
    "sg:postcode":"IG1 1LZ",
    "sg:province":"Essex",
    "sg:tags":[
        "furnishers",
        "planner",
        "kitchen"
    ],
    "wof:name":"Simply Kitchens",
    "wof:placetype":"venue"
},
  "geometry": {"coordinates":[0.074862,51.559425],"type":"Point"}
}