{
  "type": "Feature",
  "properties": {
    "iso:country":"GB",
    "sg:address":"2 Elmhay Cotts, Middle Street, Eastington",
    "sg:city":"Stonehouse",
    "sg:classifiers":[
        {
            "category":"Military Area",
            "subcategory":"Army Base",
            "type":"Public Place"
        },
        {
            "category":"Professional",
            "subcategory":"Business Services",
            "type":"Services"
        }
    ],
    "sg:phone":"+44 1453 822041",
    "sg:postcode":"GL10 3BD",
    "sg:province":"Gloucestershire",
    "sg:tags":[
        "transportation",
        "livestock",
        "transport"
    ],
    "wof:name":"Foote Transport",
    "wof:placetype":"venue"
},
  "geometry": {"coordinates":[-2.325842,51.746082],"type":"Point"}
}