{
  "type": "Feature",
  "properties": {
    "addr:full":"9 Bryn Rhos Llanelli Carmarthenshire SA14 8RB",
    "addr:housenumber":"9",
    "addr:postcode":"sa14 8rb",
    "addr:street":"Bryn Rhos Llanelli",
    "iso:country":"GB",
    "sg:address":"9 Bryn Rhos",
    "sg:city":"Llanelli",
    "sg:classifiers":[
        {
            "category":"Professional",
            "subcategory":"Accounting & Tax Preparation",
            "type":"Services"
        }
    ],
    "sg:postcode":"SA14 8RB",
    "sg:province":"Carmarthenshire",
    "sg:tags":[
        "accountant"
    ],
    "wof:name":"P J Evans",
    "wof:placetype":"venue"
},
  "geometry": {"coordinates":[-4.1219978333,51.6860809326],"type":"Point"}
}