{
  "type": "Feature",
  "properties": {
    "addr:full":"15 Fieldhead Square Glasgow Glasgow City G43 1HL",
    "addr:housenumber":"15",
    "addr:postcode":"g43 1hl",
    "addr:street":"Fieldhead Square",
    "iso:country":"GB",
    "sg:address":"15 Fieldhead Square",
    "sg:city":"Glasgow",
    "sg:classifiers":[
        {
            "category":"Personal",
            "subcategory":"Beauty Salon",
            "type":"Services"
        }
    ],
    "sg:phone":"+44 141 632 8546",
    "sg:postcode":"G43 1HL",
    "sg:province":"Glasgow City",
    "sg:tags":[
        "unisex",
        "hairdresser"
    ],
    "wof:name":"Angela Harvey Hairdressing",
    "wof:placetype":"venue"
},
  "geometry": {"coordinates":[-4.3088059425,55.8150367737],"type":"Point"}
}