{
  "type": "Feature",
  "properties": {
    "iso:country":"GB",
    "sg:address":"Chandler Way, Parkhouse",
    "sg:city":"Carlisle",
    "sg:classifiers":[
        {
            "category":"Food & Beverages",
            "subcategory":"Supermarket",
            "type":"Retail Goods"
        }
    ],
    "sg:phone":"+44 1228 526550",
    "sg:postcode":"CA3 0JQ",
    "sg:province":"Cumbria",
    "wof:name":"Asda Superstores",
    "wof:placetype":"venue"
},
  "geometry": {"coordinates":[-2.9549970627,54.9290161133],"type":"Point"}
}