{
  "type": "Feature",
  "properties": {
    "iso:country":"GB",
    "sg:address":"1 Halifax Road",
    "sg:city":"Todmorden",
    "sg:classifiers":[
        {
            "category":"Banks & Credit Unions",
            "subcategory":"Financial Services",
            "type":"Services"
        }
    ],
    "sg:phone":"+44 1706 818982",
    "sg:postcode":"OL14 5AG",
    "sg:province":"Lancashire",
    "sg:tags":[
        "consultant"
    ],
    "wof:name":"Richmond Residential & Commercial Plc",
    "wof:placetype":"venue"
},
  "geometry": {"coordinates":[-2.097211,53.713699],"type":"Point"}
}