{
  "type": "Feature",
  "properties": {
    "addr:full":"8 Baker Street, Gorleston Great Yarmouth Norfolk NR31 6QT",
    "addr:housenumber":"8",
    "addr:postcode":"nr31 6qt",
    "addr:street":"Baker Street",
    "iso:country":"GB",
    "sg:address":"8 Baker Street, Gorleston",
    "sg:city":"Great Yarmouth",
    "sg:classifiers":[
        {
            "category":"Fast Food",
            "type":"Food & Drink"
        }
    ],
    "sg:phone":"+44 1493 661801",
    "sg:postcode":"NR31 6QT",
    "sg:province":"Norfolk",
    "sg:tags":[
        "away",
        "take"
    ],
    "wof:name":"Good Luck",
    "wof:placetype":"venue"
},
  "geometry": {"coordinates":[1.728322,52.577747],"type":"Point"}
}