{
  "type": "Feature",
  "properties": {
    "iso:country":"GB",
    "sg:address":"179 Chessington Road",
    "sg:city":"Epsom",
    "sg:classifiers":[
        {
            "category":"Food & Beverages",
            "subcategory":"Meat & Fish",
            "type":"Retail Goods"
        }
    ],
    "sg:phone":"+44 20 8393 2701",
    "sg:postcode":"KT19 9XE",
    "sg:province":"Surrey",
    "sg:tags":[
        "butcher"
    ],
    "wof:name":"A Clark Butchers",
    "wof:placetype":"venue"
},
  "geometry": {"coordinates":[-0.267833,51.35268],"type":"Point"}
}