{
  "type": "Feature",
  "properties": {
    "addr:full":"13c Hunter Street, East Kilbride Glasgow South Lanarkshire G74 4LZ",
    "addr:housenumber":"13c",
    "addr:postcode":"g74 4lz",
    "addr:street":"Hunter Street",
    "iso:country":"GB",
    "sg:address":"13c Hunter Street, East Kilbride",
    "sg:city":"Glasgow",
    "sg:classifiers":[
        {
            "category":"Health Services",
            "subcategory":"Dentist",
            "type":"Services"
        }
    ],
    "sg:phone":"+44 1355 264222",
    "sg:postcode":"G74 4LZ",
    "sg:province":"South Lanarkshire",
    "wof:name":"Frank Rafters",
    "wof:placetype":"venue"
},
  "geometry": {"coordinates":[-4.175191,55.765221],"type":"Point"}
}