{
  "type": "Feature",
  "properties": {
    "addr:full":"South Bank Surbiton Surrey KT6 6DF",
    "addr:postcode":"kt6 6df",
    "iso:country":"GB",
    "sg:address":"South Bank",
    "sg:city":"Surbiton",
    "sg:classifiers":[
        {
            "category":"Education",
            "subcategory":"University",
            "type":"Public Place"
        }
    ],
    "sg:phone":"+44 20 8399 2688",
    "sg:postcode":"KT6 6DF",
    "sg:province":"Surrey",
    "sg:tags":[
        "adult"
    ],
    "wof:name":"Hillcroft College (Incorporated) Ltd.",
    "wof:placetype":"venue"
},
  "geometry": {"coordinates":[-0.300889,51.392174],"type":"Point"}
}