{
  "type": "Feature",
  "properties": {
    "iso:country":"GB",
    "sg:address":"28 Greenwich Church Street",
    "sg:city":"London",
    "sg:classifiers":[
        {
            "category":"Shopping",
            "subcategory":"Antiques",
            "type":"Retail Goods"
        }
    ],
    "sg:phone":"+44 20 8853 5777",
    "sg:postcode":"SE10 9BJ",
    "sg:province":"Greater London",
    "wof:name":"Peter Laurie",
    "wof:placetype":"venue"
},
  "geometry": {"coordinates":[-0.009562,51.481133],"type":"Point"}
}