{
  "type": "Feature",
  "properties": {
    "iso:country":"GB",
    "sg:address":"33 Hestham Avenue",
    "sg:city":"Morecambe",
    "sg:classifiers":[
        {
            "category":"Personal",
            "type":"Services"
        },
        {
            "category":"Retail",
            "subcategory":"Driving School",
            "type":"Services"
        }
    ],
    "sg:phone":"+44 1524 418592",
    "sg:postcode":"LA4 4PZ",
    "sg:province":"Lancashire",
    "sg:tags":[
        "wedding"
    ],
    "wof:name":"Woodlands",
    "wof:placetype":"venue"
},
  "geometry": {"coordinates":[-2.862009,54.067505],"type":"Point"}
}