{
  "type": "Feature",
  "properties": {
    "iso:country":"GB",
    "sg:address":"10 Meadow La",
    "sg:city":"Wickford",
    "sg:classifiers":[
        {
            "category":"Building & Trades",
            "subcategory":"Construction",
            "type":"Services"
        }
    ],
    "sg:postcode":"SS11 7DY",
    "sg:province":"Essex",
    "sg:tags":[
        "builder"
    ],
    "wof:name":"Lee Property Maintenance",
    "wof:placetype":"venue"
},
  "geometry": {"coordinates":[0.5294079781,51.6315498352],"type":"Point"}
}