{
  "type": "Feature",
  "properties": {
    "addr:full":"High View House, Bishops Rise Hatfield Hertfordshire AL10 9BZ",
    "addr:postcode":"al10 9bz",
    "addr:street":"Bishops Rise",
    "iso:country":"GB",
    "sg:address":"High View House, Bishops Rise",
    "sg:city":"Hatfield",
    "sg:classifiers":[
        {
            "category":"Organizations",
            "subcategory":"Non-profit Organization",
            "type":"Services"
        }
    ],
    "sg:phone":"+44 1707 271785",
    "sg:postcode":"AL10 9BZ",
    "sg:province":"Hertfordshire",
    "sg:tags":[
        "organisation",
        "voluntary",
        "charity"
    ],
    "wof:name":"Hospitaller Order of St.John of God",
    "wof:placetype":"venue"
},
  "geometry": {"coordinates":[-0.238436,51.758266],"type":"Point"}
}