{
  "type": "Feature",
  "properties": {
    "iso:country":"GB",
    "sg:address":"Swan La Mill, Higher Swan La",
    "sg:city":"Bolton",
    "sg:classifiers":[
        {
            "category":"Shopping",
            "subcategory":"Stationery & Office Supplies",
            "type":"Retail Goods"
        }
    ],
    "sg:postcode":"BL3 3BJ",
    "sg:province":"Lancashire",
    "wof:name":"Maccas",
    "wof:placetype":"venue"
},
  "geometry": {"coordinates":[-2.441459,53.560783],"type":"Point"}
}