{
  "type": "Feature",
  "properties": {
    "iso:country":"GB",
    "sg:address":"34 Penny Meadow",
    "sg:city":"Ashton-under-lyne",
    "sg:classifiers":[
        {
            "category":"Professional",
            "subcategory":"Accounting & Tax Preparation",
            "type":"Services"
        }
    ],
    "sg:phone":"+44 161 343 7780",
    "sg:postcode":"OL6 6HG",
    "sg:province":"Greater Manchester",
    "sg:tags":[
        "accountant"
    ],
    "wof:name":"F Atwell &Co",
    "wof:placetype":"venue"
},
  "geometry": {"coordinates":[-2.088138,53.490154],"type":"Point"}
}