{
  "type": "Feature",
  "properties": {
    "iso:country":"GB",
    "sg:address":"218 Mitcham Road",
    "sg:city":"Croydon",
    "sg:classifiers":[
        {
            "category":"Shopping",
            "subcategory":"News",
            "type":"Retail Goods"
        }
    ],
    "sg:phone":"+44 20 8684 2603",
    "sg:postcode":"CR0 3JG",
    "sg:province":"Surrey",
    "sg:tags":[
        "newsagent"
    ],
    "wof:name":"J Golding Group",
    "wof:placetype":"venue"
},
  "geometry": {"coordinates":[-0.114884,51.382187],"type":"Point"}
}