{
  "type": "Feature",
  "properties": {
    "addr:full":"79 Abbey Road, Dunscroft Doncaster South Yorkshire DN7 4LE",
    "addr:housenumber":"79",
    "addr:postcode":"dn7 4le",
    "addr:street":"Abbey Road",
    "iso:country":"GB",
    "sg:address":"79 Abbey Road, Dunscroft",
    "sg:city":"Doncaster",
    "sg:classifiers":[
        {
            "category":"Personal",
            "subcategory":"Beauty Salon",
            "type":"Services"
        },
        {
            "category":"Personal",
            "subcategory":"Barber",
            "type":"Services"
        }
    ],
    "sg:phone":"+44 1302 840512",
    "sg:postcode":"DN7 4LE",
    "sg:province":"South Yorkshire",
    "sg:tags":[
        "unisex",
        "hairdresser"
    ],
    "wof:name":"Shylocks",
    "wof:placetype":"venue"
},
  "geometry": {"coordinates":[-1.014959,53.58157],"type":"Point"}
}