{
  "type": "Feature",
  "properties": {
    "addr:full":"3 Lainshaw Street, Stewarton Kilmarnock East Ayrshire KA3 5BY",
    "addr:housenumber":"3",
    "addr:postcode":"ka3 5by",
    "addr:street":"Lainshaw Street",
    "iso:country":"GB",
    "sg:address":"3 Lainshaw Street, Stewarton",
    "sg:city":"Kilmarnock",
    "sg:classifiers":[
        {
            "category":"Shopping",
            "subcategory":"Antiques",
            "type":"Retail Goods"
        }
    ],
    "sg:phone":"+44 1560 484113",
    "sg:postcode":"KA3 5BY",
    "sg:province":"East Ayrshire",
    "wof:name":"Woolfsons of James Street Ltd.",
    "wof:placetype":"venue"
},
  "geometry": {"coordinates":[-4.5158061981,55.6803092957],"type":"Point"}
}