{
  "type": "Feature",
  "properties": {
    "addr:full":"104 Ely Road Ely Cambridgeshire CB6 1RT",
    "addr:housenumber":"104",
    "addr:postcode":"cb6 1rt",
    "addr:street":"Ely Road",
    "iso:country":"GB",
    "sg:address":"104 Ely Road",
    "sg:city":"Ely",
    "sg:classifiers":[
        {
            "category":"Taxi",
            "type":"Transportation"
        }
    ],
    "sg:phone":"+44 1353 860211",
    "sg:postcode":"CB6 1RT",
    "sg:province":"Cambridgeshire",
    "sg:tags":[
        "mini",
        "cab"
    ],
    "wof:name":"S J Cole",
    "wof:placetype":"venue"
},
  "geometry": {"coordinates":[0.3011029959,52.4405136108],"type":"Point"}
}