{
  "type": "Feature",
  "properties": {
    "addr:full":"Clarence House, Akeds Rd Halifax West Yorkshire HX1 2TR",
    "addr:postcode":"hx1 2tr",
    "addr:street":"Akeds Rd",
    "iso:country":"GB",
    "sg:address":"Clarence House, Akeds Rd",
    "sg:city":"Halifax",
    "sg:classifiers":[
        {
            "category":"Manufacturing",
            "subcategory":"Metals",
            "type":"Manufacturing & Wholesale Goods"
        }
    ],
    "sg:phone":"+44 1422 365760",
    "sg:postcode":"HX1 2TR",
    "sg:province":"West Yorkshire",
    "sg:tags":[
        "die-casting"
    ],
    "wof:name":"Halifax Castings Brass Founders",
    "wof:placetype":"venue"
},
  "geometry": {"coordinates":[-1.8701000214,53.720539093],"type":"Point"}
}