{
  "type": "Feature",
  "properties": {
    "iso:country":"GB",
    "sg:address":"Four Elms, Lake End Road, Taplow",
    "sg:city":"Slough",
    "sg:classifiers":[
        {
            "category":"Travel",
            "subcategory":"Travel Agent",
            "type":"Entertainment"
        }
    ],
    "sg:phone":"+44 1628 602010",
    "sg:postcode":"SL6 0PN",
    "sg:province":"Berkshire",
    "sg:tags":[
        "agency",
        "activity"
    ],
    "wof:name":"Afro Asian Travel Ltd.",
    "wof:placetype":"venue"
},
  "geometry": {"coordinates":[-0.687149,51.532169],"type":"Point"}
}