{
  "type": "Feature",
  "properties": {
    "iso:country":"GB",
    "sg:address":"37 Lower Hall Lane",
    "sg:city":"Walsall",
    "sg:classifiers":[
        {
            "category":"Cafe",
            "type":"Food & Drink"
        }
    ],
    "sg:phone":"+44 1922 638830",
    "sg:postcode":"WS1 1RH",
    "sg:province":"West Midlands",
    "sg:tags":[
        "tea",
        "room"
    ],
    "wof:name":"Digbys Cafe",
    "wof:placetype":"venue"
},
  "geometry": {"coordinates":[-1.982876,52.582207],"type":"Point"}
}