{
  "type": "Feature",
  "properties": {
    "addr:full":"16 Hockley Street Birmingham West Midlands B18 6BL",
    "addr:housenumber":"16",
    "addr:postcode":"b18 6bl",
    "addr:street":"Hockley Street",
    "iso:country":"GB",
    "sg:address":"16 Hockley Street",
    "sg:city":"Birmingham",
    "sg:classifiers":[
        {
            "category":"Shopping",
            "subcategory":"Comic Books",
            "type":"Retail Goods"
        }
    ],
    "sg:phone":"+44 121 523 5822",
    "sg:postcode":"B18 6BL",
    "sg:province":"West Midlands",
    "sg:tags":[
        "jeweller"
    ],
    "wof:name":"M Manna",
    "wof:placetype":"venue"
},
  "geometry": {"coordinates":[-1.9124289751,52.4893035889],"type":"Point"}
}