{
  "type": "Feature",
  "properties": {
    "addr:full":"643 Watford Way, Apex Corner London Greater London NW7 3JR",
    "addr:housenumber":"643",
    "addr:postcode":"nw7 3jr",
    "addr:street":"Watford Way;Corner",
    "iso:country":"GB",
    "sg:address":"643 Watford Way, Apex Corner",
    "sg:city":"London",
    "sg:classifiers":[
        {
            "category":"Professional",
            "subcategory":"Accounting & Tax Preparation",
            "type":"Services"
        }
    ],
    "sg:phone":"+44 20 8959 0440",
    "sg:postcode":"NW7 3JR",
    "sg:province":"Greater London",
    "sg:tags":[
        "accountant"
    ],
    "wof:name":"Steinberg Platt",
    "wof:placetype":"venue"
},
  "geometry": {"coordinates":[-0.250011,51.619129],"type":"Point"}
}