{
  "type": "Feature",
  "properties": {
    "addr:full":"7 Front Street, Kelloe Durham Durham DH6 4PD",
    "addr:housenumber":"7",
    "addr:postcode":"dh6 4pd",
    "addr:street":"Front Street",
    "iso:country":"GB",
    "sg:address":"7 Front Street, Kelloe",
    "sg:city":"Durham",
    "sg:classifiers":[
        {
            "category":"Government",
            "subcategory":"Post Office",
            "type":"Public Place"
        }
    ],
    "sg:phone":"+44 845 722 3344",
    "sg:postcode":"DH6 4PD",
    "sg:province":"Durham",
    "wof:name":"Kelloe Post Office",
    "wof:placetype":"venue"
},
  "geometry": {"coordinates":[-1.4621889591,54.7411956787],"type":"Point"}
}