{
  "type": "Feature",
  "properties": {
    "iso:country":"GB",
    "sg:address":"2 Carcut Rd",
    "sg:city":"Middlesbrough",
    "sg:classifiers":[
        {
            "category":"Building & Trades",
            "subcategory":"Construction",
            "type":"Services"
        }
    ],
    "sg:phone":"+44 1253 349122",
    "sg:postcode":"TS3 6QL",
    "sg:province":"North Yorkshire",
    "sg:tags":[
        "platform",
        "work",
        "scaffolding"
    ],
    "wof:name":"S iE North East Ltd",
    "wof:placetype":"venue"
},
  "geometry": {"coordinates":[-1.205623,54.573498],"type":"Point"}
}