{
  "type": "Feature",
  "properties": {
    "iso:country":"GB",
    "sg:address":"Caroline House, Ryston End",
    "sg:city":"Downham Market",
    "sg:classifiers":[
        {
            "category":"Shopping",
            "type":"Retail Goods"
        }
    ],
    "sg:postcode":"PE38 9AU",
    "sg:province":"Cambridgeshire",
    "sg:tags":[
        "merchant"
    ],
    "wof:name":"Flax (U K) Ltd.",
    "wof:placetype":"venue"
},
  "geometry": {"coordinates":[0.38022,52.599293],"type":"Point"}
}