{
  "type": "Feature",
  "properties": {
    "addr:full":"Highgate Hill St Columb Cornwall TR9 6LY",
    "addr:postcode":"tr9 6ly",
    "addr:street":"Highgate Hill St",
    "iso:country":"GB",
    "sg:address":"Highgate Hill",
    "sg:city":"St Columb",
    "sg:classifiers":[
        {
            "category":"Retail",
            "subcategory":"Auto Repair",
            "type":"Services"
        }
    ],
    "sg:phone":"+44 1726 860531",
    "sg:postcode":"TR9 6LY",
    "sg:province":"Cornwall",
    "sg:tags":[
        "modification",
        "garage"
    ],
    "wof:name":"Robinsons Tyre & Vehicle Services",
    "wof:placetype":"venue"
},
  "geometry": {"coordinates":[-4.9227890968,50.3951950073],"type":"Point"}
}