{
  "type": "Feature",
  "properties": {
    "addr:full":"70 Windsor Road, Cosham Portsmouth Hampshire PO6 2TG",
    "addr:housenumber":"70",
    "addr:postcode":"hampshire po6 2tg",
    "addr:street":"Windsor Road Cosham",
    "iso:country":"GB",
    "sg:address":"70 Windsor Road, Cosham",
    "sg:city":"Portsmouth",
    "sg:classifiers":[
        {
            "category":"Professional",
            "subcategory":"Management & Consulting",
            "type":"Services"
        }
    ],
    "sg:postcode":"PO6 2TG",
    "sg:province":"Hampshire",
    "sg:tags":[
        "consultant",
        "specialist"
    ],
    "wof:name":"Rosemary Anne Joyce",
    "wof:placetype":"venue"
},
  "geometry": {"coordinates":[-1.064351,50.841305],"type":"Point"}
}