{
  "type": "Feature",
  "properties": {
    "addr:full":"Theobalds Park Farm, Great Cambridge Road Waltham Cross Essex EN8 8EU",
    "addr:postcode":"en8 8eu",
    "addr:street":"Great Cambridge Road",
    "iso:country":"GB",
    "sg:address":"Theobalds Park Farm, Great Cambridge Road",
    "sg:city":"Waltham Cross",
    "sg:classifiers":[
        {
            "category":"Food & Beverages",
            "subcategory":"Farmers Market",
            "type":"Retail Goods"
        }
    ],
    "sg:phone":"+44 1992 622170",
    "sg:postcode":"EN8 8EU",
    "sg:province":"Essex",
    "sg:tags":[
        "farm",
        "shop",
        "pyo"
    ],
    "wof:name":"J M Oyler",
    "wof:placetype":"venue"
},
  "geometry": {"coordinates":[-0.0391229987,51.69323349],"type":"Point"}
}