{
  "type": "Feature",
  "properties": {
    "iso:country":"GB",
    "sg:address":"6 Laythorpe Avenue",
    "sg:city":"Skegness",
    "sg:classifiers":[
        {
            "category":"Professional",
            "type":"Services"
        },
        {
            "category":"Building & Trades",
            "subcategory":"Cleaning & Sanitation",
            "type":"Services"
        }
    ],
    "sg:phone":"+44 1754 767890",
    "sg:postcode":"PE25 3BX",
    "sg:province":"Lincolnshire",
    "sg:tags":[
        "dry",
        "control",
        "damp",
        "rot",
        "preservation"
    ],
    "wof:name":"Skegness Damp Proofing",
    "wof:placetype":"venue"
},
  "geometry": {"coordinates":[0.339524,53.133682],"type":"Point"}
}