{
  "type": "Feature",
  "properties": {
    "addr:full":"44 Beauchamp Rd Edinburgh City of Edinburgh EH16 6LU",
    "addr:housenumber":"44",
    "addr:postcode":"eh16 6lu",
    "addr:street":"Beauchamp Rd",
    "iso:country":"GB",
    "sg:address":"44 Beauchamp Rd",
    "sg:city":"Edinburgh",
    "sg:classifiers":[
        {
            "category":"Professional",
            "subcategory":"Secretarial Services",
            "type":"Services"
        }
    ],
    "sg:postcode":"EH16 6LU",
    "sg:province":"City of Edinburgh",
    "wof:name":"Begg,Lucian J,",
    "wof:placetype":"venue"
},
  "geometry": {"coordinates":[-3.165783,55.913277],"type":"Point"}
}