{
  "type": "Feature",
  "properties": {
    "iso:country":"GB",
    "sg:address":"Marina Way",
    "sg:city":"Hartlepool",
    "sg:classifiers":[
        {
            "category":"Food & Beverages",
            "subcategory":"Supermarket",
            "type":"Retail Goods"
        }
    ],
    "sg:phone":"+44 1429 221380",
    "sg:postcode":"TS24 0XR",
    "sg:province":"Durham",
    "wof:name":"Asda Superstores",
    "wof:placetype":"venue"
},
  "geometry": {"coordinates":[-1.20897,54.691708],"type":"Point"}
}