{
  "type": "Feature",
  "properties": {
    "addr:full":"Unit 4b Boardman Industrial Estate, Boardman Road Swadlincote Derbyshire DE11 9DL",
    "addr:housenumber":"unit 4b;estate",
    "addr:postcode":"de11 9dl",
    "addr:street":"Boardman Industrial;Boardman Road",
    "iso:country":"GB",
    "sg:address":"Unit 4b Boardman Industrial Estate, Boardman Road",
    "sg:city":"Swadlincote",
    "sg:classifiers":[
        {
            "category":"Professional",
            "subcategory":"Engineering",
            "type":"Services"
        }
    ],
    "sg:phone":"+44 1283 216283",
    "sg:postcode":"DE11 9DL",
    "sg:province":"Derbyshire",
    "sg:tags":[
        "engineer"
    ],
    "wof:name":"Tubeweld Engineering Ltd",
    "wof:placetype":"venue"
},
  "geometry": {"coordinates":[-1.552209,52.774094],"type":"Point"}
}