{
  "type": "Feature",
  "properties": {
    "addr:full":"33 Camp Hill Avenue Worcester Worcestershire WR5 2HQ",
    "addr:housenumber":"33",
    "addr:postcode":"wr5 2hq",
    "addr:street":"Camp Hill Avenue",
    "iso:country":"GB",
    "sg:address":"33 Camp Hill Avenue",
    "sg:city":"Worcester",
    "sg:classifiers":[
        {
            "category":"Professional",
            "subcategory":"Art Services",
            "type":"Services"
        },
        {
            "category":"Real Estate",
            "subcategory":"Architect",
            "type":"Services"
        }
    ],
    "sg:phone":"+44 1905 350190",
    "sg:postcode":"WR5 2HQ",
    "sg:province":"Worcestershire",
    "sg:tags":[
        "consultant",
        "design"
    ],
    "wof:name":"Whewell Design",
    "wof:placetype":"venue"
},
  "geometry": {"coordinates":[-2.2069489956,52.1843185425],"type":"Point"}
}