{
  "type": "Feature",
  "properties": {
    "iso:country":"GB",
    "sg:address":"54 Ewenny Rd",
    "sg:city":"Bridgend",
    "sg:classifiers":[
        {
            "category":"Building & Trades",
            "subcategory":"Construction",
            "type":"Services"
        }
    ],
    "sg:postcode":"CF31 3HR",
    "sg:province":"Bridgend",
    "sg:tags":[
        "builder"
    ],
    "wof:name":"Davies,Phillip,",
    "wof:placetype":"venue"
},
  "geometry": {"coordinates":[-3.5760889053,51.5000686646],"type":"Point"}
}