{
  "type": "Feature",
  "properties": {
    "addr:full":"South Row Milton Keynes Buckinghamshire MK9 1BL",
    "addr:postcode":"mk9 1bl",
    "addr:street":"South Row",
    "iso:country":"GB",
    "sg:address":"South Row",
    "sg:city":"Milton Keynes",
    "sg:classifiers":[
        {
            "category":"Sports & Exercise",
            "subcategory":"Sports Center",
            "type":"Entertainment"
        }
    ],
    "sg:phone":"+44 1908 678866",
    "sg:postcode":"MK9 1BL",
    "sg:province":"Buckinghamshire",
    "sg:tags":[
        "shop",
        "good"
    ],
    "wof:name":"Skate Express",
    "wof:placetype":"venue"
},
  "geometry": {"coordinates":[-0.733666,51.995827],"type":"Point"}
}