{
  "type": "Feature",
  "properties": {
    "addr:full":"Unit 1 Daybrook Business Centre, Sherbrooke Road Nottingham Nottinghamshire NG5 6AT",
    "addr:housenumber":"unit 1",
    "addr:postcode":"ng5 6at",
    "addr:street":"Sherbrooke Road",
    "iso:country":"GB",
    "sg:address":"Unit 1 Daybrook Business Centre, Sherbrooke Road",
    "sg:city":"Nottingham",
    "sg:classifiers":[
        {
            "category":"Shopping",
            "subcategory":"Clothing, Apparel, & Fashions",
            "type":"Retail Goods"
        }
    ],
    "sg:phone":"+44 115 967 9862",
    "sg:postcode":"NG5 6AT",
    "sg:province":"Nottinghamshire",
    "sg:tags":[
        "lingerie"
    ],
    "wof:name":"Annabelle Hosiery",
    "wof:placetype":"venue"
},
  "geometry": {"coordinates":[-1.14411,52.998268],"type":"Point"}
}