{
  "type": "Feature",
  "properties": {
    "iso:country":"GB",
    "sg:address":"Flat A 11 Wharfdale Road",
    "sg:city":"London",
    "sg:classifiers":[
        {
            "category":"Professional",
            "subcategory":"Computer Services",
            "type":"Services"
        }
    ],
    "sg:postcode":"N1 9SB",
    "sg:province":"Greater London",
    "sg:tags":[
        "system",
        "software"
    ],
    "wof:name":"Journaltech Ltd",
    "wof:placetype":"venue"
},
  "geometry": {"coordinates":[-0.119599998,51.5333786011],"type":"Point"}
}