{
  "type": "Feature",
  "properties": {
    "iso:country":"GB",
    "sg:address":"Summer Place, Hayfield Close, Wingerwoth",
    "sg:city":"Chesterfield",
    "sg:classifiers":[
        {
            "category":"Manufacturing",
            "subcategory":"Metals",
            "type":"Manufacturing & Wholesale Goods"
        }
    ],
    "sg:phone":"+44 1246 238251",
    "sg:postcode":"S42 6QF",
    "sg:province":"Derbyshire",
    "sg:tags":[
        "product",
        "fabricated"
    ],
    "wof:name":"Axiom Ltd.",
    "wof:placetype":"venue"
},
  "geometry": {"coordinates":[-1.43378,53.201431],"type":"Point"}
}