{
  "type": "Feature",
  "properties": {
    "addr:full":"Crowness Road, Hatston Kirkwall Orkney Islands KW15 1RG",
    "addr:postcode":"kw15 1rg",
    "addr:street":"Crowness Road Hatston",
    "iso:country":"GB",
    "sg:address":"Crowness Road, Hatston",
    "sg:city":"Kirkwall",
    "sg:classifiers":[
        {
            "category":"Home & Garden",
            "subcategory":"Furniture",
            "type":"Retail Goods"
        }
    ],
    "sg:postcode":"KW15 1RG",
    "sg:province":"Orkney Islands",
    "wof:name":"Wolstenholme Carpet & Curtain Centre",
    "wof:placetype":"venue"
},
  "geometry": {"coordinates":[-2.9604189396,58.9817314148],"type":"Point"}
}