{
  "type": "Feature",
  "properties": {
    "addr:full":"Tanhouse Lane Widnes Cheshire WA8 0SW",
    "addr:postcode":"wa8 0sw",
    "addr:street":"Tanhouse Lane",
    "iso:country":"GB",
    "sg:address":"Tanhouse Lane",
    "sg:city":"Widnes",
    "sg:classifiers":[
        {
            "category":"Cafe",
            "type":"Food & Drink"
        }
    ],
    "sg:phone":"+44 151 257 9387",
    "sg:postcode":"WA8 0SW",
    "sg:province":"Cheshire",
    "sg:tags":[
        "tea",
        "room"
    ],
    "wof:name":"Twice As Nice Cafe",
    "wof:placetype":"venue"
},
  "geometry": {"coordinates":[-2.7182838917,53.3669433594],"type":"Point"}
}