{
  "type": "Feature",
  "properties": {
    "addr:full":"253 Milby Drive Nuneaton Leicestershire CV11 6UL",
    "addr:housenumber":"253",
    "addr:postcode":"cv11 6ul",
    "addr:street":"Milby Drive",
    "iso:country":"GB",
    "sg:address":"253 Milby Drive",
    "sg:city":"Nuneaton",
    "sg:classifiers":[
        {
            "category":"Professional",
            "subcategory":"Engineering",
            "type":"Services"
        }
    ],
    "sg:postcode":"CV11 6UL",
    "sg:province":"Leicestershire",
    "sg:tags":[
        "contractor",
        "electrical",
        "engineer"
    ],
    "wof:name":"S P Butterick",
    "wof:placetype":"venue"
},
  "geometry": {"coordinates":[-1.440225,52.535858],"type":"Point"}
}