{
  "type": "Feature",
  "properties": {
    "iso:country":"GB",
    "sg:address":"Bigsbys Corner, Benhall",
    "sg:city":"Saxmundham",
    "sg:classifiers":[
        {
            "category":"Retail",
            "subcategory":"Auto Repair",
            "type":"Services"
        }
    ],
    "sg:phone":"+44 1728 603874",
    "sg:postcode":"IP17 1HB",
    "sg:province":"Suffolk",
    "sg:tags":[
        "modification",
        "garage"
    ],
    "wof:name":"F P Stephenson & Sons",
    "wof:placetype":"venue"
},
  "geometry": {"coordinates":[1.489533,52.216713],"type":"Point"}
}