{
  "type": "Feature",
  "properties": {
    "addr:full":"66 Sterling Road Sittingbourne Kent ME10 1SL",
    "addr:housenumber":"66",
    "addr:postcode":"me10 1sl",
    "addr:street":"Sterling Road",
    "iso:country":"GB",
    "sg:address":"66 Sterling Road",
    "sg:city":"Sittingbourne",
    "sg:classifiers":[
        {
            "category":"Building & Trades",
            "subcategory":"Plumbing",
            "type":"Services"
        }
    ],
    "sg:phone":"+44 1795 470962",
    "sg:postcode":"ME10 1SL",
    "sg:province":"Kent",
    "sg:tags":[
        "heating"
    ],
    "wof:name":"Goldings Plumbing Services",
    "wof:placetype":"venue"
},
  "geometry": {"coordinates":[0.7206749916,51.3298416138],"type":"Point"}
}