{
  "type": "Feature",
  "properties": {
    "addr:full":"Copper Beeches, Gayton Road, Milton Malsor Northampton Buckinghamshire NN7 3AA",
    "addr:postcode":"nn7 3aa",
    "addr:street":"Copper;Gayton Road",
    "iso:country":"GB",
    "sg:address":"Copper Beeches, Gayton Road, Milton Malsor",
    "sg:city":"Northampton",
    "sg:classifiers":[
        {
            "category":"Professional",
            "subcategory":"Management & Consulting",
            "type":"Services"
        },
        {
            "category":"Professional",
            "subcategory":"Research",
            "type":"Services"
        }
    ],
    "sg:phone":"+44 1604 859456",
    "sg:postcode":"NN7 3AA",
    "sg:province":"Buckinghamshire",
    "sg:tags":[
        "consultant",
        "organisation",
        "business",
        "market"
    ],
    "wof:name":"COUNTRY CONSULTANCY LTD.",
    "wof:placetype":"venue"
},
  "geometry": {"coordinates":[-0.923379004,52.1930656433],"type":"Point"}
}