{
  "type": "Feature",
  "properties": {
    "addr:full":"18 Wentworth Way Northampton Northamptonshire NN2 7LW",
    "addr:housenumber":"18",
    "addr:postcode":"nn2 7lw",
    "addr:street":"Wentworth Way",
    "iso:country":"GB",
    "sg:address":"18 Wentworth Way",
    "sg:city":"Northampton",
    "sg:classifiers":[
        {
            "category":"Home & Garden",
            "subcategory":"Carpets & Floor Coverings",
            "type":"Retail Goods"
        }
    ],
    "sg:phone":"+44 1604 792850",
    "sg:postcode":"NN2 7LW",
    "sg:province":"Northamptonshire",
    "sg:tags":[
        "carpets",
        "rug",
        "matting"
    ],
    "wof:name":"M A Carpets",
    "wof:placetype":"venue"
},
  "geometry": {"coordinates":[-0.88270998,52.2599830627],"type":"Point"}
}