{
  "type": "Feature",
  "properties": {
    "addr:full":"Tramway Offices, Mellor Street Rochdale Lancashire OL12 6AA",
    "addr:postcode":"ol12 6aa",
    "addr:street":"Mellor Street",
    "iso:country":"GB",
    "sg:address":"Tramway Offices, Mellor Street",
    "sg:city":"Rochdale",
    "sg:classifiers":[
        {
            "category":"Professional",
            "subcategory":"Engineering",
            "type":"Services"
        }
    ],
    "sg:postcode":"OL12 6AA",
    "sg:province":"Lancashire",
    "sg:tags":[
        "consulting",
        "design",
        "engineer"
    ],
    "wof:name":"Chem Line Services Ltd.",
    "wof:placetype":"venue"
},
  "geometry": {"coordinates":[-2.162766,53.619007],"type":"Point"}
}