{
  "type": "Feature",
  "properties": {
    "addr:full":"1 Markers Cullompton Devon EX15 3DZ",
    "addr:housenumber":"1",
    "addr:postcode":"ex15 3dz",
    "addr:street":"Markers Cullompton",
    "iso:country":"GB",
    "sg:address":"1 Markers",
    "sg:city":"Cullompton",
    "sg:classifiers":[
        {
            "category":"Social Services",
            "subcategory":"Adult Care",
            "type":"Services"
        },
        {
            "category":"Social Services",
            "subcategory":"Retirement Home",
            "type":"Services"
        }
    ],
    "sg:postcode":"EX15 3DZ",
    "sg:province":"Devon",
    "sg:tags":[
        "residential",
        "housing",
        "sheltered"
    ],
    "wof:name":"The Uffculme Housing Trust",
    "wof:placetype":"venue"
},
  "geometry": {"coordinates":[-3.3284420967,50.9053573608],"type":"Point"}
}