{
  "type": "Feature",
  "properties": {
    "iso:country":"GB",
    "sg:address":"9 Oldbury Road",
    "sg:city":"Nuneaton",
    "sg:classifiers":[
        {
            "category":"Arts & Performance",
            "subcategory":"Music",
            "type":"Entertainment"
        }
    ],
    "sg:phone":"+44 24 7639 4185",
    "sg:postcode":"CV10 0TD",
    "sg:province":"Leicestershire",
    "sg:tags":[
        "mobile",
        "disco"
    ],
    "wof:name":"Lee James Roadshow",
    "wof:placetype":"venue"
},
  "geometry": {"coordinates":[-1.521036,52.541325],"type":"Point"}
}