{
  "type": "Feature",
  "properties": {
    "iso:country":"GB",
    "sg:address":"Crowfield",
    "sg:city":"Cheltenham",
    "sg:classifiers":[
        {
            "category":"Social Services",
            "subcategory":"Adult Care",
            "type":"Services"
        }
    ],
    "sg:phone":"+44 1242 677437",
    "sg:postcode":"GL52 4HP",
    "sg:province":"Gloucestershire",
    "sg:tags":[
        "housing",
        "sheltered"
    ],
    "wof:name":"Crowfield Sheltered Housing",
    "wof:placetype":"venue"
},
  "geometry": {"coordinates":[-2.045136,51.946262],"type":"Point"}
}