{
  "type": "Feature",
  "properties": {
    "iso:country":"GB",
    "sg:address":"1 Baffins Road",
    "sg:city":"Portsmouth",
    "sg:classifiers":[
        {
            "category":"Retail",
            "subcategory":"Auto Repair",
            "type":"Services"
        }
    ],
    "sg:phone":"+44 23 9273 7879",
    "sg:postcode":"PO3 6BD",
    "sg:province":"Hampshire",
    "sg:tags":[
        "modification",
        "garage",
        "related"
    ],
    "wof:name":"Kingsley Garage",
    "wof:placetype":"venue"
},
  "geometry": {"coordinates":[-1.063766,50.802792],"type":"Point"}
}