{
  "type": "Feature",
  "properties": {
    "addr:full":"1000 Kennishead Road Glasgow East Renfrewshire G53 7RA",
    "addr:housenumber":"1000",
    "addr:postcode":"g53 7ra",
    "addr:street":"Kennishead Road",
    "iso:country":"GB",
    "sg:address":"1000 Kennishead Road",
    "sg:city":"Glasgow",
    "sg:classifiers":[
        {
            "category":"Autos & Motor Vehicles",
            "subcategory":"Automobile Sales",
            "type":"Retail Goods"
        }
    ],
    "sg:postcode":"G53 7RA",
    "sg:province":"East Renfrewshire",
    "sg:tags":[
        "car"
    ],
    "wof:name":"Wylies Ltd.",
    "wof:placetype":"venue"
},
  "geometry": {"coordinates":[-4.3477659225,55.80884552],"type":"Point"}
}