{
  "type": "Feature",
  "properties": {
    "addr:full":"22 The Blvd Crawley Surrey RH10 1XT",
    "addr:housenumber":"22",
    "addr:postcode":"rh10 1xt",
    "addr:street":"The Blvd",
    "iso:country":"GB",
    "sg:address":"22 The Blvd",
    "sg:city":"Crawley",
    "sg:classifiers":[
        {
            "category":"Travel",
            "subcategory":"Travel Agent",
            "type":"Entertainment"
        }
    ],
    "sg:phone":"+44 1293 542222",
    "sg:postcode":"RH10 1XT",
    "sg:province":"Surrey",
    "wof:name":"Going Places Leisure Travel",
    "wof:placetype":"venue"
},
  "geometry": {"coordinates":[-0.187741,51.116154],"type":"Point"}
}