{
  "type": "Feature",
  "properties": {
    "iso:country":"GB",
    "sg:address":"5 John Oliver Buildings",
    "sg:city":"Barnet",
    "sg:classifiers":[
        {
            "category":"Real Estate",
            "subcategory":"Developer",
            "type":"Services"
        }
    ],
    "sg:phone":"+44 20 8441 8686",
    "sg:postcode":"EN5 4BS",
    "sg:province":"Hertfordshire",
    "sg:tags":[
        "property"
    ],
    "wof:name":"Almond Beech Developments Ltd.",
    "wof:placetype":"venue"
},
  "geometry": {"coordinates":[-0.2049989998,51.6587257385],"type":"Point"}
}