{
  "type": "Feature",
  "properties": {
    "addr:full":"68 Blakberry Lane Alton Hampshire GU34 5DG",
    "addr:housenumber":"68",
    "addr:postcode":"gu34 5dg",
    "addr:street":"Blakberry Lane",
    "iso:country":"GB",
    "sg:address":"68 Blakberry Lane",
    "sg:city":"Alton",
    "sg:classifiers":[
        {
            "category":"Building & Trades",
            "subcategory":"Construction",
            "type":"Services"
        }
    ],
    "sg:phone":"+44 1420 562886",
    "sg:postcode":"GU34 5DG",
    "sg:province":"Hampshire",
    "sg:tags":[
        "contractor"
    ],
    "wof:name":"Flint Construction Ltd.",
    "wof:placetype":"venue"
},
  "geometry": {"coordinates":[-1.0451450348,51.1079597473],"type":"Point"}
}