{
  "type": "Feature",
  "properties": {
    "addr:full":"102 Colne Road, Earby Barnoldswick Lancashire BB18 6XS",
    "addr:housenumber":"102",
    "addr:postcode":"bb18 6xs",
    "addr:street":"Colne Road",
    "iso:country":"GB",
    "sg:address":"102 Colne Road, Earby",
    "sg:city":"Barnoldswick",
    "sg:classifiers":[
        {
            "category":"Shopping",
            "subcategory":"News",
            "type":"Retail Goods"
        }
    ],
    "sg:phone":"+44 1282 842472",
    "sg:postcode":"BB18 6XS",
    "sg:province":"Lancashire",
    "sg:tags":[
        "newsagent"
    ],
    "wof:name":"J J News",
    "wof:placetype":"venue"
},
  "geometry": {"coordinates":[-2.147482,53.912182],"type":"Point"}
}