{
  "type": "Feature",
  "properties": {
    "iso:country":"GB",
    "sg:address":"Berlin House, Upper Frog Street",
    "sg:city":"Tenby",
    "sg:classifiers":[
        {
            "category":"Professional",
            "subcategory":"Advertising",
            "type":"Services"
        }
    ],
    "sg:phone":"+44 1834 845210",
    "sg:postcode":"SA70 7JD",
    "sg:province":"Pembrokeshire",
    "sg:tags":[
        "directory"
    ],
    "wof:name":"Optic Uk Services",
    "wof:placetype":"venue"
},
  "geometry": {"coordinates":[-4.7005691528,51.6715736389],"type":"Point"}
}