{
  "type": "Feature",
  "properties": {
    "addr:full":"14 Beaumont Rd Birmingham West Midlands B30 2DY",
    "addr:housenumber":"14",
    "addr:postcode":"b30 2dy",
    "addr:street":"Beaumont Rd",
    "iso:country":"GB",
    "sg:address":"14 Beaumont Rd",
    "sg:city":"Birmingham",
    "sg:classifiers":[
        {
            "category":"Personal",
            "type":"Services"
        }
    ],
    "sg:phone":"+44 121 433 5666",
    "sg:postcode":"B30 2DY",
    "sg:province":"West Midlands",
    "sg:tags":[
        "wedding"
    ],
    "wof:name":"Touch Of Elegance",
    "wof:placetype":"venue"
},
  "geometry": {"coordinates":[-1.9297100306,52.4247131348],"type":"Point"}
}