{
  "type": "Feature",
  "properties": {
    "addr:full":"59 Catherine Street St Albans Hertfordshire AL3 5BN",
    "addr:housenumber":"59",
    "addr:postcode":"al3 5bn",
    "addr:street":"Catherine Street",
    "iso:country":"GB",
    "sg:address":"59 Catherine Street",
    "sg:city":"St Albans",
    "sg:classifiers":[
        {
            "category":"Food & Beverages",
            "subcategory":"Bakery",
            "type":"Retail Goods"
        },
        {
            "category":"Bakery",
            "type":"Food & Drink"
        }
    ],
    "sg:phone":"+44 1727 854405",
    "sg:postcode":"AL3 5BN",
    "sg:province":"Hertfordshire",
    "sg:tags":[
        "cake",
        "baker",
        "maker"
    ],
    "wof:name":"Ushers Cakes",
    "wof:placetype":"venue"
},
  "geometry": {"coordinates":[-0.3387129903,51.7558746338],"type":"Point"}
}