{
  "type": "Feature",
  "properties": {
    "iso:country":"GB",
    "sg:address":"56 Poole Road",
    "sg:city":"Bournemouth",
    "sg:classifiers":[
        {
            "category":"Food & Beverages",
            "subcategory":"Meat & Fish",
            "type":"Retail Goods"
        }
    ],
    "sg:phone":"+44 1202 763437",
    "sg:postcode":"BH4 9DZ",
    "sg:province":"Dorset",
    "sg:tags":[
        "butcher"
    ],
    "wof:name":"Peter Treble",
    "wof:placetype":"venue"
},
  "geometry": {"coordinates":[-1.901888,50.72295],"type":"Point"}
}