{
  "type": "Feature",
  "properties": {
    "iso:country":"GB",
    "sg:address":"174 Southworth Rd",
    "sg:city":"Newton-le-willows",
    "sg:classifiers":[
        {
            "category":"Shopping",
            "subcategory":"Gifts & Souvenirs",
            "type":"Retail Goods"
        }
    ],
    "sg:postcode":"WA12 0BS",
    "sg:province":"Cheshire",
    "sg:tags":[
        "christmas"
    ],
    "wof:name":"Withers,M",
    "wof:placetype":"venue"
},
  "geometry": {"coordinates":[-2.6052589417,53.455581665],"type":"Point"}
}