{
  "type": "Feature",
  "properties": {
    "addr:full":"42 Rainham Road Rainham Essex RM13 7RL",
    "addr:housenumber":"42",
    "addr:postcode":"rm13 7rl",
    "addr:street":"Rainham Road",
    "iso:country":"GB",
    "sg:address":"42 Rainham Road",
    "sg:city":"Rainham",
    "sg:classifiers":[
        {
            "category":"Health Services",
            "subcategory":"Clinic",
            "type":"Services"
        }
    ],
    "sg:postcode":"RM13 7RL",
    "sg:province":"Essex",
    "sg:tags":[
        "aromatherapy"
    ],
    "wof:name":"D Wilkins",
    "wof:placetype":"venue"
},
  "geometry": {"coordinates":[0.191429,51.528133],"type":"Point"}
}