{
  "type": "Feature",
  "properties": {
    "addr:full":"Unit 37 Taunton Trading Estate, Norton Fitzwarren Taunton Somerset TA2 6RX",
    "addr:housenumber":"unit 37;estate",
    "addr:postcode":"ta2 6rx",
    "addr:street":"Trading;Fitzwarren",
    "iso:country":"GB",
    "sg:address":"Unit 37 Taunton Trading Estate, Norton Fitzwarren",
    "sg:city":"Taunton",
    "sg:classifiers":[
        {
            "category":"Government",
            "subcategory":"Post Office",
            "type":"Public Place"
        }
    ],
    "sg:phone":"+44 1823 253534",
    "sg:postcode":"TA2 6RX",
    "sg:province":"Somerset",
    "sg:tags":[
        "messenger",
        "courier"
    ],
    "wof:name":"Nightspeed",
    "wof:placetype":"venue"
},
  "geometry": {"coordinates":[-3.137962,51.029549],"type":"Point"}
}