{
  "type": "Feature",
  "properties": {
    "addr:full":"Quarry Cottage, The Village, Hartlebury Kidderminster Staffordshire DY11 7TE",
    "addr:postcode":"dy11 7te",
    "addr:street":"The",
    "iso:country":"GB",
    "sg:address":"Quarry Cottage, The Village, Hartlebury",
    "sg:city":"Kidderminster",
    "sg:classifiers":[
        {
            "category":"Professional",
            "type":"Services"
        }
    ],
    "sg:phone":"+44 1299 251458",
    "sg:postcode":"DY11 7TE",
    "sg:province":"Staffordshire",
    "sg:tags":[
        "auctioneer"
    ],
    "wof:name":"Rowley M J",
    "wof:placetype":"venue"
},
  "geometry": {"coordinates":[-2.236529,52.336182],"type":"Point"}
}