{
  "type": "Feature",
  "properties": {
    "addr:full":"34 Thistlewaite Rd Clapton Greater London E5 0QQ",
    "addr:housenumber":"34",
    "addr:postcode":"e5 0qq",
    "addr:street":"Thistlewaite Rd",
    "iso:country":"GB",
    "sg:address":"34 Thistlewaite Rd",
    "sg:city":"Clapton",
    "sg:classifiers":[
        {
            "category":"Professional",
            "type":"Services"
        }
    ],
    "sg:phone":"+44 20 8533 1372",
    "sg:postcode":"E5 0QQ",
    "sg:province":"Greater London",
    "sg:tags":[
        "entertainer"
    ],
    "wof:name":"Lively Sounds",
    "wof:placetype":"venue"
},
  "geometry": {"coordinates":[-0.0541590005,51.5577049255],"type":"Point"}
}