{
  "type": "Feature",
  "properties": {
    "addr:full":"Glasgow St, Thornaby Stockton-on-tees Durham TS17 7AH",
    "addr:postcode":"ts17 7ah",
    "addr:street":"Glasgow St",
    "iso:country":"GB",
    "sg:address":"Glasgow St, Thornaby",
    "sg:city":"Stockton-on-tees",
    "sg:classifiers":[
        {
            "category":"Cafe",
            "type":"Food & Drink"
        }
    ],
    "sg:postcode":"TS17 7AH",
    "sg:province":"Durham",
    "sg:tags":[
        "tea",
        "room"
    ],
    "wof:name":"Bon Lea Cafe (The)",
    "wof:placetype":"venue"
},
  "geometry": {"coordinates":[-1.29864,54.558067],"type":"Point"}
}