{
  "type": "Feature",
  "properties": {
    "addr:full":"37 Repington Rd Tamworth Staffordshire B77 4AA",
    "addr:housenumber":"37",
    "addr:postcode":"b77 4aa",
    "addr:street":"Repington Rd",
    "iso:country":"GB",
    "sg:address":"37 Repington Rd",
    "sg:city":"Tamworth",
    "sg:classifiers":[
        {
            "category":"Professional",
            "subcategory":"Art Services",
            "type":"Services"
        }
    ],
    "sg:phone":"+44 1827 69677",
    "sg:postcode":"B77 4AA",
    "sg:province":"Staffordshire",
    "sg:tags":[
        "consultant",
        "design"
    ],
    "wof:name":"Task Design & Build",
    "wof:placetype":"venue"
},
  "geometry": {"coordinates":[-1.6543890238,52.6371574402],"type":"Point"}
}