{
  "type": "Feature",
  "properties": {
    "addr:full":"148 Westpole Avenue, Cockfosters Barnet Hertfordshire EN4 0AR",
    "addr:housenumber":"148",
    "addr:postcode":"en4 0ar",
    "addr:street":"Westpole Avenue",
    "iso:country":"GB",
    "sg:address":"148 Westpole Avenue, Cockfosters",
    "sg:city":"Barnet",
    "sg:classifiers":[
        {
            "category":"Home & Garden",
            "subcategory":"Carpets & Floor Coverings",
            "type":"Retail Goods"
        }
    ],
    "sg:postcode":"EN4 0AR",
    "sg:province":"Hertfordshire",
    "sg:tags":[
        "carpets",
        "rug",
        "matting"
    ],
    "wof:name":"Evermore Carpet Co",
    "wof:placetype":"venue"
},
  "geometry": {"coordinates":[-0.1476110071,51.6497268677],"type":"Point"}
}