{
  "type": "Feature",
  "properties": {
    "iso:country":"GB",
    "sg:address":"100 Constitution Street",
    "sg:city":"Edinburgh",
    "sg:classifiers":[
        {
            "category":"Utilities",
            "type":"Services"
        }
    ],
    "sg:phone":"+44 131 454 3310",
    "sg:postcode":"EH6 6AW",
    "sg:province":"City of Edinburgh",
    "sg:tags":[
        "internet"
    ],
    "wof:name":"Web Advertising Ltd.",
    "wof:placetype":"venue"
},
  "geometry": {"coordinates":[-3.167329,55.97459],"type":"Point"}
}