{
  "type": "Feature",
  "properties": {
    "addr:full":"11 Segsbury Gro, Harmanswater Bracknell Berkshire RG12 9JL",
    "addr:housenumber":"11",
    "addr:postcode":"rg12 9jl",
    "addr:street":"Segsbury Gro Harmanswater",
    "iso:country":"GB",
    "sg:address":"11 Segsbury Gro, Harmanswater",
    "sg:city":"Bracknell",
    "sg:classifiers":[
        {
            "category":"Professional",
            "subcategory":"Computer Services",
            "type":"Services"
        }
    ],
    "sg:phone":"+44 1344 642300",
    "sg:postcode":"RG12 9JL",
    "sg:province":"Berkshire",
    "sg:tags":[
        "aided",
        "design"
    ],
    "wof:name":"R S Designs",
    "wof:placetype":"venue"
},
  "geometry": {"coordinates":[-0.728018,51.405403],"type":"Point"}
}