{
  "type": "Feature",
  "properties": {
    "iso:country":"GB",
    "sg:address":"Chickenley Mills",
    "sg:city":"Dewsbury",
    "sg:classifiers":[
        {
            "category":"Real Estate",
            "subcategory":"Real Estate Operator",
            "type":"Services"
        }
    ],
    "sg:phone":"+44 1924 463252",
    "sg:postcode":"WF12 8ND",
    "sg:province":"West Yorkshire",
    "sg:tags":[
        "letting",
        "agent"
    ],
    "wof:name":"Wilson Bros (Chickenley) Ltd.",
    "wof:placetype":"venue"
},
  "geometry": {"coordinates":[-1.599514,53.688274],"type":"Point"}
}