{
  "type": "Feature",
  "properties": {
    "addr:full":"Maxwood Road Galston East Ayrshire KA4 8JJ",
    "addr:postcode":"ka4 8jj",
    "addr:street":"Maxwood Road",
    "iso:country":"GB",
    "sg:address":"Maxwood Road",
    "sg:city":"Galston",
    "sg:classifiers":[
        {
            "category":"Wholesale",
            "subcategory":"Non-durable Goods",
            "type":"Manufacturing & Wholesale Goods"
        },
        {
            "category":"Fast Food",
            "type":"Food & Drink"
        }
    ],
    "sg:phone":"+44 1563 820484",
    "sg:postcode":"KA4 8JJ",
    "sg:province":"East Ayrshire",
    "sg:tags":[
        "frozen",
        "carry",
        "cash"
    ],
    "wof:name":"Snowking Ltd.",
    "wof:placetype":"venue"
},
  "geometry": {"coordinates":[-4.3751587868,55.6006851196],"type":"Point"}
}