{
  "type": "Feature",
  "properties": {
    "iso:country":"GB",
    "sg:address":"Unit 5 Chunnel Industrial Estate, Victoria Road",
    "sg:city":"Ashford",
    "sg:classifiers":[
        {
            "category":"Wholesale",
            "subcategory":"Machinery & Supplies",
            "type":"Manufacturing & Wholesale Goods"
        },
        {
            "category":"Building & Trades",
            "subcategory":"Equipment Rental",
            "type":"Services"
        },
        {
            "category":"Professional",
            "subcategory":"Printing & Photocopies",
            "type":"Services"
        }
    ],
    "sg:phone":"+44 1233 624461",
    "sg:postcode":"TN23 7HJ",
    "sg:province":"Kent",
    "sg:tags":[
        "plate",
        "plant",
        "tool",
        "lithographic",
        "hire",
        "pump",
        "maker"
    ],
    "sg:website":"http://www.andrews-sykes.com",
    "wof:name":"Andrews Sykes Hire Ltd",
    "wof:placetype":"venue"
},
  "geometry": {"coordinates":[0.876037,51.146633],"type":"Point"}
}