{
  "type": "Feature",
  "properties": {
    "iso:country":"GB",
    "sg:address":"31-35 Pitfield Street",
    "sg:city":"London",
    "sg:classifiers":[
        {
            "category":"Professional",
            "subcategory":"Management & Consulting",
            "type":"Services"
        }
    ],
    "sg:postcode":"N1 6HB",
    "sg:province":"Greater London",
    "sg:tags":[
        "consultant",
        "business"
    ],
    "wof:name":"The Association of Co  Directors",
    "wof:placetype":"venue"
},
  "geometry": {"coordinates":[-0.083867,51.527252],"type":"Point"}
}