{
  "type": "Feature",
  "properties": {
    "addr:full":"Unit 3 Foundry House, Foundry Square Hayle Cornwall TR27 4HH",
    "addr:housenumber":"unit 3",
    "addr:postcode":"tr27 4hh",
    "iso:country":"GB",
    "sg:address":"Unit 3 Foundry House, Foundry Square",
    "sg:city":"Hayle",
    "sg:classifiers":[
        {
            "category":"Cinema",
            "subcategory":"Movie Rental",
            "type":"Entertainment"
        }
    ],
    "sg:phone":"+44 1736 752720",
    "sg:postcode":"TR27 4HH",
    "sg:province":"Cornwall",
    "sg:tags":[
        "video",
        "library"
    ],
    "wof:name":"Video View",
    "wof:placetype":"venue"
},
  "geometry": {"coordinates":[-5.421143055,50.1836738586],"type":"Point"}
}