{
  "type": "Feature",
  "properties": {
    "addr:full":"141 West St, Bedminster Bristol City of Bristol BS3 3PD",
    "addr:housenumber":"141",
    "addr:postcode":"bs3 3pd",
    "addr:street":"West St",
    "iso:country":"GB",
    "sg:address":"141 West St, Bedminster",
    "sg:city":"Bristol",
    "sg:classifiers":[
        {
            "category":"Fast Food",
            "type":"Food & Drink"
        }
    ],
    "sg:postcode":"BS3 3PD",
    "sg:province":"City of Bristol",
    "sg:tags":[
        "away",
        "take"
    ],
    "wof:name":"Southern Fried Chicken",
    "wof:placetype":"venue"
},
  "geometry": {"coordinates":[-2.605512,51.436428],"type":"Point"}
}