{
  "type": "Feature",
  "properties": {
    "addr:full":"6 West Craibstone Street Aberdeen Aberdeen City AB11 6DL",
    "addr:housenumber":"6",
    "addr:postcode":"ab11 6dl",
    "addr:street":"West Craibstone Street",
    "iso:country":"GB",
    "sg:address":"6 West Craibstone Street",
    "sg:city":"Aberdeen",
    "sg:classifiers":[
        {
            "category":"Professional",
            "subcategory":"Management & Consulting",
            "type":"Services"
        }
    ],
    "sg:phone":"+44 1224 577950",
    "sg:postcode":"AB11 6DL",
    "sg:province":"Aberdeen City",
    "sg:tags":[
        "consultant",
        "safety"
    ],
    "wof:name":"Risx Ltd.",
    "wof:placetype":"venue"
},
  "geometry": {"coordinates":[-2.107465,57.142731],"type":"Point"}
}