{
  "type": "Feature",
  "properties": {
    "addr:full":"3 Betts Avenue, Martlesham Heath Ipswich Suffolk IP5 3RH",
    "addr:housenumber":"3",
    "addr:postcode":"ip5 3rh",
    "addr:street":"Betts Avenue",
    "iso:country":"GB",
    "sg:address":"3 Betts Avenue, Martlesham Heath",
    "sg:city":"Ipswich",
    "sg:classifiers":[
        {
            "category":"Shopping",
            "type":"Retail Goods"
        }
    ],
    "sg:phone":"+44 1473 623995",
    "sg:postcode":"IP5 3RH",
    "sg:province":"Suffolk",
    "sg:tags":[
        "med",
        "scientific",
        "apparatus"
    ],
    "wof:name":"Northern Biological Supplies Ltd.",
    "wof:placetype":"venue"
},
  "geometry": {"coordinates":[1.27994,52.061626],"type":"Point"}
}