{
  "type": "Feature",
  "properties": {
    "iso:country":"GB",
    "sg:address":"Binnswood View, Business Centre, Oakhanger",
    "sg:city":"Bordon",
    "sg:classifiers":[
        {
            "category":"Shopping",
            "subcategory":"Computers & Home Electronics",
            "type":"Retail Goods"
        }
    ],
    "sg:phone":"+44 1420 477686",
    "sg:postcode":"GU35 9JW",
    "sg:province":"Hampshire",
    "sg:tags":[
        "aerial",
        "television",
        "radio"
    ],
    "wof:name":"Alton Aerials",
    "wof:placetype":"venue"
},
  "geometry": {"coordinates":[-0.865114,51.108856],"type":"Point"}
}