{
  "type": "Feature",
  "properties": {
    "addr:full":"93 Ealing Road Wembley Greater London HA0 4BN",
    "addr:housenumber":"93",
    "addr:postcode":"ha0 4bn",
    "addr:street":"Ealing Road",
    "iso:country":"GB",
    "sg:address":"93 Ealing Road",
    "sg:city":"Wembley",
    "sg:classifiers":[
        {
            "category":"Health Services",
            "subcategory":"Dentist",
            "type":"Services"
        }
    ],
    "sg:phone":"+44 20 8903 1580",
    "sg:postcode":"HA0 4BN",
    "sg:province":"Greater London",
    "wof:name":"Dental Surgery",
    "wof:placetype":"venue"
},
  "geometry": {"coordinates":[-0.2973560095,51.5464439392],"type":"Point"}
}