{
  "type": "Feature",
  "properties": {
    "addr:full":"St Martins House, 31-35 Clarendon Road Watford Hertfordshire WD17 1JF",
    "addr:housenumber":"31-35",
    "addr:postcode":"wd17 1jf",
    "addr:street":"Clarendon Road",
    "iso:country":"GB",
    "sg:address":"St Martins House, 31-35 Clarendon Road",
    "sg:city":"Watford",
    "sg:classifiers":[
        {
            "category":"Bars & Pubs",
            "type":"Food & Drink"
        }
    ],
    "sg:postcode":"WD17 1JF",
    "sg:province":"Hertfordshire",
    "sg:tags":[
        "pubs",
        "inn"
    ],
    "wof:name":"Sparaton Ltd",
    "wof:placetype":"venue"
},
  "geometry": {"coordinates":[-0.3971979916,51.6578788757],"type":"Point"}
}