{
  "type": "Feature",
  "properties": {
    "addr:full":"Colchester Road Romford Essex RM3 0AA",
    "addr:postcode":"rm3 0aa",
    "addr:street":"Colchester Road",
    "iso:country":"GB",
    "sg:address":"Colchester Road",
    "sg:city":"Romford",
    "sg:classifiers":[
        {
            "category":"Restaurant",
            "type":"Food & Drink"
        }
    ],
    "sg:phone":"+44 1708 342043",
    "sg:postcode":"RM3 0AA",
    "sg:province":"Essex",
    "wof:name":"The Plough",
    "wof:placetype":"venue"
},
  "geometry": {"coordinates":[0.23627,51.599648],"type":"Point"}
}