{
  "type": "Feature",
  "properties": {
    "addr:full":"31-35 Bar Hill Business Park, Saxon Way Cambridge Cambridgeshire CB3 8SL",
    "addr:housenumber":"31-35",
    "addr:postcode":"cb3 8sl",
    "addr:street":"Bar Hill Business Park Saxon Way",
    "iso:country":"GB",
    "sg:address":"31-35 Bar Hill Business Park, Saxon Way",
    "sg:city":"Cambridge",
    "sg:classifiers":[
        {
            "category":"Personal",
            "subcategory":"Tanning Parlor",
            "type":"Services"
        }
    ],
    "sg:phone":"+44 1954 782266",
    "sg:postcode":"CB3 8SL",
    "sg:province":"Cambridgeshire",
    "sg:tags":[
        "laser"
    ],
    "wof:name":"Perkinelmer Q-Arc Ltd.",
    "wof:placetype":"venue"
},
  "geometry": {"coordinates":[0.1115650013,52.2098693848],"type":"Point"}
}