{
  "type": "Feature",
  "properties": {
    "addr:full":"C/o Baines Corliss Chartered, Surveyors 29c Walton Road East Molesey Greater London KT8 0DH",
    "addr:housenumber":"/ o baines;29c",
    "addr:postcode":"kt8 0dh",
    "addr:street":"C;Walton Road",
    "iso:country":"GB",
    "sg:address":"C/o Baines Corliss Chartered, Surveyors 29c Walton Road",
    "sg:city":"East Molesey",
    "sg:classifiers":[
        {
            "category":"Organizations",
            "subcategory":"Membership Organization",
            "type":"Services"
        }
    ],
    "sg:postcode":"KT8 0DH",
    "sg:province":"Greater London",
    "sg:tags":[
        "club"
    ],
    "wof:name":"Selsdon Hill Place Residents Co  Ltd",
    "wof:placetype":"venue"
},
  "geometry": {"coordinates":[-0.3445410132,51.4019622803],"type":"Point"}
}