{
  "type": "Feature",
  "properties": {
    "addr:full":"Acre Business Park Reading Berkshire RG2 0SU",
    "addr:postcode":"rg2 0su",
    "iso:country":"GB",
    "sg:address":"Acre Business Park",
    "sg:city":"Reading",
    "sg:classifiers":[
        {
            "category":"Shopping",
            "subcategory":"Computers & Home Electronics",
            "type":"Retail Goods"
        }
    ],
    "sg:phone":"+44 118 975 8500",
    "sg:postcode":"RG2 0SU",
    "sg:province":"Berkshire",
    "sg:tags":[
        "aerial",
        "television",
        "radio"
    ],
    "wof:name":"Astral Aeriel Systems",
    "wof:placetype":"venue"
},
  "geometry": {"coordinates":[-0.9765599966,51.4234695435],"type":"Point"}
}