{
  "type": "Feature",
  "properties": {
    "iso:country":"GB",
    "sg:address":"5-7 Castle Street",
    "sg:city":"Clitheroe",
    "sg:classifiers":[
        {
            "category":"Real Estate",
            "subcategory":"Real Estate Agent",
            "type":"Services"
        }
    ],
    "sg:phone":"+44 1200 427331",
    "sg:postcode":"BB7 2BT",
    "sg:province":"Lancashire",
    "wof:name":"Mortimers",
    "wof:placetype":"venue"
},
  "geometry": {"coordinates":[-2.3924100399,53.8716659546],"type":"Point"}
}