{
  "type": "Feature",
  "properties": {
    "addr:full":"18 Hambro Close Rayleigh Essex SS6 8BZ",
    "addr:housenumber":"18",
    "addr:postcode":"ss6 8bz",
    "addr:street":"Hambro Close Rayleigh",
    "iso:country":"GB",
    "sg:address":"18 Hambro Close",
    "sg:city":"Rayleigh",
    "sg:classifiers":[
        {
            "category":"Home & Garden",
            "subcategory":"Carpets & Floor Coverings",
            "type":"Retail Goods"
        }
    ],
    "sg:postcode":"SS6 8BZ",
    "sg:province":"Essex",
    "sg:tags":[
        "cleaner",
        "upholstery"
    ],
    "wof:name":"Attack Professional Cleaning Services",
    "wof:placetype":"venue"
},
  "geometry": {"coordinates":[0.61768502,51.5960006714],"type":"Point"}
}