{
  "type": "Feature",
  "properties": {
    "iso:country":"GB",
    "sg:address":"Church Lane, Bugbrooke",
    "sg:city":"Northampton",
    "sg:classifiers":[
        {
            "category":"Home & Garden",
            "subcategory":"Building Materials",
            "type":"Retail Goods"
        }
    ],
    "sg:phone":"+44 1604 831988",
    "sg:postcode":"NN7 3PD",
    "sg:province":"Buckinghamshire",
    "sg:tags":[
        "polythene",
        "plastic"
    ],
    "wof:name":"JESUS FELLOWSHIP CATERING",
    "wof:placetype":"venue"
},
  "geometry": {"coordinates":[-1.010495,52.212185],"type":"Point"}
}