{
  "type": "Feature",
  "properties": {
    "iso:country":"GB",
    "sg:address":"61 Fife Road",
    "sg:city":"Kingston-upon-thames",
    "sg:classifiers":[
        {
            "category":"Real Estate",
            "subcategory":"Real Estate Agent",
            "type":"Services"
        }
    ],
    "sg:phone":"+44 20 8547 1066",
    "sg:postcode":"KT1 1SF",
    "sg:province":"Greater London",
    "wof:name":"Townings",
    "wof:placetype":"venue"
},
  "geometry": {"coordinates":[-0.301437,51.412315],"type":"Point"}
}