{
  "type": "Feature",
  "properties": {
    "addr:full":"25 Market Square, Potton Sandy Bedfordshire SG19 2NP",
    "addr:housenumber":"25",
    "addr:postcode":"sg19 2np",
    "addr:street":"Market Square",
    "iso:country":"GB",
    "sg:address":"25 Market Square, Potton",
    "sg:city":"Sandy",
    "sg:classifiers":[
        {
            "category":"Shopping",
            "subcategory":"News",
            "type":"Retail Goods"
        }
    ],
    "sg:phone":"+44 1767 260256",
    "sg:postcode":"SG19 2NP",
    "sg:province":"Bedfordshire",
    "sg:tags":[
        "newsagent"
    ],
    "wof:name":"Cox Newsagents",
    "wof:placetype":"venue"
},
  "geometry": {"coordinates":[-0.2140659988,52.1274223328],"type":"Point"}
}