{
  "type": "Feature",
  "properties": {
    "addr:full":"Unit 3, The Leys Bedford Bedfordshire LU7 9PU",
    "addr:housenumber":"unit 3",
    "addr:postcode":"lu7 9pu",
    "addr:street":"The Leys",
    "iso:country":"GB",
    "sg:address":"Unit 3, The Leys",
    "sg:city":"Bedford",
    "sg:classifiers":[
        {
            "category":"Shopping",
            "type":"Retail Goods"
        }
    ],
    "sg:postcode":"LU7 9PU",
    "sg:province":"Bedfordshire",
    "sg:tags":[
        "part",
        "accessory"
    ],
    "wof:name":"M Price",
    "wof:placetype":"venue"
},
  "geometry": {"coordinates":[-0.612039,51.899071],"type":"Point"}
}