{
  "type": "Feature",
  "properties": {
    "iso:country":"GB",
    "sg:address":"The Old Police Station, 4 Castle Street",
    "sg:city":"Aylesbury",
    "sg:classifiers":[
        {
            "category":"Professional",
            "subcategory":"Art Services",
            "type":"Services"
        }
    ],
    "sg:phone":"+44 1296 420133",
    "sg:postcode":"HP20 2RF",
    "sg:province":"Buckinghamshire",
    "sg:tags":[
        "graphic",
        "designer"
    ],
    "wof:name":"Broomfield Davies Moss Turner Ltd.",
    "wof:placetype":"venue"
},
  "geometry": {"coordinates":[-0.811864,51.818779],"type":"Point"}
}