{
  "type": "Feature",
  "properties": {
    "iso:country":"GB",
    "sg:address":"39 Garden Pl",
    "sg:city":"Houghton Le Spring",
    "sg:classifiers":[
        {
            "category":"Bus Charters",
            "type":"Transportation"
        }
    ],
    "sg:phone":"+44 191 584 8185",
    "sg:postcode":"DH4 7EH",
    "sg:province":"Durham",
    "sg:tags":[
        "hire",
        "coach"
    ],
    "wof:name":"Monument Travel",
    "wof:placetype":"venue"
},
  "geometry": {"coordinates":[-1.4885469675,54.8748168945],"type":"Point"}
}