{
  "type": "Feature",
  "properties": {
    "addr:full":"Carlton Road Sidcup Kent DA14 6AH",
    "addr:postcode":"da14 6ah",
    "addr:street":"Carlton Road",
    "iso:country":"GB",
    "sg:address":"Carlton Road",
    "sg:city":"Sidcup",
    "sg:classifiers":[
        {
            "category":"Social Services",
            "subcategory":"Adult Care",
            "type":"Services"
        }
    ],
    "sg:phone":"+44 20 8302 4619",
    "sg:postcode":"DA14 6AH",
    "sg:province":"Kent",
    "sg:tags":[
        "day",
        "centre"
    ],
    "wof:name":"Carlton Resource Centre",
    "wof:placetype":"venue"
},
  "geometry": {"coordinates":[0.0977649987,51.4230957031],"type":"Point"}
}