{
  "type": "Feature",
  "properties": {
    "iso:country":"GB",
    "sg:address":"30 High St, Apperknowle",
    "sg:city":"Dronfield",
    "sg:classifiers":[
        {
            "category":"Professional",
            "subcategory":"Detective & Security Services",
            "type":"Services"
        }
    ],
    "sg:phone":"+44 1246 417013",
    "sg:postcode":"S18 4BD",
    "sg:province":"Derbyshire",
    "sg:tags":[
        "car"
    ],
    "wof:name":"Secure Cars",
    "wof:placetype":"venue"
},
  "geometry": {"coordinates":[-1.4277080297,53.3003425598],"type":"Point"}
}