{
  "type": "Feature",
  "properties": {
    "iso:country":"GB",
    "sg:address":"Hartfield House, The Hanger, Headley",
    "sg:city":"Bordon",
    "sg:classifiers":[
        {
            "category":"Home & Garden",
            "subcategory":"Home Furnishings",
            "type":"Retail Goods"
        }
    ],
    "sg:phone":"+44 1428 713101",
    "sg:postcode":"GU35 8SQ",
    "sg:province":"Hampshire",
    "sg:tags":[
        "homefurnishings"
    ],
    "wof:name":"Colony",
    "wof:placetype":"venue"
},
  "geometry": {"coordinates":[-0.82079,51.119625],"type":"Point"}
}