{
  "type": "Feature",
  "properties": {
    "addr:full":"Pamwell Ho, Pennywell Rd Bristol City of Bristol BS5 0TX",
    "addr:postcode":"bs5 0tx",
    "addr:street":"Pennywell Rd",
    "iso:country":"GB",
    "sg:address":"Pamwell Ho, Pennywell Rd",
    "sg:city":"Bristol",
    "sg:classifiers":[
        {
            "category":"Government",
            "subcategory":"Office",
            "type":"Public Place"
        }
    ],
    "sg:postcode":"BS5 0TX",
    "sg:province":"City of Bristol",
    "sg:tags":[
        "central"
    ],
    "wof:name":"Scope Bristol",
    "wof:placetype":"venue"
},
  "geometry": {"coordinates":[-2.57627,51.462959],"type":"Point"}
}