{
  "type": "Feature",
  "properties": {
    "iso:country":"GB",
    "sg:address":"40 High Street, Navenby",
    "sg:city":"Lincoln",
    "sg:classifiers":[
        {
            "category":"Commercial Area",
            "type":"Public Place"
        },
        {
            "category":"Travel",
            "subcategory":"Travel Agent",
            "type":"Entertainment"
        },
        {
            "category":"Food & Beverages",
            "subcategory":"Fruits & Vegetables",
            "type":"Retail Goods"
        },
        {
            "category":"Food & Beverages",
            "subcategory":"Groceries & Convenience Stores",
            "type":"Retail Goods"
        }
    ],
    "sg:phone":"+44 1522 811659",
    "sg:postcode":"LN5 0DZ",
    "sg:province":"Lincolnshire",
    "sg:tags":[
        "shop",
        "greengrocer",
        "centre"
    ],
    "wof:name":"Lincoln Co-Operative Society Ltd.",
    "wof:placetype":"venue"
},
  "geometry": {"coordinates":[-0.633103,53.075256],"type":"Point"}
}