{
  "type": "Feature",
  "properties": {
    "addr:full":"90 Clapham Rd Brixton Greater London SW9 0JT",
    "addr:housenumber":"90",
    "addr:postcode":"sw9 0jt",
    "addr:street":"Clapham Rd",
    "iso:country":"GB",
    "sg:address":"90 Clapham Rd",
    "sg:city":"Brixton",
    "sg:classifiers":[
        {
            "category":"Government",
            "subcategory":"Office",
            "type":"Public Place"
        }
    ],
    "sg:phone":"+44 20 7793 0834",
    "sg:postcode":"SW9 0JT",
    "sg:province":"Greater London",
    "sg:tags":[
        "local"
    ],
    "wof:name":"ILPS-SOVA Through Care Partnership",
    "wof:placetype":"venue"
},
  "geometry": {"coordinates":[-0.1180479974,51.4764175415],"type":"Point"}
}