{
  "type": "Feature",
  "properties": {
    "iso:country":"GB",
    "sg:address":"711 Wilmslow Road",
    "sg:city":"Manchester",
    "sg:classifiers":[
        {
            "category":"Shopping",
            "subcategory":"News",
            "type":"Retail Goods"
        }
    ],
    "sg:phone":"+44 161 445 3182",
    "sg:postcode":"M20 6RE",
    "sg:province":"Greater Manchester",
    "sg:tags":[
        "newsagent"
    ],
    "wof:name":"Zayn News",
    "wof:placetype":"venue"
},
  "geometry": {"coordinates":[-2.2260990143,53.415851593],"type":"Point"}
}