{
  "type": "Feature",
  "properties": {
    "addr:full":"Rose-gyll Cottage, Rectory Rd Retford Nottinghamshire DN22 7AY",
    "addr:postcode":"dn22 7ay",
    "addr:street":"Rectory Rd",
    "iso:country":"GB",
    "sg:address":"Rose-gyll Cottage, Rectory Rd",
    "sg:city":"Retford",
    "sg:classifiers":[
        {
            "category":"Home & Garden",
            "subcategory":"Home Furnishings",
            "type":"Retail Goods"
        }
    ],
    "sg:phone":"+44 1777 705067",
    "sg:postcode":"DN22 7AY",
    "sg:province":"Nottinghamshire",
    "sg:tags":[
        "patio",
        "furniture"
    ],
    "wof:name":"Ivy Leaf Stonecraft",
    "wof:placetype":"venue"
},
  "geometry": {"coordinates":[-0.945728,53.325184],"type":"Point"}
}