{
  "type": "Feature",
  "properties": {
    "iso:country":"GB",
    "sg:address":"72 Grimsby Rd",
    "sg:city":"Cleethorpes",
    "sg:classifiers":[
        {
            "category":"Insurance",
            "subcategory":"Life Insurance",
            "type":"Services"
        }
    ],
    "sg:phone":"+44 1472 251711",
    "sg:postcode":"DN35 7DP",
    "sg:province":"Lincolnshire",
    "sg:tags":[
        "assurance"
    ],
    "wof:name":"Allenby & Todd",
    "wof:placetype":"venue"
},
  "geometry": {"coordinates":[-0.052929,53.570393],"type":"Point"}
}