{
  "type": "Feature",
  "properties": {
    "addr:full":"4-5 Market Parade, High Street, Ewell Epsom Surrey KT17 1SL",
    "addr:housenumber":"4-5",
    "addr:postcode":"kt17 1sl",
    "addr:street":"Market Parade High Street",
    "iso:country":"GB",
    "sg:address":"4-5 Market Parade, High Street, Ewell",
    "sg:city":"Epsom",
    "sg:classifiers":[
        {
            "category":"Government",
            "subcategory":"Post Office",
            "type":"Public Place"
        }
    ],
    "sg:phone":"+44 20 8393 1443",
    "sg:postcode":"KT17 1SL",
    "sg:province":"Surrey",
    "wof:name":"The Ewell High Street Post Office",
    "wof:placetype":"venue"
},
  "geometry": {"coordinates":[-0.249664,51.349918],"type":"Point"}
}