{
  "type": "Feature",
  "properties": {
    "iso:country":"GB",
    "sg:address":"71-75 Main Street",
    "sg:city":"Prestwick",
    "sg:classifiers":[
        {
            "category":"Bars & Pubs",
            "type":"Food & Drink"
        },
        {
            "category":"Community Center",
            "subcategory":"Social",
            "type":"Public Place"
        }
    ],
    "sg:phone":"+44 1292 479321",
    "sg:postcode":"KA9 1JN",
    "sg:province":"South Ayrshire",
    "sg:tags":[
        "pubs",
        "house",
        "inn",
        "activity"
    ],
    "wof:name":"Cafe Bonne",
    "wof:placetype":"venue"
},
  "geometry": {"coordinates":[-4.610748,55.50005],"type":"Point"}
}