{
  "type": "Feature",
  "properties": {
    "addr:full":"Llechwedd Slate Caverns Blaenau Ffestiniog Gwynedd LL41 3NB",
    "addr:postcode":"ll41 3nb",
    "iso:country":"GB",
    "sg:address":"Llechwedd Slate Caverns",
    "sg:city":"Blaenau Ffestiniog",
    "sg:classifiers":[
        {
            "category":"Mining & Drilling",
            "type":"Manufacturing & Wholesale Goods"
        },
        {
            "category":"Manufacturing",
            "subcategory":"Glass & Minerals",
            "type":"Manufacturing & Wholesale Goods"
        }
    ],
    "sg:phone":"+44 1766 830343",
    "sg:postcode":"LL41 3NB",
    "sg:province":"Gwynedd",
    "sg:tags":[
        "product",
        "chalk",
        "stone",
        "quarried",
        "slate"
    ],
    "sg:website":"http://www.llechwedd.co.uk",
    "wof:name":"Llechwedd Slate Products",
    "wof:placetype":"venue"
},
  "geometry": {"coordinates":[-3.9405050278,52.9953422546],"type":"Point"}
}