{
  "type": "Feature",
  "properties": {
    "iso:country":"GB",
    "sg:address":"4 Dale St",
    "sg:city":"Huddersfield",
    "sg:classifiers":[
        {
            "category":"Food & Beverages",
            "subcategory":"Bakery",
            "type":"Retail Goods"
        }
    ],
    "sg:phone":"+44 1484 640649",
    "sg:postcode":"HD3 4TG",
    "sg:province":"West Yorkshire",
    "sg:tags":[
        "confectionery"
    ],
    "wof:name":"Barretts",
    "wof:placetype":"venue"
},
  "geometry": {"coordinates":[-1.8313369751,53.643913269],"type":"Point"}
}