{
  "type": "Feature",
  "properties": {
    "iso:country":"GB",
    "sg:address":"37 Burnt Oak Broadway",
    "sg:city":"Edgware",
    "sg:classifiers":[
        {
            "category":"Retail",
            "subcategory":"Repair Shop",
            "type":"Services"
        }
    ],
    "sg:phone":"+44 20 8200 1600",
    "sg:postcode":"HA8 5JZ",
    "sg:province":"Greater London",
    "sg:tags":[
        "radio",
        "television",
        "video"
    ],
    "wof:name":"Burnt Oak Electronics",
    "wof:placetype":"venue"
},
  "geometry": {"coordinates":[-0.266687,51.599796],"type":"Point"}
}