{
  "type": "Feature",
  "properties": {
    "addr:full":"7 Castle Street High Wycombe Buckinghamshire HP13 6RZ",
    "addr:housenumber":"7",
    "addr:postcode":"hp13 6rz",
    "addr:street":"Castle Street",
    "iso:country":"GB",
    "sg:address":"7 Castle Street",
    "sg:city":"High Wycombe",
    "sg:classifiers":[
        {
            "category":"Professional",
            "subcategory":"Lawyer & Legal Services",
            "type":"Services"
        }
    ],
    "sg:phone":"+44 1494 511345",
    "sg:postcode":"HP13 6RZ",
    "sg:province":"Buckinghamshire",
    "sg:tags":[
        "solicitor"
    ],
    "wof:name":"Hodders Solicitors",
    "wof:placetype":"venue"
},
  "geometry": {"coordinates":[-0.749257,51.630234],"type":"Point"}
}