{
  "type": "Feature",
  "properties": {
    "addr:full":"Stokes Bay Gosport Hampshire PO12 2QT",
    "addr:postcode":"po12 2qt",
    "iso:country":"GB",
    "sg:address":"Stokes Bay",
    "sg:city":"Gosport",
    "sg:classifiers":[
        {
            "category":"Organizations",
            "subcategory":"Membership Organization",
            "type":"Services"
        }
    ],
    "sg:phone":"+44 23 9258 4541",
    "sg:postcode":"PO12 2QT",
    "sg:province":"Hampshire",
    "sg:tags":[
        "club"
    ],
    "wof:name":"Gosport & District Angling Club",
    "wof:placetype":"venue"
},
  "geometry": {"coordinates":[-1.167107,50.787197],"type":"Point"}
}