{
  "type": "Feature",
  "properties": {
    "iso:country":"GB",
    "sg:address":"25 Lindow St",
    "sg:city":"Sale",
    "sg:classifiers":[
        {
            "category":"Professional",
            "subcategory":"Printing & Photocopies",
            "type":"Services"
        }
    ],
    "sg:phone":"+44 161 962 0683",
    "sg:postcode":"M33 2PU",
    "sg:province":"Cheshire",
    "sg:tags":[
        "printer"
    ],
    "wof:name":"Rocket Print & Design",
    "wof:placetype":"venue"
},
  "geometry": {"coordinates":[-2.2916929722,53.418548584],"type":"Point"}
}