{
  "type": "Feature",
  "properties": {
    "iso:country":"GB",
    "sg:address":"42 Jubilee Street",
    "sg:city":"High Peak",
    "sg:classifiers":[
        {
            "category":"Building & Trades",
            "subcategory":"Construction",
            "type":"Services"
        }
    ],
    "sg:phone":"+44 1663 747995",
    "sg:postcode":"SK22 4NX",
    "sg:province":"Cheshire",
    "sg:tags":[
        "builder"
    ],
    "wof:name":"Christopher Goodwin",
    "wof:placetype":"venue"
},
  "geometry": {"coordinates":[-1.9952130318,53.3632278442],"type":"Point"}
}