{
  "type": "Feature",
  "properties": {
    "iso:country":"GB",
    "sg:address":"34 Holywell Hill",
    "sg:city":"St Albans",
    "sg:classifiers":[
        {
            "category":"Shopping",
            "subcategory":"Books",
            "type":"Retail Goods"
        }
    ],
    "sg:phone":"+44 1727 853984",
    "sg:postcode":"AL1 1DE",
    "sg:province":"Hertfordshire",
    "sg:tags":[
        "bookseller"
    ],
    "wof:name":"St.Albans Bookshop Ltd.",
    "wof:placetype":"venue"
},
  "geometry": {"coordinates":[-0.340472,51.750011],"type":"Point"}
}