{
  "type": "Feature",
  "properties": {
    "iso:country":"GB",
    "sg:address":"43a Fitzmaurice Road",
    "sg:city":"Christchurch",
    "sg:classifiers":[
        {
            "category":"Manufacturing",
            "subcategory":"Electronics",
            "type":"Manufacturing & Wholesale Goods"
        }
    ],
    "sg:postcode":"BH23 2DY",
    "sg:province":"Dorset",
    "sg:tags":[
        "control",
        "component",
        "-",
        "electronic"
    ],
    "wof:name":"Richard W Hussey",
    "wof:placetype":"venue"
},
  "geometry": {"coordinates":[-1.797623,50.74284],"type":"Point"}
}