{
  "type": "Feature",
  "properties": {
    "iso:country":"GB",
    "sg:address":"9 King Street",
    "sg:city":"Truro",
    "sg:classifiers":[
        {
            "category":"Travel",
            "subcategory":"Travel Agent",
            "type":"Entertainment"
        }
    ],
    "sg:phone":"+44 1872 279521",
    "sg:postcode":"TR1 2RE",
    "sg:province":"Cornwall",
    "wof:name":"Going Places",
    "wof:placetype":"venue"
},
  "geometry": {"coordinates":[-5.05195,50.263397],"type":"Point"}
}