{
  "type": "Feature",
  "properties": {
    "addr:full":"31 King Street Boston Lincolnshire PE21 8UU",
    "addr:housenumber":"31",
    "addr:postcode":"pe21 8uu",
    "addr:street":"King Street",
    "iso:country":"GB",
    "sg:address":"31 King Street",
    "sg:city":"Boston",
    "sg:classifiers":[
        {
            "category":"Banks & Credit Unions",
            "subcategory":"Bank",
            "type":"Services"
        }
    ],
    "sg:postcode":"PE21 8UU",
    "sg:province":"Lincolnshire",
    "sg:tags":[
        "stocktaking",
        "inventory"
    ],
    "wof:name":"Gwen Kenneally",
    "wof:placetype":"venue"
},
  "geometry": {"coordinates":[-0.030208,52.973675],"type":"Point"}
}