{
  "type": "Feature",
  "properties": {
    "iso:country":"GB",
    "sg:address":"143 Stratford Road",
    "sg:city":"Birmingham",
    "sg:classifiers":[
        {
            "category":"Military Area",
            "subcategory":"Air Force Base",
            "type":"Public Place"
        }
    ],
    "sg:phone":"+44 121 766 6688",
    "sg:postcode":"B11 1RD",
    "sg:province":"West Midlands",
    "sg:tags":[
        "taxi",
        "hire",
        "private"
    ],
    "wof:name":"Five Star Cabs",
    "wof:placetype":"venue"
},
  "geometry": {"coordinates":[-1.876908,52.463844],"type":"Point"}
}