{
  "type": "Feature",
  "properties": {
    "iso:country":"GB",
    "sg:address":"Bay 9, Fox's Industrial Estate, Holyoake Avenue",
    "sg:city":"Blackpool",
    "sg:classifiers":[
        {
            "category":"Communications",
            "subcategory":"Film & Video Production",
            "type":"Services"
        }
    ],
    "sg:phone":"+44 1253 358439",
    "sg:postcode":"FY2 0QX",
    "sg:province":"Lancashire",
    "sg:tags":[
        "curers",
        "bacon",
        "ham"
    ],
    "wof:name":"John Jackson (Bacon) Ltd.",
    "wof:placetype":"venue"
},
  "geometry": {"coordinates":[-3.02729,53.837391],"type":"Point"}
}