{
  "type": "Feature",
  "properties": {
    "addr:full":"5 Springwell Lane, Whetstone Leicester Leicestershire LE8 6LT",
    "addr:housenumber":"5",
    "addr:postcode":"le8 6lt",
    "addr:street":"Springwell Lane",
    "iso:country":"GB",
    "sg:address":"5 Springwell Lane, Whetstone",
    "sg:city":"Leicester",
    "sg:classifiers":[
        {
            "category":"Building & Trades",
            "subcategory":"Construction",
            "type":"Services"
        }
    ],
    "sg:phone":"+44 116 275 1455",
    "sg:postcode":"LE8 6LT",
    "sg:province":"Leicestershire",
    "sg:tags":[
        "roofing",
        "contracting"
    ],
    "wof:name":"B T  & R Broome Hall",
    "wof:placetype":"venue"
},
  "geometry": {"coordinates":[-1.1790930033,52.5605545044],"type":"Point"}
}