{
  "type": "Feature",
  "properties": {
    "iso:country":"GB",
    "sg:address":"7g2 The Leather Market, Weston Street",
    "sg:city":"London",
    "sg:classifiers":[
        {
            "category":"Professional",
            "subcategory":"Management & Consulting",
            "type":"Services"
        }
    ],
    "sg:phone":"+44 20 7407 4575",
    "sg:postcode":"SE1 3ER",
    "sg:province":"Greater London",
    "sg:tags":[
        "consultant",
        "business"
    ],
    "wof:name":"The Procedure Documentation Co. Ltd.",
    "wof:placetype":"venue"
},
  "geometry": {"coordinates":[-0.08446,51.500389],"type":"Point"}
}