{
  "type": "Feature",
  "properties": {
    "addr:full":"Units 13-14 Western Industrial Estate, Lon-y-llyn Caerphilly Caerphilly CF83 1BQ",
    "addr:housenumber":"units 13-14",
    "addr:postcode":"cf83 1bq",
    "addr:street":"Western Industrial",
    "iso:country":"GB",
    "sg:address":"Units 13-14 Western Industrial Estate, Lon-y-llyn",
    "sg:city":"Caerphilly",
    "sg:classifiers":[
        {
            "category":"Building & Trades",
            "subcategory":"Construction",
            "type":"Services"
        }
    ],
    "sg:phone":"+44 29 2088 3797",
    "sg:postcode":"CF83 1BQ",
    "sg:province":"Caerphilly",
    "sg:tags":[
        "roofing"
    ],
    "wof:name":"Rentokil Four Seasons Roofing",
    "wof:placetype":"venue"
},
  "geometry": {"coordinates":[-3.217728,51.576588],"type":"Point"}
}