{
  "type": "Feature",
  "properties": {
    "iso:country":"GB",
    "sg:address":"24 Lime Road",
    "sg:city":"Swanley",
    "sg:classifiers":[
        {
            "category":"Building & Trades",
            "subcategory":"Landscaping Services",
            "type":"Services"
        }
    ],
    "sg:phone":"+44 1322 294737",
    "sg:postcode":"BR8 7ED",
    "sg:province":"Kent",
    "sg:tags":[
        "landscape",
        "contractor"
    ],
    "wof:name":"A T Fencing Pitfield & Landscaping",
    "wof:placetype":"venue"
},
  "geometry": {"coordinates":[0.167058,51.397121],"type":"Point"}
}