{
  "type": "Feature",
  "properties": {
    "iso:country":"GB",
    "sg:address":"Unit 12/13",
    "sg:city":"Cwmbran",
    "sg:classifiers":[
        {
            "category":"Home & Garden",
            "subcategory":"Kitchen Supply",
            "type":"Retail Goods"
        }
    ],
    "sg:phone":"+44 1633 875895",
    "sg:postcode":"NP44 5AZ",
    "sg:province":"Monmouthshire",
    "sg:tags":[
        "equipment",
        "catering"
    ],
    "wof:name":"J J Blackburn & Co",
    "wof:placetype":"venue"
},
  "geometry": {"coordinates":[-3.0539040565,51.6527748108],"type":"Point"}
}