{
  "type": "Feature",
  "properties": {
    "iso:country":"GB",
    "sg:address":"121 Lawn Lane",
    "sg:city":"Hemel Hempstead",
    "sg:classifiers":[
        {
            "category":"Fast Food",
            "type":"Food & Drink"
        }
    ],
    "sg:postcode":"HP3 9HS",
    "sg:province":"Hertfordshire",
    "sg:tags":[
        "away",
        "take"
    ],
    "wof:name":"Kashmiri Xpress",
    "wof:placetype":"venue"
},
  "geometry": {"coordinates":[-0.468854,51.741901],"type":"Point"}
}