{
  "type": "Feature",
  "properties": {
    "addr:full":"London Road Hitchin Hertfordshire SG4 7NJ",
    "addr:postcode":"sg4 7nj",
    "addr:street":"London Road",
    "iso:country":"GB",
    "sg:address":"London Road",
    "sg:city":"Hitchin",
    "sg:classifiers":[
        {
            "category":"Retail",
            "subcategory":"Auto Repair",
            "type":"Services"
        }
    ],
    "sg:phone":"+44 1462 434301",
    "sg:postcode":"SG4 7NJ",
    "sg:province":"Hertfordshire",
    "sg:tags":[
        "modification",
        "garage"
    ],
    "wof:name":"Bob Howard Motor Repairs",
    "wof:placetype":"venue"
},
  "geometry": {"coordinates":[-0.270984,51.936775],"type":"Point"}
}