{
  "type": "Feature",
  "properties": {
    "iso:country":"GB",
    "sg:address":"1 St Annes Rd",
    "sg:city":"Reading",
    "sg:classifiers":[
        {
            "category":"Professional",
            "type":"Services"
        },
        {
            "category":"Casinos & Gambling",
            "type":"Entertainment"
        }
    ],
    "sg:phone":"+44 118 947 7170",
    "sg:postcode":"RG4 7PA",
    "sg:province":"Berkshire",
    "sg:tags":[
        "entertainer",
        "turf",
        "accountant",
        "bookmaker"
    ],
    "wof:name":"J STEELE",
    "wof:placetype":"venue"
},
  "geometry": {"coordinates":[-0.9782339931,51.4678726196],"type":"Point"}
}