{
  "type": "Feature",
  "properties": {
    "addr:full":"6 Ridgeside, Kirk Merrington Spennymoor Durham DL16 7HG",
    "addr:housenumber":"6",
    "addr:postcode":"dl16 7hg",
    "addr:street":"Ridgeside Kirk",
    "iso:country":"GB",
    "sg:address":"6 Ridgeside, Kirk Merrington",
    "sg:city":"Spennymoor",
    "sg:classifiers":[
        {
            "category":"Building & Trades",
            "subcategory":"Construction",
            "type":"Services"
        }
    ],
    "sg:postcode":"DL16 7HG",
    "sg:province":"Durham",
    "sg:tags":[
        "builder"
    ],
    "wof:name":"N J Tweedall",
    "wof:placetype":"venue"
},
  "geometry": {"coordinates":[-1.5970020294,54.6835632324],"type":"Point"}
}