{
  "type": "Feature",
  "properties": {
    "addr:full":"88 Bedminster Rd Bristol City of Bristol BS3 5NP",
    "addr:housenumber":"88",
    "addr:postcode":"bs3 5np",
    "addr:street":"Bedminster Rd",
    "iso:country":"GB",
    "sg:address":"88 Bedminster Rd",
    "sg:city":"Bristol",
    "sg:classifiers":[
        {
            "category":"Shopping",
            "subcategory":"Clothing, Apparel, & Fashions",
            "type":"Retail Goods"
        }
    ],
    "sg:phone":"+44 117 966 7176",
    "sg:postcode":"BS3 5NP",
    "sg:province":"City of Bristol",
    "sg:tags":[
        "workwear",
        "protective"
    ],
    "wof:name":"Bristol Safetyware",
    "wof:placetype":"venue"
},
  "geometry": {"coordinates":[-2.6036379337,51.4335708618],"type":"Point"}
}