{
  "type": "Feature",
  "properties": {
    "addr:full":"2-10 Archer House Britland Est, Northbourne Road Eastbourne East Sussex BN22 8PW",
    "addr:housenumber":"2-10",
    "addr:postcode":"bn22 8pw",
    "addr:street":"Archer House Britland Est Northbourne Road",
    "iso:country":"GB",
    "sg:address":"2-10 Archer House Britland Est, Northbourne Road",
    "sg:city":"Eastbourne",
    "sg:classifiers":[
        {
            "category":"Wholesale",
            "subcategory":"Books, Periodicals, & Newspapers",
            "type":"Manufacturing & Wholesale Goods"
        }
    ],
    "sg:phone":"+44 800 028 2165",
    "sg:postcode":"BN22 8PW",
    "sg:province":"East Sussex",
    "sg:tags":[
        "publishing"
    ],
    "wof:name":"Country Publications Ltd",
    "wof:placetype":"venue"
},
  "geometry": {"coordinates":[0.2988399863,50.7854995728],"type":"Point"}
}