{
  "type": "Feature",
  "properties": {
    "iso:country":"GB",
    "sg:address":"Coleshill Freight Terminal, Station Rd",
    "sg:city":"Birmingham",
    "sg:classifiers":[
        {
            "category":"Freight",
            "type":"Transportation"
        }
    ],
    "sg:phone":"+44 1675 466251",
    "sg:postcode":"B46 1JG",
    "sg:province":"Warwickshire",
    "sg:tags":[
        "haulage",
        "road"
    ],
    "wof:name":"Robert James Transport",
    "wof:placetype":"venue"
},
  "geometry": {"coordinates":[-1.707264,52.500317],"type":"Point"}
}