{
  "type": "Feature",
  "properties": {
    "iso:country":"GB",
    "sg:address":"Montpellier Terrace",
    "sg:city":"Cheltenham",
    "sg:classifiers":[
        {
            "category":"Autos & Motor Vehicles",
            "subcategory":"Fuel & Gas Station",
            "type":"Retail Goods"
        }
    ],
    "sg:postcode":"GL50 1XE",
    "sg:province":"Gloucestershire",
    "sg:tags":[
        "petrol",
        "filling"
    ],
    "wof:name":"Save Service Station",
    "wof:placetype":"venue"
},
  "geometry": {"coordinates":[-2.081114,51.894005],"type":"Point"}
}