{
  "type": "Feature",
  "properties": {
    "addr:full":"13 Langshaw Drive Clitheroe Lancashire BB7 1EY",
    "addr:housenumber":"13",
    "addr:postcode":"bb7 1ey",
    "addr:street":"Langshaw Drive",
    "iso:country":"GB",
    "sg:address":"13 Langshaw Drive",
    "sg:city":"Clitheroe",
    "sg:classifiers":[
        {
            "category":"Shopping",
            "subcategory":"Musical Instruments",
            "type":"Retail Goods"
        },
        {
            "category":"Transit Center",
            "subcategory":"Freight",
            "type":"Transportation"
        }
    ],
    "sg:phone":"+44 1200 442081",
    "sg:postcode":"BB7 1EY",
    "sg:province":"Lancashire",
    "sg:tags":[
        "piano",
        "tuning",
        "maintenance",
        "accessory"
    ],
    "wof:name":"Trevor Lord",
    "wof:placetype":"venue"
},
  "geometry": {"coordinates":[-2.388511,53.864948],"type":"Point"}
}