{
  "type": "Feature",
  "properties": {
    "iso:country":"GB",
    "sg:address":"196 Stratford Road, Shirley",
    "sg:city":"Solihull",
    "sg:classifiers":[
        {
            "category":"Shopping",
            "subcategory":"Bicycles & Sporting Goods",
            "type":"Retail Goods"
        }
    ],
    "sg:phone":"+44 121 744 5135",
    "sg:postcode":"B90 3AQ",
    "sg:province":"West Midlands",
    "sg:tags":[
        "equipment",
        "camping"
    ],
    "wof:name":"Shirley Army & Navy Stores",
    "wof:placetype":"venue"
},
  "geometry": {"coordinates":[-1.827693,52.41238],"type":"Point"}
}