{
  "type": "Feature",
  "properties": {
    "addr:full":"127 Tarring Road Worthing West Sussex BN11 4HE",
    "addr:housenumber":"127",
    "addr:postcode":"bn11 4he",
    "addr:street":"Tarring Road",
    "iso:country":"GB",
    "sg:address":"127 Tarring Road",
    "sg:city":"Worthing",
    "sg:classifiers":[
        {
            "category":"Manufacturing",
            "subcategory":"Metals",
            "type":"Manufacturing & Wholesale Goods"
        }
    ],
    "sg:phone":"+44 1903 239261",
    "sg:postcode":"BN11 4HE",
    "sg:province":"West Sussex",
    "sg:tags":[
        "heat",
        "-",
        "treatment"
    ],
    "wof:name":"A & S French Polishing",
    "wof:placetype":"venue"
},
  "geometry": {"coordinates":[-0.3848839998,50.8179740906],"type":"Point"}
}