{
  "type": "Feature",
  "properties": {
    "iso:country":"GB",
    "sg:address":"35 Jackson Road",
    "sg:city":"Scunthorpe",
    "sg:classifiers":[
        {
            "category":"Fast Food",
            "type":"Food & Drink"
        }
    ],
    "sg:phone":"+44 1724 860202",
    "sg:postcode":"DN15 8ET",
    "sg:province":"Lincolnshire",
    "sg:tags":[
        "away",
        "take"
    ],
    "wof:name":"Peter's Palace",
    "wof:placetype":"venue"
},
  "geometry": {"coordinates":[-0.663703,53.592266],"type":"Point"}
}