{
  "type": "Feature",
  "properties": {
    "addr:full":"24 Fitzroy Avenue, Kingsgate Broadstairs Kent CT10 3LS",
    "addr:housenumber":"24",
    "addr:postcode":"ct10 3ls",
    "addr:street":"Fitzroy Avenue Kingsgate",
    "iso:country":"GB",
    "sg:address":"24 Fitzroy Avenue, Kingsgate",
    "sg:city":"Broadstairs",
    "sg:classifiers":[
        {
            "category":"Professional",
            "subcategory":"Management & Consulting",
            "type":"Services"
        }
    ],
    "sg:phone":"+44 1843 862499",
    "sg:postcode":"CT10 3LS",
    "sg:province":"Kent",
    "sg:tags":[
        "consultant",
        "safety"
    ],
    "wof:name":"Kent Industrial Health",
    "wof:placetype":"venue"
},
  "geometry": {"coordinates":[1.434866,51.383606],"type":"Point"}
}