{
  "type": "Feature",
  "properties": {
    "addr:full":"Victoria Avenue Newport Newport NP19 8GF",
    "addr:postcode":"np19 8gf",
    "addr:street":"Victoria Avenue",
    "iso:country":"GB",
    "sg:address":"Victoria Avenue",
    "sg:city":"Newport",
    "sg:classifiers":[
        {
            "category":"Government",
            "subcategory":"Office",
            "type":"Public Place"
        },
        {
            "category":"Sports & Exercise",
            "subcategory":"Swimming Pool",
            "type":"Entertainment"
        }
    ],
    "sg:phone":"+44 1633 671820",
    "sg:postcode":"NP19 8GF",
    "sg:province":"Newport",
    "sg:tags":[
        "local"
    ],
    "wof:name":"Maindee Swimming Pool",
    "wof:placetype":"venue"
},
  "geometry": {"coordinates":[-2.9740040302,51.5941734314],"type":"Point"}
}