{
  "type": "Feature",
  "properties": {
    "iso:country":"GB",
    "sg:address":"14 Tuesday Market Pl",
    "sg:city":"King's Lynn",
    "sg:classifiers":[
        {
            "category":"Ferry",
            "type":"Transportation"
        }
    ],
    "sg:phone":"+44 1553 766739",
    "sg:postcode":"PE30 1JN",
    "sg:province":"Norfolk",
    "wof:name":"Washport Bunkering Service Ltd",
    "wof:placetype":"venue"
},
  "geometry": {"coordinates":[0.39462,52.756939],"type":"Point"}
}