{
  "type": "Feature",
  "properties": {
    "addr:full":"1 Kendal Steps, St Georges Fields London Greater London W2 2YE",
    "addr:housenumber":"1",
    "addr:postcode":"w2 2ye",
    "addr:street":"Kendal Steps St Georges Fields",
    "iso:country":"GB",
    "sg:address":"1 Kendal Steps, St Georges Fields",
    "sg:city":"London",
    "sg:classifiers":[
        {
            "category":"Real Estate",
            "subcategory":"Real Estate Operator",
            "type":"Services"
        },
        {
            "category":"Real Estate",
            "subcategory":"Real Estate Agent",
            "type":"Services"
        }
    ],
    "sg:phone":"+44 20 7723 7728",
    "sg:postcode":"W2 2YE",
    "sg:province":"Greater London",
    "sg:tags":[
        "letting"
    ],
    "wof:name":"St. George'S Fields (No. 2) Ltd",
    "wof:placetype":"venue"
},
  "geometry": {"coordinates":[-0.164997,51.513409],"type":"Point"}
}