{
  "type": "Feature",
  "properties": {
    "addr:full":"Gildor Ho, West St Leicester Leicestershire LE9 7EJ",
    "addr:postcode":"le9 7ej",
    "addr:street":"West St",
    "iso:country":"GB",
    "sg:address":"Gildor Ho, West St",
    "sg:city":"Leicester",
    "sg:classifiers":[
        {
            "category":"Professional",
            "subcategory":"Art Services",
            "type":"Services"
        }
    ],
    "sg:phone":"+44 1455 842248",
    "sg:postcode":"LE9 7EJ",
    "sg:province":"Leicestershire",
    "sg:tags":[
        "graphic",
        "designer"
    ],
    "wof:name":"Posiform",
    "wof:placetype":"venue"
},
  "geometry": {"coordinates":[-1.31145,52.57795],"type":"Point"}
}