{
  "type": "Feature",
  "properties": {
    "addr:full":"Newbarn Lane, Seer Grn Beaconsfield Buckinghamshire HP9 2QZ",
    "addr:postcode":"hp9 2qz",
    "addr:street":"Newbarn Lane;Grn",
    "iso:country":"GB",
    "sg:address":"Newbarn Lane, Seer Grn",
    "sg:city":"Beaconsfield",
    "sg:classifiers":[
        {
            "category":"Travel",
            "subcategory":"Hotels & Motels",
            "type":"Entertainment"
        }
    ],
    "sg:postcode":"HP9 2QZ",
    "sg:province":"Buckinghamshire",
    "sg:tags":[
        "house",
        "guest"
    ],
    "wof:name":"Highclere Farm",
    "wof:placetype":"venue"
},
  "geometry": {"coordinates":[-0.591341,51.62492],"type":"Point"}
}