{
  "type": "Feature",
  "properties": {
    "addr:full":"123 Tyers Street London Greater London SE11 5HS",
    "addr:housenumber":"123",
    "addr:postcode":"se11 5hs",
    "addr:street":"Tyers Street",
    "iso:country":"GB",
    "sg:address":"123 Tyers Street",
    "sg:city":"London",
    "sg:classifiers":[
        {
            "category":"Transit Center",
            "subcategory":"Passenger",
            "type":"Transportation"
        }
    ],
    "sg:phone":"+44 20 7587 1460",
    "sg:postcode":"SE11 5HS",
    "sg:province":"Greater London",
    "sg:tags":[
        "ship",
        "broker"
    ],
    "wof:name":"Canary - U K Service Ltd.",
    "wof:placetype":"venue"
},
  "geometry": {"coordinates":[-0.119015,51.48666],"type":"Point"}
}