{
  "type": "Feature",
  "properties": {
    "addr:full":"68 Downs View Bradford On Avon Wiltshire BA15 1PW",
    "addr:housenumber":"68",
    "addr:postcode":"ba15 1pw",
    "addr:street":"Downs View",
    "iso:country":"GB",
    "sg:address":"68 Downs View",
    "sg:city":"Bradford On Avon",
    "sg:classifiers":[
        {
            "category":"Professional",
            "subcategory":"Accounting & Tax Preparation",
            "type":"Services"
        }
    ],
    "sg:phone":"+44 1225 862014",
    "sg:postcode":"BA15 1PW",
    "sg:province":"Wiltshire",
    "sg:tags":[
        "accountant"
    ],
    "wof:name":"Brooklands Accountancy Services",
    "wof:placetype":"venue"
},
  "geometry": {"coordinates":[-2.261972,51.349552],"type":"Point"}
}