{
  "type": "Feature",
  "properties": {
    "addr:full":"225 Beckfield Lane, Acomb York North Yorkshire YO26 5PH",
    "addr:housenumber":"225",
    "addr:postcode":"yo26 5ph",
    "addr:street":"Beckfield Lane",
    "iso:country":"GB",
    "sg:address":"225 Beckfield Lane, Acomb",
    "sg:city":"York",
    "sg:classifiers":[
        {
            "category":"Recreation",
            "subcategory":"Dog Park",
            "type":"Entertainment"
        }
    ],
    "sg:postcode":"YO26 5PH",
    "sg:province":"North Yorkshire",
    "wof:name":"Clanestar Dog Grooming",
    "wof:placetype":"venue"
},
  "geometry": {"coordinates":[-1.134024,53.966667],"type":"Point"}
}