{
  "type": "Feature",
  "properties": {
    "addr:full":"Wymeswold Business Park, Wymeswold Lane Loughborough Leicestershire LE12 5TR",
    "addr:postcode":"le12 5tr",
    "addr:street":"Wymeswold Lane",
    "iso:country":"GB",
    "sg:address":"Wymeswold Business Park, Wymeswold Lane",
    "sg:city":"Loughborough",
    "sg:classifiers":[
        {
            "category":"Freight",
            "type":"Transportation"
        }
    ],
    "sg:postcode":"LE12 5TR",
    "sg:province":"Leicestershire",
    "sg:tags":[
        "overseas",
        "shipping",
        "removal"
    ],
    "wof:name":"C M Export Services",
    "wof:placetype":"venue"
},
  "geometry": {"coordinates":[-1.1186740398,52.7931251526],"type":"Point"}
}