{
  "type": "Feature",
  "properties": {
    "iso:country":"GB",
    "sg:address":"64 Catharine Street",
    "sg:city":"Cambridge",
    "sg:classifiers":[
        {
            "category":"Wholesale",
            "subcategory":"Groceries",
            "type":"Manufacturing & Wholesale Goods"
        }
    ],
    "sg:phone":"+44 1223 566998",
    "sg:postcode":"CB1 3AW",
    "sg:province":"Cambridgeshire",
    "sg:tags":[
        "sausage",
        "product"
    ],
    "wof:name":"B A Biggs & Son",
    "wof:placetype":"venue"
},
  "geometry": {"coordinates":[0.146213,52.198952],"type":"Point"}
}