{
  "type": "Feature",
  "properties": {
    "iso:country":"GB",
    "sg:address":"Advanced House, Water Lane",
    "sg:city":"Halifax",
    "sg:classifiers":[
        {
            "category":"Professional",
            "subcategory":"Computer Services",
            "type":"Services"
        }
    ],
    "sg:phone":"+44 1422 386000",
    "sg:postcode":"HX3 9HG",
    "sg:province":"West Yorkshire",
    "sg:tags":[
        "consultant"
    ],
    "wof:name":"Advanced Processing Ltd.",
    "wof:placetype":"venue"
},
  "geometry": {"coordinates":[-1.855568,53.717236],"type":"Point"}
}