{
  "type": "Feature",
  "properties": {
    "addr:full":"Widney Manor Road Solihull West Midlands B91 3JQ",
    "addr:postcode":"b91 3jq",
    "addr:street":"Widney Manor Road",
    "iso:country":"GB",
    "sg:address":"Widney Manor Road",
    "sg:city":"Solihull",
    "sg:classifiers":[
        {
            "category":"Retail",
            "subcategory":"Funeral Services",
            "type":"Services"
        }
    ],
    "sg:phone":"+44 121 744 7079",
    "sg:postcode":"B91 3JQ",
    "sg:province":"West Midlands",
    "sg:tags":[
        "cemetery",
        "crematorium"
    ],
    "wof:name":"Widney Manor Cemetery",
    "wof:placetype":"venue"
},
  "geometry": {"coordinates":[-1.775806,52.403065],"type":"Point"}
}