{
  "type": "Feature",
  "properties": {
    "addr:full":"455b New Cross Rd New Cross Greater London SE14 6TA",
    "addr:housenumber":"455b",
    "addr:postcode":"se14 6ta",
    "addr:street":"New Cross Rd New",
    "iso:country":"GB",
    "sg:address":"455b New Cross Rd",
    "sg:city":"New Cross",
    "sg:classifiers":[
        {
            "category":"Health Services",
            "subcategory":"Health Practitioner",
            "type":"Services"
        }
    ],
    "sg:phone":"+44 20 8469 0468",
    "sg:postcode":"SE14 6TA",
    "sg:province":"Greater London",
    "sg:tags":[
        "homoeopathic"
    ],
    "wof:name":"Agolo Homoeopathic Clinic",
    "wof:placetype":"venue"
},
  "geometry": {"coordinates":[-0.029663,51.475655],"type":"Point"}
}