{
  "type": "Feature",
  "properties": {
    "iso:country":"GB",
    "sg:address":"20 Centre Way, Locks Heath",
    "sg:city":"Southampton",
    "sg:classifiers":[
        {
            "category":"Food & Beverages",
            "subcategory":"Bakery",
            "type":"Retail Goods"
        }
    ],
    "sg:phone":"+44 1489 570585",
    "sg:postcode":"SO31 6DX",
    "sg:province":"Hampshire",
    "sg:tags":[
        "baker"
    ],
    "wof:name":"Soothills Ltd.",
    "wof:placetype":"venue"
},
  "geometry": {"coordinates":[-1.275157,50.862778],"type":"Point"}
}