{
  "type": "Feature",
  "properties": {
    "iso:country":"GB",
    "sg:address":"165-169 High Street",
    "sg:city":"Hounslow",
    "sg:classifiers":[
        {
            "category":"Shopping",
            "subcategory":"Department Store",
            "type":"Retail Goods"
        }
    ],
    "sg:phone":"+44 20 8570 4855",
    "sg:postcode":"TW3 1QL",
    "sg:province":"Greater London",
    "wof:name":"Primark",
    "wof:placetype":"venue"
},
  "geometry": {"coordinates":[-0.359348,51.469379],"type":"Point"}
}