{
  "type": "Feature",
  "properties": {
    "addr:full":"5 Alice St Bradford West Yorkshire BD8 7RT",
    "addr:housenumber":"5",
    "addr:postcode":"bd8 7rt",
    "addr:street":"Alice St",
    "iso:country":"GB",
    "sg:address":"5 Alice St",
    "sg:city":"Bradford",
    "sg:classifiers":[
        {
            "category":"Health Services",
            "subcategory":"Doctor",
            "type":"Services"
        }
    ],
    "sg:phone":"+44 1274 736996",
    "sg:postcode":"BD8 7RT",
    "sg:province":"West Yorkshire",
    "sg:tags":[
        "practitioners"
    ],
    "wof:name":"Dr Bindu",
    "wof:placetype":"venue"
},
  "geometry": {"coordinates":[-1.762927,53.801743],"type":"Point"}
}