{
  "type": "Feature",
  "properties": {
    "addr:full":"Putney Towpath London Greater London SW13 0DG",
    "addr:postcode":"sw13 0dg",
    "addr:street":"Putney Towpath",
    "iso:country":"GB",
    "sg:address":"Putney Towpath",
    "sg:city":"London",
    "sg:classifiers":[
        {
            "category":"Recreation",
            "subcategory":"Water Park",
            "type":"Entertainment"
        }
    ],
    "sg:phone":"+44 20 8788 9472",
    "sg:postcode":"SW13 0DG",
    "sg:province":"Greater London",
    "sg:tags":[
        "sport"
    ],
    "wof:name":"Barn Elms Boathouse",
    "wof:placetype":"venue"
},
  "geometry": {"coordinates":[-0.2389100045,51.475151062],"type":"Point"}
}