{
  "type": "Feature",
  "properties": {
    "iso:country":"GB",
    "sg:address":"1 Malvern Villas",
    "sg:city":"Bath",
    "sg:classifiers":[
        {
            "category":"Real Estate",
            "subcategory":"Architect",
            "type":"Services"
        }
    ],
    "sg:postcode":"BA1 5JS",
    "sg:province":"Bath and North East Somerset",
    "wof:name":"N Magniac Architects",
    "wof:placetype":"venue"
},
  "geometry": {"coordinates":[-2.352994,51.398518],"type":"Point"}
}