{
  "type": "Feature",
  "properties": {
    "addr:full":"329 Manchester Rd, Ince Wigan Lancashire WN2 2LA",
    "addr:housenumber":"329",
    "addr:postcode":"wn2 2la",
    "addr:street":"Manchester Rd",
    "iso:country":"GB",
    "sg:address":"329 Manchester Rd, Ince",
    "sg:city":"Wigan",
    "sg:classifiers":[
        {
            "category":"Bars & Pubs",
            "type":"Food & Drink"
        }
    ],
    "sg:postcode":"WN2 2LA",
    "sg:province":"Lancashire",
    "sg:tags":[
        "pubs",
        "inn"
    ],
    "wof:name":"Showstep Ltd",
    "wof:placetype":"venue"
},
  "geometry": {"coordinates":[-2.5977540016,53.5406913757],"type":"Point"}
}