{
  "type": "Feature",
  "properties": {
    "addr:full":"10 Treruffe Terrace Redruth Cornwall TR15 2PY",
    "addr:housenumber":"10",
    "addr:postcode":"tr15 2py",
    "addr:street":"Treruffe Terrace",
    "iso:country":"GB",
    "sg:address":"10 Treruffe Terrace",
    "sg:city":"Redruth",
    "sg:classifiers":[
        {
            "category":"Professional",
            "subcategory":"Testing Lab",
            "type":"Services"
        }
    ],
    "sg:postcode":"TR15 2PY",
    "sg:province":"Cornwall",
    "sg:tags":[
        "mot"
    ],
    "wof:name":"Harris Norman & Son",
    "wof:placetype":"venue"
},
  "geometry": {"coordinates":[-5.227279,50.231079],"type":"Point"}
}