{
  "type": "Feature",
  "properties": {
    "iso:country":"GB",
    "sg:address":"1 Hathaway Clo",
    "sg:city":"Salisbury",
    "sg:classifiers":[
        {
            "category":"Professional",
            "type":"Services"
        }
    ],
    "sg:phone":"+44 1722 503343",
    "sg:postcode":"SP1 3JT",
    "sg:province":"Wiltshire",
    "sg:tags":[
        "caterer"
    ],
    "wof:name":"Comtel",
    "wof:placetype":"venue"
},
  "geometry": {"coordinates":[-1.804639,51.084476],"type":"Point"}
}