{
  "type": "Feature",
  "properties": {
    "addr:full":"Units 9 Fairfield Industrial Estate, Taffs Well Cardiff Caerphilly CF15 8LA",
    "addr:housenumber":"units 9",
    "addr:postcode":"cf15 8la",
    "addr:street":"Fairfield Industrial Estate;Well",
    "iso:country":"GB",
    "sg:address":"Units 9 Fairfield Industrial Estate, Taffs Well",
    "sg:city":"Cardiff",
    "sg:classifiers":[
        {
            "category":"Social Services",
            "type":"Services"
        }
    ],
    "sg:phone":"+44 29 2081 1999",
    "sg:postcode":"CF15 8LA",
    "sg:province":"Caerphilly",
    "sg:tags":[
        "need",
        "disability",
        "special"
    ],
    "wof:name":"Serco Technology",
    "wof:placetype":"venue"
},
  "geometry": {"coordinates":[-3.262360096,51.5375595093],"type":"Point"}
}