{
  "type": "Feature",
  "properties": {
    "addr:full":"Moss House Farm, Great Plumpton Preston Lancashire PR4 3PE",
    "addr:postcode":"pr4 3pe",
    "addr:street":"Great",
    "iso:country":"GB",
    "sg:address":"Moss House Farm, Great Plumpton",
    "sg:city":"Preston",
    "sg:classifiers":[
        {
            "category":"Farming",
            "subcategory":"Livestock Farm",
            "type":"Manufacturing & Wholesale Goods"
        }
    ],
    "sg:phone":"+44 1772 684952",
    "sg:postcode":"PR4 3PE",
    "sg:province":"Lancashire",
    "sg:tags":[
        "others"
    ],
    "wof:name":"H C & J N Gardener",
    "wof:placetype":"venue"
},
  "geometry": {"coordinates":[-2.9329950809,53.792930603],"type":"Point"}
}