{
  "type": "Feature",
  "properties": {
    "addr:full":"38a Robertson Street Hastings East Sussex TN34 1HT",
    "addr:housenumber":"38a",
    "addr:postcode":"tn34 1ht",
    "addr:street":"Robertson Street",
    "iso:country":"GB",
    "sg:address":"38a Robertson Street",
    "sg:city":"Hastings",
    "sg:classifiers":[
        {
            "category":"Military Area",
            "subcategory":"Air Force Base",
            "type":"Public Place"
        }
    ],
    "sg:phone":"+44 1424 466466",
    "sg:postcode":"TN34 1HT",
    "sg:province":"East Sussex",
    "sg:tags":[
        "taxi",
        "hire",
        "private"
    ],
    "wof:name":"Phoenix Taxis",
    "wof:placetype":"venue"
},
  "geometry": {"coordinates":[0.5768380165,50.8550109863],"type":"Point"}
}