{
  "type": "Feature",
  "properties": {
    "iso:country":"GB",
    "sg:address":"1 Paradise Pl, Stoke",
    "sg:city":"Plymouth",
    "sg:classifiers":[
        {
            "category":"Bars & Pubs",
            "type":"Food & Drink"
        }
    ],
    "sg:postcode":"PL1 5QU",
    "sg:province":"Devon",
    "sg:tags":[
        "pubs",
        "inn"
    ],
    "wof:name":"Malone,A,",
    "wof:placetype":"venue"
},
  "geometry": {"coordinates":[-4.165794,50.37447],"type":"Point"}
}