{
  "type": "Feature",
  "properties": {
    "addr:full":"Unit 9, 747 Warwick Road Birmingham West Midlands B11 2HA",
    "addr:housenumber":"unit 9 747",
    "addr:postcode":"b11 2ha",
    "addr:street":"Warwick Road",
    "iso:country":"GB",
    "sg:address":"Unit 9, 747 Warwick Road",
    "sg:city":"Birmingham",
    "sg:classifiers":[
        {
            "category":"Home & Garden",
            "subcategory":"Hardware",
            "type":"Retail Goods"
        }
    ],
    "sg:postcode":"B11 2HA",
    "sg:province":"West Midlands",
    "sg:tags":[
        "heat",
        "mech",
        "exchanger"
    ],
    "wof:name":"Heat Exchanger Services",
    "wof:placetype":"venue"
},
  "geometry": {"coordinates":[-1.839518,52.452919],"type":"Point"}
}