{
  "type": "Feature",
  "properties": {
    "addr:full":"7 Bank Street Alloa Clackmannanshire FK10 1HP",
    "addr:housenumber":"7",
    "addr:postcode":"fk10 1hp",
    "addr:street":"Bank Street",
    "iso:country":"GB",
    "sg:address":"7 Bank Street",
    "sg:city":"Alloa",
    "sg:classifiers":[
        {
            "category":"Food & Beverages",
            "subcategory":"Meat & Fish",
            "type":"Retail Goods"
        }
    ],
    "sg:phone":"+44 1259 722096",
    "sg:postcode":"FK10 1HP",
    "sg:province":"Clackmannanshire",
    "sg:tags":[
        "butcher"
    ],
    "wof:name":"Andrew Wilson",
    "wof:placetype":"venue"
},
  "geometry": {"coordinates":[-3.7927110195,56.1141204834],"type":"Point"}
}