{
  "type": "Feature",
  "properties": {
    "addr:full":"Unit 2 Platts Eyot Hampton Greater London TW12 2HF",
    "addr:housenumber":"unit 2",
    "addr:postcode":"tw12 2hf",
    "iso:country":"GB",
    "sg:address":"Unit 2 Platts Eyot",
    "sg:city":"Hampton",
    "sg:classifiers":[
        {
            "category":"Professional",
            "type":"Services"
        }
    ],
    "sg:phone":"+44 20 8979 1568",
    "sg:postcode":"TW12 2HF",
    "sg:province":"Greater London",
    "sg:tags":[
        "marine"
    ],
    "wof:name":"T M P Group Ltd.",
    "wof:placetype":"venue"
},
  "geometry": {"coordinates":[-0.373679,51.417568],"type":"Point"}
}