{
  "type": "Feature",
  "properties": {
    "iso:country":"GB",
    "sg:address":"Higham Common Road, Barugh Grn",
    "sg:city":"Barnsley",
    "sg:classifiers":[
        {
            "category":"Education",
            "subcategory":"School",
            "type":"Public Place"
        }
    ],
    "sg:phone":"+44 1226 383800",
    "sg:postcode":"S75 1LD",
    "sg:province":"South Yorkshire",
    "sg:tags":[
        "local",
        "authority"
    ],
    "wof:name":"Barugh Green Primary School",
    "wof:placetype":"venue"
},
  "geometry": {"coordinates":[-1.532799,53.567684],"type":"Point"}
}