{
  "type": "Feature",
  "properties": {
    "iso:country":"GB",
    "sg:address":"117 Cannon Street",
    "sg:city":"London",
    "sg:classifiers":[
        {
            "category":"Banks & Credit Unions",
            "subcategory":"Bureau De Change",
            "type":"Services"
        },
        {
            "category":"Fast Food",
            "type":"Food & Drink"
        }
    ],
    "sg:postcode":"EC4N 5AX",
    "sg:province":"Greater London",
    "sg:tags":[
        "away",
        "take"
    ],
    "wof:name":"City Harvest",
    "wof:placetype":"venue"
},
  "geometry": {"coordinates":[-0.0926589966,51.5121498108],"type":"Point"}
}