{
  "type": "Feature",
  "properties": {
    "iso:country":"GB",
    "sg:address":"54 East Parade",
    "sg:city":"Harrogate",
    "sg:classifiers":[
        {
            "category":"Shopping",
            "subcategory":"Computers & Home Electronics",
            "type":"Retail Goods"
        },
        {
            "category":"Professional",
            "subcategory":"Computer Services",
            "type":"Services"
        }
    ],
    "sg:phone":"+44 1423 564685",
    "sg:postcode":"HG1 5LT",
    "sg:province":"North Yorkshire",
    "sg:tags":[
        "system",
        "software"
    ],
    "wof:name":"Plan-It Systems Ltd.",
    "wof:placetype":"venue"
},
  "geometry": {"coordinates":[-1.5310659409,53.996635437],"type":"Point"}
}