{
  "type": "Feature",
  "properties": {
    "addr:full":"Rectory, Congleton Rd Macclesfield Cheshire SK10 4TW",
    "addr:postcode":"sk10 4tw",
    "addr:street":"Congleton Rd",
    "iso:country":"GB",
    "sg:address":"Rectory, Congleton Rd",
    "sg:city":"Macclesfield",
    "sg:classifiers":[
        {
            "category":"Place Of Worship",
            "type":"Public Place"
        }
    ],
    "sg:phone":"+44 1625 583134",
    "sg:postcode":"SK10 4TW",
    "sg:province":"Cheshire",
    "wof:name":"St Marys Church",
    "wof:placetype":"venue"
},
  "geometry": {"coordinates":[-2.2345659733,53.2657470703],"type":"Point"}
}