{
  "type": "Feature",
  "properties": {
    "iso:country":"GB",
    "sg:address":"Riverbank House, Putney Bridge App",
    "sg:city":"London",
    "sg:classifiers":[
        {
            "category":"Wholesale",
            "subcategory":"Music Publishers",
            "type":"Manufacturing & Wholesale Goods"
        }
    ],
    "sg:phone":"+44 20 7371 0022",
    "sg:postcode":"SW6 3JD",
    "sg:province":"Greater London",
    "wof:name":"B M P- Broken Music Publishing (U K) Ltd.",
    "wof:placetype":"venue"
},
  "geometry": {"coordinates":[-0.211654,51.468048],"type":"Point"}
}