{
  "type": "Feature",
  "properties": {
    "addr:full":"149 Market Street St Andrews Fife KY16 9PF",
    "addr:housenumber":"149",
    "addr:postcode":"ky16 9pf",
    "addr:street":"Market Street",
    "iso:country":"GB",
    "sg:address":"149 Market Street",
    "sg:city":"St Andrews",
    "sg:classifiers":[
        {
            "category":"Professional",
            "subcategory":"Accounting & Tax Preparation",
            "type":"Services"
        }
    ],
    "sg:phone":"+44 1334 472255",
    "sg:postcode":"KY16 9PF",
    "sg:province":"Fife",
    "sg:tags":[
        "accountant",
        "chartered"
    ],
    "wof:name":"Henderson Black & Co.",
    "wof:placetype":"venue"
},
  "geometry": {"coordinates":[-2.798672,56.340553],"type":"Point"}
}