{
  "type": "Feature",
  "properties": {
    "iso:country":"GB",
    "sg:address":"53 Miller Street",
    "sg:city":"Glasgow",
    "sg:classifiers":[
        {
            "category":"Personal",
            "type":"Services"
        }
    ],
    "sg:postcode":"G1 1EB",
    "sg:province":"Glasgow City",
    "sg:tags":[
        "wedding"
    ],
    "wof:name":"Virginian Restaurant",
    "wof:placetype":"venue"
},
  "geometry": {"coordinates":[-4.251182,55.859154],"type":"Point"}
}