{
  "type": "Feature",
  "properties": {
    "addr:full":"Rowan Croft, Roman Road Dorking Surrey RH4 3EU",
    "addr:postcode":"rh4 3eu",
    "addr:street":"Roman Road",
    "iso:country":"GB",
    "sg:address":"Rowan Croft, Roman Road",
    "sg:city":"Dorking",
    "sg:classifiers":[
        {
            "category":"Professional",
            "subcategory":"Accounting & Tax Preparation",
            "type":"Services"
        }
    ],
    "sg:postcode":"RH4 3EU",
    "sg:province":"Surrey",
    "sg:tags":[
        "accountant"
    ],
    "wof:name":"C M Wiltshire & Co",
    "wof:placetype":"venue"
},
  "geometry": {"coordinates":[-0.332724005,51.2208251953],"type":"Point"}
}