{
  "type": "Feature",
  "properties": {
    "addr:full":"Trefigyn Quarry Cardigan Ceredigion SA43 3BL",
    "addr:postcode":"sa43 3bl",
    "addr:street":"Trefigyn Quarry Cardigan",
    "iso:country":"GB",
    "sg:address":"Trefigyn Quarry",
    "sg:city":"Cardigan",
    "sg:classifiers":[
        {
            "category":"Utilities",
            "subcategory":"Fuel Oil & Lpg",
            "type":"Services"
        }
    ],
    "sg:phone":"+44 1239 881282",
    "sg:postcode":"SA43 3BL",
    "sg:province":"Ceredigion",
    "sg:tags":[
        "distributor"
    ],
    "wof:name":"Olew Trefigin Oil",
    "wof:placetype":"venue"
},
  "geometry": {"coordinates":[-4.6550440788,52.0868682861],"type":"Point"}
}