{
  "type": "Feature",
  "properties": {
    "iso:country":"GB",
    "sg:address":"Elton Park Business Centre",
    "sg:city":"Ipswich",
    "sg:classifiers":[
        {
            "category":"Home & Garden",
            "subcategory":"Household Appliances",
            "type":"Retail Goods"
        }
    ],
    "sg:phone":"+44 1473 211713",
    "sg:postcode":"IP2 0DD",
    "sg:province":"Suffolk",
    "sg:tags":[
        "electrical"
    ],
    "wof:name":"Service Force",
    "wof:placetype":"venue"
},
  "geometry": {"coordinates":[1.1193350554,52.0569992065],"type":"Point"}
}