{
  "type": "Feature",
  "properties": {
    "addr:full":"111 Pondtail Road Horsham West Sussex RH12 5HT",
    "addr:housenumber":"111",
    "addr:postcode":"rh12 5ht",
    "addr:street":"Pondtail Road",
    "iso:country":"GB",
    "sg:address":"111 Pondtail Road",
    "sg:city":"Horsham",
    "sg:classifiers":[
        {
            "category":"Building & Trades",
            "subcategory":"Construction",
            "type":"Services"
        }
    ],
    "sg:postcode":"RH12 5HT",
    "sg:province":"West Sussex",
    "sg:tags":[
        "decorator",
        "painter"
    ],
    "wof:name":"Graham Decorating",
    "wof:placetype":"venue"
},
  "geometry": {"coordinates":[-0.3211050034,51.0838546753],"type":"Point"}
}