{
  "type": "Feature",
  "properties": {
    "addr:full":"Tadcaster House, Keytec 7 Park Kempton Road Pershore Worcestershire WR10 2TA",
    "addr:housenumber":"7",
    "addr:postcode":"wr10 2ta",
    "addr:street":"Keytec;Park Kempton Road",
    "iso:country":"GB",
    "sg:address":"Tadcaster House, Keytec 7 Park Kempton Road",
    "sg:city":"Pershore",
    "sg:classifiers":[
        {
            "category":"Utilities",
            "subcategory":"Electric",
            "type":"Services"
        }
    ],
    "sg:phone":"+44 870 011 1992",
    "sg:postcode":"WR10 2TA",
    "sg:province":"Worcestershire",
    "sg:tags":[
        "electricity"
    ],
    "wof:name":"Nortech Management Ltd.",
    "wof:placetype":"venue"
},
  "geometry": {"coordinates":[-2.079339,52.113766],"type":"Point"}
}