{
  "type": "Feature",
  "properties": {
    "addr:full":"The Manor House, Hockley Road, Wilnecote Tamworth Staffordshire B77 5EE",
    "addr:postcode":"b77 5ee",
    "addr:street":"Hockley Road",
    "iso:country":"GB",
    "sg:address":"The Manor House, Hockley Road, Wilnecote",
    "sg:city":"Tamworth",
    "sg:classifiers":[
        {
            "category":"Personal",
            "subcategory":"Barber",
            "type":"Services"
        }
    ],
    "sg:phone":"+44 1827 285759",
    "sg:postcode":"B77 5EE",
    "sg:province":"Staffordshire",
    "sg:tags":[
        "men's",
        "hairdresser"
    ],
    "wof:name":"The Squires",
    "wof:placetype":"venue"
},
  "geometry": {"coordinates":[-1.668369,52.598461],"type":"Point"}
}