{
  "type": "Feature",
  "properties": {
    "addr:full":"20 Back Road, Linton Cambridge Cambridgeshire CB1 6JF",
    "addr:housenumber":"20",
    "addr:postcode":"cb1 6jf",
    "addr:street":"Back Road",
    "iso:country":"GB",
    "sg:address":"20 Back Road, Linton",
    "sg:city":"Cambridge",
    "sg:classifiers":[
        {
            "category":"Social Services",
            "subcategory":"Job Training",
            "type":"Services"
        }
    ],
    "sg:phone":"+44 1223 890390",
    "sg:postcode":"CB1 6JF",
    "sg:province":"Cambridgeshire",
    "sg:tags":[
        "translator",
        "interpreter"
    ],
    "wof:name":"Oak Lodge Consulting Ltd.",
    "wof:placetype":"venue"
},
  "geometry": {"coordinates":[0.279683,52.100098],"type":"Point"}
}