{
  "type": "Feature",
  "properties": {
    "iso:country":"GB",
    "sg:address":"Unit 68, Gilwilly Road, Gilwilly Industrial Estate",
    "sg:city":"Penrith",
    "sg:classifiers":[
        {
            "category":"Autos & Motor Vehicles",
            "subcategory":"Fuel & Gas Station",
            "type":"Retail Goods"
        },
        {
            "category":"Retail",
            "subcategory":"Auto Repair",
            "type":"Services"
        }
    ],
    "sg:phone":"+44 1768 892444",
    "sg:postcode":"CA11 9BL",
    "sg:province":"Cumbria",
    "sg:tags":[
        "petrol",
        "garage",
        "pump",
        "related"
    ],
    "wof:name":"R M Pumps (Cumbria) Ltd.",
    "wof:placetype":"venue"
},
  "geometry": {"coordinates":[-2.7619490623,54.6670417786],"type":"Point"}
}