{
  "type": "Feature",
  "properties": {
    "iso:country":"GB",
    "sg:address":"41 Manasty Rd, Orton Southgate",
    "sg:city":"Peterborough",
    "sg:classifiers":[
        {
            "category":"Manufacturing",
            "subcategory":"Metals",
            "type":"Manufacturing & Wholesale Goods"
        }
    ],
    "sg:phone":"+44 1733 238271",
    "sg:postcode":"PE2 6UP",
    "sg:province":"Cambridgeshire",
    "sg:tags":[
        "industry",
        "f-m"
    ],
    "wof:name":"Signode Coil Master",
    "wof:placetype":"venue"
},
  "geometry": {"coordinates":[-0.3108139932,52.539981842],"type":"Point"}
}