{
  "type": "Feature",
  "properties": {
    "iso:country":"GB",
    "sg:address":"Unit 7 Exis Court, Veasey Close",
    "sg:city":"Nuneaton",
    "sg:classifiers":[
        {
            "category":"Professional",
            "subcategory":"Detective & Security Services",
            "type":"Services"
        }
    ],
    "sg:phone":"+44 24 7634 4130",
    "sg:postcode":"CV11 6RT",
    "sg:province":"Leicestershire",
    "sg:tags":[
        "activity"
    ],
    "wof:name":"Manor Security Ltd",
    "wof:placetype":"venue"
},
  "geometry": {"coordinates":[-1.4488840103,52.5159492493],"type":"Point"}
}