{
  "type": "Feature",
  "properties": {
    "addr:full":"14 The Durdans Basildon Essex SS16 6DA",
    "addr:housenumber":"14",
    "addr:postcode":"ss16 6da",
    "addr:street":"The Durdans",
    "iso:country":"GB",
    "sg:address":"14 The Durdans",
    "sg:city":"Basildon",
    "sg:classifiers":[
        {
            "category":"Professional",
            "subcategory":"Accounting & Tax Preparation",
            "type":"Services"
        }
    ],
    "sg:phone":"+44 1268 413845",
    "sg:postcode":"SS16 6DA",
    "sg:province":"Essex",
    "sg:tags":[
        "accountant"
    ],
    "wof:name":"D P Short & Co.",
    "wof:placetype":"venue"
},
  "geometry": {"coordinates":[0.417066,51.563507],"type":"Point"}
}