{
  "type": "Feature",
  "properties": {
    "addr:full":"17 Barbourne Road Worcester Worcestershire WR1 1RS",
    "addr:housenumber":"17",
    "addr:postcode":"wr1 1rs",
    "addr:street":"Barbourne Road",
    "iso:country":"GB",
    "sg:address":"17 Barbourne Road",
    "sg:city":"Worcester",
    "sg:classifiers":[
        {
            "category":"Real Estate",
            "subcategory":"Surveying",
            "type":"Services"
        }
    ],
    "sg:postcode":"WR1 1RS",
    "sg:province":"Worcestershire",
    "sg:tags":[
        "building",
        "surveyor"
    ],
    "wof:name":"Applied Surverying & Design Group",
    "wof:placetype":"venue"
},
  "geometry": {"coordinates":[-2.225992,52.202053],"type":"Point"}
}