{
  "type": "Feature",
  "properties": {
    "addr:full":"2 Duchess Close Alton Hampshire GU34 1PQ",
    "addr:housenumber":"2",
    "addr:postcode":"gu34 1pq",
    "addr:street":"Duchess Close",
    "iso:country":"GB",
    "sg:address":"2 Duchess Close",
    "sg:city":"Alton",
    "sg:classifiers":[
        {
            "category":"Manufacturing",
            "subcategory":"Metals",
            "type":"Manufacturing & Wholesale Goods"
        }
    ],
    "sg:phone":"+44 116 262 9499",
    "sg:postcode":"GU34 1PQ",
    "sg:province":"Hampshire",
    "sg:tags":[
        "industry",
        "f-a"
    ],
    "wof:name":"Regaldesign Ltd",
    "wof:placetype":"venue"
},
  "geometry": {"coordinates":[-0.98495,51.147247],"type":"Point"}
}