{
  "type": "Feature",
  "properties": {
    "addr:full":"202 Havant Road, Drayton Portsmouth Hampshire PO6 2EH",
    "addr:housenumber":"202",
    "addr:postcode":"hampshire po6 2eh",
    "addr:street":"Havant Road",
    "iso:country":"GB",
    "sg:address":"202 Havant Road, Drayton",
    "sg:city":"Portsmouth",
    "sg:classifiers":[
        {
            "category":"Building & Trades",
            "subcategory":"Plumbing",
            "type":"Services"
        },
        {
            "category":"Building & Trades",
            "subcategory":"Construction",
            "type":"Services"
        }
    ],
    "sg:phone":"+44 23 9232 4393",
    "sg:postcode":"PO6 2EH",
    "sg:province":"Hampshire",
    "sg:tags":[
        "suspended",
        "ceiling",
        "heating",
        "flooring"
    ],
    "wof:name":"S K Interiors Ltd",
    "wof:placetype":"venue"
},
  "geometry": {"coordinates":[-1.0496590137,50.8464317322],"type":"Point"}
}