{
  "type": "Feature",
  "properties": {
    "iso:country":"GB",
    "sg:address":"84 Commercial Street",
    "sg:city":"Newport",
    "sg:classifiers":[
        {
            "category":"Fast Food",
            "type":"Food & Drink"
        },
        {
            "category":"Restaurant",
            "type":"Food & Drink"
        }
    ],
    "sg:postcode":"NP20 1LS",
    "sg:province":"Newport",
    "sg:tags":[
        "away",
        "indian",
        "take"
    ],
    "wof:name":"The Grand Balti Tandoori",
    "wof:placetype":"venue"
},
  "geometry": {"coordinates":[-2.992872,51.583595],"type":"Point"}
}