{
  "type": "Feature",
  "properties": {
    "iso:country":"GB",
    "sg:address":"8 Mercer Row",
    "sg:city":"Louth",
    "sg:classifiers":[
        {
            "category":"Shopping",
            "subcategory":"Pets & Pet Supplies",
            "type":"Retail Goods"
        }
    ],
    "sg:phone":"+44 1507 603621",
    "sg:postcode":"LN11 9JQ",
    "sg:province":"Lincolnshire",
    "sg:tags":[
        "shop"
    ],
    "wof:name":"Potty About Pets",
    "wof:placetype":"venue"
},
  "geometry": {"coordinates":[-0.0061590001,53.3658561707],"type":"Point"}
}