{
  "type": "Feature",
  "properties": {
    "addr:full":"11 Gravesend Arbroath Angus DD11 1HT",
    "addr:housenumber":"11",
    "addr:postcode":"dd11 1ht",
    "addr:street":"Gravesend",
    "iso:country":"GB",
    "sg:address":"11 Gravesend",
    "sg:city":"Arbroath",
    "sg:classifiers":[
        {
            "category":"Autos & Motor Vehicles",
            "subcategory":"Auto Supplies",
            "type":"Retail Goods"
        },
        {
            "category":"Shopping",
            "type":"Retail Goods"
        }
    ],
    "sg:phone":"+44 1241 871718",
    "sg:postcode":"DD11 1HT",
    "sg:province":"Angus",
    "sg:tags":[
        "car",
        "part",
        "accessory"
    ],
    "wof:name":"Central Autoparts",
    "wof:placetype":"venue"
},
  "geometry": {"coordinates":[-2.5829899311,56.5590019226],"type":"Point"}
}