{
  "type": "Feature",
  "properties": {
    "iso:country":"GB",
    "sg:address":"188 Rainhill Road, Rainhill",
    "sg:city":"Prescot",
    "sg:classifiers":[
        {
            "category":"Professional",
            "type":"Services"
        },
        {
            "category":"Professional",
            "subcategory":"Business Services",
            "type":"Services"
        }
    ],
    "sg:phone":"+44 151 426 3999",
    "sg:postcode":"L35 4PL",
    "sg:province":"Cheshire",
    "sg:tags":[
        "shopfitting",
        "shopfitters",
        "contractor"
    ],
    "wof:name":"J B S Contracts Ltd",
    "wof:placetype":"venue"
},
  "geometry": {"coordinates":[-2.765682,53.419762],"type":"Point"}
}