{
  "type": "Feature",
  "properties": {
    "iso:country":"GB",
    "sg:address":"141 Victoria Road",
    "sg:city":"Aldershot",
    "sg:classifiers":[
        {
            "category":"Personal",
            "subcategory":"Barber",
            "type":"Services"
        }
    ],
    "sg:phone":"+44 1252 320426",
    "sg:postcode":"GU11 1JW",
    "sg:province":"Hampshire",
    "sg:tags":[
        "men's",
        "gents",
        "hairdresser"
    ],
    "wof:name":"His Hair",
    "wof:placetype":"venue"
},
  "geometry": {"coordinates":[-0.7646729946,51.2483482361],"type":"Point"}
}