{
  "type": "Feature",
  "properties": {
    "addr:full":"7 Westgate Otley North Yorkshire LS21 3AT",
    "addr:housenumber":"7",
    "addr:postcode":"ls21 3at",
    "addr:street":"Westgate",
    "iso:country":"GB",
    "sg:address":"7 Westgate",
    "sg:city":"Otley",
    "sg:classifiers":[
        {
            "category":"Professional",
            "subcategory":"Printing & Photocopies",
            "type":"Services"
        }
    ],
    "sg:phone":"+44 1943 462413",
    "sg:postcode":"LS21 3AT",
    "sg:province":"North Yorkshire",
    "sg:tags":[
        "trophy",
        "medal"
    ],
    "wof:name":"Dalsetter Trophies",
    "wof:placetype":"venue"
},
  "geometry": {"coordinates":[-1.6958730221,53.9054870605],"type":"Point"}
}