{
  "type": "Feature",
  "properties": {
    "addr:full":"1 Montpelier Road Plymouth Devon PL2 3LP",
    "addr:housenumber":"1",
    "addr:postcode":"pl2 3lp",
    "addr:street":"Montpelier Road",
    "iso:country":"GB",
    "sg:address":"1 Montpelier Road",
    "sg:city":"Plymouth",
    "sg:classifiers":[
        {
            "category":"Home & Garden",
            "subcategory":"Hardware",
            "type":"Retail Goods"
        }
    ],
    "sg:phone":"+44 1752 707529",
    "sg:postcode":"PL2 3LP",
    "sg:province":"Devon",
    "sg:tags":[
        "retailer",
        "diy"
    ],
    "wof:name":"Homebase",
    "wof:placetype":"venue"
},
  "geometry": {"coordinates":[-4.1517930031,50.393573761],"type":"Point"}
}