{
  "type": "Feature",
  "properties": {
    "addr:full":"1-7 Shirley Road, Acocks Grn Birmingham West Midlands B27 7XX",
    "addr:housenumber":"1-7",
    "addr:postcode":"b27 7xx",
    "addr:street":"Shirley Road Acocks Grn",
    "iso:country":"GB",
    "sg:address":"1-7 Shirley Road, Acocks Grn",
    "sg:city":"Birmingham",
    "sg:classifiers":[
        {
            "category":"Shopping",
            "subcategory":"Department Store",
            "type":"Retail Goods"
        }
    ],
    "sg:phone":"+44 121 706 1757",
    "sg:postcode":"B27 7XX",
    "sg:province":"West Midlands",
    "sg:tags":[
        "departmental"
    ],
    "wof:name":"Woolworths Plc",
    "wof:placetype":"venue"
},
  "geometry": {"coordinates":[-1.823579,52.44545],"type":"Point"}
}