{
  "type": "Feature",
  "properties": {
    "addr:full":"Lower Bristol Rd Bath Somerset BA2 3BN",
    "addr:postcode":"ba2 3bn",
    "addr:street":"Lower Bristol Rd",
    "iso:country":"GB",
    "sg:address":"Lower Bristol Rd",
    "sg:city":"Bath",
    "sg:classifiers":[
        {
            "category":"Autos & Motor Vehicles",
            "subcategory":"Auto Supplies",
            "type":"Retail Goods"
        }
    ],
    "sg:phone":"+44 1225 422294",
    "sg:postcode":"BA2 3BN",
    "sg:province":"Somerset",
    "sg:tags":[
        "tyre"
    ],
    "wof:name":"Motorway Tyre & Auto Centres",
    "wof:placetype":"venue"
},
  "geometry": {"coordinates":[-2.370584,51.379623],"type":"Point"}
}