{
  "type": "Feature",
  "properties": {
    "addr:full":"6 Bede Terrace Chester-le-street Durham DH2 2AZ",
    "addr:housenumber":"6",
    "addr:postcode":"dh2 2az",
    "addr:street":"Bede Terrace",
    "iso:country":"GB",
    "sg:address":"6 Bede Terrace",
    "sg:city":"Chester-le-street",
    "sg:classifiers":[
        {
            "category":"Manufacturing",
            "subcategory":"Petroleum Products",
            "type":"Manufacturing & Wholesale Goods"
        },
        {
            "category":"Building & Trades",
            "subcategory":"Construction",
            "type":"Services"
        }
    ],
    "sg:phone":"+44 191 389 3795",
    "sg:postcode":"DH2 2AZ",
    "sg:province":"Durham",
    "sg:tags":[
        "double",
        "glazing",
        "installers"
    ],
    "wof:name":"Northside Windows & Conservatories",
    "wof:placetype":"venue"
},
  "geometry": {"coordinates":[-1.5821429491,54.85496521],"type":"Point"}
}