{
  "type": "Feature",
  "properties": {
    "iso:country":"GB",
    "sg:address":"126a Liverpool Road",
    "sg:city":"Newcastle",
    "sg:classifiers":[
        {
            "category":"Shopping",
            "subcategory":"Computers & Home Electronics",
            "type":"Retail Goods"
        }
    ],
    "sg:postcode":"ST5 9EQ",
    "sg:province":"Staffordshire",
    "sg:tags":[
        "electrical"
    ],
    "wof:name":"Electrical Trade Supplies",
    "wof:placetype":"venue"
},
  "geometry": {"coordinates":[-2.230236,53.01775],"type":"Point"}
}