{
  "type": "Feature",
  "properties": {
    "addr:full":"C Company, 4-5 Green Howards, T A Centre Harrogate North Yorkshire HG3 2SB",
    "addr:housenumber":"4-5",
    "addr:postcode":"hg3 2sb",
    "addr:street":"Green",
    "iso:country":"GB",
    "sg:address":"C Company, 4-5 Green Howards, T A Centre",
    "sg:city":"Harrogate",
    "sg:classifiers":[
        {
            "category":"Government",
            "subcategory":"Office",
            "type":"Public Place"
        }
    ],
    "sg:phone":"+44 1423 501097",
    "sg:postcode":"HG3 2SB",
    "sg:province":"North Yorkshire",
    "sg:tags":[
        "armed",
        "reserve"
    ],
    "wof:name":"Territorial Army",
    "wof:placetype":"venue"
},
  "geometry": {"coordinates":[-1.58934,53.996658],"type":"Point"}
}