{
  "type": "Feature",
  "properties": {
    "addr:full":"43 Glendevon Place Edinburgh City of Edinburgh EH12 5UQ",
    "addr:housenumber":"43",
    "addr:postcode":"eh12 5uq",
    "addr:street":"Glendevon Place Edinburgh",
    "iso:country":"GB",
    "sg:address":"43 Glendevon Place",
    "sg:city":"Edinburgh",
    "sg:classifiers":[
        {
            "category":"Professional",
            "subcategory":"Management & Consulting",
            "type":"Services"
        }
    ],
    "sg:phone":"+44 131 477 4320",
    "sg:postcode":"EH12 5UQ",
    "sg:province":"City of Edinburgh",
    "sg:tags":[
        "consultant"
    ],
    "wof:name":"LineFinders Communications",
    "wof:placetype":"venue"
},
  "geometry": {"coordinates":[-3.242164,55.945606],"type":"Point"}
}