{
  "type": "Feature",
  "properties": {
    "iso:country":"GB",
    "sg:address":"16 Highbury Park",
    "sg:city":"London",
    "sg:classifiers":[
        {
            "category":"Food & Beverages",
            "subcategory":"Meat & Fish",
            "type":"Retail Goods"
        }
    ],
    "sg:phone":"+44 20 7226 1604",
    "sg:postcode":"N5 2AB",
    "sg:province":"Greater London",
    "sg:tags":[
        "butcher"
    ],
    "wof:name":"Eddie's Butchers",
    "wof:placetype":"venue"
},
  "geometry": {"coordinates":[-0.095697,51.554672],"type":"Point"}
}