{
  "type": "Feature",
  "properties": {
    "iso:country":"GB",
    "sg:address":"Little Reeds Studio, Andrews Lane, Ropley",
    "sg:city":"Alresford",
    "sg:classifiers":[
        {
            "category":"Professional",
            "subcategory":"Art Services",
            "type":"Services"
        }
    ],
    "sg:phone":"+44 1962 772363",
    "sg:postcode":"SO24 0BZ",
    "sg:province":"Hampshire",
    "sg:tags":[
        "glass",
        "engraver"
    ],
    "wof:name":"Anthony O Gilliam",
    "wof:placetype":"venue"
},
  "geometry": {"coordinates":[-1.089354,51.080662],"type":"Point"}
}