{
  "type": "Feature",
  "properties": {
    "iso:country":"GB",
    "sg:address":"190 South Park Rd",
    "sg:city":"Maidstone",
    "sg:classifiers":[
        {
            "category":"Manufacturing",
            "subcategory":"Petroleum Products",
            "type":"Manufacturing & Wholesale Goods"
        }
    ],
    "sg:phone":"+44 1622 691791",
    "sg:postcode":"ME15 7AJ",
    "sg:province":"Kent",
    "sg:tags":[
        "double",
        "glazing"
    ],
    "wof:name":"ATF Window Installations",
    "wof:placetype":"venue"
},
  "geometry": {"coordinates":[0.541798,51.259628],"type":"Point"}
}