{
  "type": "Feature",
  "properties": {
    "addr:full":"Cressing Lodge, Cressing Braintree Essex CM7 8DL",
    "addr:postcode":"cm7 8dl",
    "addr:street":"Cressing",
    "iso:country":"GB",
    "sg:address":"Cressing Lodge, Cressing",
    "sg:city":"Braintree",
    "sg:classifiers":[
        {
            "category":"Home & Garden",
            "subcategory":"Garden Supply",
            "type":"Retail Goods"
        },
        {
            "category":"Farming",
            "subcategory":"Livestock Farm",
            "type":"Manufacturing & Wholesale Goods"
        }
    ],
    "sg:postcode":"CM7 8DL",
    "sg:province":"Essex",
    "sg:tags":[
        "bulb",
        "grower",
        "others"
    ],
    "wof:name":"Cousins,John,",
    "wof:placetype":"venue"
},
  "geometry": {"coordinates":[0.553242,51.877758],"type":"Point"}
}