{
  "type": "Feature",
  "properties": {
    "iso:country":"GB",
    "sg:address":"21 Shaw Lane, Markfield",
    "sg:city":"Leicester",
    "sg:classifiers":[
        {
            "category":"Manufacturing",
            "subcategory":"Metals",
            "type":"Manufacturing & Wholesale Goods"
        }
    ],
    "sg:phone":"+44 1530 242116",
    "sg:postcode":"LE67 9PU",
    "sg:province":"Leicestershire",
    "sg:tags":[
        "steel",
        "stockholder"
    ],
    "wof:name":"C J Upton & Sons Ltd.",
    "wof:placetype":"venue"
},
  "geometry": {"coordinates":[-1.3057390451,52.7004013062],"type":"Point"}
}