{
  "type": "Feature",
  "properties": {
    "addr:full":"Harrison Hill Castle & Co, Melbury Ho, 34 Southborough Bromley Kent BR1 2EB",
    "addr:housenumber":"34",
    "addr:postcode":"br1 2eb",
    "addr:street":"Harrison",
    "iso:country":"GB",
    "sg:address":"Harrison Hill Castle & Co, Melbury Ho, 34 Southborough",
    "sg:city":"Bromley",
    "sg:classifiers":[
        {
            "category":"Arena",
            "subcategory":"Bull Ring",
            "type":"Entertainment"
        }
    ],
    "sg:phone":"+44 1474 321226",
    "sg:postcode":"BR1 2EB",
    "sg:province":"Kent",
    "sg:tags":[
        "rating",
        "surveyor"
    ],
    "wof:name":"Professional Property Consultants Ltd",
    "wof:placetype":"venue"
},
  "geometry": {"coordinates":[0.0455829985,51.3991088867],"type":"Point"}
}