{
  "type": "Feature",
  "properties": {
    "iso:country":"GB",
    "sg:address":"4 Turnpike Lane",
    "sg:city":"Bury St Edmunds",
    "sg:classifiers":[
        {
            "category":"Home & Garden",
            "subcategory":"Furniture",
            "type":"Retail Goods"
        }
    ],
    "sg:postcode":"IP28 8LF",
    "sg:province":"Cambridgeshire",
    "wof:name":"Red Lodge Sofa & Chair Centre",
    "wof:placetype":"venue"
},
  "geometry": {"coordinates":[0.4822100103,52.3020896912],"type":"Point"}
}