{
  "type": "Feature",
  "properties": {
    "addr:full":"Greg St, Reddish Stockport Cheshire SK5 7BS",
    "addr:postcode":"sk5 7bs",
    "addr:street":"Greg St",
    "iso:country":"GB",
    "sg:address":"Greg St, Reddish",
    "sg:city":"Stockport",
    "sg:classifiers":[
        {
            "category":"Autos & Motor Vehicles",
            "subcategory":"Automobile Sales",
            "type":"Retail Goods"
        }
    ],
    "sg:phone":"+44 161 477 7056",
    "sg:postcode":"SK5 7BS",
    "sg:province":"Cheshire",
    "sg:tags":[
        "car"
    ],
    "wof:name":"Dace Motor Co",
    "wof:placetype":"venue"
},
  "geometry": {"coordinates":[-2.157879,53.434635],"type":"Point"}
}