{
  "type": "Feature",
  "properties": {
    "addr:full":"Town Mills, High Street Dulverton Devon TA22 9HB",
    "addr:postcode":"ta22 9hb",
    "addr:street":"High Street",
    "iso:country":"GB",
    "sg:address":"Town Mills, High Street",
    "sg:city":"Dulverton",
    "sg:classifiers":[
        {
            "category":"Real Estate",
            "subcategory":"Real Estate Services",
            "type":"Services"
        },
        {
            "category":"Retail",
            "subcategory":"Repair Shop",
            "type":"Services"
        }
    ],
    "sg:postcode":"TA22 9HB",
    "sg:province":"Devon",
    "sg:tags":[
        "property",
        "maintenance"
    ],
    "wof:name":"CHARLES BUCKINGHAM",
    "wof:placetype":"venue"
},
  "geometry": {"coordinates":[-3.5504629612,51.0399169922],"type":"Point"}
}