{
  "type": "Feature",
  "properties": {
    "addr:full":"Hurst Farm, Copper Lane, Whitefield Manchester Lancashire M45 7TQ",
    "addr:housenumber":"hurst farm",
    "addr:postcode":"m45 7tq",
    "addr:street":"Copper Lane",
    "iso:country":"GB",
    "sg:address":"Hurst Farm, Copper Lane, Whitefield",
    "sg:city":"Manchester",
    "sg:classifiers":[
        {
            "category":"Farming",
            "subcategory":"Livestock Farm",
            "type":"Manufacturing & Wholesale Goods"
        }
    ],
    "sg:phone":"+44 161 796 8820",
    "sg:postcode":"M45 7TQ",
    "sg:province":"Lancashire",
    "sg:tags":[
        "others"
    ],
    "wof:name":"A R Howarth",
    "wof:placetype":"venue"
},
  "geometry": {"coordinates":[-2.32531,53.539539],"type":"Point"}
}