{
  "type": "Feature",
  "properties": {
    "addr:full":"Falcon Court, Wonastow Monmouth Gloucestershire NP25 4DN",
    "addr:postcode":"np25 4dn",
    "addr:street":"Falcon Court",
    "iso:country":"GB",
    "sg:address":"Falcon Court, Wonastow",
    "sg:city":"Monmouth",
    "sg:classifiers":[
        {
            "category":"Banks & Credit Unions",
            "subcategory":"Financial Services",
            "type":"Services"
        }
    ],
    "sg:phone":"+44 1600 740411",
    "sg:postcode":"NP25 4DN",
    "sg:province":"Gloucestershire",
    "sg:tags":[
        "consultant"
    ],
    "wof:name":"South Wales Financial Services",
    "wof:placetype":"venue"
},
  "geometry": {"coordinates":[-2.739167,51.801659],"type":"Point"}
}