{
  "type": "Feature",
  "properties": {
    "addr:full":"Leechmore Cross, Wick Cowbridge The Vale of Glamorgan CF71 7QR",
    "addr:postcode":"cf71 7qr",
    "addr:street":"Leechmore Cross;Vale",
    "iso:country":"GB",
    "sg:address":"Leechmore Cross, Wick",
    "sg:city":"Cowbridge",
    "sg:classifiers":[
        {
            "category":"Farming",
            "subcategory":"Livestock Farm",
            "type":"Manufacturing & Wholesale Goods"
        }
    ],
    "sg:phone":"+44 1656 890501",
    "sg:postcode":"CF71 7QR",
    "sg:province":"The Vale of Glamorgan",
    "sg:tags":[
        "others"
    ],
    "wof:name":"Cae Bush Farm",
    "wof:placetype":"venue"
},
  "geometry": {"coordinates":[-3.450425,51.462391],"type":"Point"}
}