{
  "type": "Feature",
  "properties": {
    "iso:country":"GB",
    "sg:address":"11 Deanpark Place",
    "sg:city":"Balerno",
    "sg:classifiers":[
        {
            "category":"Building & Trades",
            "subcategory":"Construction",
            "type":"Services"
        }
    ],
    "sg:phone":"+44 131 449 2585",
    "sg:postcode":"EH14 7ED",
    "sg:province":"City of Edinburgh",
    "sg:tags":[
        "decorator",
        "painter"
    ],
    "wof:name":"J & C Thorpe",
    "wof:placetype":"venue"
},
  "geometry": {"coordinates":[-3.3418281078,55.8814353943],"type":"Point"}
}