{
  "type": "Feature",
  "properties": {
    "iso:country":"GB",
    "sg:address":"Nursery Gardens",
    "sg:city":"Ipswich",
    "sg:classifiers":[
        {
            "category":"Home & Garden",
            "subcategory":"Garden Supply",
            "type":"Retail Goods"
        }
    ],
    "sg:phone":"+44 1473 780322",
    "sg:postcode":"IP9 1AY",
    "sg:province":"Suffolk",
    "sg:tags":[
        "planting",
        "tree",
        "shrub"
    ],
    "wof:name":"Paul Double Nurseries Ltd.",
    "wof:placetype":"venue"
},
  "geometry": {"coordinates":[1.18735,52.002151],"type":"Point"}
}