{
  "type": "Feature",
  "properties": {
    "iso:country":"GB",
    "sg:address":"Carmunnock Road",
    "sg:city":"Glasgow",
    "sg:classifiers":[
        {
            "category":"Place Of Worship",
            "type":"Public Place"
        }
    ],
    "sg:postcode":"G44 4TZ",
    "sg:province":"East Renfrewshire",
    "wof:name":"Castlemilk West Church of Scotland",
    "wof:placetype":"venue"
},
  "geometry": {"coordinates":[-4.257104,55.825191],"type":"Point"}
}