{
  "type": "Feature",
  "properties": {
    "iso:country":"GB",
    "sg:address":"Broadway, Silver End",
    "sg:city":"Witham",
    "sg:classifiers":[
        {
            "category":"Health Services",
            "subcategory":"Doctor",
            "type":"Services"
        }
    ],
    "sg:phone":"+44 1376 583387",
    "sg:postcode":"CM8 3RQ",
    "sg:province":"Essex",
    "sg:tags":[
        "practitioners"
    ],
    "wof:name":"The Surgery",
    "wof:placetype":"venue"
},
  "geometry": {"coordinates":[0.6250039935,51.8464431763],"type":"Point"}
}