{
  "type": "Feature",
  "properties": {
    "addr:full":"38 Bank Street Rossendale West Yorkshire BD4 8DY",
    "addr:housenumber":"38",
    "addr:postcode":"bd4 8dy",
    "addr:street":"Bank Street;West",
    "iso:country":"GB",
    "sg:address":"38 Bank Street",
    "sg:city":"Rossendale",
    "sg:classifiers":[
        {
            "category":"Shopping",
            "subcategory":"News",
            "type":"Retail Goods"
        }
    ],
    "sg:phone":"+44 1706 214307",
    "sg:postcode":"BD4 8DY",
    "sg:province":"West Yorkshire",
    "sg:tags":[
        "newsagent"
    ],
    "wof:name":"Barbara J Procter",
    "wof:placetype":"venue"
},
  "geometry": {"coordinates":[-1.71714,53.786518],"type":"Point"}
}