{
  "type": "Feature",
  "properties": {
    "addr:full":"51 Lichfield Rd Wolverhampton Staffordshire WV11 1TW",
    "addr:housenumber":"51",
    "addr:postcode":"wv11 1tw",
    "addr:street":"Lichfield Rd",
    "iso:country":"GB",
    "sg:address":"51 Lichfield Rd",
    "sg:city":"Wolverhampton",
    "sg:classifiers":[
        {
            "category":"Food & Beverages",
            "subcategory":"Meat & Fish",
            "type":"Retail Goods"
        }
    ],
    "sg:phone":"+44 1902 865975",
    "sg:postcode":"WV11 1TW",
    "sg:province":"Staffordshire",
    "sg:tags":[
        "chip"
    ],
    "wof:name":"Big Fish The",
    "wof:placetype":"venue"
},
  "geometry": {"coordinates":[-2.124481,52.586868],"type":"Point"}
}