{
  "type": "Feature",
  "properties": {
    "addr:full":"8 The Bank Barnard Castle Cumbria DL12 8PQ",
    "addr:housenumber":"8",
    "addr:postcode":"dl12 8pq",
    "addr:street":"The Bank",
    "iso:country":"GB",
    "sg:address":"8 The Bank",
    "sg:city":"Barnard Castle",
    "sg:classifiers":[
        {
            "category":"Shopping",
            "subcategory":"Clothing, Apparel, & Fashions",
            "type":"Retail Goods"
        }
    ],
    "sg:postcode":"DL12 8PQ",
    "sg:province":"Cumbria",
    "sg:tags":[
        "dresswear"
    ],
    "wof:name":"Labels of Barnard Castle",
    "wof:placetype":"venue"
},
  "geometry": {"coordinates":[-1.9236170053,54.5419311523],"type":"Point"}
}