{
  "type": "Feature",
  "properties": {
    "addr:full":"187 Blackstock Road London Greater London N5 2LL",
    "addr:housenumber":"187",
    "addr:postcode":"n5 2ll",
    "addr:street":"Blackstock Road",
    "iso:country":"GB",
    "sg:address":"187 Blackstock Road",
    "sg:city":"London",
    "sg:classifiers":[
        {
            "category":"Shopping",
            "subcategory":"Department Store",
            "type":"Retail Goods"
        }
    ],
    "sg:phone":"+44 20 7354 1400",
    "sg:postcode":"N5 2LL",
    "sg:province":"Greater London",
    "wof:name":"Wallers",
    "wof:placetype":"venue"
},
  "geometry": {"coordinates":[-0.0984740034,51.5603561401],"type":"Point"}
}