{
  "type": "Feature",
  "properties": {
    "iso:country":"GB",
    "sg:address":"103-105 Scrogg Rd",
    "sg:city":"Newcastle Upon Tyne",
    "sg:classifiers":[
        {
            "category":"Shopping",
            "subcategory":"Department Store",
            "type":"Retail Goods"
        }
    ],
    "sg:phone":"+44 191 276 2969",
    "sg:postcode":"NE6 4HA",
    "sg:province":"Tyne and Wear",
    "wof:name":"Premier Convenience Store",
    "wof:placetype":"venue"
},
  "geometry": {"coordinates":[-1.5543019772,54.9758796692],"type":"Point"}
}