{
  "type": "Feature",
  "properties": {
    "addr:full":"8 Bridge Street Caernarfon Gwynedd LL55 1AB",
    "addr:housenumber":"8",
    "addr:postcode":"ll55 1ab",
    "addr:street":"Bridge Street",
    "iso:country":"GB",
    "sg:address":"8 Bridge Street",
    "sg:city":"Caernarfon",
    "sg:classifiers":[
        {
            "category":"Shopping",
            "subcategory":"Clothing, Apparel, & Fashions",
            "type":"Retail Goods"
        }
    ],
    "sg:phone":"+44 1286 676612",
    "sg:postcode":"LL55 1AB",
    "sg:province":"Gwynedd",
    "sg:tags":[
        "menswear"
    ],
    "wof:name":"Trefor Jones",
    "wof:placetype":"venue"
},
  "geometry": {"coordinates":[-4.2740287781,53.140750885],"type":"Point"}
}