{
  "type": "Feature",
  "properties": {
    "addr:full":"3 Chislehurst Road Richmond Greater London TW10 6PW",
    "addr:housenumber":"3",
    "addr:postcode":"tw10 6pw",
    "addr:street":"Chislehurst Road",
    "iso:country":"GB",
    "sg:address":"3 Chislehurst Road",
    "sg:city":"Richmond",
    "sg:classifiers":[
        {
            "category":"Health Services",
            "subcategory":"Health Practitioner",
            "type":"Services"
        }
    ],
    "sg:phone":"+44 20 8940 7222",
    "sg:postcode":"TW10 6PW",
    "sg:province":"Greater London",
    "sg:tags":[
        "technique",
        "alexander"
    ],
    "wof:name":"J Fenwick",
    "wof:placetype":"venue"
},
  "geometry": {"coordinates":[-0.2981860042,51.4570007324],"type":"Point"}
}