{
  "type": "Feature",
  "properties": {
    "addr:full":"110 Long Street, Easingwold York North Yorkshire YO61 3HX",
    "addr:housenumber":"110",
    "addr:postcode":"yo61 3hx",
    "addr:street":"Long Street",
    "iso:country":"GB",
    "sg:address":"110 Long Street, Easingwold",
    "sg:city":"York",
    "sg:classifiers":[
        {
            "category":"Professional",
            "subcategory":"Business Services",
            "type":"Services"
        }
    ],
    "sg:phone":"+44 1347 821484",
    "sg:postcode":"YO61 3HX",
    "sg:province":"North Yorkshire",
    "sg:tags":[
        "bookmaker"
    ],
    "wof:name":"Mack's Sporting Investments",
    "wof:placetype":"venue"
},
  "geometry": {"coordinates":[-1.193212,54.119797],"type":"Point"}
}