{
  "type": "Feature",
  "properties": {
    "addr:full":"101 Knighton Lane East Leicester Leicestershire LE2 6FT",
    "addr:housenumber":"101",
    "addr:postcode":"le2 6ft",
    "addr:street":"Knighton Lane",
    "iso:country":"GB",
    "sg:address":"101 Knighton Lane East",
    "sg:city":"Leicester",
    "sg:classifiers":[
        {
            "category":"Autos & Motor Vehicles",
            "subcategory":"Automobile Sales",
            "type":"Retail Goods"
        },
        {
            "category":"Retail",
            "subcategory":"Auto Repair",
            "type":"Services"
        }
    ],
    "sg:phone":"+44 116 270 3374",
    "sg:postcode":"LE2 6FT",
    "sg:province":"Leicestershire",
    "sg:tags":[
        "car",
        "commercial"
    ],
    "wof:name":"John March Commercials",
    "wof:placetype":"venue"
},
  "geometry": {"coordinates":[-1.130802,52.608742],"type":"Point"}
}