{
  "type": "Feature",
  "properties": {
    "iso:country":"GB",
    "sg:address":"Fir Tree Cottage, South Lane, Nomansland",
    "sg:city":"Salisbury",
    "sg:classifiers":[
        {
            "category":"Building & Trades",
            "subcategory":"Construction",
            "type":"Services"
        }
    ],
    "sg:phone":"+44 1794 390404",
    "sg:postcode":"SP5 2BZ",
    "sg:province":"Dorset",
    "sg:tags":[
        "welder",
        "mechanical"
    ],
    "wof:name":"N J M (Welding & Steel Fabrications) Ltd.",
    "wof:placetype":"venue"
},
  "geometry": {"coordinates":[-1.639309,50.956059],"type":"Point"}
}