{
  "type": "Feature",
  "properties": {
    "addr:full":"Stanmore Industrial Bridgnorth Shropshire WV15 5HR",
    "addr:postcode":"wv15 5hr",
    "iso:country":"GB",
    "sg:address":"Stanmore Industrial",
    "sg:city":"Bridgnorth",
    "sg:classifiers":[
        {
            "category":"Home & Garden",
            "subcategory":"Garden Supply",
            "type":"Retail Goods"
        }
    ],
    "sg:postcode":"WV15 5HR",
    "sg:province":"Shropshire",
    "sg:tags":[
        "fertiliser"
    ],
    "wof:name":"Fertiliser Products Leith Ltd",
    "wof:placetype":"venue"
},
  "geometry": {"coordinates":[-2.3767089844,52.5273208618],"type":"Point"}
}