{
  "type": "Feature",
  "properties": {
    "addr:full":"P O Box 7, Ferry Ho, Crown St Dagenham Essex RM10 9UD",
    "addr:housenumber":"7",
    "addr:postcode":"rm10 9ud",
    "addr:street":"P O Box;Ferry Ho Crown St",
    "iso:country":"GB",
    "sg:address":"P O Box 7, Ferry Ho, Crown St",
    "sg:city":"Dagenham",
    "sg:classifiers":[
        {
            "category":"Freight",
            "type":"Transportation"
        }
    ],
    "sg:phone":"+44 20 8592 3044",
    "sg:postcode":"RM10 9UD",
    "sg:province":"Essex",
    "sg:tags":[
        "forwarders"
    ],
    "wof:name":"FFG Hillebrand",
    "wof:placetype":"venue"
},
  "geometry": {"coordinates":[0.147961,51.541618],"type":"Point"}
}