{
  "type": "Feature",
  "properties": {
    "addr:full":"65 Fleet St London Greater London EC4Y 1HS",
    "addr:housenumber":"65",
    "addr:postcode":"ec4y 1hs",
    "addr:street":"Fleet St",
    "iso:country":"GB",
    "sg:address":"65 Fleet St",
    "sg:city":"London",
    "sg:classifiers":[
        {
            "category":"Professional",
            "subcategory":"Lawyer & Legal Services",
            "type":"Services"
        }
    ],
    "sg:postcode":"EC4Y 1HS",
    "sg:province":"Greater London",
    "sg:tags":[
        "solicitor"
    ],
    "wof:name":"Phoenix Travel (F S C) Ltd",
    "wof:placetype":"venue"
},
  "geometry": {"coordinates":[-0.1075500026,51.5141448975],"type":"Point"}
}