{
  "type": "Feature",
  "properties": {
    "addr:full":"Longfield Road Tunbridge Wells East Sussex TN2 3UR",
    "addr:postcode":"tn2 3ur",
    "addr:street":"Longfield Road",
    "iso:country":"GB",
    "sg:address":"Longfield Road",
    "sg:city":"Tunbridge Wells",
    "sg:classifiers":[
        {
            "category":"Building & Trades",
            "subcategory":"Construction",
            "type":"Services"
        }
    ],
    "sg:phone":"+44 1892 511088",
    "sg:postcode":"TN2 3UR",
    "sg:province":"East Sussex",
    "sg:tags":[
        "joinery"
    ],
    "wof:name":"Magnet",
    "wof:placetype":"venue"
},
  "geometry": {"coordinates":[0.2958520055,51.1573677063],"type":"Point"}
}