{
  "type": "Feature",
  "properties": {
    "addr:full":"35 Waddesdon Road Harwich Essex CO12 3BA",
    "addr:housenumber":"35",
    "addr:postcode":"co12 3ba",
    "addr:street":"Waddesdon Road",
    "iso:country":"GB",
    "sg:address":"35 Waddesdon Road",
    "sg:city":"Harwich",
    "sg:classifiers":[
        {
            "category":"Professional",
            "subcategory":"Engineering",
            "type":"Services"
        }
    ],
    "sg:phone":"+44 1255 508283",
    "sg:postcode":"CO12 3BA",
    "sg:province":"Essex",
    "sg:tags":[
        "design",
        "engineer"
    ],
    "wof:name":"G Starkings Amice",
    "wof:placetype":"venue"
},
  "geometry": {"coordinates":[1.2828749418,51.9385681152],"type":"Point"}
}