{
  "type": "Feature",
  "properties": {
    "addr:full":"Princes Parade Hythe Kent CT21 6AE",
    "addr:postcode":"ct21 6ae",
    "addr:street":"Princes Parade Hythe",
    "iso:country":"GB",
    "sg:address":"Princes Parade",
    "sg:city":"Hythe",
    "sg:classifiers":[
        {
            "category":"Travel",
            "subcategory":"Hotels & Motels",
            "type":"Entertainment"
        }
    ],
    "sg:phone":"+44 1303 267441",
    "sg:postcode":"CT21 6AE",
    "sg:province":"Kent",
    "wof:name":"The Hotel Imperial (Hythe) Ltd.",
    "wof:placetype":"venue"
},
  "geometry": {"coordinates":[1.124216,51.071495],"type":"Point"}
}