{
  "type": "Feature",
  "properties": {
    "iso:country":"GB",
    "sg:address":"Beaumont Lodge, Beaumont Fee",
    "sg:city":"Lincoln",
    "sg:classifiers":[
        {
            "category":"Professional",
            "subcategory":"Lawyer & Legal Services",
            "type":"Services"
        }
    ],
    "sg:phone":"+44 845 052 5252",
    "sg:postcode":"LN1 1UL",
    "sg:province":"Lincolnshire",
    "sg:tags":[
        "advice",
        "counselling"
    ],
    "wof:name":"Lincoln & District Citizens Advice Bureau Ltd.",
    "wof:placetype":"venue"
},
  "geometry": {"coordinates":[-0.5422189832,53.2316055298],"type":"Point"}
}