{
  "type": "Feature",
  "properties": {
    "iso:country":"GB",
    "sg:address":"Spadesbourne House, 184 Worcester Road",
    "sg:city":"Bromsgrove",
    "sg:classifiers":[
        {
            "category":"Professional",
            "subcategory":"Computer Services",
            "type":"Services"
        }
    ],
    "sg:postcode":"B61 7AZ",
    "sg:province":"Worcestershire",
    "sg:tags":[
        "bureau",
        "facility"
    ],
    "wof:name":"Latymer Associates Ltd.",
    "wof:placetype":"venue"
},
  "geometry": {"coordinates":[-2.070011,52.327766],"type":"Point"}
}