{
  "type": "Feature",
  "properties": {
    "addr:full":"Bourne Hall House, Bourne Hall Road Bushey Hertfordshire WD23 3YG",
    "addr:postcode":"wd23 3yg",
    "addr:street":"Bourne Hall Road",
    "iso:country":"GB",
    "sg:address":"Bourne Hall House, Bourne Hall Road",
    "sg:city":"Bushey",
    "sg:classifiers":[
        {
            "category":"Professional",
            "subcategory":"Computer Services",
            "type":"Services"
        }
    ],
    "sg:phone":"+44 20 8421 8123",
    "sg:postcode":"WD23 3YG",
    "sg:province":"Hertfordshire",
    "sg:tags":[
        "bureau",
        "facility"
    ],
    "wof:name":"Bellsize Datamatic Ltd.",
    "wof:placetype":"venue"
},
  "geometry": {"coordinates":[-0.363069,51.644341],"type":"Point"}
}