{
  "type": "Feature",
  "properties": {
    "iso:country":"GB",
    "sg:address":"Main Street",
    "sg:city":"Connel",
    "sg:classifiers":[
        {
            "category":"Home & Garden",
            "subcategory":"Hardware",
            "type":"Retail Goods"
        }
    ],
    "sg:postcode":"PA37 1PA",
    "sg:province":"Argyll and Bute",
    "sg:tags":[
        "lawnmowers",
        "machinery"
    ],
    "wof:name":"Blades & Co",
    "wof:placetype":"venue"
},
  "geometry": {"coordinates":[-5.386774,56.454735],"type":"Point"}
}