{
  "type": "Feature",
  "properties": {
    "addr:full":"Knighton Market Drayton Shropshire TF9 4HJ",
    "addr:postcode":"tf9 4hj",
    "iso:country":"GB",
    "sg:address":"Knighton",
    "sg:city":"Market Drayton",
    "sg:classifiers":[
        {
            "category":"Bars & Pubs",
            "type":"Food & Drink"
        },
        {
            "category":"Restaurant",
            "type":"Food & Drink"
        }
    ],
    "sg:phone":"+44 1630 647300",
    "sg:postcode":"TF9 4HJ",
    "sg:province":"Shropshire",
    "sg:tags":[
        "-"
    ],
    "wof:name":"White Lion Inn",
    "wof:placetype":"venue"
},
  "geometry": {"coordinates":[-2.40438,52.957569],"type":"Point"}
}