{
  "type": "Feature",
  "properties": {
    "addr:full":"190 London Road, New Balderton Newark Nottinghamshire NG24 3BN",
    "addr:housenumber":"190",
    "addr:postcode":"ng24 3bn",
    "addr:street":"London Road New",
    "iso:country":"GB",
    "sg:address":"190 London Road, New Balderton",
    "sg:city":"Newark",
    "sg:classifiers":[
        {
            "category":"Retail",
            "subcategory":"Auto Repair",
            "type":"Services"
        }
    ],
    "sg:phone":"+44 1636 704937",
    "sg:postcode":"NG24 3BN",
    "sg:province":"Nottinghamshire",
    "sg:tags":[
        "modification",
        "garage"
    ],
    "wof:name":"Nelsons of Newark Ltd.",
    "wof:placetype":"venue"
},
  "geometry": {"coordinates":[-0.7854880095,53.0579338074],"type":"Point"}
}