{
  "type": "Feature",
  "properties": {
    "addr:full":"High Street, Holme On Spalding Moor York East Riding of Yorkshire YO43 4EN",
    "addr:postcode":"yo43 4en",
    "addr:street":"High Street;Moor",
    "iso:country":"GB",
    "sg:address":"High Street, Holme On Spalding Moor",
    "sg:city":"York",
    "sg:classifiers":[
        {
            "category":"Personal",
            "subcategory":"Beauty Salon",
            "type":"Services"
        }
    ],
    "sg:postcode":"YO43 4EN",
    "sg:province":"East Riding of Yorkshire",
    "sg:tags":[
        "lady",
        "hairdresser"
    ],
    "wof:name":"His N Hairs",
    "wof:placetype":"venue"
},
  "geometry": {"coordinates":[-0.6352390051,53.8414993286],"type":"Point"}
}