{
  "type": "Feature",
  "properties": {
    "addr:full":"37 Drumlanrig Street Thornhill Dumfries and Galloway DG3 5LJ",
    "addr:housenumber":"37",
    "addr:postcode":"dg3 5lj",
    "addr:street":"Drumlanrig Street",
    "iso:country":"GB",
    "sg:address":"37 Drumlanrig Street",
    "sg:city":"Thornhill",
    "sg:classifiers":[
        {
            "category":"Shopping",
            "subcategory":"Florist",
            "type":"Retail Goods"
        }
    ],
    "sg:phone":"+44 1848 330252",
    "sg:postcode":"DG3 5LJ",
    "sg:province":"Dumfries and Galloway",
    "wof:name":"A Dial Daisy",
    "wof:placetype":"venue"
},
  "geometry": {"coordinates":[-3.766173,55.241962],"type":"Point"}
}