{
  "type": "Feature",
  "properties": {
    "iso:country":"GB",
    "sg:address":"5 Waters Drive",
    "sg:city":"Sutton Coldfield",
    "sg:classifiers":[
        {
            "category":"Building & Trades",
            "subcategory":"Construction",
            "type":"Services"
        }
    ],
    "sg:postcode":"B74 4TQ",
    "sg:province":"Staffordshire",
    "sg:tags":[
        "builder"
    ],
    "wof:name":"L J Smith Building & Construction",
    "wof:placetype":"venue"
},
  "geometry": {"coordinates":[-1.855167985,52.5898513794],"type":"Point"}
}