{
  "type": "Feature",
  "properties": {
    "addr:full":"13 Rectory La Wigan Lancashire WN6 0XA",
    "addr:housenumber":"13",
    "addr:postcode":"wn6 0xa",
    "addr:street":"Rectory La Wigan",
    "iso:country":"GB",
    "sg:address":"13 Rectory La",
    "sg:city":"Wigan",
    "sg:classifiers":[
        {
            "category":"Place Of Worship",
            "type":"Public Place"
        }
    ],
    "sg:phone":"+44 1257 421396",
    "sg:postcode":"WN6 0XA",
    "sg:province":"Lancashire",
    "wof:name":"St Wilfrid C Of E Church",
    "wof:placetype":"venue"
},
  "geometry": {"coordinates":[-2.660682,53.587559],"type":"Point"}
}