{
  "type": "Feature",
  "properties": {
    "iso:country":"GB",
    "sg:address":"80a Blakes Road",
    "sg:city":"London",
    "sg:classifiers":[
        {
            "category":"Building & Trades",
            "subcategory":"Construction",
            "type":"Services"
        }
    ],
    "sg:phone":"+44 20 7277 1188",
    "sg:postcode":"SE15 6EP",
    "sg:province":"Greater London",
    "sg:tags":[
        "builder"
    ],
    "wof:name":"Salisbury Ltd.",
    "wof:placetype":"venue"
},
  "geometry": {"coordinates":[-0.079957,51.478161],"type":"Point"}
}