{
  "type": "Feature",
  "properties": {
    "addr:full":"6 Ardsley Rd Barnsley South Yorkshire S70 4RW",
    "addr:housenumber":"6",
    "addr:postcode":"s70 4rw",
    "addr:street":"Ardsley Rd;Yorkshire",
    "iso:country":"GB",
    "sg:address":"6 Ardsley Rd",
    "sg:city":"Barnsley",
    "sg:classifiers":[
        {
            "category":"Professional",
            "subcategory":"Accounting & Tax Preparation",
            "type":"Services"
        }
    ],
    "sg:phone":"+44 1226 770648",
    "sg:postcode":"S70 4RW",
    "sg:province":"South Yorkshire",
    "sg:tags":[
        "accountant"
    ],
    "wof:name":"Walker Business Services",
    "wof:placetype":"venue"
},
  "geometry": {"coordinates":[-1.448362,53.53434],"type":"Point"}
}