{
  "type": "Feature",
  "properties": {
    "addr:full":"Clophill Fruit Farm, Shefford Road, Clophill Bedford Bedfordshire MK45 4BT",
    "addr:postcode":"mk45 4bt",
    "addr:street":"Shefford Road",
    "iso:country":"GB",
    "sg:address":"Clophill Fruit Farm, Shefford Road, Clophill",
    "sg:city":"Bedford",
    "sg:classifiers":[
        {
            "category":"Health Services",
            "subcategory":"Health Practitioner",
            "type":"Services"
        }
    ],
    "sg:postcode":"MK45 4BT",
    "sg:province":"Bedfordshire",
    "sg:tags":[
        "technique",
        "alexander"
    ],
    "wof:name":"K Diss",
    "wof:placetype":"venue"
},
  "geometry": {"coordinates":[-0.4187679887,52.0291252136],"type":"Point"}
}