{
  "type": "Feature",
  "properties": {
    "addr:full":"10 Mills Road Sudbury Essex CO10 2XX",
    "addr:housenumber":"10",
    "addr:postcode":"co10 2xx",
    "addr:street":"Mills Road",
    "iso:country":"GB",
    "sg:address":"10 Mills Road",
    "sg:city":"Sudbury",
    "sg:classifiers":[
        {
            "category":"Manufacturing",
            "subcategory":"Petroleum Products",
            "type":"Manufacturing & Wholesale Goods"
        }
    ],
    "sg:phone":"+44 1787 883346",
    "sg:postcode":"CO10 2XX",
    "sg:province":"Essex",
    "sg:tags":[
        "double",
        "glazing"
    ],
    "wof:name":"Sky Windows (Suffolk) Ltd.",
    "wof:placetype":"venue"
},
  "geometry": {"coordinates":[0.745513,52.040108],"type":"Point"}
}