{
  "type": "Feature",
  "properties": {
    "iso:country":"GB",
    "sg:address":"The Oaks, Alderton, Montford Bridge",
    "sg:city":"Shrewsbury",
    "sg:classifiers":[
        {
            "category":"Farming",
            "subcategory":"Livestock Farm",
            "type":"Manufacturing & Wholesale Goods"
        }
    ],
    "sg:phone":"+44 1743 741284",
    "sg:postcode":"SY4 1AP",
    "sg:province":"Shropshire",
    "sg:tags":[
        "others"
    ],
    "wof:name":"E J Williams & Son",
    "wof:placetype":"venue"
},
  "geometry": {"coordinates":[-2.8436141014,52.7332992554],"type":"Point"}
}