{
  "type": "Feature",
  "properties": {
    "addr:full":"1c Parkwood Rd Bournemouth Dorset BH5 2BP",
    "addr:housenumber":"1c",
    "addr:postcode":"bh5 2bp",
    "addr:street":"Parkwood Rd",
    "iso:country":"GB",
    "sg:address":"1c Parkwood Rd",
    "sg:city":"Bournemouth",
    "sg:classifiers":[
        {
            "category":"Shopping",
            "subcategory":"Used Merchandise",
            "type":"Retail Goods"
        }
    ],
    "sg:postcode":"BH5 2BP",
    "sg:province":"Dorset",
    "sg:tags":[
        "shop",
        "second-hand"
    ],
    "wof:name":"McCartney,William Talmadge,",
    "wof:placetype":"venue"
},
  "geometry": {"coordinates":[-1.8301769495,50.7288551331],"type":"Point"}
}