{
  "type": "Feature",
  "properties": {
    "iso:country":"GB",
    "sg:address":"3 Holywell Hill",
    "sg:city":"St Albans",
    "sg:classifiers":[
        {
            "category":"Professional",
            "subcategory":"Computer Services",
            "type":"Services"
        }
    ],
    "sg:phone":"+44 1727 836736",
    "sg:postcode":"AL1 1ER",
    "sg:province":"Hertfordshire",
    "sg:tags":[
        "system",
        "software"
    ],
    "wof:name":"E C S United Kingdom PLC",
    "wof:placetype":"venue"
},
  "geometry": {"coordinates":[-0.33971,51.750629],"type":"Point"}
}