{
  "type": "Feature",
  "properties": {
    "iso:country":"GB",
    "sg:address":"2 Wearside Rd",
    "sg:city":"Lewisham",
    "sg:classifiers":[
        {
            "category":"Building & Trades",
            "subcategory":"Construction",
            "type":"Services"
        }
    ],
    "sg:phone":"+44 20 8690 7114",
    "sg:postcode":"SE13 7UN",
    "sg:province":"Greater London",
    "sg:tags":[
        "decorator",
        "painter"
    ],
    "wof:name":"Lady Decorator",
    "wof:placetype":"venue"
},
  "geometry": {"coordinates":[-0.016281,51.45686],"type":"Point"}
}