{
  "type": "Feature",
  "properties": {
    "addr:full":"2 Prospect Cottages Andover Hampshire SP11 9EP",
    "addr:housenumber":"2",
    "addr:postcode":"sp11 9ep",
    "addr:street":"Prospect Cottages",
    "iso:country":"GB",
    "sg:address":"2 Prospect Cottages",
    "sg:city":"Andover",
    "sg:classifiers":[
        {
            "category":"Building & Trades",
            "subcategory":"Construction",
            "type":"Services"
        }
    ],
    "sg:phone":"+44 1264 730212",
    "sg:postcode":"SP11 9EP",
    "sg:province":"Hampshire",
    "sg:tags":[
        "conservation",
        "craft",
        "thatching"
    ],
    "wof:name":"L C Foster & Sons",
    "wof:placetype":"venue"
},
  "geometry": {"coordinates":[-1.5769000053,51.2828903198],"type":"Point"}
}