{
  "type": "Feature",
  "properties": {
    "addr:full":"The Grange, Uffington Rd, Barnack Stamford Cambridgeshire PE9 3DU",
    "addr:postcode":"pe9 3du",
    "addr:street":"Uffington Rd",
    "iso:country":"GB",
    "sg:address":"The Grange, Uffington Rd, Barnack",
    "sg:city":"Stamford",
    "sg:classifiers":[
        {
            "category":"Shopping",
            "subcategory":"Photographic Equipment",
            "type":"Retail Goods"
        }
    ],
    "sg:phone":"+44 1780 740077",
    "sg:postcode":"PE9 3DU",
    "sg:province":"Cambridgeshire",
    "wof:name":"Roy Beck Photography",
    "wof:placetype":"venue"
},
  "geometry": {"coordinates":[-0.4117549956,52.633682251],"type":"Point"}
}