{
  "type": "Feature",
  "properties": {
    "iso:country":"GB",
    "sg:address":"42 Stow Road, Magdalen",
    "sg:city":"King's Lynn",
    "sg:classifiers":[
        {
            "category":"Professional",
            "subcategory":"Engineering",
            "type":"Services"
        },
        {
            "category":"Real Estate",
            "subcategory":"Architect",
            "type":"Services"
        }
    ],
    "sg:postcode":"PE34 3BX",
    "sg:province":"Lincolnshire",
    "wof:name":"Stuart D Warren",
    "wof:placetype":"venue"
},
  "geometry": {"coordinates":[0.3617,52.672649],"type":"Point"}
}