{
  "type": "Feature",
  "properties": {
    "addr:full":"The Drive Coventry Warwickshire CV2 5FU",
    "addr:postcode":"cv2 5fu",
    "addr:street":"The Drive",
    "iso:country":"GB",
    "sg:address":"The Drive",
    "sg:city":"Coventry",
    "sg:classifiers":[
        {
            "category":"Education",
            "subcategory":"School",
            "type":"Public Place"
        },
        {
            "category":"Government",
            "subcategory":"Office",
            "type":"Public Place"
        }
    ],
    "sg:phone":"+44 24 7645 0023",
    "sg:postcode":"CV2 5FU",
    "sg:province":"Warwickshire",
    "sg:tags":[
        "local",
        "authority"
    ],
    "wof:name":"Richard Lee Primary School",
    "wof:placetype":"venue"
},
  "geometry": {"coordinates":[-1.4565659761,52.4095230103],"type":"Point"}
}