{
  "type": "Feature",
  "properties": {
    "iso:country":"GB",
    "sg:address":"30-34 Magpie Hall Road",
    "sg:city":"Chatham",
    "sg:classifiers":[
        {
            "category":"Health Services",
            "subcategory":"Doctor",
            "type":"Services"
        },
        {
            "category":"Health Services",
            "subcategory":"Clinic",
            "type":"Services"
        }
    ],
    "sg:phone":"+44 1634 404632",
    "sg:postcode":"ME4 5JY",
    "sg:province":"Kent",
    "sg:tags":[
        "nh",
        "practitioners"
    ],
    "wof:name":"V Morton",
    "wof:placetype":"venue"
},
  "geometry": {"coordinates":[0.5345420241,51.3772964478],"type":"Point"}
}