{
  "type": "Feature",
  "properties": {
    "iso:country":"GB",
    "sg:address":"20 Churchill Ave",
    "sg:city":"Aldershot",
    "sg:classifiers":[
        {
            "category":"Real Estate",
            "subcategory":"Architect",
            "type":"Services"
        }
    ],
    "sg:postcode":"GU12 4JR",
    "sg:province":"Hampshire",
    "sg:tags":[
        "architectural"
    ],
    "wof:name":"Kiy,Martin,",
    "wof:placetype":"venue"
},
  "geometry": {"coordinates":[-0.7531809807,51.241607666],"type":"Point"}
}