{
  "type": "Feature",
  "properties": {
    "addr:full":"5 Newton Road, Great Barr Birmingham West Midlands B43 6AA",
    "addr:housenumber":"5",
    "addr:postcode":"b43 6aa",
    "addr:street":"Newton Road",
    "iso:country":"GB",
    "sg:address":"5 Newton Road, Great Barr",
    "sg:city":"Birmingham",
    "sg:classifiers":[
        {
            "category":"Health Services",
            "subcategory":"Clinic",
            "type":"Services"
        }
    ],
    "sg:phone":"+44 121 358 5638",
    "sg:postcode":"B43 6AA",
    "sg:province":"West Midlands",
    "sg:tags":[
        "aromatherapy"
    ],
    "wof:name":"Ann Hayes",
    "wof:placetype":"venue"
},
  "geometry": {"coordinates":[-1.9546010494,52.5446853638],"type":"Point"}
}