{
  "type": "Feature",
  "properties": {
    "addr:full":"Middlesexguildhall, Broad Sanctuary London Greater London SW1P 3BB",
    "addr:postcode":"sw1p 3bb",
    "iso:country":"GB",
    "sg:address":"Middlesexguildhall, Broad Sanctuary",
    "sg:city":"London",
    "sg:classifiers":[
        {
            "category":"Government",
            "subcategory":"Court House",
            "type":"Public Place"
        }
    ],
    "sg:phone":"+44 20 7799 2131",
    "sg:postcode":"SW1P 3BB",
    "sg:province":"Greater London",
    "wof:name":"Crown Court",
    "wof:placetype":"venue"
},
  "geometry": {"coordinates":[-0.128169,51.500679],"type":"Point"}
}