{
  "type": "Feature",
  "properties": {
    "addr:full":"24 Maple Road Ashtead Surrey KT21 2LX",
    "addr:housenumber":"24",
    "addr:postcode":"kt21 2lx",
    "addr:street":"Maple Road",
    "iso:country":"GB",
    "sg:address":"24 Maple Road",
    "sg:city":"Ashtead",
    "sg:classifiers":[
        {
            "category":"Professional",
            "type":"Services"
        }
    ],
    "sg:phone":"+44 1372 270190",
    "sg:postcode":"KT21 2LX",
    "sg:province":"Surrey",
    "sg:tags":[
        "entertainer"
    ],
    "wof:name":"Imagination Productions Ltd.",
    "wof:placetype":"venue"
},
  "geometry": {"coordinates":[-0.3093979955,51.3074035645],"type":"Point"}
}