{
  "type": "Feature",
  "properties": {
    "iso:country":"GB",
    "sg:address":"18 Coleswood Road",
    "sg:city":"Harpenden",
    "sg:classifiers":[
        {
            "category":"Shopping",
            "subcategory":"Books",
            "type":"Retail Goods"
        },
        {
            "category":"Wholesale",
            "subcategory":"Books, Periodicals, & Newspapers",
            "type":"Manufacturing & Wholesale Goods"
        }
    ],
    "sg:phone":"+44 1582 761264",
    "sg:postcode":"AL5 1EQ",
    "sg:province":"Hertfordshire",
    "sg:tags":[
        "publisher"
    ],
    "wof:name":"Oldcastle Books Ltd.",
    "wof:placetype":"venue"
},
  "geometry": {"coordinates":[-0.339979,51.805534],"type":"Point"}
}