{
  "type": "Feature",
  "properties": {
    "iso:country":"GB",
    "sg:address":"Capella Frith, Sden Copse, Potten End",
    "sg:city":"Berkhamsted",
    "sg:classifiers":[
        {
            "category":"Shopping",
            "subcategory":"Clothing, Apparel, & Fashions",
            "type":"Retail Goods"
        }
    ],
    "sg:phone":"+44 1442 866202",
    "sg:postcode":"HP4 2RG",
    "sg:province":"Bedfordshire",
    "sg:tags":[
        "dresswear"
    ],
    "wof:name":"Jules",
    "wof:placetype":"venue"
},
  "geometry": {"coordinates":[-0.564559,51.760414],"type":"Point"}
}