{
  "type": "Feature",
  "properties": {
    "iso:country":"GB",
    "sg:address":"74 Forton Road",
    "sg:city":"Newport",
    "sg:classifiers":[
        {
            "category":"Health Services",
            "subcategory":"Nursing And Care Facility",
            "type":"Services"
        }
    ],
    "sg:phone":"+44 1952 814871",
    "sg:postcode":"TF10 8BT",
    "sg:province":"Shropshire",
    "sg:tags":[
        "home"
    ],
    "wof:name":"Marches Care Ltd.",
    "wof:placetype":"venue"
},
  "geometry": {"coordinates":[-2.374968,52.77869],"type":"Point"}
}