{
  "type": "Feature",
  "properties": {
    "addr:full":"11 Compton Avenue, Tilehurst Reading Berkshire RG31 5LH",
    "addr:housenumber":"11",
    "addr:postcode":"rg31 5lh",
    "addr:street":"Compton Avenue",
    "iso:country":"GB",
    "sg:address":"11 Compton Avenue, Tilehurst",
    "sg:city":"Reading",
    "sg:classifiers":[
        {
            "category":"Building & Trades",
            "subcategory":"Cleaning & Sanitation",
            "type":"Services"
        }
    ],
    "sg:phone":"+44 118 945 4745",
    "sg:postcode":"RG31 5LH",
    "sg:province":"Berkshire",
    "sg:tags":[
        "sweep",
        "chimney"
    ],
    "wof:name":"Abbey Chimney Sweeps",
    "wof:placetype":"venue"
},
  "geometry": {"coordinates":[-1.05219,51.455967],"type":"Point"}
}