{
  "type": "Feature",
  "properties": {
    "addr:full":"Ground Floor, Gurney Ho, Gurney St Middlesbrough North Yorkshire TS1 1JL",
    "addr:housenumber":"ground floor",
    "addr:postcode":"ts1 1jl",
    "addr:street":"Gurney Ho Gurney St",
    "iso:country":"GB",
    "sg:address":"Ground Floor, Gurney Ho, Gurney St",
    "sg:city":"Middlesbrough",
    "sg:classifiers":[
        {
            "category":"Communications",
            "subcategory":"Film & Video Production",
            "type":"Services"
        }
    ],
    "sg:phone":"+44 1642 262424",
    "sg:postcode":"TS1 1JL",
    "sg:province":"North Yorkshire",
    "sg:tags":[
        "illustrator",
        "artist"
    ],
    "wof:name":"Cleveland Arts",
    "wof:placetype":"venue"
},
  "geometry": {"coordinates":[-1.236569047,54.572971344],"type":"Point"}
}