{
  "type": "Feature",
  "properties": {
    "iso:country":"GB",
    "sg:address":"47 Westgate End",
    "sg:city":"Wakefield",
    "sg:classifiers":[
        {
            "category":"Government",
            "subcategory":"Post Office",
            "type":"Public Place"
        }
    ],
    "sg:phone":"+44 1924 372832",
    "sg:postcode":"WF2 9RL",
    "sg:province":"West Yorkshire",
    "wof:name":"St.Michaels Post Office",
    "wof:placetype":"venue"
},
  "geometry": {"coordinates":[-1.51005,53.679939],"type":"Point"}
}