{
  "type": "Feature",
  "properties": {
    "addr:full":"49 Coxtie Green Rd, Pilgrims Hatch Brentwood Essex CM14 5PS",
    "addr:housenumber":"49",
    "addr:postcode":"cm14 5ps",
    "addr:street":"Coxtie Green Rd",
    "iso:country":"GB",
    "sg:address":"49 Coxtie Green Rd, Pilgrims Hatch",
    "sg:city":"Brentwood",
    "sg:classifiers":[
        {
            "category":"Shopping",
            "subcategory":"Books",
            "type":"Retail Goods"
        }
    ],
    "sg:phone":"+44 1277 373436",
    "sg:postcode":"CM14 5PS",
    "sg:province":"Essex",
    "wof:name":"Alive Uk",
    "wof:placetype":"venue"
},
  "geometry": {"coordinates":[0.2640599906,51.6395797729],"type":"Point"}
}