{
  "type": "Feature",
  "properties": {
    "iso:country":"GB",
    "sg:address":"276 Shirley Road",
    "sg:city":"Southampton",
    "sg:classifiers":[
        {
            "category":"Building & Trades",
            "subcategory":"Construction",
            "type":"Services"
        }
    ],
    "sg:phone":"+44 23 8077 0440",
    "sg:postcode":"SO15 3HP",
    "sg:province":"Hampshire",
    "sg:tags":[
        "monumental",
        "mason"
    ],
    "wof:name":"Wessex Memorials Ltd.",
    "wof:placetype":"venue"
},
  "geometry": {"coordinates":[-1.425686,50.916119],"type":"Point"}
}