{
  "type": "Feature",
  "properties": {
    "addr:full":"9 White Lion Street Norwich Norfolk NR2 1QA",
    "addr:housenumber":"9",
    "addr:postcode":"nr2 1qa",
    "addr:street":"White Lion Street",
    "iso:country":"GB",
    "sg:address":"9 White Lion Street",
    "sg:city":"Norwich",
    "sg:classifiers":[
        {
            "category":"Food & Beverages",
            "subcategory":"Bakery",
            "type":"Retail Goods"
        }
    ],
    "sg:phone":"+44 1603 631652",
    "sg:postcode":"NR2 1QA",
    "sg:province":"Norfolk",
    "sg:tags":[
        "baker"
    ],
    "wof:name":"The Bakers Oven",
    "wof:placetype":"venue"
},
  "geometry": {"coordinates":[1.2939449549,52.6276779175],"type":"Point"}
}