{
  "type": "Feature",
  "properties": {
    "addr:full":"Gorcott Hill, Beoley Redditch Warwickshire B98 9EP",
    "addr:postcode":"b98 9ep",
    "addr:street":"Gorcott Hill",
    "iso:country":"GB",
    "sg:address":"Gorcott Hill, Beoley",
    "sg:city":"Redditch",
    "sg:classifiers":[
        {
            "category":"Manufacturing",
            "subcategory":"Building Materials",
            "type":"Manufacturing & Wholesale Goods"
        }
    ],
    "sg:phone":"+44 1564 742732",
    "sg:postcode":"B98 9EP",
    "sg:province":"Warwickshire",
    "sg:tags":[
        "merchant",
        "builder"
    ],
    "wof:name":"Hilltop Supplies (Gorcott) Ltd.",
    "wof:placetype":"venue"
},
  "geometry": {"coordinates":[-1.906234026,52.3238983154],"type":"Point"}
}