{
  "type": "Feature",
  "properties": {
    "addr:full":"Pen-y-fai Bridgend Bridgend CF31 4LX",
    "addr:postcode":"cf31 4lx",
    "addr:street":"Bridgend",
    "iso:country":"GB",
    "sg:address":"Pen-y-fai",
    "sg:city":"Bridgend",
    "sg:classifiers":[
        {
            "category":"Education",
            "subcategory":"School",
            "type":"Public Place"
        }
    ],
    "sg:phone":"+44 1656 720376",
    "sg:postcode":"CF31 4LX",
    "sg:province":"Bridgend",
    "sg:tags":[
        "local",
        "authority"
    ],
    "wof:name":"Pen Y Fai Church In Wales Primary School",
    "wof:placetype":"venue"
},
  "geometry": {"coordinates":[-3.5967,51.526001],"type":"Point"}
}