{
  "type": "Feature",
  "properties": {
    "addr:full":"24 Westpole Avenue Barnet Hertfordshire EN4 0AY",
    "addr:housenumber":"24",
    "addr:postcode":"en4 0ay",
    "addr:street":"Westpole Avenue",
    "iso:country":"GB",
    "sg:address":"24 Westpole Avenue",
    "sg:city":"Barnet",
    "sg:classifiers":[
        {
            "category":"Professional",
            "subcategory":"Accounting & Tax Preparation",
            "type":"Services"
        }
    ],
    "sg:phone":"+44 20 8449 3644",
    "sg:postcode":"EN4 0AY",
    "sg:province":"Hertfordshire",
    "sg:tags":[
        "accountant"
    ],
    "wof:name":"McGoverns",
    "wof:placetype":"venue"
},
  "geometry": {"coordinates":[-0.138657,51.647575],"type":"Point"}
}