{
  "type": "Feature",
  "properties": {
    "iso:country":"GB",
    "sg:address":"138 Burncross Rd",
    "sg:city":"Sheffield",
    "sg:classifiers":[
        {
            "category":"Retail",
            "subcategory":"Driving School",
            "type":"Services"
        }
    ],
    "sg:phone":"+44 114 245 5481",
    "sg:postcode":"S30 4QN",
    "sg:province":"Derbyshire",
    "wof:name":"Lorraine School Of Motoring",
    "wof:placetype":"venue"
},
  "geometry": {"coordinates":[-1.473525,53.462276],"type":"Point"}
}