{
  "type": "Feature",
  "properties": {
    "iso:country":"GB",
    "sg:address":"Mottram Road, Broadbottom",
    "sg:city":"Hyde",
    "sg:classifiers":[
        {
            "category":"Education",
            "subcategory":"School",
            "type":"Public Place"
        }
    ],
    "sg:phone":"+44 1457 762382",
    "sg:postcode":"SK14 6BB",
    "sg:province":"Cheshire",
    "sg:tags":[
        "local",
        "authority"
    ],
    "wof:name":"Broadbottom C E Primary School",
    "wof:placetype":"venue"
},
  "geometry": {"coordinates":[-2.018208,53.444309],"type":"Point"}
}