{
  "type": "Feature",
  "properties": {
    "addr:full":"43 Cross La, Farnley Leeds West Yorkshire LS12 5AA",
    "addr:housenumber":"43",
    "addr:postcode":"ls12 5aa",
    "addr:street":"Cross La Farnley Leeds West",
    "iso:country":"GB",
    "sg:address":"43 Cross La, Farnley",
    "sg:city":"Leeds",
    "sg:classifiers":[
        {
            "category":"Personal",
            "subcategory":"Beauty Salon",
            "type":"Services"
        }
    ],
    "sg:postcode":"LS12 5AA",
    "sg:province":"West Yorkshire",
    "sg:tags":[
        "unisex",
        "hairdresser"
    ],
    "wof:name":"Nicholls,Angela,",
    "wof:placetype":"venue"
},
  "geometry": {"coordinates":[-1.6188440323,53.786819458],"type":"Point"}
}