{
  "type": "Feature",
  "properties": {
    "iso:country":"GB",
    "sg:address":"93 Clipstone Road West, Forest Town",
    "sg:city":"Mansfield",
    "sg:classifiers":[
        {
            "category":"Shopping",
            "subcategory":"Clothing, Apparel, & Fashions",
            "type":"Retail Goods"
        }
    ],
    "sg:postcode":"NG19 0BT",
    "sg:province":"Derbyshire",
    "sg:tags":[
        "shop"
    ],
    "wof:name":"Jean Terry",
    "wof:placetype":"venue"
},
  "geometry": {"coordinates":[-1.159879,53.153816],"type":"Point"}
}