{
  "type": "Feature",
  "properties": {
    "addr:full":"Bucklow Farm, Pinfold Lane Knutsford Cheshire WA16 9RP",
    "addr:postcode":"wa16 9rp",
    "addr:street":"Pinfold Lane",
    "iso:country":"GB",
    "sg:address":"Bucklow Farm, Pinfold Lane",
    "sg:city":"Knutsford",
    "sg:classifiers":[
        {
            "category":"Professional",
            "subcategory":"Engineering",
            "type":"Services"
        }
    ],
    "sg:phone":"+44 1565 722806",
    "sg:postcode":"WA16 9RP",
    "sg:province":"Cheshire",
    "wof:name":"Ratter Agricultural",
    "wof:placetype":"venue"
},
  "geometry": {"coordinates":[-2.37624,53.304203],"type":"Point"}
}