{
  "type": "Feature",
  "properties": {
    "iso:country":"GB",
    "sg:address":"24 Bastion Road",
    "sg:city":"London",
    "sg:classifiers":[
        {
            "category":"Building & Trades",
            "subcategory":"Construction",
            "type":"Services"
        }
    ],
    "sg:postcode":"SE2 0RG",
    "sg:province":"Greater London",
    "sg:tags":[
        "roofing"
    ],
    "wof:name":"Sandford Bros",
    "wof:placetype":"venue"
},
  "geometry": {"coordinates":[0.104411,51.484058],"type":"Point"}
}