{
  "type": "Feature",
  "properties": {
    "iso:country":"GB",
    "sg:address":"8 Landmark Commercial Centre, Commercial Road",
    "sg:city":"London",
    "sg:classifiers":[
        {
            "category":"Building & Trades",
            "subcategory":"Construction",
            "type":"Services"
        }
    ],
    "sg:postcode":"N18 1UB",
    "sg:province":"Greater London",
    "sg:tags":[
        "welder"
    ],
    "wof:name":"Bridge Welding Co",
    "wof:placetype":"venue"
},
  "geometry": {"coordinates":[-0.07412,51.609821],"type":"Point"}
}