{
  "type": "Feature",
  "properties": {
    "iso:country":"GB",
    "sg:address":"Expressway Business Park, Station Rd",
    "sg:city":"Deeside",
    "sg:classifiers":[
        {
            "category":"Retail",
            "subcategory":"Auto Repair",
            "type":"Services"
        }
    ],
    "sg:phone":"+44 1244 836459",
    "sg:postcode":"CH5 2ZA",
    "sg:province":"Flintshire",
    "sg:tags":[
        "garage"
    ],
    "wof:name":"Tyresave Uk",
    "wof:placetype":"venue"
},
  "geometry": {"coordinates":[-3.019006,53.208645],"type":"Point"}
}