{
  "type": "Feature",
  "properties": {
    "addr:full":"Bourn Hall, High Street, Bourn Cambridge Cambridgeshire CB3 7TR",
    "addr:postcode":"cb3 7tr",
    "addr:street":"High Street Bourn",
    "iso:country":"GB",
    "sg:address":"Bourn Hall, High Street, Bourn",
    "sg:city":"Cambridge",
    "sg:classifiers":[
        {
            "category":"Health Services",
            "subcategory":"Clinic",
            "type":"Services"
        },
        {
            "category":"Government",
            "subcategory":"Post Office",
            "type":"Public Place"
        }
    ],
    "sg:phone":"+44 1954 719111",
    "sg:postcode":"CB3 7TR",
    "sg:province":"Cambridgeshire",
    "sg:tags":[
        "organisation",
        "soc",
        "private",
        "research"
    ],
    "wof:name":"Bourn Hall Ltd.",
    "wof:placetype":"venue"
},
  "geometry": {"coordinates":[-0.0604679994,52.1864547729],"type":"Point"}
}