{
  "type": "Feature",
  "properties": {
    "addr:full":"97 High Street, Old Harlow Harlow Essex CM17 0DP",
    "addr:housenumber":"97",
    "addr:postcode":"cm17 0dp",
    "addr:street":"High Street",
    "iso:country":"GB",
    "sg:address":"97 High Street, Old Harlow",
    "sg:city":"Harlow",
    "sg:classifiers":[
        {
            "category":"Professional",
            "subcategory":"Advertising",
            "type":"Services"
        },
        {
            "category":"Professional",
            "subcategory":"Art Services",
            "type":"Services"
        }
    ],
    "sg:phone":"+44 1279 416017",
    "sg:postcode":"CM17 0DP",
    "sg:province":"Essex",
    "sg:tags":[
        "designer",
        "graphic",
        "related"
    ],
    "wof:name":"Mulberry Communications Ltd.",
    "wof:placetype":"venue"
},
  "geometry": {"coordinates":[0.13784,51.784088],"type":"Point"}
}