{
  "type": "Feature",
  "properties": {
    "addr:full":"South Road, Lerwick Shetland Shetland Islands ZE1 0RD",
    "addr:postcode":"ze1 0rd",
    "addr:street":"South Road",
    "iso:country":"GB",
    "sg:address":"South Road, Lerwick",
    "sg:city":"Shetland",
    "sg:classifiers":[
        {
            "category":"Autos & Motor Vehicles",
            "subcategory":"Fuel & Gas Station",
            "type":"Retail Goods"
        }
    ],
    "sg:phone":"+44 1595 693772",
    "sg:postcode":"ZE1 0RD",
    "sg:province":"Shetland Islands",
    "sg:tags":[
        "petrol",
        "filling"
    ],
    "wof:name":"Sound Service Station",
    "wof:placetype":"venue"
},
  "geometry": {"coordinates":[-1.170289,60.144829],"type":"Point"}
}