{
  "type": "Feature",
  "properties": {
    "iso:country":"GB",
    "sg:address":"106 Star Street",
    "sg:city":"London",
    "sg:classifiers":[
        {
            "category":"Professional",
            "subcategory":"Management & Consulting",
            "type":"Services"
        }
    ],
    "sg:phone":"+44 20 7706 1014",
    "sg:postcode":"W2 1QF",
    "sg:province":"Greater London",
    "sg:tags":[
        "marketing",
        "consultant"
    ],
    "wof:name":"Chilworth Communications Ltd.",
    "wof:placetype":"venue"
},
  "geometry": {"coordinates":[-0.1712390035,51.5169906616],"type":"Point"}
}