{
  "type": "Feature",
  "properties": {
    "iso:country":"GB",
    "sg:address":"2 Gothic Close, Wilmington",
    "sg:city":"Dartford",
    "sg:classifiers":[
        {
            "category":"Building & Trades",
            "subcategory":"Cleaning & Sanitation",
            "type":"Services"
        },
        {
            "category":"Home & Garden",
            "subcategory":"Carpets & Floor Coverings",
            "type":"Retail Goods"
        }
    ],
    "sg:phone":"+44 1322 277085",
    "sg:postcode":"DA1 1PR",
    "sg:province":"Kent",
    "sg:tags":[
        "cleaner",
        "upholstery"
    ],
    "wof:name":"Belmont Cleaning Services",
    "wof:placetype":"venue"
},
  "geometry": {"coordinates":[0.2138449997,51.4285507202],"type":"Point"}
}