{
  "type": "Feature",
  "properties": {
    "addr:full":"52 Eastgate St Gloucester Gloucestershire GL1 1QN",
    "addr:housenumber":"52",
    "addr:postcode":"gl1 1qn",
    "addr:street":"Eastgate St",
    "iso:country":"GB",
    "sg:address":"52 Eastgate St",
    "sg:city":"Gloucester",
    "sg:classifiers":[
        {
            "category":"Sports & Exercise",
            "subcategory":"Sports Center",
            "type":"Entertainment"
        }
    ],
    "sg:postcode":"GL1 1QN",
    "sg:province":"Gloucestershire",
    "sg:tags":[
        "shop",
        "good"
    ],
    "wof:name":"Brinn,Alan,",
    "wof:placetype":"venue"
},
  "geometry": {"coordinates":[-2.2429668903,51.8635787964],"type":"Point"}
}