{
  "type": "Feature",
  "properties": {
    "addr:full":"22 Fullarton St Ayr South Ayrshire KA7 1UB",
    "addr:housenumber":"22",
    "addr:postcode":"ka7 1ub",
    "addr:street":"Fullarton St",
    "iso:country":"GB",
    "sg:address":"22 Fullarton St",
    "sg:city":"Ayr",
    "sg:classifiers":[
        {
            "category":"Shopping",
            "subcategory":"Pharmacy",
            "type":"Retail Goods"
        }
    ],
    "sg:phone":"+44 1292 261043",
    "sg:postcode":"KA7 1UB",
    "sg:province":"South Ayrshire",
    "sg:tags":[
        "pharmacist",
        "chemist"
    ],
    "wof:name":"Carrick",
    "wof:placetype":"venue"
},
  "geometry": {"coordinates":[-4.6338601112,55.4614982605],"type":"Point"}
}