{
  "type": "Feature",
  "properties": {
    "addr:full":"Horne Lane, Potton Sandy Bedfordshire SG19 2LS",
    "addr:postcode":"sg19 2ls",
    "addr:street":"Horne Lane",
    "iso:country":"GB",
    "sg:address":"Horne Lane, Potton",
    "sg:city":"Sandy",
    "sg:classifiers":[
        {
            "category":"Real Estate",
            "subcategory":"Architect",
            "type":"Services"
        }
    ],
    "sg:phone":"+44 1767 261088",
    "sg:postcode":"SG19 2LS",
    "sg:province":"Bedfordshire",
    "wof:name":"Raybridge Engineering Ltd.",
    "wof:placetype":"venue"
},
  "geometry": {"coordinates":[-0.2146259993,52.1258468628],"type":"Point"}
}