{
  "type": "Feature",
  "properties": {
    "addr:full":"Unit 455 Carr Place, Walton Summit Centre, Bamber Bridge Preston Lancashire PR5 8AU",
    "addr:housenumber":"455",
    "addr:postcode":"pr5 8au",
    "addr:street":"Carr Place",
    "iso:country":"GB",
    "sg:address":"Unit 455 Carr Place, Walton Summit Centre, Bamber Bridge",
    "sg:city":"Preston",
    "sg:classifiers":[
        {
            "category":"Professional",
            "subcategory":"Engineering",
            "type":"Services"
        }
    ],
    "sg:phone":"+44 1772 626100",
    "sg:postcode":"PR5 8AU",
    "sg:province":"Lancashire",
    "sg:tags":[
        "contractor",
        "electrical",
        "engineer"
    ],
    "wof:name":"James Scott",
    "wof:placetype":"venue"
},
  "geometry": {"coordinates":[-2.6405539513,53.7210540771],"type":"Point"}
}