{
  "type": "Feature",
  "properties": {
    "iso:country":"GB",
    "sg:address":"Watts Lane",
    "sg:city":"Chislehurst",
    "sg:classifiers":[
        {
            "category":"Bars & Pubs",
            "type":"Food & Drink"
        }
    ],
    "sg:phone":"+44 20 8467 3070",
    "sg:postcode":"BR7 5PW",
    "sg:province":"Kent",
    "sg:tags":[
        "pubs",
        "inn"
    ],
    "wof:name":"The Tigers Head",
    "wof:placetype":"venue"
},
  "geometry": {"coordinates":[0.066091001,51.40965271],"type":"Point"}
}