{
  "type": "Feature",
  "properties": {
    "iso:country":"GB",
    "sg:address":"24 Ely Rd, Stretham",
    "sg:city":"Ely",
    "sg:classifiers":[
        {
            "category":"Autos & Motor Vehicles",
            "subcategory":"Motorcycle Sales",
            "type":"Retail Goods"
        }
    ],
    "sg:phone":"+44 1353 648632",
    "sg:postcode":"CB6 3JH",
    "sg:province":"Cambridgeshire",
    "sg:tags":[
        "component"
    ],
    "wof:name":"A R Brushwork",
    "wof:placetype":"venue"
},
  "geometry": {"coordinates":[0.2198359966,52.3527336121],"type":"Point"}
}