{
  "type": "Feature",
  "properties": {
    "addr:full":"869 Govan Road Glasgow Glasgow City G51 3DL",
    "addr:housenumber":"869",
    "addr:postcode":"g51 3dl",
    "addr:street":"Govan Road",
    "iso:country":"GB",
    "sg:address":"869 Govan Road",
    "sg:city":"Glasgow",
    "sg:classifiers":[
        {
            "category":"Professional",
            "type":"Services"
        },
        {
            "category":"Fast Food",
            "type":"Food & Drink"
        }
    ],
    "sg:phone":"+44 141 445 4401",
    "sg:postcode":"G51 3DL",
    "sg:province":"Glasgow City",
    "sg:tags":[
        "away",
        "take",
        "caterer"
    ],
    "wof:name":"MACPHEE'S FAST FOOD",
    "wof:placetype":"venue"
},
  "geometry": {"coordinates":[-4.315638,55.863766],"type":"Point"}
}