{
  "type": "Feature",
  "properties": {
    "iso:country":"GB",
    "sg:address":"1 Western Road",
    "sg:city":"Hailsham",
    "sg:classifiers":[
        {
            "category":"Health Services",
            "subcategory":"Doctor",
            "type":"Services"
        },
        {
            "category":"Health Services",
            "subcategory":"Clinic",
            "type":"Services"
        }
    ],
    "sg:phone":"+44 1323 441234",
    "sg:postcode":"BN27 3DG",
    "sg:province":"East Sussex",
    "sg:tags":[
        "nh",
        "practitioners"
    ],
    "wof:name":"Bridge Side Surgery",
    "wof:placetype":"venue"
},
  "geometry": {"coordinates":[0.252544,50.862995],"type":"Point"}
}