{
  "type": "Feature",
  "properties": {
    "addr:full":"2-4 Henwick Road, St Johns Worcester Worcestershire WR2 5NR",
    "addr:housenumber":"2-4",
    "addr:postcode":"wr2 5nr",
    "addr:street":"Henwick Road",
    "iso:country":"GB",
    "sg:address":"2-4 Henwick Road, St Johns",
    "sg:city":"Worcester",
    "sg:classifiers":[
        {
            "category":"Professional",
            "subcategory":"Credit Reporting & Collection",
            "type":"Services"
        }
    ],
    "sg:phone":"+44 1905 745544",
    "sg:postcode":"WR2 5NR",
    "sg:province":"Worcestershire",
    "sg:tags":[
        "agency",
        "reference"
    ],
    "wof:name":"Total Credit Reports Ltd.",
    "wof:placetype":"venue"
},
  "geometry": {"coordinates":[-2.2378959656,52.1932601929],"type":"Point"}
}