{
  "type": "Feature",
  "properties": {
    "addr:full":"60a High St, Dawley Telford Shropshire TF4 2EX",
    "addr:housenumber":"60a",
    "addr:postcode":"tf4 2ex",
    "addr:street":"High St",
    "iso:country":"GB",
    "sg:address":"60a High St, Dawley",
    "sg:city":"Telford",
    "sg:classifiers":[
        {
            "category":"Health Services",
            "subcategory":"Dentist",
            "type":"Services"
        }
    ],
    "sg:phone":"+44 1952 505353",
    "sg:postcode":"TF4 2EX",
    "sg:province":"Shropshire",
    "wof:name":"Dr R Holmes",
    "wof:placetype":"venue"
},
  "geometry": {"coordinates":[-2.466889,52.66367],"type":"Point"}
}