{
  "type": "Feature",
  "properties": {
    "addr:full":"Queen Street Carmarthen Carmarthenshire SA31 1JR",
    "addr:postcode":"sa31 1jr",
    "addr:street":"Queen Street",
    "iso:country":"GB",
    "sg:address":"Queen Street",
    "sg:city":"Carmarthen",
    "sg:classifiers":[
        {
            "category":"Bars & Pubs",
            "subcategory":"Nightclub",
            "type":"Food & Drink"
        }
    ],
    "sg:phone":"+44 1267 234378",
    "sg:postcode":"SA31 1JR",
    "sg:province":"Carmarthenshire",
    "sg:tags":[
        "club",
        "night"
    ],
    "wof:name":"Harveys Club",
    "wof:placetype":"venue"
},
  "geometry": {"coordinates":[-4.3051490784,51.856388092],"type":"Point"}
}