{
  "type": "Feature",
  "properties": {
    "iso:country":"GB",
    "sg:address":"36 New Dover Road",
    "sg:city":"Canterbury",
    "sg:classifiers":[
        {
            "category":"Travel",
            "subcategory":"Hotels & Motels",
            "type":"Entertainment"
        }
    ],
    "sg:phone":"+44 1227 760341",
    "sg:postcode":"CT1 3DU",
    "sg:province":"Kent",
    "wof:name":"Best Western Abbots Barton Hotel****",
    "wof:placetype":"venue"
},
  "geometry": {"coordinates":[1.0900499821,51.272983551],"type":"Point"}
}