{
  "type": "Feature",
  "properties": {
    "addr:full":"13 Penlline Road Cardiff Cardiff CF14 2AA",
    "addr:housenumber":"13",
    "addr:postcode":"cf14 2aa",
    "addr:street":"Penlline Road",
    "iso:country":"GB",
    "sg:address":"13 Penlline Road",
    "sg:city":"Cardiff",
    "sg:classifiers":[
        {
            "category":"Restaurant",
            "type":"Food & Drink"
        }
    ],
    "sg:phone":"+44 29 2061 5202",
    "sg:postcode":"CF14 2AA",
    "sg:province":"Cardiff",
    "sg:tags":[
        "indian"
    ],
    "wof:name":"Khazana",
    "wof:placetype":"venue"
},
  "geometry": {"coordinates":[-3.2204248905,51.5134124756],"type":"Point"}
}