{
  "type": "Feature",
  "properties": {
    "addr:full":"Briary House, Polton Bank, Lasswade Edinburgh City of Edinburgh EH18 1JW",
    "addr:postcode":"eh18 1jw",
    "addr:street":"Lasswade",
    "iso:country":"GB",
    "sg:address":"Briary House, Polton Bank, Lasswade",
    "sg:city":"Edinburgh",
    "sg:classifiers":[
        {
            "category":"Manufacturing",
            "subcategory":"Tools & Machinery",
            "type":"Manufacturing & Wholesale Goods"
        }
    ],
    "sg:phone":"+44 131 660 6900",
    "sg:postcode":"EH18 1JW",
    "sg:province":"City of Edinburgh",
    "sg:tags":[
        "society",
        "friendly"
    ],
    "wof:name":"S P I (Scot) Ltd.",
    "wof:placetype":"venue"
},
  "geometry": {"coordinates":[-3.114514,55.883186],"type":"Point"}
}