{
  "type": "Feature",
  "properties": {
    "addr:full":"36 Market Place Norwich Norfolk NR2 1RD",
    "addr:housenumber":"36",
    "addr:postcode":"nr2 1rd",
    "addr:street":"Market Place Norwich Norfolk",
    "iso:country":"GB",
    "sg:address":"36 Market Place",
    "sg:city":"Norwich",
    "sg:classifiers":[
        {
            "category":"Bars & Pubs",
            "type":"Food & Drink"
        }
    ],
    "sg:phone":"+44 1603 615892",
    "sg:postcode":"NR2 1RD",
    "sg:province":"Norfolk",
    "sg:tags":[
        "pubs",
        "inn"
    ],
    "wof:name":"Sir Garnet Wolsey",
    "wof:placetype":"venue"
},
  "geometry": {"coordinates":[1.2977750301,52.6290512085],"type":"Point"}
}