{
  "type": "Feature",
  "properties": {
    "iso:country":"GB",
    "sg:address":"3 Bicknell Road, Frimley",
    "sg:city":"Camberley",
    "sg:classifiers":[
        {
            "category":"Personal",
            "subcategory":"Beauty Salon",
            "type":"Services"
        }
    ],
    "sg:postcode":"GU16 8SZ",
    "sg:province":"Hampshire",
    "sg:tags":[
        "unisex",
        "hairdresser"
    ],
    "wof:name":"Sharons Mobile Hairdressers",
    "wof:placetype":"venue"
},
  "geometry": {"coordinates":[-0.7343230247,51.3208007812],"type":"Point"}
}