{
  "type": "Feature",
  "properties": {
    "iso:country":"GB",
    "sg:address":"Kingsway, Team Valley Trading Estate",
    "sg:city":"Gateshead",
    "sg:classifiers":[
        {
            "category":"Organizations",
            "subcategory":"Community Association",
            "type":"Services"
        }
    ],
    "sg:phone":"+44 191 482 4409",
    "sg:postcode":"NE11 0JS",
    "sg:province":"Tyne and Wear",
    "sg:tags":[
        "national"
    ],
    "wof:name":"The Association of International Accountants",
    "wof:placetype":"venue"
},
  "geometry": {"coordinates":[-1.61852,54.93343],"type":"Point"}
}