{
  "type": "Feature",
  "properties": {
    "addr:full":"Park Sqare Works, Saville Street Ossett West Yorkshire WF5 0JX",
    "addr:postcode":"wf5 0jx",
    "addr:street":"Park;Saville Street",
    "iso:country":"GB",
    "sg:address":"Park Sqare Works, Saville Street",
    "sg:city":"Ossett",
    "sg:classifiers":[
        {
            "category":"Professional",
            "subcategory":"Art Services",
            "type":"Services"
        }
    ],
    "sg:phone":"+44 1924 272703",
    "sg:postcode":"WF5 0JX",
    "sg:province":"West Yorkshire",
    "sg:tags":[
        "glass",
        "engraver"
    ],
    "wof:name":"Windrush Crystal",
    "wof:placetype":"venue"
},
  "geometry": {"coordinates":[-1.5878059864,53.6842346191],"type":"Point"}
}