{
  "type": "Feature",
  "properties": {
    "addr:full":"32 Hathaway Road Coventry Warwickshire CV4 9HW",
    "addr:housenumber":"32",
    "addr:postcode":"cv4 9hw",
    "addr:street":"Hathaway Road",
    "iso:country":"GB",
    "sg:address":"32 Hathaway Road",
    "sg:city":"Coventry",
    "sg:classifiers":[
        {
            "category":"Professional",
            "subcategory":"Detective & Security Services",
            "type":"Services"
        }
    ],
    "sg:phone":"+44 24 7647 4505",
    "sg:postcode":"CV4 9HW",
    "sg:province":"Warwickshire",
    "sg:tags":[
        "alarm",
        "burglar",
        "system"
    ],
    "wof:name":"Elite Security Systems",
    "wof:placetype":"venue"
},
  "geometry": {"coordinates":[-1.5942109823,52.399974823],"type":"Point"}
}