{
  "type": "Feature",
  "properties": {
    "addr:full":"Unit 4, Sheeplands Farm, Twyford Road Reading Berkshire RG10 8DL",
    "addr:housenumber":"unit 4;farm",
    "addr:postcode":"rg10 8dl",
    "addr:street":"Sheeplands;Twyford Road",
    "iso:country":"GB",
    "sg:address":"Unit 4, Sheeplands Farm, Twyford Road",
    "sg:city":"Reading",
    "sg:classifiers":[
        {
            "category":"Manufacturing",
            "subcategory":"Pottery",
            "type":"Manufacturing & Wholesale Goods"
        }
    ],
    "sg:phone":"+44 118 940 4089",
    "sg:postcode":"RG10 8DL",
    "sg:province":"Berkshire",
    "sg:tags":[
        "furnaces"
    ],
    "wof:name":"Acorn Pottery",
    "wof:placetype":"venue"
},
  "geometry": {"coordinates":[-0.9630089998,51.4535217285],"type":"Point"}
}