{
  "type": "Feature",
  "properties": {
    "iso:country":"GB",
    "sg:address":"54 Sandy Park Road",
    "sg:city":"Bristol",
    "sg:classifiers":[
        {
            "category":"Professional",
            "subcategory":"Business Services",
            "type":"Services"
        }
    ],
    "sg:postcode":"BS4 3PF",
    "sg:province":"City of Bristol",
    "sg:tags":[
        "fashion",
        "agent"
    ],
    "wof:name":"Breathe Clothing",
    "wof:placetype":"venue"
},
  "geometry": {"coordinates":[-2.553828,51.440414],"type":"Point"}
}