{
  "type": "Feature",
  "properties": {
    "addr:full":"170 King Street Aberdeen Aberdeen City AB24 5BD",
    "addr:housenumber":"170",
    "addr:postcode":"ab24 5bd",
    "addr:street":"King Street",
    "iso:country":"GB",
    "sg:address":"170 King Street",
    "sg:city":"Aberdeen",
    "sg:classifiers":[
        {
            "category":"Food & Beverages",
            "subcategory":"Liquor & Beverages",
            "type":"Retail Goods"
        }
    ],
    "sg:postcode":"AB24 5BD",
    "sg:province":"Aberdeen City",
    "sg:tags":[
        "beer",
        "wine",
        "spirit",
        "wines"
    ],
    "wof:name":"AL ASKAN SEE",
    "wof:placetype":"venue"
},
  "geometry": {"coordinates":[-2.094749,57.153999],"type":"Point"}
}