{
  "type": "Feature",
  "properties": {
    "iso:country":"GB",
    "sg:address":"Sherwood Road, Woodley",
    "sg:city":"Stockport",
    "sg:classifiers":[
        {
            "category":"Education",
            "subcategory":"School",
            "type":"Public Place"
        }
    ],
    "sg:phone":"+44 161 430 4658",
    "sg:postcode":"SK6 1LH",
    "sg:province":"Cheshire",
    "sg:tags":[
        "local",
        "authority"
    ],
    "wof:name":"Woodley Junior School",
    "wof:placetype":"venue"
},
  "geometry": {"coordinates":[-2.097542,53.426571],"type":"Point"}
}