{
  "type": "Feature",
  "properties": {
    "addr:full":"22 Little Oxhey Lane Watford Hertfordshire WD19 6FR",
    "addr:housenumber":"22",
    "addr:postcode":"wd19 6fr",
    "addr:street":"Little Oxhey Lane",
    "iso:country":"GB",
    "sg:address":"22 Little Oxhey Lane",
    "sg:city":"Watford",
    "sg:classifiers":[
        {
            "category":"Shopping",
            "subcategory":"News",
            "type":"Retail Goods"
        }
    ],
    "sg:phone":"+44 20 8428 1532",
    "sg:postcode":"WD19 6FR",
    "sg:province":"Hertfordshire",
    "sg:tags":[
        "newsagent"
    ],
    "wof:name":"Little Oxhey News",
    "wof:placetype":"venue"
},
  "geometry": {"coordinates":[-0.385847,51.619495],"type":"Point"}
}