{
  "type": "Feature",
  "properties": {
    "iso:country":"GB",
    "sg:address":"26 Wast Hill Gro",
    "sg:city":"Birmingham",
    "sg:classifiers":[
        {
            "category":"Retail",
            "subcategory":"Repair Shop",
            "type":"Services"
        }
    ],
    "sg:phone":"+44 121 458 1023",
    "sg:postcode":"B38 9RP",
    "sg:province":"West Midlands",
    "sg:tags":[
        "maintenance"
    ],
    "wof:name":"K Jordan Property Maintenance",
    "wof:placetype":"venue"
},
  "geometry": {"coordinates":[-1.932786,52.393536],"type":"Point"}
}