{
  "type": "Feature",
  "properties": {
    "addr:full":"Unit 18 Hilton Indust Est, Sutton La Derby Derbyshire DE65 5FE",
    "addr:housenumber":"unit 18",
    "addr:postcode":"de65 5fe",
    "addr:street":"La Derby",
    "iso:country":"GB",
    "sg:address":"Unit 18 Hilton Indust Est, Sutton La",
    "sg:city":"Derby",
    "sg:classifiers":[
        {
            "category":"Building & Trades",
            "subcategory":"Construction",
            "type":"Services"
        }
    ],
    "sg:phone":"+44 1332 830134",
    "sg:postcode":"DE65 5FE",
    "sg:province":"Derbyshire",
    "sg:tags":[
        "welder"
    ],
    "wof:name":"J W Gribbet",
    "wof:placetype":"venue"
},
  "geometry": {"coordinates":[-1.63692,52.874321],"type":"Point"}
}