{
  "type": "Feature",
  "properties": {
    "iso:country":"GB",
    "sg:address":"Bryn Y Mor, Turkey Shore Road",
    "sg:city":"Holyhead",
    "sg:classifiers":[
        {
            "category":"Manufacturing",
            "subcategory":"Lumber",
            "type":"Manufacturing & Wholesale Goods"
        }
    ],
    "sg:phone":"+44 1407 760266",
    "sg:postcode":"LL65 2HN",
    "sg:province":"Isle of Anglesey",
    "sg:tags":[
        "importer",
        "merchants",
        "agent",
        "timber"
    ],
    "wof:name":"Anglesey Timber Co. Ltd.",
    "wof:placetype":"venue"
},
  "geometry": {"coordinates":[-4.625484,53.309704],"type":"Point"}
}