{
  "type": "Feature",
  "properties": {
    "addr:full":"Rostrevor, Station Road, West Hallam Ilkeston Derbyshire DE7 6HB",
    "addr:postcode":"de7 6hb",
    "addr:street":"Station Road",
    "iso:country":"GB",
    "sg:address":"Rostrevor, Station Road, West Hallam",
    "sg:city":"Ilkeston",
    "sg:classifiers":[
        {
            "category":"Freight",
            "type":"Transportation"
        }
    ],
    "sg:phone":"+44 115 932 5450",
    "sg:postcode":"DE7 6HB",
    "sg:province":"Derbyshire",
    "sg:tags":[
        "haulage",
        "transport",
        "road"
    ],
    "wof:name":"G. NORMAN & SONS LTD",
    "wof:placetype":"venue"
},
  "geometry": {"coordinates":[-1.3589890003,52.9667549133],"type":"Point"}
}