{
  "type": "Feature",
  "properties": {
    "addr:full":"Cadfan Farm, Broad Oak Carmarthen Carmarthenshire SA32 8QW",
    "addr:postcode":"sa32 8qw",
    "addr:street":"Oak;Carmarthenshire",
    "iso:country":"GB",
    "sg:address":"Cadfan Farm, Broad Oak",
    "sg:city":"Carmarthen",
    "sg:classifiers":[
        {
            "category":"Farming",
            "subcategory":"Farm",
            "type":"Manufacturing & Wholesale Goods"
        }
    ],
    "sg:phone":"+44 1558 668285",
    "sg:postcode":"SA32 8QW",
    "sg:province":"Carmarthenshire",
    "sg:tags":[
        "mixed",
        "crop"
    ],
    "wof:name":"David T G Morgan",
    "wof:placetype":"venue"
},
  "geometry": {"coordinates":[-4.065111,51.885071],"type":"Point"}
}