{
  "type": "Feature",
  "properties": {
    "iso:country":"GB",
    "sg:address":"The Cotswold Business Village, London Road",
    "sg:city":"Moreton-in-marsh",
    "sg:classifiers":[
        {
            "category":"Home & Garden",
            "subcategory":"Garden Supply",
            "type":"Retail Goods"
        }
    ],
    "sg:postcode":"GL56 0JQ",
    "sg:province":"Gloucestershire",
    "sg:tags":[
        "merchant",
        "seed"
    ],
    "wof:name":"Cotswold Seeds Ltd.",
    "wof:placetype":"venue"
},
  "geometry": {"coordinates":[-1.703281,51.989727],"type":"Point"}
}