{
  "type": "Feature",
  "properties": {
    "iso:country":"GB",
    "sg:address":"Hall Court, Much Marcle",
    "sg:city":"Ledbury",
    "sg:classifiers":[
        {
            "category":"Farming",
            "subcategory":"Livestock Farm",
            "type":"Manufacturing & Wholesale Goods"
        }
    ],
    "sg:phone":"+44 1531 660605",
    "sg:postcode":"HR8 2PD",
    "sg:province":"Gloucestershire",
    "sg:tags":[
        "others"
    ],
    "wof:name":"G A & J M West",
    "wof:placetype":"venue"
},
  "geometry": {"coordinates":[-2.437939,52.033051],"type":"Point"}
}