{
  "type": "Feature",
  "properties": {
    "iso:country":"GB",
    "sg:address":"80 Castle Drive, Pevensey Bay",
    "sg:city":"Pevensey",
    "sg:classifiers":[
        {
            "category":"Banks & Credit Unions",
            "subcategory":"Financial Services",
            "type":"Services"
        }
    ],
    "sg:postcode":"BN24 6LA",
    "sg:province":"East Sussex",
    "sg:tags":[
        "consultant"
    ],
    "wof:name":"The A H B Partnership",
    "wof:placetype":"venue"
},
  "geometry": {"coordinates":[0.349723,50.812737],"type":"Point"}
}