{
  "type": "Feature",
  "properties": {
    "addr:full":"55 Portland Avenue Gravesend Kent DA12 5HJ",
    "addr:housenumber":"55",
    "addr:postcode":"da12 5hj",
    "addr:street":"Portland Avenue",
    "iso:country":"GB",
    "sg:address":"55 Portland Avenue",
    "sg:city":"Gravesend",
    "sg:classifiers":[
        {
            "category":"Professional",
            "subcategory":"Management & Consulting",
            "type":"Services"
        }
    ],
    "sg:phone":"+44 1474 335225",
    "sg:postcode":"DA12 5HJ",
    "sg:province":"Kent",
    "sg:tags":[
        "consultant",
        "business"
    ],
    "wof:name":"Malcolm Wilkins Associates",
    "wof:placetype":"venue"
},
  "geometry": {"coordinates":[0.3714709878,51.4300804138],"type":"Point"}
}