{
  "type": "Feature",
  "properties": {
    "iso:country":"GB",
    "sg:address":"Westgate Road",
    "sg:city":"Newcastle-upon-tyne",
    "sg:classifiers":[
        {
            "category":"Organizations",
            "subcategory":"Non-profit Organization",
            "type":"Services"
        }
    ],
    "sg:phone":"+44 191 226 1544",
    "sg:postcode":"NE4 6BE",
    "sg:province":"Tyne and Wear",
    "sg:tags":[
        "organisation",
        "voluntary",
        "charity"
    ],
    "wof:name":"Cancer Relief Macmillan Fund",
    "wof:placetype":"venue"
},
  "geometry": {"coordinates":[-1.642194,54.973854],"type":"Point"}
}