{
  "type": "Feature",
  "properties": {
    "addr:full":"147 Buckingham Gardens West Molesey Greater London KT8 1TW",
    "addr:housenumber":"147",
    "addr:postcode":"kt8 1tw",
    "addr:street":"Buckingham Gardens",
    "iso:country":"GB",
    "sg:address":"147 Buckingham Gardens",
    "sg:city":"West Molesey",
    "sg:classifiers":[
        {
            "category":"Building & Trades",
            "subcategory":"Construction",
            "type":"Services"
        }
    ],
    "sg:phone":"+44 20 8979 9616",
    "sg:postcode":"KT8 1TW",
    "sg:province":"Greater London",
    "sg:tags":[
        "decorator",
        "painter"
    ],
    "wof:name":"Keane's",
    "wof:placetype":"venue"
},
  "geometry": {"coordinates":[-0.367469,51.409149],"type":"Point"}
}