{
  "type": "Feature",
  "properties": {
    "addr:full":"502 High Road Wembley Greater London HA9 7BH",
    "addr:housenumber":"502",
    "addr:postcode":"ha9 7bh",
    "addr:street":"High Road",
    "iso:country":"GB",
    "sg:address":"502 High Road",
    "sg:city":"Wembley",
    "sg:classifiers":[
        {
            "category":"Shopping",
            "subcategory":"Shoes",
            "type":"Retail Goods"
        }
    ],
    "sg:phone":"+44 20 8902 9824",
    "sg:postcode":"HA9 7BH",
    "sg:province":"Greater London",
    "sg:tags":[
        "shop"
    ],
    "wof:name":"Barratts",
    "wof:placetype":"venue"
},
  "geometry": {"coordinates":[-0.2957000136,51.553024292],"type":"Point"}
}