{
  "type": "Feature",
  "properties": {
    "iso:country":"GB",
    "sg:address":"Slade Road",
    "sg:city":"Ryde",
    "sg:classifiers":[
        {
            "category":"Arena",
            "subcategory":"Sports Club",
            "type":"Entertainment"
        }
    ],
    "sg:phone":"+44 1983 565755",
    "sg:postcode":"PO33 1EG",
    "sg:province":"Isle of Wight",
    "wof:name":"Oakfield Football & Community Club",
    "wof:placetype":"venue"
},
  "geometry": {"coordinates":[-1.154207,50.720421],"type":"Point"}
}