{
  "type": "Feature",
  "properties": {
    "addr:full":"14 Leamington Road Broadway Gloucestershire WR12 7DZ",
    "addr:housenumber":"14",
    "addr:postcode":"wr12 7dz",
    "addr:street":"Leamington Road",
    "iso:country":"GB",
    "sg:address":"14 Leamington Road",
    "sg:city":"Broadway",
    "sg:classifiers":[
        {
            "category":"Manufacturing",
            "subcategory":"Building Materials",
            "type":"Manufacturing & Wholesale Goods"
        }
    ],
    "sg:phone":"+44 1386 852552",
    "sg:postcode":"WR12 7DZ",
    "sg:province":"Gloucestershire",
    "sg:tags":[
        "merchant",
        "builder"
    ],
    "wof:name":"Cotswold Building Supplies Ltd.",
    "wof:placetype":"venue"
},
  "geometry": {"coordinates":[-1.8564640284,52.0379676819],"type":"Point"}
}