{
  "type": "Feature",
  "properties": {
    "addr:full":"4 Bridge Street, Caversham Reading Berkshire RG4 8AA",
    "addr:housenumber":"4",
    "addr:postcode":"rg4 8aa",
    "addr:street":"Bridge Street",
    "iso:country":"GB",
    "sg:address":"4 Bridge Street, Caversham",
    "sg:city":"Reading",
    "sg:classifiers":[
        {
            "category":"Professional",
            "subcategory":"Computer Services",
            "type":"Services"
        }
    ],
    "sg:postcode":"RG4 8AA",
    "sg:province":"Berkshire",
    "sg:tags":[
        "consultant"
    ],
    "wof:name":"Neil Thomas & Associates",
    "wof:placetype":"venue"
},
  "geometry": {"coordinates":[-0.9769949913,51.4664611816],"type":"Point"}
}