{
  "type": "Feature",
  "properties": {
    "iso:country":"GB",
    "sg:address":"Damask Green, Weston",
    "sg:city":"Hitchin",
    "sg:classifiers":[
        {
            "category":"Arena",
            "subcategory":"Sports Club",
            "type":"Entertainment"
        }
    ],
    "sg:phone":"+44 1462 790501",
    "sg:postcode":"SG4 7BZ",
    "sg:province":"Hertfordshire",
    "wof:name":"Weston Cricket Club",
    "wof:placetype":"venue"
},
  "geometry": {"coordinates":[-0.169696,51.953316],"type":"Point"}
}