{
  "type": "Feature",
  "properties": {
    "addr:full":"Petticoat Lane Arcade, 102 Bold Street Liverpool Merseyside L1 4HY",
    "addr:housenumber":"102",
    "addr:postcode":"l1 4hy",
    "addr:street":"Petticoat Lane;Bold Street",
    "iso:country":"GB",
    "sg:address":"Petticoat Lane Arcade, 102 Bold Street",
    "sg:city":"Liverpool",
    "sg:classifiers":[
        {
            "category":"Personal",
            "subcategory":"Tattoo Parlor",
            "type":"Services"
        }
    ],
    "sg:phone":"+44 151 707 1343",
    "sg:postcode":"L1 4HY",
    "sg:province":"Merseyside",
    "sg:tags":[
        "tattooing",
        "piercing"
    ],
    "wof:name":"Bodz Peircing Jewellry",
    "wof:placetype":"venue"
},
  "geometry": {"coordinates":[-2.978481,53.409775],"type":"Point"}
}