{
  "type": "Feature",
  "properties": {
    "iso:country":"GB",
    "sg:address":"10 Tennyson Close, Rodeheath",
    "sg:city":"Stoke-on-trent",
    "sg:classifiers":[
        {
            "category":"Building & Trades",
            "subcategory":"Plumbing",
            "type":"Services"
        }
    ],
    "sg:postcode":"ST7 3TZ",
    "sg:province":"Cheshire",
    "sg:tags":[
        "central",
        "heating"
    ],
    "wof:name":"Cartwright Plumbing & Heating",
    "wof:placetype":"venue"
},
  "geometry": {"coordinates":[-2.296911,53.114635],"type":"Point"}
}