{
  "type": "Feature",
  "properties": {
    "iso:country":"GB",
    "sg:address":"53 Carfax Avenue, Tongham",
    "sg:city":"Farnham",
    "sg:classifiers":[
        {
            "category":"Professional",
            "subcategory":"Engineering",
            "type":"Services"
        }
    ],
    "sg:phone":"+44 1252 327323",
    "sg:postcode":"GU10 1BD",
    "sg:province":"Hampshire",
    "sg:tags":[
        "contractor",
        "electrical",
        "engineer"
    ],
    "wof:name":"R C Hatch Electrical Contractor",
    "wof:placetype":"venue"
},
  "geometry": {"coordinates":[-0.7323870063,51.2394256592],"type":"Point"}
}