{
  "type": "Feature",
  "properties": {
    "iso:country":"GB",
    "sg:address":"The Rink Bakery Herbert St, Stacksteads",
    "sg:city":"Bacup",
    "sg:classifiers":[
        {
            "category":"Home & Garden",
            "subcategory":"Kitchen Supply",
            "type":"Retail Goods"
        }
    ],
    "sg:phone":"+44 1706 879080",
    "sg:postcode":"OL13 0TY",
    "sg:province":"Lancashire",
    "sg:tags":[
        "equipment",
        "bakery"
    ],
    "wof:name":"C Cheadle & Son",
    "wof:placetype":"venue"
},
  "geometry": {"coordinates":[-2.2312040329,53.6918296814],"type":"Point"}
}