{
  "type": "Feature",
  "properties": {
    "iso:country":"GB",
    "sg:address":"Barrow Road, New Holland",
    "sg:city":"Barrow-upon-humber",
    "sg:classifiers":[
        {
            "category":"Bars & Pubs",
            "type":"Food & Drink"
        }
    ],
    "sg:phone":"+44 1469 533305",
    "sg:postcode":"DN19 7PH",
    "sg:province":"Lincolnshire",
    "sg:tags":[
        "pubs",
        "inn"
    ],
    "wof:name":"Magna Carter Inn",
    "wof:placetype":"venue"
},
  "geometry": {"coordinates":[-0.36091,53.701366],"type":"Point"}
}