{
  "type": "Feature",
  "properties": {
    "iso:country":"GB",
    "sg:address":"3 Lower Hall Lane",
    "sg:city":"Walsall",
    "sg:classifiers":[
        {
            "category":"Food & Beverages",
            "subcategory":"Specialty",
            "type":"Retail Goods"
        }
    ],
    "sg:phone":"+44 1922 636640",
    "sg:postcode":"WS1 1RH",
    "sg:province":"West Midlands",
    "sg:tags":[
        "product",
        "health"
    ],
    "wof:name":"D & R Ltd.",
    "wof:placetype":"venue"
},
  "geometry": {"coordinates":[-1.980797,52.583321],"type":"Point"}
}