{
  "type": "Feature",
  "properties": {
    "addr:full":"Wellington Road, West Buckland Wellington Devon TA21 9HY",
    "addr:postcode":"ta21 9hy",
    "addr:street":"Wellington Road",
    "iso:country":"GB",
    "sg:address":"Wellington Road, West Buckland",
    "sg:city":"Wellington",
    "sg:classifiers":[
        {
            "category":"Bars & Pubs",
            "type":"Food & Drink"
        }
    ],
    "sg:postcode":"TA21 9HY",
    "sg:province":"Devon",
    "sg:tags":[
        "pubs",
        "inn"
    ],
    "wof:name":"E Harrison",
    "wof:placetype":"venue"
},
  "geometry": {"coordinates":[-3.218319,50.961849],"type":"Point"}
}