{
  "type": "Feature",
  "properties": {
    "addr:full":"30 Hurstbourne Priors Whitchurch Hampshire RG28 7SE",
    "addr:housenumber":"30",
    "addr:postcode":"rg28 7se",
    "addr:street":"Hurstbourne Priors Whitchurch",
    "iso:country":"GB",
    "sg:address":"30 Hurstbourne Priors",
    "sg:city":"Whitchurch",
    "sg:classifiers":[
        {
            "category":"Retail",
            "subcategory":"Auto Repair",
            "type":"Services"
        }
    ],
    "sg:postcode":"RG28 7SE",
    "sg:province":"Hampshire",
    "sg:tags":[
        "modification",
        "garage"
    ],
    "wof:name":"Wilkinson,M,",
    "wof:placetype":"venue"
},
  "geometry": {"coordinates":[-1.336454,51.236626],"type":"Point"}
}