{
  "type": "Feature",
  "properties": {
    "addr:full":"B Company, 2 Priory Road London Greater London N8 7QT",
    "addr:housenumber":"2",
    "addr:postcode":"n8 7qt",
    "addr:street":"Priory Road",
    "iso:country":"GB",
    "sg:address":"B Company, 2 Priory Road",
    "sg:city":"London",
    "sg:classifiers":[
        {
            "category":"Government",
            "subcategory":"Office",
            "type":"Public Place"
        }
    ],
    "sg:phone":"+44 20 8340 7651",
    "sg:postcode":"N8 7QT",
    "sg:province":"Greater London",
    "sg:tags":[
        "armed",
        "reserve"
    ],
    "wof:name":"Territorial Army",
    "wof:placetype":"venue"
},
  "geometry": {"coordinates":[-0.1196400002,51.5875282288],"type":"Point"}
}