{
  "type": "Feature",
  "properties": {
    "addr:full":"Unit 6 Chapel Street, Long Eaton Nottingham Derbyshire NG10 1EQ",
    "addr:housenumber":"unit 6",
    "addr:postcode":"ng10 1eq",
    "addr:street":"Chapel Street",
    "iso:country":"GB",
    "sg:address":"Unit 6 Chapel Street, Long Eaton",
    "sg:city":"Nottingham",
    "sg:classifiers":[
        {
            "category":"Building & Trades",
            "subcategory":"Construction",
            "type":"Services"
        }
    ],
    "sg:phone":"+44 115 973 0701",
    "sg:postcode":"NG10 1EQ",
    "sg:province":"Derbyshire",
    "sg:tags":[
        "welder"
    ],
    "wof:name":"Frost Brothers Engineering Fabrications",
    "wof:placetype":"venue"
},
  "geometry": {"coordinates":[-1.268584013,52.8951148987],"type":"Point"}
}