{
  "type": "Feature",
  "properties": {
    "iso:country":"GB",
    "sg:address":"6 Merefield Road, Timperley",
    "sg:city":"Altrincham",
    "sg:classifiers":[
        {
            "category":"Personal",
            "subcategory":"Beauty Salon",
            "type":"Services"
        }
    ],
    "sg:phone":"+44 161 980 5362",
    "sg:postcode":"WA15 7DE",
    "sg:province":"Cheshire",
    "sg:tags":[
        "lady",
        "hairdresser"
    ],
    "wof:name":"Ruths Hair Design",
    "wof:placetype":"venue"
},
  "geometry": {"coordinates":[-2.311224,53.392773],"type":"Point"}
}