{
  "type": "Feature",
  "properties": {
    "iso:country":"GB",
    "sg:address":"Unit 9, Robins Drive",
    "sg:city":"Bridgwater",
    "sg:classifiers":[
        {
            "category":"Manufacturing",
            "subcategory":"Wood Products",
            "type":"Manufacturing & Wholesale Goods"
        }
    ],
    "sg:phone":"+44 1278 450020",
    "sg:postcode":"TA6 4DL",
    "sg:province":"Somerset",
    "sg:tags":[
        "packaging",
        "crate",
        "pallets"
    ],
    "wof:name":"Lawson Mardon Flexible",
    "wof:placetype":"venue"
},
  "geometry": {"coordinates":[-2.998979,51.134819],"type":"Point"}
}