{
  "type": "Feature",
  "properties": {
    "iso:country":"GB",
    "sg:address":"13b Dean Chapter Industrial Estate",
    "sg:city":"Ferryhill",
    "sg:classifiers":[
        {
            "category":"Personal",
            "type":"Services"
        }
    ],
    "sg:phone":"+44 1740 657722",
    "sg:postcode":"DL17 8LN",
    "sg:province":"Durham",
    "sg:tags":[
        "delivery"
    ],
    "wof:name":"Brian Adams Transport",
    "wof:placetype":"venue"
},
  "geometry": {"coordinates":[-1.5576519966,54.6888122559],"type":"Point"}
}