{
  "type": "Feature",
  "properties": {
    "addr:full":"104 Craven Park Road London Greater London NW10 8QD",
    "addr:housenumber":"104",
    "addr:postcode":"nw10 8qd",
    "addr:street":"Craven Park Road",
    "iso:country":"GB",
    "sg:address":"104 Craven Park Road",
    "sg:city":"London",
    "sg:classifiers":[
        {
            "category":"Fast Food",
            "type":"Food & Drink"
        },
        {
            "category":"Food & Beverages",
            "subcategory":"Meat & Fish",
            "type":"Retail Goods"
        }
    ],
    "sg:phone":"+44 20 8965 6628",
    "sg:postcode":"NW10 8QD",
    "sg:province":"Greater London",
    "sg:tags":[
        "shop",
        "chip"
    ],
    "wof:name":"Big Ben Fish Bar",
    "wof:placetype":"venue"
},
  "geometry": {"coordinates":[-0.253054,51.53989],"type":"Point"}
}