{
  "type": "Feature",
  "properties": {
    "addr:full":"Pontins Holiday Camp Sandy Bay, Kewstoke Weston-super-mare Somerset BS22 9UR",
    "addr:postcode":"bs22 9ur",
    "iso:country":"GB",
    "sg:address":"Pontins Holiday Camp Sandy Bay, Kewstoke",
    "sg:city":"Weston-super-mare",
    "sg:classifiers":[
        {
            "category":"Recreation",
            "subcategory":"Amusement Park",
            "type":"Entertainment"
        }
    ],
    "sg:phone":"+44 1934 417960",
    "sg:postcode":"BS22 9UR",
    "sg:province":"Somerset",
    "sg:tags":[
        "arcade"
    ],
    "wof:name":"Leisure Projects",
    "wof:placetype":"venue"
},
  "geometry": {"coordinates":[-2.955006,51.365665],"type":"Point"}
}