{
  "type": "Feature",
  "properties": {
    "addr:full":"56 Swan Centre Eastleigh Hampshire SO50 5SG",
    "addr:housenumber":"56",
    "addr:postcode":"so50 5sg",
    "addr:street":"Swan Centre",
    "iso:country":"GB",
    "sg:address":"56 Swan Centre",
    "sg:city":"Eastleigh",
    "sg:classifiers":[
        {
            "category":"Banks & Credit Unions",
            "subcategory":"Bank",
            "type":"Services"
        }
    ],
    "sg:postcode":"SO50 5SG",
    "sg:province":"Hampshire",
    "wof:name":"Halifax Plc",
    "wof:placetype":"venue"
},
  "geometry": {"coordinates":[-1.364119,50.964321],"type":"Point"}
}