{
  "type": "Feature",
  "properties": {
    "iso:country":"GB",
    "sg:address":"153 High St",
    "sg:city":"Hassocks",
    "sg:classifiers":[
        {
            "category":"Parking",
            "type":"Transportation"
        }
    ],
    "sg:phone":"+44 1273 835216",
    "sg:postcode":"BN6 9PU",
    "sg:province":"East Sussex",
    "sg:tags":[
        "car",
        "valet"
    ],
    "wof:name":"Southern Valeting Services",
    "wof:placetype":"venue"
},
  "geometry": {"coordinates":[-0.1747470051,50.9325294495],"type":"Point"}
}