{
  "type": "Feature",
  "properties": {
    "iso:country":"GB",
    "sg:address":"108 Hoads Wood Road",
    "sg:city":"Hastings",
    "sg:classifiers":[
        {
            "category":"Travel",
            "subcategory":"Travel Agent",
            "type":"Entertainment"
        }
    ],
    "sg:phone":"+44 1424 422075",
    "sg:postcode":"TN34 2BA",
    "sg:province":"East Sussex",
    "wof:name":"Angus Travel Services Ltd.",
    "wof:placetype":"venue"
},
  "geometry": {"coordinates":[0.592074,50.872532],"type":"Point"}
}