{
  "type": "Feature",
  "properties": {
    "iso:country":"GB",
    "sg:address":"252 Old Laira Road",
    "sg:city":"Plymouth",
    "sg:classifiers":[
        {
            "category":"Food & Beverages",
            "subcategory":"Groceries & Convenience Stores",
            "type":"Retail Goods"
        }
    ],
    "sg:phone":"+44 1752 667542",
    "sg:postcode":"PL3 6AF",
    "sg:province":"Devon",
    "wof:name":"Spar Stores",
    "wof:placetype":"venue"
},
  "geometry": {"coordinates":[-4.106719017,50.3838043213],"type":"Point"}
}