{
  "type": "Feature",
  "properties": {
    "addr:full":"The Old Shippon, Wall-under-heywood Church Stretton Shropshire SY6 7DS",
    "addr:postcode":"sy6 7ds",
    "iso:country":"GB",
    "sg:address":"The Old Shippon, Wall-under-heywood",
    "sg:city":"Church Stretton",
    "sg:classifiers":[
        {
            "category":"Professional",
            "type":"Services"
        }
    ],
    "sg:phone":"+44 1694 771771",
    "sg:postcode":"SY6 7DS",
    "sg:province":"Shropshire",
    "sg:tags":[
        "auctioneer"
    ],
    "wof:name":"Mullock Madeley Agricultural Auctioneers",
    "wof:placetype":"venue"
},
  "geometry": {"coordinates":[-2.8003339767,52.5376548767],"type":"Point"}
}