{
  "type": "Feature",
  "properties": {
    "addr:full":"Unit 2 The Forge, Camerton Hull East Riding of Yorkshire HU12 9NQ",
    "addr:housenumber":"unit 2",
    "addr:postcode":"hu12 9nq",
    "addr:street":"The Forge",
    "iso:country":"GB",
    "sg:address":"Unit 2 The Forge, Camerton",
    "sg:city":"Hull",
    "sg:classifiers":[
        {
            "category":"Retail",
            "subcategory":"Auto Repair",
            "type":"Services"
        }
    ],
    "sg:phone":"+44 1964 623121",
    "sg:postcode":"HU12 9NQ",
    "sg:province":"East Riding of Yorkshire",
    "sg:tags":[
        "modification",
        "garage"
    ],
    "wof:name":"Glen Carmichael",
    "wof:placetype":"venue"
},
  "geometry": {"coordinates":[-0.1358080059,53.7310333252],"type":"Point"}
}