{
  "type": "Feature",
  "properties": {
    "addr:full":"37 Myrtle Rd Leicester Leicestershire LE2 1FU",
    "addr:housenumber":"37",
    "addr:postcode":"le2 1fu",
    "addr:street":"Myrtle Rd",
    "iso:country":"GB",
    "sg:address":"37 Myrtle Rd",
    "sg:city":"Leicester",
    "sg:classifiers":[
        {
            "category":"Autos & Motor Vehicles",
            "subcategory":"Automobile Sales",
            "type":"Retail Goods"
        }
    ],
    "sg:phone":"+44 116 254 6495",
    "sg:postcode":"LE2 1FU",
    "sg:province":"Leicestershire",
    "sg:tags":[
        "car",
        "specialist",
        "sales",
        "classic"
    ],
    "wof:name":"Martin's Morris Minors",
    "wof:placetype":"venue"
},
  "geometry": {"coordinates":[-1.112318,52.627365],"type":"Point"}
}