{
  "type": "Feature",
  "properties": {
    "iso:country":"GB",
    "sg:address":"Greenway Garage, Greenway Lane",
    "sg:city":"Fakenham",
    "sg:classifiers":[
        {
            "category":"Autos & Motor Vehicles",
            "subcategory":"Automobile Sales",
            "type":"Retail Goods"
        }
    ],
    "sg:postcode":"NR21 8ET",
    "sg:province":"Norfolk",
    "sg:tags":[
        "car"
    ],
    "wof:name":"Cookes of Fakenham Ltd.",
    "wof:placetype":"venue"
},
  "geometry": {"coordinates":[0.850265,52.834694],"type":"Point"}
}