{
  "type": "Feature",
  "properties": {
    "addr:full":"22 Edinburgh Road Penicuik Midlothian EH26 8NW",
    "addr:housenumber":"22",
    "addr:postcode":"eh26 8nw",
    "addr:street":"Edinburgh Road",
    "iso:country":"GB",
    "sg:address":"22 Edinburgh Road",
    "sg:city":"Penicuik",
    "sg:classifiers":[
        {
            "category":"Shopping",
            "subcategory":"Pharmacy",
            "type":"Retail Goods"
        }
    ],
    "sg:phone":"+44 1968 676868",
    "sg:postcode":"EH26 8NW",
    "sg:province":"Midlothian",
    "sg:tags":[
        "store",
        "drug"
    ],
    "wof:name":"Beattie Chemist",
    "wof:placetype":"venue"
},
  "geometry": {"coordinates":[-3.220897,55.835571],"type":"Point"}
}