{
  "type": "Feature",
  "properties": {
    "addr:full":"4-5 Waddington Road St Albans Hertfordshire AL3 5EX",
    "addr:housenumber":"4-5",
    "addr:postcode":"al3 5ex",
    "addr:street":"Waddington Road",
    "iso:country":"GB",
    "sg:address":"4-5 Waddington Road",
    "sg:city":"St Albans",
    "sg:classifiers":[
        {
            "category":"Restaurant",
            "type":"Food & Drink"
        }
    ],
    "sg:phone":"+44 1727 856801",
    "sg:postcode":"AL3 5EX",
    "sg:province":"Hertfordshire",
    "wof:name":"la Tapa",
    "wof:placetype":"venue"
},
  "geometry": {"coordinates":[-0.339068,51.753139],"type":"Point"}
}