{
  "type": "Feature",
  "properties": {
    "iso:country":"GB",
    "sg:address":"Baryta House, 29 Victoria Avenue",
    "sg:city":"Southend-on-sea",
    "sg:classifiers":[
        {
            "category":"Real Estate",
            "subcategory":"Architect",
            "type":"Services"
        }
    ],
    "sg:postcode":"SS2 6AZ",
    "sg:province":"Essex",
    "wof:name":"Welton Bremner Partnership",
    "wof:placetype":"venue"
},
  "geometry": {"coordinates":[0.709172,51.542995],"type":"Point"}
}