{
  "type": "Feature",
  "properties": {
    "addr:full":"Tibberton Post Office, Plough Rd Droitwich Worcestershire WR9 7NL",
    "addr:postcode":"wr9 7nl",
    "addr:street":"Plough Rd",
    "iso:country":"GB",
    "sg:address":"Tibberton Post Office, Plough Rd",
    "sg:city":"Droitwich",
    "sg:classifiers":[
        {
            "category":"Food & Beverages",
            "subcategory":"Supermarket",
            "type":"Retail Goods"
        }
    ],
    "sg:postcode":"WR9 7NL",
    "sg:province":"Worcestershire",
    "wof:name":"G Jameson",
    "wof:placetype":"venue"
},
  "geometry": {"coordinates":[-2.1564879417,52.2680778503],"type":"Point"}
}