{
  "type": "Feature",
  "properties": {
    "addr:full":"67 High Street Wells Somerset BA5 2AG",
    "addr:housenumber":"67",
    "addr:postcode":"ba5 2ag",
    "addr:street":"High Street",
    "iso:country":"GB",
    "sg:address":"67 High Street",
    "sg:city":"Wells",
    "sg:classifiers":[
        {
            "category":"Shopping",
            "subcategory":"Gifts & Souvenirs",
            "type":"Retail Goods"
        }
    ],
    "sg:phone":"+44 1749 673018",
    "sg:postcode":"BA5 2AG",
    "sg:province":"Somerset",
    "sg:tags":[
        "shop",
        "poster",
        "card"
    ],
    "wof:name":"Scribbles (Wells) Ltd.",
    "wof:placetype":"venue"
},
  "geometry": {"coordinates":[-2.648092,51.208241],"type":"Point"}
}