{
  "type": "Feature",
  "properties": {
    "iso:country":"GB",
    "sg:address":"Loch Ct, Loch St",
    "sg:city":"Aberdeen",
    "sg:classifiers":[
        {
            "category":"Government",
            "subcategory":"Office",
            "type":"Public Place"
        }
    ],
    "sg:phone":"+44 1224 621586",
    "sg:postcode":"AB25 1DZ",
    "sg:province":"Aberdeen City",
    "sg:tags":[
        "local"
    ],
    "wof:name":"Aberdeen City Council",
    "wof:placetype":"venue"
},
  "geometry": {"coordinates":[-2.101369,57.152225],"type":"Point"}
}