{
  "type": "Feature",
  "properties": {
    "iso:country":"GB",
    "sg:address":"Unit 8 Westmans Industrial Estate, Love Lane",
    "sg:city":"Burnham-on-sea",
    "sg:classifiers":[
        {
            "category":"Manufacturing",
            "subcategory":"Petroleum Products",
            "type":"Manufacturing & Wholesale Goods"
        }
    ],
    "sg:phone":"+44 1278 786612",
    "sg:postcode":"TA8 1EB",
    "sg:province":"Somerset",
    "sg:tags":[
        "double",
        "glazing"
    ],
    "wof:name":"Ace Windows",
    "wof:placetype":"venue"
},
  "geometry": {"coordinates":[-2.993099,51.238449],"type":"Point"}
}