{
  "type": "Feature",
  "properties": {
    "addr:full":"Woodton Barn, Norwich Road, Woodton Bungay Norfolk NR35 2LU",
    "addr:postcode":"nr35 2lu",
    "addr:street":"Norwich Road Woodton Bungay",
    "iso:country":"GB",
    "sg:address":"Woodton Barn, Norwich Road, Woodton",
    "sg:city":"Bungay",
    "sg:classifiers":[
        {
            "category":"Professional",
            "subcategory":"Business Services",
            "type":"Services"
        },
        {
            "category":"Shopping",
            "type":"Retail Goods"
        }
    ],
    "sg:phone":"+44 1603 456444",
    "sg:postcode":"NR35 2LU",
    "sg:province":"Norfolk",
    "sg:tags":[
        "merchant",
        "agricultural"
    ],
    "wof:name":"NORFOLK LIQUID FEEDS LTD",
    "wof:placetype":"venue"
},
  "geometry": {"coordinates":[1.37437,52.495434],"type":"Point"}
}