{
  "type": "Feature",
  "properties": {
    "addr:full":"Muirheads Farm, Colliston Arbroath Angus DD11 3RN",
    "addr:postcode":"dd11 3rn",
    "addr:street":"Colliston",
    "iso:country":"GB",
    "sg:address":"Muirheads Farm, Colliston",
    "sg:city":"Arbroath",
    "sg:classifiers":[
        {
            "category":"Farming",
            "subcategory":"Farm",
            "type":"Manufacturing & Wholesale Goods"
        }
    ],
    "sg:phone":"+44 1241 890222",
    "sg:postcode":"DD11 3RN",
    "sg:province":"Angus",
    "sg:tags":[
        "mixed",
        "crop"
    ],
    "wof:name":"Frank Henderson",
    "wof:placetype":"venue"
},
  "geometry": {"coordinates":[-2.5908410549,56.5629081726],"type":"Point"}
}