{
  "type": "Feature",
  "properties": {
    "addr:full":"4 Ash Close Swaffham Norfolk PE37 7NH",
    "addr:housenumber":"4",
    "addr:postcode":"pe37 7nh",
    "addr:street":"Ash Close",
    "iso:country":"GB",
    "sg:address":"4 Ash Close",
    "sg:city":"Swaffham",
    "sg:classifiers":[
        {
            "category":"Travel",
            "subcategory":"Hotels & Motels",
            "type":"Entertainment"
        }
    ],
    "sg:postcode":"PE37 7NH",
    "sg:province":"Norfolk",
    "wof:name":"Strattons",
    "wof:placetype":"venue"
},
  "geometry": {"coordinates":[0.68712,52.648937],"type":"Point"}
}