{
  "type": "Feature",
  "properties": {
    "addr:full":"Homefield, Thurlestone Kingsbridge Devon TQ7 3NJ",
    "addr:postcode":"tq7 3nj",
    "iso:country":"GB",
    "sg:address":"Homefield, Thurlestone",
    "sg:city":"Kingsbridge",
    "sg:classifiers":[
        {
            "category":"Food & Beverages",
            "subcategory":"Supermarket",
            "type":"Retail Goods"
        }
    ],
    "sg:phone":"+44 1548 560230",
    "sg:postcode":"TQ7 3NJ",
    "sg:province":"Devon",
    "wof:name":"Gordon W H Bromfield",
    "wof:placetype":"venue"
},
  "geometry": {"coordinates":[-3.8570590019,50.2737884521],"type":"Point"}
}