{
  "type": "Feature",
  "properties": {
    "iso:country":"GB",
    "sg:address":"109 Prospect Lane",
    "sg:city":"Solihull",
    "sg:classifiers":[
        {
            "category":"Building & Trades",
            "subcategory":"Construction",
            "type":"Services"
        }
    ],
    "sg:phone":"+44 121 744 4683",
    "sg:postcode":"B91 1HT",
    "sg:province":"West Midlands",
    "sg:tags":[
        "builder"
    ],
    "wof:name":"Mills & Son",
    "wof:placetype":"venue"
},
  "geometry": {"coordinates":[-1.8097970486,52.4149208069],"type":"Point"}
}