{
  "type": "Feature",
  "properties": {
    "addr:full":"1-3 Keptie Street Arbroath Angus DD11 1RQ",
    "addr:housenumber":"1-3",
    "addr:postcode":"dd11 1rq",
    "addr:street":"Keptie Street",
    "iso:country":"GB",
    "sg:address":"1-3 Keptie Street",
    "sg:city":"Arbroath",
    "sg:classifiers":[
        {
            "category":"Home & Garden",
            "subcategory":"Household Appliances",
            "type":"Retail Goods"
        },
        {
            "category":"Retail",
            "subcategory":"Event Space",
            "type":"Services"
        },
        {
            "category":"Communications",
            "type":"Services"
        }
    ],
    "sg:phone":"+44 1241 872676",
    "sg:postcode":"DD11 1RQ",
    "sg:province":"Angus",
    "sg:tags":[
        "product",
        "tv",
        "domestic",
        "sales",
        "video",
        "radio",
        "electrical"
    ],
    "wof:name":"ALEX M MURRAY",
    "wof:placetype":"venue"
},
  "geometry": {"coordinates":[-2.5903389454,56.5594100952],"type":"Point"}
}