{
  "type": "Feature",
  "properties": {
    "iso:country":"GB",
    "sg:address":"47 Broadhurst Dr, Kennington",
    "sg:city":"Ashford",
    "sg:classifiers":[
        {
            "category":"Professional",
            "subcategory":"Employment Agencies",
            "type":"Services"
        }
    ],
    "sg:phone":"+44 1233 660000",
    "sg:postcode":"TN24 9RQ",
    "sg:province":"Kent",
    "sg:tags":[
        "consultant"
    ],
    "wof:name":"Congreve Project Services Ltd",
    "wof:placetype":"venue"
},
  "geometry": {"coordinates":[0.882195,51.171181],"type":"Point"}
}