{
  "type": "Feature",
  "properties": {
    "addr:full":"166 High Street Ryde Isle of Wight PO33 2HW",
    "addr:housenumber":"166",
    "addr:postcode":"po33 2hw",
    "addr:street":"High Street",
    "iso:country":"GB",
    "sg:address":"166 High Street",
    "sg:city":"Ryde",
    "sg:classifiers":[
        {
            "category":"Social Services",
            "subcategory":"Job Training",
            "type":"Services"
        },
        {
            "category":"Education",
            "subcategory":"Special Training",
            "type":"Public Place"
        }
    ],
    "sg:postcode":"PO33 2HW",
    "sg:province":"Isle of Wight",
    "sg:tags":[
        "product",
        "centre"
    ],
    "wof:name":"Comcare Training Agency",
    "wof:placetype":"venue"
},
  "geometry": {"coordinates":[-1.163331,50.728321],"type":"Point"}
}