{
  "type": "Feature",
  "properties": {
    "addr:full":"Grosvenor Ho, 39-41 High St Colchester Essex CO7 9BE",
    "addr:housenumber":"39-41",
    "addr:postcode":"co7 9be",
    "addr:street":"High St",
    "iso:country":"GB",
    "sg:address":"Grosvenor Ho, 39-41 High St",
    "sg:city":"Colchester",
    "sg:classifiers":[
        {
            "category":"Building & Trades",
            "subcategory":"Construction",
            "type":"Services"
        }
    ],
    "sg:phone":"+44 1206 822225",
    "sg:postcode":"CO7 9BE",
    "sg:province":"Essex",
    "sg:tags":[
        "bricklaying"
    ],
    "wof:name":"Wivenhoe Brickwork Ltd",
    "wof:placetype":"venue"
},
  "geometry": {"coordinates":[0.95887,51.855431],"type":"Point"}
}