{
  "type": "Feature",
  "properties": {
    "addr:full":"217 Elmhurst Mansions, Elmhurst Street London Greater London SW4 6HH",
    "addr:housenumber":"217",
    "addr:postcode":"sw4 6hh",
    "addr:street":"Mansions Elmhurst Street",
    "iso:country":"GB",
    "sg:address":"217 Elmhurst Mansions, Elmhurst Street",
    "sg:city":"London",
    "sg:classifiers":[
        {
            "category":"Professional",
            "subcategory":"Management & Consulting",
            "type":"Services"
        }
    ],
    "sg:phone":"+44 20 7498 4426",
    "sg:postcode":"SW4 6HH",
    "sg:province":"Greater London",
    "sg:tags":[
        "consultant",
        "business"
    ],
    "wof:name":"Teambase",
    "wof:placetype":"venue"
},
  "geometry": {"coordinates":[-0.136172995,51.4666748047],"type":"Point"}
}