{
  "type": "Feature",
  "properties": {
    "addr:full":"26 Knowles Street, Rishton Blackburn Lancashire BB1 4JA",
    "addr:housenumber":"26",
    "addr:postcode":"bb1 4ja",
    "addr:street":"Knowles Street",
    "iso:country":"GB",
    "sg:address":"26 Knowles Street, Rishton",
    "sg:city":"Blackburn",
    "sg:classifiers":[
        {
            "category":"Professional",
            "subcategory":"Business Services",
            "type":"Services"
        },
        {
            "category":"Manufacturing",
            "subcategory":"Musical Instruments",
            "type":"Manufacturing & Wholesale Goods"
        }
    ],
    "sg:phone":"+44 1254 886555",
    "sg:postcode":"BB1 4JA",
    "sg:province":"Lancashire",
    "sg:tags":[
        "manufacturers'",
        "agent",
        "manufacturer"
    ],
    "wof:name":"Anwill Instrument Co",
    "wof:placetype":"venue"
},
  "geometry": {"coordinates":[-2.416179,53.767082],"type":"Point"}
}