{
  "type": "Feature",
  "properties": {
    "iso:country":"GB",
    "sg:address":"P O Box 3285",
    "sg:city":"Tamworth",
    "sg:classifiers":[
        {
            "category":"Professional",
            "subcategory":"Printing & Photocopies",
            "type":"Services"
        }
    ],
    "sg:postcode":"B77 5TG",
    "sg:province":"Staffordshire",
    "sg:tags":[
        "plate",
        "printer",
        "lithographic",
        "maker"
    ],
    "wof:name":"Virgin Print Services",
    "wof:placetype":"venue"
},
  "geometry": {"coordinates":[-1.661549,52.603828],"type":"Point"}
}