{
  "type": "Feature",
  "properties": {
    "iso:country":"GB",
    "sg:address":"Mostyn Road, Greenfields",
    "sg:city":"Holywell",
    "sg:classifiers":[
        {
            "category":"Health Services",
            "subcategory":"Nursing And Care Facility",
            "type":"Services"
        }
    ],
    "sg:phone":"+44 1352 714500",
    "sg:postcode":"CH8 9DN",
    "sg:province":"Denbighshire",
    "sg:tags":[
        "home"
    ],
    "wof:name":"Plas Newydd Nursing Home",
    "wof:placetype":"venue"
},
  "geometry": {"coordinates":[-3.225195,53.274548],"type":"Point"}
}