{
  "type": "Feature",
  "properties": {
    "iso:country":"GB",
    "sg:address":"36 Dean Road",
    "sg:city":"South Shields",
    "sg:classifiers":[
        {
            "category":"Fast Food",
            "type":"Food & Drink"
        }
    ],
    "sg:phone":"+44 191 425 0113",
    "sg:postcode":"NE33 3PT",
    "sg:province":"Tyne and Wear",
    "sg:tags":[
        "away",
        "meal",
        "outlet",
        "take"
    ],
    "wof:name":"Sophies Sandwich Shop",
    "wof:placetype":"venue"
},
  "geometry": {"coordinates":[-1.4239259958,54.986869812],"type":"Point"}
}