{
  "type": "Feature",
  "properties": {
    "addr:full":"Regal House, Manwick Road Felixstowe Suffolk IP11 2DQ",
    "addr:postcode":"ip11 2dq",
    "addr:street":"Manwick Road",
    "iso:country":"GB",
    "sg:address":"Regal House, Manwick Road",
    "sg:city":"Felixstowe",
    "sg:classifiers":[
        {
            "category":"Recreation",
            "subcategory":"Amusement Park",
            "type":"Entertainment"
        }
    ],
    "sg:phone":"+44 1394 284680",
    "sg:postcode":"IP11 2DQ",
    "sg:province":"Suffolk",
    "sg:tags":[
        "arcade",
        "activity"
    ],
    "wof:name":"Family Amusements Ltd.",
    "wof:placetype":"venue"
},
  "geometry": {"coordinates":[1.33927,51.954311],"type":"Point"}
}