{
  "type": "Feature",
  "properties": {
    "iso:country":"GB",
    "sg:address":"29-39 Glendale Gdns",
    "sg:city":"Leigh-on-sea",
    "sg:classifiers":[
        {
            "category":"Building & Trades",
            "subcategory":"Construction",
            "type":"Services"
        }
    ],
    "sg:phone":"+44 1702 480303",
    "sg:postcode":"SS9 2AT",
    "sg:province":"Essex",
    "sg:tags":[
        "roofing"
    ],
    "wof:name":"Seeco (Roof Tiling) Ltd",
    "wof:placetype":"venue"
},
  "geometry": {"coordinates":[0.6532790065,51.5444869995],"type":"Point"}
}