{
  "type": "Feature",
  "properties": {
    "addr:full":"32 Lindsey Street Epping Essex CM16 6RD",
    "addr:housenumber":"32",
    "addr:postcode":"cm16 6rd",
    "addr:street":"Lindsey Street",
    "iso:country":"GB",
    "sg:address":"32 Lindsey Street",
    "sg:city":"Epping",
    "sg:classifiers":[
        {
            "category":"Retail",
            "subcategory":"Driving School",
            "type":"Services"
        }
    ],
    "sg:postcode":"CM16 6RD",
    "sg:province":"Essex",
    "wof:name":"Epping School of Motoring",
    "wof:placetype":"venue"
},
  "geometry": {"coordinates":[0.112469,51.706947],"type":"Point"}
}