{
  "type": "Feature",
  "properties": {
    "iso:country":"GB",
    "sg:address":"88 Northern Road, Cosham",
    "sg:city":"Portsmouth",
    "sg:classifiers":[
        {
            "category":"Professional",
            "subcategory":"Accounting & Tax Preparation",
            "type":"Services"
        }
    ],
    "sg:phone":"+44 23 9238 3207",
    "sg:postcode":"PO6 3ER",
    "sg:province":"Hampshire",
    "sg:tags":[
        "accountant"
    ],
    "wof:name":"Rothman Pantall & Co.",
    "wof:placetype":"venue"
},
  "geometry": {"coordinates":[-1.067334,50.847389],"type":"Point"}
}