{
  "type": "Feature",
  "properties": {
    "addr:full":"5 Golden Cross Parade, Ashingdon Rd Rochford Essex SS4 1UB",
    "addr:housenumber":"5",
    "addr:postcode":"ss4 1ub",
    "addr:street":"Golden Cross Parade Ashingdon Rd",
    "iso:country":"GB",
    "sg:address":"5 Golden Cross Parade, Ashingdon Rd",
    "sg:city":"Rochford",
    "sg:classifiers":[
        {
            "category":"Food & Beverages",
            "subcategory":"Bakery",
            "type":"Retail Goods"
        }
    ],
    "sg:phone":"+44 1702 541853",
    "sg:postcode":"SS4 1UB",
    "sg:province":"Essex",
    "sg:tags":[
        "baker"
    ],
    "wof:name":"The Cottage Bakery",
    "wof:placetype":"venue"
},
  "geometry": {"coordinates":[0.7013890147,51.5832214355],"type":"Point"}
}