{
  "type": "Feature",
  "properties": {
    "iso:country":"GB",
    "sg:address":"22 Regent Street",
    "sg:city":"Rugby",
    "sg:classifiers":[
        {
            "category":"Shopping",
            "subcategory":"Florist",
            "type":"Retail Goods"
        }
    ],
    "sg:phone":"+44 1788 543250",
    "sg:postcode":"CV21 2PZ",
    "sg:province":"Warwickshire",
    "wof:name":"Townsend the Flower Shop",
    "wof:placetype":"venue"
},
  "geometry": {"coordinates":[-1.260725,52.373909],"type":"Point"}
}