{
  "type": "Feature",
  "properties": {
    "addr:full":"47 Albert Road Evesham Gloucestershire WR11 4LA",
    "addr:housenumber":"47",
    "addr:postcode":"wr11 4la",
    "addr:street":"Albert Road",
    "iso:country":"GB",
    "sg:address":"47 Albert Road",
    "sg:city":"Evesham",
    "sg:classifiers":[
        {
            "category":"Personal",
            "type":"Services"
        }
    ],
    "sg:phone":"+44 1386 41668",
    "sg:postcode":"WR11 4LA",
    "sg:province":"Gloucestershire",
    "sg:tags":[
        "tailor"
    ],
    "wof:name":"Avon Classics",
    "wof:placetype":"venue"
},
  "geometry": {"coordinates":[-1.9517630339,52.095790863],"type":"Point"}
}