{
  "type": "Feature",
  "properties": {
    "addr:full":"8-10 Norwich Common Wymondham Norfolk NR18 0SP",
    "addr:housenumber":"8-10",
    "addr:postcode":"nr18 0sp",
    "addr:street":"Norwich Common",
    "iso:country":"GB",
    "sg:address":"8-10 Norwich Common",
    "sg:city":"Wymondham",
    "sg:classifiers":[
        {
            "category":"Retail",
            "subcategory":"Auto Repair",
            "type":"Services"
        }
    ],
    "sg:phone":"+44 1603 813400",
    "sg:postcode":"NR18 0SP",
    "sg:province":"Norfolk",
    "sg:tags":[
        "car",
        "upholsterer"
    ],
    "wof:name":"Car Interior Care & Upholstery Service",
    "wof:placetype":"venue"
},
  "geometry": {"coordinates":[1.1480220556,52.5844802856],"type":"Point"}
}