{
  "type": "Feature",
  "properties": {
    "iso:country":"GB",
    "sg:address":"12 Brookway",
    "sg:city":"Wirral",
    "sg:classifiers":[
        {
            "category":"Home & Garden",
            "subcategory":"Household Appliances",
            "type":"Retail Goods"
        }
    ],
    "sg:phone":"+44 151 678 3983",
    "sg:postcode":"CH60 7RE",
    "sg:province":"Merseyside",
    "sg:tags":[
        "electrical"
    ],
    "wof:name":"Appliance Repairs",
    "wof:placetype":"venue"
},
  "geometry": {"coordinates":[-3.112346,53.385685],"type":"Point"}
}