{
  "type": "Feature",
  "properties": {
    "addr:full":"65 Debden Road Saffron Walden Essex CB11 4AL",
    "addr:housenumber":"65",
    "addr:postcode":"cb11 4al",
    "addr:street":"Debden Road",
    "iso:country":"GB",
    "sg:address":"65 Debden Road",
    "sg:city":"Saffron Walden",
    "sg:classifiers":[
        {
            "category":"Farming",
            "subcategory":"Nursery",
            "type":"Manufacturing & Wholesale Goods"
        }
    ],
    "sg:phone":"+44 1799 527235",
    "sg:postcode":"CB11 4AL",
    "sg:province":"Essex",
    "sg:tags":[
        "creche"
    ],
    "wof:name":"Gibson House Nursery",
    "wof:placetype":"venue"
},
  "geometry": {"coordinates":[0.2409459949,52.0149650574],"type":"Point"}
}