{
  "type": "Feature",
  "properties": {
    "iso:country":"GB",
    "sg:address":"3 Harrington Road",
    "sg:city":"London",
    "sg:classifiers":[
        {
            "category":"Restaurant",
            "type":"Food & Drink"
        }
    ],
    "sg:phone":"+44 20 7584 4114",
    "sg:postcode":"SW7 3ES",
    "sg:province":"Greater London",
    "sg:tags":[
        "indian"
    ],
    "wof:name":"Ali & Suol Khan",
    "wof:placetype":"venue"
},
  "geometry": {"coordinates":[-0.176279,51.494068],"type":"Point"}
}