{
  "type": "Feature",
  "properties": {
    "iso:country":"GB",
    "sg:address":"Technology Management Centre, Moss Lane View",
    "sg:city":"Skelmersdale",
    "sg:classifiers":[
        {
            "category":"Insurance",
            "subcategory":"Insurance Agent",
            "type":"Services"
        }
    ],
    "sg:phone":"+44 1695 556688",
    "sg:postcode":"WN8 9TL",
    "sg:province":"Lancashire",
    "sg:tags":[
        "broker"
    ],
    "wof:name":"Risk Management & Insurance Services",
    "wof:placetype":"venue"
},
  "geometry": {"coordinates":[-2.7757840157,53.5494041443],"type":"Point"}
}