{
  "type": "Feature",
  "properties": {
    "iso:country":"GB",
    "sg:address":"150 Morningside Rd",
    "sg:city":"Edinburgh",
    "sg:classifiers":[
        {
            "category":"Health Services",
            "subcategory":"Dentist",
            "type":"Services"
        }
    ],
    "sg:phone":"+44 131 447 6431",
    "sg:postcode":"EH10 4AX",
    "sg:province":"City of Edinburgh",
    "wof:name":"Susan Graham-Marr",
    "wof:placetype":"venue"
},
  "geometry": {"coordinates":[-3.207379,55.936981],"type":"Point"}
}