{
  "type": "Feature",
  "properties": {
    "addr:full":"Arreton Cottage, Station Rd Moreton In Marsh Gloucestershire GL56 9DT",
    "addr:postcode":"gl56 9dt",
    "addr:street":"Station Rd",
    "iso:country":"GB",
    "sg:address":"Arreton Cottage, Station Rd",
    "sg:city":"Moreton In Marsh",
    "sg:classifiers":[
        {
            "category":"Building & Trades",
            "subcategory":"Construction",
            "type":"Services"
        }
    ],
    "sg:phone":"+44 1386 701077",
    "sg:postcode":"GL56 9DT",
    "sg:province":"Gloucestershire",
    "sg:tags":[
        "builder"
    ],
    "wof:name":"John Bayliss",
    "wof:placetype":"venue"
},
  "geometry": {"coordinates":[-1.703281,51.989727],"type":"Point"}
}