{
  "type": "Feature",
  "properties": {
    "iso:country":"GB",
    "sg:address":"11 Morlan Road",
    "sg:city":"Blackburn",
    "sg:classifiers":[
        {
            "category":"Banks & Credit Unions",
            "subcategory":"Bank",
            "type":"Services"
        }
    ],
    "sg:postcode":"BB2 4SA",
    "sg:province":"Lancashire",
    "sg:tags":[
        "stocktaking",
        "inventory"
    ],
    "wof:name":"Raymond Hacking",
    "wof:placetype":"venue"
},
  "geometry": {"coordinates":[-2.498065,53.724091],"type":"Point"}
}