{
  "type": "Feature",
  "properties": {
    "iso:country":"GB",
    "sg:address":"23 Springfield",
    "sg:city":"Tewkesbury",
    "sg:classifiers":[
        {
            "category":"Professional",
            "subcategory":"Engineering",
            "type":"Services"
        },
        {
            "category":"Building & Trades",
            "subcategory":"Electrical",
            "type":"Services"
        }
    ],
    "sg:phone":"+44 1684 772666",
    "sg:postcode":"GL20 8EP",
    "sg:province":"Gloucestershire",
    "sg:tags":[
        "engineer",
        "electrician",
        "contractor"
    ],
    "wof:name":"Tombs & Crilley",
    "wof:placetype":"venue"
},
  "geometry": {"coordinates":[-2.135705,51.997204],"type":"Point"}
}