{
  "type": "Feature",
  "properties": {
    "addr:full":"Underwood House Crawley Surrey RH10 1LU",
    "addr:postcode":"rh10 1lu",
    "iso:country":"GB",
    "sg:address":"Underwood House",
    "sg:city":"Crawley",
    "sg:classifiers":[
        {
            "category":"Real Estate",
            "subcategory":"Real Estate Agent",
            "type":"Services"
        }
    ],
    "sg:postcode":"RH10 1LU",
    "sg:province":"Surrey",
    "wof:name":"Underwood Payne & Co.",
    "wof:placetype":"venue"
},
  "geometry": {"coordinates":[-0.1847530007,51.1184577942],"type":"Point"}
}