{
  "type": "Feature",
  "properties": {
    "addr:full":"Suite 401 National Bank Building, 24 Fenwick St Liverpool Merseyside L2 7NE",
    "addr:housenumber":"suite 401;24",
    "addr:postcode":"l2 7ne",
    "addr:street":"Fenwick St",
    "iso:country":"GB",
    "sg:address":"Suite 401 National Bank Building, 24 Fenwick St",
    "sg:city":"Liverpool",
    "sg:classifiers":[
        {
            "category":"Social Services",
            "type":"Services"
        }
    ],
    "sg:phone":"+44 151 474 3383",
    "sg:postcode":"L2 7NE",
    "sg:province":"Merseyside",
    "sg:tags":[
        "helplines"
    ],
    "wof:name":"Seekers (UK) Bureau Of Lost Children & Missing Persons",
    "wof:placetype":"venue"
},
  "geometry": {"coordinates":[-2.9914200306,53.4051513672],"type":"Point"}
}