{
  "type": "Feature",
  "properties": {
    "addr:full":"24 Church Street Rickmansworth Hertfordshire WD3 1DD",
    "addr:housenumber":"24",
    "addr:postcode":"wd3 1dd",
    "addr:street":"Church Street",
    "iso:country":"GB",
    "sg:address":"24 Church Street",
    "sg:city":"Rickmansworth",
    "sg:classifiers":[
        {
            "category":"Building & Trades",
            "subcategory":"Construction",
            "type":"Services"
        }
    ],
    "sg:postcode":"WD3 1DD",
    "sg:province":"Hertfordshire",
    "sg:tags":[
        "builder"
    ],
    "wof:name":"Southbell Ltd",
    "wof:placetype":"venue"
},
  "geometry": {"coordinates":[-0.4689069986,51.6376876831],"type":"Point"}
}