{
  "type": "Feature",
  "properties": {
    "addr:full":"5a High Street Tain Highland IV19 1AB",
    "addr:housenumber":"5a",
    "addr:postcode":"iv19 1ab",
    "addr:street":"High Street",
    "iso:country":"GB",
    "sg:address":"5a High Street",
    "sg:city":"Tain",
    "sg:classifiers":[
        {
            "category":"Recreation",
            "subcategory":"Gun Range",
            "type":"Entertainment"
        }
    ],
    "sg:phone":"+44 1862 893333",
    "sg:postcode":"IV19 1AB",
    "sg:province":"Highland",
    "sg:tags":[
        "operator",
        "tour"
    ],
    "wof:name":"Trans European Holidays",
    "wof:placetype":"venue"
},
  "geometry": {"coordinates":[-4.055191,57.811798],"type":"Point"}
}