{
  "type": "Feature",
  "properties": {
    "iso:country":"GB",
    "sg:address":"1 Oakfield Road",
    "sg:city":"Benfleet",
    "sg:classifiers":[
        {
            "category":"Building & Trades",
            "subcategory":"Construction",
            "type":"Services"
        }
    ],
    "sg:phone":"+44 1268 750988",
    "sg:postcode":"SS7 5NS",
    "sg:province":"Essex",
    "sg:tags":[
        "builder"
    ],
    "wof:name":"Parkways Builders",
    "wof:placetype":"venue"
},
  "geometry": {"coordinates":[0.5510650277,51.5578079224],"type":"Point"}
}