{
  "type": "Feature",
  "properties": {
    "iso:country":"GB",
    "sg:address":"24 Edinburgh Road",
    "sg:city":"Northampton",
    "sg:classifiers":[
        {
            "category":"Place Of Worship",
            "type":"Public Place"
        }
    ],
    "sg:phone":"+44 1604 711468",
    "sg:postcode":"NN2 6PH",
    "sg:province":"Northamptonshire",
    "wof:name":"Holy Trinity & St.Pauls Church",
    "wof:placetype":"venue"
},
  "geometry": {"coordinates":[-0.895878,52.255482],"type":"Point"}
}