{
  "type": "Feature",
  "properties": {
    "iso:country":"GB",
    "sg:address":"Amundsen House, Factory Road",
    "sg:city":"Hinckley",
    "sg:classifiers":[
        {
            "category":"Shopping",
            "subcategory":"Clothing, Apparel, & Fashions",
            "type":"Retail Goods"
        }
    ],
    "sg:phone":"+44 1455 633937",
    "sg:postcode":"LE10 0DP",
    "sg:province":"Leicestershire",
    "sg:tags":[
        "clothing",
        "fabric"
    ],
    "wof:name":"Flint Casual Wear",
    "wof:placetype":"venue"
},
  "geometry": {"coordinates":[-1.37077,52.547688],"type":"Point"}
}