{
  "type": "Feature",
  "properties": {
    "iso:country":"GB",
    "sg:address":"62 Lowndes Way, Winslow",
    "sg:city":"Buckingham",
    "sg:classifiers":[
        {
            "category":"Retail",
            "subcategory":"Repair Shop",
            "type":"Services"
        }
    ],
    "sg:phone":"+44 1296 712886",
    "sg:postcode":"MK18 3EL",
    "sg:province":"Buckinghamshire",
    "sg:tags":[
        "radio",
        "television",
        "video"
    ],
    "wof:name":"Winslow T V Services",
    "wof:placetype":"venue"
},
  "geometry": {"coordinates":[-0.8798199892,51.9471702576],"type":"Point"}
}