{
  "type": "Feature",
  "properties": {
    "addr:full":"The Print Centre, Johnson Street, Howebridge Manchester Greater Manchester M46 0RB",
    "addr:postcode":"m46 0rb",
    "addr:street":"Johnson Street",
    "iso:country":"GB",
    "sg:address":"The Print Centre, Johnson Street, Howebridge",
    "sg:city":"Manchester",
    "sg:classifiers":[
        {
            "category":"Professional",
            "subcategory":"Printing & Photocopies",
            "type":"Services"
        }
    ],
    "sg:phone":"+44 1942 873961",
    "sg:postcode":"M46 0RB",
    "sg:province":"Greater Manchester",
    "sg:tags":[
        "printer"
    ],
    "wof:name":"Murbros Printers Ltd",
    "wof:placetype":"venue"
},
  "geometry": {"coordinates":[-2.5104100704,53.5150184631],"type":"Point"}
}