{
  "type": "Feature",
  "properties": {
    "addr:full":"Ayscough Street Grimsby Lincolnshire DN31 1TG",
    "addr:postcode":"dn31 1tg",
    "addr:street":"Ayscough Street",
    "iso:country":"GB",
    "sg:address":"Ayscough Street",
    "sg:city":"Grimsby",
    "sg:classifiers":[
        {
            "category":"Wholesale",
            "subcategory":"Scrap",
            "type":"Manufacturing & Wholesale Goods"
        },
        {
            "category":"Wholesale",
            "subcategory":"Auto Parts",
            "type":"Manufacturing & Wholesale Goods"
        }
    ],
    "sg:phone":"+44 1472 340403",
    "sg:postcode":"DN31 1TG",
    "sg:province":"Lincolnshire",
    "sg:tags":[
        "car",
        "breaker",
        "dismantlers"
    ],
    "wof:name":"Moore & Pinder",
    "wof:placetype":"venue"
},
  "geometry": {"coordinates":[-0.0922589973,53.5720939636],"type":"Point"}
}