{
  "type": "Feature",
  "properties": {
    "iso:country":"GB",
    "sg:address":"Norton Street",
    "sg:city":"Nottingham",
    "sg:classifiers":[
        {
            "category":"Shopping",
            "subcategory":"Books",
            "type":"Retail Goods"
        },
        {
            "category":"Organizations",
            "subcategory":"Religious Organization",
            "type":"Services"
        }
    ],
    "sg:postcode":"NG7 3HR",
    "sg:province":"Nottinghamshire",
    "sg:tags":[
        "organisation"
    ],
    "wof:name":"I V P Book Centre",
    "wof:placetype":"venue"
},
  "geometry": {"coordinates":[-1.173473,52.960419],"type":"Point"}
}