{
  "type": "Feature",
  "properties": {
    "addr:full":"34 New Park Road London Greater London SW2 4UN",
    "addr:housenumber":"34",
    "addr:postcode":"sw2 4un",
    "addr:street":"New Park Road",
    "iso:country":"GB",
    "sg:address":"34 New Park Road",
    "sg:city":"London",
    "sg:classifiers":[
        {
            "category":"Shopping",
            "subcategory":"Pharmacy",
            "type":"Retail Goods"
        }
    ],
    "sg:phone":"+44 20 8674 4391",
    "sg:postcode":"SW2 4UN",
    "sg:province":"Greater London",
    "sg:tags":[
        "pharmacist",
        "chemist"
    ],
    "wof:name":"S G Manning",
    "wof:placetype":"venue"
},
  "geometry": {"coordinates":[-0.125436,51.448578],"type":"Point"}
}