{
  "type": "Feature",
  "properties": {
    "iso:country":"GB",
    "sg:address":"27 Harraton Terrace, Durham Road",
    "sg:city":"Chester-le-street",
    "sg:classifiers":[
        {
            "category":"Professional",
            "subcategory":"Accounting & Tax Preparation",
            "type":"Services"
        }
    ],
    "sg:postcode":"DH3 2QG",
    "sg:province":"Durham",
    "sg:tags":[
        "accountant"
    ],
    "wof:name":"Torbitt & Co",
    "wof:placetype":"venue"
},
  "geometry": {"coordinates":[-1.577379,54.893089],"type":"Point"}
}