{
  "type": "Feature",
  "properties": {
    "iso:country":"GB",
    "sg:address":"7 Livingstone Place",
    "sg:city":"St Andrews",
    "sg:classifiers":[
        {
            "category":"Manufacturing",
            "subcategory":"Metals",
            "type":"Manufacturing & Wholesale Goods"
        }
    ],
    "sg:phone":"+44 1334 473787",
    "sg:postcode":"KY16 8JH",
    "sg:province":"Fife",
    "sg:tags":[
        "product",
        "blacksmith",
        "forgemasters",
        "fabricated"
    ],
    "wof:name":"Irvine Engineering",
    "wof:placetype":"venue"
},
  "geometry": {"coordinates":[-2.801282,56.334625],"type":"Point"}
}