{
  "type": "Feature",
  "properties": {
    "addr:full":"Old Station Yard, Vine Street, Colvenfords Galashiels Scottish Borders TD1 3LU",
    "addr:postcode":"td1 3lu",
    "addr:street":"Old Station Yard Vine Street",
    "iso:country":"GB",
    "sg:address":"Old Station Yard, Vine Street, Colvenfords",
    "sg:city":"Galashiels",
    "sg:classifiers":[
        {
            "category":"Building & Trades",
            "subcategory":"Plumbing",
            "type":"Services"
        }
    ],
    "sg:phone":"+44 1896 850217",
    "sg:postcode":"TD1 3LU",
    "sg:province":"Scottish Borders",
    "sg:tags":[
        "heating"
    ],
    "wof:name":"Elliot Tanks",
    "wof:placetype":"venue"
},
  "geometry": {"coordinates":[-2.8029789925,55.6121559143],"type":"Point"}
}