{
  "type": "Feature",
  "properties": {
    "iso:country":"GB",
    "sg:address":"109 Ilkeston Road",
    "sg:city":"Nottingham",
    "sg:classifiers":[
        {
            "category":"Food & Beverages",
            "subcategory":"Meat & Fish",
            "type":"Retail Goods"
        }
    ],
    "sg:postcode":"NG7 3HE",
    "sg:province":"Nottinghamshire",
    "sg:tags":[
        "butcher"
    ],
    "wof:name":"Parkins",
    "wof:placetype":"venue"
},
  "geometry": {"coordinates":[-1.170482,52.955826],"type":"Point"}
}