{
  "type": "Feature",
  "properties": {
    "iso:country":"GB",
    "sg:address":"Old Co-op Buildings, Waldridge",
    "sg:city":"Chester-le-street",
    "sg:classifiers":[
        {
            "category":"Building & Trades",
            "subcategory":"Construction",
            "type":"Services"
        }
    ],
    "sg:phone":"+44 191 388 2397",
    "sg:postcode":"DH2 3SA",
    "sg:province":"Durham",
    "sg:tags":[
        "decorator",
        "painter"
    ],
    "wof:name":"S & R Interiors Ltd.",
    "wof:placetype":"venue"
},
  "geometry": {"coordinates":[-1.6086740494,54.8466262817],"type":"Point"}
}