{
  "type": "Feature",
  "properties": {
    "iso:country":"GB",
    "sg:address":"Unit 12, Glaholm Rd, Hendon",
    "sg:city":"Sunderland",
    "sg:classifiers":[
        {
            "category":"Manufacturing",
            "subcategory":"Petroleum Products",
            "type":"Manufacturing & Wholesale Goods"
        }
    ],
    "sg:phone":"+44 191 564 1899",
    "sg:postcode":"SR1 2NX",
    "sg:province":"Tyne and Wear",
    "sg:tags":[
        "double",
        "glazing"
    ],
    "wof:name":"Fiesta Windows (N E) Ltd",
    "wof:placetype":"venue"
},
  "geometry": {"coordinates":[-1.366636,54.90366],"type":"Point"}
}