{
  "type": "Feature",
  "properties": {
    "addr:full":"6 Air Links Industrial Estate, Spitfire Way Hounslow Greater London TW5 9NR",
    "addr:housenumber":"6",
    "addr:postcode":"tw5 9nr",
    "addr:street":"Air Links Industrial Estate Spitfire Way",
    "iso:country":"GB",
    "sg:address":"6 Air Links Industrial Estate, Spitfire Way",
    "sg:city":"Hounslow",
    "sg:classifiers":[
        {
            "category":"Personal",
            "type":"Services"
        }
    ],
    "sg:phone":"+44 20 8573 7174",
    "sg:postcode":"TW5 9NR",
    "sg:province":"Greater London",
    "sg:tags":[
        "delivery"
    ],
    "wof:name":"Amtrak Express Parcels Ltd.",
    "wof:placetype":"venue"
},
  "geometry": {"coordinates":[-0.39621,51.491749],"type":"Point"}
}