{
  "type": "Feature",
  "properties": {
    "addr:full":"Rectory, 30 Leswell St Kidderminster Staffordshire DY10 1RP",
    "addr:housenumber":"30",
    "addr:postcode":"dy10 1rp",
    "addr:street":"Leswell St",
    "iso:country":"GB",
    "sg:address":"Rectory, 30 Leswell St",
    "sg:city":"Kidderminster",
    "sg:classifiers":[
        {
            "category":"Place Of Worship",
            "type":"Public Place"
        }
    ],
    "sg:phone":"+44 1562 822131",
    "sg:postcode":"DY10 1RP",
    "sg:province":"Staffordshire",
    "wof:name":"St George C of E Church",
    "wof:placetype":"venue"
},
  "geometry": {"coordinates":[-2.249084,52.388111],"type":"Point"}
}