{
  "type": "Feature",
  "properties": {
    "iso:country":"GB",
    "sg:address":"Newcastle Street",
    "sg:city":"Stone",
    "sg:classifiers":[
        {
            "category":"Professional",
            "subcategory":"Engineering",
            "type":"Services"
        }
    ],
    "sg:phone":"+44 1785 815544",
    "sg:postcode":"ST15 8JU",
    "sg:province":"Staffordshire",
    "sg:tags":[
        "precision",
        "engineer"
    ],
    "wof:name":"M G Sanders Co. Ltd.",
    "wof:placetype":"venue"
},
  "geometry": {"coordinates":[-2.1492729187,52.9027442932],"type":"Point"}
}