{
  "type": "Feature",
  "properties": {
    "addr:full":"2 Chantry Place Harrow Greater London HA3 6NY",
    "addr:housenumber":"2",
    "addr:postcode":"ha3 6ny",
    "addr:street":"Chantry Place",
    "iso:country":"GB",
    "sg:address":"2 Chantry Place",
    "sg:city":"Harrow",
    "sg:classifiers":[
        {
            "category":"Communications",
            "subcategory":"Newspaper",
            "type":"Services"
        }
    ],
    "sg:phone":"+44 20 8420 1210",
    "sg:postcode":"HA3 6NY",
    "sg:province":"Greater London",
    "sg:tags":[
        "magazine"
    ],
    "wof:name":"Saleworld Ltd.",
    "wof:placetype":"venue"
},
  "geometry": {"coordinates":[-0.358362,51.603725],"type":"Point"}
}