{
  "type": "Feature",
  "properties": {
    "addr:full":"56 Charlotte Dundas Court Grangemouth Falkirk FK3 9EB",
    "addr:housenumber":"56",
    "addr:postcode":"fk3 9eb",
    "addr:street":"Charlotte Dundas Court",
    "iso:country":"GB",
    "sg:address":"56 Charlotte Dundas Court",
    "sg:city":"Grangemouth",
    "sg:classifiers":[
        {
            "category":"Fast Food",
            "type":"Food & Drink"
        }
    ],
    "sg:phone":"+44 1324 483277",
    "sg:postcode":"FK3 9EB",
    "sg:province":"Falkirk",
    "sg:tags":[
        "away",
        "take"
    ],
    "wof:name":"Dhillons",
    "wof:placetype":"venue"
},
  "geometry": {"coordinates":[-3.723894,56.009331],"type":"Point"}
}