{
  "type": "Feature",
  "properties": {
    "addr:full":"Wellcross Grange, Five Oaks Rd, Slinfold Horsham West Sussex RH13 7QW",
    "addr:postcode":"rh13 7qw",
    "addr:street":"Five Oaks Rd",
    "iso:country":"GB",
    "sg:address":"Wellcross Grange, Five Oaks Rd, Slinfold",
    "sg:city":"Horsham",
    "sg:classifiers":[
        {
            "category":"Health Services",
            "subcategory":"Nursing And Care Facility",
            "type":"Services"
        }
    ],
    "sg:phone":"+44 1403 790140",
    "sg:postcode":"RH13 7QW",
    "sg:province":"West Sussex",
    "sg:tags":[
        "home"
    ],
    "wof:name":"Wellcross Nursing",
    "wof:placetype":"venue"
},
  "geometry": {"coordinates":[-0.40533,51.070011],"type":"Point"}
}