{
  "type": "Feature",
  "properties": {
    "iso:country":"GB",
    "sg:address":"8 Mill Road, Houghton Regis",
    "sg:city":"Dunstable",
    "sg:classifiers":[
        {
            "category":"Retail",
            "subcategory":"Auto Repair",
            "type":"Services"
        }
    ],
    "sg:phone":"+44 1582 861425",
    "sg:postcode":"LU5 5BD",
    "sg:province":"Bedfordshire",
    "sg:tags":[
        "modification",
        "garage",
        "related"
    ],
    "wof:name":"Camrod Motors",
    "wof:placetype":"venue"
},
  "geometry": {"coordinates":[-0.5267009735,51.9028358459],"type":"Point"}
}