{
  "type": "Feature",
  "properties": {
    "iso:country":"GB",
    "sg:address":"7 Fairoak Court, Whitehouse Industrial Estate",
    "sg:city":"Runcorn",
    "sg:classifiers":[
        {
            "category":"Shopping",
            "type":"Retail Goods"
        }
    ],
    "sg:phone":"+44 1928 790063",
    "sg:postcode":"WA7 3DX",
    "sg:province":"Cheshire",
    "sg:tags":[
        "bag"
    ],
    "wof:name":"Menardi-Criswell Ltd.",
    "wof:placetype":"venue"
},
  "geometry": {"coordinates":[-2.648689,53.308506],"type":"Point"}
}