{
  "type": "Feature",
  "properties": {
    "iso:country":"GB",
    "sg:address":"280 Shirley Road",
    "sg:city":"Southampton",
    "sg:classifiers":[
        {
            "category":"Arts & Performance",
            "subcategory":"Art Gallery",
            "type":"Entertainment"
        },
        {
            "category":"Shopping",
            "subcategory":"Antiques",
            "type":"Retail Goods"
        },
        {
            "category":"Museum",
            "subcategory":"Art Museum",
            "type":"Entertainment"
        }
    ],
    "sg:phone":"+44 23 8077 4772",
    "sg:postcode":"SO15 3HL",
    "sg:province":"Hampshire",
    "wof:name":"THE MORRIS GALLERY",
    "wof:placetype":"venue"
},
  "geometry": {"coordinates":[-1.425925,50.91637],"type":"Point"}
}