{
  "type": "Feature",
  "properties": {
    "iso:country":"GB",
    "sg:address":"Hollygate Road",
    "sg:city":"Dalton-in-furness",
    "sg:classifiers":[
        {
            "category":"Wholesale",
            "subcategory":"Scrap",
            "type":"Manufacturing & Wholesale Goods"
        }
    ],
    "sg:postcode":"LA15 8PU",
    "sg:province":"Cumbria",
    "sg:tags":[
        "breaker",
        "dismantlers"
    ],
    "wof:name":"J Gabriel",
    "wof:placetype":"venue"
},
  "geometry": {"coordinates":[-3.183194,54.152149],"type":"Point"}
}