{
  "type": "Feature",
  "properties": {
    "iso:country":"GB",
    "sg:address":"12 Russell Street",
    "sg:city":"Keighley",
    "sg:classifiers":[
        {
            "category":"Professional",
            "subcategory":"Engineering",
            "type":"Services"
        }
    ],
    "sg:phone":"+44 1535 605641",
    "sg:postcode":"BD21 2JS",
    "sg:province":"West Yorkshire",
    "sg:tags":[
        "engineer"
    ],
    "wof:name":"John Wilson (Steel) Ltd.",
    "wof:placetype":"venue"
},
  "geometry": {"coordinates":[-1.911647,53.867001],"type":"Point"}
}