{
  "type": "Feature",
  "properties": {
    "addr:full":"6 Richmond St Weston-super-mare Somerset BS23 1SY",
    "addr:housenumber":"6",
    "addr:postcode":"bs23 1sy",
    "addr:street":"Richmond St",
    "iso:country":"GB",
    "sg:address":"6 Richmond St",
    "sg:city":"Weston-super-mare",
    "sg:classifiers":[
        {
            "category":"Fast Food",
            "type":"Food & Drink"
        }
    ],
    "sg:postcode":"BS23 1SY",
    "sg:province":"Somerset",
    "sg:tags":[
        "away",
        "take"
    ],
    "wof:name":"Haghani,M,",
    "wof:placetype":"venue"
},
  "geometry": {"coordinates":[-2.9803419113,51.3467674255],"type":"Point"}
}