{
  "type": "Feature",
  "properties": {
    "iso:country":"GB",
    "sg:address":"The Old Grain Store, 4 Denne Road",
    "sg:city":"Horsham",
    "sg:classifiers":[
        {
            "category":"Food & Beverages",
            "subcategory":"Specialty",
            "type":"Retail Goods"
        }
    ],
    "sg:postcode":"RH12 1JE",
    "sg:province":"West Sussex",
    "sg:tags":[
        "product",
        "health"
    ],
    "wof:name":"Comet Scientific Ltd.",
    "wof:placetype":"venue"
},
  "geometry": {"coordinates":[-0.329107,51.065182],"type":"Point"}
}