{
  "type": "Feature",
  "properties": {
    "addr:full":"362 Aigburth Road Liverpool Merseyside L17 6AE",
    "addr:housenumber":"362",
    "addr:postcode":"l17 6ae",
    "addr:street":"Aigburth Road",
    "iso:country":"GB",
    "sg:address":"362 Aigburth Road",
    "sg:city":"Liverpool",
    "sg:classifiers":[
        {
            "category":"Real Estate",
            "subcategory":"Real Estate Agent",
            "type":"Services"
        }
    ],
    "sg:phone":"+44 151 475 4111",
    "sg:postcode":"L17 6AE",
    "sg:province":"Merseyside",
    "wof:name":"Willams Estate Management",
    "wof:placetype":"venue"
},
  "geometry": {"coordinates":[-2.9254848957,53.3672866821],"type":"Point"}
}