{
  "type": "Feature",
  "properties": {
    "addr:full":"Oad St Craft Centre, Oad Street Sittingbourne Kent ME9 8LB",
    "addr:postcode":"me9 8lb",
    "addr:street":"Oad Street",
    "iso:country":"GB",
    "sg:address":"Oad St Craft Centre, Oad Street",
    "sg:city":"Sittingbourne",
    "sg:classifiers":[
        {
            "category":"Cafe",
            "type":"Food & Drink"
        }
    ],
    "sg:phone":"+44 1795 843130",
    "sg:postcode":"ME9 8LB",
    "sg:province":"Kent",
    "sg:tags":[
        "tea",
        "room"
    ],
    "wof:name":"Oad Street Tea Room",
    "wof:placetype":"venue"
},
  "geometry": {"coordinates":[0.6826099753,51.3274917603],"type":"Point"}
}