{
  "type": "Feature",
  "properties": {
    "iso:country":"GB",
    "sg:address":"Tysea Rd",
    "sg:city":"Harlow",
    "sg:classifiers":[
        {
            "category":"Place Of Worship",
            "type":"Public Place"
        }
    ],
    "sg:phone":"+44 1279 431035",
    "sg:postcode":"CM18 7DR",
    "sg:province":"Essex",
    "wof:name":"Church of Jesus Christ of Latter Day Saints",
    "wof:placetype":"venue"
},
  "geometry": {"coordinates":[0.11085,51.754795],"type":"Point"}
}