{
  "type": "Feature",
  "properties": {
    "addr:full":"100 Paisley Road Renfrew Renfrewshire PA4 8HD",
    "addr:housenumber":"100",
    "addr:postcode":"pa4 8hd",
    "addr:street":"Paisley Road",
    "iso:country":"GB",
    "sg:address":"100 Paisley Road",
    "sg:city":"Renfrew",
    "sg:classifiers":[
        {
            "category":"Cinema",
            "subcategory":"Movie Rental",
            "type":"Entertainment"
        }
    ],
    "sg:postcode":"PA4 8HD",
    "sg:province":"Renfrewshire",
    "sg:tags":[
        "video",
        "library"
    ],
    "wof:name":"Ian Cunningham",
    "wof:placetype":"venue"
},
  "geometry": {"coordinates":[-4.397359848,55.871837616],"type":"Point"}
}