{
  "type": "Feature",
  "properties": {
    "addr:full":"141 Western Road Haywards Heath East Sussex RH16 3LH",
    "addr:housenumber":"141",
    "addr:postcode":"rh16 3lh",
    "addr:street":"Western Road",
    "iso:country":"GB",
    "sg:address":"141 Western Road",
    "sg:city":"Haywards Heath",
    "sg:classifiers":[
        {
            "category":"Professional",
            "subcategory":"Secretarial Services",
            "type":"Services"
        }
    ],
    "sg:phone":"+44 1444 416645",
    "sg:postcode":"RH16 3LH",
    "sg:province":"East Sussex",
    "wof:name":"Mid Sussex Business Centre",
    "wof:placetype":"venue"
},
  "geometry": {"coordinates":[-0.0922740027,50.9986343384],"type":"Point"}
}