{
  "type": "Feature",
  "properties": {
    "addr:full":"Limerick Clo Ipswich Suffolk IP1 5LR",
    "addr:postcode":"ip1 5lr",
    "iso:country":"GB",
    "sg:address":"Limerick Clo",
    "sg:city":"Ipswich",
    "sg:classifiers":[
        {
            "category":"Social Services",
            "type":"Services"
        }
    ],
    "sg:phone":"+44 1473 588150",
    "sg:postcode":"IP1 5LR",
    "sg:province":"Suffolk",
    "wof:name":"Child Protection",
    "wof:placetype":"venue"
},
  "geometry": {"coordinates":[1.123166,52.079395],"type":"Point"}
}