{
  "type": "Feature",
  "properties": {
    "addr:full":"31 Market Place Coleford Gloucestershire GL16 8AA",
    "addr:housenumber":"31",
    "addr:postcode":"gl16 8aa",
    "addr:street":"Market Place",
    "iso:country":"GB",
    "sg:address":"31 Market Place",
    "sg:city":"Coleford",
    "sg:classifiers":[
        {
            "category":"Shopping",
            "subcategory":"Florist",
            "type":"Retail Goods"
        }
    ],
    "sg:phone":"+44 1594 837409",
    "sg:postcode":"GL16 8AA",
    "sg:province":"Gloucestershire",
    "wof:name":"B & M Weston",
    "wof:placetype":"venue"
},
  "geometry": {"coordinates":[-2.616698,51.793701],"type":"Point"}
}