{
  "type": "Feature",
  "properties": {
    "addr:full":"Kevin Wood Newport East Riding of Yorkshire NP1 9DA",
    "addr:postcode":"np1 9da",
    "addr:street":"Wood",
    "iso:country":"GB",
    "sg:address":"Kevin Wood",
    "sg:city":"Newport",
    "sg:classifiers":[
        {
            "category":"Government",
            "subcategory":"Police Station",
            "type":"Public Place"
        }
    ],
    "sg:phone":"+44 1633 894382",
    "sg:postcode":"NP1 9DA",
    "sg:province":"East Riding of Yorkshire",
    "sg:tags":[
        "support"
    ],
    "wof:name":"Rogerstone Police Station",
    "wof:placetype":"venue"
},
  "geometry": {"coordinates":[-3.01236,51.61314],"type":"Point"}
}