{
  "type": "Feature",
  "properties": {
    "addr:full":"Wycliffe Court, Pinehurst Close Abbots Langley Hertfordshire WD5 0LZ",
    "addr:postcode":"wd5 0lz",
    "addr:street":"Wycliffe Court Pinehurst Close",
    "iso:country":"GB",
    "sg:address":"Wycliffe Court, Pinehurst Close",
    "sg:city":"Abbots Langley",
    "sg:classifiers":[
        {
            "category":"Organizations",
            "subcategory":"Community Association",
            "type":"Services"
        }
    ],
    "sg:phone":"+44 1923 260730",
    "sg:postcode":"WD5 0LZ",
    "sg:province":"Hertfordshire",
    "sg:tags":[
        "society",
        "housing"
    ],
    "wof:name":"The North British Housing Ltd.",
    "wof:placetype":"venue"
},
  "geometry": {"coordinates":[-0.419933,51.699577],"type":"Point"}
}