{
  "type": "Feature",
  "properties": {
    "addr:full":"19 Market Street, Oakengates Telford Shropshire TF2 6EL",
    "addr:housenumber":"19",
    "addr:postcode":"tf2 6el",
    "addr:street":"Market Street",
    "iso:country":"GB",
    "sg:address":"19 Market Street, Oakengates",
    "sg:city":"Telford",
    "sg:classifiers":[
        {
            "category":"Food & Beverages",
            "subcategory":"Bakery",
            "type":"Retail Goods"
        }
    ],
    "sg:phone":"+44 1952 612666",
    "sg:postcode":"TF2 6EL",
    "sg:province":"Shropshire",
    "sg:tags":[
        "baker"
    ],
    "wof:name":"Greggs",
    "wof:placetype":"venue"
},
  "geometry": {"coordinates":[-2.4520161152,52.6950035095],"type":"Point"}
}