{
  "type": "Feature",
  "properties": {
    "iso:country":"GB",
    "sg:address":"8 Trinity Av",
    "sg:city":"Llandudno",
    "sg:classifiers":[
        {
            "category":"Home & Garden",
            "subcategory":"Household Appliances",
            "type":"Retail Goods"
        }
    ],
    "sg:phone":"+44 1492 877887",
    "sg:postcode":"LL30 2NQ",
    "sg:province":"Conwy",
    "sg:tags":[
        "electrical"
    ],
    "wof:name":"Samson Domestic Appliance Centre",
    "wof:placetype":"venue"
},
  "geometry": {"coordinates":[-3.8284409046,53.3213615417],"type":"Point"}
}