{
  "type": "Feature",
  "properties": {
    "iso:country":"GB",
    "sg:address":"12 Cavendish Street",
    "sg:city":"Chesterfield",
    "sg:classifiers":[
        {
            "category":"Home & Garden",
            "subcategory":"Household Appliances",
            "type":"Retail Goods"
        }
    ],
    "sg:phone":"+44 1246 234953",
    "sg:postcode":"S40 1UY",
    "sg:province":"Derbyshire",
    "sg:tags":[
        "electrical",
        "domestic"
    ],
    "wof:name":"Roy Smith",
    "wof:placetype":"venue"
},
  "geometry": {"coordinates":[-1.425865,53.236816],"type":"Point"}
}