{
  "type": "Feature",
  "properties": {
    "addr:full":"44 Barnton Street Stirling Stirling FK8 1NA",
    "addr:housenumber":"44",
    "addr:postcode":"fk8 1na",
    "addr:street":"Barnton Street",
    "iso:country":"GB",
    "sg:address":"44 Barnton Street",
    "sg:city":"Stirling",
    "sg:classifiers":[
        {
            "category":"Shopping",
            "subcategory":"Department Store",
            "type":"Retail Goods"
        },
        {
            "category":"Shopping",
            "subcategory":"Bicycles & Sporting Goods",
            "type":"Retail Goods"
        }
    ],
    "sg:phone":"+44 1786 465292",
    "sg:postcode":"FK8 1NA",
    "sg:province":"Stirling",
    "sg:tags":[
        "accessory",
        "cycle"
    ],
    "wof:name":"Avanti Cycles",
    "wof:placetype":"venue"
},
  "geometry": {"coordinates":[-3.9383580685,56.1207923889],"type":"Point"}
}