{
  "type": "Feature",
  "properties": {
    "addr:full":"Matbro House Burgess Hill East Sussex RH15 9EQ",
    "addr:postcode":"rh15 9eq",
    "iso:country":"GB",
    "sg:address":"Matbro House",
    "sg:city":"Burgess Hill",
    "sg:classifiers":[
        {
            "category":"Building & Trades",
            "subcategory":"Construction",
            "type":"Services"
        }
    ],
    "sg:phone":"+44 1444 248666",
    "sg:postcode":"RH15 9EQ",
    "sg:province":"East Sussex",
    "sg:tags":[
        "roofing"
    ],
    "wof:name":"Kaycee Roofing & Supplies",
    "wof:placetype":"venue"
},
  "geometry": {"coordinates":[-0.1391739994,50.955329895],"type":"Point"}
}