{
  "type": "Feature",
  "properties": {
    "iso:country":"GB",
    "sg:address":"Unit 1, Old House Farm Parsonage Road Ta",
    "sg:city":"Bishops Stortford",
    "sg:classifiers":[
        {
            "category":"Retail",
            "subcategory":"Auto Repair",
            "type":"Services"
        }
    ],
    "sg:phone":"+44 7768 088651",
    "sg:postcode":"CM22 6PU",
    "sg:province":"Essex",
    "sg:tags":[
        "modification",
        "garage"
    ],
    "wof:name":"The Motor Surgery",
    "wof:placetype":"venue"
},
  "geometry": {"coordinates":[0.2658039927,51.8707847595],"type":"Point"}
}