{
  "type": "Feature",
  "properties": {
    "addr:full":"66-69 Grainger Market Newcastle-upon-tyne Tyne and Wear NE1 5QQ",
    "addr:housenumber":"66-69",
    "addr:postcode":"ne1 5qq",
    "addr:street":"Grainger",
    "iso:country":"GB",
    "sg:address":"66-69 Grainger Market",
    "sg:city":"Newcastle-upon-tyne",
    "sg:classifiers":[
        {
            "category":"Food & Beverages",
            "subcategory":"Meat & Fish",
            "type":"Retail Goods"
        }
    ],
    "sg:postcode":"NE1 5QQ",
    "sg:province":"Tyne and Wear",
    "sg:tags":[
        "butcher"
    ],
    "wof:name":"Charles F Hunter Ltd.",
    "wof:placetype":"venue"
},
  "geometry": {"coordinates":[-1.61494,54.971317],"type":"Point"}
}