{
  "type": "Feature",
  "properties": {
    "iso:country":"GB",
    "sg:address":"66-69 Grainger Market",
    "sg:city":"Newcastle-upon-tyne",
    "sg:classifiers":[
        {
            "category":"Food & Beverages",
            "subcategory":"Meat & Fish",
            "type":"Retail Goods"
        }
    ],
    "sg:postcode":"NE1 5QQ",
    "sg:province":"Tyne and Wear",
    "sg:tags":[
        "butcher"
    ],
    "wof:name":"Charles F Hunter Ltd.",
    "wof:placetype":"venue"
},
  "geometry": {"coordinates":[-1.61494,54.971317],"type":"Point"}
}