{
  "type": "Feature",
  "properties": {
    "iso:country":"GB",
    "sg:address":"The First Floor, The Butter Market Centre",
    "sg:city":"Newark",
    "sg:classifiers":[
        {
            "category":"Personal",
            "subcategory":"Beauty Salon",
            "type":"Services"
        }
    ],
    "sg:postcode":"NG24 1BF",
    "sg:province":"Nottinghamshire",
    "wof:name":"The Beauty Clinic",
    "wof:placetype":"venue"
},
  "geometry": {"coordinates":[-0.809347,53.073895],"type":"Point"}
}