{
  "type": "Feature",
  "properties": {
    "iso:country":"GB",
    "sg:address":"Kings Road House, 2 Kings Road",
    "sg:city":"Windsor",
    "sg:classifiers":[
        {
            "category":"Banks & Credit Unions",
            "subcategory":"Financial Services",
            "type":"Services"
        }
    ],
    "sg:postcode":"SL4 2AG",
    "sg:province":"Berkshire",
    "sg:tags":[
        "consultant"
    ],
    "wof:name":"Nimbus Securities Ltd.",
    "wof:placetype":"venue"
},
  "geometry": {"coordinates":[-0.6064199805,51.4780883789],"type":"Point"}
}