{
  "type": "Feature",
  "properties": {
    "iso:country":"GB",
    "sg:address":"43a High Street, St Peters",
    "sg:city":"Broadstairs",
    "sg:classifiers":[
        {
            "category":"Personal",
            "subcategory":"Beauty Salon",
            "type":"Services"
        }
    ],
    "sg:phone":"+44 1843 867546",
    "sg:postcode":"CT10 2TH",
    "sg:province":"Kent",
    "sg:tags":[
        "unisex",
        "lady",
        "hairdresser"
    ],
    "wof:name":"Albion Hair Studio",
    "wof:placetype":"venue"
},
  "geometry": {"coordinates":[1.421459,51.364311],"type":"Point"}
}