{
  "type": "Feature",
  "properties": {
    "addr:full":"Nottingham Airport, Tollerton La Nottingham Nottinghamshire NG12 4GA",
    "addr:postcode":"ng12 4ga",
    "addr:street":"La",
    "iso:country":"GB",
    "sg:address":"Nottingham Airport, Tollerton La",
    "sg:city":"Nottingham",
    "sg:classifiers":[
        {
            "category":"Organizations",
            "subcategory":"Labor Organization",
            "type":"Services"
        }
    ],
    "sg:phone":"+44 115 982 7300",
    "sg:postcode":"NG12 4GA",
    "sg:province":"Nottinghamshire",
    "sg:tags":[
        "woodworking",
        "machinery"
    ],
    "wof:name":"Poole Wood Machinery",
    "wof:placetype":"venue"
},
  "geometry": {"coordinates":[-1.1007150412,52.8992118835],"type":"Point"}
}