{
  "type": "Feature",
  "properties": {
    "iso:country":"GB",
    "sg:address":"18 Anson Rd",
    "sg:city":"Cricklewood",
    "sg:classifiers":[
        {
            "category":"Health Services",
            "subcategory":"Doctor",
            "type":"Services"
        }
    ],
    "sg:phone":"+44 20 8452 6636",
    "sg:postcode":"NW2 3UU",
    "sg:province":"Greater London",
    "sg:tags":[
        "practitioners"
    ],
    "wof:name":"Samarasinghe, K P B",
    "wof:placetype":"venue"
},
  "geometry": {"coordinates":[-0.2149749994,51.5542297363],"type":"Point"}
}