{
  "type": "Feature",
  "properties": {
    "addr:full":"50 Bermondsey Street London Greater London SE1 3UD",
    "addr:housenumber":"50",
    "addr:postcode":"se1 3ud",
    "addr:street":"Bermondsey Street",
    "iso:country":"GB",
    "sg:address":"50 Bermondsey Street",
    "sg:city":"London",
    "sg:classifiers":[
        {
            "category":"Professional",
            "type":"Services"
        }
    ],
    "sg:phone":"+44 20 7378 8033",
    "sg:postcode":"SE1 3UD",
    "sg:province":"Greater London",
    "sg:tags":[
        "entertainer"
    ],
    "wof:name":"Brodsky Management",
    "wof:placetype":"venue"
},
  "geometry": {"coordinates":[-0.082603,51.502102],"type":"Point"}
}