{
  "type": "Feature",
  "properties": {
    "addr:full":"43 Chappell Road, Deeping St Nicholas Spalding Lincolnshire PE11 3ER",
    "addr:housenumber":"43",
    "addr:postcode":"pe11 3er",
    "addr:street":"Chappell Road Deeping St;Spalding",
    "iso:country":"GB",
    "sg:address":"43 Chappell Road, Deeping St Nicholas",
    "sg:city":"Spalding",
    "sg:classifiers":[
        {
            "category":"Social Services",
            "subcategory":"Adult Care",
            "type":"Services"
        },
        {
            "category":"Social Services",
            "subcategory":"Retirement Home",
            "type":"Services"
        }
    ],
    "sg:phone":"+44 1775 630333",
    "sg:postcode":"PE11 3ER",
    "sg:province":"Lincolnshire",
    "sg:tags":[
        "accomodation",
        "housing",
        "sheltered"
    ],
    "wof:name":"Chappel Road Sheltered Housing",
    "wof:placetype":"venue"
},
  "geometry": {"coordinates":[-0.209348,52.720528],"type":"Point"}
}