{
  "type": "Feature",
  "properties": {
    "iso:country":"GB",
    "sg:address":"Clayhill Farm, Clayhill, Beckley",
    "sg:city":"Rye",
    "sg:classifiers":[
        {
            "category":"Farming",
            "subcategory":"Livestock Farm",
            "type":"Manufacturing & Wholesale Goods"
        }
    ],
    "sg:postcode":"TN31 6SQ",
    "sg:province":"East Sussex",
    "sg:tags":[
        "others"
    ],
    "wof:name":"D E Hales & Son",
    "wof:placetype":"venue"
},
  "geometry": {"coordinates":[0.635345,50.984589],"type":"Point"}
}