{
  "type": "Feature",
  "properties": {
    "addr:full":"7 Rockside Stoke On Trent Cheshire ST7 4PG",
    "addr:housenumber":"7",
    "addr:postcode":"st7 4pg",
    "addr:street":"Rockside Stoke On Trent",
    "iso:country":"GB",
    "sg:address":"7 Rockside",
    "sg:city":"Stoke On Trent",
    "sg:classifiers":[
        {
            "category":"Retail",
            "subcategory":"Driving School",
            "type":"Services"
        }
    ],
    "sg:phone":"+44 1782 514925",
    "sg:postcode":"ST7 4PG",
    "sg:province":"Cheshire",
    "wof:name":"F Bibby",
    "wof:placetype":"venue"
},
  "geometry": {"coordinates":[-2.217352,53.109528],"type":"Point"}
}