{
  "type": "Feature",
  "properties": {
    "iso:country":"GB",
    "sg:address":"Unit 1 Meadow Farm, Dickens Heath Road",
    "sg:city":"Solihull",
    "sg:classifiers":[
        {
            "category":"Home & Garden",
            "subcategory":"Furniture",
            "type":"Retail Goods"
        }
    ],
    "sg:phone":"+44 1564 823450",
    "sg:postcode":"B90 1QW",
    "sg:province":"West Midlands",
    "wof:name":"Solihull Furnishings",
    "wof:placetype":"venue"
},
  "geometry": {"coordinates":[-1.8410689831,52.3843231201],"type":"Point"}
}