{
  "type": "Feature",
  "properties": {
    "iso:country":"GB",
    "sg:address":"The Pavilion, Esplanade",
    "sg:city":"Weymouth",
    "sg:classifiers":[
        {
            "category":"Government",
            "subcategory":"Office",
            "type":"Public Place"
        }
    ],
    "sg:phone":"+44 1305 765240",
    "sg:postcode":"DT4 8ED",
    "sg:province":"Dorset",
    "sg:tags":[
        "local"
    ],
    "wof:name":"Weymouth Pavilion Catering Services",
    "wof:placetype":"venue"
},
  "geometry": {"coordinates":[-2.4592061043,50.6099014282],"type":"Point"}
}