{
  "type": "Feature",
  "properties": {
    "addr:full":"2 Central Walk, Hucknall Nottingham Nottinghamshire NG15 7HF",
    "addr:housenumber":"2",
    "addr:postcode":"ng15 7hf",
    "addr:street":"Central Walk",
    "iso:country":"GB",
    "sg:address":"2 Central Walk, Hucknall",
    "sg:city":"Nottingham",
    "sg:classifiers":[
        {
            "category":"Health Services",
            "subcategory":"Optometrist",
            "type":"Services"
        }
    ],
    "sg:phone":"+44 115 963 6732",
    "sg:postcode":"NG15 7HF",
    "sg:province":"Nottinghamshire",
    "sg:tags":[
        "optician"
    ],
    "wof:name":"D I Blow (Opticians) Ltd.",
    "wof:placetype":"venue"
},
  "geometry": {"coordinates":[-1.2069020271,53.0365829468],"type":"Point"}
}