{
  "type": "Feature",
  "properties": {
    "addr:full":"66 The Avenue Southampton Hampshire SO17 1XS",
    "addr:housenumber":"66",
    "addr:postcode":"so17 1xs",
    "addr:street":"The Avenue",
    "iso:country":"GB",
    "sg:address":"66 The Avenue",
    "sg:city":"Southampton",
    "sg:classifiers":[
        {
            "category":"Personal",
            "subcategory":"Beauty Salon",
            "type":"Services"
        }
    ],
    "sg:phone":"+44 23 8022 7529",
    "sg:postcode":"SO17 1XS",
    "sg:province":"Hampshire",
    "sg:tags":[
        "unisex",
        "hairdresser"
    ],
    "wof:name":"X L Hairwear",
    "wof:placetype":"venue"
},
  "geometry": {"coordinates":[-1.404304,50.919212],"type":"Point"}
}