{
  "type": "Feature",
  "properties": {
    "addr:full":"Redditch Youth House, Ipsley Street Redditch Warwickshire B98 7AR",
    "addr:postcode":"b98 7ar",
    "addr:street":"Ipsley Street",
    "iso:country":"GB",
    "sg:address":"Redditch Youth House, Ipsley Street",
    "sg:city":"Redditch",
    "sg:classifiers":[
        {
            "category":"Community Center",
            "subcategory":"Youth",
            "type":"Public Place"
        }
    ],
    "sg:phone":"+44 1527 595036",
    "sg:postcode":"B98 7AR",
    "sg:province":"Warwickshire",
    "sg:tags":[
        "organisation",
        "centre"
    ],
    "wof:name":"Redditch Youth House",
    "wof:placetype":"venue"
},
  "geometry": {"coordinates":[-1.9368089437,52.3047218323],"type":"Point"}
}