{
  "type": "Feature",
  "properties": {
    "addr:full":"9 Hillfield Road London Greater London NW6 1QD",
    "addr:housenumber":"9",
    "addr:postcode":"nw6 1qd",
    "addr:street":"Hillfield Road",
    "iso:country":"GB",
    "sg:address":"9 Hillfield Road",
    "sg:city":"London",
    "sg:classifiers":[
        {
            "category":"Retail",
            "subcategory":"Storage",
            "type":"Services"
        }
    ],
    "sg:postcode":"NW6 1QD",
    "sg:province":"Greater London",
    "sg:tags":[
        "household",
        "removal"
    ],
    "wof:name":"Lees Removals",
    "wof:placetype":"venue"
},
  "geometry": {"coordinates":[-0.200954,51.551933],"type":"Point"}
}