{
  "type": "Feature",
  "properties": {
    "addr:full":"31 St Johns Rd Epping Essex CM16 5DW",
    "addr:housenumber":"31",
    "addr:postcode":"cm16 5dw",
    "addr:street":"St Johns Rd",
    "iso:country":"GB",
    "sg:address":"31 St Johns Rd",
    "sg:city":"Epping",
    "sg:classifiers":[
        {
            "category":"Building & Trades",
            "subcategory":"Construction",
            "type":"Services"
        }
    ],
    "sg:postcode":"CM16 5DW",
    "sg:province":"Essex",
    "sg:tags":[
        "builder"
    ],
    "wof:name":"Leer,A,",
    "wof:placetype":"venue"
},
  "geometry": {"coordinates":[0.1085800007,51.6999053955],"type":"Point"}
}