{
  "type": "Feature",
  "properties": {
    "iso:country":"GB",
    "sg:address":"Unit B Park Road Retail Park, Park Road",
    "sg:city":"Pontefract",
    "sg:classifiers":[
        {
            "category":"Food & Beverages",
            "subcategory":"Bakery",
            "type":"Retail Goods"
        }
    ],
    "sg:phone":"+44 1977 690080",
    "sg:postcode":"WF8 4PR",
    "sg:province":"North Yorkshire",
    "sg:tags":[
        "baker"
    ],
    "wof:name":"Pastry Plus",
    "wof:placetype":"venue"
},
  "geometry": {"coordinates":[-1.320519,53.697433],"type":"Point"}
}