{
  "type": "Feature",
  "properties": {
    "iso:country":"GB",
    "sg:address":"20 Fullarton Street",
    "sg:city":"Ayr",
    "sg:classifiers":[
        {
            "category":"Professional",
            "subcategory":"Art Services",
            "type":"Services"
        }
    ],
    "sg:phone":"+44 1292 260689",
    "sg:postcode":"KA7 1UB",
    "sg:province":"South Ayrshire",
    "sg:tags":[
        "photographer"
    ],
    "wof:name":"Crawford Photography",
    "wof:placetype":"venue"
},
  "geometry": {"coordinates":[-4.6340517998,55.4615745544],"type":"Point"}
}