{
  "type": "Feature",
  "properties": {
    "iso:country":"GB",
    "sg:address":"Unit E2 New Yatt Business Centre, Kite La, New Yatt",
    "sg:city":"Witney",
    "sg:classifiers":[
        {
            "category":"Shopping",
            "subcategory":"Stationery & Office Supplies",
            "type":"Retail Goods"
        }
    ],
    "sg:phone":"+44 1993 868070",
    "sg:postcode":"OX29 6TJ",
    "sg:province":"Oxfordshire",
    "sg:tags":[
        "equipment"
    ],
    "wof:name":"Mill Copiers Ltd",
    "wof:placetype":"venue"
},
  "geometry": {"coordinates":[-1.4626200199,51.8160438538],"type":"Point"}
}