{
  "type": "Feature",
  "properties": {
    "iso:country":"GB",
    "sg:address":"1 Queens Passage",
    "sg:city":"Chislehurst",
    "sg:classifiers":[
        {
            "category":"Building & Trades",
            "subcategory":"Construction",
            "type":"Services"
        }
    ],
    "sg:phone":"+44 7808 159195",
    "sg:postcode":"BR7 5AP",
    "sg:province":"Kent",
    "sg:tags":[
        "joinery"
    ],
    "wof:name":"Alphabet Wood Design & Joinery",
    "wof:placetype":"venue"
},
  "geometry": {"coordinates":[0.068445,51.41798],"type":"Point"}
}