{
  "type": "Feature",
  "properties": {
    "addr:full":"7 Augusta Road Ramsgate Kent CT11 8JP",
    "addr:housenumber":"7",
    "addr:postcode":"ct11 8jp",
    "addr:street":"Augusta Road Ramsgate",
    "iso:country":"GB",
    "sg:address":"7 Augusta Road",
    "sg:city":"Ramsgate",
    "sg:classifiers":[
        {
            "category":"Travel",
            "subcategory":"Hotels & Motels",
            "type":"Entertainment"
        }
    ],
    "sg:postcode":"CT11 8JP",
    "sg:province":"Kent",
    "sg:tags":[
        "house",
        "guest"
    ],
    "wof:name":"York House",
    "wof:placetype":"venue"
},
  "geometry": {"coordinates":[1.4245289564,51.3354606628],"type":"Point"}
}