{
  "type": "Feature",
  "properties": {
    "addr:full":"Unit 39, Penley Industrial Estate, Penley Wrexham Wrexham LL13 0LQ",
    "addr:housenumber":"unit 39",
    "addr:postcode":"ll13 0lq",
    "addr:street":"Penley Industrial Estate Penley",
    "iso:country":"GB",
    "sg:address":"Unit 39, Penley Industrial Estate, Penley",
    "sg:city":"Wrexham",
    "sg:classifiers":[
        {
            "category":"Professional",
            "subcategory":"Engineering",
            "type":"Services"
        }
    ],
    "sg:phone":"+44 1948 830268",
    "sg:postcode":"LL13 0LQ",
    "sg:province":"Wrexham",
    "sg:tags":[
        "precision",
        "engineer"
    ],
    "wof:name":"Wade Precision Engineering",
    "wof:placetype":"venue"
},
  "geometry": {"coordinates":[-2.915759,53.00412],"type":"Point"}
}