{
  "type": "Feature",
  "properties": {
    "addr:full":"14 Charles Wood Road Dereham Norfolk NR19 1UQ",
    "addr:housenumber":"14",
    "addr:postcode":"nr19 1uq",
    "addr:street":"Charles Wood Road",
    "iso:country":"GB",
    "sg:address":"14 Charles Wood Road",
    "sg:city":"Dereham",
    "sg:classifiers":[
        {
            "category":"Shopping",
            "subcategory":"Computers & Home Electronics",
            "type":"Retail Goods"
        }
    ],
    "sg:phone":"+44 1362 696824",
    "sg:postcode":"NR19 1UQ",
    "sg:province":"Norfolk",
    "sg:tags":[
        "electrical"
    ],
    "wof:name":"Post Haste Electrical Distributors",
    "wof:placetype":"venue"
},
  "geometry": {"coordinates":[0.950945,52.66766],"type":"Point"}
}