{
  "type": "Feature",
  "properties": {
    "iso:country":"GB",
    "sg:address":"The Boat Buildings, Courthouse Street",
    "sg:city":"Otley",
    "sg:classifiers":[
        {
            "category":"Home & Garden",
            "subcategory":"Furniture",
            "type":"Retail Goods"
        }
    ],
    "sg:phone":"+44 1943 468494",
    "sg:postcode":"LS21 1SP",
    "sg:province":"North Yorkshire",
    "wof:name":"Old Country Pine",
    "wof:placetype":"venue"
},
  "geometry": {"coordinates":[-1.694953,53.90572],"type":"Point"}
}