{
  "type": "Feature",
  "properties": {
    "addr:full":"29 Oldham Road, Springhead Oldham Lancashire OL4 4PH",
    "addr:housenumber":"29",
    "addr:postcode":"ol4 4ph",
    "addr:street":"Oldham Road",
    "iso:country":"GB",
    "sg:address":"29 Oldham Road, Springhead",
    "sg:city":"Oldham",
    "sg:classifiers":[
        {
            "category":"Professional",
            "subcategory":"Accounting & Tax Preparation",
            "type":"Services"
        }
    ],
    "sg:phone":"+44 161 624 6321",
    "sg:postcode":"OL4 4PH",
    "sg:province":"Lancashire",
    "sg:tags":[
        "accountant",
        "bookkeeping",
        "primarily",
        "activity"
    ],
    "sg:website":"http://www.amserve.com",
    "wof:name":"W A Mascord & Co",
    "wof:placetype":"venue"
},
  "geometry": {"coordinates":[-2.066753,53.5378],"type":"Point"}
}