{
  "type": "Feature",
  "properties": {
    "iso:country":"GB",
    "sg:address":"1 Cooper Street",
    "sg:city":"Bideford",
    "sg:classifiers":[
        {
            "category":"Restaurant",
            "type":"Food & Drink"
        }
    ],
    "sg:postcode":"EX39 2DA",
    "sg:province":"Devon",
    "wof:name":"COOPERS RESTAURANT",
    "wof:placetype":"venue"
},
  "geometry": {"coordinates":[-4.205933,51.018749],"type":"Point"}
}