{
  "type": "Feature",
  "properties": {
    "iso:country":"GB",
    "sg:address":"3 Fairview Terrace, Abercynon",
    "sg:city":"Mountain Ash",
    "sg:classifiers":[
        {
            "category":"Retail",
            "subcategory":"Driving School",
            "type":"Services"
        },
        {
            "category":"Arts & Performance",
            "subcategory":"Music",
            "type":"Entertainment"
        }
    ],
    "sg:postcode":"CF45 4UP",
    "sg:province":"Rhondda, Cynon, Taff",
    "sg:tags":[
        "mobile",
        "disco"
    ],
    "wof:name":"Mechanical Pig Disco",
    "wof:placetype":"venue"
},
  "geometry": {"coordinates":[-3.3196470737,51.6506347656],"type":"Point"}
}