{
  "type": "Feature",
  "properties": {
    "addr:full":"3 Fairview Terrace, Abercynon Mountain Ash Rhondda, Cynon, Taff CF45 4UP",
    "addr:housenumber":"3",
    "addr:postcode":"cf45 4up",
    "addr:street":"Fairview Terrace Abercynon;Ash;Cynon Taff",
    "iso:country":"GB",
    "sg:address":"3 Fairview Terrace, Abercynon",
    "sg:city":"Mountain Ash",
    "sg:classifiers":[
        {
            "category":"Retail",
            "subcategory":"Driving School",
            "type":"Services"
        },
        {
            "category":"Arts & Performance",
            "subcategory":"Music",
            "type":"Entertainment"
        }
    ],
    "sg:postcode":"CF45 4UP",
    "sg:province":"Rhondda, Cynon, Taff",
    "sg:tags":[
        "mobile",
        "disco"
    ],
    "wof:name":"Mechanical Pig Disco",
    "wof:placetype":"venue"
},
  "geometry": {"coordinates":[-3.3196470737,51.6506347656],"type":"Point"}
}