{
  "type": "Feature",
  "properties": {
    "addr:full":"3 The Paddocks, Wyesham Monmouth Gloucestershire NP25 3NP",
    "addr:housenumber":"3",
    "addr:postcode":"np25 3np",
    "addr:street":"The Paddocks",
    "iso:country":"GB",
    "sg:address":"3 The Paddocks, Wyesham",
    "sg:city":"Monmouth",
    "sg:classifiers":[
        {
            "category":"Military Area",
            "subcategory":"Air Force Base",
            "type":"Public Place"
        }
    ],
    "sg:phone":"+44 1600 715365",
    "sg:postcode":"NP25 3NP",
    "sg:province":"Gloucestershire",
    "sg:tags":[
        "taxi",
        "hire",
        "private"
    ],
    "wof:name":"D B Taxis",
    "wof:placetype":"venue"
},
  "geometry": {"coordinates":[-2.709193,51.813625],"type":"Point"}
}