{
  "type": "Feature",
  "properties": {
    "iso:country":"GB",
    "sg:address":"161 Brooklands Road",
    "sg:city":"Sale",
    "sg:classifiers":[
        {
            "category":"Health Services",
            "subcategory":"Doctor",
            "type":"Services"
        }
    ],
    "sg:postcode":"M33 3PD",
    "sg:province":"Cheshire",
    "sg:tags":[
        "surgeon"
    ],
    "wof:name":"P H Jones",
    "wof:placetype":"venue"
},
  "geometry": {"coordinates":[-2.3186340332,53.4104728699],"type":"Point"}
}