{
  "type": "Feature",
  "properties": {
    "iso:country":"GB",
    "sg:address":"Stock In Hey Farm, Wood La, Mobberley",
    "sg:city":"Knutsford",
    "sg:classifiers":[
        {
            "category":"Farming",
            "subcategory":"Livestock Farm",
            "type":"Manufacturing & Wholesale Goods"
        }
    ],
    "sg:postcode":"WA16 7NH",
    "sg:province":"Cheshire",
    "sg:tags":[
        "others"
    ],
    "wof:name":"Cheshire Breeding Services Ltd",
    "wof:placetype":"venue"
},
  "geometry": {"coordinates":[-2.331652,53.314552],"type":"Point"}
}