{
  "type": "Feature",
  "properties": {
    "addr:full":"Abbey Park Industrial Estate, 14 Premier Way Romsey Hampshire SO51 9AQ",
    "addr:housenumber":"14",
    "addr:postcode":"so51 9aq",
    "addr:street":"Park Industrial;Premier Way",
    "iso:country":"GB",
    "sg:address":"Abbey Park Industrial Estate, 14 Premier Way",
    "sg:city":"Romsey",
    "sg:classifiers":[
        {
            "category":"Retail",
            "subcategory":"Auto Repair",
            "type":"Services"
        }
    ],
    "sg:postcode":"SO51 9AQ",
    "sg:province":"Hampshire",
    "sg:tags":[
        "body",
        "car"
    ],
    "wof:name":"Mitchells Bodyshop",
    "wof:placetype":"venue"
},
  "geometry": {"coordinates":[-1.4953910112,50.9885826111],"type":"Point"}
}