{
  "type": "Feature",
  "properties": {
    "iso:country":"GB",
    "sg:address":"Thames Side",
    "sg:city":"Windsor",
    "sg:classifiers":[
        {
            "category":"Professional",
            "subcategory":"Management & Consulting",
            "type":"Services"
        }
    ],
    "sg:phone":"+44 1753 802000",
    "sg:postcode":"SL4 1TY",
    "sg:province":"Berkshire",
    "sg:tags":[
        "consultant",
        "business"
    ],
    "wof:name":"Total Contract Management Ltd.",
    "wof:placetype":"venue"
},
  "geometry": {"coordinates":[-0.6067669988,51.4863357544],"type":"Point"}
}