{
  "type": "Feature",
  "properties": {
    "addr:full":"154-162 Barrack Road Christchurch Dorset BH23 2BD",
    "addr:housenumber":"154-162",
    "addr:postcode":"bh23 2bd",
    "addr:street":"Barrack Road",
    "iso:country":"GB",
    "sg:address":"154-162 Barrack Road",
    "sg:city":"Christchurch",
    "sg:classifiers":[
        {
            "category":"Autos & Motor Vehicles",
            "subcategory":"Automobile Sales",
            "type":"Retail Goods"
        }
    ],
    "sg:phone":"+44 1202 485633",
    "sg:postcode":"BH23 2BD",
    "sg:province":"Dorset",
    "sg:tags":[
        "car"
    ],
    "wof:name":"Motor Port",
    "wof:placetype":"venue"
},
  "geometry": {"coordinates":[-1.7943550348,50.7404632568],"type":"Point"}
}