{
  "type": "Feature",
  "properties": {
    "iso:country":"GB",
    "sg:address":"Savile Road",
    "sg:city":"Dewsbury",
    "sg:classifiers":[
        {
            "category":"Autos & Motor Vehicles",
            "subcategory":"Fuel & Gas Station",
            "type":"Retail Goods"
        }
    ],
    "sg:phone":"+44 1924 469839",
    "sg:postcode":"WF12 9LN",
    "sg:province":"West Yorkshire",
    "sg:tags":[
        "petrol",
        "filling"
    ],
    "wof:name":"Save Service Station Ltd.",
    "wof:placetype":"venue"
},
  "geometry": {"coordinates":[-1.630614,53.686508],"type":"Point"}
}