{
  "type": "Feature",
  "properties": {
    "addr:full":"55 Old Milton Road New Milton Hampshire BH25 6DJ",
    "addr:housenumber":"55",
    "addr:postcode":"bh25 6dj",
    "addr:street":"Old Milton Road",
    "iso:country":"GB",
    "sg:address":"55 Old Milton Road",
    "sg:city":"New Milton",
    "sg:classifiers":[
        {
            "category":"Shopping",
            "subcategory":"Department Store",
            "type":"Retail Goods"
        },
        {
            "category":"Shopping",
            "subcategory":"Party Supplies",
            "type":"Retail Goods"
        }
    ],
    "sg:phone":"+44 1425 612044",
    "sg:postcode":"BH25 6DJ",
    "sg:province":"Hampshire",
    "sg:tags":[
        "novelty"
    ],
    "wof:name":"Party Spot",
    "wof:placetype":"venue"
},
  "geometry": {"coordinates":[-1.6583679914,50.7520294189],"type":"Point"}
}