{
  "type": "Feature",
  "properties": {
    "iso:country":"GB",
    "sg:address":"15 Delderfield",
    "sg:city":"Leatherhead",
    "sg:classifiers":[
        {
            "category":"Real Estate",
            "subcategory":"Real Estate Operator",
            "type":"Services"
        }
    ],
    "sg:phone":"+44 1372 747261",
    "sg:postcode":"KT22 8UA",
    "sg:province":"Surrey",
    "sg:tags":[
        "letting",
        "agent"
    ],
    "wof:name":"Burgess Residential Lettings",
    "wof:placetype":"venue"
},
  "geometry": {"coordinates":[-0.3099940121,51.2997589111],"type":"Point"}
}