{
  "type": "Feature",
  "properties": {
    "addr:full":"Inzievar School, Station Rd Dunfermline Fife KY12 9RJ",
    "addr:postcode":"ky12 9rj",
    "addr:street":"Station Rd",
    "iso:country":"GB",
    "sg:address":"Inzievar School, Station Rd",
    "sg:city":"Dunfermline",
    "sg:classifiers":[
        {
            "category":"Education",
            "subcategory":"Library",
            "type":"Public Place"
        }
    ],
    "sg:phone":"+44 1383 850841",
    "sg:postcode":"KY12 9RJ",
    "sg:province":"Fife",
    "sg:tags":[
        "book"
    ],
    "wof:name":"Oakley Branch Library",
    "wof:placetype":"venue"
},
  "geometry": {"coordinates":[-3.4613740444,56.0748443604],"type":"Point"}
}