{
  "type": "Feature",
  "properties": {
    "addr:full":"3 Ct, 19 Market St Ashby De La Zouch Derbyshire LE65 1AJ",
    "addr:housenumber":"19",
    "addr:postcode":"le65 1aj",
    "addr:street":"3 Ct;Market St",
    "iso:country":"GB",
    "sg:address":"3 Ct, 19 Market St",
    "sg:city":"Ashby De La Zouch",
    "sg:classifiers":[
        {
            "category":"Shopping",
            "subcategory":"Baby Store",
            "type":"Retail Goods"
        }
    ],
    "sg:phone":"+44 1530 411181",
    "sg:postcode":"LE65 1AJ",
    "sg:province":"Derbyshire",
    "sg:tags":[
        "nursery",
        "accessory"
    ],
    "wof:name":"Baby Wheels",
    "wof:placetype":"venue"
},
  "geometry": {"coordinates":[-1.4748610258,52.7480926514],"type":"Point"}
}