{
  "type": "Feature",
  "properties": {
    "addr:full":"Beach Road, Portreath Redruth Cornwall TR16 4PH",
    "addr:postcode":"tr16 4ph",
    "addr:street":"Beach Road",
    "iso:country":"GB",
    "sg:address":"Beach Road, Portreath",
    "sg:city":"Redruth",
    "sg:classifiers":[
        {
            "category":"Cafe",
            "type":"Food & Drink"
        }
    ],
    "sg:phone":"+44 1209 842321",
    "sg:postcode":"TR16 4PH",
    "sg:province":"Cornwall",
    "sg:tags":[
        "tea",
        "room"
    ],
    "wof:name":"Colporth Beach Ltd.",
    "wof:placetype":"venue"
},
  "geometry": {"coordinates":[-5.290253,50.25972],"type":"Point"}
}