{
  "type": "Feature",
  "properties": {
    "iso:country":"GB",
    "sg:address":"12 Osmaston Rd",
    "sg:city":"Derby",
    "sg:classifiers":[
        {
            "category":"Shopping",
            "subcategory":"Mobile Phones",
            "type":"Retail Goods"
        }
    ],
    "sg:phone":"+44 1332 363655",
    "sg:postcode":"DE1 2HR",
    "sg:province":"Derbyshire",
    "wof:name":"Convergent Dormant Two Ltd",
    "wof:placetype":"venue"
},
  "geometry": {"coordinates":[-1.475111,52.91869],"type":"Point"}
}