{
  "type": "Feature",
  "properties": {
    "iso:country":"GB",
    "sg:address":"78 Church Street",
    "sg:city":"Leighton Buzzard",
    "sg:classifiers":[
        {
            "category":"Banks & Credit Unions",
            "subcategory":"Bank",
            "type":"Services"
        },
        {
            "category":"Building & Trades",
            "subcategory":"Construction",
            "type":"Services"
        }
    ],
    "sg:phone":"+44 1525 382798",
    "sg:postcode":"LU7 1BT",
    "sg:province":"Bedfordshire",
    "sg:tags":[
        "road",
        "marking",
        "surfacing",
        "surface"
    ],
    "wof:name":"P A Marking Co",
    "wof:placetype":"venue"
},
  "geometry": {"coordinates":[-0.660219,51.92247],"type":"Point"}
}