{
  "type": "Feature",
  "properties": {
    "iso:country":"GB",
    "sg:address":"Consort House, Wesley St",
    "sg:city":"Ossett",
    "sg:classifiers":[
        {
            "category":"Health Services",
            "subcategory":"Dentist",
            "type":"Services"
        }
    ],
    "sg:phone":"+44 1924 283283",
    "sg:postcode":"WF5 8ET",
    "sg:province":"West Yorkshire",
    "wof:name":"P.R Jefferson",
    "wof:placetype":"venue"
},
  "geometry": {"coordinates":[-1.588312,53.681381],"type":"Point"}
}