{
  "type": "Feature",
  "properties": {
    "iso:country":"GB",
    "sg:address":"St James Road, Goffs Oak",
    "sg:city":"Waltham Cross",
    "sg:classifiers":[
        {
            "category":"Banks & Credit Unions",
            "subcategory":"Investment Brokerage",
            "type":"Services"
        }
    ],
    "sg:phone":"+44 1707 872099",
    "sg:postcode":"EN7 6TR",
    "sg:province":"Greater London",
    "sg:tags":[
        "contractor"
    ],
    "wof:name":"Paul Cable Agricultural Contractor",
    "wof:placetype":"venue"
},
  "geometry": {"coordinates":[-0.07975,51.712624],"type":"Point"}
}