{
  "type": "Feature",
  "properties": {
    "iso:country":"GB",
    "sg:address":"78 Bawdlands",
    "sg:city":"Clitheroe",
    "sg:classifiers":[
        {
            "category":"Home & Garden",
            "subcategory":"Building Materials",
            "type":"Retail Goods"
        }
    ],
    "sg:phone":"+44 1200 426842",
    "sg:postcode":"BB7 2LA",
    "sg:province":"Lancashire",
    "sg:tags":[
        "hinge"
    ],
    "wof:name":"Allsafe Lockshop",
    "wof:placetype":"venue"
},
  "geometry": {"coordinates":[-2.3981399536,53.8701400757],"type":"Point"}
}