{
  "type": "Feature",
  "properties": {
    "addr:full":"C/o Petros Textiles Valley Mills Bradford West Yorkshire BD1 4RU",
    "addr:postcode":"bd1 4ru",
    "addr:street":"C;West",
    "iso:country":"GB",
    "sg:address":"C/o Petros Textiles Valley Mills",
    "sg:city":"Bradford",
    "sg:classifiers":[
        {
            "category":"Professional",
            "subcategory":"Business Services",
            "type":"Services"
        }
    ],
    "sg:postcode":"BD1 4RU",
    "sg:province":"West Yorkshire",
    "sg:tags":[
        "accomodation"
    ],
    "wof:name":"Landheath Ltd.",
    "wof:placetype":"venue"
},
  "geometry": {"coordinates":[-1.7568700314,53.8050689697],"type":"Point"}
}