{
  "type": "Feature",
  "properties": {
    "iso:country":"GB",
    "sg:address":"417-419 Ecclesall Road",
    "sg:city":"Sheffield",
    "sg:classifiers":[
        {
            "category":"Wholesale",
            "subcategory":"Toys & Hobbies",
            "type":"Manufacturing & Wholesale Goods"
        }
    ],
    "sg:postcode":"S11 8PG",
    "sg:province":"Derbyshire",
    "sg:tags":[
        "balloon",
        "novelty"
    ],
    "wof:name":"The Design Studio",
    "wof:placetype":"venue"
},
  "geometry": {"coordinates":[-1.492463,53.370083],"type":"Point"}
}