{
  "type": "Feature",
  "properties": {
    "addr:full":"Cherry Trees Bedlars Green, Great Hallingbury Bishops Stortford Essex CM22 7TL",
    "addr:housenumber":"hallingbury",
    "addr:postcode":"cm22 7tl",
    "addr:street":"Bedlars Green",
    "iso:country":"GB",
    "sg:address":"Cherry Trees Bedlars Green, Great Hallingbury",
    "sg:city":"Bishops Stortford",
    "sg:classifiers":[
        {
            "category":"Building & Trades",
            "subcategory":"Cleaning & Sanitation",
            "type":"Services"
        }
    ],
    "sg:phone":"+44 1279 656168",
    "sg:postcode":"CM22 7TL",
    "sg:province":"Essex",
    "sg:tags":[
        "commercial"
    ],
    "wof:name":"Slainte Cleaning Services",
    "wof:placetype":"venue"
},
  "geometry": {"coordinates":[0.19433,51.855236],"type":"Point"}
}