{
  "type": "Feature",
  "properties": {
    "iso:country":"GB",
    "sg:address":"Winterbourne House, 53-55 Argyle Road",
    "sg:city":"Reading",
    "sg:classifiers":[
        {
            "category":"Health Services",
            "subcategory":"Health Practitioner",
            "type":"Services"
        }
    ],
    "sg:phone":"+44 118 956 1250",
    "sg:postcode":"RG1 7YL",
    "sg:province":"Berkshire",
    "sg:tags":[
        "psychotherapist"
    ],
    "wof:name":"West Berkshire Psychotherapy Service",
    "wof:placetype":"venue"
},
  "geometry": {"coordinates":[-0.9898120165,51.4536132812],"type":"Point"}
}