{
  "type": "Feature",
  "properties": {
    "addr:full":"24 Kingswood, Marchwood Southampton Hampshire SO40 4YQ",
    "addr:housenumber":"24",
    "addr:postcode":"so40 4yq",
    "addr:street":"Kingswood",
    "iso:country":"GB",
    "sg:address":"24 Kingswood, Marchwood",
    "sg:city":"Southampton",
    "sg:classifiers":[
        {
            "category":"Building & Trades",
            "subcategory":"Cleaning & Sanitation",
            "type":"Services"
        }
    ],
    "sg:phone":"+44 23 8066 0996",
    "sg:postcode":"SO40 4YQ",
    "sg:province":"Hampshire",
    "sg:tags":[
        "hygiene",
        "cleansing"
    ],
    "wof:name":"Remark Chemicals",
    "wof:placetype":"venue"
},
  "geometry": {"coordinates":[-1.4542989731,50.8926506042],"type":"Point"}
}