{
  "type": "Feature",
  "properties": {
    "addr:full":"Cottage Street Macclesfield Cheshire SK10 1AQ",
    "addr:postcode":"sk10 1aq",
    "addr:street":"Cottage Street",
    "iso:country":"GB",
    "sg:address":"Cottage Street",
    "sg:city":"Macclesfield",
    "sg:classifiers":[
        {
            "category":"Home & Garden",
            "subcategory":"Furniture",
            "type":"Retail Goods"
        }
    ],
    "sg:phone":"+44 1625 422525",
    "sg:postcode":"SK10 1AQ",
    "sg:province":"Cheshire",
    "wof:name":"Monk Furniture U K Ltd.",
    "wof:placetype":"venue"
},
  "geometry": {"coordinates":[-2.107964,53.258156],"type":"Point"}
}