{
  "type": "Feature",
  "properties": {
    "addr:full":"17 Grange View, Newbottle Houghton-le-spring Durham DH4 4HU",
    "addr:housenumber":"17",
    "addr:postcode":"dh4 4hu",
    "addr:street":"Grange View",
    "iso:country":"GB",
    "sg:address":"17 Grange View, Newbottle",
    "sg:city":"Houghton-le-spring",
    "sg:classifiers":[
        {
            "category":"Farming",
            "subcategory":"Dairy Farm",
            "type":"Manufacturing & Wholesale Goods"
        }
    ],
    "sg:postcode":"DH4 4HU",
    "sg:province":"Durham",
    "wof:name":"K R Cummings",
    "wof:placetype":"venue"
},
  "geometry": {"coordinates":[-1.4781810045,54.857585907],"type":"Point"}
}