{
  "type": "Feature",
  "properties": {
    "addr:full":"40-42 Coombe Road Kingston-upon-thames Greater London KT2 7AF",
    "addr:housenumber":"40-42",
    "addr:postcode":"kt2 7af",
    "addr:street":"Coombe Road",
    "iso:country":"GB",
    "sg:address":"40-42 Coombe Road",
    "sg:city":"Kingston-upon-thames",
    "sg:classifiers":[
        {
            "category":"Home & Garden",
            "subcategory":"Kitchen Supply",
            "type":"Retail Goods"
        },
        {
            "category":"Wholesale",
            "subcategory":"Groceries",
            "type":"Manufacturing & Wholesale Goods"
        },
        {
            "category":"Food & Beverages",
            "subcategory":"Meat & Fish",
            "type":"Retail Goods"
        }
    ],
    "sg:phone":"+44 20 8547 3588",
    "sg:postcode":"KT2 7AF",
    "sg:province":"Greater London",
    "sg:tags":[
        "supplier",
        "drink",
        "butcher",
        "catering"
    ],
    "wof:name":"Jefferies Two Butchers",
    "wof:placetype":"venue"
},
  "geometry": {"coordinates":[-0.283104986,51.4128341675],"type":"Point"}
}