{
  "type": "Feature",
  "properties": {
    "iso:country":"GB",
    "sg:address":"24a White Hart St",
    "sg:city":"High Wycombe",
    "sg:classifiers":[
        {
            "category":"Retail",
            "subcategory":"Laundry & Dry Cleaning",
            "type":"Services"
        }
    ],
    "sg:phone":"+44 1494 524378",
    "sg:postcode":"HP11 2HL",
    "sg:province":"Buckinghamshire",
    "sg:tags":[
        "alteration"
    ],
    "wof:name":"Bentleys",
    "wof:placetype":"venue"
},
  "geometry": {"coordinates":[-0.752368,51.630039],"type":"Point"}
}