{
  "type": "Feature",
  "properties": {
    "addr:full":"West House, 21 West Street Haslemere Hampshire GU27 2AB",
    "addr:housenumber":"21",
    "addr:postcode":"gu27 2ab",
    "addr:street":"West Street",
    "iso:country":"GB",
    "sg:address":"West House, 21 West Street",
    "sg:city":"Haslemere",
    "sg:classifiers":[
        {
            "category":"Wholesale",
            "subcategory":"Books, Periodicals, & Newspapers",
            "type":"Manufacturing & Wholesale Goods"
        }
    ],
    "sg:phone":"+44 1428 609099",
    "sg:postcode":"GU27 2AB",
    "sg:province":"Hampshire",
    "sg:tags":[
        "publishing"
    ],
    "wof:name":"Emmett Publishing Ltd.",
    "wof:placetype":"venue"
},
  "geometry": {"coordinates":[-0.7098680139,51.0888824463],"type":"Point"}
}