{
  "type": "Feature",
  "properties": {
    "addr:full":"8 Lennox Street Weymouth Dorset DT4 7HD",
    "addr:housenumber":"8",
    "addr:postcode":"dt4 7hd",
    "addr:street":"Lennox Street",
    "iso:country":"GB",
    "sg:address":"8 Lennox Street",
    "sg:city":"Weymouth",
    "sg:classifiers":[
        {
            "category":"Travel",
            "subcategory":"Hotels & Motels",
            "type":"Entertainment"
        }
    ],
    "sg:phone":"+44 1305 771238",
    "sg:postcode":"DT4 7HD",
    "sg:province":"Dorset",
    "sg:tags":[
        "house",
        "guest"
    ],
    "wof:name":"Gleneagles Guest House",
    "wof:placetype":"venue"
},
  "geometry": {"coordinates":[-2.4529130459,50.6179656982],"type":"Point"}
}