{
  "type": "Feature",
  "properties": {
    "iso:country":"GB",
    "sg:address":"108 High Street, Portishead",
    "sg:city":"Bristol",
    "sg:classifiers":[
        {
            "category":"Professional",
            "subcategory":"Accounting & Tax Preparation",
            "type":"Services"
        }
    ],
    "sg:phone":"+44 1275 847463",
    "sg:postcode":"BS20 6AJ",
    "sg:province":"Somerset",
    "sg:tags":[
        "accountant"
    ],
    "wof:name":"Dingley Brown & Co.",
    "wof:placetype":"venue"
},
  "geometry": {"coordinates":[-2.768796,51.482006],"type":"Point"}
}