{
  "type": "Feature",
  "properties": {
    "iso:country":"GB",
    "sg:address":"Chisenhale Road",
    "sg:city":"London",
    "sg:classifiers":[
        {
            "category":"Education",
            "subcategory":"School",
            "type":"Public Place"
        }
    ],
    "sg:phone":"+44 20 8980 2584",
    "sg:postcode":"E3 5QY",
    "sg:province":"Greater London",
    "sg:tags":[
        "local",
        "authority"
    ],
    "wof:name":"Chisenhale Primary School",
    "wof:placetype":"venue"
},
  "geometry": {"coordinates":[-0.038329,51.533535],"type":"Point"}
}