{
  "type": "Feature",
  "properties": {
    "addr:full":"167 Victoria Road Swindon Wiltshire SN1 3BU",
    "addr:housenumber":"167",
    "addr:postcode":"sn1 3bu",
    "addr:street":"Victoria Road",
    "iso:country":"GB",
    "sg:address":"167 Victoria Road",
    "sg:city":"Swindon",
    "sg:classifiers":[
        {
            "category":"Real Estate",
            "subcategory":"Real Estate Operator",
            "type":"Services"
        }
    ],
    "sg:phone":"+44 1793 512346",
    "sg:postcode":"SN1 3BU",
    "sg:province":"Wiltshire",
    "sg:tags":[
        "rental"
    ],
    "wof:name":"Chrisgate Holdings Ltd.",
    "wof:placetype":"venue"
},
  "geometry": {"coordinates":[-1.7789599895,51.5564575195],"type":"Point"}
}