{
  "type": "Feature",
  "properties": {
    "iso:country":"GB",
    "sg:address":"12 Mount Pleasant",
    "sg:city":"Bilston",
    "sg:classifiers":[
        {
            "category":"Personal",
            "subcategory":"Beauty Salon",
            "type":"Services"
        }
    ],
    "sg:phone":"+44 1902 492878",
    "sg:postcode":"WV14 7LJ",
    "sg:province":"West Midlands",
    "sg:tags":[
        "unisex",
        "hairdresser"
    ],
    "wof:name":"Herr Flick",
    "wof:placetype":"venue"
},
  "geometry": {"coordinates":[-2.0747981071,52.5673294067],"type":"Point"}
}