{
  "type": "Feature",
  "properties": {
    "addr:full":"247-249 Bury New Rd, Whitefield Manchester Lancashire M45 8QP",
    "addr:housenumber":"247-249",
    "addr:postcode":"m45 8qp",
    "addr:street":"Bury New Rd",
    "iso:country":"GB",
    "sg:address":"247-249 Bury New Rd, Whitefield",
    "sg:city":"Manchester",
    "sg:classifiers":[
        {
            "category":"Retail",
            "subcategory":"Laundry & Dry Cleaning",
            "type":"Services"
        }
    ],
    "sg:phone":"+44 161 796 1696",
    "sg:postcode":"M45 8QP",
    "sg:province":"Lancashire",
    "sg:tags":[
        "alteration"
    ],
    "wof:name":"ALLENS THE CLEANERS",
    "wof:placetype":"venue"
},
  "geometry": {"coordinates":[-2.2962489128,53.5516204834],"type":"Point"}
}