{
  "type": "Feature",
  "properties": {
    "addr:full":"Oathall Community College, Appledore Gardens Haywards Heath East Sussex RH16 2AQ",
    "addr:postcode":"rh16 2aq",
    "addr:street":"Appledore Gardens",
    "iso:country":"GB",
    "sg:address":"Oathall Community College, Appledore Gardens",
    "sg:city":"Haywards Heath",
    "sg:classifiers":[
        {
            "category":"Education",
            "subcategory":"University",
            "type":"Public Place"
        }
    ],
    "sg:postcode":"RH16 2AQ",
    "sg:province":"East Sussex",
    "sg:tags":[
        "adult"
    ],
    "wof:name":"Haywards Heath Adult Education",
    "wof:placetype":"venue"
},
  "geometry": {"coordinates":[-0.102047,50.996658],"type":"Point"}
}