{
  "type": "Feature",
  "properties": {
    "addr:full":"Dolafan Newtown Powys SY16 4LN",
    "addr:postcode":"sy16 4ln",
    "addr:street":"Dolafan",
    "iso:country":"GB",
    "sg:address":"Dolafan",
    "sg:city":"Newtown",
    "sg:classifiers":[
        {
            "category":"Shopping",
            "subcategory":"Pharmacy",
            "type":"Retail Goods"
        }
    ],
    "sg:phone":"+44 1686 670706",
    "sg:postcode":"SY16 4LN",
    "sg:province":"Powys",
    "sg:tags":[
        "medicine",
        "therapy"
    ],
    "wof:name":"J & A Perry",
    "wof:placetype":"venue"
},
  "geometry": {"coordinates":[-3.2797091007,52.49269104],"type":"Point"}
}