{
  "type": "Feature",
  "properties": {
    "addr:full":"Kirton Holme Boston Lincolnshire PE20 1TT",
    "addr:postcode":"pe20 1tt",
    "iso:country":"GB",
    "sg:address":"Kirton Holme",
    "sg:city":"Boston",
    "sg:classifiers":[
        {
            "category":"Food & Beverages",
            "subcategory":"Groceries & Convenience Stores",
            "type":"Retail Goods"
        }
    ],
    "sg:phone":"+44 1205 290029",
    "sg:postcode":"PE20 1TT",
    "sg:province":"Lincolnshire",
    "sg:tags":[
        "merchant",
        "potato"
    ],
    "wof:name":"Boston Potato Co. Ltd.",
    "wof:placetype":"venue"
},
  "geometry": {"coordinates":[-0.12474,52.963551],"type":"Point"}
}