{
  "type": "Feature",
  "properties": {
    "iso:country":"GB",
    "sg:address":"93 Hunters Road",
    "sg:city":"Chessington",
    "sg:classifiers":[
        {
            "category":"Professional",
            "subcategory":"Engineering",
            "type":"Services"
        }
    ],
    "sg:postcode":"KT9 1RY",
    "sg:province":"Surrey",
    "sg:tags":[
        "gas",
        "engineer"
    ],
    "wof:name":"Ruder Gas Plumbing & Heating Services",
    "wof:placetype":"venue"
},
  "geometry": {"coordinates":[-0.2998560071,51.3699493408],"type":"Point"}
}