{
  "type": "Feature",
  "properties": {
    "iso:country":"GB",
    "sg:address":"47 Glen Rise",
    "sg:city":"Birmingham",
    "sg:classifiers":[
        {
            "category":"Building & Trades",
            "subcategory":"Construction",
            "type":"Services"
        }
    ],
    "sg:phone":"+44 121 777 7850",
    "sg:postcode":"B13 0EH",
    "sg:province":"West Midlands",
    "sg:tags":[
        "builder"
    ],
    "wof:name":"Peter Dalton",
    "wof:placetype":"venue"
},
  "geometry": {"coordinates":[-1.862112,52.424969],"type":"Point"}
}