{
  "type": "Feature",
  "properties": {
    "addr:full":"16 Melville Terrace Stirling Stirling FK8 2NE",
    "addr:housenumber":"16",
    "addr:postcode":"fk8 2ne",
    "addr:street":"Melville Terrace",
    "iso:country":"GB",
    "sg:address":"16 Melville Terrace",
    "sg:city":"Stirling",
    "sg:classifiers":[
        {
            "category":"Building & Trades",
            "subcategory":"Construction",
            "type":"Services"
        }
    ],
    "sg:phone":"+44 1786 446910",
    "sg:postcode":"FK8 2NE",
    "sg:province":"Stirling",
    "sg:tags":[
        "builder"
    ],
    "wof:name":"John Arnott Associates",
    "wof:placetype":"venue"
},
  "geometry": {"coordinates":[-3.939015,56.112396],"type":"Point"}
}