{
  "type": "Feature",
  "properties": {
    "addr:full":"Caravan Site Wincanton Somerset BA9 8BJ",
    "addr:postcode":"ba9 8bj",
    "iso:country":"GB",
    "sg:address":"Caravan Site",
    "sg:city":"Wincanton",
    "sg:classifiers":[
        {
            "category":"Recreation",
            "subcategory":"Campground",
            "type":"Entertainment"
        }
    ],
    "sg:phone":"+44 1963 34276",
    "sg:postcode":"BA9 8BJ",
    "sg:province":"Somerset",
    "sg:tags":[
        "caravan",
        "park"
    ],
    "wof:name":"Wincanton Racecourse",
    "wof:placetype":"venue"
},
  "geometry": {"coordinates":[-2.413179,51.0578],"type":"Point"}
}