{
  "type": "Feature",
  "properties": {
    "addr:full":"3 Metcalfe Road, Skippers Lane Industrial Estate Middlesbrough North Yorkshire TS6 6PT",
    "addr:housenumber":"3",
    "addr:postcode":"ts6 6pt",
    "addr:street":"Metcalfe Road Skippers Lane Industrial Estate",
    "iso:country":"GB",
    "sg:address":"3 Metcalfe Road, Skippers Lane Industrial Estate",
    "sg:city":"Middlesbrough",
    "sg:classifiers":[
        {
            "category":"Retail",
            "subcategory":"Auto Repair",
            "type":"Services"
        }
    ],
    "sg:phone":"+44 1642 467080",
    "sg:postcode":"TS6 6PT",
    "sg:province":"North Yorkshire",
    "sg:tags":[
        "body",
        "car",
        "repairer"
    ],
    "wof:name":"Century Auto Refinishers",
    "wof:placetype":"venue"
},
  "geometry": {"coordinates":[-1.187089,54.574585],"type":"Point"}
}