{
  "type": "Feature",
  "properties": {
    "addr:full":"Denaby Lane, Denaby Main Industrial Estate Doncaster South Yorkshire DN12 4LQ",
    "addr:housenumber":"estate",
    "addr:postcode":"dn12 4lq",
    "addr:street":"Denaby Lane;Main Industrial",
    "iso:country":"GB",
    "sg:address":"Denaby Lane, Denaby Main Industrial Estate",
    "sg:city":"Doncaster",
    "sg:classifiers":[
        {
            "category":"Wholesale",
            "subcategory":"Construction Materials",
            "type":"Manufacturing & Wholesale Goods"
        }
    ],
    "sg:phone":"+44 1709 864848",
    "sg:postcode":"DN12 4LQ",
    "sg:province":"South Yorkshire",
    "sg:tags":[
        "refractory"
    ],
    "wof:name":"Monocon Refractories Ltd.",
    "wof:placetype":"venue"
},
  "geometry": {"coordinates":[-1.245274,53.491844],"type":"Point"}
}