{
  "type": "Feature",
  "properties": {
    "iso:country":"GB",
    "sg:address":"276 Warwick Rd",
    "sg:city":"Banbury",
    "sg:classifiers":[
        {
            "category":"Bus Charters",
            "type":"Transportation"
        }
    ],
    "sg:phone":"+44 1295 258930",
    "sg:postcode":"OX16 7AZ",
    "sg:province":"Oxfordshire",
    "sg:tags":[
        "mini",
        "hire",
        "leasing"
    ],
    "wof:name":"1st T & J Mini-Bus Service",
    "wof:placetype":"venue"
},
  "geometry": {"coordinates":[-1.350988,52.066555],"type":"Point"}
}