{
  "type": "Feature",
  "properties": {
    "addr:full":"Gatcombe Drive Portsmouth Hampshire PO2 0TX",
    "addr:postcode":"hampshire po2 0tx",
    "addr:street":"Gatcombe Drive",
    "iso:country":"GB",
    "sg:address":"Gatcombe Drive",
    "sg:city":"Portsmouth",
    "sg:classifiers":[
        {
            "category":"Government",
            "subcategory":"Office",
            "type":"Public Place"
        }
    ],
    "sg:phone":"+44 23 9269 4423",
    "sg:postcode":"PO2 0TX",
    "sg:province":"Hampshire",
    "sg:tags":[
        "local"
    ],
    "wof:name":"Russets Hostel",
    "wof:placetype":"venue"
},
  "geometry": {"coordinates":[-1.070089,50.826736],"type":"Point"}
}