{
  "type": "Feature",
  "properties": {
    "iso:country":"GB",
    "sg:address":"34a High West Street",
    "sg:city":"Dorchester",
    "sg:classifiers":[
        {
            "category":"Personal",
            "subcategory":"Beauty Salon",
            "type":"Services"
        }
    ],
    "sg:postcode":"DT1 1UT",
    "sg:province":"Dorset",
    "sg:tags":[
        "unisex",
        "hairdresser"
    ],
    "wof:name":"Carol Chambers",
    "wof:placetype":"venue"
},
  "geometry": {"coordinates":[-2.440679,50.71487],"type":"Point"}
}