{
  "type": "Feature",
  "properties": {
    "addr:full":"Canning St Maidstone Kent ME14 2RY",
    "addr:postcode":"me14 2ry",
    "addr:street":"Canning St",
    "iso:country":"GB",
    "sg:address":"Canning St",
    "sg:city":"Maidstone",
    "sg:classifiers":[
        {
            "category":"Manufacturing",
            "subcategory":"Building Materials",
            "type":"Manufacturing & Wholesale Goods"
        }
    ],
    "sg:phone":"+44 1622 757151",
    "sg:postcode":"ME14 2RY",
    "sg:province":"Kent",
    "sg:tags":[
        "merchant",
        "builder"
    ],
    "wof:name":"Hall & Co Ltd",
    "wof:placetype":"venue"
},
  "geometry": {"coordinates":[0.52322,51.283676],"type":"Point"}
}