{
  "type": "Feature",
  "properties": {
    "addr:full":"Unit 12 & 13 Daniels Trading Estate, Bath Road, Lightpill Stroud Gloucestershire GL5 3TL",
    "addr:housenumber":"unit 12 & 13",
    "addr:postcode":"gl5 3tl",
    "addr:street":"Daniels Trading Estate Bath Road Lightpill",
    "iso:country":"GB",
    "sg:address":"Unit 12 & 13 Daniels Trading Estate, Bath Road, Lightpill",
    "sg:city":"Stroud",
    "sg:classifiers":[
        {
            "category":"Professional",
            "subcategory":"Engineering",
            "type":"Services"
        }
    ],
    "sg:phone":"+44 1453 759456",
    "sg:postcode":"GL5 3TL",
    "sg:province":"Gloucestershire",
    "sg:tags":[
        "precision",
        "engineer"
    ],
    "wof:name":"Dibone Engineering Ltd",
    "wof:placetype":"venue"
},
  "geometry": {"coordinates":[-2.2329499722,51.7372207642],"type":"Point"}
}