{
  "type": "Feature",
  "properties": {
    "iso:country":"GB",
    "sg:address":"27 Swinegate",
    "sg:city":"Grantham",
    "sg:classifiers":[
        {
            "category":"Building & Trades",
            "subcategory":"Construction",
            "type":"Services"
        }
    ],
    "sg:phone":"+44 1476 563767",
    "sg:postcode":"NG31 6RL",
    "sg:province":"Lincolnshire",
    "sg:tags":[
        "glazier"
    ],
    "wof:name":"A & A Glass & Glazing",
    "wof:placetype":"venue"
},
  "geometry": {"coordinates":[-0.643011,52.915558],"type":"Point"}
}