{
  "type": "Feature",
  "properties": {
    "addr:full":"Brook Fold Farm, Brookfold Lane, Harwood Bolton Lancashire BL2 4LT",
    "addr:postcode":"bl2 4lt",
    "addr:street":"Brook;Brookfold Lane",
    "iso:country":"GB",
    "sg:address":"Brook Fold Farm, Brookfold Lane, Harwood",
    "sg:city":"Bolton",
    "sg:classifiers":[
        {
            "category":"Transit Center",
            "subcategory":"Passenger",
            "type":"Transportation"
        }
    ],
    "sg:phone":"+44 1204 307780",
    "sg:postcode":"BL2 4LT",
    "sg:province":"Lancashire",
    "sg:tags":[
        "boarding",
        "kennel",
        "catteries"
    ],
    "wof:name":"J Morgan",
    "wof:placetype":"venue"
},
  "geometry": {"coordinates":[-2.3894119263,53.6249427795],"type":"Point"}
}