{
  "type": "Feature",
  "properties": {
    "addr:full":"Castletown Medical Practice, The Surgery, Murrayfield Thurso Highland KW14 8TY",
    "addr:postcode":"kw14 8ty",
    "iso:country":"GB",
    "sg:address":"Castletown Medical Practice, The Surgery, Murrayfield",
    "sg:city":"Thurso",
    "sg:classifiers":[
        {
            "category":"Health Services",
            "subcategory":"Doctor",
            "type":"Services"
        }
    ],
    "sg:phone":"+44 1847 821205",
    "sg:postcode":"KW14 8TY",
    "sg:province":"Highland",
    "sg:tags":[
        "practitioners"
    ],
    "wof:name":"Duncan G Robertson",
    "wof:placetype":"venue"
},
  "geometry": {"coordinates":[-3.388349,58.592079],"type":"Point"}
}