{
  "type": "Feature",
  "properties": {
    "addr:full":"Weeth Farm, Penhale Rd Camborne Cornwall TR14 0LT",
    "addr:postcode":"tr14 0lt",
    "addr:street":"Penhale Rd",
    "iso:country":"GB",
    "sg:address":"Weeth Farm, Penhale Rd",
    "sg:city":"Camborne",
    "sg:classifiers":[
        {
            "category":"Building & Trades",
            "subcategory":"Construction",
            "type":"Services"
        }
    ],
    "sg:phone":"+44 1209 831724",
    "sg:postcode":"TR14 0LT",
    "sg:province":"Cornwall",
    "sg:tags":[
        "builder"
    ],
    "wof:name":"3a's Roofing & Building",
    "wof:placetype":"venue"
},
  "geometry": {"coordinates":[-5.3012580872,50.2136535645],"type":"Point"}
}