{
  "type": "Feature",
  "properties": {
    "iso:country":"GB",
    "sg:address":"5 Park Drive",
    "sg:city":"Glasgow",
    "sg:classifiers":[
        {
            "category":"Wholesale",
            "subcategory":"Scrap",
            "type":"Manufacturing & Wholesale Goods"
        }
    ],
    "sg:postcode":"G74 5AS",
    "sg:province":"South Lanarkshire",
    "sg:tags":[
        "waste",
        "metal"
    ],
    "wof:name":"Taylor Metals",
    "wof:placetype":"venue"
},
  "geometry": {"coordinates":[-4.2456579208,55.7695159912],"type":"Point"}
}