{
  "type": "Feature",
  "properties": {
    "addr:full":"Station Yard Business Park, Station Road     Barnack Stamford Cambridgeshire PE9 3DW",
    "addr:postcode":"pe9 3dw",
    "addr:street":"Station Road",
    "iso:country":"GB",
    "sg:address":"Station Yard Business Park, Station Road     Barnack",
    "sg:city":"Stamford",
    "sg:classifiers":[
        {
            "category":"Shopping",
            "subcategory":"Books",
            "type":"Retail Goods"
        }
    ],
    "sg:postcode":"PE9 3DW",
    "sg:province":"Cambridgeshire",
    "wof:name":"Fitness Today Ltd",
    "wof:placetype":"venue"
},
  "geometry": {"coordinates":[-0.4057590067,52.6343460083],"type":"Point"}
}