{
  "type": "Feature",
  "properties": {
    "addr:full":"Oak Lane West Bromwich West Midlands B70 8PR",
    "addr:postcode":"b70 8pr",
    "addr:street":"Oak Lane",
    "iso:country":"GB",
    "sg:address":"Oak Lane",
    "sg:city":"West Bromwich",
    "sg:classifiers":[
        {
            "category":"Organizations",
            "subcategory":"Community Association",
            "type":"Services"
        },
        {
            "category":"Organizations",
            "subcategory":"Membership Organization",
            "type":"Services"
        }
    ],
    "sg:phone":"+44 121 553 0739",
    "sg:postcode":"B70 8PR",
    "sg:province":"West Midlands",
    "sg:tags":[
        "club",
        "social"
    ],
    "wof:name":"Oakdale Social Club",
    "wof:placetype":"venue"
},
  "geometry": {"coordinates":[-2.0053939819,52.5187568665],"type":"Point"}
}