{
  "type": "Feature",
  "properties": {
    "addr:full":"74a The Broadway London Greater London W13 0SY",
    "addr:housenumber":"74a",
    "addr:postcode":"w13 0sy",
    "addr:street":"The Broadway",
    "iso:country":"GB",
    "sg:address":"74a The Broadway",
    "sg:city":"London",
    "sg:classifiers":[
        {
            "category":"Shopping",
            "subcategory":"Shoes",
            "type":"Retail Goods"
        }
    ],
    "sg:phone":"+44 20 8579 1128",
    "sg:postcode":"W13 0SY",
    "sg:province":"Greater London",
    "sg:tags":[
        "shop"
    ],
    "wof:name":"Stead & Simpson Ltd.",
    "wof:placetype":"venue"
},
  "geometry": {"coordinates":[-0.303348,51.513466],"type":"Point"}
}