{
  "type": "Feature",
  "properties": {
    "addr:full":"Fourdoun House, Rue De St Lawrence Waltham Abbey Essex EN9 1PF",
    "addr:postcode":"en9 1pf",
    "addr:street":"Rue De St",
    "iso:country":"GB",
    "sg:address":"Fourdoun House, Rue De St Lawrence",
    "sg:city":"Waltham Abbey",
    "sg:classifiers":[
        {
            "category":"Professional",
            "subcategory":"Detective & Security Services",
            "type":"Services"
        },
        {
            "category":"Shopping",
            "subcategory":"Computers & Home Electronics",
            "type":"Retail Goods"
        }
    ],
    "sg:phone":"+44 1992 714604",
    "sg:postcode":"EN9 1PF",
    "sg:province":"Essex",
    "sg:tags":[
        "equipment",
        "video",
        "cctv"
    ],
    "wof:name":"Videcom Security Ltd.",
    "wof:placetype":"venue"
},
  "geometry": {"coordinates":[0.00101,51.685371],"type":"Point"}
}