{
  "type": "Feature",
  "properties": {
    "iso:country":"GB",
    "sg:address":"40 North Corston Holdings, Coupar Angus",
    "sg:city":"Blairgowrie",
    "sg:classifiers":[
        {
            "category":"Farming",
            "subcategory":"Farm",
            "type":"Manufacturing & Wholesale Goods"
        }
    ],
    "sg:postcode":"PH13 9JH",
    "sg:province":"Angus",
    "sg:tags":[
        "mixed",
        "crop"
    ],
    "wof:name":"A & R Yeaman",
    "wof:placetype":"venue"
},
  "geometry": {"coordinates":[-3.303018,56.519924],"type":"Point"}
}