{
  "type": "Feature",
  "properties": {
    "addr:full":"Mersey View, Carrington Rd Manchester Cheshire M41 6GX",
    "addr:postcode":"m41 6gx",
    "addr:street":"Mersey;Carrington Rd",
    "iso:country":"GB",
    "sg:address":"Mersey View, Carrington Rd",
    "sg:city":"Manchester",
    "sg:classifiers":[
        {
            "category":"Building & Trades",
            "subcategory":"Cleaning & Sanitation",
            "type":"Services"
        }
    ],
    "sg:phone":"+44 161 748 5848",
    "sg:postcode":"M41 6GX",
    "sg:province":"Cheshire",
    "sg:tags":[
        "dry",
        "control",
        "damp",
        "rot"
    ],
    "wof:name":"S I Pugh & Associates Ltd",
    "wof:placetype":"venue"
},
  "geometry": {"coordinates":[-2.384754,53.442635],"type":"Point"}
}