{
  "type": "Feature",
  "properties": {
    "iso:country":"GB",
    "sg:address":"44 Windy Harbour Road",
    "sg:city":"Southport",
    "sg:classifiers":[
        {
            "category":"Professional",
            "subcategory":"Engineering",
            "type":"Services"
        },
        {
            "category":"Building & Trades",
            "subcategory":"Electrical",
            "type":"Services"
        }
    ],
    "sg:phone":"+44 1704 573676",
    "sg:postcode":"PR8 3DU",
    "sg:province":"Lancashire",
    "sg:tags":[
        "engineer",
        "electrician",
        "contractor"
    ],
    "wof:name":"Paul Switzer Electrical Services",
    "wof:placetype":"venue"
},
  "geometry": {"coordinates":[-3.024452,53.6129],"type":"Point"}
}