{
  "type": "Feature",
  "properties": {
    "addr:full":"6a Polgine La Camborne Cornwall TR14 9DY",
    "addr:housenumber":"6a",
    "addr:postcode":"tr14 9dy",
    "addr:street":"Polgine La Camborne",
    "iso:country":"GB",
    "sg:address":"6a Polgine La",
    "sg:city":"Camborne",
    "sg:classifiers":[
        {
            "category":"Building & Trades",
            "subcategory":"Construction",
            "type":"Services"
        }
    ],
    "sg:phone":"+44 1209 718301",
    "sg:postcode":"TR14 9DY",
    "sg:province":"Cornwall",
    "sg:tags":[
        "decorator",
        "painter"
    ],
    "wof:name":"Thompson Don Painting & Maintenance",
    "wof:placetype":"venue"
},
  "geometry": {"coordinates":[-5.2762131691,50.1988754272],"type":"Point"}
}