{
  "type": "Feature",
  "properties": {
    "addr:full":"17 Foulpapple Road Newmilns East Ayrshire KA16 9LB",
    "addr:housenumber":"17",
    "addr:postcode":"ka16 9lb",
    "addr:street":"Foulpapple Road",
    "iso:country":"GB",
    "sg:address":"17 Foulpapple Road",
    "sg:city":"Newmilns",
    "sg:classifiers":[
        {
            "category":"Building & Trades",
            "subcategory":"Pest Control",
            "type":"Services"
        }
    ],
    "sg:postcode":"KA16 9LB",
    "sg:province":"East Ayrshire",
    "sg:tags":[
        "woodworm"
    ],
    "wof:name":"C U Building Services",
    "wof:placetype":"venue"
},
  "geometry": {"coordinates":[-4.310166,55.609287],"type":"Point"}
}