{
  "type": "Feature",
  "properties": {
    "addr:full":"Celtic House, Heritage Gate, Friary St Derby Derbyshire DE1 1QX",
    "addr:postcode":"de1 1qx",
    "addr:street":"Heritage Gate Friary St",
    "iso:country":"GB",
    "sg:address":"Celtic House, Heritage Gate, Friary St",
    "sg:city":"Derby",
    "sg:classifiers":[
        {
            "category":"Education",
            "subcategory":"Library",
            "type":"Public Place"
        }
    ],
    "sg:phone":"+44 1332 716607",
    "sg:postcode":"DE1 1QX",
    "sg:province":"Derbyshire",
    "sg:tags":[
        "book"
    ],
    "wof:name":"Library Headquarters",
    "wof:placetype":"venue"
},
  "geometry": {"coordinates":[-1.483684,52.925171],"type":"Point"}
}