{
  "type": "Feature",
  "properties": {
    "iso:country":"GB",
    "sg:address":"2 Bekesbourne Lane, Littlebourne",
    "sg:city":"Canterbury",
    "sg:classifiers":[
        {
            "category":"Bars & Pubs",
            "type":"Food & Drink"
        }
    ],
    "sg:phone":"+44 1227 721207",
    "sg:postcode":"CT3 1UY",
    "sg:province":"Kent",
    "sg:tags":[
        "pubs",
        "inn",
        "-",
        "restaurant"
    ],
    "wof:name":"The Anchor Inn",
    "wof:placetype":"venue"
},
  "geometry": {"coordinates":[1.16543,51.271191],"type":"Point"}
}