{
  "type": "Feature",
  "properties": {
    "iso:country":"GB",
    "sg:address":"Blythe House, Great Hollands Square",
    "sg:city":"Bracknell",
    "sg:classifiers":[
        {
            "category":"Health Services",
            "subcategory":"Nursing And Care Facility",
            "type":"Services"
        },
        {
            "category":"Organizations",
            "subcategory":"Community Association",
            "type":"Services"
        }
    ],
    "sg:phone":"+44 1344 455512",
    "sg:postcode":"RG12 8QH",
    "sg:province":"Berkshire",
    "sg:tags":[
        "residential",
        "housing",
        "society"
    ],
    "wof:name":"THE FELLOWSHIP HOUSES TRUST",
    "wof:placetype":"venue"
},
  "geometry": {"coordinates":[-0.771594,51.398853],"type":"Point"}
}