{
  "type": "Feature",
  "properties": {
    "addr:full":"26 Aintree Ave, Eastham London Greater London E6 1NX",
    "addr:housenumber":"26",
    "addr:postcode":"e6 1nx",
    "addr:street":"Aintree Ave",
    "iso:country":"GB",
    "sg:address":"26 Aintree Ave, Eastham",
    "sg:city":"London",
    "sg:classifiers":[
        {
            "category":"Building & Trades",
            "subcategory":"Plumbing",
            "type":"Services"
        }
    ],
    "sg:postcode":"E6 1NX",
    "sg:province":"Greater London",
    "sg:tags":[
        "heating"
    ],
    "wof:name":"Manthar,Balraj,",
    "wof:placetype":"venue"
},
  "geometry": {"coordinates":[0.048583,51.532921],"type":"Point"}
}