{
  "type": "Feature",
  "properties": {
    "addr:full":"15 South End Croydon Surrey CR0 1BE",
    "addr:housenumber":"15",
    "addr:postcode":"cr0 1be",
    "addr:street":"South End",
    "iso:country":"GB",
    "sg:address":"15 South End",
    "sg:city":"Croydon",
    "sg:classifiers":[
        {
            "category":"Shopping",
            "subcategory":"Bicycles & Sporting Goods",
            "type":"Retail Goods"
        }
    ],
    "sg:phone":"+44 20 8688 5094",
    "sg:postcode":"CR0 1BE",
    "sg:province":"Surrey",
    "sg:tags":[
        "cycle",
        "accessory"
    ],
    "wof:name":"Geoffrey Butler (Cycles) Ltd.",
    "wof:placetype":"venue"
},
  "geometry": {"coordinates":[-0.098807998,51.3673248291],"type":"Point"}
}