{
  "type": "Feature",
  "properties": {
    "iso:country":"GB",
    "sg:address":"117 Elmcroft Avenue, Edmonton",
    "sg:city":"London",
    "sg:classifiers":[
        {
            "category":"Building & Trades",
            "subcategory":"Construction",
            "type":"Services"
        }
    ],
    "sg:phone":"+44 20 8443 2159",
    "sg:postcode":"N9 7DP",
    "sg:province":"Greater London",
    "sg:tags":[
        "decorator",
        "painter"
    ],
    "wof:name":"T A Brown Decorating Contractor",
    "wof:placetype":"venue"
},
  "geometry": {"coordinates":[-0.053789001,51.6408042908],"type":"Point"}
}