{
  "type": "Feature",
  "properties": {
    "iso:country":"GB",
    "sg:address":"82 Midland Road",
    "sg:city":"Bedford",
    "sg:classifiers":[
        {
            "category":"Shopping",
            "subcategory":"Department Store",
            "type":"Retail Goods"
        }
    ],
    "sg:postcode":"MK40 1QH",
    "sg:province":"Bedfordshire",
    "wof:name":"Lee & Sons",
    "wof:placetype":"venue"
},
  "geometry": {"coordinates":[-0.473524,52.135704],"type":"Point"}
}