{
  "type": "Feature",
  "properties": {
    "addr:full":"54 Dales Brow, Sharples Bolton Lancashire BL1 7RU",
    "addr:housenumber":"54",
    "addr:postcode":"bl1 7ru",
    "addr:street":"Dales Brow",
    "iso:country":"GB",
    "sg:address":"54 Dales Brow, Sharples",
    "sg:city":"Bolton",
    "sg:classifiers":[
        {
            "category":"Building & Trades",
            "subcategory":"Construction",
            "type":"Services"
        }
    ],
    "sg:postcode":"BL1 7RU",
    "sg:province":"Lancashire",
    "sg:tags":[
        "glazier",
        "decorator",
        "painter"
    ],
    "wof:name":"Taylor,Stanley,",
    "wof:placetype":"venue"
},
  "geometry": {"coordinates":[-2.4267539978,53.6125297546],"type":"Point"}
}