{
  "type": "Feature",
  "properties": {
    "addr:full":"1 Alpine Court, Knighton Fields Sheffield South Yorkshire S35 2XH",
    "addr:housenumber":"1",
    "addr:postcode":"s35 2xh",
    "addr:street":"Alpine Court;Fields",
    "iso:country":"GB",
    "sg:address":"1 Alpine Court, Knighton Fields",
    "sg:city":"Sheffield",
    "sg:classifiers":[
        {
            "category":"Professional",
            "subcategory":"Advertising",
            "type":"Services"
        }
    ],
    "sg:phone":"+44 114 246 3777",
    "sg:postcode":"S35 2XH",
    "sg:province":"South Yorkshire",
    "sg:tags":[
        "agency"
    ],
    "wof:name":"Jag Design Consultancy",
    "wof:placetype":"venue"
},
  "geometry": {"coordinates":[-1.4652700424,53.4623908997],"type":"Point"}
}