{
  "type": "Feature",
  "properties": {
    "iso:country":"GB",
    "sg:address":"Walcot Road",
    "sg:city":"Diss",
    "sg:classifiers":[
        {
            "category":"Organizations",
            "subcategory":"Membership Organization",
            "type":"Services"
        }
    ],
    "sg:phone":"+44 1379 643088",
    "sg:postcode":"IP22 4DH",
    "sg:province":"Norfolk",
    "sg:tags":[
        "club"
    ],
    "wof:name":"Diss Squash Club",
    "wof:placetype":"venue"
},
  "geometry": {"coordinates":[1.114135,52.38121],"type":"Point"}
}