{
  "type": "Feature",
  "properties": {
    "addr:full":"55a High St Harrow Greater London HA3 5DQ",
    "addr:housenumber":"55a",
    "addr:postcode":"ha3 5dq",
    "addr:street":"High St",
    "iso:country":"GB",
    "sg:address":"55a High St",
    "sg:city":"Harrow",
    "sg:classifiers":[
        {
            "category":"Shopping",
            "subcategory":"Shoes",
            "type":"Retail Goods"
        }
    ],
    "sg:postcode":"HA3 5DQ",
    "sg:province":"Greater London",
    "sg:tags":[
        "shop"
    ],
    "wof:name":"Blackman,Raymond,",
    "wof:placetype":"venue"
},
  "geometry": {"coordinates":[-0.335425,51.595356],"type":"Point"}
}