{
  "type": "Feature",
  "properties": {
    "addr:full":"Stanford Hill Farm, Tatchbury La Southampton Hampshire SO4 2HA",
    "addr:postcode":"so4 2ha",
    "addr:street":"Stanford;La",
    "iso:country":"GB",
    "sg:address":"Stanford Hill Farm, Tatchbury La",
    "sg:city":"Southampton",
    "sg:classifiers":[
        {
            "category":"Farming",
            "subcategory":"Livestock Farm",
            "type":"Manufacturing & Wholesale Goods"
        }
    ],
    "sg:phone":"+44 23 8081 2284",
    "sg:postcode":"SO4 2HA",
    "sg:province":"Hampshire",
    "sg:tags":[
        "others"
    ],
    "wof:name":"A Hunt",
    "wof:placetype":"venue"
},
  "geometry": {"coordinates":[-1.4158960581,50.9132461548],"type":"Point"}
}