{
  "type": "Feature",
  "properties": {
    "addr:full":"23 Alma Road London Greater London SW18 1AA",
    "addr:housenumber":"23",
    "addr:postcode":"sw18 1aa",
    "addr:street":"Alma Road",
    "iso:country":"GB",
    "sg:address":"23 Alma Road",
    "sg:city":"London",
    "sg:classifiers":[
        {
            "category":"Wholesale",
            "subcategory":"Vending Machines",
            "type":"Manufacturing & Wholesale Goods"
        }
    ],
    "sg:phone":"+44 800 028 1079",
    "sg:postcode":"SW18 1AA",
    "sg:province":"Greater London",
    "sg:tags":[
        "sale"
    ],
    "wof:name":"Reynolds London Vending Co. Ltd.",
    "wof:placetype":"venue"
},
  "geometry": {"coordinates":[-0.185491994,51.4584922791],"type":"Point"}
}