{
  "type": "Feature",
  "properties": {
    "addr:full":"395 Hucknall Rd Nottingham Nottinghamshire NG5 1FU",
    "addr:housenumber":"395",
    "addr:postcode":"ng5 1fu",
    "addr:street":"Hucknall Rd",
    "iso:country":"GB",
    "sg:address":"395 Hucknall Rd",
    "sg:city":"Nottingham",
    "sg:classifiers":[
        {
            "category":"Deli",
            "type":"Food & Drink"
        }
    ],
    "sg:postcode":"NG5 1FU",
    "sg:province":"Nottinghamshire",
    "sg:tags":[
        "delicatessen"
    ],
    "wof:name":"Power,Shaun,Quality Fresh Foods",
    "wof:placetype":"venue"
},
  "geometry": {"coordinates":[-1.158376,52.983437],"type":"Point"}
}