{
  "type": "Feature",
  "properties": {
    "iso:country":"GB",
    "sg:address":"32 Ridgeway, Wargrave",
    "sg:city":"Reading",
    "sg:classifiers":[
        {
            "category":"Organizations",
            "subcategory":"Community Association",
            "type":"Services"
        }
    ],
    "sg:postcode":"RG10 8AS",
    "sg:province":"Berkshire",
    "sg:tags":[
        "relation",
        "public"
    ],
    "wof:name":"Wendy Ball Communications",
    "wof:placetype":"venue"
},
  "geometry": {"coordinates":[-0.872824,51.519794],"type":"Point"}
}