{
  "type": "Feature",
  "properties": {
    "iso:country":"GB",
    "sg:address":"Po Box 400",
    "sg:city":"Newmarket",
    "sg:classifiers":[
        {
            "category":"Professional",
            "subcategory":"Computer Services",
            "type":"Services"
        }
    ],
    "sg:phone":"+44 1638 578000",
    "sg:postcode":"CB8 7HZ",
    "sg:province":"Cambridgeshire",
    "sg:tags":[
        "consultant"
    ],
    "wof:name":"All Systems Group",
    "wof:placetype":"venue"
},
  "geometry": {"coordinates":[0.3921000063,52.2686004639],"type":"Point"}
}