{
  "type": "Feature",
  "properties": {
    "iso:country":"GB",
    "sg:address":"High St",
    "sg:city":"Huntingdon",
    "sg:classifiers":[
        {
            "category":"Place Of Worship",
            "type":"Public Place"
        }
    ],
    "sg:phone":"+44 1480 860279",
    "sg:postcode":"PE18 0HB",
    "sg:province":"Cambridgeshire",
    "wof:name":"St Andrews Church",
    "wof:placetype":"venue"
},
  "geometry": {"coordinates":[-0.456166,52.310528],"type":"Point"}
}