{
  "type": "Feature",
  "properties": {
    "addr:full":"349 Lansdowne Rd Cardiff Cardiff CF5 1JS",
    "addr:housenumber":"349",
    "addr:postcode":"cf5 1js",
    "addr:street":"Lansdowne Rd",
    "iso:country":"GB",
    "sg:address":"349 Lansdowne Rd",
    "sg:city":"Cardiff",
    "sg:classifiers":[
        {
            "category":"Building & Trades",
            "subcategory":"Construction",
            "type":"Services"
        }
    ],
    "sg:postcode":"CF5 1JS",
    "sg:province":"Cardiff",
    "sg:tags":[
        "builder"
    ],
    "wof:name":"Elliot,J,",
    "wof:placetype":"venue"
},
  "geometry": {"coordinates":[-3.220709,51.482941],"type":"Point"}
}