{
  "type": "Feature",
  "properties": {
    "addr:full":"3rd Floor Room 56 London Fruit Exchange, Brushfield St Whitechapel Greater London E1 6EP",
    "addr:housenumber":"3rd floor room 56",
    "addr:postcode":"e1 6ep",
    "addr:street":"Brushfield St",
    "iso:country":"GB",
    "sg:address":"3rd Floor Room 56 London Fruit Exchange, Brushfield St",
    "sg:city":"Whitechapel",
    "sg:classifiers":[
        {
            "category":"Travel",
            "subcategory":"Hotels & Motels",
            "type":"Entertainment"
        }
    ],
    "sg:phone":"+44 20 7375 2121",
    "sg:postcode":"E1 6EP",
    "sg:province":"Greater London",
    "wof:name":"Sol Melia Hotels",
    "wof:placetype":"venue"
},
  "geometry": {"coordinates":[-0.0753780007,51.5190696716],"type":"Point"}
}