{
  "type": "Feature",
  "properties": {
    "iso:country":"GB",
    "sg:address":"C/o Mid Suffolk District Depot, Creeting Road",
    "sg:city":"Stowmarket",
    "sg:classifiers":[
        {
            "category":"Utilities",
            "subcategory":"Refuse",
            "type":"Services"
        }
    ],
    "sg:phone":"+44 1449 678014",
    "sg:postcode":"IP14 5AT",
    "sg:province":"Suffolk",
    "sg:tags":[
        "collection"
    ],
    "wof:name":"Onyx U K Ltd.",
    "wof:placetype":"venue"
},
  "geometry": {"coordinates":[0.996769,52.188625],"type":"Point"}
}