{
  "type": "Feature",
  "properties": {
    "iso:country":"GB",
    "sg:address":"Chestnut Avenue",
    "sg:city":"Chatham",
    "sg:classifiers":[
        {
            "category":"Organizations",
            "subcategory":"Community Association",
            "type":"Services"
        },
        {
            "category":"Organizations",
            "subcategory":"Membership Organization",
            "type":"Services"
        }
    ],
    "sg:phone":"+44 1634 864627",
    "sg:postcode":"ME5 9AH",
    "sg:province":"Kent",
    "sg:tags":[
        "club",
        "social"
    ],
    "wof:name":"WALDERSLADE WORKING MEN'S CLUB",
    "wof:placetype":"venue"
},
  "geometry": {"coordinates":[0.52149,51.343601],"type":"Point"}
}