{
  "type": "Feature",
  "properties": {
    "iso:country":"GB",
    "sg:address":"71 Rochester Road, Cuxton",
    "sg:city":"Rochester",
    "sg:classifiers":[
        {
            "category":"Autos & Motor Vehicles",
            "subcategory":"Automobile Sales",
            "type":"Retail Goods"
        }
    ],
    "sg:postcode":"ME2 2BU",
    "sg:province":"Kent",
    "sg:tags":[
        "car"
    ],
    "wof:name":"Medway Motor Co",
    "wof:placetype":"venue"
},
  "geometry": {"coordinates":[0.4688639939,51.3812599182],"type":"Point"}
}