{
  "type": "Feature",
  "properties": {
    "iso:country":"GB",
    "sg:address":"Richmond Road",
    "sg:city":"Twickenham",
    "sg:classifiers":[
        {
            "category":"Education",
            "subcategory":"School",
            "type":"Public Place"
        }
    ],
    "sg:phone":"+44 20 8891 0187",
    "sg:postcode":"TW1 3BB",
    "sg:province":"Greater London",
    "sg:tags":[
        "local",
        "authority"
    ],
    "wof:name":"Orleans Park Secondary School",
    "wof:placetype":"venue"
},
  "geometry": {"coordinates":[-0.319926,51.450996],"type":"Point"}
}