{
  "type": "Feature",
  "properties": {
    "addr:full":"Parham Ho, Parham Pk Pulborough West Sussex RH20 4HS",
    "addr:postcode":"rh20 4hs",
    "addr:street":"Pk Pulborough",
    "iso:country":"GB",
    "sg:address":"Parham Ho, Parham Pk",
    "sg:city":"Pulborough",
    "sg:classifiers":[
        {
            "category":"Landmark",
            "subcategory":"Tourist Attraction",
            "type":"Public Place"
        }
    ],
    "sg:phone":"+44 1903 742021",
    "sg:postcode":"RH20 4HS",
    "sg:province":"West Sussex",
    "sg:tags":[
        "interest"
    ],
    "wof:name":"Parham Park Ltd",
    "wof:placetype":"venue"
},
  "geometry": {"coordinates":[-0.5118790269,50.9570770264],"type":"Point"}
}