{
  "type": "Feature",
  "properties": {
    "addr:full":"8 Uttoxeter Rd, Alton Stoke On Trent Staffordshire ST10 4AT",
    "addr:housenumber":"8",
    "addr:postcode":"st10 4at",
    "addr:street":"Uttoxeter Rd;On Trent",
    "iso:country":"GB",
    "sg:address":"8 Uttoxeter Rd, Alton",
    "sg:city":"Stoke On Trent",
    "sg:classifiers":[
        {
            "category":"Building & Trades",
            "subcategory":"Construction",
            "type":"Services"
        }
    ],
    "sg:phone":"+44 1538 702781",
    "sg:postcode":"ST10 4AT",
    "sg:province":"Staffordshire",
    "sg:tags":[
        "flooring"
    ],
    "wof:name":"Creative Coatings",
    "wof:placetype":"venue"
},
  "geometry": {"coordinates":[-1.891341,52.973717],"type":"Point"}
}