{
  "type": "Feature",
  "properties": {
    "iso:country":"GB",
    "sg:address":"51 Cronton Lane",
    "sg:city":"Widnes",
    "sg:classifiers":[
        {
            "category":"Building & Trades",
            "subcategory":"Cleaning & Sanitation",
            "type":"Services"
        }
    ],
    "sg:phone":"+44 151 420 0200",
    "sg:postcode":"WA8 9AR",
    "sg:province":"Cheshire",
    "sg:tags":[
        "commercial"
    ],
    "wof:name":"Maintenance Cleaning Services",
    "wof:placetype":"venue"
},
  "geometry": {"coordinates":[-2.741328001,53.390007019],"type":"Point"}
}