{
  "type": "Feature",
  "properties": {
    "iso:country":"GB",
    "sg:address":"University College Farm",
    "sg:city":"Llanfairfechan",
    "sg:classifiers":[
        {
            "category":"Education",
            "subcategory":"University",
            "type":"Public Place"
        }
    ],
    "sg:phone":"+44 1248 680570",
    "sg:postcode":"LL33 0LB",
    "sg:province":"Conwy",
    "sg:tags":[
        "medical",
        "school"
    ],
    "wof:name":"University College of North Wales",
    "wof:placetype":"venue"
},
  "geometry": {"coordinates":[-3.978774,53.253571],"type":"Point"}
}