{
  "type": "Feature",
  "properties": {
    "iso:country":"GB",
    "sg:address":"11 Hill Crest",
    "sg:city":"Berwick-upon-tweed",
    "sg:classifiers":[
        {
            "category":"Building & Trades",
            "subcategory":"Construction",
            "type":"Services"
        }
    ],
    "sg:phone":"+44 1289 306520",
    "sg:postcode":"TD15 2LX",
    "sg:province":"Northumberland",
    "sg:tags":[
        "builder"
    ],
    "wof:name":"Thomas Turner & Sons",
    "wof:placetype":"venue"
},
  "geometry": {"coordinates":[-2.0345270634,55.757270813],"type":"Point"}
}