{
  "type": "Feature",
  "properties": {
    "addr:full":"61 Severn Road Weston-super-mare Somerset BS23 1DR",
    "addr:housenumber":"61",
    "addr:postcode":"bs23 1dr",
    "addr:street":"Severn Road",
    "iso:country":"GB",
    "sg:address":"61 Severn Road",
    "sg:city":"Weston-super-mare",
    "sg:classifiers":[
        {
            "category":"Restaurant",
            "type":"Food & Drink"
        }
    ],
    "sg:phone":"+44 1934 629720",
    "sg:postcode":"BS23 1DR",
    "sg:province":"Somerset",
    "sg:tags":[
        "chinese"
    ],
    "wof:name":"Lotus Chinese Restaurant",
    "wof:placetype":"venue"
},
  "geometry": {"coordinates":[-2.975816,51.33847],"type":"Point"}
}