{
  "type": "Feature",
  "properties": {
    "addr:full":"183 Mackenzie Road Beckenham Kent BR3 4SE",
    "addr:housenumber":"183",
    "addr:postcode":"br3 4se",
    "addr:street":"Mackenzie Road",
    "iso:country":"GB",
    "sg:address":"183 Mackenzie Road",
    "sg:city":"Beckenham",
    "sg:classifiers":[
        {
            "category":"Conference Center",
            "type":"Public Place"
        }
    ],
    "sg:phone":"+44 20 8659 3827",
    "sg:postcode":"BR3 4SE",
    "sg:province":"Kent",
    "wof:name":"Meeting Objectives Ltd.",
    "wof:placetype":"venue"
},
  "geometry": {"coordinates":[-0.051987,51.405979],"type":"Point"}
}