{
  "type": "Feature",
  "properties": {
    "iso:country":"GB",
    "sg:address":"Hope Street",
    "sg:city":"Rotherham",
    "sg:classifiers":[
        {
            "category":"Food & Beverages",
            "subcategory":"Meat & Fish",
            "type":"Retail Goods"
        }
    ],
    "sg:phone":"+44 1709 365142",
    "sg:postcode":"S60 1LH",
    "sg:province":"South Yorkshire",
    "sg:tags":[
        "merchant"
    ],
    "wof:name":"A W & Son Tate",
    "wof:placetype":"venue"
},
  "geometry": {"coordinates":[-1.364734,53.435211],"type":"Point"}
}