{
  "type": "Feature",
  "properties": {
    "addr:full":"Cedar Square Blackpool Lancashire FY1 1BP",
    "addr:postcode":"fy1 1bp",
    "addr:street":"Cedar Square",
    "iso:country":"GB",
    "sg:address":"Cedar Square",
    "sg:city":"Blackpool",
    "sg:classifiers":[
        {
            "category":"Place Of Worship",
            "type":"Public Place"
        }
    ],
    "sg:phone":"+44 1253 294451",
    "sg:postcode":"FY1 1BP",
    "sg:province":"Lancashire",
    "wof:name":"St John's C Of E Church",
    "wof:placetype":"venue"
},
  "geometry": {"coordinates":[-3.0505189896,53.8185462952],"type":"Point"}
}