{
  "type": "Feature",
  "properties": {
    "addr:full":"189 Cambridge Heath Road London Greater London E2 0EL",
    "addr:housenumber":"189",
    "addr:postcode":"e2 0el",
    "addr:street":"Cambridge Heath Road",
    "iso:country":"GB",
    "sg:address":"189 Cambridge Heath Road",
    "sg:city":"London",
    "sg:classifiers":[
        {
            "category":"Retail",
            "subcategory":"Auto Repair",
            "type":"Services"
        }
    ],
    "sg:phone":"+44 20 7729 9066",
    "sg:postcode":"E2 0EL",
    "sg:province":"Greater London",
    "sg:tags":[
        "electrical",
        "centre"
    ],
    "wof:name":"Ricky's Cab Electrics",
    "wof:placetype":"venue"
},
  "geometry": {"coordinates":[-0.055132,51.523487],"type":"Point"}
}