{
  "type": "Feature",
  "properties": {
    "iso:country":"GB",
    "sg:address":"1 Dalfibble Cotts, Parkgate",
    "sg:city":"Dumfries",
    "sg:classifiers":[
        {
            "category":"Professional",
            "subcategory":"Accounting & Tax Preparation",
            "type":"Services"
        }
    ],
    "sg:postcode":"DG1 3NF",
    "sg:province":"Dumfries and Galloway",
    "sg:tags":[
        "accountant"
    ],
    "wof:name":"M Gilboy & Associates",
    "wof:placetype":"venue"
},
  "geometry": {"coordinates":[-3.544029,55.172501],"type":"Point"}
}