{
  "type": "Feature",
  "properties": {
    "iso:country":"GB",
    "sg:address":"60-62 Bury St",
    "sg:city":"Heywood",
    "sg:classifiers":[
        {
            "category":"Retail",
            "subcategory":"Repair Shop",
            "type":"Services"
        }
    ],
    "sg:phone":"+44 1706 369237",
    "sg:postcode":"OL10 4QF",
    "sg:province":"Lancashire",
    "sg:tags":[
        "radio",
        "television",
        "video"
    ],
    "wof:name":"Wilcox & Wild",
    "wof:placetype":"venue"
},
  "geometry": {"coordinates":[-2.232761,53.593307],"type":"Point"}
}