{
  "type": "Feature",
  "properties": {
    "iso:country":"GB",
    "sg:address":"Flat A, Old Fishery House, Old Fishery Lane",
    "sg:city":"Hemel Hempstead",
    "sg:classifiers":[
        {
            "category":"Shopping",
            "subcategory":"Pharmacy",
            "type":"Retail Goods"
        }
    ],
    "sg:phone":"+44 1442 259737",
    "sg:postcode":"HP1 2BN",
    "sg:province":"Hertfordshire",
    "sg:tags":[
        "medicine",
        "therapy"
    ],
    "wof:name":"Anita Ohras",
    "wof:placetype":"venue"
},
  "geometry": {"coordinates":[-0.495846,51.745445],"type":"Point"}
}