{
  "type": "Feature",
  "properties": {
    "addr:full":"9 Bridge Street Tadcaster North Yorkshire LS24 9AW",
    "addr:housenumber":"9",
    "addr:postcode":"ls24 9aw",
    "addr:street":"Bridge Street",
    "iso:country":"GB",
    "sg:address":"9 Bridge Street",
    "sg:city":"Tadcaster",
    "sg:classifiers":[
        {
            "category":"Professional",
            "subcategory":"Employment Agencies",
            "type":"Services"
        }
    ],
    "sg:phone":"+44 1977 681255",
    "sg:postcode":"LS24 9AW",
    "sg:province":"North Yorkshire",
    "sg:tags":[
        "consultant"
    ],
    "wof:name":"Tailored Recruitment Ltd.",
    "wof:placetype":"venue"
},
  "geometry": {"coordinates":[-1.260254,53.884594],"type":"Point"}
}