{
  "type": "Feature",
  "properties": {
    "iso:country":"GB",
    "sg:address":"138 London Rd, Headington",
    "sg:city":"Oxford",
    "sg:classifiers":[
        {
            "category":"Home & Garden",
            "subcategory":"Furniture",
            "type":"Retail Goods"
        }
    ],
    "sg:phone":"+44 1865 751000",
    "sg:postcode":"OX33 1JH",
    "sg:province":"Buckinghamshire",
    "wof:name":"The Cotswold Collection",
    "wof:placetype":"venue"
},
  "geometry": {"coordinates":[-1.116635,51.742332],"type":"Point"}
}