{
  "type": "Feature",
  "properties": {
    "addr:full":"10 Queen Street Newton Abbot Devon TQ12 1EU",
    "addr:housenumber":"10",
    "addr:postcode":"tq12 1eu",
    "addr:street":"Queen Street",
    "iso:country":"GB",
    "sg:address":"10 Queen Street",
    "sg:city":"Newton Abbot",
    "sg:classifiers":[
        {
            "category":"Home & Garden",
            "subcategory":"Home Furnishings",
            "type":"Retail Goods"
        }
    ],
    "sg:phone":"+44 1626 365428",
    "sg:postcode":"TQ12 1EU",
    "sg:province":"Devon",
    "sg:tags":[
        "wall",
        "wallpaper",
        "covering"
    ],
    "wof:name":"Fanfare Interiors Ltd.",
    "wof:placetype":"venue"
},
  "geometry": {"coordinates":[-3.609208,50.530521],"type":"Point"}
}