{
  "type": "Feature",
  "properties": {
    "iso:country":"GB",
    "sg:address":"Cottesloe Farm, Wing",
    "sg:city":"Leighton Buzzard",
    "sg:classifiers":[
        {
            "category":"Farming",
            "subcategory":"Livestock Farm",
            "type":"Manufacturing & Wholesale Goods"
        },
        {
            "category":"Farming",
            "subcategory":"Farm",
            "type":"Manufacturing & Wholesale Goods"
        }
    ],
    "sg:phone":"+44 1296 688563",
    "sg:postcode":"LU7 0LB",
    "sg:province":"Bedfordshire",
    "sg:tags":[
        "mixed",
        "others"
    ],
    "wof:name":"P & D L Warren",
    "wof:placetype":"venue"
},
  "geometry": {"coordinates":[-0.714999,51.897835],"type":"Point"}
}