{
  "type": "Feature",
  "properties": {
    "addr:full":"43 Palace Avenue Paignton Devon TQ3 3EN",
    "addr:housenumber":"43",
    "addr:postcode":"tq3 3en",
    "addr:street":"Palace Avenue",
    "iso:country":"GB",
    "sg:address":"43 Palace Avenue",
    "sg:city":"Paignton",
    "sg:classifiers":[
        {
            "category":"Manufacturing",
            "subcategory":"Tools & Machinery",
            "type":"Manufacturing & Wholesale Goods"
        }
    ],
    "sg:phone":"+44 1803 666656",
    "sg:postcode":"TQ3 3EN",
    "sg:province":"Devon",
    "sg:tags":[
        "society",
        "friendly"
    ],
    "wof:name":"Cutler & Co",
    "wof:placetype":"venue"
},
  "geometry": {"coordinates":[-3.570423,50.435513],"type":"Point"}
}