{
  "type": "Feature",
  "properties": {
    "addr:full":"Pine Trees Leisure Park, Tyndrum Crianlarich Argyll and Bute FK20 8RY",
    "addr:postcode":"fk20 8ry",
    "addr:street":"Pine;Leisure Park Tyndrum",
    "iso:country":"GB",
    "sg:address":"Pine Trees Leisure Park, Tyndrum",
    "sg:city":"Crianlarich",
    "sg:classifiers":[
        {
            "category":"Recreation",
            "subcategory":"Campground",
            "type":"Entertainment"
        }
    ],
    "sg:postcode":"FK20 8RY",
    "sg:province":"Argyll and Bute",
    "sg:tags":[
        "site",
        "camping"
    ],
    "wof:name":"Pine Trees Leisure Park (Tyndrum) Ltd.",
    "wof:placetype":"venue"
},
  "geometry": {"coordinates":[-4.6189618111,56.3928947449],"type":"Point"}
}