{
  "type": "Feature",
  "properties": {
    "iso:country":"GB",
    "sg:address":"7a Rothersthorpe Avenue, Rothersthorpe Ind Est",
    "sg:city":"Northampton",
    "sg:classifiers":[
        {
            "category":"Retail",
            "subcategory":"Auto Repair",
            "type":"Services"
        }
    ],
    "sg:phone":"+44 1604 705900",
    "sg:postcode":"NN4 8JH",
    "sg:province":"Northamptonshire",
    "sg:tags":[
        "modification",
        "garage"
    ],
    "wof:name":"Broadmead Mobile Car Repair",
    "wof:placetype":"venue"
},
  "geometry": {"coordinates":[-0.9067100286,52.2248153687],"type":"Point"}
}