{
  "type": "Feature",
  "properties": {
    "addr:full":"Unit C1 Clarence Business Centre, Clarence Road Bollington Macclesfield Cheshire SK10 5JZ",
    "addr:postcode":"sk10 5jz",
    "addr:street":"Clarence Road",
    "iso:country":"GB",
    "sg:address":"Unit C1 Clarence Business Centre, Clarence Road Bollington",
    "sg:city":"Macclesfield",
    "sg:classifiers":[
        {
            "category":"Professional",
            "subcategory":"Testing Lab",
            "type":"Services"
        }
    ],
    "sg:phone":"+44 1625 573583",
    "sg:postcode":"SK10 5JZ",
    "sg:province":"Cheshire",
    "sg:tags":[
        "inspection",
        "calibration"
    ],
    "wof:name":"Matrix Test Ltd",
    "wof:placetype":"venue"
},
  "geometry": {"coordinates":[-2.1103689671,53.2933883667],"type":"Point"}
}