{
  "type": "Feature",
  "properties": {
    "addr:full":"Mary St Taunton Somerset TA1 3PE",
    "addr:postcode":"ta1 3pe",
    "addr:street":"Mary St",
    "iso:country":"GB",
    "sg:address":"Mary St",
    "sg:city":"Taunton",
    "sg:classifiers":[
        {
            "category":"Organizations",
            "subcategory":"Membership Organization",
            "type":"Services"
        }
    ],
    "sg:phone":"+44 1823 333488",
    "sg:postcode":"TA1 3PE",
    "sg:province":"Somerset",
    "sg:tags":[
        "club"
    ],
    "wof:name":"Ivory Club The",
    "wof:placetype":"venue"
},
  "geometry": {"coordinates":[-3.1017420292,51.0124816895],"type":"Point"}
}