{
  "type": "Feature",
  "properties": {
    "addr:full":"28 Old Forge Road, Fenny Drayton Nuneaton Leicestershire CV13 6BD",
    "addr:housenumber":"28",
    "addr:postcode":"cv13 6bd",
    "addr:street":"Old Forge Road",
    "iso:country":"GB",
    "sg:address":"28 Old Forge Road, Fenny Drayton",
    "sg:city":"Nuneaton",
    "sg:classifiers":[
        {
            "category":"Wholesale",
            "subcategory":"Computers",
            "type":"Manufacturing & Wholesale Goods"
        },
        {
            "category":"Professional",
            "subcategory":"Computer Services",
            "type":"Services"
        }
    ],
    "sg:phone":"+44 1827 715214",
    "sg:postcode":"CV13 6BD",
    "sg:province":"Leicestershire",
    "sg:tags":[
        "supplier",
        "consultant",
        "consumables"
    ],
    "wof:name":"Drayton Data Ltd",
    "wof:placetype":"venue"
},
  "geometry": {"coordinates":[-1.484449029,52.5687484741],"type":"Point"}
}