{
  "type": "Feature",
  "properties": {
    "addr:full":"Royal Bank Buildings, Glaisnock St Cumnock East Ayrshire KA18 1BT",
    "addr:postcode":"ka18 1bt",
    "addr:street":"St;East",
    "iso:country":"GB",
    "sg:address":"Royal Bank Buildings, Glaisnock St",
    "sg:city":"Cumnock",
    "sg:classifiers":[
        {
            "category":"Professional",
            "subcategory":"Lawyer & Legal Services",
            "type":"Services"
        }
    ],
    "sg:phone":"+44 1290 421484",
    "sg:postcode":"KA18 1BT",
    "sg:province":"East Ayrshire",
    "sg:tags":[
        "solicitor"
    ],
    "wof:name":"D W Shaw Solicitors",
    "wof:placetype":"venue"
},
  "geometry": {"coordinates":[-4.2665290833,55.4551200867],"type":"Point"}
}