{
  "type": "Feature",
  "properties": {
    "addr:full":"New Lane Garage, New Lane, Upton Pontefract West Yorkshire WF9 1HJ",
    "addr:postcode":"wf9 1hj",
    "addr:street":"New;New Lane;Pontefract West",
    "iso:country":"GB",
    "sg:address":"New Lane Garage, New Lane, Upton",
    "sg:city":"Pontefract",
    "sg:classifiers":[
        {
            "category":"Retail",
            "subcategory":"Auto Repair",
            "type":"Services"
        }
    ],
    "sg:phone":"+44 1977 642275",
    "sg:postcode":"WF9 1HJ",
    "sg:province":"West Yorkshire",
    "sg:tags":[
        "body",
        "car"
    ],
    "wof:name":"Upton Panel Beating",
    "wof:placetype":"venue"
},
  "geometry": {"coordinates":[-1.286404,53.613316],"type":"Point"}
}