{
  "type": "Feature",
  "properties": {
    "addr:full":"St Marys House Dumfries Dumfries and Galloway DG1 1LU",
    "addr:postcode":"dg1 1lu",
    "iso:country":"GB",
    "sg:address":"St Marys House",
    "sg:city":"Dumfries",
    "sg:classifiers":[
        {
            "category":"Professional",
            "subcategory":"Engineering",
            "type":"Services"
        }
    ],
    "sg:postcode":"DG1 1LU",
    "sg:province":"Dumfries and Galloway",
    "sg:tags":[
        "consulting",
        "engineer"
    ],
    "wof:name":"L G Mouchel & Partners",
    "wof:placetype":"venue"
},
  "geometry": {"coordinates":[-3.600536,55.100868],"type":"Point"}
}