{
  "type": "Feature",
  "properties": {
    "iso:country":"GB",
    "sg:address":"Conisholme Home Farm, Main Road, Conisholme",
    "sg:city":"Louth",
    "sg:classifiers":[
        {
            "category":"Home & Garden",
            "subcategory":"Garden Supply",
            "type":"Retail Goods"
        },
        {
            "category":"Farming",
            "subcategory":"Farm",
            "type":"Manufacturing & Wholesale Goods"
        }
    ],
    "sg:phone":"+44 1507 358349",
    "sg:postcode":"LN11 7LS",
    "sg:province":"Lincolnshire",
    "sg:tags":[
        "mixed",
        "bulb",
        "crop",
        "grower"
    ],
    "wof:name":"G A Dickinson & Sons",
    "wof:placetype":"venue"
},
  "geometry": {"coordinates":[0.1054859981,53.4398193359],"type":"Point"}
}