{
  "type": "Feature",
  "properties": {
    "iso:country":"GB",
    "sg:address":"31 Curran Avenue",
    "sg:city":"Sidcup",
    "sg:classifiers":[
        {
            "category":"Autos & Motor Vehicles",
            "subcategory":"Fuel & Gas Station",
            "type":"Retail Goods"
        }
    ],
    "sg:postcode":"DA15 8RP",
    "sg:province":"Kent",
    "sg:tags":[
        "petrol",
        "filling"
    ],
    "wof:name":"Garage Support (Southern) Ltd",
    "wof:placetype":"venue"
},
  "geometry": {"coordinates":[0.0981710032,51.4524726868],"type":"Point"}
}