{
  "type": "Feature",
  "properties": {
    "addr:full":"Wesley House, Jesus Lane Cambridge Cambridgeshire CB5 8BJ",
    "addr:postcode":"cambridgeshire cb5 8bj",
    "addr:street":"Jesus Lane",
    "iso:country":"GB",
    "sg:address":"Wesley House, Jesus Lane",
    "sg:city":"Cambridge",
    "sg:classifiers":[
        {
            "category":"Organizations",
            "subcategory":"Religious Organization",
            "type":"Services"
        }
    ],
    "sg:phone":"+44 1223 741047",
    "sg:postcode":"CB5 8BJ",
    "sg:province":"Cambridgeshire",
    "sg:tags":[
        "organisation"
    ],
    "wof:name":"Cambridge Theological Federation",
    "wof:placetype":"venue"
},
  "geometry": {"coordinates":[0.122924,52.2084541321],"type":"Point"}
}