{
  "type": "Feature",
  "properties": {
    "addr:full":"1 High Street, Halling Rochester Kent ME2 1BW",
    "addr:housenumber":"1",
    "addr:postcode":"me2 1bw",
    "addr:street":"High Street",
    "iso:country":"GB",
    "sg:address":"1 High Street, Halling",
    "sg:city":"Rochester",
    "sg:classifiers":[
        {
            "category":"Autos & Motor Vehicles",
            "subcategory":"Fuel & Gas Station",
            "type":"Retail Goods"
        }
    ],
    "sg:phone":"+44 1634 243162",
    "sg:postcode":"ME2 1BW",
    "sg:province":"Kent",
    "sg:tags":[
        "petrol",
        "filling"
    ],
    "wof:name":"M G M Autos Halling Service Station",
    "wof:placetype":"venue"
},
  "geometry": {"coordinates":[0.4917800128,51.3959999084],"type":"Point"}
}