{
  "type": "Feature",
  "properties": {
    "addr:full":"Shiel Dyke, Felton Morpeth Northumberland NE65 9LS",
    "addr:postcode":"ne65 9ls",
    "addr:street":"Shiel Dyke",
    "iso:country":"GB",
    "sg:address":"Shiel Dyke, Felton",
    "sg:city":"Morpeth",
    "sg:classifiers":[
        {
            "category":"Farming",
            "subcategory":"Livestock Farm",
            "type":"Manufacturing & Wholesale Goods"
        }
    ],
    "sg:phone":"+44 1665 575533",
    "sg:postcode":"NE65 9LS",
    "sg:province":"Northumberland",
    "sg:tags":[
        "others"
    ],
    "wof:name":"N B  Robinson & Son Ltd.",
    "wof:placetype":"venue"
},
  "geometry": {"coordinates":[-1.7118480206,55.3008918762],"type":"Point"}
}