{
  "type": "Feature",
  "properties": {
    "addr:full":"Unit 1 Marlands Shopping Centre, Civic Centre Road Southampton Hampshire SO14 7SJ",
    "addr:housenumber":"unit 1",
    "addr:postcode":"so14 7sj",
    "addr:street":"Marlands Shopping;Civic Centre Road",
    "iso:country":"GB",
    "sg:address":"Unit 1 Marlands Shopping Centre, Civic Centre Road",
    "sg:city":"Southampton",
    "sg:classifiers":[
        {
            "category":"Shopping",
            "subcategory":"Shoes",
            "type":"Retail Goods"
        }
    ],
    "sg:phone":"+44 23 8023 3301",
    "sg:postcode":"SO14 7SJ",
    "sg:province":"Hampshire",
    "sg:tags":[
        "shop"
    ],
    "wof:name":"Raw Shoe Corporation",
    "wof:placetype":"venue"
},
  "geometry": {"coordinates":[-1.4058899879,50.9058418274],"type":"Point"}
}