{
  "type": "Feature",
  "properties": {
    "iso:country":"GB",
    "sg:address":"4 Cyprus Road",
    "sg:city":"Exmouth",
    "sg:classifiers":[
        {
            "category":"Social Services",
            "subcategory":"Retirement Home",
            "type":"Services"
        }
    ],
    "sg:phone":"+44 1395 263363",
    "sg:postcode":"EX8 2DZ",
    "sg:province":"Devon",
    "sg:tags":[
        "residential",
        "care"
    ],
    "wof:name":"Redcliff House Residential Home",
    "wof:placetype":"venue"
},
  "geometry": {"coordinates":[-3.402492,50.617992],"type":"Point"}
}