{
  "type": "Feature",
  "properties": {
    "addr:full":"London Rd Salisbury Wiltshire SP1 3YU",
    "addr:postcode":"sp1 3yu",
    "addr:street":"London Rd",
    "iso:country":"GB",
    "sg:address":"London Rd",
    "sg:city":"Salisbury",
    "sg:classifiers":[
        {
            "category":"Autos & Motor Vehicles",
            "subcategory":"Fuel & Gas Station",
            "type":"Retail Goods"
        }
    ],
    "sg:phone":"+44 1722 322897",
    "sg:postcode":"SP1 3YU",
    "sg:province":"Wiltshire",
    "sg:tags":[
        "petrol",
        "filling"
    ],
    "wof:name":"Riverbourne Filling Station",
    "wof:placetype":"venue"
},
  "geometry": {"coordinates":[-1.7848080397,51.0761642456],"type":"Point"}
}