{
  "type": "Feature",
  "properties": {
    "addr:full":"89 Sitwell St, Spondon Derby Derbyshire DE21 7FH",
    "addr:housenumber":"89",
    "addr:postcode":"de21 7fh",
    "addr:street":"Sitwell St",
    "iso:country":"GB",
    "sg:address":"89 Sitwell St, Spondon",
    "sg:city":"Derby",
    "sg:classifiers":[
        {
            "category":"Shopping",
            "type":"Retail Goods"
        }
    ],
    "sg:postcode":"DE21 7FH",
    "sg:province":"Derbyshire",
    "sg:tags":[
        "part",
        "accessory"
    ],
    "wof:name":"Blundell Automotive Ltd",
    "wof:placetype":"venue"
},
  "geometry": {"coordinates":[-1.403853,52.920547],"type":"Point"}
}