{
  "type": "Feature",
  "properties": {
    "addr:full":"65b King Street Belper Derbyshire DE56 1QA",
    "addr:housenumber":"65b",
    "addr:postcode":"de56 1qa",
    "addr:street":"King Street",
    "iso:country":"GB",
    "sg:address":"65b King Street",
    "sg:city":"Belper",
    "sg:classifiers":[
        {
            "category":"Shopping",
            "subcategory":"Mobile Phones",
            "type":"Retail Goods"
        }
    ],
    "sg:phone":"+44 1773 825555",
    "sg:postcode":"DE56 1QA",
    "sg:province":"Derbyshire",
    "wof:name":"D J Communications",
    "wof:placetype":"venue"
},
  "geometry": {"coordinates":[-1.479742,53.023491],"type":"Point"}
}