{
  "type": "Feature",
  "properties": {
    "addr:full":"3 St.marys Grove, Nailsea Bristol Somerset BS48 4NQ",
    "addr:housenumber":"3",
    "addr:postcode":"bs48 4nq",
    "addr:street":"St.Marys Grove",
    "iso:country":"GB",
    "sg:address":"3 St.marys Grove, Nailsea",
    "sg:city":"Bristol",
    "sg:classifiers":[
        {
            "category":"Building & Trades",
            "subcategory":"Construction",
            "type":"Services"
        }
    ],
    "sg:phone":"+44 1275 851270",
    "sg:postcode":"BS48 4NQ",
    "sg:province":"Somerset",
    "sg:tags":[
        "joiner",
        "carpenter"
    ],
    "wof:name":"Foulkes Carpentry",
    "wof:placetype":"venue"
},
  "geometry": {"coordinates":[-2.769551,51.425179],"type":"Point"}
}