{
  "type": "Feature",
  "properties": {
    "addr:full":"Symes Corner, Houchin Street, Bishops Waltham Southampton Hampshire SO32 1AN",
    "addr:postcode":"so32 1an",
    "addr:street":"Houchin Street",
    "iso:country":"GB",
    "sg:address":"Symes Corner, Houchin Street, Bishops Waltham",
    "sg:city":"Southampton",
    "sg:classifiers":[
        {
            "category":"Food & Beverages",
            "subcategory":"Liquor & Beverages",
            "type":"Retail Goods"
        }
    ],
    "sg:phone":"+44 1489 892969",
    "sg:postcode":"SO32 1AN",
    "sg:province":"Hampshire",
    "sg:tags":[
        "beer",
        "spirit",
        "wines"
    ],
    "wof:name":"Just-in-Case (Wine Merchants) Ltd.",
    "wof:placetype":"venue"
},
  "geometry": {"coordinates":[-1.2120419741,50.9547996521],"type":"Point"}
}