{
  "type": "Feature",
  "properties": {
    "addr:full":"Wharf Cottage, Gas Works La Elland West Yorkshire HX5 9HJ",
    "addr:postcode":"hx5 9hj",
    "addr:street":"La Elland West",
    "iso:country":"GB",
    "sg:address":"Wharf Cottage, Gas Works La",
    "sg:city":"Elland",
    "sg:classifiers":[
        {
            "category":"Home & Garden",
            "subcategory":"Household Appliances",
            "type":"Retail Goods"
        }
    ],
    "sg:phone":"+44 1422 371952",
    "sg:postcode":"HX5 9HJ",
    "sg:province":"West Yorkshire",
    "sg:tags":[
        "domestic",
        "oven",
        "microwave"
    ],
    "wof:name":"P Dix",
    "wof:placetype":"venue"
},
  "geometry": {"coordinates":[-1.835879,53.686256],"type":"Point"}
}