{
  "type": "Feature",
  "properties": {
    "iso:country":"GB",
    "sg:address":"Team Valley Retail World",
    "sg:city":"Gateshead",
    "sg:classifiers":[
        {
            "category":"Shopping",
            "type":"Retail Goods"
        }
    ],
    "sg:phone":"+44 191 482 6688",
    "sg:postcode":"NE11 0BD",
    "sg:province":"Tyne and Wear",
    "sg:tags":[
        "part",
        "accessory"
    ],
    "wof:name":"Halfords Superstore",
    "wof:placetype":"venue"
},
  "geometry": {"coordinates":[-1.620189,54.923721],"type":"Point"}
}