{
  "type": "Feature",
  "properties": {
    "iso:country":"GB",
    "sg:address":"1 Black Bull Lane, Fulwood",
    "sg:city":"Preston",
    "sg:classifiers":[
        {
            "category":"Food & Beverages",
            "subcategory":"Groceries & Convenience Stores",
            "type":"Retail Goods"
        }
    ],
    "sg:phone":"+44 1772 717665",
    "sg:postcode":"PR2 3PT",
    "sg:province":"Lancashire",
    "wof:name":"Spar 8 Till Late",
    "wof:placetype":"venue"
},
  "geometry": {"coordinates":[-2.716159,53.777512],"type":"Point"}
}