{
  "type": "Feature",
  "properties": {
    "addr:full":"Almena, Cross Lees Todmorden Lancashire OL14 5NZ",
    "addr:postcode":"ol14 5nz",
    "iso:country":"GB",
    "sg:address":"Almena, Cross Lees",
    "sg:city":"Todmorden",
    "sg:classifiers":[
        {
            "category":"Retail",
            "subcategory":"Auto Repair",
            "type":"Services"
        }
    ],
    "sg:phone":"+44 1706 813851",
    "sg:postcode":"OL14 5NZ",
    "sg:province":"Lancashire",
    "sg:tags":[
        "modification",
        "garage"
    ],
    "wof:name":"A Highley",
    "wof:placetype":"venue"
},
  "geometry": {"coordinates":[-2.1087899208,53.7249755859],"type":"Point"}
}