{
  "type": "Feature",
  "properties": {
    "iso:country":"GB",
    "sg:address":"1 Burley Street",
    "sg:city":"Leeds",
    "sg:classifiers":[
        {
            "category":"Fast Food",
            "type":"Food & Drink"
        }
    ],
    "sg:phone":"+44 113 243 8119",
    "sg:postcode":"LS3 1LD",
    "sg:province":"West Yorkshire",
    "sg:tags":[
        "delivery"
    ],
    "wof:name":"Pizza La Fonte",
    "wof:placetype":"venue"
},
  "geometry": {"coordinates":[-1.559194,53.800163],"type":"Point"}
}