{
  "type": "Feature",
  "properties": {
    "iso:country":"GB",
    "sg:address":"2nd Floor, 50a Downing St",
    "sg:city":"Farnham",
    "sg:classifiers":[
        {
            "category":"Professional",
            "subcategory":"Accounting & Tax Preparation",
            "type":"Services"
        }
    ],
    "sg:phone":"+44 1252 722239",
    "sg:postcode":"GU9 7PH",
    "sg:province":"Surrey",
    "sg:tags":[
        "accountant"
    ],
    "wof:name":"Keith Graham",
    "wof:placetype":"venue"
},
  "geometry": {"coordinates":[-0.79971,51.214455],"type":"Point"}
}