{
  "type": "Feature",
  "properties": {
    "addr:full":"Front St Inveraray Argyll and Bute PA32 8UY",
    "addr:postcode":"pa32 8uy",
    "addr:street":"Front St",
    "iso:country":"GB",
    "sg:address":"Front St",
    "sg:city":"Inveraray",
    "sg:classifiers":[
        {
            "category":"Fast Food",
            "type":"Food & Drink"
        }
    ],
    "sg:phone":"+44 1499 302418",
    "sg:postcode":"PA32 8UY",
    "sg:province":"Argyll and Bute",
    "sg:tags":[
        "away",
        "take"
    ],
    "wof:name":"Pier Shop",
    "wof:placetype":"venue"
},
  "geometry": {"coordinates":[-5.072494,56.231445],"type":"Point"}
}