{
  "type": "Feature",
  "properties": {
    "addr:full":"1 Church Road, Tilston Malpas Cheshire SY14 7HB",
    "addr:housenumber":"1",
    "addr:postcode":"sy14 7hb",
    "addr:street":"Church Road",
    "iso:country":"GB",
    "sg:address":"1 Church Road, Tilston",
    "sg:city":"Malpas",
    "sg:classifiers":[
        {
            "category":"Government",
            "subcategory":"Post Office",
            "type":"Public Place"
        }
    ],
    "sg:phone":"+44 845 722 3344",
    "sg:postcode":"SY14 7HB",
    "sg:province":"Cheshire",
    "wof:name":"Tilston Post Office",
    "wof:placetype":"venue"
},
  "geometry": {"coordinates":[-2.808857,53.056297],"type":"Point"}
}