{
  "type": "Feature",
  "properties": {
    "iso:country":"GB",
    "sg:address":"North Campbell Avenue, Milngavie",
    "sg:city":"Glasgow",
    "sg:classifiers":[
        {
            "category":"Education",
            "subcategory":"School",
            "type":"Public Place"
        }
    ],
    "sg:phone":"+44 141 956 1600",
    "sg:postcode":"G62 7AA",
    "sg:province":"East Dunbartonshire",
    "sg:tags":[
        "local",
        "authority"
    ],
    "wof:name":"St Joseph's Primary School",
    "wof:placetype":"venue"
},
  "geometry": {"coordinates":[-4.323718,55.940598],"type":"Point"}
}