{
  "type": "Feature",
  "properties": {
    "addr:full":"18 Kerrs Way, Wroughton Swindon Wiltshire SN4 9EH",
    "addr:housenumber":"18",
    "addr:postcode":"sn4 9eh",
    "addr:street":"Kerrs Way",
    "iso:country":"GB",
    "sg:address":"18 Kerrs Way, Wroughton",
    "sg:city":"Swindon",
    "sg:classifiers":[
        {
            "category":"Home & Garden",
            "subcategory":"Household Appliances",
            "type":"Retail Goods"
        },
        {
            "category":"Retail",
            "subcategory":"Repair Shop",
            "type":"Services"
        }
    ],
    "sg:phone":"+44 1793 813081",
    "sg:postcode":"SN4 9EH",
    "sg:province":"Wiltshire",
    "sg:tags":[
        "machine",
        "electrical",
        "washing"
    ],
    "wof:name":"S & H Domestic Appliances",
    "wof:placetype":"venue"
},
  "geometry": {"coordinates":[-1.797016,51.526073],"type":"Point"}
}