{
  "type": "Feature",
  "properties": {
    "iso:country":"GB",
    "sg:address":"47-49 Newtown Road",
    "sg:city":"Hereford",
    "sg:classifiers":[
        {
            "category":"Bars & Pubs",
            "type":"Food & Drink"
        }
    ],
    "sg:phone":"+44 1432 360858",
    "sg:postcode":"HR4 9LJ",
    "sg:province":"Herefordshire",
    "sg:tags":[
        "pubs",
        "house",
        "inn",
        "public",
        "activity"
    ],
    "wof:name":"The Heart of Oak",
    "wof:placetype":"venue"
},
  "geometry": {"coordinates":[-2.717069,52.06451],"type":"Point"}
}