{
  "type": "Feature",
  "properties": {
    "addr:full":"Within Ffrith Filling Station, Victoria Rd West Prestatyn Denbighshire LL19 7AR",
    "addr:postcode":"ll19 7ar",
    "addr:street":"Victoria Rd West",
    "iso:country":"GB",
    "sg:address":"Within Ffrith Filling Station, Victoria Rd West",
    "sg:city":"Prestatyn",
    "sg:classifiers":[
        {
            "category":"Autos & Motor Vehicles",
            "subcategory":"Automobile Sales",
            "type":"Retail Goods"
        }
    ],
    "sg:phone":"+44 1745 889977",
    "sg:postcode":"LL19 7AR",
    "sg:province":"Denbighshire",
    "sg:tags":[
        "commercial"
    ],
    "wof:name":"Butler Motor Co",
    "wof:placetype":"venue"
},
  "geometry": {"coordinates":[-3.416739,53.336128],"type":"Point"}
}