{
  "type": "Feature",
  "properties": {
    "addr:full":"120 Lansdowne Road Worcester Worcestershire WR3 8JL",
    "addr:housenumber":"120",
    "addr:postcode":"wr3 8jl",
    "addr:street":"Lansdowne Road",
    "iso:country":"GB",
    "sg:address":"120 Lansdowne Road",
    "sg:city":"Worcester",
    "sg:classifiers":[
        {
            "category":"Building & Trades",
            "subcategory":"Cleaning & Sanitation",
            "type":"Services"
        }
    ],
    "sg:phone":"+44 1905 23921",
    "sg:postcode":"WR3 8JL",
    "sg:province":"Worcestershire",
    "sg:tags":[
        "commercial"
    ],
    "wof:name":"Dublcheck",
    "wof:placetype":"venue"
},
  "geometry": {"coordinates":[-2.212417,52.20163],"type":"Point"}
}