{
  "type": "Feature",
  "properties": {
    "addr:full":"Lauderdale Tower, Barbican London Greater London EC2Y 8BY",
    "addr:postcode":"ec2y 8by",
    "iso:country":"GB",
    "sg:address":"Lauderdale Tower, Barbican",
    "sg:city":"London",
    "sg:classifiers":[
        {
            "category":"Personal",
            "subcategory":"Beauty Salon",
            "type":"Services"
        }
    ],
    "sg:phone":"+44 20 7588 0051",
    "sg:postcode":"EC2Y 8BY",
    "sg:province":"Greater London",
    "sg:tags":[
        "unisex",
        "hairdresser"
    ],
    "wof:name":"Cissors Palace",
    "wof:placetype":"venue"
},
  "geometry": {"coordinates":[-0.096649,51.520031],"type":"Point"}
}