{
  "type": "Feature",
  "properties": {
    "iso:country":"GB",
    "sg:address":"472 Nottingham Road",
    "sg:city":"Derby",
    "sg:classifiers":[
        {
            "category":"Fast Food",
            "type":"Food & Drink"
        }
    ],
    "sg:phone":"+44 1332 544844",
    "sg:postcode":"DE21 6PF",
    "sg:province":"Derbyshire",
    "sg:tags":[
        "away",
        "meal",
        "outlet",
        "take"
    ],
    "wof:name":"3 Chefs Takeaway",
    "wof:placetype":"venue"
},
  "geometry": {"coordinates":[-1.439195,52.92429],"type":"Point"}
}