{
  "type": "Feature",
  "properties": {
    "iso:country":"GB",
    "sg:address":"Blackmoorfoot Road",
    "sg:city":"Huddersfield",
    "sg:classifiers":[
        {
            "category":"Home & Garden",
            "subcategory":"Carpets & Floor Coverings",
            "type":"Retail Goods"
        }
    ],
    "sg:phone":"+44 1484 538569",
    "sg:postcode":"HD4 5BQ",
    "sg:province":"West Yorkshire",
    "sg:tags":[
        "carpets",
        "retailer",
        "rug",
        "matting"
    ],
    "wof:name":"Carpet Remnant Centre",
    "wof:placetype":"venue"
},
  "geometry": {"coordinates":[-1.8151539564,53.6351509094],"type":"Point"}
}