{
  "type": "Feature",
  "properties": {
    "iso:country":"GB",
    "sg:address":"34 Thorold Street",
    "sg:city":"Boston",
    "sg:classifiers":[
        {
            "category":"Banks & Credit Unions",
            "subcategory":"Financial Services",
            "type":"Services"
        }
    ],
    "sg:postcode":"PE21 6PH",
    "sg:province":"Lincolnshire",
    "sg:tags":[
        "claim",
        "assessor"
    ],
    "wof:name":"Blackburn & Associates",
    "wof:placetype":"venue"
},
  "geometry": {"coordinates":[-0.024996,52.981812],"type":"Point"}
}