{
  "type": "Feature",
  "properties": {
    "addr:full":"46 Darby Rd Telford Shropshire TF8 7EP",
    "addr:housenumber":"46",
    "addr:postcode":"tf8 7ep",
    "addr:street":"Darby Rd",
    "iso:country":"GB",
    "sg:address":"46 Darby Rd",
    "sg:city":"Telford",
    "sg:classifiers":[
        {
            "category":"Shopping",
            "subcategory":"Pets & Pet Supplies",
            "type":"Retail Goods"
        }
    ],
    "sg:phone":"+44 1952 432711",
    "sg:postcode":"TF8 7EP",
    "sg:province":"Shropshire",
    "sg:tags":[
        "food"
    ],
    "wof:name":"Paws & Claws (Mobile)",
    "wof:placetype":"venue"
},
  "geometry": {"coordinates":[-2.498852,52.643524],"type":"Point"}
}