{
  "type": "Feature",
  "properties": {
    "iso:country":"GB",
    "sg:address":"5 The Pde, Waterloo",
    "sg:city":"Poole",
    "sg:classifiers":[
        {
            "category":"Personal",
            "subcategory":"Beauty Salon",
            "type":"Services"
        }
    ],
    "sg:postcode":"BH17 7EZ",
    "sg:province":"Dorset",
    "sg:tags":[
        "unisex",
        "hairdresser"
    ],
    "wof:name":"Waterloo Hairdressers",
    "wof:placetype":"venue"
},
  "geometry": {"coordinates":[-1.983222,50.750126],"type":"Point"}
}