{
  "type": "Feature",
  "properties": {
    "addr:full":"Chipping Garage, Talbot Street, Chipping Preston Lancashire PR3 2QE",
    "addr:postcode":"pr3 2qe",
    "addr:street":"Talbot Street",
    "iso:country":"GB",
    "sg:address":"Chipping Garage, Talbot Street, Chipping",
    "sg:city":"Preston",
    "sg:classifiers":[
        {
            "category":"Retail",
            "subcategory":"Auto Repair",
            "type":"Services"
        }
    ],
    "sg:phone":"+44 1995 61203",
    "sg:postcode":"PR3 2QE",
    "sg:province":"Lancashire",
    "sg:tags":[
        "modification",
        "garage"
    ],
    "wof:name":"Chipping Garage",
    "wof:placetype":"venue"
},
  "geometry": {"coordinates":[-2.576094,53.88443],"type":"Point"}
}