{
  "type": "Feature",
  "properties": {
    "addr:full":"10/11 Main Street Ferryhill Durham DL17 8LA",
    "addr:housenumber":"10 / 11",
    "addr:postcode":"dl17 8la",
    "addr:street":"Main Street",
    "iso:country":"GB",
    "sg:address":"10/11 Main Street",
    "sg:city":"Ferryhill",
    "sg:classifiers":[
        {
            "category":"Shopping",
            "subcategory":"Pharmacy",
            "type":"Retail Goods"
        }
    ],
    "sg:phone":"+44 1740 651200",
    "sg:postcode":"DL17 8LA",
    "sg:province":"Durham",
    "sg:tags":[
        "store",
        "drug"
    ],
    "wof:name":"C Higginbottom",
    "wof:placetype":"venue"
},
  "geometry": {"coordinates":[-1.5578110218,54.688911438],"type":"Point"}
}