{
  "type": "Feature",
  "properties": {
    "addr:full":"9 High East Street Dorchester Dorset DT1 1HS",
    "addr:housenumber":"9",
    "addr:postcode":"dt1 1hs",
    "addr:street":"High East Street",
    "iso:country":"GB",
    "sg:address":"9 High East Street",
    "sg:city":"Dorchester",
    "sg:classifiers":[
        {
            "category":"Shopping",
            "subcategory":"Antiques",
            "type":"Retail Goods"
        }
    ],
    "sg:phone":"+44 1305 261546",
    "sg:postcode":"DT1 1HS",
    "sg:province":"Dorset",
    "wof:name":"The Antiques Emporium",
    "wof:placetype":"venue"
},
  "geometry": {"coordinates":[-2.433857,50.715523],"type":"Point"}
}