{
  "type": "Feature",
  "properties": {
    "addr:full":"5 High Street South London Greater London E6 6EN",
    "addr:housenumber":"5",
    "addr:postcode":"e6 6en",
    "addr:street":"High Street South",
    "iso:country":"GB",
    "sg:address":"5 High Street South",
    "sg:city":"London",
    "sg:classifiers":[
        {
            "category":"Fast Food",
            "type":"Food & Drink"
        }
    ],
    "sg:phone":"+44 20 8471 3848",
    "sg:postcode":"E6 6EN",
    "sg:province":"Greater London",
    "sg:tags":[
        "away",
        "take"
    ],
    "wof:name":"Sing Hee Chinese Take Away",
    "wof:placetype":"venue"
},
  "geometry": {"coordinates":[0.0556199998,51.5316886902],"type":"Point"}
}