{
  "type": "Feature",
  "properties": {
    "iso:country":"GB",
    "sg:address":"13 Clarendon Place",
    "sg:city":"Hyde",
    "sg:classifiers":[
        {
            "category":"Shopping",
            "subcategory":"Clothing, Apparel, & Fashions",
            "type":"Retail Goods"
        }
    ],
    "sg:postcode":"SK14 2ND",
    "sg:province":"Cheshire",
    "sg:tags":[
        "menswear"
    ],
    "wof:name":"Daily Discounts Ltd",
    "wof:placetype":"venue"
},
  "geometry": {"coordinates":[-2.075261,53.451405],"type":"Point"}
}