{
  "type": "Feature",
  "properties": {
    "iso:country":"GB",
    "sg:address":"29 Arundel Drive West, Saltdean",
    "sg:city":"Brighton",
    "sg:classifiers":[
        {
            "category":"Health Services",
            "subcategory":"Podiatrist",
            "type":"Services"
        }
    ],
    "sg:phone":"+44 1273 305342",
    "sg:postcode":"BN2 8SJ",
    "sg:province":"East Sussex",
    "sg:tags":[
        "podiatrists",
        "chiropodist"
    ],
    "wof:name":"Ronald Hart",
    "wof:placetype":"venue"
},
  "geometry": {"coordinates":[-0.041266,50.804623],"type":"Point"}
}