{
  "type": "Feature",
  "properties": {
    "iso:country":"GB",
    "sg:address":"Unit 2, Pottery Close, Winterstoke Road",
    "sg:city":"Weston-super-mare",
    "sg:classifiers":[
        {
            "category":"Retail",
            "subcategory":"Auto Repair",
            "type":"Services"
        }
    ],
    "sg:phone":"+44 1934 627771",
    "sg:postcode":"BS23 3YH",
    "sg:province":"Somerset",
    "sg:tags":[
        "modification",
        "garage",
        "electrician"
    ],
    "wof:name":"Chris Field A I R T E Auto Electrician",
    "wof:placetype":"venue"
},
  "geometry": {"coordinates":[-2.962272,51.340294],"type":"Point"}
}