{
  "type": "Feature",
  "properties": {
    "iso:country":"GB",
    "sg:address":"Paddington House, Rosslyn Avenue, Preesall",
    "sg:city":"Poulton-le-fylde",
    "sg:classifiers":[
        {
            "category":"Building & Trades",
            "subcategory":"Construction",
            "type":"Services"
        }
    ],
    "sg:phone":"+44 1253 811359",
    "sg:postcode":"FY6 0HE",
    "sg:province":"Lancashire",
    "sg:tags":[
        "joiner",
        "carpenter"
    ],
    "wof:name":"Peter Taylor Joiner Contractor",
    "wof:placetype":"venue"
},
  "geometry": {"coordinates":[-2.9705491066,53.9311408997],"type":"Point"}
}