{
  "type": "Feature",
  "properties": {
    "addr:full":"7 Abbey Court Kelso Scottish Borders TD5 7JA",
    "addr:housenumber":"7",
    "addr:postcode":"td5 7ja",
    "addr:street":"Abbey Court",
    "iso:country":"GB",
    "sg:address":"7 Abbey Court",
    "sg:city":"Kelso",
    "sg:classifiers":[
        {
            "category":"Fast Food",
            "type":"Food & Drink"
        },
        {
            "category":"Cafe",
            "type":"Food & Drink"
        }
    ],
    "sg:postcode":"TD5 7JA",
    "sg:province":"Scottish Borders",
    "sg:tags":[
        "tea",
        "away",
        "room",
        "take"
    ],
    "wof:name":"The Cottage Garden Tea Room",
    "wof:placetype":"venue"
},
  "geometry": {"coordinates":[-2.4335539341,55.5965766907],"type":"Point"}
}