{
  "type": "Feature",
  "properties": {
    "addr:full":"19-21 Ball Haye Street Leek Staffordshire ST13 6JN",
    "addr:housenumber":"19-21",
    "addr:postcode":"st13 6jn",
    "addr:street":"Ball Haye Street",
    "iso:country":"GB",
    "sg:address":"19-21 Ball Haye Street",
    "sg:city":"Leek",
    "sg:classifiers":[
        {
            "category":"Farming",
            "subcategory":"Fish & Marine Products",
            "type":"Manufacturing & Wholesale Goods"
        }
    ],
    "sg:phone":"+44 1538 383094",
    "sg:postcode":"ST13 6JN",
    "sg:province":"Staffordshire",
    "sg:tags":[
        "fishmonger"
    ],
    "wof:name":"J W Ash & Sons",
    "wof:placetype":"venue"
},
  "geometry": {"coordinates":[-2.021112,53.106445],"type":"Point"}
}