{
  "type": "Feature",
  "properties": {
    "iso:country":"GB",
    "sg:address":"26 Cranford Terrace, Harborough Rd, Kingsthorpe",
    "sg:city":"Northampton",
    "sg:classifiers":[
        {
            "category":"Real Estate",
            "subcategory":"Architect",
            "type":"Services"
        }
    ],
    "sg:phone":"+44 1604 716700",
    "sg:postcode":"NN2 7AZ",
    "sg:province":"Northamptonshire",
    "wof:name":"BHC Partnership",
    "wof:placetype":"venue"
},
  "geometry": {"coordinates":[-0.898015,52.262875],"type":"Point"}
}