{
  "type": "Feature",
  "properties": {
    "addr:full":"Unit 6 Holt Road Cromer Norfolk NR27 9JW",
    "addr:housenumber":"unit 6",
    "addr:postcode":"nr27 9jw",
    "addr:street":"Holt Road",
    "iso:country":"GB",
    "sg:address":"Unit 6 Holt Road",
    "sg:city":"Cromer",
    "sg:classifiers":[
        {
            "category":"Retail",
            "subcategory":"Auto Repair",
            "type":"Services"
        }
    ],
    "sg:phone":"+44 1263 515297",
    "sg:postcode":"NR27 9JW",
    "sg:province":"Norfolk",
    "sg:tags":[
        "body",
        "car",
        "repairer"
    ],
    "wof:name":"Anglia Refinishing Services",
    "wof:placetype":"venue"
},
  "geometry": {"coordinates":[1.2928090096,52.9297904968],"type":"Point"}
}