{
  "type": "Feature",
  "properties": {
    "iso:country":"GB",
    "sg:address":"Harmire Enterprise Park",
    "sg:city":"Barnard Castle",
    "sg:classifiers":[
        {
            "category":"Education",
            "subcategory":"Special Training",
            "type":"Public Place"
        },
        {
            "category":"Government",
            "subcategory":"Office",
            "type":"Public Place"
        }
    ],
    "sg:phone":"+44 1833 631251",
    "sg:postcode":"DL12 8XT",
    "sg:province":"Cumbria",
    "sg:tags":[
        "product",
        "local",
        "centre"
    ],
    "sg:website":"http://www.britnett.co.uk",
    "wof:name":"Enterprise House",
    "wof:placetype":"venue"
},
  "geometry": {"coordinates":[-1.923809,54.543152],"type":"Point"}
}