{
  "type": "Feature",
  "properties": {
    "addr:full":"65 West Main Street, Whitburn Bathgate North Lanarkshire EH47 0QD",
    "addr:housenumber":"65",
    "addr:postcode":"eh47 0qd",
    "addr:street":"West Main Street;Bathgate",
    "iso:country":"GB",
    "sg:address":"65 West Main Street, Whitburn",
    "sg:city":"Bathgate",
    "sg:classifiers":[
        {
            "category":"Government",
            "subcategory":"Post Office",
            "type":"Public Place"
        },
        {
            "category":"Professional",
            "subcategory":"Computer Services",
            "type":"Services"
        }
    ],
    "sg:phone":"+44 1501 743509",
    "sg:postcode":"EH47 0QD",
    "sg:province":"North Lanarkshire",
    "sg:tags":[
        "pc",
        "consultant",
        "manufacturer"
    ],
    "wof:name":"Creative Computers",
    "wof:placetype":"venue"
},
  "geometry": {"coordinates":[-3.687828064,55.8661956787],"type":"Point"}
}