{
  "type": "Feature",
  "properties": {
    "addr:full":"100 Portland Road Hove East Sussex BN3 5DN",
    "addr:housenumber":"100",
    "addr:postcode":"bn3 5dn",
    "addr:street":"Portland Road",
    "iso:country":"GB",
    "sg:address":"100 Portland Road",
    "sg:city":"Hove",
    "sg:classifiers":[
        {
            "category":"Personal",
            "subcategory":"Beauty Salon",
            "type":"Services"
        }
    ],
    "sg:phone":"+44 1273 726675",
    "sg:postcode":"BN3 5DN",
    "sg:province":"East Sussex",
    "sg:tags":[
        "lady",
        "hairdresser"
    ],
    "wof:name":"Jay's Hair Studio",
    "wof:placetype":"venue"
},
  "geometry": {"coordinates":[-0.182383,50.832798],"type":"Point"}
}