{
  "type": "Feature",
  "properties": {
    "iso:country":"GB",
    "sg:address":"84 Brookfield Road, Churchdown",
    "sg:city":"Gloucester",
    "sg:classifiers":[
        {
            "category":"Wholesale",
            "subcategory":"Motor Vehicles",
            "type":"Manufacturing & Wholesale Goods"
        }
    ],
    "sg:postcode":"GL3 2PD",
    "sg:province":"Gloucestershire",
    "sg:tags":[
        "turbine"
    ],
    "wof:name":"A L P Hydraulics",
    "wof:placetype":"venue"
},
  "geometry": {"coordinates":[-2.1598138809,51.878944397],"type":"Point"}
}