{
  "type": "Feature",
  "properties": {
    "addr:full":"Whitefield Place Morecambe Lancashire LA3 3EA",
    "addr:postcode":"la3 3ea",
    "addr:street":"Whitefield Place",
    "iso:country":"GB",
    "sg:address":"Whitefield Place",
    "sg:city":"Morecambe",
    "sg:classifiers":[
        {
            "category":"Retail",
            "subcategory":"Auto Repair",
            "type":"Services"
        }
    ],
    "sg:postcode":"LA3 3EA",
    "sg:province":"Lancashire",
    "sg:tags":[
        "body",
        "car"
    ],
    "wof:name":"J M Harris",
    "wof:placetype":"venue"
},
  "geometry": {"coordinates":[-2.852349,54.059055],"type":"Point"}
}