{
  "type": "Feature",
  "properties": {
    "iso:country":"GB",
    "sg:address":"The Ferneries, Ferneries Lane",
    "sg:city":"Barnetby",
    "sg:classifiers":[
        {
            "category":"Shopping",
            "subcategory":"Florist",
            "type":"Retail Goods"
        }
    ],
    "sg:phone":"+44 1652 688206",
    "sg:postcode":"DN38 6HN",
    "sg:province":"Lincolnshire",
    "wof:name":"J B Smith",
    "wof:placetype":"venue"
},
  "geometry": {"coordinates":[-0.404299,53.574619],"type":"Point"}
}