{
  "type": "Feature",
  "properties": {
    "addr:full":"26 St Giles Terrace Dundee Dundee City DD3 9JQ",
    "addr:housenumber":"26",
    "addr:postcode":"dd3 9jq",
    "addr:street":"St Giles Terrace",
    "iso:country":"GB",
    "sg:address":"26 St Giles Terrace",
    "sg:city":"Dundee",
    "sg:classifiers":[
        {
            "category":"Government",
            "subcategory":"Post Office",
            "type":"Public Place"
        }
    ],
    "sg:phone":"+44 1382 825656",
    "sg:postcode":"DD3 9JQ",
    "sg:province":"Dundee City",
    "wof:name":"St.Mary's Post Office",
    "wof:placetype":"venue"
},
  "geometry": {"coordinates":[-3.009751,56.492901],"type":"Point"}
}