{
  "type": "Feature",
  "properties": {
    "addr:full":"100-106 Leonard St Moorgate Greater London EC2A 4RH",
    "addr:housenumber":"100-106",
    "addr:postcode":"ec2a 4rh",
    "addr:street":"Leonard St Moorgate",
    "iso:country":"GB",
    "sg:address":"100-106 Leonard St",
    "sg:city":"Moorgate",
    "sg:classifiers":[
        {
            "category":"Professional",
            "subcategory":"Management & Consulting",
            "type":"Services"
        }
    ],
    "sg:phone":"+44 20 7613 0189",
    "sg:postcode":"EC2A 4RH",
    "sg:province":"Greater London",
    "sg:tags":[
        "marketing",
        "consultant"
    ],
    "wof:name":"Direct Link",
    "wof:placetype":"venue"
},
  "geometry": {"coordinates":[-0.0815479979,51.5245437622],"type":"Point"}
}