{
  "type": "Feature",
  "properties": {
    "iso:country":"GB",
    "sg:address":"3 Pummery Square, Poundbury",
    "sg:city":"Dorchester",
    "sg:classifiers":[
        {
            "category":"Home & Garden",
            "subcategory":"Home Furnishings",
            "type":"Retail Goods"
        },
        {
            "category":"Home & Garden",
            "subcategory":"Furniture",
            "type":"Retail Goods"
        }
    ],
    "sg:phone":"+44 1305 250782",
    "sg:postcode":"DT1 3GW",
    "sg:province":"Dorset",
    "sg:tags":[
        "soft",
        "sale"
    ],
    "wof:name":"Stitchinghouse Design",
    "wof:placetype":"venue"
},
  "geometry": {"coordinates":[-2.457579,50.710758],"type":"Point"}
}