{
  "type": "Feature",
  "properties": {
    "addr:full":"22 The Hemmells Basildon Essex SS15 6ED",
    "addr:housenumber":"22",
    "addr:postcode":"ss15 6ed",
    "addr:street":"The Hemmells",
    "iso:country":"GB",
    "sg:address":"22 The Hemmells",
    "sg:city":"Basildon",
    "sg:classifiers":[
        {
            "category":"Retail",
            "subcategory":"Auto Repair",
            "type":"Services"
        }
    ],
    "sg:phone":"+44 1268 419466",
    "sg:postcode":"SS15 6ED",
    "sg:province":"Essex",
    "sg:tags":[
        "car",
        "specialist",
        "customizing"
    ],
    "wof:name":"Martroll Ltd",
    "wof:placetype":"venue"
},
  "geometry": {"coordinates":[0.4225730002,51.5824661255],"type":"Point"}
}