{
  "type": "Feature",
  "properties": {
    "addr:full":"65 Burr Road, Wandsworth London Greater London SW18 4PD",
    "addr:housenumber":"65",
    "addr:postcode":"sw18 4pd",
    "addr:street":"Burr Road",
    "iso:country":"GB",
    "sg:address":"65 Burr Road, Wandsworth",
    "sg:city":"London",
    "sg:classifiers":[
        {
            "category":"Manufacturing",
            "subcategory":"Electronics",
            "type":"Manufacturing & Wholesale Goods"
        }
    ],
    "sg:postcode":"SW18 4PD",
    "sg:province":"Greater London",
    "sg:tags":[
        "control",
        "component",
        "-",
        "electronic"
    ],
    "wof:name":"High Speed Production (Holdings) Ltd.",
    "wof:placetype":"venue"
},
  "geometry": {"coordinates":[-0.1957290024,51.4485397339],"type":"Point"}
}