{
  "type": "Feature",
  "properties": {
    "addr:full":"8 Windsor Road Droitwich Worcestershire WR9 7BZ",
    "addr:housenumber":"8",
    "addr:postcode":"wr9 7bz",
    "addr:street":"Windsor Road",
    "iso:country":"GB",
    "sg:address":"8 Windsor Road",
    "sg:city":"Droitwich",
    "sg:classifiers":[
        {
            "category":"Taxi",
            "type":"Transportation"
        }
    ],
    "sg:postcode":"WR9 7BZ",
    "sg:province":"Worcestershire",
    "sg:tags":[
        "toastmaster"
    ],
    "wof:name":"David L Tilt & Associates",
    "wof:placetype":"venue"
},
  "geometry": {"coordinates":[-2.1502170563,52.2558822632],"type":"Point"}
}