{
  "type": "Feature",
  "properties": {
    "addr:full":"The Racecourse Newbury Berkshire RG14 7NZ",
    "addr:postcode":"rg14 7nz",
    "addr:street":"Newbury",
    "iso:country":"GB",
    "sg:address":"The Racecourse",
    "sg:city":"Newbury",
    "sg:classifiers":[
        {
            "category":"Sports & Exercise",
            "subcategory":"Race Track",
            "type":"Entertainment"
        },
        {
            "category":"Sports & Exercise",
            "subcategory":"Golf",
            "type":"Entertainment"
        }
    ],
    "sg:phone":"+44 1635 40015",
    "sg:postcode":"RG14 7NZ",
    "sg:province":"Berkshire",
    "sg:tags":[
        "club",
        "course",
        "racecourse"
    ],
    "wof:name":"Newbury Racecourse Enterprises Ltd.",
    "wof:placetype":"venue"
},
  "geometry": {"coordinates":[-1.317702,51.394608],"type":"Point"}
}