{
  "type": "Feature",
  "properties": {
    "addr:full":"15 Grosvenor Rd Scarborough North Yorkshire YO11 2LZ",
    "addr:housenumber":"15",
    "addr:postcode":"yo11 2lz",
    "addr:street":"Grosvenor Rd",
    "iso:country":"GB",
    "sg:address":"15 Grosvenor Rd",
    "sg:city":"Scarborough",
    "sg:classifiers":[
        {
            "category":"Health Services",
            "subcategory":"Nursing And Care Facility",
            "type":"Services"
        }
    ],
    "sg:phone":"+44 1723 364538",
    "sg:postcode":"YO11 2LZ",
    "sg:province":"North Yorkshire",
    "sg:tags":[
        "home"
    ],
    "wof:name":"Sanctuary Housing Association",
    "wof:placetype":"venue"
},
  "geometry": {"coordinates":[-0.4034880102,54.2765846252],"type":"Point"}
}