{
  "type": "Feature",
  "properties": {
    "addr:full":"23 West Rd Westcliff On Sea Essex SS0 9AU",
    "addr:housenumber":"23",
    "addr:postcode":"ss0 9au",
    "addr:street":"West Rd",
    "iso:country":"GB",
    "sg:address":"23 West Rd",
    "sg:city":"Westcliff On Sea",
    "sg:classifiers":[
        {
            "category":"Autos & Motor Vehicles",
            "subcategory":"Automobile Sales",
            "type":"Retail Goods"
        }
    ],
    "sg:phone":"+44 1702 430766",
    "sg:postcode":"SS0 9AU",
    "sg:province":"Essex",
    "sg:tags":[
        "car"
    ],
    "wof:name":"West Road Motor Co",
    "wof:placetype":"venue"
},
  "geometry": {"coordinates":[0.6932970285,51.5440788269],"type":"Point"}
}