{
  "type": "Feature",
  "properties": {
    "iso:country":"GB",
    "sg:address":"Tannery Close, Off Power Station Road",
    "sg:city":"Rugeley",
    "sg:classifiers":[
        {
            "category":"Freight",
            "type":"Transportation"
        }
    ],
    "sg:postcode":"WS15 2HR",
    "sg:province":"Staffordshire",
    "sg:tags":[
        "haulage",
        "road"
    ],
    "wof:name":"Gerald Southwell",
    "wof:placetype":"venue"
},
  "geometry": {"coordinates":[-1.929571,52.762218],"type":"Point"}
}