{
  "type": "Feature",
  "properties": {
    "addr:full":"Rock Rd, Rock Wadebridge Cornwall PL27 6NW",
    "addr:postcode":"pl27 6nw",
    "addr:street":"Rock Rd",
    "iso:country":"GB",
    "sg:address":"Rock Rd, Rock",
    "sg:city":"Wadebridge",
    "sg:classifiers":[
        {
            "category":"Shopping",
            "subcategory":"Gifts & Souvenirs",
            "type":"Retail Goods"
        }
    ],
    "sg:postcode":"PL27 6NW",
    "sg:province":"Cornwall",
    "sg:tags":[
        "shop"
    ],
    "wof:name":"Cole,V,",
    "wof:placetype":"venue"
},
  "geometry": {"coordinates":[-4.9036898613,50.5495262146],"type":"Point"}
}