{
  "type": "Feature",
  "properties": {
    "addr:full":"183 Nottingham Road, Somercotes Alfreton Derbyshire DE55 4JG",
    "addr:housenumber":"183",
    "addr:postcode":"de55 4jg",
    "addr:street":"Nottingham Road",
    "iso:country":"GB",
    "sg:address":"183 Nottingham Road, Somercotes",
    "sg:city":"Alfreton",
    "sg:classifiers":[
        {
            "category":"Shopping",
            "subcategory":"Jewelry",
            "type":"Retail Goods"
        },
        {
            "category":"Shopping",
            "subcategory":"Comic Books",
            "type":"Retail Goods"
        }
    ],
    "sg:phone":"+44 1773 602956",
    "sg:postcode":"DE55 4JG",
    "sg:province":"Derbyshire",
    "sg:tags":[
        "jeweller",
        "sale",
        "jewellery"
    ],
    "wof:name":"Jenkinson Jewellers",
    "wof:placetype":"venue"
},
  "geometry": {"coordinates":[-1.3697869778,53.0810089111],"type":"Point"}
}