{
  "type": "Feature",
  "properties": {
    "addr:full":"23a Acorn Street Glasgow Glasgow City G40 4AN",
    "addr:housenumber":"23a",
    "addr:postcode":"g40 4an",
    "addr:street":"Acorn Street",
    "iso:country":"GB",
    "sg:address":"23a Acorn Street",
    "sg:city":"Glasgow",
    "sg:classifiers":[
        {
            "category":"Health Services",
            "subcategory":"Hospital",
            "type":"Services"
        }
    ],
    "sg:phone":"+44 141 556 4789",
    "sg:postcode":"G40 4AN",
    "sg:province":"Glasgow City",
    "wof:name":"Acorn Street Day Hospital",
    "wof:placetype":"venue"
},
  "geometry": {"coordinates":[-4.225281,55.847305],"type":"Point"}
}