{
  "type": "Feature",
  "properties": {
    "addr:full":"44 Moulsham Street Chelmsford Essex CM2 0HY",
    "addr:housenumber":"44",
    "addr:postcode":"cm2 0hy",
    "addr:street":"Moulsham Street",
    "iso:country":"GB",
    "sg:address":"44 Moulsham Street",
    "sg:city":"Chelmsford",
    "sg:classifiers":[
        {
            "category":"Restaurant",
            "type":"Food & Drink"
        }
    ],
    "sg:phone":"+44 1245 352245",
    "sg:postcode":"CM2 0HY",
    "sg:province":"Essex",
    "sg:tags":[
        "thai",
        "-"
    ],
    "wof:name":"Siam Cottage Thai Restaurant",
    "wof:placetype":"venue"
},
  "geometry": {"coordinates":[0.471942991,51.7294616699],"type":"Point"}
}