{
  "type": "Feature",
  "properties": {
    "addr:full":"81 Woodhall Road, Kidsgrove Stoke-on-trent Cheshire ST7 4QY",
    "addr:housenumber":"81",
    "addr:postcode":"st7 4qy",
    "addr:street":"Woodhall Road",
    "iso:country":"GB",
    "sg:address":"81 Woodhall Road, Kidsgrove",
    "sg:city":"Stoke-on-trent",
    "sg:classifiers":[
        {
            "category":"Communications",
            "type":"Services"
        }
    ],
    "sg:postcode":"ST7 4QY",
    "sg:province":"Cheshire",
    "sg:tags":[
        "data",
        "network"
    ],
    "wof:name":"Mightforge Data Ltd.",
    "wof:placetype":"venue"
},
  "geometry": {"coordinates":[-2.2170510292,53.0940361023],"type":"Point"}
}