{
  "type": "Feature",
  "properties": {
    "iso:country":"GB",
    "sg:address":"1 Davies Mews",
    "sg:city":"London",
    "sg:classifiers":[
        {
            "category":"Shopping",
            "subcategory":"Antiques",
            "type":"Retail Goods"
        }
    ],
    "sg:phone":"+44 20 7495 0635",
    "sg:postcode":"W1K 5AB",
    "sg:province":"Greater London",
    "wof:name":"Shiraz Antiques",
    "wof:placetype":"venue"
},
  "geometry": {"coordinates":[-0.1486250013,51.5128250122],"type":"Point"}
}