{
  "type": "Feature",
  "properties": {
    "addr:full":"15 Pitts Lane, Bishopstone Salisbury Dorset SP5 4DQ",
    "addr:housenumber":"15",
    "addr:postcode":"sp5 4dq",
    "addr:street":"Pitts Lane",
    "iso:country":"GB",
    "sg:address":"15 Pitts Lane, Bishopstone",
    "sg:city":"Salisbury",
    "sg:classifiers":[
        {
            "category":"Home & Garden",
            "subcategory":"Building Materials",
            "type":"Retail Goods"
        }
    ],
    "sg:phone":"+44 1722 780090",
    "sg:postcode":"SP5 4DQ",
    "sg:province":"Dorset",
    "sg:tags":[
        "ironwork",
        "wrought"
    ],
    "wof:name":"Metal Artwork",
    "wof:placetype":"venue"
},
  "geometry": {"coordinates":[-1.8964450359,51.0336494446],"type":"Point"}
}