{
  "type": "Feature",
  "properties": {
    "iso:country":"GB",
    "sg:address":"23a Church Street",
    "sg:city":"Seaham",
    "sg:classifiers":[
        {
            "category":"Personal",
            "subcategory":"Beauty Salon",
            "type":"Services"
        }
    ],
    "sg:phone":"+44 191 581 3078",
    "sg:postcode":"SR7 7HQ",
    "sg:province":"Durham",
    "sg:tags":[
        "unisex",
        "hairdresser"
    ],
    "wof:name":"Snip & Style",
    "wof:placetype":"venue"
},
  "geometry": {"coordinates":[-1.332535,54.836964],"type":"Point"}
}