{
  "type": "Feature",
  "properties": {
    "addr:full":"308 Seven Sisters Rd London Greater London N4 2DL",
    "addr:housenumber":"308",
    "addr:postcode":"n4 2dl",
    "addr:street":"Seven Sisters Rd",
    "iso:country":"GB",
    "sg:address":"308 Seven Sisters Rd",
    "sg:city":"London",
    "sg:classifiers":[
        {
            "category":"Shopping",
            "subcategory":"Clothing, Apparel, & Fashions",
            "type":"Retail Goods"
        }
    ],
    "sg:postcode":"N4 2DL",
    "sg:province":"Greater London",
    "sg:tags":[
        "shop"
    ],
    "wof:name":"Matata,Gracie,",
    "wof:placetype":"venue"
},
  "geometry": {"coordinates":[-0.103207998,51.5653877258],"type":"Point"}
}