{
  "type": "Feature",
  "properties": {
    "addr:full":"13 Morow Gardens Melrose Scottish Borders TD6 9LA",
    "addr:housenumber":"13",
    "addr:postcode":"td6 9la",
    "addr:street":"Morow Gardens",
    "iso:country":"GB",
    "sg:address":"13 Morow Gardens",
    "sg:city":"Melrose",
    "sg:classifiers":[
        {
            "category":"Food & Beverages",
            "subcategory":"Candy",
            "type":"Retail Goods"
        }
    ],
    "sg:phone":"+44 1896 823411",
    "sg:postcode":"TD6 9LA",
    "sg:province":"Scottish Borders",
    "sg:tags":[
        "confectioner"
    ],
    "wof:name":"Cathrine Fletcher",
    "wof:placetype":"venue"
},
  "geometry": {"coordinates":[-2.737578,55.598831],"type":"Point"}
}