{
  "type": "Feature",
  "properties": {
    "iso:country":"GB",
    "sg:address":"Campleshlan Rd",
    "sg:city":"York",
    "sg:classifiers":[
        {
            "category":"Place Of Worship",
            "type":"Public Place"
        }
    ],
    "sg:phone":"+44 1904 654707",
    "sg:postcode":"YO23 1EY",
    "sg:province":"North Yorkshire",
    "wof:name":"St Chad C Of E Church",
    "wof:placetype":"venue"
},
  "geometry": {"coordinates":[-1.083427,53.953339],"type":"Point"}
}