{
  "type": "Feature",
  "properties": {
    "addr:full":"Marsh House Farm, Marsh Lane Lancaster Lancashire LA2 0EJ",
    "addr:postcode":"la2 0ej",
    "addr:street":"Marsh Lane",
    "iso:country":"GB",
    "sg:address":"Marsh House Farm, Marsh Lane",
    "sg:city":"Lancaster",
    "sg:classifiers":[
        {
            "category":"Farming",
            "subcategory":"Dairy Farm",
            "type":"Manufacturing & Wholesale Goods"
        }
    ],
    "sg:postcode":"LA2 0EJ",
    "sg:province":"Lancashire",
    "wof:name":"W Simpson & Co.",
    "wof:placetype":"venue"
},
  "geometry": {"coordinates":[-2.83203,53.956303],"type":"Point"}
}