{
  "type": "Feature",
  "properties": {
    "iso:country":"GB",
    "sg:address":"Sandpits Ho, High St",
    "sg:city":"Southampton",
    "sg:classifiers":[
        {
            "category":"Recreation",
            "subcategory":"Dog Park",
            "type":"Entertainment"
        }
    ],
    "sg:phone":"+44 1489 781941",
    "sg:postcode":"SO32 2JN",
    "sg:province":"Hampshire",
    "wof:name":"Supreme Dog Grooming",
    "wof:placetype":"venue"
},
  "geometry": {"coordinates":[-1.18891,50.9235],"type":"Point"}
}