{
  "type": "Feature",
  "properties": {
    "addr:full":"65-67 College Road, Crosby Liverpool Merseyside L23 0RN",
    "addr:housenumber":"65-67",
    "addr:postcode":"l23 0rn",
    "addr:street":"College Road",
    "iso:country":"GB",
    "sg:address":"65-67 College Road, Crosby",
    "sg:city":"Liverpool",
    "sg:classifiers":[
        {
            "category":"Home & Garden",
            "subcategory":"Home Furnishings",
            "type":"Retail Goods"
        }
    ],
    "sg:postcode":"L23 0RN",
    "sg:province":"Merseyside",
    "sg:tags":[
        "furnishers",
        "planner",
        "kitchen"
    ],
    "wof:name":"Munro Kitchens",
    "wof:placetype":"venue"
},
  "geometry": {"coordinates":[-3.030342,53.48447],"type":"Point"}
}