{
  "type": "Feature",
  "properties": {
    "iso:country":"GB",
    "sg:address":"14 Fore Street, Kingsteignton",
    "sg:city":"Newton Abbot",
    "sg:classifiers":[
        {
            "category":"Retail",
            "subcategory":"Auto Repair",
            "type":"Services"
        }
    ],
    "sg:phone":"+44 1626 364192",
    "sg:postcode":"TQ12 3AS",
    "sg:province":"Devon",
    "sg:tags":[
        "body",
        "car"
    ],
    "wof:name":"Hills Motors",
    "wof:placetype":"venue"
},
  "geometry": {"coordinates":[-3.5944058895,50.5462112427],"type":"Point"}
}