{
  "type": "Feature",
  "properties": {
    "addr:full":"Leaside, Longland Salisbury Wiltshire SP2 7ET",
    "addr:postcode":"sp2 7et",
    "iso:country":"GB",
    "sg:address":"Leaside, Longland",
    "sg:city":"Salisbury",
    "sg:classifiers":[
        {
            "category":"Building & Trades",
            "subcategory":"Construction",
            "type":"Services"
        }
    ],
    "sg:postcode":"SP2 7ET",
    "sg:province":"Wiltshire",
    "sg:tags":[
        "builder"
    ],
    "wof:name":"William Dables",
    "wof:placetype":"venue"
},
  "geometry": {"coordinates":[-1.8002840281,51.0695381165],"type":"Point"}
}