{
  "type": "Feature",
  "properties": {
    "addr:full":"Preseli Crymych Pembrokeshire SA41 3QH",
    "addr:postcode":"sa41 3qh",
    "iso:country":"GB",
    "sg:address":"Preseli",
    "sg:city":"Crymych",
    "sg:classifiers":[
        {
            "category":"Education",
            "subcategory":"School",
            "type":"Public Place"
        },
        {
            "category":"Government",
            "subcategory":"Office",
            "type":"Public Place"
        }
    ],
    "sg:phone":"+44 1239 831406",
    "sg:postcode":"SA41 3QH",
    "sg:province":"Pembrokeshire",
    "sg:tags":[
        "local",
        "authority"
    ],
    "wof:name":"Ysgol Y Preseli Comprehensive School",
    "wof:placetype":"venue"
},
  "geometry": {"coordinates":[-4.648454,51.971241],"type":"Point"}
}