{
  "type": "Feature",
  "properties": {
    "addr:full":"Scotts Surfferance Wharf London Greater London SE1 2DF",
    "addr:postcode":"se1 2df",
    "iso:country":"GB",
    "sg:address":"Scotts Surfferance Wharf",
    "sg:city":"London",
    "sg:classifiers":[
        {
            "category":"Professional",
            "type":"Services"
        }
    ],
    "sg:postcode":"SE1 2DF",
    "sg:province":"Greater London",
    "sg:tags":[
        "marine"
    ],
    "wof:name":"Bmt Edon Liddiard Vince",
    "wof:placetype":"venue"
},
  "geometry": {"coordinates":[-0.07263,51.500389],"type":"Point"}
}