{
  "type": "Feature",
  "properties": {
    "addr:full":"Sutton Rd Mablethorpe Lincolnshire LN12 2PN",
    "addr:postcode":"ln12 2pn",
    "addr:street":"Sutton Rd",
    "iso:country":"GB",
    "sg:address":"Sutton Rd",
    "sg:city":"Mablethorpe",
    "sg:classifiers":[
        {
            "category":"Recreation",
            "subcategory":"Campground",
            "type":"Entertainment"
        }
    ],
    "sg:phone":"+44 1507 472421",
    "sg:postcode":"LN12 2PN",
    "sg:province":"Lincolnshire",
    "sg:tags":[
        "holiday",
        "camp",
        "park",
        "centre"
    ],
    "wof:name":"Seacroft Holiday Estate Ltd",
    "wof:placetype":"venue"
},
  "geometry": {"coordinates":[0.2722840011,53.3316841125],"type":"Point"}
}