{
  "type": "Feature",
  "properties": {
    "addr:full":"Unit 304, Via Gellia Mills, Via Gellia Rd, Bonsall Matlock Derbyshire DE4 2AJ",
    "addr:housenumber":"304",
    "addr:postcode":"de4 2aj",
    "addr:street":"Via Gellia Mills Via Gellia Rd",
    "iso:country":"GB",
    "sg:address":"Unit 304, Via Gellia Mills, Via Gellia Rd, Bonsall",
    "sg:city":"Matlock",
    "sg:classifiers":[
        {
            "category":"Building & Trades",
            "subcategory":"Landscaping Services",
            "type":"Services"
        }
    ],
    "sg:phone":"+44 1629 826977",
    "sg:postcode":"DE4 2AJ",
    "sg:province":"Derbyshire",
    "sg:tags":[
        "consultant"
    ],
    "wof:name":"A Clark",
    "wof:placetype":"venue"
},
  "geometry": {"coordinates":[-1.5838060379,53.1204071045],"type":"Point"}
}