{
  "type": "Feature",
  "properties": {
    "addr:full":"10 Clive Crescent Penarth The Vale of Glamorgan CF64 1AT",
    "addr:housenumber":"10",
    "addr:postcode":"cf64 1at",
    "addr:street":"Clive Crescent;Vale",
    "iso:country":"GB",
    "sg:address":"10 Clive Crescent",
    "sg:city":"Penarth",
    "sg:classifiers":[
        {
            "category":"Social Services",
            "subcategory":"Retirement Home",
            "type":"Services"
        }
    ],
    "sg:phone":"+44 29 2070 1271",
    "sg:postcode":"CF64 1AT",
    "sg:province":"The Vale of Glamorgan",
    "sg:tags":[
        "residential",
        "care"
    ],
    "wof:name":"Cliffhaven",
    "wof:placetype":"venue"
},
  "geometry": {"coordinates":[-3.1719388962,51.4397850037],"type":"Point"}
}