{
  "type": "Feature",
  "properties": {
    "iso:country":"GB",
    "sg:address":"Glebe Cottage Farm, Sutton-on-derwent",
    "sg:city":"York",
    "sg:classifiers":[
        {
            "category":"Building & Trades",
            "subcategory":"Landscaping Services",
            "type":"Services"
        }
    ],
    "sg:postcode":"YO41 4BY",
    "sg:province":"East Riding of Yorkshire",
    "sg:tags":[
        "horticultural",
        "consultant"
    ],
    "wof:name":"East Riding Horticulture Ltd.",
    "wof:placetype":"venue"
},
  "geometry": {"coordinates":[-0.923817,53.914783],"type":"Point"}
}