{
  "type": "Feature",
  "properties": {
    "iso:country":"GB",
    "sg:address":"21 King George Avenue, Morley",
    "sg:city":"Leeds",
    "sg:classifiers":[
        {
            "category":"Building & Trades",
            "subcategory":"Cleaning & Sanitation",
            "type":"Services"
        },
        {
            "category":"Building & Trades",
            "subcategory":"Construction",
            "type":"Services"
        }
    ],
    "sg:phone":"+44 113 252 1735",
    "sg:postcode":"LS27 8LW",
    "sg:province":"West Yorkshire",
    "sg:tags":[
        "resurfacing",
        "laying",
        "refinishing",
        "flooring",
        "floor"
    ],
    "wof:name":"A & B Flooring",
    "wof:placetype":"venue"
},
  "geometry": {"coordinates":[-1.595986,53.754154],"type":"Point"}
}