{
  "type": "Feature",
  "properties": {
    "addr:full":"Unit B6, The Dresser Centre Manchester Greater Manchester M11 2NE",
    "addr:postcode":"m11 2ne",
    "addr:street":"The",
    "iso:country":"GB",
    "sg:address":"Unit B6, The Dresser Centre",
    "sg:city":"Manchester",
    "sg:classifiers":[
        {
            "category":"Home & Garden",
            "subcategory":"Home Furnishings",
            "type":"Retail Goods"
        }
    ],
    "sg:postcode":"M11 2NE",
    "sg:province":"Greater Manchester",
    "sg:tags":[
        "mantelpiece",
        "fireplace"
    ],
    "wof:name":"Frank Malacrino Mantels",
    "wof:placetype":"venue"
},
  "geometry": {"coordinates":[-2.1857790947,53.4766693115],"type":"Point"}
}