{
  "type": "Feature",
  "properties": {
    "addr:full":"166 Westgate Wakefield West Yorkshire WF2 9SR",
    "addr:housenumber":"166",
    "addr:postcode":"wf2 9sr",
    "addr:street":"Westgate Wakefield West",
    "iso:country":"GB",
    "sg:address":"166 Westgate",
    "sg:city":"Wakefield",
    "sg:classifiers":[
        {
            "category":"Home & Garden",
            "subcategory":"Building Materials",
            "type":"Retail Goods"
        }
    ],
    "sg:postcode":"WF2 9SR",
    "sg:province":"West Yorkshire",
    "sg:tags":[
        "insulation",
        "installers"
    ],
    "wof:name":"City Plasterers",
    "wof:placetype":"venue"
},
  "geometry": {"coordinates":[-1.5071320534,53.6809005737],"type":"Point"}
}