{
  "type": "Feature",
  "properties": {
    "addr:full":"Woodfield, Trimpley Lane Bewdley Shropshire DY12 1RL",
    "addr:postcode":"dy12 1rl",
    "addr:street":"Trimpley Lane",
    "iso:country":"GB",
    "sg:address":"Woodfield, Trimpley Lane",
    "sg:city":"Bewdley",
    "sg:classifiers":[
        {
            "category":"Manufacturing",
            "subcategory":"Textiles",
            "type":"Manufacturing & Wholesale Goods"
        }
    ],
    "sg:phone":"+44 1384 877631",
    "sg:postcode":"DY12 1RL",
    "sg:province":"Shropshire",
    "sg:tags":[
        "mnfr",
        "rug",
        "carpet"
    ],
    "wof:name":"Kinver Clean",
    "wof:placetype":"venue"
},
  "geometry": {"coordinates":[-2.309033,52.406006],"type":"Point"}
}