{
  "type": "Feature",
  "properties": {
    "addr:full":"8 Rivulet Road Wrexham Wrexham LL13 8DT",
    "addr:housenumber":"8",
    "addr:postcode":"ll13 8dt",
    "addr:street":"Rivulet Road",
    "iso:country":"GB",
    "sg:address":"8 Rivulet Road",
    "sg:city":"Wrexham",
    "sg:classifiers":[
        {
            "category":"Shopping",
            "type":"Retail Goods"
        }
    ],
    "sg:phone":"+44 1978 313123",
    "sg:postcode":"LL13 8DT",
    "sg:province":"Wrexham",
    "sg:tags":[
        "part",
        "accessory"
    ],
    "wof:name":"Paul Nichols Motor Sports",
    "wof:placetype":"venue"
},
  "geometry": {"coordinates":[-2.9886300564,53.0427513123],"type":"Point"}
}