{
  "type": "Feature",
  "properties": {
    "addr:full":"11 & 12 Sutton Ct, Bath St Market Harborough Leicestershire LE16 9EQ",
    "addr:housenumber":"11 & 12",
    "addr:postcode":"le16 9eq",
    "addr:street":"Sutton Ct Bath St",
    "iso:country":"GB",
    "sg:address":"11 & 12 Sutton Ct, Bath St",
    "sg:city":"Market Harborough",
    "sg:classifiers":[
        {
            "category":"Professional",
            "type":"Services"
        }
    ],
    "sg:phone":"+44 1858 432501",
    "sg:postcode":"LE16 9EQ",
    "sg:province":"Leicestershire",
    "sg:tags":[
        "shopfitters"
    ],
    "wof:name":"L M Woodworking",
    "wof:placetype":"venue"
},
  "geometry": {"coordinates":[-0.9033830166,52.4941673279],"type":"Point"}
}