{
  "type": "Feature",
  "properties": {
    "iso:country":"GB",
    "sg:address":"1 Peterborough Rd,",
    "sg:city":"Harrow",
    "sg:classifiers":[
        {
            "category":"Professional",
            "subcategory":"Computer Services",
            "type":"Services"
        }
    ],
    "sg:postcode":"HA1 2AP",
    "sg:province":"Greater London",
    "sg:tags":[
        "system",
        "software"
    ],
    "wof:name":"Infotech International Ltd",
    "wof:placetype":"venue"
},
  "geometry": {"coordinates":[-0.333957,51.578072],"type":"Point"}
}