{
  "type": "Feature",
  "properties": {
    "addr:full":"35 Paignton Avenue Whitley Bay Northumberland NE25 8SY",
    "addr:housenumber":"35",
    "addr:postcode":"ne25 8sy",
    "addr:street":"Paignton Avenue",
    "iso:country":"GB",
    "sg:address":"35 Paignton Avenue",
    "sg:city":"Whitley Bay",
    "sg:classifiers":[
        {
            "category":"Building & Trades",
            "subcategory":"Construction",
            "type":"Services"
        }
    ],
    "sg:phone":"+44 191 253 3690",
    "sg:postcode":"NE25 8SY",
    "sg:province":"Northumberland",
    "sg:tags":[
        "joiner",
        "carpenter"
    ],
    "wof:name":"Ken Allan",
    "wof:placetype":"venue"
},
  "geometry": {"coordinates":[-1.4672299623,55.0387496948],"type":"Point"}
}