{
  "type": "Feature",
  "properties": {
    "iso:country":"GB",
    "sg:address":"93 Parsonage Lane",
    "sg:city":"Enfield",
    "sg:classifiers":[
        {
            "category":"Home & Garden",
            "subcategory":"Home Furnishings",
            "type":"Retail Goods"
        }
    ],
    "sg:phone":"+44 20 8363 9436",
    "sg:postcode":"EN2 0AB",
    "sg:province":"Greater London",
    "sg:tags":[
        "blind",
        "manufacture",
        "fitting",
        "curtain"
    ],
    "wof:name":"Enfield Fabrics",
    "wof:placetype":"venue"
},
  "geometry": {"coordinates":[-0.083255,51.657696],"type":"Point"}
}