{
  "type": "Feature",
  "properties": {
    "addr:full":"North Road Fort William Highland PH33 6TQ",
    "addr:postcode":"ph33 6tq",
    "addr:street":"North Road",
    "iso:country":"GB",
    "sg:address":"North Road",
    "sg:city":"Fort William",
    "sg:classifiers":[
        {
            "category":"Military Area",
            "subcategory":"Air Force Base",
            "type":"Public Place"
        }
    ],
    "sg:phone":"+44 1397 700000",
    "sg:postcode":"PH33 6TQ",
    "sg:province":"Highland",
    "sg:tags":[
        "taxi",
        "hire",
        "private"
    ],
    "wof:name":"Linnhe Taxis",
    "wof:placetype":"venue"
},
  "geometry": {"coordinates":[-5.108459,56.818432],"type":"Point"}
}