{
  "type": "Feature",
  "properties": {
    "addr:full":"48 Drewstead Rd Streatham Greater London SW16 1AG",
    "addr:housenumber":"48",
    "addr:postcode":"sw16 1ag",
    "addr:street":"Drewstead Rd",
    "iso:country":"GB",
    "sg:address":"48 Drewstead Rd",
    "sg:city":"Streatham",
    "sg:classifiers":[
        {
            "category":"Building & Trades",
            "subcategory":"Construction",
            "type":"Services"
        }
    ],
    "sg:phone":"+44 20 8769 4477",
    "sg:postcode":"SW16 1AG",
    "sg:province":"Greater London",
    "sg:tags":[
        "builder"
    ],
    "wof:name":"Garthmass Ltd",
    "wof:placetype":"venue"
},
  "geometry": {"coordinates":[-0.130089,51.430126],"type":"Point"}
}