{
  "type": "Feature",
  "properties": {
    "iso:country":"GB",
    "sg:address":"39 Greenloons Walk, Formby",
    "sg:city":"Liverpool",
    "sg:classifiers":[
        {
            "category":"Manufacturing",
            "subcategory":"Buildings",
            "type":"Manufacturing & Wholesale Goods"
        }
    ],
    "sg:postcode":"L37 2LE",
    "sg:province":"Lancashire",
    "sg:tags":[
        "system",
        "air conditioning"
    ],
    "wof:name":"Airtech Services",
    "wof:placetype":"venue"
},
  "geometry": {"coordinates":[-3.0816779137,53.5544166565],"type":"Point"}
}