{
  "type": "Feature",
  "properties": {
    "addr:full":"Park Garage, Macclesfield Street Stoke-on-trent Staffordshire ST6 1EH",
    "addr:postcode":"st6 1eh",
    "addr:street":"Macclesfield Street",
    "iso:country":"GB",
    "sg:address":"Park Garage, Macclesfield Street",
    "sg:city":"Stoke-on-trent",
    "sg:classifiers":[
        {
            "category":"Freight",
            "type":"Transportation"
        },
        {
            "category":"Building & Trades",
            "subcategory":"Construction",
            "type":"Services"
        },
        {
            "category":"Retail",
            "subcategory":"Storage",
            "type":"Services"
        }
    ],
    "sg:phone":"+44 1782 839452",
    "sg:postcode":"ST6 1EH",
    "sg:province":"Staffordshire",
    "sg:tags":[
        "haulage",
        "equipment",
        "household",
        "road",
        "removal"
    ],
    "wof:name":"Keith Faulkner Ltd.",
    "wof:placetype":"venue"
},
  "geometry": {"coordinates":[-2.1832039356,53.0496444702],"type":"Point"}
}