{
  "type": "Feature",
  "properties": {
    "addr:full":"2 Market Place Dunmow Essex CM6 1AT",
    "addr:housenumber":"2",
    "addr:postcode":"cm6 1at",
    "addr:street":"Market Place Dunmow",
    "iso:country":"GB",
    "sg:address":"2 Market Place",
    "sg:city":"Dunmow",
    "sg:classifiers":[
        {
            "category":"Home & Garden",
            "subcategory":"Hardware",
            "type":"Retail Goods"
        }
    ],
    "sg:postcode":"CM6 1AT",
    "sg:province":"Essex",
    "wof:name":"Smiths Hardware",
    "wof:placetype":"venue"
},
  "geometry": {"coordinates":[0.362347,51.872959],"type":"Point"}
}