{
  "type": "Feature",
  "properties": {
    "iso:country":"GB",
    "sg:address":"20 Lorn Dr",
    "sg:city":"Ballachulish",
    "sg:classifiers":[
        {
            "category":"Education",
            "subcategory":"Special Training",
            "type":"Public Place"
        }
    ],
    "sg:phone":"+44 1855 811443",
    "sg:postcode":"PA39 4HR",
    "sg:province":"Highland",
    "sg:tags":[
        "aid",
        "first"
    ],
    "wof:name":"B A S P",
    "wof:placetype":"venue"
},
  "geometry": {"coordinates":[-5.1362099648,56.6780700684],"type":"Point"}
}