{
  "type": "Feature",
  "properties": {
    "iso:country":"GB",
    "sg:address":"Oakwood House, Ringwood Road, Woodlands",
    "sg:city":"Southampton",
    "sg:classifiers":[
        {
            "category":"Professional",
            "subcategory":"Advertising",
            "type":"Services"
        }
    ],
    "sg:phone":"+44 23 8086 2723",
    "sg:postcode":"SO40 7GY",
    "sg:province":"Hampshire",
    "sg:tags":[
        "agency"
    ],
    "wof:name":"M W Publicity Ltd.",
    "wof:placetype":"venue"
},
  "geometry": {"coordinates":[-1.5508780479,50.9148368835],"type":"Point"}
}