{
  "type": "Feature",
  "properties": {
    "addr:full":"92 Eastwood Road, Brislington Bristol City of Bristol BS4 4RS",
    "addr:housenumber":"92",
    "addr:postcode":"bs4 4rs",
    "addr:street":"Eastwood Road",
    "iso:country":"GB",
    "sg:address":"92 Eastwood Road, Brislington",
    "sg:city":"Bristol",
    "sg:classifiers":[
        {
            "category":"Health Services",
            "subcategory":"Nursing And Care Facility",
            "type":"Services"
        }
    ],
    "sg:phone":"+44 117 977 9802",
    "sg:postcode":"BS4 4RS",
    "sg:province":"City of Bristol",
    "sg:tags":[
        "home"
    ],
    "wof:name":"Broomhill Home",
    "wof:placetype":"venue"
},
  "geometry": {"coordinates":[-2.536141,51.442173],"type":"Point"}
}