{
  "type": "Feature",
  "properties": {
    "iso:country":"GB",
    "sg:address":"Sheridan House, 23/25 London Street",
    "sg:city":"Andover",
    "sg:classifiers":[
        {
            "category":"Professional",
            "subcategory":"Management & Consulting",
            "type":"Services"
        }
    ],
    "sg:postcode":"SP10 2NU",
    "sg:province":"Hampshire",
    "sg:tags":[
        "project"
    ],
    "wof:name":"P M Directions Ltd",
    "wof:placetype":"venue"
},
  "geometry": {"coordinates":[-1.4777050018,51.2063598633],"type":"Point"}
}