{
  "type": "Feature",
  "properties": {
    "addr:full":"P O Box 1 Biggleswade Bedfordshire SG18 9HN",
    "addr:housenumber":"1",
    "addr:postcode":"sg18 9hn",
    "addr:street":"P O Box",
    "iso:country":"GB",
    "sg:address":"P O Box 1",
    "sg:city":"Biggleswade",
    "sg:classifiers":[
        {
            "category":"Manufacturing",
            "subcategory":"Wood Products",
            "type":"Manufacturing & Wholesale Goods"
        }
    ],
    "sg:postcode":"SG18 9HN",
    "sg:province":"Bedfordshire",
    "sg:tags":[
        "packaging",
        "crate",
        "pallets"
    ],
    "wof:name":"Frame Consultants",
    "wof:placetype":"venue"
},
  "geometry": {"coordinates":[-0.292006,52.071102],"type":"Point"}
}