{
  "type": "Feature",
  "properties": {
    "addr:full":"Rosemullion, Gunswell La South Molton Devon EX36 4DH",
    "addr:housenumber":"molton",
    "addr:postcode":"ex36 4dh",
    "addr:street":"La South",
    "iso:country":"GB",
    "sg:address":"Rosemullion, Gunswell La",
    "sg:city":"South Molton",
    "sg:classifiers":[
        {
            "category":"Freight",
            "type":"Transportation"
        }
    ],
    "sg:postcode":"EX36 4DH",
    "sg:province":"Devon",
    "sg:tags":[
        "haulage",
        "road"
    ],
    "wof:name":"Jennings,R J,",
    "wof:placetype":"venue"
},
  "geometry": {"coordinates":[-3.831824,51.017647],"type":"Point"}
}