{
  "type": "Feature",
  "properties": {
    "iso:country":"GB",
    "sg:address":"55a Beam Street",
    "sg:city":"Nantwich",
    "sg:classifiers":[
        {
            "category":"Health Services",
            "subcategory":"Health Practitioner",
            "type":"Services"
        }
    ],
    "sg:phone":"+44 1270 610629",
    "sg:postcode":"CW5 5NF",
    "sg:province":"Cheshire",
    "sg:tags":[
        "homoeopathic"
    ],
    "wof:name":"P Kirkland",
    "wof:placetype":"venue"
},
  "geometry": {"coordinates":[-2.5199511051,53.0690612793],"type":"Point"}
}