{
  "type": "Feature",
  "properties": {
    "iso:country":"GB",
    "sg:address":"6 Eadie Street",
    "sg:city":"Nuneaton",
    "sg:classifiers":[
        {
            "category":"Personal",
            "subcategory":"Beauty Salon",
            "type":"Services"
        }
    ],
    "sg:postcode":"CV10 8JA",
    "sg:province":"Leicestershire",
    "sg:tags":[
        "unisex",
        "hairdresser"
    ],
    "wof:name":"Upper Cuts",
    "wof:placetype":"venue"
},
  "geometry": {"coordinates":[-1.5076819658,52.5225448608],"type":"Point"}
}