{
  "type": "Feature",
  "properties": {
    "addr:full":"30a Grenfell Road Mitcham Greater London CR4 2BY",
    "addr:housenumber":"30a",
    "addr:postcode":"cr4 2by",
    "addr:street":"Grenfell Road",
    "iso:country":"GB",
    "sg:address":"30a Grenfell Road",
    "sg:city":"Mitcham",
    "sg:classifiers":[
        {
            "category":"Home & Garden",
            "subcategory":"Building Materials",
            "type":"Retail Goods"
        }
    ],
    "sg:postcode":"CR4 2BY",
    "sg:province":"Greater London",
    "sg:tags":[
        "fencing"
    ],
    "wof:name":"London Fencing",
    "wof:placetype":"venue"
},
  "geometry": {"coordinates":[-0.160155,51.419041],"type":"Point"}
}