{
  "type": "Feature",
  "properties": {
    "addr:full":"2 Kinross Place Fort William Highland PH33 6UN",
    "addr:housenumber":"2",
    "addr:postcode":"ph33 6un",
    "addr:street":"Kinross Place",
    "iso:country":"GB",
    "sg:address":"2 Kinross Place",
    "sg:city":"Fort William",
    "sg:classifiers":[
        {
            "category":"Home & Garden",
            "subcategory":"Carpets & Floor Coverings",
            "type":"Retail Goods"
        }
    ],
    "sg:postcode":"PH33 6UN",
    "sg:province":"Highland",
    "sg:tags":[
        "carpets",
        "rug",
        "matting"
    ],
    "wof:name":"G S Reid",
    "wof:placetype":"venue"
},
  "geometry": {"coordinates":[-5.1134958267,56.8078536987],"type":"Point"}
}