{
  "type": "Feature",
  "properties": {
    "iso:country":"GB",
    "sg:address":"78 The Strand, Newlyn",
    "sg:city":"Penzance",
    "sg:classifiers":[
        {
            "category":"Real Estate",
            "subcategory":"Developer",
            "type":"Services"
        }
    ],
    "sg:phone":"+44 1736 361793",
    "sg:postcode":"TR18 5HW",
    "sg:province":"Cornwall",
    "sg:tags":[
        "property"
    ],
    "wof:name":"Trelawney Ltd.",
    "wof:placetype":"venue"
},
  "geometry": {"coordinates":[-5.5502867699,50.106716156],"type":"Point"}
}