{
  "type": "Feature",
  "properties": {
    "addr:full":"Nether Barr Farm, Barr Girvan South Ayrshire KA26 9TY",
    "addr:housenumber":"barr",
    "addr:postcode":"ka26 9ty",
    "addr:street":"Nether",
    "iso:country":"GB",
    "sg:address":"Nether Barr Farm, Barr",
    "sg:city":"Girvan",
    "sg:classifiers":[
        {
            "category":"Farming",
            "subcategory":"Livestock Farm",
            "type":"Manufacturing & Wholesale Goods"
        }
    ],
    "sg:phone":"+44 1465 861236",
    "sg:postcode":"KA26 9TY",
    "sg:province":"South Ayrshire",
    "sg:tags":[
        "others"
    ],
    "wof:name":"Messrs John Wilson",
    "wof:placetype":"venue"
},
  "geometry": {"coordinates":[-4.713569,55.210251],"type":"Point"}
}