{
  "type": "Feature",
  "properties": {
    "iso:country":"GB",
    "sg:address":"162 Canterbury Street",
    "sg:city":"Gillingham",
    "sg:classifiers":[
        {
            "category":"Taxi",
            "type":"Transportation"
        },
        {
            "category":"Military Area",
            "subcategory":"Air Force Base",
            "type":"Public Place"
        }
    ],
    "sg:phone":"+44 1634 575656",
    "sg:postcode":"ME7 5UB",
    "sg:province":"Kent",
    "sg:tags":[
        "hire",
        "private"
    ],
    "wof:name":"Star Taxis",
    "wof:placetype":"venue"
},
  "geometry": {"coordinates":[0.545707,51.381905],"type":"Point"}
}