{
  "type": "Feature",
  "properties": {
    "addr:full":"4 Harlech Rd Camberley Hampshire GU17 9DF",
    "addr:housenumber":"4",
    "addr:postcode":"gu17 9df",
    "addr:street":"Harlech Rd",
    "iso:country":"GB",
    "sg:address":"4 Harlech Rd",
    "sg:city":"Camberley",
    "sg:classifiers":[
        {
            "category":"Building & Trades",
            "subcategory":"Plumbing",
            "type":"Services"
        }
    ],
    "sg:postcode":"GU17 9DF",
    "sg:province":"Hampshire",
    "sg:tags":[
        "central",
        "heating"
    ],
    "wof:name":"Blofeld,Craig,",
    "wof:placetype":"venue"
},
  "geometry": {"coordinates":[-0.7849259973,51.3297271729],"type":"Point"}
}