{
  "type": "Feature",
  "properties": {
    "iso:country":"GB",
    "sg:address":"P O Box 321",
    "sg:city":"Dover",
    "sg:classifiers":[
        {
            "category":"Shopping",
            "subcategory":"Musical Instruments",
            "type":"Retail Goods"
        }
    ],
    "sg:phone":"+44 1304 872812",
    "sg:postcode":"CT15 7YQ",
    "sg:province":"Kent",
    "sg:tags":[
        "music",
        "sheet"
    ],
    "wof:name":"Forwoods Music",
    "wof:placetype":"venue"
},
  "geometry": {"coordinates":[1.21877,51.148659],"type":"Point"}
}