{
  "type": "Feature",
  "properties": {
    "addr:full":"Monkswell Park Indstrl Estate, Manse Lane Knaresborough North Yorkshire HG5 8NQ",
    "addr:postcode":"hg5 8nq",
    "addr:street":"Monkswell Park Indstrl Estate Manse Lane",
    "iso:country":"GB",
    "sg:address":"Monkswell Park Indstrl Estate, Manse Lane",
    "sg:city":"Knaresborough",
    "sg:classifiers":[
        {
            "category":"Fast Food",
            "type":"Food & Drink"
        }
    ],
    "sg:phone":"+44 1423 860171",
    "sg:postcode":"HG5 8NQ",
    "sg:province":"North Yorkshire",
    "sg:tags":[
        "away",
        "meal",
        "outlet",
        "take"
    ],
    "wof:name":"Sandwiches Unlimited",
    "wof:placetype":"venue"
},
  "geometry": {"coordinates":[-1.446956,54.003174],"type":"Point"}
}