{
  "type": "Feature",
  "properties": {
    "addr:full":"Barton Lodge, Barton Road Wirral Merseyside CH47 1HJ",
    "addr:postcode":"ch47 1hj",
    "addr:street":"Barton Road",
    "iso:country":"GB",
    "sg:address":"Barton Lodge, Barton Road",
    "sg:city":"Wirral",
    "sg:classifiers":[
        {
            "category":"Building & Trades",
            "subcategory":"Construction",
            "type":"Services"
        }
    ],
    "sg:postcode":"CH47 1HJ",
    "sg:province":"Merseyside",
    "sg:tags":[
        "builder"
    ],
    "wof:name":"Rowmac (House Builders) Ltd.",
    "wof:placetype":"venue"
},
  "geometry": {"coordinates":[-3.1869900227,53.3907394409],"type":"Point"}
}