{
  "type": "Feature",
  "properties": {
    "addr:full":"The County Primary School, Back Lane, Horsmonden Tonbridge Kent TN12 8JN",
    "addr:postcode":"tn12 8jn",
    "addr:street":"Back Lane",
    "iso:country":"GB",
    "sg:address":"The County Primary School, Back Lane, Horsmonden",
    "sg:city":"Tonbridge",
    "sg:classifiers":[
        {
            "category":"Education",
            "subcategory":"Library",
            "type":"Public Place"
        }
    ],
    "sg:postcode":"TN12 8JN",
    "sg:province":"Kent",
    "sg:tags":[
        "book"
    ],
    "wof:name":"Horsmonden Library",
    "wof:placetype":"venue"
},
  "geometry": {"coordinates":[0.4291400015,51.1393013],"type":"Point"}
}