{
  "type": "Feature",
  "properties": {
    "addr:full":"Downs Chambers, The Downs Altrincham Cheshire WA14 2QZ",
    "addr:postcode":"wa14 2qz",
    "addr:street":"Downs Altrincham",
    "iso:country":"GB",
    "sg:address":"Downs Chambers, The Downs",
    "sg:city":"Altrincham",
    "sg:classifiers":[
        {
            "category":"Professional",
            "subcategory":"Advertising",
            "type":"Services"
        }
    ],
    "sg:postcode":"WA14 2QZ",
    "sg:province":"Cheshire",
    "sg:tags":[
        "agency"
    ],
    "wof:name":"Cahoots Creative Services",
    "wof:placetype":"venue"
},
  "geometry": {"coordinates":[-2.352741003,53.3842735291],"type":"Point"}
}