{
  "type": "Feature",
  "properties": {
    "iso:country":"GB",
    "sg:address":"10 Stephens Firs, Mortimer",
    "sg:city":"Reading",
    "sg:classifiers":[
        {
            "category":"Personal",
            "type":"Services"
        }
    ],
    "sg:phone":"+44 118 933 3415",
    "sg:postcode":"RG7 3UY",
    "sg:province":"Berkshire",
    "sg:tags":[
        "wedding"
    ],
    "wof:name":"Berkshire Video Productions",
    "wof:placetype":"venue"
},
  "geometry": {"coordinates":[-1.07104,51.376633],"type":"Point"}
}