{
  "type": "Feature",
  "properties": {
    "iso:country":"GB",
    "sg:address":"Cascade Ct, North End",
    "sg:city":"Bedale",
    "sg:classifiers":[
        {
            "category":"Farming",
            "subcategory":"Livestock Farm",
            "type":"Manufacturing & Wholesale Goods"
        }
    ],
    "sg:postcode":"DL8 1XQ",
    "sg:province":"North Yorkshire",
    "sg:tags":[
        "others"
    ],
    "wof:name":"Dalesend Farms Ltd",
    "wof:placetype":"venue"
},
  "geometry": {"coordinates":[-1.592345953,54.28881073],"type":"Point"}
}