{
  "type": "Feature",
  "properties": {
    "iso:country":"GB",
    "sg:address":"11 Silver Street, Ashwell",
    "sg:city":"Baldock",
    "sg:classifiers":[
        {
            "category":"Real Estate",
            "subcategory":"Architect",
            "type":"Services"
        }
    ],
    "sg:phone":"+44 1462 742685",
    "sg:postcode":"SG7 5QJ",
    "sg:province":"Bedfordshire",
    "wof:name":"Mervyn Miller",
    "wof:placetype":"venue"
},
  "geometry": {"coordinates":[-0.151544,52.040581],"type":"Point"}
}