{
  "type": "Feature",
  "properties": {
    "addr:full":"Raikes Hall, Cowling Keighley North Yorkshire BD22 0JX",
    "addr:postcode":"bd22 0jx",
    "iso:country":"GB",
    "sg:address":"Raikes Hall, Cowling",
    "sg:city":"Keighley",
    "sg:classifiers":[
        {
            "category":"Farming",
            "subcategory":"Livestock Farm",
            "type":"Manufacturing & Wholesale Goods"
        }
    ],
    "sg:phone":"+44 1535 634120",
    "sg:postcode":"BD22 0JX",
    "sg:province":"North Yorkshire",
    "sg:tags":[
        "others"
    ],
    "wof:name":"J & J Westaway",
    "wof:placetype":"venue"
},
  "geometry": {"coordinates":[-2.0406939983,53.8850631714],"type":"Point"}
}