{
  "type": "Feature",
  "properties": {
    "iso:country":"GB",
    "sg:address":"3 Pincey Brook, The Street, Takeley",
    "sg:city":"Bishops Stortford",
    "sg:classifiers":[
        {
            "category":"Building & Trades",
            "subcategory":"Construction",
            "type":"Services"
        }
    ],
    "sg:phone":"+44 1279 850090",
    "sg:postcode":"CM22 6QN",
    "sg:province":"Essex",
    "sg:tags":[
        "decorator",
        "painter"
    ],
    "wof:name":"Paul Allen Interiors",
    "wof:placetype":"venue"
},
  "geometry": {"coordinates":[0.2668350041,51.8677711487],"type":"Point"}
}