{
  "type": "Feature",
  "properties": {
    "addr:full":"The Street, Hothfield Ashford Kent TN26 1ES",
    "addr:postcode":"tn26 1es",
    "addr:street":"The Street",
    "iso:country":"GB",
    "sg:address":"The Street, Hothfield",
    "sg:city":"Ashford",
    "sg:classifiers":[
        {
            "category":"Bars & Pubs",
            "type":"Food & Drink"
        }
    ],
    "sg:phone":"+44 1233 626262",
    "sg:postcode":"TN26 1ES",
    "sg:province":"Kent",
    "sg:tags":[
        "pubs",
        "inn"
    ],
    "wof:name":"The Tufton Bailiffehouse",
    "wof:placetype":"venue"
},
  "geometry": {"coordinates":[0.816965,51.171291],"type":"Point"}
}