{
  "type": "Feature",
  "properties": {
    "addr:full":"221 Pettits Lane North, Rise Park Romford Essex RM1 4NU",
    "addr:housenumber":"221",
    "addr:postcode":"rm1 4nu",
    "addr:street":"Pettits Lane North Rise Park",
    "iso:country":"GB",
    "sg:address":"221 Pettits Lane North, Rise Park",
    "sg:city":"Romford",
    "sg:classifiers":[
        {
            "category":"Manufacturing",
            "subcategory":"Tools & Machinery",
            "type":"Manufacturing & Wholesale Goods"
        }
    ],
    "sg:phone":"+44 1708 734343",
    "sg:postcode":"RM1 4NU",
    "sg:province":"Essex",
    "sg:tags":[
        "power"
    ],
    "wof:name":"Trojan Tools (U K) Ltd.",
    "wof:placetype":"venue"
},
  "geometry": {"coordinates":[0.1811,51.593048],"type":"Point"}
}