{
  "type": "Feature",
  "properties": {
    "iso:country":"GB",
    "sg:address":"Southcott Barton, Westleigh",
    "sg:city":"Bideford",
    "sg:classifiers":[
        {
            "category":"Health Services",
            "subcategory":"Nursing And Care Facility",
            "type":"Services"
        },
        {
            "category":"Social Services",
            "subcategory":"Retirement Home",
            "type":"Services"
        }
    ],
    "sg:phone":"+44 1237 475133",
    "sg:postcode":"EX39 4NH",
    "sg:province":"Devon",
    "sg:tags":[
        "residential"
    ],
    "wof:name":"Southcott Barton",
    "wof:placetype":"venue"
},
  "geometry": {"coordinates":[-4.1825661659,51.0361824036],"type":"Point"}
}