{
  "type": "Feature",
  "properties": {
    "iso:country":"GB",
    "sg:address":"3 Horsemarket St, Golden Square",
    "sg:city":"Warrington",
    "sg:classifiers":[
        {
            "category":"Home & Garden",
            "subcategory":"Home Furnishings",
            "type":"Retail Goods"
        }
    ],
    "sg:phone":"+44 1925 411404",
    "sg:postcode":"WA1 1TP",
    "sg:province":"Cheshire",
    "sg:tags":[
        "awning",
        "canopy",
        "blinds"
    ],
    "wof:name":"Apollo Window Blinds",
    "wof:placetype":"venue"
},
  "geometry": {"coordinates":[-2.5937159061,53.3892974854],"type":"Point"}
}