{
  "type": "Feature",
  "properties": {
    "addr:full":"11 Millway Road Andover Hampshire SP10 3EU",
    "addr:housenumber":"11",
    "addr:postcode":"sp10 3eu",
    "addr:street":"Millway Road",
    "iso:country":"GB",
    "sg:address":"11 Millway Road",
    "sg:city":"Andover",
    "sg:classifiers":[
        {
            "category":"Health Services",
            "subcategory":"Nursing And Care Facility",
            "type":"Services"
        }
    ],
    "sg:phone":"+44 1264 333800",
    "sg:postcode":"SP10 3EU",
    "sg:province":"Hampshire",
    "sg:tags":[
        "home"
    ],
    "wof:name":"Mountwood Nursing Home",
    "wof:placetype":"venue"
},
  "geometry": {"coordinates":[-1.496695,51.209007],"type":"Point"}
}