{
  "type": "Feature",
  "properties": {
    "iso:country":"GB",
    "sg:address":"54 Mill Street",
    "sg:city":"Selkirk",
    "sg:classifiers":[
        {
            "category":"Building & Trades",
            "subcategory":"Construction",
            "type":"Services"
        }
    ],
    "sg:phone":"+44 1750 20700",
    "sg:postcode":"TD7 5DQ",
    "sg:province":"Scottish Borders",
    "sg:tags":[
        "decorator",
        "painter"
    ],
    "sg:website":"http://www.calumscott.freeservenet.co.uk",
    "wof:name":"Calum Scott",
    "wof:placetype":"venue"
},
  "geometry": {"coordinates":[-2.8460800648,55.5487823486],"type":"Point"}
}