{
  "type": "Feature",
  "properties": {
    "iso:country":"GB",
    "sg:address":"Academic Studies Centre, 10-11 Bulstrode Place",
    "sg:city":"West End",
    "sg:classifiers":[
        {
            "category":"Education",
            "subcategory":"Music School",
            "type":"Public Place"
        }
    ],
    "sg:phone":"+44 20 7486 6018",
    "sg:postcode":"W1M 5FW",
    "sg:province":"Hampshire",
    "wof:name":"Trinity College Of Music",
    "wof:placetype":"venue"
},
  "geometry": {"coordinates":[-0.13899,51.50758],"type":"Point"}
}