{
  "type": "Feature",
  "properties": {
    "addr:full":"77 Hollydown Way London Greater London E11 4NB",
    "addr:housenumber":"77",
    "addr:postcode":"e11 4nb",
    "addr:street":"Hollydown Way",
    "iso:country":"GB",
    "sg:address":"77 Hollydown Way",
    "sg:city":"London",
    "sg:classifiers":[
        {
            "category":"Professional",
            "subcategory":"Accounting & Tax Preparation",
            "type":"Services"
        }
    ],
    "sg:phone":"+44 121 237 4000",
    "sg:postcode":"E11 4NB",
    "sg:province":"Greater London",
    "sg:tags":[
        "accountant"
    ],
    "wof:name":"N S K & Co International Accountants",
    "wof:placetype":"venue"
},
  "geometry": {"coordinates":[0.0025800001,51.5589103699],"type":"Point"}
}