{
  "type": "Feature",
  "properties": {
    "addr:full":"71 High Street Sittingbourne Kent ME10 4AW",
    "addr:housenumber":"71",
    "addr:postcode":"me10 4aw",
    "addr:street":"High Street",
    "iso:country":"GB",
    "sg:address":"71 High Street",
    "sg:city":"Sittingbourne",
    "sg:classifiers":[
        {
            "category":"Professional",
            "subcategory":"Lawyer & Legal Services",
            "type":"Services"
        }
    ],
    "sg:phone":"+44 1795 474004",
    "sg:postcode":"ME10 4AW",
    "sg:province":"Kent",
    "sg:tags":[
        "solicitor"
    ],
    "wof:name":"Pope & Co",
    "wof:placetype":"venue"
},
  "geometry": {"coordinates":[0.73641,51.339809],"type":"Point"}
}