{
  "type": "Feature",
  "properties": {
    "iso:country":"GB",
    "sg:address":"Scotstown Medical Centre, Cairnfold Road, Bridge Of Don",
    "sg:city":"Aberdeen",
    "sg:classifiers":[
        {
            "category":"Health Services",
            "subcategory":"Doctor",
            "type":"Services"
        }
    ],
    "sg:phone":"+44 1224 702149",
    "sg:postcode":"AB22 8LD",
    "sg:province":"Aberdeen City",
    "sg:tags":[
        "practitioners"
    ],
    "wof:name":"Scotstown Medical Centre",
    "wof:placetype":"venue"
},
  "geometry": {"coordinates":[-2.100278,57.180534],"type":"Point"}
}