{
  "type": "Feature",
  "properties": {
    "addr:full":"522 Muswell Hill Broadway London Greater London N10 1BT",
    "addr:housenumber":"522",
    "addr:postcode":"n10 1bt",
    "addr:street":"Muswell Hill Broadway",
    "iso:country":"GB",
    "sg:address":"522 Muswell Hill Broadway",
    "sg:city":"London",
    "sg:classifiers":[
        {
            "category":"Cafe",
            "type":"Food & Drink"
        }
    ],
    "sg:phone":"+44 20 8883 7523",
    "sg:postcode":"N10 1BT",
    "sg:province":"Greater London",
    "sg:tags":[
        "tea",
        "snack",
        "bar",
        "room"
    ],
    "wof:name":"The Broadway Cafe",
    "wof:placetype":"venue"
},
  "geometry": {"coordinates":[-0.1435119957,51.5930099487],"type":"Point"}
}