{
  "type": "Feature",
  "properties": {
    "addr:full":"Redhill Road Cobham Surrey KT11 1EF",
    "addr:postcode":"kt11 1ef",
    "addr:street":"Redhill Road",
    "iso:country":"GB",
    "sg:address":"Redhill Road",
    "sg:city":"Cobham",
    "sg:classifiers":[
        {
            "category":"Sports & Exercise",
            "subcategory":"Golf",
            "type":"Entertainment"
        }
    ],
    "sg:phone":"+44 1932 867275",
    "sg:postcode":"KT11 1EF",
    "sg:province":"Surrey",
    "sg:tags":[
        "club",
        "course"
    ],
    "wof:name":"Silvermere Golf Complex",
    "wof:placetype":"venue"
},
  "geometry": {"coordinates":[-0.451761,51.337963],"type":"Point"}
}