{
  "type": "Feature",
  "properties": {
    "addr:full":"Watery Lane, Lower Bullingham Hereford Herefordshire HR2 6JW",
    "addr:postcode":"hr2 6jw",
    "addr:street":"Watery Lane",
    "iso:country":"GB",
    "sg:address":"Watery Lane, Lower Bullingham",
    "sg:city":"Hereford",
    "sg:classifiers":[
        {
            "category":"Wholesale",
            "subcategory":"Scrap",
            "type":"Manufacturing & Wholesale Goods"
        },
        {
            "category":"Wholesale",
            "subcategory":"Auto Parts",
            "type":"Manufacturing & Wholesale Goods"
        }
    ],
    "sg:phone":"+44 1432 268939",
    "sg:postcode":"HR2 6JW",
    "sg:province":"Herefordshire",
    "sg:tags":[
        "car",
        "breaker",
        "dismantlers"
    ],
    "wof:name":"City Spares",
    "wof:placetype":"venue"
},
  "geometry": {"coordinates":[-2.6975491047,52.0399513245],"type":"Point"}
}