{
  "type": "Feature",
  "properties": {
    "iso:country":"GB",
    "sg:address":"Barwick Ford",
    "sg:city":"Ware",
    "sg:classifiers":[
        {
            "category":"Manufacturing",
            "subcategory":"Lumber",
            "type":"Manufacturing & Wholesale Goods"
        }
    ],
    "sg:postcode":"SG11 1DA",
    "sg:province":"Hertfordshire",
    "sg:tags":[
        "importer",
        "merchants",
        "agent",
        "timber"
    ],
    "wof:name":"A10 Timber Co.",
    "wof:placetype":"venue"
},
  "geometry": {"coordinates":[0.0044269999,51.8568305969],"type":"Point"}
}