{
  "type": "Feature",
  "properties": {
    "addr:full":"1 Edward St London Greater London SE8 5HA",
    "addr:housenumber":"1",
    "addr:postcode":"se8 5ha",
    "addr:street":"Edward St",
    "iso:country":"GB",
    "sg:address":"1 Edward St",
    "sg:city":"London",
    "sg:classifiers":[
        {
            "category":"Wholesale",
            "subcategory":"Scrap",
            "type":"Manufacturing & Wholesale Goods"
        }
    ],
    "sg:postcode":"SE8 5HA",
    "sg:province":"Greater London",
    "sg:tags":[
        "breaker",
        "dismantlers"
    ],
    "wof:name":"Escort-Orion Centre",
    "wof:placetype":"venue"
},
  "geometry": {"coordinates":[-0.02723,51.481022],"type":"Point"}
}