{
  "type": "Feature",
  "properties": {
    "iso:country":"GB",
    "sg:address":"Newtonmills, Tomich",
    "sg:city":"Invergordon",
    "sg:classifiers":[
        {
            "category":"Professional",
            "subcategory":"Engineering",
            "type":"Services"
        }
    ],
    "sg:postcode":"IV18 0NP",
    "sg:province":"Highland",
    "sg:tags":[
        "contractor",
        "electrical",
        "engineer"
    ],
    "wof:name":"R R Mackenzie",
    "wof:placetype":"venue"
},
  "geometry": {"coordinates":[-4.1664438248,57.6878509521],"type":"Point"}
}