{
  "type": "Feature",
  "properties": {
    "iso:country":"GB",
    "sg:address":"49 Gaer Road",
    "sg:city":"Newport",
    "sg:classifiers":[
        {
            "category":"Professional",
            "subcategory":"Computer Services",
            "type":"Services"
        }
    ],
    "sg:phone":"+44 1633 663442",
    "sg:postcode":"NP20 3GY",
    "sg:province":"Newport",
    "sg:tags":[
        "information"
    ],
    "wof:name":"The Gaer Neighbourhood Watch",
    "wof:placetype":"venue"
},
  "geometry": {"coordinates":[-3.0191230774,51.5772628784],"type":"Point"}
}