{
  "type": "Feature",
  "properties": {
    "addr:full":"69 Sutton Common Road Sutton Surrey SM1 3HN",
    "addr:housenumber":"69",
    "addr:postcode":"sm1 3hn",
    "addr:street":"Sutton Common Road",
    "iso:country":"GB",
    "sg:address":"69 Sutton Common Road",
    "sg:city":"Sutton",
    "sg:classifiers":[
        {
            "category":"Food & Beverages",
            "subcategory":"Liquor & Beverages",
            "type":"Retail Goods"
        }
    ],
    "sg:phone":"+44 20 8241 2940",
    "sg:postcode":"SM1 3HN",
    "sg:province":"Surrey",
    "sg:tags":[
        "beer",
        "spirit",
        "wines"
    ],
    "wof:name":"Patson",
    "wof:placetype":"venue"
},
  "geometry": {"coordinates":[-0.197101,51.374817],"type":"Point"}
}