{
  "type": "Feature",
  "properties": {
    "iso:country":"GB",
    "sg:address":"New Connection Street",
    "sg:city":"Camborne",
    "sg:classifiers":[
        {
            "category":"Organizations",
            "subcategory":"Non-profit Organization",
            "type":"Services"
        }
    ],
    "sg:phone":"+44 1209 613088",
    "sg:postcode":"TR14 8AU",
    "sg:province":"Cornwall",
    "sg:tags":[
        "organisation",
        "voluntary",
        "charity"
    ],
    "wof:name":"New Connection Centre",
    "wof:placetype":"venue"
},
  "geometry": {"coordinates":[-5.297754,50.213894],"type":"Point"}
}