{
  "type": "Feature",
  "properties": {
    "addr:full":"1074 Whitgift Centre Croydon Surrey CR0 1UX",
    "addr:housenumber":"1074",
    "addr:postcode":"cr0 1ux",
    "addr:street":"Whitgift Centre",
    "iso:country":"GB",
    "sg:address":"1074 Whitgift Centre",
    "sg:city":"Croydon",
    "sg:classifiers":[
        {
            "category":"Cafe",
            "type":"Food & Drink"
        }
    ],
    "sg:phone":"+44 20 8681 0569",
    "sg:postcode":"CR0 1UX",
    "sg:province":"Surrey",
    "sg:tags":[
        "tea",
        "room"
    ],
    "wof:name":"English & Continental Bar",
    "wof:placetype":"venue"
},
  "geometry": {"coordinates":[-0.097916998,51.3748893738],"type":"Point"}
}