{
  "type": "Feature",
  "properties": {
    "iso:country":"GB",
    "sg:address":"19a Paradise Street",
    "sg:city":"Oxford",
    "sg:classifiers":[
        {
            "category":"Shopping",
            "subcategory":"Books",
            "type":"Retail Goods"
        }
    ],
    "sg:postcode":"OX1 1LD",
    "sg:province":"Oxfordshire",
    "wof:name":"Griffinwood (U K) Ltd.",
    "wof:placetype":"venue"
},
  "geometry": {"coordinates":[-1.263956,51.751286],"type":"Point"}
}