{
  "type": "Feature",
  "properties": {
    "addr:full":"54 Beacon Rd Scarborough North Yorkshire YO12 4HT",
    "addr:housenumber":"54",
    "addr:postcode":"yo12 4ht",
    "addr:street":"Beacon Rd",
    "iso:country":"GB",
    "sg:address":"54 Beacon Rd",
    "sg:city":"Scarborough",
    "sg:classifiers":[
        {
            "category":"Military Area",
            "subcategory":"Air Force Base",
            "type":"Public Place"
        }
    ],
    "sg:postcode":"YO12 4HT",
    "sg:province":"North Yorkshire",
    "sg:tags":[
        "taxi",
        "hire",
        "private"
    ],
    "wof:name":"Huneyman,John,",
    "wof:placetype":"venue"
},
  "geometry": {"coordinates":[-0.442432,54.243168],"type":"Point"}
}