{
  "type": "Feature",
  "properties": {
    "addr:full":"110 Queen St Withernsea East Riding of Yorkshire HU19 2HB",
    "addr:housenumber":"110",
    "addr:postcode":"hu19 2hb",
    "addr:street":"Queen St",
    "iso:country":"GB",
    "sg:address":"110 Queen St",
    "sg:city":"Withernsea",
    "sg:classifiers":[
        {
            "category":"Food & Beverages",
            "subcategory":"Fruits & Vegetables",
            "type":"Retail Goods"
        }
    ],
    "sg:postcode":"HU19 2HB",
    "sg:province":"East Riding of Yorkshire",
    "sg:tags":[
        "greengrocer"
    ],
    "wof:name":"Richardson,J & M,",
    "wof:placetype":"venue"
},
  "geometry": {"coordinates":[0.029424,53.735073],"type":"Point"}
}