{
  "type": "Feature",
  "properties": {
    "iso:country":"GB",
    "sg:address":"619 Fishponds Road, Fishponds",
    "sg:city":"Bristol",
    "sg:classifiers":[
        {
            "category":"Banks & Credit Unions",
            "subcategory":"Bank",
            "type":"Services"
        }
    ],
    "sg:phone":"+44 117 939 1100",
    "sg:postcode":"BS16 3BA",
    "sg:province":"City of Bristol",
    "sg:tags":[
        "broker",
        "mortgage"
    ],
    "wof:name":"The Mortgage Advice Co. Ltd.",
    "wof:placetype":"venue"
},
  "geometry": {"coordinates":[-2.536641,51.477539],"type":"Point"}
}