{
  "type": "Feature",
  "properties": {
    "addr:full":"Unit 2 Newyearfield Farm, Hawk Brae, Ladywell East Livingston West Lothian EH54 6AG",
    "addr:housenumber":"unit 2 newyearfield farm",
    "addr:postcode":"eh54 6ag",
    "addr:street":"Hawk Brae Ladywell East",
    "iso:country":"GB",
    "sg:address":"Unit 2 Newyearfield Farm, Hawk Brae, Ladywell East",
    "sg:city":"Livingston",
    "sg:classifiers":[
        {
            "category":"Professional",
            "subcategory":"Management & Consulting",
            "type":"Services"
        }
    ],
    "sg:phone":"+44 1506 414207",
    "sg:postcode":"EH54 6AG",
    "sg:province":"West Lothian",
    "sg:tags":[
        "conservation"
    ],
    "wof:name":"Woodland Trust (Livingston Office)",
    "wof:placetype":"venue"
},
  "geometry": {"coordinates":[-3.5098340511,55.8862457275],"type":"Point"}
}