{
  "type": "Feature",
  "properties": {
    "addr:full":"20 Adelaide Clo Derby Derbyshire DE3 5JN",
    "addr:housenumber":"20",
    "addr:postcode":"de3 5jn",
    "iso:country":"GB",
    "sg:address":"20 Adelaide Clo",
    "sg:city":"Derby",
    "sg:classifiers":[
        {
            "category":"Building & Trades",
            "subcategory":"Construction",
            "type":"Services"
        }
    ],
    "sg:phone":"+44 1332 511963",
    "sg:postcode":"DE3 5JN",
    "sg:province":"Derbyshire",
    "sg:tags":[
        "decorator",
        "painter"
    ],
    "wof:name":"G E Noble",
    "wof:placetype":"venue"
},
  "geometry": {"coordinates":[-1.538812,52.917744],"type":"Point"}
}