{
  "type": "Feature",
  "properties": {
    "addr:full":"North St Industrial Estate Droitwich Worcestershire WR9 8JB",
    "addr:postcode":"wr9 8jb",
    "addr:street":"North St Industrial Estate",
    "iso:country":"GB",
    "sg:address":"North St Industrial Estate",
    "sg:city":"Droitwich",
    "sg:classifiers":[
        {
            "category":"Retail",
            "subcategory":"Auto Repair",
            "type":"Services"
        }
    ],
    "sg:phone":"+44 1905 775532",
    "sg:postcode":"WR9 8JB",
    "sg:province":"Worcestershire",
    "sg:tags":[
        "modification",
        "garage"
    ],
    "wof:name":"Hagland Auto-Tec",
    "wof:placetype":"venue"
},
  "geometry": {"coordinates":[-2.155944109,52.2682800293],"type":"Point"}
}