{
  "type": "Feature",
  "properties": {
    "iso:country":"GB",
    "sg:address":"27 Revesby Ave",
    "sg:city":"Scunthorpe",
    "sg:classifiers":[
        {
            "category":"Professional",
            "subcategory":"Detective & Security Services",
            "type":"Services"
        }
    ],
    "sg:postcode":"DN16 2DG",
    "sg:province":"Lincolnshire",
    "sg:tags":[
        "alarm",
        "burglar",
        "system"
    ],
    "wof:name":"Harris,J,",
    "wof:placetype":"venue"
},
  "geometry": {"coordinates":[-0.6502150297,53.5729827881],"type":"Point"}
}