{
  "type": "Feature",
  "properties": {
    "addr:full":"114a High Street Godalming Surrey GU7 1DW",
    "addr:housenumber":"114a",
    "addr:postcode":"gu7 1dw",
    "addr:street":"High Street",
    "iso:country":"GB",
    "sg:address":"114a High Street",
    "sg:city":"Godalming",
    "sg:classifiers":[
        {
            "category":"Professional",
            "subcategory":"Detective & Security Services",
            "type":"Services"
        }
    ],
    "sg:postcode":"GU7 1DW",
    "sg:province":"Surrey",
    "wof:name":"Tantalus Computer Security Ltd",
    "wof:placetype":"venue"
},
  "geometry": {"coordinates":[-0.6156640053,51.1854171753],"type":"Point"}
}