{
  "type": "Feature",
  "properties": {
    "iso:country":"GB",
    "sg:address":"245 High Street",
    "sg:city":"Dorking",
    "sg:classifiers":[
        {
            "category":"Fast Food",
            "type":"Food & Drink"
        },
        {
            "category":"Food & Beverages",
            "subcategory":"Meat & Fish",
            "type":"Retail Goods"
        }
    ],
    "sg:phone":"+44 1306 889600",
    "sg:postcode":"RH4 1RT",
    "sg:province":"Surrey",
    "sg:tags":[
        "shop",
        "chip"
    ],
    "wof:name":"C Hill",
    "wof:placetype":"venue"
},
  "geometry": {"coordinates":[-0.3284749985,51.233795166],"type":"Point"}
}