{
  "type": "Feature",
  "properties": {
    "addr:full":"110 Townhead Road, Dore Sheffield Derbyshire S17 3GB",
    "addr:housenumber":"110",
    "addr:postcode":"s17 3gb",
    "addr:street":"Townhead Road",
    "iso:country":"GB",
    "sg:address":"110 Townhead Road, Dore",
    "sg:city":"Sheffield",
    "sg:classifiers":[
        {
            "category":"Real Estate",
            "subcategory":"Surveying",
            "type":"Services"
        }
    ],
    "sg:phone":"+44 114 236 6014",
    "sg:postcode":"S17 3GB",
    "sg:province":"Derbyshire",
    "sg:tags":[
        "surveyor",
        "quantity"
    ],
    "wof:name":"John M Drakeford Associates",
    "wof:placetype":"venue"
},
  "geometry": {"coordinates":[-1.545807004,53.3260002136],"type":"Point"}
}