{
  "type": "Feature",
  "properties": {
    "addr:full":"48 Darlinghurst Grove Leigh-on-sea Essex SS9 3LG",
    "addr:housenumber":"48",
    "addr:postcode":"ss9 3lg",
    "addr:street":"Darlinghurst Grove",
    "iso:country":"GB",
    "sg:address":"48 Darlinghurst Grove",
    "sg:city":"Leigh-on-sea",
    "sg:classifiers":[
        {
            "category":"Professional",
            "subcategory":"Computer Services",
            "type":"Services"
        },
        {
            "category":"Utilities",
            "type":"Services"
        }
    ],
    "sg:phone":"+44 1702 480222",
    "sg:postcode":"SS9 3LG",
    "sg:province":"Essex",
    "sg:tags":[
        "software",
        "system",
        "internet"
    ],
    "wof:name":"Avocado Computers",
    "wof:placetype":"venue"
},
  "geometry": {"coordinates":[0.668249,51.548378],"type":"Point"}
}