{
  "type": "Feature",
  "properties": {
    "iso:country":"GB",
    "sg:address":"Town Court Farm, Bayham Road",
    "sg:city":"Tunbridge Wells",
    "sg:classifiers":[
        {
            "category":"Home & Garden",
            "subcategory":"Furniture",
            "type":"Retail Goods"
        }
    ],
    "sg:postcode":"TN2 5HU",
    "sg:province":"East Sussex",
    "wof:name":"Bayham Pine",
    "wof:placetype":"venue"
},
  "geometry": {"coordinates":[0.261789,51.117298],"type":"Point"}
}