{
  "type": "Feature",
  "properties": {
    "iso:country":"GB",
    "sg:address":"Glenmorrison Rd",
    "sg:city":"Glasgow",
    "sg:classifiers":[
        {
            "category":"Place Of Worship",
            "type":"Public Place"
        }
    ],
    "sg:phone":"+44 141 638 6101",
    "sg:postcode":"G53 7UG",
    "sg:province":"East Renfrewshire",
    "wof:name":"United Free Church Of Scotland",
    "wof:placetype":"venue"
},
  "geometry": {"coordinates":[-4.3408632278,55.8087120056],"type":"Point"}
}