{
  "type": "Feature",
  "properties": {
    "addr:full":"Crookes Lane, Kewstoke Weston-super-mare Somerset BS22 9XL",
    "addr:postcode":"bs22 9xl",
    "addr:street":"Crookes Lane",
    "iso:country":"GB",
    "sg:address":"Crookes Lane, Kewstoke",
    "sg:city":"Weston-super-mare",
    "sg:classifiers":[
        {
            "category":"Bars & Pubs",
            "type":"Food & Drink"
        }
    ],
    "sg:phone":"+44 1934 622766",
    "sg:postcode":"BS22 9XL",
    "sg:province":"Somerset",
    "sg:tags":[
        "pubs",
        "inn"
    ],
    "wof:name":"The New Inn",
    "wof:placetype":"venue"
},
  "geometry": {"coordinates":[-2.955006,51.365665],"type":"Point"}
}