{
  "type": "Feature",
  "properties": {
    "iso:country":"GB",
    "sg:address":"276 Lower Farnham Road",
    "sg:city":"Aldershot",
    "sg:classifiers":[
        {
            "category":"Health Services",
            "subcategory":"Doctor",
            "type":"Services"
        }
    ],
    "sg:phone":"+44 1252 344868",
    "sg:postcode":"GU11 3RB",
    "sg:province":"Hampshire",
    "sg:tags":[
        "practitioners"
    ],
    "wof:name":"Southlea Surgery",
    "wof:placetype":"venue"
},
  "geometry": {"coordinates":[-0.7561330199,51.2355041504],"type":"Point"}
}