{
  "type": "Feature",
  "properties": {
    "addr:full":"Milford House, Bath Rd, Speen Newbury Berkshire RG14 1RG",
    "addr:postcode":"rg14 1rg",
    "addr:street":"Bath Rd",
    "iso:country":"GB",
    "sg:address":"Milford House, Bath Rd, Speen",
    "sg:city":"Newbury",
    "sg:classifiers":[
        {
            "category":"Professional",
            "subcategory":"Management & Consulting",
            "type":"Services"
        }
    ],
    "sg:phone":"+44 1635 522249",
    "sg:postcode":"RG14 1RG",
    "sg:province":"Berkshire",
    "sg:tags":[
        "consultant",
        "business"
    ],
    "wof:name":"Milford Associates",
    "wof:placetype":"venue"
},
  "geometry": {"coordinates":[-1.3481390476,51.4107513428],"type":"Point"}
}