{
  "type": "Feature",
  "properties": {
    "iso:country":"GB",
    "sg:address":"64 Foxglove Close",
    "sg:city":"Witham",
    "sg:classifiers":[
        {
            "category":"Military Area",
            "subcategory":"Air Force Base",
            "type":"Public Place"
        }
    ],
    "sg:phone":"+44 1376 512450",
    "sg:postcode":"CM8 2XW",
    "sg:province":"Essex",
    "sg:tags":[
        "taxi",
        "hire",
        "private"
    ],
    "wof:name":"A 1 Taxis",
    "wof:placetype":"venue"
},
  "geometry": {"coordinates":[0.619938,51.807774],"type":"Point"}
}