{
  "type": "Feature",
  "properties": {
    "iso:country":"GB",
    "sg:address":"Cherry Row",
    "sg:city":"Leeds",
    "sg:classifiers":[
        {
            "category":"Bars & Pubs",
            "type":"Food & Drink"
        }
    ],
    "sg:phone":"+44 113 245 3383",
    "sg:postcode":"LS9 7LY",
    "sg:province":"West Yorkshire",
    "sg:tags":[
        "pubs",
        "inn"
    ],
    "wof:name":"Cherry Tree",
    "wof:placetype":"venue"
},
  "geometry": {"coordinates":[-1.528633,53.804749],"type":"Point"}
}