{
  "type": "Feature",
  "properties": {
    "addr:full":"10 Carfin Road Wishaw North Lanarkshire ML2 7UG",
    "addr:housenumber":"10",
    "addr:postcode":"ml2 7ug",
    "addr:street":"Carfin Road",
    "iso:country":"GB",
    "sg:address":"10 Carfin Road",
    "sg:city":"Wishaw",
    "sg:classifiers":[
        {
            "category":"Bars & Pubs",
            "type":"Food & Drink"
        }
    ],
    "sg:phone":"+44 1698 374714",
    "sg:postcode":"ML2 7UG",
    "sg:province":"North Lanarkshire",
    "sg:tags":[
        "pubs",
        "inn"
    ],
    "wof:name":"Era Bar",
    "wof:placetype":"venue"
},
  "geometry": {"coordinates":[-3.9564979076,55.7808456421],"type":"Point"}
}