{
  "type": "Feature",
  "properties": {
    "iso:country":"GB",
    "sg:address":"28 Lowther Rd",
    "sg:city":"Rochdale",
    "sg:classifiers":[
        {
            "category":"Professional",
            "subcategory":"Detective & Security Services",
            "type":"Services"
        }
    ],
    "sg:phone":"+44 1706 341116",
    "sg:postcode":"OL11 2NE",
    "sg:province":"Lancashire",
    "sg:tags":[
        "car"
    ],
    "wof:name":"Karmark",
    "wof:placetype":"venue"
},
  "geometry": {"coordinates":[-2.161459,53.600567],"type":"Point"}
}