{
  "type": "Feature",
  "properties": {
    "addr:full":"1 Wythall Green Way, Wythall Birmingham Worcestershire B47 6WG",
    "addr:housenumber":"1",
    "addr:postcode":"b47 6wg",
    "addr:street":"Wythall Green Way",
    "iso:country":"GB",
    "sg:address":"1 Wythall Green Way, Wythall",
    "sg:city":"Birmingham",
    "sg:classifiers":[
        {
            "category":"Insurance",
            "subcategory":"Insurance Agent",
            "type":"Services"
        }
    ],
    "sg:phone":"+44 1564 828888",
    "sg:postcode":"B47 6WG",
    "sg:province":"Worcestershire",
    "wof:name":"Britannic Assurance Plc",
    "wof:placetype":"venue"
},
  "geometry": {"coordinates":[-1.8942699432,52.3761787415],"type":"Point"}
}