{
  "type": "Feature",
  "properties": {
    "iso:country":"GB",
    "sg:address":"80 London Road",
    "sg:city":"Bognor Regis",
    "sg:classifiers":[
        {
            "category":"Professional",
            "subcategory":"Printing & Photocopies",
            "type":"Services"
        }
    ],
    "sg:phone":"+44 1243 842687",
    "sg:postcode":"PO21 1DD",
    "sg:province":"West Sussex",
    "sg:tags":[
        "printer"
    ],
    "wof:name":"Peter Taylor Litho",
    "wof:placetype":"venue"
},
  "geometry": {"coordinates":[-0.67443,50.786484],"type":"Point"}
}