{
  "type": "Feature",
  "properties": {
    "addr:full":"Woolwich Rd, Charlton Charlton Greater London SE7 7AW",
    "addr:postcode":"se7 7aw",
    "addr:street":"Woolwich Rd",
    "iso:country":"GB",
    "sg:address":"Woolwich Rd, Charlton",
    "sg:city":"Charlton",
    "sg:classifiers":[
        {
            "category":"Autos & Motor Vehicles",
            "subcategory":"Automobile Sales",
            "type":"Retail Goods"
        }
    ],
    "sg:phone":"+44 20 8293 1694",
    "sg:postcode":"SE7 7AW",
    "sg:province":"Greater London",
    "sg:tags":[
        "commercial"
    ],
    "wof:name":"Daewoo Support Centre",
    "wof:placetype":"venue"
},
  "geometry": {"coordinates":[0.0243619997,51.4871406555],"type":"Point"}
}