{
  "type": "Feature",
  "properties": {
    "iso:country":"GB",
    "sg:address":"69 Aintree Road, Lordswood",
    "sg:city":"Chatham",
    "sg:classifiers":[
        {
            "category":"Retail",
            "subcategory":"Driving School",
            "type":"Services"
        }
    ],
    "sg:phone":"+44 1634 681647",
    "sg:postcode":"ME5 8PQ",
    "sg:province":"Kent",
    "wof:name":"Smith's Driving School",
    "wof:placetype":"venue"
},
  "geometry": {"coordinates":[0.5438839793,51.3392868042],"type":"Point"}
}