{
  "type": "Feature",
  "properties": {
    "addr:full":"211 Breck Rd, Everton Liverpool Merseyside L5 6PT",
    "addr:housenumber":"211",
    "addr:postcode":"l5 6pt",
    "addr:street":"Breck Rd",
    "iso:country":"GB",
    "sg:address":"211 Breck Rd, Everton",
    "sg:city":"Liverpool",
    "sg:classifiers":[
        {
            "category":"Retail",
            "subcategory":"Laundry & Dry Cleaning",
            "type":"Services"
        }
    ],
    "sg:postcode":"L5 6PT",
    "sg:province":"Merseyside",
    "sg:tags":[
        "alteration"
    ],
    "wof:name":"Thomsons the Cleaners",
    "wof:placetype":"venue"
},
  "geometry": {"coordinates":[-2.9599208832,53.4226989746],"type":"Point"}
}