{
  "type": "Feature",
  "properties": {
    "iso:country":"GB",
    "sg:address":"591 Neath Road",
    "sg:city":"Swansea",
    "sg:classifiers":[
        {
            "category":"Social Services",
            "subcategory":"Retirement Home",
            "type":"Services"
        }
    ],
    "sg:phone":"+44 1792 771350",
    "sg:postcode":"SA6 8EF",
    "sg:province":"Swansea",
    "sg:tags":[
        "residential",
        "care"
    ],
    "wof:name":"Glanelfred Residential & Day Services",
    "wof:placetype":"venue"
},
  "geometry": {"coordinates":[-3.9228229523,51.6609802246],"type":"Point"}
}