{
  "type": "Feature",
  "properties": {
    "iso:country":"GB",
    "sg:address":"21 Spring Vale, Cowplain",
    "sg:city":"Waterlooville",
    "sg:classifiers":[
        {
            "category":"Professional",
            "subcategory":"Engineering",
            "type":"Services"
        }
    ],
    "sg:postcode":"PO8 9DA",
    "sg:province":"Hampshire",
    "sg:tags":[
        "contractor",
        "electrical",
        "engineer"
    ],
    "wof:name":"A K Brown Electrical",
    "wof:placetype":"venue"
},
  "geometry": {"coordinates":[-1.0087870359,50.9007301331],"type":"Point"}
}