{
  "type": "Feature",
  "properties": {
    "iso:country":"GB",
    "sg:address":"17 South Street",
    "sg:city":"Bishops Stortford",
    "sg:classifiers":[
        {
            "category":"Shopping",
            "subcategory":"Clothing, Apparel, & Fashions",
            "type":"Retail Goods"
        }
    ],
    "sg:phone":"+44 1279 655613",
    "sg:postcode":"CM23 3AB",
    "sg:province":"Essex",
    "sg:tags":[
        "shop"
    ],
    "wof:name":"Laura Ashley",
    "wof:placetype":"venue"
},
  "geometry": {"coordinates":[0.160715,51.869213],"type":"Point"}
}