{
  "type": "Feature",
  "properties": {
    "addr:full":"282 Sandbanks Road, Parkstone Poole Dorset BH14 8HX",
    "addr:housenumber":"282",
    "addr:postcode":"bh14 8hx",
    "addr:street":"Sandbanks Road",
    "iso:country":"GB",
    "sg:address":"282 Sandbanks Road, Parkstone",
    "sg:city":"Poole",
    "sg:classifiers":[
        {
            "category":"Shopping",
            "subcategory":"Clothing, Apparel, & Fashions",
            "type":"Retail Goods"
        }
    ],
    "sg:phone":"+44 1202 708160",
    "sg:postcode":"BH14 8HX",
    "sg:province":"Dorset",
    "sg:tags":[
        "shop"
    ],
    "wof:name":"Siesta",
    "wof:placetype":"venue"
},
  "geometry": {"coordinates":[-1.9454090595,50.7080383301],"type":"Point"}
}