{
  "type": "Feature",
  "properties": {
    "addr:full":"New Mill Flatt,, Newby, Penrith Cumbria CA10 3HG",
    "addr:postcode":"ca10 3hg",
    "addr:street":"New",
    "iso:country":"GB",
    "sg:address":"New Mill Flatt,, Newby,",
    "sg:city":"Penrith",
    "sg:classifiers":[
        {
            "category":"Professional",
            "subcategory":"Business Services",
            "type":"Services"
        }
    ],
    "sg:postcode":"CA10 3HG",
    "sg:province":"Cumbria",
    "sg:tags":[
        "import",
        "export",
        "agent"
    ],
    "wof:name":"Palmer,David J,",
    "wof:placetype":"venue"
},
  "geometry": {"coordinates":[-2.631264,54.585602],"type":"Point"}
}