{
  "type": "Feature",
  "properties": {
    "iso:country":"GB",
    "sg:address":"137-139 Seaside Road",
    "sg:city":"Eastbourne",
    "sg:classifiers":[
        {
            "category":"Shopping",
            "subcategory":"Used Merchandise",
            "type":"Retail Goods"
        }
    ],
    "sg:phone":"+44 1323 411422",
    "sg:postcode":"BN21 3PG",
    "sg:province":"East Sussex",
    "sg:tags":[
        "shop",
        "second-hand"
    ],
    "wof:name":"Instant Enterprises Ltd.",
    "wof:placetype":"venue"
},
  "geometry": {"coordinates":[0.2937709987,50.7692871094],"type":"Point"}
}