{
  "type": "Feature",
  "properties": {
    "iso:country":"GB",
    "sg:address":"Bournevale, Little Hardwick Rd, Aldridge",
    "sg:city":"Walsall",
    "sg:classifiers":[
        {
            "category":"Arena",
            "subcategory":"Sports Club",
            "type":"Entertainment"
        }
    ],
    "sg:phone":"+44 121 353 2856",
    "sg:postcode":"WS9 0SQ",
    "sg:province":"Staffordshire",
    "wof:name":"Aldridge RFC",
    "wof:placetype":"venue"
},
  "geometry": {"coordinates":[-1.889949,52.587299],"type":"Point"}
}