{
  "type": "Feature",
  "properties": {
    "iso:country":"GB",
    "sg:address":"1a Talygarn St",
    "sg:city":"Cardiff",
    "sg:classifiers":[
        {
            "category":"Retail",
            "subcategory":"Auto Repair",
            "type":"Services"
        }
    ],
    "sg:postcode":"CF14 3PS",
    "sg:province":"Cardiff",
    "sg:tags":[
        "modification",
        "garage"
    ],
    "wof:name":"Raven,L,",
    "wof:placetype":"venue"
},
  "geometry": {"coordinates":[-3.1870939732,51.5005340576],"type":"Point"}
}