{
  "type": "Feature",
  "properties": {
    "iso:country":"GB",
    "sg:address":"Bron Menai",
    "sg:city":"Llanfairpwllgwyngyll",
    "sg:classifiers":[
        {
            "category":"Autos & Motor Vehicles",
            "subcategory":"Auto Supplies",
            "type":"Retail Goods"
        }
    ],
    "sg:phone":"+44 1248 430242",
    "sg:postcode":"LL61 6BJ",
    "sg:province":"Isle of Anglesey",
    "sg:tags":[
        "electric"
    ],
    "wof:name":"Anglesey Rewinds",
    "wof:placetype":"venue"
},
  "geometry": {"coordinates":[-4.2929091454,53.1729011536],"type":"Point"}
}