{
  "type": "Feature",
  "properties": {
    "addr:full":"The Old Station Yard, North Walsham Road, Aylsham Norwich Norfolk NR11 6LP",
    "addr:postcode":"nr11 6lp",
    "addr:street":"North Walsham Road;Norwich",
    "iso:country":"GB",
    "sg:address":"The Old Station Yard, North Walsham Road, Aylsham",
    "sg:city":"Norwich",
    "sg:classifiers":[
        {
            "category":"Building & Trades",
            "subcategory":"Equipment Rental",
            "type":"Services"
        }
    ],
    "sg:phone":"+44 1263 732368",
    "sg:postcode":"NR11 6LP",
    "sg:province":"Norfolk",
    "sg:tags":[
        "plant",
        "machinery"
    ],
    "wof:name":"Aylsham Plant Hire Ltd.",
    "wof:placetype":"venue"
},
  "geometry": {"coordinates":[1.2503540516,52.7950668335],"type":"Point"}
}