{
  "type": "Feature",
  "properties": {
    "addr:full":"St Peters Way Birkenhead Merseyside L43 9QR",
    "addr:postcode":"l43 9qr",
    "addr:street":"St Peters Way",
    "iso:country":"GB",
    "sg:address":"St Peters Way",
    "sg:city":"Birkenhead",
    "sg:classifiers":[
        {
            "category":"Education",
            "subcategory":"School",
            "type":"Public Place"
        }
    ],
    "sg:phone":"+44 151 677 8438",
    "sg:postcode":"L43 9QR",
    "sg:province":"Merseyside",
    "sg:tags":[
        "local",
        "authority"
    ],
    "wof:name":"St Peter's R C Aided Primary School",
    "wof:placetype":"venue"
},
  "geometry": {"coordinates":[-3.076669,53.383469],"type":"Point"}
}