{
  "type": "Feature",
  "properties": {
    "addr:full":"Unit B Riverside Court, Wharf Way Leicester Leicestershire LE2 9TF",
    "addr:postcode":"le2 9tf",
    "addr:street":"Wharf Way",
    "iso:country":"GB",
    "sg:address":"Unit B Riverside Court, Wharf Way",
    "sg:city":"Leicester",
    "sg:classifiers":[
        {
            "category":"Shopping",
            "subcategory":"Stationery & Office Supplies",
            "type":"Retail Goods"
        },
        {
            "category":"Professional",
            "subcategory":"Printing & Photocopies",
            "type":"Services"
        }
    ],
    "sg:phone":"+44 116 278 9391",
    "sg:postcode":"LE2 9TF",
    "sg:province":"Leicestershire",
    "sg:tags":[
        "printers'",
        "printer"
    ],
    "wof:name":"REPRICO LTD",
    "wof:placetype":"venue"
},
  "geometry": {"coordinates":[-1.16515,52.583416],"type":"Point"}
}