{
  "type": "Feature",
  "properties": {
    "iso:country":"GB",
    "sg:address":"Merryfield, The Fields",
    "sg:city":"Warminster",
    "sg:classifiers":[
        {
            "category":"Personal",
            "type":"Services"
        }
    ],
    "sg:phone":"+44 1747 861339",
    "sg:postcode":"BA12 6EA",
    "sg:province":"Somerset",
    "sg:tags":[
        "delivery"
    ],
    "wof:name":"Caretaker Despatch",
    "wof:placetype":"venue"
},
  "geometry": {"coordinates":[-2.265233,51.092812],"type":"Point"}
}