{
  "type": "Feature",
  "properties": {
    "iso:country":"GB",
    "sg:address":"61 Worcester Road, Hagley",
    "sg:city":"Stourbridge",
    "sg:classifiers":[
        {
            "category":"Shopping",
            "subcategory":"Clothing, Apparel, & Fashions",
            "type":"Retail Goods"
        }
    ],
    "sg:phone":"+44 1562 883372",
    "sg:postcode":"DY9 0LF",
    "sg:province":"West Midlands",
    "sg:tags":[
        "shop"
    ],
    "wof:name":"Modar Rossini",
    "wof:placetype":"venue"
},
  "geometry": {"coordinates":[-2.145862,52.417133],"type":"Point"}
}