{
  "type": "Feature",
  "properties": {
    "addr:full":"P O Box 11 Newark Nottinghamshire NG22 0BD",
    "addr:housenumber":"box 11",
    "addr:postcode":"ng22 0bd",
    "addr:street":"P O",
    "iso:country":"GB",
    "sg:address":"P O Box 11",
    "sg:city":"Newark",
    "sg:classifiers":[
        {
            "category":"Professional",
            "subcategory":"Management & Consulting",
            "type":"Services"
        }
    ],
    "sg:phone":"+44 1623 862771",
    "sg:postcode":"NG22 0BD",
    "sg:province":"Nottinghamshire",
    "sg:tags":[
        "sport"
    ],
    "wof:name":"Quiet Storm Associates",
    "wof:placetype":"venue"
},
  "geometry": {"coordinates":[-0.898539,53.21122],"type":"Point"}
}