{
  "type": "Feature",
  "properties": {
    "iso:country":"GB",
    "sg:address":"Riverfield Drive",
    "sg:city":"Bedford",
    "sg:classifiers":[
        {
            "category":"Autos & Motor Vehicles",
            "subcategory":"Automobile Sales",
            "type":"Retail Goods"
        }
    ],
    "sg:phone":"+44 1234 360666",
    "sg:postcode":"MK41 0SA",
    "sg:province":"Bedfordshire",
    "sg:tags":[
        "car"
    ],
    "wof:name":"Bells Motor Group",
    "wof:placetype":"venue"
},
  "geometry": {"coordinates":[-0.426154,52.137344],"type":"Point"}
}