{
  "type": "Feature",
  "properties": {
    "addr:full":"475-477 London Rd Camberley Berkshire GU15 3JA",
    "addr:housenumber":"475-477",
    "addr:postcode":"gu15 3ja",
    "addr:street":"London Rd",
    "iso:country":"GB",
    "sg:address":"475-477 London Rd",
    "sg:city":"Camberley",
    "sg:classifiers":[
        {
            "category":"Home & Garden",
            "subcategory":"Building Materials",
            "type":"Retail Goods"
        }
    ],
    "sg:phone":"+44 1276 676744",
    "sg:postcode":"GU15 3JA",
    "sg:province":"Berkshire",
    "sg:tags":[
        "brick"
    ],
    "wof:name":"Marble Granite & Slate",
    "wof:placetype":"venue"
},
  "geometry": {"coordinates":[-0.76636,51.334503],"type":"Point"}
}