{
  "type": "Feature",
  "properties": {
    "iso:country":"GB",
    "sg:address":"20 Padstow Close",
    "sg:city":"Nuneaton",
    "sg:classifiers":[
        {
            "category":"Home & Garden",
            "subcategory":"Kitchen Supply",
            "type":"Retail Goods"
        }
    ],
    "sg:postcode":"CV11 6FN",
    "sg:province":"Leicestershire",
    "sg:tags":[
        "measuring",
        "scale"
    ],
    "wof:name":"A Quinton Scale Makers",
    "wof:placetype":"venue"
},
  "geometry": {"coordinates":[-1.442722,52.525398],"type":"Point"}
}