{
  "type": "Feature",
  "properties": {
    "iso:country":"GB",
    "sg:address":"28 Cathedral Road",
    "sg:city":"Cardiff",
    "sg:classifiers":[
        {
            "category":"Professional",
            "subcategory":"Accounting & Tax Preparation",
            "type":"Services"
        }
    ],
    "sg:postcode":"CF11 9LJ",
    "sg:province":"Cardiff",
    "sg:tags":[
        "accountant"
    ],
    "wof:name":"Agincourt Ltd.",
    "wof:placetype":"venue"
},
  "geometry": {"coordinates":[-3.190737,51.483364],"type":"Point"}
}