{
  "type": "Feature",
  "properties": {
    "addr:full":"Warwick Road Stratford-upon-avon Warwickshire CV37 0NR",
    "addr:postcode":"cv37 0nr",
    "addr:street":"Warwick Road",
    "iso:country":"GB",
    "sg:address":"Warwick Road",
    "sg:city":"Stratford-upon-avon",
    "sg:classifiers":[
        {
            "category":"Travel",
            "subcategory":"Hotels & Motels",
            "type":"Entertainment"
        }
    ],
    "sg:phone":"+44 1789 295252",
    "sg:postcode":"CV37 0NR",
    "sg:province":"Warwickshire",
    "wof:name":"Welcombe Hotel & Golf Course Ltd.",
    "wof:placetype":"venue"
},
  "geometry": {"coordinates":[-1.6953350306,52.1992073059],"type":"Point"}
}