{
  "type": "Feature",
  "properties": {
    "addr:full":"Mayne St Stoke-on-trent Staffordshire ST4 4QZ",
    "addr:postcode":"st4 4qz",
    "addr:street":"Mayne St",
    "iso:country":"GB",
    "sg:address":"Mayne St",
    "sg:city":"Stoke-on-trent",
    "sg:classifiers":[
        {
            "category":"Building & Trades",
            "subcategory":"Construction",
            "type":"Services"
        }
    ],
    "sg:phone":"+44 1782 643878",
    "sg:postcode":"ST4 4QZ",
    "sg:province":"Staffordshire",
    "sg:tags":[
        "decorator",
        "painter"
    ],
    "wof:name":"Bateman,Paul,",
    "wof:placetype":"venue"
},
  "geometry": {"coordinates":[-2.199234,52.980614],"type":"Point"}
}