{
  "type": "Feature",
  "properties": {
    "iso:country":"GB",
    "sg:address":"24 Zetland Street",
    "sg:city":"Wakefield",
    "sg:classifiers":[
        {
            "category":"Shopping",
            "subcategory":"Books",
            "type":"Retail Goods"
        }
    ],
    "sg:phone":"+44 1924 444688",
    "sg:postcode":"WF1 1QT",
    "sg:province":"West Yorkshire",
    "sg:tags":[
        "second-hand"
    ],
    "wof:name":"The Old Vicarage Book Shop",
    "wof:placetype":"venue"
},
  "geometry": {"coordinates":[-1.4942829609,53.6836395264],"type":"Point"}
}