{
  "type": "Feature",
  "properties": {
    "addr:full":"34 Hollingarth Way, Hemyock Cullompton Devon EX15 3XB",
    "addr:housenumber":"34",
    "addr:postcode":"ex15 3xb",
    "addr:street":"Hollingarth Way",
    "iso:country":"GB",
    "sg:address":"34 Hollingarth Way, Hemyock",
    "sg:city":"Cullompton",
    "sg:classifiers":[
        {
            "category":"Professional",
            "subcategory":"Computer Services",
            "type":"Services"
        }
    ],
    "sg:phone":"+44 1823 680119",
    "sg:postcode":"EX15 3XB",
    "sg:province":"Devon",
    "sg:tags":[
        "system",
        "software"
    ],
    "wof:name":"N E M Business Solutions",
    "wof:placetype":"venue"
},
  "geometry": {"coordinates":[-3.226018,50.916161],"type":"Point"}
}