{
  "type": "Feature",
  "properties": {
    "iso:country":"GB",
    "sg:address":"1/2 Aston Works, Back Lane, Aston",
    "sg:city":"Bampton",
    "sg:classifiers":[
        {
            "category":"Professional",
            "subcategory":"Advertising",
            "type":"Services"
        }
    ],
    "sg:phone":"+44 1993 852200",
    "sg:postcode":"OX18 2DQ",
    "sg:province":"Gloucestershire",
    "sg:tags":[
        "agency"
    ],
    "wof:name":"A D S Advertising & Design (Oxford) Ltd.",
    "wof:placetype":"venue"
},
  "geometry": {"coordinates":[-1.546758,51.727924],"type":"Point"}
}