{
  "type": "Feature",
  "properties": {
    "iso:country":"GB",
    "sg:address":"73 Selbourne Road",
    "sg:city":"Luton",
    "sg:classifiers":[
        {
            "category":"Food & Beverages",
            "subcategory":"Groceries & Convenience Stores",
            "type":"Retail Goods"
        }
    ],
    "sg:phone":"+44 1582 725572",
    "sg:postcode":"LU4 8LR",
    "sg:province":"Bedfordshire",
    "wof:name":"M & H Food Store",
    "wof:placetype":"venue"
},
  "geometry": {"coordinates":[-0.435036,51.890285],"type":"Point"}
}