{
  "type": "Feature",
  "properties": {
    "addr:full":"98 Conway Rd Colwyn Bay Conwy LL29 7LE",
    "addr:housenumber":"98",
    "addr:postcode":"ll29 7le",
    "addr:street":"Conway Rd",
    "iso:country":"GB",
    "sg:address":"98 Conway Rd",
    "sg:city":"Colwyn Bay",
    "sg:classifiers":[
        {
            "category":"Health Services",
            "subcategory":"Doctor",
            "type":"Services"
        }
    ],
    "sg:phone":"+44 1492 532807",
    "sg:postcode":"LL29 7LE",
    "sg:province":"Conwy",
    "sg:tags":[
        "practitioners"
    ],
    "wof:name":"Drs Rouse Powell Owen Williams",
    "wof:placetype":"venue"
},
  "geometry": {"coordinates":[-3.7346889973,53.2981033325],"type":"Point"}
}