{
  "type": "Feature",
  "properties": {
    "addr:full":"Deans Court, 1-3 London Road Bicester Oxfordshire OX26 6BU",
    "addr:housenumber":"1-3",
    "addr:postcode":"ox26 6bu",
    "addr:street":"Deans;London Road",
    "iso:country":"GB",
    "sg:address":"Deans Court, 1-3 London Road",
    "sg:city":"Bicester",
    "sg:classifiers":[
        {
            "category":"Professional",
            "subcategory":"Management & Consulting",
            "type":"Services"
        }
    ],
    "sg:postcode":"OX26 6BU",
    "sg:province":"Oxfordshire",
    "sg:tags":[
        "consultant",
        "business"
    ],
    "wof:name":"I C R International Ltd",
    "wof:placetype":"venue"
},
  "geometry": {"coordinates":[-1.14969,51.896564],"type":"Point"}
}