{
  "type": "Feature",
  "properties": {
    "iso:country":"GB",
    "sg:address":"Guillimont Health Centre, 4 Stoke Road, Bishops Cleeve",
    "sg:city":"Gloucester",
    "sg:classifiers":[
        {
            "category":"Health Services",
            "subcategory":"Optometrist",
            "type":"Services"
        }
    ],
    "sg:phone":"+44 1242 673634",
    "sg:postcode":"GL52 8RP",
    "sg:province":"Gloucestershire",
    "sg:tags":[
        "optician"
    ],
    "wof:name":"F Norville Ltd.",
    "wof:placetype":"venue"
},
  "geometry": {"coordinates":[-2.060244,51.948891],"type":"Point"}
}