{
  "type": "Feature",
  "properties": {
    "iso:country":"GB",
    "sg:address":"Albert Place, Finchley",
    "sg:city":"London",
    "sg:classifiers":[
        {
            "category":"Insurance",
            "subcategory":"Insurance Agent",
            "type":"Services"
        }
    ],
    "sg:phone":"+44 20 8349 0046",
    "sg:postcode":"N3 1QB",
    "sg:province":"Greater London",
    "sg:tags":[
        "broker"
    ],
    "wof:name":"John Nicholls & Co. Ltd.",
    "wof:placetype":"venue"
},
  "geometry": {"coordinates":[-0.19334,51.602421],"type":"Point"}
}