{
  "type": "Feature",
  "properties": {
    "iso:country":"GB",
    "sg:address":"51 Montague Ave",
    "sg:city":"Southampton",
    "sg:classifiers":[
        {
            "category":"Shopping",
            "subcategory":"News",
            "type":"Retail Goods"
        }
    ],
    "sg:postcode":"SO190QB",
    "sg:province":"Hampshire",
    "sg:tags":[
        "newsagent"
    ],
    "wof:name":"Downman,R C,",
    "wof:placetype":"venue"
},
  "geometry": {"coordinates":[-1.337569952,50.9000701904],"type":"Point"}
}