{
  "type": "Feature",
  "properties": {
    "iso:country":"GB",
    "sg:address":"182 Henley Road, Caversham",
    "sg:city":"Reading",
    "sg:classifiers":[
        {
            "category":"Retail",
            "subcategory":"Auto Repair",
            "type":"Services"
        }
    ],
    "sg:postcode":"RG4 0LW",
    "sg:province":"Berkshire",
    "sg:tags":[
        "body",
        "car"
    ],
    "wof:name":"Tabbitt Two Ltd.",
    "wof:placetype":"venue"
},
  "geometry": {"coordinates":[-0.96745,51.502972],"type":"Point"}
}