{
  "type": "Feature",
  "properties": {
    "addr:full":"169 High Street, Gosforth Newcastle-upon-tyne Tyne and Wear NE3 1HE",
    "addr:housenumber":"169",
    "addr:postcode":"ne3 1he",
    "addr:street":"High Street",
    "iso:country":"GB",
    "sg:address":"169 High Street, Gosforth",
    "sg:city":"Newcastle-upon-tyne",
    "sg:classifiers":[
        {
            "category":"Professional",
            "subcategory":"Art Services",
            "type":"Services"
        }
    ],
    "sg:phone":"+44 191 284 9133",
    "sg:postcode":"NE3 1HE",
    "sg:province":"Tyne and Wear",
    "sg:tags":[
        "photographer"
    ],
    "wof:name":"Klick Photopoint",
    "wof:placetype":"venue"
},
  "geometry": {"coordinates":[-1.6198669672,55.0064582825],"type":"Point"}
}