{
  "type": "Feature",
  "properties": {
    "iso:country":"GB",
    "sg:address":"Stephenson Way",
    "sg:city":"Thetford",
    "sg:classifiers":[
        {
            "category":"Professional",
            "type":"Services"
        }
    ],
    "sg:phone":"+44 1842 753505",
    "sg:postcode":"IP24 3RU",
    "sg:province":"Norfolk",
    "sg:tags":[
        "services",
        "belt",
        "conveyor"
    ],
    "wof:name":"Dawson",
    "wof:placetype":"venue"
},
  "geometry": {"coordinates":[0.729613,52.404774],"type":"Point"}
}