{
  "type": "Feature",
  "properties": {
    "addr:full":"The Smithy, High Street Newmilns East Ayrshire KA16 9EE",
    "addr:postcode":"ka16 9ee",
    "addr:street":"High Street",
    "iso:country":"GB",
    "sg:address":"The Smithy, High Street",
    "sg:city":"Newmilns",
    "sg:classifiers":[
        {
            "category":"Personal",
            "subcategory":"Adult",
            "type":"Services"
        }
    ],
    "sg:phone":"+44 1560 323002",
    "sg:postcode":"KA16 9EE",
    "sg:province":"East Ayrshire",
    "sg:tags":[
        "equestrian"
    ],
    "wof:name":"James & Alan Ferrie",
    "wof:placetype":"venue"
},
  "geometry": {"coordinates":[-4.329726,55.607479],"type":"Point"}
}