{
  "type": "Feature",
  "properties": {
    "iso:country":"GB",
    "sg:address":"Heath Park Surgery, 44 Grantham Rd, Bracebridge Heath",
    "sg:city":"Lincoln",
    "sg:classifiers":[
        {
            "category":"Health Services",
            "subcategory":"Doctor",
            "type":"Services"
        }
    ],
    "sg:phone":"+44 1522 871775",
    "sg:postcode":"LN4 2LD",
    "sg:province":"Lincolnshire",
    "sg:tags":[
        "practitioners"
    ],
    "wof:name":"Drs Qureshi Clark & Partners",
    "wof:placetype":"venue"
},
  "geometry": {"coordinates":[-0.536474,53.191395],"type":"Point"}
}