{
  "type": "Feature",
  "properties": {
    "iso:country":"GB",
    "sg:address":"Unit 9 The Vanguards, Vanguard Way",
    "sg:city":"Southend-on-sea",
    "sg:classifiers":[
        {
            "category":"Shopping",
            "subcategory":"Hobbies, Toys, & Games",
            "type":"Retail Goods"
        }
    ],
    "sg:phone":"+44 1702 295110",
    "sg:postcode":"SS3 9QY",
    "sg:province":"Essex",
    "sg:tags":[
        "toy"
    ],
    "wof:name":"D P R Models",
    "wof:placetype":"venue"
},
  "geometry": {"coordinates":[0.79303,51.534039],"type":"Point"}
}