{
  "type": "Feature",
  "properties": {
    "iso:country":"GB",
    "sg:address":"162 Bell Hill Road",
    "sg:city":"Bristol",
    "sg:classifiers":[
        {
            "category":"Building & Trades",
            "subcategory":"Equipment Rental",
            "type":"Services"
        }
    ],
    "sg:phone":"+44 117 961 1649",
    "sg:postcode":"BS5 7NF",
    "sg:province":"City of Bristol",
    "sg:tags":[
        "hire",
        "centre"
    ],
    "wof:name":"Hss Hire Shops",
    "wof:placetype":"venue"
},
  "geometry": {"coordinates":[-2.5294790268,51.4609069824],"type":"Point"}
}