{
  "type": "Feature",
  "properties": {
    "addr:full":"79 Royal Jubilee Court, Main Road Romford Essex RM2 5AW",
    "addr:housenumber":"79",
    "addr:postcode":"rm2 5aw",
    "addr:street":"Royal Jubilee;Main Road",
    "iso:country":"GB",
    "sg:address":"79 Royal Jubilee Court, Main Road",
    "sg:city":"Romford",
    "sg:classifiers":[
        {
            "category":"Social Services",
            "subcategory":"Adult Care",
            "type":"Services"
        }
    ],
    "sg:phone":"+44 1708 742389",
    "sg:postcode":"RM2 5AW",
    "sg:province":"Essex",
    "sg:tags":[
        "housing",
        "sheltered"
    ],
    "wof:name":"Charles House Sheltered Housing",
    "wof:placetype":"venue"
},
  "geometry": {"coordinates":[0.19415,51.585152],"type":"Point"}
}