{
  "type": "Feature",
  "properties": {
    "addr:full":"Backrampart Stranraer Dumfries and Galloway DG9 7LW",
    "addr:postcode":"dg9 7lw",
    "iso:country":"GB",
    "sg:address":"Backrampart",
    "sg:city":"Stranraer",
    "sg:classifiers":[
        {
            "category":"Retail",
            "subcategory":"Auto Repair",
            "type":"Services"
        }
    ],
    "sg:postcode":"DG9 7LW",
    "sg:province":"Dumfries and Galloway",
    "sg:tags":[
        "body",
        "car"
    ],
    "wof:name":"Cars",
    "wof:placetype":"venue"
},
  "geometry": {"coordinates":[-5.032948,54.905083],"type":"Point"}
}