{
  "type": "Feature",
  "properties": {
    "addr:full":"Unit 15, Alexander Business Centre Enfield Greater London EN3 7BB",
    "addr:housenumber":"unit 15",
    "addr:postcode":"en3 7bb",
    "addr:street":"Alexander Business Centre",
    "iso:country":"GB",
    "sg:address":"Unit 15, Alexander Business Centre",
    "sg:city":"Enfield",
    "sg:classifiers":[
        {
            "category":"Shopping",
            "subcategory":"Clothing, Apparel, & Fashions",
            "type":"Retail Goods"
        }
    ],
    "sg:phone":"+44 20 8364 7952",
    "sg:postcode":"EN3 7BB",
    "sg:province":"Greater London",
    "sg:tags":[
        "clothing",
        "fabric"
    ],
    "wof:name":"Deritex Fashions Ltd",
    "wof:placetype":"venue"
},
  "geometry": {"coordinates":[-0.0206739996,51.6566085815],"type":"Point"}
}