{
  "type": "Feature",
  "properties": {
    "iso:country":"GB",
    "sg:address":"227 Oilmills Road, Mereside, Ramsey",
    "sg:city":"Huntingdon",
    "sg:classifiers":[
        {
            "category":"Manufacturing",
            "subcategory":"Metals",
            "type":"Manufacturing & Wholesale Goods"
        }
    ],
    "sg:phone":"+44 1733 844676",
    "sg:postcode":"PE26 2UA",
    "sg:province":"Cambridgeshire",
    "sg:tags":[
        "foundry"
    ],
    "wof:name":"M D S Services",
    "wof:placetype":"venue"
},
  "geometry": {"coordinates":[-0.1158950031,52.4903068542],"type":"Point"}
}