{
  "type": "Feature",
  "properties": {
    "addr:full":"India Buildings, Brunswick St Liverpool Merseyside L2 0PL",
    "addr:postcode":"l2 0pl",
    "addr:street":"Brunswick St",
    "iso:country":"GB",
    "sg:address":"India Buildings, Brunswick St",
    "sg:city":"Liverpool",
    "sg:classifiers":[
        {
            "category":"Deli",
            "type":"Food & Drink"
        }
    ],
    "sg:phone":"+44 151 236 5996",
    "sg:postcode":"L2 0PL",
    "sg:province":"Merseyside",
    "sg:tags":[
        "delicatessen"
    ],
    "wof:name":"Bagels Ltd",
    "wof:placetype":"venue"
},
  "geometry": {"coordinates":[-2.9922399521,53.4057884216],"type":"Point"}
}