{
  "type": "Feature",
  "properties": {
    "iso:country":"GB",
    "sg:address":"Station Rd, Christian Malford",
    "sg:city":"Chippenham",
    "sg:classifiers":[
        {
            "category":"Bus Charters",
            "type":"Transportation"
        }
    ],
    "sg:phone":"+44 1249 720360",
    "sg:postcode":"SN15 4BG",
    "sg:province":"Wiltshire",
    "sg:tags":[
        "hire",
        "coach"
    ],
    "wof:name":"Silver Knight Coaches Ltd",
    "wof:placetype":"venue"
},
  "geometry": {"coordinates":[-2.0559771061,51.5107688904],"type":"Point"}
}