{
  "type": "Feature",
  "properties": {
    "iso:country":"GB",
    "sg:address":"28 Ridgeway",
    "sg:city":"Broadstone",
    "sg:classifiers":[
        {
            "category":"Real Estate",
            "subcategory":"Architect",
            "type":"Services"
        }
    ],
    "sg:phone":"+44 1202 603003",
    "sg:postcode":"BH18 8EA",
    "sg:province":"Dorset",
    "wof:name":"RWN Architects",
    "wof:placetype":"venue"
},
  "geometry": {"coordinates":[-1.991222024,50.7607421875],"type":"Point"}
}