{
  "type": "Feature",
  "properties": {
    "addr:full":"Oatlands Mount Post Office, 67 Leeds Road Harrogate North Yorkshire HG2 8BE",
    "addr:housenumber":"67",
    "addr:postcode":"hg2 8be",
    "addr:street":"Leeds Road",
    "iso:country":"GB",
    "sg:address":"Oatlands Mount Post Office, 67 Leeds Road",
    "sg:city":"Harrogate",
    "sg:classifiers":[
        {
            "category":"Shopping",
            "subcategory":"Gifts & Souvenirs",
            "type":"Retail Goods"
        }
    ],
    "sg:phone":"+44 1423 871364",
    "sg:postcode":"HG2 8BE",
    "sg:province":"North Yorkshire",
    "sg:tags":[
        "shop",
        "poster",
        "card"
    ],
    "wof:name":"Oatlands Mount Post Office",
    "wof:placetype":"venue"
},
  "geometry": {"coordinates":[-1.5340379477,53.9781265259],"type":"Point"}
}