{
  "type": "Feature",
  "properties": {
    "iso:country":"GB",
    "sg:address":"8 The Quay",
    "sg:city":"Bideford",
    "sg:classifiers":[
        {
            "category":"Shopping",
            "subcategory":"Bicycles & Sporting Goods",
            "type":"Retail Goods"
        }
    ],
    "sg:phone":"+44 1237 470791",
    "sg:postcode":"EX39 2HW",
    "sg:province":"Devon",
    "sg:tags":[
        "cycle",
        "accessory"
    ],
    "wof:name":"Freebird",
    "wof:placetype":"venue"
},
  "geometry": {"coordinates":[-4.204914,51.017639],"type":"Point"}
}