{
  "type": "Feature",
  "properties": {
    "addr:full":"33 High Street Newcastle Staffordshire ST5 1QZ",
    "addr:postcode":"33;st5 1qz",
    "addr:street":"High Street",
    "iso:country":"GB",
    "sg:address":"33 High Street",
    "sg:city":"Newcastle",
    "sg:classifiers":[
        {
            "category":"Shopping",
            "subcategory":"Department Store",
            "type":"Retail Goods"
        }
    ],
    "sg:phone":"+44 1782 717787",
    "sg:postcode":"ST5 1QZ",
    "sg:province":"Staffordshire",
    "wof:name":"Pamela Joan Campbell",
    "wof:placetype":"venue"
},
  "geometry": {"coordinates":[-2.2282519341,53.0113487244],"type":"Point"}
}