{
  "type": "Feature",
  "properties": {
    "addr:full":"Units 21 & 23, 49 Effra Road London Greater London SW2 1BZ",
    "addr:housenumber":"units 21 &;49",
    "addr:postcode":"sw2 1bz",
    "addr:street":"Effra Road",
    "iso:country":"GB",
    "sg:address":"Units 21 & 23, 49 Effra Road",
    "sg:city":"London",
    "sg:classifiers":[
        {
            "category":"Government",
            "subcategory":"Office",
            "type":"Public Place"
        }
    ],
    "sg:phone":"+44 20 7733 7646",
    "sg:postcode":"SW2 1BZ",
    "sg:province":"Greater London",
    "sg:tags":[
        "project",
        "gov",
        "community"
    ],
    "wof:name":"Vietnamese Mental Health Services",
    "wof:placetype":"venue"
},
  "geometry": {"coordinates":[-0.11441,51.457596],"type":"Point"}
}