{
  "type": "Feature",
  "properties": {
    "addr:full":"Unit 2 The Ridge, Off Primrose Hill Alfreton Derbyshire DE55 5JR",
    "addr:housenumber":"unit 2",
    "addr:postcode":"de55 5jr",
    "iso:country":"GB",
    "sg:address":"Unit 2 The Ridge, Off Primrose Hill",
    "sg:city":"Alfreton",
    "sg:classifiers":[
        {
            "category":"Retail",
            "subcategory":"Auto Repair",
            "type":"Services"
        }
    ],
    "sg:postcode":"DE55 5JR",
    "sg:province":"Derbyshire",
    "sg:tags":[
        "modification",
        "garage"
    ],
    "wof:name":"Last,Christopher,",
    "wof:placetype":"venue"
},
  "geometry": {"coordinates":[-1.3527150154,53.1184310913],"type":"Point"}
}