{
  "type": "Feature",
  "properties": {
    "addr:full":"156-158 Grays Inn Rd London Greater London WC1X 8EQ",
    "addr:housenumber":"156-158",
    "addr:postcode":"wc1x 8eq",
    "addr:street":"Grays Inn Rd",
    "iso:country":"GB",
    "sg:address":"156-158 Grays Inn Rd",
    "sg:city":"London",
    "sg:classifiers":[
        {
            "category":"Communications",
            "type":"Services"
        }
    ],
    "sg:phone":"+44 20 7419 1035",
    "sg:postcode":"WC1X 8EQ",
    "sg:province":"Greater London",
    "sg:tags":[
        "broadcasting"
    ],
    "wof:name":"Country Music Radio Ltd",
    "wof:placetype":"venue"
},
  "geometry": {"coordinates":[-0.1166350022,51.5247840881],"type":"Point"}
}