{
  "type": "Feature",
  "properties": {
    "addr:full":"Havelock House, Barrack Road Aldershot Hampshire GU11 3NP",
    "addr:postcode":"gu11 3np",
    "addr:street":"Barrack Road",
    "iso:country":"GB",
    "sg:address":"Havelock House, Barrack Road",
    "sg:city":"Aldershot",
    "sg:classifiers":[
        {
            "category":"Organizations",
            "subcategory":"Non-profit Organization",
            "type":"Services"
        }
    ],
    "sg:phone":"+44 1252 311221",
    "sg:postcode":"GU11 3NP",
    "sg:province":"Hampshire",
    "sg:tags":[
        "charitable",
        "organisation",
        "voluntary",
        "charity"
    ],
    "wof:name":"Officers Christian Union",
    "wof:placetype":"venue"
},
  "geometry": {"coordinates":[-0.7682340145,51.2487640381],"type":"Point"}
}