{
  "type": "Feature",
  "properties": {
    "iso:country":"GB",
    "sg:address":"Marlin House, Kings Rd",
    "sg:city":"Immingham",
    "sg:classifiers":[
        {
            "category":"Manufacturing",
            "subcategory":"Signs",
            "type":"Manufacturing & Wholesale Goods"
        }
    ],
    "sg:phone":"+44 1469 576660",
    "sg:postcode":"DN40 1AW",
    "sg:province":"Lincolnshire",
    "sg:tags":[
        "marquee"
    ],
    "wof:name":"Humbershade Fabrics & Covers",
    "wof:placetype":"venue"
},
  "geometry": {"coordinates":[-0.198079,53.619179],"type":"Point"}
}