{
  "type": "Feature",
  "properties": {
    "iso:country":"GB",
    "sg:address":"Unit 9, First Stage Business Park, Brimington Rd North, Whittington Moor",
    "sg:city":"Chesterfield",
    "sg:classifiers":[
        {
            "category":"Home & Garden",
            "subcategory":"Kitchen Supply",
            "type":"Retail Goods"
        }
    ],
    "sg:phone":"+44 1246 260804",
    "sg:postcode":"S41 9BE",
    "sg:province":"Derbyshire",
    "sg:tags":[
        "equipment",
        "catering"
    ],
    "wof:name":"J.S Bakery & Catering Equipment",
    "wof:placetype":"venue"
},
  "geometry": {"coordinates":[-1.4293400049,53.2613105774],"type":"Point"}
}