{
  "type": "Feature",
  "properties": {
    "iso:country":"GB",
    "sg:address":"47 High Street",
    "sg:city":"Northallerton",
    "sg:classifiers":[
        {
            "category":"Government",
            "subcategory":"Post Office",
            "type":"Public Place"
        }
    ],
    "sg:postcode":"DL7 8EG",
    "sg:province":"North Yorkshire",
    "wof:name":"North End Post Office",
    "wof:placetype":"venue"
},
  "geometry": {"coordinates":[-1.437651,54.343475],"type":"Point"}
}