{
  "type": "Feature",
  "properties": {
    "iso:country":"GB",
    "sg:address":"Mantra House, South St",
    "sg:city":"Keighley",
    "sg:classifiers":[
        {
            "category":"Professional",
            "subcategory":"Management & Consulting",
            "type":"Services"
        }
    ],
    "sg:phone":"+44 1535 605101",
    "sg:postcode":"BD21 1SX",
    "sg:province":"West Yorkshire",
    "sg:tags":[
        "consultant",
        "business"
    ],
    "wof:name":"Northern Operations",
    "wof:placetype":"venue"
},
  "geometry": {"coordinates":[-1.911474,53.863605],"type":"Point"}
}