{
  "type": "Feature",
  "properties": {
    "iso:country":"GB",
    "sg:address":"Lady Heyes Farm, Kingsley Rd",
    "sg:city":"Frodsham",
    "sg:classifiers":[
        {
            "category":"Retail",
            "subcategory":"Animal Services",
            "type":"Services"
        }
    ],
    "sg:phone":"+44 1928 787919",
    "sg:postcode":"WA6 6SU",
    "sg:province":"Cheshire",
    "sg:tags":[
        "pet"
    ],
    "wof:name":"Whitley Brook Crematorium ForPets",
    "wof:placetype":"venue"
},
  "geometry": {"coordinates":[-2.69808,53.275669],"type":"Point"}
}