{
  "type": "Feature",
  "properties": {
    "iso:country":"GB",
    "sg:address":"5 High St, Rhuddlan",
    "sg:city":"Rhyl",
    "sg:classifiers":[
        {
            "category":"Personal",
            "subcategory":"Beauty Salon",
            "type":"Services"
        }
    ],
    "sg:postcode":"LL18 2UB",
    "sg:province":"Conwy",
    "sg:tags":[
        "unisex",
        "hairdresser"
    ],
    "wof:name":"Tong,Stuart,",
    "wof:placetype":"venue"
},
  "geometry": {"coordinates":[-3.4671399593,53.2910194397],"type":"Point"}
}