{
  "type": "Feature",
  "properties": {
    "iso:country":"GB",
    "sg:address":"Chilton Indust Est, Northern Rd",
    "sg:city":"Sudbury",
    "sg:classifiers":[
        {
            "category":"Freight",
            "type":"Transportation"
        }
    ],
    "sg:phone":"+44 1787 310900",
    "sg:postcode":"CO10 6XQ",
    "sg:province":"Essex",
    "sg:tags":[
        "haulage",
        "road"
    ],
    "wof:name":"Star Fleet Transport",
    "wof:placetype":"venue"
},
  "geometry": {"coordinates":[0.7343900204,52.0386047363],"type":"Point"}
}