{
  "type": "Feature",
  "properties": {
    "iso:country":"GB",
    "sg:address":"Little Barn Farm, Pennypot Lane",
    "sg:city":"Woking",
    "sg:classifiers":[
        {
            "category":"Shopping",
            "subcategory":"Clothing, Apparel, & Fashions",
            "type":"Retail Goods"
        },
        {
            "category":"Wholesale",
            "subcategory":"Apparel",
            "type":"Manufacturing & Wholesale Goods"
        }
    ],
    "sg:phone":"+44 1276 855877",
    "sg:postcode":"GU24 8DJ",
    "sg:province":"Surrey",
    "sg:tags":[
        "wholesaler",
        "sport",
        "clothing",
        "sportswear"
    ],
    "wof:name":"Kit Direct Ltd.",
    "wof:placetype":"venue"
},
  "geometry": {"coordinates":[-0.6186800003,51.34141922],"type":"Point"}
}