{
  "type": "Feature",
  "properties": {
    "iso:country":"GB",
    "sg:address":"Cowpasture Lodge Farm, Witham On The Hill",
    "sg:city":"Bourne",
    "sg:classifiers":[
        {
            "category":"Farming",
            "subcategory":"Livestock Farm",
            "type":"Manufacturing & Wholesale Goods"
        }
    ],
    "sg:phone":"+44 1778 590258",
    "sg:postcode":"PE10 0JP",
    "sg:province":"Lincolnshire",
    "sg:tags":[
        "others"
    ],
    "wof:name":"G E & J Hales",
    "wof:placetype":"venue"
},
  "geometry": {"coordinates":[-0.441555,52.734989],"type":"Point"}
}