{
  "type": "Feature",
  "properties": {
    "addr:full":"6 High St Bolton Lancashire BL3 6TA",
    "addr:housenumber":"6",
    "addr:postcode":"bl3 6ta",
    "addr:street":"High St",
    "iso:country":"GB",
    "sg:address":"6 High St",
    "sg:city":"Bolton",
    "sg:classifiers":[
        {
            "category":"Shopping",
            "subcategory":"Clothing, Apparel, & Fashions",
            "type":"Retail Goods"
        }
    ],
    "sg:phone":"+44 1204 528966",
    "sg:postcode":"BL3 6TA",
    "sg:province":"Lancashire",
    "sg:tags":[
        "lingerie"
    ],
    "wof:name":"Star Hosiery Ltd",
    "wof:placetype":"venue"
},
  "geometry": {"coordinates":[-2.4412269592,53.5678672791],"type":"Point"}
}