{
  "type": "Feature",
  "properties": {
    "iso:country":"GB",
    "sg:address":"79 Upper Manor Road, Preston",
    "sg:city":"Paignton",
    "sg:classifiers":[
        {
            "category":"Wholesale",
            "subcategory":"Construction Materials",
            "type":"Manufacturing & Wholesale Goods"
        }
    ],
    "sg:phone":"+44 1803 663711",
    "sg:postcode":"TQ3 2TH",
    "sg:province":"Devon",
    "sg:tags":[
        "merchant",
        "glass"
    ],
    "wof:name":"Discount Glass & Glazing",
    "wof:placetype":"venue"
},
  "geometry": {"coordinates":[-3.563644,50.444592],"type":"Point"}
}