{
  "type": "Feature",
  "properties": {
    "iso:country":"GB",
    "sg:address":"Edmonds Close, Denington Industrial Estate",
    "sg:city":"Wellingborough",
    "sg:classifiers":[
        {
            "category":"Professional",
            "subcategory":"Engineering",
            "type":"Services"
        }
    ],
    "sg:phone":"+44 1933 443333",
    "sg:postcode":"NN8 2QY",
    "sg:province":"Northamptonshire",
    "sg:tags":[
        "agricultural",
        "engineer"
    ],
    "wof:name":"P A Turney Ltd",
    "wof:placetype":"venue"
},
  "geometry": {"coordinates":[-0.690034,52.289669],"type":"Point"}
}