{
  "type": "Feature",
  "properties": {
    "addr:full":"16 Old Parr Close Banbury Oxfordshire OX16 5HY",
    "addr:housenumber":"16",
    "addr:postcode":"ox16 5hy",
    "addr:street":"Old Parr Close",
    "iso:country":"GB",
    "sg:address":"16 Old Parr Close",
    "sg:city":"Banbury",
    "sg:classifiers":[
        {
            "category":"Building & Trades",
            "subcategory":"Construction",
            "type":"Services"
        }
    ],
    "sg:phone":"+44 1295 258619",
    "sg:postcode":"OX16 5HY",
    "sg:province":"Oxfordshire",
    "sg:tags":[
        "joinery"
    ],
    "wof:name":"Newlook Fencing & Gates",
    "wof:placetype":"venue"
},
  "geometry": {"coordinates":[-1.3353509903,52.0568275452],"type":"Point"}
}