{
  "type": "Feature",
  "properties": {
    "addr:full":"Marshalls Road Surgery Wellingborough Northamptonshire NN9 6ET",
    "addr:postcode":"nn9 6et",
    "addr:street":"Marshalls",
    "iso:country":"GB",
    "sg:address":"Marshalls Road Surgery",
    "sg:city":"Wellingborough",
    "sg:classifiers":[
        {
            "category":"Health Services",
            "subcategory":"Doctor",
            "type":"Services"
        }
    ],
    "sg:phone":"+44 1933 622349",
    "sg:postcode":"NN9 6ET",
    "sg:province":"Northamptonshire",
    "sg:tags":[
        "practitioners"
    ],
    "wof:name":"Betournay, L",
    "wof:placetype":"venue"
},
  "geometry": {"coordinates":[-0.546464,52.345364],"type":"Point"}
}