{
  "type": "Feature",
  "properties": {
    "iso:country":"GB",
    "sg:address":"10a Westbourne Place",
    "sg:city":"Hove",
    "sg:classifiers":[
        {
            "category":"Professional",
            "subcategory":"Art Services",
            "type":"Services"
        }
    ],
    "sg:phone":"+44 1273 748921",
    "sg:postcode":"BN3 4GN",
    "sg:province":"East Sussex",
    "sg:tags":[
        "graphic",
        "designer"
    ],
    "wof:name":"Ian Hunt Design",
    "wof:placetype":"venue"
},
  "geometry": {"coordinates":[-0.183443,50.828224],"type":"Point"}
}