{
  "type": "Feature",
  "properties": {
    "iso:country":"GB",
    "sg:address":"15 Martingale Road",
    "sg:city":"Bristol",
    "sg:classifiers":[
        {
            "category":"Building & Trades",
            "subcategory":"Landscaping Services",
            "type":"Services"
        }
    ],
    "sg:postcode":"BS4 3RB",
    "sg:province":"City of Bristol",
    "sg:tags":[
        "landscape",
        "contractor"
    ],
    "wof:name":"Phoenix Landscaping",
    "wof:placetype":"venue"
},
  "geometry": {"coordinates":[-2.555055,51.443302],"type":"Point"}
}