{
  "type": "Feature",
  "properties": {
    "iso:country":"GB",
    "sg:address":"Coronation Park, Park Road",
    "sg:city":"Ormskirk",
    "sg:classifiers":[
        {
            "category":"Government",
            "subcategory":"Office",
            "type":"Public Place"
        },
        {
            "category":"Sports & Exercise",
            "subcategory":"Swimming Pool",
            "type":"Entertainment"
        }
    ],
    "sg:phone":"+44 1695 576325",
    "sg:postcode":"L39 3BY",
    "sg:province":"Lancashire",
    "sg:tags":[
        "local"
    ],
    "wof:name":"The Park Pool",
    "wof:placetype":"venue"
},
  "geometry": {"coordinates":[-2.8863,53.566277],"type":"Point"}
}