{
  "type": "Feature",
  "properties": {
    "iso:country":"GB",
    "sg:address":"Far Lane",
    "sg:city":"Sheffield",
    "sg:classifiers":[
        {
            "category":"Organizations",
            "subcategory":"Community Association",
            "type":"Services"
        },
        {
            "category":"Organizations",
            "subcategory":"Membership Organization",
            "type":"Services"
        }
    ],
    "sg:phone":"+44 114 234 4177",
    "sg:postcode":"S6 4FF",
    "sg:province":"South Yorkshire",
    "sg:tags":[
        "club",
        "social"
    ],
    "wof:name":"DIAL HOUSE SPORTS & SOCIAL CLUB",
    "wof:placetype":"venue"
},
  "geometry": {"coordinates":[-1.5078,53.409569],"type":"Point"}
}