{
  "type": "Feature",
  "properties": {
    "addr:full":"20 New Street, Stonehouse Larkhall South Lanarkshire ML9 3LT",
    "addr:housenumber":"20",
    "addr:postcode":"ml9 3lt",
    "addr:street":"New Street",
    "iso:country":"GB",
    "sg:address":"20 New Street, Stonehouse",
    "sg:city":"Larkhall",
    "sg:classifiers":[
        {
            "category":"Building & Trades",
            "subcategory":"Construction",
            "type":"Services"
        }
    ],
    "sg:phone":"+44 1698 791046",
    "sg:postcode":"ML9 3LT",
    "sg:province":"South Lanarkshire",
    "sg:tags":[
        "window",
        "replacement"
    ],
    "wof:name":"Top Grade Windows Ltd.",
    "wof:placetype":"venue"
},
  "geometry": {"coordinates":[-3.98044,55.698742],"type":"Point"}
}