{
  "type": "Feature",
  "properties": {
    "addr:full":"67-71 Widnes Road Widnes Cheshire WA8 6AZ",
    "addr:housenumber":"67-71",
    "addr:postcode":"wa8 6az",
    "addr:street":"Widnes Road",
    "iso:country":"GB",
    "sg:address":"67-71 Widnes Road",
    "sg:city":"Widnes",
    "sg:classifiers":[
        {
            "category":"Shopping",
            "subcategory":"Thrift Store",
            "type":"Retail Goods"
        }
    ],
    "sg:phone":"+44 151 423 4429",
    "sg:postcode":"WA8 6AZ",
    "sg:province":"Cheshire",
    "sg:tags":[
        "shop",
        "charity"
    ],
    "wof:name":"Imperial Cancer Research Fund",
    "wof:placetype":"venue"
},
  "geometry": {"coordinates":[-2.727699995,53.3668937683],"type":"Point"}
}