{
  "type": "Feature",
  "properties": {
    "addr:full":"Hill Farm, Elmbridge Droitwich Worcestershire WR9 0DB",
    "addr:postcode":"wr9 0db",
    "addr:street":"Hill",
    "iso:country":"GB",
    "sg:address":"Hill Farm, Elmbridge",
    "sg:city":"Droitwich",
    "sg:classifiers":[
        {
            "category":"Farming",
            "subcategory":"Livestock Farm",
            "type":"Manufacturing & Wholesale Goods"
        }
    ],
    "sg:postcode":"WR9 0DB",
    "sg:province":"Worcestershire",
    "sg:tags":[
        "others"
    ],
    "wof:name":"W B Cartwright",
    "wof:placetype":"venue"
},
  "geometry": {"coordinates":[-2.200128,52.274284],"type":"Point"}
}