{
  "type": "Feature",
  "properties": {
    "addr:full":"4 Newark Close, Shepshed Loughborough Leicestershire LE12 9PJ",
    "addr:housenumber":"4",
    "addr:postcode":"le12 9pj",
    "addr:street":"Newark Close",
    "iso:country":"GB",
    "sg:address":"4 Newark Close, Shepshed",
    "sg:city":"Loughborough",
    "sg:classifiers":[
        {
            "category":"Manufacturing",
            "subcategory":"Petroleum Products",
            "type":"Manufacturing & Wholesale Goods"
        },
        {
            "category":"Building & Trades",
            "subcategory":"Construction",
            "type":"Services"
        }
    ],
    "sg:phone":"+44 1509 502517",
    "sg:postcode":"LE12 9PJ",
    "sg:province":"Leicestershire",
    "sg:tags":[
        "double",
        "glazing",
        "installers"
    ],
    "wof:name":"Adams Executive Windows",
    "wof:placetype":"venue"
},
  "geometry": {"coordinates":[-1.3054939508,52.7678451538],"type":"Point"}
}