{
  "type": "Feature",
  "properties": {
    "addr:full":"73-75 Barnsley Road, South Elmsall Pontefract West Yorkshire WF9 2QW",
    "addr:housenumber":"73-75",
    "addr:postcode":"wf9 2qw",
    "addr:street":"Barnsley Road South;Pontefract West",
    "iso:country":"GB",
    "sg:address":"73-75 Barnsley Road, South Elmsall",
    "sg:city":"Pontefract",
    "sg:classifiers":[
        {
            "category":"Wholesale",
            "subcategory":"Construction Materials",
            "type":"Manufacturing & Wholesale Goods"
        }
    ],
    "sg:phone":"+44 1977 642667",
    "sg:postcode":"WF9 2QW",
    "sg:province":"West Yorkshire",
    "sg:tags":[
        "merchant",
        "glass"
    ],
    "wof:name":"Shackeltons",
    "wof:placetype":"venue"
},
  "geometry": {"coordinates":[-1.292526,53.594803],"type":"Point"}
}