{
  "type": "Feature",
  "properties": {
    "addr:full":"1st Floor, 151a Sydney Street London Greater London SW3 6NT",
    "addr:housenumber":"151a",
    "addr:postcode":"sw3 6nt",
    "addr:street":"Sydney Street",
    "iso:country":"GB",
    "sg:address":"1st Floor, 151a Sydney Street",
    "sg:city":"London",
    "sg:classifiers":[
        {
            "category":"Wholesale",
            "subcategory":"Apparel",
            "type":"Manufacturing & Wholesale Goods"
        }
    ],
    "sg:phone":"+44 20 7460 1268",
    "sg:postcode":"SW3 6NT",
    "sg:province":"Greater London",
    "sg:tags":[
        "w'sale",
        "ladieswear"
    ],
    "wof:name":"Anne Storey Clothing Ltd.",
    "wof:placetype":"venue"
},
  "geometry": {"coordinates":[-0.168689,51.48745],"type":"Point"}
}