{
  "type": "Feature",
  "properties": {
    "iso:country":"GB",
    "sg:address":"Grange Lodge, Felcourt Rd, Felcourt",
    "sg:city":"East Grinstead",
    "sg:classifiers":[
        {
            "category":"Professional",
            "type":"Services"
        }
    ],
    "sg:phone":"+44 1342 870606",
    "sg:postcode":"RH19 2LA",
    "sg:province":"East Sussex",
    "sg:tags":[
        "interior",
        "furnishers",
        "designer"
    ],
    "wof:name":"The White House of Interior Design",
    "wof:placetype":"venue"
},
  "geometry": {"coordinates":[-0.0232190005,51.1599693298],"type":"Point"}
}