{
  "type": "Feature",
  "properties": {
    "addr:full":"Church Hill Centre, Loxley Close Redditch Warwickshire B98 9JG",
    "addr:postcode":"b98 9jg",
    "addr:street":"Church Hill Centre Loxley Close",
    "iso:country":"GB",
    "sg:address":"Church Hill Centre, Loxley Close",
    "sg:city":"Redditch",
    "sg:classifiers":[
        {
            "category":"Government",
            "subcategory":"Post Office",
            "type":"Public Place"
        }
    ],
    "sg:phone":"+44 1527 694189",
    "sg:postcode":"B98 9JG",
    "sg:province":"Warwickshire",
    "wof:name":"Church Hill Post Office",
    "wof:placetype":"venue"
},
  "geometry": {"coordinates":[-1.905384,52.324024],"type":"Point"}
}