{
  "type": "Feature",
  "properties": {
    "addr:full":"Aldermoor Way, Longwell Green Bristol Gloucestershire BS30 7DA",
    "addr:postcode":"bs30 7da",
    "addr:street":"Aldermoor Way",
    "iso:country":"GB",
    "sg:address":"Aldermoor Way, Longwell Green",
    "sg:city":"Bristol",
    "sg:classifiers":[
        {
            "category":"Freight",
            "type":"Transportation"
        }
    ],
    "sg:phone":"+44 117 961 5213",
    "sg:postcode":"BS30 7DA",
    "sg:province":"Gloucestershire",
    "sg:tags":[
        "forwarders"
    ],
    "wof:name":"Atlasair",
    "wof:placetype":"venue"
},
  "geometry": {"coordinates":[-2.498159,51.446594],"type":"Point"}
}