{
  "type": "Feature",
  "properties": {
    "iso:country":"GB",
    "sg:address":"63-65 High Street",
    "sg:city":"Droitwich",
    "sg:classifiers":[
        {
            "category":"Professional",
            "subcategory":"Advertising",
            "type":"Services"
        }
    ],
    "sg:phone":"+44 1905 775645",
    "sg:postcode":"WR9 8EP",
    "sg:province":"Worcestershire",
    "sg:tags":[
        "agency"
    ],
    "wof:name":"Concept",
    "wof:placetype":"venue"
},
  "geometry": {"coordinates":[-2.1463840008,52.2682991028],"type":"Point"}
}