{
  "type": "Feature",
  "properties": {
    "iso:country":"GB",
    "sg:address":"36a Leicester Road",
    "sg:city":"Loughborough",
    "sg:classifiers":[
        {
            "category":"Shopping",
            "subcategory":"Clothing, Apparel, & Fashions",
            "type":"Retail Goods"
        }
    ],
    "sg:phone":"+44 1509 263665",
    "sg:postcode":"LE11 2AG",
    "sg:province":"Leicestershire",
    "sg:tags":[
        "shop"
    ],
    "wof:name":"Elisabeth's",
    "wof:placetype":"venue"
},
  "geometry": {"coordinates":[-1.20237,52.769444],"type":"Point"}
}