{
  "type": "Feature",
  "properties": {
    "addr:full":"Eastend Farm, Lanark Road, Carstairs Lanark South Lanarkshire ML11 8QG",
    "addr:postcode":"ml11 8qg",
    "addr:street":"Lanark Road",
    "iso:country":"GB",
    "sg:address":"Eastend Farm, Lanark Road, Carstairs",
    "sg:city":"Lanark",
    "sg:classifiers":[
        {
            "category":"Manufacturing",
            "subcategory":"Building Materials",
            "type":"Manufacturing & Wholesale Goods"
        }
    ],
    "sg:phone":"+44 1555 870747",
    "sg:postcode":"ML11 8QG",
    "sg:province":"South Lanarkshire",
    "sg:tags":[
        "stonemason"
    ],
    "wof:name":"A Steele",
    "wof:placetype":"venue"
},
  "geometry": {"coordinates":[-3.6927499771,55.6958961487],"type":"Point"}
}