{
  "type": "Feature",
  "properties": {
    "addr:full":"Ark Cottage, Cricklade Swindon Gloucestershire SN6 6HU",
    "addr:housenumber":"cricklade",
    "addr:postcode":"sn6 6hu",
    "iso:country":"GB",
    "sg:address":"Ark Cottage, Cricklade",
    "sg:city":"Swindon",
    "sg:classifiers":[
        {
            "category":"Professional",
            "subcategory":"Engineering",
            "type":"Services"
        }
    ],
    "sg:postcode":"SN6 6HU",
    "sg:province":"Gloucestershire",
    "sg:tags":[
        "consulting",
        "engineer"
    ],
    "wof:name":"Gwelo Strategies Ltd.",
    "wof:placetype":"venue"
},
  "geometry": {"coordinates":[-1.8569899797,51.6400489807],"type":"Point"}
}