{
  "type": "Feature",
  "properties": {
    "iso:country":"GB",
    "sg:address":"12 Doncaster Gate",
    "sg:city":"Rotherham",
    "sg:classifiers":[
        {
            "category":"Personal",
            "subcategory":"Beauty Salon",
            "type":"Services"
        }
    ],
    "sg:postcode":"S65 1DJ",
    "sg:province":"South Yorkshire",
    "sg:tags":[
        "unisex",
        "hairdresser"
    ],
    "wof:name":"Tsunami",
    "wof:placetype":"venue"
},
  "geometry": {"coordinates":[-1.35375,53.430763],"type":"Point"}
}