{
  "type": "Feature",
  "properties": {
    "iso:country":"GB",
    "sg:address":"3 Drury Close, Waltham",
    "sg:city":"Grimsby",
    "sg:classifiers":[
        {
            "category":"Retail",
            "subcategory":"Driving School",
            "type":"Services"
        }
    ],
    "sg:postcode":"DN37 0XP",
    "sg:province":"Lincolnshire",
    "wof:name":"Academy School of Motoring",
    "wof:placetype":"venue"
},
  "geometry": {"coordinates":[-0.1161290035,53.5176773071],"type":"Point"}
}