{
  "type": "Feature",
  "properties": {
    "iso:country":"GB",
    "sg:address":"Unit 8 & 23, Sweetmans Yard, Plough Lane",
    "sg:city":"Hereford",
    "sg:classifiers":[
        {
            "category":"Retail",
            "subcategory":"Auto Repair",
            "type":"Services"
        },
        {
            "category":"Sports & Exercise",
            "subcategory":"Tennis Court",
            "type":"Entertainment"
        }
    ],
    "sg:phone":"+44 1432 357449",
    "sg:postcode":"HR4 0EE",
    "sg:province":"Herefordshire",
    "sg:tags":[
        "breakdown",
        "recovery",
        "car",
        "commercial",
        "garage",
        "vehicle",
        "modification"
    ],
    "wof:name":"B V Recovery",
    "wof:placetype":"venue"
},
  "geometry": {"coordinates":[-2.72881,52.058731],"type":"Point"}
}