{
  "type": "Feature",
  "properties": {
    "iso:country":"GB",
    "sg:address":"Royal Devon & Exeter Hospital, Barrack Road",
    "sg:city":"Exeter",
    "sg:classifiers":[
        {
            "category":"Health Services",
            "subcategory":"Hospital",
            "type":"Services"
        }
    ],
    "sg:phone":"+44 1392 411611",
    "sg:postcode":"EX2 5DW",
    "sg:province":"Devon",
    "wof:name":"Royal Devon & Exeter Healthcare N H S Trust",
    "wof:placetype":"venue"
},
  "geometry": {"coordinates":[-3.50673,50.716648],"type":"Point"}
}