{
  "type": "Feature",
  "properties": {
    "addr:full":"30 Lathom Rd Southport Lancashire PR9 0JP",
    "addr:housenumber":"30",
    "addr:postcode":"pr9 0jp",
    "addr:street":"Lathom Rd",
    "iso:country":"GB",
    "sg:address":"30 Lathom Rd",
    "sg:city":"Southport",
    "sg:classifiers":[
        {
            "category":"Travel",
            "subcategory":"Hotels & Motels",
            "type":"Entertainment"
        }
    ],
    "sg:phone":"+44 1704 530223",
    "sg:postcode":"PR9 0JP",
    "sg:province":"Lancashire",
    "wof:name":"The Fraser House Hotel",
    "wof:placetype":"venue"
},
  "geometry": {"coordinates":[-2.9971940517,53.6581230164],"type":"Point"}
}