{
  "type": "Feature",
  "properties": {
    "iso:country":"GB",
    "sg:address":"79 Fowler St",
    "sg:city":"South Shields",
    "sg:classifiers":[
        {
            "category":"Manufacturing",
            "subcategory":"Textiles",
            "type":"Manufacturing & Wholesale Goods"
        }
    ],
    "sg:phone":"+44 191 496 7953",
    "sg:postcode":"NE33 1NT",
    "sg:province":"Tyne and Wear",
    "sg:tags":[
        "made-up"
    ],
    "wof:name":"Mattress Warehouse",
    "wof:placetype":"venue"
},
  "geometry": {"coordinates":[-1.4303809404,54.9966697693],"type":"Point"}
}