{
  "type": "Feature",
  "properties": {
    "iso:country":"GB",
    "sg:address":"157 Cherry Hinton Road",
    "sg:city":"Cambridge",
    "sg:classifiers":[
        {
            "category":"Shopping",
            "subcategory":"Bicycles & Sporting Goods",
            "type":"Retail Goods"
        },
        {
            "category":"Arts & Performance",
            "subcategory":"Theater",
            "type":"Entertainment"
        }
    ],
    "sg:phone":"+44 1223 245866",
    "sg:postcode":"CB1 7BX",
    "sg:province":"Cambridgeshire",
    "sg:tags":[
        "dance",
        "dancewear",
        "ballet",
        "balletwear"
    ],
    "wof:name":"Scissors Haircare & Dancewear",
    "wof:placetype":"venue"
},
  "geometry": {"coordinates":[0.1441379935,52.1882171631],"type":"Point"}
}