{
  "type": "Feature",
  "properties": {
    "iso:country":"GB",
    "sg:address":"11 Devon Sq",
    "sg:city":"Newton Abbot",
    "sg:classifiers":[
        {
            "category":"Place Of Worship",
            "type":"Public Place"
        }
    ],
    "sg:phone":"+44 1626 353423",
    "sg:postcode":"TQ12 2HN",
    "sg:province":"Devon",
    "wof:name":"Convent Of The Holy Ghost",
    "wof:placetype":"venue"
},
  "geometry": {"coordinates":[-3.603103,50.529675],"type":"Point"}
}