{
  "type": "Feature",
  "properties": {
    "iso:country":"GB",
    "sg:address":"Unit 23a, Pant Industrial Estate, Dowlais",
    "sg:city":"Merthyr Tydfil",
    "sg:classifiers":[
        {
            "category":"Manufacturing",
            "subcategory":"Metals",
            "type":"Manufacturing & Wholesale Goods"
        },
        {
            "category":"Professional",
            "subcategory":"Art Services",
            "type":"Services"
        }
    ],
    "sg:phone":"+44 1685 723677",
    "sg:postcode":"CF48 2SR",
    "sg:province":"Caerphilly",
    "sg:tags":[
        "polishing",
        "finishing"
    ],
    "wof:name":"Merthyr Electro-Plating Co. Ltd.",
    "wof:placetype":"venue"
},
  "geometry": {"coordinates":[-3.3658139706,51.7676315308],"type":"Point"}
}