{
  "type": "Feature",
  "properties": {
    "iso:country":"GB",
    "sg:address":"12 Eldon St North",
    "sg:city":"Barnsley",
    "sg:classifiers":[
        {
            "category":"Insurance",
            "subcategory":"Insurance Agent",
            "type":"Services"
        }
    ],
    "sg:postcode":"S71 1LG",
    "sg:province":"South Yorkshire",
    "wof:name":"Swinton",
    "wof:placetype":"venue"
},
  "geometry": {"coordinates":[-1.47738,53.55653],"type":"Point"}
}