{
  "type": "Feature",
  "properties": {
    "addr:full":"Commercial Road, Porthleven Helston Cornwall TR13 9JD",
    "addr:postcode":"tr13 9jd",
    "addr:street":"Commercial Road",
    "iso:country":"GB",
    "sg:address":"Commercial Road, Porthleven",
    "sg:city":"Helston",
    "sg:classifiers":[
        {
            "category":"Ice Cream",
            "type":"Food & Drink"
        }
    ],
    "sg:phone":"+44 1326 573747",
    "sg:postcode":"TR13 9JD",
    "sg:province":"Cornwall",
    "sg:tags":[
        "shop",
        "mobile",
        "parlour"
    ],
    "wof:name":"Nauti But Ice",
    "wof:placetype":"venue"
},
  "geometry": {"coordinates":[-5.313275,50.086704],"type":"Point"}
}