{
  "type": "Feature",
  "properties": {
    "addr:full":"Shipdham Road, Toftwood Dereham Norfolk NR19 1NP",
    "addr:postcode":"nr19 1np",
    "addr:street":"Shipdham Road Toftwood Dereham",
    "iso:country":"GB",
    "sg:address":"Shipdham Road, Toftwood",
    "sg:city":"Dereham",
    "sg:classifiers":[
        {
            "category":"Food & Beverages",
            "subcategory":"Farmers Market",
            "type":"Retail Goods"
        }
    ],
    "sg:postcode":"NR19 1NP",
    "sg:province":"Norfolk",
    "sg:tags":[
        "gardener"
    ],
    "wof:name":"J E Anema",
    "wof:placetype":"venue"
},
  "geometry": {"coordinates":[0.9455890059,52.6801681519],"type":"Point"}
}