{
  "type": "Feature",
  "properties": {
    "iso:country":"GB",
    "sg:address":"26 Roberts Avenue, Huthwaite",
    "sg:city":"Sutton-in-ashfield",
    "sg:classifiers":[
        {
            "category":"Retail",
            "subcategory":"Driving School",
            "type":"Services"
        }
    ],
    "sg:phone":"+44 1623 559035",
    "sg:postcode":"NG17 2JP",
    "sg:province":"Nottinghamshire",
    "wof:name":"Alison Moore School Of Motoring",
    "wof:placetype":"venue"
},
  "geometry": {"coordinates":[-1.299849,53.122505],"type":"Point"}
}