{
  "type": "Feature",
  "properties": {
    "iso:country":"GB",
    "sg:address":"9 Wakefield, Swillington",
    "sg:city":"Leeds",
    "sg:classifiers":[
        {
            "category":"Taxi",
            "type":"Transportation"
        },
        {
            "category":"Military Area",
            "subcategory":"Air Force Base",
            "type":"Public Place"
        }
    ],
    "sg:phone":"+44 113 287 7776",
    "sg:postcode":"LS26 8UT",
    "sg:province":"West Yorkshire",
    "sg:tags":[
        "mini",
        "hire",
        "private",
        "cab"
    ],
    "wof:name":"P J's Cars",
    "wof:placetype":"venue"
},
  "geometry": {"coordinates":[-1.4528340101,53.744102478],"type":"Point"}
}