{
  "type": "Feature",
  "properties": {
    "addr:full":"Unit 7, Marlborough Wks, Archway Rd Luton Bedfordshire LU3 2QZ",
    "addr:housenumber":"unit 7",
    "addr:postcode":"lu3 2qz",
    "addr:street":"Wks Archway Rd",
    "iso:country":"GB",
    "sg:address":"Unit 7, Marlborough Wks, Archway Rd",
    "sg:city":"Luton",
    "sg:classifiers":[
        {
            "category":"Manufacturing",
            "subcategory":"Metals",
            "type":"Manufacturing & Wholesale Goods"
        }
    ],
    "sg:phone":"+44 1582 494844",
    "sg:postcode":"LU3 2QZ",
    "sg:province":"Bedfordshire",
    "sg:tags":[
        "product",
        "fabricated"
    ],
    "wof:name":"B & N Fabrications",
    "wof:placetype":"venue"
},
  "geometry": {"coordinates":[-0.45287,51.903629],"type":"Point"}
}