{
  "type": "Feature",
  "properties": {
    "iso:country":"GB",
    "sg:address":"Stanfield House, 447 Warwick Road, Tyseley",
    "sg:city":"Birmingham",
    "sg:classifiers":[
        {
            "category":"Education",
            "subcategory":"School",
            "type":"Public Place"
        }
    ],
    "sg:phone":"+44 121 764 5373",
    "sg:postcode":"B11 2JR",
    "sg:province":"West Midlands",
    "sg:tags":[
        "independent",
        "preparatory"
    ],
    "wof:name":"Al-Furqan School",
    "wof:placetype":"venue"
},
  "geometry": {"coordinates":[-1.851233,52.452923],"type":"Point"}
}