{
  "type": "Feature",
  "properties": {
    "iso:country":"GB",
    "sg:address":"Coltman Avenue Clinic, Coltman Av",
    "sg:city":"Beverley",
    "sg:classifiers":[
        {
            "category":"Health Services",
            "subcategory":"Clinic",
            "type":"Services"
        }
    ],
    "sg:phone":"+44 1482 869200",
    "sg:postcode":"HU17 9LP",
    "sg:province":"East Riding of Yorkshire",
    "sg:tags":[
        "nh"
    ],
    "wof:name":"East Yorkshire Community Health Care",
    "wof:placetype":"venue"
},
  "geometry": {"coordinates":[-0.4218550026,53.850063324],"type":"Point"}
}