{
  "type": "Feature",
  "properties": {
    "addr:full":"8 Gordon Place Kensington Greater London W8 4JD",
    "addr:housenumber":"8",
    "addr:postcode":"w8 4jd",
    "addr:street":"Gordon Place",
    "iso:country":"GB",
    "sg:address":"8 Gordon Place",
    "sg:city":"Kensington",
    "sg:classifiers":[
        {
            "category":"Professional",
            "subcategory":"Computer Services",
            "type":"Services"
        }
    ],
    "sg:phone":"+44 20 7376 9601",
    "sg:postcode":"W8 4JD",
    "sg:province":"Greater London",
    "sg:tags":[
        "system",
        "software"
    ],
    "wof:name":"Gavin Lavelle",
    "wof:placetype":"venue"
},
  "geometry": {"coordinates":[-0.1947119981,51.5038223267],"type":"Point"}
}