{
  "type": "Feature",
  "properties": {
    "iso:country":"GB",
    "sg:address":"5a Standhill Road, Carlton",
    "sg:city":"Nottingham",
    "sg:classifiers":[
        {
            "category":"Manufacturing",
            "subcategory":"Petroleum Products",
            "type":"Manufacturing & Wholesale Goods"
        }
    ],
    "sg:phone":"+44 115 911 9998",
    "sg:postcode":"NG4 1JL",
    "sg:province":"Nottinghamshire",
    "sg:tags":[
        "double",
        "glazing"
    ],
    "wof:name":"Eurostyle Windows Ltd.",
    "wof:placetype":"venue"
},
  "geometry": {"coordinates":[-1.111946,52.966553],"type":"Point"}
}