{
  "type": "Feature",
  "properties": {
    "iso:country":"GB",
    "sg:address":"Harbour Office South Quay, Ferryden",
    "sg:city":"Montrose",
    "sg:classifiers":[
        {
            "category":"Professional",
            "type":"Services"
        }
    ],
    "sg:postcode":"DD10 9SL",
    "sg:province":"Aberdeenshire",
    "sg:tags":[
        "marine"
    ],
    "wof:name":"Stennes Maritime Uk Ltd.",
    "wof:placetype":"venue"
},
  "geometry": {"coordinates":[-2.461344,56.701248],"type":"Point"}
}