{
  "type": "Feature",
  "properties": {
    "addr:full":"Block 5 Glengarnock Steelworks, Glengarnock Beith North Ayrshire KA14 3DA",
    "addr:postcode":"ka14 3da",
    "addr:street":"Glengarnock;Glengarnock",
    "iso:country":"GB",
    "sg:address":"Block 5 Glengarnock Steelworks, Glengarnock",
    "sg:city":"Beith",
    "sg:classifiers":[
        {
            "category":"Building & Trades",
            "subcategory":"Landscaping Services",
            "type":"Services"
        }
    ],
    "sg:phone":"+44 1505 684888",
    "sg:postcode":"KA14 3DA",
    "sg:province":"North Ayrshire",
    "sg:tags":[
        "steel"
    ],
    "wof:name":"Ryeside Construction Ltd.",
    "wof:placetype":"venue"
},
  "geometry": {"coordinates":[-4.675038,55.739285],"type":"Point"}
}