{
  "type": "Feature",
  "properties": {
    "addr:full":"Argyle Road Whitby North Yorkshire YO21 3HS",
    "addr:postcode":"yo21 3hs",
    "addr:street":"Argyle Road",
    "iso:country":"GB",
    "sg:address":"Argyle Road",
    "sg:city":"Whitby",
    "sg:classifiers":[
        {
            "category":"Autos & Motor Vehicles",
            "subcategory":"Automobile Sales",
            "type":"Retail Goods"
        }
    ],
    "sg:phone":"+44 1947 604719",
    "sg:postcode":"YO21 3HS",
    "sg:province":"North Yorkshire",
    "sg:tags":[
        "car",
        "used"
    ],
    "wof:name":"Argyle Garage",
    "wof:placetype":"venue"
},
  "geometry": {"coordinates":[-0.6250290275,54.490070343],"type":"Point"}
}