{
  "type": "Feature",
  "properties": {
    "addr:full":"48 Main Street Campbeltown Argyll and Bute PA28 6AD",
    "addr:housenumber":"48",
    "addr:postcode":"pa28 6ad",
    "addr:street":"Main Street",
    "iso:country":"GB",
    "sg:address":"48 Main Street",
    "sg:city":"Campbeltown",
    "sg:classifiers":[
        {
            "category":"Shopping",
            "subcategory":"Party Supplies",
            "type":"Retail Goods"
        },
        {
            "category":"Shopping",
            "subcategory":"Gifts & Souvenirs",
            "type":"Retail Goods"
        }
    ],
    "sg:phone":"+44 1586 552699",
    "sg:postcode":"PA28 6AD",
    "sg:province":"Argyll and Bute",
    "sg:tags":[
        "shop",
        "novelty"
    ],
    "wof:name":"D M Brown",
    "wof:placetype":"venue"
},
  "geometry": {"coordinates":[-5.6056962013,55.42420578],"type":"Point"}
}