{
  "type": "Feature",
  "properties": {
    "iso:country":"GB",
    "sg:address":"180 Haverstock Hill, Belsize Park",
    "sg:city":"London",
    "sg:classifiers":[
        {
            "category":"Organizations",
            "subcategory":"Non-profit Organization",
            "type":"Services"
        }
    ],
    "sg:phone":"+44 20 7431 3634",
    "sg:postcode":"NW3 2AL",
    "sg:province":"Greater London",
    "sg:tags":[
        "charitable",
        "organisation",
        "voluntary",
        "charity"
    ],
    "sg:website":"http://www.umbrella.org.uk",
    "wof:name":"Umbrella",
    "wof:placetype":"venue"
},
  "geometry": {"coordinates":[-0.1547240019,51.5447349548],"type":"Point"}
}