{
  "type": "Feature",
  "properties": {
    "iso:country":"GB",
    "sg:address":"36 Tynewydd Road",
    "sg:city":"Rhyl",
    "sg:classifiers":[
        {
            "category":"Home & Garden",
            "subcategory":"Hardware",
            "type":"Retail Goods"
        }
    ],
    "sg:phone":"+44 1745 355066",
    "sg:postcode":"LL18 3SP",
    "sg:province":"Conwy",
    "sg:tags":[
        "equipment",
        "central",
        "heating"
    ],
    "wof:name":"Chas Appliance Spares",
    "wof:placetype":"venue"
},
  "geometry": {"coordinates":[-3.4717140198,53.3267021179],"type":"Point"}
}