{
  "type": "Feature",
  "properties": {
    "addr:full":"10-12 Campbell Street Dunfermline Fife KY12 0QJ",
    "addr:housenumber":"10-12",
    "addr:postcode":"ky12 0qj",
    "addr:street":"Campbell Street",
    "iso:country":"GB",
    "sg:address":"10-12 Campbell Street",
    "sg:city":"Dunfermline",
    "sg:classifiers":[
        {
            "category":"Building & Trades",
            "subcategory":"Plumbing",
            "type":"Services"
        }
    ],
    "sg:postcode":"KY12 0QJ",
    "sg:province":"Fife",
    "sg:tags":[
        "heating"
    ],
    "wof:name":"Inglis James & Son",
    "wof:placetype":"venue"
},
  "geometry": {"coordinates":[-3.461135,56.074749],"type":"Point"}
}