{
  "type": "Feature",
  "properties": {
    "iso:country":"GB",
    "sg:address":"Victoria Square",
    "sg:city":"Aberdare",
    "sg:classifiers":[
        {
            "category":"Food & Beverages",
            "subcategory":"Meat & Fish",
            "type":"Retail Goods"
        }
    ],
    "sg:phone":"+44 1685 872062",
    "sg:postcode":"CF44 7LA",
    "sg:province":"Neath Port Talbot",
    "sg:tags":[
        "butcher"
    ],
    "wof:name":"H Woodley & Co. Ltd.",
    "wof:placetype":"venue"
},
  "geometry": {"coordinates":[-3.444319,51.712952],"type":"Point"}
}