{
  "type": "Feature",
  "properties": {
    "addr:full":"186 Hungerford Rd Crewe Cheshire CW1 1EJ",
    "addr:housenumber":"186",
    "addr:postcode":"cw1 1ej",
    "addr:street":"Hungerford Rd",
    "iso:country":"GB",
    "sg:address":"186 Hungerford Rd",
    "sg:city":"Crewe",
    "sg:classifiers":[
        {
            "category":"Health Services",
            "subcategory":"Dentist",
            "type":"Services"
        }
    ],
    "sg:phone":"+44 1270 581024",
    "sg:postcode":"CW1 1EJ",
    "sg:province":"Cheshire",
    "wof:name":"Allen House Dental Practice",
    "wof:placetype":"venue"
},
  "geometry": {"coordinates":[-2.429757,53.097458],"type":"Point"}
}