{
  "type": "Feature",
  "properties": {
    "addr:full":"15 New Street Cheltenham Gloucestershire GL50 3LN",
    "addr:housenumber":"15",
    "addr:postcode":"gl50 3ln",
    "addr:street":"New Street",
    "iso:country":"GB",
    "sg:address":"15 New Street",
    "sg:city":"Cheltenham",
    "sg:classifiers":[
        {
            "category":"Personal",
            "subcategory":"Beauty Salon",
            "type":"Services"
        }
    ],
    "sg:phone":"+44 1242 523105",
    "sg:postcode":"GL50 3LN",
    "sg:province":"Gloucestershire",
    "sg:tags":[
        "unisex",
        "ladies",
        "hairdresser"
    ],
    "wof:name":"Roderick Hair Fashions",
    "wof:placetype":"venue"
},
  "geometry": {"coordinates":[-2.079744,51.902946],"type":"Point"}
}