{
  "type": "Feature",
  "properties": {
    "iso:country":"GB",
    "sg:address":"1925 Warwick Road, Knowle",
    "sg:city":"Solihull",
    "sg:classifiers":[
        {
            "category":"Building & Trades",
            "subcategory":"Landscaping Services",
            "type":"Services"
        }
    ],
    "sg:phone":"+44 1564 773296",
    "sg:postcode":"B93 0DX",
    "sg:province":"Warwickshire",
    "sg:tags":[
        "forestry",
        "surgeon",
        "tree"
    ],
    "wof:name":"Arden Nurseries",
    "wof:placetype":"venue"
},
  "geometry": {"coordinates":[-1.732558,52.378796],"type":"Point"}
}