{
  "type": "Feature",
  "properties": {
    "addr:full":"16 Peel Precinct, Canterbury Road London Greater London NW6 5BS",
    "addr:housenumber":"16",
    "addr:postcode":"nw6 5bs",
    "addr:street":"Peel Precinct Canterbury Road",
    "iso:country":"GB",
    "sg:address":"16 Peel Precinct, Canterbury Road",
    "sg:city":"London",
    "sg:classifiers":[
        {
            "category":"Fast Food",
            "type":"Food & Drink"
        }
    ],
    "sg:phone":"+44 20 7328 0240",
    "sg:postcode":"NW6 5BS",
    "sg:province":"Greater London",
    "sg:tags":[
        "away",
        "take"
    ],
    "wof:name":"Good Food Takeaway",
    "wof:placetype":"venue"
},
  "geometry": {"coordinates":[-0.1985819936,51.5332221985],"type":"Point"}
}