{
  "type": "Feature",
  "properties": {
    "addr:full":"72 Barrington Road Altrincham Cheshire WA14 1JB",
    "addr:housenumber":"72",
    "addr:postcode":"wa14 1jb",
    "addr:street":"Barrington Road",
    "iso:country":"GB",
    "sg:address":"72 Barrington Road",
    "sg:city":"Altrincham",
    "sg:classifiers":[
        {
            "category":"Military Area",
            "subcategory":"Air Force Base",
            "type":"Public Place"
        }
    ],
    "sg:phone":"+44 161 928 7777",
    "sg:postcode":"WA14 1JB",
    "sg:province":"Cheshire",
    "sg:tags":[
        "taxi",
        "hire",
        "private"
    ],
    "wof:name":"Lindsell Taxi's",
    "wof:placetype":"venue"
},
  "geometry": {"coordinates":[-2.3511369228,53.3951835632],"type":"Point"}
}