{
  "type": "Feature",
  "properties": {
    "iso:country":"GB",
    "sg:address":"Unit 12, Kingfisher Park, Three Cross Road",
    "sg:city":"Wimborne",
    "sg:classifiers":[
        {
            "category":"Shopping",
            "subcategory":"Computers & Home Electronics",
            "type":"Retail Goods"
        }
    ],
    "sg:postcode":"BH21 6US",
    "sg:province":"Dorset",
    "sg:tags":[
        "electrical"
    ],
    "wof:name":"Gary Duncan Merchanting Ltd.",
    "wof:placetype":"venue"
},
  "geometry": {"coordinates":[-1.8849190474,50.8415412903],"type":"Point"}
}