{
  "type": "Feature",
  "properties": {
    "addr:full":"69 Clayton Street Newcastle-upon-tyne Tyne and Wear NE1 5PY",
    "addr:housenumber":"69",
    "addr:postcode":"ne1 5py",
    "addr:street":"Clayton Street",
    "iso:country":"GB",
    "sg:address":"69 Clayton Street",
    "sg:city":"Newcastle-upon-tyne",
    "sg:classifiers":[
        {
            "category":"Shopping",
            "subcategory":"Gifts & Souvenirs",
            "type":"Retail Goods"
        }
    ],
    "sg:phone":"+44 191 232 3474",
    "sg:postcode":"NE1 5PY",
    "sg:province":"Tyne and Wear",
    "sg:tags":[
        "shop"
    ],
    "wof:name":"Pennystretcher Ltd.",
    "wof:placetype":"venue"
},
  "geometry": {"coordinates":[-1.6166319847,54.9717788696],"type":"Point"}
}