{
  "type": "Feature",
  "properties": {
    "iso:country":"GB",
    "sg:address":"Fontaine, Smallgains Lane, Stock",
    "sg:city":"Ingatestone",
    "sg:classifiers":[
        {
            "category":"Utilities",
            "subcategory":"Refuse",
            "type":"Services"
        },
        {
            "category":"Wholesale",
            "subcategory":"Auto Parts",
            "type":"Manufacturing & Wholesale Goods"
        }
    ],
    "sg:phone":"+44 1277 840446",
    "sg:postcode":"CM4 9PT",
    "sg:province":"Essex",
    "sg:tags":[
        "disposal",
        "breaker",
        "waste",
        "car",
        "retail"
    ],
    "wof:name":"E R I Industrial Division Ltd.",
    "wof:placetype":"venue"
},
  "geometry": {"coordinates":[0.443575,51.664009],"type":"Point"}
}