{
  "type": "Feature",
  "properties": {
    "iso:country":"GB",
    "sg:address":"C/o Bkr Haines Watts, Trident House 31-33 Dale Street",
    "sg:city":"Liverpool",
    "sg:classifiers":[
        {
            "category":"Home & Garden",
            "subcategory":"Household Appliances",
            "type":"Retail Goods"
        }
    ],
    "sg:postcode":"L2 2HF",
    "sg:province":"Merseyside",
    "sg:tags":[
        "cleaner",
        "vacuum"
    ],
    "wof:name":"M.K. Systems Ltd",
    "wof:placetype":"venue"
},
  "geometry": {"coordinates":[-2.988898,53.408028],"type":"Point"}
}