{
  "type": "Feature",
  "properties": {
    "addr:full":"67 Lodge La Bridgnorth Shropshire WV15 5DF",
    "addr:housenumber":"67",
    "addr:postcode":"wv15 5df",
    "addr:street":"Lodge La Bridgnorth",
    "iso:country":"GB",
    "sg:address":"67 Lodge La",
    "sg:city":"Bridgnorth",
    "sg:classifiers":[
        {
            "category":"Food & Beverages",
            "subcategory":"Groceries & Convenience Stores",
            "type":"Retail Goods"
        }
    ],
    "sg:phone":"+44 1746 762608",
    "sg:postcode":"WV15 5DF",
    "sg:province":"Shropshire",
    "wof:name":"Spar Stores",
    "wof:placetype":"venue"
},
  "geometry": {"coordinates":[-2.4068291187,52.5331993103],"type":"Point"}
}