{
  "type": "Feature",
  "properties": {
    "addr:full":"26 Live Court, 4 Grange Road Solihull West Midlands B91 1BL",
    "addr:housenumber":"26;4",
    "addr:postcode":"b91 1bl",
    "addr:street":"Live;Grange Road",
    "iso:country":"GB",
    "sg:address":"26 Live Court, 4 Grange Road",
    "sg:city":"Solihull",
    "sg:classifiers":[
        {
            "category":"Professional",
            "subcategory":"Management & Consulting",
            "type":"Services"
        }
    ],
    "sg:postcode":"B91 1BL",
    "sg:province":"West Midlands",
    "sg:tags":[
        "consultant",
        "business"
    ],
    "wof:name":"Dr Henry Warson",
    "wof:placetype":"venue"
},
  "geometry": {"coordinates":[-1.777849,52.415066],"type":"Point"}
}