{
  "type": "Feature",
  "properties": {
    "addr:full":"6 Reform Street Industrial Estate, Reform Street Sutton-in-ashfield Nottinghamshire NG17 5DB",
    "addr:housenumber":"6",
    "addr:postcode":"estate;ng17 5db",
    "addr:street":"Reform Street Industrial;Reform Street",
    "iso:country":"GB",
    "sg:address":"6 Reform Street Industrial Estate, Reform Street",
    "sg:city":"Sutton-in-ashfield",
    "sg:classifiers":[
        {
            "category":"Manufacturing",
            "subcategory":"Rubber & Plastics",
            "type":"Manufacturing & Wholesale Goods"
        }
    ],
    "sg:phone":"+44 1623 441022",
    "sg:postcode":"NG17 5DB",
    "sg:province":"Nottinghamshire",
    "sg:tags":[
        "injection",
        "moulding"
    ],
    "wof:name":"Central Mouldings Ltd.",
    "wof:placetype":"venue"
},
  "geometry": {"coordinates":[-1.2592699528,53.1224899292],"type":"Point"}
}