{
  "type": "Feature",
  "properties": {
    "addr:full":"66 Studfold Chorley Lancashire PR7 1UB",
    "addr:housenumber":"66",
    "addr:postcode":"pr7 1ub",
    "addr:street":"Studfold",
    "iso:country":"GB",
    "sg:address":"66 Studfold",
    "sg:city":"Chorley",
    "sg:classifiers":[
        {
            "category":"Professional",
            "subcategory":"Engineering",
            "type":"Services"
        },
        {
            "category":"Building & Trades",
            "subcategory":"Electrical",
            "type":"Services"
        }
    ],
    "sg:postcode":"PR7 1UB",
    "sg:province":"Lancashire",
    "sg:tags":[
        "engineer",
        "electrician",
        "contractor"
    ],
    "wof:name":"Mike Griffiths Electrical",
    "wof:placetype":"venue"
},
  "geometry": {"coordinates":[-2.6395049095,53.6634178162],"type":"Point"}
}