{
  "type": "Feature",
  "properties": {
    "iso:country":"GB",
    "sg:address":"6 Stonecrop",
    "sg:city":"Colchester",
    "sg:classifiers":[
        {
            "category":"Professional",
            "subcategory":"Art Services",
            "type":"Services"
        }
    ],
    "sg:phone":"+44 1206 852502",
    "sg:postcode":"CO4 5UG",
    "sg:province":"Essex",
    "sg:tags":[
        "photographer"
    ],
    "wof:name":"Abbey Weddings",
    "wof:placetype":"venue"
},
  "geometry": {"coordinates":[0.882358,51.904385],"type":"Point"}
}