{
  "type": "Feature",
  "properties": {
    "addr:full":"7 Brockley Hill Stanmore Greater London HA7 4LS",
    "addr:housenumber":"7",
    "addr:postcode":"ha7 4ls",
    "addr:street":"Brockley Hill",
    "iso:country":"GB",
    "sg:address":"7 Brockley Hill",
    "sg:city":"Stanmore",
    "sg:classifiers":[
        {
            "category":"Professional",
            "subcategory":"Computer Services",
            "type":"Services"
        }
    ],
    "sg:postcode":"HA7 4LS",
    "sg:province":"Greater London",
    "sg:tags":[
        "system",
        "software"
    ],
    "wof:name":"Technolux Ltd.",
    "wof:placetype":"venue"
},
  "geometry": {"coordinates":[-0.296357,51.62532],"type":"Point"}
}