{
  "type": "Feature",
  "properties": {
    "addr:full":"1500 Stratford Road, Hall Grn Birmingham West Midlands B28 9ET",
    "addr:housenumber":"1500",
    "addr:postcode":"b28 9et",
    "addr:street":"Stratford Road Hall Grn",
    "iso:country":"GB",
    "sg:address":"1500 Stratford Road, Hall Grn",
    "sg:city":"Birmingham",
    "sg:classifiers":[
        {
            "category":"Food & Beverages",
            "subcategory":"Bakery",
            "type":"Retail Goods"
        },
        {
            "category":"Wholesale",
            "subcategory":"Groceries",
            "type":"Manufacturing & Wholesale Goods"
        }
    ],
    "sg:phone":"+44 121 733 1777",
    "sg:postcode":"B28 9ET",
    "sg:province":"West Midlands",
    "sg:tags":[
        "supplier",
        "pizza"
    ],
    "wof:name":"Gino's Dial A Pizza",
    "wof:placetype":"venue"
},
  "geometry": {"coordinates":[-1.8357169628,52.4218215942],"type":"Point"}
}