{
  "type": "Feature",
  "properties": {
    "iso:country":"GB",
    "sg:address":"Proser House, 146-154 Kilburn High Road",
    "sg:city":"Kilburn",
    "sg:classifiers":[
        {
            "category":"Professional",
            "subcategory":"Lawyer & Legal Services",
            "type":"Services"
        }
    ],
    "sg:phone":"+44 20 7625 7301",
    "sg:postcode":"NW6 4JD",
    "sg:province":"Greater London",
    "sg:tags":[
        "solicitor"
    ],
    "wof:name":"Mabarana & Co Solicitors",
    "wof:placetype":"venue"
},
  "geometry": {"coordinates":[-0.197644,51.54163],"type":"Point"}
}