{
  "type": "Feature",
  "properties": {
    "addr:full":"214 Forest Road London Greater London E17 6JG",
    "addr:housenumber":"214",
    "addr:postcode":"e17 6jg",
    "addr:street":"Forest Road",
    "iso:country":"GB",
    "sg:address":"214 Forest Road",
    "sg:city":"London",
    "sg:classifiers":[
        {
            "category":"Government",
            "subcategory":"Post Office",
            "type":"Public Place"
        }
    ],
    "sg:postcode":"E17 6JG",
    "sg:province":"Greater London",
    "sg:tags":[
        "copper",
        "brass"
    ],
    "wof:name":"Designer Brass",
    "wof:placetype":"venue"
},
  "geometry": {"coordinates":[-0.0317200013,51.5884132385],"type":"Point"}
}