{
  "type": "Feature",
  "properties": {
    "iso:country":"GB",
    "sg:address":"High Street, Hermitage",
    "sg:city":"Thatcham",
    "sg:classifiers":[
        {
            "category":"Retail",
            "subcategory":"Auto Repair",
            "type":"Services"
        }
    ],
    "sg:phone":"+44 1635 202401",
    "sg:postcode":"RG18 9SS",
    "sg:province":"Berkshire",
    "sg:tags":[
        "modification",
        "garage"
    ],
    "wof:name":"Hermitage Garage",
    "wof:placetype":"venue"
},
  "geometry": {"coordinates":[-1.271127,51.454067],"type":"Point"}
}