{
  "type": "Feature",
  "properties": {
    "addr:full":"Care Of Daniels 120-125 Peascod St Windsor Berkshire SL4 1DP",
    "addr:housenumber":"120-125",
    "addr:postcode":"sl4 1dp",
    "addr:street":"Peascod St",
    "iso:country":"GB",
    "sg:address":"Care Of Daniels 120-125 Peascod St",
    "sg:city":"Windsor",
    "sg:classifiers":[
        {
            "category":"Shopping",
            "subcategory":"Clothing, Apparel, & Fashions",
            "type":"Retail Goods"
        }
    ],
    "sg:phone":"+44 1753 868762",
    "sg:postcode":"SL4 1DP",
    "sg:province":"Berkshire",
    "sg:tags":[
        "shop"
    ],
    "wof:name":"Lerose Ltd",
    "wof:placetype":"venue"
},
  "geometry": {"coordinates":[-0.612228,51.481735],"type":"Point"}
}