{
  "type": "Feature",
  "properties": {
    "addr:full":"121 Greenlands Road Birmingham West Midlands B37 7XB",
    "addr:housenumber":"121",
    "addr:postcode":"b37 7xb",
    "addr:street":"Greenlands Road",
    "iso:country":"GB",
    "sg:address":"121 Greenlands Road",
    "sg:city":"Birmingham",
    "sg:classifiers":[
        {
            "category":"Autos & Motor Vehicles",
            "subcategory":"Fuel & Gas Station",
            "type":"Retail Goods"
        }
    ],
    "sg:phone":"+44 121 770 5459",
    "sg:postcode":"B37 7XB",
    "sg:province":"West Midlands",
    "sg:tags":[
        "petrol",
        "filling"
    ],
    "wof:name":"Greenlands Service Station",
    "wof:placetype":"venue"
},
  "geometry": {"coordinates":[-1.7209219933,52.4690284729],"type":"Point"}
}