{
  "type": "Feature",
  "properties": {
    "iso:country":"GB",
    "sg:address":"65 Talbot Street",
    "sg:city":"Whitchurch",
    "sg:classifiers":[
        {
            "category":"Shopping",
            "subcategory":"News",
            "type":"Retail Goods"
        }
    ],
    "sg:phone":"+44 1948 667667",
    "sg:postcode":"SY13 1PJ",
    "sg:province":"Cheshire",
    "sg:tags":[
        "newsagent"
    ],
    "wof:name":"Lloyds Newsagents",
    "wof:placetype":"venue"
},
  "geometry": {"coordinates":[-2.674919,52.970146],"type":"Point"}
}