{
  "type": "Feature",
  "properties": {
    "addr:full":"113 Church Road, Hartshill Nuneaton Leicestershire CV10 0LU",
    "addr:housenumber":"113",
    "addr:postcode":"cv10 0lu",
    "addr:street":"Church Road",
    "iso:country":"GB",
    "sg:address":"113 Church Road, Hartshill",
    "sg:city":"Nuneaton",
    "sg:classifiers":[
        {
            "category":"Personal",
            "subcategory":"Beauty Salon",
            "type":"Services"
        }
    ],
    "sg:phone":"+44 24 7639 7887",
    "sg:postcode":"CV10 0LU",
    "sg:province":"Leicestershire",
    "sg:tags":[
        "unisex",
        "hairdresser"
    ],
    "wof:name":"Classy Cuts",
    "wof:placetype":"venue"
},
  "geometry": {"coordinates":[-1.5196260214,52.5434341431],"type":"Point"}
}