{
  "type": "Feature",
  "properties": {
    "addr:full":"Topcliffe Road, Topcliffe Thirsk North Yorkshire YO7 3HN",
    "addr:postcode":"yo7 3hn",
    "addr:street":"Topcliffe Road",
    "iso:country":"GB",
    "sg:address":"Topcliffe Road, Topcliffe",
    "sg:city":"Thirsk",
    "sg:classifiers":[
        {
            "category":"Autos & Motor Vehicles",
            "subcategory":"Fuel & Gas Station",
            "type":"Retail Goods"
        }
    ],
    "sg:phone":"+44 1845 577827",
    "sg:postcode":"YO7 3HN",
    "sg:province":"North Yorkshire",
    "sg:tags":[
        "petrol",
        "filling"
    ],
    "wof:name":"Midway Service Stations",
    "wof:placetype":"venue"
},
  "geometry": {"coordinates":[-1.3852690458,54.1783752441],"type":"Point"}
}