{
  "type": "Feature",
  "properties": {
    "addr:full":"Premier House, 12-13 Hatton Garden Clerkenwell Greater London EC1N 8AN",
    "addr:housenumber":"12-13",
    "addr:postcode":"ec1n 8an",
    "addr:street":"Hatton Garden",
    "iso:country":"GB",
    "sg:address":"Premier House, 12-13 Hatton Garden",
    "sg:city":"Clerkenwell",
    "sg:classifiers":[
        {
            "category":"Professional",
            "subcategory":"Management & Consulting",
            "type":"Services"
        }
    ],
    "sg:phone":"+44 1923 236050",
    "sg:postcode":"EC1N 8AN",
    "sg:province":"Greater London",
    "sg:tags":[
        "consultant",
        "business"
    ],
    "wof:name":"Thyron",
    "wof:placetype":"venue"
},
  "geometry": {"coordinates":[-0.107684,51.518665],"type":"Point"}
}