{
  "type": "Feature",
  "properties": {
    "iso:country":"GB",
    "sg:address":"31 Church Street",
    "sg:city":"Dagenham",
    "sg:classifiers":[
        {
            "category":"Retail",
            "subcategory":"Repair Shop",
            "type":"Services"
        }
    ],
    "sg:phone":"+44 20 8595 1223",
    "sg:postcode":"RM10 9UR",
    "sg:province":"Essex",
    "sg:tags":[
        "maintenance"
    ],
    "wof:name":"Petronne Services Ltd.",
    "wof:placetype":"venue"
},
  "geometry": {"coordinates":[0.163017,51.538448],"type":"Point"}
}