{
  "type": "Feature",
  "properties": {
    "addr:full":"7a Ailsa Road Twickenham Greater London TW1 1QJ",
    "addr:housenumber":"7a",
    "addr:postcode":"tw1 1qj",
    "addr:street":"Ailsa Road",
    "iso:country":"GB",
    "sg:address":"7a Ailsa Road",
    "sg:city":"Twickenham",
    "sg:classifiers":[
        {
            "category":"Education",
            "subcategory":"Music School",
            "type":"Public Place"
        }
    ],
    "sg:postcode":"TW1 1QJ",
    "sg:province":"Greater London",
    "sg:tags":[
        "conservatory"
    ],
    "wof:name":"Yvonne Howie Chartered Designer",
    "wof:placetype":"venue"
},
  "geometry": {"coordinates":[-0.3210549951,51.4586677551],"type":"Point"}
}