{
  "type": "Feature",
  "properties": {
    "addr:full":"Cathedral Street Norwich Norfolk NR1 1LX",
    "addr:postcode":"nr1 1lx",
    "addr:street":"Cathedral Street",
    "iso:country":"GB",
    "sg:address":"Cathedral Street",
    "sg:city":"Norwich",
    "sg:classifiers":[
        {
            "category":"Professional",
            "type":"Services"
        },
        {
            "category":"Government",
            "subcategory":"Office",
            "type":"Public Place"
        }
    ],
    "sg:phone":"+44 1603 878200",
    "sg:postcode":"NR1 1LX",
    "sg:province":"Norfolk",
    "sg:tags":[
        "archaeologist",
        "local"
    ],
    "wof:name":"Norfolk County Council",
    "wof:placetype":"venue"
},
  "geometry": {"coordinates":[1.3028550148,52.6295051575],"type":"Point"}
}