{
  "type": "Feature",
  "properties": {
    "addr:full":"7 Dunblane Drive, Orton Southgate Peterborough Cambridgeshire PE2 6SW",
    "addr:housenumber":"7",
    "addr:postcode":"pe2 6sw",
    "addr:street":"Dunblane Drive",
    "iso:country":"GB",
    "sg:address":"7 Dunblane Drive, Orton Southgate",
    "sg:city":"Peterborough",
    "sg:classifiers":[
        {
            "category":"Professional",
            "subcategory":"Art Services",
            "type":"Services"
        }
    ],
    "sg:phone":"+44 1733 236557",
    "sg:postcode":"PE2 6SW",
    "sg:province":"Cambridgeshire",
    "sg:tags":[
        "graphic",
        "designer"
    ],
    "wof:name":"N2 Design Etc",
    "wof:placetype":"venue"
},
  "geometry": {"coordinates":[-0.309888,52.544823],"type":"Point"}
}