{
  "type": "Feature",
  "properties": {
    "addr:full":"Gatehouse Enterprise Centre, Albert St,, Lockwood Huddersfield West Yorkshire HD1 3QD",
    "addr:postcode":"hd1 3qd",
    "addr:street":"Albert St;West",
    "iso:country":"GB",
    "sg:address":"Gatehouse Enterprise Centre, Albert St,, Lockwood",
    "sg:city":"Huddersfield",
    "sg:classifiers":[
        {
            "category":"Personal",
            "type":"Services"
        }
    ],
    "sg:postcode":"HD1 3QD",
    "sg:province":"West Yorkshire",
    "sg:tags":[
        "delivery"
    ],
    "wof:name":"Delivery Systems",
    "wof:placetype":"venue"
},
  "geometry": {"coordinates":[-1.7923339605,53.63514328],"type":"Point"}
}