{
  "type": "Feature",
  "properties": {
    "addr:full":"39 Mount Pleasant Road Tunbridge Wells Kent TN1 1PN",
    "addr:housenumber":"39",
    "addr:postcode":"tn1 1pn",
    "addr:street":"Mount Pleasant Road",
    "iso:country":"GB",
    "sg:address":"39 Mount Pleasant Road",
    "sg:city":"Tunbridge Wells",
    "sg:classifiers":[
        {
            "category":"Travel",
            "subcategory":"Travel Agent",
            "type":"Entertainment"
        }
    ],
    "sg:phone":"+44 1892 522445",
    "sg:postcode":"TN1 1PN",
    "sg:province":"Kent",
    "wof:name":"Romania Travel Centre",
    "wof:placetype":"venue"
},
  "geometry": {"coordinates":[0.2632290125,51.1316261292],"type":"Point"}
}