{
  "type": "Feature",
  "properties": {
    "iso:country":"GB",
    "sg:address":"45 New Cut, Layer De La Haye",
    "sg:city":"Colchester",
    "sg:classifiers":[
        {
            "category":"Health Services",
            "subcategory":"Doctor",
            "type":"Services"
        }
    ],
    "sg:phone":"+44 1206 734454",
    "sg:postcode":"CO2 0EG",
    "sg:province":"Essex",
    "sg:tags":[
        "practitioners"
    ],
    "wof:name":"Drs O'Callaghan Morris & Gunetilleke",
    "wof:placetype":"venue"
},
  "geometry": {"coordinates":[0.857019,51.84771],"type":"Point"}
}