{
  "type": "Feature",
  "properties": {
    "addr:full":"21-22 Whitgift Centre Croydon Surrey CR0 1UP",
    "addr:housenumber":"21-22",
    "addr:postcode":"cr0 1up",
    "addr:street":"Whitgift Centre",
    "iso:country":"GB",
    "sg:address":"21-22 Whitgift Centre",
    "sg:city":"Croydon",
    "sg:classifiers":[
        {
            "category":"Shopping",
            "subcategory":"Shoes",
            "type":"Retail Goods"
        }
    ],
    "sg:phone":"+44 20 8667 1230",
    "sg:postcode":"CR0 1UP",
    "sg:province":"Surrey",
    "sg:tags":[
        "shop"
    ],
    "wof:name":"Schuh Clothing for Feet",
    "wof:placetype":"venue"
},
  "geometry": {"coordinates":[-0.097916998,51.3748893738],"type":"Point"}
}