{
  "type": "Feature",
  "properties": {
    "iso:country":"GB",
    "sg:address":"East Farm, Abbotsbury",
    "sg:city":"Weymouth",
    "sg:classifiers":[
        {
            "category":"Sports & Exercise",
            "subcategory":"Stables",
            "type":"Entertainment"
        }
    ],
    "sg:postcode":"DT3 4JN",
    "sg:province":"Dorset",
    "sg:tags":[
        "education",
        "equestrian"
    ],
    "wof:name":"Woodcoate Stud",
    "wof:placetype":"venue"
},
  "geometry": {"coordinates":[-2.598651886,50.6656837463],"type":"Point"}
}