{
  "type": "Feature",
  "properties": {
    "iso:country":"GB",
    "sg:address":"15 Orchard Waye",
    "sg:city":"Uxbridge",
    "sg:classifiers":[
        {
            "category":"Communications",
            "subcategory":"Film & Video Production",
            "type":"Services"
        },
        {
            "category":"Shopping",
            "subcategory":"Gifts & Souvenirs",
            "type":"Retail Goods"
        },
        {
            "category":"Farming",
            "subcategory":"Farm",
            "type":"Manufacturing & Wholesale Goods"
        }
    ],
    "sg:phone":"+44 1895 847166",
    "sg:postcode":"UB8 2BN",
    "sg:province":"Buckinghamshire",
    "sg:tags":[
        "supp",
        "agricultural",
        "window",
        "leaded"
    ],
    "wof:name":"Lead Light Services",
    "wof:placetype":"venue"
},
  "geometry": {"coordinates":[-0.475547,51.538536],"type":"Point"}
}