{
  "type": "Feature",
  "properties": {
    "iso:country":"GB",
    "sg:address":"Five Pines, Carclew Road, Mylor Downs",
    "sg:city":"Falmouth",
    "sg:classifiers":[
        {
            "category":"Sports & Exercise",
            "subcategory":"Swimming Pool",
            "type":"Entertainment"
        }
    ],
    "sg:postcode":"TR11 5UN",
    "sg:province":"Cornwall",
    "sg:tags":[
        "bee"
    ],
    "wof:name":"B J Sheriff",
    "wof:placetype":"venue"
},
  "geometry": {"coordinates":[-5.080033,50.152206],"type":"Point"}
}