{
  "type": "Feature",
  "properties": {
    "addr:full":"36 Lancaster Road Southport Lancashire PR8 2LE",
    "addr:housenumber":"36",
    "addr:postcode":"pr8 2le",
    "addr:street":"Lancaster Road",
    "iso:country":"GB",
    "sg:address":"36 Lancaster Road",
    "sg:city":"Southport",
    "sg:classifiers":[
        {
            "category":"Health Services",
            "subcategory":"Nursing And Care Facility",
            "type":"Services"
        },
        {
            "category":"Social Services",
            "subcategory":"Retirement Home",
            "type":"Services"
        }
    ],
    "sg:phone":"+44 1704 568019",
    "sg:postcode":"PR8 2LE",
    "sg:province":"Lancashire",
    "sg:tags":[
        "residential"
    ],
    "wof:name":"Northern Counties Eventide Home Ltd",
    "wof:placetype":"venue"
},
  "geometry": {"coordinates":[-3.02905,53.632484],"type":"Point"}
}