{
  "type": "Feature",
  "properties": {
    "addr:full":"Rocklands Lane, East Hill Hastings East Sussex TN35 5DY",
    "addr:postcode":"tn35 5dy",
    "addr:street":"Rocklands Lane",
    "iso:country":"GB",
    "sg:address":"Rocklands Lane, East Hill",
    "sg:city":"Hastings",
    "sg:classifiers":[
        {
            "category":"Travel",
            "subcategory":"Hotels & Motels",
            "type":"Entertainment"
        }
    ],
    "sg:phone":"+44 1424 423097",
    "sg:postcode":"TN35 5DY",
    "sg:province":"East Sussex",
    "sg:tags":[
        "self",
        "catering"
    ],
    "wof:name":"Rocklands Holiday Park",
    "wof:placetype":"venue"
},
  "geometry": {"coordinates":[0.6066589952,50.8624992371],"type":"Point"}
}