{
  "type": "Feature",
  "properties": {
    "addr:full":"Unit 3, Moor Green Farm, Stanningfield Bury St Edmunds Suffolk IP29 4RX",
    "addr:housenumber":"unit 3",
    "addr:postcode":"ip29 4rx",
    "addr:street":"Moor Green;Stanningfield",
    "iso:country":"GB",
    "sg:address":"Unit 3, Moor Green Farm, Stanningfield",
    "sg:city":"Bury St Edmunds",
    "sg:classifiers":[
        {
            "category":"Freight",
            "type":"Transportation"
        }
    ],
    "sg:phone":"+44 1284 386346",
    "sg:postcode":"IP29 4RX",
    "sg:province":"Suffolk",
    "sg:tags":[
        "haulage",
        "road"
    ],
    "wof:name":"Cargosmiths Ltd.",
    "wof:placetype":"venue"
},
  "geometry": {"coordinates":[0.74938,52.182819],"type":"Point"}
}