{
  "type": "Feature",
  "properties": {
    "addr:full":"Canal Wharf, Morton Bridge, East Morton Keighley North Yorkshire BD20 5RP",
    "addr:postcode":"bd20 5rp",
    "iso:country":"GB",
    "sg:address":"Canal Wharf, Morton Bridge, East Morton",
    "sg:city":"Keighley",
    "sg:classifiers":[
        {
            "category":"Autos & Motor Vehicles",
            "subcategory":"Automobile Sales",
            "type":"Retail Goods"
        }
    ],
    "sg:phone":"+44 1274 563235",
    "sg:postcode":"BD20 5RP",
    "sg:province":"North Yorkshire",
    "sg:tags":[
        "commercial"
    ],
    "wof:name":"James Gore & Sons Ltd.",
    "wof:placetype":"venue"
},
  "geometry": {"coordinates":[-1.887854,53.878395],"type":"Point"}
}