{
  "type": "Feature",
  "properties": {
    "addr:full":"21 Brierley Croydon Surrey CR0 9DP",
    "addr:housenumber":"21",
    "addr:postcode":"cr0 9dp",
    "addr:street":"Brierley",
    "iso:country":"GB",
    "sg:address":"21 Brierley",
    "sg:city":"Croydon",
    "sg:classifiers":[
        {
            "category":"Building & Trades",
            "subcategory":"Landscaping Services",
            "type":"Services"
        }
    ],
    "sg:phone":"+44 1689 842809",
    "sg:postcode":"CR0 9DP",
    "sg:province":"Surrey",
    "sg:tags":[
        "landscape",
        "contractor"
    ],
    "wof:name":"E J O'Connell",
    "wof:placetype":"venue"
},
  "geometry": {"coordinates":[-0.0226760004,51.3546600342],"type":"Point"}
}