{
  "type": "Feature",
  "properties": {
    "addr:full":"Borough Chamber, 1 St Petersgate Stockport Cheshire SK1 1EB",
    "addr:housenumber":"1",
    "addr:postcode":"sk1 1eb",
    "addr:street":"St Petersgate",
    "iso:country":"GB",
    "sg:address":"Borough Chamber, 1 St Petersgate",
    "sg:city":"Stockport",
    "sg:classifiers":[
        {
            "category":"Home & Garden",
            "subcategory":"Furniture",
            "type":"Retail Goods"
        }
    ],
    "sg:phone":"+44 161 480 5453",
    "sg:postcode":"SK1 1EB",
    "sg:province":"Cheshire",
    "wof:name":"Walmsleys Furniture Store",
    "wof:placetype":"venue"
},
  "geometry": {"coordinates":[-2.1578900814,53.4101409912],"type":"Point"}
}