{
  "type": "Feature",
  "properties": {
    "addr:full":"22 Brunswick Place Dawlish Devon EX7 9PD",
    "addr:housenumber":"22",
    "addr:postcode":"ex7 9pd",
    "addr:street":"Brunswick Place",
    "iso:country":"GB",
    "sg:address":"22 Brunswick Place",
    "sg:city":"Dawlish",
    "sg:classifiers":[
        {
            "category":"Retail",
            "subcategory":"Funeral Services",
            "type":"Services"
        }
    ],
    "sg:phone":"+44 1626 862426",
    "sg:postcode":"EX7 9PD",
    "sg:province":"Devon",
    "wof:name":"B G Wills & Son",
    "wof:placetype":"venue"
},
  "geometry": {"coordinates":[-3.467916,50.580311],"type":"Point"}
}