{
  "type": "Feature",
  "properties": {
    "iso:country":"GB",
    "sg:address":"Seaforth Avenue",
    "sg:city":"Wick",
    "sg:classifiers":[
        {
            "category":"Education",
            "subcategory":"School",
            "type":"Public Place"
        },
        {
            "category":"Government",
            "subcategory":"Office",
            "type":"Public Place"
        }
    ],
    "sg:phone":"+44 1955 602649",
    "sg:postcode":"KW1 5ND",
    "sg:province":"Highland",
    "sg:tags":[
        "local",
        "authority"
    ],
    "wof:name":"Pulteneytown Academy Primary School",
    "wof:placetype":"venue"
},
  "geometry": {"coordinates":[-3.0960700512,58.4366836548],"type":"Point"}
}