{
  "type": "Feature",
  "properties": {
    "iso:country":"GB",
    "sg:address":"Laundry Cottage, Tantobie",
    "sg:city":"Stanley",
    "sg:classifiers":[
        {
            "category":"Bus Charters",
            "type":"Transportation"
        }
    ],
    "sg:phone":"+44 1207 235544",
    "sg:postcode":"DH9 9TQ",
    "sg:province":"Durham",
    "sg:tags":[
        "hire",
        "coach"
    ],
    "wof:name":"Weightman Mini Coaches",
    "wof:placetype":"venue"
},
  "geometry": {"coordinates":[-1.727729,54.885704],"type":"Point"}
}