{
  "type": "Feature",
  "properties": {
    "addr:full":"Pool House Farm, Weston Jones Newport Shropshire TF10 8ED",
    "addr:postcode":"tf10 8ed",
    "addr:street":"Jones",
    "iso:country":"GB",
    "sg:address":"Pool House Farm, Weston Jones",
    "sg:city":"Newport",
    "sg:classifiers":[
        {
            "category":"Farming",
            "subcategory":"Livestock Farm",
            "type":"Manufacturing & Wholesale Goods"
        }
    ],
    "sg:postcode":"TF10 8ED",
    "sg:province":"Shropshire",
    "sg:tags":[
        "others"
    ],
    "wof:name":"W R & S M Marginson",
    "wof:placetype":"venue"
},
  "geometry": {"coordinates":[-2.3764920235,52.7698287964],"type":"Point"}
}