{
  "type": "Feature",
  "properties": {
    "addr:full":"Porthcurno, Churchtown, St Levan Penzance Cornwall TR19 6JU",
    "addr:postcode":"tr19 6ju",
    "addr:street":"Porthcurno Churchtown St",
    "iso:country":"GB",
    "sg:address":"Porthcurno, Churchtown, St Levan",
    "sg:city":"Penzance",
    "sg:classifiers":[
        {
            "category":"Travel",
            "subcategory":"Hotels & Motels",
            "type":"Entertainment"
        }
    ],
    "sg:postcode":"TR19 6JU",
    "sg:province":"Cornwall",
    "wof:name":"Mariners Lodge Hotel",
    "wof:placetype":"venue"
},
  "geometry": {"coordinates":[-5.65429,50.043308],"type":"Point"}
}