{
  "type": "Feature",
  "properties": {
    "iso:country":"GB",
    "sg:address":"East Balhaggarty Cottage, Garvock Hill",
    "sg:city":"Laurencekirk",
    "sg:classifiers":[
        {
            "category":"Manufacturing",
            "subcategory":"Electronics",
            "type":"Manufacturing & Wholesale Goods"
        }
    ],
    "sg:postcode":"AB30 1HT",
    "sg:province":"Aberdeenshire",
    "sg:tags":[
        "control",
        "component",
        "-",
        "electronic"
    ],
    "wof:name":"Magpie Electronics Ltd",
    "wof:placetype":"venue"
},
  "geometry": {"coordinates":[-2.4693739414,56.8306617737],"type":"Point"}
}