{
  "type": "Feature",
  "properties": {
    "iso:country":"GB",
    "sg:address":"Twiggs Lane, Marchwood",
    "sg:city":"Southampton",
    "sg:classifiers":[
        {
            "category":"Education",
            "subcategory":"School",
            "type":"Public Place"
        }
    ],
    "sg:phone":"+44 23 8086 8819",
    "sg:postcode":"SO40 4ZE",
    "sg:province":"Hampshire",
    "sg:tags":[
        "local",
        "authority"
    ],
    "wof:name":"Marchwood C of E (Controlled) Infant School",
    "wof:placetype":"venue"
},
  "geometry": {"coordinates":[-1.4478340149,50.892539978],"type":"Point"}
}