{
  "type": "Feature",
  "properties": {
    "iso:country":"GB",
    "sg:address":"37 Queenstown Road",
    "sg:city":"London",
    "sg:classifiers":[
        {
            "category":"Fast Food",
            "type":"Food & Drink"
        }
    ],
    "sg:phone":"+44 20 7622 4629",
    "sg:postcode":"SW8 3RE",
    "sg:province":"Greater London",
    "sg:tags":[
        "away",
        "meal",
        "outlet",
        "take"
    ],
    "wof:name":"Moonlight",
    "wof:placetype":"venue"
},
  "geometry": {"coordinates":[-0.150834,51.467388],"type":"Point"}
}