{
  "type": "Feature",
  "properties": {
    "addr:full":"Unit 8 & 12 Woodside Business Park Birkenhead Merseyside L41 1EL",
    "addr:housenumber":"unit 8 & 12",
    "addr:postcode":"l41 1el",
    "addr:street":"Woodside Business Park",
    "iso:country":"GB",
    "sg:address":"Unit 8 & 12 Woodside Business Park",
    "sg:city":"Birkenhead",
    "sg:classifiers":[
        {
            "category":"Professional",
            "subcategory":"Advertising",
            "type":"Services"
        }
    ],
    "sg:phone":"+44 151 647 7155",
    "sg:postcode":"L41 1EL",
    "sg:province":"Merseyside",
    "sg:tags":[
        "agency"
    ],
    "wof:name":"Production Outfit (Merseyside) Ltd The",
    "wof:placetype":"venue"
},
  "geometry": {"coordinates":[-3.010174,53.396526],"type":"Point"}
}