{
  "type": "Feature",
  "properties": {
    "addr:full":"2 Mill Lane Tenterden Kent TN30 6NA",
    "addr:housenumber":"2",
    "addr:postcode":"tn30 6na",
    "addr:street":"Mill Lane",
    "iso:country":"GB",
    "sg:address":"2 Mill Lane",
    "sg:city":"Tenterden",
    "sg:classifiers":[
        {
            "category":"Health Services",
            "subcategory":"Hospital",
            "type":"Services"
        }
    ],
    "sg:phone":"+44 1580 763222",
    "sg:postcode":"TN30 6NA",
    "sg:province":"Kent",
    "sg:tags":[
        "ambulance"
    ],
    "wof:name":"Allard Ambulance Services",
    "wof:placetype":"venue"
},
  "geometry": {"coordinates":[0.695141,51.076031],"type":"Point"}
}