{
  "type": "Feature",
  "properties": {
    "addr:full":"28 New Road Chippenham Wiltshire SN15 1HS",
    "addr:housenumber":"28",
    "addr:postcode":"sn15 1hs",
    "addr:street":"New Road",
    "iso:country":"GB",
    "sg:address":"28 New Road",
    "sg:city":"Chippenham",
    "sg:classifiers":[
        {
            "category":"Retail",
            "subcategory":"Laundry & Dry Cleaning",
            "type":"Services"
        }
    ],
    "sg:postcode":"SN15 1HS",
    "sg:province":"Wiltshire",
    "sg:tags":[
        "alteration"
    ],
    "wof:name":"Clean New Image",
    "wof:placetype":"venue"
},
  "geometry": {"coordinates":[-2.117638,51.463089],"type":"Point"}
}