{
  "type": "Feature",
  "properties": {
    "addr:full":"24a Scotts Rd Bromley Kent BR1 3QD",
    "addr:housenumber":"24a",
    "addr:postcode":"br1 3qd",
    "addr:street":"Scotts Rd",
    "iso:country":"GB",
    "sg:address":"24a Scotts Rd",
    "sg:city":"Bromley",
    "sg:classifiers":[
        {
            "category":"Building & Trades",
            "subcategory":"Equipment Rental",
            "type":"Services"
        }
    ],
    "sg:phone":"+44 20 8460 9111",
    "sg:postcode":"BR1 3QD",
    "sg:province":"Kent",
    "sg:tags":[
        "hire",
        "centre"
    ],
    "wof:name":"Hewden Hire Centres",
    "wof:placetype":"venue"
},
  "geometry": {"coordinates":[0.0133450003,51.4117240906],"type":"Point"}
}