{
  "type": "Feature",
  "properties": {
    "iso:country":"GB",
    "sg:address":"Hatherleigh Farm, Lawrence Hill",
    "sg:city":"Wincanton",
    "sg:classifiers":[
        {
            "category":"Home & Garden",
            "subcategory":"Home Furnishings",
            "type":"Retail Goods"
        }
    ],
    "sg:phone":"+44 1963 34356",
    "sg:postcode":"BA9 8AB",
    "sg:province":"Somerset",
    "sg:tags":[
        "homefurnishings"
    ],
    "wof:name":"I.Longpre Cabinet Makers",
    "wof:placetype":"venue"
},
  "geometry": {"coordinates":[-2.413179,51.0578],"type":"Point"}
}