{
  "type": "Feature",
  "properties": {
    "addr:full":"Wolfscastle Haverfordwest Pembrokeshire SA62 5LZ",
    "addr:postcode":"sa62 5lz",
    "addr:street":"Wolfscastle;Pembrokeshire",
    "iso:country":"GB",
    "sg:address":"Wolfscastle",
    "sg:city":"Haverfordwest",
    "sg:classifiers":[
        {
            "category":"Education",
            "subcategory":"School",
            "type":"Public Place"
        },
        {
            "category":"Government",
            "subcategory":"Office",
            "type":"Public Place"
        }
    ],
    "sg:postcode":"SA62 5LZ",
    "sg:province":"Pembrokeshire",
    "sg:tags":[
        "local",
        "authority"
    ],
    "wof:name":"Wolfscastle County Primary School",
    "wof:placetype":"venue"
},
  "geometry": {"coordinates":[-4.970573,51.897137],"type":"Point"}
}