{
  "type": "Feature",
  "properties": {
    "addr:full":"4 Flower Court, Bull St Stratford Upon Avon Warwickshire CV37 6GX",
    "addr:housenumber":"4",
    "addr:postcode":"cv37 6gx",
    "addr:street":"Flower Court Bull St",
    "iso:country":"GB",
    "sg:address":"4 Flower Court, Bull St",
    "sg:city":"Stratford Upon Avon",
    "sg:classifiers":[
        {
            "category":"Real Estate",
            "subcategory":"Architect",
            "type":"Services"
        }
    ],
    "sg:phone":"+44 1789 296009",
    "sg:postcode":"CV37 6GX",
    "sg:province":"Warwickshire",
    "wof:name":"Angus & Rachel Liddell",
    "wof:placetype":"venue"
},
  "geometry": {"coordinates":[-1.7107490301,52.1872406006],"type":"Point"}
}