{
  "type": "Feature",
  "properties": {
    "addr:full":"93 Shore Street Fraserburgh Aberdeenshire AB43 9BR",
    "addr:housenumber":"93",
    "addr:postcode":"ab43 9br",
    "addr:street":"Shore Street",
    "iso:country":"GB",
    "sg:address":"93 Shore Street",
    "sg:city":"Fraserburgh",
    "sg:classifiers":[
        {
            "category":"Bars & Pubs",
            "type":"Food & Drink"
        }
    ],
    "sg:phone":"+44 1346 513543",
    "sg:postcode":"AB43 9BR",
    "sg:province":"Aberdeenshire",
    "sg:tags":[
        "pubs",
        "inn"
    ],
    "wof:name":"Oak Tree Bar",
    "wof:placetype":"venue"
},
  "geometry": {"coordinates":[-2.003848,57.692757],"type":"Point"}
}