{
  "type": "Feature",
  "properties": {
    "iso:country":"GB",
    "sg:address":"The Earlsfield Practice, 2-4 Steerforth St",
    "sg:city":"Wandsworth",
    "sg:classifiers":[
        {
            "category":"Health Services",
            "subcategory":"Doctor",
            "type":"Services"
        }
    ],
    "sg:phone":"+44 20 8946 5681",
    "sg:postcode":"SW18 4HH",
    "sg:province":"Greater London",
    "sg:tags":[
        "practitioners"
    ],
    "wof:name":"Roche, C J H",
    "wof:placetype":"venue"
},
  "geometry": {"coordinates":[-0.194479,51.456871],"type":"Point"}
}