{
  "type": "Feature",
  "properties": {
    "iso:country":"GB",
    "sg:address":"103 Tonge Moor Road",
    "sg:city":"Bolton",
    "sg:classifiers":[
        {
            "category":"Food & Beverages",
            "subcategory":"Candy",
            "type":"Retail Goods"
        }
    ],
    "sg:phone":"+44 1204 525546",
    "sg:postcode":"BL2 2DL",
    "sg:province":"Lancashire",
    "sg:tags":[
        "confectioner"
    ],
    "wof:name":"Taylor Lawrence (Confectioners)",
    "wof:placetype":"venue"
},
  "geometry": {"coordinates":[-2.413495,53.587822],"type":"Point"}
}