{
  "type": "Feature",
  "properties": {
    "addr:full":"Suite 49 Eurolink Business, Centre 49 Effra Road London Greater London SW2 1BZ",
    "addr:housenumber":"business;49",
    "addr:postcode":"sw2 1bz",
    "addr:street":"Suite 49 Eurolink;Effra Road",
    "iso:country":"GB",
    "sg:address":"Suite 49 Eurolink Business, Centre 49 Effra Road",
    "sg:city":"London",
    "sg:classifiers":[
        {
            "category":"Professional",
            "subcategory":"Computer Services",
            "type":"Services"
        }
    ],
    "sg:postcode":"SW2 1BZ",
    "sg:province":"Greater London",
    "sg:tags":[
        "consultant"
    ],
    "wof:name":"All I.T. Ltd",
    "wof:placetype":"venue"
},
  "geometry": {"coordinates":[-0.11446,51.457581],"type":"Point"}
}