{
  "type": "Feature",
  "properties": {
    "iso:country":"GB",
    "sg:address":"281a London Road",
    "sg:city":"Westcliff-on-sea",
    "sg:classifiers":[
        {
            "category":"Shopping",
            "subcategory":"Music",
            "type":"Retail Goods"
        }
    ],
    "sg:phone":"+44 1702 338593",
    "sg:postcode":"SS0 7BX",
    "sg:province":"Essex",
    "sg:tags":[
        "record",
        "tape",
        "cd"
    ],
    "wof:name":"Carmel Records",
    "wof:placetype":"venue"
},
  "geometry": {"coordinates":[0.6987230182,51.5410842896],"type":"Point"}
}