{
  "type": "Feature",
  "properties": {
    "addr:full":"12 Railway Street Stockton-on-tees Durham TS18 2BB",
    "addr:housenumber":"12",
    "addr:postcode":"ts18 2bb",
    "addr:street":"Railway Street",
    "iso:country":"GB",
    "sg:address":"12 Railway Street",
    "sg:city":"Stockton-on-tees",
    "sg:classifiers":[
        {
            "category":"Bus Charters",
            "type":"Transportation"
        }
    ],
    "sg:phone":"+44 1642 611294",
    "sg:postcode":"TS18 2BB",
    "sg:province":"Durham",
    "sg:tags":[
        "mini",
        "hire",
        "coach",
        "leasing"
    ],
    "wof:name":"Sapphire Mini-Coaches Ltd.",
    "wof:placetype":"venue"
},
  "geometry": {"coordinates":[-1.3118439913,54.5729598999],"type":"Point"}
}