{
  "type": "Feature",
  "properties": {
    "iso:country":"GB",
    "sg:address":"61-61a High Street",
    "sg:city":"Whitstable",
    "sg:classifiers":[
        {
            "category":"Food & Beverages",
            "subcategory":"Fruits & Vegetables",
            "type":"Retail Goods"
        }
    ],
    "sg:phone":"+44 1227 262949",
    "sg:postcode":"CT5 1AP",
    "sg:province":"Kent",
    "sg:tags":[
        "greengrocer"
    ],
    "wof:name":"Staines Farm Shop",
    "wof:placetype":"venue"
},
  "geometry": {"coordinates":[1.024796,51.358685],"type":"Point"}
}