{
  "type": "Feature",
  "properties": {
    "addr:full":"35 Baxter Gate Loughborough Leicestershire LE11 1TQ",
    "addr:housenumber":"35",
    "addr:postcode":"le11 1tq",
    "addr:street":"Baxter Gate",
    "iso:country":"GB",
    "sg:address":"35 Baxter Gate",
    "sg:city":"Loughborough",
    "sg:classifiers":[
        {
            "category":"Shopping",
            "subcategory":"Florist",
            "type":"Retail Goods"
        }
    ],
    "sg:phone":"+44 1509 263821",
    "sg:postcode":"LE11 1TQ",
    "sg:province":"Leicestershire",
    "wof:name":"Savoy Florist",
    "wof:placetype":"venue"
},
  "geometry": {"coordinates":[-1.2025539875,52.7731513977],"type":"Point"}
}