{
  "type": "Feature",
  "properties": {
    "addr:full":"359 Greenland Road, Darnall Sheffield South Yorkshire S9 5FD",
    "addr:housenumber":"359",
    "addr:postcode":"s9 5fd",
    "addr:street":"Greenland Road",
    "iso:country":"GB",
    "sg:address":"359 Greenland Road, Darnall",
    "sg:city":"Sheffield",
    "sg:classifiers":[
        {
            "category":"Autos & Motor Vehicles",
            "subcategory":"Automobile Sales",
            "type":"Retail Goods"
        }
    ],
    "sg:phone":"+44 114 242 6117",
    "sg:postcode":"S9 5FD",
    "sg:province":"South Yorkshire",
    "sg:tags":[
        "car"
    ],
    "wof:name":"Darnall Motor Company",
    "wof:placetype":"venue"
},
  "geometry": {"coordinates":[-1.4101719856,53.393611908],"type":"Point"}
}