{
  "type": "Feature",
  "properties": {
    "iso:country":"GB",
    "sg:address":"20 Cowgate",
    "sg:city":"Norwich",
    "sg:classifiers":[
        {
            "category":"Bars & Pubs",
            "type":"Food & Drink"
        }
    ],
    "sg:phone":"+44 1603 475001",
    "sg:postcode":"NR3 1SY",
    "sg:province":"Norfolk",
    "sg:tags":[
        "pubs",
        "inn"
    ],
    "wof:name":"Blueberry Public House",
    "wof:placetype":"venue"
},
  "geometry": {"coordinates":[1.2973890305,52.6366233826],"type":"Point"}
}