{
  "type": "Feature",
  "properties": {
    "iso:country":"GB",
    "sg:address":"Caxton House, Creake Road, Sculthorpe",
    "sg:city":"Fakenham",
    "sg:classifiers":[
        {
            "category":"Shopping",
            "subcategory":"Bicycles & Sporting Goods",
            "type":"Retail Goods"
        }
    ],
    "sg:phone":"+44 1328 864785",
    "sg:postcode":"NR21 9NG",
    "sg:province":"Norfolk",
    "sg:tags":[
        "shop",
        "cycle",
        "accessory"
    ],
    "wof:name":"Engledow Cycle Centre",
    "wof:placetype":"venue"
},
  "geometry": {"coordinates":[0.809607,52.842388],"type":"Point"}
}