{
  "type": "Feature",
  "properties": {
    "addr:full":"6 Vigo St West End Hampshire W1X 3PB",
    "addr:housenumber":"6",
    "addr:postcode":"w1x 3pb",
    "addr:street":"Vigo St",
    "iso:country":"GB",
    "sg:address":"6 Vigo St",
    "sg:city":"West End",
    "sg:classifiers":[
        {
            "category":"Real Estate",
            "subcategory":"Real Estate Operator",
            "type":"Services"
        }
    ],
    "sg:phone":"+44 20 7629 2522",
    "sg:postcode":"W1X 3PB",
    "sg:province":"Hampshire",
    "sg:tags":[
        "letting",
        "agent"
    ],
    "wof:name":"Home Made",
    "wof:placetype":"venue"
},
  "geometry": {"coordinates":[-0.1392890066,51.5103340149],"type":"Point"}
}