{
  "type": "Feature",
  "properties": {
    "addr:full":"Limberline Rd Portsmouth Hampshire PO3 5JF",
    "addr:postcode":"hampshire po3 5jf",
    "addr:street":"Limberline Rd",
    "iso:country":"GB",
    "sg:address":"Limberline Rd",
    "sg:city":"Portsmouth",
    "sg:classifiers":[
        {
            "category":"Professional",
            "subcategory":"Testing Lab",
            "type":"Services"
        }
    ],
    "sg:phone":"+44 23 9267 1032",
    "sg:postcode":"PO3 5JF",
    "sg:province":"Hampshire",
    "sg:tags":[
        "laboratory"
    ],
    "wof:name":"Electrolux Corporate Quality Product Saf",
    "wof:placetype":"venue"
},
  "geometry": {"coordinates":[-1.0632090569,50.8313102722],"type":"Point"}
}