{
  "type": "Feature",
  "properties": {
    "addr:full":"20 Westcotes Drive Leicester Leicestershire LE3 0QR",
    "addr:housenumber":"20",
    "addr:postcode":"le3 0qr",
    "addr:street":"Westcotes Drive",
    "iso:country":"GB",
    "sg:address":"20 Westcotes Drive",
    "sg:city":"Leicester",
    "sg:classifiers":[
        {
            "category":"Social Services",
            "subcategory":"Retirement Home",
            "type":"Services"
        }
    ],
    "sg:phone":"+44 116 224 7087",
    "sg:postcode":"LE3 0QR",
    "sg:province":"Leicestershire",
    "sg:tags":[
        "residential",
        "care"
    ],
    "wof:name":"Porter Lodge",
    "wof:placetype":"venue"
},
  "geometry": {"coordinates":[-1.1511889696,52.6286506653],"type":"Point"}
}