{
  "type": "Feature",
  "properties": {
    "iso:country":"GB",
    "sg:address":"3 Wright Street",
    "sg:city":"Renfrew",
    "sg:classifiers":[
        {
            "category":"Government",
            "subcategory":"Post Office",
            "type":"Public Place"
        }
    ],
    "sg:phone":"+44 141 889 3169",
    "sg:postcode":"PA4 8BJ",
    "sg:province":"Renfrewshire",
    "wof:name":"Wright Street Post Office",
    "wof:placetype":"venue"
},
  "geometry": {"coordinates":[-4.407337,55.863747],"type":"Point"}
}