{
  "type": "Feature",
  "properties": {
    "iso:country":"GB",
    "sg:address":"1 Coopers Crescent",
    "sg:city":"Borehamwood",
    "sg:classifiers":[
        {
            "category":"Building & Trades",
            "subcategory":"Construction",
            "type":"Services"
        }
    ],
    "sg:phone":"+44 20 8953 5872",
    "sg:postcode":"WD6 5RF",
    "sg:province":"Hertfordshire",
    "sg:tags":[
        "decorator",
        "painter"
    ],
    "wof:name":"D B Decorators",
    "wof:placetype":"venue"
},
  "geometry": {"coordinates":[-0.259564,51.664612],"type":"Point"}
}