{
  "type": "Feature",
  "properties": {
    "iso:country":"GB",
    "sg:address":"48 Lidgate Crescent, Langthwaite Grange Industrial Estate",
    "sg:city":"Pontefract",
    "sg:classifiers":[
        {
            "category":"Manufacturing",
            "subcategory":"Chemicals & Compounds",
            "type":"Manufacturing & Wholesale Goods"
        },
        {
            "category":"Wholesale",
            "subcategory":"Chemicals & Plastics",
            "type":"Manufacturing & Wholesale Goods"
        }
    ],
    "sg:phone":"+44 1977 608066",
    "sg:postcode":"WF9 3NR",
    "sg:province":"West Yorkshire",
    "sg:tags":[
        "product",
        "allied",
        "distribution",
        "manufacturer"
    ],
    "wof:name":"Univar Ltd",
    "wof:placetype":"venue"
},
  "geometry": {"coordinates":[-1.306604,53.589825],"type":"Point"}
}