{
  "type": "Feature",
  "properties": {
    "addr:full":"292 Milkwood Road, Herne Hill London Greater London SE24 0EZ",
    "addr:housenumber":"292",
    "addr:postcode":"se24 0ez",
    "addr:street":"Milkwood Road",
    "iso:country":"GB",
    "sg:address":"292 Milkwood Road, Herne Hill",
    "sg:city":"London",
    "sg:classifiers":[
        {
            "category":"Home & Garden",
            "subcategory":"Building Materials",
            "type":"Retail Goods"
        }
    ],
    "sg:phone":"+44 20 7274 6802",
    "sg:postcode":"SE24 0EZ",
    "sg:province":"Greater London",
    "sg:tags":[
        "gate",
        "door",
        "barrier"
    ],
    "wof:name":"Ace Gates",
    "wof:placetype":"venue"
},
  "geometry": {"coordinates":[-0.101799,51.453236],"type":"Point"}
}