{
  "type": "Feature",
  "properties": {
    "addr:full":"115-117 High St Galashiels Scottish Borders TD1 1RZ",
    "addr:housenumber":"115-117",
    "addr:postcode":"td1 1rz",
    "addr:street":"High St",
    "iso:country":"GB",
    "sg:address":"115-117 High St",
    "sg:city":"Galashiels",
    "sg:classifiers":[
        {
            "category":"Professional",
            "subcategory":"Management & Consulting",
            "type":"Services"
        }
    ],
    "sg:phone":"+44 1896 755516",
    "sg:postcode":"TD1 1RZ",
    "sg:province":"Scottish Borders",
    "sg:tags":[
        "conservation"
    ],
    "wof:name":"Scottish Wildlife Trust",
    "wof:placetype":"venue"
},
  "geometry": {"coordinates":[-2.8120410442,55.6184806824],"type":"Point"}
}