{
  "type": "Feature",
  "properties": {
    "addr:full":"9 Buxton Court, Manners Avenue Ilkeston Derbyshire DE7 8EF",
    "addr:housenumber":"9",
    "addr:postcode":"de7 8ef",
    "addr:street":"Buxton Court Manners Avenue",
    "iso:country":"GB",
    "sg:address":"9 Buxton Court, Manners Avenue",
    "sg:city":"Ilkeston",
    "sg:classifiers":[
        {
            "category":"Retail",
            "subcategory":"Auto Repair",
            "type":"Services"
        }
    ],
    "sg:phone":"+44 115 930 5454",
    "sg:postcode":"DE7 8EF",
    "sg:province":"Derbyshire",
    "sg:tags":[
        "electrician"
    ],
    "wof:name":"Vehicle Wiring Products",
    "wof:placetype":"venue"
},
  "geometry": {"coordinates":[-1.310189,52.978611],"type":"Point"}
}