{
  "type": "Feature",
  "properties": {
    "iso:country":"GB",
    "sg:address":"1 Victoria Square",
    "sg:city":"Birmingham",
    "sg:classifiers":[
        {
            "category":"Insurance",
            "subcategory":"Life Insurance",
            "type":"Services"
        }
    ],
    "sg:phone":"+44 121 633 8997",
    "sg:postcode":"B1 1BD",
    "sg:province":"West Midlands",
    "sg:tags":[
        "assurance"
    ],
    "wof:name":"American Life Insurance Co.",
    "wof:placetype":"venue"
},
  "geometry": {"coordinates":[-1.902952,52.48],"type":"Point"}
}