{
  "type": "Feature",
  "properties": {
    "addr:full":"11 Kings Road, Clifton Bristol City of Bristol BS8 4AB",
    "addr:housenumber":"11",
    "addr:postcode":"bs8 4ab",
    "addr:street":"Kings Road",
    "iso:country":"GB",
    "sg:address":"11 Kings Road, Clifton",
    "sg:city":"Bristol",
    "sg:classifiers":[
        {
            "category":"Shopping",
            "subcategory":"Computers & Home Electronics",
            "type":"Retail Goods"
        }
    ],
    "sg:postcode":"BS8 4AB",
    "sg:province":"City of Bristol",
    "wof:name":"Aj Synetics Ltd",
    "wof:placetype":"venue"
},
  "geometry": {"coordinates":[-2.619349,51.45554],"type":"Point"}
}