{
  "type": "Feature",
  "properties": {
    "addr:full":"Howards Close Farm, Brewery Road, Trunt North Walsham Norfolk NR28 0PX",
    "addr:postcode":"nr28 0px",
    "addr:street":"Howards Close;Brewery Road;Walsham",
    "iso:country":"GB",
    "sg:address":"Howards Close Farm, Brewery Road, Trunt",
    "sg:city":"North Walsham",
    "sg:classifiers":[
        {
            "category":"Retail",
            "subcategory":"Repair Shop",
            "type":"Services"
        },
        {
            "category":"Wholesale",
            "subcategory":"Machinery & Supplies",
            "type":"Manufacturing & Wholesale Goods"
        }
    ],
    "sg:phone":"+44 1263 721609",
    "sg:postcode":"NR28 0PX",
    "sg:province":"Norfolk",
    "sg:tags":[
        "agricultural",
        "sale"
    ],
    "wof:name":"K W Farm Services",
    "wof:placetype":"venue"
},
  "geometry": {"coordinates":[1.3847600222,52.8183135986],"type":"Point"}
}