{
  "type": "Feature",
  "properties": {
    "iso:country":"GB",
    "sg:address":"Church Farm, Semley",
    "sg:city":"Shaftesbury",
    "sg:classifiers":[
        {
            "category":"Farming",
            "subcategory":"Farm",
            "type":"Manufacturing & Wholesale Goods"
        }
    ],
    "sg:phone":"+44 1747 830257",
    "sg:postcode":"SP7 9AS",
    "sg:province":"Dorset",
    "sg:tags":[
        "mixed",
        "crop"
    ],
    "wof:name":"Bowerman & Sons",
    "wof:placetype":"venue"
},
  "geometry": {"coordinates":[-2.155759,51.041698],"type":"Point"}
}