{
  "type": "Feature",
  "properties": {
    "addr:full":"7 Firs Gate Harrogate North Yorkshire HG2 9HE",
    "addr:housenumber":"7",
    "addr:postcode":"hg2 9he",
    "addr:street":"Firs Gate",
    "iso:country":"GB",
    "sg:address":"7 Firs Gate",
    "sg:city":"Harrogate",
    "sg:classifiers":[
        {
            "category":"Professional",
            "subcategory":"Business Services",
            "type":"Services"
        }
    ],
    "sg:phone":"+44 1423 874088",
    "sg:postcode":"HG2 9HE",
    "sg:province":"North Yorkshire",
    "sg:tags":[
        "trade"
    ],
    "wof:name":"Expense Reduction Analyst",
    "wof:placetype":"venue"
},
  "geometry": {"coordinates":[-1.5328919888,53.972202301],"type":"Point"}
}