{
  "type": "Feature",
  "properties": {
    "addr:full":"Eton House, 156 High Street Ruislip Greater London HA4 8LJ",
    "addr:housenumber":"156",
    "addr:postcode":"ha4 8lj",
    "addr:street":"High Street",
    "iso:country":"GB",
    "sg:address":"Eton House, 156 High Street",
    "sg:city":"Ruislip",
    "sg:classifiers":[
        {
            "category":"Food & Beverages",
            "subcategory":"Supermarket",
            "type":"Retail Goods"
        }
    ],
    "sg:phone":"+44 1895 622240",
    "sg:postcode":"HA4 8LJ",
    "sg:province":"Greater London",
    "sg:tags":[
        "frozen"
    ],
    "wof:name":"Golden Valley Microwave Foods Inc",
    "wof:placetype":"venue"
},
  "geometry": {"coordinates":[-0.4230430126,51.572719574],"type":"Point"}
}