{
  "type": "Feature",
  "properties": {
    "addr:full":"S12 Chester Enterprise Centre Chester Cheshire CH2 3NE",
    "addr:postcode":"ch2 3ne",
    "addr:street":"Chester",
    "iso:country":"GB",
    "sg:address":"S12 Chester Enterprise Centre",
    "sg:city":"Chester",
    "sg:classifiers":[
        {
            "category":"Recreation",
            "subcategory":"Gun Range",
            "type":"Entertainment"
        }
    ],
    "sg:phone":"+44 1978 361108",
    "sg:postcode":"CH2 3NE",
    "sg:province":"Cheshire",
    "sg:tags":[
        "operator",
        "tour"
    ],
    "wof:name":"Xenos Holidays",
    "wof:placetype":"venue"
},
  "geometry": {"coordinates":[-2.8796598911,53.1978416443],"type":"Point"}
}