{
  "type": "Feature",
  "properties": {
    "iso:country":"GB",
    "sg:address":"1 The Precinct, Hedge End",
    "sg:city":"Southampton",
    "sg:classifiers":[
        {
            "category":"Shopping",
            "subcategory":"Clothing, Apparel, & Fashions",
            "type":"Retail Goods"
        }
    ],
    "sg:postcode":"SO30 0BL",
    "sg:province":"Hampshire",
    "sg:tags":[
        "dresswear"
    ],
    "wof:name":"Revival Fashion Agency",
    "wof:placetype":"venue"
},
  "geometry": {"coordinates":[-1.30296,50.913422],"type":"Point"}
}