{
  "type": "Feature",
  "properties": {
    "iso:country":"GB",
    "sg:address":"Brookland Terrace",
    "sg:city":"North Shields",
    "sg:classifiers":[
        {
            "category":"Health Services",
            "subcategory":"Doctor",
            "type":"Services"
        }
    ],
    "sg:phone":"+44 191 258 5316",
    "sg:postcode":"NE29 8EA",
    "sg:province":"Tyne and Wear",
    "sg:tags":[
        "practitioners"
    ],
    "wof:name":"New York Surgery",
    "wof:placetype":"venue"
},
  "geometry": {"coordinates":[-1.4839539528,55.0246200562],"type":"Point"}
}