{
  "type": "Feature",
  "properties": {
    "addr:full":"Trooper Road Tring Buckinghamshire HP23 5RW",
    "addr:postcode":"hp23 5rw",
    "addr:street":"Trooper Road",
    "iso:country":"GB",
    "sg:address":"Trooper Road",
    "sg:city":"Tring",
    "sg:classifiers":[
        {
            "category":"Restaurant",
            "type":"Food & Drink"
        }
    ],
    "sg:postcode":"HP23 5RW",
    "sg:province":"Buckinghamshire",
    "wof:name":"Troopers Eating House",
    "wof:placetype":"venue"
},
  "geometry": {"coordinates":[-0.6025000215,51.8011016846],"type":"Point"}
}