{
  "type": "Feature",
  "properties": {
    "addr:full":"32 Hambleton View York North Yorkshire YO61 1QW",
    "addr:housenumber":"32",
    "addr:postcode":"yo61 1qw",
    "addr:street":"Hambleton View",
    "iso:country":"GB",
    "sg:address":"32 Hambleton View",
    "sg:city":"York",
    "sg:classifiers":[
        {
            "category":"Personal",
            "subcategory":"Beauty Salon",
            "type":"Services"
        }
    ],
    "sg:phone":"+44 1347 838915",
    "sg:postcode":"YO61 1QW",
    "sg:province":"North Yorkshire",
    "sg:tags":[
        "unisex",
        "hairdresser"
    ],
    "wof:name":"Sue's Mobile Hairdressing",
    "wof:placetype":"venue"
},
  "geometry": {"coordinates":[-1.2140940428,54.0713653564],"type":"Point"}
}