{
  "type": "Feature",
  "properties": {
    "addr:full":"1 Sanderstead Court Avenue, Sanderstead South Croydon Surrey CR2 9AU",
    "addr:housenumber":"1",
    "addr:postcode":"cr2 9au",
    "addr:street":"Sanderstead Court Avenue",
    "iso:country":"GB",
    "sg:address":"1 Sanderstead Court Avenue, Sanderstead",
    "sg:city":"South Croydon",
    "sg:classifiers":[
        {
            "category":"Professional",
            "type":"Services"
        }
    ],
    "sg:postcode":"CR2 9AU",
    "sg:province":"Surrey",
    "sg:tags":[
        "caterer"
    ],
    "wof:name":"Aristocooks",
    "wof:placetype":"venue"
},
  "geometry": {"coordinates":[-0.073463,51.32901],"type":"Point"}
}