{
  "type": "Feature",
  "properties": {
    "iso:country":"GB",
    "sg:address":"Crocus Place, Crocus Street",
    "sg:city":"Nottingham",
    "sg:classifiers":[
        {
            "category":"Home & Garden",
            "subcategory":"Building Materials",
            "type":"Retail Goods"
        }
    ],
    "sg:postcode":"NG2 3DE",
    "sg:province":"Nottinghamshire",
    "sg:tags":[
        "furnishers",
        "bathroom",
        "planner"
    ],
    "wof:name":"Santura Ltd.",
    "wof:placetype":"venue"
},
  "geometry": {"coordinates":[-1.1452790499,52.9453735352],"type":"Point"}
}