{
  "type": "Feature",
  "properties": {
    "addr:full":"Burnside, Birks Road, Heddon On The Wall Newcastle-upon-tyne Northumberland NE15 0HF",
    "addr:postcode":"ne15 0hf",
    "addr:street":"Birks Road",
    "iso:country":"GB",
    "sg:address":"Burnside, Birks Road, Heddon On The Wall",
    "sg:city":"Newcastle-upon-tyne",
    "sg:classifiers":[
        {
            "category":"Home & Garden",
            "subcategory":"Building Materials",
            "type":"Retail Goods"
        },
        {
            "category":"Building & Trades",
            "subcategory":"Construction",
            "type":"Services"
        }
    ],
    "sg:phone":"+44 191 264 4707",
    "sg:postcode":"NE15 0HF",
    "sg:province":"Northumberland",
    "sg:tags":[
        "insulation",
        "specialised",
        "contractor",
        "installers"
    ],
    "wof:name":"J P S CAVITY WALL & LOFT INSULATION",
    "wof:placetype":"venue"
},
  "geometry": {"coordinates":[-1.7947679758,54.997303009],"type":"Point"}
}