{
  "type": "Feature",
  "properties": {
    "iso:country":"GB",
    "sg:address":"192 Kings Rd",
    "sg:city":"Chelsea",
    "sg:classifiers":[
        {
            "category":"Shopping",
            "subcategory":"Clothing, Apparel, & Fashions",
            "type":"Retail Goods"
        }
    ],
    "sg:phone":"+44 20 7376 4997",
    "sg:postcode":"SW3 5XP",
    "sg:province":"Greater London",
    "sg:tags":[
        "clothing",
        "fabric"
    ],
    "wof:name":"Natural Blue",
    "wof:placetype":"venue"
},
  "geometry": {"coordinates":[-0.166407,51.488335],"type":"Point"}
}