{
  "type": "Feature",
  "properties": {
    "iso:country":"GB",
    "sg:address":"Throne Road",
    "sg:city":"Rowley Regis",
    "sg:classifiers":[
        {
            "category":"Education",
            "subcategory":"University",
            "type":"Public Place"
        },
        {
            "category":"Education",
            "subcategory":"School",
            "type":"Public Place"
        }
    ],
    "sg:phone":"+44 121 559 5224",
    "sg:postcode":"B65 9LD",
    "sg:province":"West Midlands",
    "sg:tags":[
        "local",
        "adult",
        "authority"
    ],
    "wof:name":"Sandwell Metropolitan Borough Council",
    "wof:placetype":"venue"
},
  "geometry": {"coordinates":[-2.0382790565,52.4914398193],"type":"Point"}
}