{
  "type": "Feature",
  "properties": {
    "addr:full":"By The Brook, Buckland Road Bampton Gloucestershire OX18 2AA",
    "addr:postcode":"ox18 2aa",
    "addr:street":"Buckland Road",
    "iso:country":"GB",
    "sg:address":"By The Brook, Buckland Road",
    "sg:city":"Bampton",
    "sg:classifiers":[
        {
            "category":"Utilities",
            "type":"Services"
        }
    ],
    "sg:phone":"+44 1993 850202",
    "sg:postcode":"OX18 2AA",
    "sg:province":"Gloucestershire",
    "sg:tags":[
        "internet"
    ],
    "wof:name":"Internet Marketing Strategies Ltd",
    "wof:placetype":"venue"
},
  "geometry": {"coordinates":[-1.546758,51.727924],"type":"Point"}
}