{
  "type": "Feature",
  "properties": {
    "addr:full":"Unit 2 Tower Court, St Davids Road Swansea Swansea SA6 8QL",
    "addr:housenumber":"unit 2",
    "addr:postcode":"sa6 8ql",
    "addr:street":"Tower Court St Davids Road",
    "iso:country":"GB",
    "sg:address":"Unit 2 Tower Court, St Davids Road",
    "sg:city":"Swansea",
    "sg:classifiers":[
        {
            "category":"Home & Garden",
            "subcategory":"Hardware",
            "type":"Retail Goods"
        }
    ],
    "sg:phone":"+44 1792 701202",
    "sg:postcode":"SA6 8QL",
    "sg:province":"Swansea",
    "sg:tags":[
        "sealant",
        "glue",
        "adhesives"
    ],
    "wof:name":"S W B Industrial Components Ltd.",
    "wof:placetype":"venue"
},
  "geometry": {"coordinates":[-3.9167430401,51.6607551575],"type":"Point"}
}