{
  "type": "Feature",
  "properties": {
    "iso:country":"GB",
    "sg:address":"Lewannick House, Hurdon Road",
    "sg:city":"Launceston",
    "sg:classifiers":[
        {
            "category":"Shopping",
            "subcategory":"Department Store",
            "type":"Retail Goods"
        },
        {
            "category":"Home & Garden",
            "subcategory":"Hardware",
            "type":"Retail Goods"
        }
    ],
    "sg:postcode":"PL15 9HW",
    "sg:province":"Cornwall",
    "sg:tags":[
        "lawnmowers",
        "machinery"
    ],
    "wof:name":"Southwest Cycle & Garden Machinery",
    "wof:placetype":"venue"
},
  "geometry": {"coordinates":[-4.3559532166,50.6298713684],"type":"Point"}
}