{
  "type": "Feature",
  "properties": {
    "iso:country":"GB",
    "sg:address":"391 Northolt Rd",
    "sg:city":"Harrow",
    "sg:classifiers":[
        {
            "category":"Building & Trades",
            "subcategory":"Equipment Rental",
            "type":"Services"
        }
    ],
    "sg:phone":"+44 20 8423 3898",
    "sg:postcode":"HA2 8JD",
    "sg:province":"Greater London",
    "sg:tags":[
        "plant",
        "machinery"
    ],
    "wof:name":"Express Tool & Equipment Ltd",
    "wof:placetype":"venue"
},
  "geometry": {"coordinates":[-0.3579159975,51.5608024597],"type":"Point"}
}