{
  "type": "Feature",
  "properties": {
    "addr:full":"South Division, Viewmont Arduthie Road Stonehaven Aberdeenshire AB39 2DQ",
    "addr:postcode":"ab39 2dq",
    "addr:street":"South Division Viewmont Arduthie Road",
    "iso:country":"GB",
    "sg:address":"South Division, Viewmont Arduthie Road",
    "sg:city":"Stonehaven",
    "sg:classifiers":[
        {
            "category":"Government",
            "subcategory":"Office",
            "type":"Public Place"
        }
    ],
    "sg:phone":"+44 1569 762001",
    "sg:postcode":"AB39 2DQ",
    "sg:province":"Aberdeenshire",
    "sg:tags":[
        "local"
    ],
    "wof:name":"Aberdeenshire Council",
    "wof:placetype":"venue"
},
  "geometry": {"coordinates":[-2.208759,56.963741],"type":"Point"}
}