{
  "type": "Feature",
  "properties": {
    "addr:full":"216-218 Hither Green Lane Lewisham Greater London SE13 6RT",
    "addr:housenumber":"216-218",
    "addr:postcode":"se13 6rt",
    "addr:street":"Hither Green Lane",
    "iso:country":"GB",
    "sg:address":"216-218 Hither Green Lane",
    "sg:city":"Lewisham",
    "sg:classifiers":[
        {
            "category":"Shopping",
            "type":"Retail Goods"
        }
    ],
    "sg:phone":"+44 20 8244 2088",
    "sg:postcode":"SE13 6RT",
    "sg:province":"Greater London",
    "sg:tags":[
        "part",
        "accessory"
    ],
    "wof:name":"Autic Motor Spares",
    "wof:placetype":"venue"
},
  "geometry": {"coordinates":[-0.006099,51.450771],"type":"Point"}
}