{
  "type": "Feature",
  "properties": {
    "iso:country":"GB",
    "sg:address":"Cosaig, Glenelg",
    "sg:city":"Kyle",
    "sg:classifiers":[
        {
            "category":"Taxi",
            "type":"Transportation"
        }
    ],
    "sg:phone":"+44 1599 522233",
    "sg:postcode":"IV40 8LB",
    "sg:province":"Highland",
    "sg:tags":[
        "mini",
        "cab"
    ],
    "wof:name":"Diversions",
    "wof:placetype":"venue"
},
  "geometry": {"coordinates":[-5.714052,57.280945],"type":"Point"}
}