{
  "type": "Feature",
  "properties": {
    "iso:country":"GB",
    "sg:address":"15 Beaconsfield St, Acomb",
    "sg:city":"York",
    "sg:classifiers":[
        {
            "category":"Building & Trades",
            "subcategory":"Construction",
            "type":"Services"
        }
    ],
    "sg:phone":"+44 1904 783829",
    "sg:postcode":"YO24 4NB",
    "sg:province":"North Yorkshire",
    "sg:tags":[
        "builder"
    ],
    "wof:name":"Conway Property Services",
    "wof:placetype":"venue"
},
  "geometry": {"coordinates":[-1.1225459576,53.9552841187],"type":"Point"}
}