{
  "type": "Feature",
  "properties": {
    "addr:full":"Unit 1 Moreton Park Industrial E, State Moreton Roa Luton Bedfordshire LU2 0TL",
    "addr:housenumber":"unit 1",
    "addr:postcode":"lu2 0tl",
    "addr:street":"Moreton Park Industrial E State",
    "iso:country":"GB",
    "sg:address":"Unit 1 Moreton Park Industrial E, State Moreton Roa",
    "sg:city":"Luton",
    "sg:classifiers":[
        {
            "category":"Manufacturing",
            "subcategory":"Rubber & Plastics",
            "type":"Manufacturing & Wholesale Goods"
        },
        {
            "category":"Professional",
            "subcategory":"Printing & Photocopies",
            "type":"Services"
        }
    ],
    "sg:phone":"+44 1582 734630",
    "sg:postcode":"LU2 0TL",
    "sg:province":"Bedfordshire",
    "sg:tags":[
        "injection",
        "moulding",
        "printer"
    ],
    "wof:name":"A M A Plastics",
    "wof:placetype":"venue"
},
  "geometry": {"coordinates":[-0.399594,51.892353],"type":"Point"}
}