{
  "type": "Feature",
  "properties": {
    "addr:full":"Reynard House, 5 Castlefield Rd Reigate Surrey RH2 0SA",
    "addr:housenumber":"5",
    "addr:postcode":"rh2 0sa",
    "addr:street":"Castlefield Rd",
    "iso:country":"GB",
    "sg:address":"Reynard House, 5 Castlefield Rd",
    "sg:city":"Reigate",
    "sg:classifiers":[
        {
            "category":"Real Estate",
            "subcategory":"Surveying",
            "type":"Services"
        }
    ],
    "sg:phone":"+44 1737 230700",
    "sg:postcode":"RH2 0SA",
    "sg:province":"Surrey",
    "sg:tags":[
        "surveyor",
        "valuer"
    ],
    "wof:name":"Michael Rogers",
    "wof:placetype":"venue"
},
  "geometry": {"coordinates":[-0.204465,51.239094],"type":"Point"}
}