{
  "type": "Feature",
  "properties": {
    "iso:country":"GB",
    "sg:address":"Kirk Hill Farm, 355 Gosberton Westhorpe, Gosberton",
    "sg:city":"Spalding",
    "sg:classifiers":[
        {
            "category":"Farming",
            "subcategory":"Livestock Farm",
            "type":"Manufacturing & Wholesale Goods"
        }
    ],
    "sg:phone":"+44 1775 750455",
    "sg:postcode":"PE11 4ER",
    "sg:province":"Lincolnshire",
    "sg:tags":[
        "others"
    ],
    "wof:name":"S F Spridgen & Son",
    "wof:placetype":"venue"
},
  "geometry": {"coordinates":[-0.161082,52.868965],"type":"Point"}
}