{
  "type": "Feature",
  "properties": {
    "addr:full":"Fishers Slack Cottage, Larbreck Rd Poulton Le Fylde Lancashire FY6 8NF",
    "addr:postcode":"fy6 8nf",
    "addr:street":"Larbreck Rd",
    "iso:country":"GB",
    "sg:address":"Fishers Slack Cottage, Larbreck Rd",
    "sg:city":"Poulton Le Fylde",
    "sg:classifiers":[
        {
            "category":"Building & Trades",
            "subcategory":"Plumbing",
            "type":"Services"
        }
    ],
    "sg:phone":"+44 1995 670160",
    "sg:postcode":"FY6 8NF",
    "sg:province":"Lancashire",
    "sg:tags":[
        "central",
        "heating"
    ],
    "wof:name":"A D Hawthornthwaite",
    "wof:placetype":"venue"
},
  "geometry": {"coordinates":[-2.994658947,53.8480796814],"type":"Point"}
}