{
  "type": "Feature",
  "properties": {
    "iso:country":"GB",
    "sg:address":"106 Pinstone Street",
    "sg:city":"Sheffield",
    "sg:classifiers":[
        {
            "category":"Shopping",
            "subcategory":"Catalog Store",
            "type":"Retail Goods"
        }
    ],
    "sg:phone":"+44 114 272 8835",
    "sg:postcode":"S1 2HQ",
    "sg:province":"South Yorkshire",
    "sg:tags":[
        "mail",
        "order",
        "house"
    ],
    "wof:name":"Damart",
    "wof:placetype":"venue"
},
  "geometry": {"coordinates":[-1.471628,53.37825],"type":"Point"}
}