{
  "type": "Feature",
  "properties": {
    "addr:full":"1 Tavelhurst, Two Mile Ash Milton Keynes Buckinghamshire MK8 8EE",
    "addr:housenumber":"1",
    "addr:postcode":"mk8 8ee",
    "addr:street":"Tavelhurst Two Mile Ash",
    "iso:country":"GB",
    "sg:address":"1 Tavelhurst, Two Mile Ash",
    "sg:city":"Milton Keynes",
    "sg:classifiers":[
        {
            "category":"Real Estate",
            "subcategory":"Surveying",
            "type":"Services"
        }
    ],
    "sg:phone":"+44 1908 263939",
    "sg:postcode":"MK8 8EE",
    "sg:province":"Buckinghamshire",
    "sg:tags":[
        "building",
        "surveyor"
    ],
    "wof:name":"Turner,Jon,(Surveying) Ltd",
    "wof:placetype":"venue"
},
  "geometry": {"coordinates":[-0.8007900119,52.0368385315],"type":"Point"}
}