{
  "type": "Feature",
  "properties": {
    "addr:full":"Annanside Moffat Dumfries and Galloway DG10 9HB",
    "addr:postcode":"dg10 9hb",
    "addr:street":"Annanside",
    "iso:country":"GB",
    "sg:address":"Annanside",
    "sg:city":"Moffat",
    "sg:classifiers":[
        {
            "category":"Retail",
            "subcategory":"Auto Repair",
            "type":"Services"
        }
    ],
    "sg:phone":"+44 1683 220535",
    "sg:postcode":"DG10 9HB",
    "sg:province":"Dumfries and Galloway",
    "sg:tags":[
        "modification",
        "garage"
    ],
    "wof:name":"Hepburn Motors",
    "wof:placetype":"venue"
},
  "geometry": {"coordinates":[-3.4472830296,55.3319168091],"type":"Point"}
}