{
  "type": "Feature",
  "properties": {
    "addr:full":"158 London Road Kingston-upon-thames Greater London KT2 6QW",
    "addr:housenumber":"158",
    "addr:postcode":"kt2 6qw",
    "addr:street":"London Road",
    "iso:country":"GB",
    "sg:address":"158 London Road",
    "sg:city":"Kingston-upon-thames",
    "sg:classifiers":[
        {
            "category":"Professional",
            "type":"Services"
        }
    ],
    "sg:phone":"+44 20 8541 4414",
    "sg:postcode":"KT2 6QW",
    "sg:province":"Greater London",
    "sg:tags":[
        "interior",
        "furnishers",
        "designer"
    ],
    "wof:name":"Mc Atkinson Cormack & Zand Ltd.",
    "wof:placetype":"venue"
},
  "geometry": {"coordinates":[-0.2892419994,51.4123916626],"type":"Point"}
}