{
  "type": "Feature",
  "properties": {
    "addr:full":"5 Suffolk Parade Cheltenham Gloucestershire GL50 2AB",
    "addr:housenumber":"5",
    "addr:postcode":"gl50 2ab",
    "addr:street":"Suffolk Parade",
    "iso:country":"GB",
    "sg:address":"5 Suffolk Parade",
    "sg:city":"Cheltenham",
    "sg:classifiers":[
        {
            "category":"Food & Beverages",
            "subcategory":"Meat & Fish",
            "type":"Retail Goods"
        }
    ],
    "sg:phone":"+44 1242 522151",
    "sg:postcode":"GL50 2AB",
    "sg:province":"Gloucestershire",
    "sg:tags":[
        "butcher"
    ],
    "wof:name":"M J & J A Watts",
    "wof:placetype":"venue"
},
  "geometry": {"coordinates":[-2.079606,51.893066],"type":"Point"}
}