{
  "type": "Feature",
  "properties": {
    "iso:country":"GB",
    "sg:address":"Arbury Rd",
    "sg:city":"Nuneaton",
    "sg:classifiers":[
        {
            "category":"Place Of Worship",
            "type":"Public Place"
        }
    ],
    "sg:phone":"+44 24 7638 4303",
    "sg:postcode":"CV10 7NJ",
    "sg:province":"Leicestershire",
    "wof:name":"Stockingford Methodist Church",
    "wof:placetype":"venue"
},
  "geometry": {"coordinates":[-1.495939,52.51553],"type":"Point"}
}