{
  "type": "Feature",
  "properties": {
    "addr:full":"106 Underwood, Great Hollands Bracknell Berkshire RG12 8XN",
    "addr:housenumber":"106",
    "addr:postcode":"rg12 8xn",
    "addr:street":"Underwood Great Hollands",
    "iso:country":"GB",
    "sg:address":"106 Underwood, Great Hollands",
    "sg:city":"Bracknell",
    "sg:classifiers":[
        {
            "category":"Professional",
            "subcategory":"Computer Services",
            "type":"Services"
        }
    ],
    "sg:phone":"+44 1344 645388",
    "sg:postcode":"RG12 8XN",
    "sg:province":"Berkshire",
    "sg:tags":[
        "system",
        "software"
    ],
    "wof:name":"Tedium Ltd.",
    "wof:placetype":"venue"
},
  "geometry": {"coordinates":[-0.772085011,51.3964042664],"type":"Point"}
}