{
  "type": "Feature",
  "properties": {
    "addr:full":"23 Reddicap Hl Sutton Coldfield Staffordshire B75 7BQ",
    "addr:housenumber":"23",
    "addr:postcode":"b75 7bq",
    "addr:street":"Reddicap Hl",
    "iso:country":"GB",
    "sg:address":"23 Reddicap Hl",
    "sg:city":"Sutton Coldfield",
    "sg:classifiers":[
        {
            "category":"Professional",
            "subcategory":"Art Services",
            "type":"Services"
        }
    ],
    "sg:phone":"+44 121 378 0088",
    "sg:postcode":"B75 7BQ",
    "sg:province":"Staffordshire",
    "sg:tags":[
        "consultant",
        "design"
    ],
    "wof:name":"Red & Green",
    "wof:placetype":"venue"
},
  "geometry": {"coordinates":[-1.807435,52.560028],"type":"Point"}
}