{
  "type": "Feature",
  "properties": {
    "iso:country":"GB",
    "sg:address":"Burridge Farm, Burridge",
    "sg:city":"Axminster",
    "sg:classifiers":[
        {
            "category":"Freight",
            "type":"Transportation"
        }
    ],
    "sg:postcode":"EX13 7DF",
    "sg:province":"Devon",
    "sg:tags":[
        "haulage",
        "road"
    ],
    "wof:name":"Keith Denslow",
    "wof:placetype":"venue"
},
  "geometry": {"coordinates":[-2.9749639034,50.852268219],"type":"Point"}
}