{
  "type": "Feature",
  "properties": {
    "iso:country":"GB",
    "sg:address":"Park Road South",
    "sg:city":"Middlesbrough",
    "sg:classifiers":[
        {
            "category":"Professional",
            "subcategory":"Business Services",
            "type":"Services"
        }
    ],
    "sg:phone":"+44 1642 826834",
    "sg:postcode":"TS4 2RD",
    "sg:province":"North Yorkshire",
    "sg:tags":[
        "bookmaker"
    ],
    "wof:name":"B P Racing",
    "wof:placetype":"venue"
},
  "geometry": {"coordinates":[-1.225074,54.56287],"type":"Point"}
}