{
  "type": "Feature",
  "properties": {
    "iso:country":"GB",
    "sg:address":"50 High Street",
    "sg:city":"Leamington Spa",
    "sg:classifiers":[
        {
            "category":"Fast Food",
            "type":"Food & Drink"
        }
    ],
    "sg:phone":"+44 1926 424909",
    "sg:postcode":"CV31 1LW",
    "sg:province":"Warwickshire",
    "sg:tags":[
        "away",
        "meal",
        "outlet",
        "take"
    ],
    "wof:name":"Wing Tai",
    "wof:placetype":"venue"
},
  "geometry": {"coordinates":[-1.5299429893,52.283821106],"type":"Point"}
}