{
  "type": "Feature",
  "properties": {
    "addr:full":"29 Meyrick Street Pembroke Dock Pembrokeshire SA72 6AL",
    "addr:housenumber":"29",
    "addr:postcode":"sa72 6al",
    "addr:street":"Meyrick Street",
    "iso:country":"GB",
    "sg:address":"29 Meyrick Street",
    "sg:city":"Pembroke Dock",
    "sg:classifiers":[
        {
            "category":"Fast Food",
            "type":"Food & Drink"
        },
        {
            "category":"Food & Beverages",
            "subcategory":"Meat & Fish",
            "type":"Retail Goods"
        }
    ],
    "sg:phone":"+44 1646 682699",
    "sg:postcode":"SA72 6AL",
    "sg:province":"Pembrokeshire",
    "sg:tags":[
        "shop",
        "chip"
    ],
    "wof:name":"Mr Chips",
    "wof:placetype":"venue"
},
  "geometry": {"coordinates":[-4.942492,51.693436],"type":"Point"}
}