{
  "type": "Feature",
  "properties": {
    "addr:full":"108 Central Road Worcester Park Surrey KT4 8DY",
    "addr:housenumber":"108",
    "addr:postcode":"kt4 8dy",
    "addr:street":"Central Road",
    "iso:country":"GB",
    "sg:address":"108 Central Road",
    "sg:city":"Worcester Park",
    "sg:classifiers":[
        {
            "category":"Retail",
            "subcategory":"Photofinishing",
            "type":"Services"
        }
    ],
    "sg:phone":"+44 20 8337 0478",
    "sg:postcode":"KT4 8DY",
    "sg:province":"Surrey",
    "sg:tags":[
        "photographic",
        "processor"
    ],
    "wof:name":"1-Hour Photo Shop",
    "wof:placetype":"venue"
},
  "geometry": {"coordinates":[-0.241439,51.378635],"type":"Point"}
}