{
  "type": "Feature",
  "properties": {
    "iso:country":"GB",
    "sg:address":"Clare St",
    "sg:city":"Swansea",
    "sg:classifiers":[
        {
            "category":"Autos & Motor Vehicles",
            "subcategory":"Automobile Sales",
            "type":"Retail Goods"
        }
    ],
    "sg:postcode":"SA5 9PG",
    "sg:province":"Swansea",
    "sg:tags":[
        "car"
    ],
    "wof:name":"Clare Street Autos",
    "wof:placetype":"venue"
},
  "geometry": {"coordinates":[-3.949259,51.640518],"type":"Point"}
}