{
  "type": "Feature",
  "properties": {
    "iso:country":"GB",
    "sg:address":"18 Furmston Court, Icknield Way",
    "sg:city":"Letchworth",
    "sg:classifiers":[
        {
            "category":"Building & Trades",
            "subcategory":"Cleaning & Sanitation",
            "type":"Services"
        }
    ],
    "sg:phone":"+44 1462 487271",
    "sg:postcode":"SG6 1UJ",
    "sg:province":"Hertfordshire",
    "sg:tags":[
        "computer",
        "telephone"
    ],
    "wof:name":"Compukleen Ltd.",
    "wof:placetype":"venue"
},
  "geometry": {"coordinates":[-0.220626995,51.9848670959],"type":"Point"}
}