{
  "type": "Feature",
  "properties": {
    "addr:full":"13 Motcomb Street, Milgravia London Greater London SW1X 8LB",
    "addr:housenumber":"13",
    "addr:postcode":"sw1x 8lb",
    "addr:street":"Motcomb Street",
    "iso:country":"GB",
    "sg:address":"13 Motcomb Street, Milgravia",
    "sg:city":"London",
    "sg:classifiers":[
        {
            "category":"Real Estate",
            "subcategory":"Developer",
            "type":"Services"
        }
    ],
    "sg:phone":"+44 20 7823 2560",
    "sg:postcode":"SW1X 8LB",
    "sg:province":"Greater London",
    "sg:tags":[
        "property"
    ],
    "wof:name":"Richcliff (Group) Ltd.",
    "wof:placetype":"venue"
},
  "geometry": {"coordinates":[-0.1567009985,51.4994812012],"type":"Point"}
}