{
  "type": "Feature",
  "properties": {
    "addr:full":"Berrow Court, Gardens Walk, Upton-upon-severn Worcester Gloucestershire WR8 0JP",
    "addr:postcode":"wr8 0jp",
    "addr:street":"Berrow Court Gardens Walk",
    "iso:country":"GB",
    "sg:address":"Berrow Court, Gardens Walk, Upton-upon-severn",
    "sg:city":"Worcester",
    "sg:classifiers":[
        {
            "category":"Social Services",
            "subcategory":"Adult Care",
            "type":"Services"
        }
    ],
    "sg:phone":"+44 1684 593718",
    "sg:postcode":"WR8 0JP",
    "sg:province":"Gloucestershire",
    "sg:tags":[
        "housing",
        "sheltered"
    ],
    "wof:name":"Berrow Court",
    "wof:placetype":"venue"
},
  "geometry": {"coordinates":[-2.215771,52.063133],"type":"Point"}
}