{
  "type": "Feature",
  "properties": {
    "iso:country":"GB",
    "sg:address":"7 Keighley Close",
    "sg:city":"Bury",
    "sg:classifiers":[
        {
            "category":"Shopping",
            "subcategory":"Department Store",
            "type":"Retail Goods"
        }
    ],
    "sg:postcode":"BL8 2JY",
    "sg:province":"Lancashire",
    "wof:name":"Starline Sales",
    "wof:placetype":"venue"
},
  "geometry": {"coordinates":[-2.338017,53.593739],"type":"Point"}
}