{
  "type": "Feature",
  "properties": {
    "addr:full":"Cill Chuimein Medical Centre Fort Augustus Highland PH32 4BH",
    "addr:postcode":"ph32 4bh",
    "addr:street":"Augustus",
    "iso:country":"GB",
    "sg:address":"Cill Chuimein Medical Centre",
    "sg:city":"Fort Augustus",
    "sg:classifiers":[
        {
            "category":"Health Services",
            "subcategory":"Doctor",
            "type":"Services"
        }
    ],
    "sg:phone":"+44 1320 366216",
    "sg:postcode":"PH32 4BH",
    "sg:province":"Highland",
    "sg:tags":[
        "practitioners"
    ],
    "wof:name":"CILL CHUIMEIN MEDICAL CENTRE",
    "wof:placetype":"venue"
},
  "geometry": {"coordinates":[-4.6806569099,57.1451034546],"type":"Point"}
}