{
  "type": "Feature",
  "properties": {
    "addr:full":"C R S Homeworld, Hedge End Retail Park, Charles Watts Way Southampton Hampshire SO30 4RT",
    "addr:postcode":"so30 4rt",
    "addr:street":"Retail Park Charles Watts Way",
    "iso:country":"GB",
    "sg:address":"C R S Homeworld, Hedge End Retail Park, Charles Watts Way",
    "sg:city":"Southampton",
    "sg:classifiers":[
        {
            "category":"Home & Garden",
            "subcategory":"Furniture",
            "type":"Retail Goods"
        }
    ],
    "sg:phone":"+44 1489 788707",
    "sg:postcode":"SO30 4RT",
    "sg:province":"Hampshire",
    "wof:name":"Christies Fitted Furniture",
    "wof:placetype":"venue"
},
  "geometry": {"coordinates":[-1.2925310135,50.9158401489],"type":"Point"}
}