{
  "type": "Feature",
  "properties": {
    "iso:country":"GB",
    "sg:address":"Unit 2 Mowat Industrial Estate, Sandown Road",
    "sg:city":"Watford",
    "sg:classifiers":[
        {
            "category":"Professional",
            "subcategory":"Printing & Photocopies",
            "type":"Services"
        }
    ],
    "sg:phone":"+44 1923 242244",
    "sg:postcode":"WD24 7UY",
    "sg:province":"Hertfordshire",
    "sg:tags":[
        "printer"
    ],
    "wof:name":"Deckprint Ltd.",
    "wof:placetype":"venue"
},
  "geometry": {"coordinates":[-0.3927800059,51.6729507446],"type":"Point"}
}