{
  "type": "Feature",
  "properties": {
    "iso:country":"GB",
    "sg:address":"Woodgate Farm, Crawley Lane, Kings Bromley",
    "sg:city":"Burton-on-trent",
    "sg:classifiers":[
        {
            "category":"Home & Garden",
            "subcategory":"Building Materials",
            "type":"Retail Goods"
        }
    ],
    "sg:postcode":"DE13 7JF",
    "sg:province":"Derbyshire",
    "sg:tags":[
        "roofing",
        "rafter",
        "beams"
    ],
    "wof:name":"The Little Craft Co.",
    "wof:placetype":"venue"
},
  "geometry": {"coordinates":[-1.821126,52.749306],"type":"Point"}
}