{
  "type": "Feature",
  "properties": {
    "iso:country":"GB",
    "sg:address":"Tithe Barn 3 South St, Isham",
    "sg:city":"Kettering",
    "sg:classifiers":[
        {
            "category":"Wholesale",
            "subcategory":"Office Equipment",
            "type":"Manufacturing & Wholesale Goods"
        }
    ],
    "sg:postcode":"NN14 1HP",
    "sg:province":"Northamptonshire",
    "sg:tags":[
        "partition",
        "cubicle"
    ],
    "wof:name":"Construction Services & Panels Ltd",
    "wof:placetype":"venue"
},
  "geometry": {"coordinates":[-0.7021539807,52.3558197021],"type":"Point"}
}