{
  "type": "Feature",
  "properties": {
    "iso:country":"GB",
    "sg:address":"Building 2e, Swan Lane, Hindley",
    "sg:city":"Wigan",
    "sg:classifiers":[
        {
            "category":"Building & Trades",
            "subcategory":"Plumbing",
            "type":"Services"
        },
        {
            "category":"Shopping",
            "subcategory":"Gifts & Souvenirs",
            "type":"Retail Goods"
        }
    ],
    "sg:phone":"+44 1942 526900",
    "sg:postcode":"WN2 4HD",
    "sg:province":"Lancashire",
    "sg:tags":[
        "ducting",
        "heating"
    ],
    "wof:name":"P S E Engineering Ltd.",
    "wof:placetype":"venue"
},
  "geometry": {"coordinates":[-2.5434670448,53.5299072266],"type":"Point"}
}