{
  "type": "Feature",
  "properties": {
    "addr:full":"Evington House, Cordery Road Leicester Leicestershire LE5 6DE",
    "addr:postcode":"le5 6de",
    "addr:street":"Cordery Road",
    "iso:country":"GB",
    "sg:address":"Evington House, Cordery Road",
    "sg:city":"Leicester",
    "sg:classifiers":[
        {
            "category":"Community Center",
            "type":"Public Place"
        }
    ],
    "sg:phone":"+44 116 273 7726",
    "sg:postcode":"LE5 6DE",
    "sg:province":"Leicestershire",
    "sg:tags":[
        "centre"
    ],
    "wof:name":"Park Services",
    "wof:placetype":"venue"
},
  "geometry": {"coordinates":[-1.076014,52.625889],"type":"Point"}
}