{
  "type": "Feature",
  "properties": {
    "iso:country":"GB",
    "sg:address":"Wellingborough Road",
    "sg:city":"Northampton",
    "sg:classifiers":[
        {
            "category":"Social Services",
            "subcategory":"Retirement Home",
            "type":"Services"
        }
    ],
    "sg:postcode":"NN3 3JF",
    "sg:province":"Northamptonshire",
    "sg:tags":[
        "residential",
        "care"
    ],
    "wof:name":"St.Johns Home",
    "wof:placetype":"venue"
},
  "geometry": {"coordinates":[-0.864814,52.249805],"type":"Point"}
}