{
  "type": "Feature",
  "properties": {
    "addr:full":"7 Woodyard Lane, Woolaton Nottingham Nottinghamshire NG8 1GW",
    "addr:housenumber":"7",
    "addr:postcode":"ng8 1gw",
    "addr:street":"Woodyard Lane",
    "iso:country":"GB",
    "sg:address":"7 Woodyard Lane, Woolaton",
    "sg:city":"Nottingham",
    "sg:classifiers":[
        {
            "category":"Social Services",
            "subcategory":"Child Care",
            "type":"Services"
        }
    ],
    "sg:phone":"+44 115 928 2169",
    "sg:postcode":"NG8 1GW",
    "sg:province":"Nottinghamshire",
    "sg:tags":[
        "children's",
        "home"
    ],
    "wof:name":"Cherry Orchard House",
    "wof:placetype":"venue"
},
  "geometry": {"coordinates":[-1.2092100382,52.9555854797],"type":"Point"}
}