{
  "type": "Feature",
  "properties": {
    "addr:full":"Firbank Way Leighton Buzzard Bedfordshire LU7 4YP",
    "addr:postcode":"lu7 4yp",
    "addr:street":"Firbank Way",
    "iso:country":"GB",
    "sg:address":"Firbank Way",
    "sg:city":"Leighton Buzzard",
    "sg:classifiers":[
        {
            "category":"Freight",
            "type":"Transportation"
        }
    ],
    "sg:phone":"+44 1525 850009",
    "sg:postcode":"LU7 4YP",
    "sg:province":"Bedfordshire",
    "sg:tags":[
        "haulage",
        "transport",
        "road"
    ],
    "wof:name":"S & J Pierce Transport",
    "wof:placetype":"venue"
},
  "geometry": {"coordinates":[-0.656957,51.908253],"type":"Point"}
}