{
  "type": "Feature",
  "properties": {
    "addr:full":"The Lodge, Rothersthorpe Northampton Northamptonshire NN4 9QY",
    "addr:housenumber":"rothersthorpe",
    "addr:postcode":"nn4 9qy",
    "addr:street":"Northampton",
    "iso:country":"GB",
    "sg:address":"The Lodge, Rothersthorpe",
    "sg:city":"Northampton",
    "sg:classifiers":[
        {
            "category":"Real Estate",
            "subcategory":"Developer",
            "type":"Services"
        }
    ],
    "sg:phone":"+44 1604 832693",
    "sg:postcode":"NN4 9QY",
    "sg:province":"Northamptonshire",
    "sg:tags":[
        "property"
    ],
    "wof:name":"Sygnet Project Management",
    "wof:placetype":"venue"
},
  "geometry": {"coordinates":[-0.9518300295,52.2134208679],"type":"Point"}
}