{
  "type": "Feature",
  "properties": {
    "addr:full":"Greenwood Crescent Warrington Cheshire WA2 0EA",
    "addr:postcode":"wa2 0ea",
    "addr:street":"Greenwood Crescent",
    "iso:country":"GB",
    "sg:address":"Greenwood Crescent",
    "sg:city":"Warrington",
    "sg:classifiers":[
        {
            "category":"Social Services",
            "subcategory":"Retirement Home",
            "type":"Services"
        }
    ],
    "sg:phone":"+44 1925 815944",
    "sg:postcode":"WA2 0EA",
    "sg:province":"Cheshire",
    "sg:tags":[
        "residential",
        "care"
    ],
    "wof:name":"Houghton Hall",
    "wof:placetype":"venue"
},
  "geometry": {"coordinates":[-2.568334,53.414974],"type":"Point"}
}