{
  "type": "Feature",
  "properties": {
    "iso:country":"GB",
    "sg:address":"Park Of Tongland, Tongland",
    "sg:city":"Kirkcudbright",
    "sg:classifiers":[
        {
            "category":"Farming",
            "subcategory":"Livestock Farm",
            "type":"Manufacturing & Wholesale Goods"
        }
    ],
    "sg:postcode":"DG6 4NE",
    "sg:province":"Dumfries and Galloway",
    "sg:tags":[
        "others"
    ],
    "wof:name":"John Corrie",
    "wof:placetype":"venue"
},
  "geometry": {"coordinates":[-4.0476388931,54.836971283],"type":"Point"}
}