{
  "type": "Feature",
  "properties": {
    "addr:full":"Cambrian Service Station Dolwyddelan Conwy LL25 0DX",
    "addr:postcode":"ll25 0dx",
    "iso:country":"GB",
    "sg:address":"Cambrian Service Station",
    "sg:city":"Dolwyddelan",
    "sg:classifiers":[
        {
            "category":"Autos & Motor Vehicles",
            "subcategory":"Fuel & Gas Station",
            "type":"Retail Goods"
        },
        {
            "category":"Sports & Exercise",
            "subcategory":"Tennis Court",
            "type":"Entertainment"
        }
    ],
    "sg:postcode":"LL25 0DX",
    "sg:province":"Conwy",
    "sg:tags":[
        "breakdown",
        "petrol",
        "filling",
        "recovery"
    ],
    "wof:name":"Cambrian Service Station",
    "wof:placetype":"venue"
},
  "geometry": {"coordinates":[-3.8905580044,53.0536193848],"type":"Point"}
}