{
  "type": "Feature",
  "properties": {
    "addr:full":"Gresham House, 2a Unicorn Trading Estate, Weydown Lane Haslemere Hampshire GU27 1DN",
    "addr:housenumber":"2a;trading estate",
    "addr:postcode":"gu27 1dn",
    "addr:street":"Weydown Lane",
    "iso:country":"GB",
    "sg:address":"Gresham House, 2a Unicorn Trading Estate, Weydown Lane",
    "sg:city":"Haslemere",
    "sg:classifiers":[
        {
            "category":"Building & Trades",
            "subcategory":"Electrical",
            "type":"Services"
        }
    ],
    "sg:phone":"+44 1428 651919",
    "sg:postcode":"GU27 1DN",
    "sg:province":"Hampshire",
    "sg:tags":[
        "lighting"
    ],
    "wof:name":"Deltalight (U K) Ltd.",
    "wof:placetype":"venue"
},
  "geometry": {"coordinates":[-0.708724,51.088791],"type":"Point"}
}