{
  "type": "Feature",
  "properties": {
    "iso:country":"GB",
    "sg:address":"22 Chesterfield Road",
    "sg:city":"Dronfield",
    "sg:classifiers":[
        {
            "category":"Shopping",
            "type":"Retail Goods"
        }
    ],
    "sg:phone":"+44 1246 418752",
    "sg:postcode":"S18 2XB",
    "sg:province":"Derbyshire",
    "sg:tags":[
        "part",
        "accessory"
    ],
    "wof:name":"Donfield Motor Spares",
    "wof:placetype":"venue"
},
  "geometry": {"coordinates":[-1.4668450356,53.3010673523],"type":"Point"}
}