{
  "type": "Feature",
  "properties": {
    "iso:country":"GB",
    "sg:address":"38 Lewis Wynd",
    "sg:city":"Irvine",
    "sg:classifiers":[
        {
            "category":"Retail",
            "subcategory":"Driving School",
            "type":"Services"
        }
    ],
    "sg:postcode":"KA11 1HL",
    "sg:province":"East Ayrshire",
    "wof:name":"Alan Murphy School of Motoring",
    "wof:placetype":"venue"
},
  "geometry": {"coordinates":[-4.637449,55.614895],"type":"Point"}
}