{
  "type": "Feature",
  "properties": {
    "addr:full":"178 Burscough St Ormskirk Lancashire L39 2EY",
    "addr:housenumber":"178",
    "addr:postcode":"l39 2ey",
    "addr:street":"Burscough St",
    "iso:country":"GB",
    "sg:address":"178 Burscough St",
    "sg:city":"Ormskirk",
    "sg:classifiers":[
        {
            "category":"Building & Trades",
            "subcategory":"Construction",
            "type":"Services"
        }
    ],
    "sg:postcode":"L39 2EY",
    "sg:province":"Lancashire",
    "sg:tags":[
        "builder"
    ],
    "wof:name":"Cribb,Paul,",
    "wof:placetype":"venue"
},
  "geometry": {"coordinates":[-2.882304,53.571571],"type":"Point"}
}