{
  "type": "Feature",
  "properties": {
    "addr:full":"49 High Street, South Kyme Lincoln Lincolnshire LN4 4AD",
    "addr:housenumber":"49",
    "addr:postcode":"ln4 4ad",
    "addr:street":"High Street South",
    "iso:country":"GB",
    "sg:address":"49 High Street, South Kyme",
    "sg:city":"Lincoln",
    "sg:classifiers":[
        {
            "category":"Shopping",
            "subcategory":"Used Merchandise",
            "type":"Retail Goods"
        }
    ],
    "sg:postcode":"LN4 4AD",
    "sg:province":"Lincolnshire",
    "sg:tags":[
        "shop",
        "second-hand"
    ],
    "wof:name":"Gary's Secondhand Shop",
    "wof:placetype":"venue"
},
  "geometry": {"coordinates":[-0.277535,53.078461],"type":"Point"}
}