{
  "type": "Feature",
  "properties": {
    "iso:country":"GB",
    "sg:address":"Calves Hill",
    "sg:city":"Cheltenham",
    "sg:classifiers":[
        {
            "category":"Manufacturing",
            "subcategory":"Building Materials",
            "type":"Manufacturing & Wholesale Goods"
        }
    ],
    "sg:postcode":"GL54 4AH",
    "sg:province":"Gloucestershire",
    "sg:tags":[
        "tile",
        "mnfrs"
    ],
    "wof:name":"Hill & Valley Tiles",
    "wof:placetype":"venue"
},
  "geometry": {"coordinates":[-1.9177999496,51.8028411865],"type":"Point"}
}