{
  "type": "Feature",
  "properties": {
    "addr:full":"Bents St Sunderland Tyne and Wear SR6 7TN",
    "addr:postcode":"sr6 7tn",
    "addr:street":"Bents St",
    "iso:country":"GB",
    "sg:address":"Bents St",
    "sg:city":"Sunderland",
    "sg:classifiers":[
        {
            "category":"Farming",
            "subcategory":"Fish & Marine Products",
            "type":"Manufacturing & Wholesale Goods"
        }
    ],
    "sg:phone":"+44 191 529 2649",
    "sg:postcode":"SR6 7TN",
    "sg:province":"Tyne and Wear",
    "sg:tags":[
        "fishmonger"
    ],
    "wof:name":"Whitburn Sea Foods",
    "wof:placetype":"venue"
},
  "geometry": {"coordinates":[-1.4037599564,54.9455795288],"type":"Point"}
}