{
  "type": "Feature",
  "properties": {
    "iso:country":"GB",
    "sg:address":"6 Cobham Towers Sutton Place",
    "sg:city":"Bexhill On Sea",
    "sg:classifiers":[
        {
            "category":"Professional",
            "type":"Services"
        }
    ],
    "sg:phone":"+44 1424 735901",
    "sg:postcode":"TN40 1PG",
    "sg:province":"East Sussex",
    "sg:tags":[
        "repair",
        "tech",
        "maintenance"
    ],
    "wof:name":"Brimstone Computer Consultancy",
    "wof:placetype":"venue"
},
  "geometry": {"coordinates":[0.4787310064,50.8449554443],"type":"Point"}
}