{
  "type": "Feature",
  "properties": {
    "addr:full":"23 King St Cambridge Cambridgeshire CB1 1LH",
    "addr:housenumber":"23",
    "addr:postcode":"cb1 1lh",
    "addr:street":"King St",
    "iso:country":"GB",
    "sg:address":"23 King St",
    "sg:city":"Cambridge",
    "sg:classifiers":[
        {
            "category":"Professional",
            "subcategory":"Computer Services",
            "type":"Services"
        }
    ],
    "sg:phone":"+44 1223 506505",
    "sg:postcode":"CB1 1LH",
    "sg:province":"Cambridgeshire",
    "sg:tags":[
        "system",
        "software"
    ],
    "wof:name":"Pceez Ltd",
    "wof:placetype":"venue"
},
  "geometry": {"coordinates":[0.1227639988,52.2072181702],"type":"Point"}
}