{
  "type": "Feature",
  "properties": {
    "iso:country":"GB",
    "sg:address":"22 Fenkle Street",
    "sg:city":"Alnwick",
    "sg:classifiers":[
        {
            "category":"Personal",
            "type":"Services"
        }
    ],
    "sg:postcode":"NE66 1HR",
    "sg:province":"Northumberland",
    "sg:tags":[
        "wedding"
    ],
    "wof:name":"Northumbria Bride & Groom",
    "wof:placetype":"venue"
},
  "geometry": {"coordinates":[-1.707597,55.414021],"type":"Point"}
}