{
  "type": "Feature",
  "properties": {
    "addr:full":"48 Stirling Street Alva Clackmannanshire FK12 5EA",
    "addr:housenumber":"48",
    "addr:postcode":"fk12 5ea",
    "addr:street":"Stirling Street",
    "iso:country":"GB",
    "sg:address":"48 Stirling Street",
    "sg:city":"Alva",
    "sg:classifiers":[
        {
            "category":"Travel",
            "subcategory":"Hotels & Motels",
            "type":"Entertainment"
        }
    ],
    "sg:phone":"+44 1259 762884",
    "sg:postcode":"FK12 5EA",
    "sg:province":"Clackmannanshire",
    "wof:name":"The Johnstone Arms",
    "wof:placetype":"venue"
},
  "geometry": {"coordinates":[-3.7987360954,56.1531715393],"type":"Point"}
}