{
  "type": "Feature",
  "properties": {
    "iso:country":"GB",
    "sg:address":"12 Pyket Way",
    "sg:city":"Northampton",
    "sg:classifiers":[
        {
            "category":"Manufacturing",
            "subcategory":"Tools & Machinery",
            "type":"Manufacturing & Wholesale Goods"
        }
    ],
    "sg:phone":"+44 1604 405891",
    "sg:postcode":"NN3 3JU",
    "sg:province":"Northamptonshire",
    "sg:tags":[
        "society",
        "friendly"
    ],
    "wof:name":"H R Thadani & Co. (Holdings) Ltd.",
    "wof:placetype":"venue"
},
  "geometry": {"coordinates":[-0.843786,52.250458],"type":"Point"}
}