{
  "type": "Feature",
  "properties": {
    "addr:full":"393 Lincoln Road Enfield Greater London EN3 4AG",
    "addr:housenumber":"393",
    "addr:postcode":"en3 4ag",
    "addr:street":"Lincoln Road",
    "iso:country":"GB",
    "sg:address":"393 Lincoln Road",
    "sg:city":"Enfield",
    "sg:classifiers":[
        {
            "category":"Insurance",
            "subcategory":"Insurance Agent",
            "type":"Services"
        }
    ],
    "sg:phone":"+44 20 8804 6225",
    "sg:postcode":"EN3 4AG",
    "sg:province":"Greater London",
    "wof:name":"Midway Insurance Services Ltd.",
    "wof:placetype":"venue"
},
  "geometry": {"coordinates":[-0.0507499985,51.6436080933],"type":"Point"}
}