{
  "type": "Feature",
  "properties": {
    "addr:full":"55 Thorn Gro Cheadle Cheshire SK8 7LP",
    "addr:housenumber":"55",
    "addr:postcode":"sk8 7lp",
    "addr:street":"Thorn Gro Cheadle",
    "iso:country":"GB",
    "sg:address":"55 Thorn Gro",
    "sg:city":"Cheadle",
    "sg:classifiers":[
        {
            "category":"Arts & Performance",
            "subcategory":"Music",
            "type":"Entertainment"
        }
    ],
    "sg:phone":"+44 161 439 2657",
    "sg:postcode":"SK8 7LP",
    "sg:province":"Cheshire",
    "sg:tags":[
        "mobile",
        "disco"
    ],
    "wof:name":"Lomax Discos",
    "wof:placetype":"venue"
},
  "geometry": {"coordinates":[-2.1897990704,53.3605690002],"type":"Point"}
}