{
  "type": "Feature",
  "properties": {
    "addr:full":"87 Robert St Milford Haven Pembrokeshire SA73 2DH",
    "addr:housenumber":"87",
    "addr:postcode":"sa73 2dh",
    "addr:street":"Robert St",
    "iso:country":"GB",
    "sg:address":"87 Robert St",
    "sg:city":"Milford Haven",
    "sg:classifiers":[
        {
            "category":"Shopping",
            "subcategory":"Discount & Variety Stores",
            "type":"Retail Goods"
        }
    ],
    "sg:phone":"+44 1646 698962",
    "sg:postcode":"SA73 2DH",
    "sg:province":"Pembrokeshire",
    "sg:tags":[
        "centre"
    ],
    "wof:name":"Richvick Sportswear",
    "wof:placetype":"venue"
},
  "geometry": {"coordinates":[-5.036161,51.713749],"type":"Point"}
}