{
  "type": "Feature",
  "properties": {
    "addr:full":"3a Moorland Parade, Moorland Way Poole Dorset BH16 5JS",
    "addr:housenumber":"3a;parade",
    "addr:postcode":"bh16 5js",
    "addr:street":"Moorland;Moorland Way",
    "iso:country":"GB",
    "sg:address":"3a Moorland Parade, Moorland Way",
    "sg:city":"Poole",
    "sg:classifiers":[
        {
            "category":"Shopping",
            "subcategory":"Florist",
            "type":"Retail Goods"
        }
    ],
    "sg:phone":"+44 1202 621911",
    "sg:postcode":"BH16 5JS",
    "sg:province":"Dorset",
    "wof:name":"Broadway Flowers",
    "wof:placetype":"venue"
},
  "geometry": {"coordinates":[-2.033834,50.737007],"type":"Point"}
}