{
  "type": "Feature",
  "properties": {
    "addr:full":"Unit 9, Boston Court Salford Greater Manchester M5 2GN",
    "addr:housenumber":"unit 9",
    "addr:postcode":"m5 2gn",
    "addr:street":"Boston Court",
    "iso:country":"GB",
    "sg:address":"Unit 9, Boston Court",
    "sg:city":"Salford",
    "sg:classifiers":[
        {
            "category":"Professional",
            "type":"Services"
        }
    ],
    "sg:phone":"+44 161 872 5005",
    "sg:postcode":"M5 2GN",
    "sg:province":"Greater Manchester",
    "sg:tags":[
        "caterer"
    ],
    "wof:name":"Selfresh Salads",
    "wof:placetype":"venue"
},
  "geometry": {"coordinates":[-2.2993741035,53.4774436951],"type":"Point"}
}