{
  "type": "Feature",
  "properties": {
    "addr:full":"3 Bestwood Park Chesterfield Derbyshire S45 9LD",
    "addr:housenumber":"3",
    "addr:postcode":"s45 9ld",
    "addr:street":"Bestwood Park",
    "iso:country":"GB",
    "sg:address":"3 Bestwood Park",
    "sg:city":"Chesterfield",
    "sg:classifiers":[
        {
            "category":"Building & Trades",
            "subcategory":"Construction",
            "type":"Services"
        }
    ],
    "sg:phone":"+44 1246 861665",
    "sg:postcode":"S45 9LD",
    "sg:province":"Derbyshire",
    "sg:tags":[
        "decorator",
        "painter"
    ],
    "wof:name":"G Smith",
    "wof:placetype":"venue"
},
  "geometry": {"coordinates":[-1.4107739925,53.1657981873],"type":"Point"}
}