{
  "type": "Feature",
  "properties": {
    "iso:country":"GB",
    "sg:address":"4-7 Alfred Rd, Sparkhill",
    "sg:city":"Birmingham",
    "sg:classifiers":[
        {
            "category":"Home & Garden",
            "subcategory":"Carpets & Floor Coverings",
            "type":"Retail Goods"
        }
    ],
    "sg:phone":"+44 121 766 8823",
    "sg:postcode":"B11 4PB",
    "sg:province":"West Midlands",
    "sg:tags":[
        "carpets",
        "retailer",
        "rug",
        "matting"
    ],
    "wof:name":"S K Carpets",
    "wof:placetype":"venue"
},
  "geometry": {"coordinates":[-1.863289,52.44994],"type":"Point"}
}