{
  "type": "Feature",
  "properties": {
    "iso:country":"GB",
    "sg:address":"Bucks Drove, Ramsey St Marys",
    "sg:city":"Huntingdon",
    "sg:classifiers":[
        {
            "category":"Farming",
            "subcategory":"Livestock Farm",
            "type":"Manufacturing & Wholesale Goods"
        }
    ],
    "sg:phone":"+44 1733 844250",
    "sg:postcode":"PE26 2TA",
    "sg:province":"Cambridgeshire",
    "sg:tags":[
        "others"
    ],
    "wof:name":"G W Swales & Son",
    "wof:placetype":"venue"
},
  "geometry": {"coordinates":[-0.153674,52.486679],"type":"Point"}
}