{
  "type": "Feature",
  "properties": {
    "addr:full":"102-104 Hull Road York North Yorkshire YO10 3LQ",
    "addr:housenumber":"102-104",
    "addr:postcode":"yo10 3lq",
    "addr:street":"Hull Road",
    "iso:country":"GB",
    "sg:address":"102-104 Hull Road",
    "sg:city":"York",
    "sg:classifiers":[
        {
            "category":"Shopping",
            "subcategory":"News",
            "type":"Retail Goods"
        }
    ],
    "sg:phone":"+44 1904 431027",
    "sg:postcode":"YO10 3LQ",
    "sg:province":"North Yorkshire",
    "sg:tags":[
        "newsagent"
    ],
    "wof:name":"Maynews Ltd.",
    "wof:placetype":"venue"
},
  "geometry": {"coordinates":[-1.0533709526,53.9537582397],"type":"Point"}
}