{
  "type": "Feature",
  "properties": {
    "addr:full":"73 Chiltern Street London Greater London W1U 6NN",
    "addr:housenumber":"73",
    "addr:postcode":"w1u 6nn",
    "addr:street":"Chiltern Street",
    "iso:country":"GB",
    "sg:address":"73 Chiltern Street",
    "sg:city":"London",
    "sg:classifiers":[
        {
            "category":"Professional",
            "subcategory":"Business Services",
            "type":"Services"
        }
    ],
    "sg:postcode":"W1U 6NN",
    "sg:province":"Greater London",
    "sg:tags":[
        "accomodation"
    ],
    "wof:name":"Citaco (1957) Limited",
    "wof:placetype":"venue"
},
  "geometry": {"coordinates":[-0.1560429931,51.5208625793],"type":"Point"}
}