{
  "type": "Feature",
  "properties": {
    "addr:full":"9 Albany Park, Cabot La Poole Dorset BH17 7BX",
    "addr:housenumber":"9",
    "addr:postcode":"bh17 7bx",
    "addr:street":"Albany Park;La Poole",
    "iso:country":"GB",
    "sg:address":"9 Albany Park, Cabot La",
    "sg:city":"Poole",
    "sg:classifiers":[
        {
            "category":"Professional",
            "subcategory":"Engineering",
            "type":"Services"
        }
    ],
    "sg:phone":"+44 1202 699399",
    "sg:postcode":"BH17 7BX",
    "sg:province":"Dorset",
    "sg:tags":[
        "design",
        "engineer"
    ],
    "wof:name":"Charge Electronic Design Ltd",
    "wof:placetype":"venue"
},
  "geometry": {"coordinates":[-1.988004,50.743687],"type":"Point"}
}