{
  "type": "Feature",
  "properties": {
    "addr:full":"Middle Aston Ho Bicester Oxfordshire OX6 3PT",
    "addr:postcode":"ox6 3pt",
    "addr:street":"Middle Aston",
    "iso:country":"GB",
    "sg:address":"Middle Aston Ho",
    "sg:city":"Bicester",
    "sg:classifiers":[
        {
            "category":"Education",
            "subcategory":"Special Training",
            "type":"Public Place"
        }
    ],
    "sg:phone":"+44 1869 347755",
    "sg:postcode":"OX6 3PT",
    "sg:province":"Oxfordshire",
    "sg:tags":[
        "product",
        "centre"
    ],
    "wof:name":"Pera Group",
    "wof:placetype":"venue"
},
  "geometry": {"coordinates":[-1.311444,51.949833],"type":"Point"}
}