{
  "type": "Feature",
  "properties": {
    "iso:country":"GB",
    "sg:address":"33 Woodland Road",
    "sg:city":"Rushden",
    "sg:classifiers":[
        {
            "category":"Building & Trades",
            "subcategory":"Construction",
            "type":"Services"
        }
    ],
    "sg:phone":"+44 1933 315808",
    "sg:postcode":"NN10 6US",
    "sg:province":"Bedfordshire",
    "sg:tags":[
        "builder"
    ],
    "wof:name":"S & R Cavender Ltd",
    "wof:placetype":"venue"
},
  "geometry": {"coordinates":[-0.6069049835,52.2953796387],"type":"Point"}
}