{
  "type": "Feature",
  "properties": {
    "addr:full":"6 Beaumont St, Milehouse Plymouth Devon PL2 3AG",
    "addr:housenumber":"6",
    "addr:postcode":"pl2 3ag",
    "addr:street":"Beaumont St",
    "iso:country":"GB",
    "sg:address":"6 Beaumont St, Milehouse",
    "sg:city":"Plymouth",
    "sg:classifiers":[
        {
            "category":"Shopping",
            "subcategory":"News",
            "type":"Retail Goods"
        }
    ],
    "sg:postcode":"PL2 3AG",
    "sg:province":"Devon",
    "sg:tags":[
        "newsagent"
    ],
    "wof:name":"Maguire,Anthony,",
    "wof:placetype":"venue"
},
  "geometry": {"coordinates":[-4.158498,50.386055],"type":"Point"}
}