{
  "type": "Feature",
  "properties": {
    "iso:country":"GB",
    "sg:address":"Mapel Road",
    "sg:city":"Mexborough",
    "sg:classifiers":[
        {
            "category":"Education",
            "subcategory":"School",
            "type":"Public Place"
        },
        {
            "category":"Government",
            "subcategory":"Office",
            "type":"Public Place"
        }
    ],
    "sg:phone":"+44 1709 585858",
    "sg:postcode":"S64 9SD",
    "sg:province":"South Yorkshire",
    "sg:tags":[
        "local",
        "authority"
    ],
    "wof:name":"Mexborough School",
    "wof:placetype":"venue"
},
  "geometry": {"coordinates":[-1.293109,53.501148],"type":"Point"}
}