{
  "type": "Feature",
  "properties": {
    "iso:country":"GB",
    "sg:address":"Burnbrae Road",
    "sg:city":"Falkirk",
    "sg:classifiers":[
        {
            "category":"Social Services",
            "subcategory":"Retirement Home",
            "type":"Services"
        }
    ],
    "sg:phone":"+44 1324 631441",
    "sg:postcode":"FK1 5SD",
    "sg:province":"Falkirk",
    "sg:tags":[
        "residential",
        "care"
    ],
    "wof:name":"Burnbrae Home",
    "wof:placetype":"venue"
},
  "geometry": {"coordinates":[-3.795693,56.002628],"type":"Point"}
}