{
  "type": "Feature",
  "properties": {
    "addr:full":"13a Brougham St Edinburgh City of Edinburgh EH3 9JS",
    "addr:housenumber":"13a",
    "addr:postcode":"eh3 9js",
    "addr:street":"Brougham St Edinburgh",
    "iso:country":"GB",
    "sg:address":"13a Brougham St",
    "sg:city":"Edinburgh",
    "sg:classifiers":[
        {
            "category":"Professional",
            "subcategory":"Computer Services",
            "type":"Services"
        }
    ],
    "sg:postcode":"EH3 9JS",
    "sg:province":"City of Edinburgh",
    "sg:tags":[
        "system",
        "software"
    ],
    "wof:name":"Agio Consultants Ltd",
    "wof:placetype":"venue"
},
  "geometry": {"coordinates":[-3.2027308941,55.9432907104],"type":"Point"}
}