{
  "type": "Feature",
  "properties": {
    "addr:full":"14 Tewkesbury Road London Greater London N15 6SE",
    "addr:housenumber":"14",
    "addr:postcode":"n15 6se",
    "addr:street":"Tewkesbury Road",
    "iso:country":"GB",
    "sg:address":"14 Tewkesbury Road",
    "sg:city":"London",
    "sg:classifiers":[
        {
            "category":"Retail",
            "subcategory":"Auto Repair",
            "type":"Services"
        }
    ],
    "sg:phone":"+44 20 8800 6528",
    "sg:postcode":"N15 6SE",
    "sg:province":"Greater London",
    "sg:tags":[
        "modification",
        "garage",
        "related"
    ],
    "wof:name":"T H Motors",
    "wof:placetype":"venue"
},
  "geometry": {"coordinates":[-0.0855240002,51.5761451721],"type":"Point"}
}