{
  "type": "Feature",
  "properties": {
    "iso:country":"GB",
    "sg:address":"33 Parker Drive",
    "sg:city":"Leicester",
    "sg:classifiers":[
        {
            "category":"Retail",
            "subcategory":"Auto Repair",
            "type":"Services"
        }
    ],
    "sg:phone":"+44 116 299 9090",
    "sg:postcode":"LE4 0JP",
    "sg:province":"Leicestershire",
    "sg:tags":[
        "modification",
        "garage"
    ],
    "wof:name":"Autotecnic Leicester",
    "wof:placetype":"venue"
},
  "geometry": {"coordinates":[-1.144231,52.65181],"type":"Point"}
}