{
  "type": "Feature",
  "properties": {
    "addr:full":"2 Rock 'm' Jock Lancaster Lancashire LA2 9QB",
    "addr:housenumber":"2",
    "addr:postcode":"la2 9qb",
    "addr:street":"Rock ' M ' Jock",
    "iso:country":"GB",
    "sg:address":"2 Rock 'm' Jock",
    "sg:city":"Lancaster",
    "sg:classifiers":[
        {
            "category":"Military Area",
            "subcategory":"Air Force Base",
            "type":"Public Place"
        }
    ],
    "sg:phone":"+44 1524 411097",
    "sg:postcode":"LA2 9QB",
    "sg:province":"Lancashire",
    "sg:tags":[
        "taxi",
        "hire",
        "private"
    ],
    "wof:name":"Transair",
    "wof:placetype":"venue"
},
  "geometry": {"coordinates":[-2.72033,54.073189],"type":"Point"}
}