{
  "type": "Feature",
  "properties": {
    "addr:full":"Unit 6 Frieslawn Farm, Hodsoll St, Ash-cum-ridley Sevenoaks Kent TN15 7LH",
    "addr:housenumber":"unit 6 frieslawn farm",
    "addr:postcode":"tn15 7lh",
    "addr:street":"Hodsoll St",
    "iso:country":"GB",
    "sg:address":"Unit 6 Frieslawn Farm, Hodsoll St, Ash-cum-ridley",
    "sg:city":"Sevenoaks",
    "sg:classifiers":[
        {
            "category":"Retail",
            "subcategory":"Event Space",
            "type":"Services"
        }
    ],
    "sg:phone":"+44 1732 824536",
    "sg:postcode":"TN15 7LH",
    "sg:province":"Kent",
    "sg:tags":[
        "exhibition",
        "organiser"
    ],
    "wof:name":"Athene Design & Display Ltd",
    "wof:placetype":"venue"
},
  "geometry": {"coordinates":[0.3247399926,51.3420982361],"type":"Point"}
}