{
  "type": "Feature",
  "properties": {
    "iso:country":"GB",
    "sg:address":"20a Lower Addiscombe Road",
    "sg:city":"Croydon",
    "sg:classifiers":[
        {
            "category":"Restaurant",
            "type":"Food & Drink"
        }
    ],
    "sg:postcode":"CR0 6AA",
    "sg:province":"Surrey",
    "wof:name":"Polka Continental Restaurant",
    "wof:placetype":"venue"
},
  "geometry": {"coordinates":[-0.088702,51.380672],"type":"Point"}
}