{
  "type": "Feature",
  "properties": {
    "addr:full":"Hardengreen Business Park, 44/3 Dalhousie Rd Dalkeith City of Edinburgh EH22 3NU",
    "addr:housenumber":"44 / 3",
    "addr:postcode":"eh22 3nu",
    "addr:street":"Dalhousie Rd",
    "iso:country":"GB",
    "sg:address":"Hardengreen Business Park, 44/3 Dalhousie Rd",
    "sg:city":"Dalkeith",
    "sg:classifiers":[
        {
            "category":"Professional",
            "type":"Services"
        }
    ],
    "sg:phone":"+44 131 454 9090",
    "sg:postcode":"EH22 3NU",
    "sg:province":"City of Edinburgh",
    "sg:tags":[
        "auctioneer"
    ],
    "wof:name":"Thomson Roddick & Medcalf",
    "wof:placetype":"venue"
},
  "geometry": {"coordinates":[-3.079570055,55.8837585449],"type":"Point"}
}