{
  "type": "Feature",
  "properties": {
    "addr:full":"213 Valley Road Nottingham Nottinghamshire NG5 3BG",
    "addr:housenumber":"213",
    "addr:postcode":"ng5 3bg",
    "addr:street":"Valley Road",
    "iso:country":"GB",
    "sg:address":"213 Valley Road",
    "sg:city":"Nottingham",
    "sg:classifiers":[
        {
            "category":"Shopping",
            "subcategory":"Bicycles & Sporting Goods",
            "type":"Retail Goods"
        }
    ],
    "sg:phone":"+44 115 985 8001",
    "sg:postcode":"NG5 3BG",
    "sg:province":"Nottinghamshire",
    "sg:tags":[
        "cycle",
        "accessory"
    ],
    "wof:name":"Olympic Cycles",
    "wof:placetype":"venue"
},
  "geometry": {"coordinates":[-1.159216,52.986881],"type":"Point"}
}