{
  "type": "Feature",
  "properties": {
    "addr:full":"11a Brougham Road Worthing West Sussex BN11 2NP",
    "addr:housenumber":"11a",
    "addr:postcode":"bn11 2np",
    "addr:street":"Brougham Road",
    "iso:country":"GB",
    "sg:address":"11a Brougham Road",
    "sg:city":"Worthing",
    "sg:classifiers":[
        {
            "category":"Personal",
            "subcategory":"Beauty Salon",
            "type":"Services"
        }
    ],
    "sg:postcode":"BN11 2NP",
    "sg:province":"West Sussex",
    "sg:tags":[
        "lady",
        "hairdresser"
    ],
    "wof:name":"T M Barbers",
    "wof:placetype":"venue"
},
  "geometry": {"coordinates":[-0.351438,50.817169],"type":"Point"}
}