{
  "type": "Feature",
  "properties": {
    "addr:full":"13 Jerome Cres St John's Wood Greater London NW8 8SB",
    "addr:housenumber":"13",
    "addr:postcode":"nw8 8sb",
    "addr:street":"Jerome Cres St John'S",
    "iso:country":"GB",
    "sg:address":"13 Jerome Cres",
    "sg:city":"St John's Wood",
    "sg:classifiers":[
        {
            "category":"Professional",
            "subcategory":"Engineering",
            "type":"Services"
        }
    ],
    "sg:phone":"+44 20 7724 1527",
    "sg:postcode":"NW8 8SB",
    "sg:province":"Greater London",
    "sg:tags":[
        "contractor",
        "electrical",
        "engineer"
    ],
    "wof:name":"J Banks Electrical Ltd",
    "wof:placetype":"venue"
},
  "geometry": {"coordinates":[-0.16957,51.526035],"type":"Point"}
}