{
  "type": "Feature",
  "properties": {
    "iso:country":"GB",
    "sg:address":"481 Green Lanes",
    "sg:city":"London",
    "sg:classifiers":[
        {
            "category":"Professional",
            "subcategory":"Management & Consulting",
            "type":"Services"
        }
    ],
    "sg:postcode":"N13 4BS",
    "sg:province":"Greater London",
    "sg:tags":[
        "consultant",
        "business"
    ],
    "wof:name":"N.D.L. Consultants Ltd",
    "wof:placetype":"venue"
},
  "geometry": {"coordinates":[-0.1052939966,51.6224098206],"type":"Point"}
}