{
  "type": "Feature",
  "properties": {
    "iso:country":"GB",
    "sg:address":"Cawdor House, Cawdor St, Worsley",
    "sg:city":"Manchester",
    "sg:classifiers":[
        {
            "category":"Professional",
            "subcategory":"Accounting & Tax Preparation",
            "type":"Services"
        }
    ],
    "sg:phone":"+44 161 799 9996",
    "sg:postcode":"M28 3HF",
    "sg:province":"Greater Manchester",
    "sg:tags":[
        "payroll"
    ],
    "wof:name":"Trafford Management Services Ltd",
    "wof:placetype":"venue"
},
  "geometry": {"coordinates":[-2.387759,53.522594],"type":"Point"}
}