{
  "type": "Feature",
  "properties": {
    "addr:full":"107 Church Rd Hereford Herefordshire HR1 1RT",
    "addr:housenumber":"107",
    "addr:postcode":"hr1 1rt",
    "addr:street":"Church Rd",
    "iso:country":"GB",
    "sg:address":"107 Church Rd",
    "sg:city":"Hereford",
    "sg:classifiers":[
        {
            "category":"Place Of Worship",
            "type":"Public Place"
        }
    ],
    "sg:phone":"+44 1432 274490",
    "sg:postcode":"HR1 1RT",
    "sg:province":"Herefordshire",
    "wof:name":"St.Paul Church Tupsley",
    "wof:placetype":"venue"
},
  "geometry": {"coordinates":[-2.6854801178,52.0547561646],"type":"Point"}
}