{
  "type": "Feature",
  "properties": {
    "addr:full":"Betton Alkmere Farm, Betton Strange, Cross Houses Shrewsbury Shropshire SY5 6HZ",
    "addr:postcode":"sy5 6hz",
    "addr:street":"Strange Cross",
    "iso:country":"GB",
    "sg:address":"Betton Alkmere Farm, Betton Strange, Cross Houses",
    "sg:city":"Shrewsbury",
    "sg:classifiers":[
        {
            "category":"Farming",
            "subcategory":"Dairy Farm",
            "type":"Manufacturing & Wholesale Goods"
        }
    ],
    "sg:postcode":"SY5 6HZ",
    "sg:province":"Shropshire",
    "wof:name":"R Maund & Co",
    "wof:placetype":"venue"
},
  "geometry": {"coordinates":[-2.6852140427,52.6633262634],"type":"Point"}
}