{
  "type": "Feature",
  "properties": {
    "addr:full":"Ings Meadow, Potterton Close, Barwick In Elmet Leeds West Yorkshire LS15 4DY",
    "addr:postcode":"barwick;ls15 4dy",
    "addr:street":"Ings Meadow Potterton Close;In Elmet Leeds West",
    "iso:country":"GB",
    "sg:address":"Ings Meadow, Potterton Close, Barwick In Elmet",
    "sg:city":"Leeds",
    "sg:classifiers":[
        {
            "category":"Education",
            "subcategory":"School",
            "type":"Public Place"
        },
        {
            "category":"Education",
            "subcategory":"University",
            "type":"Public Place"
        }
    ],
    "sg:phone":"+44 113 281 2988",
    "sg:postcode":"LS15 4DY",
    "sg:province":"West Yorkshire",
    "sg:tags":[
        "private",
        "tuition"
    ],
    "wof:name":"Barwick Tutorials",
    "wof:placetype":"venue"
},
  "geometry": {"coordinates":[-1.3942849636,53.8314552307],"type":"Point"}
}