{
  "type": "Feature",
  "properties": {
    "addr:full":"Bottom Farm, Brook Street, Hargrave Wellingborough Northamptonshire NN9 6BP",
    "addr:postcode":"nn9 6bp",
    "addr:street":"Brook Street",
    "iso:country":"GB",
    "sg:address":"Bottom Farm, Brook Street, Hargrave",
    "sg:city":"Wellingborough",
    "sg:classifiers":[
        {
            "category":"Farming",
            "subcategory":"Crops",
            "type":"Manufacturing & Wholesale Goods"
        },
        {
            "category":"Farming",
            "subcategory":"Livestock Farm",
            "type":"Manufacturing & Wholesale Goods"
        }
    ],
    "sg:phone":"+44 1933 622809",
    "sg:postcode":"NN9 6BP",
    "sg:province":"Northamptonshire",
    "sg:tags":[
        "arable",
        "others"
    ],
    "wof:name":"F R W Farrington & Son",
    "wof:placetype":"venue"
},
  "geometry": {"coordinates":[-0.4800589979,52.324016571],"type":"Point"}
}