{
  "type": "Feature",
  "properties": {
    "iso:country":"GB",
    "sg:address":"100 Palmerston Rd",
    "sg:city":"Walthamstow",
    "sg:classifiers":[
        {
            "category":"Shopping",
            "subcategory":"Clothing, Apparel, & Fashions",
            "type":"Retail Goods"
        }
    ],
    "sg:phone":"+44 20 8521 1129",
    "sg:postcode":"E17 6PZ",
    "sg:province":"Greater London",
    "sg:tags":[
        "lingerie"
    ],
    "wof:name":"Juvan Fashion House",
    "wof:placetype":"venue"
},
  "geometry": {"coordinates":[-0.029344,51.586437],"type":"Point"}
}