{
  "type": "Feature",
  "properties": {
    "addr:full":"6 Wallace Parade, Goring Road, Goring-by-sea Worthing West Sussex BN12 4AL",
    "addr:housenumber":"6",
    "addr:postcode":"bn12 4al",
    "addr:street":"Wallace Parade Goring Road",
    "iso:country":"GB",
    "sg:address":"6 Wallace Parade, Goring Road, Goring-by-sea",
    "sg:city":"Worthing",
    "sg:classifiers":[
        {
            "category":"Shopping",
            "subcategory":"Optician",
            "type":"Retail Goods"
        }
    ],
    "sg:phone":"+44 1903 249177",
    "sg:postcode":"BN12 4AL",
    "sg:province":"West Sussex",
    "wof:name":"Dollond & Aitchison",
    "wof:placetype":"venue"
},
  "geometry": {"coordinates":[-0.4241290092,50.8150787354],"type":"Point"}
}