{
  "type": "Feature",
  "properties": {
    "iso:country":"GB",
    "sg:address":"321 Essex Rd, Unit 16",
    "sg:city":"Islington",
    "sg:classifiers":[
        {
            "category":"Food & Beverages",
            "subcategory":"Specialty",
            "type":"Retail Goods"
        }
    ],
    "sg:phone":"+44 20 7354 4789",
    "sg:postcode":"N1 3PS",
    "sg:province":"Greater London",
    "sg:tags":[
        "organic"
    ],
    "wof:name":"Gavioli & Son Import",
    "wof:placetype":"venue"
},
  "geometry": {"coordinates":[-0.091459,51.542919],"type":"Point"}
}