{
  "type": "Feature",
  "properties": {
    "iso:country":"GB",
    "sg:address":"65 Marshfield Rd, Fishponds",
    "sg:city":"Bristol",
    "sg:classifiers":[
        {
            "category":"Building & Trades",
            "subcategory":"Cleaning & Sanitation",
            "type":"Services"
        }
    ],
    "sg:postcode":"BS16 4JF",
    "sg:province":"City of Bristol",
    "sg:tags":[
        "cleaner",
        "window"
    ],
    "wof:name":"Smiths Window Cleaning Services",
    "wof:placetype":"venue"
},
  "geometry": {"coordinates":[-2.516611,51.47776],"type":"Point"}
}