{
  "type": "Feature",
  "properties": {
    "iso:country":"GB",
    "sg:address":"Unit C Faraday Court, Faraday Rd",
    "sg:city":"Crawley",
    "sg:classifiers":[
        {
            "category":"Food & Beverages",
            "subcategory":"Liquor & Beverages",
            "type":"Retail Goods"
        }
    ],
    "sg:phone":"+44 870 606 0260",
    "sg:postcode":"RH10 2PU",
    "sg:province":"Surrey",
    "sg:tags":[
        "drink",
        "soft"
    ],
    "wof:name":"Coca-Cola & Schweppes (Southern Region)",
    "wof:placetype":"venue"
},
  "geometry": {"coordinates":[-0.178634,51.13435],"type":"Point"}
}