{
  "type": "Feature",
  "properties": {
    "addr:full":"Temple Manor Ho, The Lawns Aylesbury Buckinghamshire HP18 9SN",
    "addr:postcode":"hp18 9sn",
    "iso:country":"GB",
    "sg:address":"Temple Manor Ho, The Lawns",
    "sg:city":"Aylesbury",
    "sg:classifiers":[
        {
            "category":"Professional",
            "subcategory":"Management & Consulting",
            "type":"Services"
        }
    ],
    "sg:phone":"+44 1844 238552",
    "sg:postcode":"HP18 9SN",
    "sg:province":"Buckinghamshire",
    "sg:tags":[
        "marketing",
        "consultant"
    ],
    "wof:name":"TSM Ltd",
    "wof:placetype":"venue"
},
  "geometry": {"coordinates":[-1.0493040085,51.8231620789],"type":"Point"}
}