{
  "type": "Feature",
  "properties": {
    "iso:country":"GB",
    "sg:address":"Monktonhall Gdns",
    "sg:city":"Musselburgh",
    "sg:classifiers":[
        {
            "category":"Professional",
            "subcategory":"Lawyer & Legal Services",
            "type":"Services"
        }
    ],
    "sg:postcode":"EH21 8SH",
    "sg:province":"City of Edinburgh",
    "sg:tags":[
        "patent",
        "agent"
    ],
    "wof:name":"Livingstone,Sheena,",
    "wof:placetype":"venue"
},
  "geometry": {"coordinates":[-3.0662999153,55.9221382141],"type":"Point"}
}