{
  "type": "Feature",
  "properties": {
    "addr:full":"Roman Way Farnham Surrey GU9 9RE",
    "addr:postcode":"gu9 9re",
    "addr:street":"Roman Way",
    "iso:country":"GB",
    "sg:address":"Roman Way",
    "sg:city":"Farnham",
    "sg:classifiers":[
        {
            "category":"Social Services",
            "subcategory":"Retirement Home",
            "type":"Services"
        }
    ],
    "sg:phone":"+44 1252 717021",
    "sg:postcode":"GU9 9RE",
    "sg:province":"Surrey",
    "sg:tags":[
        "residential",
        "care"
    ],
    "wof:name":"Cavell House",
    "wof:placetype":"venue"
},
  "geometry": {"coordinates":[-0.7835890055,51.2230644226],"type":"Point"}
}