{
  "type": "Feature",
  "properties": {
    "iso:country":"GB",
    "sg:address":"Jaque Royd Hall, Shelf",
    "sg:city":"Halifax",
    "sg:classifiers":[
        {
            "category":"Personal",
            "type":"Services"
        }
    ],
    "sg:postcode":"HX3 7TX",
    "sg:province":"West Yorkshire",
    "sg:tags":[
        "wedding"
    ],
    "wof:name":"Precious Memories Bouquet Preservation",
    "wof:placetype":"venue"
},
  "geometry": {"coordinates":[-1.816379,53.752666],"type":"Point"}
}