{
  "type": "Feature",
  "properties": {
    "iso:country":"GB",
    "sg:address":"Bryn Lluarth Farms, Prion",
    "sg:city":"Denbigh",
    "sg:classifiers":[
        {
            "category":"Freight",
            "type":"Transportation"
        }
    ],
    "sg:phone":"+44 1745 890235",
    "sg:postcode":"LL16 4RY",
    "sg:province":"Conwy",
    "sg:tags":[
        "haulage",
        "road"
    ],
    "wof:name":"Elwyn Jones Haulage",
    "wof:placetype":"venue"
},
  "geometry": {"coordinates":[-3.4203400612,53.1485748291],"type":"Point"}
}