{
  "type": "Feature",
  "properties": {
    "iso:country":"GB",
    "sg:address":"60 Glade Road",
    "sg:city":"Marlow",
    "sg:classifiers":[
        {
            "category":"Building & Trades",
            "subcategory":"Construction",
            "type":"Services"
        }
    ],
    "sg:phone":"+44 1628 475094",
    "sg:postcode":"SL7 1DH",
    "sg:province":"Berkshire",
    "sg:tags":[
        "builder"
    ],
    "wof:name":"C & S Kallides Builders",
    "wof:placetype":"venue"
},
  "geometry": {"coordinates":[-0.7716469765,51.5743942261],"type":"Point"}
}