{
  "type": "Feature",
  "properties": {
    "addr:full":"Stansfield Works, 158 Moorland Road Stoke-on-trent Staffordshire ST6 1EB",
    "addr:housenumber":"158",
    "addr:postcode":"st6 1eb",
    "addr:street":"Moorland Road",
    "iso:country":"GB",
    "sg:address":"Stansfield Works, 158 Moorland Road",
    "sg:city":"Stoke-on-trent",
    "sg:classifiers":[
        {
            "category":"Home & Garden",
            "subcategory":"Home Furnishings",
            "type":"Retail Goods"
        }
    ],
    "sg:phone":"+44 1782 824900",
    "sg:postcode":"ST6 1EB",
    "sg:province":"Staffordshire",
    "sg:tags":[
        "homefurnishings"
    ],
    "wof:name":"Highline Furniture Ltd.",
    "wof:placetype":"venue"
},
  "geometry": {"coordinates":[-2.1882200241,53.0470581055],"type":"Point"}
}