{
  "type": "Feature",
  "properties": {
    "addr:full":"537 Bury Road Bolton Lancashire BL2 6DH",
    "addr:housenumber":"537",
    "addr:postcode":"bl2 6dh",
    "addr:street":"Bury Road",
    "iso:country":"GB",
    "sg:address":"537 Bury Road",
    "sg:city":"Bolton",
    "sg:classifiers":[
        {
            "category":"Food & Beverages",
            "subcategory":"Liquor & Beverages",
            "type":"Retail Goods"
        }
    ],
    "sg:phone":"+44 1204 398255",
    "sg:postcode":"BL2 6DH",
    "sg:province":"Lancashire",
    "sg:tags":[
        "beer",
        "spirit",
        "wines"
    ],
    "wof:name":"B J's Off Licence",
    "wof:placetype":"venue"
},
  "geometry": {"coordinates":[-2.3959300518,53.5808105469],"type":"Point"}
}