{
  "type": "Feature",
  "properties": {
    "iso:country":"GB",
    "sg:address":"4 Axis, Hawkfield Way, Whitchurch",
    "sg:city":"Bristol",
    "sg:classifiers":[
        {
            "category":"Shopping",
            "subcategory":"Stationery & Office Supplies",
            "type":"Retail Goods"
        }
    ],
    "sg:phone":"+44 117 964 1300",
    "sg:postcode":"BS14 0BY",
    "sg:province":"City of Bristol",
    "sg:tags":[
        "equipment"
    ],
    "wof:name":"Broughton & Co. (Bristol) Ltd.",
    "wof:placetype":"venue"
},
  "geometry": {"coordinates":[-2.551224947,51.4050331116],"type":"Point"}
}