{
  "type": "Feature",
  "properties": {
    "addr:full":"56 Tankerton Rd Surbiton Surrey KT6 7LG",
    "addr:housenumber":"56",
    "addr:postcode":"kt6 7lg",
    "addr:street":"Tankerton Rd",
    "iso:country":"GB",
    "sg:address":"56 Tankerton Rd",
    "sg:city":"Surbiton",
    "sg:classifiers":[
        {
            "category":"Professional",
            "subcategory":"Engineering",
            "type":"Services"
        }
    ],
    "sg:phone":"+44 20 8397 2870",
    "sg:postcode":"KT6 7LG",
    "sg:province":"Surrey",
    "sg:tags":[
        "contractor",
        "electrical",
        "engineer"
    ],
    "wof:name":"Marshall Kelly Installations",
    "wof:placetype":"venue"
},
  "geometry": {"coordinates":[-0.2922900021,51.37865448],"type":"Point"}
}