{
  "type": "Feature",
  "properties": {
    "addr:full":"Waterloo Youth Centre, Kitchener Crescent, Waterloo Estate Poole Dorset BH17 7HX",
    "addr:postcode":"bh17 7hx",
    "addr:street":"Kitchener Crescent",
    "iso:country":"GB",
    "sg:address":"Waterloo Youth Centre, Kitchener Crescent, Waterloo Estate",
    "sg:city":"Poole",
    "sg:classifiers":[
        {
            "category":"Education",
            "subcategory":"Preschool",
            "type":"Public Place"
        }
    ],
    "sg:phone":"+44 1202 693288",
    "sg:postcode":"BH17 7HX",
    "sg:province":"Dorset",
    "sg:tags":[
        "pre-school",
        "playgroups"
    ],
    "wof:name":"Twin Oaks Playgroup",
    "wof:placetype":"venue"
},
  "geometry": {"coordinates":[-1.989099,50.751835],"type":"Point"}
}