{
  "type": "Feature",
  "properties": {
    "iso:country":"GB",
    "sg:address":"7 Fenkle Street",
    "sg:city":"Alnwick",
    "sg:classifiers":[
        {
            "category":"Travel",
            "subcategory":"Hotels & Motels",
            "type":"Entertainment"
        }
    ],
    "sg:phone":"+44 1665 602759",
    "sg:postcode":"NE66 1HW",
    "sg:province":"Northumberland",
    "wof:name":"The Market Tavern Hotel",
    "wof:placetype":"venue"
},
  "geometry": {"coordinates":[-1.70781,55.413803],"type":"Point"}
}