{
  "type": "Feature",
  "properties": {
    "iso:country":"GB",
    "sg:address":"67 Melford Road",
    "sg:city":"Sudbury",
    "sg:classifiers":[
        {
            "category":"Fast Food",
            "type":"Food & Drink"
        },
        {
            "category":"Restaurant",
            "type":"Food & Drink"
        }
    ],
    "sg:postcode":"CO10 1JS",
    "sg:province":"Essex",
    "sg:tags":[
        "away",
        "take"
    ],
    "wof:name":"Youngs Restaurant",
    "wof:placetype":"venue"
},
  "geometry": {"coordinates":[0.727634,52.043751],"type":"Point"}
}