{
  "type": "Feature",
  "properties": {
    "addr:full":"11 Moor Park Avenue Preston Lancashire PR1 6AS",
    "addr:housenumber":"11",
    "addr:postcode":"pr1 6as",
    "addr:street":"Moor Park Avenue",
    "iso:country":"GB",
    "sg:address":"11 Moor Park Avenue",
    "sg:city":"Preston",
    "sg:classifiers":[
        {
            "category":"Health Services",
            "subcategory":"Doctor",
            "type":"Services"
        }
    ],
    "sg:postcode":"PR1 6AS",
    "sg:province":"Lancashire",
    "sg:tags":[
        "surgeon"
    ],
    "wof:name":"J D Wright",
    "wof:placetype":"venue"
},
  "geometry": {"coordinates":[-2.704153,53.771427],"type":"Point"}
}