{
  "type": "Feature",
  "properties": {
    "addr:full":"Leyland Rd, Penwortham Preston Lancashire PR1 9XR",
    "addr:postcode":"pr1 9xr",
    "addr:street":"Leyland Rd",
    "iso:country":"GB",
    "sg:address":"Leyland Rd, Penwortham",
    "sg:city":"Preston",
    "sg:classifiers":[
        {
            "category":"Bars & Pubs",
            "type":"Food & Drink"
        }
    ],
    "sg:phone":"+44 1772 753921",
    "sg:postcode":"PR1 9XR",
    "sg:province":"Lancashire",
    "sg:tags":[
        "pubs",
        "inn"
    ],
    "wof:name":"The Bridge",
    "wof:placetype":"venue"
},
  "geometry": {"coordinates":[-2.716191,53.749157],"type":"Point"}
}