{
  "type": "Feature",
  "properties": {
    "addr:full":"Smithfield Inverness Highland IV13 7YN",
    "addr:postcode":"iv13 7yn",
    "addr:street":"Smithfield",
    "iso:country":"GB",
    "sg:address":"Smithfield",
    "sg:city":"Inverness",
    "sg:classifiers":[
        {
            "category":"Freight",
            "type":"Transportation"
        }
    ],
    "sg:phone":"+44 1808 511272",
    "sg:postcode":"IV13 7YN",
    "sg:province":"Highland",
    "sg:tags":[
        "haulage",
        "road"
    ],
    "wof:name":"W & F Kelly Ltd.",
    "wof:placetype":"venue"
},
  "geometry": {"coordinates":[-4.0124921799,57.3429412842],"type":"Point"}
}