{
  "type": "Feature",
  "properties": {
    "addr:full":"55 Hunter Rd, Willesborough Ashford Kent TN24 0RT",
    "addr:housenumber":"55",
    "addr:postcode":"tn24 0rt",
    "addr:street":"Hunter Rd",
    "iso:country":"GB",
    "sg:address":"55 Hunter Rd, Willesborough",
    "sg:city":"Ashford",
    "sg:classifiers":[
        {
            "category":"Professional",
            "subcategory":"Engineering",
            "type":"Services"
        }
    ],
    "sg:postcode":"TN24 0RT",
    "sg:province":"Kent",
    "sg:tags":[
        "contractor",
        "electrical",
        "engineer"
    ],
    "wof:name":"Hill,David Alan,",
    "wof:placetype":"venue"
},
  "geometry": {"coordinates":[0.89228,51.142326],"type":"Point"}
}