{
  "type": "Feature",
  "properties": {
    "iso:country":"GB",
    "sg:address":"4 Medway Avenue",
    "sg:city":"Fleetwood",
    "sg:classifiers":[
        {
            "category":"Building & Trades",
            "subcategory":"Landscaping Services",
            "type":"Services"
        }
    ],
    "sg:postcode":"FY7 8PZ",
    "sg:province":"Lancashire",
    "sg:tags":[
        "landscape",
        "contractor"
    ],
    "wof:name":"Steve Higgin Landscapes",
    "wof:placetype":"venue"
},
  "geometry": {"coordinates":[-3.042811,53.904705],"type":"Point"}
}