{
  "type": "Feature",
  "properties": {
    "iso:country":"GB",
    "sg:address":"156 Windsor Avenue, Hillingdon",
    "sg:city":"Uxbridge",
    "sg:classifiers":[
        {
            "category":"Professional",
            "subcategory":"Engineering",
            "type":"Services"
        }
    ],
    "sg:postcode":"UB10 9BD",
    "sg:province":"Greater London",
    "sg:tags":[
        "contractor",
        "electrical",
        "engineer"
    ],
    "wof:name":"Clasper & Simpson",
    "wof:placetype":"venue"
},
  "geometry": {"coordinates":[-0.4491159916,51.5431938171],"type":"Point"}
}