{
  "type": "Feature",
  "properties": {
    "iso:country":"GB",
    "sg:address":"53 Colwell Rise",
    "sg:city":"Luton",
    "sg:classifiers":[
        {
            "category":"Professional",
            "subcategory":"Engineering",
            "type":"Services"
        }
    ],
    "sg:phone":"+44 1582 451054",
    "sg:postcode":"LU2 9TJ",
    "sg:province":"Bedfordshire",
    "sg:tags":[
        "contractor",
        "electrical",
        "engineer"
    ],
    "wof:name":"Sinclair Electrical Services",
    "wof:placetype":"venue"
},
  "geometry": {"coordinates":[-0.3687709868,51.8907699585],"type":"Point"}
}