{
  "type": "Feature",
  "properties": {
    "iso:country":"GB",
    "sg:address":"1 Parkwood Street",
    "sg:city":"Keighley",
    "sg:classifiers":[
        {
            "category":"Manufacturing",
            "subcategory":"Metals",
            "type":"Manufacturing & Wholesale Goods"
        }
    ],
    "sg:phone":"+44 1535 683290",
    "sg:postcode":"BD21 4QH",
    "sg:province":"West Yorkshire",
    "sg:tags":[
        "fabricator",
        "aluminium",
        "mnfrs"
    ],
    "wof:name":"Aire Valley Architectural (Aluminium) Ltd.",
    "wof:placetype":"venue"
},
  "geometry": {"coordinates":[-1.9042110443,53.8621253967],"type":"Point"}
}