{
  "type": "Feature",
  "properties": {
    "iso:country":"GB",
    "sg:address":"58-60 Wallasey Rd",
    "sg:city":"Wallasey",
    "sg:classifiers":[
        {
            "category":"Home & Garden",
            "subcategory":"Carpets & Floor Coverings",
            "type":"Retail Goods"
        }
    ],
    "sg:phone":"+44 151 639 1205",
    "sg:postcode":"CH45 4NW",
    "sg:province":"Merseyside",
    "sg:tags":[
        "carpets",
        "rug",
        "matting"
    ],
    "wof:name":"Liscard Carpets",
    "wof:placetype":"venue"
},
  "geometry": {"coordinates":[-3.047323,53.419708],"type":"Point"}
}