{
  "type": "Feature",
  "properties": {
    "iso:country":"GB",
    "sg:address":"Brunel House, 1 Archers Court, Dukely Road",
    "sg:city":"Huntingdon",
    "sg:classifiers":[
        {
            "category":"Organizations",
            "subcategory":"Professional Association",
            "type":"Services"
        }
    ],
    "sg:postcode":"PE29 6HQ",
    "sg:province":"Cambridgeshire",
    "sg:tags":[
        "tech",
        "system",
        "automation"
    ],
    "wof:name":"Pneumatic Lines Ltd.",
    "wof:placetype":"venue"
},
  "geometry": {"coordinates":[-0.1910640001,52.3371505737],"type":"Point"}
}