{
  "type": "Feature",
  "properties": {
    "addr:full":"Third Floor, Empire House Cardiff Cardiff CF10 5FN",
    "addr:housenumber":"third",
    "addr:postcode":"cf10 5fn",
    "iso:country":"GB",
    "sg:address":"Third Floor, Empire House",
    "sg:city":"Cardiff",
    "sg:classifiers":[
        {
            "category":"Organizations",
            "subcategory":"Non-profit Organization",
            "type":"Services"
        }
    ],
    "sg:phone":"+44 29 2048 4606",
    "sg:postcode":"CF10 5FN",
    "sg:province":"Cardiff",
    "sg:tags":[
        "organisation",
        "voluntary",
        "charity"
    ],
    "wof:name":"Civic Trust for Wales",
    "wof:placetype":"venue"
},
  "geometry": {"coordinates":[-3.180669,51.481258],"type":"Point"}
}