{
  "type": "Feature",
  "properties": {
    "iso:country":"GB",
    "sg:address":"King Street, Great Harwood",
    "sg:city":"Blackburn",
    "sg:classifiers":[
        {
            "category":"Place Of Worship",
            "type":"Public Place"
        }
    ],
    "sg:phone":"+44 1254 886128",
    "sg:postcode":"BB6 7JN",
    "sg:province":"Lancashire",
    "wof:name":"Central Methodist Church",
    "wof:placetype":"venue"
},
  "geometry": {"coordinates":[-2.410589,53.785267],"type":"Point"}
}