{
  "type": "Feature",
  "properties": {
    "iso:country":"GB",
    "sg:address":"55 Caverswall Road, Blythe Bridge",
    "sg:city":"Stoke-on-trent",
    "sg:classifiers":[
        {
            "category":"Building & Trades",
            "subcategory":"Construction",
            "type":"Services"
        }
    ],
    "sg:phone":"+44 1782 396995",
    "sg:postcode":"ST11 9BG",
    "sg:province":"Staffordshire",
    "sg:tags":[
        "guttering"
    ],
    "wof:name":"Professional Plastics",
    "wof:placetype":"venue"
},
  "geometry": {"coordinates":[-2.065983,52.970291],"type":"Point"}
}