{
  "type": "Feature",
  "properties": {
    "addr:full":"14 The Thoroughfare Woodbridge Suffolk IP12 1AG",
    "addr:housenumber":"14",
    "addr:postcode":"ip12 1ag",
    "addr:street":"The Thoroughfare",
    "iso:country":"GB",
    "sg:address":"14 The Thoroughfare",
    "sg:city":"Woodbridge",
    "sg:classifiers":[
        {
            "category":"Shopping",
            "subcategory":"News",
            "type":"Retail Goods"
        }
    ],
    "sg:phone":"+44 1394 387744",
    "sg:postcode":"IP12 1AG",
    "sg:province":"Suffolk",
    "sg:tags":[
        "newsagent"
    ],
    "wof:name":"United News Shops Ltd.",
    "wof:placetype":"venue"
},
  "geometry": {"coordinates":[1.330412,52.105209],"type":"Point"}
}