{
  "type": "Feature",
  "properties": {
    "addr:full":"51 Cambridge Street, St Neots Huntingdon Bedfordshire PE19 1PH",
    "addr:housenumber":"51",
    "addr:postcode":"pe19 1ph",
    "addr:street":"Cambridge Street",
    "iso:country":"GB",
    "sg:address":"51 Cambridge Street, St Neots",
    "sg:city":"Huntingdon",
    "sg:classifiers":[
        {
            "category":"Shopping",
            "subcategory":"Discount & Variety Stores",
            "type":"Retail Goods"
        }
    ],
    "sg:phone":"+44 1480 216077",
    "sg:postcode":"PE19 1PH",
    "sg:province":"Bedfordshire",
    "sg:tags":[
        "cleaning",
        "supply"
    ],
    "wof:name":"Sharpe",
    "wof:placetype":"venue"
},
  "geometry": {"coordinates":[-0.260761,52.228073],"type":"Point"}
}