{
  "type": "Feature",
  "properties": {
    "addr:full":"216 Eastwoodmains Rd Glasgow East Renfrewshire G76 7HA",
    "addr:housenumber":"216",
    "addr:postcode":"g76 7ha",
    "addr:street":"Eastwoodmains Rd",
    "iso:country":"GB",
    "sg:address":"216 Eastwoodmains Rd",
    "sg:city":"Glasgow",
    "sg:classifiers":[
        {
            "category":"Shopping",
            "subcategory":"Mobile Phones",
            "type":"Retail Goods"
        }
    ],
    "sg:postcode":"G76 7HA",
    "sg:province":"East Renfrewshire",
    "wof:name":"Direct Communications (Scotland) Ltd",
    "wof:placetype":"venue"
},
  "geometry": {"coordinates":[-4.2789020538,55.7907180786],"type":"Point"}
}