{
  "type": "Feature",
  "properties": {
    "addr:full":"208 Old Chester Rd Birkenhead Merseyside L42 3TE",
    "addr:housenumber":"208",
    "addr:postcode":"l42 3te",
    "addr:street":"Old Chester Rd",
    "iso:country":"GB",
    "sg:address":"208 Old Chester Rd",
    "sg:city":"Birkenhead",
    "sg:classifiers":[
        {
            "category":"Personal",
            "subcategory":"Beauty Salon",
            "type":"Services"
        }
    ],
    "sg:phone":"+44 151 645 1258",
    "sg:postcode":"L42 3TE",
    "sg:province":"Merseyside",
    "sg:tags":[
        "unisex",
        "hairdresser"
    ],
    "wof:name":"Hair By Margaret",
    "wof:placetype":"venue"
},
  "geometry": {"coordinates":[-3.0162661076,53.3771896362],"type":"Point"}
}