{
  "type": "Feature",
  "properties": {
    "addr:full":"636 Huddersfield Road, Wyke Bradford West Yorkshire BD12 8JR",
    "addr:housenumber":"636",
    "addr:postcode":"bd12 8jr",
    "addr:street":"Huddersfield Road",
    "iso:country":"GB",
    "sg:address":"636 Huddersfield Road, Wyke",
    "sg:city":"Bradford",
    "sg:classifiers":[
        {
            "category":"Professional",
            "subcategory":"Management & Consulting",
            "type":"Services"
        }
    ],
    "sg:phone":"+44 1274 693079",
    "sg:postcode":"BD12 8JR",
    "sg:province":"West Yorkshire",
    "sg:tags":[
        "consultant",
        "business"
    ],
    "wof:name":"Andrew Murison Consultants",
    "wof:placetype":"venue"
},
  "geometry": {"coordinates":[-1.771578,53.739082],"type":"Point"}
}