{
  "type": "Feature",
  "properties": {
    "addr:full":"20 King Edward Street, Kirton In Lindsey Gainsborough Lincolnshire DN21 4NQ",
    "addr:housenumber":"20",
    "addr:postcode":"dn21 4nq",
    "addr:street":"King Edward Street",
    "iso:country":"GB",
    "sg:address":"20 King Edward Street, Kirton In Lindsey",
    "sg:city":"Gainsborough",
    "sg:classifiers":[
        {
            "category":"Education",
            "subcategory":"Library",
            "type":"Public Place"
        }
    ],
    "sg:phone":"+44 1652 648406",
    "sg:postcode":"DN21 4NQ",
    "sg:province":"Lincolnshire",
    "sg:tags":[
        "book"
    ],
    "wof:name":"Kirton in Lindsey Library",
    "wof:placetype":"venue"
},
  "geometry": {"coordinates":[-0.589256,53.477226],"type":"Point"}
}