{
  "type": "Feature",
  "properties": {
    "iso:country":"GB",
    "sg:address":"53 Coalvilles Place, Kelvin Estate",
    "sg:city":"Glasgow",
    "sg:classifiers":[
        {
            "category":"Professional",
            "subcategory":"Engineering",
            "type":"Services"
        }
    ],
    "sg:phone":"+44 1355 241744",
    "sg:postcode":"G75 0PZ",
    "sg:province":"South Lanarkshire",
    "sg:tags":[
        "precision",
        "engineer"
    ],
    "wof:name":"L & R Engineering Ltd.",
    "wof:placetype":"venue"
},
  "geometry": {"coordinates":[-4.154737,55.751759],"type":"Point"}
}