{
  "type": "Feature",
  "properties": {
    "addr:full":"39 Penny Street Lancaster Lancashire LA1 1UA",
    "addr:housenumber":"39",
    "addr:postcode":"la1 1ua",
    "addr:street":"Penny Street",
    "iso:country":"GB",
    "sg:address":"39 Penny Street",
    "sg:city":"Lancaster",
    "sg:classifiers":[
        {
            "category":"Banks & Credit Unions",
            "subcategory":"Financial Services",
            "type":"Services"
        }
    ],
    "sg:phone":"+44 1524 66613",
    "sg:postcode":"LA1 1UA",
    "sg:province":"Lancashire",
    "sg:tags":[
        "building",
        "society"
    ],
    "wof:name":"Skipton Building Society plc",
    "wof:placetype":"venue"
},
  "geometry": {"coordinates":[-2.800112009,54.0473213196],"type":"Point"}
}