{
  "type": "Feature",
  "properties": {
    "iso:country":"GB",
    "sg:address":"Blacksmith Lane, Calow",
    "sg:city":"Chesterfield",
    "sg:classifiers":[
        {
            "category":"Retail",
            "subcategory":"Auto Repair",
            "type":"Services"
        }
    ],
    "sg:phone":"+44 1246 271039",
    "sg:postcode":"S44 5TQ",
    "sg:province":"Derbyshire",
    "sg:tags":[
        "body",
        "car"
    ],
    "wof:name":"P C Motors",
    "wof:placetype":"venue"
},
  "geometry": {"coordinates":[-1.3888440132,53.2337493896],"type":"Point"}
}