{
  "type": "Feature",
  "properties": {
    "addr:full":"Mid Suffolk Business Park, Progress Way Eye Suffolk IP23 7HU",
    "addr:postcode":"ip23 7hu",
    "addr:street":"Park Progress Way",
    "iso:country":"GB",
    "sg:address":"Mid Suffolk Business Park, Progress Way",
    "sg:city":"Eye",
    "sg:classifiers":[
        {
            "category":"Manufacturing",
            "subcategory":"Food",
            "type":"Manufacturing & Wholesale Goods"
        }
    ],
    "sg:postcode":"IP23 7HU",
    "sg:province":"Suffolk",
    "sg:tags":[
        "processing"
    ],
    "wof:name":"Wrightfield Ltd.",
    "wof:placetype":"venue"
},
  "geometry": {"coordinates":[1.145876,52.322071],"type":"Point"}
}