{
  "type": "Feature",
  "properties": {
    "addr:full":"Unit 32 Octagon Shopping Centre Burton-on-trent Derbyshire DE14 3TN",
    "addr:housenumber":"unit 32",
    "addr:postcode":"de14 3tn",
    "addr:street":"Burton-On-Trent",
    "iso:country":"GB",
    "sg:address":"Unit 32 Octagon Shopping Centre",
    "sg:city":"Burton-on-trent",
    "sg:classifiers":[
        {
            "category":"Arts & Performance",
            "subcategory":"Art Gallery",
            "type":"Entertainment"
        }
    ],
    "sg:postcode":"DE14 3TN",
    "sg:province":"Derbyshire",
    "wof:name":"Abdul Choudry",
    "wof:placetype":"venue"
},
  "geometry": {"coordinates":[-1.63372,52.800621],"type":"Point"}
}