{
  "type": "Feature",
  "properties": {
    "addr:full":"Lagrannoch Industrial Estate Callander Stirling FK17 8LD",
    "addr:postcode":"fk17 8ld",
    "addr:street":"Estate Callander",
    "iso:country":"GB",
    "sg:address":"Lagrannoch Industrial Estate",
    "sg:city":"Callander",
    "sg:classifiers":[
        {
            "category":"Professional",
            "subcategory":"Engineering",
            "type":"Services"
        }
    ],
    "sg:phone":"+44 1877 330404",
    "sg:postcode":"FK17 8LD",
    "sg:province":"Stirling",
    "sg:tags":[
        "agricultural",
        "engineer"
    ],
    "wof:name":"John Clark",
    "wof:placetype":"venue"
},
  "geometry": {"coordinates":[-4.199279,56.237835],"type":"Point"}
}