{
  "type": "Feature",
  "properties": {
    "iso:country":"GB",
    "sg:address":"3 High Street",
    "sg:city":"Gillingham",
    "sg:classifiers":[
        {
            "category":"Bars & Pubs",
            "type":"Food & Drink"
        }
    ],
    "sg:phone":"+44 1634 301800",
    "sg:postcode":"ME7 1BE",
    "sg:province":"Kent",
    "sg:tags":[
        "pubs",
        "inn"
    ],
    "wof:name":"The Viscount Harding",
    "wof:placetype":"venue"
},
  "geometry": {"coordinates":[0.54254,51.389114],"type":"Point"}
}