{
  "type": "Feature",
  "properties": {
    "addr:full":"Marzion, Woodhall Road, Tattershall Thorpe Lincoln Lincolnshire LN4 4JT",
    "addr:postcode":"ln4 4jt",
    "addr:street":"Woodhall Road",
    "iso:country":"GB",
    "sg:address":"Marzion, Woodhall Road, Tattershall Thorpe",
    "sg:city":"Lincoln",
    "sg:classifiers":[
        {
            "category":"Freight",
            "type":"Transportation"
        }
    ],
    "sg:phone":"+44 1526 342247",
    "sg:postcode":"LN4 4JT",
    "sg:province":"Lincolnshire",
    "sg:tags":[
        "haulage",
        "transport",
        "road"
    ],
    "wof:name":"Mackinder Transport",
    "wof:placetype":"venue"
},
  "geometry": {"coordinates":[-0.190553993,53.1039810181],"type":"Point"}
}