{
  "type": "Feature",
  "properties": {
    "addr:full":"137a High Street Rochester Kent ME1 1EY",
    "addr:housenumber":"137a",
    "addr:postcode":"me1 1ey",
    "addr:street":"High Street",
    "iso:country":"GB",
    "sg:address":"137a High Street",
    "sg:city":"Rochester",
    "sg:classifiers":[
        {
            "category":"Shopping",
            "subcategory":"Clothing, Apparel, & Fashions",
            "type":"Retail Goods"
        }
    ],
    "sg:phone":"+44 1634 405853",
    "sg:postcode":"ME1 1EY",
    "sg:province":"Kent",
    "sg:tags":[
        "shop"
    ],
    "wof:name":"Revival Little Dorrit",
    "wof:placetype":"venue"
},
  "geometry": {"coordinates":[0.50592,51.387436],"type":"Point"}
}