{
  "type": "Feature",
  "properties": {
    "addr:full":"26 The Square Kenilworth Warwickshire CV8 1EB",
    "addr:housenumber":"26",
    "addr:postcode":"cv8 1eb",
    "addr:street":"The Square",
    "iso:country":"GB",
    "sg:address":"26 The Square",
    "sg:city":"Kenilworth",
    "sg:classifiers":[
        {
            "category":"Shopping",
            "subcategory":"Crafts & Fabrics",
            "type":"Retail Goods"
        }
    ],
    "sg:postcode":"CV8 1EB",
    "sg:province":"Warwickshire",
    "sg:tags":[
        "shop"
    ],
    "wof:name":"Sew & Sew",
    "wof:placetype":"venue"
},
  "geometry": {"coordinates":[-1.579668045,52.3429069519],"type":"Point"}
}