{
  "type": "Feature",
  "properties": {
    "addr:full":"1 Angel Court London EC2R 7HJ",
    "addr:housenumber":"1",
    "addr:postcode":"ec2r 7hj",
    "addr:street":"Angel Court",
    "iso:country":"GB",
    "sg:address":"1 Angel Court",
    "sg:city":"London",
    "sg:classifiers":[
        {
            "category":"Professional",
            "subcategory":"Computer Services",
            "type":"Services"
        }
    ],
    "sg:postcode":"EC2R 7HJ",
    "sg:tags":[
        "environment",
        "environmental",
        "campaigning",
        "campaign",
        "campaigns",
        "green",
        "eco",
        "grassroots",
        "social-network",
        "social-media"
    ],
    "sg:website":"http://greenvoice.com/",
    "wof:name":"Greenvoice",
    "wof:placetype":"venue"
},
  "geometry": {"coordinates":[-0.0874239,51.5147349],"type":"Point"}
}