{
  "type": "Feature",
  "properties": {
    "addr:full":"P O Box 200 Harrogate North Yorkshire HG1 2YR",
    "addr:housenumber":"200",
    "addr:postcode":"hg1 2yr",
    "addr:street":"P O Box",
    "iso:country":"GB",
    "sg:address":"P O Box 200",
    "sg:city":"Harrogate",
    "sg:classifiers":[
        {
            "category":"Wholesale",
            "subcategory":"Books, Periodicals, & Newspapers",
            "type":"Manufacturing & Wholesale Goods"
        }
    ],
    "sg:postcode":"HG1 2YR",
    "sg:province":"North Yorkshire",
    "sg:tags":[
        "publishing"
    ],
    "wof:name":"Take That Ltd.",
    "wof:placetype":"venue"
},
  "geometry": {"coordinates":[-1.544524,53.99469],"type":"Point"}
}