{
  "type": "Feature",
  "properties": {
    "iso:country":"GB",
    "sg:address":"325 Brettell Lane",
    "sg:city":"Brierley Hill",
    "sg:classifiers":[
        {
            "category":"Government",
            "subcategory":"Post Office",
            "type":"Public Place"
        }
    ],
    "sg:phone":"+44 1384 486327",
    "sg:postcode":"DY5 3QR",
    "sg:province":"West Midlands",
    "wof:name":"Silver End Post Office Stores",
    "wof:placetype":"venue"
},
  "geometry": {"coordinates":[-2.132851,52.475689],"type":"Point"}
}