{
  "type": "Feature",
  "properties": {
    "iso:country":"GB",
    "sg:address":"209 Melton Road",
    "sg:city":"Leicester",
    "sg:classifiers":[
        {
            "category":"Professional",
            "subcategory":"Accounting & Tax Preparation",
            "type":"Services"
        }
    ],
    "sg:phone":"+44 116 261 2772",
    "sg:postcode":"LE4 6QT",
    "sg:province":"Leicestershire",
    "sg:tags":[
        "accountant"
    ],
    "wof:name":"Mapara & Co",
    "wof:placetype":"venue"
},
  "geometry": {"coordinates":[-1.116574,52.657124],"type":"Point"}
}