{
  "type": "Feature",
  "properties": {
    "iso:country":"GB",
    "sg:address":"6 Princes Street",
    "sg:city":"Thurso",
    "sg:classifiers":[
        {
            "category":"Real Estate",
            "subcategory":"Architect",
            "type":"Services"
        }
    ],
    "sg:phone":"+44 1847 893811",
    "sg:postcode":"KW14 7BQ",
    "sg:province":"Highland",
    "wof:name":"Peter Knight Architects",
    "wof:placetype":"venue"
},
  "geometry": {"coordinates":[-3.5214738846,58.5947608948],"type":"Point"}
}