{
  "type": "Feature",
  "properties": {
    "addr:full":"Lurista House, Littlewood Lane, Wroxham Hoveton Norwich Norfolk NR12 8DZ",
    "addr:postcode":"nr12 8dz",
    "addr:street":"Littlewood Lane",
    "iso:country":"GB",
    "sg:address":"Lurista House, Littlewood Lane, Wroxham Hoveton",
    "sg:city":"Norwich",
    "sg:classifiers":[
        {
            "category":"Wholesale",
            "subcategory":"Chemicals & Plastics",
            "type":"Manufacturing & Wholesale Goods"
        }
    ],
    "sg:phone":"+44 1603 783061",
    "sg:postcode":"NR12 8DZ",
    "sg:province":"Norfolk",
    "sg:tags":[
        "product",
        "allied"
    ],
    "wof:name":"Slater & Frith Ltd.",
    "wof:placetype":"venue"
},
  "geometry": {"coordinates":[1.414644,52.714527],"type":"Point"}
}