{
  "type": "Feature",
  "properties": {
    "addr:full":"Constellation Mill, Ainasworth Road, Radcliffe Manchester Greater Manchester M26 4HD",
    "addr:postcode":"m26 4hd",
    "addr:street":"Constellation;Ainasworth Road",
    "iso:country":"GB",
    "sg:address":"Constellation Mill, Ainasworth Road, Radcliffe",
    "sg:city":"Manchester",
    "sg:classifiers":[
        {
            "category":"Home & Garden",
            "subcategory":"Home Furnishings",
            "type":"Retail Goods"
        }
    ],
    "sg:phone":"+44 161 724 6537",
    "sg:postcode":"M26 4HD",
    "sg:province":"Greater Manchester",
    "sg:tags":[
        "furnishers",
        "planner",
        "kitchen"
    ],
    "wof:name":"Woodcraft Designs (Radcliffe) Ltd.",
    "wof:placetype":"venue"
},
  "geometry": {"coordinates":[-2.3383700848,53.5737495422],"type":"Point"}
}