{
  "type": "Feature",
  "properties": {
    "iso:country":"GB",
    "sg:address":"15 High Street",
    "sg:city":"Axbridge",
    "sg:classifiers":[
        {
            "category":"Transit Center",
            "subcategory":"Freight",
            "type":"Transportation"
        }
    ],
    "sg:postcode":"BS26 2AF",
    "sg:province":"Somerset",
    "sg:tags":[
        "shop",
        "craft",
        "centre"
    ],
    "wof:name":"St.Jude's Gallery",
    "wof:placetype":"venue"
},
  "geometry": {"coordinates":[-2.818613,51.287155],"type":"Point"}
}