{
  "type": "Feature",
  "properties": {
    "addr:full":"Unit 3 The Best Business Centre, Matthias Street Morecambe Lancashire LA4 5JR",
    "addr:housenumber":"unit 3",
    "addr:postcode":"la4 5jr",
    "addr:street":"The;Matthias Street",
    "iso:country":"GB",
    "sg:address":"Unit 3 The Best Business Centre, Matthias Street",
    "sg:city":"Morecambe",
    "sg:classifiers":[
        {
            "category":"Professional",
            "subcategory":"Detective & Security Services",
            "type":"Services"
        }
    ],
    "sg:phone":"+44 1524 582865",
    "sg:postcode":"LA4 5JR",
    "sg:province":"Lancashire",
    "wof:name":"J P Security",
    "wof:placetype":"venue"
},
  "geometry": {"coordinates":[-2.8544940948,54.0701293945],"type":"Point"}
}