{
  "type": "Feature",
  "properties": {
    "addr:full":"Norway Chadwick, Nick La Belper Derbyshire DE56 2HL",
    "addr:postcode":"de56 2hl",
    "iso:country":"GB",
    "sg:address":"Norway Chadwick, Nick La",
    "sg:city":"Belper",
    "sg:classifiers":[
        {
            "category":"Manufacturing",
            "subcategory":"Wood Products",
            "type":"Manufacturing & Wholesale Goods"
        }
    ],
    "sg:postcode":"DE56 2HL",
    "sg:province":"Derbyshire",
    "sg:tags":[
        "woodturning",
        "craftsman"
    ],
    "wof:name":"Woodcrafts World Ltd",
    "wof:placetype":"venue"
},
  "geometry": {"coordinates":[-1.4735980034,53.0713195801],"type":"Point"}
}