{
  "type": "Feature",
  "properties": {
    "iso:country":"GB",
    "sg:address":"218 High Street",
    "sg:city":"Ayr",
    "sg:classifiers":[
        {
            "category":"Home & Garden",
            "subcategory":"Household Appliances",
            "type":"Retail Goods"
        },
        {
            "category":"Communications",
            "type":"Services"
        }
    ],
    "sg:postcode":"KA7 1RQ",
    "sg:province":"South Ayrshire",
    "sg:tags":[
        "tv",
        "video",
        "electrical",
        "domestic",
        "radio"
    ],
    "wof:name":"Cochranes Electrical & Hardware",
    "wof:placetype":"venue"
},
  "geometry": {"coordinates":[-4.628757,55.461178],"type":"Point"}
}