{
  "type": "Feature",
  "properties": {
    "iso:country":"GB",
    "sg:address":"22 Chapel St",
    "sg:city":"Llangollen",
    "sg:classifiers":[
        {
            "category":"Professional",
            "type":"Services"
        }
    ],
    "sg:phone":"+44 1978 869384",
    "sg:postcode":"LL20 8NN",
    "sg:province":"Denbighshire",
    "sg:tags":[
        "repair",
        "tech",
        "maintenance"
    ],
    "wof:name":"Gallery Computer World",
    "wof:placetype":"venue"
},
  "geometry": {"coordinates":[-3.168934,52.969673],"type":"Point"}
}