{
  "type": "Feature",
  "properties": {
    "iso:country":"GB",
    "sg:address":"Eastern Midlothian Branch, 131 High Street",
    "sg:city":"Dalkeith",
    "sg:classifiers":[
        {
            "category":"Organizations",
            "subcategory":"Non-profit Organization",
            "type":"Services"
        }
    ],
    "sg:phone":"+44 131 654 0340",
    "sg:postcode":"EH22 1BE",
    "sg:province":"City of Edinburgh",
    "sg:tags":[
        "charitable",
        "organisation",
        "voluntary",
        "charity"
    ],
    "wof:name":"British Red Cross Society",
    "wof:placetype":"venue"
},
  "geometry": {"coordinates":[-3.068613,55.892879],"type":"Point"}
}