{
  "type": "Feature",
  "properties": {
    "addr:full":"24 Nuneaton Way, The Boltons Newcastle-upon-tyne Tyne and Wear NE5 1QN",
    "addr:housenumber":"24",
    "addr:postcode":"ne5 1qn",
    "addr:street":"Nuneaton Way",
    "iso:country":"GB",
    "sg:address":"24 Nuneaton Way, The Boltons",
    "sg:city":"Newcastle-upon-tyne",
    "sg:classifiers":[
        {
            "category":"Manufacturing",
            "subcategory":"Signs",
            "type":"Manufacturing & Wholesale Goods"
        }
    ],
    "sg:phone":"+44 191 267 9333",
    "sg:postcode":"NE5 1QN",
    "sg:province":"Tyne and Wear",
    "sg:tags":[
        "nameplate"
    ],
    "wof:name":"Supreme Sales Signs & Systems",
    "wof:placetype":"venue"
},
  "geometry": {"coordinates":[-1.724856,55.002537],"type":"Point"}
}