{
  "type": "Feature",
  "properties": {
    "addr:full":"76 Norbreck Road Thornton-cleveleys Lancashire FY5 1RP",
    "addr:housenumber":"76",
    "addr:postcode":"fy5 1rp",
    "addr:street":"Norbreck Road",
    "iso:country":"GB",
    "sg:address":"76 Norbreck Road",
    "sg:city":"Thornton-cleveleys",
    "sg:classifiers":[
        {
            "category":"Food & Beverages",
            "subcategory":"Bakery",
            "type":"Retail Goods"
        }
    ],
    "sg:phone":"+44 1253 351544",
    "sg:postcode":"FY5 1RP",
    "sg:province":"Lancashire",
    "sg:tags":[
        "shop",
        "baker"
    ],
    "wof:name":"Norbreck Bakery",
    "wof:placetype":"venue"
},
  "geometry": {"coordinates":[-3.0467679501,53.857837677],"type":"Point"}
}