{
  "type": "Feature",
  "properties": {
    "addr:full":"1 Park View, Station Road, Groombridge Tunbridge Wells East Sussex TN3 9RB",
    "addr:housenumber":"1",
    "addr:postcode":"tn3 9rb",
    "addr:street":"Park View Station Road",
    "iso:country":"GB",
    "sg:address":"1 Park View, Station Road, Groombridge",
    "sg:city":"Tunbridge Wells",
    "sg:classifiers":[
        {
            "category":"Professional",
            "subcategory":"Employment Agencies",
            "type":"Services"
        }
    ],
    "sg:phone":"+44 1892 861073",
    "sg:postcode":"TN3 9RB",
    "sg:province":"East Sussex",
    "sg:tags":[
        "consultant"
    ],
    "wof:name":"Warburtons Catering Recruitment",
    "wof:placetype":"venue"
},
  "geometry": {"coordinates":[0.178580001,51.1116256714],"type":"Point"}
}