{
  "type": "Feature",
  "properties": {
    "addr:full":"4 Dodmoor Grange, Telford Shropshire TF3 2AW",
    "addr:housenumber":"4",
    "addr:postcode":"tf3 2aw",
    "addr:street":"Dodmoor Grange",
    "iso:country":"GB",
    "sg:address":"4 Dodmoor Grange,",
    "sg:city":"Telford",
    "sg:classifiers":[
        {
            "category":"Shopping",
            "subcategory":"Computers & Home Electronics",
            "type":"Retail Goods"
        }
    ],
    "sg:phone":"+44 1952 597326",
    "sg:postcode":"TF3 2AW",
    "sg:province":"Shropshire",
    "wof:name":"Ade Home Computers.",
    "wof:placetype":"venue"
},
  "geometry": {"coordinates":[-2.4385950565,52.6662445068],"type":"Point"}
}