{
  "type": "Feature",
  "properties": {
    "addr:full":"11 The Broadway Haywards Heath East Sussex RH16 3AQ",
    "addr:housenumber":"11",
    "addr:postcode":"rh16 3aq",
    "addr:street":"The Broadway",
    "iso:country":"GB",
    "sg:address":"11 The Broadway",
    "sg:city":"Haywards Heath",
    "sg:classifiers":[
        {
            "category":"Shopping",
            "subcategory":"Books",
            "type":"Retail Goods"
        }
    ],
    "sg:phone":"+44 1444 412785",
    "sg:postcode":"RH16 3AQ",
    "sg:province":"East Sussex",
    "sg:tags":[
        "bookseller",
        "retailer"
    ],
    "sg:website":"http://www.halcyonbookshop.com",
    "wof:name":"The Halcyon Bookshop",
    "wof:placetype":"venue"
},
  "geometry": {"coordinates":[-0.1066400036,50.9996681213],"type":"Point"}
}