{
  "type": "Feature",
  "properties": {
    "iso:country":"GB",
    "sg:address":"1 Blackberry Way, Orchard Park",
    "sg:city":"Skegness",
    "sg:classifiers":[
        {
            "category":"Professional",
            "subcategory":"Detective & Security Services",
            "type":"Services"
        }
    ],
    "sg:postcode":"PE25 1JF",
    "sg:province":"Lincolnshire",
    "sg:tags":[
        "alarm",
        "burglar",
        "system"
    ],
    "wof:name":"John Lait",
    "wof:placetype":"venue"
},
  "geometry": {"coordinates":[0.3370000124,53.1452713013],"type":"Point"}
}