{
  "type": "Feature",
  "properties": {
    "iso:country":"GB",
    "sg:address":"152 Haverstock Hill",
    "sg:city":"Hampstead",
    "sg:classifiers":[
        {
            "category":"Restaurant",
            "type":"Food & Drink"
        }
    ],
    "sg:phone":"+44 20 7722 5047",
    "sg:postcode":"NW3 2AY",
    "sg:province":"Greater London",
    "sg:tags":[
        "italian"
    ],
    "wof:name":"Hampstead Osteria",
    "wof:placetype":"venue"
},
  "geometry": {"coordinates":[-0.154724,51.544735],"type":"Point"}
}