{
  "type": "Feature",
  "properties": {
    "addr:full":"71 Camp Road Farnborough Hampshire GU14 6EP",
    "addr:housenumber":"71",
    "addr:postcode":"gu14 6ep",
    "addr:street":"Camp Road",
    "iso:country":"GB",
    "sg:address":"71 Camp Road",
    "sg:city":"Farnborough",
    "sg:classifiers":[
        {
            "category":"Shopping",
            "subcategory":"Jewelry",
            "type":"Retail Goods"
        },
        {
            "category":"Shopping",
            "subcategory":"Comic Books",
            "type":"Retail Goods"
        }
    ],
    "sg:phone":"+44 1252 542045",
    "sg:postcode":"GU14 6EP",
    "sg:province":"Hampshire",
    "sg:tags":[
        "jeweller",
        "sale",
        "jewellery"
    ],
    "wof:name":"Leslie E Biles Ltd.",
    "wof:placetype":"venue"
},
  "geometry": {"coordinates":[-0.747727,51.276505],"type":"Point"}
}