{
  "type": "Feature",
  "properties": {
    "iso:country":"GB",
    "sg:address":"355 Wellingborough Road",
    "sg:city":"Northampton",
    "sg:classifiers":[
        {
            "category":"Food & Beverages",
            "subcategory":"Liquor & Beverages",
            "type":"Retail Goods"
        }
    ],
    "sg:phone":"+44 1604 639703",
    "sg:postcode":"NN1 4ER",
    "sg:province":"Northamptonshire",
    "sg:tags":[
        "beer",
        "wine",
        "spirit",
        "wines"
    ],
    "wof:name":"Wine Rack",
    "wof:placetype":"venue"
},
  "geometry": {"coordinates":[-0.8721489906,52.2438583374],"type":"Point"}
}