{
  "type": "Feature",
  "properties": {
    "addr:full":"24 Romilly Crescent Cardiff Cardiff CF11 9YP",
    "addr:housenumber":"24",
    "addr:postcode":"cf11 9yp",
    "addr:street":"Romilly Crescent",
    "iso:country":"GB",
    "sg:address":"24 Romilly Crescent",
    "sg:city":"Cardiff",
    "sg:classifiers":[
        {
            "category":"Health Services",
            "subcategory":"Hospital",
            "type":"Services"
        },
        {
            "category":"Health Services",
            "subcategory":"Nursing And Care Facility",
            "type":"Services"
        }
    ],
    "sg:phone":"+44 29 2022 8784",
    "sg:postcode":"CF11 9YP",
    "sg:province":"Cardiff",
    "sg:tags":[
        "home"
    ],
    "wof:name":"ST WINIFREDE'S HOSPITAL",
    "wof:placetype":"venue"
},
  "geometry": {"coordinates":[-3.202831,51.485592],"type":"Point"}
}