{
  "type": "Feature",
  "properties": {
    "iso:country":"GB",
    "sg:address":"38 Coombe Shaw, Ninfield",
    "sg:city":"Battle",
    "sg:classifiers":[
        {
            "category":"Military Area",
            "subcategory":"Air Force Base",
            "type":"Public Place"
        }
    ],
    "sg:phone":"+44 1424 731366",
    "sg:postcode":"TN33 9LQ",
    "sg:province":"East Sussex",
    "sg:tags":[
        "taxi",
        "hire",
        "private"
    ],
    "wof:name":"Airport Cars",
    "wof:placetype":"venue"
},
  "geometry": {"coordinates":[0.414888,50.893734],"type":"Point"}
}