{
  "type": "Feature",
  "properties": {
    "addr:full":"206a Nine Mile Ride Wokingham Berkshire RG40 3PX",
    "addr:housenumber":"206a",
    "addr:postcode":"rg40 3px",
    "addr:street":"Nine Mile Ride",
    "iso:country":"GB",
    "sg:address":"206a Nine Mile Ride",
    "sg:city":"Wokingham",
    "sg:classifiers":[
        {
            "category":"Building & Trades",
            "subcategory":"Construction",
            "type":"Services"
        }
    ],
    "sg:postcode":"RG40 3PX",
    "sg:province":"Berkshire",
    "sg:tags":[
        "ceiling",
        "contractor"
    ],
    "wof:name":"Alexander Lucas",
    "wof:placetype":"venue"
},
  "geometry": {"coordinates":[-0.8541809916,51.3771057129],"type":"Point"}
}