{
  "type": "Feature",
  "properties": {
    "addr:full":"34 Summerfield Earlston Scottish Borders TD4 6ET",
    "addr:housenumber":"34",
    "addr:postcode":"td4 6et",
    "addr:street":"Summerfield Earlston",
    "iso:country":"GB",
    "sg:address":"34 Summerfield",
    "sg:city":"Earlston",
    "sg:classifiers":[
        {
            "category":"Farming",
            "subcategory":"Dairy Farm",
            "type":"Manufacturing & Wholesale Goods"
        }
    ],
    "sg:phone":"+44 1896 849615",
    "sg:postcode":"TD4 6ET",
    "sg:province":"Scottish Borders",
    "wof:name":"Doug Welsh",
    "wof:placetype":"venue"
},
  "geometry": {"coordinates":[-2.6705141068,55.6412200928],"type":"Point"}
}