{
  "type": "Feature",
  "properties": {
    "addr:full":"Collier Row Rd Romford Essex RM5 2BH",
    "addr:postcode":"rm5 2bh",
    "addr:street":"Collier Row Rd",
    "iso:country":"GB",
    "sg:address":"Collier Row Rd",
    "sg:city":"Romford",
    "sg:classifiers":[
        {
            "category":"Personal",
            "type":"Services"
        }
    ],
    "sg:phone":"+44 20 8500 0000",
    "sg:postcode":"RM5 2BH",
    "sg:province":"Essex",
    "sg:tags":[
        "wedding"
    ],
    "wof:name":"Mayflower Wedding Cars",
    "wof:placetype":"venue"
},
  "geometry": {"coordinates":[0.160365,51.598598],"type":"Point"}
}