{
  "type": "Feature",
  "properties": {
    "addr:full":"35 Station Road, New Barnet Barnet Hertfordshire EN5 1PR",
    "addr:housenumber":"35",
    "addr:postcode":"en5 1pr",
    "addr:street":"Station Road",
    "iso:country":"GB",
    "sg:address":"35 Station Road, New Barnet",
    "sg:city":"Barnet",
    "sg:classifiers":[
        {
            "category":"Professional",
            "subcategory":"Computer Services",
            "type":"Services"
        }
    ],
    "sg:postcode":"EN5 1PR",
    "sg:province":"Hertfordshire",
    "sg:tags":[
        "consultant"
    ],
    "wof:name":"Ferndale Consultancy",
    "wof:placetype":"venue"
},
  "geometry": {"coordinates":[-0.178515,51.648842],"type":"Point"}
}