{
  "type": "Feature",
  "properties": {
    "addr:full":"82 Centurion Road Brighton East Sussex BN1 3LN",
    "addr:housenumber":"82",
    "addr:postcode":"bn1 3ln",
    "addr:street":"Centurion Road",
    "iso:country":"GB",
    "sg:address":"82 Centurion Road",
    "sg:city":"Brighton",
    "sg:classifiers":[
        {
            "category":"Shopping",
            "subcategory":"Clothing, Apparel, & Fashions",
            "type":"Retail Goods"
        }
    ],
    "sg:postcode":"BN1 3LN",
    "sg:province":"East Sussex",
    "sg:tags":[
        "clothing",
        "fabric"
    ],
    "wof:name":"Axfords",
    "wof:placetype":"venue"
},
  "geometry": {"coordinates":[-0.1434080005,50.8266296387],"type":"Point"}
}