{
  "type": "Feature",
  "properties": {
    "addr:full":"16 Kings Pde, King St Stanford-le-hope Essex SS17 0HP",
    "addr:housenumber":"16",
    "addr:postcode":"ss17 0hp",
    "addr:street":"Kings Pde King St",
    "iso:country":"GB",
    "sg:address":"16 Kings Pde, King St",
    "sg:city":"Stanford-le-hope",
    "sg:classifiers":[
        {
            "category":"Shopping",
            "subcategory":"Pharmacy",
            "type":"Retail Goods"
        }
    ],
    "sg:phone":"+44 1375 675478",
    "sg:postcode":"SS17 0HP",
    "sg:province":"Essex",
    "sg:tags":[
        "pharmacist",
        "chemist"
    ],
    "wof:name":"Macrofield Ltd",
    "wof:placetype":"venue"
},
  "geometry": {"coordinates":[0.4147500098,51.5136451721],"type":"Point"}
}