{
  "type": "Feature",
  "properties": {
    "iso:country":"GB",
    "sg:address":"Unit 10 British Wharf, Landmann Way",
    "sg:city":"New Cross",
    "sg:classifiers":[
        {
            "category":"Shopping",
            "subcategory":"Stationery & Office Supplies",
            "type":"Retail Goods"
        }
    ],
    "sg:phone":"+44 20 8691 6682",
    "sg:postcode":"SE14 5RS",
    "sg:province":"Greater London",
    "sg:tags":[
        "equipment",
        "furniture"
    ],
    "wof:name":"Primary Solutions",
    "wof:placetype":"venue"
},
  "geometry": {"coordinates":[-0.040459,51.47496],"type":"Point"}
}