{
  "type": "Feature",
  "properties": {
    "addr:full":"Suite 107 Crown House, Armley Road Leeds West Yorkshire LS12 2EJ",
    "addr:housenumber":"suite 107",
    "addr:postcode":"ls12 2ej",
    "addr:street":"Crown;Armley Road",
    "iso:country":"GB",
    "sg:address":"Suite 107 Crown House, Armley Road",
    "sg:city":"Leeds",
    "sg:classifiers":[
        {
            "category":"Professional",
            "subcategory":"Employment Agencies",
            "type":"Services"
        }
    ],
    "sg:phone":"+44 113 245 6199",
    "sg:postcode":"LS12 2EJ",
    "sg:province":"West Yorkshire",
    "sg:tags":[
        "consultant"
    ],
    "wof:name":"Morson Alltrades",
    "wof:placetype":"venue"
},
  "geometry": {"coordinates":[-1.586364,53.798302],"type":"Point"}
}