{
  "type": "Feature",
  "properties": {
    "addr:full":"118 Willows La Bolton Lancashire BL3 4AB",
    "addr:housenumber":"118",
    "addr:postcode":"bl3 4ab",
    "addr:street":"Willows La Bolton",
    "iso:country":"GB",
    "sg:address":"118 Willows La",
    "sg:city":"Bolton",
    "sg:classifiers":[
        {
            "category":"Shopping",
            "subcategory":"News",
            "type":"Retail Goods"
        }
    ],
    "sg:phone":"+44 1204 62572",
    "sg:postcode":"BL3 4AB",
    "sg:province":"Lancashire",
    "sg:tags":[
        "newsagent"
    ],
    "wof:name":"Aspinall's",
    "wof:placetype":"venue"
},
  "geometry": {"coordinates":[-2.4497768879,53.5673828125],"type":"Point"}
}