{
  "type": "Feature",
  "properties": {
    "iso:country":"GB",
    "sg:address":"Church Lane, Willoughby On The Wolds",
    "sg:city":"Loughborough",
    "sg:classifiers":[
        {
            "category":"Education",
            "subcategory":"School",
            "type":"Public Place"
        }
    ],
    "sg:phone":"+44 1509 880620",
    "sg:postcode":"LE12 6SS",
    "sg:province":"Leicestershire",
    "sg:tags":[
        "local",
        "authority"
    ],
    "wof:name":"Willoughby-on-the-wolds Primary School",
    "wof:placetype":"venue"
},
  "geometry": {"coordinates":[-1.150187,52.832825],"type":"Point"}
}