{
  "type": "Feature",
  "properties": {
    "addr:full":"146 Valley Rd Rickmansworth Hertfordshire WD3 4BP",
    "addr:housenumber":"146",
    "addr:postcode":"wd3 4bp",
    "addr:street":"Valley Rd",
    "iso:country":"GB",
    "sg:address":"146 Valley Rd",
    "sg:city":"Rickmansworth",
    "sg:classifiers":[
        {
            "category":"Professional",
            "subcategory":"Computer Services",
            "type":"Services"
        }
    ],
    "sg:phone":"+44 1923 897477",
    "sg:postcode":"WD3 4BP",
    "sg:province":"Hertfordshire",
    "sg:tags":[
        "consultant"
    ],
    "wof:name":"Alan Leibert Consultancy",
    "wof:placetype":"venue"
},
  "geometry": {"coordinates":[-0.4940319955,51.6492347717],"type":"Point"}
}