{
  "type": "Feature",
  "properties": {
    "addr:full":"Suite 8 Ludgate House, 107-111 Fleet Street London Greater London EC4A 2AB",
    "addr:housenumber":"suite 8;107-111",
    "addr:postcode":"ec4a 2ab",
    "addr:street":"Ludgate;Fleet Street",
    "iso:country":"GB",
    "sg:address":"Suite 8 Ludgate House, 107-111 Fleet Street",
    "sg:city":"London",
    "sg:classifiers":[
        {
            "category":"Professional",
            "subcategory":"Lawyer & Legal Services",
            "type":"Services"
        }
    ],
    "sg:postcode":"EC4A 2AB",
    "sg:province":"Greater London",
    "sg:tags":[
        "solicitor"
    ],
    "wof:name":"Robinson & Co.",
    "wof:placetype":"venue"
},
  "geometry": {"coordinates":[-0.104652,51.51421],"type":"Point"}
}