{
  "type": "Feature",
  "properties": {
    "addr:full":"Wilton Farm, Hockwold Thetford Norfolk IP26 4NA",
    "addr:postcode":"ip26 4na",
    "addr:street":"Wilton;Hockwold",
    "iso:country":"GB",
    "sg:address":"Wilton Farm, Hockwold",
    "sg:city":"Thetford",
    "sg:classifiers":[
        {
            "category":"Farming",
            "subcategory":"Livestock Farm",
            "type":"Manufacturing & Wholesale Goods"
        }
    ],
    "sg:phone":"+44 1842 828494",
    "sg:postcode":"IP26 4NA",
    "sg:province":"Norfolk",
    "sg:tags":[
        "others"
    ],
    "wof:name":"Enefer Bros",
    "wof:placetype":"venue"
},
  "geometry": {"coordinates":[0.5380529761,52.4628677368],"type":"Point"}
}