{
  "type": "Feature",
  "properties": {
    "iso:country":"GB",
    "sg:address":"27 Craven Road",
    "sg:city":"Newbury",
    "sg:classifiers":[
        {
            "category":"Professional",
            "type":"Services"
        },
        {
            "category":"Health Services",
            "subcategory":"Health Practitioner",
            "type":"Services"
        },
        {
            "category":"Shopping",
            "subcategory":"Pharmacy",
            "type":"Retail Goods"
        }
    ],
    "sg:postcode":"RG14 5NG",
    "sg:province":"Berkshire",
    "sg:tags":[
        "medicine",
        "therapy",
        "reflexologists",
        "osteopath"
    ],
    "wof:name":"Diamond Holistic Centre",
    "wof:placetype":"venue"
},
  "geometry": {"coordinates":[-1.328221,51.39893],"type":"Point"}
}