{
  "type": "Feature",
  "properties": {
    "iso:country":"GB",
    "sg:address":"Pool House, Bancroft Rd",
    "sg:city":"Reigate",
    "sg:classifiers":[
        {
            "category":"Social Services",
            "subcategory":"Retirement Home",
            "type":"Services"
        }
    ],
    "sg:phone":"+44 1737 246777",
    "sg:postcode":"RH2 7RP",
    "sg:province":"Surrey",
    "sg:tags":[
        "care"
    ],
    "wof:name":"Primrose Care Ltd",
    "wof:placetype":"venue"
},
  "geometry": {"coordinates":[-0.203805,51.236767],"type":"Point"}
}