{
  "type": "Feature",
  "properties": {
    "addr:full":"Ivy Cottage Brook Lane, Cold Waltham Pulborough West Sussex RH20 1LS",
    "addr:postcode":"rh20 1ls",
    "addr:street":"Brook Lane Cold",
    "iso:country":"GB",
    "sg:address":"Ivy Cottage Brook Lane, Cold Waltham",
    "sg:city":"Pulborough",
    "sg:classifiers":[
        {
            "category":"Professional",
            "subcategory":"Management & Consulting",
            "type":"Services"
        }
    ],
    "sg:postcode":"RH20 1LS",
    "sg:province":"West Sussex",
    "sg:tags":[
        "consultant",
        "business"
    ],
    "wof:name":"Dab Consulting Ltd.",
    "wof:placetype":"venue"
},
  "geometry": {"coordinates":[-0.5459799767,50.9366493225],"type":"Point"}
}