{
  "type": "Feature",
  "properties": {
    "addr:full":"1 Upper Wimpole Street London Greater London W1G 6LD",
    "addr:housenumber":"1",
    "addr:postcode":"w1g 6ld",
    "addr:street":"Upper Wimpole Street",
    "iso:country":"GB",
    "sg:address":"1 Upper Wimpole Street",
    "sg:city":"London",
    "sg:classifiers":[
        {
            "category":"Personal",
            "type":"Services"
        }
    ],
    "sg:phone":"+44 20 7486 5744",
    "sg:postcode":"W1G 6LD",
    "sg:province":"Greater London",
    "sg:tags":[
        "stress",
        "management"
    ],
    "wof:name":"Corporate Stress Care Ltd.",
    "wof:placetype":"venue"
},
  "geometry": {"coordinates":[-0.149043,51.520508],"type":"Point"}
}