{
  "type": "Feature",
  "properties": {
    "addr:full":"27 Chaucer Road Sittingbourne Kent ME10 1EZ",
    "addr:housenumber":"27",
    "addr:postcode":"me10 1ez",
    "addr:street":"Chaucer Road",
    "iso:country":"GB",
    "sg:address":"27 Chaucer Road",
    "sg:city":"Sittingbourne",
    "sg:classifiers":[
        {
            "category":"Food & Beverages",
            "subcategory":"Fruits & Vegetables",
            "type":"Retail Goods"
        }
    ],
    "sg:postcode":"ME10 1EZ",
    "sg:province":"Kent",
    "sg:tags":[
        "greengrocer"
    ],
    "wof:name":"Roots & Fruits",
    "wof:placetype":"venue"
},
  "geometry": {"coordinates":[0.725062,51.334751],"type":"Point"}
}