{
  "type": "Feature",
  "properties": {
    "addr:full":"Fox House, 135 High Street Bromley Kent BR1 1JF",
    "addr:housenumber":"135",
    "addr:postcode":"br1 1jf",
    "addr:street":"High Street",
    "iso:country":"GB",
    "sg:address":"Fox House, 135 High Street",
    "sg:city":"Bromley",
    "sg:classifiers":[
        {
            "category":"Home & Garden",
            "subcategory":"Household Appliances",
            "type":"Retail Goods"
        }
    ],
    "sg:phone":"+44 20 8460 5791",
    "sg:postcode":"BR1 1JF",
    "sg:province":"Kent",
    "sg:tags":[
        "refrigeration",
        "air conditioning"
    ],
    "wof:name":"Weaver Engineering Services Ltd.",
    "wof:placetype":"venue"
},
  "geometry": {"coordinates":[0.015336,51.404278],"type":"Point"}
}