{
  "type": "Feature",
  "properties": {
    "addr:full":"13 Market Place Margate Kent CT9 1ES",
    "addr:housenumber":"13",
    "addr:postcode":"ct9 1es",
    "addr:street":"Market Place Margate",
    "iso:country":"GB",
    "sg:address":"13 Market Place",
    "sg:city":"Margate",
    "sg:classifiers":[
        {
            "category":"Shopping",
            "subcategory":"Music",
            "type":"Retail Goods"
        }
    ],
    "sg:phone":"+44 1843 295595",
    "sg:postcode":"CT9 1ES",
    "sg:province":"Kent",
    "sg:tags":[
        "record",
        "tape",
        "cd"
    ],
    "wof:name":"Funhouse Records",
    "wof:placetype":"venue"
},
  "geometry": {"coordinates":[1.382185,51.389259],"type":"Point"}
}