{
  "type": "Feature",
  "properties": {
    "iso:country":"GB",
    "sg:address":"47 Market Square",
    "sg:city":"Duns",
    "sg:classifiers":[
        {
            "category":"Professional",
            "subcategory":"Lawyer & Legal Services",
            "type":"Services"
        }
    ],
    "sg:phone":"+44 1361 882752",
    "sg:postcode":"TD11 3BX",
    "sg:province":"East Lothian",
    "sg:tags":[
        "solicitor"
    ],
    "wof:name":"Melrose & Porteous",
    "wof:placetype":"venue"
},
  "geometry": {"coordinates":[-2.3436989784,55.7779388428],"type":"Point"}
}