{
  "type": "Feature",
  "properties": {
    "addr:full":"Unit 12, Nazeing New Rd Broxbourne Essex EN10 6SU",
    "addr:housenumber":"unit 12",
    "addr:postcode":"en10 6su",
    "addr:street":"New Rd",
    "iso:country":"GB",
    "sg:address":"Unit 12, Nazeing New Rd",
    "sg:city":"Broxbourne",
    "sg:classifiers":[
        {
            "category":"Communications",
            "subcategory":"Film & Video Production",
            "type":"Services"
        }
    ],
    "sg:phone":"+44 1992 446396",
    "sg:postcode":"EN10 6SU",
    "sg:province":"Essex",
    "sg:tags":[
        "tv"
    ],
    "wof:name":"T.v.s Ltd",
    "wof:placetype":"venue"
},
  "geometry": {"coordinates":[-0.008327,51.743404],"type":"Point"}
}