{
  "type": "Feature",
  "properties": {
    "iso:country":"GB",
    "sg:address":"233 Sandycombe Road",
    "sg:city":"Richmond",
    "sg:classifiers":[
        {
            "category":"Autos & Motor Vehicles",
            "subcategory":"Boat Sales",
            "type":"Retail Goods"
        }
    ],
    "sg:phone":"+44 20 8948 8157",
    "sg:postcode":"TW9 2EW",
    "sg:province":"Greater London",
    "sg:tags":[
        "balloon"
    ],
    "wof:name":"The Balloon Works",
    "wof:placetype":"venue"
},
  "geometry": {"coordinates":[-0.286496,51.473114],"type":"Point"}
}