{
  "type": "Feature",
  "properties": {
    "addr:full":"4a Spencer Street St Albans Hertfordshire AL3 5EQ",
    "addr:housenumber":"4a",
    "addr:postcode":"al3 5eq",
    "addr:street":"Spencer Street",
    "iso:country":"GB",
    "sg:address":"4a Spencer Street",
    "sg:city":"St Albans",
    "sg:classifiers":[
        {
            "category":"Travel",
            "subcategory":"Travel Agent",
            "type":"Entertainment"
        }
    ],
    "sg:postcode":"AL3 5EQ",
    "sg:province":"Hertfordshire",
    "wof:name":"St. Albans Travel Business House",
    "wof:placetype":"venue"
},
  "geometry": {"coordinates":[-0.339101,51.752453],"type":"Point"}
}