{
  "type": "Feature",
  "properties": {
    "iso:country":"GB",
    "sg:address":"97 Knollbeck Avenue, Brampton",
    "sg:city":"Barnsley",
    "sg:classifiers":[
        {
            "category":"Food & Beverages",
            "subcategory":"Meat & Fish",
            "type":"Retail Goods"
        }
    ],
    "sg:postcode":"S73 0UB",
    "sg:province":"South Yorkshire",
    "sg:tags":[
        "butcher"
    ],
    "wof:name":"D Greaves",
    "wof:placetype":"venue"
},
  "geometry": {"coordinates":[-1.378629,53.508896],"type":"Point"}
}