{
  "type": "Feature",
  "properties": {
    "iso:country":"GB",
    "sg:address":"3 Campden House Court, 42 Gloucester Walk",
    "sg:city":"London",
    "sg:classifiers":[
        {
            "category":"Wholesale",
            "subcategory":"Books, Periodicals, & Newspapers",
            "type":"Manufacturing & Wholesale Goods"
        }
    ],
    "sg:postcode":"W8 4HU",
    "sg:province":"Greater London",
    "sg:tags":[
        "publishing"
    ],
    "wof:name":"Q M Lumsden",
    "wof:placetype":"venue"
},
  "geometry": {"coordinates":[-0.19387,51.504951],"type":"Point"}
}