{
  "type": "Feature",
  "properties": {
    "iso:country":"GB",
    "sg:address":"55 Doddington Road",
    "sg:city":"Wellingborough",
    "sg:classifiers":[
        {
            "category":"Building & Trades",
            "subcategory":"Construction",
            "type":"Services"
        }
    ],
    "sg:postcode":"NN8 2JH",
    "sg:province":"Northamptonshire",
    "sg:tags":[
        "decorator",
        "painter"
    ],
    "wof:name":"I D Lloyd & Sons",
    "wof:placetype":"venue"
},
  "geometry": {"coordinates":[-0.695657,52.294312],"type":"Point"}
}