{
  "type": "Feature",
  "properties": {
    "iso:country":"GB",
    "sg:address":"40 Aberconway Road",
    "sg:city":"Morden",
    "sg:classifiers":[
        {
            "category":"Personal",
            "subcategory":"Beauty Salon",
            "type":"Services"
        },
        {
            "category":"Personal",
            "subcategory":"Barber",
            "type":"Services"
        }
    ],
    "sg:phone":"+44 20 8640 9997",
    "sg:postcode":"SM4 5LF",
    "sg:province":"Surrey",
    "sg:tags":[
        "unisex",
        "hairdresser"
    ],
    "wof:name":"SAM'S HAIR STUDIO",
    "wof:placetype":"venue"
},
  "geometry": {"coordinates":[-0.1939560026,51.401966095],"type":"Point"}
}