{
  "type": "Feature",
  "properties": {
    "iso:country":"GB",
    "sg:address":"Rear Of Hanson House, Knight Rd, Strood",
    "sg:city":"Rochester",
    "sg:classifiers":[
        {
            "category":"Sports & Exercise",
            "subcategory":"Gym",
            "type":"Entertainment"
        }
    ],
    "sg:phone":"+44 1634 294113",
    "sg:postcode":"ME2 2JH",
    "sg:province":"Kent",
    "sg:tags":[
        "fitness",
        "health",
        "centre"
    ],
    "wof:name":"Ricky's Health & Fitness",
    "wof:placetype":"venue"
},
  "geometry": {"coordinates":[0.493163,51.394577],"type":"Point"}
}