{
  "type": "Feature",
  "properties": {
    "addr:full":"Pier House, Boringdon Road, Turnchapel Plymouth Devon PL9 9TF",
    "addr:postcode":"pl9 9tf",
    "addr:street":"Boringdon Road",
    "iso:country":"GB",
    "sg:address":"Pier House, Boringdon Road, Turnchapel",
    "sg:city":"Plymouth",
    "sg:classifiers":[
        {
            "category":"Utilities",
            "subcategory":"Sewage",
            "type":"Services"
        }
    ],
    "sg:phone":"+44 1752 482352",
    "sg:postcode":"PL9 9TF",
    "sg:province":"Devon",
    "sg:tags":[
        "acoustic",
        "consultant"
    ],
    "wof:name":"Sonardyne Ltd.",
    "wof:placetype":"venue"
},
  "geometry": {"coordinates":[-4.1187310219,50.3578186035],"type":"Point"}
}