{
  "type": "Feature",
  "properties": {
    "addr:full":"The Old Saddlery Robertsbridge East Sussex TN32 5AP",
    "addr:postcode":"tn32 5ap",
    "iso:country":"GB",
    "sg:address":"The Old Saddlery",
    "sg:city":"Robertsbridge",
    "sg:classifiers":[
        {
            "category":"Shopping",
            "subcategory":"Antiques",
            "type":"Retail Goods"
        }
    ],
    "sg:phone":"+44 1580 880631",
    "sg:postcode":"TN32 5AP",
    "sg:province":"East Sussex",
    "wof:name":"Spearman Books",
    "wof:placetype":"venue"
},
  "geometry": {"coordinates":[0.4744699895,50.9856491089],"type":"Point"}
}