{
  "type": "Feature",
  "properties": {
    "addr:full":"25 Ophir Road, Northend Portsmouth Hampshire PO2 9EL",
    "addr:housenumber":"25",
    "addr:postcode":"hampshire po2 9el",
    "addr:street":"Ophir Road",
    "iso:country":"GB",
    "sg:address":"25 Ophir Road, Northend",
    "sg:city":"Portsmouth",
    "sg:classifiers":[
        {
            "category":"Building & Trades",
            "subcategory":"Construction",
            "type":"Services"
        }
    ],
    "sg:phone":"+44 23 9269 1932",
    "sg:postcode":"PO2 9EL",
    "sg:province":"Hampshire",
    "sg:tags":[
        "roofing",
        "bricklaying"
    ],
    "wof:name":"M G Martin & Son",
    "wof:placetype":"venue"
},
  "geometry": {"coordinates":[-1.0760190487,50.8230552673],"type":"Point"}
}