{
  "type": "Feature",
  "properties": {
    "addr:full":"47 St. Austins Grove Sheringham Norfolk NR26 8DF",
    "addr:housenumber":"47",
    "addr:postcode":"nr26 8df",
    "addr:street":"St. Austins Grove",
    "iso:country":"GB",
    "sg:address":"47 St. Austins Grove",
    "sg:city":"Sheringham",
    "sg:classifiers":[
        {
            "category":"Health Services",
            "subcategory":"Health Practitioner",
            "type":"Services"
        }
    ],
    "sg:phone":"+44 1263 824146",
    "sg:postcode":"NR26 8DF",
    "sg:province":"Norfolk",
    "sg:tags":[
        "therapist",
        "speech"
    ],
    "wof:name":"S & K McVeigh",
    "wof:placetype":"venue"
},
  "geometry": {"coordinates":[1.2193529606,52.9417304993],"type":"Point"}
}