{
  "type": "Feature",
  "properties": {
    "addr:full":"82-88 Montague St Worthing West Sussex BN11 3HF",
    "addr:housenumber":"82-88",
    "addr:postcode":"bn11 3hf",
    "addr:street":"Montague St",
    "iso:country":"GB",
    "sg:address":"82-88 Montague St",
    "sg:city":"Worthing",
    "sg:classifiers":[
        {
            "category":"Communications",
            "subcategory":"Film & Video Production",
            "type":"Services"
        }
    ],
    "sg:phone":"+44 1903 210110",
    "sg:postcode":"BN11 3HF",
    "sg:province":"West Sussex",
    "sg:tags":[
        "tv"
    ],
    "wof:name":"Granada Home Technology",
    "wof:placetype":"venue"
},
  "geometry": {"coordinates":[-0.376259,50.809959],"type":"Point"}
}