{
  "type": "Feature",
  "properties": {
    "iso:country":"GB",
    "sg:address":"25 Greens Road",
    "sg:city":"Cambridge",
    "sg:classifiers":[
        {
            "category":"Building & Trades",
            "subcategory":"Construction",
            "type":"Services"
        }
    ],
    "sg:phone":"+44 1223 501616",
    "sg:postcode":"CB4 3EF",
    "sg:province":"Cambridgeshire",
    "sg:tags":[
        "conversion",
        "loft"
    ],
    "wof:name":"Colin Barnes",
    "wof:placetype":"venue"
},
  "geometry": {"coordinates":[0.1212209985,52.215297699],"type":"Point"}
}