{
  "type": "Feature",
  "properties": {
    "addr:full":"8 Foxdell Northwood Greater London HA6 2BU",
    "addr:housenumber":"8",
    "addr:postcode":"ha6 2bu",
    "addr:street":"Foxdell",
    "iso:country":"GB",
    "sg:address":"8 Foxdell",
    "sg:city":"Northwood",
    "sg:classifiers":[
        {
            "category":"Professional",
            "subcategory":"Management & Consulting",
            "type":"Services"
        },
        {
            "category":"Professional",
            "subcategory":"Advertising",
            "type":"Services"
        }
    ],
    "sg:phone":"+44 1923 820223",
    "sg:postcode":"HA6 2BU",
    "sg:province":"Greater London",
    "sg:tags":[
        "marketing",
        "agency",
        "consultant"
    ],
    "wof:name":"Churchard Martin Advertising Ltd",
    "wof:placetype":"venue"
},
  "geometry": {"coordinates":[-0.4290710092,51.6134643555],"type":"Point"}
}