{
  "type": "Feature",
  "properties": {
    "addr:full":"15 Danbury Road Loughton Essex IG10 3AR",
    "addr:housenumber":"15",
    "addr:postcode":"ig10 3ar",
    "addr:street":"Danbury Road",
    "iso:country":"GB",
    "sg:address":"15 Danbury Road",
    "sg:city":"Loughton",
    "sg:classifiers":[
        {
            "category":"Building & Trades",
            "subcategory":"Plumbing",
            "type":"Services"
        }
    ],
    "sg:postcode":"IG10 3AR",
    "sg:province":"Essex",
    "sg:tags":[
        "drain",
        "clearance",
        "sewer"
    ],
    "wof:name":"A Star Plumbing & Drains",
    "wof:placetype":"venue"
},
  "geometry": {"coordinates":[0.05444,51.636524],"type":"Point"}
}