{
  "type": "Feature",
  "properties": {
    "addr:full":"27a Queens Rd Southend On Sea Essex SS1 1LT",
    "addr:housenumber":"27a",
    "addr:postcode":"ss1 1lt",
    "addr:street":"Queens Rd",
    "iso:country":"GB",
    "sg:address":"27a Queens Rd",
    "sg:city":"Southend On Sea",
    "sg:classifiers":[
        {
            "category":"Professional",
            "subcategory":"Business Services",
            "type":"Services"
        }
    ],
    "sg:phone":"+44 1702 337198",
    "sg:postcode":"SS1 1LT",
    "sg:province":"Essex",
    "sg:tags":[
        "accomodation"
    ],
    "wof:name":"Bodys Business Centre",
    "wof:placetype":"venue"
},
  "geometry": {"coordinates":[0.710211,51.539345],"type":"Point"}
}