{
  "type": "Feature",
  "properties": {
    "addr:full":"210-212 Higher Road, Urmston Manchester Cheshire M41 9BH",
    "addr:housenumber":"210-212",
    "addr:postcode":"m41 9bh",
    "addr:street":"Higher Road",
    "iso:country":"GB",
    "sg:address":"210-212 Higher Road, Urmston",
    "sg:city":"Manchester",
    "sg:classifiers":[
        {
            "category":"Professional",
            "type":"Services"
        }
    ],
    "sg:phone":"+44 161 747 7277",
    "sg:postcode":"M41 9BH",
    "sg:province":"Cheshire",
    "sg:tags":[
        "linen",
        "hire"
    ],
    "wof:name":"Initial Textile Services",
    "wof:placetype":"venue"
},
  "geometry": {"coordinates":[-2.341416,53.44833],"type":"Point"}
}