{
  "type": "Feature",
  "properties": {
    "iso:country":"GB",
    "sg:address":"Unit 2, 113 Walnut Tree Close",
    "sg:city":"Guildford",
    "sg:classifiers":[
        {
            "category":"Home & Garden",
            "subcategory":"Home Furnishings",
            "type":"Retail Goods"
        },
        {
            "category":"Manufacturing",
            "subcategory":"Signs",
            "type":"Manufacturing & Wholesale Goods"
        }
    ],
    "sg:phone":"+44 1483 567756",
    "sg:postcode":"GU1 4UQ",
    "sg:province":"Surrey",
    "sg:tags":[
        "awning",
        "canopy",
        "blinds",
        "marquee"
    ],
    "wof:name":"Interior Fixings Ltd.",
    "wof:placetype":"venue"
},
  "geometry": {"coordinates":[-0.58075,51.241386],"type":"Point"}
}