{
  "type": "Feature",
  "properties": {
    "iso:country":"GB",
    "sg:address":"South Road",
    "sg:city":"Sheffield",
    "sg:classifiers":[
        {
            "category":"Education",
            "subcategory":"Library",
            "type":"Public Place"
        }
    ],
    "sg:phone":"+44 114 203 9532",
    "sg:postcode":"S6 3TD",
    "sg:province":"South Yorkshire",
    "sg:tags":[
        "book"
    ],
    "wof:name":"Walkley Library",
    "wof:placetype":"venue"
},
  "geometry": {"coordinates":[-1.502724,53.394917],"type":"Point"}
}