{
  "type": "Feature",
  "properties": {
    "addr:full":"Llwyn Y Brain, Adfa Newtown Powys SY16 3DA",
    "addr:postcode":"sy16 3da",
    "addr:street":"Llwyn;Adfa",
    "iso:country":"GB",
    "sg:address":"Llwyn Y Brain, Adfa",
    "sg:city":"Newtown",
    "sg:classifiers":[
        {
            "category":"Farming",
            "subcategory":"Livestock Farm",
            "type":"Manufacturing & Wholesale Goods"
        }
    ],
    "sg:phone":"+44 1938 810394",
    "sg:postcode":"SY16 3DA",
    "sg:province":"Powys",
    "sg:tags":[
        "others"
    ],
    "wof:name":"Yeomans & Partners",
    "wof:placetype":"venue"
},
  "geometry": {"coordinates":[-3.3882288933,52.599319458],"type":"Point"}
}