{
  "type": "Feature",
  "properties": {
    "addr:full":"10 Ledborough Wood Beaconsfield Buckinghamshire HP9 2DJ",
    "addr:housenumber":"10",
    "addr:postcode":"hp9 2dj",
    "addr:street":"Ledborough Wood",
    "iso:country":"GB",
    "sg:address":"10 Ledborough Wood",
    "sg:city":"Beaconsfield",
    "sg:classifiers":[
        {
            "category":"Building & Trades",
            "subcategory":"Construction",
            "type":"Services"
        }
    ],
    "sg:phone":"+44 1494 674562",
    "sg:postcode":"HP9 2DJ",
    "sg:province":"Buckinghamshire",
    "sg:tags":[
        "builder"
    ],
    "wof:name":"Abraxas Quality Building",
    "wof:placetype":"venue"
},
  "geometry": {"coordinates":[-0.638823,51.616936],"type":"Point"}
}