{
  "type": "Feature",
  "properties": {
    "iso:country":"GB",
    "sg:address":"4 New Windsor Street",
    "sg:city":"Uxbridge",
    "sg:classifiers":[
        {
            "category":"Professional",
            "subcategory":"Business Services",
            "type":"Services"
        }
    ],
    "sg:postcode":"UB8 2TU",
    "sg:province":"Buckinghamshire",
    "sg:tags":[
        "operator",
        "market"
    ],
    "wof:name":"Wendy Fair Markets Ltd.",
    "wof:placetype":"venue"
},
  "geometry": {"coordinates":[-0.4828790128,51.5446434021],"type":"Point"}
}