{
  "type": "Feature",
  "properties": {
    "addr:full":"Brickyard La, New Rd Gillingham Dorset SP8 4JL",
    "addr:postcode":"sp8 4jl",
    "addr:street":"New Rd",
    "iso:country":"GB",
    "sg:address":"Brickyard La, New Rd",
    "sg:city":"Gillingham",
    "sg:classifiers":[
        {
            "category":"Professional",
            "subcategory":"Engineering",
            "type":"Services"
        }
    ],
    "sg:phone":"+44 1747 824216",
    "sg:postcode":"SP8 4JL",
    "sg:province":"Dorset",
    "sg:tags":[
        "precision",
        "engineer"
    ],
    "wof:name":"Bo-mic",
    "wof:placetype":"venue"
},
  "geometry": {"coordinates":[-2.2750959396,51.033000946],"type":"Point"}
}