{
  "type": "Feature",
  "properties": {
    "iso:country":"GB",
    "sg:address":"40-42 Lothian Street",
    "sg:city":"Norwich",
    "sg:classifiers":[
        {
            "category":"Professional",
            "subcategory":"Printing & Photocopies",
            "type":"Services"
        }
    ],
    "sg:phone":"+44 1263 732767",
    "sg:postcode":"NR2 4PH",
    "sg:province":"Norfolk",
    "sg:tags":[
        "printer"
    ],
    "wof:name":"Rigby Print",
    "wof:placetype":"venue"
},
  "geometry": {"coordinates":[1.284808,52.632755],"type":"Point"}
}