{
  "type": "Feature",
  "properties": {
    "addr:full":"7 The Village Square Shops, Brighton Marina Village Brighton East Sussex BN2 5WA",
    "addr:housenumber":"7",
    "addr:postcode":"bn2 5wa",
    "addr:street":"The Village;Brighton Marina Village",
    "iso:country":"GB",
    "sg:address":"7 The Village Square Shops, Brighton Marina Village",
    "sg:city":"Brighton",
    "sg:classifiers":[
        {
            "category":"Manufacturing",
            "subcategory":"Textiles",
            "type":"Manufacturing & Wholesale Goods"
        }
    ],
    "sg:postcode":"BN2 5WA",
    "sg:province":"East Sussex",
    "sg:tags":[
        "knitwear"
    ],
    "wof:name":"Honeysuckle Fashions Ltd",
    "wof:placetype":"venue"
},
  "geometry": {"coordinates":[-0.091444,50.812279],"type":"Point"}
}