{
  "type": "Feature",
  "properties": {
    "addr:full":"3 Wharfedale Close, Wall Hth Kingswinford Staffordshire DY6 9AZ",
    "addr:housenumber":"3",
    "addr:postcode":"dy6 9az",
    "addr:street":"Wharfedale Close",
    "iso:country":"GB",
    "sg:address":"3 Wharfedale Close, Wall Hth",
    "sg:city":"Kingswinford",
    "sg:classifiers":[
        {
            "category":"Home & Garden",
            "subcategory":"Hardware",
            "type":"Retail Goods"
        }
    ],
    "sg:phone":"+44 1384 277666",
    "sg:postcode":"DY6 9AZ",
    "sg:province":"Staffordshire",
    "sg:tags":[
        "equipment",
        "welding"
    ],
    "wof:name":"Kingswinford Welding Supplies & Services",
    "wof:placetype":"venue"
},
  "geometry": {"coordinates":[-2.167674,52.495804],"type":"Point"}
}