{
  "type": "Feature",
  "properties": {
    "addr:full":"Abbey Rd Huntingdon Cambridgeshire PE17 1DG",
    "addr:postcode":"pe17 1dg",
    "addr:street":"Abbey Rd",
    "iso:country":"GB",
    "sg:address":"Abbey Rd",
    "sg:city":"Huntingdon",
    "sg:classifiers":[
        {
            "category":"Community Center",
            "type":"Public Place"
        }
    ],
    "sg:phone":"+44 1487 710275",
    "sg:postcode":"PE17 1DG",
    "sg:province":"Cambridgeshire",
    "sg:tags":[
        "recreation",
        "leisure",
        "centre"
    ],
    "wof:name":"Ramsey Sports Centre",
    "wof:placetype":"venue"
},
  "geometry": {"coordinates":[-0.0992290005,52.4457359314],"type":"Point"}
}