{
  "type": "Feature",
  "properties": {
    "iso:country":"GB",
    "sg:address":"97 Welsh Row",
    "sg:city":"Nantwich",
    "sg:classifiers":[
        {
            "category":"Bars & Pubs",
            "type":"Food & Drink"
        }
    ],
    "sg:phone":"+44 1270 624758",
    "sg:postcode":"CW5 5ET",
    "sg:province":"Cheshire",
    "sg:tags":[
        "pubs",
        "house",
        "inn",
        "public",
        "activity"
    ],
    "wof:name":"Oddfellows Arms",
    "wof:placetype":"venue"
},
  "geometry": {"coordinates":[-2.52947402,53.0675888062],"type":"Point"}
}