{
  "type": "Feature",
  "properties": {
    "iso:country":"GB",
    "sg:address":"Ystrad Rd",
    "sg:city":"Swansea",
    "sg:classifiers":[
        {
            "category":"Arena",
            "subcategory":"Sports Club",
            "type":"Entertainment"
        }
    ],
    "sg:phone":"+44 1792 579368",
    "sg:postcode":"SA5 4NE",
    "sg:province":"Swansea",
    "sg:tags":[
        "ground"
    ],
    "wof:name":"Swansea Greyhound Stadium",
    "wof:placetype":"venue"
},
  "geometry": {"coordinates":[-3.9961390495,51.6489677429],"type":"Point"}
}