{
  "type": "Feature",
  "properties": {
    "iso:country":"GB",
    "sg:address":"250 Bromham Rd",
    "sg:city":"Bedford",
    "sg:classifiers":[
        {
            "category":"Professional",
            "subcategory":"Engineering",
            "type":"Services"
        }
    ],
    "sg:phone":"+44 1234 266135",
    "sg:postcode":"MK40 4AA",
    "sg:province":"Bedfordshire",
    "sg:tags":[
        "civil",
        "engineer"
    ],
    "wof:name":"Jacob,Joseph,(Civil Engineering) Ltd",
    "wof:placetype":"venue"
},
  "geometry": {"coordinates":[-0.496953994,52.1418762207],"type":"Point"}
}