{
  "type": "Feature",
  "properties": {
    "iso:country":"GB",
    "sg:address":"University College Northampton, Park Campus, Boughton Green Rd",
    "sg:city":"Northampton",
    "sg:classifiers":[
        {
            "category":"Personal",
            "type":"Services"
        }
    ],
    "sg:postcode":"NN2 7AL",
    "sg:province":"Northamptonshire",
    "sg:tags":[
        "stress",
        "management"
    ],
    "wof:name":"Depression Care Training Centre Ltd",
    "wof:placetype":"venue"
},
  "geometry": {"coordinates":[-0.88254,52.272442],"type":"Point"}
}