{
  "type": "Feature",
  "properties": {
    "addr:full":"43 Briarwood Drive, Northwood Hills Northwood Greater London HA6 1PN",
    "addr:housenumber":"43",
    "addr:postcode":"ha6 1pn",
    "addr:street":"Briarwood Drive",
    "iso:country":"GB",
    "sg:address":"43 Briarwood Drive, Northwood Hills",
    "sg:city":"Northwood",
    "sg:classifiers":[
        {
            "category":"Professional",
            "subcategory":"Art Services",
            "type":"Services"
        }
    ],
    "sg:phone":"+44 20 8866 7679",
    "sg:postcode":"HA6 1PN",
    "sg:province":"Greater London",
    "sg:tags":[
        "photographer"
    ],
    "wof:name":"Phyllis Stern",
    "wof:placetype":"venue"
},
  "geometry": {"coordinates":[-0.4068419933,51.6007728577],"type":"Point"}
}