{
  "type": "Feature",
  "properties": {
    "addr:full":"105-127 Victoria Road, Netherfield Nottingham Nottinghamshire NG4 2PD",
    "addr:housenumber":"105-127",
    "addr:postcode":"ng4 2pd",
    "addr:street":"Victoria Road",
    "iso:country":"GB",
    "sg:address":"105-127 Victoria Road, Netherfield",
    "sg:city":"Nottingham",
    "sg:classifiers":[
        {
            "category":"Shopping",
            "subcategory":"Bicycles & Sporting Goods",
            "type":"Retail Goods"
        }
    ],
    "sg:phone":"+44 115 961 4555",
    "sg:postcode":"NG4 2PD",
    "sg:province":"Nottinghamshire",
    "sg:tags":[
        "cycle",
        "accessory"
    ],
    "wof:name":"Graham Read Cycle Warehouse",
    "wof:placetype":"venue"
},
  "geometry": {"coordinates":[-1.074978,52.963013],"type":"Point"}
}