{
  "type": "Feature",
  "properties": {
    "addr:full":"Little Dale, Wigston Harcourt Wigston Leicestershire LE18 3LF",
    "addr:postcode":"le18 3lf",
    "iso:country":"GB",
    "sg:address":"Little Dale, Wigston Harcourt",
    "sg:city":"Wigston",
    "sg:classifiers":[
        {
            "category":"Professional",
            "subcategory":"Engineering",
            "type":"Services"
        }
    ],
    "sg:postcode":"LE18 3LF",
    "sg:province":"Leicestershire",
    "sg:tags":[
        "contractor",
        "electrical",
        "engineer"
    ],
    "wof:name":"John Windley Electrical",
    "wof:placetype":"venue"
},
  "geometry": {"coordinates":[-1.097105,52.579109],"type":"Point"}
}