{
  "type": "Feature",
  "properties": {
    "addr:full":"2 Bunns Lane Works, Bunns La Mill Hill Greater London NW7 2AJ",
    "addr:housenumber":"2",
    "addr:postcode":"nw7 2aj",
    "addr:street":"Bunns Lane;Bunns La Mill Hill",
    "iso:country":"GB",
    "sg:address":"2 Bunns Lane Works, Bunns La",
    "sg:city":"Mill Hill",
    "sg:classifiers":[
        {
            "category":"Utilities",
            "type":"Services"
        }
    ],
    "sg:phone":"+44 20 8905 3549",
    "sg:postcode":"NW7 2AJ",
    "sg:province":"Greater London",
    "sg:tags":[
        "internet"
    ],
    "wof:name":"CCCP Internet Ltd",
    "wof:placetype":"venue"
},
  "geometry": {"coordinates":[-0.2340990007,51.6081466675],"type":"Point"}
}