{
  "type": "Feature",
  "properties": {
    "iso:country":"GB",
    "sg:address":"Kirrin",
    "sg:city":"Hockley",
    "sg:classifiers":[
        {
            "category":"Professional",
            "subcategory":"Management & Consulting",
            "type":"Services"
        }
    ],
    "sg:postcode":"SS5 4PT",
    "sg:province":"Essex",
    "sg:tags":[
        "consultant",
        "business"
    ],
    "wof:name":"P R S Consultancy Ltd.",
    "wof:placetype":"venue"
},
  "geometry": {"coordinates":[0.6557229757,51.6007041931],"type":"Point"}
}