{
  "type": "Feature",
  "properties": {
    "addr:full":"85 Wilton Rd Westminster Greater London SW1V 1DN",
    "addr:housenumber":"85",
    "addr:postcode":"sw1v 1dn",
    "addr:street":"Wilton Rd",
    "iso:country":"GB",
    "sg:address":"85 Wilton Rd",
    "sg:city":"Westminster",
    "sg:classifiers":[
        {
            "category":"Shopping",
            "subcategory":"Thrift Store",
            "type":"Retail Goods"
        }
    ],
    "sg:phone":"+44 20 7931 7191",
    "sg:postcode":"SW1V 1DN",
    "sg:province":"Greater London",
    "sg:tags":[
        "shop",
        "charity"
    ],
    "wof:name":"Trinity Hospice Shop",
    "wof:placetype":"venue"
},
  "geometry": {"coordinates":[-0.140086,51.492264],"type":"Point"}
}