{
  "type": "Feature",
  "properties": {
    "iso:country":"GB",
    "sg:address":"116a Park Rd",
    "sg:city":"Chorley",
    "sg:classifiers":[
        {
            "category":"Food & Beverages",
            "subcategory":"Bakery",
            "type":"Retail Goods"
        }
    ],
    "sg:phone":"+44 1257 267442",
    "sg:postcode":"PR7 1QY",
    "sg:province":"Lancashire",
    "sg:tags":[
        "baker"
    ],
    "wof:name":"Astley Training Bakery",
    "wof:placetype":"venue"
},
  "geometry": {"coordinates":[-2.6305150986,53.6595420837],"type":"Point"}
}