{
  "type": "Feature",
  "properties": {
    "addr:full":"60 Cross Arthurlie Street, Barrhead Glasgow East Ayrshire G78 1RP",
    "addr:housenumber":"60",
    "addr:postcode":"g78 1rp",
    "addr:street":"Cross Arthurlie Street",
    "iso:country":"GB",
    "sg:address":"60 Cross Arthurlie Street, Barrhead",
    "sg:city":"Glasgow",
    "sg:classifiers":[
        {
            "category":"Food & Beverages",
            "subcategory":"Liquor & Beverages",
            "type":"Retail Goods"
        }
    ],
    "sg:phone":"+44 141 881 0695",
    "sg:postcode":"G78 1RP",
    "sg:province":"East Ayrshire",
    "sg:tags":[
        "beer",
        "spirit",
        "wines"
    ],
    "wof:name":"G101 Off Sales",
    "wof:placetype":"venue"
},
  "geometry": {"coordinates":[-4.397281,55.800762],"type":"Point"}
}