{
  "type": "Feature",
  "properties": {
    "iso:country":"GB",
    "sg:address":"42 Station Road",
    "sg:city":"Kenilworth",
    "sg:classifiers":[
        {
            "category":"Health Services",
            "subcategory":"Doctor",
            "type":"Services"
        },
        {
            "category":"Health Services",
            "subcategory":"Clinic",
            "type":"Services"
        }
    ],
    "sg:postcode":"CV8 1JD",
    "sg:province":"Warwickshire",
    "sg:tags":[
        "nh",
        "practitioners"
    ],
    "wof:name":"Abbey Medical Centre",
    "wof:placetype":"venue"
},
  "geometry": {"coordinates":[-1.5786169767,52.3429260254],"type":"Point"}
}