{
  "type": "Feature",
  "properties": {
    "addr:full":"Newton Of Darnaway, Darnaway Forres Moray IV36 2SU",
    "addr:postcode":"iv36 2su",
    "addr:street":"Darnaway",
    "iso:country":"GB",
    "sg:address":"Newton Of Darnaway, Darnaway",
    "sg:city":"Forres",
    "sg:classifiers":[
        {
            "category":"Farming",
            "subcategory":"Farm",
            "type":"Manufacturing & Wholesale Goods"
        }
    ],
    "sg:phone":"+44 1309 641241",
    "sg:postcode":"IV36 2SU",
    "sg:province":"Moray",
    "sg:tags":[
        "mixed",
        "crop"
    ],
    "wof:name":"G F Macarthur & Co.",
    "wof:placetype":"venue"
},
  "geometry": {"coordinates":[-3.6930890083,57.5622367859],"type":"Point"}
}