{
  "type": "Feature",
  "properties": {
    "iso:country":"GB",
    "sg:address":"Stacey Road",
    "sg:city":"Falmouth",
    "sg:classifiers":[
        {
            "category":"Travel",
            "subcategory":"Hotels & Motels",
            "type":"Entertainment"
        }
    ],
    "sg:phone":"+44 1326 312707",
    "sg:postcode":"TR11 4NB",
    "sg:province":"Cornwall",
    "wof:name":"St Michaels Hotel",
    "wof:placetype":"venue"
},
  "geometry": {"coordinates":[-5.069922924,50.1462554932],"type":"Point"}
}