{
  "type": "Feature",
  "properties": {
    "addr:full":"High Street, Heacham King's Lynn Norfolk PE31 7EP",
    "addr:postcode":"pe31 7ep",
    "addr:street":"High Street;Lynn",
    "iso:country":"GB",
    "sg:address":"High Street, Heacham",
    "sg:city":"King's Lynn",
    "sg:classifiers":[
        {
            "category":"Shopping",
            "subcategory":"Florist",
            "type":"Retail Goods"
        }
    ],
    "sg:phone":"+44 1485 572212",
    "sg:postcode":"PE31 7EP",
    "sg:province":"Norfolk",
    "wof:name":"Fleuritique Flower Shop",
    "wof:placetype":"venue"
},
  "geometry": {"coordinates":[0.4950200021,52.9092788696],"type":"Point"}
}