{
  "type": "Feature",
  "properties": {
    "addr:full":"Contract Service Organisation, 38 Powis Terrace Aberdeen Aberdeen City AB25 3RF",
    "addr:housenumber":"38",
    "addr:postcode":"ab25 3rf",
    "addr:street":"Powis Terrace",
    "iso:country":"GB",
    "sg:address":"Contract Service Organisation, 38 Powis Terrace",
    "sg:city":"Aberdeen",
    "sg:classifiers":[
        {
            "category":"Government",
            "subcategory":"Office",
            "type":"Public Place"
        }
    ],
    "sg:phone":"+44 1224 480281",
    "sg:postcode":"AB25 3RF",
    "sg:province":"Aberdeen City",
    "sg:tags":[
        "local"
    ],
    "wof:name":"Aberdeen City Council",
    "wof:placetype":"venue"
},
  "geometry": {"coordinates":[-2.1067891121,57.1538200378],"type":"Point"}
}