{
  "type": "Feature",
  "properties": {
    "addr:full":"14 Wickham Av Bexhill On Sea East Sussex TN39 3EN",
    "addr:housenumber":"14",
    "addr:postcode":"tn39 3en",
    "addr:street":"Wickham Av",
    "iso:country":"GB",
    "sg:address":"14 Wickham Av",
    "sg:city":"Bexhill On Sea",
    "sg:classifiers":[
        {
            "category":"Professional",
            "subcategory":"Lawyer & Legal Services",
            "type":"Services"
        }
    ],
    "sg:phone":"+44 1424 221962",
    "sg:postcode":"TN39 3EN",
    "sg:province":"East Sussex",
    "sg:tags":[
        "advice",
        "counselling"
    ],
    "wof:name":"Richard Thomas",
    "wof:placetype":"venue"
},
  "geometry": {"coordinates":[0.468555,50.839939],"type":"Point"}
}