{
  "type": "Feature",
  "properties": {
    "iso:country":"GB",
    "sg:address":"2 Medway Close, Skelton In Cleveland",
    "sg:city":"Saltburn-by-the-sea",
    "sg:classifiers":[
        {
            "category":"Building & Trades",
            "subcategory":"Construction",
            "type":"Services"
        }
    ],
    "sg:postcode":"TS12 2JZ",
    "sg:province":"North Yorkshire",
    "sg:tags":[
        "dry",
        "lining",
        "plasterers",
        "screeders"
    ],
    "wof:name":"Armstrong Plasterers",
    "wof:placetype":"venue"
},
  "geometry": {"coordinates":[-0.9730340242,54.5663528442],"type":"Point"}
}