{
  "type": "Feature",
  "properties": {
    "iso:country":"GB",
    "sg:address":"170 Carlton Hill, Carlton",
    "sg:city":"Nottingham",
    "sg:classifiers":[
        {
            "category":"Manufacturing",
            "subcategory":"Lumber",
            "type":"Manufacturing & Wholesale Goods"
        },
        {
            "category":"Building & Trades",
            "subcategory":"Construction",
            "type":"Services"
        }
    ],
    "sg:phone":"+44 115 987 0015",
    "sg:postcode":"NG4 1FS",
    "sg:province":"Nottinghamshire",
    "sg:tags":[
        "merchants",
        "glazing",
        "double",
        "agent",
        "importer",
        "installers",
        "timber"
    ],
    "wof:name":"D & M A FEARN",
    "wof:placetype":"venue"
},
  "geometry": {"coordinates":[-1.0988179445,52.9664573669],"type":"Point"}
}