{
  "type": "Feature",
  "properties": {
    "addr:full":"39 Highfield Rd Dartford Kent DA1 2JS",
    "addr:housenumber":"39",
    "addr:postcode":"da1 2js",
    "addr:street":"Highfield Rd",
    "iso:country":"GB",
    "sg:address":"39 Highfield Rd",
    "sg:city":"Dartford",
    "sg:classifiers":[
        {
            "category":"Professional",
            "subcategory":"Employment Agencies",
            "type":"Services"
        }
    ],
    "sg:phone":"+44 1322 290029",
    "sg:postcode":"DA1 2JS",
    "sg:province":"Kent",
    "sg:tags":[
        "consultant"
    ],
    "wof:name":"Penthouse Personnel Engineering & Technical Division",
    "wof:placetype":"venue"
},
  "geometry": {"coordinates":[0.212034,51.442963],"type":"Point"}
}