{
  "type": "Feature",
  "properties": {
    "addr:full":"Fighting Cocks Farm, Salisbury Road, Ower Romsey Hampshire SO51 6AN",
    "addr:postcode":"so51 6an",
    "addr:street":"Salisbury Road",
    "iso:country":"GB",
    "sg:address":"Fighting Cocks Farm, Salisbury Road, Ower",
    "sg:city":"Romsey",
    "sg:classifiers":[
        {
            "category":"Farming",
            "subcategory":"Farm",
            "type":"Manufacturing & Wholesale Goods"
        }
    ],
    "sg:postcode":"SO51 6AN",
    "sg:province":"Hampshire",
    "sg:tags":[
        "mixed",
        "crop"
    ],
    "wof:name":"E Brown",
    "wof:placetype":"venue"
},
  "geometry": {"coordinates":[-1.5387040377,50.9466209412],"type":"Point"}
}