{
  "type": "Feature",
  "properties": {
    "addr:full":"115a The Grove, Stratford London Greater London E15 1EN",
    "addr:housenumber":"115a",
    "addr:postcode":"e15 1en",
    "addr:street":"The Grove",
    "iso:country":"GB",
    "sg:address":"115a The Grove, Stratford",
    "sg:city":"London",
    "sg:classifiers":[
        {
            "category":"Professional",
            "subcategory":"Management & Consulting",
            "type":"Services"
        }
    ],
    "sg:postcode":"E15 1EN",
    "sg:province":"Greater London",
    "sg:tags":[
        "consultant",
        "business"
    ],
    "wof:name":"Glemstone Consultants Ltd.",
    "wof:placetype":"venue"
},
  "geometry": {"coordinates":[0.0046950001,51.5444068909],"type":"Point"}
}