{
  "type": "Feature",
  "properties": {
    "addr:full":"4 Pill Street Penarth The Vale of Glamorgan CF64 2JR",
    "addr:housenumber":"4",
    "addr:postcode":"cf64 2jr",
    "addr:street":"Pill Street;Vale",
    "iso:country":"GB",
    "sg:address":"4 Pill Street",
    "sg:city":"Penarth",
    "sg:classifiers":[
        {
            "category":"Food & Beverages",
            "subcategory":"Meat & Fish",
            "type":"Retail Goods"
        },
        {
            "category":"Food & Beverages",
            "subcategory":"Groceries & Convenience Stores",
            "type":"Retail Goods"
        }
    ],
    "sg:phone":"+44 29 2070 5578",
    "sg:postcode":"CF64 2JR",
    "sg:province":"The Vale of Glamorgan",
    "sg:tags":[
        "shop",
        "chip"
    ],
    "wof:name":"Spring Garden",
    "wof:placetype":"venue"
},
  "geometry": {"coordinates":[-3.187287,51.443848],"type":"Point"}
}