{
  "type": "Feature",
  "properties": {
    "iso:country":"GB",
    "sg:address":"Body Farm, Nutburn Road, North Baddesley",
    "sg:city":"Southampton",
    "sg:classifiers":[
        {
            "category":"Real Estate",
            "subcategory":"Developer",
            "type":"Services"
        }
    ],
    "sg:phone":"+44 23 8073 4406",
    "sg:postcode":"SO52 9BG",
    "sg:province":"Hampshire",
    "sg:tags":[
        "property"
    ],
    "wof:name":"Peter Hall & Co. Ltd.",
    "wof:placetype":"venue"
},
  "geometry": {"coordinates":[-1.4382439852,50.9783592224],"type":"Point"}
}