{
  "type": "Feature",
  "properties": {
    "iso:country":"GB",
    "sg:address":"Unit G3, Chaucer Business Park, Watery Lane",
    "sg:city":"Sevenoaks",
    "sg:classifiers":[
        {
            "category":"Professional",
            "type":"Services"
        },
        {
            "category":"Retail",
            "subcategory":"Event Space",
            "type":"Services"
        }
    ],
    "sg:phone":"+44 1732 760123",
    "sg:postcode":"TN15 6PW",
    "sg:province":"Kent",
    "sg:tags":[
        "exhibition",
        "organiser"
    ],
    "wof:name":"Key Systems Ltd.",
    "wof:placetype":"venue"
},
  "geometry": {"coordinates":[0.24799,51.297489],"type":"Point"}
}