{
  "type": "Feature",
  "properties": {
    "iso:country":"GB",
    "sg:address":"94 Chapel St",
    "sg:city":"Leigh",
    "sg:classifiers":[
        {
            "category":"Retail",
            "subcategory":"Funeral Services",
            "type":"Services"
        }
    ],
    "sg:phone":"+44 1942 261936",
    "sg:postcode":"WN7 2DB",
    "sg:province":"Lancashire",
    "wof:name":"L Heyes",
    "wof:placetype":"venue"
},
  "geometry": {"coordinates":[-2.508594,53.494953],"type":"Point"}
}