{
  "type": "Feature",
  "properties": {
    "addr:full":"2 Hayes Villas, Frimley Rd Aldershot Hampshire GU12 5NS",
    "addr:housenumber":"2",
    "addr:postcode":"gu12 5ns",
    "addr:street":"Hayes Villas Frimley Rd",
    "iso:country":"GB",
    "sg:address":"2 Hayes Villas, Frimley Rd",
    "sg:city":"Aldershot",
    "sg:classifiers":[
        {
            "category":"Professional",
            "subcategory":"Printing & Photocopies",
            "type":"Services"
        }
    ],
    "sg:phone":"+44 1483 797929",
    "sg:postcode":"GU12 5NS",
    "sg:province":"Hampshire",
    "sg:tags":[
        "printer"
    ],
    "wof:name":"Manor Print",
    "wof:placetype":"venue"
},
  "geometry": {"coordinates":[-0.7593399882,51.2495994568],"type":"Point"}
}