{
  "type": "Feature",
  "properties": {
    "addr:full":"39 Main Street, Escrick York North Yorkshire YO19 6LQ",
    "addr:housenumber":"39",
    "addr:postcode":"yo19 6lq",
    "addr:street":"Main Street",
    "iso:country":"GB",
    "sg:address":"39 Main Street, Escrick",
    "sg:city":"York",
    "sg:classifiers":[
        {
            "category":"Building & Trades",
            "subcategory":"Cleaning & Sanitation",
            "type":"Services"
        }
    ],
    "sg:postcode":"YO19 6LQ",
    "sg:province":"North Yorkshire",
    "sg:tags":[
        "commercial"
    ],
    "wof:name":"Pro-Clene",
    "wof:placetype":"venue"
},
  "geometry": {"coordinates":[-1.0587029457,53.8327407837],"type":"Point"}
}