{
  "type": "Feature",
  "properties": {
    "iso:country":"GB",
    "sg:address":"19h Airport Indust Estate",
    "sg:city":"Newcastle Upon Tyne",
    "sg:classifiers":[
        {
            "category":"Fast Food",
            "type":"Food & Drink"
        }
    ],
    "sg:phone":"+44 191 214 0505",
    "sg:postcode":"NE3 2EF",
    "sg:province":"Tyne and Wear",
    "sg:tags":[
        "delivery"
    ],
    "wof:name":"Curry Express Home Delivery Service",
    "wof:placetype":"venue"
},
  "geometry": {"coordinates":[-1.66313,55.01157],"type":"Point"}
}