{
  "type": "Feature",
  "properties": {
    "iso:country":"GB",
    "sg:address":"Old Flaig Glassworks",
    "sg:city":"Broadstairs",
    "sg:classifiers":[
        {
            "category":"Manufacturing",
            "subcategory":"Petroleum Products",
            "type":"Manufacturing & Wholesale Goods"
        }
    ],
    "sg:phone":"+44 1843 868804",
    "sg:postcode":"CT10 2PR",
    "sg:province":"Kent",
    "sg:tags":[
        "double",
        "glazing"
    ],
    "wof:name":"Stroud Windows & Doors",
    "wof:placetype":"venue"
},
  "geometry": {"coordinates":[1.44106,51.358604],"type":"Point"}
}