{
  "type": "Feature",
  "properties": {
    "addr:full":"12 Ash Hill Rd, Hatfield Doncaster South Yorkshire DN7 6JG",
    "addr:housenumber":"12",
    "addr:postcode":"dn7 6jg",
    "addr:street":"Ash Hill Rd",
    "iso:country":"GB",
    "sg:address":"12 Ash Hill Rd, Hatfield",
    "sg:city":"Doncaster",
    "sg:classifiers":[
        {
            "category":"Utilities",
            "subcategory":"Fuel Oil & Lpg",
            "type":"Services"
        }
    ],
    "sg:phone":"+44 1302 840131",
    "sg:postcode":"DN7 6JG",
    "sg:province":"South Yorkshire",
    "wof:name":"K.E Mears",
    "wof:placetype":"venue"
},
  "geometry": {"coordinates":[-1.0083459616,53.5755958557],"type":"Point"}
}