{
  "type": "Feature",
  "properties": {
    "iso:country":"GB",
    "sg:address":"83 Chatsworth Road",
    "sg:city":"Chesterfield",
    "sg:classifiers":[
        {
            "category":"Shopping",
            "subcategory":"Musical Instruments",
            "type":"Retail Goods"
        }
    ],
    "sg:phone":"+44 1246 204889",
    "sg:postcode":"S40 2AP",
    "sg:province":"Derbyshire",
    "sg:tags":[
        "music",
        "sheet"
    ],
    "wof:name":"Frets 'N' Keys",
    "wof:placetype":"venue"
},
  "geometry": {"coordinates":[-1.441543,53.235168],"type":"Point"}
}