{
  "type": "Feature",
  "properties": {
    "addr:full":"54 Clatterfield Gardens Westcliff On Sea Essex SS0 0AX",
    "addr:housenumber":"54",
    "addr:postcode":"ss0 0ax",
    "addr:street":"Clatterfield Gardens",
    "iso:country":"GB",
    "sg:address":"54 Clatterfield Gardens",
    "sg:city":"Westcliff On Sea",
    "sg:classifiers":[
        {
            "category":"Professional",
            "subcategory":"Art Services",
            "type":"Services"
        }
    ],
    "sg:phone":"+44 1702 349712",
    "sg:postcode":"SS0 0AX",
    "sg:province":"Essex",
    "sg:tags":[
        "graphic",
        "designer"
    ],
    "wof:name":"Apple Mac Services",
    "wof:placetype":"venue"
},
  "geometry": {"coordinates":[0.674207,51.551285],"type":"Point"}
}