{
  "type": "Feature",
  "properties": {
    "iso:country":"GB",
    "sg:address":"Waterloo",
    "sg:city":"Pembroke Dock",
    "sg:classifiers":[
        {
            "category":"Manufacturing",
            "subcategory":"Metals",
            "type":"Manufacturing & Wholesale Goods"
        },
        {
            "category":"Wholesale",
            "subcategory":"Scrap",
            "type":"Manufacturing & Wholesale Goods"
        }
    ],
    "sg:phone":"+44 1646 622822",
    "sg:postcode":"SA72 4RR",
    "sg:province":"Pembrokeshire",
    "sg:tags":[
        "waste"
    ],
    "wof:name":"Waterloo Metals",
    "wof:placetype":"venue"
},
  "geometry": {"coordinates":[-4.931927,51.704174],"type":"Point"}
}