{
  "type": "Feature",
  "properties": {
    "iso:country":"GB",
    "sg:address":"13 Queens Avenue",
    "sg:city":"Hastings",
    "sg:classifiers":[
        {
            "category":"Farming",
            "subcategory":"Fish & Marine Products",
            "type":"Manufacturing & Wholesale Goods"
        }
    ],
    "sg:phone":"+44 1424 435459",
    "sg:postcode":"TN34 1PA",
    "sg:province":"East Sussex",
    "sg:tags":[
        "fishmonger"
    ],
    "wof:name":"Arcade Fisheries",
    "wof:placetype":"venue"
},
  "geometry": {"coordinates":[0.58144,50.856392],"type":"Point"}
}