{
  "type": "Feature",
  "properties": {
    "addr:full":"9 Bath Rd Wells Somerset BA5 3HP",
    "addr:housenumber":"9",
    "addr:postcode":"ba5 3hp",
    "addr:street":"Bath Rd",
    "iso:country":"GB",
    "sg:address":"9 Bath Rd",
    "sg:city":"Wells",
    "sg:classifiers":[
        {
            "category":"Community Center",
            "subcategory":"Social",
            "type":"Public Place"
        }
    ],
    "sg:phone":"+44 1749 675534",
    "sg:postcode":"BA5 3HP",
    "sg:province":"Somerset",
    "sg:tags":[
        "furnishers",
        "contract"
    ],
    "wof:name":"Prospect Contract Furnishings",
    "wof:placetype":"venue"
},
  "geometry": {"coordinates":[-2.635436058,51.2136802673],"type":"Point"}
}