{
  "type": "Feature",
  "properties": {
    "iso:country":"GB",
    "sg:address":"Court Farm, Mudgley",
    "sg:city":"Wedmore",
    "sg:classifiers":[
        {
            "category":"Farming",
            "subcategory":"Livestock Farm",
            "type":"Manufacturing & Wholesale Goods"
        }
    ],
    "sg:phone":"+44 1934 712367",
    "sg:postcode":"BS28 4TY",
    "sg:province":"Somerset",
    "sg:tags":[
        "others"
    ],
    "wof:name":"K H Tucker",
    "wof:placetype":"venue"
},
  "geometry": {"coordinates":[-2.815929,51.225739],"type":"Point"}
}