{
  "type": "Feature",
  "properties": {
    "addr:full":"44 Glaisnock St Cumnock East Ayrshire KA18 1BU",
    "addr:housenumber":"44",
    "addr:postcode":"ka18 1bu",
    "addr:street":"Glaisnock St",
    "iso:country":"GB",
    "sg:address":"44 Glaisnock St",
    "sg:city":"Cumnock",
    "sg:classifiers":[
        {
            "category":"Retail",
            "subcategory":"Funeral Services",
            "type":"Services"
        }
    ],
    "sg:phone":"+44 1290 423628",
    "sg:postcode":"KA18 1BU",
    "sg:province":"East Ayrshire",
    "wof:name":"Co-operative Funeral Services",
    "wof:placetype":"venue"
},
  "geometry": {"coordinates":[-4.26420784,55.4530982971],"type":"Point"}
}