{
  "type": "Feature",
  "properties": {
    "addr:full":"Pound Lane Exmouth Devon EX8 4NP",
    "addr:postcode":"ex8 4np",
    "addr:street":"Pound Lane",
    "iso:country":"GB",
    "sg:address":"Pound Lane",
    "sg:city":"Exmouth",
    "sg:classifiers":[
        {
            "category":"Building & Trades",
            "subcategory":"Equipment Rental",
            "type":"Services"
        }
    ],
    "sg:phone":"+44 1395 225000",
    "sg:postcode":"EX8 4NP",
    "sg:province":"Devon",
    "sg:tags":[
        "hire",
        "centre"
    ],
    "wof:name":"Torex Hire Point",
    "wof:placetype":"venue"
},
  "geometry": {"coordinates":[-3.4008901119,50.6330223083],"type":"Point"}
}