{
  "type": "Feature",
  "properties": {
    "addr:full":"Albright Industrial Estate, Ferry Lane Rainham Essex RM13 9BU",
    "addr:postcode":"rm13 9bu",
    "addr:street":"Industrial Estate Ferry Lane",
    "iso:country":"GB",
    "sg:address":"Albright Industrial Estate, Ferry Lane",
    "sg:city":"Rainham",
    "sg:classifiers":[
        {
            "category":"Autos & Motor Vehicles",
            "subcategory":"Auto Supplies",
            "type":"Retail Goods"
        }
    ],
    "sg:phone":"+44 1708 525252",
    "sg:postcode":"RM13 9BU",
    "sg:province":"Essex",
    "sg:tags":[
        "taxi",
        "equipment"
    ],
    "wof:name":"Rainham Radio Taxis Ltd.",
    "wof:placetype":"venue"
},
  "geometry": {"coordinates":[0.190426,51.517914],"type":"Point"}
}