{
  "type": "Feature",
  "properties": {
    "iso:country":"GB",
    "sg:address":"615 Wilmslow Road, Didsbury",
    "sg:city":"Manchester",
    "sg:classifiers":[
        {
            "category":"Professional",
            "subcategory":"Business Services",
            "type":"Services"
        }
    ],
    "sg:postcode":"M20 6DF",
    "sg:province":"Greater Manchester",
    "sg:tags":[
        "import",
        "export",
        "agent"
    ],
    "wof:name":"Belmar Ltd.",
    "wof:placetype":"venue"
},
  "geometry": {"coordinates":[-2.232308,53.422409],"type":"Point"}
}