{
  "type": "Feature",
  "properties": {
    "addr:full":"15 Lower Hall La Walsall West Midlands WS1 1RL",
    "addr:housenumber":"15",
    "addr:postcode":"ws1 1rl",
    "addr:street":"Lower Hall La Walsall",
    "iso:country":"GB",
    "sg:address":"15 Lower Hall La",
    "sg:city":"Walsall",
    "sg:classifiers":[
        {
            "category":"Professional",
            "subcategory":"Lawyer & Legal Services",
            "type":"Services"
        }
    ],
    "sg:phone":"+44 1922 611966",
    "sg:postcode":"WS1 1RL",
    "sg:province":"West Midlands",
    "sg:tags":[
        "advice",
        "counselling"
    ],
    "wof:name":"Walsall Family Mediation Service",
    "wof:placetype":"venue"
},
  "geometry": {"coordinates":[-1.981881,52.582577],"type":"Point"}
}