{
  "type": "Feature",
  "properties": {
    "addr:full":"Shutterton Industrial Estate Dawlish Devon EX7 0NH",
    "addr:housenumber":"estate dawlish",
    "addr:postcode":"ex7 0nh",
    "iso:country":"GB",
    "sg:address":"Shutterton Industrial Estate",
    "sg:city":"Dawlish",
    "sg:classifiers":[
        {
            "category":"Manufacturing",
            "subcategory":"Tools & Machinery",
            "type":"Manufacturing & Wholesale Goods"
        },
        {
            "category":"Wholesale",
            "subcategory":"Machinery & Supplies",
            "type":"Manufacturing & Wholesale Goods"
        }
    ],
    "sg:phone":"+44 1626 863634",
    "sg:postcode":"EX7 0NH",
    "sg:province":"Devon",
    "sg:tags":[
        "equipment",
        "hydraulic",
        "manufacturer"
    ],
    "sg:website":"http://www.hypro.co.uk",
    "wof:name":"Hydraulic Project Ltd",
    "wof:placetype":"venue"
},
  "geometry": {"coordinates":[-3.458509,50.597301],"type":"Point"}
}