{
  "type": "Feature",
  "properties": {
    "addr:full":"Alexandra Parade Dunoon Argyll and Bute PA23 8AE",
    "addr:postcode":"pa23 8ae",
    "addr:street":"Alexandra Parade",
    "iso:country":"GB",
    "sg:address":"Alexandra Parade",
    "sg:city":"Dunoon",
    "sg:classifiers":[
        {
            "category":"Autos & Motor Vehicles",
            "subcategory":"Fuel & Gas Station",
            "type":"Retail Goods"
        },
        {
            "category":"Retail",
            "subcategory":"Auto Rental",
            "type":"Services"
        }
    ],
    "sg:phone":"+44 1369 703199",
    "sg:postcode":"PA23 8AE",
    "sg:province":"Argyll and Bute",
    "sg:tags":[
        "petrol",
        "car"
    ],
    "wof:name":"COUNTY GARAGE",
    "wof:placetype":"venue"
},
  "geometry": {"coordinates":[-4.9159069061,55.9558563232],"type":"Point"}
}