{
  "type": "Feature",
  "properties": {
    "addr:full":"High Street, Stonesfield Witney Oxfordshire OX29 8PU",
    "addr:postcode":"ox29 8pu",
    "addr:street":"High Street",
    "iso:country":"GB",
    "sg:address":"High Street, Stonesfield",
    "sg:city":"Witney",
    "sg:classifiers":[
        {
            "category":"Education",
            "subcategory":"School",
            "type":"Public Place"
        }
    ],
    "sg:phone":"+44 1993 891687",
    "sg:postcode":"OX29 8PU",
    "sg:province":"Oxfordshire",
    "sg:tags":[
        "local",
        "authority"
    ],
    "wof:name":"Stonesfield County Primary School",
    "wof:placetype":"venue"
},
  "geometry": {"coordinates":[-1.430052,51.855747],"type":"Point"}
}