{
  "type": "Feature",
  "properties": {
    "iso:country":"GB",
    "sg:address":"Hall Farm Cottage, Church Lane, Roydon",
    "sg:city":"King's Lynn",
    "sg:classifiers":[
        {
            "category":"Retail",
            "subcategory":"Veterinary Services",
            "type":"Services"
        },
        {
            "category":"Organizations",
            "subcategory":"Non-profit Organization",
            "type":"Services"
        }
    ],
    "sg:phone":"+44 1485 600022",
    "sg:postcode":"PE32 1AR",
    "sg:province":"Norfolk",
    "sg:tags":[
        "organisation",
        "welfare",
        "animal",
        "activity"
    ],
    "wof:name":"Sunnyside Veterinary Clinic",
    "wof:placetype":"venue"
},
  "geometry": {"coordinates":[0.5162299871,52.7836303711],"type":"Point"}
}