{
  "type": "Feature",
  "properties": {
    "iso:country":"GB",
    "sg:address":"St G, Sunderland City Innvtn Cntr, Sunderland Entpse Park",
    "sg:city":"Sunderland",
    "sg:classifiers":[
        {
            "category":"Education",
            "subcategory":"Special Training",
            "type":"Public Place"
        }
    ],
    "sg:phone":"+44 191 516 6464",
    "sg:postcode":"SR5 2TA",
    "sg:province":"Tyne and Wear",
    "sg:tags":[
        "product",
        "centre"
    ],
    "wof:name":"Assessment North East Ltd.",
    "wof:placetype":"venue"
},
  "geometry": {"coordinates":[-1.41556,54.918678],"type":"Point"}
}