{
  "type": "Feature",
  "properties": {
    "addr:full":"74 Ashburner Street Bolton Lancashire BL1 1TN",
    "addr:housenumber":"74",
    "addr:postcode":"bl1 1tn",
    "addr:street":"Ashburner Street",
    "iso:country":"GB",
    "sg:address":"74 Ashburner Street",
    "sg:city":"Bolton",
    "sg:classifiers":[
        {
            "category":"Government",
            "subcategory":"Office",
            "type":"Public Place"
        },
        {
            "category":"Organizations",
            "subcategory":"Membership Organization",
            "type":"Services"
        }
    ],
    "sg:postcode":"BL1 1TN",
    "sg:province":"Lancashire",
    "sg:tags":[
        "local",
        "organisation",
        "consumer"
    ],
    "wof:name":"Bolton Metropolitan Borough Council",
    "wof:placetype":"venue"
},
  "geometry": {"coordinates":[-2.4329669476,53.5768585205],"type":"Point"}
}