{
  "type": "Feature",
  "properties": {
    "addr:full":"Skylines Village, Limeharbour London Greater London E14 9TS",
    "addr:postcode":"e14 9ts",
    "addr:street":"Skylines Village Limeharbour",
    "iso:country":"GB",
    "sg:address":"Skylines Village, Limeharbour",
    "sg:city":"London",
    "sg:classifiers":[
        {
            "category":"Professional",
            "subcategory":"Computer Services",
            "type":"Services"
        }
    ],
    "sg:phone":"+44 20 7538 2405",
    "sg:postcode":"E14 9TS",
    "sg:province":"Greater London",
    "sg:tags":[
        "system",
        "software"
    ],
    "wof:name":"Integral Technologies (1994) Ltd.",
    "wof:placetype":"venue"
},
  "geometry": {"coordinates":[-0.012929,51.4993209839],"type":"Point"}
}