{
  "type": "Feature",
  "properties": {
    "iso:country":"GB",
    "sg:address":"The Rectory, 1 The Park",
    "sg:city":"Bristol",
    "sg:classifiers":[
        {
            "category":"Place Of Worship",
            "type":"Public Place"
        }
    ],
    "sg:phone":"+44 117 986 3354",
    "sg:postcode":"BS31 2BL",
    "sg:province":"City of Bristol",
    "wof:name":"Keynsham Parish Church",
    "wof:placetype":"venue"
},
  "geometry": {"coordinates":[-2.4973700047,51.4167785645],"type":"Point"}
}