{
  "type": "Feature",
  "properties": {
    "iso:country":"GB",
    "sg:address":"17 Spitfire Close, Lordswood",
    "sg:city":"Chatham",
    "sg:classifiers":[
        {
            "category":"Social Services",
            "subcategory":"Adult Care",
            "type":"Services"
        }
    ],
    "sg:phone":"+44 1634 312861",
    "sg:postcode":"ME5 7QW",
    "sg:province":"Kent",
    "sg:tags":[
        "domestic",
        "cleaning"
    ],
    "wof:name":"Dustbusters",
    "wof:placetype":"venue"
},
  "geometry": {"coordinates":[0.538293,51.354935],"type":"Point"}
}