{
  "type": "Feature",
  "properties": {
    "addr:full":"85 Byng Rd Barnet Hertfordshire EN5 4NP",
    "addr:housenumber":"85",
    "addr:postcode":"en5 4np",
    "addr:street":"Byng Rd",
    "iso:country":"GB",
    "sg:address":"85 Byng Rd",
    "sg:city":"Barnet",
    "sg:classifiers":[
        {
            "category":"Social Services",
            "type":"Services"
        }
    ],
    "sg:postcode":"EN5 4NP",
    "sg:province":"Hertfordshire",
    "sg:tags":[
        "disability"
    ],
    "wof:name":"Barnet Mobility Care",
    "wof:placetype":"venue"
},
  "geometry": {"coordinates":[-0.213963,51.657616],"type":"Point"}
}