{
  "type": "Feature",
  "properties": {
    "addr:full":"Westhill Heights Westhill Aberdeen City AB32 6RY",
    "addr:postcode":"ab32 6ry",
    "addr:street":"Westhill",
    "iso:country":"GB",
    "sg:address":"Westhill Heights",
    "sg:city":"Westhill",
    "sg:classifiers":[
        {
            "category":"Sports & Exercise",
            "subcategory":"Golf",
            "type":"Entertainment"
        }
    ],
    "sg:phone":"+44 1224 742567",
    "sg:postcode":"AB32 6RY",
    "sg:province":"Aberdeen City",
    "sg:tags":[
        "club",
        "course"
    ],
    "wof:name":"Westhill Golf Club",
    "wof:placetype":"venue"
},
  "geometry": {"coordinates":[-2.2866959572,57.1614723206],"type":"Point"}
}