{
  "type": "Feature",
  "properties": {
    "iso:country":"GB",
    "sg:address":"Unit 13, Hurst End Farm, North Crawley",
    "sg:city":"Newport Pagnell",
    "sg:classifiers":[
        {
            "category":"Building & Trades",
            "subcategory":"Plumbing",
            "type":"Services"
        }
    ],
    "sg:phone":"+44 1234 391919",
    "sg:postcode":"MK16 9HS",
    "sg:province":"Buckinghamshire",
    "sg:tags":[
        "drain",
        "clearance",
        "sewer"
    ],
    "wof:name":"Aquajet",
    "wof:placetype":"venue"
},
  "geometry": {"coordinates":[-0.6486250162,52.0931358337],"type":"Point"}
}