{
  "type": "Feature",
  "properties": {
    "iso:country":"GB",
    "sg:address":"Willow House, Lawhitton",
    "sg:city":"Launceston",
    "sg:classifiers":[
        {
            "category":"Professional",
            "subcategory":"Engineering",
            "type":"Services"
        }
    ],
    "sg:phone":"+44 1566 772005",
    "sg:postcode":"PL15 9NQ",
    "sg:province":"Cornwall",
    "sg:tags":[
        "contractor",
        "electrical",
        "engineer"
    ],
    "wof:name":"Keith Hopper",
    "wof:placetype":"venue"
},
  "geometry": {"coordinates":[-4.3269639015,50.6166267395],"type":"Point"}
}