{
  "type": "Feature",
  "properties": {
    "iso:country":"GB",
    "sg:address":"3 William Street",
    "sg:city":"Cardigan",
    "sg:classifiers":[
        {
            "category":"Health Services",
            "subcategory":"Dentist",
            "type":"Services"
        }
    ],
    "sg:phone":"+44 1239 614416",
    "sg:postcode":"SA43 1EL",
    "sg:province":"Ceredigion",
    "wof:name":"The Dental Surgery",
    "wof:placetype":"venue"
},
  "geometry": {"coordinates":[-4.660209,52.084358],"type":"Point"}
}