{
  "type": "Feature",
  "properties": {
    "addr:full":"5 Cowlgrove Parade, Steppingley Road, Flitwick Bedford Bedfordshire MK45 1AJ",
    "addr:housenumber":"5",
    "addr:postcode":"mk45 1aj",
    "addr:street":"Cowlgrove Parade Steppingley Road",
    "iso:country":"GB",
    "sg:address":"5 Cowlgrove Parade, Steppingley Road, Flitwick",
    "sg:city":"Bedford",
    "sg:classifiers":[
        {
            "category":"Personal",
            "subcategory":"Beauty Salon",
            "type":"Services"
        }
    ],
    "sg:phone":"+44 1525 716612",
    "sg:postcode":"MK45 1AJ",
    "sg:province":"Bedfordshire",
    "sg:tags":[
        "unisex",
        "hairdresser"
    ],
    "wof:name":"Josephs",
    "wof:placetype":"venue"
},
  "geometry": {"coordinates":[-0.49649,52.005814],"type":"Point"}
}