{
  "type": "Feature",
  "properties": {
    "addr:full":"C/o J T Sports & Leisure, The Square, Wickham Fareham Hampshire PO17 5JT",
    "addr:postcode":"po17 5jt",
    "addr:street":"C;The Square",
    "iso:country":"GB",
    "sg:address":"C/o J T Sports & Leisure, The Square, Wickham",
    "sg:city":"Fareham",
    "sg:classifiers":[
        {
            "category":"Professional",
            "subcategory":"Computer Services",
            "type":"Services"
        }
    ],
    "sg:postcode":"PO17 5JT",
    "sg:province":"Hampshire",
    "sg:tags":[
        "consultant"
    ],
    "wof:name":"Joltswift Ltd",
    "wof:placetype":"venue"
},
  "geometry": {"coordinates":[-1.187,50.900269],"type":"Point"}
}