{
  "type": "Feature",
  "properties": {
    "iso:country":"GB",
    "sg:address":"17 High Road, Ickenham",
    "sg:city":"Uxbridge",
    "sg:classifiers":[
        {
            "category":"Home & Garden",
            "subcategory":"Garden Supply",
            "type":"Retail Goods"
        }
    ],
    "sg:postcode":"UB10 8LE",
    "sg:province":"Greater London",
    "sg:tags":[
        "nursery",
        "centre"
    ],
    "wof:name":"Ickenham Garden Centre",
    "wof:placetype":"venue"
},
  "geometry": {"coordinates":[-0.465983,51.562641],"type":"Point"}
}