{
  "type": "Feature",
  "properties": {
    "addr:full":"Causeway Wood Farm, Causeway Wood, Acton Burnell Shrewsbury Shropshire SY5 7HT",
    "addr:postcode":"sy5 7ht",
    "addr:street":"Causeway;Causeway Wood",
    "iso:country":"GB",
    "sg:address":"Causeway Wood Farm, Causeway Wood, Acton Burnell",
    "sg:city":"Shrewsbury",
    "sg:classifiers":[
        {
            "category":"Farming",
            "subcategory":"Livestock Farm",
            "type":"Manufacturing & Wholesale Goods"
        }
    ],
    "sg:postcode":"SY5 7HT",
    "sg:province":"Shropshire",
    "sg:tags":[
        "others"
    ],
    "wof:name":"K V Harrison",
    "wof:placetype":"venue"
},
  "geometry": {"coordinates":[-2.6942820549,52.6141471863],"type":"Point"}
}