{
  "type": "Feature",
  "properties": {
    "addr:full":"6 Wells Road Ilkley North Yorkshire LS29 9JD",
    "addr:housenumber":"6",
    "addr:postcode":"ls29 9jd",
    "addr:street":"Wells Road",
    "iso:country":"GB",
    "sg:address":"6 Wells Road",
    "sg:city":"Ilkley",
    "sg:classifiers":[
        {
            "category":"Shopping",
            "subcategory":"Thrift Store",
            "type":"Retail Goods"
        },
        {
            "category":"Organizations",
            "subcategory":"Non-profit Organization",
            "type":"Services"
        }
    ],
    "sg:phone":"+44 1943 865161",
    "sg:postcode":"LS29 9JD",
    "sg:province":"North Yorkshire",
    "sg:tags":[
        "shop",
        "charitable",
        "organisation",
        "charity"
    ],
    "wof:name":"Ilkley Good Neighbours Charity Shop",
    "wof:placetype":"venue"
},
  "geometry": {"coordinates":[-1.822971,53.924145],"type":"Point"}
}