{
  "type": "Feature",
  "properties": {
    "addr:full":"Manor Farm, Chartway Street Maidstone Kent ME17 3DP",
    "addr:postcode":"me17 3dp",
    "addr:street":"Manor;Chartway Street",
    "iso:country":"GB",
    "sg:address":"Manor Farm, Chartway Street",
    "sg:city":"Maidstone",
    "sg:classifiers":[
        {
            "category":"Professional",
            "subcategory":"Printing & Photocopies",
            "type":"Services"
        }
    ],
    "sg:postcode":"ME17 3DP",
    "sg:province":"Kent",
    "sg:tags":[
        "printer"
    ],
    "wof:name":"Manor Print",
    "wof:placetype":"venue"
},
  "geometry": {"coordinates":[0.62809,51.222328],"type":"Point"}
}