{
  "type": "Feature",
  "properties": {
    "addr:full":"13 Roscow Avenue Bolton Lancashire BL2 6HU",
    "addr:housenumber":"13",
    "addr:postcode":"bl2 6hu",
    "addr:street":"Roscow Avenue",
    "iso:country":"GB",
    "sg:address":"13 Roscow Avenue",
    "sg:city":"Bolton",
    "sg:classifiers":[
        {
            "category":"Shopping",
            "subcategory":"Photographic Equipment",
            "type":"Retail Goods"
        }
    ],
    "sg:phone":"+44 1204 403873",
    "sg:postcode":"BL2 6HU",
    "sg:province":"Lancashire",
    "wof:name":"Studio 67",
    "wof:placetype":"venue"
},
  "geometry": {"coordinates":[-2.392079,53.582108],"type":"Point"}
}