{
  "type": "Feature",
  "properties": {
    "addr:full":"35 Oxford Street Wellingborough Northamptonshire NN8 4JF",
    "addr:housenumber":"35",
    "addr:postcode":"nn8 4jf",
    "addr:street":"Oxford Street",
    "iso:country":"GB",
    "sg:address":"35 Oxford Street",
    "sg:city":"Wellingborough",
    "sg:classifiers":[
        {
            "category":"Autos & Motor Vehicles",
            "subcategory":"Auto Supplies",
            "type":"Retail Goods"
        }
    ],
    "sg:phone":"+44 1933 223271",
    "sg:postcode":"NN8 4JF",
    "sg:province":"Northamptonshire",
    "sg:tags":[
        "tyre"
    ],
    "wof:name":"National Tyres and Autocare",
    "wof:placetype":"venue"
},
  "geometry": {"coordinates":[-0.695274,52.301422],"type":"Point"}
}