{
  "type": "Feature",
  "properties": {
    "iso:country":"GB",
    "sg:address":"16 New Street",
    "sg:city":"Shipston-on-stour",
    "sg:classifiers":[
        {
            "category":"Bars & Pubs",
            "type":"Food & Drink"
        }
    ],
    "sg:phone":"+44 1608 661335",
    "sg:postcode":"CV36 4EN",
    "sg:province":"Warwickshire",
    "sg:tags":[
        "pubs",
        "house",
        "inn",
        "public",
        "activity"
    ],
    "wof:name":"Coach & Horses",
    "wof:placetype":"venue"
},
  "geometry": {"coordinates":[-1.6244469881,52.0617752075],"type":"Point"}
}