{
  "type": "Feature",
  "properties": {
    "addr:full":"The Old Rectory, The Ave, Bletsoe Bedford Bedfordshire MK44 1QD",
    "addr:postcode":"mk44 1qd",
    "addr:street":"The Ave",
    "iso:country":"GB",
    "sg:address":"The Old Rectory, The Ave, Bletsoe",
    "sg:city":"Bedford",
    "sg:classifiers":[
        {
            "category":"Social Services",
            "subcategory":"Retirement Home",
            "type":"Services"
        }
    ],
    "sg:postcode":"MK44 1QD",
    "sg:province":"Bedfordshire",
    "sg:tags":[
        "residential",
        "care"
    ],
    "wof:name":"Kingfisher Residential Care Home",
    "wof:placetype":"venue"
},
  "geometry": {"coordinates":[-0.509936,52.211136],"type":"Point"}
}