{
  "type": "Feature",
  "properties": {
    "addr:full":"86 Axe Street Barking Essex IG11 7LX",
    "addr:housenumber":"86",
    "addr:postcode":"ig11 7lx",
    "addr:street":"Axe Street",
    "iso:country":"GB",
    "sg:address":"86 Axe Street",
    "sg:city":"Barking",
    "sg:classifiers":[
        {
            "category":"Bars & Pubs",
            "type":"Food & Drink"
        }
    ],
    "sg:phone":"+44 20 8594 2143",
    "sg:postcode":"IG11 7LX",
    "sg:province":"Essex",
    "sg:tags":[
        "pubs",
        "inn"
    ],
    "wof:name":"The Victoria",
    "wof:placetype":"venue"
},
  "geometry": {"coordinates":[0.079971,51.535751],"type":"Point"}
}