{
  "type": "Feature",
  "properties": {
    "iso:country":"GB",
    "sg:address":"50 Beaufort Road",
    "sg:city":"London",
    "sg:classifiers":[
        {
            "category":"Distillery",
            "subcategory":"None",
            "type":"Food & Drink"
        }
    ],
    "sg:phone":"+44 20 8810 7411",
    "sg:postcode":"W5 3EA",
    "sg:province":"Greater London",
    "wof:name":"Montrose Whisky Co. Ltd.",
    "wof:placetype":"venue"
},
  "geometry": {"coordinates":[-0.287301,51.522205],"type":"Point"}
}