{
  "type": "Feature",
  "properties": {
    "addr:full":"4-10 Temple Street, Beverley Road Hull East Riding of Yorkshire HU5 1AP",
    "addr:housenumber":"4-10",
    "addr:postcode":"hu5 1ap",
    "addr:street":"Temple Street Beverley Road",
    "iso:country":"GB",
    "sg:address":"4-10 Temple Street, Beverley Road",
    "sg:city":"Hull",
    "sg:classifiers":[
        {
            "category":"Building & Trades",
            "subcategory":"Construction",
            "type":"Services"
        }
    ],
    "sg:phone":"+44 1482 471825",
    "sg:postcode":"HU5 1AP",
    "sg:province":"East Riding of Yorkshire",
    "sg:tags":[
        "roofing"
    ],
    "wof:name":"R Milner",
    "wof:placetype":"venue"
},
  "geometry": {"coordinates":[-0.347592,53.757553],"type":"Point"}
}