{
  "type": "Feature",
  "properties": {
    "addr:full":"Po Box 14 Barrow-in-furness Cumbria LA14 1AG",
    "addr:housenumber":"po box 14",
    "addr:postcode":"la14 1ag",
    "iso:country":"GB",
    "sg:address":"Po Box 14",
    "sg:city":"Barrow-in-furness",
    "sg:classifiers":[
        {
            "category":"Professional",
            "subcategory":"Engineering",
            "type":"Services"
        }
    ],
    "sg:phone":"+44 1229 824829",
    "sg:postcode":"LA14 1AG",
    "sg:province":"Cumbria",
    "sg:tags":[
        "engineer",
        "mechanical"
    ],
    "wof:name":"Rolls Royce Associates",
    "wof:placetype":"venue"
},
  "geometry": {"coordinates":[-3.225847,54.111088],"type":"Point"}
}