{
  "type": "Feature",
  "properties": {
    "iso:country":"GB",
    "sg:address":"11 Hafod Olau, Deiniolen",
    "sg:city":"Caernarfon",
    "sg:classifiers":[
        {
            "category":"Manufacturing",
            "subcategory":"Wood Products",
            "type":"Manufacturing & Wholesale Goods"
        }
    ],
    "sg:phone":"+44 1286 871929",
    "sg:postcode":"LL55 3LP",
    "sg:province":"Gwynedd",
    "sg:tags":[
        "maker",
        "cabinet"
    ],
    "wof:name":"K.T.S Gwynedd",
    "wof:placetype":"venue"
},
  "geometry": {"coordinates":[-4.127439,53.147484],"type":"Point"}
}