{
  "type": "Feature",
  "properties": {
    "addr:full":"Monkwick Avenue Colchester Essex CO2 8NJ",
    "addr:postcode":"co2 8nj",
    "addr:street":"Avenue",
    "iso:country":"GB",
    "sg:address":"Monkwick Avenue",
    "sg:city":"Colchester",
    "sg:classifiers":[
        {
            "category":"Education",
            "subcategory":"School",
            "type":"Public Place"
        }
    ],
    "sg:phone":"+44 1206 547911",
    "sg:postcode":"CO2 8NJ",
    "sg:province":"Essex",
    "sg:tags":[
        "local",
        "authority",
        "catering"
    ],
    "wof:name":"Thomas Lord Audley School",
    "wof:placetype":"venue"
},
  "geometry": {"coordinates":[0.901777029,51.8661193848],"type":"Point"}
}