{
  "type": "Feature",
  "properties": {
    "iso:country":"GB",
    "sg:address":"Wisborough Grn",
    "sg:city":"Billingshurst",
    "sg:classifiers":[
        {
            "category":"Farming",
            "subcategory":"Livestock Farm",
            "type":"Manufacturing & Wholesale Goods"
        },
        {
            "category":"Retail",
            "subcategory":"Animal Services",
            "type":"Services"
        }
    ],
    "sg:phone":"+44 1403 700557",
    "sg:postcode":"RH14 0HR",
    "sg:province":"West Sussex",
    "sg:tags":[
        "breeder",
        "horse",
        "stud"
    ],
    "wof:name":"Crimbourne Stud",
    "wof:placetype":"venue"
},
  "geometry": {"coordinates":[-0.4966320097,51.019657135],"type":"Point"}
}