{
  "type": "Feature",
  "properties": {
    "iso:country":"GB",
    "sg:address":"58 Fife Rd",
    "sg:city":"Kingston Upon Thames",
    "sg:classifiers":[
        {
            "category":"Shopping",
            "subcategory":"News",
            "type":"Retail Goods"
        },
        {
            "category":"Food & Beverages",
            "subcategory":"Groceries & Convenience Stores",
            "type":"Retail Goods"
        }
    ],
    "sg:phone":"+44 20 8549 3834",
    "sg:postcode":"KT1 1SP",
    "sg:province":"Greater London",
    "sg:tags":[
        "newsagent"
    ],
    "wof:name":"KINGSTON NEWS LTD",
    "wof:placetype":"venue"
},
  "geometry": {"coordinates":[-0.301678,51.411884],"type":"Point"}
}