{
  "type": "Feature",
  "properties": {
    "iso:country":"GB",
    "sg:address":"68 Queen Street",
    "sg:city":"Newton Abbot",
    "sg:classifiers":[
        {
            "category":"Retail",
            "subcategory":"Funeral Services",
            "type":"Services"
        }
    ],
    "sg:phone":"+44 1626 334444",
    "sg:postcode":"TQ12 2ES",
    "sg:province":"Devon",
    "wof:name":"Hugh Mills Gaye & Co. Ltd.",
    "wof:placetype":"venue"
},
  "geometry": {"coordinates":[-3.6058731079,50.5306739807],"type":"Point"}
}