{
  "type": "Feature",
  "properties": {
    "iso:country":"GB",
    "sg:address":"Western Rd",
    "sg:city":"Hailsham",
    "sg:classifiers":[
        {
            "category":"Social Services",
            "subcategory":"Retirement Home",
            "type":"Services"
        },
        {
            "category":"Government",
            "subcategory":"Office",
            "type":"Public Place"
        }
    ],
    "sg:phone":"+44 1323 847945",
    "sg:postcode":"BN27 3DY",
    "sg:province":"East Sussex",
    "sg:tags":[
        "residential",
        "central",
        "care"
    ],
    "wof:name":"Eastbourne Health Authority",
    "wof:placetype":"venue"
},
  "geometry": {"coordinates":[0.252456,50.862873],"type":"Point"}
}