{
  "type": "Feature",
  "properties": {
    "iso:country":"GB",
    "sg:address":"Waingrove, Blyth Rd",
    "sg:city":"Retford",
    "sg:classifiers":[
        {
            "category":"Farming",
            "subcategory":"Livestock Farm",
            "type":"Manufacturing & Wholesale Goods"
        }
    ],
    "sg:phone":"+44 1777 818789",
    "sg:postcode":"DN22 8LR",
    "sg:province":"Nottinghamshire",
    "sg:tags":[
        "others"
    ],
    "wof:name":"J B Kitchin",
    "wof:placetype":"venue"
},
  "geometry": {"coordinates":[-0.945728,53.325184],"type":"Point"}
}