{
  "type": "Feature",
  "properties": {
    "addr:full":"Silver Birches, Plomer Green Lane, Downley High Wycombe Buckinghamshire HP13 5XN",
    "addr:postcode":"hp13 5xn",
    "addr:street":"Plomer Green Lane",
    "iso:country":"GB",
    "sg:address":"Silver Birches, Plomer Green Lane, Downley",
    "sg:city":"High Wycombe",
    "sg:classifiers":[
        {
            "category":"Home & Garden",
            "subcategory":"Household Appliances",
            "type":"Retail Goods"
        },
        {
            "category":"Retail",
            "subcategory":"Repair Shop",
            "type":"Services"
        }
    ],
    "sg:phone":"+44 1494 436726",
    "sg:postcode":"HP13 5XN",
    "sg:province":"Buckinghamshire",
    "sg:tags":[
        "electrical",
        "television",
        "video",
        "radio"
    ],
    "wof:name":"Mr Tiller",
    "wof:placetype":"venue"
},
  "geometry": {"coordinates":[-0.7760570049,51.6499176025],"type":"Point"}
}