{
  "type": "Feature",
  "properties": {
    "iso:country":"GB",
    "sg:address":"263 Luton Road",
    "sg:city":"Chatham",
    "sg:classifiers":[
        {
            "category":"Shopping",
            "subcategory":"Florist",
            "type":"Retail Goods"
        }
    ],
    "sg:phone":"+44 1634 848787",
    "sg:postcode":"ME4 5BN",
    "sg:province":"Kent",
    "wof:name":"Petals & Stems",
    "wof:placetype":"venue"
},
  "geometry": {"coordinates":[0.5413169861,51.3738288879],"type":"Point"}
}