{
  "type": "Feature",
  "properties": {
    "addr:full":"39 Kingsand Rd Grove Park Greater London SE12 0LE",
    "addr:housenumber":"39",
    "addr:postcode":"se12 0le",
    "addr:street":"Kingsand Rd",
    "iso:country":"GB",
    "sg:address":"39 Kingsand Rd",
    "sg:city":"Grove Park",
    "sg:classifiers":[
        {
            "category":"Professional",
            "subcategory":"Engineering",
            "type":"Services"
        }
    ],
    "sg:phone":"+44 20 8857 9106",
    "sg:postcode":"SE12 0LE",
    "sg:province":"Greater London",
    "sg:tags":[
        "engineer"
    ],
    "wof:name":"Chase & Co",
    "wof:placetype":"venue"
},
  "geometry": {"coordinates":[0.0197800007,51.4383010864],"type":"Point"}
}