{
  "type": "Feature",
  "properties": {
    "iso:country":"GB",
    "sg:address":"Unit N6, Europa Trading Estate, Fraser Road",
    "sg:city":"Erith",
    "sg:classifiers":[
        {
            "category":"Freight",
            "type":"Transportation"
        }
    ],
    "sg:phone":"+44 1322 432639",
    "sg:postcode":"DA8 1QL",
    "sg:province":"Kent",
    "sg:tags":[
        "forwarders"
    ],
    "wof:name":"A Cheverton Forwarding Ltd.",
    "wof:placetype":"venue"
},
  "geometry": {"coordinates":[0.180495,51.479221],"type":"Point"}
}