{
  "type": "Feature",
  "properties": {
    "addr:full":"Cross Street, Thornton Dale Pickering North Yorkshire YO18 7RW",
    "addr:postcode":"yo18 7rw",
    "addr:street":"Cross Street;Dale",
    "iso:country":"GB",
    "sg:address":"Cross Street, Thornton Dale",
    "sg:city":"Pickering",
    "sg:classifiers":[
        {
            "category":"Cafe",
            "type":"Food & Drink"
        }
    ],
    "sg:postcode":"YO18 7RW",
    "sg:province":"North Yorkshire",
    "sg:tags":[
        "tea",
        "room"
    ],
    "wof:name":"Baldersons",
    "wof:placetype":"venue"
},
  "geometry": {"coordinates":[-0.779388,54.24501],"type":"Point"}
}