{
  "type": "Feature",
  "properties": {
    "addr:full":"Unit 20 The Ivories, 6-8 Northampton Street London Greater London N1 2HY",
    "addr:housenumber":"unit 20;6-8",
    "addr:postcode":"n1 2hy",
    "addr:street":"The Ivories;Northampton Street",
    "iso:country":"GB",
    "sg:address":"Unit 20 The Ivories, 6-8 Northampton Street",
    "sg:city":"London",
    "sg:classifiers":[
        {
            "category":"Manufacturing",
            "subcategory":"Textiles",
            "type":"Manufacturing & Wholesale Goods"
        }
    ],
    "sg:phone":"+44 20 7359 2311",
    "sg:postcode":"N1 2HY",
    "sg:province":"Greater London",
    "sg:tags":[
        "knitwear"
    ],
    "wof:name":"Addison Smith Ltd.",
    "wof:placetype":"venue"
},
  "geometry": {"coordinates":[-0.09521,51.54121],"type":"Point"}
}