{
  "type": "Feature",
  "properties": {
    "addr:full":"Thorpe Green Sheffield Derbyshire S19 6HH",
    "addr:postcode":"s19 6hh",
    "addr:street":"Green",
    "iso:country":"GB",
    "sg:address":"Thorpe Green",
    "sg:city":"Sheffield",
    "sg:classifiers":[
        {
            "category":"Bars & Pubs",
            "type":"Food & Drink"
        }
    ],
    "sg:phone":"+44 114 247 0240",
    "sg:postcode":"S19 6HH",
    "sg:province":"Derbyshire",
    "sg:tags":[
        "pubs",
        "inn"
    ],
    "wof:name":"Hawk & Dove The",
    "wof:placetype":"venue"
},
  "geometry": {"coordinates":[-1.4743690491,53.3686676025],"type":"Point"}
}