{
  "type": "Feature",
  "properties": {
    "iso:country":"GB",
    "sg:address":"6 Polwarth Crescent",
    "sg:city":"Edinburgh",
    "sg:classifiers":[
        {
            "category":"Banks & Credit Unions",
            "subcategory":"Financial Services",
            "type":"Services"
        }
    ],
    "sg:phone":"+44 131 229 9386",
    "sg:postcode":"EH11 1HW",
    "sg:province":"City of Edinburgh",
    "sg:tags":[
        "adviser"
    ],
    "wof:name":"J D Chisholm",
    "wof:placetype":"venue"
},
  "geometry": {"coordinates":[-3.216588,55.937778],"type":"Point"}
}