{
  "type": "Feature",
  "properties": {
    "iso:country":"GB",
    "sg:address":"Unit C Beevor Street",
    "sg:city":"Barnsley",
    "sg:classifiers":[
        {
            "category":"Professional",
            "type":"Services"
        }
    ],
    "sg:phone":"+44 1226 280280",
    "sg:postcode":"S71 1HN",
    "sg:province":"South Yorkshire",
    "sg:tags":[
        "directory",
        "pub"
    ],
    "wof:name":"Leaflet World",
    "wof:placetype":"venue"
},
  "geometry": {"coordinates":[-1.459149,53.553146],"type":"Point"}
}