{
  "type": "Feature",
  "properties": {
    "iso:country":"GB",
    "sg:address":"Cockburns, Gowan Avenue",
    "sg:city":"Falkirk",
    "sg:classifiers":[
        {
            "category":"Retail",
            "subcategory":"Auto Repair",
            "type":"Services"
        }
    ],
    "sg:phone":"+44 1324 633526",
    "sg:postcode":"FK2 7HL",
    "sg:province":"Falkirk",
    "sg:tags":[
        "modification",
        "garage"
    ],
    "wof:name":"Scott James Citroen",
    "wof:placetype":"venue"
},
  "geometry": {"coordinates":[-3.792039,56.017288],"type":"Point"}
}