{
  "type": "Feature",
  "properties": {
    "addr:full":"132 Waterton Lane, Mossley Ashton Under Lyne Greater Manchester OL5 0NQ",
    "addr:housenumber":"132",
    "addr:postcode":"ol5 0nq",
    "addr:street":"Waterton Lane;Under Lyne",
    "iso:country":"GB",
    "sg:address":"132 Waterton Lane, Mossley",
    "sg:city":"Ashton Under Lyne",
    "sg:classifiers":[
        {
            "category":"Home & Garden",
            "subcategory":"Building Materials",
            "type":"Retail Goods"
        }
    ],
    "sg:phone":"+44 1457 838282",
    "sg:postcode":"OL5 0NQ",
    "sg:province":"Greater Manchester",
    "sg:tags":[
        "brick"
    ],
    "wof:name":"A.E Clarke",
    "wof:placetype":"venue"
},
  "geometry": {"coordinates":[-2.0506329536,53.5223693848],"type":"Point"}
}