{
  "type": "Feature",
  "properties": {
    "addr:full":"87 New Bristol Rd Weston Super Mare Somerset BS22 6AJ",
    "addr:housenumber":"87",
    "addr:postcode":"bs22 6aj",
    "addr:street":"New Bristol Rd",
    "iso:country":"GB",
    "sg:address":"87 New Bristol Rd",
    "sg:city":"Weston Super Mare",
    "sg:classifiers":[
        {
            "category":"Health Services",
            "subcategory":"Doctor",
            "type":"Services"
        }
    ],
    "sg:phone":"+44 1934 515878",
    "sg:postcode":"BS22 6AJ",
    "sg:province":"Somerset",
    "sg:tags":[
        "practitioners"
    ],
    "wof:name":"Pimm, M H J",
    "wof:placetype":"venue"
},
  "geometry": {"coordinates":[-2.9177689552,51.3588104248],"type":"Point"}
}