{
  "type": "Feature",
  "properties": {
    "iso:country":"GB",
    "sg:address":"The Old Rectory, Holdenby",
    "sg:city":"Northampton",
    "sg:classifiers":[
        {
            "category":"Manufacturing",
            "subcategory":"Wood Products",
            "type":"Manufacturing & Wholesale Goods"
        }
    ],
    "sg:phone":"+44 1604 771173",
    "sg:postcode":"NN6 8DJ",
    "sg:province":"Northamptonshire",
    "sg:tags":[
        "packaging",
        "crate",
        "pallets"
    ],
    "wof:name":"Northampton Packaging Supplies Ltd",
    "wof:placetype":"venue"
},
  "geometry": {"coordinates":[-0.980969,52.305607],"type":"Point"}
}