{
  "type": "Feature",
  "properties": {
    "addr:full":"Grange Keith Moray AB55 3SS",
    "addr:postcode":"ab55 3ss",
    "addr:street":"Keith",
    "iso:country":"GB",
    "sg:address":"Grange",
    "sg:city":"Keith",
    "sg:classifiers":[
        {
            "category":"Building & Trades",
            "subcategory":"Equipment Rental",
            "type":"Services"
        }
    ],
    "sg:phone":"+44 1542 870292",
    "sg:postcode":"AB55 3SS",
    "sg:province":"Moray",
    "sg:tags":[
        "plant",
        "machinery"
    ],
    "wof:name":"Limehillock Quarry Plant Ltd.",
    "wof:placetype":"venue"
},
  "geometry": {"coordinates":[-2.9504199028,57.5432357788],"type":"Point"}
}