{
  "type": "Feature",
  "properties": {
    "iso:country":"GB",
    "sg:address":"Kings Cross, Quadring Road, Donington",
    "sg:city":"Spalding",
    "sg:classifiers":[
        {
            "category":"Manufacturing",
            "subcategory":"Wood Products",
            "type":"Manufacturing & Wholesale Goods"
        }
    ],
    "sg:phone":"+44 1775 820831",
    "sg:postcode":"PE11 4TB",
    "sg:province":"Lincolnshire",
    "sg:tags":[
        "packaging",
        "crate",
        "pallets"
    ],
    "wof:name":"Donington Packaging Supplies Ltd.",
    "wof:placetype":"venue"
},
  "geometry": {"coordinates":[-0.198247999,52.9040336609],"type":"Point"}
}