{
  "type": "Feature",
  "properties": {
    "addr:full":"Unit 43n Siddons Factory Estate, Unit 43s, Siddons Factory Estate, Howard Street West Bromwich West Midlands B70 0SU",
    "addr:housenumber":"43n;factory estate unit 43s;factory estate",
    "addr:postcode":"b70 0su",
    "addr:street":"Howard Street",
    "iso:country":"GB",
    "sg:address":"Unit 43n Siddons Factory Estate, Unit 43s, Siddons Factory Estate, Howard Street",
    "sg:city":"West Bromwich",
    "sg:classifiers":[
        {
            "category":"Manufacturing",
            "subcategory":"Metals",
            "type":"Manufacturing & Wholesale Goods"
        },
        {
            "category":"Wholesale",
            "subcategory":"Metals & Minerals",
            "type":"Manufacturing & Wholesale Goods"
        }
    ],
    "sg:phone":"+44 121 556 9120",
    "sg:postcode":"B70 0SU",
    "sg:province":"West Midlands",
    "sg:tags":[
        "fabricator",
        "work",
        "sheet"
    ],
    "wof:name":"West Bromwich Sheet Metal Ltd",
    "wof:placetype":"venue"
},
  "geometry": {"coordinates":[-2.0185260773,52.539440155],"type":"Point"}
}