{
  "type": "Feature",
  "properties": {
    "addr:full":"10 Union Street Stratford-upon-avon Warwickshire CV37 6QT",
    "addr:housenumber":"10",
    "addr:postcode":"cv37 6qt",
    "addr:street":"Union Street",
    "iso:country":"GB",
    "sg:address":"10 Union Street",
    "sg:city":"Stratford-upon-avon",
    "sg:classifiers":[
        {
            "category":"Insurance",
            "subcategory":"Insurance Agent",
            "type":"Services"
        }
    ],
    "sg:phone":"+44 1789 293815",
    "sg:postcode":"CV37 6QT",
    "sg:province":"Warwickshire",
    "sg:tags":[
        "broker"
    ],
    "wof:name":"Three Counties Insurance Brokers",
    "wof:placetype":"venue"
},
  "geometry": {"coordinates":[-1.706372,52.193279],"type":"Point"}
}