{
  "type": "Feature",
  "properties": {
    "iso:country":"GB",
    "sg:address":"2nd Floor, 12 West Street",
    "sg:city":"Ware",
    "sg:classifiers":[
        {
            "category":"Building & Trades",
            "subcategory":"Construction",
            "type":"Services"
        }
    ],
    "sg:phone":"+44 1920 464620",
    "sg:postcode":"SG12 9EE",
    "sg:province":"Hertfordshire",
    "sg:tags":[
        "bricklaying"
    ],
    "wof:name":"Potting Construction Ltd.",
    "wof:placetype":"venue"
},
  "geometry": {"coordinates":[-0.0323700011,51.8116111755],"type":"Point"}
}