{
  "type": "Feature",
  "properties": {
    "iso:country":"GB",
    "sg:address":"12 Church Street, Frodsham",
    "sg:city":"Warrington",
    "sg:classifiers":[
        {
            "category":"Bars & Pubs",
            "type":"Food & Drink"
        }
    ],
    "sg:phone":"+44 1928 734459",
    "sg:postcode":"WA6 7EB",
    "sg:province":"Cheshire",
    "sg:tags":[
        "pubs",
        "inn"
    ],
    "wof:name":"Cholmondeley Arms",
    "wof:placetype":"venue"
},
  "geometry": {"coordinates":[-2.725298,53.295292],"type":"Point"}
}