{
  "type": "Feature",
  "properties": {
    "iso:country":"GB",
    "sg:address":"10 Castle Street",
    "sg:city":"Reading",
    "sg:classifiers":[
        {
            "category":"Fast Food",
            "type":"Food & Drink"
        },
        {
            "category":"Restaurant",
            "type":"Food & Drink"
        }
    ],
    "sg:phone":"+44 118 958 6466",
    "sg:postcode":"RG1 7RD",
    "sg:province":"Berkshire",
    "sg:tags":[
        "away",
        "-",
        "take",
        "english"
    ],
    "wof:name":"Sweeney & Todd",
    "wof:placetype":"venue"
},
  "geometry": {"coordinates":[-0.974375,51.45377],"type":"Point"}
}