{
  "type": "Feature",
  "properties": {
    "addr:full":"179 West Road Westcliff-on-sea Essex SS0 9DH",
    "addr:housenumber":"179",
    "addr:postcode":"ss0 9dh",
    "addr:street":"West Road",
    "iso:country":"GB",
    "sg:address":"179 West Road",
    "sg:city":"Westcliff-on-sea",
    "sg:classifiers":[
        {
            "category":"Health Services",
            "subcategory":"Health Practitioner",
            "type":"Services"
        }
    ],
    "sg:postcode":"SS0 9DH",
    "sg:province":"Essex",
    "sg:tags":[
        "hypnotherapists"
    ],
    "wof:name":"George Kyriakos",
    "wof:placetype":"venue"
},
  "geometry": {"coordinates":[0.6995379925,51.5463752747],"type":"Point"}
}