{
  "type": "Feature",
  "properties": {
    "addr:full":"136 Buckingham Palace Rd London Greater London SW1W 9SA",
    "addr:housenumber":"136",
    "addr:postcode":"sw1w 9sa",
    "addr:street":"Buckingham Palace Rd",
    "iso:country":"GB",
    "sg:address":"136 Buckingham Palace Rd",
    "sg:city":"London",
    "sg:classifiers":[
        {
            "category":"Freight",
            "type":"Transportation"
        }
    ],
    "sg:postcode":"SW1W 9SA",
    "sg:province":"Greater London",
    "sg:tags":[
        "overseas",
        "shipping",
        "removal"
    ],
    "wof:name":"Stelmar Tankers (U K) Ltd",
    "wof:placetype":"venue"
},
  "geometry": {"coordinates":[-0.1472930014,51.4933891296],"type":"Point"}
}