{
  "type": "Feature",
  "properties": {
    "iso:country":"GB",
    "sg:address":"Boclair Farm, Boclair Road, Bearsden",
    "sg:city":"Glasgow",
    "sg:classifiers":[
        {
            "category":"Farming",
            "subcategory":"Livestock Farm",
            "type":"Manufacturing & Wholesale Goods"
        }
    ],
    "sg:postcode":"G61 2TH",
    "sg:province":"East Dunbartonshire",
    "sg:tags":[
        "others"
    ],
    "wof:name":"Jack Brewster",
    "wof:placetype":"venue"
},
  "geometry": {"coordinates":[-4.290459,55.926342],"type":"Point"}
}