{
  "type": "Feature",
  "properties": {
    "addr:full":"Lansdowne, 148 Banstead Road, Ewell Epsom Surrey KT17 3HN",
    "addr:housenumber":"148",
    "addr:postcode":"kt17 3hn",
    "addr:street":"Banstead Road",
    "iso:country":"GB",
    "sg:address":"Lansdowne, 148 Banstead Road, Ewell",
    "sg:city":"Epsom",
    "sg:classifiers":[
        {
            "category":"Building & Trades",
            "subcategory":"Plumbing",
            "type":"Services"
        }
    ],
    "sg:phone":"+44 20 8393 5963",
    "sg:postcode":"KT17 3HN",
    "sg:province":"Surrey",
    "sg:tags":[
        "central",
        "heating"
    ],
    "wof:name":"E H V Services Maintenance",
    "wof:placetype":"venue"
},
  "geometry": {"coordinates":[-0.2279900014,51.3366317749],"type":"Point"}
}