{
  "type": "Feature",
  "properties": {
    "addr:full":"11 St Chads Street London Greater London WC1H 8BG",
    "addr:housenumber":"11",
    "addr:postcode":"wc1h 8bg",
    "addr:street":"St Chads Street",
    "iso:country":"GB",
    "sg:address":"11 St Chads Street",
    "sg:city":"London",
    "sg:classifiers":[
        {
            "category":"Organizations",
            "subcategory":"Non-profit Organization",
            "type":"Services"
        }
    ],
    "sg:postcode":"WC1H 8BG",
    "sg:province":"Greater London",
    "sg:tags":[
        "organisation",
        "voluntary",
        "charity"
    ],
    "wof:name":"Camden Age Concern",
    "wof:placetype":"venue"
},
  "geometry": {"coordinates":[-0.121424,51.529736],"type":"Point"}
}