{
  "type": "Feature",
  "properties": {
    "addr:full":"31 Town End Field Witham Essex CM8 1EU",
    "addr:housenumber":"31",
    "addr:postcode":"cm8 1eu",
    "addr:street":"Town End Field",
    "iso:country":"GB",
    "sg:address":"31 Town End Field",
    "sg:city":"Witham",
    "sg:classifiers":[
        {
            "category":"Professional",
            "subcategory":"Management & Consulting",
            "type":"Services"
        }
    ],
    "sg:postcode":"CM8 1EU",
    "sg:province":"Essex",
    "sg:tags":[
        "consultant",
        "business"
    ],
    "wof:name":"Jrd Marketing",
    "wof:placetype":"venue"
},
  "geometry": {"coordinates":[0.630625,51.792122],"type":"Point"}
}