{
  "type": "Feature",
  "properties": {
    "addr:full":"95 Causeyside St Paisley Renfrewshire PA1 1TU",
    "addr:housenumber":"95",
    "addr:postcode":"pa1 1tu",
    "addr:street":"Causeyside St",
    "iso:country":"GB",
    "sg:address":"95 Causeyside St",
    "sg:city":"Paisley",
    "sg:classifiers":[
        {
            "category":"Professional",
            "subcategory":"Detective & Security Services",
            "type":"Services"
        }
    ],
    "sg:phone":"+44 141 887 1276",
    "sg:postcode":"PA1 1TU",
    "sg:province":"Renfrewshire",
    "sg:tags":[
        "locksmith"
    ],
    "wof:name":"Paisley Lock & Safe Co",
    "wof:placetype":"venue"
},
  "geometry": {"coordinates":[-4.424681,55.839516],"type":"Point"}
}