{
  "type": "Feature",
  "properties": {
    "iso:country":"GB",
    "sg:address":"Coleford Bridge Rd",
    "sg:city":"Camberley",
    "sg:classifiers":[
        {
            "category":"Bars & Pubs",
            "type":"Food & Drink"
        }
    ],
    "sg:phone":"+44 1252 372656",
    "sg:postcode":"GU16 6DS",
    "sg:province":"Hampshire",
    "sg:tags":[
        "pubs",
        "inn"
    ],
    "wof:name":"Quays The",
    "wof:placetype":"venue"
},
  "geometry": {"coordinates":[-0.736933,51.293385],"type":"Point"}
}