{
  "type": "Feature",
  "properties": {
    "iso:country":"GB",
    "sg:address":"40-44 Middle Street",
    "sg:city":"Yeovil",
    "sg:classifiers":[
        {
            "category":"Shopping",
            "subcategory":"Gifts & Souvenirs",
            "type":"Retail Goods"
        }
    ],
    "sg:phone":"+44 1935 412366",
    "sg:postcode":"BA20 1LX",
    "sg:province":"Somerset",
    "sg:tags":[
        "poster",
        "card"
    ],
    "wof:name":"Bastins Ltd.",
    "wof:placetype":"venue"
},
  "geometry": {"coordinates":[-2.6296429634,50.9411392212],"type":"Point"}
}