{
  "type": "Feature",
  "properties": {
    "iso:country":"GB",
    "sg:address":"8 Derwent Avenue",
    "sg:city":"Ashton-under-lyne",
    "sg:classifiers":[
        {
            "category":"Building & Trades",
            "subcategory":"Landscaping Services",
            "type":"Services"
        }
    ],
    "sg:phone":"+44 161 339 5103",
    "sg:postcode":"OL7 9EP",
    "sg:province":"Greater Manchester",
    "sg:tags":[
        "gardening"
    ],
    "wof:name":"Ceejay Gardening Services",
    "wof:placetype":"venue"
},
  "geometry": {"coordinates":[-2.106557,53.493481],"type":"Point"}
}