{
  "type": "Feature",
  "properties": {
    "addr:full":"Beechwood Av Runcorn Cheshire WA7 4SB",
    "addr:postcode":"wa7 4sb",
    "addr:street":"Beechwood Av Runcorn Cheshire",
    "iso:country":"GB",
    "sg:address":"Beechwood Av",
    "sg:city":"Runcorn",
    "sg:classifiers":[
        {
            "category":"Professional",
            "subcategory":"Advertising",
            "type":"Services"
        }
    ],
    "sg:phone":"+44 1928 590210",
    "sg:postcode":"WA7 4SB",
    "sg:province":"Cheshire",
    "wof:name":"T D I Advertising Ltd",
    "wof:placetype":"venue"
},
  "geometry": {"coordinates":[-2.6927258968,53.3153648376],"type":"Point"}
}