{
  "type": "Feature",
  "properties": {
    "addr:full":"Unit 8 Oxford Business Centre, Osney Lane Oxford Oxfordshire OX1 1TB",
    "addr:housenumber":"unit 8",
    "addr:postcode":"ox1 1tb",
    "addr:street":"Oxford Business Centre Osney Lane",
    "iso:country":"GB",
    "sg:address":"Unit 8 Oxford Business Centre, Osney Lane",
    "sg:city":"Oxford",
    "sg:classifiers":[
        {
            "category":"Shopping",
            "subcategory":"Stationery & Office Supplies",
            "type":"Retail Goods"
        }
    ],
    "sg:phone":"+44 1865 727292",
    "sg:postcode":"OX1 1TB",
    "sg:province":"Oxfordshire",
    "wof:name":"Nicholas Hunter Ltd.",
    "wof:placetype":"venue"
},
  "geometry": {"coordinates":[-1.2594890594,51.7562065125],"type":"Point"}
}