{
  "type": "Feature",
  "properties": {
    "iso:country":"GB",
    "sg:address":"The Tower Building",
    "sg:city":"London",
    "sg:classifiers":[
        {
            "category":"Professional",
            "subcategory":"Business Services",
            "type":"Services"
        }
    ],
    "sg:phone":"+44 20 7922 0880",
    "sg:postcode":"SE1 7NX",
    "sg:province":"Greater London",
    "sg:tags":[
        "publishers'"
    ],
    "wof:name":"T & T Clark Ltd.",
    "wof:placetype":"venue"
},
  "geometry": {"coordinates":[-0.11648,51.5023],"type":"Point"}
}