{
  "type": "Feature",
  "properties": {
    "addr:full":"64 Green Lanes London Greater London N16 9NH",
    "addr:housenumber":"64",
    "addr:postcode":"n16 9nh",
    "addr:street":"Green Lanes",
    "iso:country":"GB",
    "sg:address":"64 Green Lanes",
    "sg:city":"London",
    "sg:classifiers":[
        {
            "category":"Retail",
            "subcategory":"Repair Shop",
            "type":"Services"
        }
    ],
    "sg:phone":"+44 20 7254 8052",
    "sg:postcode":"N16 9NH",
    "sg:province":"Greater London",
    "sg:tags":[
        "radio",
        "television",
        "video"
    ],
    "wof:name":"Stereovision",
    "wof:placetype":"venue"
},
  "geometry": {"coordinates":[-0.0880099982,51.5535469055],"type":"Point"}
}