{
  "type": "Feature",
  "properties": {
    "addr:full":"Foxbro, Park Lane, Bulmer Tye Sudbury Essex CO10 7EQ",
    "addr:postcode":"co10 7eq",
    "addr:street":"Park Lane;Tye",
    "iso:country":"GB",
    "sg:address":"Foxbro, Park Lane, Bulmer Tye",
    "sg:city":"Sudbury",
    "sg:classifiers":[
        {
            "category":"Home & Garden",
            "subcategory":"Garden Supply",
            "type":"Retail Goods"
        }
    ],
    "sg:postcode":"CO10 7EQ",
    "sg:province":"Essex",
    "sg:tags":[
        "planting",
        "tree",
        "shrub"
    ],
    "wof:name":"Ken Leech Trees",
    "wof:placetype":"venue"
},
  "geometry": {"coordinates":[0.687295,52.030289],"type":"Point"}
}