{
  "type": "Feature",
  "properties": {
    "iso:country":"GB",
    "sg:address":"2 Portsmouth Rd, Cosham",
    "sg:city":"Portsmouth",
    "sg:classifiers":[
        {
            "category":"Professional",
            "subcategory":"Art Services",
            "type":"Services"
        }
    ],
    "sg:phone":"+44 23 9220 1717",
    "sg:postcode":"PO6 2SG",
    "sg:province":"Hampshire",
    "sg:tags":[
        "consultant",
        "design"
    ],
    "wof:name":"Geoffrey B Hogg",
    "wof:placetype":"venue"
},
  "geometry": {"coordinates":[-1.068323,50.840782],"type":"Point"}
}