{
  "type": "Feature",
  "properties": {
    "iso:country":"GB",
    "sg:address":"52 High Street",
    "sg:city":"Menai Bridge",
    "sg:classifiers":[
        {
            "category":"Travel",
            "subcategory":"Hotels & Motels",
            "type":"Entertainment"
        }
    ],
    "sg:postcode":"LL59 5EF",
    "sg:province":"Isle of Anglesey",
    "sg:tags":[
        "house",
        "guest"
    ],
    "wof:name":"Ty Gwyn Guest House",
    "wof:placetype":"venue"
},
  "geometry": {"coordinates":[-4.162164,53.227379],"type":"Point"}
}