{
  "type": "Feature",
  "properties": {
    "addr:full":"Pant Du Road Mold Denbighshire CH7 4DD",
    "addr:postcode":"ch7 4dd",
    "addr:street":"Pant Du Road",
    "iso:country":"GB",
    "sg:address":"Pant Du Road",
    "sg:city":"Mold",
    "sg:classifiers":[
        {
            "category":"Retail",
            "subcategory":"Auto Repair",
            "type":"Services"
        }
    ],
    "sg:phone":"+44 1352 810688",
    "sg:postcode":"CH7 4DD",
    "sg:province":"Denbighshire",
    "sg:tags":[
        "modification",
        "garage"
    ],
    "wof:name":"Burley Hill Garage",
    "wof:placetype":"venue"
},
  "geometry": {"coordinates":[-3.1324520111,53.1069259644],"type":"Point"}
}