{
  "type": "Feature",
  "properties": {
    "addr:full":"The Old Manor House Surgery, Market Street Hailsham East Sussex BN27 2AE",
    "addr:postcode":"bn27 2ae",
    "addr:street":"Market Street",
    "iso:country":"GB",
    "sg:address":"The Old Manor House Surgery, Market Street",
    "sg:city":"Hailsham",
    "sg:classifiers":[
        {
            "category":"Retail",
            "subcategory":"Veterinary Services",
            "type":"Services"
        }
    ],
    "sg:phone":"+44 1323 842141",
    "sg:postcode":"BN27 2AE",
    "sg:province":"East Sussex",
    "sg:tags":[
        "surgeon"
    ],
    "wof:name":"Foreman & Hanna",
    "wof:placetype":"venue"
},
  "geometry": {"coordinates":[0.25652,50.865383],"type":"Point"}
}