{
  "type": "Feature",
  "properties": {
    "addr:full":"Claremont, Victoria St, Coombe Martin Ilfracombe Devon EX34 0JR",
    "addr:postcode":"ex34 0jr",
    "addr:street":"Victoria St",
    "iso:country":"GB",
    "sg:address":"Claremont, Victoria St, Coombe Martin",
    "sg:city":"Ilfracombe",
    "sg:classifiers":[
        {
            "category":"Professional",
            "subcategory":"Printing & Photocopies",
            "type":"Services"
        }
    ],
    "sg:phone":"+44 1271 882524",
    "sg:postcode":"EX34 0JR",
    "sg:province":"Devon",
    "sg:tags":[
        "emblem",
        "wholesale",
        "badge"
    ],
    "wof:name":"The Jammy Badge Co",
    "wof:placetype":"venue"
},
  "geometry": {"coordinates":[-4.0194501877,51.1964416504],"type":"Point"}
}