{
  "type": "Feature",
  "properties": {
    "addr:full":"137 Crombie Avenue York North Yorkshire YO30 6SS",
    "addr:housenumber":"137",
    "addr:postcode":"yo30 6ss",
    "addr:street":"Crombie Avenue",
    "iso:country":"GB",
    "sg:address":"137 Crombie Avenue",
    "sg:city":"York",
    "sg:classifiers":[
        {
            "category":"Health Services",
            "subcategory":"Health Practitioner",
            "type":"Services"
        }
    ],
    "sg:phone":"+44 1904 671104",
    "sg:postcode":"YO30 6SS",
    "sg:province":"North Yorkshire",
    "sg:tags":[
        "psychotherapist"
    ],
    "wof:name":"York Psychotherapy Clinic Ltd.",
    "wof:placetype":"venue"
},
  "geometry": {"coordinates":[-1.0893360376,53.9754524231],"type":"Point"}
}