{
  "type": "Feature",
  "properties": {
    "addr:full":"Down House, 205 Broomhill Road London Greater London SW18 4JQ",
    "addr:housenumber":"205",
    "addr:postcode":"sw18 4jq",
    "addr:street":"Broomhill Road",
    "iso:country":"GB",
    "sg:address":"Down House, 205 Broomhill Road",
    "sg:city":"London",
    "sg:classifiers":[
        {
            "category":"Wholesale",
            "subcategory":"Medical Equipment & Supplies",
            "type":"Manufacturing & Wholesale Goods"
        }
    ],
    "sg:phone":"+44 20 8871 5216",
    "sg:postcode":"SW18 4JQ",
    "sg:province":"Greater London",
    "wof:name":"R F O Medical Company",
    "wof:placetype":"venue"
},
  "geometry": {"coordinates":[-0.197359,51.454639],"type":"Point"}
}