{
  "type": "Feature",
  "properties": {
    "iso:country":"GB",
    "sg:address":"2 Totherway, Church Lane, Headley",
    "sg:city":"Bordon",
    "sg:classifiers":[
        {
            "category":"Building & Trades",
            "subcategory":"Construction",
            "type":"Services"
        }
    ],
    "sg:phone":"+44 1428 712567",
    "sg:postcode":"GU35 8PJ",
    "sg:province":"Hampshire",
    "sg:tags":[
        "builder"
    ],
    "wof:name":"Hampshire Building Contractors",
    "wof:placetype":"venue"
},
  "geometry": {"coordinates":[-0.8207899928,51.1196250916],"type":"Point"}
}