{
  "type": "Feature",
  "properties": {
    "addr:full":"44 East Lancashire Road Blackburn Lancashire BB1 9QZ",
    "addr:housenumber":"44",
    "addr:postcode":"bb1 9qz",
    "addr:street":"East Lancashire Road",
    "iso:country":"GB",
    "sg:address":"44 East Lancashire Road",
    "sg:city":"Blackburn",
    "sg:classifiers":[
        {
            "category":"Retail",
            "subcategory":"Driving School",
            "type":"Services"
        }
    ],
    "sg:phone":"+44 1254 249890",
    "sg:postcode":"BB1 9QZ",
    "sg:province":"Lancashire",
    "wof:name":"Brownhill School Of Motoring",
    "wof:placetype":"venue"
},
  "geometry": {"coordinates":[-2.472315073,53.7774162292],"type":"Point"}
}