{
  "type": "Feature",
  "properties": {
    "iso:country":"GB",
    "sg:address":"15 Cliffhill Road, Shaw",
    "sg:city":"Oldham",
    "sg:classifiers":[
        {
            "category":"Building & Trades",
            "subcategory":"Construction",
            "type":"Services"
        }
    ],
    "sg:phone":"+44 1706 845912",
    "sg:postcode":"OL2 8DE",
    "sg:province":"Lancashire",
    "sg:tags":[
        "roofing"
    ],
    "wof:name":"A R Marsden Roofing Services",
    "wof:placetype":"venue"
},
  "geometry": {"coordinates":[-2.0825328827,53.5874404907],"type":"Point"}
}