{
  "type": "Feature",
  "properties": {
    "addr:full":"715-719 The Corn Exchange, Senwick Street Liverpool Merseyside L2 7RL",
    "addr:housenumber":"715-719",
    "addr:postcode":"l2 7rl",
    "addr:street":"The;Senwick Street",
    "iso:country":"GB",
    "sg:address":"715-719 The Corn Exchange, Senwick Street",
    "sg:city":"Liverpool",
    "sg:classifiers":[
        {
            "category":"Professional",
            "subcategory":"Accounting & Tax Preparation",
            "type":"Services"
        }
    ],
    "sg:phone":"+44 151 227 3373",
    "sg:postcode":"L2 7RL",
    "sg:province":"Merseyside",
    "sg:tags":[
        "accountant"
    ],
    "wof:name":"Jopling & Co.",
    "wof:placetype":"venue"
},
  "geometry": {"coordinates":[-2.9916,53.40498],"type":"Point"}
}