{
  "type": "Feature",
  "properties": {
    "iso:country":"GB",
    "sg:address":"1 Princess Road",
    "sg:city":"Stonehaven",
    "sg:classifiers":[
        {
            "category":"Freight",
            "type":"Transportation"
        }
    ],
    "sg:postcode":"AB39 2DR",
    "sg:province":"Aberdeenshire",
    "sg:tags":[
        "haulage",
        "road"
    ],
    "wof:name":"William J Killoh",
    "wof:placetype":"venue"
},
  "geometry": {"coordinates":[-2.224239,56.95998],"type":"Point"}
}