{
  "type": "Feature",
  "properties": {
    "addr:full":"55 Binley Road Coventry Warwickshire CV3 1HU",
    "addr:housenumber":"55",
    "addr:postcode":"cv3 1hu",
    "addr:street":"Binley Road",
    "iso:country":"GB",
    "sg:address":"55 Binley Road",
    "sg:city":"Coventry",
    "sg:classifiers":[
        {
            "category":"Shopping",
            "subcategory":"Pharmacy",
            "type":"Retail Goods"
        }
    ],
    "sg:phone":"+44 24 7645 7513",
    "sg:postcode":"CV3 1HU",
    "sg:province":"Warwickshire",
    "sg:tags":[
        "pharmacist",
        "chemist"
    ],
    "wof:name":"Cara Pharmacy",
    "wof:placetype":"venue"
},
  "geometry": {"coordinates":[-1.477962,52.406429],"type":"Point"}
}