{
  "type": "Feature",
  "properties": {
    "addr:full":"90 Graham Avenue, Portslade Brighton East Sussex BN41 2WL",
    "addr:housenumber":"90",
    "addr:postcode":"bn41 2wl",
    "addr:street":"Graham Avenue",
    "iso:country":"GB",
    "sg:address":"90 Graham Avenue, Portslade",
    "sg:city":"Brighton",
    "sg:classifiers":[
        {
            "category":"Personal",
            "subcategory":"Beauty Salon",
            "type":"Services"
        }
    ],
    "sg:phone":"+44 1273 416332",
    "sg:postcode":"BN41 2WL",
    "sg:province":"East Sussex",
    "sg:tags":[
        "lady",
        "hairdresser"
    ],
    "wof:name":"Mahogany",
    "wof:placetype":"venue"
},
  "geometry": {"coordinates":[-0.228098,50.853474],"type":"Point"}
}