{
  "type": "Feature",
  "properties": {
    "iso:country":"GB",
    "sg:address":"14-15 Newhallhey Business Park, Newhallhey Road",
    "sg:city":"Rossendale",
    "sg:classifiers":[
        {
            "category":"Building & Trades",
            "subcategory":"Construction",
            "type":"Services"
        }
    ],
    "sg:phone":"+44 1706 212232",
    "sg:postcode":"BB4 6HR",
    "sg:province":"Lancashire",
    "sg:tags":[
        "window",
        "replacement"
    ],
    "wof:name":"High Profile Windows Ltd.",
    "wof:placetype":"venue"
},
  "geometry": {"coordinates":[-2.274824,53.708961],"type":"Point"}
}