{
  "type": "Feature",
  "properties": {
    "addr:full":"28b Commercial Road Buckie Moray AB56 1UN",
    "addr:housenumber":"28b",
    "addr:postcode":"ab56 1un",
    "addr:street":"Commercial Road",
    "iso:country":"GB",
    "sg:address":"28b Commercial Road",
    "sg:city":"Buckie",
    "sg:classifiers":[
        {
            "category":"Harbor",
            "type":"Transportation"
        },
        {
            "category":"Organizations",
            "subcategory":"Professional Association",
            "type":"Services"
        }
    ],
    "sg:phone":"+44 1542 831700",
    "sg:postcode":"AB56 1UN",
    "sg:province":"Moray",
    "sg:tags":[
        "dock",
        "operation",
        "port",
        "harbour",
        "ports"
    ],
    "wof:name":"Buckie Harbour Authority",
    "wof:placetype":"venue"
},
  "geometry": {"coordinates":[-2.9555630684,57.6799201965],"type":"Point"}
}