{
  "type": "Feature",
  "properties": {
    "iso:country":"GB",
    "sg:address":"25 Raynham Rd",
    "sg:city":"Bishops Stortford",
    "sg:classifiers":[
        {
            "category":"Building & Trades",
            "subcategory":"Construction",
            "type":"Services"
        }
    ],
    "sg:phone":"+44 1279 505936",
    "sg:postcode":"CM23 5PD",
    "sg:province":"Essex",
    "sg:tags":[
        "glazier"
    ],
    "wof:name":"Highway Glass Harlow",
    "wof:placetype":"venue"
},
  "geometry": {"coordinates":[0.176967,51.871941],"type":"Point"}
}