{
  "type": "Feature",
  "properties": {
    "iso:country":"GB",
    "sg:address":"Abbey Road, Pity Me",
    "sg:city":"Durham",
    "sg:classifiers":[
        {
            "category":"Freight",
            "type":"Transportation"
        }
    ],
    "sg:phone":"+44 191 384 4646",
    "sg:postcode":"DH1 5DQ",
    "sg:province":"Durham",
    "sg:tags":[
        "haulage",
        "road"
    ],
    "wof:name":"W A Glendinning Ltd.",
    "wof:placetype":"venue"
},
  "geometry": {"coordinates":[-1.592314,54.803543],"type":"Point"}
}