{
  "type": "Feature",
  "properties": {
    "iso:country":"GB",
    "sg:address":"227 Kenton Lane",
    "sg:city":"Harrow",
    "sg:classifiers":[
        {
            "category":"Government",
            "subcategory":"Fire Station",
            "type":"Public Place"
        }
    ],
    "sg:phone":"+44 20 8909 2553",
    "sg:postcode":"HA3 8RP",
    "sg:province":"Greater London",
    "sg:tags":[
        "w'sale",
        "lighting"
    ],
    "wof:name":"Revelec",
    "wof:placetype":"venue"
},
  "geometry": {"coordinates":[-0.312743,51.59573],"type":"Point"}
}