{
  "type": "Feature",
  "properties": {
    "addr:full":"6 Church Street South Brent Devon TQ10 9AB",
    "addr:housenumber":"6",
    "addr:postcode":"tq10 9ab",
    "addr:street":"Church Street",
    "iso:country":"GB",
    "sg:address":"6 Church Street",
    "sg:city":"South Brent",
    "sg:classifiers":[
        {
            "category":"Food & Beverages",
            "subcategory":"Fruits & Vegetables",
            "type":"Retail Goods"
        }
    ],
    "sg:postcode":"TQ10 9AB",
    "sg:province":"Devon",
    "sg:tags":[
        "greengrocer"
    ],
    "wof:name":"F & B Stores",
    "wof:placetype":"venue"
},
  "geometry": {"coordinates":[-3.8347299099,50.4265899658],"type":"Point"}
}