{
  "type": "Feature",
  "properties": {
    "iso:country":"GB",
    "sg:address":"22 Endsleigh Rd",
    "sg:city":"Colwyn Bay",
    "sg:classifiers":[
        {
            "category":"Retail",
            "subcategory":"Driving School",
            "type":"Services"
        }
    ],
    "sg:phone":"+44 1492 515821",
    "sg:postcode":"LL29 9DT",
    "sg:province":"Conwy",
    "wof:name":"North Wales Skid Car",
    "wof:placetype":"venue"
},
  "geometry": {"coordinates":[-3.692606,53.290852],"type":"Point"}
}