{
  "type": "Feature",
  "properties": {
    "addr:full":"5 Adrian Av Cricklewood Greater London NW2 1LX",
    "addr:housenumber":"5",
    "addr:postcode":"nw2 1lx",
    "addr:street":"Adrian Av",
    "iso:country":"GB",
    "sg:address":"5 Adrian Av",
    "sg:city":"Cricklewood",
    "sg:classifiers":[
        {
            "category":"Retail",
            "subcategory":"Auto Repair",
            "type":"Services"
        }
    ],
    "sg:phone":"+44 20 8450 8489",
    "sg:postcode":"NW2 1LX",
    "sg:province":"Greater London",
    "sg:tags":[
        "modification",
        "garage"
    ],
    "wof:name":"Garrett Motors",
    "wof:placetype":"venue"
},
  "geometry": {"coordinates":[-0.231457,51.572132],"type":"Point"}
}