{
  "type": "Feature",
  "properties": {
    "iso:country":"GB",
    "sg:address":"Treluckey Farm, Tregony",
    "sg:city":"Truro",
    "sg:classifiers":[
        {
            "category":"Farming",
            "subcategory":"Livestock Farm",
            "type":"Manufacturing & Wholesale Goods"
        }
    ],
    "sg:phone":"+44 1872 530272",
    "sg:postcode":"TR2 5TU",
    "sg:province":"Cornwall",
    "sg:tags":[
        "others"
    ],
    "wof:name":"P Hooper & Son",
    "wof:placetype":"venue"
},
  "geometry": {"coordinates":[-4.9126501083,50.2677154541],"type":"Point"}
}