{
  "type": "Feature",
  "properties": {
    "addr:full":"75 Granville Road Sidcup Kent DA14 4BT",
    "addr:housenumber":"75",
    "addr:postcode":"da14 4bt",
    "addr:street":"Granville Road",
    "iso:country":"GB",
    "sg:address":"75 Granville Road",
    "sg:city":"Sidcup",
    "sg:classifiers":[
        {
            "category":"Banks & Credit Unions",
            "subcategory":"Bank",
            "type":"Services"
        }
    ],
    "sg:phone":"+44 20 8309 6789",
    "sg:postcode":"DA14 4BT",
    "sg:province":"Kent",
    "sg:tags":[
        "broker",
        "mortgage"
    ],
    "wof:name":"S & J Financial Consultants",
    "wof:placetype":"venue"
},
  "geometry": {"coordinates":[0.1079280004,51.4275970459],"type":"Point"}
}