{
  "type": "Feature",
  "properties": {
    "addr:full":"3a Manor Road Wallington Surrey SM6 0BW",
    "addr:housenumber":"3a",
    "addr:postcode":"sm6 0bw",
    "addr:street":"Manor Road",
    "iso:country":"GB",
    "sg:address":"3a Manor Road",
    "sg:city":"Wallington",
    "sg:classifiers":[
        {
            "category":"Food & Beverages",
            "subcategory":"Meat & Fish",
            "type":"Retail Goods"
        },
        {
            "category":"Food & Beverages",
            "subcategory":"Groceries & Convenience Stores",
            "type":"Retail Goods"
        }
    ],
    "sg:phone":"+44 20 8647 3198",
    "sg:postcode":"SM6 0BW",
    "sg:province":"Surrey",
    "sg:tags":[
        "shop",
        "chip"
    ],
    "wof:name":"TONYS FISH BAR",
    "wof:placetype":"venue"
},
  "geometry": {"coordinates":[-0.1534530073,51.3671379089],"type":"Point"}
}