{
  "type": "Feature",
  "properties": {
    "addr:full":"45 The Coppice West Drayton Greater London UB7 8DX",
    "addr:housenumber":"45",
    "addr:postcode":"ub7 8dx",
    "addr:street":"The Coppice",
    "iso:country":"GB",
    "sg:address":"45 The Coppice",
    "sg:city":"West Drayton",
    "sg:classifiers":[
        {
            "category":"Home & Garden",
            "subcategory":"Home Furnishings",
            "type":"Retail Goods"
        }
    ],
    "sg:phone":"+44 1895 447959",
    "sg:postcode":"UB7 8DX",
    "sg:province":"Greater London",
    "sg:tags":[
        "blind",
        "curtain",
        "fitting"
    ],
    "wof:name":"Sonia",
    "wof:placetype":"venue"
},
  "geometry": {"coordinates":[-0.470284,51.52121],"type":"Point"}
}