{
  "type": "Feature",
  "properties": {
    "iso:country":"GB",
    "sg:address":"35 Prices La",
    "sg:city":"Reigate",
    "sg:classifiers":[
        {
            "category":"Building & Trades",
            "subcategory":"Construction",
            "type":"Services"
        }
    ],
    "sg:phone":"+44 1737 249396",
    "sg:postcode":"RH2 8BA",
    "sg:province":"Surrey",
    "sg:tags":[
        "decorator",
        "painter"
    ],
    "wof:name":"Coventry Decorating Specialist",
    "wof:placetype":"venue"
},
  "geometry": {"coordinates":[-0.202024,51.223087],"type":"Point"}
}