{
  "type": "Feature",
  "properties": {
    "addr:full":"Patriot Dr Milton Keynes Buckinghamshire MK13 8PZ",
    "addr:postcode":"mk13 8pz",
    "addr:street":"Patriot Dr",
    "iso:country":"GB",
    "sg:address":"Patriot Dr",
    "sg:city":"Milton Keynes",
    "sg:classifiers":[
        {
            "category":"Home & Garden",
            "subcategory":"Home Furnishings",
            "type":"Retail Goods"
        }
    ],
    "sg:phone":"+44 1908 694630",
    "sg:postcode":"MK13 8PZ",
    "sg:province":"Buckinghamshire",
    "sg:tags":[
        "wall",
        "wallpaper",
        "covering"
    ],
    "wof:name":"Homestyle By Fads",
    "wof:placetype":"venue"
},
  "geometry": {"coordinates":[-0.777117,52.042313],"type":"Point"}
}