{
  "type": "Feature",
  "properties": {
    "addr:full":"Dartmoor View, Mary Street Newton Abbot Devon TQ13 9HQ",
    "addr:postcode":"tq13 9hq",
    "addr:street":"Dartmoor View Mary Street",
    "iso:country":"GB",
    "sg:address":"Dartmoor View, Mary Street",
    "sg:city":"Newton Abbot",
    "sg:classifiers":[
        {
            "category":"Wholesale",
            "subcategory":"Books, Periodicals, & Newspapers",
            "type":"Manufacturing & Wholesale Goods"
        }
    ],
    "sg:postcode":"TQ13 9HQ",
    "sg:province":"Devon",
    "sg:tags":[
        "publishing"
    ],
    "wof:name":"Flyfishers Classic Library",
    "wof:placetype":"venue"
},
  "geometry": {"coordinates":[-3.6813690662,50.5845451355],"type":"Point"}
}