{
  "type": "Feature",
  "properties": {
    "iso:country":"GB",
    "sg:address":"20 Liverpool Gdns",
    "sg:city":"Worthing",
    "sg:classifiers":[
        {
            "category":"Banks & Credit Unions",
            "subcategory":"Financial Services",
            "type":"Services"
        }
    ],
    "sg:postcode":"BN11 1RY",
    "sg:province":"West Sussex",
    "sg:tags":[
        "adviser"
    ],
    "wof:name":"Lynch Hall Financial Advisers",
    "wof:placetype":"venue"
},
  "geometry": {"coordinates":[-0.3715310097,50.8129806519],"type":"Point"}
}