{
  "type": "Feature",
  "properties": {
    "addr:full":"Suma Farm House, Ockham Lane, Hatchford Cobham Surrey KT11 1LP",
    "addr:postcode":"kt11 1lp",
    "addr:street":"Ockham Lane",
    "iso:country":"GB",
    "sg:address":"Suma Farm House, Ockham Lane, Hatchford",
    "sg:city":"Cobham",
    "sg:classifiers":[
        {
            "category":"Transit Center",
            "subcategory":"Passenger",
            "type":"Transportation"
        },
        {
            "category":"Retail",
            "subcategory":"Pet Boarding",
            "type":"Services"
        }
    ],
    "sg:phone":"+44 1932 862210",
    "sg:postcode":"KT11 1LP",
    "sg:province":"Surrey",
    "sg:tags":[
        "kennel",
        "catteries"
    ],
    "wof:name":"Suma Farm Cat Hotel",
    "wof:placetype":"venue"
},
  "geometry": {"coordinates":[-0.4217739999,51.31432724],"type":"Point"}
}