{
  "type": "Feature",
  "properties": {
    "iso:country":"GB",
    "sg:address":"4 Wells St",
    "sg:city":"Chelmsford",
    "sg:classifiers":[
        {
            "category":"Home & Garden",
            "subcategory":"Building Materials",
            "type":"Retail Goods"
        }
    ],
    "sg:phone":"+44 1245 352420",
    "sg:postcode":"CM1 1HZ",
    "sg:province":"Essex",
    "sg:tags":[
        "dust",
        "extraction",
        "system"
    ],
    "wof:name":"Essex Environmental Services",
    "wof:placetype":"venue"
},
  "geometry": {"coordinates":[0.467165,51.736713],"type":"Point"}
}