{
  "type": "Feature",
  "properties": {
    "addr:full":"57 Beardmore Way Clydebank East Dunbartonshire G81 4HT",
    "addr:housenumber":"57",
    "addr:postcode":"g81 4ht",
    "addr:street":"Beardmore Way",
    "iso:country":"GB",
    "sg:address":"57 Beardmore Way",
    "sg:city":"Clydebank",
    "sg:classifiers":[
        {
            "category":"Professional",
            "subcategory":"Engineering",
            "type":"Services"
        }
    ],
    "sg:phone":"+44 141 941 1414",
    "sg:postcode":"G81 4HT",
    "sg:province":"East Dunbartonshire",
    "sg:tags":[
        "contractor",
        "electrical",
        "engineer"
    ],
    "wof:name":"Milngavie Controls (East) Ltd.",
    "wof:placetype":"venue"
},
  "geometry": {"coordinates":[-4.434398,55.9076],"type":"Point"}
}