{
  "type": "Feature",
  "properties": {
    "iso:country":"GB",
    "sg:address":"4 Croffets",
    "sg:city":"Tadworth",
    "sg:classifiers":[
        {
            "category":"Banks & Credit Unions",
            "subcategory":"Financial Services",
            "type":"Services"
        }
    ],
    "sg:postcode":"KT20 5TX",
    "sg:province":"Surrey",
    "sg:tags":[
        "adviser"
    ],
    "wof:name":"Mair,James,",
    "wof:placetype":"venue"
},
  "geometry": {"coordinates":[-0.226905,51.296448],"type":"Point"}
}