{
  "type": "Feature",
  "properties": {
    "iso:country":"GB",
    "sg:address":"Green Lane, Burnham",
    "sg:city":"Slough",
    "sg:classifiers":[
        {
            "category":"Sports & Exercise",
            "subcategory":"Golf",
            "type":"Entertainment"
        }
    ],
    "sg:phone":"+44 1628 661448",
    "sg:postcode":"SL1 8EG",
    "sg:province":"Berkshire",
    "sg:tags":[
        "club",
        "course"
    ],
    "wof:name":"THE BURNHAM BEECHES GOLF CLUB LTD",
    "wof:placetype":"venue"
},
  "geometry": {"coordinates":[-0.661145,51.536346],"type":"Point"}
}