{
  "type": "Feature",
  "properties": {
    "addr:full":"425 Bromley Rd Bromley Kent BR1 4PJ",
    "addr:housenumber":"425",
    "addr:postcode":"br1 4pj",
    "addr:street":"Bromley Rd",
    "iso:country":"GB",
    "sg:address":"425 Bromley Rd",
    "sg:city":"Bromley",
    "sg:classifiers":[
        {
            "category":"Shopping",
            "subcategory":"News",
            "type":"Retail Goods"
        }
    ],
    "sg:postcode":"BR1 4PJ",
    "sg:province":"Kent",
    "sg:tags":[
        "newsagent"
    ],
    "wof:name":"Jirasanghe,Raj,",
    "wof:placetype":"venue"
},
  "geometry": {"coordinates":[-0.005877,51.425987],"type":"Point"}
}