{
  "type": "Feature",
  "properties": {
    "addr:full":"Unit 4 Arden Park, Old Wolverton Road, Old Wolverton Milton Keynes Buckinghamshire MK12 5RH",
    "addr:housenumber":"unit 4 arden",
    "addr:postcode":"mk12 5rh",
    "addr:street":"Park Old Wolverton Road Old",
    "iso:country":"GB",
    "sg:address":"Unit 4 Arden Park, Old Wolverton Road, Old Wolverton",
    "sg:city":"Milton Keynes",
    "sg:classifiers":[
        {
            "category":"Retail",
            "subcategory":"Auto Repair",
            "type":"Services"
        }
    ],
    "sg:phone":"+44 1908 226071",
    "sg:postcode":"MK12 5RH",
    "sg:province":"Buckinghamshire",
    "sg:tags":[
        "modification",
        "garage"
    ],
    "wof:name":"D & K Autos",
    "wof:placetype":"venue"
},
  "geometry": {"coordinates":[-0.8149340153,52.0664634705],"type":"Point"}
}