{
  "type": "Feature",
  "properties": {
    "iso:country":"GB",
    "sg:address":"24 Clent Road",
    "sg:city":"Stourbridge",
    "sg:classifiers":[
        {
            "category":"Building & Trades",
            "subcategory":"Construction",
            "type":"Services"
        }
    ],
    "sg:phone":"+44 1384 440091",
    "sg:postcode":"DY8 4LN",
    "sg:province":"Staffordshire",
    "sg:tags":[
        "decorator",
        "painter"
    ],
    "wof:name":"Prime Decorators",
    "wof:placetype":"venue"
},
  "geometry": {"coordinates":[-2.143892,52.461761],"type":"Point"}
}