{
  "type": "Feature",
  "properties": {
    "addr:full":"Dockside Road London Greater London E16 2QT",
    "addr:postcode":"e16 2qt",
    "addr:street":"Dockside Road",
    "iso:country":"GB",
    "sg:address":"Dockside Road",
    "sg:city":"London",
    "sg:classifiers":[
        {
            "category":"Organizations",
            "subcategory":"Non-profit Organization",
            "type":"Services"
        }
    ],
    "sg:phone":"+44 20 7511 6622",
    "sg:postcode":"E16 2QT",
    "sg:province":"Greater London",
    "sg:tags":[
        "organisation",
        "voluntary",
        "charity"
    ],
    "wof:name":"Royal Albert Dock Trust",
    "wof:placetype":"venue"
},
  "geometry": {"coordinates":[0.043268,51.508259],"type":"Point"}
}