{
  "type": "Feature",
  "properties": {
    "addr:full":"Glebe Close, South Normanton Alfreton Derbyshire DE55 2JN",
    "addr:postcode":"de55 2jn",
    "addr:street":"Glebe Close",
    "iso:country":"GB",
    "sg:address":"Glebe Close, South Normanton",
    "sg:city":"Alfreton",
    "sg:classifiers":[
        {
            "category":"Organizations",
            "subcategory":"Community Association",
            "type":"Services"
        }
    ],
    "sg:phone":"+44 1773 580846",
    "sg:postcode":"DE55 2JN",
    "sg:province":"Derbyshire",
    "sg:tags":[
        "co-operatives",
        "society",
        "housing",
        "trust"
    ],
    "wof:name":"Northern Counties Housing Association Ltd",
    "wof:placetype":"venue"
},
  "geometry": {"coordinates":[-1.3391619921,53.1018371582],"type":"Point"}
}