{
  "type": "Feature",
  "properties": {
    "iso:country":"GB",
    "sg:address":"193-195 North Road",
    "sg:city":"Preston",
    "sg:classifiers":[
        {
            "category":"Organizations",
            "subcategory":"Membership Organization",
            "type":"Services"
        }
    ],
    "sg:phone":"+44 1772 251025",
    "sg:postcode":"PR1 1YQ",
    "sg:province":"Lancashire",
    "sg:tags":[
        "club"
    ],
    "wof:name":"New Meadow Street Labour & Social Club & Institute Ltd.",
    "wof:placetype":"venue"
},
  "geometry": {"coordinates":[-2.6989688873,53.7641487122],"type":"Point"}
}