{
  "type": "Feature",
  "properties": {
    "addr:full":"35-39 Old Street London Greater London EC1V 9HX",
    "addr:housenumber":"35-39",
    "addr:postcode":"ec1v 9hx",
    "addr:street":"Old Street",
    "iso:country":"GB",
    "sg:address":"35-39 Old Street",
    "sg:city":"London",
    "sg:classifiers":[
        {
            "category":"Professional",
            "subcategory":"Art Services",
            "type":"Services"
        }
    ],
    "sg:phone":"+44 20 7490 4992",
    "sg:postcode":"EC1V 9HX",
    "sg:province":"Greater London",
    "sg:tags":[
        "graphic",
        "designer"
    ],
    "wof:name":"The Saward Roberts Studio",
    "wof:placetype":"venue"
},
  "geometry": {"coordinates":[-0.0974000022,51.523853302],"type":"Point"}
}