{
  "type": "Feature",
  "properties": {
    "iso:country":"GB",
    "sg:address":"Ardura, Duncraggan Road",
    "sg:city":"Oban",
    "sg:classifiers":[
        {
            "category":"Travel",
            "subcategory":"Hotels & Motels",
            "type":"Entertainment"
        }
    ],
    "sg:phone":"+44 1631 562380",
    "sg:postcode":"PA34 5DU",
    "sg:province":"Argyll and Bute",
    "sg:tags":[
        "house",
        "guest"
    ],
    "wof:name":"Ardura",
    "wof:placetype":"venue"
},
  "geometry": {"coordinates":[-5.468227,56.418259],"type":"Point"}
}