{
  "type": "Feature",
  "properties": {
    "addr:full":"137 Halifax Road Todmorden Lancashire OL14 5BE",
    "addr:housenumber":"137",
    "addr:postcode":"ol14 5be",
    "addr:street":"Halifax Road",
    "iso:country":"GB",
    "sg:address":"137 Halifax Road",
    "sg:city":"Todmorden",
    "sg:classifiers":[
        {
            "category":"Government",
            "subcategory":"Post Office",
            "type":"Public Place"
        }
    ],
    "sg:phone":"+44 1706 813635",
    "sg:postcode":"OL14 5BE",
    "sg:province":"Lancashire",
    "wof:name":"Roomfield Post Office",
    "wof:placetype":"venue"
},
  "geometry": {"coordinates":[-2.0896480083,53.7146034241],"type":"Point"}
}