{
  "type": "Feature",
  "properties": {
    "addr:full":"Stonecastle Farm, Whetsted Road, Five Oak Green Tonbridge Kent TN12 6SD",
    "addr:postcode":"tn12 6sd",
    "addr:street":"Whetsted Road",
    "iso:country":"GB",
    "sg:address":"Stonecastle Farm, Whetsted Road, Five Oak Green",
    "sg:city":"Tonbridge",
    "sg:classifiers":[
        {
            "category":"Home & Garden",
            "subcategory":"Garden Supply",
            "type":"Retail Goods"
        }
    ],
    "sg:phone":"+44 1892 832671",
    "sg:postcode":"TN12 6SD",
    "sg:province":"Kent",
    "sg:tags":[
        "sand",
        "gravel"
    ],
    "wof:name":"Lafarge Aggregates Ltd.",
    "wof:placetype":"venue"
},
  "geometry": {"coordinates":[0.3571450114,51.1834793091],"type":"Point"}
}