{
  "type": "Feature",
  "properties": {
    "iso:country":"GB",
    "sg:address":"30 King Street",
    "sg:city":"Luton",
    "sg:classifiers":[
        {
            "category":"Health Services",
            "subcategory":"Dentist",
            "type":"Services"
        }
    ],
    "sg:phone":"+44 1582 405706",
    "sg:postcode":"LU1 2DP",
    "sg:province":"Bedfordshire",
    "wof:name":"T W Coulter",
    "wof:placetype":"venue"
},
  "geometry": {"coordinates":[-0.418125,51.878082],"type":"Point"}
}