{
  "type": "Feature",
  "properties": {
    "iso:country":"GB",
    "sg:address":"4 Business Centre West, Avenue 1",
    "sg:city":"Letchworth",
    "sg:classifiers":[
        {
            "category":"Professional",
            "subcategory":"Business Services",
            "type":"Services"
        }
    ],
    "sg:phone":"+44 1462 482509",
    "sg:postcode":"SG6 2HB",
    "sg:province":"Hertfordshire",
    "sg:tags":[
        "import",
        "export",
        "agent"
    ],
    "wof:name":"Ragdale Industries Ltd.",
    "wof:placetype":"venue"
},
  "geometry": {"coordinates":[-0.207936,51.981407],"type":"Point"}
}