{
  "type": "Feature",
  "properties": {
    "iso:country":"GB",
    "sg:address":"7 Wellington Esplanade",
    "sg:city":"Lowestoft",
    "sg:classifiers":[
        {
            "category":"Travel",
            "subcategory":"Hotels & Motels",
            "type":"Entertainment"
        }
    ],
    "sg:phone":"+44 1502 565037",
    "sg:postcode":"NR33 0QQ",
    "sg:province":"Suffolk",
    "sg:tags":[
        "house",
        "guest"
    ],
    "wof:name":"Frank Nolan",
    "wof:placetype":"venue"
},
  "geometry": {"coordinates":[1.745344,52.467224],"type":"Point"}
}