{
  "type": "Feature",
  "properties": {
    "iso:country":"GB",
    "sg:address":"Fossway",
    "sg:city":"Newcastle-upon-tyne",
    "sg:classifiers":[
        {
            "category":"Bars & Pubs",
            "type":"Food & Drink"
        },
        {
            "category":"Community Center",
            "subcategory":"Social",
            "type":"Public Place"
        }
    ],
    "sg:phone":"+44 191 276 9000",
    "sg:postcode":"NE6 4AN",
    "sg:province":"Tyne and Wear",
    "sg:tags":[
        "pubs",
        "house",
        "inn",
        "activity"
    ],
    "wof:name":"Fosse Hotel",
    "wof:placetype":"venue"
},
  "geometry": {"coordinates":[-1.543709,54.984097],"type":"Point"}
}