{
  "type": "Feature",
  "properties": {
    "iso:country":"GB",
    "sg:address":"79-81 Norwich Road",
    "sg:city":"Ipswich",
    "sg:classifiers":[
        {
            "category":"Travel",
            "subcategory":"Travel Agent",
            "type":"Entertainment"
        }
    ],
    "sg:phone":"+44 1473 214305",
    "sg:postcode":"IP1 2PR",
    "sg:province":"Suffolk",
    "sg:tags":[
        "agency",
        "activity"
    ],
    "wof:name":"Eastravel Ltd.",
    "wof:placetype":"venue"
},
  "geometry": {"coordinates":[1.142944,52.061661],"type":"Point"}
}