{
  "type": "Feature",
  "properties": {
    "addr:full":"53 Dale Street London Greater London W4 2BY",
    "addr:housenumber":"53",
    "addr:postcode":"w4 2by",
    "addr:street":"Dale Street",
    "iso:country":"GB",
    "sg:address":"53 Dale Street",
    "sg:city":"London",
    "sg:classifiers":[
        {
            "category":"Social Services",
            "subcategory":"Job Training",
            "type":"Services"
        }
    ],
    "sg:postcode":"W4 2BY",
    "sg:province":"Greater London",
    "sg:tags":[
        "translator",
        "interpreter"
    ],
    "wof:name":"Spanish & French Interpreter Services",
    "wof:placetype":"venue"
},
  "geometry": {"coordinates":[-0.2560659945,51.4898910522],"type":"Point"}
}