{
  "type": "Feature",
  "properties": {
    "addr:full":"92 Wolverhampton Street Dudley West Midlands DY1 3AP",
    "addr:housenumber":"92",
    "addr:postcode":"dy1 3ap",
    "addr:street":"Wolverhampton Street",
    "iso:country":"GB",
    "sg:address":"92 Wolverhampton Street",
    "sg:city":"Dudley",
    "sg:classifiers":[
        {
            "category":"Manufacturing",
            "subcategory":"Metals",
            "type":"Manufacturing & Wholesale Goods"
        },
        {
            "category":"Manufacturing",
            "subcategory":"Tools & Machinery",
            "type":"Manufacturing & Wholesale Goods"
        }
    ],
    "sg:phone":"+44 1384 238320",
    "sg:postcode":"DY1 3AP",
    "sg:province":"West Midlands",
    "sg:tags":[
        "foundry",
        "supply"
    ],
    "wof:name":"Midland Shell Cores",
    "wof:placetype":"venue"
},
  "geometry": {"coordinates":[-2.0945429802,52.5126686096],"type":"Point"}
}