{
  "type": "Feature",
  "properties": {
    "addr:full":"Longrood Road Rugby Warwickshire CV22 7RE",
    "addr:postcode":"cv22 7re",
    "addr:street":"Longrood Road",
    "iso:country":"GB",
    "sg:address":"Longrood Road",
    "sg:city":"Rugby",
    "sg:classifiers":[
        {
            "category":"Education",
            "subcategory":"School",
            "type":"Public Place"
        }
    ],
    "sg:phone":"+44 1788 810518",
    "sg:postcode":"CV22 7RE",
    "sg:province":"Warwickshire",
    "sg:tags":[
        "foundation",
        "college"
    ],
    "wof:name":"Rugby High School for Girls",
    "wof:placetype":"venue"
},
  "geometry": {"coordinates":[-1.28639,52.354889],"type":"Point"}
}