{
  "type": "Feature",
  "properties": {
    "addr:full":"2 Nelson Road Birkenhead Merseyside CH42 2AL",
    "addr:housenumber":"2",
    "addr:postcode":"ch42 2al",
    "addr:street":"Nelson Road",
    "iso:country":"GB",
    "sg:address":"2 Nelson Road",
    "sg:city":"Birkenhead",
    "sg:classifiers":[
        {
            "category":"Bars & Pubs",
            "type":"Food & Drink"
        }
    ],
    "sg:phone":"+44 151 643 1233",
    "sg:postcode":"CH42 2AL",
    "sg:province":"Merseyside",
    "sg:tags":[
        "pubs",
        "inn"
    ],
    "wof:name":"Derby Arms",
    "wof:placetype":"venue"
},
  "geometry": {"coordinates":[-3.0057609081,53.3700828552],"type":"Point"}
}