{
  "type": "Feature",
  "properties": {
    "addr:full":"74 Mill Road Irvine North Ayrshire KA12 0JW",
    "addr:housenumber":"74",
    "addr:postcode":"ka12 0jw",
    "addr:street":"Mill Road",
    "iso:country":"GB",
    "sg:address":"74 Mill Road",
    "sg:city":"Irvine",
    "sg:classifiers":[
        {
            "category":"Professional",
            "subcategory":"Engineering",
            "type":"Services"
        }
    ],
    "sg:phone":"+44 1294 274429",
    "sg:postcode":"KA12 0JW",
    "sg:province":"North Ayrshire",
    "sg:tags":[
        "contractor",
        "electrical",
        "engineer"
    ],
    "wof:name":"J C Electrics",
    "wof:placetype":"venue"
},
  "geometry": {"coordinates":[-4.6507911682,55.6148948669],"type":"Point"}
}