{
  "type": "Feature",
  "properties": {
    "addr:full":"49b Lowthwaite Dr Nelson Lancashire BB9 0SU",
    "addr:housenumber":"49b",
    "addr:postcode":"bb9 0su",
    "addr:street":"Lowthwaite Dr",
    "iso:country":"GB",
    "sg:address":"49b Lowthwaite Dr",
    "sg:city":"Nelson",
    "sg:classifiers":[
        {
            "category":"Building & Trades",
            "subcategory":"Construction",
            "type":"Services"
        }
    ],
    "sg:phone":"+44 1282 611990",
    "sg:postcode":"BB9 0SU",
    "sg:province":"Lancashire",
    "sg:tags":[
        "builder"
    ],
    "wof:name":"Shaws",
    "wof:placetype":"venue"
},
  "geometry": {"coordinates":[-2.2078518867,53.8260574341],"type":"Point"}
}