{
  "type": "Feature",
  "properties": {
    "iso:country":"GB",
    "sg:address":"7 Princes Street",
    "sg:city":"Penrith",
    "sg:classifiers":[
        {
            "category":"Shopping",
            "subcategory":"Antiques",
            "type":"Retail Goods"
        }
    ],
    "sg:postcode":"CA11 7BQ",
    "sg:province":"Cumbria",
    "wof:name":"Ratchers",
    "wof:placetype":"venue"
},
  "geometry": {"coordinates":[-2.752077,54.662788],"type":"Point"}
}