{
  "type": "Feature",
  "properties": {
    "addr:full":"65 Templedene Avenue Staines Berkshire TW18 1LJ",
    "addr:housenumber":"65",
    "addr:postcode":"tw18 1lj",
    "addr:street":"Templedene Avenue",
    "iso:country":"GB",
    "sg:address":"65 Templedene Avenue",
    "sg:city":"Staines",
    "sg:classifiers":[
        {
            "category":"Building & Trades",
            "subcategory":"Cleaning & Sanitation",
            "type":"Services"
        }
    ],
    "sg:phone":"+44 1784 453913",
    "sg:postcode":"TW18 1LJ",
    "sg:province":"Berkshire",
    "sg:tags":[
        "commercial"
    ],
    "wof:name":"M C R",
    "wof:placetype":"venue"
},
  "geometry": {"coordinates":[-0.4905210137,51.4239845276],"type":"Point"}
}