{
  "type": "Feature",
  "properties": {
    "addr:full":"426 Stenson Rd Derby Derbyshire DE23 7LH",
    "addr:housenumber":"426",
    "addr:postcode":"de23 7lh",
    "addr:street":"Stenson Rd",
    "iso:country":"GB",
    "sg:address":"426 Stenson Rd",
    "sg:city":"Derby",
    "sg:classifiers":[
        {
            "category":"Food & Beverages",
            "subcategory":"Bakery",
            "type":"Retail Goods"
        }
    ],
    "sg:phone":"+44 1332 760625",
    "sg:postcode":"DE23 7LH",
    "sg:province":"Derbyshire",
    "sg:tags":[
        "baker"
    ],
    "wof:name":"Cake Shop The",
    "wof:placetype":"venue"
},
  "geometry": {"coordinates":[-1.498788,52.888115],"type":"Point"}
}