{
  "type": "Feature",
  "properties": {
    "addr:full":"8 Higher Market Street, Farnworth Bolton Lancashire BL4 9AJ",
    "addr:housenumber":"8",
    "addr:postcode":"bl4 9aj",
    "addr:street":"Higher Market Street",
    "iso:country":"GB",
    "sg:address":"8 Higher Market Street, Farnworth",
    "sg:city":"Bolton",
    "sg:classifiers":[
        {
            "category":"Sports & Exercise",
            "subcategory":"Sports Center",
            "type":"Entertainment"
        }
    ],
    "sg:phone":"+44 1204 573287",
    "sg:postcode":"BL4 9AJ",
    "sg:province":"Lancashire",
    "sg:tags":[
        "shop",
        "good"
    ],
    "wof:name":"Salter Sports",
    "wof:placetype":"venue"
},
  "geometry": {"coordinates":[-2.392104,53.546799],"type":"Point"}
}