{
  "type": "Feature",
  "properties": {
    "iso:country":"GB",
    "sg:address":"140-142 Wantz Road",
    "sg:city":"Maldon",
    "sg:classifiers":[
        {
            "category":"Shopping",
            "subcategory":"Bicycles & Sporting Goods",
            "type":"Retail Goods"
        }
    ],
    "sg:postcode":"CM9 5DG",
    "sg:province":"Essex",
    "sg:tags":[
        "shop",
        "cycle",
        "accessory"
    ],
    "wof:name":"BLACKWATER CYCLES",
    "wof:placetype":"venue"
},
  "geometry": {"coordinates":[0.682016,51.726692],"type":"Point"}
}