{
  "type": "Feature",
  "properties": {
    "addr:full":"110 The Border, Telford Centre Telford Shropshire TF3 4AE",
    "addr:housenumber":"110",
    "addr:postcode":"tf3 4ae",
    "addr:street":"The",
    "iso:country":"GB",
    "sg:address":"110 The Border, Telford Centre",
    "sg:city":"Telford",
    "sg:classifiers":[
        {
            "category":"Shopping",
            "subcategory":"Clothing, Apparel, & Fashions",
            "type":"Retail Goods"
        }
    ],
    "sg:phone":"+44 1952 293482",
    "sg:postcode":"TF3 4AE",
    "sg:province":"Shropshire",
    "sg:tags":[
        "shop"
    ],
    "wof:name":"New Look",
    "wof:placetype":"venue"
},
  "geometry": {"coordinates":[-2.44176507,52.6766624451],"type":"Point"}
}