{
  "type": "Feature",
  "properties": {
    "addr:full":"50 Erleigh Road Reading Berkshire RG1 5NA",
    "addr:housenumber":"50",
    "addr:postcode":"rg1 5na",
    "addr:street":"Erleigh Road",
    "iso:country":"GB",
    "sg:address":"50 Erleigh Road",
    "sg:city":"Reading",
    "sg:classifiers":[
        {
            "category":"Fast Food",
            "type":"Food & Drink"
        }
    ],
    "sg:postcode":"RG1 5NA",
    "sg:province":"Berkshire",
    "sg:tags":[
        "away",
        "take"
    ],
    "wof:name":"Gold Coin",
    "wof:placetype":"venue"
},
  "geometry": {"coordinates":[-0.949818,51.449543],"type":"Point"}
}