{
  "type": "Feature",
  "properties": {
    "iso:country":"GB",
    "sg:address":"19-23 Shubbery Road, Streatham",
    "sg:city":"London",
    "sg:classifiers":[
        {
            "category":"Professional",
            "subcategory":"Lawyer & Legal Services",
            "type":"Services"
        }
    ],
    "sg:phone":"+44 20 8769 1113",
    "sg:postcode":"SW16 2AS",
    "sg:province":"Greater London",
    "sg:tags":[
        "solicitor"
    ],
    "wof:name":"McMillan Williams",
    "wof:placetype":"venue"
},
  "geometry": {"coordinates":[-0.1286559999,51.4302558899],"type":"Point"}
}