{
  "type": "Feature",
  "properties": {
    "addr:full":"7 Ayres Yard, Station Road Wallingford Oxfordshire OX10 0JZ",
    "addr:housenumber":"7",
    "addr:postcode":"ox10 0jz",
    "addr:street":"Ayres Yard Station Road",
    "iso:country":"GB",
    "sg:address":"7 Ayres Yard, Station Road",
    "sg:city":"Wallingford",
    "sg:classifiers":[
        {
            "category":"Retail",
            "subcategory":"Auto Repair",
            "type":"Services"
        }
    ],
    "sg:phone":"+44 1491 826717",
    "sg:postcode":"OX10 0JZ",
    "sg:province":"Oxfordshire",
    "sg:tags":[
        "modification",
        "garage"
    ],
    "wof:name":"Auto Services J S",
    "wof:placetype":"venue"
},
  "geometry": {"coordinates":[-1.125623,51.60091],"type":"Point"}
}