{
  "type": "Feature",
  "properties": {
    "iso:country":"GB",
    "sg:address":"337 Leysdown Road, Bayview",
    "sg:city":"Sheerness",
    "sg:classifiers":[
        {
            "category":"Shopping",
            "subcategory":"Clothing, Apparel, & Fashions",
            "type":"Retail Goods"
        }
    ],
    "sg:postcode":"ME12 4AR",
    "sg:province":"Kent",
    "sg:tags":[
        "workwear",
        "protective"
    ],
    "wof:name":"The Orna-Met Co.",
    "wof:placetype":"venue"
},
  "geometry": {"coordinates":[0.8956159949,51.3962974548],"type":"Point"}
}