{
  "type": "Feature",
  "properties": {
    "addr:full":"232 Court Street Tonypandy Rhondda, Cynon, Taff CF40 2RF",
    "addr:housenumber":"232",
    "addr:postcode":"cf40 2rf",
    "addr:street":"Court Street;Cynon Taff",
    "iso:country":"GB",
    "sg:address":"232 Court Street",
    "sg:city":"Tonypandy",
    "sg:classifiers":[
        {
            "category":"Professional",
            "subcategory":"Employment Agencies",
            "type":"Services"
        }
    ],
    "sg:phone":"+44 1443 432555",
    "sg:postcode":"CF40 2RF",
    "sg:province":"Rhondda, Cynon, Taff",
    "sg:tags":[
        "career",
        "guidance"
    ],
    "wof:name":"Mid Glamorgan Careers Ltd.",
    "wof:placetype":"venue"
},
  "geometry": {"coordinates":[-3.465764,51.625137],"type":"Point"}
}