{
  "type": "Feature",
  "properties": {
    "addr:full":"27 Neville Road Croydon Surrey CR0 2DS",
    "addr:housenumber":"27",
    "addr:postcode":"cr0 2ds",
    "addr:street":"Neville Road",
    "iso:country":"GB",
    "sg:address":"27 Neville Road",
    "sg:city":"Croydon",
    "sg:classifiers":[
        {
            "category":"Retail",
            "subcategory":"Auto Repair",
            "type":"Services"
        }
    ],
    "sg:postcode":"CR0 2DS",
    "sg:province":"Surrey",
    "sg:tags":[
        "modification",
        "garage"
    ],
    "wof:name":"R B Motor Services",
    "wof:placetype":"venue"
},
  "geometry": {"coordinates":[-0.0911310017,51.3846931458],"type":"Point"}
}