{
  "type": "Feature",
  "properties": {
    "addr:full":"The Yard, Glencoe Shrewsbury Shropshire SY4 3AZ",
    "addr:postcode":"sy4 3az",
    "addr:street":"Glencoe",
    "iso:country":"GB",
    "sg:address":"The Yard, Glencoe",
    "sg:city":"Shrewsbury",
    "sg:classifiers":[
        {
            "category":"Freight",
            "type":"Transportation"
        }
    ],
    "sg:phone":"+44 1939 291132",
    "sg:postcode":"SY4 3AZ",
    "sg:province":"Shropshire",
    "sg:tags":[
        "haulage",
        "road"
    ],
    "wof:name":"Cole's Transport",
    "wof:placetype":"venue"
},
  "geometry": {"coordinates":[-2.814150095,52.7717018127],"type":"Point"}
}