{
  "type": "Feature",
  "properties": {
    "iso:country":"GB",
    "sg:address":"60 Lanwood Road, Graigwen",
    "sg:city":"Pontypridd",
    "sg:classifiers":[
        {
            "category":"Retail",
            "subcategory":"Driving School",
            "type":"Services"
        }
    ],
    "sg:phone":"+44 1443 493571",
    "sg:postcode":"CF37 2EP",
    "sg:province":"Caerphilly",
    "wof:name":"Henderson School of Motoring",
    "wof:placetype":"venue"
},
  "geometry": {"coordinates":[-3.344324,51.608421],"type":"Point"}
}