{
  "type": "Feature",
  "properties": {
    "addr:full":"135 Church Street, Horwich Bolton Lancashire BL6 7BR",
    "addr:housenumber":"135",
    "addr:postcode":"bl6 7br",
    "addr:street":"Church Street",
    "iso:country":"GB",
    "sg:address":"135 Church Street, Horwich",
    "sg:city":"Bolton",
    "sg:classifiers":[
        {
            "category":"Building & Trades",
            "subcategory":"Construction",
            "type":"Services"
        }
    ],
    "sg:postcode":"BL6 7BR",
    "sg:province":"Lancashire",
    "sg:tags":[
        "builder"
    ],
    "wof:name":"Loft Maintenance Services",
    "wof:placetype":"venue"
},
  "geometry": {"coordinates":[-2.5452001095,53.5994033813],"type":"Point"}
}