{
  "type": "Feature",
  "properties": {
    "addr:full":"84 Berkeley St Glasgow Glasgow City G3 7DS",
    "addr:housenumber":"84",
    "addr:postcode":"g3 7ds",
    "addr:street":"Berkeley St",
    "iso:country":"GB",
    "sg:address":"84 Berkeley St",
    "sg:city":"Glasgow",
    "sg:classifiers":[
        {
            "category":"Building & Trades",
            "subcategory":"Construction",
            "type":"Services"
        }
    ],
    "sg:phone":"+44 141 221 1547",
    "sg:postcode":"G3 7DS",
    "sg:province":"Glasgow City",
    "sg:tags":[
        "contractor"
    ],
    "wof:name":"Kuaerner Construction (Regions) Ltd",
    "wof:placetype":"venue"
},
  "geometry": {"coordinates":[-4.275865078,55.8654136658],"type":"Point"}
}