{
  "type": "Feature",
  "properties": {
    "iso:country":"GB",
    "sg:address":"Park Drive",
    "sg:city":"Maldon",
    "sg:classifiers":[
        {
            "category":"Community Center",
            "type":"Public Place"
        }
    ],
    "sg:phone":"+44 1621 851898",
    "sg:postcode":"CM9 5UR",
    "sg:province":"Essex",
    "sg:tags":[
        "recreation",
        "leisure",
        "centre"
    ],
    "wof:name":"Blackwater Leisure Centre",
    "wof:placetype":"venue"
},
  "geometry": {"coordinates":[0.68704,51.72646],"type":"Point"}
}