{
  "type": "Feature",
  "properties": {
    "addr:full":"109 West Street Crewe Cheshire CW1 3HF",
    "addr:housenumber":"109",
    "addr:postcode":"cw1 3hf",
    "addr:street":"West Street",
    "iso:country":"GB",
    "sg:address":"109 West Street",
    "sg:city":"Crewe",
    "sg:classifiers":[
        {
            "category":"Home & Garden",
            "subcategory":"Home Furnishings",
            "type":"Retail Goods"
        },
        {
            "category":"Wholesale",
            "subcategory":"Home Furnishings",
            "type":"Manufacturing & Wholesale Goods"
        }
    ],
    "sg:phone":"+44 1270 256491",
    "sg:postcode":"CW1 3HF",
    "sg:province":"Cheshire",
    "sg:tags":[
        "blind",
        "manufacture",
        "fitting",
        "curtain"
    ],
    "wof:name":"Best for the West",
    "wof:placetype":"venue"
},
  "geometry": {"coordinates":[-2.452376,53.101856],"type":"Point"}
}