{
  "type": "Feature",
  "properties": {
    "addr:full":"9 Verney Close, Lighthorne Warwick Warwickshire CV35 0AZ",
    "addr:housenumber":"9",
    "addr:postcode":"cv35 0az",
    "addr:street":"Verney Close Lighthorne",
    "iso:country":"GB",
    "sg:address":"9 Verney Close, Lighthorne",
    "sg:city":"Warwick",
    "sg:classifiers":[
        {
            "category":"Building & Trades",
            "subcategory":"Plumbing",
            "type":"Services"
        }
    ],
    "sg:phone":"+44 1926 651943",
    "sg:postcode":"CV35 0AZ",
    "sg:province":"Warwickshire",
    "sg:tags":[
        "heating"
    ],
    "wof:name":"Timothy C Sweetman",
    "wof:placetype":"venue"
},
  "geometry": {"coordinates":[-1.504750967,52.1984786987],"type":"Point"}
}