{
  "type": "Feature",
  "properties": {
    "addr:full":"18 West Avenue Clacton-on-sea Essex CO15 1QT",
    "addr:housenumber":"18",
    "addr:postcode":"co15 1qt",
    "addr:street":"West Avenue",
    "iso:country":"GB",
    "sg:address":"18 West Avenue",
    "sg:city":"Clacton-on-sea",
    "sg:classifiers":[
        {
            "category":"Shopping",
            "subcategory":"Thrift Store",
            "type":"Retail Goods"
        }
    ],
    "sg:phone":"+44 1255 475016",
    "sg:postcode":"CO15 1QT",
    "sg:province":"Essex",
    "sg:tags":[
        "shop",
        "charity"
    ],
    "wof:name":"Imperial Cancer Research Fund",
    "wof:placetype":"venue"
},
  "geometry": {"coordinates":[1.151055,51.788548],"type":"Point"}
}