{
  "type": "Feature",
  "properties": {
    "addr:full":"133 Ralph Road, Shirley Solihull West Midlands B90 3JZ",
    "addr:housenumber":"133",
    "addr:postcode":"b90 3jz",
    "addr:street":"Ralph Road",
    "iso:country":"GB",
    "sg:address":"133 Ralph Road, Shirley",
    "sg:city":"Solihull",
    "sg:classifiers":[
        {
            "category":"Home & Garden",
            "subcategory":"Household Appliances",
            "type":"Retail Goods"
        }
    ],
    "sg:phone":"+44 121 705 5222",
    "sg:postcode":"B90 3JZ",
    "sg:province":"West Midlands",
    "sg:tags":[
        "electrical"
    ],
    "wof:name":"Solihull Domestic Services",
    "wof:placetype":"venue"
},
  "geometry": {"coordinates":[-1.8193910122,52.4158210754],"type":"Point"}
}