{
  "type": "Feature",
  "properties": {
    "addr:full":"Southbank Ho, Black Prince Rd Southwark Greater London SE1 7SJ",
    "addr:postcode":"se1 7sj",
    "addr:street":"Black Prince Rd",
    "iso:country":"GB",
    "sg:address":"Southbank Ho, Black Prince Rd",
    "sg:city":"Southwark",
    "sg:classifiers":[
        {
            "category":"Professional",
            "subcategory":"Management & Consulting",
            "type":"Services"
        }
    ],
    "sg:phone":"+44 20 7582 5708",
    "sg:postcode":"SE1 7SJ",
    "sg:province":"Greater London",
    "sg:tags":[
        "consultant",
        "safety"
    ],
    "wof:name":"Ark Health & Safety",
    "wof:placetype":"venue"
},
  "geometry": {"coordinates":[-0.11987,51.492168],"type":"Point"}
}