{
  "type": "Feature",
  "properties": {
    "addr:full":"89 Narborough Road Leicester Leicestershire LE3 0PA",
    "addr:housenumber":"89",
    "addr:postcode":"le3 0pa",
    "addr:street":"Narborough Road",
    "iso:country":"GB",
    "sg:address":"89 Narborough Road",
    "sg:city":"Leicester",
    "sg:classifiers":[
        {
            "category":"Shopping",
            "subcategory":"Clothing, Apparel, & Fashions",
            "type":"Retail Goods"
        }
    ],
    "sg:postcode":"LE3 0PA",
    "sg:province":"Leicestershire",
    "sg:tags":[
        "clothing"
    ],
    "wof:name":"Superdiscount",
    "wof:placetype":"venue"
},
  "geometry": {"coordinates":[-1.150004,52.627808],"type":"Point"}
}