{
  "type": "Feature",
  "properties": {
    "addr:full":"2 Walnut Drive Pontefract North Yorkshire WF8 4NR",
    "addr:housenumber":"2",
    "addr:postcode":"wf8 4nr",
    "addr:street":"Walnut Drive",
    "iso:country":"GB",
    "sg:address":"2 Walnut Drive",
    "sg:city":"Pontefract",
    "sg:classifiers":[
        {
            "category":"Professional",
            "type":"Services"
        },
        {
            "category":"Professional",
            "subcategory":"Employment Agencies",
            "type":"Services"
        }
    ],
    "sg:phone":"+44 1977 791655",
    "sg:postcode":"WF8 4NR",
    "sg:province":"North Yorkshire",
    "sg:tags":[
        "entertainer",
        "entertainment"
    ],
    "wof:name":"Globe Entertainments",
    "wof:placetype":"venue"
},
  "geometry": {"coordinates":[-1.3194270134,53.6795578003],"type":"Point"}
}