{
  "type": "Feature",
  "properties": {
    "iso:country":"GB",
    "sg:address":"8 Court Street",
    "sg:city":"Faversham",
    "sg:classifiers":[
        {
            "category":"Cinema",
            "subcategory":"Movie Rental",
            "type":"Entertainment"
        }
    ],
    "sg:phone":"+44 1795 531547",
    "sg:postcode":"ME13 7AN",
    "sg:province":"Kent",
    "sg:tags":[
        "video",
        "library"
    ],
    "wof:name":"Videodome",
    "wof:placetype":"venue"
},
  "geometry": {"coordinates":[0.891602,51.316441],"type":"Point"}
}