{
  "type": "Feature",
  "properties": {
    "addr:full":"Sheethanger La Hemel Hempstead Hertfordshire HP3 0BG",
    "addr:postcode":"hp3 0bg",
    "addr:street":"La Hemel Hempstead",
    "iso:country":"GB",
    "sg:address":"Sheethanger La",
    "sg:city":"Hemel Hempstead",
    "sg:classifiers":[
        {
            "category":"Education",
            "subcategory":"Special Training",
            "type":"Public Place"
        }
    ],
    "sg:phone":"+44 1442 268148",
    "sg:postcode":"HP3 0BG",
    "sg:province":"Hertfordshire",
    "sg:tags":[
        "product",
        "centre"
    ],
    "wof:name":"Myword Computer Training",
    "wof:placetype":"venue"
},
  "geometry": {"coordinates":[-0.491659,51.738628],"type":"Point"}
}