{
  "type": "Feature",
  "properties": {
    "iso:country":"GB",
    "sg:address":"Argyle Market, 28-33 Argyle Street",
    "sg:city":"Glasgow",
    "sg:classifiers":[
        {
            "category":"Home & Garden",
            "subcategory":"Hardware",
            "type":"Retail Goods"
        }
    ],
    "sg:postcode":"G2 8AD",
    "sg:province":"Glasgow City",
    "wof:name":"Glasgow Electrics & Hardware",
    "wof:placetype":"venue"
},
  "geometry": {"coordinates":[-4.2603797913,55.8586883545],"type":"Point"}
}