{
  "type": "Feature",
  "properties": {
    "iso:country":"GB",
    "sg:address":"Old Nazeing Rd",
    "sg:city":"Broxbourne",
    "sg:classifiers":[
        {
            "category":"Restaurant",
            "type":"Food & Drink"
        }
    ],
    "sg:phone":"+44 1992 446893",
    "sg:postcode":"EN10 6QT",
    "sg:province":"Essex",
    "wof:name":"The Crown Toby Grill",
    "wof:placetype":"venue"
},
  "geometry": {"coordinates":[-0.01252,51.742279],"type":"Point"}
}