{
  "type": "Feature",
  "properties": {
    "iso:country":"GB",
    "sg:address":"49 Copnor Road",
    "sg:city":"Portsmouth",
    "sg:classifiers":[
        {
            "category":"Building & Trades",
            "subcategory":"Construction",
            "type":"Services"
        }
    ],
    "sg:phone":"+44 23 9265 1415",
    "sg:postcode":"PO3 5AB",
    "sg:province":"Hampshire",
    "sg:tags":[
        "joiner",
        "carpenter"
    ],
    "wof:name":"W S Baxter",
    "wof:placetype":"venue"
},
  "geometry": {"coordinates":[-1.064176,50.810402],"type":"Point"}
}