{
  "type": "Feature",
  "properties": {
    "iso:country":"GB",
    "sg:address":"253 Hayes Lane",
    "sg:city":"Kenley",
    "sg:classifiers":[
        {
            "category":"Building & Trades",
            "subcategory":"Cleaning & Sanitation",
            "type":"Services"
        },
        {
            "category":"Home & Garden",
            "subcategory":"Carpets & Floor Coverings",
            "type":"Retail Goods"
        }
    ],
    "sg:phone":"+44 20 8668 9329",
    "sg:postcode":"CR8 5HN",
    "sg:province":"Surrey",
    "sg:tags":[
        "cleaner",
        "upholstery"
    ],
    "wof:name":"Ultra-Clean",
    "wof:placetype":"venue"
},
  "geometry": {"coordinates":[-0.1011430025,51.3097343445],"type":"Point"}
}