{
  "type": "Feature",
  "properties": {
    "addr:full":"66-67 Brindley Rd, Astmoor Ind Est Runcorn Cheshire WA7 1PF",
    "addr:housenumber":"66-67",
    "addr:postcode":"wa7 1pf",
    "addr:street":"Brindley Rd",
    "iso:country":"GB",
    "sg:address":"66-67 Brindley Rd, Astmoor Ind Est",
    "sg:city":"Runcorn",
    "sg:classifiers":[
        {
            "category":"Food & Beverages",
            "subcategory":"Candy",
            "type":"Retail Goods"
        }
    ],
    "sg:phone":"+44 1928 569696",
    "sg:postcode":"WA7 1PF",
    "sg:province":"Cheshire",
    "sg:tags":[
        "confectionery"
    ],
    "wof:name":"Perfect Pastries",
    "wof:placetype":"venue"
},
  "geometry": {"coordinates":[-2.6940310001,53.342792511],"type":"Point"}
}