{
  "type": "Feature",
  "properties": {
    "addr:full":"The Findhorn Foundation, The Park, Findhorn Bay Forres Moray IV36 3TZ",
    "addr:postcode":"iv36 3tz",
    "addr:street":"The;Findhorn Bay",
    "iso:country":"GB",
    "sg:address":"The Findhorn Foundation, The Park, Findhorn Bay",
    "sg:city":"Forres",
    "sg:classifiers":[
        {
            "category":"Shopping",
            "subcategory":"Books",
            "type":"Retail Goods"
        }
    ],
    "sg:phone":"+44 1309 690110",
    "sg:postcode":"IV36 3TZ",
    "sg:province":"Moray",
    "sg:tags":[
        "bookseller"
    ],
    "wof:name":"Phoenix Community Stores Ltd.",
    "wof:placetype":"venue"
},
  "geometry": {"coordinates":[-3.612209,57.66013],"type":"Point"}
}