{
  "type": "Feature",
  "properties": {
    "iso:country":"GB",
    "sg:address":"Nightingale Farm, Bentley",
    "sg:city":"Atherstone",
    "sg:classifiers":[
        {
            "category":"Farming",
            "subcategory":"Livestock Farm",
            "type":"Manufacturing & Wholesale Goods"
        }
    ],
    "sg:phone":"+44 1827 713378",
    "sg:postcode":"CV9 2JR",
    "sg:province":"Leicestershire",
    "sg:tags":[
        "others"
    ],
    "wof:name":"Derek Hollinshead",
    "wof:placetype":"venue"
},
  "geometry": {"coordinates":[-1.595529,52.549332],"type":"Point"}
}