{
  "type": "Feature",
  "properties": {
    "addr:full":"Appointments, Bridgeton Health Centre, 201 Abercromby St Glasgow Glasgow City G40 2DA",
    "addr:housenumber":"201",
    "addr:postcode":"g40 2da",
    "addr:street":"Appointments;Abercromby St",
    "iso:country":"GB",
    "sg:address":"Appointments, Bridgeton Health Centre, 201 Abercromby St",
    "sg:city":"Glasgow",
    "sg:classifiers":[
        {
            "category":"Health Services",
            "subcategory":"Doctor",
            "type":"Services"
        }
    ],
    "sg:phone":"+44 141 531 6650",
    "sg:postcode":"G40 2DA",
    "sg:province":"Glasgow City",
    "sg:tags":[
        "practitioners"
    ],
    "wof:name":"Dunn, J J",
    "wof:placetype":"venue"
},
  "geometry": {"coordinates":[-4.2276601791,55.8535003662],"type":"Point"}
}