{
  "type": "Feature",
  "properties": {
    "iso:country":"GB",
    "sg:address":"27 Wood Street",
    "sg:city":"Mansfield",
    "sg:classifiers":[
        {
            "category":"Fast Food",
            "type":"Food & Drink"
        }
    ],
    "sg:phone":"+44 1623 470016",
    "sg:postcode":"NG18 1QB",
    "sg:province":"Nottinghamshire",
    "sg:tags":[
        "away",
        "take"
    ],
    "wof:name":"Y Jones",
    "wof:placetype":"venue"
},
  "geometry": {"coordinates":[-1.203528,53.146706],"type":"Point"}
}