{
  "type": "Feature",
  "properties": {
    "iso:country":"GB",
    "sg:address":"68 The Highway, Hawarden",
    "sg:city":"Deeside",
    "sg:classifiers":[
        {
            "category":"Restaurant",
            "type":"Food & Drink"
        }
    ],
    "sg:phone":"+44 1244 536353",
    "sg:postcode":"CH5 3DH",
    "sg:province":"Flintshire",
    "wof:name":"The Brasserie",
    "wof:placetype":"venue"
},
  "geometry": {"coordinates":[-3.030471,53.18568],"type":"Point"}
}