{
  "type": "Feature",
  "properties": {
    "iso:country":"GB",
    "sg:address":"11 Harvest Way, Oakwood",
    "sg:city":"Derby",
    "sg:classifiers":[
        {
            "category":"Professional",
            "subcategory":"Art Services",
            "type":"Services"
        },
        {
            "category":"Building & Trades",
            "subcategory":"Construction",
            "type":"Services"
        }
    ],
    "sg:phone":"+44 1332 678980",
    "sg:postcode":"DE21 2XB",
    "sg:province":"Derbyshire",
    "sg:tags":[
        "glazier",
        "decorator",
        "painter"
    ],
    "wof:name":"Shaw Vic",
    "wof:placetype":"venue"
},
  "geometry": {"coordinates":[-1.417363,52.948448],"type":"Point"}
}