{
  "type": "Feature",
  "properties": {
    "addr:full":"John Storer Ho Loughborough Leicestershire LE12 5AN",
    "addr:postcode":"le12 5an",
    "addr:street":"Leicestershire",
    "iso:country":"GB",
    "sg:address":"John Storer Ho",
    "sg:city":"Loughborough",
    "sg:classifiers":[
        {
            "category":"Place Of Worship",
            "type":"Public Place"
        }
    ],
    "sg:phone":"+44 1509 880012",
    "sg:postcode":"LE12 5AN",
    "sg:province":"Leicestershire",
    "wof:name":"Society Of Friends (Quakers)",
    "wof:placetype":"venue"
},
  "geometry": {"coordinates":[-1.1307300329,52.7836990356],"type":"Point"}
}