{
  "type": "Feature",
  "properties": {
    "iso:country":"GB",
    "sg:address":"587 Barking Road, Plaistow",
    "sg:city":"London",
    "sg:classifiers":[
        {
            "category":"Professional",
            "subcategory":"Detective & Security Services",
            "type":"Services"
        }
    ],
    "sg:phone":"+44 20 8472 3431",
    "sg:postcode":"E13 9EZ",
    "sg:province":"Greater London",
    "sg:tags":[
        "locksmith"
    ],
    "wof:name":"J Reeder Lock & Safe Ltd.",
    "wof:placetype":"venue"
},
  "geometry": {"coordinates":[0.031742,51.527702],"type":"Point"}
}