{
  "type": "Feature",
  "properties": {
    "addr:full":"Stonebench House, Stonebench Gloucester Gloucestershire GL2 3NP",
    "addr:postcode":"gl2 3np",
    "addr:street":"Stonebench",
    "iso:country":"GB",
    "sg:address":"Stonebench House, Stonebench",
    "sg:city":"Gloucester",
    "sg:classifiers":[
        {
            "category":"Building & Trades",
            "subcategory":"Equipment Rental",
            "type":"Services"
        }
    ],
    "sg:postcode":"GL2 3NP",
    "sg:province":"Gloucestershire",
    "sg:tags":[
        "plant",
        "machinery"
    ],
    "wof:name":"Mike May Plant Hire",
    "wof:placetype":"venue"
},
  "geometry": {"coordinates":[-2.323509,51.832729],"type":"Point"}
}