{
  "type": "Feature",
  "properties": {
    "addr:full":"Unit 2 Pine Copse, Nine Mile Ride Wokingham Berkshire RG40 3ND",
    "addr:housenumber":"unit 2",
    "addr:postcode":"rg40 3nd",
    "addr:street":"Pine Copse Nine",
    "iso:country":"GB",
    "sg:address":"Unit 2 Pine Copse, Nine Mile Ride",
    "sg:city":"Wokingham",
    "sg:classifiers":[
        {
            "category":"Professional",
            "subcategory":"Detective & Security Services",
            "type":"Services"
        }
    ],
    "sg:phone":"+44 1344 772269",
    "sg:postcode":"RG40 3ND",
    "sg:province":"Berkshire",
    "wof:name":"Chartwell Security Services Ltd.",
    "wof:placetype":"venue"
},
  "geometry": {"coordinates":[-0.8458989859,51.3780593872],"type":"Point"}
}