{
  "type": "Feature",
  "properties": {
    "addr:full":"106 North End Ho, Fitzjames Ave West Kensington Greater London W14 0RY",
    "addr:housenumber":"106",
    "addr:postcode":"w14 0ry",
    "addr:street":"North End;Fitzjames Ave",
    "iso:country":"GB",
    "sg:address":"106 North End Ho, Fitzjames Ave",
    "sg:city":"West Kensington",
    "sg:classifiers":[
        {
            "category":"Food & Beverages",
            "subcategory":"Specialty",
            "type":"Retail Goods"
        }
    ],
    "sg:phone":"+44 20 7603 1467",
    "sg:postcode":"W14 0RY",
    "sg:province":"Greater London",
    "sg:tags":[
        "product",
        "health"
    ],
    "wof:name":"Herbalife Weight Loss Gain Supervisor",
    "wof:placetype":"venue"
},
  "geometry": {"coordinates":[-0.20979,51.493149],"type":"Point"}
}