{
  "type": "Feature",
  "properties": {
    "addr:full":"22-26 Camden Passage London Greater London N1 8ED",
    "addr:housenumber":"22-26",
    "addr:postcode":"n1 8ed",
    "addr:street":"Camden Passage",
    "iso:country":"GB",
    "sg:address":"22-26 Camden Passage",
    "sg:city":"London",
    "sg:classifiers":[
        {
            "category":"Shopping",
            "subcategory":"Hobbies, Toys, & Games",
            "type":"Retail Goods"
        }
    ],
    "sg:phone":"+44 20 7226 3403",
    "sg:postcode":"N1 8ED",
    "sg:province":"Greater London",
    "sg:tags":[
        "shop",
        "toy"
    ],
    "wof:name":"Frederick Beck Ltd.",
    "wof:placetype":"venue"
},
  "geometry": {"coordinates":[-0.1039490029,51.5350189209],"type":"Point"}
}