{
  "type": "Feature",
  "properties": {
    "addr:full":"51-52 Frith Street West End Hampshire W1V 5TE",
    "addr:housenumber":"51-52",
    "addr:postcode":"w1v 5te",
    "addr:street":"Frith Street",
    "iso:country":"GB",
    "sg:address":"51-52 Frith Street",
    "sg:city":"West End",
    "sg:classifiers":[
        {
            "category":"Retail",
            "subcategory":"Photofinishing",
            "type":"Services"
        }
    ],
    "sg:phone":"+44 20 7896 3100",
    "sg:postcode":"W1V 5TE",
    "sg:province":"Hampshire",
    "sg:tags":[
        "photographic",
        "processor"
    ],
    "wof:name":"Tapestry",
    "wof:placetype":"venue"
},
  "geometry": {"coordinates":[-0.1389899999,51.5075798035],"type":"Point"}
}