{
  "type": "Feature",
  "properties": {
    "addr:full":"282 Stand Lane, Radcliffe Manchester Greater Manchester M26 1JE",
    "addr:housenumber":"282",
    "addr:postcode":"m26 1je",
    "addr:street":"Stand Lane",
    "iso:country":"GB",
    "sg:address":"282 Stand Lane, Radcliffe",
    "sg:city":"Manchester",
    "sg:classifiers":[
        {
            "category":"Personal",
            "subcategory":"Beauty Salon",
            "type":"Services"
        }
    ],
    "sg:phone":"+44 161 766 4287",
    "sg:postcode":"M26 1JE",
    "sg:province":"Greater Manchester",
    "sg:tags":[
        "unisex",
        "hairdresser"
    ],
    "wof:name":"Images Hair Studio",
    "wof:placetype":"venue"
},
  "geometry": {"coordinates":[-2.3139369488,53.55103302],"type":"Point"}
}