{
  "type": "Feature",
  "properties": {
    "addr:full":"59 Yarborough Road Grimsby Lincolnshire DN34 4EG",
    "addr:housenumber":"59",
    "addr:postcode":"dn34 4eg",
    "addr:street":"Yarborough Road",
    "iso:country":"GB",
    "sg:address":"59 Yarborough Road",
    "sg:city":"Grimsby",
    "sg:classifiers":[
        {
            "category":"Food & Beverages",
            "subcategory":"Meat & Fish",
            "type":"Retail Goods"
        }
    ],
    "sg:phone":"+44 1472 357781",
    "sg:postcode":"DN34 4EG",
    "sg:province":"Lincolnshire",
    "sg:tags":[
        "chip"
    ],
    "wof:name":"H Richardson",
    "wof:placetype":"venue"
},
  "geometry": {"coordinates":[-0.10681,53.564281],"type":"Point"}
}