{
  "type": "Feature",
  "properties": {
    "iso:country":"GB",
    "sg:address":"312 Hillmorton Road",
    "sg:city":"Rugby",
    "sg:classifiers":[
        {
            "category":"Shopping",
            "subcategory":"News",
            "type":"Retail Goods"
        }
    ],
    "sg:phone":"+44 1788 544282",
    "sg:postcode":"CV22 5BP",
    "sg:province":"Warwickshire",
    "sg:tags":[
        "newsagent"
    ],
    "wof:name":"MADDEN'S (RUGBY) LTD",
    "wof:placetype":"venue"
},
  "geometry": {"coordinates":[-1.23034,52.360832],"type":"Point"}
}