{
  "type": "Feature",
  "properties": {
    "addr:full":"6 Hill Street Sandown Isle of Wight PO36 9DB",
    "addr:housenumber":"6",
    "addr:postcode":"po36 9db",
    "addr:street":"Hill Street",
    "iso:country":"GB",
    "sg:address":"6 Hill Street",
    "sg:city":"Sandown",
    "sg:classifiers":[
        {
            "category":"Travel",
            "subcategory":"Hotels & Motels",
            "type":"Entertainment"
        }
    ],
    "sg:phone":"+44 1983 403635",
    "sg:postcode":"PO36 9DB",
    "sg:province":"Isle of Wight",
    "sg:website":"http://www.sandhill-hotel.co.uk",
    "wof:name":"Sandhill Hotel",
    "wof:placetype":"venue"
},
  "geometry": {"coordinates":[-1.160739,50.656036],"type":"Point"}
}