{
  "type": "Feature",
  "properties": {
    "addr:full":"53 The Crofts Witney Oxfordshire OX28 4AQ",
    "addr:housenumber":"53",
    "addr:postcode":"ox28 4aq",
    "addr:street":"The Crofts",
    "iso:country":"GB",
    "sg:address":"53 The Crofts",
    "sg:city":"Witney",
    "sg:classifiers":[
        {
            "category":"Building & Trades",
            "subcategory":"Construction",
            "type":"Services"
        }
    ],
    "sg:postcode":"OX28 4AQ",
    "sg:province":"Oxfordshire",
    "sg:tags":[
        "joiner",
        "carpenter"
    ],
    "wof:name":"W B Wall",
    "wof:placetype":"venue"
},
  "geometry": {"coordinates":[-1.489935,51.782158],"type":"Point"}
}