{
  "type": "Feature",
  "properties": {
    "iso:country":"GB",
    "sg:address":"24 Moss Street",
    "sg:city":"Liverpool",
    "sg:classifiers":[
        {
            "category":"Building & Trades",
            "subcategory":"Construction",
            "type":"Services"
        }
    ],
    "sg:postcode":"L6 1HF",
    "sg:province":"Merseyside",
    "sg:tags":[
        "flooring"
    ],
    "wof:name":"Harry Aspinal",
    "wof:placetype":"venue"
},
  "geometry": {"coordinates":[-2.967763,53.411663],"type":"Point"}
}