{
  "type": "Feature",
  "properties": {
    "addr:full":"3c Monson Road Tunbridge Wells Kent TN1 1LS",
    "addr:housenumber":"3c",
    "addr:postcode":"tn1 1ls",
    "addr:street":"Monson Road",
    "iso:country":"GB",
    "sg:address":"3c Monson Road",
    "sg:city":"Tunbridge Wells",
    "sg:classifiers":[
        {
            "category":"Shopping",
            "subcategory":"News",
            "type":"Retail Goods"
        }
    ],
    "sg:postcode":"TN1 1LS",
    "sg:province":"Kent",
    "sg:tags":[
        "newsagent"
    ],
    "wof:name":"Dee's News",
    "wof:placetype":"venue"
},
  "geometry": {"coordinates":[0.2659969926,51.1335067749],"type":"Point"}
}