{
  "type": "Feature",
  "properties": {
    "iso:country":"GB",
    "sg:address":"91 Drayton High Road, Drayton",
    "sg:city":"Norwich",
    "sg:classifiers":[
        {
            "category":"Home & Garden",
            "subcategory":"Carpets & Floor Coverings",
            "type":"Retail Goods"
        }
    ],
    "sg:postcode":"NR8 6AL",
    "sg:province":"Norfolk",
    "sg:tags":[
        "cleaner",
        "upholstery"
    ],
    "wof:name":"Broadland Cleaning Services",
    "wof:placetype":"venue"
},
  "geometry": {"coordinates":[1.233304,52.672943],"type":"Point"}
}