{
  "type": "Feature",
  "properties": {
    "iso:country":"GB",
    "sg:address":"The Rectory, Main St",
    "sg:city":"Oakham",
    "sg:classifiers":[
        {
            "category":"Place Of Worship",
            "type":"Public Place"
        }
    ],
    "sg:phone":"+44 1572 812202",
    "sg:postcode":"LE15 7DJ",
    "sg:province":"Leicestershire",
    "wof:name":"Ashwell St Mary",
    "wof:placetype":"venue"
},
  "geometry": {"coordinates":[-0.751416,52.692543],"type":"Point"}
}