{
  "type": "Feature",
  "properties": {
    "addr:full":"2b Pollards Hill North London Greater London SW16 4NL",
    "addr:housenumber":"2b",
    "addr:postcode":"sw16 4nl",
    "addr:street":"Pollards Hill North",
    "iso:country":"GB",
    "sg:address":"2b Pollards Hill North",
    "sg:city":"London",
    "sg:classifiers":[
        {
            "category":"Health Services",
            "subcategory":"Doctor",
            "type":"Services"
        },
        {
            "category":"Health Services",
            "subcategory":"Clinic",
            "type":"Services"
        }
    ],
    "sg:phone":"+44 20 8679 1700",
    "sg:postcode":"SW16 4NL",
    "sg:province":"Greater London",
    "sg:tags":[
        "nh",
        "practitioners"
    ],
    "wof:name":"Norbury Health Centre",
    "wof:placetype":"venue"
},
  "geometry": {"coordinates":[-0.1211860031,51.4047431946],"type":"Point"}
}