{
  "type": "Feature",
  "properties": {
    "iso:country":"GB",
    "sg:address":"22 Station Rd",
    "sg:city":"Daventry",
    "sg:classifiers":[
        {
            "category":"Manufacturing",
            "subcategory":"Signs",
            "type":"Manufacturing & Wholesale Goods"
        }
    ],
    "sg:phone":"+44 1327 260434",
    "sg:postcode":"NN11 3RB",
    "sg:province":"Northamptonshire",
    "sg:tags":[
        "nameplate"
    ],
    "wof:name":"Sign Update",
    "wof:placetype":"venue"
},
  "geometry": {"coordinates":[-1.214194,52.167999],"type":"Point"}
}