{
  "type": "Feature",
  "properties": {
    "addr:full":"Unit 1 Thomas Street Wolverhampton West Midlands WV2 4JS",
    "addr:housenumber":"unit 1",
    "addr:postcode":"wv2 4js",
    "addr:street":"Thomas Street",
    "iso:country":"GB",
    "sg:address":"Unit 1 Thomas Street",
    "sg:city":"Wolverhampton",
    "sg:classifiers":[
        {
            "category":"Home & Garden",
            "subcategory":"Furniture",
            "type":"Retail Goods"
        }
    ],
    "sg:postcode":"WV2 4JS",
    "sg:province":"West Midlands",
    "wof:name":"Sheerline Home Improvements",
    "wof:placetype":"venue"
},
  "geometry": {"coordinates":[-2.1288640499,52.5796890259],"type":"Point"}
}