{
  "type": "Feature",
  "properties": {
    "addr:full":"62 High Street Cleator Moor Cumbria CA25 5BN",
    "addr:housenumber":"62",
    "addr:postcode":"ca25 5bn",
    "addr:street":"High Street",
    "iso:country":"GB",
    "sg:address":"62 High Street",
    "sg:city":"Cleator Moor",
    "sg:classifiers":[
        {
            "category":"Banks & Credit Unions",
            "subcategory":"Financial Services",
            "type":"Services"
        }
    ],
    "sg:phone":"+44 1946 821150",
    "sg:postcode":"CA25 5BN",
    "sg:province":"Cumbria",
    "sg:tags":[
        "adviser"
    ],
    "wof:name":"The Ifa Co. (C A) Ltd.",
    "wof:placetype":"venue"
},
  "geometry": {"coordinates":[-3.5180768967,54.5218276978],"type":"Point"}
}