{
  "type": "Feature",
  "properties": {
    "addr:full":"5 Market Row Northallerton North Yorkshire DL7 8LN",
    "addr:housenumber":"5",
    "addr:postcode":"dl7 8ln",
    "addr:street":"Market Row",
    "iso:country":"GB",
    "sg:address":"5 Market Row",
    "sg:city":"Northallerton",
    "sg:classifiers":[
        {
            "category":"Shopping",
            "subcategory":"Clothing, Apparel, & Fashions",
            "type":"Retail Goods"
        }
    ],
    "sg:phone":"+44 1609 777140",
    "sg:postcode":"DL7 8LN",
    "sg:province":"North Yorkshire",
    "sg:tags":[
        "shop"
    ],
    "wof:name":"Benetton",
    "wof:placetype":"venue"
},
  "geometry": {"coordinates":[-1.4349399805,54.3395881653],"type":"Point"}
}