{
  "type": "Feature",
  "properties": {
    "addr:full":"8 St Wilfreds Drive, Harehills Leeds West Yorkshire LS8 3PE",
    "addr:housenumber":"8",
    "addr:postcode":"ls8 3pe",
    "addr:street":"St Wilfreds Drive",
    "iso:country":"GB",
    "sg:address":"8 St Wilfreds Drive, Harehills",
    "sg:city":"Leeds",
    "sg:classifiers":[
        {
            "category":"Home & Garden",
            "subcategory":"Household Appliances",
            "type":"Retail Goods"
        },
        {
            "category":"Wholesale",
            "subcategory":"Chemicals & Plastics",
            "type":"Manufacturing & Wholesale Goods"
        }
    ],
    "sg:postcode":"LS8 3PE",
    "sg:province":"West Yorkshire",
    "sg:tags":[
        "electrical",
        "refrigerator",
        "freezer"
    ],
    "wof:name":"N Sutton",
    "wof:placetype":"venue"
},
  "geometry": {"coordinates":[-1.508457,53.814514],"type":"Point"}
}