{
  "type": "Feature",
  "properties": {
    "iso:country":"GB",
    "sg:address":"9 Winchester Road",
    "sg:city":"Chingford",
    "sg:classifiers":[
        {
            "category":"Professional",
            "subcategory":"Computer Services",
            "type":"Services"
        }
    ],
    "sg:phone":"+44 20 8527 7477",
    "sg:postcode":"E4 9LH",
    "sg:province":"Greater London",
    "sg:tags":[
        "consultant"
    ],
    "wof:name":"Focus It",
    "wof:placetype":"venue"
},
  "geometry": {"coordinates":[-0.001101,51.6070785522],"type":"Point"}
}