{
  "type": "Feature",
  "properties": {
    "iso:country":"GB",
    "sg:address":"Prospect House, Huntley",
    "sg:city":"Gloucester",
    "sg:classifiers":[
        {
            "category":"Freight",
            "type":"Transportation"
        }
    ],
    "sg:phone":"+44 1452 830267",
    "sg:postcode":"GL19 3EA",
    "sg:province":"Gloucestershire",
    "sg:tags":[
        "haulage",
        "road"
    ],
    "wof:name":"Morgan Transport",
    "wof:placetype":"venue"
},
  "geometry": {"coordinates":[-2.409314,51.873001],"type":"Point"}
}