{
  "type": "Feature",
  "properties": {
    "iso:country":"GB",
    "sg:address":"5 Wesley House, Wesley Street",
    "sg:city":"Castleford",
    "sg:classifiers":[
        {
            "category":"Professional",
            "subcategory":"Management & Consulting",
            "type":"Services"
        }
    ],
    "sg:phone":"+44 1977 517813",
    "sg:postcode":"WF10 1AE",
    "sg:province":"West Yorkshire",
    "sg:tags":[
        "consultant",
        "specialist"
    ],
    "wof:name":"Aspects of Beauty",
    "wof:placetype":"venue"
},
  "geometry": {"coordinates":[-1.344208,53.721699],"type":"Point"}
}