{
  "type": "Feature",
  "properties": {
    "addr:full":"55 Kyoto Court Bognor Regis West Sussex PO21 2UL",
    "addr:housenumber":"55",
    "addr:postcode":"po21 2ul",
    "addr:street":"Kyoto Court",
    "iso:country":"GB",
    "sg:address":"55 Kyoto Court",
    "sg:city":"Bognor Regis",
    "sg:classifiers":[
        {
            "category":"Organizations",
            "subcategory":"Political Organization",
            "type":"Services"
        }
    ],
    "sg:phone":"+44 1243 864206",
    "sg:postcode":"PO21 2UL",
    "sg:province":"West Sussex",
    "sg:tags":[
        "party"
    ],
    "wof:name":"Liberal Democrats",
    "wof:placetype":"venue"
},
  "geometry": {"coordinates":[-0.6904709935,50.7859954834],"type":"Point"}
}