{
  "type": "Feature",
  "properties": {
    "iso:country":"GB",
    "sg:address":"Lyon Road",
    "sg:city":"Walton-on-thames",
    "sg:classifiers":[
        {
            "category":"Retail",
            "subcategory":"Auto Repair",
            "type":"Services"
        }
    ],
    "sg:phone":"+44 1932 254057",
    "sg:postcode":"KT12 3PU",
    "sg:province":"Surrey",
    "sg:tags":[
        "body",
        "car"
    ],
    "wof:name":"Sunbury Coach Works",
    "wof:placetype":"venue"
},
  "geometry": {"coordinates":[-0.386587,51.378899],"type":"Point"}
}