{
  "type": "Feature",
  "properties": {
    "addr:full":"Unit 2 Stockport Trading Est, Yew St Stockport Cheshire SK4 2JZ",
    "addr:housenumber":"unit 2",
    "addr:postcode":"yew;sk4 2jz",
    "addr:street":"St",
    "iso:country":"GB",
    "sg:address":"Unit 2 Stockport Trading Est, Yew St",
    "sg:city":"Stockport",
    "sg:classifiers":[
        {
            "category":"Home & Garden",
            "subcategory":"Building Materials",
            "type":"Retail Goods"
        }
    ],
    "sg:phone":"+44 161 477 9378",
    "sg:postcode":"SK4 2JZ",
    "sg:province":"Cheshire",
    "sg:tags":[
        "furnishers",
        "bathroom",
        "planner"
    ],
    "wof:name":"Just Bathrooms",
    "wof:placetype":"venue"
},
  "geometry": {"coordinates":[-2.1859600544,53.4066963196],"type":"Point"}
}