{
  "type": "Feature",
  "properties": {
    "addr:full":"13 Sheridan Road Dover Kent CT16 2BZ",
    "addr:housenumber":"13",
    "addr:postcode":"ct16 2bz",
    "addr:street":"Sheridan Road",
    "iso:country":"GB",
    "sg:address":"13 Sheridan Road",
    "sg:city":"Dover",
    "sg:classifiers":[
        {
            "category":"Personal",
            "subcategory":"Beauty Salon",
            "type":"Services"
        }
    ],
    "sg:phone":"+44 1304 823014",
    "sg:postcode":"CT16 2BZ",
    "sg:province":"Kent",
    "sg:tags":[
        "unisex",
        "hairdresser"
    ],
    "wof:name":"Trend Hair Fashions",
    "wof:placetype":"venue"
},
  "geometry": {"coordinates":[1.2975660563,51.1436576843],"type":"Point"}
}