{
  "type": "Feature",
  "properties": {
    "addr:full":"Moor Road Manchester Cheshire M23 9BQ",
    "addr:postcode":"m23 9bq",
    "addr:street":"Moor Road",
    "iso:country":"GB",
    "sg:address":"Moor Road",
    "sg:city":"Manchester",
    "sg:classifiers":[
        {
            "category":"Community Center",
            "subcategory":"Youth",
            "type":"Public Place"
        }
    ],
    "sg:phone":"+44 161 945 2413",
    "sg:postcode":"M23 9BQ",
    "sg:province":"Cheshire",
    "sg:tags":[
        "organisation",
        "centre"
    ],
    "wof:name":"West Wythenshawe Youth Centre",
    "wof:placetype":"venue"
},
  "geometry": {"coordinates":[-2.29648,53.389225],"type":"Point"}
}