{
  "type": "Feature",
  "properties": {
    "addr:full":"12 Hexton Road, Lilley Luton Bedfordshire LU2 8LY",
    "addr:housenumber":"12",
    "addr:postcode":"lu2 8ly",
    "addr:street":"Hexton Road",
    "iso:country":"GB",
    "sg:address":"12 Hexton Road, Lilley",
    "sg:city":"Luton",
    "sg:classifiers":[
        {
            "category":"Manufacturing",
            "subcategory":"Tools & Machinery",
            "type":"Manufacturing & Wholesale Goods"
        },
        {
            "category":"Home & Garden",
            "subcategory":"Hardware",
            "type":"Retail Goods"
        }
    ],
    "sg:phone":"+44 1462 768676",
    "sg:postcode":"LU2 8LY",
    "sg:province":"Bedfordshire",
    "sg:tags":[
        "machine",
        "equipment",
        "welding",
        "manufacturer"
    ],
    "wof:name":"Gold Star Welding Plant Services",
    "wof:placetype":"venue"
},
  "geometry": {"coordinates":[-0.374682,51.924862],"type":"Point"}
}