{
  "type": "Feature",
  "properties": {
    "addr:full":"202 Martin Way Morden Surrey SM4 4AJ",
    "addr:housenumber":"202",
    "addr:postcode":"sm4 4aj",
    "addr:street":"Martin Way",
    "iso:country":"GB",
    "sg:address":"202 Martin Way",
    "sg:city":"Morden",
    "sg:classifiers":[
        {
            "category":"Manufacturing",
            "subcategory":"Petroleum Products",
            "type":"Manufacturing & Wholesale Goods"
        },
        {
            "category":"Building & Trades",
            "subcategory":"Construction",
            "type":"Services"
        }
    ],
    "sg:phone":"+44 20 8540 1449",
    "sg:postcode":"SM4 4AJ",
    "sg:province":"Surrey",
    "sg:tags":[
        "double",
        "glazing",
        "installers"
    ],
    "wof:name":"Brytahomes Window Co",
    "wof:placetype":"venue"
},
  "geometry": {"coordinates":[-0.210788995,51.4028282166],"type":"Point"}
}