{
  "type": "Feature",
  "properties": {
    "iso:country":"GB",
    "sg:address":"Orchard Drive, Theydon Bois",
    "sg:city":"Epping",
    "sg:classifiers":[
        {
            "category":"Education",
            "subcategory":"School",
            "type":"Public Place"
        }
    ],
    "sg:phone":"+44 1992 813083",
    "sg:postcode":"CM16 7DH",
    "sg:province":"Essex",
    "sg:tags":[
        "local",
        "authority"
    ],
    "wof:name":"Theydon Bois County Primary School",
    "wof:placetype":"venue"
},
  "geometry": {"coordinates":[0.0960450023,51.6724624634],"type":"Point"}
}