{
  "type": "Feature",
  "properties": {
    "addr:full":"Bury New Road, Prestwich Manchester Greater Manchester M25 9WN",
    "addr:postcode":"m25 9wn",
    "addr:street":"Bury New Road",
    "iso:country":"GB",
    "sg:address":"Bury New Road, Prestwich",
    "sg:city":"Manchester",
    "sg:classifiers":[
        {
            "category":"Community Center",
            "type":"Public Place"
        }
    ],
    "sg:phone":"+44 161 773 3333",
    "sg:postcode":"M25 9WN",
    "sg:province":"Greater Manchester",
    "sg:tags":[
        "nursery",
        "centre"
    ],
    "wof:name":"Barnfield Park",
    "wof:placetype":"venue"
},
  "geometry": {"coordinates":[-2.2809290886,53.5283164978],"type":"Point"}
}