{
  "type": "Feature",
  "properties": {
    "iso:country":"GB",
    "sg:address":"65 Manor Crescent, Walton",
    "sg:city":"Wakefield",
    "sg:classifiers":[
        {
            "category":"Education",
            "subcategory":"Dance Studio",
            "type":"Public Place"
        }
    ],
    "sg:phone":"+44 1924 251902",
    "sg:postcode":"WF2 6PG",
    "sg:province":"West Yorkshire",
    "sg:tags":[
        "school",
        "dancing"
    ],
    "wof:name":"Scott Stevenson School of Dancing",
    "wof:placetype":"venue"
},
  "geometry": {"coordinates":[-1.466534,53.655151],"type":"Point"}
}