{
  "type": "Feature",
  "properties": {
    "addr:full":"27 Lorne Street Kidderminster Staffordshire DY10 1SY",
    "addr:housenumber":"27",
    "addr:postcode":"dy10 1sy",
    "addr:street":"Lorne Street",
    "iso:country":"GB",
    "sg:address":"27 Lorne Street",
    "sg:city":"Kidderminster",
    "sg:classifiers":[
        {
            "category":"Building & Trades",
            "subcategory":"Landscaping Services",
            "type":"Services"
        }
    ],
    "sg:phone":"+44 1562 747757",
    "sg:postcode":"DY10 1SY",
    "sg:province":"Staffordshire",
    "sg:tags":[
        "forestry",
        "tree"
    ],
    "wof:name":"County Tree Care",
    "wof:placetype":"venue"
},
  "geometry": {"coordinates":[-2.235605,52.386158],"type":"Point"}
}