{
  "type": "Feature",
  "properties": {
    "iso:country":"GB",
    "sg:address":"2 Silver End Industrial Estate, Brettell Lane",
    "sg:city":"Brierley Hill",
    "sg:classifiers":[
        {
            "category":"Retail",
            "subcategory":"Auto Repair",
            "type":"Services"
        }
    ],
    "sg:phone":"+44 1384 77991",
    "sg:postcode":"DY5 3EA",
    "sg:province":"West Midlands",
    "sg:tags":[
        "garage",
        "mechanic"
    ],
    "wof:name":"M S Autos",
    "wof:placetype":"venue"
},
  "geometry": {"coordinates":[-2.1213009357,52.48204422],"type":"Point"}
}