{
  "type": "Feature",
  "properties": {
    "iso:country":"GB",
    "sg:address":"Woodgrange House",
    "sg:city":"Ingatestone",
    "sg:classifiers":[
        {
            "category":"Manufacturing",
            "subcategory":"Lumber",
            "type":"Manufacturing & Wholesale Goods"
        }
    ],
    "sg:phone":"+44 1277 355551",
    "sg:postcode":"CM4 9ED",
    "sg:province":"Essex",
    "sg:tags":[
        "merchant",
        "merchants",
        "importer",
        "agent",
        "timber"
    ],
    "wof:name":"Guardian Forest Products Ltd.",
    "wof:placetype":"venue"
},
  "geometry": {"coordinates":[0.43725,51.661201],"type":"Point"}
}