{
  "type": "Feature",
  "properties": {
    "iso:country":"GB",
    "sg:address":"P O Box 3358",
    "sg:city":"Poole",
    "sg:classifiers":[
        {
            "category":"Professional",
            "subcategory":"Printing & Photocopies",
            "type":"Services"
        }
    ],
    "sg:postcode":"BH12 4ZF",
    "sg:province":"Dorset",
    "sg:tags":[
        "duplicating",
        "copying"
    ],
    "wof:name":"The Copier Co",
    "wof:placetype":"venue"
},
  "geometry": {"coordinates":[-1.93419,50.746861],"type":"Point"}
}