{
  "type": "Feature",
  "properties": {
    "addr:full":"4 Connaught Road Harpenden Hertfordshire AL5 4TW",
    "addr:housenumber":"4",
    "addr:postcode":"al5 4tw",
    "addr:street":"Connaught Road",
    "iso:country":"GB",
    "sg:address":"4 Connaught Road",
    "sg:city":"Harpenden",
    "sg:classifiers":[
        {
            "category":"Home & Garden",
            "subcategory":"Carpets & Floor Coverings",
            "type":"Retail Goods"
        }
    ],
    "sg:postcode":"AL5 4TW",
    "sg:province":"Hertfordshire",
    "sg:tags":[
        "cleaner",
        "upholstery"
    ],
    "wof:name":"Fibredry Ltd",
    "wof:placetype":"venue"
},
  "geometry": {"coordinates":[-0.348999,51.817822],"type":"Point"}
}