{
  "type": "Feature",
  "properties": {
    "addr:full":"8 Park Road Kirkcaldy Fife KY1 3ER",
    "addr:housenumber":"8",
    "addr:postcode":"ky1 3er",
    "addr:street":"Park Road",
    "iso:country":"GB",
    "sg:address":"8 Park Road",
    "sg:city":"Kirkcaldy",
    "sg:classifiers":[
        {
            "category":"Professional",
            "type":"Services"
        },
        {
            "category":"Wholesale",
            "subcategory":"Groceries",
            "type":"Manufacturing & Wholesale Goods"
        }
    ],
    "sg:phone":"+44 1592 652255",
    "sg:postcode":"KY1 3ER",
    "sg:province":"Fife",
    "sg:tags":[
        "food",
        "supplier",
        "drink",
        "caterer"
    ],
    "wof:name":"William Yule & Son Ltd.",
    "wof:placetype":"venue"
},
  "geometry": {"coordinates":[-3.137499,56.13118],"type":"Point"}
}