{
  "type": "Feature",
  "properties": {
    "iso:country":"GB",
    "sg:address":"Anchorhold, 35 Paddockhall Rd",
    "sg:city":"Haywards Heath",
    "sg:classifiers":[
        {
            "category":"Place Of Worship",
            "type":"Public Place"
        }
    ],
    "sg:phone":"+44 1444 452468",
    "sg:postcode":"RH16 1HN",
    "sg:province":"East Sussex",
    "wof:name":"Society Of St John The Evangelist The",
    "wof:placetype":"venue"
},
  "geometry": {"coordinates":[-0.102047,50.996658],"type":"Point"}
}