{
  "type": "Feature",
  "properties": {
    "iso:country":"GB",
    "sg:address":"91 Queens Park Parade",
    "sg:city":"Northampton",
    "sg:classifiers":[
        {
            "category":"Health Services",
            "subcategory":"Dentist",
            "type":"Services"
        }
    ],
    "sg:phone":"+44 1604 715147",
    "sg:postcode":"NN2 6LR",
    "sg:province":"Northamptonshire",
    "wof:name":"N A Bhatia & Associates",
    "wof:placetype":"venue"
},
  "geometry": {"coordinates":[-0.900363,52.254135],"type":"Point"}
}