{
  "type": "Feature",
  "properties": {
    "iso:country":"GB",
    "sg:address":"Napiershall Centre",
    "sg:city":"Glasgow",
    "sg:classifiers":[
        {
            "category":"Personal",
            "type":"Services"
        },
        {
            "category":"Professional",
            "subcategory":"Lawyer & Legal Services",
            "type":"Services"
        }
    ],
    "sg:phone":"+44 141 341 0025",
    "sg:postcode":"G20 6EZ",
    "sg:province":"Glasgow City",
    "sg:tags":[
        "advice",
        "counselling"
    ],
    "wof:name":"Scottish Asian Action Committee",
    "wof:placetype":"venue"
},
  "geometry": {"coordinates":[-4.2733359337,55.8732833862],"type":"Point"}
}