{
  "type": "Feature",
  "properties": {
    "addr:full":"121 Goldhawk Road Shepherd's Bush Greater London W12 8EN",
    "addr:housenumber":"121",
    "addr:postcode":"w12 8en",
    "addr:street":"Goldhawk Road",
    "iso:country":"GB",
    "sg:address":"121 Goldhawk Road",
    "sg:city":"Shepherd's Bush",
    "sg:classifiers":[
        {
            "category":"Banks & Credit Unions",
            "subcategory":"Financial Services",
            "type":"Services"
        }
    ],
    "sg:postcode":"W12 8EN",
    "sg:province":"Greater London",
    "sg:tags":[
        "consultant"
    ],
    "wof:name":"The Trustgroup Ltd",
    "wof:placetype":"venue"
},
  "geometry": {"coordinates":[-0.2304919958,51.5015258789],"type":"Point"}
}