{
  "type": "Feature",
  "properties": {
    "addr:full":"5 Lancing Close Hastings East Sussex TN34 2PL",
    "addr:housenumber":"5",
    "addr:postcode":"tn34 2pl",
    "addr:street":"Lancing Close",
    "iso:country":"GB",
    "sg:address":"5 Lancing Close",
    "sg:city":"Hastings",
    "sg:classifiers":[
        {
            "category":"Retail",
            "subcategory":"Driving School",
            "type":"Services"
        }
    ],
    "sg:postcode":"TN34 2PL",
    "sg:province":"East Sussex",
    "wof:name":"Westfield School of Motoring",
    "wof:placetype":"venue"
},
  "geometry": {"coordinates":[0.5692269802,50.8718185425],"type":"Point"}
}