{
  "type": "Feature",
  "properties": {
    "iso:country":"GB",
    "sg:address":"Hatton Farm, Hatton Lane, Waverton",
    "sg:city":"Chester",
    "sg:classifiers":[
        {
            "category":"Farming",
            "subcategory":"Livestock Farm",
            "type":"Manufacturing & Wholesale Goods"
        }
    ],
    "sg:phone":"+44 1244 335254",
    "sg:postcode":"CH3 7RE",
    "sg:province":"Cheshire",
    "sg:tags":[
        "others"
    ],
    "wof:name":"A H Bate",
    "wof:placetype":"venue"
},
  "geometry": {"coordinates":[-2.8212890625,53.1696586609],"type":"Point"}
}