{
  "type": "Feature",
  "properties": {
    "addr:full":"7 Bowood Rd Taunton Somerset TA2 7QE",
    "addr:housenumber":"7",
    "addr:postcode":"ta2 7qe",
    "addr:street":"Bowood Rd",
    "iso:country":"GB",
    "sg:address":"7 Bowood Rd",
    "sg:city":"Taunton",
    "sg:classifiers":[
        {
            "category":"Shopping",
            "subcategory":"Baby Store",
            "type":"Retail Goods"
        }
    ],
    "sg:phone":"+44 1823 254395",
    "sg:postcode":"TA2 7QE",
    "sg:province":"Somerset",
    "sg:tags":[
        "nursery",
        "accessory"
    ],
    "wof:name":"Rockabye Baby Equipment Hire",
    "wof:placetype":"venue"
},
  "geometry": {"coordinates":[-3.093977,51.025742],"type":"Point"}
}