{
  "type": "Feature",
  "properties": {
    "iso:country":"GB",
    "sg:address":"The Point, Leigh Road",
    "sg:city":"Eastleigh",
    "sg:classifiers":[
        {
            "category":"Communications",
            "type":"Services"
        }
    ],
    "sg:phone":"+44 23 8065 2220",
    "sg:postcode":"SO50 9DE",
    "sg:province":"Hampshire",
    "sg:tags":[
        "audio-visual"
    ],
    "wof:name":"Cass Productions Ltd.",
    "wof:placetype":"venue"
},
  "geometry": {"coordinates":[-1.350593,50.968323],"type":"Point"}
}