{
  "type": "Feature",
  "properties": {
    "iso:country":"GB",
    "sg:address":"Ashburton Industrial Estate",
    "sg:city":"Ross-on-wye",
    "sg:classifiers":[
        {
            "category":"Manufacturing",
            "subcategory":"Metals",
            "type":"Manufacturing & Wholesale Goods"
        }
    ],
    "sg:phone":"+44 1989 563656",
    "sg:postcode":"HR9 7BW",
    "sg:province":"Gloucestershire",
    "sg:tags":[
        "product",
        "fabricated"
    ],
    "sg:website":"http://www.abtproducts.com",
    "wof:name":"A B T Products Ltd",
    "wof:placetype":"venue"
},
  "geometry": {"coordinates":[-2.581733,51.916481],"type":"Point"}
}