{
  "type": "Feature",
  "properties": {
    "addr:full":"Bridge Wharf Garage Carmarthen Carmarthenshire SA31 2BE",
    "addr:postcode":"sa31 2be",
    "addr:street":"Bridge",
    "iso:country":"GB",
    "sg:address":"Bridge Wharf Garage",
    "sg:city":"Carmarthen",
    "sg:classifiers":[
        {
            "category":"Retail",
            "subcategory":"Auto Repair",
            "type":"Services"
        }
    ],
    "sg:phone":"+44 1267 231600",
    "sg:postcode":"SA31 2BE",
    "sg:province":"Carmarthenshire",
    "sg:tags":[
        "modification",
        "garage"
    ],
    "wof:name":"Brian Thomas",
    "wof:placetype":"venue"
},
  "geometry": {"coordinates":[-4.299404,51.860275],"type":"Point"}
}