{
  "type": "Feature",
  "properties": {
    "addr:full":"Kiosk 6 Waterloo Station, Waterloo Road London Greater London SE1 7LY",
    "addr:housenumber":"6 waterloo",
    "addr:postcode":"se1 7ly",
    "addr:street":"Waterloo Road",
    "iso:country":"GB",
    "sg:address":"Kiosk 6 Waterloo Station, Waterloo Road",
    "sg:city":"London",
    "sg:classifiers":[
        {
            "category":"Shopping",
            "subcategory":"Gifts & Souvenirs",
            "type":"Retail Goods"
        }
    ],
    "sg:phone":"+44 20 7633 9615",
    "sg:postcode":"SE1 7LY",
    "sg:province":"Greater London",
    "sg:tags":[
        "shop"
    ],
    "wof:name":"Journeys Friend Ltd.",
    "wof:placetype":"venue"
},
  "geometry": {"coordinates":[-0.11388,51.503181],"type":"Point"}
}