{
  "type": "Feature",
  "properties": {
    "addr:full":"2-2a Cranbrook Rd, Chiswick Chiswick Greater London W4 2LH",
    "addr:housenumber":"2-2a",
    "addr:postcode":"w4 2lh",
    "addr:street":"Cranbrook Rd",
    "iso:country":"GB",
    "sg:address":"2-2a Cranbrook Rd, Chiswick",
    "sg:city":"Chiswick",
    "sg:classifiers":[
        {
            "category":"Professional",
            "type":"Services"
        }
    ],
    "sg:phone":"+44 20 8747 0648",
    "sg:postcode":"W4 2LH",
    "sg:province":"Greater London",
    "sg:tags":[
        "caterer"
    ],
    "wof:name":"Capital Catering London Ltd",
    "wof:placetype":"venue"
},
  "geometry": {"coordinates":[-0.2528190017,51.4924507141],"type":"Point"}
}