{
  "type": "Feature",
  "properties": {
    "addr:full":"Butterfly La Eltham Greater London SE9 1NP",
    "addr:postcode":"se9 1np",
    "iso:country":"GB",
    "sg:address":"Butterfly La",
    "sg:city":"Eltham",
    "sg:classifiers":[
        {
            "category":"Arena",
            "subcategory":"Sports Club",
            "type":"Entertainment"
        }
    ],
    "sg:phone":"+44 20 8850 1894",
    "sg:postcode":"SE9 1NP",
    "sg:province":"Greater London",
    "wof:name":"Butterfly Sports Club",
    "wof:placetype":"venue"
},
  "geometry": {"coordinates":[0.0544600002,51.4674987793],"type":"Point"}
}