{
  "type": "Feature",
  "properties": {
    "iso:country":"GB",
    "sg:address":"73 Aldenham Road",
    "sg:city":"Watford",
    "sg:classifiers":[
        {
            "category":"Fast Food",
            "type":"Food & Drink"
        }
    ],
    "sg:phone":"+44 1923 233344",
    "sg:postcode":"WD23 2LX",
    "sg:province":"Hertfordshire",
    "sg:tags":[
        "away",
        "take"
    ],
    "wof:name":"Downtown Kebabs",
    "wof:placetype":"venue"
},
  "geometry": {"coordinates":[-0.3326730132,51.6649246216],"type":"Point"}
}