{
  "type": "Feature",
  "properties": {
    "iso:country":"GB",
    "sg:address":"42 Chorley Avenue, Saltdean",
    "sg:city":"Brighton",
    "sg:classifiers":[
        {
            "category":"Professional",
            "subcategory":"Engineering",
            "type":"Services"
        },
        {
            "category":"Building & Trades",
            "subcategory":"Electrical",
            "type":"Services"
        }
    ],
    "sg:phone":"+44 1273 309397",
    "sg:postcode":"BN2 8AQ",
    "sg:province":"East Sussex",
    "sg:tags":[
        "engineer",
        "electrician",
        "contractor"
    ],
    "wof:name":"S Crunden",
    "wof:placetype":"venue"
},
  "geometry": {"coordinates":[-0.0461440012,50.8083152771],"type":"Point"}
}