{
  "type": "Feature",
  "properties": {
    "addr:full":"Whitestripes Way Aberdeen Aberdeen City AB22 8WG",
    "addr:postcode":"ab22 8wg",
    "addr:street":"Whitestripes Way",
    "iso:country":"GB",
    "sg:address":"Whitestripes Way",
    "sg:city":"Aberdeen",
    "sg:classifiers":[
        {
            "category":"Social Services",
            "subcategory":"Adult Care",
            "type":"Services"
        }
    ],
    "sg:phone":"+44 1224 820806",
    "sg:postcode":"AB22 8WG",
    "sg:province":"Aberdeen City",
    "sg:tags":[
        "housing",
        "sheltered"
    ],
    "wof:name":"Charlie Devine Court Sheltered Housing",
    "wof:placetype":"venue"
},
  "geometry": {"coordinates":[-2.133992,57.17931],"type":"Point"}
}