{
  "type": "Feature",
  "properties": {
    "addr:full":"Church Street Bromyard Herefordshire HR7 4DP",
    "addr:postcode":"hr7 4dp",
    "addr:street":"Church Street",
    "iso:country":"GB",
    "sg:address":"Church Street",
    "sg:city":"Bromyard",
    "sg:classifiers":[
        {
            "category":"Community Center",
            "subcategory":"Youth",
            "type":"Public Place"
        }
    ],
    "sg:phone":"+44 1885 488269",
    "sg:postcode":"HR7 4DP",
    "sg:province":"Herefordshire",
    "sg:tags":[
        "organisation",
        "centre"
    ],
    "wof:name":"Bromyard Youth Centre",
    "wof:placetype":"venue"
},
  "geometry": {"coordinates":[-2.5045089722,52.1891441345],"type":"Point"}
}