{
  "type": "Feature",
  "properties": {
    "addr:full":"10 Fosters Lane, Bradwell Milton Keynes Buckinghamshire MK13 9HD",
    "addr:housenumber":"10",
    "addr:postcode":"mk13 9hd",
    "addr:street":"Fosters Lane",
    "iso:country":"GB",
    "sg:address":"10 Fosters Lane, Bradwell",
    "sg:city":"Milton Keynes",
    "sg:classifiers":[
        {
            "category":"Professional",
            "subcategory":"Management & Consulting",
            "type":"Services"
        }
    ],
    "sg:phone":"+44 1908 221220",
    "sg:postcode":"MK13 9HD",
    "sg:province":"Buckinghamshire",
    "sg:tags":[
        "consultant",
        "energy",
        "conservation"
    ],
    "wof:name":"Victor Marketing",
    "wof:placetype":"venue"
},
  "geometry": {"coordinates":[-0.786277,52.04467],"type":"Point"}
}