{
  "type": "Feature",
  "properties": {
    "iso:country":"GB",
    "sg:address":"Greenlands",
    "sg:city":"Taunton",
    "sg:classifiers":[
        {
            "category":"Social Services",
            "subcategory":"Adult Care",
            "type":"Services"
        },
        {
            "category":"Government",
            "subcategory":"Office",
            "type":"Public Place"
        }
    ],
    "sg:phone":"+44 1823 274186",
    "sg:postcode":"TA1 3EB",
    "sg:province":"Somerset",
    "sg:tags":[
        "housing",
        "local",
        "sheltered"
    ],
    "wof:name":"Greenlands Sheltered Housing",
    "wof:placetype":"venue"
},
  "geometry": {"coordinates":[-3.0876269341,51.00623703],"type":"Point"}
}