{
  "type": "Feature",
  "properties": {
    "addr:full":"67 Summer Rd East Molesey Greater London KT8 9LX",
    "addr:housenumber":"67",
    "addr:postcode":"kt8 9lx",
    "addr:street":"Summer Rd",
    "iso:country":"GB",
    "sg:address":"67 Summer Rd",
    "sg:city":"East Molesey",
    "sg:classifiers":[
        {
            "category":"Retail",
            "subcategory":"Event Space",
            "type":"Services"
        }
    ],
    "sg:phone":"+44 20 8398 8444",
    "sg:postcode":"KT8 9LX",
    "sg:province":"Greater London",
    "sg:tags":[
        "exhibition",
        "organiser"
    ],
    "wof:name":"Aztec Management",
    "wof:placetype":"venue"
},
  "geometry": {"coordinates":[-0.346274,51.398327],"type":"Point"}
}