{
  "type": "Feature",
  "properties": {
    "iso:country":"GB",
    "sg:address":"Churchill Way",
    "sg:city":"Macclesfield",
    "sg:classifiers":[
        {
            "category":"Shopping",
            "type":"Retail Goods"
        }
    ],
    "sg:phone":"+44 1625 430328",
    "sg:postcode":"SK11 6AY",
    "sg:province":"Cheshire",
    "sg:tags":[
        "part",
        "accessory"
    ],
    "wof:name":"Halfords Superstore",
    "wof:placetype":"venue"
},
  "geometry": {"coordinates":[-2.128088,53.259811],"type":"Point"}
}