{
  "type": "Feature",
  "properties": {
    "addr:full":"1 Ferndale Road, Leytonstone London Greater London E11 3DW",
    "addr:housenumber":"1",
    "addr:postcode":"e11 3dw",
    "addr:street":"Ferndale Road",
    "iso:country":"GB",
    "sg:address":"1 Ferndale Road, Leytonstone",
    "sg:city":"London",
    "sg:classifiers":[
        {
            "category":"Professional",
            "subcategory":"Engineering",
            "type":"Services"
        }
    ],
    "sg:phone":"+44 20 8539 6339",
    "sg:postcode":"E11 3DW",
    "sg:province":"Greater London",
    "sg:tags":[
        "contractor",
        "electrical",
        "engineer"
    ],
    "wof:name":"D Bussey Electrcial Installations",
    "wof:placetype":"venue"
},
  "geometry": {"coordinates":[0.0099480003,51.5632743835],"type":"Point"}
}