{
  "type": "Feature",
  "properties": {
    "iso:country":"GB",
    "sg:address":"51 Talbot Rd",
    "sg:city":"Bayswater",
    "sg:classifiers":[
        {
            "category":"Travel",
            "subcategory":"Travel Agent",
            "type":"Entertainment"
        }
    ],
    "sg:phone":"+44 20 7221 6969",
    "sg:postcode":"W2 5JJ",
    "sg:province":"Greater London",
    "wof:name":"A Place In The Sun",
    "wof:placetype":"venue"
},
  "geometry": {"coordinates":[-0.196775,51.517204],"type":"Point"}
}