{
  "type": "Feature",
  "properties": {
    "iso:country":"GB",
    "sg:address":"19 Winnington La",
    "sg:city":"Northwich",
    "sg:classifiers":[
        {
            "category":"Food & Beverages",
            "subcategory":"Liquor & Beverages",
            "type":"Retail Goods"
        }
    ],
    "sg:postcode":"CW8 4DE",
    "sg:province":"Cheshire",
    "sg:tags":[
        "beer",
        "spirit",
        "wines"
    ],
    "wof:name":"Garner,H A,",
    "wof:placetype":"venue"
},
  "geometry": {"coordinates":[-2.527584,53.263107],"type":"Point"}
}