{
  "type": "Feature",
  "properties": {
    "addr:full":"6 Albemarle Way Clerkenwell Greater London EC1V 4JB",
    "addr:housenumber":"6",
    "addr:postcode":"ec1v 4jb",
    "addr:street":"Albemarle Way",
    "iso:country":"GB",
    "sg:address":"6 Albemarle Way",
    "sg:city":"Clerkenwell",
    "sg:classifiers":[
        {
            "category":"Deli",
            "type":"Food & Drink"
        }
    ],
    "sg:phone":"+44 20 7490 1347",
    "sg:postcode":"EC1V 4JB",
    "sg:province":"Greater London",
    "sg:tags":[
        "delivery",
        "sandwich"
    ],
    "wof:name":"Le Figaro",
    "wof:placetype":"venue"
},
  "geometry": {"coordinates":[-0.10257,51.522861],"type":"Point"}
}