{
  "type": "Feature",
  "properties": {
    "addr:full":"22 Cross Keys Close London Greater London W1U 2DW",
    "addr:housenumber":"22",
    "addr:postcode":"w1u 2dw",
    "addr:street":"Cross Keys Close",
    "iso:country":"GB",
    "sg:address":"22 Cross Keys Close",
    "sg:city":"London",
    "sg:classifiers":[
        {
            "category":"Real Estate",
            "subcategory":"Architect",
            "type":"Services"
        }
    ],
    "sg:phone":"+44 20 7486 7666",
    "sg:postcode":"W1U 2DW",
    "sg:province":"Greater London",
    "wof:name":"Dawe & Geddes Architects Ltd.",
    "wof:placetype":"venue"
},
  "geometry": {"coordinates":[-0.1501850039,51.5183792114],"type":"Point"}
}