{
  "type": "Feature",
  "properties": {
    "iso:country":"GB",
    "sg:address":"Unit 7 Stambermill Indust Est",
    "sg:city":"Stourbridge",
    "sg:classifiers":[
        {
            "category":"Manufacturing",
            "subcategory":"Metals",
            "type":"Manufacturing & Wholesale Goods"
        }
    ],
    "sg:phone":"+44 1384 832434",
    "sg:postcode":"DY9 7BQ",
    "sg:province":"West Midlands",
    "sg:tags":[
        "work",
        "sheet"
    ],
    "wof:name":"KT Sheet Metal Work Ltd",
    "wof:placetype":"venue"
},
  "geometry": {"coordinates":[-2.125574,52.457184],"type":"Point"}
}