{
  "type": "Feature",
  "properties": {
    "addr:full":"16-18 Avenue Road, Seaton Delaval Whitley Bay Northumberland NE25 0DU",
    "addr:housenumber":"16-18",
    "addr:postcode":"ne25 0du",
    "addr:street":"Avenue Road",
    "iso:country":"GB",
    "sg:address":"16-18 Avenue Road, Seaton Delaval",
    "sg:city":"Whitley Bay",
    "sg:classifiers":[
        {
            "category":"Food & Beverages",
            "subcategory":"Fruits & Vegetables",
            "type":"Retail Goods"
        }
    ],
    "sg:postcode":"NE25 0DU",
    "sg:province":"Northumberland",
    "sg:tags":[
        "greengrocer"
    ],
    "wof:name":"Seaton Savers",
    "wof:placetype":"venue"
},
  "geometry": {"coordinates":[-1.5260219574,55.0722579956],"type":"Point"}
}