{
  "type": "Feature",
  "properties": {
    "iso:country":"GB",
    "sg:address":"27 Chilmark Gardens",
    "sg:city":"New Malden",
    "sg:classifiers":[
        {
            "category":"Building & Trades",
            "subcategory":"Plumbing",
            "type":"Services"
        }
    ],
    "sg:phone":"+44 20 8942 2333",
    "sg:postcode":"KT3 6RS",
    "sg:province":"Surrey",
    "sg:tags":[
        "heating"
    ],
    "wof:name":"Alpha Plumbing & Heating",
    "wof:placetype":"venue"
},
  "geometry": {"coordinates":[-0.247327,51.389908],"type":"Point"}
}