{
  "type": "Feature",
  "properties": {
    "iso:country":"GB",
    "sg:address":"19 Westbury Road, Boscombe",
    "sg:city":"Bournemouth",
    "sg:classifiers":[
        {
            "category":"Travel",
            "subcategory":"Hotels & Motels",
            "type":"Entertainment"
        }
    ],
    "sg:postcode":"BH5 1HA",
    "sg:province":"Dorset",
    "wof:name":"The Strand Hotel",
    "wof:placetype":"venue"
},
  "geometry": {"coordinates":[-1.838689,50.724964],"type":"Point"}
}