{
  "type": "Feature",
  "properties": {
    "iso:country":"GB",
    "sg:address":"1-2 West Street",
    "sg:city":"Reading",
    "sg:classifiers":[
        {
            "category":"Professional",
            "subcategory":"Employment Agencies",
            "type":"Services"
        }
    ],
    "sg:phone":"+44 118 950 8757",
    "sg:postcode":"RG1 1TT",
    "sg:province":"Berkshire",
    "sg:tags":[
        "consultant"
    ],
    "wof:name":"Gravity Personnel Ltd.",
    "wof:placetype":"venue"
},
  "geometry": {"coordinates":[-0.975911,51.45639],"type":"Point"}
}