{
  "type": "Feature",
  "properties": {
    "addr:full":"259 Bilston Rd Wolverhampton West Midlands WV2 2JN",
    "addr:housenumber":"259",
    "addr:postcode":"wv2 2jn",
    "addr:street":"Bilston Rd",
    "iso:country":"GB",
    "sg:address":"259 Bilston Rd",
    "sg:city":"Wolverhampton",
    "sg:classifiers":[
        {
            "category":"Professional",
            "subcategory":"Detective & Security Services",
            "type":"Services"
        }
    ],
    "sg:postcode":"WV2 2JN",
    "sg:province":"West Midlands",
    "sg:tags":[
        "locksmith"
    ],
    "wof:name":"Bodley,Leslie John,",
    "wof:placetype":"venue"
},
  "geometry": {"coordinates":[-2.105295,52.575947],"type":"Point"}
}