{
  "type": "Feature",
  "properties": {
    "iso:country":"GB",
    "sg:address":"198 Kings Road",
    "sg:city":"London",
    "sg:classifiers":[
        {
            "category":"Insurance",
            "subcategory":"Insurance Agent",
            "type":"Services"
        },
        {
            "category":"Banks & Credit Unions",
            "subcategory":"Financial Services",
            "type":"Services"
        }
    ],
    "sg:phone":"+44 20 7376 5844",
    "sg:postcode":"SW3 5XX",
    "sg:province":"Greater London",
    "sg:tags":[
        "discount",
        "card"
    ],
    "wof:name":"Marks & Spencer Card Safe",
    "wof:placetype":"venue"
},
  "geometry": {"coordinates":[-0.166388,51.488373],"type":"Point"}
}