{
  "type": "Feature",
  "properties": {
    "addr:full":"Friars Hill, Sinnington York North Yorkshire YO62 6SL",
    "addr:postcode":"yo62 6sl",
    "addr:street":"Friars Hill",
    "iso:country":"GB",
    "sg:address":"Friars Hill, Sinnington",
    "sg:city":"York",
    "sg:classifiers":[
        {
            "category":"Sports & Exercise",
            "subcategory":"Stables",
            "type":"Entertainment"
        }
    ],
    "sg:phone":"+44 1751 432758",
    "sg:postcode":"YO62 6SL",
    "sg:province":"North Yorkshire",
    "sg:tags":[
        "education",
        "equestrian"
    ],
    "wof:name":"Friars Hill Riding Stables",
    "wof:placetype":"venue"
},
  "geometry": {"coordinates":[-0.8589689732,54.2598381042],"type":"Point"}
}