{
  "type": "Feature",
  "properties": {
    "iso:country":"GB",
    "sg:address":"Oxford Road, Enstone",
    "sg:city":"Chipping Norton",
    "sg:classifiers":[
        {
            "category":"Travel",
            "subcategory":"Hotels & Motels",
            "type":"Entertainment"
        }
    ],
    "sg:phone":"+44 1608 678736",
    "sg:postcode":"OX7 4NE",
    "sg:province":"Gloucestershire",
    "sg:tags":[
        "house",
        "guest"
    ],
    "wof:name":"Swan Lodge",
    "wof:placetype":"venue"
},
  "geometry": {"coordinates":[-1.452295,51.914867],"type":"Point"}
}