{
  "type": "Feature",
  "properties": {
    "addr:full":"Chapel Road, Tumby Woodside Boston Lincolnshire PE22 7SP",
    "addr:postcode":"pe22 7sp",
    "addr:street":"Chapel Road",
    "iso:country":"GB",
    "sg:address":"Chapel Road, Tumby Woodside",
    "sg:city":"Boston",
    "sg:classifiers":[
        {
            "category":"Farming",
            "subcategory":"Farm",
            "type":"Manufacturing & Wholesale Goods"
        }
    ],
    "sg:phone":"+44 1526 342424",
    "sg:postcode":"PE22 7SP",
    "sg:province":"Lincolnshire",
    "sg:tags":[
        "mixed",
        "crop"
    ],
    "wof:name":"Tumby Wood Farm",
    "wof:placetype":"venue"
},
  "geometry": {"coordinates":[-0.053294,53.09634],"type":"Point"}
}