{
  "type": "Feature",
  "properties": {
    "addr:full":"Eagle House, Redstone Industrial Estate Boston Lincolnshire PE21 8EA",
    "addr:housenumber":"estate",
    "addr:postcode":"pe21 8ea",
    "addr:street":"Redstone Industrial",
    "iso:country":"GB",
    "sg:address":"Eagle House, Redstone Industrial Estate",
    "sg:city":"Boston",
    "sg:classifiers":[
        {
            "category":"Professional",
            "subcategory":"Art Services",
            "type":"Services"
        }
    ],
    "sg:phone":"+44 1205 360050",
    "sg:postcode":"PE21 8EA",
    "sg:province":"Lincolnshire",
    "sg:tags":[
        "consultant",
        "design"
    ],
    "wof:name":"Otus Design Print & Marketing",
    "wof:placetype":"venue"
},
  "geometry": {"coordinates":[-0.0297219995,52.9679336548],"type":"Point"}
}