{
  "type": "Feature",
  "properties": {
    "addr:full":"84 Beckenham Gardens, Hemlington Middlesbrough North Yorkshire TS8 9JT",
    "addr:housenumber":"84",
    "addr:postcode":"ts8 9jt",
    "addr:street":"Beckenham Gardens Hemlington",
    "iso:country":"GB",
    "sg:address":"84 Beckenham Gardens, Hemlington",
    "sg:city":"Middlesbrough",
    "sg:classifiers":[
        {
            "category":"Building & Trades",
            "subcategory":"Construction",
            "type":"Services"
        }
    ],
    "sg:phone":"+44 1642 591499",
    "sg:postcode":"TS8 9JT",
    "sg:province":"North Yorkshire",
    "sg:tags":[
        "glazier"
    ],
    "wof:name":"D.L Double Glazing Repairs",
    "wof:placetype":"venue"
},
  "geometry": {"coordinates":[-1.231629,54.52235],"type":"Point"}
}