{
  "type": "Feature",
  "properties": {
    "addr:full":"152 Connaught Road, Brookwood Woking Surrey GU24 0AL",
    "addr:housenumber":"152",
    "addr:postcode":"gu24 0al",
    "addr:street":"Connaught Road",
    "iso:country":"GB",
    "sg:address":"152 Connaught Road, Brookwood",
    "sg:city":"Woking",
    "sg:classifiers":[
        {
            "category":"Food & Beverages",
            "subcategory":"Meat & Fish",
            "type":"Retail Goods"
        },
        {
            "category":"Food & Beverages",
            "subcategory":"Groceries & Convenience Stores",
            "type":"Retail Goods"
        }
    ],
    "sg:phone":"+44 1483 473064",
    "sg:postcode":"GU24 0AL",
    "sg:province":"Surrey",
    "sg:tags":[
        "shop",
        "chip"
    ],
    "wof:name":"Mayo Fish Bar",
    "wof:placetype":"venue"
},
  "geometry": {"coordinates":[-0.6398710012,51.3047561646],"type":"Point"}
}