{
  "type": "Feature",
  "properties": {
    "addr:full":"93 Nethergate Dundee Dundee City DD1 4DH",
    "addr:housenumber":"93",
    "addr:postcode":"dd1 4dh",
    "addr:street":"Nethergate",
    "iso:country":"GB",
    "sg:address":"93 Nethergate",
    "sg:city":"Dundee",
    "sg:classifiers":[
        {
            "category":"Banks & Credit Unions",
            "subcategory":"Financial Services",
            "type":"Services"
        }
    ],
    "sg:phone":"+44 1382 229336",
    "sg:postcode":"DD1 4DH",
    "sg:province":"Dundee City",
    "sg:tags":[
        "adviser",
        "independent"
    ],
    "wof:name":"H E Grant Ltd",
    "wof:placetype":"venue"
},
  "geometry": {"coordinates":[-2.9745929241,56.4581947327],"type":"Point"}
}