{
  "type": "Feature",
  "properties": {
    "addr:full":"P O Box14 Stockport Cheshire SK5 8NN",
    "addr:housenumber":"box14",
    "addr:postcode":"sk5 8nn",
    "addr:street":"P O",
    "iso:country":"GB",
    "sg:address":"P O Box14",
    "sg:city":"Stockport",
    "sg:classifiers":[
        {
            "category":"Professional",
            "subcategory":"Testing Lab",
            "type":"Services"
        }
    ],
    "sg:phone":"+44 161 612 1747",
    "sg:postcode":"SK5 8NN",
    "sg:province":"Cheshire",
    "sg:tags":[
        "pregnancy"
    ],
    "wof:name":"Addams Womens Centre",
    "wof:placetype":"venue"
},
  "geometry": {"coordinates":[-2.1382501125,53.430480957],"type":"Point"}
}