{
  "type": "Feature",
  "properties": {
    "addr:full":"Unit 8 Clock Tower Park Road, Bestwood Village Nottingham Nottinghamshire NG6 8TQ",
    "addr:housenumber":"unit 8",
    "addr:postcode":"ng6 8tq",
    "addr:street":"Clock Tower Park Road",
    "iso:country":"GB",
    "sg:address":"Unit 8 Clock Tower Park Road, Bestwood Village",
    "sg:city":"Nottingham",
    "sg:classifiers":[
        {
            "category":"Professional",
            "subcategory":"Engineering",
            "type":"Services"
        }
    ],
    "sg:phone":"+44 115 975 4867",
    "sg:postcode":"NG6 8TQ",
    "sg:province":"Nottinghamshire",
    "sg:tags":[
        "contractor",
        "electrical",
        "engineer"
    ],
    "wof:name":"Blanco White James",
    "wof:placetype":"venue"
},
  "geometry": {"coordinates":[-1.1793270111,53.0253562927],"type":"Point"}
}