{
  "type": "Feature",
  "properties": {
    "iso:country":"GB",
    "sg:address":"2nd Floor, Carriage Row, 183 Eversholt St",
    "sg:city":"Camden",
    "sg:classifiers":[
        {
            "category":"Shopping",
            "subcategory":"Stationery & Office Supplies",
            "type":"Retail Goods"
        }
    ],
    "sg:phone":"+44 171 387 8382",
    "sg:postcode":"NW1 1BU",
    "sg:province":"Greater London",
    "sg:tags":[
        "equipment"
    ],
    "wof:name":"Steelcase Strafor Worklife",
    "wof:placetype":"venue"
},
  "geometry": {"coordinates":[-0.127944,51.532581],"type":"Point"}
}