{
  "type": "Feature",
  "properties": {
    "iso:country":"GB",
    "sg:address":"8 Solihull Lane",
    "sg:city":"Birmingham",
    "sg:classifiers":[
        {
            "category":"Personal",
            "subcategory":"Beauty Salon",
            "type":"Services"
        },
        {
            "category":"Personal",
            "subcategory":"Barber",
            "type":"Services"
        }
    ],
    "sg:phone":"+44 121 744 1693",
    "sg:postcode":"B28 9LU",
    "sg:province":"West Midlands",
    "sg:tags":[
        "unisex",
        "hairdresser"
    ],
    "wof:name":"MARK ANTHONY",
    "wof:placetype":"venue"
},
  "geometry": {"coordinates":[-1.836191,52.422611],"type":"Point"}
}