{
  "type": "Feature",
  "properties": {
    "iso:country":"GB",
    "sg:address":"Roughton Mill, Horncastle Road, Roughton Moor",
    "sg:city":"Woodhall Spa",
    "sg:classifiers":[
        {
            "category":"Recreation",
            "subcategory":"Campground",
            "type":"Entertainment"
        }
    ],
    "sg:phone":"+44 1526 352903",
    "sg:postcode":"LN10 6UX",
    "sg:province":"Lincolnshire",
    "sg:tags":[
        "caravan",
        "holiday",
        "camp",
        "park",
        "centre"
    ],
    "sg:website":"http://www.bainland.co.uk",
    "wof:name":"Bainland Country Park Ltd",
    "wof:placetype":"venue"
},
  "geometry": {"coordinates":[-0.201089,53.154961],"type":"Point"}
}