{
  "type": "Feature",
  "properties": {
    "iso:country":"GB",
    "sg:address":"15 Dam Street",
    "sg:city":"Lichfield",
    "sg:classifiers":[
        {
            "category":"Shopping",
            "subcategory":"Florist",
            "type":"Retail Goods"
        }
    ],
    "sg:phone":"+44 1543 257520",
    "sg:postcode":"WS13 6AE",
    "sg:province":"Staffordshire",
    "wof:name":"Elizabeths",
    "wof:placetype":"venue"
},
  "geometry": {"coordinates":[-1.8283920288,52.6844978333],"type":"Point"}
}