{
  "type": "Feature",
  "properties": {
    "addr:full":"735 Lincoln Road Peterborough Cambridgeshire PE1 3HD",
    "addr:housenumber":"735",
    "addr:postcode":"pe1 3hd",
    "addr:street":"Lincoln Road",
    "iso:country":"GB",
    "sg:address":"735 Lincoln Road",
    "sg:city":"Peterborough",
    "sg:classifiers":[
        {
            "category":"Shopping",
            "subcategory":"News",
            "type":"Retail Goods"
        }
    ],
    "sg:phone":"+44 1733 312707",
    "sg:postcode":"PE1 3HD",
    "sg:province":"Cambridgeshire",
    "sg:tags":[
        "newsagent"
    ],
    "wof:name":"Alexander Trading",
    "wof:placetype":"venue"
},
  "geometry": {"coordinates":[-0.2584750056,52.5950431824],"type":"Point"}
}