{
  "type": "Feature",
  "properties": {
    "addr:full":"21 Mkt Hill Brandon Norfolk IP27 0AA",
    "addr:housenumber":"21",
    "addr:postcode":"ip27 0aa",
    "addr:street":"Mkt Hill",
    "iso:country":"GB",
    "sg:address":"21 Mkt Hill",
    "sg:city":"Brandon",
    "sg:classifiers":[
        {
            "category":"Shopping",
            "subcategory":"Clothing, Apparel, & Fashions",
            "type":"Retail Goods"
        }
    ],
    "sg:phone":"+44 1842 810528",
    "sg:postcode":"IP27 0AA",
    "sg:province":"Norfolk",
    "sg:tags":[
        "shop"
    ],
    "wof:name":"Matsell,Mary,Boutique",
    "wof:placetype":"venue"
},
  "geometry": {"coordinates":[0.623718977,52.4470481873],"type":"Point"}
}