{
  "type": "Feature",
  "properties": {
    "iso:country":"GB",
    "sg:address":"City Plaza, Cannon Street",
    "sg:city":"Birmingham",
    "sg:classifiers":[
        {
            "category":"Sports & Exercise",
            "subcategory":"Sports Center",
            "type":"Entertainment"
        }
    ],
    "sg:phone":"+44 121 633 0296",
    "sg:postcode":"B2 5EF",
    "sg:province":"West Midlands",
    "sg:tags":[
        "shop",
        "good"
    ],
    "wof:name":"Legends Surf Shops",
    "wof:placetype":"venue"
},
  "geometry": {"coordinates":[-1.89825,52.480042],"type":"Point"}
}