{
  "type": "Feature",
  "properties": {
    "addr:full":"Little Laceby Farm, Grimsby Road Grimsby Lincolnshire DN37 7DR",
    "addr:postcode":"dn37 7dr",
    "addr:street":"Grimsby Road",
    "iso:country":"GB",
    "sg:address":"Little Laceby Farm, Grimsby Road",
    "sg:city":"Grimsby",
    "sg:classifiers":[
        {
            "category":"Home & Garden",
            "subcategory":"Carpets & Floor Coverings",
            "type":"Retail Goods"
        }
    ],
    "sg:phone":"+44 1472 276066",
    "sg:postcode":"DN37 7DR",
    "sg:province":"Lincolnshire",
    "sg:tags":[
        "carpets",
        "rug",
        "matting"
    ],
    "wof:name":"Carpet Kingdom (Northern) Ltd.",
    "wof:placetype":"venue"
},
  "geometry": {"coordinates":[-0.1565800011,53.5424003601],"type":"Point"}
}