{
  "type": "Feature",
  "properties": {
    "iso:country":"GB",
    "sg:address":"190 Blackburn Rd, Great Harwood",
    "sg:city":"Blackburn",
    "sg:classifiers":[
        {
            "category":"Building & Trades",
            "subcategory":"Construction",
            "type":"Services"
        }
    ],
    "sg:phone":"+44 1254 876677",
    "sg:postcode":"BB6 7LU",
    "sg:province":"Lancashire",
    "sg:tags":[
        "glazier"
    ],
    "wof:name":"R Adams & Co",
    "wof:placetype":"venue"
},
  "geometry": {"coordinates":[-2.4098279476,53.7807998657],"type":"Point"}
}