{
  "type": "Feature",
  "properties": {
    "addr:full":"Low Farm, Aisthorpe Lincoln Lincolnshire LN1 2SG",
    "addr:postcode":"ln1 2sg",
    "addr:street":"Lincoln",
    "iso:country":"GB",
    "sg:address":"Low Farm, Aisthorpe",
    "sg:city":"Lincoln",
    "sg:classifiers":[
        {
            "category":"Building & Trades",
            "subcategory":"Plumbing",
            "type":"Services"
        }
    ],
    "sg:phone":"+44 1522 730320",
    "sg:postcode":"LN1 2SG",
    "sg:province":"Lincolnshire",
    "sg:tags":[
        "central",
        "heating"
    ],
    "wof:name":"C & P Heating",
    "wof:placetype":"venue"
},
  "geometry": {"coordinates":[-0.577014,53.310604],"type":"Point"}
}