{
  "type": "Feature",
  "properties": {
    "addr:full":"Ground Floor Flat, 25 Plato Road London Greater London SW2 5UP",
    "addr:housenumber":"25",
    "addr:postcode":"sw2 5up",
    "addr:street":"Plato Road",
    "iso:country":"GB",
    "sg:address":"Ground Floor Flat, 25 Plato Road",
    "sg:city":"London",
    "sg:classifiers":[
        {
            "category":"Professional",
            "subcategory":"Management & Consulting",
            "type":"Services"
        }
    ],
    "sg:postcode":"SW2 5UP",
    "sg:province":"Greater London",
    "sg:tags":[
        "consultant",
        "business"
    ],
    "wof:name":"Pagoda I.T. Ltd",
    "wof:placetype":"venue"
},
  "geometry": {"coordinates":[-0.1258600056,51.4598388672],"type":"Point"}
}