{
  "type": "Feature",
  "properties": {
    "addr:full":"23 Wellstead Road Wareham Dorset BH20 4EY",
    "addr:housenumber":"23",
    "addr:postcode":"bh20 4ey",
    "addr:street":"Wellstead Road",
    "iso:country":"GB",
    "sg:address":"23 Wellstead Road",
    "sg:city":"Wareham",
    "sg:classifiers":[
        {
            "category":"Communications",
            "subcategory":"Film & Video Production",
            "type":"Services"
        }
    ],
    "sg:postcode":"BH20 4EY",
    "sg:province":"Dorset",
    "sg:tags":[
        "illustrator",
        "artist"
    ],
    "wof:name":"Roger Lowless",
    "wof:placetype":"venue"
},
  "geometry": {"coordinates":[-2.119681,50.69743],"type":"Point"}
}