{
  "type": "Feature",
  "properties": {
    "iso:country":"GB",
    "sg:address":"Care Of Kwiksave Store",
    "sg:city":"Walsall",
    "sg:classifiers":[
        {
            "category":"Food & Beverages",
            "subcategory":"Meat & Fish",
            "type":"Retail Goods"
        }
    ],
    "sg:postcode":"WS6 6DA",
    "sg:province":"Staffordshire",
    "sg:tags":[
        "butcher"
    ],
    "wof:name":"Castle Wholesale Meats Ltd",
    "wof:placetype":"venue"
},
  "geometry": {"coordinates":[-2.0173699856,52.6607017517],"type":"Point"}
}