{
  "type": "Feature",
  "properties": {
    "iso:country":"GB",
    "sg:address":"7 Chapel Street, Ton Pentre, Ystrad",
    "sg:city":"Pentre",
    "sg:classifiers":[
        {
            "category":"Government",
            "subcategory":"Office",
            "type":"Public Place"
        }
    ],
    "sg:phone":"+44 1443 422954",
    "sg:postcode":"CF41 7RW",
    "sg:province":"Rhondda, Cynon, Taff",
    "sg:tags":[
        "education",
        "agency",
        "authority"
    ],
    "wof:name":"Raid",
    "wof:placetype":"venue"
},
  "geometry": {"coordinates":[-3.4639,51.644897],"type":"Point"}
}