{
  "type": "Feature",
  "properties": {
    "addr:full":"Unit 47a Joseph Wilson Industrial Estate, Millstrood Road Whitstable Kent CT5 3PS",
    "addr:housenumber":"unit 47a",
    "addr:postcode":"ct5 3ps",
    "addr:street":"Joseph Wilson Industrial Estate Millstrood Road",
    "iso:country":"GB",
    "sg:address":"Unit 47a Joseph Wilson Industrial Estate, Millstrood Road",
    "sg:city":"Whitstable",
    "sg:classifiers":[
        {
            "category":"Shopping",
            "subcategory":"Stationery & Office Supplies",
            "type":"Retail Goods"
        },
        {
            "category":"Retail",
            "subcategory":"Auto Repair",
            "type":"Services"
        }
    ],
    "sg:phone":"+44 1227 274040",
    "sg:postcode":"CT5 3PS",
    "sg:province":"Kent",
    "sg:tags":[
        "equipment",
        "agricultural",
        "sales",
        "machinery"
    ],
    "wof:name":"COUNTY BUSINESS SYSTEMS",
    "wof:placetype":"venue"
},
  "geometry": {"coordinates":[1.0264060497,51.362247467],"type":"Point"}
}