{
  "type": "Feature",
  "properties": {
    "iso:country":"GB",
    "sg:address":"Latchmere House, Watling Street",
    "sg:city":"Canterbury",
    "sg:classifiers":[
        {
            "category":"Professional",
            "subcategory":"Accounting & Tax Preparation",
            "type":"Services"
        }
    ],
    "sg:phone":"+44 1227 451304",
    "sg:postcode":"CT1 2UD",
    "sg:province":"Kent",
    "sg:tags":[
        "accountant",
        "activity"
    ],
    "wof:name":"Timothy P Bolton",
    "wof:placetype":"venue"
},
  "geometry": {"coordinates":[1.078510046,51.2775344849],"type":"Point"}
}