{
  "type": "Feature",
  "properties": {
    "addr:full":"Cemetery Rd, James Bridge Wednesbury West Midlands WS10 8NA",
    "addr:postcode":"ws10 8na",
    "addr:street":"Cemetery Rd",
    "iso:country":"GB",
    "sg:address":"Cemetery Rd, James Bridge",
    "sg:city":"Wednesbury",
    "sg:classifiers":[
        {
            "category":"Bars & Pubs",
            "type":"Food & Drink"
        }
    ],
    "sg:phone":"+44 121 526 2604",
    "sg:postcode":"WS10 8NA",
    "sg:province":"West Midlands",
    "sg:tags":[
        "pubs",
        "inn"
    ],
    "wof:name":"Railway Tavern",
    "wof:placetype":"venue"
},
  "geometry": {"coordinates":[-2.0190091133,52.5760192871],"type":"Point"}
}