{
  "type": "Feature",
  "properties": {
    "iso:country":"GB",
    "sg:address":"Unit 4 Lloyd St",
    "sg:city":"Glasgow",
    "sg:classifiers":[
        {
            "category":"Bus Charters",
            "type":"Transportation"
        }
    ],
    "sg:phone":"+44 141 647 9191",
    "sg:postcode":"G73 1NP",
    "sg:province":"Glasgow City",
    "sg:tags":[
        "hire",
        "coach"
    ],
    "wof:name":"Williamson Coaches",
    "wof:placetype":"venue"
},
  "geometry": {"coordinates":[-4.208708,55.833305],"type":"Point"}
}