{
  "type": "Feature",
  "properties": {
    "addr:full":"4 Bond Terrace Wakefield West Yorkshire WF1 2HW",
    "addr:housenumber":"4",
    "addr:postcode":"wf1 2hw",
    "addr:street":"Bond Terrace",
    "iso:country":"GB",
    "sg:address":"4 Bond Terrace",
    "sg:city":"Wakefield",
    "sg:classifiers":[
        {
            "category":"Professional",
            "subcategory":"Lawyer & Legal Services",
            "type":"Services"
        }
    ],
    "sg:phone":"+44 1924 379078",
    "sg:postcode":"WF1 2HW",
    "sg:province":"West Yorkshire",
    "sg:tags":[
        "solicitor"
    ],
    "sg:website":"http://www.chadlaw.co.uk",
    "wof:name":"Chadwick Lawrence",
    "wof:placetype":"venue"
},
  "geometry": {"coordinates":[-1.5018490553,53.6849365234],"type":"Point"}
}