{
  "type": "Feature",
  "properties": {
    "iso:country":"GB",
    "sg:address":"Unit 2a Ellesmere Shpping Ctr, Bolton Road, Worsley",
    "sg:city":"Manchester",
    "sg:classifiers":[
        {
            "category":"Home & Garden",
            "subcategory":"Furniture",
            "type":"Retail Goods"
        }
    ],
    "sg:phone":"+44 161 702 6668",
    "sg:postcode":"M28 3ZD",
    "sg:province":"Greater Manchester",
    "wof:name":"The Sofa Co",
    "wof:placetype":"venue"
},
  "geometry": {"coordinates":[-2.401644,53.524807],"type":"Point"}
}