{
  "type": "Feature",
  "properties": {
    "iso:country":"GB",
    "sg:address":"5 Fulford Rd, Heavitree",
    "sg:city":"Exeter",
    "sg:classifiers":[
        {
            "category":"Building & Trades",
            "subcategory":"Construction",
            "type":"Services"
        }
    ],
    "sg:phone":"+44 1392 433179",
    "sg:postcode":"EX1 2UA",
    "sg:province":"Devon",
    "sg:tags":[
        "welder",
        "mechanical"
    ],
    "wof:name":"R.G Sandford",
    "wof:placetype":"venue"
},
  "geometry": {"coordinates":[-3.5034201145,50.7305526733],"type":"Point"}
}