{
  "type": "Feature",
  "properties": {
    "addr:full":"Unit 9 Riverside Place, 6 Bridgewater Rd Leeds West Yorkshire LS9 0RQ",
    "addr:housenumber":"unit 9;6",
    "addr:postcode":"ls9 0rq",
    "addr:street":"Riverside Place;Bridgewater Rd",
    "iso:country":"GB",
    "sg:address":"Unit 9 Riverside Place, 6 Bridgewater Rd",
    "sg:city":"Leeds",
    "sg:classifiers":[
        {
            "category":"Personal",
            "type":"Services"
        }
    ],
    "sg:phone":"+44 113 235 1313",
    "sg:postcode":"LS9 0RQ",
    "sg:province":"West Yorkshire",
    "sg:tags":[
        "delivery"
    ],
    "wof:name":"X P Express Parcels Ltd",
    "wof:placetype":"venue"
},
  "geometry": {"coordinates":[-1.5227400064,53.7861404419],"type":"Point"}
}