{
  "type": "Feature",
  "properties": {
    "iso:country":"GB",
    "sg:address":"68 Millman Street",
    "sg:city":"Bloomsbury",
    "sg:classifiers":[
        {
            "category":"Cafe",
            "type":"Food & Drink"
        }
    ],
    "sg:phone":"+44 20 7405 3697",
    "sg:postcode":"WC1N 3EF",
    "sg:province":"Greater London",
    "sg:tags":[
        "tea",
        "room"
    ],
    "wof:name":"Angelo's Coffee Shop",
    "wof:placetype":"venue"
},
  "geometry": {"coordinates":[-0.118259,51.523495],"type":"Point"}
}