{
  "type": "Feature",
  "properties": {
    "iso:country":"GB",
    "sg:address":"Within Bolton Crown Court, Blackhorse St",
    "sg:city":"Bolton",
    "sg:classifiers":[
        {
            "category":"Government",
            "subcategory":"Police Station",
            "type":"Public Place"
        }
    ],
    "sg:phone":"+44 1204 372119",
    "sg:postcode":"BL1 1SU",
    "sg:province":"Lancashire",
    "sg:tags":[
        "support"
    ],
    "wof:name":"Probation Service",
    "wof:placetype":"venue"
},
  "geometry": {"coordinates":[-2.4334290028,53.5787658691],"type":"Point"}
}