{
  "type": "Feature",
  "properties": {
    "iso:country":"GB",
    "sg:address":"Craigard, Grangemouth Road",
    "sg:city":"Bo'ness",
    "sg:classifiers":[
        {
            "category":"Professional",
            "subcategory":"Engineering",
            "type":"Services"
        }
    ],
    "sg:phone":"+44 1506 822774",
    "sg:postcode":"EH51 0PU",
    "sg:province":"Falkirk",
    "sg:tags":[
        "instrumentation",
        "engineer"
    ],
    "wof:name":"R & I Instruments Ltd.",
    "wof:placetype":"venue"
},
  "geometry": {"coordinates":[-3.6447000504,56.0061416626],"type":"Point"}
}