{
  "type": "Feature",
  "properties": {
    "addr:full":"320 Hamstead Road, Handsworth Birmingham West Midlands B20 2RA",
    "addr:housenumber":"320",
    "addr:postcode":"b20 2ra",
    "addr:street":"Hamstead Road",
    "iso:country":"GB",
    "sg:address":"320 Hamstead Road, Handsworth",
    "sg:city":"Birmingham",
    "sg:classifiers":[
        {
            "category":"Building & Trades",
            "subcategory":"Construction",
            "type":"Services"
        }
    ],
    "sg:phone":"+44 121 554 2347",
    "sg:postcode":"B20 2RA",
    "sg:province":"West Midlands",
    "sg:tags":[
        "builder"
    ],
    "wof:name":"Stubbs Bros (Handsworth) Ltd.",
    "wof:placetype":"venue"
},
  "geometry": {"coordinates":[-1.9206949472,52.512676239],"type":"Point"}
}