{
  "type": "Feature",
  "properties": {
    "addr:full":"Albert Mill, St Huberts Street, Great Harwood Blackburn Lancashire BB6 7BE",
    "addr:postcode":"bb6 7be",
    "addr:street":"Albert Mill St Huberts Street",
    "iso:country":"GB",
    "sg:address":"Albert Mill, St Huberts Street, Great Harwood",
    "sg:city":"Blackburn",
    "sg:classifiers":[
        {
            "category":"Building & Trades",
            "subcategory":"Plumbing",
            "type":"Services"
        }
    ],
    "sg:phone":"+44 1254 877222",
    "sg:postcode":"BB6 7BE",
    "sg:province":"Lancashire",
    "sg:tags":[
        "merchant",
        "plumbers'"
    ],
    "wof:name":"Accrington Plumbing Supplies",
    "wof:placetype":"venue"
},
  "geometry": {"coordinates":[-2.4076440334,53.7870140076],"type":"Point"}
}