{
  "type": "Feature",
  "properties": {
    "addr:full":"6 Newgate Street Morpeth Northumberland NE61 1BA",
    "addr:housenumber":"6",
    "addr:postcode":"ne61 1ba",
    "addr:street":"Newgate Street",
    "iso:country":"GB",
    "sg:address":"6 Newgate Street",
    "sg:city":"Morpeth",
    "sg:classifiers":[
        {
            "category":"Personal",
            "type":"Services"
        }
    ],
    "sg:phone":"+44 1670 519329",
    "sg:postcode":"NE61 1BA",
    "sg:province":"Northumberland",
    "sg:tags":[
        "tailor"
    ],
    "wof:name":"John Blades & Son Ltd.",
    "wof:placetype":"venue"
},
  "geometry": {"coordinates":[-1.6904950142,55.1677513123],"type":"Point"}
}