{
  "type": "Feature",
  "properties": {
    "iso:country":"GB",
    "sg:address":"St Marys Chambers",
    "sg:city":"Stone",
    "sg:classifiers":[
        {
            "category":"Professional",
            "subcategory":"Computer Services",
            "type":"Services"
        }
    ],
    "sg:phone":"+44 1785 818833",
    "sg:postcode":"ST15 8JP",
    "sg:province":"Staffordshire",
    "sg:tags":[
        "system",
        "software"
    ],
    "wof:name":"Game Computing",
    "wof:placetype":"venue"
},
  "geometry": {"coordinates":[-2.1422870159,52.9012184143],"type":"Point"}
}