{
  "type": "Feature",
  "properties": {
    "iso:country":"GB",
    "sg:address":"47a Church Balk, Edenthorpe",
    "sg:city":"Doncaster",
    "sg:classifiers":[
        {
            "category":"Social Services",
            "type":"Services"
        }
    ],
    "sg:phone":"+44 1302 887757",
    "sg:postcode":"DN3 2LX",
    "sg:province":"South Yorkshire",
    "sg:tags":[
        "need",
        "disability",
        "special"
    ],
    "wof:name":"Abbey Mobility",
    "wof:placetype":"venue"
},
  "geometry": {"coordinates":[-1.0731790066,53.5577316284],"type":"Point"}
}