{
  "type": "Feature",
  "properties": {
    "iso:country":"GB",
    "sg:address":"50 Tywardreath Highway",
    "sg:city":"Par",
    "sg:classifiers":[
        {
            "category":"Military Area",
            "subcategory":"Air Force Base",
            "type":"Public Place"
        }
    ],
    "sg:phone":"+44 1726 815212",
    "sg:postcode":"PL24 2RN",
    "sg:province":"Cornwall",
    "sg:tags":[
        "taxi",
        "hire",
        "private"
    ],
    "wof:name":"Alans Taxis",
    "wof:placetype":"venue"
},
  "geometry": {"coordinates":[-4.7119841576,50.357257843],"type":"Point"}
}