{
  "type": "Feature",
  "properties": {
    "iso:country":"GB",
    "sg:address":"19 Peel Street",
    "sg:city":"Bingley",
    "sg:classifiers":[
        {
            "category":"Building & Trades",
            "subcategory":"Construction",
            "type":"Services"
        }
    ],
    "sg:phone":"+44 1274 566365",
    "sg:postcode":"BD16 4QJ",
    "sg:province":"West Yorkshire",
    "sg:tags":[
        "roofing",
        "contracting"
    ],
    "wof:name":"S Edmondson",
    "wof:placetype":"venue"
},
  "geometry": {"coordinates":[-1.825647,53.848476],"type":"Point"}
}