{
  "type": "Feature",
  "properties": {
    "iso:country":"GB",
    "sg:address":"17 Daleside, Sacriston",
    "sg:city":"Durham",
    "sg:classifiers":[
        {
            "category":"Shopping",
            "subcategory":"Hobbies, Toys, & Games",
            "type":"Retail Goods"
        }
    ],
    "sg:postcode":"DH7 6BJ",
    "sg:province":"Durham",
    "sg:tags":[
        "shop"
    ],
    "wof:name":"Tartan Entertainment",
    "wof:placetype":"venue"
},
  "geometry": {"coordinates":[-1.6279970407,54.8264923096],"type":"Point"}
}