{
  "type": "Feature",
  "properties": {
    "iso:country":"GB",
    "sg:address":"Lime Lane, Pelsall",
    "sg:city":"Walsall",
    "sg:classifiers":[
        {
            "category":"Real Estate",
            "subcategory":"Real Estate Agent",
            "type":"Services"
        }
    ],
    "sg:phone":"+44 1543 373456",
    "sg:postcode":"WS3 5AS",
    "sg:province":"Staffordshire",
    "wof:name":"Yates Bros (Norton Canes) Ltd.",
    "wof:placetype":"venue"
},
  "geometry": {"coordinates":[-1.972943,52.657623],"type":"Point"}
}