{
  "type": "Feature",
  "properties": {
    "addr:full":"46-58 Dewsbury Road Wakefield West Yorkshire WF2 9BS",
    "addr:housenumber":"46-58",
    "addr:postcode":"wf2 9bs",
    "addr:street":"Dewsbury Road",
    "iso:country":"GB",
    "sg:address":"46-58 Dewsbury Road",
    "sg:city":"Wakefield",
    "sg:classifiers":[
        {
            "category":"Autos & Motor Vehicles",
            "subcategory":"Auto Supplies",
            "type":"Retail Goods"
        },
        {
            "category":"Shopping",
            "type":"Retail Goods"
        }
    ],
    "sg:phone":"+44 1924 200060",
    "sg:postcode":"WF2 9BS",
    "sg:province":"West Yorkshire",
    "sg:tags":[
        "car",
        "part",
        "accessory"
    ],
    "wof:name":"Motormania",
    "wof:placetype":"venue"
},
  "geometry": {"coordinates":[-1.5814369917,53.7274589539],"type":"Point"}
}