{
  "type": "Feature",
  "properties": {
    "iso:country":"GB",
    "sg:address":"Wheatley Hall Road",
    "sg:city":"Doncaster",
    "sg:classifiers":[
        {
            "category":"Autos & Motor Vehicles",
            "subcategory":"Auto Supplies",
            "type":"Retail Goods"
        }
    ],
    "sg:phone":"+44 1302 366631",
    "sg:postcode":"DN2 4QQ",
    "sg:province":"South Yorkshire",
    "sg:tags":[
        "agricultural"
    ],
    "wof:name":"Case United Kingdom Ltd.",
    "wof:placetype":"venue"
},
  "geometry": {"coordinates":[-1.122959,53.534065],"type":"Point"}
}