{
  "type": "Feature",
  "properties": {
    "iso:country":"GB",
    "sg:address":"28 Birches Rd",
    "sg:city":"Wolverhampton",
    "sg:classifiers":[
        {
            "category":"Banks & Credit Unions",
            "subcategory":"Financial Services",
            "type":"Services"
        }
    ],
    "sg:phone":"+44 1902 847944",
    "sg:postcode":"WV8 2JR",
    "sg:province":"Shropshire",
    "sg:tags":[
        "adviser"
    ],
    "wof:name":"B D H Insurance Services",
    "wof:placetype":"venue"
},
  "geometry": {"coordinates":[-2.176242,52.618668],"type":"Point"}
}