{
  "type": "Feature",
  "properties": {
    "addr:full":"533 Lord Street Southport Lancashire PR9 0BB",
    "addr:housenumber":"533",
    "addr:postcode":"pr9 0bb",
    "addr:street":"Lord Street",
    "iso:country":"GB",
    "sg:address":"533 Lord Street",
    "sg:city":"Southport",
    "sg:classifiers":[
        {
            "category":"Shopping",
            "subcategory":"Clothing, Apparel, & Fashions",
            "type":"Retail Goods"
        }
    ],
    "sg:phone":"+44 1704 533713",
    "sg:postcode":"PR9 0BB",
    "sg:province":"Lancashire",
    "sg:tags":[
        "shop"
    ],
    "wof:name":"Parisian Tailor Ltd.",
    "wof:placetype":"venue"
},
  "geometry": {"coordinates":[-3.001808,53.650574],"type":"Point"}
}