{
  "type": "Feature",
  "properties": {
    "addr:full":"Pengelli Treorchy Rhondda, Cynon, Taff CF42 6UL",
    "addr:postcode":"cf42 6ul",
    "addr:street":"Treorchy;Cynon Taff",
    "iso:country":"GB",
    "sg:address":"Pengelli",
    "sg:city":"Treorchy",
    "sg:classifiers":[
        {
            "category":"Education",
            "subcategory":"School",
            "type":"Public Place"
        },
        {
            "category":"Government",
            "subcategory":"Office",
            "type":"Public Place"
        }
    ],
    "sg:phone":"+44 1443 773128",
    "sg:postcode":"CF42 6UL",
    "sg:province":"Rhondda, Cynon, Taff",
    "sg:tags":[
        "local",
        "authority"
    ],
    "wof:name":"Treorchy Comprehensive School",
    "wof:placetype":"venue"
},
  "geometry": {"coordinates":[-3.512458,51.659012],"type":"Point"}
}