{
  "type": "Feature",
  "properties": {
    "addr:full":"13 Ewart Street, Chirk Wrexham Wrexham LL14 5LA",
    "addr:housenumber":"13",
    "addr:postcode":"ll14 5la",
    "addr:street":"Ewart Street",
    "iso:country":"GB",
    "sg:address":"13 Ewart Street, Chirk",
    "sg:city":"Wrexham",
    "sg:classifiers":[
        {
            "category":"Professional",
            "type":"Services"
        }
    ],
    "sg:postcode":"LL14 5LA",
    "sg:province":"Wrexham",
    "sg:tags":[
        "entertainer"
    ],
    "wof:name":"J Cliffson",
    "wof:placetype":"venue"
},
  "geometry": {"coordinates":[-3.0562150478,52.9416847229],"type":"Point"}
}