{
  "type": "Feature",
  "properties": {
    "iso:country":"GB",
    "sg:address":"12 Rise Cottages",
    "sg:city":"Ware",
    "sg:classifiers":[
        {
            "category":"Shopping",
            "subcategory":"Pharmacy",
            "type":"Retail Goods"
        }
    ],
    "sg:phone":"+44 1279 843565",
    "sg:postcode":"SG12 8SB",
    "sg:province":"Hertfordshire",
    "sg:tags":[
        "medicine",
        "therapy"
    ],
    "wof:name":"Pro-Health",
    "wof:placetype":"venue"
},
  "geometry": {"coordinates":[0.0554950014,51.8152961731],"type":"Point"}
}