{
  "type": "Feature",
  "properties": {
    "addr:full":"146 High Street Godalming Surrey GU7 1AB",
    "addr:housenumber":"146",
    "addr:postcode":"gu7 1ab",
    "addr:street":"High Street",
    "iso:country":"GB",
    "sg:address":"146 High Street",
    "sg:city":"Godalming",
    "sg:classifiers":[
        {
            "category":"Shopping",
            "subcategory":"Department Store",
            "type":"Retail Goods"
        }
    ],
    "sg:phone":"+44 1483 861359",
    "sg:postcode":"GU7 1AB",
    "sg:province":"Surrey",
    "wof:name":"The Music Shop At Godalming",
    "wof:placetype":"venue"
},
  "geometry": {"coordinates":[-0.6171870232,51.184677124],"type":"Point"}
}