{
  "type": "Feature",
  "properties": {
    "iso:country":"GB",
    "sg:address":"Redhouse Lane, Bredbury",
    "sg:city":"Stockport",
    "sg:classifiers":[
        {
            "category":"Bars & Pubs",
            "type":"Food & Drink"
        }
    ],
    "sg:phone":"+44 161 494 5746",
    "sg:postcode":"SK6 1BX",
    "sg:province":"Cheshire",
    "sg:tags":[
        "pubs",
        "inn"
    ],
    "wof:name":"The Samuel Webster",
    "wof:placetype":"venue"
},
  "geometry": {"coordinates":[-2.105032,53.423782],"type":"Point"}
}