{
  "type": "Feature",
  "properties": {
    "addr:full":"1 Loughton Villas, Western Road Crowborough East Sussex TN6 3ED",
    "addr:housenumber":"1",
    "addr:postcode":"tn6 3ed",
    "addr:street":"Loughton Villas Western Road",
    "iso:country":"GB",
    "sg:address":"1 Loughton Villas, Western Road",
    "sg:city":"Crowborough",
    "sg:classifiers":[
        {
            "category":"Building & Trades",
            "subcategory":"Construction",
            "type":"Services"
        }
    ],
    "sg:phone":"+44 1892 653865",
    "sg:postcode":"TN6 3ED",
    "sg:province":"East Sussex",
    "sg:tags":[
        "decorator",
        "painter"
    ],
    "wof:name":"F Puttock",
    "wof:placetype":"venue"
},
  "geometry": {"coordinates":[0.171893,51.053196],"type":"Point"}
}