{
  "type": "Feature",
  "properties": {
    "addr:full":"Valley Farm, Soar Lane, Sutton Bonington Loughborough Leicestershire LE12 5PH",
    "addr:postcode":"le12 5ph",
    "addr:street":"Valley;Soar Lane",
    "iso:country":"GB",
    "sg:address":"Valley Farm, Soar Lane, Sutton Bonington",
    "sg:city":"Loughborough",
    "sg:classifiers":[
        {
            "category":"Farming",
            "subcategory":"Dairy Farm",
            "type":"Manufacturing & Wholesale Goods"
        },
        {
            "category":"Farming",
            "subcategory":"Livestock Farm",
            "type":"Manufacturing & Wholesale Goods"
        }
    ],
    "sg:phone":"+44 1509 672574",
    "sg:postcode":"LE12 5PH",
    "sg:province":"Leicestershire",
    "sg:tags":[
        "others",
        "farmer"
    ],
    "wof:name":"MALTBY & REEVES",
    "wof:placetype":"venue"
},
  "geometry": {"coordinates":[-1.253779,52.823792],"type":"Point"}
}