{
  "type": "Feature",
  "properties": {
    "iso:country":"GB",
    "sg:address":"16 Augusta Road East",
    "sg:city":"Birmingham",
    "sg:classifiers":[
        {
            "category":"Health Services",
            "subcategory":"Nursing And Care Facility",
            "type":"Services"
        }
    ],
    "sg:phone":"+44 121 449 1841",
    "sg:postcode":"B13 8AJ",
    "sg:province":"West Midlands",
    "sg:tags":[
        "home"
    ],
    "wof:name":"Wilson Lodge",
    "wof:placetype":"venue"
},
  "geometry": {"coordinates":[-1.8896640539,52.4530525208],"type":"Point"}
}