{
  "type": "Feature",
  "properties": {
    "addr:full":"Wheatfields Park Worcester Worcestershire WR2 4UP",
    "addr:postcode":"wr2 4up",
    "iso:country":"GB",
    "sg:address":"Wheatfields Park",
    "sg:city":"Worcester",
    "sg:classifiers":[
        {
            "category":"Manufacturing",
            "subcategory":"Buildings",
            "type":"Manufacturing & Wholesale Goods"
        }
    ],
    "sg:phone":"+44 1905 830079",
    "sg:postcode":"WR2 4UP",
    "sg:province":"Worcestershire",
    "sg:tags":[
        "mobile",
        "home"
    ],
    "wof:name":"Wheatfield Residential Park",
    "wof:placetype":"venue"
},
  "geometry": {"coordinates":[-2.242939949,52.1504898071],"type":"Point"}
}