{
  "type": "Feature",
  "properties": {
    "addr:full":"69 Station Road, Filtwick Bedford Bedfordshire MK45 1JU",
    "addr:housenumber":"69",
    "addr:postcode":"mk45 1ju",
    "addr:street":"Station Road Filtwick",
    "iso:country":"GB",
    "sg:address":"69 Station Road, Filtwick",
    "sg:city":"Bedford",
    "sg:classifiers":[
        {
            "category":"Professional",
            "subcategory":"Printing & Photocopies",
            "type":"Services"
        }
    ],
    "sg:postcode":"MK45 1JU",
    "sg:province":"Bedfordshire",
    "sg:tags":[
        "plate",
        "printer",
        "lithographic",
        "maker"
    ],
    "wof:name":"Lister & Durling Printers",
    "wof:placetype":"venue"
},
  "geometry": {"coordinates":[-0.488313,52.001503],"type":"Point"}
}