{
  "type": "Feature",
  "properties": {
    "iso:country":"GB",
    "sg:address":"Unit 17, Bankside Coverack Road",
    "sg:city":"Newport",
    "sg:classifiers":[
        {
            "category":"Building & Trades",
            "subcategory":"Construction",
            "type":"Services"
        }
    ],
    "sg:phone":"+44 1633 253671",
    "sg:postcode":"NP19 0DS",
    "sg:province":"Newport",
    "sg:tags":[
        "roofing"
    ],
    "wof:name":"David Truelove",
    "wof:placetype":"venue"
},
  "geometry": {"coordinates":[-2.9811139107,51.5857315063],"type":"Point"}
}