{
  "type": "Feature",
  "properties": {
    "addr:full":"Swallowfield Street Reading Berkshire RG7 1QQ",
    "addr:postcode":"rg7 1qq",
    "addr:street":"Swallowfield Street",
    "iso:country":"GB",
    "sg:address":"Swallowfield Street",
    "sg:city":"Reading",
    "sg:classifiers":[
        {
            "category":"Shopping",
            "type":"Retail Goods"
        }
    ],
    "sg:postcode":"RG7 1QQ",
    "sg:province":"Berkshire",
    "sg:tags":[
        "part",
        "accessory"
    ],
    "wof:name":"Swallowfield Volvo Specialists",
    "wof:placetype":"venue"
},
  "geometry": {"coordinates":[-0.966979,51.375095],"type":"Point"}
}