{
  "type": "Feature",
  "properties": {
    "addr:full":"Unit 1 Northgate, White Lund Industrial Estate Morecambe Lancashire LA3 3AY",
    "addr:housenumber":"unit 1",
    "addr:postcode":"la3 3ay",
    "addr:street":"Northgate White Lund Industrial Estate",
    "iso:country":"GB",
    "sg:address":"Unit 1 Northgate, White Lund Industrial Estate",
    "sg:city":"Morecambe",
    "sg:classifiers":[
        {
            "category":"Retail",
            "subcategory":"Auto Rental",
            "type":"Services"
        }
    ],
    "sg:phone":"+44 1524 64844",
    "sg:postcode":"LA3 3AY",
    "sg:province":"Lancashire",
    "sg:tags":[
        "car"
    ],
    "wof:name":"Enterprise Rent-A-Car",
    "wof:placetype":"venue"
},
  "geometry": {"coordinates":[-2.834924,54.059135],"type":"Point"}
}