{
  "type": "Feature",
  "properties": {
    "addr:full":"Moss Road Newcastleton Cumbria TD9 0RN",
    "addr:postcode":"td9 0rn",
    "addr:street":"Moss Road",
    "iso:country":"GB",
    "sg:address":"Moss Road",
    "sg:city":"Newcastleton",
    "sg:classifiers":[
        {
            "category":"Health Services",
            "subcategory":"Doctor",
            "type":"Services"
        }
    ],
    "sg:phone":"+44 13873 75202",
    "sg:postcode":"TD9 0RN",
    "sg:province":"Cumbria",
    "sg:tags":[
        "practitioners"
    ],
    "wof:name":"Borders Health Board",
    "wof:placetype":"venue"
},
  "geometry": {"coordinates":[-2.811999,55.181694],"type":"Point"}
}