{
  "type": "Feature",
  "properties": {
    "iso:country":"GB",
    "sg:address":"Whithorn Community Centre, Castlehill, Whithorn",
    "sg:city":"Newton Stewart",
    "sg:classifiers":[
        {
            "category":"Education",
            "subcategory":"Preschool",
            "type":"Public Place"
        }
    ],
    "sg:phone":"+44 1988 500902",
    "sg:postcode":"DG8 8PQ",
    "sg:province":"Dumfries and Galloway",
    "sg:tags":[
        "pre-school",
        "playgroups"
    ],
    "wof:name":"Southern Machars Playcare",
    "wof:placetype":"venue"
},
  "geometry": {"coordinates":[-4.415584,54.733227],"type":"Point"}
}