{
  "type": "Feature",
  "properties": {
    "addr:full":"3-5 King St Ramsgate Kent CT11 8NN",
    "addr:housenumber":"3-5",
    "addr:postcode":"ct11 8nn",
    "addr:street":"King St",
    "iso:country":"GB",
    "sg:address":"3-5 King St",
    "sg:city":"Ramsgate",
    "sg:classifiers":[
        {
            "category":"Shopping",
            "subcategory":"Clothing, Apparel, & Fashions",
            "type":"Retail Goods"
        }
    ],
    "sg:phone":"+44 1843 851401",
    "sg:postcode":"CT11 8NN",
    "sg:province":"Kent",
    "sg:tags":[
        "shop"
    ],
    "wof:name":"Leather Land",
    "wof:placetype":"venue"
},
  "geometry": {"coordinates":[1.4200370312,51.3336296082],"type":"Point"}
}