{
  "type": "Feature",
  "properties": {
    "iso:country":"GB",
    "sg:address":"Unit 16, Oyster Place, Montrose Rd",
    "sg:city":"Chelmsford",
    "sg:classifiers":[
        {
            "category":"Professional",
            "subcategory":"Printing & Photocopies",
            "type":"Services"
        }
    ],
    "sg:phone":"+44 1245 467773",
    "sg:postcode":"CM2 6TX",
    "sg:province":"Essex",
    "sg:tags":[
        "process",
        "screen",
        "printer"
    ],
    "wof:name":"Mesh Works",
    "wof:placetype":"venue"
},
  "geometry": {"coordinates":[0.50201,51.742271],"type":"Point"}
}