{
  "type": "Feature",
  "properties": {
    "iso:country":"GB",
    "sg:address":"4 Park Road, Cults",
    "sg:city":"Aberdeen",
    "sg:classifiers":[
        {
            "category":"Building & Trades",
            "subcategory":"Construction",
            "type":"Services"
        }
    ],
    "sg:phone":"+44 1224 862000",
    "sg:postcode":"AB15 9HR",
    "sg:province":"Aberdeen City",
    "sg:tags":[
        "joiner",
        "carpenter"
    ],
    "wof:name":"Cruickshank & Gordon",
    "wof:placetype":"venue"
},
  "geometry": {"coordinates":[-2.179091,57.114906],"type":"Point"}
}