{
  "type": "Feature",
  "properties": {
    "addr:full":"106 Heath Street Hampstead Greater London NW3 1DR",
    "addr:housenumber":"106",
    "addr:postcode":"nw3 1dr",
    "addr:street":"Heath Street",
    "iso:country":"GB",
    "sg:address":"106 Heath Street",
    "sg:city":"Hampstead",
    "sg:classifiers":[
        {
            "category":"Shopping",
            "subcategory":"Antiques",
            "type":"Retail Goods"
        }
    ],
    "sg:phone":"+44 20 7431 9560",
    "sg:postcode":"NW3 1DR",
    "sg:province":"Greater London",
    "wof:name":"Invernizzi Antiques",
    "wof:placetype":"venue"
},
  "geometry": {"coordinates":[-0.179636,51.561829],"type":"Point"}
}