{
  "type": "Feature",
  "properties": {
    "iso:country":"GB",
    "sg:address":"129 North Road, Stoke Gifford",
    "sg:city":"Bristol",
    "sg:classifiers":[
        {
            "category":"Health Services",
            "subcategory":"Podiatrist",
            "type":"Services"
        }
    ],
    "sg:phone":"+44 117 931 1261",
    "sg:postcode":"BS34 8PE",
    "sg:province":"Gloucestershire",
    "sg:tags":[
        "podiatrists",
        "chiropodist"
    ],
    "wof:name":"V W Collins",
    "wof:placetype":"venue"
},
  "geometry": {"coordinates":[-2.54213,51.51627],"type":"Point"}
}