{
  "type": "Feature",
  "properties": {
    "iso:country":"GB",
    "sg:address":"Main Road, Filby",
    "sg:city":"Great Yarmouth",
    "sg:classifiers":[
        {
            "category":"Government",
            "subcategory":"Post Office",
            "type":"Public Place"
        }
    ],
    "sg:phone":"+44 1493 369250",
    "sg:postcode":"NR29 3AA",
    "sg:province":"Norfolk",
    "wof:name":"Filby Post Office",
    "wof:placetype":"venue"
},
  "geometry": {"coordinates":[1.586785,52.661045],"type":"Point"}
}