{
  "type": "Feature",
  "properties": {
    "iso:country":"GB",
    "sg:address":"17 Armitage Close, Rhodes, Middleton",
    "sg:city":"Manchester",
    "sg:classifiers":[
        {
            "category":"Professional",
            "subcategory":"Computer Services",
            "type":"Services"
        }
    ],
    "sg:phone":"+44 161 654 6507",
    "sg:postcode":"M24 4PA",
    "sg:province":"Greater Manchester",
    "sg:tags":[
        "system",
        "software"
    ],
    "wof:name":"Tech Installations (Computers) Ltd.",
    "wof:placetype":"venue"
},
  "geometry": {"coordinates":[-2.216957,53.545464],"type":"Point"}
}