{
  "type": "Feature",
  "properties": {
    "iso:country":"GB",
    "sg:address":"The Ridgeway, Woodnesborough Road",
    "sg:city":"Sandwich",
    "sg:classifiers":[
        {
            "category":"Wholesale",
            "subcategory":"Fruits & Vegetables",
            "type":"Manufacturing & Wholesale Goods"
        }
    ],
    "sg:postcode":"CT13 0BA",
    "sg:province":"Kent",
    "wof:name":"H J Durban & Son",
    "wof:placetype":"venue"
},
  "geometry": {"coordinates":[1.306945,51.262691],"type":"Point"}
}