{
  "type": "Feature",
  "properties": {
    "addr:full":"17 Ongar Rd Brentwood Essex CM15 9AU",
    "addr:housenumber":"17",
    "addr:postcode":"cm15 9au",
    "addr:street":"Ongar Rd",
    "iso:country":"GB",
    "sg:address":"17 Ongar Rd",
    "sg:city":"Brentwood",
    "sg:classifiers":[
        {
            "category":"Bars & Pubs",
            "type":"Food & Drink"
        }
    ],
    "sg:phone":"+44 1277 212676",
    "sg:postcode":"CM15 9AU",
    "sg:province":"Essex",
    "sg:tags":[
        "pubs",
        "inn"
    ],
    "wof:name":"Punch Retail (Holdings) Ltd",
    "wof:placetype":"venue"
},
  "geometry": {"coordinates":[0.305024,51.622257],"type":"Point"}
}