{
  "type": "Feature",
  "properties": {
    "addr:full":"2 Upper High Street Bargoed Caerphilly CF81 8QY",
    "addr:housenumber":"2",
    "addr:postcode":"cf81 8qy",
    "addr:street":"Upper High Street",
    "iso:country":"GB",
    "sg:address":"2 Upper High Street",
    "sg:city":"Bargoed",
    "sg:classifiers":[
        {
            "category":"Fast Food",
            "type":"Food & Drink"
        }
    ],
    "sg:phone":"+44 1443 831063",
    "sg:postcode":"CF81 8QY",
    "sg:province":"Caerphilly",
    "sg:tags":[
        "away",
        "meal",
        "outlet",
        "take"
    ],
    "wof:name":"The Continental Restaurant",
    "wof:placetype":"venue"
},
  "geometry": {"coordinates":[-3.2302050591,51.6913528442],"type":"Point"}
}