{
  "type": "Feature",
  "properties": {
    "addr:full":"Little Tye, Upper Hartfield Hartfield East Sussex TN7 4DX",
    "addr:postcode":"tn7 4dx",
    "iso:country":"GB",
    "sg:address":"Little Tye, Upper Hartfield",
    "sg:city":"Hartfield",
    "sg:classifiers":[
        {
            "category":"Professional",
            "type":"Services"
        }
    ],
    "sg:phone":"+44 1342 822427",
    "sg:postcode":"TN7 4DX",
    "sg:province":"East Sussex",
    "sg:tags":[
        "entertainer"
    ],
    "wof:name":"Holland,David,",
    "wof:placetype":"venue"
},
  "geometry": {"coordinates":[0.111161001,51.1034889221],"type":"Point"}
}