{
  "type": "Feature",
  "properties": {
    "iso:country":"GB",
    "sg:address":"Little Baldon House, Little Baldon",
    "sg:city":"Oxford",
    "sg:classifiers":[
        {
            "category":"Professional",
            "subcategory":"Research",
            "type":"Services"
        }
    ],
    "sg:phone":"+44 1865 788000",
    "sg:postcode":"OX44 9PU",
    "sg:province":"Oxfordshire",
    "sg:tags":[
        "market"
    ],
    "wof:name":"Market Research Solutions Ltd.",
    "wof:placetype":"venue"
},
  "geometry": {"coordinates":[-1.1797189713,51.6808815002],"type":"Point"}
}