{
  "type": "Feature",
  "properties": {
    "addr:full":"264 Grand Drive, Raynes Park London Greater London SW20 9NE",
    "addr:housenumber":"264",
    "addr:postcode":"sw20 9ne",
    "addr:street":"Grand Drive Raynes Park",
    "iso:country":"GB",
    "sg:address":"264 Grand Drive, Raynes Park",
    "sg:city":"London",
    "sg:classifiers":[
        {
            "category":"Autos & Motor Vehicles",
            "subcategory":"Motorcycle Sales",
            "type":"Retail Goods"
        }
    ],
    "sg:phone":"+44 20 8543 0321",
    "sg:postcode":"SW20 9NE",
    "sg:province":"Greater London",
    "wof:name":"Wheelpower Bike Centre Ltd.",
    "wof:placetype":"venue"
},
  "geometry": {"coordinates":[-0.2237470001,51.3933753967],"type":"Point"}
}