{
  "type": "Feature",
  "properties": {
    "addr:full":"South Staffs Business Park Cannock Staffordshire WS11 0XU",
    "addr:postcode":"ws11 0xu",
    "addr:street":"South;Business Park",
    "iso:country":"GB",
    "sg:address":"South Staffs Business Park",
    "sg:city":"Cannock",
    "sg:classifiers":[
        {
            "category":"Shopping",
            "subcategory":"Gifts & Souvenirs",
            "type":"Retail Goods"
        }
    ],
    "sg:phone":"+44 1922 415777",
    "sg:postcode":"WS11 0XU",
    "sg:province":"Staffordshire",
    "sg:tags":[
        "ducting"
    ],
    "wof:name":"S W Ductwork Ltd.",
    "wof:placetype":"venue"
},
  "geometry": {"coordinates":[-2.033145,52.690952],"type":"Point"}
}