{
  "type": "Feature",
  "properties": {
    "iso:country":"GB",
    "sg:address":"1st Floor, 15 High St",
    "sg:city":"Reading",
    "sg:classifiers":[
        {
            "category":"Health Services",
            "subcategory":"Dentist",
            "type":"Services"
        }
    ],
    "sg:phone":"+44 118 930 5205",
    "sg:postcode":"RG7 5AH",
    "sg:province":"Berkshire",
    "wof:name":"Abacus Dental Practice",
    "wof:placetype":"venue"
},
  "geometry": {"coordinates":[-1.075818,51.437538],"type":"Point"}
}