{
  "type": "Feature",
  "properties": {
    "addr:full":"The Harbour Troon South Ayrshire KA10 6DH",
    "addr:postcode":"ka10 6dh",
    "iso:country":"GB",
    "sg:address":"The Harbour",
    "sg:city":"Troon",
    "sg:classifiers":[
        {
            "category":"Recreation",
            "subcategory":"Sailing Club",
            "type":"Entertainment"
        }
    ],
    "sg:phone":"+44 1292 311190",
    "sg:postcode":"KA10 6DH",
    "sg:province":"South Ayrshire",
    "wof:name":"Troon Cruising Club",
    "wof:placetype":"venue"
},
  "geometry": {"coordinates":[-4.6537041664,55.5463142395],"type":"Point"}
}