{
  "type": "Feature",
  "properties": {
    "iso:country":"GB",
    "sg:address":"1a Market Place, South Normanton",
    "sg:city":"Alfreton",
    "sg:classifiers":[
        {
            "category":"Shopping",
            "subcategory":"Clothing, Apparel, & Fashions",
            "type":"Retail Goods"
        }
    ],
    "sg:postcode":"DE55 2BN",
    "sg:province":"Derbyshire",
    "sg:tags":[
        "clothing",
        "fabric"
    ],
    "wof:name":"Keeley Anna",
    "wof:placetype":"venue"
},
  "geometry": {"coordinates":[-1.3425680399,53.1059532166],"type":"Point"}
}