{
  "type": "Feature",
  "properties": {
    "iso:country":"GB",
    "sg:address":"43a Leigh Road",
    "sg:city":"Eastleigh",
    "sg:classifiers":[
        {
            "category":"Bakery",
            "type":"Food & Drink"
        }
    ],
    "sg:phone":"+44 23 8065 0200",
    "sg:postcode":"SO50 9DD",
    "sg:province":"Hampshire",
    "sg:tags":[
        "cake",
        "maker"
    ],
    "wof:name":"Celebrations",
    "wof:placetype":"venue"
},
  "geometry": {"coordinates":[-1.353736,50.969296],"type":"Point"}
}