{
  "type": "Feature",
  "properties": {
    "addr:full":"11 Brookgate, South Liberty Lane Bristol City of Bristol BS3 2UN",
    "addr:housenumber":"11",
    "addr:postcode":"bs3 2un",
    "addr:street":"Brookgate South Liberty Lane",
    "iso:country":"GB",
    "sg:address":"11 Brookgate, South Liberty Lane",
    "sg:city":"Bristol",
    "sg:classifiers":[
        {
            "category":"Shopping",
            "subcategory":"Stationery & Office Supplies",
            "type":"Retail Goods"
        }
    ],
    "sg:postcode":"BS3 2UN",
    "sg:province":"City of Bristol",
    "sg:tags":[
        "box",
        "carton"
    ],
    "wof:name":"Forton Packaging Ltd.",
    "wof:placetype":"venue"
},
  "geometry": {"coordinates":[-2.611914,51.432545],"type":"Point"}
}