{
  "type": "Feature",
  "properties": {
    "addr:full":"132 Queen Street Crewe Cheshire CW1 4AU",
    "addr:housenumber":"132",
    "addr:postcode":"cw1 4au",
    "addr:street":"Queen Street",
    "iso:country":"GB",
    "sg:address":"132 Queen Street",
    "sg:city":"Crewe",
    "sg:classifiers":[
        {
            "category":"Building & Trades",
            "subcategory":"Cleaning & Sanitation",
            "type":"Services"
        },
        {
            "category":"Professional",
            "subcategory":"Employment Agencies",
            "type":"Services"
        }
    ],
    "sg:phone":"+44 1270 254655",
    "sg:postcode":"CW1 4AU",
    "sg:province":"Cheshire",
    "sg:tags":[
        "repairing",
        "corrosion",
        "tank",
        "prevention"
    ],
    "sg:website":"http://www.jayrubberlinings.co.uk",
    "wof:name":"Jay Rubber Linings Ltd.",
    "wof:placetype":"venue"
},
  "geometry": {"coordinates":[-2.429028,53.102772],"type":"Point"}
}