{
  "type": "Feature",
  "properties": {
    "addr:full":"The Lilacs, Chapel Rd, Roughton Norwich Norfolk NR11 8QP",
    "addr:postcode":"nr11 8qp",
    "addr:street":"Chapel Rd;Norwich",
    "iso:country":"GB",
    "sg:address":"The Lilacs, Chapel Rd, Roughton",
    "sg:city":"Norwich",
    "sg:classifiers":[
        {
            "category":"Building & Trades",
            "subcategory":"Construction",
            "type":"Services"
        }
    ],
    "sg:phone":"+44 1263 768880",
    "sg:postcode":"NR11 8QP",
    "sg:province":"Norfolk",
    "sg:tags":[
        "decorator",
        "painter"
    ],
    "wof:name":"D Quigley",
    "wof:placetype":"venue"
},
  "geometry": {"coordinates":[1.29766,52.88393],"type":"Point"}
}