{
  "type": "Feature",
  "properties": {
    "addr:full":"26 South Main Street, Wigtown Newton Stewart Dumfries and Galloway DG8 9EH",
    "addr:housenumber":"26",
    "addr:postcode":"dg8 9eh",
    "addr:street":"South Main Street",
    "iso:country":"GB",
    "sg:address":"26 South Main Street, Wigtown",
    "sg:city":"Newton Stewart",
    "sg:classifiers":[
        {
            "category":"Professional",
            "subcategory":"Management & Consulting",
            "type":"Services"
        }
    ],
    "sg:postcode":"DG8 9EH",
    "sg:province":"Dumfries and Galloway",
    "sg:tags":[
        "marketing",
        "consultant"
    ],
    "wof:name":"Wigtown Book Town Co. Ltd.",
    "wof:placetype":"venue"
},
  "geometry": {"coordinates":[-4.4434399605,54.8675689697],"type":"Point"}
}