{
  "type": "Feature",
  "properties": {
    "iso:country":"GB",
    "sg:address":"901 Ringwood Rd",
    "sg:city":"Bournemouth",
    "sg:classifiers":[
        {
            "category":"Home & Garden",
            "subcategory":"Home Furnishings",
            "type":"Retail Goods"
        }
    ],
    "sg:phone":"+44 1202 590796",
    "sg:postcode":"BH11 8LR",
    "sg:province":"Dorset",
    "sg:tags":[
        "beds",
        "bedding",
        "blanket"
    ],
    "wof:name":"Bensons Bed Centres Ltd",
    "wof:placetype":"venue"
},
  "geometry": {"coordinates":[-1.927123,50.757507],"type":"Point"}
}