{
  "type": "Feature",
  "properties": {
    "addr:full":"Houghton Road, North Anston Trading Estate Sheffield South Yorkshire S25 4JJ",
    "addr:postcode":"s25 4jj",
    "addr:street":"Houghton Road North Anston Trading Estate",
    "iso:country":"GB",
    "sg:address":"Houghton Road, North Anston Trading Estate",
    "sg:city":"Sheffield",
    "sg:classifiers":[
        {
            "category":"Shopping",
            "subcategory":"Pets & Pet Supplies",
            "type":"Retail Goods"
        }
    ],
    "sg:postcode":"S25 4JJ",
    "sg:province":"South Yorkshire",
    "sg:tags":[
        "food"
    ],
    "wof:name":"The Mealworm Co. Ltd.",
    "wof:placetype":"venue"
},
  "geometry": {"coordinates":[-1.2345279455,53.3643188477],"type":"Point"}
}