{
  "type": "Feature",
  "properties": {
    "iso:country":"GB",
    "sg:address":"Beaufort House, Hamble Lane, Bursledon",
    "sg:city":"Southampton",
    "sg:classifiers":[
        {
            "category":"Government",
            "subcategory":"Office",
            "type":"Public Place"
        }
    ],
    "sg:phone":"+44 23 8040 3716",
    "sg:postcode":"SO31 8BR",
    "sg:province":"Hampshire",
    "sg:tags":[
        "local"
    ],
    "wof:name":"Hampshire Rent Officer Service",
    "wof:placetype":"venue"
},
  "geometry": {"coordinates":[-1.321381,50.895042],"type":"Point"}
}