{
  "type": "Feature",
  "properties": {
    "addr:full":"Unit 9, Kilburn Drive, Seaview Industrial Estate Peterlee Durham SR8 4TQ",
    "addr:housenumber":"unit 9",
    "addr:postcode":"sr8 4tq",
    "addr:street":"Kilburn Drive;Industrial Estate",
    "iso:country":"GB",
    "sg:address":"Unit 9, Kilburn Drive, Seaview Industrial Estate",
    "sg:city":"Peterlee",
    "sg:classifiers":[
        {
            "category":"Shopping",
            "subcategory":"Bicycles & Sporting Goods",
            "type":"Retail Goods"
        }
    ],
    "sg:phone":"+44 191 586 6964",
    "sg:postcode":"SR8 4TQ",
    "sg:province":"Durham",
    "sg:tags":[
        "equipment",
        "marine",
        "supply"
    ],
    "wof:name":"B & H Exchangers Ltd.",
    "wof:placetype":"venue"
},
  "geometry": {"coordinates":[-1.3193720579,54.7734146118],"type":"Point"}
}