{
  "type": "Feature",
  "properties": {
    "addr:full":"49 Higher Lane Lymm Cheshire WA13 0BA",
    "addr:housenumber":"49",
    "addr:postcode":"wa13 0ba",
    "addr:street":"Higher Lane",
    "iso:country":"GB",
    "sg:address":"49 Higher Lane",
    "sg:city":"Lymm",
    "sg:classifiers":[
        {
            "category":"Food & Beverages",
            "subcategory":"Groceries & Convenience Stores",
            "type":"Retail Goods"
        }
    ],
    "sg:phone":"+44 1925 752125",
    "sg:postcode":"WA13 0BA",
    "sg:province":"Cheshire",
    "wof:name":"J Morcom",
    "wof:placetype":"venue"
},
  "geometry": {"coordinates":[-2.4721031189,53.3769378662],"type":"Point"}
}