{
  "type": "Feature",
  "properties": {
    "addr:full":"Marshburn, Fetternear Inverurie Aberdeenshire AB51 5JY",
    "addr:postcode":"ab51 5jy",
    "iso:country":"GB",
    "sg:address":"Marshburn, Fetternear",
    "sg:city":"Inverurie",
    "sg:classifiers":[
        {
            "category":"Freight",
            "type":"Transportation"
        }
    ],
    "sg:postcode":"AB51 5JY",
    "sg:province":"Aberdeenshire",
    "sg:tags":[
        "haulage",
        "road"
    ],
    "wof:name":"Newland,Ian,",
    "wof:placetype":"venue"
},
  "geometry": {"coordinates":[-2.4686090946,57.2380599976],"type":"Point"}
}