{
  "type": "Feature",
  "properties": {
    "addr:full":"21 Laburnum Way, Cheadle Heath Stockport Cheshire SK3 0LP",
    "addr:housenumber":"21",
    "addr:postcode":"sk3 0lp",
    "addr:street":"Laburnum Way",
    "iso:country":"GB",
    "sg:address":"21 Laburnum Way, Cheadle Heath",
    "sg:city":"Stockport",
    "sg:classifiers":[
        {
            "category":"Building & Trades",
            "subcategory":"Plumbing",
            "type":"Services"
        }
    ],
    "sg:postcode":"SK3 0LP",
    "sg:province":"Cheshire",
    "sg:tags":[
        "heating"
    ],
    "wof:name":"Pullin,Geoffrey,Plumbing & Heating",
    "wof:placetype":"venue"
},
  "geometry": {"coordinates":[-2.1824519634,53.4051818848],"type":"Point"}
}