{
  "type": "Feature",
  "properties": {
    "addr:full":"Warrens Hill Cheddar Somerset BS27 3LP",
    "addr:postcode":"bs27 3lp",
    "addr:street":"Warrens Hill",
    "iso:country":"GB",
    "sg:address":"Warrens Hill",
    "sg:city":"Cheddar",
    "sg:classifiers":[
        {
            "category":"Freight",
            "type":"Transportation"
        }
    ],
    "sg:phone":"+44 1934 742387",
    "sg:postcode":"BS27 3LP",
    "sg:province":"Somerset",
    "sg:tags":[
        "haulage",
        "road"
    ],
    "wof:name":"Circlepride Ltd.",
    "wof:placetype":"venue"
},
  "geometry": {"coordinates":[-2.777929,51.285015],"type":"Point"}
}