{
  "type": "Feature",
  "properties": {
    "addr:full":"20c St Charles Square London Greater London W10 6EE",
    "addr:housenumber":"20c",
    "addr:postcode":"w10 6ee",
    "addr:street":"St Charles Square",
    "iso:country":"GB",
    "sg:address":"20c St Charles Square",
    "sg:city":"London",
    "sg:classifiers":[
        {
            "category":"Professional",
            "subcategory":"Management & Consulting",
            "type":"Services"
        }
    ],
    "sg:postcode":"W10 6EE",
    "sg:province":"Greater London",
    "sg:tags":[
        "consultant",
        "business"
    ],
    "wof:name":"British Pacific Industries Ltd",
    "wof:placetype":"venue"
},
  "geometry": {"coordinates":[-0.212979,51.520969],"type":"Point"}
}