{
  "type": "Feature",
  "properties": {
    "addr:full":"2 Princess Street Knutsford Cheshire WA16 6DD",
    "addr:housenumber":"2",
    "addr:postcode":"wa16 6dd",
    "addr:street":"Princess Street",
    "iso:country":"GB",
    "sg:address":"2 Princess Street",
    "sg:city":"Knutsford",
    "sg:classifiers":[
        {
            "category":"Home & Garden",
            "subcategory":"Home Furnishings",
            "type":"Retail Goods"
        }
    ],
    "sg:postcode":"WA16 6DD",
    "sg:province":"Cheshire",
    "sg:tags":[
        "blind",
        "curtain",
        "fitting"
    ],
    "wof:name":"Simon Boyd",
    "wof:placetype":"venue"
},
  "geometry": {"coordinates":[-2.3747429848,53.3035011292],"type":"Point"}
}