{
  "type": "Feature",
  "properties": {
    "iso:country":"GB",
    "sg:address":"10 Cross Street",
    "sg:city":"Wakefield",
    "sg:classifiers":[
        {
            "category":"Shopping",
            "subcategory":"Clothing, Apparel, & Fashions",
            "type":"Retail Goods"
        }
    ],
    "sg:phone":"+44 1924 366337",
    "sg:postcode":"WF1 3BW",
    "sg:province":"West Yorkshire",
    "sg:tags":[
        "shop"
    ],
    "wof:name":"Roccola Ladies Fashions",
    "wof:placetype":"venue"
},
  "geometry": {"coordinates":[-1.499868,53.684086],"type":"Point"}
}