{
  "type": "Feature",
  "properties": {
    "addr:full":"Unit 10, Churnit Works, Macclesfield Road Leek Staffordshire ST13 8XY",
    "addr:housenumber":"unit 10",
    "addr:postcode":"st13 8xy",
    "addr:street":"Macclesfield Road",
    "iso:country":"GB",
    "sg:address":"Unit 10, Churnit Works, Macclesfield Road",
    "sg:city":"Leek",
    "sg:classifiers":[
        {
            "category":"Manufacturing",
            "subcategory":"Paper Products",
            "type":"Manufacturing & Wholesale Goods"
        }
    ],
    "sg:phone":"+44 1538 384202",
    "sg:postcode":"ST13 8XY",
    "sg:province":"Staffordshire",
    "sg:tags":[
        "cardboard"
    ],
    "wof:name":"Papermarc Tubes Ltd.",
    "wof:placetype":"venue"
},
  "geometry": {"coordinates":[-2.04102,53.11092],"type":"Point"}
}