{
  "type": "Feature",
  "properties": {
    "iso:country":"GB",
    "sg:address":"2-4 Arkwright Court",
    "sg:city":"Blackpool",
    "sg:classifiers":[
        {
            "category":"Professional",
            "subcategory":"Detective & Security Services",
            "type":"Services"
        }
    ],
    "sg:phone":"+44 1253 791888",
    "sg:postcode":"FY4 5DR",
    "sg:province":"Lancashire",
    "sg:tags":[
        "equipment"
    ],
    "wof:name":"Challenger Security Products",
    "wof:placetype":"venue"
},
  "geometry": {"coordinates":[-2.999967,53.792313],"type":"Point"}
}