{
  "type": "Feature",
  "properties": {
    "iso:country":"GB",
    "sg:address":"Portobello Road",
    "sg:city":"Edinburgh",
    "sg:classifiers":[
        {
            "category":"Autos & Motor Vehicles",
            "subcategory":"Automobile Sales",
            "type":"Retail Goods"
        }
    ],
    "sg:phone":"+44 131 669 9133",
    "sg:postcode":"EH7 6TJ",
    "sg:province":"City of Edinburgh",
    "sg:tags":[
        "car"
    ],
    "wof:name":"Rosslea",
    "wof:placetype":"venue"
},
  "geometry": {"coordinates":[-3.1233940125,55.9575843811],"type":"Point"}
}