{
  "type": "Feature",
  "properties": {
    "addr:full":"102 Ayr Road, Newton Mearns Glasgow East Ayrshire G77 6EF",
    "addr:housenumber":"102",
    "addr:postcode":"g77 6ef",
    "addr:street":"Ayr Road",
    "iso:country":"GB",
    "sg:address":"102 Ayr Road, Newton Mearns",
    "sg:city":"Glasgow",
    "sg:classifiers":[
        {
            "category":"Real Estate",
            "subcategory":"Real Estate Agent",
            "type":"Services"
        }
    ],
    "sg:phone":"+44 141 616 2424",
    "sg:postcode":"G77 6EF",
    "sg:province":"East Ayrshire",
    "wof:name":"Allen & Harris",
    "wof:placetype":"venue"
},
  "geometry": {"coordinates":[-4.321273,55.779079],"type":"Point"}
}