{
  "type": "Feature",
  "properties": {
    "iso:country":"GB",
    "sg:address":"1 Harestone Valley Road",
    "sg:city":"Caterham",
    "sg:classifiers":[
        {
            "category":"Real Estate",
            "subcategory":"Developer",
            "type":"Services"
        }
    ],
    "sg:phone":"+44 20 8549 6060",
    "sg:postcode":"CR3 6HL",
    "sg:province":"Surrey",
    "sg:tags":[
        "property"
    ],
    "wof:name":"Ruskin Homes Ltd.",
    "wof:placetype":"venue"
},
  "geometry": {"coordinates":[-0.079299,51.28101],"type":"Point"}
}