{
  "type": "Feature",
  "properties": {
    "addr:full":"Cedar Brae, Redmoor Clo, Kelly Bray Callington Cornwall PL17 8DW",
    "addr:postcode":"pl17 8dw",
    "addr:street":"Cedar Brae Redmoor Clo Kelly",
    "iso:country":"GB",
    "sg:address":"Cedar Brae, Redmoor Clo, Kelly Bray",
    "sg:city":"Callington",
    "sg:classifiers":[
        {
            "category":"Social Services",
            "subcategory":"Retirement Home",
            "type":"Services"
        }
    ],
    "sg:postcode":"PL17 8DW",
    "sg:province":"Cornwall",
    "sg:tags":[
        "residential",
        "care"
    ],
    "wof:name":"St Judes Residential Care Home",
    "wof:placetype":"venue"
},
  "geometry": {"coordinates":[-4.3160738945,50.5203666687],"type":"Point"}
}