{
  "type": "Feature",
  "properties": {
    "addr:full":"86 Westgate Guisborough North Yorkshire TS14 6AP",
    "addr:housenumber":"86",
    "addr:postcode":"ts14 6ap",
    "addr:street":"Westgate Guisborough",
    "iso:country":"GB",
    "sg:address":"86 Westgate",
    "sg:city":"Guisborough",
    "sg:classifiers":[
        {
            "category":"Real Estate",
            "subcategory":"Real Estate Agent",
            "type":"Services"
        }
    ],
    "sg:phone":"+44 1287 637557",
    "sg:postcode":"TS14 6AP",
    "sg:province":"North Yorkshire",
    "wof:name":"Graeme Johnston Estate Agents",
    "wof:placetype":"venue"
},
  "geometry": {"coordinates":[-1.0564060211,54.5346870422],"type":"Point"}
}