{
  "type": "Feature",
  "properties": {
    "addr:full":"46 Essex St Holborn Greater London WC2R 3JF",
    "addr:housenumber":"46",
    "addr:postcode":"wc2r 3jf",
    "addr:street":"Essex St",
    "iso:country":"GB",
    "sg:address":"46 Essex St",
    "sg:city":"Holborn",
    "sg:classifiers":[
        {
            "category":"Professional",
            "subcategory":"Lawyer & Legal Services",
            "type":"Services"
        }
    ],
    "sg:phone":"+44 20 7583 8899",
    "sg:postcode":"WC2R 3JF",
    "sg:province":"Greater London",
    "sg:tags":[
        "barrister"
    ],
    "wof:name":"Mary Hughes",
    "wof:placetype":"venue"
},
  "geometry": {"coordinates":[-0.1129859984,51.5129966736],"type":"Point"}
}