{
  "type": "Feature",
  "properties": {
    "addr:full":"Hill Road Chinnor Buckinghamshire OX39 4AY",
    "addr:postcode":"ox39 4ay",
    "addr:street":"Hill Road",
    "iso:country":"GB",
    "sg:address":"Hill Road",
    "sg:city":"Chinnor",
    "sg:classifiers":[
        {
            "category":"Manufacturing",
            "subcategory":"Building Materials",
            "type":"Manufacturing & Wholesale Goods"
        }
    ],
    "sg:phone":"+44 1844 351471",
    "sg:postcode":"OX39 4AY",
    "sg:province":"Buckinghamshire",
    "sg:tags":[
        "distributor",
        "mnfrs",
        "cement"
    ],
    "wof:name":"Rugby Cement",
    "wof:placetype":"venue"
},
  "geometry": {"coordinates":[-0.9046170115,51.6982688904],"type":"Point"}
}