{
  "type": "Feature",
  "properties": {
    "addr:full":"Main Street, Oxton Lauder Scottish Borders TD2 6PN",
    "addr:postcode":"td2 6pn",
    "addr:street":"Main Street",
    "iso:country":"GB",
    "sg:address":"Main Street, Oxton",
    "sg:city":"Lauder",
    "sg:classifiers":[
        {
            "category":"Freight",
            "type":"Transportation"
        }
    ],
    "sg:phone":"+44 1578 750218",
    "sg:postcode":"TD2 6PN",
    "sg:province":"Scottish Borders",
    "sg:tags":[
        "haulage",
        "transport",
        "road"
    ],
    "wof:name":"J & G Campbell Ltd",
    "wof:placetype":"venue"
},
  "geometry": {"coordinates":[-2.7500789165,55.7201194763],"type":"Point"}
}