{
  "type": "Feature",
  "properties": {
    "addr:full":"30 Park Road Bingley West Yorkshire BD16 4JD",
    "addr:housenumber":"30",
    "addr:postcode":"bd16 4jd",
    "addr:street":"Park Road",
    "iso:country":"GB",
    "sg:address":"30 Park Road",
    "sg:city":"Bingley",
    "sg:classifiers":[
        {
            "category":"Professional",
            "subcategory":"Advertising",
            "type":"Services"
        }
    ],
    "sg:phone":"+44 1274 568276",
    "sg:postcode":"BD16 4JD",
    "sg:province":"West Yorkshire",
    "sg:tags":[
        "agency"
    ],
    "sg:website":"http://www.phase1.co.uk",
    "wof:name":"Phase 1 Design",
    "wof:placetype":"venue"
},
  "geometry": {"coordinates":[-1.8363740444,53.8499031067],"type":"Point"}
}