{
  "type": "Feature",
  "properties": {
    "addr:full":"Mulberry House, 10 Little Street Macclesfield Cheshire SK10 1AW",
    "addr:housenumber":"10",
    "addr:postcode":"sk10 1aw",
    "addr:street":"Little Street",
    "iso:country":"GB",
    "sg:address":"Mulberry House, 10 Little Street",
    "sg:city":"Macclesfield",
    "sg:classifiers":[
        {
            "category":"Professional",
            "subcategory":"Employment Agencies",
            "type":"Services"
        }
    ],
    "sg:phone":"+44 1625 503556",
    "sg:postcode":"SK10 1AW",
    "sg:province":"Cheshire",
    "sg:tags":[
        "consultant"
    ],
    "wof:name":"T & C Recruitment Ltd.",
    "wof:placetype":"venue"
},
  "geometry": {"coordinates":[-2.1290140152,53.2612915039],"type":"Point"}
}