{
  "type": "Feature",
  "properties": {
    "addr:full":"5 While Road Sutton Coldfield West Midlands B72 1ND",
    "addr:housenumber":"5",
    "addr:postcode":"b72 1nd",
    "addr:street":"While Road",
    "iso:country":"GB",
    "sg:address":"5 While Road",
    "sg:city":"Sutton Coldfield",
    "sg:classifiers":[
        {
            "category":"Health Services",
            "subcategory":"Health Practitioner",
            "type":"Services"
        }
    ],
    "sg:phone":"+44 121 354 7306",
    "sg:postcode":"B72 1ND",
    "sg:province":"West Midlands",
    "sg:tags":[
        "physiotherapist"
    ],
    "wof:name":"M G Robinson",
    "wof:placetype":"venue"
},
  "geometry": {"coordinates":[-1.82606,52.557598],"type":"Point"}
}