{
  "type": "Feature",
  "properties": {
    "addr:full":"Siddal La Halifax West Yorkshire HX3 9JS",
    "addr:postcode":"hx3 9js",
    "addr:street":"La Halifax West",
    "iso:country":"GB",
    "sg:address":"Siddal La",
    "sg:city":"Halifax",
    "sg:classifiers":[
        {
            "category":"Retail",
            "subcategory":"Funeral Services",
            "type":"Services"
        }
    ],
    "sg:phone":"+44 1422 363076",
    "sg:postcode":"HX3 9JS",
    "sg:province":"West Yorkshire",
    "sg:tags":[
        "cemetery",
        "crematorium"
    ],
    "wof:name":"Stoney Royd Cemetery",
    "wof:placetype":"venue"
},
  "geometry": {"coordinates":[-1.848894,53.704464],"type":"Point"}
}