{
  "type": "Feature",
  "properties": {
    "addr:full":"Unit A3 Sutton Business Centre, Restmore Way Wallington Surrey SM6 7AH",
    "addr:housenumber":"a3",
    "addr:postcode":"sm6 7ah",
    "addr:street":"Sutton Business Centre Restmore Way",
    "iso:country":"GB",
    "sg:address":"Unit A3 Sutton Business Centre, Restmore Way",
    "sg:city":"Wallington",
    "sg:classifiers":[
        {
            "category":"Building & Trades",
            "subcategory":"Construction",
            "type":"Services"
        }
    ],
    "sg:phone":"+44 20 8668 7373",
    "sg:postcode":"SM6 7AH",
    "sg:province":"Surrey",
    "sg:tags":[
        "decorator",
        "painter"
    ],
    "wof:name":"A.C.E. Paint Strippers",
    "wof:placetype":"venue"
},
  "geometry": {"coordinates":[-0.149898,51.360123],"type":"Point"}
}