{
  "type": "Feature",
  "properties": {
    "addr:full":"Bryn Goleu Ganol, Nannerch Mold Denbighshire CH7 5RN",
    "addr:postcode":"ch7 5rn",
    "addr:street":"Bryn",
    "iso:country":"GB",
    "sg:address":"Bryn Goleu Ganol, Nannerch",
    "sg:city":"Mold",
    "sg:classifiers":[
        {
            "category":"Banks & Credit Unions",
            "subcategory":"Investment Brokerage",
            "type":"Services"
        }
    ],
    "sg:phone":"+44 1352 720304",
    "sg:postcode":"CH7 5RN",
    "sg:province":"Denbighshire",
    "sg:tags":[
        "contractor"
    ],
    "wof:name":"Keith Harper Agricultural Contractor",
    "wof:placetype":"venue"
},
  "geometry": {"coordinates":[-3.2446830273,53.2161445618],"type":"Point"}
}