{
  "type": "Feature",
  "properties": {
    "iso:country":"GB",
    "sg:address":"3 Gwydr Square, Uplands",
    "sg:city":"Swansea",
    "sg:classifiers":[
        {
            "category":"Food & Beverages",
            "subcategory":"Bakery",
            "type":"Retail Goods"
        }
    ],
    "sg:phone":"+44 1792 470818",
    "sg:postcode":"SA2 0HD",
    "sg:province":"Swansea",
    "sg:tags":[
        "baker"
    ],
    "wof:name":"J L Sweetman & Sons Ltd.",
    "wof:placetype":"venue"
},
  "geometry": {"coordinates":[-3.966395,51.617626],"type":"Point"}
}