{
  "type": "Feature",
  "properties": {
    "iso:country":"GB",
    "sg:address":"37a Waterloo Road",
    "sg:city":"Wellington",
    "sg:classifiers":[
        {
            "category":"Autos & Motor Vehicles",
            "subcategory":"Boat Sales",
            "type":"Retail Goods"
        }
    ],
    "sg:phone":"+44 1823 665151",
    "sg:postcode":"TA21 8JQ",
    "sg:province":"Devon",
    "sg:tags":[
        "repair",
        "builder"
    ],
    "wof:name":"Sea Hopper Folding Dinghys",
    "wof:placetype":"venue"
},
  "geometry": {"coordinates":[-3.2360370159,50.980506897],"type":"Point"}
}