{
  "type": "Feature",
  "properties": {
    "addr:full":"51 Market Street Aberdeen Aberdeen City AB11 5PZ",
    "addr:housenumber":"51",
    "addr:postcode":"ab11 5pz",
    "addr:street":"Market Street",
    "iso:country":"GB",
    "sg:address":"51 Market Street",
    "sg:city":"Aberdeen",
    "sg:classifiers":[
        {
            "category":"Insurance",
            "subcategory":"Insurance Agent",
            "type":"Services"
        }
    ],
    "sg:phone":"+44 1224 574145",
    "sg:postcode":"AB11 5PZ",
    "sg:province":"Aberdeen City",
    "sg:tags":[
        "broker"
    ],
    "wof:name":"Sedgwick (Uk) Risk Services",
    "wof:placetype":"venue"
},
  "geometry": {"coordinates":[-2.095609,57.14563],"type":"Point"}
}