{
  "type": "Feature",
  "properties": {
    "iso:country":"GB",
    "sg:address":"Diamond Cottage, The Broadway, Great Dunmow",
    "sg:city":"Dunmow",
    "sg:classifiers":[
        {
            "category":"Home & Garden",
            "subcategory":"Furniture",
            "type":"Retail Goods"
        }
    ],
    "sg:postcode":"CM6 3BQ",
    "sg:province":"Essex",
    "wof:name":"Cherry & Walnut Design Ltd",
    "wof:placetype":"venue"
},
  "geometry": {"coordinates":[0.4044800103,51.8683891296],"type":"Point"}
}