{
  "type": "Feature",
  "properties": {
    "addr:full":"17 Maris Dr Nottingham Nottinghamshire NG14 5AJ",
    "addr:housenumber":"17",
    "addr:postcode":"ng14 5aj",
    "addr:street":"Maris Dr",
    "iso:country":"GB",
    "sg:address":"17 Maris Dr",
    "sg:city":"Nottingham",
    "sg:classifiers":[
        {
            "category":"Retail",
            "subcategory":"Driving School",
            "type":"Services"
        }
    ],
    "sg:phone":"+44 115 931 2225",
    "sg:postcode":"NG14 5AJ",
    "sg:province":"Nottinghamshire",
    "wof:name":"Ann's School Of Motoring",
    "wof:placetype":"venue"
},
  "geometry": {"coordinates":[-1.044447,52.984867],"type":"Point"}
}