{
  "type": "Feature",
  "properties": {
    "addr:full":"Orchard Cottage,oxford Rd, Donnington Newbury Berkshire RG16 9AA",
    "addr:postcode":"rg16 9aa",
    "addr:street":"Oxford Rd",
    "iso:country":"GB",
    "sg:address":"Orchard Cottage,oxford Rd, Donnington",
    "sg:city":"Newbury",
    "sg:classifiers":[
        {
            "category":"Building & Trades",
            "subcategory":"Cleaning & Sanitation",
            "type":"Services"
        }
    ],
    "sg:postcode":"RG16 9AA",
    "sg:province":"Berkshire",
    "sg:tags":[
        "sweep",
        "chimney"
    ],
    "wof:name":"Mancini,Roger,",
    "wof:placetype":"venue"
},
  "geometry": {"coordinates":[-1.3308900595,51.4152793884],"type":"Point"}
}