{
  "type": "Feature",
  "properties": {
    "addr:full":"Lochgreen Farm Bonnybridge Falkirk FK4 2HA",
    "addr:postcode":"fk4 2ha",
    "addr:street":"Bonnybridge",
    "iso:country":"GB",
    "sg:address":"Lochgreen Farm",
    "sg:city":"Bonnybridge",
    "sg:classifiers":[
        {
            "category":"Professional",
            "subcategory":"Engineering",
            "type":"Services"
        }
    ],
    "sg:phone":"+44 1324 814990",
    "sg:postcode":"FK4 2HA",
    "sg:province":"Falkirk",
    "wof:name":"Gavin Haddow",
    "wof:placetype":"venue"
},
  "geometry": {"coordinates":[-3.8919188976,55.9900817871],"type":"Point"}
}