{
  "type": "Feature",
  "properties": {
    "iso:country":"GB",
    "sg:address":"Garden Reach, Miller Lane, Cottam",
    "sg:city":"Preston",
    "sg:classifiers":[
        {
            "category":"Building & Trades",
            "subcategory":"Construction",
            "type":"Services"
        }
    ],
    "sg:phone":"+44 1772 731420",
    "sg:postcode":"PR4 0ND",
    "sg:province":"Lancashire",
    "sg:tags":[
        "roofing"
    ],
    "wof:name":"M Clark",
    "wof:placetype":"venue"
},
  "geometry": {"coordinates":[-2.7602739334,53.7865753174],"type":"Point"}
}