{
  "type": "Feature",
  "properties": {
    "iso:country":"GB",
    "sg:address":"1 Bannerdale Road",
    "sg:city":"Sheffield",
    "sg:classifiers":[
        {
            "category":"Social Services",
            "subcategory":"Retirement Home",
            "type":"Services"
        }
    ],
    "sg:phone":"+44 114 255 0595",
    "sg:postcode":"S7 2DJ",
    "sg:province":"South Yorkshire",
    "sg:tags":[
        "children's",
        "care",
        "residential"
    ],
    "wof:name":"Rushey Meadows",
    "wof:placetype":"venue"
},
  "geometry": {"coordinates":[-1.495219,53.354923],"type":"Point"}
}