{
  "type": "Feature",
  "properties": {
    "addr:full":"135 Cologne Road, Bovington Camp Wareham Dorset BH20 6JN",
    "addr:housenumber":"135",
    "addr:postcode":"bh20 6jn",
    "addr:street":"Cologne Road",
    "iso:country":"GB",
    "sg:address":"135 Cologne Road, Bovington Camp",
    "sg:city":"Wareham",
    "sg:classifiers":[
        {
            "category":"Organizations",
            "subcategory":"Membership Organization",
            "type":"Services"
        }
    ],
    "sg:postcode":"BH20 6JN",
    "sg:province":"Dorset",
    "sg:tags":[
        "club"
    ],
    "wof:name":"Royal British Legion Bovington Camp Club Ltd.",
    "wof:placetype":"venue"
},
  "geometry": {"coordinates":[-2.229748,50.698009],"type":"Point"}
}