{
  "type": "Feature",
  "properties": {
    "addr:full":"Hurstlea Road, Needham Market Ipswich Suffolk IP6 8DE",
    "addr:postcode":"ip6 8de",
    "addr:street":"Hurstlea Road",
    "iso:country":"GB",
    "sg:address":"Hurstlea Road, Needham Market",
    "sg:city":"Ipswich",
    "sg:classifiers":[
        {
            "category":"Social Services",
            "subcategory":"Adult Care",
            "type":"Services"
        }
    ],
    "sg:phone":"+44 1449 721320",
    "sg:postcode":"IP6 8DE",
    "sg:province":"Suffolk",
    "sg:tags":[
        "housing",
        "sheltered"
    ],
    "wof:name":"Hurstlea Court",
    "wof:placetype":"venue"
},
  "geometry": {"coordinates":[1.04498,52.156609],"type":"Point"}
}