{
  "type": "Feature",
  "properties": {
    "iso:country":"GB",
    "sg:address":"7a Church Street",
    "sg:city":"Launceston",
    "sg:classifiers":[
        {
            "category":"Shopping",
            "subcategory":"Clothing, Apparel, & Fashions",
            "type":"Retail Goods"
        }
    ],
    "sg:phone":"+44 1566 775756",
    "sg:postcode":"PL15 8AW",
    "sg:province":"Cornwall",
    "sg:tags":[
        "lingerie",
        "hosiery"
    ],
    "wof:name":"Under Cover",
    "wof:placetype":"venue"
},
  "geometry": {"coordinates":[-4.360176,50.637405],"type":"Point"}
}