{
  "type": "Feature",
  "properties": {
    "addr:full":"Pilgrims, Heath Rd, Bradfield Manningtree Essex CO11 2XD",
    "addr:postcode":"co11 2xd",
    "addr:street":"Heath Rd",
    "iso:country":"GB",
    "sg:address":"Pilgrims, Heath Rd, Bradfield",
    "sg:city":"Manningtree",
    "sg:classifiers":[
        {
            "category":"Real Estate",
            "subcategory":"Architect",
            "type":"Services"
        }
    ],
    "sg:postcode":"CO11 2XD",
    "sg:province":"Essex",
    "wof:name":"Johnson,B,",
    "wof:placetype":"venue"
},
  "geometry": {"coordinates":[1.1167149544,51.935344696],"type":"Point"}
}