{
  "type": "Feature",
  "properties": {
    "iso:country":"GB",
    "sg:address":"89 Potter Street",
    "sg:city":"Worksop",
    "sg:classifiers":[
        {
            "category":"Food & Beverages",
            "subcategory":"Bakery",
            "type":"Retail Goods"
        }
    ],
    "sg:phone":"+44 1909 472685",
    "sg:postcode":"S80 2HL",
    "sg:province":"Nottinghamshire",
    "sg:tags":[
        "baker"
    ],
    "wof:name":"Scott's Bakery Ltd.",
    "wof:placetype":"venue"
},
  "geometry": {"coordinates":[-1.117645,53.302879],"type":"Point"}
}