{
  "type": "Feature",
  "properties": {
    "addr:full":"8 Broad St, Weobley Hereford Herefordshire HR4 8SA",
    "addr:housenumber":"8",
    "addr:postcode":"hr4 8sa",
    "addr:street":"Broad St",
    "iso:country":"GB",
    "sg:address":"8 Broad St, Weobley",
    "sg:city":"Hereford",
    "sg:classifiers":[
        {
            "category":"Food & Beverages",
            "subcategory":"Meat & Fish",
            "type":"Retail Goods"
        }
    ],
    "sg:phone":"+44 1544 318205",
    "sg:postcode":"HR4 8SA",
    "sg:province":"Herefordshire",
    "sg:tags":[
        "butcher"
    ],
    "wof:name":"R.E Williams & Son",
    "wof:placetype":"venue"
},
  "geometry": {"coordinates":[-2.8747050762,52.1600494385],"type":"Point"}
}