{
  "type": "Feature",
  "properties": {
    "addr:full":"Moorgreen Industrial Park, Engine Lane, Newthorpe Nottingham Derbyshire NG16 3QU",
    "addr:postcode":"ng16 3qu",
    "addr:street":"Moorgreen Industrial Park Engine Lane",
    "iso:country":"GB",
    "sg:address":"Moorgreen Industrial Park, Engine Lane, Newthorpe",
    "sg:city":"Nottingham",
    "sg:classifiers":[
        {
            "category":"Home & Garden",
            "subcategory":"Household Appliances",
            "type":"Retail Goods"
        },
        {
            "category":"Ferry Terminal",
            "type":"Transportation"
        }
    ],
    "sg:phone":"+44 1773 533842",
    "sg:postcode":"NG16 3QU",
    "sg:province":"Derbyshire",
    "sg:tags":[
        "domestic",
        "refrigerator",
        "freezer",
        "centre"
    ],
    "wof:name":"Fridge Freezer Warehouse",
    "wof:placetype":"venue"
},
  "geometry": {"coordinates":[-1.290999,53.02607],"type":"Point"}
}