{
  "type": "Feature",
  "properties": {
    "addr:full":"Mustow Street Bury St Edmunds Suffolk IP33 1XL",
    "addr:postcode":"ip33 1xl",
    "addr:street":"Mustow Street",
    "iso:country":"GB",
    "sg:address":"Mustow Street",
    "sg:city":"Bury St Edmunds",
    "sg:classifiers":[
        {
            "category":"Autos & Motor Vehicles",
            "subcategory":"Automobile Sales",
            "type":"Retail Goods"
        }
    ],
    "sg:phone":"+44 1284 754255",
    "sg:postcode":"IP33 1XL",
    "sg:province":"Suffolk",
    "sg:tags":[
        "car"
    ],
    "wof:name":"Hawkes Garage",
    "wof:placetype":"venue"
},
  "geometry": {"coordinates":[0.717765,52.245975],"type":"Point"}
}