{
  "type": "Feature",
  "properties": {
    "addr:full":"Cogan Roundabout Penarth The Vale of Glamorgan CF64 1ND",
    "addr:postcode":"cf64 1nd",
    "addr:street":"Cogan Roundabout;Vale",
    "iso:country":"GB",
    "sg:address":"Cogan Roundabout",
    "sg:city":"Penarth",
    "sg:classifiers":[
        {
            "category":"Restaurant",
            "type":"Food & Drink"
        }
    ],
    "sg:phone":"+44 29 2070 8635",
    "sg:postcode":"CF64 1ND",
    "sg:province":"The Vale of Glamorgan",
    "wof:name":"Barons Court Beefeater",
    "wof:placetype":"venue"
},
  "geometry": {"coordinates":[-3.1744139194,51.4389190674],"type":"Point"}
}