{
  "type": "Feature",
  "properties": {
    "addr:full":"20 Guildford Road St Albans Hertfordshire AL1 5JY",
    "addr:housenumber":"20",
    "addr:postcode":"al1 5jy",
    "addr:street":"Guildford Road",
    "iso:country":"GB",
    "sg:address":"20 Guildford Road",
    "sg:city":"St Albans",
    "sg:classifiers":[
        {
            "category":"Professional",
            "type":"Services"
        }
    ],
    "sg:phone":"+44 1727 865144",
    "sg:postcode":"AL1 5JY",
    "sg:province":"Hertfordshire",
    "sg:tags":[
        "caterer"
    ],
    "wof:name":"Kingfisher Caterers",
    "wof:placetype":"venue"
},
  "geometry": {"coordinates":[-0.3079870045,51.7492370605],"type":"Point"}
}