{
  "type": "Feature",
  "properties": {
    "addr:full":"Mill Stores, Mill Lane Sandwich Kent CT13 0LD",
    "addr:postcode":"ct13 0ld",
    "addr:street":"Mill Lane",
    "iso:country":"GB",
    "sg:address":"Mill Stores, Mill Lane",
    "sg:city":"Sandwich",
    "sg:classifiers":[
        {
            "category":"Shopping",
            "type":"Retail Goods"
        }
    ],
    "sg:postcode":"CT13 0LD",
    "sg:province":"Kent",
    "sg:tags":[
        "part",
        "accessory"
    ],
    "wof:name":"M W Auto Electrics",
    "wof:placetype":"venue"
},
  "geometry": {"coordinates":[1.3423039913,51.2761688232],"type":"Point"}
}