{
  "type": "Feature",
  "properties": {
    "iso:country":"GB",
    "sg:address":"Euro Centre, Whitstable Road",
    "sg:city":"Faversham",
    "sg:classifiers":[
        {
            "category":"Professional",
            "subcategory":"Business Services",
            "type":"Services"
        },
        {
            "category":"Wholesale",
            "subcategory":"Fruits & Vegetables",
            "type":"Manufacturing & Wholesale Goods"
        }
    ],
    "sg:phone":"+44 1795 562345",
    "sg:postcode":"ME13 8BQ",
    "sg:province":"Kent",
    "sg:tags":[
        "distribution"
    ],
    "wof:name":"Saphir Produce Ltd.",
    "wof:placetype":"venue"
},
  "geometry": {"coordinates":[0.9013950229,51.3133087158],"type":"Point"}
}