{
  "type": "Feature",
  "properties": {
    "addr:full":"3 St Marys Street Chippenham Wiltshire SN15 3JL",
    "addr:housenumber":"3",
    "addr:postcode":"sn15 3jl",
    "addr:street":"St Marys Street",
    "iso:country":"GB",
    "sg:address":"3 St Marys Street",
    "sg:city":"Chippenham",
    "sg:classifiers":[
        {
            "category":"Banks & Credit Unions",
            "subcategory":"Financial Services",
            "type":"Services"
        }
    ],
    "sg:postcode":"SN15 3JL",
    "sg:province":"Wiltshire",
    "sg:tags":[
        "consultant"
    ],
    "wof:name":"Koinonia Trust",
    "wof:placetype":"venue"
},
  "geometry": {"coordinates":[-2.1107990742,51.4568557739],"type":"Point"}
}