{
  "type": "Feature",
  "properties": {
    "iso:country":"GB",
    "sg:address":"16 Ship Street",
    "sg:city":"Brecon",
    "sg:classifiers":[
        {
            "category":"Professional",
            "type":"Services"
        }
    ],
    "sg:phone":"+44 1874 623200",
    "sg:postcode":"LD3 9AD",
    "sg:province":"Powys",
    "sg:tags":[
        "auctioneer"
    ],
    "wof:name":"Harris Montague & Co.",
    "wof:placetype":"venue"
},
  "geometry": {"coordinates":[-3.393029,51.947811],"type":"Point"}
}