{
  "type": "Feature",
  "properties": {
    "iso:country":"GB",
    "sg:address":"149b Market Street",
    "sg:city":"St Andrews",
    "sg:classifiers":[
        {
            "category":"Shopping",
            "subcategory":"Crafts & Fabrics",
            "type":"Retail Goods"
        },
        {
            "category":"Real Estate",
            "subcategory":"Architect",
            "type":"Services"
        }
    ],
    "sg:phone":"+44 1334 473268",
    "sg:postcode":"KY16 9PF",
    "sg:province":"Fife",
    "sg:tags":[
        "tartan",
        "supplier",
        "kilt",
        "accessory"
    ],
    "wof:name":"Kirk Wynd Highland House",
    "wof:placetype":"venue"
},
  "geometry": {"coordinates":[-2.798672,56.340553],"type":"Point"}
}