{
  "type": "Feature",
  "properties": {
    "addr:full":"Ferriby Road Barton-upon-humber Lincolnshire DN18 5RJ",
    "addr:postcode":"dn18 5rj",
    "addr:street":"Ferriby Road",
    "iso:country":"GB",
    "sg:address":"Ferriby Road",
    "sg:city":"Barton-upon-humber",
    "sg:classifiers":[
        {
            "category":"Autos & Motor Vehicles",
            "subcategory":"Auto Supplies",
            "type":"Retail Goods"
        }
    ],
    "sg:phone":"+44 1652 633331",
    "sg:postcode":"DN18 5RJ",
    "sg:province":"Lincolnshire",
    "sg:tags":[
        "tyre"
    ],
    "wof:name":"Barton Tyres",
    "wof:placetype":"venue"
},
  "geometry": {"coordinates":[-0.445961,53.684242],"type":"Point"}
}