{
  "type": "Feature",
  "properties": {
    "iso:country":"GB",
    "sg:address":"47 West Parade",
    "sg:city":"Worthing",
    "sg:classifiers":[
        {
            "category":"Professional",
            "subcategory":"Accounting & Tax Preparation",
            "type":"Services"
        }
    ],
    "sg:phone":"+44 1903 203905",
    "sg:postcode":"BN11 5EF",
    "sg:province":"West Sussex",
    "sg:tags":[
        "accountant"
    ],
    "wof:name":"Derek Longden",
    "wof:placetype":"venue"
},
  "geometry": {"coordinates":[-0.397276,50.806622],"type":"Point"}
}