{
  "type": "Feature",
  "properties": {
    "addr:full":"Unit 17a Amey Industrial Estate, Frenchmans Road, French Petersfield Hampshire GU32 3AN",
    "addr:housenumber":"unit 17a amey",
    "addr:postcode":"gu32 3an",
    "addr:street":"Industrial Estate Frenchmans Road",
    "iso:country":"GB",
    "sg:address":"Unit 17a Amey Industrial Estate, Frenchmans Road, French",
    "sg:city":"Petersfield",
    "sg:classifiers":[
        {
            "category":"Professional",
            "subcategory":"Computer Services",
            "type":"Services"
        }
    ],
    "sg:phone":"+44 1730 269860",
    "sg:postcode":"GU32 3AN",
    "sg:province":"Hampshire",
    "sg:tags":[
        "system",
        "software"
    ],
    "wof:name":"M W Computer Services",
    "wof:placetype":"venue"
},
  "geometry": {"coordinates":[-0.935826,51.003796],"type":"Point"}
}