{
  "type": "Feature",
  "properties": {
    "iso:country":"GB",
    "sg:address":"1st Floor Gerard Winstanley House, Crawford Street",
    "sg:city":"Wigan",
    "sg:classifiers":[
        {
            "category":"Organizations",
            "subcategory":"Political Organization",
            "type":"Services"
        }
    ],
    "sg:phone":"+44 1942 824029",
    "sg:postcode":"WN1 1NJ",
    "sg:province":"Lancashire",
    "sg:tags":[
        "party"
    ],
    "wof:name":"Ian McCartney",
    "wof:placetype":"venue"
},
  "geometry": {"coordinates":[-2.634094,53.545715],"type":"Point"}
}