{
  "type": "Feature",
  "properties": {
    "addr:full":"220 Old Bedford Road Luton Bedfordshire LU2 7HP",
    "addr:housenumber":"220",
    "addr:postcode":"lu2 7hp",
    "addr:street":"Old Bedford Road",
    "iso:country":"GB",
    "sg:address":"220 Old Bedford Road",
    "sg:city":"Luton",
    "sg:classifiers":[
        {
            "category":"Health Services",
            "subcategory":"Nursing And Care Facility",
            "type":"Services"
        },
        {
            "category":"Social Services",
            "subcategory":"Retirement Home",
            "type":"Services"
        }
    ],
    "sg:phone":"+44 1582 720010",
    "sg:postcode":"LU2 7HP",
    "sg:province":"Bedfordshire",
    "sg:tags":[
        "residential"
    ],
    "wof:name":"The Elizabethan",
    "wof:placetype":"venue"
},
  "geometry": {"coordinates":[-0.416281,51.895229],"type":"Point"}
}