{
  "type": "Feature",
  "properties": {
    "iso:country":"GB",
    "sg:address":"Lady Nairne Cres",
    "sg:city":"Edinburgh",
    "sg:classifiers":[
        {
            "category":"Social Services",
            "subcategory":"Adult Care",
            "type":"Services"
        }
    ],
    "sg:phone":"+44 131 661 1118",
    "sg:postcode":"EH8 7PE",
    "sg:province":"City of Edinburgh",
    "sg:tags":[
        "housing",
        "sheltered"
    ],
    "wof:name":"Lady Nairne Crescent Sheltered Housing",
    "wof:placetype":"venue"
},
  "geometry": {"coordinates":[-3.1433210373,55.9450721741],"type":"Point"}
}