{
  "type": "Feature",
  "properties": {
    "iso:country":"GB",
    "sg:address":"Leyland Lane",
    "sg:city":"Preston",
    "sg:classifiers":[
        {
            "category":"Sports & Exercise",
            "subcategory":"Gym",
            "type":"Entertainment"
        }
    ],
    "sg:phone":"+44 1772 490605",
    "sg:postcode":"PR26 8PH",
    "sg:province":"Lancashire",
    "sg:tags":[
        "club",
        "fitness",
        "health",
        "centre"
    ],
    "wof:name":"Gerry's Gym",
    "wof:placetype":"venue"
},
  "geometry": {"coordinates":[-2.695514,53.728405],"type":"Point"}
}