{
  "type": "Feature",
  "properties": {
    "addr:full":"Unit 1 Bridge Court, Ermington Road Ivybridge Devon PL21 9EY",
    "addr:housenumber":"unit 1",
    "addr:postcode":"pl21 9ey",
    "addr:street":"Bridge Court Ermington Road",
    "iso:country":"GB",
    "sg:address":"Unit 1 Bridge Court, Ermington Road",
    "sg:city":"Ivybridge",
    "sg:classifiers":[
        {
            "category":"Building & Trades",
            "subcategory":"Construction",
            "type":"Services"
        }
    ],
    "sg:phone":"+44 1752 895006",
    "sg:postcode":"PL21 9EY",
    "sg:province":"Devon",
    "sg:tags":[
        "builder"
    ],
    "wof:name":"Jack Turton",
    "wof:placetype":"venue"
},
  "geometry": {"coordinates":[-3.9189009666,50.3624725342],"type":"Point"}
}