{
  "type": "Feature",
  "properties": {
    "iso:country":"GB",
    "sg:address":"140 Magna Road",
    "sg:city":"Bournemouth",
    "sg:classifiers":[
        {
            "category":"Retail",
            "subcategory":"Auto Repair",
            "type":"Services"
        }
    ],
    "sg:postcode":"BH11 9NB",
    "sg:province":"Dorset",
    "sg:tags":[
        "modification",
        "garage"
    ],
    "wof:name":"Knighton Garage",
    "wof:placetype":"venue"
},
  "geometry": {"coordinates":[-1.9347640276,50.7730941772],"type":"Point"}
}