{
  "type": "Feature",
  "properties": {
    "addr:full":", Longhorsley Morpeth Morpeth Northumberland NE65 8XG",
    "addr:postcode":"ne65 8xg",
    "iso:country":"GB",
    "sg:address":", Longhorsley Morpeth",
    "sg:city":"Morpeth",
    "sg:classifiers":[
        {
            "category":"Sports & Exercise",
            "subcategory":"Golf",
            "type":"Entertainment"
        }
    ],
    "sg:phone":"+44 1670 788050",
    "sg:postcode":"NE65 8XG",
    "sg:province":"Northumberland",
    "sg:tags":[
        "club",
        "course"
    ],
    "wof:name":"Linden Hall Golf Club",
    "wof:placetype":"venue"
},
  "geometry": {"coordinates":[-1.7684099674,55.2459602356],"type":"Point"}
}