{
  "type": "Feature",
  "properties": {
    "iso:country":"GB",
    "sg:address":"Parkhead Farm, Welton",
    "sg:city":"Carlisle",
    "sg:classifiers":[
        {
            "category":"Farming",
            "subcategory":"Livestock Farm",
            "type":"Manufacturing & Wholesale Goods"
        },
        {
            "category":"Farming",
            "subcategory":"Farm",
            "type":"Manufacturing & Wholesale Goods"
        }
    ],
    "sg:phone":"+44 16974 78282",
    "sg:postcode":"CA5 7HL",
    "sg:province":"Cumbria",
    "sg:tags":[
        "mixed",
        "crop",
        "others"
    ],
    "wof:name":"Messers Osbourne",
    "wof:placetype":"venue"
},
  "geometry": {"coordinates":[-3.008994,54.789494],"type":"Point"}
}