{
  "type": "Feature",
  "properties": {
    "addr:full":"51 Aberdeen Walk Scarborough North Yorkshire YO11 1BD",
    "addr:housenumber":"51",
    "addr:postcode":"yo11 1bd",
    "addr:street":"Aberdeen Walk",
    "iso:country":"GB",
    "sg:address":"51 Aberdeen Walk",
    "sg:city":"Scarborough",
    "sg:classifiers":[
        {
            "category":"Professional",
            "subcategory":"Art Services",
            "type":"Services"
        }
    ],
    "sg:phone":"+44 1723 379769",
    "sg:postcode":"YO11 1BD",
    "sg:province":"North Yorkshire",
    "sg:tags":[
        "photographer"
    ],
    "wof:name":"Photo Studio",
    "wof:placetype":"venue"
},
  "geometry": {"coordinates":[-0.403542012,54.2832679749],"type":"Point"}
}