{
  "type": "Feature",
  "properties": {
    "iso:country":"GB",
    "sg:address":"Goldsworth Park Indust Est",
    "sg:city":"Woking",
    "sg:classifiers":[
        {
            "category":"Personal",
            "type":"Services"
        }
    ],
    "sg:phone":"+44 1483 750763",
    "sg:postcode":"GU21 3BA",
    "sg:province":"Surrey",
    "sg:tags":[
        "delivery"
    ],
    "wof:name":"Parcelforce Worldwide",
    "wof:placetype":"venue"
},
  "geometry": {"coordinates":[-0.5738850236,51.3152427673],"type":"Point"}
}