{
  "type": "Feature",
  "properties": {
    "addr:full":"436 Gower Road, Killay Swansea Swansea SA2 7AJ",
    "addr:housenumber":"436",
    "addr:postcode":"sa2 7aj",
    "addr:street":"Gower Road",
    "iso:country":"GB",
    "sg:address":"436 Gower Road, Killay",
    "sg:city":"Swansea",
    "sg:classifiers":[
        {
            "category":"Restaurant",
            "type":"Food & Drink"
        }
    ],
    "sg:phone":"+44 1792 205449",
    "sg:postcode":"SA2 7AJ",
    "sg:province":"Swansea",
    "sg:tags":[
        "indian"
    ],
    "wof:name":"Killay Tandoori Restaurant",
    "wof:placetype":"venue"
},
  "geometry": {"coordinates":[-4.019167,51.617733],"type":"Point"}
}