{
  "type": "Feature",
  "properties": {
    "addr:full":"United House, North Road London Greater London N7 9DP",
    "addr:postcode":"n7 9dp",
    "addr:street":"North Road",
    "iso:country":"GB",
    "sg:address":"United House, North Road",
    "sg:city":"London",
    "sg:classifiers":[
        {
            "category":"Professional",
            "type":"Services"
        }
    ],
    "sg:postcode":"N7 9DP",
    "sg:province":"Greater London",
    "sg:tags":[
        "display",
        "maker"
    ],
    "wof:name":"Sloan Visual Merchandising",
    "wof:placetype":"venue"
},
  "geometry": {"coordinates":[-0.12241,51.548721],"type":"Point"}
}