{
  "type": "Feature",
  "properties": {
    "addr:full":"Unit 3, Sulivan Rd Fulham Greater London SW6 3DJ",
    "addr:housenumber":"unit 3",
    "addr:postcode":"sw6 3dj",
    "addr:street":"Sulivan Rd",
    "iso:country":"GB",
    "sg:address":"Unit 3, Sulivan Rd",
    "sg:city":"Fulham",
    "sg:classifiers":[
        {
            "category":"Professional",
            "subcategory":"Art Services",
            "type":"Services"
        }
    ],
    "sg:phone":"+44 20 7371 0610",
    "sg:postcode":"SW6 3DJ",
    "sg:province":"Greater London",
    "sg:tags":[
        "photographer"
    ],
    "wof:name":"Ben Nicholson Photography",
    "wof:placetype":"venue"
},
  "geometry": {"coordinates":[-0.1950480044,51.4671554565],"type":"Point"}
}