{
  "type": "Feature",
  "properties": {
    "addr:full":"180 Hart La Luton Bedfordshire LU2 0JH",
    "addr:housenumber":"180",
    "addr:postcode":"lu2 0jh",
    "addr:street":"Hart La",
    "iso:country":"GB",
    "sg:address":"180 Hart La",
    "sg:city":"Luton",
    "sg:classifiers":[
        {
            "category":"Building & Trades",
            "subcategory":"Equipment Rental",
            "type":"Services"
        }
    ],
    "sg:phone":"+44 1582 482017",
    "sg:postcode":"LU2 0JH",
    "sg:province":"Bedfordshire",
    "sg:tags":[
        "hire",
        "catering"
    ],
    "wof:name":"Mealtime Hire",
    "wof:placetype":"venue"
},
  "geometry": {"coordinates":[-0.402387,51.888035],"type":"Point"}
}