{
  "type": "Feature",
  "properties": {
    "iso:country":"GB",
    "sg:address":"25 Peffer Bank",
    "sg:city":"Edinburgh",
    "sg:classifiers":[
        {
            "category":"Building & Trades",
            "subcategory":"Construction",
            "type":"Services"
        }
    ],
    "sg:phone":"+44 131 659 6505",
    "sg:postcode":"EH16 4AW",
    "sg:province":"City of Edinburgh",
    "sg:tags":[
        "glazier"
    ],
    "wof:name":"Easter Road Glass",
    "wof:placetype":"venue"
},
  "geometry": {"coordinates":[-3.143178,55.93372],"type":"Point"}
}