{
  "type": "Feature",
  "properties": {
    "addr:full":"Clotton Tarporley Cheshire CW6 0EG",
    "addr:postcode":"cw6 0eg",
    "addr:street":"Tarporley",
    "iso:country":"GB",
    "sg:address":"Clotton",
    "sg:city":"Tarporley",
    "sg:classifiers":[
        {
            "category":"Bars & Pubs",
            "type":"Food & Drink"
        }
    ],
    "sg:phone":"+44 1829 781354",
    "sg:postcode":"CW6 0EG",
    "sg:province":"Cheshire",
    "sg:tags":[
        "pubs",
        "inn"
    ],
    "wof:name":"Bulls Head",
    "wof:placetype":"venue"
},
  "geometry": {"coordinates":[-2.6687550545,53.1593551636],"type":"Point"}
}