{
  "type": "Feature",
  "properties": {
    "iso:country":"GB",
    "sg:address":"Ranger Ho, Walnut Tree Clo",
    "sg:city":"Guildford",
    "sg:classifiers":[
        {
            "category":"Communications",
            "type":"Services"
        }
    ],
    "sg:phone":"+44 1483 455848",
    "sg:postcode":"GU1 4US",
    "sg:province":"Surrey",
    "sg:tags":[
        "data",
        "network"
    ],
    "wof:name":"Spar Aerospace Ltd",
    "wof:placetype":"venue"
},
  "geometry": {"coordinates":[-0.579395,51.236385],"type":"Point"}
}