{
  "type": "Feature",
  "properties": {
    "iso:country":"GB",
    "sg:address":"Town Hall Street",
    "sg:city":"Grimsby",
    "sg:classifiers":[
        {
            "category":"Professional",
            "subcategory":"Lawyer & Legal Services",
            "type":"Services"
        }
    ],
    "sg:phone":"+44 1472 358234",
    "sg:postcode":"DN31 1HE",
    "sg:province":"Lincolnshire",
    "sg:tags":[
        "solicitor"
    ],
    "wof:name":"Helen Palmer",
    "wof:placetype":"venue"
},
  "geometry": {"coordinates":[-0.082324,53.565575],"type":"Point"}
}