{
  "type": "Feature",
  "properties": {
    "addr:full":"Vicarage Street Bolton Lancashire BL3 5LE",
    "addr:postcode":"bl3 5le",
    "addr:street":"Vicarage Street",
    "iso:country":"GB",
    "sg:address":"Vicarage Street",
    "sg:city":"Bolton",
    "sg:classifiers":[
        {
            "category":"Place Of Worship",
            "type":"Public Place"
        }
    ],
    "sg:phone":"+44 1204 520837",
    "sg:postcode":"BL3 5LE",
    "sg:province":"Lancashire",
    "wof:name":"Emmanuel Church Centre",
    "wof:placetype":"venue"
},
  "geometry": {"coordinates":[-2.442399,53.570412],"type":"Point"}
}