{
  "type": "Feature",
  "properties": {
    "addr:full":"The Hill, Newcastle Road Sandbach Cheshire CW11 1LA",
    "addr:postcode":"cw11 1la",
    "addr:street":"The Hill Newcastle Road",
    "iso:country":"GB",
    "sg:address":"The Hill, Newcastle Road",
    "sg:city":"Sandbach",
    "sg:classifiers":[
        {
            "category":"Health Services",
            "subcategory":"Nursing And Care Facility",
            "type":"Services"
        },
        {
            "category":"Social Services",
            "subcategory":"Retirement Home",
            "type":"Services"
        }
    ],
    "sg:phone":"+44 1270 762341",
    "sg:postcode":"CW11 1LA",
    "sg:province":"Cheshire",
    "sg:tags":[
        "residential"
    ],
    "wof:name":"Leonard Cheshire Home",
    "wof:placetype":"venue"
},
  "geometry": {"coordinates":[-2.3548491001,53.1418037415],"type":"Point"}
}