{
  "type": "Feature",
  "properties": {
    "iso:country":"GB",
    "sg:address":"18 Galveston Close",
    "sg:city":"Eastbourne",
    "sg:classifiers":[
        {
            "category":"Building & Trades",
            "subcategory":"Landscaping Services",
            "type":"Services"
        }
    ],
    "sg:postcode":"BN23 5RH",
    "sg:province":"East Sussex",
    "sg:tags":[
        "landscape",
        "contractor"
    ],
    "wof:name":"D Wells Landscaping",
    "wof:placetype":"venue"
},
  "geometry": {"coordinates":[0.3218359947,50.7894477844],"type":"Point"}
}