{
  "type": "Feature",
  "properties": {
    "iso:country":"GB",
    "sg:address":"301 Chester Road, Streetly",
    "sg:city":"Sutton Coldfield",
    "sg:classifiers":[
        {
            "category":"Autos & Motor Vehicles",
            "subcategory":"Automobile Sales",
            "type":"Retail Goods"
        }
    ],
    "sg:phone":"+44 121 502 8000",
    "sg:postcode":"B74 3DX",
    "sg:province":"Staffordshire",
    "sg:tags":[
        "car"
    ],
    "wof:name":"Cutlers of Streetly Ltd.",
    "wof:placetype":"venue"
},
  "geometry": {"coordinates":[-1.887678,52.586906],"type":"Point"}
}