{
  "type": "Feature",
  "properties": {
    "iso:country":"GB",
    "sg:address":"2 Kenmure Lane, Bishopbriggs",
    "sg:city":"Glasgow",
    "sg:classifiers":[
        {
            "category":"Professional",
            "subcategory":"Lawyer & Legal Services",
            "type":"Services"
        }
    ],
    "sg:phone":"+44 141 762 4040",
    "sg:postcode":"G64 2RA",
    "sg:province":"East Dunbartonshire",
    "sg:tags":[
        "solicitor"
    ],
    "wof:name":"Hennessy Bowie & Co.",
    "wof:placetype":"venue"
},
  "geometry": {"coordinates":[-4.225376,55.905273],"type":"Point"}
}