{
  "type": "Feature",
  "properties": {
    "iso:country":"GB",
    "sg:address":"C/o Hillside Garage, Barfs Road",
    "sg:city":"Workington",
    "sg:classifiers":[
        {
            "category":"Retail",
            "subcategory":"Auto Repair",
            "type":"Services"
        }
    ],
    "sg:postcode":"CA14 5TG",
    "sg:province":"Cumbria",
    "sg:tags":[
        "modification",
        "garage"
    ],
    "wof:name":"Hillside Garage Ltd.",
    "wof:placetype":"venue"
},
  "geometry": {"coordinates":[-3.5500020981,54.6389808655],"type":"Point"}
}