{
  "type": "Feature",
  "properties": {
    "addr:full":"Fitzjohns, Dynes Hall Road Halstead Essex CO9 2QW",
    "addr:postcode":"co9 2qw",
    "addr:street":"Fitzjohns;Hall Road",
    "iso:country":"GB",
    "sg:address":"Fitzjohns, Dynes Hall Road",
    "sg:city":"Halstead",
    "sg:classifiers":[
        {
            "category":"Farming",
            "subcategory":"Livestock Farm",
            "type":"Manufacturing & Wholesale Goods"
        }
    ],
    "sg:phone":"+44 1787 472116",
    "sg:postcode":"CO9 2QW",
    "sg:province":"Essex",
    "sg:tags":[
        "others"
    ],
    "wof:name":"W A Craig & Son",
    "wof:placetype":"venue"
},
  "geometry": {"coordinates":[0.635825,51.943996],"type":"Point"}
}