{
  "type": "Feature",
  "properties": {
    "iso:country":"GB",
    "sg:address":"Whitehouse Farm, Haisthorpe",
    "sg:city":"Driffield",
    "sg:classifiers":[
        {
            "category":"Home & Garden",
            "subcategory":"Garden Supply",
            "type":"Retail Goods"
        }
    ],
    "sg:phone":"+44 1262 490345",
    "sg:postcode":"YO25 4NR",
    "sg:province":"East Riding of Yorkshire",
    "sg:tags":[
        "bulb",
        "grower"
    ],
    "wof:name":"J K & D Shipley",
    "wof:placetype":"venue"
},
  "geometry": {"coordinates":[-0.2778509855,54.0652809143],"type":"Point"}
}