{
  "type": "Feature",
  "properties": {
    "iso:country":"GB",
    "sg:address":"Buckingham Rd",
    "sg:city":"Milton Keynes",
    "sg:classifiers":[
        {
            "category":"Restaurant",
            "type":"Food & Drink"
        }
    ],
    "sg:phone":"+44 1908 564727",
    "sg:postcode":"MK19 6JU",
    "sg:province":"Buckinghamshire",
    "wof:name":"Little Chef",
    "wof:placetype":"venue"
},
  "geometry": {"coordinates":[-0.8852419853,52.048538208],"type":"Point"}
}