{
  "type": "Feature",
  "properties": {
    "iso:country":"GB",
    "sg:address":"Suite 2 Realtex Ho, 2 Leeds Rd, Rawdon",
    "sg:city":"Leeds",
    "sg:classifiers":[
        {
            "category":"Food & Beverages",
            "subcategory":"Specialty",
            "type":"Retail Goods"
        }
    ],
    "sg:phone":"+44 113 250 1505",
    "sg:postcode":"LS19 6AX",
    "sg:province":"West Yorkshire",
    "sg:tags":[
        "product",
        "health"
    ],
    "wof:name":"Caring Naturally Ltd",
    "wof:placetype":"venue"
},
  "geometry": {"coordinates":[-1.682068,53.855892],"type":"Point"}
}