{
  "type": "Feature",
  "properties": {
    "iso:country":"GB",
    "sg:address":"3 Essex Close, St Thomas",
    "sg:city":"Exeter",
    "sg:classifiers":[
        {
            "category":"Building & Trades",
            "subcategory":"Construction",
            "type":"Services"
        }
    ],
    "sg:postcode":"EX4 1LS",
    "sg:province":"Devon",
    "sg:tags":[
        "builder"
    ],
    "wof:name":"All-Plas (South West) Ltd",
    "wof:placetype":"venue"
},
  "geometry": {"coordinates":[-3.556657,50.7127],"type":"Point"}
}