{
  "type": "Feature",
  "properties": {
    "addr:full":"Po Box 774 High Wycombe Buckinghamshire HP14 3FS",
    "addr:housenumber":"po;774",
    "addr:postcode":"hp14 3fs",
    "addr:street":"Box",
    "iso:country":"GB",
    "sg:address":"Po Box 774",
    "sg:city":"High Wycombe",
    "sg:classifiers":[
        {
            "category":"Coffee & Tea",
            "type":"Food & Drink"
        }
    ],
    "sg:postcode":"HP14 3FS",
    "sg:province":"Buckinghamshire",
    "wof:name":"East India & China Tea Co. Ltd.",
    "wof:placetype":"venue"
},
  "geometry": {"coordinates":[-0.866146,51.645012],"type":"Point"}
}