{
  "type": "Feature",
  "properties": {
    "addr:full":"69 Egremont Road, Bearsted Maidstone Kent ME15 8NA",
    "addr:housenumber":"69",
    "addr:postcode":"me15 8na",
    "addr:street":"Egremont Road",
    "iso:country":"GB",
    "sg:address":"69 Egremont Road, Bearsted",
    "sg:city":"Maidstone",
    "sg:classifiers":[
        {
            "category":"Retail",
            "subcategory":"Driving School",
            "type":"Services"
        }
    ],
    "sg:phone":"+44 1622 730438",
    "sg:postcode":"ME15 8NA",
    "sg:province":"Kent",
    "wof:name":"E C School Of Motoring",
    "wof:placetype":"venue"
},
  "geometry": {"coordinates":[0.5610960126,51.2650604248],"type":"Point"}
}