{
  "type": "Feature",
  "properties": {
    "addr:full":"49 Cressing Road Braintree Essex CM7 3PP",
    "addr:housenumber":"49",
    "addr:postcode":"cm7 3pp",
    "addr:street":"Cressing Road",
    "iso:country":"GB",
    "sg:address":"49 Cressing Road",
    "sg:city":"Braintree",
    "sg:classifiers":[
        {
            "category":"Building & Trades",
            "subcategory":"Landscaping Services",
            "type":"Services"
        }
    ],
    "sg:phone":"+44 1376 321955",
    "sg:postcode":"CM7 3PP",
    "sg:province":"Essex",
    "sg:tags":[
        "gardening"
    ],
    "wof:name":"J & B Contracts",
    "wof:placetype":"venue"
},
  "geometry": {"coordinates":[0.566965,51.880058],"type":"Point"}
}