{
  "type": "Feature",
  "properties": {
    "addr:full":"St John's Business Park, Turnpike Helston Cornwall TR13 8EX",
    "addr:postcode":"tr13 8ex",
    "addr:street":"Business Park Turnpike",
    "iso:country":"GB",
    "sg:address":"St John's Business Park, Turnpike",
    "sg:city":"Helston",
    "sg:classifiers":[
        {
            "category":"Professional",
            "subcategory":"Business Services",
            "type":"Services"
        }
    ],
    "sg:phone":"+44 1326 563515",
    "sg:postcode":"TR13 8EX",
    "sg:province":"Cornwall",
    "sg:tags":[
        "tile",
        "stockist"
    ],
    "wof:name":"Ceramic Stiles",
    "wof:placetype":"venue"
},
  "geometry": {"coordinates":[-5.2679429054,50.1068115234],"type":"Point"}
}