{
  "type": "Feature",
  "properties": {
    "iso:country":"GB",
    "sg:address":"21c Stanley Road",
    "sg:city":"Bournemouth",
    "sg:classifiers":[
        {
            "category":"Banks & Credit Unions",
            "subcategory":"Financial Services",
            "type":"Services"
        },
        {
            "category":"Organizations",
            "subcategory":"Non-profit Organization",
            "type":"Services"
        }
    ],
    "sg:phone":"+44 1202 399733",
    "sg:postcode":"BH1 4SD",
    "sg:province":"Dorset",
    "sg:tags":[
        "consultant",
        "organisation",
        "voluntary",
        "charity"
    ],
    "wof:name":"The Childrens Society",
    "wof:placetype":"venue"
},
  "geometry": {"coordinates":[-1.8566169739,50.729347229],"type":"Point"}
}