{
  "type": "Feature",
  "properties": {
    "addr:full":"Unit 4 Riverbank Business Park, 455 Dyehouse Lane London Greater London E3 2TB",
    "addr:housenumber":"unit 4;455",
    "addr:postcode":"e3 2tb",
    "addr:street":"Riverbank Business Park;Dyehouse Lane",
    "iso:country":"GB",
    "sg:address":"Unit 4 Riverbank Business Park, 455 Dyehouse Lane",
    "sg:city":"London",
    "sg:classifiers":[
        {
            "category":"Wholesale",
            "subcategory":"Vending Machines",
            "type":"Manufacturing & Wholesale Goods"
        }
    ],
    "sg:phone":"+44 20 8983 0777",
    "sg:postcode":"E3 2TB",
    "sg:province":"Greater London",
    "sg:tags":[
        "business"
    ],
    "wof:name":"Concorde Business Machines Ltd.",
    "wof:placetype":"venue"
},
  "geometry": {"coordinates":[-0.02182,51.534351],"type":"Point"}
}