{
  "type": "Feature",
  "properties": {
    "iso:country":"GB",
    "sg:address":"35 Leabrooks Road, Somercotes",
    "sg:city":"Alfreton",
    "sg:classifiers":[
        {
            "category":"Retail",
            "subcategory":"Auto Repair",
            "type":"Services"
        }
    ],
    "sg:phone":"+44 1773 604444",
    "sg:postcode":"DE55 4HB",
    "sg:province":"Derbyshire",
    "sg:tags":[
        "modification",
        "garage"
    ],
    "wof:name":"Leabrook Road Garage",
    "wof:placetype":"venue"
},
  "geometry": {"coordinates":[-1.3728560209,53.078540802],"type":"Point"}
}