{
  "type": "Feature",
  "properties": {
    "addr:full":"98 Vauxhall Road Liverpool Merseyside L3 6EZ",
    "addr:housenumber":"98",
    "addr:postcode":"l3 6ez",
    "addr:street":"Vauxhall Road",
    "iso:country":"GB",
    "sg:address":"98 Vauxhall Road",
    "sg:city":"Liverpool",
    "sg:classifiers":[
        {
            "category":"Building & Trades",
            "subcategory":"Construction",
            "type":"Services"
        }
    ],
    "sg:phone":"+44 151 236 7421",
    "sg:postcode":"L3 6EZ",
    "sg:province":"Merseyside",
    "sg:tags":[
        "fork",
        "lift",
        "truck"
    ],
    "sg:website":"http://www.evcuk.com",
    "wof:name":"A A Fork Truck & Engineering Ltd",
    "wof:placetype":"venue"
},
  "geometry": {"coordinates":[-2.990022,53.418957],"type":"Point"}
}