{
  "type": "Feature",
  "properties": {
    "iso:country":"GB",
    "sg:address":"16 Upton Road",
    "sg:city":"Wirral",
    "sg:classifiers":[
        {
            "category":"Education",
            "subcategory":"Dance Studio",
            "type":"Public Place"
        }
    ],
    "sg:postcode":"CH46 0PA",
    "sg:province":"Merseyside",
    "sg:tags":[
        "toning"
    ],
    "wof:name":"The Figure Firm",
    "wof:placetype":"venue"
},
  "geometry": {"coordinates":[-3.111457,53.400677],"type":"Point"}
}