{
  "type": "Feature",
  "properties": {
    "iso:country":"GB",
    "sg:address":"The Quarry, Waters Upton",
    "sg:city":"Telford",
    "sg:classifiers":[
        {
            "category":"Building & Trades",
            "subcategory":"Construction",
            "type":"Services"
        }
    ],
    "sg:postcode":"TF6 6NP",
    "sg:province":"Shropshire",
    "sg:tags":[
        "builder"
    ],
    "wof:name":"Norman Quinn",
    "wof:placetype":"venue"
},
  "geometry": {"coordinates":[-2.548499,52.771168],"type":"Point"}
}