{
  "type": "Feature",
  "properties": {
    "iso:country":"GB",
    "sg:address":"12 Market Place",
    "sg:city":"Diss",
    "sg:classifiers":[
        {
            "category":"Food & Beverages",
            "subcategory":"Meat & Fish",
            "type":"Retail Goods"
        }
    ],
    "sg:phone":"+44 1379 642452",
    "sg:postcode":"IP22 4AB",
    "sg:province":"Norfolk",
    "sg:tags":[
        "butcher"
    ],
    "wof:name":"Meat Inn Ltd.",
    "wof:placetype":"venue"
},
  "geometry": {"coordinates":[1.108718,52.376476],"type":"Point"}
}