{
  "type": "Feature",
  "properties": {
    "iso:country":"GB",
    "sg:address":"Aviation Way",
    "sg:city":"Southend-on-sea",
    "sg:classifiers":[
        {
            "category":"Arena",
            "subcategory":"Sports Club",
            "type":"Entertainment"
        }
    ],
    "sg:phone":"+44 1702 541499",
    "sg:postcode":"SS2 6UN",
    "sg:province":"Essex",
    "wof:name":"Westcliff Rugby Football Club Ltd.",
    "wof:placetype":"venue"
},
  "geometry": {"coordinates":[0.6834899783,51.5681343079],"type":"Point"}
}