{
  "type": "Feature",
  "properties": {
    "addr:full":"Moorgate House, Moorgate Road Rotherham South Yorkshire S60 2EN",
    "addr:postcode":"s60 2en",
    "addr:street":"Moorgate;Moorgate Road",
    "iso:country":"GB",
    "sg:address":"Moorgate House, Moorgate Road",
    "sg:city":"Rotherham",
    "sg:classifiers":[
        {
            "category":"Professional",
            "subcategory":"Management & Consulting",
            "type":"Services"
        }
    ],
    "sg:phone":"+44 1709 522235",
    "sg:postcode":"S60 2EN",
    "sg:province":"South Yorkshire",
    "sg:tags":[
        "consultant",
        "business"
    ],
    "wof:name":"Direct Creditor Administration Ltd.",
    "wof:placetype":"venue"
},
  "geometry": {"coordinates":[-1.353903,53.427063],"type":"Point"}
}