{
  "type": "Feature",
  "properties": {
    "addr:full":"17 Highbanks Road Pinner Greater London HA5 4AR",
    "addr:housenumber":"17",
    "addr:postcode":"ha5 4ar",
    "addr:street":"Highbanks Road",
    "iso:country":"GB",
    "sg:address":"17 Highbanks Road",
    "sg:city":"Pinner",
    "sg:classifiers":[
        {
            "category":"Professional",
            "subcategory":"Business Services",
            "type":"Services"
        }
    ],
    "sg:phone":"+44 20 8930 9231",
    "sg:postcode":"HA5 4AR",
    "sg:province":"Greater London",
    "sg:tags":[
        "import",
        "export",
        "agent"
    ],
    "wof:name":"Canam Africa Trading Co. (U K) Ltd.",
    "wof:placetype":"venue"
},
  "geometry": {"coordinates":[-0.3610300124,51.6149978638],"type":"Point"}
}