{
  "type": "Feature",
  "properties": {
    "iso:country":"GB",
    "sg:address":"Park Road",
    "sg:city":"Milnthorpe",
    "sg:classifiers":[
        {
            "category":"Real Estate",
            "subcategory":"Architect",
            "type":"Services"
        }
    ],
    "sg:phone":"+44 15395 64455",
    "sg:postcode":"LA7 7AD",
    "sg:province":"Cumbria",
    "wof:name":"Carr Humphreys Architecture",
    "wof:placetype":"venue"
},
  "geometry": {"coordinates":[-2.773389,54.226845],"type":"Point"}
}