{
  "type": "Feature",
  "properties": {
    "iso:country":"GB",
    "sg:address":"158 Broadway",
    "sg:city":"Peterborough",
    "sg:classifiers":[
        {
            "category":"Retail",
            "subcategory":"Veterinary Services",
            "type":"Services"
        }
    ],
    "sg:phone":"+44 1733 562904",
    "sg:postcode":"PE1 4DG",
    "sg:province":"Cambridgeshire",
    "sg:tags":[
        "surgeon",
        "pharmacy"
    ],
    "wof:name":"Broadway Veterinary Hospital",
    "wof:placetype":"venue"
},
  "geometry": {"coordinates":[-0.236697,52.581738],"type":"Point"}
}