{
  "type": "Feature",
  "properties": {
    "iso:country":"GB",
    "sg:address":"150 Lode Lane",
    "sg:city":"Solihull",
    "sg:classifiers":[
        {
            "category":"Professional",
            "subcategory":"Business Services",
            "type":"Services"
        },
        {
            "category":"Government",
            "subcategory":"Post Office",
            "type":"Public Place"
        }
    ],
    "sg:phone":"+44 121 704 5018",
    "sg:postcode":"B91 2HP",
    "sg:province":"West Midlands",
    "sg:tags":[
        "messenger",
        "courier"
    ],
    "wof:name":"A 2 Z Freight",
    "wof:placetype":"venue"
},
  "geometry": {"coordinates":[-1.776645,52.42561],"type":"Point"}
}