{
  "type": "Feature",
  "properties": {
    "iso:country":"GB",
    "sg:address":"Unit 6, Manor Farm Road, Tyseley",
    "sg:city":"Birmingham",
    "sg:classifiers":[
        {
            "category":"Freight",
            "type":"Transportation"
        }
    ],
    "sg:phone":"+44 121 707 4929",
    "sg:postcode":"B11 2HT",
    "sg:province":"West Midlands",
    "sg:tags":[
        "overseas",
        "shipping",
        "removal"
    ],
    "wof:name":"Vanstead Ltd.",
    "wof:placetype":"venue"
},
  "geometry": {"coordinates":[-1.848239,52.454075],"type":"Point"}
}