{
  "type": "Feature",
  "properties": {
    "iso:country":"GB",
    "sg:address":"Firs Ind Est, Oldington Lane",
    "sg:city":"Kidderminster",
    "sg:classifiers":[
        {
            "category":"Autos & Motor Vehicles",
            "subcategory":"Boat Sales",
            "type":"Retail Goods"
        },
        {
            "category":"Manufacturing",
            "subcategory":"Watercraft",
            "type":"Manufacturing & Wholesale Goods"
        }
    ],
    "sg:phone":"+44 1562 746336",
    "sg:postcode":"DY11 7QN",
    "sg:province":"Staffordshire",
    "sg:tags":[
        "boatbuilder",
        "repair",
        "builder"
    ],
    "wof:name":"Blue C Marine Ltd",
    "wof:placetype":"venue"
},
  "geometry": {"coordinates":[-2.267474,52.359871],"type":"Point"}
}