{
  "type": "Feature",
  "properties": {
    "addr:full":"2-4 Walsall Road Wednesbury West Midlands WS10 9JL",
    "addr:housenumber":"2-4",
    "addr:postcode":"ws10 9jl",
    "addr:street":"Walsall Road",
    "iso:country":"GB",
    "sg:address":"2-4 Walsall Road",
    "sg:city":"Wednesbury",
    "sg:classifiers":[
        {
            "category":"Personal",
            "subcategory":"Beauty Salon",
            "type":"Services"
        }
    ],
    "sg:postcode":"WS10 9JL",
    "sg:province":"West Midlands",
    "sg:tags":[
        "unisex",
        "hairdresser"
    ],
    "wof:name":"Spot on Hair Fashions",
    "wof:placetype":"venue"
},
  "geometry": {"coordinates":[-2.034719944,52.5668792725],"type":"Point"}
}