{
  "type": "Feature",
  "properties": {
    "addr:full":"2 Twyford Close, Colsterworth Grantham Leicestershire NG33 5JX",
    "addr:housenumber":"2",
    "addr:postcode":"ng33 5jx",
    "addr:street":"Twyford Close",
    "iso:country":"GB",
    "sg:address":"2 Twyford Close, Colsterworth",
    "sg:city":"Grantham",
    "sg:classifiers":[
        {
            "category":"Real Estate",
            "subcategory":"Surveying",
            "type":"Services"
        }
    ],
    "sg:phone":"+44 1476 860223",
    "sg:postcode":"NG33 5JX",
    "sg:province":"Leicestershire",
    "sg:tags":[
        "surveyor",
        "quantity"
    ],
    "wof:name":"Ian R Richards",
    "wof:placetype":"venue"
},
  "geometry": {"coordinates":[-0.6185209751,52.8042488098],"type":"Point"}
}