{
  "type": "Feature",
  "properties": {
    "iso:country":"GB",
    "sg:address":"15 Prescott Pl",
    "sg:city":"Clapham",
    "sg:classifiers":[
        {
            "category":"Real Estate",
            "subcategory":"Architect",
            "type":"Services"
        }
    ],
    "sg:phone":"+44 7956 304900",
    "sg:postcode":"SW4 6BS",
    "sg:province":"Greater London",
    "wof:name":"Michael Betts Architects",
    "wof:placetype":"venue"
},
  "geometry": {"coordinates":[-0.13587,51.463531],"type":"Point"}
}