{
  "type": "Feature",
  "properties": {
    "iso:country":"GB",
    "sg:address":"Plantation House, Lynn Road, Littleport",
    "sg:city":"Ely",
    "sg:classifiers":[
        {
            "category":"Farming",
            "subcategory":"Crops",
            "type":"Manufacturing & Wholesale Goods"
        },
        {
            "category":"Farming",
            "subcategory":"Livestock Farm",
            "type":"Manufacturing & Wholesale Goods"
        }
    ],
    "sg:phone":"+44 1353 676276",
    "sg:postcode":"CB7 4TD",
    "sg:province":"Cambridgeshire",
    "sg:tags":[
        "arable",
        "others"
    ],
    "wof:name":"Riverfen Farms Ltd.",
    "wof:placetype":"venue"
},
  "geometry": {"coordinates":[0.323034,52.464973],"type":"Point"}
}