{
  "type": "Feature",
  "properties": {
    "addr:full":"Maesarddafen Road, Llwynhendy Llanelli Carmarthenshire SA14 9BT",
    "addr:postcode":"sa14 9bt",
    "addr:street":"Maesarddafen Road Llwynhendy;Carmarthenshire",
    "iso:country":"GB",
    "sg:address":"Maesarddafen Road, Llwynhendy",
    "sg:city":"Llanelli",
    "sg:classifiers":[
        {
            "category":"Education",
            "subcategory":"School",
            "type":"Public Place"
        }
    ],
    "sg:phone":"+44 1554 776168",
    "sg:postcode":"SA14 9BT",
    "sg:province":"Carmarthenshire",
    "sg:tags":[
        "local",
        "authority"
    ],
    "wof:name":"Ysgol Yr Ynys",
    "wof:placetype":"venue"
},
  "geometry": {"coordinates":[-4.1243839264,51.6794052124],"type":"Point"}
}