{
  "type": "Feature",
  "properties": {
    "addr:full":"Barling Manor, Barling Road Southend-on-sea Essex SS3 0QB",
    "addr:postcode":"ss3 0qb",
    "addr:street":"Barling Road",
    "iso:country":"GB",
    "sg:address":"Barling Manor, Barling Road",
    "sg:city":"Southend-on-sea",
    "sg:classifiers":[
        {
            "category":"Banks & Credit Unions",
            "subcategory":"Investment Brokerage",
            "type":"Services"
        }
    ],
    "sg:postcode":"SS3 0QB",
    "sg:province":"Essex",
    "wof:name":"Princedown Developments Ltd.",
    "wof:placetype":"venue"
},
  "geometry": {"coordinates":[0.7585099936,51.5547103882],"type":"Point"}
}