{
  "type": "Feature",
  "properties": {
    "addr:full":"15-16 Douglas Court Dundee Dundee City DD1 5BA",
    "addr:housenumber":"15-16",
    "addr:postcode":"dd1 5ba",
    "addr:street":"Douglas Court",
    "iso:country":"GB",
    "sg:address":"15-16 Douglas Court",
    "sg:city":"Dundee",
    "sg:classifiers":[
        {
            "category":"Professional",
            "subcategory":"Computer Services",
            "type":"Services"
        }
    ],
    "sg:postcode":"DD1 5BA",
    "sg:province":"Dundee City",
    "sg:tags":[
        "system",
        "software"
    ],
    "wof:name":"M T C Services",
    "wof:placetype":"venue"
},
  "geometry": {"coordinates":[-2.981875,56.463196],"type":"Point"}
}