{
  "type": "Feature",
  "properties": {
    "addr:full":"36 High Street Loughborough Leicestershire LE11 2PZ",
    "addr:housenumber":"36",
    "addr:postcode":"le11 2pz",
    "addr:street":"High Street",
    "iso:country":"GB",
    "sg:address":"36 High Street",
    "sg:city":"Loughborough",
    "sg:classifiers":[
        {
            "category":"Restaurant",
            "type":"Food & Drink"
        }
    ],
    "sg:phone":"+44 1509 265181",
    "sg:postcode":"LE11 2PZ",
    "sg:province":"Leicestershire",
    "sg:tags":[
        "italian"
    ],
    "wof:name":"Trenta Sei",
    "wof:placetype":"venue"
},
  "geometry": {"coordinates":[-1.205656,52.771656],"type":"Point"}
}