{
  "type": "Feature",
  "properties": {
    "iso:country":"GB",
    "sg:address":"High Street, Wick",
    "sg:city":"Bristol",
    "sg:classifiers":[
        {
            "category":"Shopping",
            "subcategory":"Musical Instruments",
            "type":"Retail Goods"
        }
    ],
    "sg:phone":"+44 117 937 4920",
    "sg:postcode":"BS30 5SH",
    "sg:province":"Gloucestershire",
    "wof:name":"Banjo Surgery",
    "wof:placetype":"venue"
},
  "geometry": {"coordinates":[-2.462891,51.447514],"type":"Point"}
}