{
  "type": "Feature",
  "properties": {
    "iso:country":"GB",
    "sg:address":"141 Dollis Road",
    "sg:city":"London",
    "sg:classifiers":[
        {
            "category":"Professional",
            "type":"Services"
        }
    ],
    "sg:phone":"+44 20 8371 9933",
    "sg:postcode":"NW7 1JX",
    "sg:province":"Greater London",
    "sg:tags":[
        "interior",
        "furnishers",
        "designer"
    ],
    "wof:name":"Jeffersons Jemnics Ltd.",
    "wof:placetype":"venue"
},
  "geometry": {"coordinates":[-0.205875,51.604374],"type":"Point"}
}