{
  "type": "Feature",
  "properties": {
    "addr:full":"Jarrold Way, Bowthorpe Employment Area Norwich Norfolk NR5 9JD",
    "addr:postcode":"nr5 9jd",
    "addr:street":"Jarrold Way;Norwich Norfolk",
    "iso:country":"GB",
    "sg:address":"Jarrold Way, Bowthorpe Employment Area",
    "sg:city":"Norwich",
    "sg:classifiers":[
        {
            "category":"Professional",
            "subcategory":"Printing & Photocopies",
            "type":"Services"
        }
    ],
    "sg:phone":"+44 1603 726400",
    "sg:postcode":"NR5 9JD",
    "sg:province":"Norfolk",
    "sg:tags":[
        "computer",
        "tag",
        "label"
    ],
    "wof:name":"Sinclair International Ltd.",
    "wof:placetype":"venue"
},
  "geometry": {"coordinates":[1.215685,52.642395],"type":"Point"}
}