{
  "type": "Feature",
  "properties": {
    "addr:full":"61 Newbottle Street Houghton-le-spring Durham DH4 4AR",
    "addr:housenumber":"61",
    "addr:postcode":"dh4 4ar",
    "addr:street":"Newbottle Street",
    "iso:country":"GB",
    "sg:address":"61 Newbottle Street",
    "sg:city":"Houghton-le-spring",
    "sg:classifiers":[
        {
            "category":"Travel",
            "subcategory":"Travel Agent",
            "type":"Entertainment"
        }
    ],
    "sg:phone":"+44 191 584 2052",
    "sg:postcode":"DH4 4AR",
    "sg:province":"Durham",
    "wof:name":"Lunn Poly Ltd.",
    "wof:placetype":"venue"
},
  "geometry": {"coordinates":[-1.471729,54.844917],"type":"Point"}
}