{
  "type": "Feature",
  "properties": {
    "addr:full":"11 Old Brompton Rd, South Kensington South Kensington Greater London SW7 3HZ",
    "addr:housenumber":"11",
    "addr:postcode":"sw7 3hz",
    "addr:street":"Old Brompton Rd",
    "iso:country":"GB",
    "sg:address":"11 Old Brompton Rd, South Kensington",
    "sg:city":"South Kensington",
    "sg:classifiers":[
        {
            "category":"Food & Beverages",
            "subcategory":"Supermarket",
            "type":"Retail Goods"
        }
    ],
    "sg:phone":"+44 20 7584 3825",
    "sg:postcode":"SW7 3HZ",
    "sg:province":"Greater London",
    "wof:name":"Spar",
    "wof:placetype":"venue"
},
  "geometry": {"coordinates":[-0.175181,51.493435],"type":"Point"}
}