{
  "type": "Feature",
  "properties": {
    "addr:full":"Unit 21, Canalside Industrial Estate, Anchouser Hill Brierley Hill West Midlands DY5 3JU",
    "addr:housenumber":"unit 21;estate anchouser",
    "addr:postcode":"dy5 3ju",
    "addr:street":"Canalside Industrial;Hill Brierley Hill",
    "iso:country":"GB",
    "sg:address":"Unit 21, Canalside Industrial Estate, Anchouser Hill",
    "sg:city":"Brierley Hill",
    "sg:classifiers":[
        {
            "category":"Retail",
            "subcategory":"Auto Repair",
            "type":"Services"
        }
    ],
    "sg:phone":"+44 1384 573434",
    "sg:postcode":"DY5 3JU",
    "sg:province":"West Midlands",
    "sg:tags":[
        "modification",
        "garage"
    ],
    "wof:name":"N E Motors",
    "wof:placetype":"venue"
},
  "geometry": {"coordinates":[-2.1213009357,52.48204422],"type":"Point"}
}