{
  "type": "Feature",
  "properties": {
    "iso:country":"GB",
    "sg:address":"Greenfields, Hall Road, Old Beetley",
    "sg:city":"Dereham",
    "sg:classifiers":[
        {
            "category":"Manufacturing",
            "subcategory":"Tools & Machinery",
            "type":"Manufacturing & Wholesale Goods"
        }
    ],
    "sg:postcode":"NR20 4DE",
    "sg:province":"Norfolk",
    "sg:tags":[
        "society",
        "friendly"
    ],
    "wof:name":"Martin Insurance Services",
    "wof:placetype":"venue"
},
  "geometry": {"coordinates":[0.919945,52.717468],"type":"Point"}
}