{
  "type": "Feature",
  "properties": {
    "addr:full":"227 Blackstock Road London Greater London N5 2LL",
    "addr:housenumber":"227",
    "addr:postcode":"n5 2ll",
    "addr:street":"Blackstock Road",
    "iso:country":"GB",
    "sg:address":"227 Blackstock Road",
    "sg:city":"London",
    "sg:classifiers":[
        {
            "category":"Cafe",
            "type":"Food & Drink"
        }
    ],
    "sg:phone":"+44 20 7359 3633",
    "sg:postcode":"N5 2LL",
    "sg:province":"Greater London",
    "sg:tags":[
        "tea",
        "snack",
        "bar",
        "room"
    ],
    "wof:name":"Arsenal Cafe",
    "wof:placetype":"venue"
},
  "geometry": {"coordinates":[-0.0983730033,51.5586204529],"type":"Point"}
}