{
  "type": "Feature",
  "properties": {
    "addr:full":"Bridgeway, Old Woods Shrewsbury Shropshire SY4 3AX",
    "addr:postcode":"sy4 3ax",
    "addr:street":"Bridgeway Old Woods",
    "iso:country":"GB",
    "sg:address":"Bridgeway, Old Woods",
    "sg:city":"Shrewsbury",
    "sg:classifiers":[
        {
            "category":"Banks & Credit Unions",
            "subcategory":"Financial Services",
            "type":"Services"
        }
    ],
    "sg:phone":"+44 1939 291323",
    "sg:postcode":"SY4 3AX",
    "sg:province":"Shropshire",
    "sg:tags":[
        "consultant"
    ],
    "wof:name":"Lease Finance Ltd.",
    "wof:placetype":"venue"
},
  "geometry": {"coordinates":[-2.81089,52.77668],"type":"Point"}
}