{
  "type": "Feature",
  "properties": {
    "iso:country":"GB",
    "sg:address":"5 Noke Lane Business Centre, Noke Lane",
    "sg:city":"St Albans",
    "sg:classifiers":[
        {
            "category":"Building & Trades",
            "subcategory":"Construction",
            "type":"Services"
        }
    ],
    "sg:phone":"+44 1727 854137",
    "sg:postcode":"AL2 3NY",
    "sg:province":"Hertfordshire",
    "sg:tags":[
        "glazier"
    ],
    "wof:name":"V I P Glass Services",
    "wof:placetype":"venue"
},
  "geometry": {"coordinates":[-0.3764339983,51.7295455933],"type":"Point"}
}