{
  "type": "Feature",
  "properties": {
    "iso:country":"GB",
    "sg:address":"59 Seaview Road, Liscard",
    "sg:city":"Wallasey",
    "sg:classifiers":[
        {
            "category":"Fast Food",
            "type":"Food & Drink"
        }
    ],
    "sg:phone":"+44 151 346 9676",
    "sg:postcode":"CH45 4QW",
    "sg:province":"Merseyside",
    "sg:tags":[
        "away",
        "take"
    ],
    "wof:name":"A Slik",
    "wof:placetype":"venue"
},
  "geometry": {"coordinates":[-3.046544,53.42194],"type":"Point"}
}