{
  "type": "Feature",
  "properties": {
    "iso:country":"GB",
    "sg:address":"210-216 High St",
    "sg:city":"Slough",
    "sg:classifiers":[
        {
            "category":"Shopping",
            "subcategory":"Catalog Store",
            "type":"Retail Goods"
        }
    ],
    "sg:phone":"+44 1753 693530",
    "sg:postcode":"SL1 1JS",
    "sg:province":"Berkshire",
    "sg:tags":[
        "catalogue",
        "showroom"
    ],
    "wof:name":"Index The Catalogue Shop",
    "wof:placetype":"venue"
},
  "geometry": {"coordinates":[-0.588758,51.507652],"type":"Point"}
}