{
  "type": "Feature",
  "properties": {
    "iso:country":"GB",
    "sg:address":"27 Station Road, Rainham",
    "sg:city":"Gillingham",
    "sg:classifiers":[
        {
            "category":"Fast Food",
            "type":"Food & Drink"
        }
    ],
    "sg:phone":"+44 1634 376223",
    "sg:postcode":"ME8 7RS",
    "sg:province":"Kent",
    "sg:tags":[
        "away",
        "take"
    ],
    "wof:name":"Castle Tandoori",
    "wof:placetype":"venue"
},
  "geometry": {"coordinates":[0.609128,51.364105],"type":"Point"}
}