{
  "type": "Feature",
  "properties": {
    "addr:full":"58a Warton Road London Greater London E15 2JU",
    "addr:housenumber":"58a",
    "addr:postcode":"e15 2ju",
    "addr:street":"Warton Road",
    "iso:country":"GB",
    "sg:address":"58a Warton Road",
    "sg:city":"London",
    "sg:classifiers":[
        {
            "category":"Utilities",
            "subcategory":"Refuse",
            "type":"Services"
        }
    ],
    "sg:phone":"+44 20 8519 5206",
    "sg:postcode":"E15 2JU",
    "sg:province":"Greater London",
    "sg:tags":[
        "disposal",
        "waste"
    ],
    "wof:name":"O'Donovan (Waste Disposal) Ltd.",
    "wof:placetype":"venue"
},
  "geometry": {"coordinates":[-0.0095619997,51.5389099121],"type":"Point"}
}