{
  "type": "Feature",
  "properties": {
    "addr:full":"44 Avondale Crescent Enfield Greater London EN3 7RY",
    "addr:housenumber":"44",
    "addr:postcode":"en3 7ry",
    "addr:street":"Avondale Crescent",
    "iso:country":"GB",
    "sg:address":"44 Avondale Crescent",
    "sg:city":"Enfield",
    "sg:classifiers":[
        {
            "category":"Building & Trades",
            "subcategory":"Construction",
            "type":"Services"
        }
    ],
    "sg:postcode":"EN3 7RY",
    "sg:province":"Greater London",
    "sg:tags":[
        "builder"
    ],
    "wof:name":"Agombar Installations Ltd",
    "wof:placetype":"venue"
},
  "geometry": {"coordinates":[-0.0325380005,51.6515464783],"type":"Point"}
}