{
  "type": "Feature",
  "properties": {
    "iso:country":"GB",
    "sg:address":"P O Box 6475",
    "sg:city":"London",
    "sg:classifiers":[
        {
            "category":"Shopping",
            "subcategory":"Mobile Phones",
            "type":"Retail Goods"
        }
    ],
    "sg:postcode":"N3 3QF",
    "sg:province":"Greater London",
    "wof:name":"Accessories Direct Uk",
    "wof:placetype":"venue"
},
  "geometry": {"coordinates":[-0.19935,51.594002],"type":"Point"}
}