{
  "type": "Feature",
  "properties": {
    "iso:country":"GB",
    "sg:address":"The Old School, 51 Princes Road",
    "sg:city":"Weybridge",
    "sg:classifiers":[
        {
            "category":"Professional",
            "subcategory":"Accounting & Tax Preparation",
            "type":"Services"
        }
    ],
    "sg:phone":"+44 1932 820612",
    "sg:postcode":"KT13 9DA",
    "sg:province":"Surrey",
    "sg:tags":[
        "accountant"
    ],
    "wof:name":"C B Heslop & Co.",
    "wof:placetype":"venue"
},
  "geometry": {"coordinates":[-0.4580650032,51.3727493286],"type":"Point"}
}