{
  "type": "Feature",
  "properties": {
    "iso:country":"GB",
    "sg:address":"Blackdog Industrial Centre, Bridge Of Don",
    "sg:city":"Aberdeen",
    "sg:classifiers":[
        {
            "category":"Freight",
            "type":"Transportation"
        }
    ],
    "sg:phone":"+44 1224 824990",
    "sg:postcode":"AB23 8BT",
    "sg:province":"Aberdeen City",
    "sg:tags":[
        "haulage",
        "road"
    ],
    "wof:name":"Newhills Logistics Ltd.",
    "wof:placetype":"venue"
},
  "geometry": {"coordinates":[-2.1003799438,57.1821784973],"type":"Point"}
}