{
  "type": "Feature",
  "properties": {
    "addr:full":"497 Herne Road, Ramsey St Marys, Ramsey Huntingdon Cambridgeshire PE26 2TJ",
    "addr:housenumber":"497",
    "addr:postcode":"pe26 2tj",
    "addr:street":"Herne Road Ramsey;Huntingdon",
    "iso:country":"GB",
    "sg:address":"497 Herne Road, Ramsey St Marys, Ramsey",
    "sg:city":"Huntingdon",
    "sg:classifiers":[
        {
            "category":"Home & Garden",
            "subcategory":"Garden Supply",
            "type":"Retail Goods"
        },
        {
            "category":"Farming",
            "subcategory":"Livestock Farm",
            "type":"Manufacturing & Wholesale Goods"
        }
    ],
    "sg:phone":"+44 1733 844530",
    "sg:postcode":"PE26 2TJ",
    "sg:province":"Cambridgeshire",
    "sg:tags":[
        "bulb",
        "grower",
        "others"
    ],
    "wof:name":"Robert William Neal",
    "wof:placetype":"venue"
},
  "geometry": {"coordinates":[-0.143123,52.511818],"type":"Point"}
}