{
  "type": "Feature",
  "properties": {
    "addr:full":"Salter House 11a Kingswood Road, Hampton Lovett Droitwich Worcestershire WR9 0QH",
    "addr:housenumber":"11a",
    "addr:postcode":"wr9 0qh",
    "addr:street":"Kingswood Road",
    "iso:country":"GB",
    "sg:address":"Salter House 11a Kingswood Road, Hampton Lovett",
    "sg:city":"Droitwich",
    "sg:classifiers":[
        {
            "category":"Communications",
            "type":"Services"
        }
    ],
    "sg:postcode":"WR9 0QH",
    "sg:province":"Worcestershire",
    "sg:tags":[
        "telecommunication"
    ],
    "wof:name":"Telecom Solutions & Services Ltd",
    "wof:placetype":"venue"
},
  "geometry": {"coordinates":[-2.1729099751,52.2860374451],"type":"Point"}
}