{
  "type": "Feature",
  "properties": {
    "addr:full":"Unit 2 Chapel Hill Braintree Essex CM7 3QT",
    "addr:housenumber":"unit 2",
    "addr:postcode":"cm7 3qt",
    "addr:street":"Chapel Hill",
    "iso:country":"GB",
    "sg:address":"Unit 2 Chapel Hill",
    "sg:city":"Braintree",
    "sg:classifiers":[
        {
            "category":"Autos & Motor Vehicles",
            "subcategory":"Motorcycle Sales",
            "type":"Retail Goods"
        }
    ],
    "sg:phone":"+44 1376 551624",
    "sg:postcode":"CM7 3QT",
    "sg:province":"Essex",
    "wof:name":"Silverex Engineers Ltd.",
    "wof:placetype":"venue"
},
  "geometry": {"coordinates":[0.567499,51.876305],"type":"Point"}
}