{
  "type": "Feature",
  "properties": {
    "addr:full":"Church Road London Greater London SW19 5AG",
    "addr:postcode":"sw19 5ag",
    "addr:street":"Church Road",
    "iso:country":"GB",
    "sg:address":"Church Road",
    "sg:city":"London",
    "sg:classifiers":[
        {
            "category":"Organizations",
            "subcategory":"Membership Organization",
            "type":"Services"
        }
    ],
    "sg:postcode":"SW19 5AG",
    "sg:province":"Greater London",
    "sg:tags":[
        "club"
    ],
    "wof:name":"Wimbledon Lakeside Club",
    "wof:placetype":"venue"
},
  "geometry": {"coordinates":[-0.21526,51.436138],"type":"Point"}
}