{
  "type": "Feature",
  "properties": {
    "iso:country":"GB",
    "sg:address":"New House Farm, Winstanley Road, Billinge",
    "sg:city":"Wigan",
    "sg:classifiers":[
        {
            "category":"Home & Garden",
            "subcategory":"Garden Supply",
            "type":"Retail Goods"
        }
    ],
    "sg:phone":"+44 1695 632317",
    "sg:postcode":"WN5 7XG",
    "sg:province":"Lancashire",
    "sg:tags":[
        "nursery",
        "centre"
    ],
    "wof:name":"Billinge Garden Centre",
    "wof:placetype":"venue"
},
  "geometry": {"coordinates":[-2.7149190903,53.4927635193],"type":"Point"}
}