{
  "type": "Feature",
  "properties": {
    "iso:country":"GB",
    "sg:address":"353 Bury Old Road, Prestwich",
    "sg:city":"Manchester",
    "sg:classifiers":[
        {
            "category":"Banks & Credit Unions",
            "subcategory":"Financial Services",
            "type":"Services"
        }
    ],
    "sg:phone":"+44 161 773 7528",
    "sg:postcode":"M25 1PY",
    "sg:province":"Greater Manchester",
    "sg:tags":[
        "adviser",
        "finance"
    ],
    "wof:name":"THORNMODE FINANCE LTD",
    "wof:placetype":"venue"
},
  "geometry": {"coordinates":[-2.2691791058,53.5353164673],"type":"Point"}
}