{
  "type": "Feature",
  "properties": {
    "addr:full":"11 Sheridan Drive, Galley Common Nuneaton Leicestershire CV10 9QU",
    "addr:housenumber":"11",
    "addr:postcode":"cv10 9qu",
    "addr:street":"Sheridan Drive",
    "iso:country":"GB",
    "sg:address":"11 Sheridan Drive, Galley Common",
    "sg:city":"Nuneaton",
    "sg:classifiers":[
        {
            "category":"Government",
            "subcategory":"Post Office",
            "type":"Public Place"
        }
    ],
    "sg:phone":"+44 24 7639 5821",
    "sg:postcode":"CV10 9QU",
    "sg:province":"Leicestershire",
    "sg:tags":[
        "messenger",
        "courier"
    ],
    "wof:name":"Special Delivery",
    "wof:placetype":"venue"
},
  "geometry": {"coordinates":[-1.5325039625,52.525932312],"type":"Point"}
}