{
  "type": "Feature",
  "properties": {
    "iso:country":"GB",
    "sg:address":"8 Church St",
    "sg:city":"Warrington",
    "sg:classifiers":[
        {
            "category":"Health Services",
            "subcategory":"Dentist",
            "type":"Services"
        }
    ],
    "sg:phone":"+44 1928 735377",
    "sg:postcode":"WA6 7EB",
    "sg:province":"Cheshire",
    "wof:name":"D A Bidwell",
    "wof:placetype":"venue"
},
  "geometry": {"coordinates":[-2.725523,53.295547],"type":"Point"}
}