{
  "type": "Feature",
  "properties": {
    "addr:full":"4 Huntsman Wood Liverpool Merseyside L12 0HY",
    "addr:housenumber":"4",
    "addr:postcode":"l12 0hy",
    "addr:street":"Huntsman Wood",
    "iso:country":"GB",
    "sg:address":"4 Huntsman Wood",
    "sg:city":"Liverpool",
    "sg:classifiers":[
        {
            "category":"Professional",
            "subcategory":"Detective & Security Services",
            "type":"Services"
        }
    ],
    "sg:phone":"+44 151 283 8161",
    "sg:postcode":"L12 0HY",
    "sg:province":"Merseyside",
    "sg:tags":[
        "car"
    ],
    "wof:name":"Erickson Car Security",
    "wof:placetype":"venue"
},
  "geometry": {"coordinates":[-2.884642,53.437466],"type":"Point"}
}