{
  "type": "Feature",
  "properties": {
    "iso:country":"GB",
    "sg:address":"157a Kings Road",
    "sg:city":"Harrogate",
    "sg:classifiers":[
        {
            "category":"Insurance",
            "subcategory":"Insurance Agent",
            "type":"Services"
        }
    ],
    "sg:phone":"+44 1423 504213",
    "sg:postcode":"HG1 5JQ",
    "sg:province":"North Yorkshire",
    "wof:name":"Swinton",
    "wof:placetype":"venue"
},
  "geometry": {"coordinates":[-1.536591053,54.0035057068],"type":"Point"}
}