{
  "type": "Feature",
  "properties": {
    "addr:full":"Hamilton St Chester Cheshire CH2 3JG",
    "addr:postcode":"ch2 3jg",
    "addr:street":"Hamilton St",
    "iso:country":"GB",
    "sg:address":"Hamilton St",
    "sg:city":"Chester",
    "sg:classifiers":[
        {
            "category":"Place Of Worship",
            "type":"Public Place"
        }
    ],
    "sg:phone":"+44 1244 321950",
    "sg:postcode":"CH2 3JG",
    "sg:province":"Cheshire",
    "wof:name":"Hamilton Street Methodist Church",
    "wof:placetype":"venue"
},
  "geometry": {"coordinates":[-2.8741340637,53.2002067566],"type":"Point"}
}