{
  "type": "Feature",
  "properties": {
    "addr:full":"Unit 6 Hecla Wks, Brown St Preston Lancashire PR5 6LW",
    "addr:housenumber":"unit 6",
    "addr:postcode":"pr5 6lw",
    "addr:street":"Wks Brown St",
    "iso:country":"GB",
    "sg:address":"Unit 6 Hecla Wks, Brown St",
    "sg:city":"Preston",
    "sg:classifiers":[
        {
            "category":"Home & Garden",
            "subcategory":"Furniture",
            "type":"Retail Goods"
        }
    ],
    "sg:postcode":"PR5 6LW",
    "sg:province":"Lancashire",
    "wof:name":"Principal Pine Furniture",
    "wof:placetype":"venue"
},
  "geometry": {"coordinates":[-2.65937,53.725712],"type":"Point"}
}