{
  "type": "Feature",
  "properties": {
    "iso:country":"GB",
    "sg:address":"133 Gloucester Road",
    "sg:city":"Bristol",
    "sg:classifiers":[
        {
            "category":"Retail",
            "subcategory":"Photofinishing",
            "type":"Services"
        }
    ],
    "sg:postcode":"BS7 8AX",
    "sg:province":"City of Bristol",
    "sg:tags":[
        "photographic",
        "processor"
    ],
    "wof:name":"Snap Shack Ltd.",
    "wof:placetype":"venue"
},
  "geometry": {"coordinates":[-2.593829,51.469872],"type":"Point"}
}