{
  "type": "Feature",
  "properties": {
    "addr:full":"361 Grimsby Road Cleethorpes Lincolnshire DN35 7JR",
    "addr:housenumber":"361",
    "addr:postcode":"dn35 7jr",
    "addr:street":"Grimsby Road",
    "iso:country":"GB",
    "sg:address":"361 Grimsby Road",
    "sg:city":"Cleethorpes",
    "sg:classifiers":[
        {
            "category":"Personal",
            "subcategory":"Barber",
            "type":"Services"
        }
    ],
    "sg:phone":"+44 1472 691543",
    "sg:postcode":"DN35 7JR",
    "sg:province":"Lincolnshire",
    "sg:tags":[
        "men's",
        "hairdresser"
    ],
    "wof:name":"Cripsey's",
    "wof:placetype":"venue"
},
  "geometry": {"coordinates":[-0.0403419994,53.5651130676],"type":"Point"}
}