{
  "type": "Feature",
  "properties": {
    "addr:full":"561 Wilbraham Road Manchester Cheshire M21 0AE",
    "addr:housenumber":"561",
    "addr:postcode":"m21 0ae",
    "addr:street":"Wilbraham Road",
    "iso:country":"GB",
    "sg:address":"561 Wilbraham Road",
    "sg:city":"Manchester",
    "sg:classifiers":[
        {
            "category":"Food & Beverages",
            "subcategory":"Bakery",
            "type":"Retail Goods"
        }
    ],
    "sg:phone":"+44 161 861 9344",
    "sg:postcode":"M21 0AE",
    "sg:province":"Cheshire",
    "sg:tags":[
        "baker"
    ],
    "wof:name":"Greggs of Manchester",
    "wof:placetype":"venue"
},
  "geometry": {"coordinates":[-2.276574,53.442524],"type":"Point"}
}