{
  "type": "Feature",
  "properties": {
    "addr:full":"Sturges Road Wokingham Berkshire RG40 2HE",
    "addr:postcode":"rg40 2he",
    "addr:street":"Sturges Road",
    "iso:country":"GB",
    "sg:address":"Sturges Road",
    "sg:city":"Wokingham",
    "sg:classifiers":[
        {
            "category":"Place Of Worship",
            "type":"Public Place"
        }
    ],
    "sg:postcode":"RG40 2HE",
    "sg:province":"Berkshire",
    "wof:name":"Corpus Christi Church (R.C)",
    "wof:placetype":"venue"
},
  "geometry": {"coordinates":[-0.8316659927,51.4092674255],"type":"Point"}
}