{
  "type": "Feature",
  "properties": {
    "iso:country":"GB",
    "sg:address":"105-111 Euston Street",
    "sg:city":"London",
    "sg:classifiers":[
        {
            "category":"Real Estate",
            "subcategory":"Architect",
            "type":"Services"
        }
    ],
    "sg:phone":"+44 20 7387 0451",
    "sg:postcode":"NW1 2EW",
    "sg:province":"Greater London",
    "wof:name":"Betham Associates Architects",
    "wof:placetype":"venue"
},
  "geometry": {"coordinates":[-0.135704,51.526752],"type":"Point"}
}