{
  "type": "Feature",
  "properties": {
    "iso:country":"GB",
    "sg:address":"24 High Street, Gnosall",
    "sg:city":"Stafford",
    "sg:classifiers":[
        {
            "category":"Shopping",
            "subcategory":"Pharmacy",
            "type":"Retail Goods"
        }
    ],
    "sg:phone":"+44 1785 822228",
    "sg:postcode":"ST20 0EX",
    "sg:province":"Staffordshire",
    "sg:tags":[
        "pharmacist",
        "chemist"
    ],
    "wof:name":"Gnosall Pharmacy",
    "wof:placetype":"venue"
},
  "geometry": {"coordinates":[-2.254412,52.784702],"type":"Point"}
}