{
  "type": "Feature",
  "properties": {
    "addr:full":"Petters Way Yeovil Somerset BA20 1SW",
    "addr:postcode":"ba20 1sw",
    "addr:street":"Petters Way",
    "iso:country":"GB",
    "sg:address":"Petters Way",
    "sg:city":"Yeovil",
    "sg:classifiers":[
        {
            "category":"Government",
            "subcategory":"Court House",
            "type":"Public Place"
        }
    ],
    "sg:phone":"+44 1935 426281",
    "sg:postcode":"BA20 1SW",
    "sg:province":"Somerset",
    "wof:name":"South Somerset Magistrates Court",
    "wof:placetype":"venue"
},
  "geometry": {"coordinates":[-2.633929,50.939869],"type":"Point"}
}