{
  "type": "Feature",
  "properties": {
    "addr:full":"84 Bookerhill Road High Wycombe Buckinghamshire HP12 4EX",
    "addr:housenumber":"84",
    "addr:postcode":"hp12 4ex",
    "addr:street":"Bookerhill Road",
    "iso:country":"GB",
    "sg:address":"84 Bookerhill Road",
    "sg:city":"High Wycombe",
    "sg:classifiers":[
        {
            "category":"Professional",
            "subcategory":"Accounting & Tax Preparation",
            "type":"Services"
        },
        {
            "category":"Building & Trades",
            "subcategory":"Landscaping Services",
            "type":"Services"
        }
    ],
    "sg:phone":"+44 1494 558228",
    "sg:postcode":"HP12 4EX",
    "sg:province":"Buckinghamshire",
    "sg:tags":[
        "accountant",
        "gardening"
    ],
    "wof:name":"P GOMME",
    "wof:placetype":"venue"
},
  "geometry": {"coordinates":[-0.7879189849,51.624080658],"type":"Point"}
}