{
  "type": "Feature",
  "properties": {
    "iso:country":"GB",
    "sg:address":"Rear Of 102 London Rd",
    "sg:city":"Cheltenham",
    "sg:classifiers":[
        {
            "category":"Professional",
            "subcategory":"Art Services",
            "type":"Services"
        }
    ],
    "sg:phone":"+44 1242 572797",
    "sg:postcode":"GL52 6HJ",
    "sg:province":"Gloucestershire",
    "sg:tags":[
        "carver",
        "sculptor"
    ],
    "wof:name":"The Sculpture Studios",
    "wof:placetype":"venue"
},
  "geometry": {"coordinates":[-2.06343,51.893059],"type":"Point"}
}