{
  "type": "Feature",
  "properties": {
    "addr:full":"59 Liddesdale Square Glasgow Glasgow City G22 7BT",
    "addr:housenumber":"59",
    "addr:postcode":"g22 7bt",
    "addr:street":"Liddesdale Square",
    "iso:country":"GB",
    "sg:address":"59 Liddesdale Square",
    "sg:city":"Glasgow",
    "sg:classifiers":[
        {
            "category":"Shopping",
            "subcategory":"Pharmacy",
            "type":"Retail Goods"
        }
    ],
    "sg:phone":"+44 141 772 1830",
    "sg:postcode":"G22 7BT",
    "sg:province":"Glasgow City",
    "sg:tags":[
        "pharmacist",
        "chemist"
    ],
    "wof:name":"J Wood",
    "wof:placetype":"venue"
},
  "geometry": {"coordinates":[-4.2406978607,55.8966598511],"type":"Point"}
}