{
  "type": "Feature",
  "properties": {
    "addr:full":"Rowms Lane, Swinton Mexborough South Yorkshire S64 8AA",
    "addr:postcode":"s64 8aa",
    "addr:street":"Rowms Lane",
    "iso:country":"GB",
    "sg:address":"Rowms Lane, Swinton",
    "sg:city":"Mexborough",
    "sg:classifiers":[
        {
            "category":"Autos & Motor Vehicles",
            "subcategory":"Fuel & Gas Station",
            "type":"Retail Goods"
        }
    ],
    "sg:postcode":"S64 8AA",
    "sg:province":"South Yorkshire",
    "sg:tags":[
        "petrol",
        "filling"
    ],
    "wof:name":"Sparks of Swinton Ltd.",
    "wof:placetype":"venue"
},
  "geometry": {"coordinates":[-1.317868948,53.4877662659],"type":"Point"}
}