{
  "type": "Feature",
  "properties": {
    "addr:full":"17a Mount Pleasant Rd Tunbridge Wells Kent TN1 1NT",
    "addr:housenumber":"17a",
    "addr:postcode":"tn1 1nt",
    "addr:street":"Mount Pleasant Rd",
    "iso:country":"GB",
    "sg:address":"17a Mount Pleasant Rd",
    "sg:city":"Tunbridge Wells",
    "sg:classifiers":[
        {
            "category":"Shopping",
            "subcategory":"Shoes",
            "type":"Retail Goods"
        }
    ],
    "sg:phone":"+44 1892 548213",
    "sg:postcode":"TN1 1NT",
    "sg:province":"Kent",
    "wof:name":"Peters Shoes",
    "wof:placetype":"venue"
},
  "geometry": {"coordinates":[0.2633010149,51.1306610107],"type":"Point"}
}