{
  "type": "Feature",
  "properties": {
    "addr:full":"693 Edenfield Rd Rochdale Lancashire OL11 5SL",
    "addr:housenumber":"693",
    "addr:postcode":"ol11 5sl",
    "addr:street":"Edenfield Rd",
    "iso:country":"GB",
    "sg:address":"693 Edenfield Rd",
    "sg:city":"Rochdale",
    "sg:classifiers":[
        {
            "category":"Shopping",
            "subcategory":"News",
            "type":"Retail Goods"
        }
    ],
    "sg:postcode":"OL11 5SL",
    "sg:province":"Lancashire",
    "sg:tags":[
        "newsagent"
    ],
    "wof:name":"Bennett,W & L,",
    "wof:placetype":"venue"
},
  "geometry": {"coordinates":[-2.2127850056,53.6270904541],"type":"Point"}
}