{
  "type": "Feature",
  "properties": {
    "iso:country":"GB",
    "sg:address":"Wheal Plenty, Scorrier",
    "sg:city":"Truro",
    "sg:classifiers":[
        {
            "category":"Food & Beverages",
            "subcategory":"Farmers Market",
            "type":"Retail Goods"
        }
    ],
    "sg:phone":"+44 1209 890521",
    "sg:postcode":"TR16 5DG",
    "sg:province":"Cornwall",
    "sg:tags":[
        "gardener"
    ],
    "wof:name":"Percival D Richards",
    "wof:placetype":"venue"
},
  "geometry": {"coordinates":[-5.186599,50.249737],"type":"Point"}
}