{
  "type": "Feature",
  "properties": {
    "addr:full":"Hayes Centre, Coldharbour Lane Hayes Greater London UB3 3BB",
    "addr:postcode":"ub3 3bb",
    "addr:street":"Coldharbour Lane",
    "iso:country":"GB",
    "sg:address":"Hayes Centre, Coldharbour Lane",
    "sg:city":"Hayes",
    "sg:classifiers":[
        {
            "category":"Farming",
            "subcategory":"Nursery",
            "type":"Manufacturing & Wholesale Goods"
        }
    ],
    "sg:phone":"+44 20 8756 0268",
    "sg:postcode":"UB3 3BB",
    "sg:province":"Greater London",
    "sg:tags":[
        "creche"
    ],
    "wof:name":"Uxbridge College Day Nursery",
    "wof:placetype":"venue"
},
  "geometry": {"coordinates":[-0.4166359901,51.5079460144],"type":"Point"}
}