{
  "type": "Feature",
  "properties": {
    "addr:full":"177 Hook Road Surbiton Surrey KT6 5AR",
    "addr:housenumber":"177",
    "addr:postcode":"kt6 5ar",
    "addr:street":"Hook Road",
    "iso:country":"GB",
    "sg:address":"177 Hook Road",
    "sg:city":"Surbiton",
    "sg:classifiers":[
        {
            "category":"Communications",
            "type":"Services"
        }
    ],
    "sg:phone":"+44 20 8407 5744",
    "sg:postcode":"KT6 5AR",
    "sg:province":"Surrey",
    "sg:tags":[
        "telecommunication"
    ],
    "wof:name":"New World Telecom (U K) Ltd.",
    "wof:placetype":"venue"
},
  "geometry": {"coordinates":[-0.303279,51.375984],"type":"Point"}
}