{
  "type": "Feature",
  "properties": {
    "addr:full":"Astral House, P O Box 7 Miller Street Preston Lancashire PR1 1EA",
    "addr:housenumber":"7",
    "addr:postcode":"pr1 1ea",
    "addr:street":"P;Box;Miller Street",
    "iso:country":"GB",
    "sg:address":"Astral House, P O Box 7 Miller Street",
    "sg:city":"Preston",
    "sg:classifiers":[
        {
            "category":"Professional",
            "type":"Services"
        }
    ],
    "sg:phone":"+44 1772 259781",
    "sg:postcode":"PR1 1EA",
    "sg:province":"Lancashire",
    "sg:tags":[
        "specialist",
        "coating"
    ],
    "wof:name":"Liquid Plastics Ltd.",
    "wof:placetype":"venue"
},
  "geometry": {"coordinates":[-2.705729,53.757961],"type":"Point"}
}