{
  "type": "Feature",
  "properties": {
    "iso:country":"GB",
    "sg:address":"Unit L Tribune Drive, Trinity Trading Estate",
    "sg:city":"Sittingbourne",
    "sg:classifiers":[
        {
            "category":"Home & Garden",
            "subcategory":"Building Materials",
            "type":"Retail Goods"
        }
    ],
    "sg:postcode":"ME10 2PG",
    "sg:province":"Kent",
    "sg:tags":[
        "ventilator",
        "ventilation",
        "system"
    ],
    "wof:name":"Gaylord Industries (Europe) Ltd.",
    "wof:placetype":"venue"
},
  "geometry": {"coordinates":[0.7379230261,51.3518295288],"type":"Point"}
}