{
  "type": "Feature",
  "properties": {
    "addr:full":"Brimham Rocks Road, Hartwith Harrogate North Yorkshire HG3 3HE",
    "addr:postcode":"hg3 3he",
    "addr:street":"Brimham Rocks Road Hartwith",
    "iso:country":"GB",
    "sg:address":"Brimham Rocks Road, Hartwith",
    "sg:city":"Harrogate",
    "sg:classifiers":[
        {
            "category":"Farming",
            "subcategory":"Dairy Farm",
            "type":"Manufacturing & Wholesale Goods"
        }
    ],
    "sg:phone":"+44 1423 771479",
    "sg:postcode":"HG3 3HE",
    "sg:province":"North Yorkshire",
    "sg:tags":[
        "farmer"
    ],
    "wof:name":"J D Crabtree & Son",
    "wof:placetype":"venue"
},
  "geometry": {"coordinates":[-1.672467,54.052914],"type":"Point"}
}