{
  "type": "Feature",
  "properties": {
    "addr:full":"441 Birmingham Road Sutton Coldfield West Midlands B72 1AX",
    "addr:housenumber":"441",
    "addr:postcode":"b72 1ax",
    "addr:street":"Birmingham Road",
    "iso:country":"GB",
    "sg:address":"441 Birmingham Road",
    "sg:city":"Sutton Coldfield",
    "sg:classifiers":[
        {
            "category":"Food & Beverages",
            "subcategory":"Supermarket",
            "type":"Retail Goods"
        },
        {
            "category":"Food & Beverages",
            "subcategory":"Groceries & Convenience Stores",
            "type":"Retail Goods"
        }
    ],
    "sg:phone":"+44 121 373 2359",
    "sg:postcode":"B72 1AX",
    "sg:province":"West Midlands",
    "wof:name":"MIDLANDS CO-OPERATIVE SOCIETY LTD",
    "wof:placetype":"venue"
},
  "geometry": {"coordinates":[-1.826818943,52.5576896667],"type":"Point"}
}