{
  "type": "Feature",
  "properties": {
    "addr:full":"71a Eastbourne Road, Willingdon Eastbourne East Sussex BN20 9NR",
    "addr:housenumber":"71a",
    "addr:postcode":"bn20 9nr",
    "addr:street":"Eastbourne Road",
    "iso:country":"GB",
    "sg:address":"71a Eastbourne Road, Willingdon",
    "sg:city":"Eastbourne",
    "sg:classifiers":[
        {
            "category":"Education",
            "subcategory":"Special Training",
            "type":"Public Place"
        }
    ],
    "sg:phone":"+44 1323 485183",
    "sg:postcode":"BN20 9NR",
    "sg:province":"East Sussex",
    "sg:tags":[
        "martial art",
        "instruction"
    ],
    "wof:name":"B B D",
    "wof:placetype":"venue"
},
  "geometry": {"coordinates":[0.248926,50.805943],"type":"Point"}
}