{
  "type": "Feature",
  "properties": {
    "addr:full":"Market Mall Aviemore Highland PH22 1PH",
    "addr:postcode":"ph22 1ph",
    "addr:street":"Aviemore",
    "iso:country":"GB",
    "sg:address":"Market Mall",
    "sg:city":"Aviemore",
    "sg:classifiers":[
        {
            "category":"Education",
            "subcategory":"Library",
            "type":"Public Place"
        },
        {
            "category":"Government",
            "subcategory":"Office",
            "type":"Public Place"
        }
    ],
    "sg:phone":"+44 1479 811113",
    "sg:postcode":"PH22 1PH",
    "sg:province":"Highland",
    "sg:tags":[
        "book",
        "local"
    ],
    "wof:name":"Aviemore Library",
    "wof:placetype":"venue"
},
  "geometry": {"coordinates":[-3.8287789822,57.1986694336],"type":"Point"}
}