{
  "type": "Feature",
  "properties": {
    "addr:full":"6 Westgate, Honley Huddersfield South Yorkshire HD9 6AA",
    "addr:housenumber":"6",
    "addr:postcode":"hd9 6aa",
    "addr:street":"Westgate Honley",
    "iso:country":"GB",
    "sg:address":"6 Westgate, Honley",
    "sg:city":"Huddersfield",
    "sg:classifiers":[
        {
            "category":"Restaurant",
            "type":"Food & Drink"
        }
    ],
    "sg:phone":"+44 1484 662066",
    "sg:postcode":"HD9 6AA",
    "sg:province":"South Yorkshire",
    "sg:tags":[
        "ethiopian",
        "-"
    ],
    "wof:name":"Mustard & Punch",
    "wof:placetype":"venue"
},
  "geometry": {"coordinates":[-1.792328,53.604034],"type":"Point"}
}