{
  "type": "Feature",
  "properties": {
    "addr:full":"15 Edith Road Oxford Oxfordshire OX1 4QB",
    "addr:housenumber":"15",
    "addr:postcode":"ox1 4qb",
    "addr:street":"Edith Road",
    "iso:country":"GB",
    "sg:address":"15 Edith Road",
    "sg:city":"Oxford",
    "sg:classifiers":[
        {
            "category":"Retail",
            "subcategory":"Auto Repair",
            "type":"Services"
        }
    ],
    "sg:phone":"+44 1865 245418",
    "sg:postcode":"OX1 4QB",
    "sg:province":"Oxfordshire",
    "sg:tags":[
        "modification",
        "garage",
        "related"
    ],
    "wof:name":"CHARLES D JAMES",
    "wof:placetype":"venue"
},
  "geometry": {"coordinates":[-1.2556190491,51.7413101196],"type":"Point"}
}