{
  "type": "Feature",
  "properties": {
    "iso:country":"GB",
    "sg:address":"The Estate Office, Melbury Sampford",
    "sg:city":"Dorchester",
    "sg:classifiers":[
        {
            "category":"Farming",
            "subcategory":"Dairy Farm",
            "type":"Manufacturing & Wholesale Goods"
        }
    ],
    "sg:phone":"+44 1935 83240",
    "sg:postcode":"DT2 0LF",
    "sg:province":"Dorset",
    "sg:tags":[
        "farmer"
    ],
    "wof:name":"EVERSHOT FARMS LTD",
    "wof:placetype":"venue"
},
  "geometry": {"coordinates":[-2.581394,50.795231],"type":"Point"}
}