{
  "type": "Feature",
  "properties": {
    "addr:full":"17 Mile Lane Exeter Devon EX4 9AA",
    "addr:housenumber":"17",
    "addr:postcode":"ex4 9aa",
    "addr:street":"Mile Lane",
    "iso:country":"GB",
    "sg:address":"17 Mile Lane",
    "sg:city":"Exeter",
    "sg:classifiers":[
        {
            "category":"Building & Trades",
            "subcategory":"Construction",
            "type":"Services"
        }
    ],
    "sg:phone":"+44 1392 435797",
    "sg:postcode":"EX4 9AA",
    "sg:province":"Devon",
    "sg:tags":[
        "joinery",
        "joiner",
        "carpenter",
        "carpentry"
    ],
    "wof:name":"Cliff Sutton",
    "wof:placetype":"venue"
},
  "geometry": {"coordinates":[-3.502849102,50.737827301],"type":"Point"}
}