{
  "type": "Feature",
  "properties": {
    "addr:full":"Clifford House, Milton St Fairford Gloucestershire GL7 4BW",
    "addr:postcode":"gl7 4bw",
    "addr:street":"Milton St",
    "iso:country":"GB",
    "sg:address":"Clifford House, Milton St",
    "sg:city":"Fairford",
    "sg:classifiers":[
        {
            "category":"Professional",
            "subcategory":"Computer Services",
            "type":"Services"
        }
    ],
    "sg:phone":"+44 1285 712223",
    "sg:postcode":"GL7 4BW",
    "sg:province":"Gloucestershire",
    "sg:tags":[
        "system",
        "software"
    ],
    "wof:name":"D Cockram",
    "wof:placetype":"venue"
},
  "geometry": {"coordinates":[-1.786151,51.707096],"type":"Point"}
}