{
  "type": "Feature",
  "properties": {
    "iso:country":"GB",
    "sg:address":"1-5 Hollow Way, Cowley",
    "sg:city":"Oxford",
    "sg:classifiers":[
        {
            "category":"Autos & Motor Vehicles",
            "subcategory":"Motorcycle Sales",
            "type":"Retail Goods"
        }
    ],
    "sg:phone":"+44 1865 777094",
    "sg:postcode":"OX4 2NA",
    "sg:province":"Oxfordshire",
    "sg:tags":[
        "scooter",
        "cycle"
    ],
    "wof:name":"Kings Two Wheel Centre",
    "wof:placetype":"venue"
},
  "geometry": {"coordinates":[-1.210475,51.734097],"type":"Point"}
}