{
  "type": "Feature",
  "properties": {
    "addr:full":"Unit 15a Elliott Rd Birmingham West Midlands B29 6LR",
    "addr:housenumber":"unit 15a",
    "addr:postcode":"b29 6lr",
    "addr:street":"Elliott Rd",
    "iso:country":"GB",
    "sg:address":"Unit 15a Elliott Rd",
    "sg:city":"Birmingham",
    "sg:classifiers":[
        {
            "category":"Communications",
            "type":"Services"
        }
    ],
    "sg:phone":"+44 121 415 5224",
    "sg:postcode":"B29 6LR",
    "sg:province":"West Midlands",
    "sg:tags":[
        "broadcasting"
    ],
    "wof:name":"Clockwork Television",
    "wof:placetype":"venue"
},
  "geometry": {"coordinates":[-1.9379650354,52.4405593872],"type":"Point"}
}