{
  "type": "Feature",
  "properties": {
    "iso:country":"GB",
    "sg:address":"155-159 Wellingborough Road",
    "sg:city":"Northampton",
    "sg:classifiers":[
        {
            "category":"Fast Food",
            "type":"Food & Drink"
        }
    ],
    "sg:phone":"+44 1604 234141",
    "sg:postcode":"NN1 4DX",
    "sg:province":"Northamptonshire",
    "sg:tags":[
        "delivery"
    ],
    "wof:name":"Bilash Tandoori",
    "wof:placetype":"venue"
},
  "geometry": {"coordinates":[-0.880391,52.241611],"type":"Point"}
}