{
  "type": "Feature",
  "properties": {
    "addr:full":"81 Lowdale Lane, Sleights Whitby North Yorkshire YO22 5AD",
    "addr:housenumber":"81",
    "addr:postcode":"yo22 5ad",
    "addr:street":"Lowdale Lane",
    "iso:country":"GB",
    "sg:address":"81 Lowdale Lane, Sleights",
    "sg:city":"Whitby",
    "sg:classifiers":[
        {
            "category":"Retail",
            "subcategory":"Driving School",
            "type":"Services"
        }
    ],
    "sg:phone":"+44 1947 810296",
    "sg:postcode":"YO22 5AD",
    "sg:province":"North Yorkshire",
    "wof:name":"Alan W Humble",
    "wof:placetype":"venue"
},
  "geometry": {"coordinates":[-0.6618840098,54.4607696533],"type":"Point"}
}