{
  "type": "Feature",
  "properties": {
    "addr:full":"8 Main St Turriff Aberdeenshire AB53 4AD",
    "addr:housenumber":"8",
    "addr:postcode":"ab53 4ad",
    "addr:street":"Main St",
    "iso:country":"GB",
    "sg:address":"8 Main St",
    "sg:city":"Turriff",
    "sg:classifiers":[
        {
            "category":"Shopping",
            "subcategory":"Thrift Store",
            "type":"Retail Goods"
        }
    ],
    "sg:phone":"+44 1888 568628",
    "sg:postcode":"AB53 4AD",
    "sg:province":"Aberdeenshire",
    "sg:tags":[
        "shop",
        "charity"
    ],
    "wof:name":"Sue Ryder Foundation",
    "wof:placetype":"venue"
},
  "geometry": {"coordinates":[-2.4605679512,57.5377197266],"type":"Point"}
}