{
  "type": "Feature",
  "properties": {
    "addr:full":"66 Hyde Way Hayes Greater London UB3 4PB",
    "addr:housenumber":"66",
    "addr:postcode":"ub3 4pb",
    "addr:street":"Hyde Way",
    "iso:country":"GB",
    "sg:address":"66 Hyde Way",
    "sg:city":"Hayes",
    "sg:classifiers":[
        {
            "category":"Banks & Credit Unions",
            "subcategory":"Atm",
            "type":"Services"
        }
    ],
    "sg:postcode":"UB3 4PB",
    "sg:province":"Greater London",
    "sg:tags":[
        "concert",
        "organiser"
    ],
    "wof:name":"B & B Concert Services",
    "wof:placetype":"venue"
},
  "geometry": {"coordinates":[-0.420055002,51.4988899231],"type":"Point"}
}