{
  "type": "Feature",
  "properties": {
    "addr:full":"94 London Rd Sevenoaks Kent TN13 1BA",
    "addr:housenumber":"94",
    "addr:postcode":"tn13 1ba",
    "addr:street":"London Rd",
    "iso:country":"GB",
    "sg:address":"94 London Rd",
    "sg:city":"Sevenoaks",
    "sg:classifiers":[
        {
            "category":"Autos & Motor Vehicles",
            "subcategory":"Automobile Sales",
            "type":"Retail Goods"
        }
    ],
    "sg:phone":"+44 1732 779300",
    "sg:postcode":"TN13 1BA",
    "sg:province":"Kent",
    "sg:tags":[
        "car"
    ],
    "wof:name":"Springtown Ltd",
    "wof:placetype":"venue"
},
  "geometry": {"coordinates":[0.189297,51.273624],"type":"Point"}
}