{
  "type": "Feature",
  "properties": {
    "iso:country":"GB",
    "sg:address":"19 Evington Rd",
    "sg:city":"Leicester",
    "sg:classifiers":[
        {
            "category":"Health Services",
            "subcategory":"Dentist",
            "type":"Services"
        }
    ],
    "sg:phone":"+44 116 254 4391",
    "sg:postcode":"LE2 1QG",
    "sg:province":"Leicestershire",
    "wof:name":"R A Ralston",
    "wof:placetype":"venue"
},
  "geometry": {"coordinates":[-1.117532,52.626663],"type":"Point"}
}