{
  "type": "Feature",
  "properties": {
    "addr:full":"High Street Edgware Greater London HA8 5AE",
    "addr:postcode":"ha8 5ae",
    "addr:street":"High Street",
    "iso:country":"GB",
    "sg:address":"High Street",
    "sg:city":"Edgware",
    "sg:classifiers":[
        {
            "category":"Autos & Motor Vehicles",
            "subcategory":"Automobile Sales",
            "type":"Retail Goods"
        }
    ],
    "sg:phone":"+44 20 8731 1000",
    "sg:postcode":"HA8 5AE",
    "sg:province":"Greater London",
    "sg:tags":[
        "car"
    ],
    "wof:name":"Warwick Wright - Edgware",
    "wof:placetype":"venue"
},
  "geometry": {"coordinates":[-0.2765440047,51.6083831787],"type":"Point"}
}