{
  "type": "Feature",
  "properties": {
    "addr:full":"98 Queens Avenue Watford Hertfordshire WD18 7NS",
    "addr:housenumber":"98",
    "addr:postcode":"wd18 7ns",
    "addr:street":"Queens Avenue",
    "iso:country":"GB",
    "sg:address":"98 Queens Avenue",
    "sg:city":"Watford",
    "sg:classifiers":[
        {
            "category":"Government",
            "subcategory":"Post Office",
            "type":"Public Place"
        }
    ],
    "sg:phone":"+44 1923 242550",
    "sg:postcode":"WD18 7NS",
    "sg:province":"Hertfordshire",
    "wof:name":"A Bandali",
    "wof:placetype":"venue"
},
  "geometry": {"coordinates":[-0.4125829935,51.6518211365],"type":"Point"}
}