{
  "type": "Feature",
  "properties": {
    "iso:country":"GB",
    "sg:address":"84 Darwen Street",
    "sg:city":"Blackburn",
    "sg:classifiers":[
        {
            "category":"Home & Garden",
            "subcategory":"Home Furnishings",
            "type":"Retail Goods"
        }
    ],
    "sg:phone":"+44 1254 665426",
    "sg:postcode":"BB2 2AJ",
    "sg:province":"Lancashire",
    "sg:tags":[
        "beds",
        "bedding",
        "blanket"
    ],
    "wof:name":"The Bed Centre",
    "wof:placetype":"venue"
},
  "geometry": {"coordinates":[-2.4825921059,53.7448692322],"type":"Point"}
}