{
  "type": "Feature",
  "properties": {
    "iso:country":"GB",
    "sg:address":"P O Box 3169",
    "sg:city":"Buckingham",
    "sg:classifiers":[
        {
            "category":"Manufacturing",
            "subcategory":"Building Materials",
            "type":"Manufacturing & Wholesale Goods"
        }
    ],
    "sg:phone":"+44 1280 823408",
    "sg:postcode":"MK18 7ZT",
    "sg:province":"Buckinghamshire",
    "sg:tags":[
        "mnfr",
        "maker",
        "cabinet"
    ],
    "wof:name":"Furnisher Restorer",
    "wof:placetype":"venue"
},
  "geometry": {"coordinates":[-0.9689689875,51.9943199158],"type":"Point"}
}