{
  "type": "Feature",
  "properties": {
    "addr:full":"1-3 Christleton Road Chester Cheshire CH3 5UF",
    "addr:housenumber":"1-3",
    "addr:postcode":"ch3 5uf",
    "addr:street":"Christleton Road",
    "iso:country":"GB",
    "sg:address":"1-3 Christleton Road",
    "sg:city":"Chester",
    "sg:classifiers":[
        {
            "category":"Shopping",
            "subcategory":"Discount & Variety Stores",
            "type":"Retail Goods"
        }
    ],
    "sg:postcode":"CH3 5UF",
    "sg:province":"Cheshire",
    "sg:tags":[
        "shop",
        "model"
    ],
    "wof:name":"Chester Model Centre",
    "wof:placetype":"venue"
},
  "geometry": {"coordinates":[-2.871329,53.19191],"type":"Point"}
}