{
  "type": "Feature",
  "properties": {
    "addr:full":"241-243 Seaside Eastbourne East Sussex BN22 7NT",
    "addr:housenumber":"241-243",
    "addr:postcode":"bn22 7nt",
    "addr:street":"Seaside",
    "iso:country":"GB",
    "sg:address":"241-243 Seaside",
    "sg:city":"Eastbourne",
    "sg:classifiers":[
        {
            "category":"Manufacturing",
            "subcategory":"Retail Goods",
            "type":"Manufacturing & Wholesale Goods"
        }
    ],
    "sg:postcode":"BN22 7NT",
    "sg:province":"East Sussex",
    "sg:tags":[
        "chandler"
    ],
    "wof:name":"Smith & Gibbs",
    "wof:placetype":"venue"
},
  "geometry": {"coordinates":[0.2993679941,50.7782592773],"type":"Point"}
}