{
  "type": "Feature",
  "properties": {
    "addr:full":"109 Humberstone Road Grimsby Lincolnshire DN32 8DR",
    "addr:housenumber":"109",
    "addr:postcode":"dn32 8dr",
    "addr:street":"Humberstone Road",
    "iso:country":"GB",
    "sg:address":"109 Humberstone Road",
    "sg:city":"Grimsby",
    "sg:classifiers":[
        {
            "category":"Food & Beverages",
            "subcategory":"Meat & Fish",
            "type":"Retail Goods"
        }
    ],
    "sg:phone":"+44 1472 354307",
    "sg:postcode":"DN32 8DR",
    "sg:province":"Lincolnshire",
    "sg:tags":[
        "chip"
    ],
    "wof:name":"Marklews Fisheries",
    "wof:placetype":"venue"
},
  "geometry": {"coordinates":[-0.0634460002,53.5628585815],"type":"Point"}
}