{
  "type": "Feature",
  "properties": {
    "addr:full":"Little Ashtree Farm, Steeple Road, Mayland Chelmsford Essex CM3 6EG",
    "addr:postcode":"cm3 6eg",
    "addr:street":"Steeple Road",
    "iso:country":"GB",
    "sg:address":"Little Ashtree Farm, Steeple Road, Mayland",
    "sg:city":"Chelmsford",
    "sg:classifiers":[
        {
            "category":"Professional",
            "type":"Services"
        },
        {
            "category":"Banks & Credit Unions",
            "subcategory":"Investment Brokerage",
            "type":"Services"
        },
        {
            "category":"Fast Food",
            "type":"Food & Drink"
        }
    ],
    "sg:phone":"+44 1621 741328",
    "sg:postcode":"CM3 6EG",
    "sg:province":"Essex",
    "sg:tags":[
        "away",
        "contractor",
        "take",
        "caterer",
        "meal",
        "outlet"
    ],
    "wof:name":"J F McLaren",
    "wof:placetype":"venue"
},
  "geometry": {"coordinates":[0.77623,51.680618],"type":"Point"}
}