{
  "type": "Feature",
  "properties": {
    "addr:full":"53 Scotch Orchard Lichfield Staffordshire WS13 6DE",
    "addr:housenumber":"53",
    "addr:postcode":"ws13 6de",
    "addr:street":"Scotch Orchard",
    "iso:country":"GB",
    "sg:address":"53 Scotch Orchard",
    "sg:city":"Lichfield",
    "sg:classifiers":[
        {
            "category":"Farming",
            "subcategory":"Nursery",
            "type":"Manufacturing & Wholesale Goods"
        }
    ],
    "sg:phone":"+44 1543 416627",
    "sg:postcode":"WS13 6DE",
    "sg:province":"Staffordshire",
    "sg:tags":[
        "creche"
    ],
    "wof:name":"Lichfield Day Nursery",
    "wof:placetype":"venue"
},
  "geometry": {"coordinates":[-1.811386,52.688946],"type":"Point"}
}