{
  "type": "Feature",
  "properties": {
    "addr:full":"Rectory, Wilbraham Rd Manchester Greater Manchester M14 6JZ",
    "addr:postcode":"m14 6jz",
    "addr:street":"Wilbraham Rd",
    "iso:country":"GB",
    "sg:address":"Rectory, Wilbraham Rd",
    "sg:city":"Manchester",
    "sg:classifiers":[
        {
            "category":"Place Of Worship",
            "type":"Public Place"
        }
    ],
    "sg:phone":"+44 161 224 1310",
    "sg:postcode":"M14 6JZ",
    "sg:province":"Greater Manchester",
    "wof:name":"Holy Innocents C Of E Church",
    "wof:placetype":"venue"
},
  "geometry": {"coordinates":[-2.226129055,53.4432411194],"type":"Point"}
}