{
  "type": "Feature",
  "properties": {
    "iso:country":"GB",
    "sg:address":"24 St Cenydd Road, Portmead",
    "sg:city":"Swansea",
    "sg:classifiers":[
        {
            "category":"Retail",
            "subcategory":"Storage",
            "type":"Services"
        }
    ],
    "sg:postcode":"SA5 5JY",
    "sg:province":"Swansea",
    "sg:tags":[
        "household",
        "removal"
    ],
    "wof:name":"Ravenhill Light Haulage",
    "wof:placetype":"venue"
},
  "geometry": {"coordinates":[-3.971125,51.651146],"type":"Point"}
}