{
  "type": "Feature",
  "properties": {
    "iso:country":"GB",
    "sg:address":"2 Clapsgate Lane",
    "sg:city":"London",
    "sg:classifiers":[
        {
            "category":"Sports & Exercise",
            "subcategory":"Stables",
            "type":"Entertainment"
        },
        {
            "category":"Personal",
            "subcategory":"Adult",
            "type":"Services"
        }
    ],
    "sg:phone":"+44 20 7511 3917",
    "sg:postcode":"E6 6JF",
    "sg:province":"Greater London",
    "sg:tags":[
        "education",
        "equestrian"
    ],
    "wof:name":"Newham Riding School Ltd.",
    "wof:placetype":"venue"
},
  "geometry": {"coordinates":[0.070188,51.521366],"type":"Point"}
}