{
  "type": "Feature",
  "properties": {
    "addr:full":"Room 21 Avenue House, East End Road, Finchley London Greater London N3 3QE",
    "addr:housenumber":"21",
    "addr:postcode":"n3 3qe",
    "addr:street":"Avenue House East End Road",
    "iso:country":"GB",
    "sg:address":"Room 21 Avenue House, East End Road, Finchley",
    "sg:city":"London",
    "sg:classifiers":[
        {
            "category":"Organizations",
            "subcategory":"Non-profit Organization",
            "type":"Services"
        }
    ],
    "sg:phone":"+44 20 8371 9678",
    "sg:postcode":"N3 3QE",
    "sg:province":"Greater London",
    "sg:tags":[
        "organisation",
        "voluntary",
        "charity"
    ],
    "wof:name":"Barnet Voice for Mental Health",
    "wof:placetype":"venue"
},
  "geometry": {"coordinates":[-0.195203,51.596676],"type":"Point"}
}