{
  "type": "Feature",
  "properties": {
    "addr:full":"London Rd Devizes Wiltshire SN10 2DL",
    "addr:postcode":"sn10 2dl",
    "addr:street":"London Rd",
    "iso:country":"GB",
    "sg:address":"London Rd",
    "sg:city":"Devizes",
    "sg:classifiers":[
        {
            "category":"Health Services",
            "subcategory":"Nursing And Care Facility",
            "type":"Services"
        }
    ],
    "sg:phone":"+44 1380 721489",
    "sg:postcode":"SN10 2DL",
    "sg:province":"Wiltshire",
    "sg:tags":[
        "home"
    ],
    "wof:name":"Mottisfont Rest Home",
    "wof:placetype":"venue"
},
  "geometry": {"coordinates":[-1.975677,51.361122],"type":"Point"}
}