{
  "type": "Feature",
  "properties": {
    "addr:full":"64 High St Ipswich Suffolk IP7 5EF",
    "addr:housenumber":"64",
    "addr:postcode":"ip7 5ef",
    "addr:street":"High St",
    "iso:country":"GB",
    "sg:address":"64 High St",
    "sg:city":"Ipswich",
    "sg:classifiers":[
        {
            "category":"Health Services",
            "subcategory":"Dentist",
            "type":"Services"
        }
    ],
    "sg:phone":"+44 1473 823003",
    "sg:postcode":"IP7 5EF",
    "sg:province":"Suffolk",
    "wof:name":"R Newton",
    "wof:placetype":"venue"
},
  "geometry": {"coordinates":[0.9539549947,52.043964386],"type":"Point"}
}