{
  "type": "Feature",
  "properties": {
    "addr:full":"14 The Walk Norwich Norfolk NR2 1NA",
    "addr:housenumber":"14",
    "addr:postcode":"nr2 1na",
    "addr:street":"The Walk Norwich Norfolk",
    "iso:country":"GB",
    "sg:address":"14 The Walk",
    "sg:city":"Norwich",
    "sg:classifiers":[
        {
            "category":"Shopping",
            "subcategory":"Comic Books",
            "type":"Retail Goods"
        }
    ],
    "sg:phone":"+44 16033665038",
    "sg:postcode":"NR2 1NA",
    "sg:province":"Norfolk",
    "sg:tags":[
        "jeweller"
    ],
    "wof:name":"H Samuel Ltd.",
    "wof:placetype":"venue"
},
  "geometry": {"coordinates":[1.2901309729,52.6273040771],"type":"Point"}
}