{
  "type": "Feature",
  "properties": {
    "addr:full":"Hillside Farm, Owmby Barnetby Lincolnshire DN38 6AY",
    "addr:housenumber":"owmby",
    "addr:postcode":"dn38 6ay",
    "iso:country":"GB",
    "sg:address":"Hillside Farm, Owmby",
    "sg:city":"Barnetby",
    "sg:classifiers":[
        {
            "category":"Building & Trades",
            "subcategory":"Equipment Rental",
            "type":"Services"
        },
        {
            "category":"Organizations",
            "subcategory":"Membership Organization",
            "type":"Services"
        }
    ],
    "sg:phone":"+44 1652 628217",
    "sg:postcode":"DN38 6AY",
    "sg:province":"Lincolnshire",
    "sg:tags":[
        "plant",
        "machinery"
    ],
    "wof:name":"D L Lyle & Co.",
    "wof:placetype":"venue"
},
  "geometry": {"coordinates":[-0.404298991,53.5746192932],"type":"Point"}
}