{
  "type": "Feature",
  "properties": {
    "iso:country":"GB",
    "sg:address":"92 High Street",
    "sg:city":"Rickmansworth",
    "sg:classifiers":[
        {
            "category":"Restaurant",
            "type":"Food & Drink"
        },
        {
            "category":"Bars & Pubs",
            "subcategory":"Wine Bar",
            "type":"Food & Drink"
        }
    ],
    "sg:phone":"+44 1923 779492",
    "sg:postcode":"WD3 1AQ",
    "sg:province":"Hertfordshire",
    "sg:tags":[
        "italian"
    ],
    "wof:name":"Remo's Piazza",
    "wof:placetype":"venue"
},
  "geometry": {"coordinates":[-0.4708000124,51.639213562],"type":"Point"}
}