{
  "type": "Feature",
  "properties": {
    "iso:country":"GB",
    "sg:address":"3 Peartree Cotts, Maltby",
    "sg:city":"Middlesbrough",
    "sg:classifiers":[
        {
            "category":"Retail",
            "subcategory":"Driving School",
            "type":"Services"
        }
    ],
    "sg:postcode":"TS8 0BH",
    "sg:province":"North Yorkshire",
    "wof:name":"Millennium Driving Centre",
    "wof:placetype":"venue"
},
  "geometry": {"coordinates":[-1.2772899866,54.5145797729],"type":"Point"}
}