{
  "type": "Feature",
  "properties": {
    "addr:full":"12 Elm Drive, Northop Hall Mold Denbighshire CH7 6JJ",
    "addr:housenumber":"12",
    "addr:postcode":"ch7 6jj",
    "addr:street":"Elm Drive",
    "iso:country":"GB",
    "sg:address":"12 Elm Drive, Northop Hall",
    "sg:city":"Mold",
    "sg:classifiers":[
        {
            "category":"Insurance",
            "subcategory":"Hazard Insurance",
            "type":"Services"
        }
    ],
    "sg:phone":"+44 1244 821820",
    "sg:postcode":"CH7 6JJ",
    "sg:province":"Denbighshire",
    "sg:tags":[
        "fire",
        "water",
        "damage"
    ],
    "wof:name":"Rainbow International",
    "wof:placetype":"venue"
},
  "geometry": {"coordinates":[-3.097055,53.201401],"type":"Point"}
}