{
  "type": "Feature",
  "properties": {
    "iso:country":"GB",
    "sg:address":"Unit 86, Whistleberry Rd",
    "sg:city":"Hamilton",
    "sg:classifiers":[
        {
            "category":"Wholesale",
            "subcategory":"Meat",
            "type":"Manufacturing & Wholesale Goods"
        }
    ],
    "sg:phone":"+44 1698 712400",
    "sg:postcode":"ML3 0EJ",
    "sg:province":"South Lanarkshire",
    "sg:tags":[
        "-"
    ],
    "wof:name":"Tannochside Quality Meats",
    "wof:placetype":"venue"
},
  "geometry": {"coordinates":[-4.069827,55.792515],"type":"Point"}
}