{
  "type": "Feature",
  "properties": {
    "addr:full":"4 Villa Street, Draycott Derby Derbyshire DE72 3PZ",
    "addr:housenumber":"4",
    "addr:postcode":"de72 3pz",
    "addr:street":"Villa Street",
    "iso:country":"GB",
    "sg:address":"4 Villa Street, Draycott",
    "sg:city":"Derby",
    "sg:classifiers":[
        {
            "category":"Retail",
            "subcategory":"Auto Repair",
            "type":"Services"
        }
    ],
    "sg:phone":"+44 1332 874434",
    "sg:postcode":"DE72 3PZ",
    "sg:province":"Derbyshire",
    "sg:tags":[
        "modification",
        "garage",
        "related"
    ],
    "wof:name":"Villa Street Motors",
    "wof:placetype":"venue"
},
  "geometry": {"coordinates":[-1.3382760286,52.8962173462],"type":"Point"}
}