{
  "type": "Feature",
  "properties": {
    "addr:full":"15 Market Place Wantage Berkshire OX12 8BQ",
    "addr:housenumber":"15",
    "addr:postcode":"ox12 8bq",
    "addr:street":"Market Place",
    "iso:country":"GB",
    "sg:address":"15 Market Place",
    "sg:city":"Wantage",
    "sg:classifiers":[
        {
            "category":"Professional",
            "subcategory":"Employment Agencies",
            "type":"Services"
        }
    ],
    "sg:phone":"+44 1235 770020",
    "sg:postcode":"OX12 8BQ",
    "sg:province":"Berkshire",
    "sg:tags":[
        "consultant"
    ],
    "wof:name":"It Training Company",
    "wof:placetype":"venue"
},
  "geometry": {"coordinates":[-1.4276729822,51.588634491],"type":"Point"}
}