{
  "type": "Feature",
  "properties": {
    "iso:country":"GB",
    "sg:address":"193 Hampton Lane",
    "sg:city":"Southampton",
    "sg:classifiers":[
        {
            "category":"Shopping",
            "subcategory":"Clothing, Apparel, & Fashions",
            "type":"Retail Goods"
        }
    ],
    "sg:phone":"+44 23 8089 0000",
    "sg:postcode":"SO45 1XA",
    "sg:province":"Hampshire",
    "sg:tags":[
        "shop"
    ],
    "wof:name":"Bubbles",
    "wof:placetype":"venue"
},
  "geometry": {"coordinates":[-1.3732479811,50.8188362122],"type":"Point"}
}