{
  "type": "Feature",
  "properties": {
    "iso:country":"GB",
    "sg:address":"Stroud Rd",
    "sg:city":"Gloucester",
    "sg:classifiers":[
        {
            "category":"Autos & Motor Vehicles",
            "subcategory":"Fuel & Gas Station",
            "type":"Retail Goods"
        }
    ],
    "sg:postcode":"GL4 0UQ",
    "sg:province":"Gloucestershire",
    "sg:tags":[
        "petrol",
        "filling"
    ],
    "wof:name":"Base,J A,",
    "wof:placetype":"venue"
},
  "geometry": {"coordinates":[-2.242466,51.839684],"type":"Point"}
}