{
  "type": "Feature",
  "properties": {
    "iso:country":"GB",
    "sg:address":"7 Poole La",
    "sg:city":"Caernarfon",
    "sg:classifiers":[
        {
            "category":"Communications",
            "type":"Services"
        }
    ],
    "sg:postcode":"LL55 2AL",
    "sg:province":"Gwynedd",
    "sg:tags":[
        "tv",
        "video",
        "radio"
    ],
    "wof:name":"Harmony in-Car Entertainments",
    "wof:placetype":"venue"
},
  "geometry": {"coordinates":[-4.2737569809,53.1395950317],"type":"Point"}
}