{
  "type": "Feature",
  "properties": {
    "iso:country":"GB",
    "sg:address":"Gas Works Rd, Aberaman",
    "sg:city":"Aberdare",
    "sg:classifiers":[
        {
            "category":"Social Services",
            "type":"Services"
        }
    ],
    "sg:phone":"+44 1685 879896",
    "sg:postcode":"CF44 6RS",
    "sg:province":"Neath Port Talbot",
    "wof:name":"Community Support Team",
    "wof:placetype":"venue"
},
  "geometry": {"coordinates":[-3.430896,51.699989],"type":"Point"}
}