{
  "type": "Feature",
  "properties": {
    "addr:full":"22 Grn Avenue Northwich Cheshire CW9 8HZ",
    "addr:housenumber":"22",
    "addr:postcode":"cw9 8hz",
    "addr:street":"Grn Avenue",
    "iso:country":"GB",
    "sg:address":"22 Grn Avenue",
    "sg:city":"Northwich",
    "sg:classifiers":[
        {
            "category":"Building & Trades",
            "subcategory":"Construction",
            "type":"Services"
        }
    ],
    "sg:postcode":"CW9 8HZ",
    "sg:province":"Cheshire",
    "sg:tags":[
        "builder"
    ],
    "wof:name":"John Pawson Builder & Property Repairer",
    "wof:placetype":"venue"
},
  "geometry": {"coordinates":[-2.5105938911,53.2344894409],"type":"Point"}
}