{
  "type": "Feature",
  "properties": {
    "iso:country":"GB",
    "sg:address":"Leyden Road",
    "sg:city":"Stevenage",
    "sg:classifiers":[
        {
            "category":"Freight",
            "type":"Transportation"
        }
    ],
    "sg:phone":"+44 1438 368092",
    "sg:postcode":"SG1 2BW",
    "sg:province":"Hertfordshire",
    "sg:tags":[
        "haulage",
        "road"
    ],
    "wof:name":"Gifford Haulage",
    "wof:placetype":"venue"
},
  "geometry": {"coordinates":[-0.2032289952,51.8917808533],"type":"Point"}
}