{
  "type": "Feature",
  "properties": {
    "addr:full":"47 Easter Road Edinburgh City of Edinburgh EH7 5PL",
    "addr:housenumber":"47",
    "addr:postcode":"eh7 5pl",
    "addr:street":"Easter Road",
    "iso:country":"GB",
    "sg:address":"47 Easter Road",
    "sg:city":"Edinburgh",
    "sg:classifiers":[
        {
            "category":"Health Services",
            "subcategory":"Dentist",
            "type":"Services"
        }
    ],
    "sg:phone":"+44 131 661 1404",
    "sg:postcode":"EH7 5PL",
    "sg:province":"City of Edinburgh",
    "wof:name":"Dental Practice",
    "wof:placetype":"venue"
},
  "geometry": {"coordinates":[-3.1719410419,55.9593391418],"type":"Point"}
}