{
  "type": "Feature",
  "properties": {
    "addr:full":"3 Southampton Street Faringdon Oxfordshire SN7 7AZ",
    "addr:housenumber":"3",
    "addr:postcode":"sn7 7az",
    "addr:street":"Southampton Street",
    "iso:country":"GB",
    "sg:address":"3 Southampton Street",
    "sg:city":"Faringdon",
    "sg:classifiers":[
        {
            "category":"Building & Trades",
            "subcategory":"Plumbing",
            "type":"Services"
        }
    ],
    "sg:postcode":"SN7 7AZ",
    "sg:province":"Oxfordshire",
    "sg:tags":[
        "heating"
    ],
    "wof:name":"R F Long",
    "wof:placetype":"venue"
},
  "geometry": {"coordinates":[-1.5833660364,51.6572303772],"type":"Point"}
}