{
  "type": "Feature",
  "properties": {
    "addr:full":"46 Waltons Avenue Southampton Hampshire SO45 2LU",
    "addr:housenumber":"46",
    "addr:postcode":"so45 2lu",
    "addr:street":"Waltons Avenue",
    "iso:country":"GB",
    "sg:address":"46 Waltons Avenue",
    "sg:city":"Southampton",
    "sg:classifiers":[
        {
            "category":"Military Area",
            "subcategory":"Air Force Base",
            "type":"Public Place"
        }
    ],
    "sg:postcode":"SO45 2LU",
    "sg:province":"Hampshire",
    "sg:tags":[
        "taxi",
        "hire",
        "private"
    ],
    "wof:name":"Cab Mobility",
    "wof:placetype":"venue"
},
  "geometry": {"coordinates":[-1.3841450214,50.8305358887],"type":"Point"}
}