{
  "type": "Feature",
  "properties": {
    "addr:full":"9a Leyton Road Harpenden Hertfordshire AL5 2HU",
    "addr:housenumber":"9a",
    "addr:postcode":"al5 2hu",
    "addr:street":"Leyton Road",
    "iso:country":"GB",
    "sg:address":"9a Leyton Road",
    "sg:city":"Harpenden",
    "sg:classifiers":[
        {
            "category":"Health Services",
            "subcategory":"Doctor",
            "type":"Services"
        },
        {
            "category":"Health Services",
            "subcategory":"Dentist",
            "type":"Services"
        }
    ],
    "sg:phone":"+44 1582 764931",
    "sg:postcode":"AL5 2HU",
    "sg:province":"Hertfordshire",
    "wof:name":"Tant Russell",
    "wof:placetype":"venue"
},
  "geometry": {"coordinates":[-0.3561049998,51.8144989014],"type":"Point"}
}