{
  "type": "Feature",
  "properties": {
    "addr:full":"Unit C 1 Muirhall Road Larbert Falkirk FK5 4RF",
    "addr:housenumber":"unit c 1",
    "addr:postcode":"fk5 4rf",
    "addr:street":"Muirhall Road",
    "iso:country":"GB",
    "sg:address":"Unit C 1 Muirhall Road",
    "sg:city":"Larbert",
    "sg:classifiers":[
        {
            "category":"Manufacturing",
            "subcategory":"Glass & Minerals",
            "type":"Manufacturing & Wholesale Goods"
        }
    ],
    "sg:phone":"+44 1324 557463",
    "sg:postcode":"FK5 4RF",
    "sg:province":"Falkirk",
    "sg:tags":[
        "fibre",
        "moulding"
    ],
    "wof:name":"G R P Larbert",
    "wof:placetype":"venue"
},
  "geometry": {"coordinates":[-3.824369,56.024384],"type":"Point"}
}