{
  "type": "Feature",
  "properties": {
    "addr:full":"Distribution Office, Whitworth Road Crawley West Sussex RH11 7SS",
    "addr:postcode":"rh11 7ss",
    "addr:street":"Whitworth Road",
    "iso:country":"GB",
    "sg:address":"Distribution Office, Whitworth Road",
    "sg:city":"Crawley",
    "sg:classifiers":[
        {
            "category":"Manufacturing",
            "subcategory":"Food",
            "type":"Manufacturing & Wholesale Goods"
        }
    ],
    "sg:phone":"+44 1293 552986",
    "sg:postcode":"RH11 7SS",
    "sg:province":"West Sussex",
    "sg:tags":[
        "mnfr",
        "drink",
        "soft"
    ],
    "wof:name":"Britvic Soft Drinks Ltd.",
    "wof:placetype":"venue"
},
  "geometry": {"coordinates":[-0.19073,51.135818],"type":"Point"}
}