{
  "type": "Feature",
  "properties": {
    "addr:full":"Griffiths House, 408 The Quadrant, Birchwood Park Warrington Cheshire WA3 6GH",
    "addr:housenumber":"408",
    "addr:postcode":"wa3 6gh",
    "addr:street":"The Quadrant;Park",
    "iso:country":"GB",
    "sg:address":"Griffiths House, 408 The Quadrant, Birchwood Park",
    "sg:city":"Warrington",
    "sg:classifiers":[
        {
            "category":"Professional",
            "subcategory":"Engineering",
            "type":"Services"
        }
    ],
    "sg:phone":"+44 1925 639979",
    "sg:postcode":"WA3 6GH",
    "sg:province":"Cheshire",
    "sg:tags":[
        "underpinning",
        "foundation",
        "engineer"
    ],
    "wof:name":"Branlow Ltd.",
    "wof:placetype":"venue"
},
  "geometry": {"coordinates":[-2.523624,53.428558],"type":"Point"}
}