{
  "type": "Feature",
  "properties": {
    "iso:country":"GB",
    "sg:address":"Westgate, 15 Aston Road",
    "sg:city":"Shrewsbury",
    "sg:classifiers":[
        {
            "category":"Building & Trades",
            "subcategory":"Landscaping Services",
            "type":"Services"
        }
    ],
    "sg:phone":"+44 1939 236677",
    "sg:postcode":"SY4 5AZ",
    "sg:province":"Shropshire",
    "sg:tags":[
        "irrigation",
        "system"
    ],
    "wof:name":"Turf Irrigation Services (Shrewsbury) Ltd.",
    "wof:placetype":"venue"
},
  "geometry": {"coordinates":[-2.71765,52.855808],"type":"Point"}
}