{
  "type": "Feature",
  "properties": {
    "iso:country":"GB",
    "sg:address":"The Silk Mill, Colne Valley Road",
    "sg:city":"Haverhill",
    "sg:classifiers":[
        {
            "category":"Shopping",
            "subcategory":"Crafts & Fabrics",
            "type":"Retail Goods"
        },
        {
            "category":"Manufacturing",
            "subcategory":"Retail Goods",
            "type":"Manufacturing & Wholesale Goods"
        }
    ],
    "sg:phone":"+44 1440 714800",
    "sg:postcode":"CB9 8DT",
    "sg:province":"Essex",
    "sg:tags":[
        "brush",
        "manufacturer"
    ],
    "wof:name":"Wisdom Toothbrushes Ltd",
    "wof:placetype":"venue"
},
  "geometry": {"coordinates":[0.441825,52.079205],"type":"Point"}
}