{
  "type": "Feature",
  "properties": {
    "iso:country":"GB",
    "sg:address":"13 Commercial St, Alyth",
    "sg:city":"Blairgowrie",
    "sg:classifiers":[
        {
            "category":"Shopping",
            "type":"Retail Goods"
        }
    ],
    "sg:phone":"+44 1828 632519",
    "sg:postcode":"PH11 8AF",
    "sg:province":"Angus",
    "sg:tags":[
        "household",
        "store"
    ],
    "wof:name":"M & A Newbigging",
    "wof:placetype":"venue"
},
  "geometry": {"coordinates":[-3.230432,56.623672],"type":"Point"}
}