{
  "type": "Feature",
  "properties": {
    "iso:country":"GB",
    "sg:address":"17 Linnhe Avenue, Bishopbriggs",
    "sg:city":"Glasgow",
    "sg:classifiers":[
        {
            "category":"Building & Trades",
            "subcategory":"Construction",
            "type":"Services"
        }
    ],
    "sg:phone":"+44 141 772 2669",
    "sg:postcode":"G64 1HQ",
    "sg:province":"East Dunbartonshire",
    "sg:tags":[
        "contractor"
    ],
    "wof:name":"Cranna Construction Ltd.",
    "wof:placetype":"venue"
},
  "geometry": {"coordinates":[-4.2098321915,55.9068183899],"type":"Point"}
}