{
  "type": "Feature",
  "properties": {
    "addr:full":"22 Farndale Road Weston Super Mare Somerset BS22 8QA",
    "addr:housenumber":"22",
    "addr:postcode":"bs22 8qa",
    "addr:street":"Farndale Road Weston",
    "iso:country":"GB",
    "sg:address":"22 Farndale Road",
    "sg:city":"Weston Super Mare",
    "sg:classifiers":[
        {
            "category":"Building & Trades",
            "subcategory":"Cleaning & Sanitation",
            "type":"Services"
        }
    ],
    "sg:phone":"+44 1934 622444",
    "sg:postcode":"BS22 8QA",
    "sg:province":"Somerset",
    "sg:tags":[
        "commercial"
    ],
    "wof:name":"D A E Coles & Son",
    "wof:placetype":"venue"
},
  "geometry": {"coordinates":[-2.9387600422,51.3500785828],"type":"Point"}
}