{
  "type": "Feature",
  "properties": {
    "iso:country":"GB",
    "sg:address":"Whitemoss, Hillcommon",
    "sg:city":"Taunton",
    "sg:classifiers":[
        {
            "category":"Utilities",
            "type":"Services"
        }
    ],
    "sg:phone":"+44 1823 401207",
    "sg:postcode":"TA4 1DU",
    "sg:province":"Devon",
    "sg:tags":[
        "internet"
    ],
    "wof:name":"Page Services",
    "wof:placetype":"venue"
},
  "geometry": {"coordinates":[-3.214454,51.027908],"type":"Point"}
}