{
  "type": "Feature",
  "properties": {
    "addr:full":"424 Soundwell Road Bristol City of Bristol BS15 1JS",
    "addr:housenumber":"424",
    "addr:postcode":"bs15 1js",
    "addr:street":"Soundwell Road",
    "iso:country":"GB",
    "sg:address":"424 Soundwell Road",
    "sg:city":"Bristol",
    "sg:classifiers":[
        {
            "category":"Home & Garden",
            "subcategory":"Household Appliances",
            "type":"Retail Goods"
        }
    ],
    "sg:phone":"+44 117 960 2225",
    "sg:postcode":"BS15 1JS",
    "sg:province":"City of Bristol",
    "sg:tags":[
        "domestic",
        "oven",
        "microwave"
    ],
    "wof:name":"Microsafe",
    "wof:placetype":"venue"
},
  "geometry": {"coordinates":[-2.5132989883,51.4655990601],"type":"Point"}
}