{
  "type": "Feature",
  "properties": {
    "addr:full":"Unit 38, Century St, Darnall Sheffield South Yorkshire S9 5DX",
    "addr:housenumber":"unit 38",
    "addr:postcode":"s9 5dx",
    "addr:street":"Century St",
    "iso:country":"GB",
    "sg:address":"Unit 38, Century St, Darnall",
    "sg:city":"Sheffield",
    "sg:classifiers":[
        {
            "category":"Professional",
            "subcategory":"Engineering",
            "type":"Services"
        }
    ],
    "sg:phone":"+44 114 249 3522",
    "sg:postcode":"S9 5DX",
    "sg:province":"South Yorkshire",
    "sg:tags":[
        "contractor",
        "electrical",
        "engineer"
    ],
    "wof:name":"Joint Electrical Services",
    "wof:placetype":"venue"
},
  "geometry": {"coordinates":[-1.419039011,53.3963394165],"type":"Point"}
}