{
  "type": "Feature",
  "properties": {
    "iso:country":"GB",
    "sg:address":"10 Treforthlan Estate, Paynters Lane End",
    "sg:city":"Redruth",
    "sg:classifiers":[
        {
            "category":"Professional",
            "subcategory":"Employment Agencies",
            "type":"Services"
        }
    ],
    "sg:phone":"+44 1209 842799",
    "sg:postcode":"TR16 4RN",
    "sg:province":"Cornwall",
    "sg:tags":[
        "career",
        "guidance"
    ],
    "wof:name":"Steve Nicholls",
    "wof:placetype":"venue"
},
  "geometry": {"coordinates":[-5.266024,50.243835],"type":"Point"}
}