{
  "type": "Feature",
  "properties": {
    "addr:full":"Mickleton Barnard Castle Cumbria DL12 0JY",
    "addr:postcode":"dl12 0jy",
    "addr:street":"Mickleton",
    "iso:country":"GB",
    "sg:address":"Mickleton",
    "sg:city":"Barnard Castle",
    "sg:classifiers":[
        {
            "category":"Bars & Pubs",
            "type":"Food & Drink"
        }
    ],
    "sg:phone":"+44 1833 640605",
    "sg:postcode":"DL12 0JY",
    "sg:province":"Cumbria",
    "sg:tags":[
        "pubs",
        "inn"
    ],
    "wof:name":"Blacksmiths Arms",
    "wof:placetype":"venue"
},
  "geometry": {"coordinates":[-2.049724,54.608715],"type":"Point"}
}