{
  "type": "Feature",
  "properties": {
    "addr:full":"6 Miranda Road Bootle Merseyside L20 2EE",
    "addr:housenumber":"6",
    "addr:postcode":"l20 2ee",
    "addr:street":"Miranda Road",
    "iso:country":"GB",
    "sg:address":"6 Miranda Road",
    "sg:city":"Bootle",
    "sg:classifiers":[
        {
            "category":"Fast Food",
            "type":"Food & Drink"
        }
    ],
    "sg:phone":"+44 151 286 6708",
    "sg:postcode":"L20 2EE",
    "sg:province":"Merseyside",
    "sg:tags":[
        "away",
        "take"
    ],
    "wof:name":"Lucky Star",
    "wof:placetype":"venue"
},
  "geometry": {"coordinates":[-2.9852020741,53.4418373108],"type":"Point"}
}