{
  "type": "Feature",
  "properties": {
    "iso:country":"GB",
    "sg:address":"11 Silver Street",
    "sg:city":"Lincoln",
    "sg:classifiers":[
        {
            "category":"Bars & Pubs",
            "subcategory":"Nightclub",
            "type":"Food & Drink"
        }
    ],
    "sg:phone":"+44 1522 522314",
    "sg:postcode":"LN2 1DY",
    "sg:province":"Lincolnshire",
    "sg:tags":[
        "club",
        "night"
    ],
    "wof:name":"Northern Leisure 2000 Ltd.",
    "wof:placetype":"venue"
},
  "geometry": {"coordinates":[-0.540319,53.229519],"type":"Point"}
}