{
  "type": "Feature",
  "properties": {
    "addr:full":"74-76 High Street Irvine North Ayrshire KA12 0AX",
    "addr:housenumber":"74-76",
    "addr:postcode":"ka12 0ax",
    "addr:street":"High Street",
    "iso:country":"GB",
    "sg:address":"74-76 High Street",
    "sg:city":"Irvine",
    "sg:classifiers":[
        {
            "category":"Fast Food",
            "type":"Food & Drink"
        },
        {
            "category":"Food & Beverages",
            "subcategory":"Meat & Fish",
            "type":"Retail Goods"
        }
    ],
    "sg:phone":"+44 1294 273504",
    "sg:postcode":"KA12 0AX",
    "sg:province":"North Ayrshire",
    "sg:tags":[
        "outlet",
        "chip",
        "meal",
        "away",
        "take"
    ],
    "wof:name":"The Victoria Cafe",
    "wof:placetype":"venue"
},
  "geometry": {"coordinates":[-4.66595,55.614594],"type":"Point"}
}