{
  "type": "Feature",
  "properties": {
    "addr:full":"London House, Lynn Road, Gayton King's Lynn Norfolk PE32 1QJ",
    "addr:postcode":"pe32 1qj",
    "addr:street":"Lynn Road;Lynn",
    "iso:country":"GB",
    "sg:address":"London House, Lynn Road, Gayton",
    "sg:city":"King's Lynn",
    "sg:classifiers":[
        {
            "category":"Home & Garden",
            "subcategory":"Home Furnishings",
            "type":"Retail Goods"
        }
    ],
    "sg:phone":"+44 1553 636430",
    "sg:postcode":"PE32 1QJ",
    "sg:province":"Norfolk",
    "sg:tags":[
        "candle"
    ],
    "wof:name":"Clearlight Candles",
    "wof:placetype":"venue"
},
  "geometry": {"coordinates":[0.5511199832,52.7449111938],"type":"Point"}
}