{
  "type": "Feature",
  "properties": {
    "addr:full":"Duffield Road Chelmsford Essex CM2 9RZ",
    "addr:postcode":"cm2 9rz",
    "addr:street":"Duffield Road",
    "iso:country":"GB",
    "sg:address":"Duffield Road",
    "sg:city":"Chelmsford",
    "sg:classifiers":[
        {
            "category":"Education",
            "subcategory":"School",
            "type":"Public Place"
        }
    ],
    "sg:phone":"+44 1245 265821",
    "sg:postcode":"CM2 9RZ",
    "sg:province":"Essex",
    "sg:tags":[
        "local",
        "authority"
    ],
    "wof:name":"Great Baddow High School",
    "wof:placetype":"venue"
},
  "geometry": {"coordinates":[0.484085,51.714985],"type":"Point"}
}