{
  "type": "Feature",
  "properties": {
    "addr:full":"7 Station Road Saltash Cornwall PL12 4DY",
    "addr:housenumber":"7",
    "addr:postcode":"pl12 4dy",
    "addr:street":"Station Road",
    "iso:country":"GB",
    "sg:address":"7 Station Road",
    "sg:city":"Saltash",
    "sg:classifiers":[
        {
            "category":"Home & Garden",
            "subcategory":"Building Materials",
            "type":"Retail Goods"
        }
    ],
    "sg:phone":"+44 1752 847682",
    "sg:postcode":"PL12 4DY",
    "sg:province":"Cornwall",
    "sg:tags":[
        "insulation",
        "installers"
    ],
    "wof:name":"Associated Insulation Services",
    "wof:placetype":"venue"
},
  "geometry": {"coordinates":[-4.209723,50.407139],"type":"Point"}
}