{
  "type": "Feature",
  "properties": {
    "addr:full":"115 Clare Street Northampton Northamptonshire NN1 3JA",
    "addr:housenumber":"115",
    "addr:postcode":"nn1 3ja",
    "addr:street":"Clare Street",
    "iso:country":"GB",
    "sg:address":"115 Clare Street",
    "sg:city":"Northampton",
    "sg:classifiers":[
        {
            "category":"Arts & Performance",
            "subcategory":"Theater",
            "type":"Entertainment"
        }
    ],
    "sg:phone":"+44 1604 627791",
    "sg:postcode":"NN1 3JA",
    "sg:province":"Northamptonshire",
    "sg:tags":[
        "hall",
        "theatre",
        "concert"
    ],
    "wof:name":"The Northampton Theatre Guild",
    "wof:placetype":"venue"
},
  "geometry": {"coordinates":[-0.887508,52.243637],"type":"Point"}
}