{
  "type": "Feature",
  "properties": {
    "iso:country":"GB",
    "sg:address":"50 Cecil St",
    "sg:city":"Glasgow",
    "sg:classifiers":[
        {
            "category":"Professional",
            "subcategory":"Business Services",
            "type":"Services"
        }
    ],
    "sg:phone":"+44 141 339 6912",
    "sg:postcode":"G12 8RJ",
    "sg:province":"Glasgow City",
    "sg:tags":[
        "import",
        "export",
        "agent"
    ],
    "wof:name":"Scotia Imports UK",
    "wof:placetype":"venue"
},
  "geometry": {"coordinates":[-4.288853,55.875347],"type":"Point"}
}