{
  "type": "Feature",
  "properties": {
    "addr:full":"Unit 4, Thrales End Farm Harpenden Hertfordshire AL5 3NS",
    "addr:housenumber":"unit 4",
    "addr:postcode":"al5 3ns",
    "addr:street":"Thrales End",
    "iso:country":"GB",
    "sg:address":"Unit 4, Thrales End Farm",
    "sg:city":"Harpenden",
    "sg:classifiers":[
        {
            "category":"Manufacturing",
            "subcategory":"Rubber & Plastics",
            "type":"Manufacturing & Wholesale Goods"
        }
    ],
    "sg:phone":"+44 1582 469797",
    "sg:postcode":"AL5 3NS",
    "sg:province":"Hertfordshire",
    "sg:tags":[
        "product",
        "forming",
        "machine",
        "vacuum",
        "making",
        "manufacturer"
    ],
    "sg:website":"http://www.formech.com",
    "wof:name":"Formech International Ltd",
    "wof:placetype":"venue"
},
  "geometry": {"coordinates":[-0.373131,51.831425],"type":"Point"}
}