{
  "type": "Feature",
  "properties": {
    "addr:full":"72 Commercial Street Halifax West Yorkshire HX1 2JE",
    "addr:housenumber":"72",
    "addr:postcode":"hx1 2je",
    "addr:street":"Commercial Street",
    "iso:country":"GB",
    "sg:address":"72 Commercial Street",
    "sg:city":"Halifax",
    "sg:classifiers":[
        {
            "category":"Personal",
            "subcategory":"Beauty Salon",
            "type":"Services"
        },
        {
            "category":"Personal",
            "subcategory":"Barber",
            "type":"Services"
        }
    ],
    "sg:phone":"+44 1422 347271",
    "sg:postcode":"HX1 2JE",
    "sg:province":"West Yorkshire",
    "sg:tags":[
        "unisex",
        "hairdresser"
    ],
    "wof:name":"Robinson & Field Haircutters",
    "wof:placetype":"venue"
},
  "geometry": {"coordinates":[-1.8604650497,53.7201042175],"type":"Point"}
}