{
  "type": "Feature",
  "properties": {
    "addr:full":"55 Bolton Street Blackpool Lancashire FY1 6AA",
    "addr:housenumber":"55",
    "addr:postcode":"fy1 6aa",
    "addr:street":"Bolton Street",
    "iso:country":"GB",
    "sg:address":"55 Bolton Street",
    "sg:city":"Blackpool",
    "sg:classifiers":[
        {
            "category":"Personal",
            "subcategory":"Skin Care",
            "type":"Services"
        }
    ],
    "sg:phone":"+44 1253 341543",
    "sg:postcode":"FY1 6AA",
    "sg:province":"Lancashire",
    "sg:tags":[
        "orthopaedic"
    ],
    "wof:name":"Shaw's Surgical Stores",
    "wof:placetype":"venue"
},
  "geometry": {"coordinates":[-3.05468,53.799431],"type":"Point"}
}