{
  "type": "Feature",
  "properties": {
    "iso:country":"GB",
    "sg:address":"Richmonds House",
    "sg:city":"Southampton",
    "sg:classifiers":[
        {
            "category":"Freight",
            "type":"Transportation"
        }
    ],
    "sg:postcode":"SO14 3PN",
    "sg:province":"Hampshire",
    "sg:tags":[
        "shipping"
    ],
    "wof:name":"Princess Cruises (1978) Ltd.",
    "wof:placetype":"venue"
},
  "geometry": {"coordinates":[-1.39655,50.899521],"type":"Point"}
}