{
  "type": "Feature",
  "properties": {
    "addr:full":"7 Came View Rd Dorchester Dorset DT1 2AE",
    "addr:housenumber":"7",
    "addr:postcode":"dt1 2ae",
    "addr:street":"Came View Rd",
    "iso:country":"GB",
    "sg:address":"7 Came View Rd",
    "sg:city":"Dorchester",
    "sg:classifiers":[
        {
            "category":"Professional",
            "subcategory":"Management & Consulting",
            "type":"Services"
        }
    ],
    "sg:postcode":"DT1 2AE",
    "sg:province":"Dorset",
    "sg:tags":[
        "consultant",
        "business"
    ],
    "wof:name":"Sherring,Stuart V,",
    "wof:placetype":"venue"
},
  "geometry": {"coordinates":[-2.417143,50.707321],"type":"Point"}
}