{
  "type": "Feature",
  "properties": {
    "addr:full":"10 Green Lane, Lye Stourbridge West Midlands DY9 7EW",
    "addr:housenumber":"10",
    "addr:postcode":"dy9 7ew",
    "addr:street":"Green Lane",
    "iso:country":"GB",
    "sg:address":"10 Green Lane, Lye",
    "sg:city":"Stourbridge",
    "sg:classifiers":[
        {
            "category":"Arts & Performance",
            "subcategory":"Music",
            "type":"Entertainment"
        }
    ],
    "sg:postcode":"DY9 7EW",
    "sg:province":"West Midlands",
    "sg:tags":[
        "mobile",
        "disco"
    ],
    "wof:name":"Goldrush Promotions-Discos",
    "wof:placetype":"venue"
},
  "geometry": {"coordinates":[-2.1188020706,52.454372406],"type":"Point"}
}