{
  "type": "Feature",
  "properties": {
    "iso:country":"GB",
    "sg:address":"8 Main St",
    "sg:city":"Ferryhill",
    "sg:classifiers":[
        {
            "category":"Real Estate",
            "subcategory":"Real Estate Agent",
            "type":"Services"
        }
    ],
    "sg:phone":"+44 1740 651111",
    "sg:postcode":"DL17 8LA",
    "sg:province":"Durham",
    "wof:name":"Local Independant Property Services",
    "wof:placetype":"venue"
},
  "geometry": {"coordinates":[-1.557937026,54.6888008118],"type":"Point"}
}