{
  "type": "Feature",
  "properties": {
    "iso:country":"GB",
    "sg:address":"2b The Halfcroft, Syston",
    "sg:city":"Leicester",
    "sg:classifiers":[
        {
            "category":"Shopping",
            "subcategory":"Stationery & Office Supplies",
            "type":"Retail Goods"
        },
        {
            "category":"Shopping",
            "type":"Retail Goods"
        }
    ],
    "sg:phone":"+44 116 260 5327",
    "sg:postcode":"LE7 1LD",
    "sg:province":"Leicestershire",
    "sg:tags":[
        "packaging",
        "equipment",
        "product",
        "disposable"
    ],
    "wof:name":"Gateway Packaging (Leicester) Ltd.",
    "wof:placetype":"venue"
},
  "geometry": {"coordinates":[-1.082804,52.701302],"type":"Point"}
}