{
  "type": "Feature",
  "properties": {
    "addr:full":"Hook Manor, Donhead St Andrew Shaftesbury Dorset SP7 9EU",
    "addr:postcode":"dorset sp7 9eu",
    "iso:country":"GB",
    "sg:address":"Hook Manor, Donhead St Andrew",
    "sg:city":"Shaftesbury",
    "sg:classifiers":[
        {
            "category":"Farming",
            "subcategory":"Dairy Farm",
            "type":"Manufacturing & Wholesale Goods"
        }
    ],
    "sg:phone":"+44 1747 828423",
    "sg:postcode":"SP7 9EU",
    "sg:province":"Dorset",
    "wof:name":"R J T Arundell",
    "wof:placetype":"venue"
},
  "geometry": {"coordinates":[-2.187124,51.005764],"type":"Point"}
}