{
  "type": "Feature",
  "properties": {
    "iso:country":"GB",
    "sg:address":"3 Canon Harnett Court, Warren Farm, Wolverton Mill",
    "sg:city":"Milton Keynes",
    "sg:classifiers":[
        {
            "category":"Professional",
            "subcategory":"Employment Agencies",
            "type":"Services"
        }
    ],
    "sg:phone":"+44 1908 226800",
    "sg:postcode":"MK12 5NF",
    "sg:province":"Buckinghamshire",
    "sg:tags":[
        "consultant"
    ],
    "wof:name":"Excal I T Ltd.",
    "wof:placetype":"venue"
},
  "geometry": {"coordinates":[-0.835343,52.05999],"type":"Point"}
}