{
  "type": "Feature",
  "properties": {
    "addr:full":"Westfield House, Quernmore Lancaster Lancashire LA2 0QR",
    "addr:postcode":"la2 0qr",
    "addr:street":"Quernmore",
    "iso:country":"GB",
    "sg:address":"Westfield House, Quernmore",
    "sg:city":"Lancaster",
    "sg:classifiers":[
        {
            "category":"Farming",
            "subcategory":"Livestock Farm",
            "type":"Manufacturing & Wholesale Goods"
        }
    ],
    "sg:phone":"+44 1524 66373",
    "sg:postcode":"LA2 0QR",
    "sg:province":"Lancashire",
    "sg:tags":[
        "others"
    ],
    "wof:name":"W J & K F Atkinson & Son",
    "wof:placetype":"venue"
},
  "geometry": {"coordinates":[-2.850934,53.99641],"type":"Point"}
}