{
  "type": "Feature",
  "properties": {
    "addr:full":"Windsor House, Barnett Way Barnwood Gloucester Gloucestershire GL4 3RT",
    "addr:postcode":"gl4 3rt",
    "addr:street":"Barnett Way",
    "iso:country":"GB",
    "sg:address":"Windsor House, Barnett Way Barnwood",
    "sg:city":"Gloucester",
    "sg:classifiers":[
        {
            "category":"Freight",
            "type":"Transportation"
        }
    ],
    "sg:postcode":"GL4 3RT",
    "sg:province":"Gloucestershire",
    "sg:tags":[
        "haulage",
        "road"
    ],
    "wof:name":"Maguires Transport Ltd",
    "wof:placetype":"venue"
},
  "geometry": {"coordinates":[-2.2093389034,51.8628005981],"type":"Point"}
}