{
  "type": "Feature",
  "properties": {
    "iso:country":"GB",
    "sg:address":"160 Queens Road",
    "sg:city":"Buckhurst Hill",
    "sg:classifiers":[
        {
            "category":"Shopping",
            "subcategory":"Discount & Variety Stores",
            "type":"Retail Goods"
        }
    ],
    "sg:phone":"+44 20 8505 4012",
    "sg:postcode":"IG9 5BD",
    "sg:province":"Essex",
    "sg:tags":[
        "centre"
    ],
    "wof:name":"Churchills",
    "wof:placetype":"venue"
},
  "geometry": {"coordinates":[0.037819,51.625778],"type":"Point"}
}