{
  "type": "Feature",
  "properties": {
    "iso:country":"GB",
    "sg:address":"Finch Foundry",
    "sg:city":"Okehampton",
    "sg:classifiers":[
        {
            "category":"Landmark",
            "subcategory":"Tourist Attraction",
            "type":"Public Place"
        }
    ],
    "sg:phone":"+44 1837 840046",
    "sg:postcode":"EX20 2NW",
    "sg:province":"Devon",
    "sg:tags":[
        "interest"
    ],
    "wof:name":"Museum of Water Power",
    "wof:placetype":"venue"
},
  "geometry": {"coordinates":[-4.0025148392,50.7392234802],"type":"Point"}
}