{
  "type": "Feature",
  "properties": {
    "addr:full":"608 Fulham Road London Greater London SW6 5RP",
    "addr:housenumber":"608",
    "addr:postcode":"sw6 5rp",
    "addr:street":"Fulham Road",
    "iso:country":"GB",
    "sg:address":"608 Fulham Road",
    "sg:city":"London",
    "sg:classifiers":[
        {
            "category":"Shopping",
            "subcategory":"Pharmacy",
            "type":"Retail Goods"
        }
    ],
    "sg:postcode":"SW6 5RP",
    "sg:province":"Greater London",
    "sg:tags":[
        "pharmacist",
        "chemist"
    ],
    "wof:name":"Fulham Pharmacy",
    "wof:placetype":"venue"
},
  "geometry": {"coordinates":[-0.2031539977,51.4769172668],"type":"Point"}
}