{
  "type": "Feature",
  "properties": {
    "addr:full":"Unit 8 Fairways View, Forest Hill Est Pontyclun Bridgend CF72 8ED",
    "addr:housenumber":"unit 8",
    "addr:postcode":"cf72 8ed",
    "addr:street":"Fairways View",
    "iso:country":"GB",
    "sg:address":"Unit 8 Fairways View, Forest Hill Est",
    "sg:city":"Pontyclun",
    "sg:classifiers":[
        {
            "category":"Building & Trades",
            "subcategory":"Pest Control",
            "type":"Services"
        }
    ],
    "sg:phone":"+44 1443 224652",
    "sg:postcode":"CF72 8ED",
    "sg:province":"Bridgend",
    "sg:tags":[
        "vermin"
    ],
    "wof:name":"Campbell Group The",
    "wof:placetype":"venue"
},
  "geometry": {"coordinates":[-3.3764100075,51.5422096252],"type":"Point"}
}