{
  "type": "Feature",
  "properties": {
    "iso:country":"GB",
    "sg:address":"820 Pershore Rd, Selly Oak",
    "sg:city":"Birmingham",
    "sg:classifiers":[
        {
            "category":"Fast Food",
            "type":"Food & Drink"
        }
    ],
    "sg:postcode":"B29 7LS",
    "sg:province":"West Midlands",
    "sg:tags":[
        "away",
        "take"
    ],
    "wof:name":"O'Reilly,Susan,",
    "wof:placetype":"venue"
},
  "geometry": {"coordinates":[-1.9154670238,52.4411315918],"type":"Point"}
}