{
  "type": "Feature",
  "properties": {
    "addr:full":"73 High St, Woodville Swadlincote Derbyshire DE11 7EA",
    "addr:housenumber":"73",
    "addr:postcode":"de11 7ea",
    "addr:street":"High St",
    "iso:country":"GB",
    "sg:address":"73 High St, Woodville",
    "sg:city":"Swadlincote",
    "sg:classifiers":[
        {
            "category":"Social Services",
            "type":"Services"
        }
    ],
    "sg:postcode":"DE11 7EA",
    "sg:province":"Derbyshire",
    "sg:tags":[
        "disability"
    ],
    "wof:name":"Sherratt,M,",
    "wof:placetype":"venue"
},
  "geometry": {"coordinates":[-1.533999,52.769146],"type":"Point"}
}