{
  "type": "Feature",
  "properties": {
    "addr:full":"6 Campions Loughton Essex IG10 2SG",
    "addr:housenumber":"6",
    "addr:postcode":"ig10 2sg",
    "addr:street":"Campions",
    "iso:country":"GB",
    "sg:address":"6 Campions",
    "sg:city":"Loughton",
    "sg:classifiers":[
        {
            "category":"Building & Trades",
            "subcategory":"Construction",
            "type":"Services"
        },
        {
            "category":"Food & Beverages",
            "subcategory":"Fruits & Vegetables",
            "type":"Retail Goods"
        }
    ],
    "sg:phone":"+44 20 8508 9246",
    "sg:postcode":"IG10 2SG",
    "sg:province":"Essex",
    "sg:tags":[
        "greengrocer",
        "restoration",
        "refurbishment"
    ],
    "wof:name":"Christian James Ltd",
    "wof:placetype":"venue"
},
  "geometry": {"coordinates":[0.068678,51.663361],"type":"Point"}
}