{
  "type": "Feature",
  "properties": {
    "addr:full":"59 Church Street Flint Flintshire CH6 5AF",
    "addr:housenumber":"59",
    "addr:postcode":"ch6 5af",
    "addr:street":"Church Street",
    "iso:country":"GB",
    "sg:address":"59 Church Street",
    "sg:city":"Flint",
    "sg:classifiers":[
        {
            "category":"Food & Beverages",
            "subcategory":"Fruits & Vegetables",
            "type":"Retail Goods"
        }
    ],
    "sg:postcode":"CH6 5AF",
    "sg:province":"Flintshire",
    "sg:tags":[
        "greengrocer"
    ],
    "wof:name":"The Apple Tree",
    "wof:placetype":"venue"
},
  "geometry": {"coordinates":[-3.1366689205,53.2482452393],"type":"Point"}
}