{
  "type": "Feature",
  "properties": {
    "addr:full":"Unit 35a, Octagon Centre Burton-on-trent Derbyshire DE14 3TN",
    "addr:housenumber":"unit 35a octagon centre",
    "addr:postcode":"de14 3tn",
    "iso:country":"GB",
    "sg:address":"Unit 35a, Octagon Centre",
    "sg:city":"Burton-on-trent",
    "sg:classifiers":[
        {
            "category":"Military Area",
            "subcategory":"Air Force Base",
            "type":"Public Place"
        }
    ],
    "sg:phone":"+44 1283 515544",
    "sg:postcode":"DE14 3TN",
    "sg:province":"Derbyshire",
    "sg:tags":[
        "taxi",
        "hire",
        "private"
    ],
    "wof:name":"New Street Taxis",
    "wof:placetype":"venue"
},
  "geometry": {"coordinates":[-1.63372,52.800621],"type":"Point"}
}