{
  "type": "Feature",
  "properties": {
    "addr:full":"Whitecliffe Park, Manor Way Swanscombe Kent DA10 0LL",
    "addr:postcode":"da10 0ll",
    "addr:street":"Whitecliffe Park Manor Way",
    "iso:country":"GB",
    "sg:address":"Whitecliffe Park, Manor Way",
    "sg:city":"Swanscombe",
    "sg:classifiers":[
        {
            "category":"Freight",
            "type":"Transportation"
        }
    ],
    "sg:phone":"+44 1322 370700",
    "sg:postcode":"DA10 0LL",
    "sg:province":"Kent",
    "sg:tags":[
        "haulage",
        "road"
    ],
    "wof:name":"M J D & Sons Ltd.",
    "wof:placetype":"venue"
},
  "geometry": {"coordinates":[0.3085449934,51.4501457214],"type":"Point"}
}