{
  "type": "Feature",
  "properties": {
    "addr:full":"130 Union St Larkhall South Lanarkshire ML9 1EF",
    "addr:housenumber":"130",
    "addr:postcode":"ml9 1ef",
    "addr:street":"Union St",
    "iso:country":"GB",
    "sg:address":"130 Union St",
    "sg:city":"Larkhall",
    "sg:classifiers":[
        {
            "category":"Personal",
            "subcategory":"Nail Salon",
            "type":"Services"
        }
    ],
    "sg:phone":"+44 1698 888937",
    "sg:postcode":"ML9 1EF",
    "sg:province":"South Lanarkshire",
    "sg:tags":[
        "solarium",
        "tanning"
    ],
    "wof:name":"Stand Tan",
    "wof:placetype":"venue"
},
  "geometry": {"coordinates":[-3.973148,55.738228],"type":"Point"}
}