{
  "type": "Feature",
  "properties": {
    "addr:full":"Unit 5 Sycamore Centre, 155 Attercliffe Common Sheffield South Yorkshire S9 2FA",
    "addr:housenumber":"unit 5;155",
    "addr:postcode":"sheffield;s9 2fa",
    "addr:street":"Sycamore Centre;Common;South",
    "iso:country":"GB",
    "sg:address":"Unit 5 Sycamore Centre, 155 Attercliffe Common",
    "sg:city":"Sheffield",
    "sg:classifiers":[
        {
            "category":"Shopping",
            "subcategory":"Stationery & Office Supplies",
            "type":"Retail Goods"
        },
        {
            "category":"Professional",
            "subcategory":"Printing & Photocopies",
            "type":"Services"
        }
    ],
    "sg:phone":"+44 114 242 4149",
    "sg:postcode":"S9 2FA",
    "sg:province":"South Yorkshire",
    "sg:tags":[
        "equipment",
        "drawing",
        "copying"
    ],
    "wof:name":"Pinders Drawing Group",
    "wof:placetype":"venue"
},
  "geometry": {"coordinates":[-1.4250899553,53.3996810913],"type":"Point"}
}