{
  "type": "Feature",
  "properties": {
    "iso:country":"GB",
    "sg:address":"9 St Johns Square",
    "sg:city":"Stoke-on-trent",
    "sg:classifiers":[
        {
            "category":"Shopping",
            "subcategory":"Thrift Store",
            "type":"Retail Goods"
        }
    ],
    "sg:phone":"+44 1782 822439",
    "sg:postcode":"ST6 3AH",
    "sg:province":"Staffordshire",
    "sg:tags":[
        "shop",
        "charity"
    ],
    "wof:name":"Shelter Trading Ltd.",
    "wof:placetype":"venue"
},
  "geometry": {"coordinates":[-2.1988079548,53.0448417664],"type":"Point"}
}