{
  "type": "Feature",
  "properties": {
    "addr:full":"Portland Drive Mansfield Derbyshire NG20 8SG",
    "addr:postcode":"ng20 8sg",
    "addr:street":"Portland Drive",
    "iso:country":"GB",
    "sg:address":"Portland Drive",
    "sg:city":"Mansfield",
    "sg:classifiers":[
        {
            "category":"Retail",
            "subcategory":"Auto Repair",
            "type":"Services"
        }
    ],
    "sg:phone":"+44 1623 748252",
    "sg:postcode":"NG20 8SG",
    "sg:province":"Derbyshire",
    "sg:tags":[
        "modification",
        "garage"
    ],
    "wof:name":"Shirebrook Plant Autos",
    "wof:placetype":"venue"
},
  "geometry": {"coordinates":[-1.2078889608,53.2038230896],"type":"Point"}
}