{
  "type": "Feature",
  "properties": {
    "iso:country":"GB",
    "sg:address":"3 Church Lane",
    "sg:city":"Barnstaple",
    "sg:classifiers":[
        {
            "category":"Shopping",
            "subcategory":"Department Store",
            "type":"Retail Goods"
        }
    ],
    "sg:phone":"+44 1271 329484",
    "sg:postcode":"EX31 1BH",
    "sg:province":"Devon",
    "wof:name":"M J Floyde",
    "wof:placetype":"venue"
},
  "geometry": {"coordinates":[-4.059279,51.079464],"type":"Point"}
}