{
  "type": "Feature",
  "properties": {
    "iso:country":"GB",
    "sg:address":"11 Kingsway",
    "sg:city":"Newport",
    "sg:classifiers":[
        {
            "category":"Shopping",
            "subcategory":"Discount & Variety Stores",
            "type":"Retail Goods"
        },
        {
            "category":"Home & Garden",
            "subcategory":"Furniture",
            "type":"Retail Goods"
        }
    ],
    "sg:phone":"+44 1633 220600",
    "sg:postcode":"NP20 1EX",
    "sg:province":"Newport",
    "sg:tags":[
        "centre"
    ],
    "wof:name":"Bargainland",
    "wof:placetype":"venue"
},
  "geometry": {"coordinates":[-2.9920489788,51.5838394165],"type":"Point"}
}