{
  "type": "Feature",
  "properties": {
    "addr:full":"Caithness Livestock Centre, Watten Wick Highland KW1 5UN",
    "addr:postcode":"kw1 5un",
    "iso:country":"GB",
    "sg:address":"Caithness Livestock Centre, Watten",
    "sg:city":"Wick",
    "sg:classifiers":[
        {
            "category":"Professional",
            "type":"Services"
        }
    ],
    "sg:phone":"+44 1955 621363",
    "sg:postcode":"KW1 5UN",
    "sg:province":"Highland",
    "sg:tags":[
        "valuer",
        "auctioneer"
    ],
    "sg:website":"http://www.goanm.co.uk",
    "wof:name":"Aberdeen & Northern Marts",
    "wof:placetype":"venue"
},
  "geometry": {"coordinates":[-3.3043489456,58.4724006653],"type":"Point"}
}