{
  "type": "Feature",
  "properties": {
    "addr:full":"Emsworth Crescent, Pendeford Wolverhampton Staffordshire WV9 5NR",
    "addr:postcode":"wv9 5nr",
    "addr:street":"Emsworth Crescent Pendeford",
    "iso:country":"GB",
    "sg:address":"Emsworth Crescent, Pendeford",
    "sg:city":"Wolverhampton",
    "sg:classifiers":[
        {
            "category":"Education",
            "subcategory":"School",
            "type":"Public Place"
        },
        {
            "category":"Government",
            "subcategory":"Office",
            "type":"Public Place"
        }
    ],
    "sg:phone":"+44 1902 558621",
    "sg:postcode":"WV9 5NR",
    "sg:province":"Staffordshire",
    "sg:tags":[
        "local",
        "authority"
    ],
    "wof:name":"St Paul's C of E Primary School",
    "wof:placetype":"venue"
},
  "geometry": {"coordinates":[-2.1541399956,52.6297187805],"type":"Point"}
}