{
  "type": "Feature",
  "properties": {
    "addr:full":"310 Birmingham Rd, Wylde Green Sutton Coldfield West Midlands B72 1DP",
    "addr:housenumber":"310",
    "addr:postcode":"b72 1dp",
    "addr:street":"Birmingham Rd",
    "iso:country":"GB",
    "sg:address":"310 Birmingham Rd, Wylde Green",
    "sg:city":"Sutton Coldfield",
    "sg:classifiers":[
        {
            "category":"Real Estate",
            "subcategory":"Architect",
            "type":"Services"
        }
    ],
    "sg:phone":"+44 121 373 0630",
    "sg:postcode":"B72 1DP",
    "sg:province":"West Midlands",
    "sg:tags":[
        "architectural"
    ],
    "wof:name":"Architectural Services",
    "wof:placetype":"venue"
},
  "geometry": {"coordinates":[-1.8266710043,52.5388259888],"type":"Point"}
}