{
  "type": "Feature",
  "properties": {
    "addr:full":"2 Bunbury Close, Stoak Chester Cheshire CH2 4HL",
    "addr:housenumber":"2",
    "addr:postcode":"ch2 4hl",
    "addr:street":"Bunbury Close",
    "iso:country":"GB",
    "sg:address":"2 Bunbury Close, Stoak",
    "sg:city":"Chester",
    "sg:classifiers":[
        {
            "category":"Arts & Performance",
            "subcategory":"Music",
            "type":"Entertainment"
        }
    ],
    "sg:phone":"+44 1244 301710",
    "sg:postcode":"CH2 4HL",
    "sg:province":"Cheshire",
    "sg:tags":[
        "mobile",
        "disco"
    ],
    "wof:name":"Supersonic Roadshow Mobile Disco",
    "wof:placetype":"venue"
},
  "geometry": {"coordinates":[-2.866406,53.251865],"type":"Point"}
}