{
  "type": "Feature",
  "properties": {
    "iso:country":"GB",
    "sg:address":"Arundel Square",
    "sg:city":"London",
    "sg:classifiers":[
        {
            "category":"Organizations",
            "subcategory":"Non-profit Organization",
            "type":"Services"
        }
    ],
    "sg:phone":"+44 20 7607 8348",
    "sg:postcode":"N7 8AS",
    "sg:province":"Greater London",
    "sg:tags":[
        "charitable",
        "organisation",
        "voluntary",
        "charity"
    ],
    "wof:name":"ISLINGTON PLAY ASSOCIATION",
    "wof:placetype":"venue"
},
  "geometry": {"coordinates":[-0.1096619964,51.5458221436],"type":"Point"}
}