{
  "type": "Feature",
  "properties": {
    "iso:country":"GB",
    "sg:address":"Brimboyte",
    "sg:city":"Liskeard",
    "sg:classifiers":[
        {
            "category":"Farming",
            "subcategory":"Livestock Farm",
            "type":"Manufacturing & Wholesale Goods"
        },
        {
            "category":"Farming",
            "subcategory":"Farm",
            "type":"Manufacturing & Wholesale Goods"
        }
    ],
    "sg:phone":"+44 1579 343364",
    "sg:postcode":"PL14 3QE",
    "sg:province":"Cornwall",
    "sg:tags":[
        "mixed",
        "crop",
        "others"
    ],
    "wof:name":"N W & D P Rundle",
    "wof:placetype":"venue"
},
  "geometry": {"coordinates":[-4.465834,50.453796],"type":"Point"}
}