{
  "type": "Feature",
  "properties": {
    "addr:full":"118 Carshalton Park Rd Carshalton Surrey SM5 3SG",
    "addr:housenumber":"118",
    "addr:postcode":"sm5 3sg",
    "addr:street":"Carshalton Park Rd",
    "iso:country":"GB",
    "sg:address":"118 Carshalton Park Rd",
    "sg:city":"Carshalton",
    "sg:classifiers":[
        {
            "category":"Health Services",
            "subcategory":"Dentist",
            "type":"Services"
        }
    ],
    "sg:phone":"+44 20 8647 5782",
    "sg:postcode":"SM5 3SG",
    "sg:province":"Surrey",
    "sg:tags":[
        "technician",
        "dental"
    ],
    "wof:name":"Carshalton Denture Repairs",
    "wof:placetype":"venue"
},
  "geometry": {"coordinates":[-0.168181,51.359795],"type":"Point"}
}