{
  "type": "Feature",
  "properties": {
    "iso:country":"GB",
    "sg:address":"33 Nicklaus Drive",
    "sg:city":"Chatham",
    "sg:classifiers":[
        {
            "category":"Building & Trades",
            "subcategory":"Construction",
            "type":"Services"
        }
    ],
    "sg:phone":"+44 1634 867228",
    "sg:postcode":"ME5 9HQ",
    "sg:province":"Kent",
    "sg:tags":[
        "builder"
    ],
    "wof:name":"Martin Towell",
    "wof:placetype":"venue"
},
  "geometry": {"coordinates":[0.521793,51.339329],"type":"Point"}
}