{
  "type": "Feature",
  "properties": {
    "addr:full":"50 Dunchurch Road Rugby Warwickshire CV22 6AD",
    "addr:housenumber":"50",
    "addr:postcode":"cv22 6ad",
    "addr:street":"Dunchurch Road",
    "iso:country":"GB",
    "sg:address":"50 Dunchurch Road",
    "sg:city":"Rugby",
    "sg:classifiers":[
        {
            "category":"Bars & Pubs",
            "type":"Food & Drink"
        }
    ],
    "sg:postcode":"CV22 6AD",
    "sg:province":"Warwickshire",
    "sg:tags":[
        "pubs",
        "inn"
    ],
    "wof:name":"The Raglan Arms",
    "wof:placetype":"venue"
},
  "geometry": {"coordinates":[-1.2647490501,52.3689117432],"type":"Point"}
}