{
  "type": "Feature",
  "properties": {
    "iso:country":"GB",
    "sg:address":"3 New Rd, Station Rd",
    "sg:city":"Thetford",
    "sg:classifiers":[
        {
            "category":"Building & Trades",
            "subcategory":"Construction",
            "type":"Services"
        }
    ],
    "sg:phone":"+44 1842 753668",
    "sg:postcode":"IP24 1AN",
    "sg:province":"Norfolk",
    "sg:tags":[
        "dry",
        "lining",
        "plasterers",
        "screeders"
    ],
    "wof:name":"S A Flude",
    "wof:placetype":"venue"
},
  "geometry": {"coordinates":[0.74727,52.417015],"type":"Point"}
}