{
  "type": "Feature",
  "properties": {
    "addr:full":"20 Caddle Road Grimsby Lincolnshire DN41 8ET",
    "addr:housenumber":"20",
    "addr:postcode":"dn41 8et",
    "addr:street":"Caddle Road",
    "iso:country":"GB",
    "sg:address":"20 Caddle Road",
    "sg:city":"Grimsby",
    "sg:classifiers":[
        {
            "category":"Building & Trades",
            "subcategory":"Plumbing",
            "type":"Services"
        }
    ],
    "sg:postcode":"DN41 8ET",
    "sg:province":"Lincolnshire",
    "sg:tags":[
        "heating"
    ],
    "wof:name":"Alan David Saxton",
    "wof:placetype":"venue"
},
  "geometry": {"coordinates":[-0.2444069982,53.5713233948],"type":"Point"}
}