{
  "type": "Feature",
  "properties": {
    "addr:full":"Kent Farm, Shapwick Bridgwater Somerset TA7 9NN",
    "addr:postcode":"ta7 9nn",
    "addr:street":"Shapwick",
    "iso:country":"GB",
    "sg:address":"Kent Farm, Shapwick",
    "sg:city":"Bridgwater",
    "sg:classifiers":[
        {
            "category":"Farming",
            "subcategory":"Livestock Farm",
            "type":"Manufacturing & Wholesale Goods"
        }
    ],
    "sg:postcode":"TA7 9NN",
    "sg:province":"Somerset",
    "sg:tags":[
        "others"
    ],
    "wof:name":"Phillip S Gibbons",
    "wof:placetype":"venue"
},
  "geometry": {"coordinates":[-2.8342030048,51.1352043152],"type":"Point"}
}