{
  "type": "Feature",
  "properties": {
    "addr:full":"67 Westgate Mansfield Nottinghamshire NG18 1RU",
    "addr:housenumber":"67",
    "addr:postcode":"ng18 1ru",
    "addr:street":"Westgate",
    "iso:country":"GB",
    "sg:address":"67 Westgate",
    "sg:city":"Mansfield",
    "sg:classifiers":[
        {
            "category":"Cafe",
            "type":"Food & Drink"
        }
    ],
    "sg:phone":"+44 1623 28602",
    "sg:postcode":"NG18 1RU",
    "sg:province":"Nottinghamshire",
    "sg:tags":[
        "tea",
        "room"
    ],
    "wof:name":"Rhodes Snack Bar",
    "wof:placetype":"venue"
},
  "geometry": {"coordinates":[-1.1991200447,53.1461791992],"type":"Point"}
}