{
  "type": "Feature",
  "properties": {
    "addr:full":"1 Central Avenue Carlisle Cumbria CA1 3QB",
    "addr:housenumber":"1",
    "addr:postcode":"ca1 3qb",
    "addr:street":"Central Avenue",
    "iso:country":"GB",
    "sg:address":"1 Central Avenue",
    "sg:city":"Carlisle",
    "sg:classifiers":[
        {
            "category":"Food & Beverages",
            "subcategory":"Bakery",
            "type":"Retail Goods"
        }
    ],
    "sg:phone":"+44 1228 526067",
    "sg:postcode":"CA1 3QB",
    "sg:province":"Cumbria",
    "sg:tags":[
        "shop",
        "baker"
    ],
    "wof:name":"H S Ruddick",
    "wof:placetype":"venue"
},
  "geometry": {"coordinates":[-2.9025781155,54.8819503784],"type":"Point"}
}