{
  "type": "Feature",
  "properties": {
    "iso:country":"GB",
    "sg:address":"The Rectory",
    "sg:city":"Edenbridge",
    "sg:classifiers":[
        {
            "category":"Place Of Worship",
            "type":"Public Place"
        }
    ],
    "sg:phone":"+44 1892 870478",
    "sg:postcode":"TN8 7AH",
    "sg:province":"East Sussex",
    "wof:name":"St Mary & St Luke Chiddingstone",
    "wof:placetype":"venue"
},
  "geometry": {"coordinates":[0.1115249991,51.1801872253],"type":"Point"}
}