{
  "type": "Feature",
  "properties": {
    "iso:country":"GB",
    "sg:address":"92 Trinity Rd",
    "sg:city":"Bridlington",
    "sg:classifiers":[
        {
            "category":"Social Services",
            "subcategory":"Retirement Home",
            "type":"Services"
        }
    ],
    "sg:postcode":"YO15 2HF",
    "sg:province":"East Riding of Yorkshire",
    "sg:tags":[
        "residential",
        "care"
    ],
    "wof:name":"Sydrene Residential Home",
    "wof:placetype":"venue"
},
  "geometry": {"coordinates":[-0.186355,54.087029],"type":"Point"}
}