{
  "type": "Feature",
  "properties": {
    "iso:country":"GB",
    "sg:address":"Rydal Mount, St Marys Terrace",
    "sg:city":"Gateshead",
    "sg:classifiers":[
        {
            "category":"Health Services",
            "subcategory":"Podiatrist",
            "type":"Services"
        }
    ],
    "sg:postcode":"NE10 0NY",
    "sg:province":"Tyne and Wear",
    "sg:tags":[
        "podiatrists",
        "chiropodist"
    ],
    "wof:name":"Deborah Richardson",
    "wof:placetype":"venue"
},
  "geometry": {"coordinates":[-1.5567690134,54.9507217407],"type":"Point"}
}