{
  "type": "Feature",
  "properties": {
    "iso:country":"GB",
    "sg:address":"1 Clapham Common, Clapham",
    "sg:city":"Worthing",
    "sg:classifiers":[
        {
            "category":"Building & Trades",
            "subcategory":"Equipment Rental",
            "type":"Services"
        }
    ],
    "sg:phone":"+44 1903 871249",
    "sg:postcode":"BN13 3UR",
    "sg:province":"West Sussex",
    "sg:tags":[
        "plant",
        "machinery"
    ],
    "wof:name":"Richard Kennard (Plant Hire) Ltd.",
    "wof:placetype":"venue"
},
  "geometry": {"coordinates":[-0.451104,50.841328],"type":"Point"}
}