{
  "type": "Feature",
  "properties": {
    "iso:country":"GB",
    "sg:address":"75 Emily Street",
    "sg:city":"West Bromwich",
    "sg:classifiers":[
        {
            "category":"Food & Beverages",
            "subcategory":"Liquor & Beverages",
            "type":"Retail Goods"
        }
    ],
    "sg:phone":"+44 121 553 1442",
    "sg:postcode":"B70 8LH",
    "sg:province":"West Midlands",
    "sg:tags":[
        "beer",
        "wine",
        "spirit",
        "wines"
    ],
    "wof:name":"The Corner Shop",
    "wof:placetype":"venue"
},
  "geometry": {"coordinates":[-2.0044019222,52.5142173767],"type":"Point"}
}