{
  "type": "Feature",
  "properties": {
    "iso:country":"GB",
    "sg:address":"44 Regent Street",
    "sg:city":"Blyth",
    "sg:classifiers":[
        {
            "category":"Professional",
            "subcategory":"Printing & Photocopies",
            "type":"Services"
        }
    ],
    "sg:postcode":"NE24 1LS",
    "sg:province":"Northumberland",
    "sg:tags":[
        "trophy"
    ],
    "wof:name":"L J Gunn",
    "wof:placetype":"venue"
},
  "geometry": {"coordinates":[-1.5106600523,55.1285972595],"type":"Point"}
}