{
  "type": "Feature",
  "properties": {
    "iso:country":"GB",
    "sg:address":"Stennack Surgery",
    "sg:city":"St Ives",
    "sg:classifiers":[
        {
            "category":"Health Services",
            "subcategory":"Clinic",
            "type":"Services"
        }
    ],
    "sg:phone":"+44 1736 576130",
    "sg:postcode":"TR26 1RU",
    "sg:province":"Cornwall",
    "sg:tags":[
        "nh"
    ],
    "wof:name":"St Ives Community Clinic",
    "wof:placetype":"venue"
},
  "geometry": {"coordinates":[-5.4857401848,50.2103614807],"type":"Point"}
}