{
  "type": "Feature",
  "properties": {
    "addr:full":"26 Pottery Lane, Wrecclesham Farnham Hampshire GU10 4QJ",
    "addr:housenumber":"26",
    "addr:postcode":"gu10 4qj",
    "addr:street":"Pottery Lane",
    "iso:country":"GB",
    "sg:address":"26 Pottery Lane, Wrecclesham",
    "sg:city":"Farnham",
    "sg:classifiers":[
        {
            "category":"Organizations",
            "subcategory":"Non-profit Organization",
            "type":"Services"
        }
    ],
    "sg:postcode":"GU10 4QJ",
    "sg:province":"Hampshire",
    "sg:tags":[
        "organisation",
        "animal",
        "welfare"
    ],
    "wof:name":"St.Bernards Rescue",
    "wof:placetype":"venue"
},
  "geometry": {"coordinates":[-0.8208580017,51.1955757141],"type":"Point"}
}