{
  "type": "Feature",
  "properties": {
    "iso:country":"GB",
    "sg:address":"Unit 5, Kay Gardens",
    "sg:city":"Bury",
    "sg:classifiers":[
        {
            "category":"Fast Food",
            "type":"Food & Drink"
        }
    ],
    "sg:phone":"+44 161 797 5448",
    "sg:postcode":"BL9 0BL",
    "sg:province":"Lancashire",
    "sg:tags":[
        "away",
        "take"
    ],
    "wof:name":"Burger King",
    "wof:placetype":"venue"
},
  "geometry": {"coordinates":[-2.2821440697,53.5994186401],"type":"Point"}
}