{
  "type": "Feature",
  "properties": {
    "addr:full":"Galliard Road London Greater London N9 7PB",
    "addr:postcode":"n9 7pb",
    "addr:street":"Galliard Road",
    "iso:country":"GB",
    "sg:address":"Galliard Road",
    "sg:city":"London",
    "sg:classifiers":[
        {
            "category":"Sports & Exercise",
            "subcategory":"Golf",
            "type":"Entertainment"
        }
    ],
    "sg:postcode":"N9 7PB",
    "sg:province":"Greater London",
    "sg:tags":[
        "club",
        "course"
    ],
    "wof:name":"Jubilee Pitch & Putt",
    "wof:placetype":"venue"
},
  "geometry": {"coordinates":[-0.0623149984,51.6359786987],"type":"Point"}
}