{
  "type": "Feature",
  "properties": {
    "addr:full":"The Knowes Kelso Scottish Borders TD5 7BH",
    "addr:postcode":"td5 7bh",
    "iso:country":"GB",
    "sg:address":"The Knowes",
    "sg:city":"Kelso",
    "sg:classifiers":[
        {
            "category":"Building & Trades",
            "subcategory":"Construction",
            "type":"Services"
        }
    ],
    "sg:phone":"+44 1573 224254",
    "sg:postcode":"TD5 7BH",
    "sg:province":"Scottish Borders",
    "sg:tags":[
        "joiner",
        "carpenter"
    ],
    "wof:name":"L C S Joinery",
    "wof:placetype":"venue"
},
  "geometry": {"coordinates":[-2.433349,55.597576],"type":"Point"}
}