{
  "type": "Feature",
  "properties": {
    "iso:country":"GB",
    "sg:address":"Old Sheriff Court Hope Street",
    "sg:city":"Falkirk",
    "sg:classifiers":[
        {
            "category":"Organizations",
            "subcategory":"Non-profit Organization",
            "type":"Services"
        }
    ],
    "sg:phone":"+44 1324 636571",
    "sg:postcode":"FK1 5AT",
    "sg:province":"Falkirk",
    "sg:tags":[
        "organisation",
        "voluntary",
        "charity"
    ],
    "wof:name":"Falkirk Voluntary Action Resource Centre",
    "wof:placetype":"venue"
},
  "geometry": {"coordinates":[-3.788329,56.002224],"type":"Point"}
}