{
  "type": "Feature",
  "properties": {
    "iso:country":"GB",
    "sg:address":"The Old Shipyard, Robinson Road",
    "sg:city":"Newhaven",
    "sg:classifiers":[
        {
            "category":"Manufacturing",
            "subcategory":"Glass & Minerals",
            "type":"Manufacturing & Wholesale Goods"
        }
    ],
    "sg:phone":"+44 1273 514814",
    "sg:postcode":"BN9 9BL",
    "sg:province":"East Sussex",
    "sg:tags":[
        "fibre",
        "moulding"
    ],
    "wof:name":"Replica Glass Fibre",
    "wof:placetype":"venue"
},
  "geometry": {"coordinates":[0.046175,50.795036],"type":"Point"}
}