{
  "type": "Feature",
  "properties": {
    "iso:country":"GB",
    "sg:address":"7 Whitby Street",
    "sg:city":"Hartlepool",
    "sg:classifiers":[
        {
            "category":"Military Area",
            "subcategory":"Air Force Base",
            "type":"Public Place"
        }
    ],
    "sg:phone":"+44 1429 233336",
    "sg:postcode":"TS24 7AD",
    "sg:province":"Durham",
    "sg:tags":[
        "taxi",
        "hire",
        "private"
    ],
    "wof:name":"Stripe Taxis Ltd.",
    "wof:placetype":"venue"
},
  "geometry": {"coordinates":[-1.2071939707,54.6856422424],"type":"Point"}
}