{
  "type": "Feature",
  "properties": {
    "addr:full":"The Warren, Warren Rd Worthing West Sussex BN14 9QD",
    "addr:postcode":"bn14 9qd",
    "addr:street":"Warren Rd",
    "iso:country":"GB",
    "sg:address":"The Warren, Warren Rd",
    "sg:city":"Worthing",
    "sg:classifiers":[
        {
            "category":"Professional",
            "subcategory":"Employment Agencies",
            "type":"Services"
        }
    ],
    "sg:postcode":"BN14 9QD",
    "sg:province":"West Sussex",
    "sg:tags":[
        "consultant"
    ],
    "wof:name":"Recruitment Facilities Management Consul",
    "wof:placetype":"venue"
},
  "geometry": {"coordinates":[-0.3827799857,50.8360710144],"type":"Point"}
}