{
  "type": "Feature",
  "properties": {
    "iso:country":"GB",
    "sg:address":"2nd Floor, Sevendale House, Dale Street",
    "sg:city":"Manchester",
    "sg:classifiers":[
        {
            "category":"Home & Garden",
            "subcategory":"Home Furnishings",
            "type":"Retail Goods"
        }
    ],
    "sg:phone":"+44 161 747 2318",
    "sg:postcode":"M1 1JB",
    "sg:province":"Greater Manchester",
    "sg:tags":[
        "homefurnishings"
    ],
    "wof:name":"Modern Living (U K) Ltd.",
    "wof:placetype":"venue"
},
  "geometry": {"coordinates":[-2.235449,53.482407],"type":"Point"}
}