{
  "type": "Feature",
  "properties": {
    "addr:full":"99 Cowick Street Exeter Devon EX4 1JF",
    "addr:housenumber":"99",
    "addr:postcode":"ex4 1jf",
    "addr:street":"Cowick Street",
    "iso:country":"GB",
    "sg:address":"99 Cowick Street",
    "sg:city":"Exeter",
    "sg:classifiers":[
        {
            "category":"Shopping",
            "subcategory":"Stationery & Office Supplies",
            "type":"Retail Goods"
        }
    ],
    "sg:phone":"+44 1392 271640",
    "sg:postcode":"EX4 1JF",
    "sg:province":"Devon",
    "wof:name":"Cowick Street Post Office",
    "wof:placetype":"venue"
},
  "geometry": {"coordinates":[-3.5466918945,50.7150192261],"type":"Point"}
}