{
  "type": "Feature",
  "properties": {
    "addr:full":"7 The Hill, Northfleet Gravesend Kent DA11 9EU",
    "addr:housenumber":"7",
    "addr:postcode":"da11 9eu",
    "addr:street":"The Hill Northfleet",
    "iso:country":"GB",
    "sg:address":"7 The Hill, Northfleet",
    "sg:city":"Gravesend",
    "sg:classifiers":[
        {
            "category":"Shopping",
            "subcategory":"Pharmacy",
            "type":"Retail Goods"
        }
    ],
    "sg:phone":"+44 1474 564615",
    "sg:postcode":"DA11 9EU",
    "sg:province":"Kent",
    "sg:tags":[
        "dispensing",
        "store",
        "pharmacist",
        "chemist",
        "drug"
    ],
    "wof:name":"Randhawa Chemist",
    "wof:placetype":"venue"
},
  "geometry": {"coordinates":[0.33626,51.443089],"type":"Point"}
}