{
  "type": "Feature",
  "properties": {
    "addr:full":"153 Goldsworth Road Woking Surrey GU21 6LS",
    "addr:housenumber":"153",
    "addr:postcode":"gu21 6ls",
    "addr:street":"Goldsworth Road",
    "iso:country":"GB",
    "sg:address":"153 Goldsworth Road",
    "sg:city":"Woking",
    "sg:classifiers":[
        {
            "category":"Professional",
            "subcategory":"Art Services",
            "type":"Services"
        }
    ],
    "sg:postcode":"GU21 6LS",
    "sg:province":"Surrey",
    "sg:tags":[
        "photographer"
    ],
    "wof:name":"John Clarke Photography",
    "wof:placetype":"venue"
},
  "geometry": {"coordinates":[-0.569396019,51.3173942566],"type":"Point"}
}