{
  "type": "Feature",
  "properties": {
    "iso:country":"GB",
    "sg:address":"266 Kimberworth Road",
    "sg:city":"Rotherham",
    "sg:classifiers":[
        {
            "category":"Health Services",
            "subcategory":"Dentist",
            "type":"Services"
        }
    ],
    "sg:phone":"+44 1709 559189",
    "sg:postcode":"S61 1HG",
    "sg:province":"South Yorkshire",
    "sg:tags":[
        "technician",
        "dental"
    ],
    "wof:name":"Walton Ceramics",
    "wof:placetype":"venue"
},
  "geometry": {"coordinates":[-1.3864359856,53.4328308105],"type":"Point"}
}