{
  "type": "Feature",
  "properties": {
    "addr:full":"39 West Street, Oundle Peterborough Cambridgeshire PE8 4EJ",
    "addr:housenumber":"39",
    "addr:postcode":"pe8 4ej",
    "addr:street":"West Street",
    "iso:country":"GB",
    "sg:address":"39 West Street, Oundle",
    "sg:city":"Peterborough",
    "sg:classifiers":[
        {
            "category":"Shopping",
            "subcategory":"Thrift Store",
            "type":"Retail Goods"
        }
    ],
    "sg:phone":"+44 1832 274276",
    "sg:postcode":"PE8 4EJ",
    "sg:province":"Cambridgeshire",
    "sg:tags":[
        "shop",
        "charity"
    ],
    "wof:name":"Oxfam",
    "wof:placetype":"venue"
},
  "geometry": {"coordinates":[-0.470879,52.480965],"type":"Point"}
}