{
  "type": "Feature",
  "properties": {
    "addr:full":"Hall Green Road Coventry Warwickshire CV6 7BS",
    "addr:postcode":"cv6 7bs",
    "addr:street":"Green Road",
    "iso:country":"GB",
    "sg:address":"Hall Green Road",
    "sg:city":"Coventry",
    "sg:classifiers":[
        {
            "category":"Bars & Pubs",
            "type":"Food & Drink"
        }
    ],
    "sg:phone":"+44 24 7666 7630",
    "sg:postcode":"CV6 7BS",
    "sg:province":"Warwickshire",
    "sg:tags":[
        "pubs",
        "inn"
    ],
    "wof:name":"The Green Man",
    "wof:placetype":"venue"
},
  "geometry": {"coordinates":[-1.475436,52.440201],"type":"Point"}
}