{
  "type": "Feature",
  "properties": {
    "addr:full":"Unit 6, Clarendon Dr, Wymbush Milton Keynes Buckinghamshire MK8 8DA",
    "addr:housenumber":"unit 6",
    "addr:postcode":"mk8 8da",
    "addr:street":"Clarendon Dr",
    "iso:country":"GB",
    "sg:address":"Unit 6, Clarendon Dr, Wymbush",
    "sg:city":"Milton Keynes",
    "sg:classifiers":[
        {
            "category":"Wholesale",
            "subcategory":"Furniture",
            "type":"Manufacturing & Wholesale Goods"
        }
    ],
    "sg:phone":"+44 1908 262822",
    "sg:postcode":"MK8 8DA",
    "sg:province":"Buckinghamshire",
    "sg:tags":[
        "shop",
        "fitting"
    ],
    "wof:name":"P O S Group Ltd (The)",
    "wof:placetype":"venue"
},
  "geometry": {"coordinates":[-0.7945600152,52.0408706665],"type":"Point"}
}