{
  "type": "Feature",
  "properties": {
    "addr:full":"25 Quarry Road Tunbridge Wells Kent TN1 2EY",
    "addr:housenumber":"25",
    "addr:postcode":"tn1 2ey",
    "addr:street":"Quarry Road",
    "iso:country":"GB",
    "sg:address":"25 Quarry Road",
    "sg:city":"Tunbridge Wells",
    "sg:classifiers":[
        {
            "category":"Shopping",
            "subcategory":"Comic Books",
            "type":"Retail Goods"
        }
    ],
    "sg:postcode":"TN1 2EY",
    "sg:province":"Kent",
    "sg:tags":[
        "jeweller"
    ],
    "wof:name":"John Fenton Jewellers",
    "wof:placetype":"venue"
},
  "geometry": {"coordinates":[0.270848006,51.1402893066],"type":"Point"}
}