{
  "type": "Feature",
  "properties": {
    "iso:country":"GB",
    "sg:address":"67 Church End, Renhold",
    "sg:city":"Bedford",
    "sg:classifiers":[
        {
            "category":"Farming",
            "subcategory":"Livestock Farm",
            "type":"Manufacturing & Wholesale Goods"
        }
    ],
    "sg:phone":"+44 1234 771215",
    "sg:postcode":"MK41 0LX",
    "sg:province":"Bedfordshire",
    "sg:tags":[
        "others"
    ],
    "wof:name":"W R Kerrison",
    "wof:placetype":"venue"
},
  "geometry": {"coordinates":[-0.4068520069,52.1631088257],"type":"Point"}
}