{
  "type": "Feature",
  "properties": {
    "addr:full":"9 Mepham Street, Harrow Weald Harrow Greater London HA3 6AH",
    "addr:housenumber":"9",
    "addr:postcode":"ha3 6ah",
    "addr:street":"Mepham Street",
    "iso:country":"GB",
    "sg:address":"9 Mepham Street, Harrow Weald",
    "sg:city":"Harrow",
    "sg:classifiers":[
        {
            "category":"Professional",
            "subcategory":"Art Services",
            "type":"Services"
        }
    ],
    "sg:phone":"+44 20 8427 9181",
    "sg:postcode":"HA3 6AH",
    "sg:province":"Greater London",
    "sg:tags":[
        "graphic",
        "designer"
    ],
    "wof:name":"Cut & Paste Design",
    "wof:placetype":"venue"
},
  "geometry": {"coordinates":[-0.3485000134,51.6086082458],"type":"Point"}
}