{
  "type": "Feature",
  "properties": {
    "addr:full":"The Vicarage, Bedford Road Bedford Bedfordshire MK44 3SS",
    "addr:postcode":"mk44 3ss",
    "addr:street":"Bedford Road",
    "iso:country":"GB",
    "sg:address":"The Vicarage, Bedford Road",
    "sg:city":"Bedford",
    "sg:classifiers":[
        {
            "category":"Place Of Worship",
            "type":"Public Place"
        }
    ],
    "sg:postcode":"MK44 3SS",
    "sg:province":"Bedfordshire",
    "wof:name":"St.Mary C of E Church",
    "wof:placetype":"venue"
},
  "geometry": {"coordinates":[-0.41695,52.120178],"type":"Point"}
}