{
  "type": "Feature",
  "properties": {
    "addr:full":"22b Front Street, Framwellgate Moor Durham Durham DH1 5EJ",
    "addr:housenumber":"22b",
    "addr:postcode":"dh1 5ej",
    "addr:street":"Front Street",
    "iso:country":"GB",
    "sg:address":"22b Front Street, Framwellgate Moor",
    "sg:city":"Durham",
    "sg:classifiers":[
        {
            "category":"Health Services",
            "subcategory":"Optometrist",
            "type":"Services"
        }
    ],
    "sg:phone":"+44 191 386 0734",
    "sg:postcode":"DH1 5EJ",
    "sg:province":"Durham",
    "sg:tags":[
        "optician"
    ],
    "wof:name":"L J Robley",
    "wof:placetype":"venue"
},
  "geometry": {"coordinates":[-1.590452,54.795113],"type":"Point"}
}