{
  "type": "Feature",
  "properties": {
    "addr:full":"Elm Gro Lane Steyning West Sussex BN44 3SA",
    "addr:postcode":"bn44 3sa",
    "addr:street":"Gro Lane",
    "iso:country":"GB",
    "sg:address":"Elm Gro Lane",
    "sg:city":"Steyning",
    "sg:classifiers":[
        {
            "category":"Shopping",
            "subcategory":"Computers & Home Electronics",
            "type":"Retail Goods"
        }
    ],
    "sg:phone":"+44 1903 817200",
    "sg:postcode":"BN44 3SA",
    "sg:province":"West Sussex",
    "sg:tags":[
        "hi-fi",
        "equipment",
        "mnfr"
    ],
    "wof:name":"B & W Loudspeakers",
    "wof:placetype":"venue"
},
  "geometry": {"coordinates":[-0.3177250028,50.8827972412],"type":"Point"}
}