{
  "type": "Feature",
  "properties": {
    "addr:full":"30 Osborn Road Fareham Hampshire PO16 7DS",
    "addr:housenumber":"30",
    "addr:postcode":"po16 7ds",
    "addr:street":"Osborn Road",
    "iso:country":"GB",
    "sg:address":"30 Osborn Road",
    "sg:city":"Fareham",
    "sg:classifiers":[
        {
            "category":"Health Services",
            "subcategory":"Chiropractor",
            "type":"Services"
        }
    ],
    "sg:phone":"+44 1329 280283",
    "sg:postcode":"PO16 7DS",
    "sg:province":"Hampshire",
    "wof:name":"Homewood Chiropractic (Fareham) Ltd.",
    "wof:placetype":"venue"
},
  "geometry": {"coordinates":[-1.1789799929,50.8549842834],"type":"Point"}
}