{
  "type": "Feature",
  "properties": {
    "iso:country":"GB",
    "sg:address":"Unit 2",
    "sg:city":"High Wycombe",
    "sg:classifiers":[
        {
            "category":"Building & Trades",
            "subcategory":"Construction",
            "type":"Services"
        }
    ],
    "sg:phone":"+44 1494 441416",
    "sg:postcode":"HP11 1RY",
    "sg:province":"Buckinghamshire",
    "sg:tags":[
        "heating",
        "contractor"
    ],
    "wof:name":"Heat Industrial Ltd.",
    "wof:placetype":"venue"
},
  "geometry": {"coordinates":[-0.757569015,51.6193733215],"type":"Point"}
}