{
  "type": "Feature",
  "properties": {
    "addr:full":"117 Winchester Avenue London Greater London NW9 9TB",
    "addr:housenumber":"117",
    "addr:postcode":"nw9 9tb",
    "addr:street":"Winchester Avenue",
    "iso:country":"GB",
    "sg:address":"117 Winchester Avenue",
    "sg:city":"London",
    "sg:classifiers":[
        {
            "category":"Professional",
            "subcategory":"Art Services",
            "type":"Services"
        }
    ],
    "sg:postcode":"NW9 9TB",
    "sg:province":"Greater London",
    "sg:tags":[
        "model",
        "maker"
    ],
    "wof:name":"N J W Gaffney",
    "wof:placetype":"venue"
},
  "geometry": {"coordinates":[-0.281774,51.59251],"type":"Point"}
}