{
  "type": "Feature",
  "properties": {
    "addr:full":"Cwmllynfe Isaf Llanwrda Carmarthenshire SA19 8BY",
    "addr:postcode":"sa19 8by",
    "iso:country":"GB",
    "sg:address":"Cwmllynfe Isaf",
    "sg:city":"Llanwrda",
    "sg:classifiers":[
        {
            "category":"Farming",
            "subcategory":"Livestock Farm",
            "type":"Manufacturing & Wholesale Goods"
        }
    ],
    "sg:phone":"+44 1550 777589",
    "sg:postcode":"SA19 8BY",
    "sg:province":"Carmarthenshire",
    "sg:tags":[
        "others"
    ],
    "wof:name":"T R Powell",
    "wof:placetype":"venue"
},
  "geometry": {"coordinates":[-3.874174118,51.9666900635],"type":"Point"}
}