{
  "type": "Feature",
  "properties": {
    "iso:country":"GB",
    "sg:address":"44 Cleveley Road",
    "sg:city":"Wirral",
    "sg:classifiers":[
        {
            "category":"Building & Trades",
            "subcategory":"Construction",
            "type":"Services"
        }
    ],
    "sg:postcode":"CH47 8XR",
    "sg:province":"Merseyside",
    "sg:tags":[
        "roofing",
        "contracting"
    ],
    "wof:name":"James A Musker",
    "wof:placetype":"venue"
},
  "geometry": {"coordinates":[-3.152323,53.401379],"type":"Point"}
}