{
  "type": "Feature",
  "properties": {
    "addr:full":"49 High Street Wellington Devon TA21 8QY",
    "addr:housenumber":"49",
    "addr:postcode":"ta21 8qy",
    "addr:street":"High Street",
    "iso:country":"GB",
    "sg:address":"49 High Street",
    "sg:city":"Wellington",
    "sg:classifiers":[
        {
            "category":"Health Services",
            "subcategory":"Optometrist",
            "type":"Services"
        }
    ],
    "sg:postcode":"TA21 8QY",
    "sg:province":"Devon",
    "sg:tags":[
        "optician"
    ],
    "wof:name":"John Askew Opticians",
    "wof:placetype":"venue"
},
  "geometry": {"coordinates":[-3.2258639336,50.9800262451],"type":"Point"}
}