{
  "type": "Feature",
  "properties": {
    "addr:full":"34 Earlstoke Clo Banbury Oxfordshire OX16 7WL",
    "addr:housenumber":"34",
    "addr:postcode":"ox16 7wl",
    "addr:street":"Earlstoke Clo",
    "iso:country":"GB",
    "sg:address":"34 Earlstoke Clo",
    "sg:city":"Banbury",
    "sg:classifiers":[
        {
            "category":"Utilities",
            "type":"Services"
        }
    ],
    "sg:phone":"+44 1295 273551",
    "sg:postcode":"OX16 7WL",
    "sg:province":"Oxfordshire",
    "sg:tags":[
        "internet"
    ],
    "wof:name":"Retarius",
    "wof:placetype":"venue"
},
  "geometry": {"coordinates":[-1.326926,52.070618],"type":"Point"}
}