{
  "type": "Feature",
  "properties": {
    "addr:full":"1 Everard Glade Sheffield Derbyshire S17 4NG",
    "addr:housenumber":"1",
    "addr:postcode":"s17 4ng",
    "addr:street":"Everard Glade",
    "iso:country":"GB",
    "sg:address":"1 Everard Glade",
    "sg:city":"Sheffield",
    "sg:classifiers":[
        {
            "category":"Building & Trades",
            "subcategory":"Construction",
            "type":"Services"
        }
    ],
    "sg:postcode":"S17 4NG",
    "sg:province":"Derbyshire",
    "sg:tags":[
        "joiner",
        "carpenter"
    ],
    "wof:name":"Rodgers Joinery",
    "wof:placetype":"venue"
},
  "geometry": {"coordinates":[-1.515954,53.31913],"type":"Point"}
}