{
  "type": "Feature",
  "properties": {
    "addr:full":"16 Nascot Rd Watford Hertfordshire WD1 3RE",
    "addr:housenumber":"16",
    "addr:postcode":"wd1 3re",
    "addr:street":"Nascot Rd",
    "iso:country":"GB",
    "sg:address":"16 Nascot Rd",
    "sg:city":"Watford",
    "sg:classifiers":[
        {
            "category":"Place Of Worship",
            "type":"Public Place"
        },
        {
            "category":"Organizations",
            "subcategory":"Religious Organization",
            "type":"Services"
        }
    ],
    "sg:phone":"+44 1923 222755",
    "sg:postcode":"WD1 3RE",
    "sg:province":"Hertfordshire",
    "sg:tags":[
        "organisation"
    ],
    "wof:name":"Watford & District Synagogue",
    "wof:placetype":"venue"
},
  "geometry": {"coordinates":[-0.400898993,51.6654663086],"type":"Point"}
}