{
  "type": "Feature",
  "properties": {
    "addr:full":"High Street, Porlock Minehead Somerset TA24 8PY",
    "addr:postcode":"ta24 8py",
    "addr:street":"High Street",
    "iso:country":"GB",
    "sg:address":"High Street, Porlock",
    "sg:city":"Minehead",
    "sg:classifiers":[
        {
            "category":"Professional",
            "subcategory":"Art Services",
            "type":"Services"
        }
    ],
    "sg:phone":"+44 1643 862238",
    "sg:postcode":"TA24 8PY",
    "sg:province":"Somerset",
    "sg:tags":[
        "picture",
        "framing"
    ],
    "wof:name":"Millwheel Gallery",
    "wof:placetype":"venue"
},
  "geometry": {"coordinates":[-3.5929949284,51.2094116211],"type":"Point"}
}