{
  "type": "Feature",
  "properties": {
    "addr:full":"142 Saltdean Vale, Saltdean Brighton East Sussex BN2 8HF",
    "addr:housenumber":"142",
    "addr:postcode":"bn2 8hf",
    "addr:street":"Saltdean Vale Saltdean",
    "iso:country":"GB",
    "sg:address":"142 Saltdean Vale, Saltdean",
    "sg:city":"Brighton",
    "sg:classifiers":[
        {
            "category":"Government",
            "subcategory":"Fire Station",
            "type":"Public Place"
        }
    ],
    "sg:phone":"+44 1273 301303",
    "sg:postcode":"BN2 8HF",
    "sg:province":"East Sussex",
    "sg:tags":[
        "security"
    ],
    "wof:name":"Sovereign Alarms",
    "wof:placetype":"venue"
},
  "geometry": {"coordinates":[-0.034352,50.812092],"type":"Point"}
}