{
  "type": "Feature",
  "properties": {
    "addr:full":"8 The Millrough, Primrose Hill Lydney Gloucestershire GL15 5TE",
    "addr:housenumber":"8",
    "addr:postcode":"gl15 5te",
    "addr:street":"The Millrough",
    "iso:country":"GB",
    "sg:address":"8 The Millrough, Primrose Hill",
    "sg:city":"Lydney",
    "sg:classifiers":[
        {
            "category":"Building & Trades",
            "subcategory":"Construction",
            "type":"Services"
        }
    ],
    "sg:postcode":"GL15 5TE",
    "sg:province":"Gloucestershire",
    "sg:tags":[
        "builder"
    ],
    "wof:name":"Snook,Brian J & Neil J,",
    "wof:placetype":"venue"
},
  "geometry": {"coordinates":[-2.5358190536,51.7244911194],"type":"Point"}
}