{
  "type": "Feature",
  "properties": {
    "addr:full":"25 Hullbridge Road, South Woodham Ferrers Chelmsford Essex CM3 5PL",
    "addr:housenumber":"25",
    "addr:postcode":"cm3 5pl",
    "addr:street":"Hullbridge Road",
    "iso:country":"GB",
    "sg:address":"25 Hullbridge Road, South Woodham Ferrers",
    "sg:city":"Chelmsford",
    "sg:classifiers":[
        {
            "category":"Government",
            "subcategory":"City Hall",
            "type":"Public Place"
        },
        {
            "category":"Retail",
            "subcategory":"Event Space",
            "type":"Services"
        }
    ],
    "sg:phone":"+44 1245 325568",
    "sg:postcode":"CM3 5PL",
    "sg:province":"Essex",
    "sg:tags":[
        "function",
        "hire",
        "room"
    ],
    "wof:name":"South Woodham Ferrers Village Hall",
    "wof:placetype":"venue"
},
  "geometry": {"coordinates":[0.6068639755,51.6514396667],"type":"Point"}
}