{
  "type": "Feature",
  "properties": {
    "addr:full":"30 Watergate St Chester Cheshire CH1 2LA",
    "addr:housenumber":"30",
    "addr:postcode":"ch1 2la",
    "addr:street":"Watergate St",
    "iso:country":"GB",
    "sg:address":"30 Watergate St",
    "sg:city":"Chester",
    "sg:classifiers":[
        {
            "category":"Professional",
            "type":"Services"
        }
    ],
    "sg:phone":"+44 1244 312300",
    "sg:postcode":"CH1 2LA",
    "sg:province":"Cheshire",
    "sg:tags":[
        "auctioneer"
    ],
    "wof:name":"Boothman of Chester",
    "wof:placetype":"venue"
},
  "geometry": {"coordinates":[-2.892981,53.190235],"type":"Point"}
}