{
  "type": "Feature",
  "properties": {
    "addr:full":"11 St Johns Pavement, Grange Precinct Birkenhead Merseyside L41 2YB",
    "addr:housenumber":"11",
    "addr:postcode":"l41 2yb",
    "addr:street":"St Johns Pavement;Precinct",
    "iso:country":"GB",
    "sg:address":"11 St Johns Pavement, Grange Precinct",
    "sg:city":"Birkenhead",
    "sg:classifiers":[
        {
            "category":"Banks & Credit Unions",
            "subcategory":"Financial Services",
            "type":"Services"
        }
    ],
    "sg:phone":"+44 151 647 8447",
    "sg:postcode":"L41 2YB",
    "sg:province":"Merseyside",
    "sg:tags":[
        "building",
        "society"
    ],
    "wof:name":"Birmingham Midshires",
    "wof:placetype":"venue"
},
  "geometry": {"coordinates":[-3.02549,53.392559],"type":"Point"}
}