{
  "type": "Feature",
  "properties": {
    "iso:country":"GB",
    "sg:address":"Davington House, Chepstow Road",
    "sg:city":"Usk",
    "sg:classifiers":[
        {
            "category":"Wholesale",
            "subcategory":"Chemicals & Plastics",
            "type":"Manufacturing & Wholesale Goods"
        },
        {
            "category":"Retail",
            "subcategory":"Event Space",
            "type":"Services"
        }
    ],
    "sg:phone":"+44 1291 672565",
    "sg:postcode":"NP15 1BL",
    "sg:province":"Monmouthshire",
    "sg:tags":[
        "refrigerator",
        "product",
        "electrical",
        "sales",
        "freezer"
    ],
    "wof:name":"U S K REFRIGERATION SERVICE",
    "wof:placetype":"venue"
},
  "geometry": {"coordinates":[-2.895208,51.703705],"type":"Point"}
}