{
  "type": "Feature",
  "properties": {
    "iso:country":"GB",
    "sg:address":"Ayr Rd",
    "sg:city":"Ayr",
    "sg:classifiers":[
        {
            "category":"Health Services",
            "subcategory":"Nursing And Care Facility",
            "type":"Services"
        }
    ],
    "sg:phone":"+44 1292 531658",
    "sg:postcode":"KA6 7LP",
    "sg:province":"East Ayrshire",
    "sg:tags":[
        "home"
    ],
    "wof:name":"Burnfoot Nursing Home",
    "wof:placetype":"venue"
},
  "geometry": {"coordinates":[-4.4988598824,55.3647613525],"type":"Point"}
}