{
  "type": "Feature",
  "properties": {
    "addr:full":"Brighton Rd Banstead Surrey SM7 1AT",
    "addr:postcode":"sm7 1at",
    "addr:street":"Brighton Rd",
    "iso:country":"GB",
    "sg:address":"Brighton Rd",
    "sg:city":"Banstead",
    "sg:classifiers":[
        {
            "category":"Bars & Pubs",
            "type":"Food & Drink"
        }
    ],
    "sg:phone":"+44 1737 215687",
    "sg:postcode":"SM7 1AT",
    "sg:province":"Surrey",
    "sg:tags":[
        "pubs",
        "inn"
    ],
    "wof:name":"Wheatsheaf Inn",
    "wof:placetype":"venue"
},
  "geometry": {"coordinates":[-0.212074995,51.31407547],"type":"Point"}
}