{
  "type": "Feature",
  "properties": {
    "addr:full":"8 Springfield Rd, Off Feltham Rd, Erdington Birmingham West Midlands B23 6AT",
    "addr:housenumber":"8",
    "addr:postcode":"b23 6at",
    "addr:street":"Springfield Rd Off Feltham Rd",
    "iso:country":"GB",
    "sg:address":"8 Springfield Rd, Off Feltham Rd, Erdington",
    "sg:city":"Birmingham",
    "sg:classifiers":[
        {
            "category":"Building & Trades",
            "subcategory":"Construction",
            "type":"Services"
        }
    ],
    "sg:postcode":"B23 6AT",
    "sg:province":"West Midlands",
    "sg:tags":[
        "flooring"
    ],
    "wof:name":"Nicholl Ramsay Ltd",
    "wof:placetype":"venue"
},
  "geometry": {"coordinates":[-1.8535439968,52.518989563],"type":"Point"}
}