{
  "type": "Feature",
  "properties": {
    "iso:country":"GB",
    "sg:address":"777 Old Kent Road",
    "sg:city":"London",
    "sg:classifiers":[
        {
            "category":"Shopping",
            "subcategory":"Mobile Phones",
            "type":"Retail Goods"
        }
    ],
    "sg:phone":"+44 20 7639 1329",
    "sg:postcode":"SE15 1NZ",
    "sg:province":"Greater London",
    "wof:name":"The Carphone Warehouse Ltd.",
    "wof:placetype":"venue"
},
  "geometry": {"coordinates":[-0.058407,51.480381],"type":"Point"}
}