{
  "type": "Feature",
  "properties": {
    "addr:full":"44 Paul Street London Greater London EC2A 4TR",
    "addr:housenumber":"44",
    "addr:postcode":"ec2a 4tr",
    "addr:street":"Paul Street",
    "iso:country":"GB",
    "sg:address":"44 Paul Street",
    "sg:city":"London",
    "sg:classifiers":[
        {
            "category":"Professional",
            "subcategory":"Computer Services",
            "type":"Services"
        }
    ],
    "sg:phone":"+44 20 7739 9635",
    "sg:postcode":"EC2A 4TR",
    "sg:province":"Greater London",
    "sg:tags":[
        "information"
    ],
    "wof:name":"Innodata Processing Corp",
    "wof:placetype":"venue"
},
  "geometry": {"coordinates":[-0.0841950029,51.5237464905],"type":"Point"}
}