{
  "type": "Feature",
  "properties": {
    "iso:country":"GB",
    "sg:address":"Brian's Farm Fayre, 21 Union Street",
    "sg:city":"Bacup",
    "sg:classifiers":[
        {
            "category":"Deli",
            "type":"Food & Drink"
        }
    ],
    "sg:phone":"+44 1706 873232",
    "sg:postcode":"OL13 0AA",
    "sg:province":"Lancashire",
    "sg:tags":[
        "delicatessen"
    ],
    "wof:name":"Brian's Farm Fayre",
    "wof:placetype":"venue"
},
  "geometry": {"coordinates":[-2.200894,53.702408],"type":"Point"}
}