{
  "type": "Feature",
  "properties": {
    "iso:country":"GB",
    "sg:address":"23 Church Street",
    "sg:city":"Godalming",
    "sg:classifiers":[
        {
            "category":"Shopping",
            "subcategory":"Clothing, Apparel, & Fashions",
            "type":"Retail Goods"
        },
        {
            "category":"Shopping",
            "subcategory":"Discount & Variety Stores",
            "type":"Retail Goods"
        }
    ],
    "sg:phone":"+44 1483 414042",
    "sg:postcode":"GU7 1EL",
    "sg:province":"Surrey",
    "sg:tags":[
        "hire",
        "rental",
        "menswear"
    ],
    "wof:name":"Anthony Hirewear",
    "wof:placetype":"venue"
},
  "geometry": {"coordinates":[-0.61585,51.186428],"type":"Point"}
}