{
  "type": "Feature",
  "properties": {
    "addr:full":"30-32 Effingham Street Rotherham South Yorkshire S65 1AJ",
    "addr:housenumber":"30-32",
    "addr:postcode":"s65 1aj",
    "addr:street":"Effingham Street",
    "iso:country":"GB",
    "sg:address":"30-32 Effingham Street",
    "sg:city":"Rotherham",
    "sg:classifiers":[
        {
            "category":"Banks & Credit Unions",
            "subcategory":"Bureau De Change",
            "type":"Services"
        }
    ],
    "sg:phone":"+44 1709 365433",
    "sg:postcode":"S65 1AJ",
    "sg:province":"South Yorkshire",
    "wof:name":"Eurochange",
    "wof:placetype":"venue"
},
  "geometry": {"coordinates":[-1.354809,53.4338],"type":"Point"}
}