{
  "type": "Feature",
  "properties": {
    "addr:full":"Unit 10, Waterside Industrial Estate London Greater London W7 2QA",
    "addr:housenumber":"unit 10",
    "addr:postcode":"w7 2qa",
    "addr:street":"Waterside Industrial Estate",
    "iso:country":"GB",
    "sg:address":"Unit 10, Waterside Industrial Estate",
    "sg:city":"London",
    "sg:classifiers":[
        {
            "category":"Shopping",
            "subcategory":"Computers & Home Electronics",
            "type":"Retail Goods"
        }
    ],
    "sg:phone":"+44 20 8571 9040",
    "sg:postcode":"W7 2QA",
    "sg:province":"Greater London",
    "sg:tags":[
        "electrical"
    ],
    "wof:name":"West London Electrical Wholesale Ltd.",
    "wof:placetype":"venue"
},
  "geometry": {"coordinates":[-0.33696,51.501518],"type":"Point"}
}