{
  "type": "Feature",
  "properties": {
    "addr:full":"8 Kinglake Court Woking Surrey GU21 1AL",
    "addr:housenumber":"8",
    "addr:postcode":"gu21 1al",
    "addr:street":"Kinglake Court",
    "iso:country":"GB",
    "sg:address":"8 Kinglake Court",
    "sg:city":"Woking",
    "sg:classifiers":[
        {
            "category":"Real Estate",
            "subcategory":"Real Estate Agent",
            "type":"Services"
        }
    ],
    "sg:phone":"+44 1483 486838",
    "sg:postcode":"GU21 1AL",
    "sg:province":"Surrey",
    "wof:name":"Stella White",
    "wof:placetype":"venue"
},
  "geometry": {"coordinates":[-0.603314,51.316448],"type":"Point"}
}