{
  "type": "Feature",
  "properties": {
    "iso:country":"GB",
    "sg:address":"Maidstone Road",
    "sg:city":"Leicester",
    "sg:classifiers":[
        {
            "category":"Community Center",
            "type":"Public Place"
        }
    ],
    "sg:phone":"+44 116 221 1793",
    "sg:postcode":"LE2 0UA",
    "sg:province":"Leicestershire",
    "sg:tags":[
        "recreation",
        "leisure",
        "centre"
    ],
    "wof:name":"African Caribbean Centre",
    "wof:placetype":"venue"
},
  "geometry": {"coordinates":[-1.117532,52.635372],"type":"Point"}
}