{
  "type": "Feature",
  "properties": {
    "iso:country":"GB",
    "sg:address":"Unit B, Dewhurst Row, Cuerden Mill, Bamber Bridge",
    "sg:city":"Preston",
    "sg:classifiers":[
        {
            "category":"Shopping",
            "type":"Retail Goods"
        }
    ],
    "sg:phone":"+44 1772 334424",
    "sg:postcode":"PR5 6BB",
    "sg:province":"Lancashire",
    "sg:tags":[
        "part",
        "accessory"
    ],
    "wof:name":"Beetle Bits",
    "wof:placetype":"venue"
},
  "geometry": {"coordinates":[-2.660569,53.727764],"type":"Point"}
}