{
  "type": "Feature",
  "properties": {
    "iso:country":"GB",
    "sg:address":"Gardner Street",
    "sg:city":"Glasgow",
    "sg:classifiers":[
        {
            "category":"Home & Garden",
            "subcategory":"Carpets & Floor Coverings",
            "type":"Retail Goods"
        }
    ],
    "sg:phone":"+44 141 334 9365",
    "sg:postcode":"G11 5NG",
    "sg:province":"Glasgow City",
    "sg:tags":[
        "carpets",
        "rug",
        "matting"
    ],
    "wof:name":"Highmead Carpets",
    "wof:placetype":"venue"
},
  "geometry": {"coordinates":[-4.242511,55.857807],"type":"Point"}
}