{
  "type": "Feature",
  "properties": {
    "addr:full":"2 Westmead Cottages, Loves Lane Bath Somerset BA2 0AZ",
    "addr:housenumber":"2",
    "addr:postcode":"ba2 0az",
    "addr:street":"Westmead Cottages Loves Lane",
    "iso:country":"GB",
    "sg:address":"2 Westmead Cottages, Loves Lane",
    "sg:city":"Bath",
    "sg:classifiers":[
        {
            "category":"Manufacturing",
            "subcategory":"Petroleum Products",
            "type":"Manufacturing & Wholesale Goods"
        },
        {
            "category":"Building & Trades",
            "subcategory":"Construction",
            "type":"Services"
        }
    ],
    "sg:phone":"+44 1761 471958",
    "sg:postcode":"BA2 0AZ",
    "sg:province":"Somerset",
    "sg:tags":[
        "double",
        "glazing",
        "installers"
    ],
    "wof:name":"Window Vision",
    "wof:placetype":"venue"
},
  "geometry": {"coordinates":[-2.4975,51.343578],"type":"Point"}
}