{
  "type": "Feature",
  "properties": {
    "addr:full":"274 Wellingborough Road Northampton Northamptonshire NN1 4EJ",
    "addr:housenumber":"274",
    "addr:postcode":"nn1 4ej",
    "addr:street":"Wellingborough Road",
    "iso:country":"GB",
    "sg:address":"274 Wellingborough Road",
    "sg:city":"Northampton",
    "sg:classifiers":[
        {
            "category":"Shopping",
            "subcategory":"Bicycles & Sporting Goods",
            "type":"Retail Goods"
        }
    ],
    "sg:phone":"+44 1604 639383",
    "sg:postcode":"NN1 4EJ",
    "sg:province":"Northamptonshire",
    "sg:tags":[
        "cycle",
        "accessory"
    ],
    "wof:name":"Lawes Ltd.",
    "wof:placetype":"venue"
},
  "geometry": {"coordinates":[-0.8748660088,52.2422828674],"type":"Point"}
}