{
  "type": "Feature",
  "properties": {
    "iso:country":"GB",
    "sg:address":"Stroke Rehabilitation Unit, Carshalton War Memorial Hospital",
    "sg:city":"Carshalton",
    "sg:classifiers":[
        {
            "category":"Government",
            "subcategory":"Office",
            "type":"Public Place"
        }
    ],
    "sg:phone":"+44 20 8669 7221",
    "sg:postcode":"SM5 3DB",
    "sg:province":"Surrey",
    "sg:tags":[
        "project",
        "gov",
        "community"
    ],
    "wof:name":"Merton & Sutton Community NHS Trust",
    "wof:placetype":"venue"
},
  "geometry": {"coordinates":[-0.161094,51.365288],"type":"Point"}
}