{
  "type": "Feature",
  "properties": {
    "addr:full":"Clayside House Sheltered Hsng, Kenton Court South Shields Tyne and Wear NE33 4HP",
    "addr:postcode":"ne33 4hp",
    "addr:street":"Kenton Court",
    "iso:country":"GB",
    "sg:address":"Clayside House Sheltered Hsng, Kenton Court",
    "sg:city":"South Shields",
    "sg:classifiers":[
        {
            "category":"Government",
            "subcategory":"Office",
            "type":"Public Place"
        }
    ],
    "sg:phone":"+44 191 456 4319",
    "sg:postcode":"NE33 4HP",
    "sg:province":"Tyne and Wear",
    "sg:tags":[
        "local"
    ],
    "wof:name":"South Tyneside Metropolitan Borough Council Clayside House Housin",
    "wof:placetype":"venue"
},
  "geometry": {"coordinates":[-1.4303489923,54.9855690002],"type":"Point"}
}