{
  "type": "Feature",
  "properties": {
    "iso:country":"GB",
    "sg:address":"Telford Racquet And Fitness Club, St Quentin Gate",
    "sg:city":"Telford",
    "sg:classifiers":[
        {
            "category":"Arena",
            "subcategory":"Sports Club",
            "type":"Entertainment"
        }
    ],
    "sg:phone":"+44 1952 291997",
    "sg:postcode":"TF3 4JH",
    "sg:province":"Shropshire",
    "wof:name":"L T A West Midlands Area Office",
    "wof:placetype":"venue"
},
  "geometry": {"coordinates":[-2.44176507,52.6766624451],"type":"Point"}
}