{
  "type": "Feature",
  "properties": {
    "addr:full":"East Grange, Station House, Blairhall Dunfermline Fife KY12 9PY",
    "addr:postcode":"ky12 9py",
    "addr:street":"East Grange;Blairhall",
    "iso:country":"GB",
    "sg:address":"East Grange, Station House, Blairhall",
    "sg:city":"Dunfermline",
    "sg:classifiers":[
        {
            "category":"Building & Trades",
            "subcategory":"Construction",
            "type":"Services"
        }
    ],
    "sg:phone":"+44 1383 850458",
    "sg:postcode":"KY12 9PY",
    "sg:province":"Fife",
    "sg:tags":[
        "roofing",
        "contracting"
    ],
    "wof:name":"Ainslie & Macaulay",
    "wof:placetype":"venue"
},
  "geometry": {"coordinates":[-3.6006190777,56.09167099],"type":"Point"}
}