{
  "type": "Feature",
  "properties": {
    "addr:full":"19a Leinster Gardens Bayswater Greater London W2 3AN",
    "addr:housenumber":"19a",
    "addr:postcode":"w2 3an",
    "addr:street":"Leinster Gardens",
    "iso:country":"GB",
    "sg:address":"19a Leinster Gardens",
    "sg:city":"Bayswater",
    "sg:classifiers":[
        {
            "category":"Professional",
            "subcategory":"Business Services",
            "type":"Services"
        }
    ],
    "sg:postcode":"W2 3AN",
    "sg:province":"Greater London",
    "sg:tags":[
        "holding"
    ],
    "wof:name":"Salisbury Group (uk) Ltd",
    "wof:placetype":"venue"
},
  "geometry": {"coordinates":[-0.1834840029,51.5125656128],"type":"Point"}
}