{
  "type": "Feature",
  "properties": {
    "addr:full":"11 Castle Street Bridgwater Somerset TA6 3DD",
    "addr:housenumber":"11",
    "addr:postcode":"ta6 3dd",
    "addr:street":"Castle Street",
    "iso:country":"GB",
    "sg:address":"11 Castle Street",
    "sg:city":"Bridgwater",
    "sg:classifiers":[
        {
            "category":"Arts & Performance",
            "subcategory":"Theater",
            "type":"Entertainment"
        }
    ],
    "sg:phone":"+44 1278 422700",
    "sg:postcode":"TA6 3DD",
    "sg:province":"Somerset",
    "sg:tags":[
        "hall",
        "theatre",
        "concert"
    ],
    "wof:name":"Bridgwater Arts Centre Co. Ltd.",
    "wof:placetype":"venue"
},
  "geometry": {"coordinates":[-3.0020010471,51.1295776367],"type":"Point"}
}