{
  "type": "Feature",
  "properties": {
    "addr:full":"Dawbarns, Harecroft Road Wisbech Cambridgeshire PE13 1RL",
    "addr:postcode":"pe13 1rl",
    "addr:street":"Harecroft Road",
    "iso:country":"GB",
    "sg:address":"Dawbarns, Harecroft Road",
    "sg:city":"Wisbech",
    "sg:classifiers":[
        {
            "category":"Manufacturing",
            "subcategory":"Textiles",
            "type":"Manufacturing & Wholesale Goods"
        },
        {
            "category":"Shopping",
            "subcategory":"Computers & Home Electronics",
            "type":"Retail Goods"
        },
        {
            "category":"Home & Garden",
            "subcategory":"Carpets & Floor Coverings",
            "type":"Retail Goods"
        }
    ],
    "sg:phone":"+44 1945 461741",
    "sg:postcode":"PE13 1RL",
    "sg:province":"Cambridgeshire",
    "sg:tags":[
        "product",
        "tarpaulin",
        "household",
        "manufacturer",
        "canvas"
    ],
    "wof:name":"DAWBARN & SONS LTD",
    "wof:placetype":"venue"
},
  "geometry": {"coordinates":[0.1500210017,52.6721229553],"type":"Point"}
}