{
  "type": "Feature",
  "properties": {
    "iso:country":"GB",
    "sg:address":"1 Southern Avenue, West Moors",
    "sg:city":"Ferndown",
    "sg:classifiers":[
        {
            "category":"Retail",
            "subcategory":"Repair Shop",
            "type":"Services"
        },
        {
            "category":"Building & Trades",
            "subcategory":"Construction",
            "type":"Services"
        }
    ],
    "sg:postcode":"BH22 0BH",
    "sg:province":"Dorset",
    "sg:tags":[
        "builder",
        "upholsterer"
    ],
    "wof:name":"Modique Furnishings Upholstery Service",
    "wof:placetype":"venue"
},
  "geometry": {"coordinates":[-1.8669420481,50.8179779053],"type":"Point"}
}