{
  "type": "Feature",
  "properties": {
    "iso:country":"GB",
    "sg:address":"The Old Hall, Ovington",
    "sg:city":"Alresford",
    "sg:classifiers":[
        {
            "category":"Professional",
            "subcategory":"Computer Services",
            "type":"Services"
        }
    ],
    "sg:postcode":"SO24 0RB",
    "sg:province":"Hampshire",
    "sg:tags":[
        "system",
        "software"
    ],
    "wof:name":"Virtual Planet Ltd",
    "wof:placetype":"venue"
},
  "geometry": {"coordinates":[-1.200759,51.082031],"type":"Point"}
}