{
  "type": "Feature",
  "properties": {
    "addr:full":"37 Phillip St Chester Cheshire CH2 3BY",
    "addr:housenumber":"37",
    "addr:postcode":"ch2 3by",
    "addr:street":"Phillip St",
    "iso:country":"GB",
    "sg:address":"37 Phillip St",
    "sg:city":"Chester",
    "sg:classifiers":[
        {
            "category":"Personal",
            "subcategory":"Beauty Salon",
            "type":"Services"
        }
    ],
    "sg:phone":"+44 1244 328415",
    "sg:postcode":"CH2 3BY",
    "sg:province":"Cheshire",
    "sg:tags":[
        "unisex",
        "hairdresser"
    ],
    "wof:name":"Barlow Hairdressing",
    "wof:placetype":"venue"
},
  "geometry": {"coordinates":[-2.878352,53.198116],"type":"Point"}
}