{
  "type": "Feature",
  "properties": {
    "addr:full":"York Station, Tea Room Square York North Yorkshire YO24 1AB",
    "addr:postcode":"yo24 1ab",
    "addr:street":"Square",
    "iso:country":"GB",
    "sg:address":"York Station, Tea Room Square",
    "sg:city":"York",
    "sg:classifiers":[
        {
            "category":"Shopping",
            "subcategory":"Gifts & Souvenirs",
            "type":"Retail Goods"
        }
    ],
    "sg:postcode":"YO24 1AB",
    "sg:province":"North Yorkshire",
    "sg:tags":[
        "shop"
    ],
    "wof:name":"York Model Railway Ltd.",
    "wof:placetype":"venue"
},
  "geometry": {"coordinates":[-1.0930099487,53.9583015442],"type":"Point"}
}