{
  "type": "Feature",
  "properties": {
    "addr:full":"34 Queens Market London Greater London E13 9BA",
    "addr:housenumber":"34",
    "addr:postcode":"e13 9ba",
    "addr:street":"Queens Market",
    "iso:country":"GB",
    "sg:address":"34 Queens Market",
    "sg:city":"London",
    "sg:classifiers":[
        {
            "category":"Food & Beverages",
            "subcategory":"Meat & Fish",
            "type":"Retail Goods"
        }
    ],
    "sg:phone":"+44 20 8552 2254",
    "sg:postcode":"E13 9BA",
    "sg:province":"Greater London",
    "sg:tags":[
        "butcher"
    ],
    "wof:name":"J Pike",
    "wof:placetype":"venue"
},
  "geometry": {"coordinates":[0.0307870004,51.5338249207],"type":"Point"}
}