{
  "type": "Feature",
  "properties": {
    "addr:full":"18 Scott St Perth Perth and Kinross PH1 5EJ",
    "addr:housenumber":"18",
    "addr:postcode":"ph1 5ej",
    "addr:street":"Scott St",
    "iso:country":"GB",
    "sg:address":"18 Scott St",
    "sg:city":"Perth",
    "sg:classifiers":[
        {
            "category":"Shopping",
            "type":"Retail Goods"
        }
    ],
    "sg:phone":"+44 1738 441505",
    "sg:postcode":"PH1 5EJ",
    "sg:province":"Perth and Kinross",
    "sg:tags":[
        "part",
        "accessory"
    ],
    "wof:name":"Taylor,Alexander,",
    "wof:placetype":"venue"
},
  "geometry": {"coordinates":[-3.432524,56.397205],"type":"Point"}
}