{
  "type": "Feature",
  "properties": {
    "iso:country":"GB",
    "sg:address":"11 Maritime Clo",
    "sg:city":"Rochester",
    "sg:classifiers":[
        {
            "category":"Arts & Performance",
            "subcategory":"Art Gallery",
            "type":"Entertainment"
        }
    ],
    "sg:phone":"+44 1634 290791",
    "sg:postcode":"ME2 4DJ",
    "sg:province":"Kent",
    "wof:name":"Just Paintings",
    "wof:placetype":"venue"
},
  "geometry": {"coordinates":[0.51319,51.400612],"type":"Point"}
}