{
  "type": "Feature",
  "properties": {
    "addr:full":"233 Perth Road Dundee Dundee City DD2 1EJ",
    "addr:housenumber":"233",
    "addr:postcode":"dd2 1ej",
    "addr:street":"Perth Road",
    "iso:country":"GB",
    "sg:address":"233 Perth Road",
    "sg:city":"Dundee",
    "sg:classifiers":[
        {
            "category":"Health Services",
            "subcategory":"Health Practitioner",
            "type":"Services"
        }
    ],
    "sg:phone":"+44 1382 665717",
    "sg:postcode":"DD2 1EJ",
    "sg:province":"Dundee City",
    "sg:tags":[
        "osteopath"
    ],
    "wof:name":"The West End Oesteopathic Clinic",
    "wof:placetype":"venue"
},
  "geometry": {"coordinates":[-2.9973750114,56.4567642212],"type":"Point"}
}