{
  "type": "Feature",
  "properties": {
    "iso:country":"GB",
    "sg:address":"142 Whitechapel Road",
    "sg:city":"London",
    "sg:classifiers":[
        {
            "category":"Taxi",
            "type":"Transportation"
        }
    ],
    "sg:phone":"+44 20 7480 7900",
    "sg:postcode":"E1 1JE",
    "sg:province":"Greater London",
    "sg:tags":[
        "mini",
        "cab"
    ],
    "wof:name":"Aldgate Car & Courier Service",
    "wof:placetype":"venue"
},
  "geometry": {"coordinates":[-0.063045,51.518307],"type":"Point"}
}