{
  "type": "Feature",
  "properties": {
    "addr:full":"Psykes Fold, Goonbell St Agnes Cornwall TR5 0PQ",
    "addr:postcode":"tr5 0pq",
    "addr:street":"Psykes;Goonbell",
    "iso:country":"GB",
    "sg:address":"Psykes Fold, Goonbell",
    "sg:city":"St Agnes",
    "sg:classifiers":[
        {
            "category":"Government",
            "subcategory":"Department Of Motor Vehicles",
            "type":"Public Place"
        },
        {
            "category":"Building & Trades",
            "subcategory":"Construction",
            "type":"Services"
        }
    ],
    "sg:phone":"+44 1872 552586",
    "sg:postcode":"TR5 0PQ",
    "sg:province":"Cornwall",
    "sg:tags":[
        "supplier",
        "agricultural",
        "builder"
    ],
    "wof:name":"Heyworth Farm Buildings",
    "wof:placetype":"venue"
},
  "geometry": {"coordinates":[-5.1991991997,50.3120994568],"type":"Point"}
}