{
  "type": "Feature",
  "properties": {
    "addr:full":"655 Loughborough Road, Birstall Leicester Leicestershire LE4 4NL",
    "addr:housenumber":"655",
    "addr:postcode":"le4 4nl",
    "addr:street":"Loughborough Road",
    "iso:country":"GB",
    "sg:address":"655 Loughborough Road, Birstall",
    "sg:city":"Leicester",
    "sg:classifiers":[
        {
            "category":"Health Services",
            "subcategory":"Optometrist",
            "type":"Services"
        },
        {
            "category":"Shopping",
            "subcategory":"Optician",
            "type":"Retail Goods"
        }
    ],
    "sg:phone":"+44 116 267 7855",
    "sg:postcode":"LE4 4NL",
    "sg:province":"Leicestershire",
    "sg:tags":[
        "ophthalmic"
    ],
    "wof:name":"Opticare Midlands Ltd.",
    "wof:placetype":"venue"
},
  "geometry": {"coordinates":[-1.125417,52.680481],"type":"Point"}
}