{
  "type": "Feature",
  "properties": {
    "addr:full":"Covert Road Sheltered Housing, Covert Road, Holts Estate Oldham Lancashire OL4 5PH",
    "addr:housenumber":"estate",
    "addr:postcode":"ol4 5ph",
    "addr:street":"Covert Road Sheltered Housing Covert Road Holts",
    "iso:country":"GB",
    "sg:address":"Covert Road Sheltered Housing, Covert Road, Holts Estate",
    "sg:city":"Oldham",
    "sg:classifiers":[
        {
            "category":"Government",
            "subcategory":"Office",
            "type":"Public Place"
        }
    ],
    "sg:phone":"+44 161 626 6262",
    "sg:postcode":"OL4 5PH",
    "sg:province":"Lancashire",
    "sg:tags":[
        "local"
    ],
    "wof:name":"Oldham Metropolitan Borough Council",
    "wof:placetype":"venue"
},
  "geometry": {"coordinates":[-2.075209,53.527676],"type":"Point"}
}