{
  "type": "Feature",
  "properties": {
    "addr:full":"30 St James Road Tunbridge Wells Kent TN1 2JZ",
    "addr:housenumber":"30",
    "addr:postcode":"tn1 2jz",
    "addr:street":"St James Road",
    "iso:country":"GB",
    "sg:address":"30 St James Road",
    "sg:city":"Tunbridge Wells",
    "sg:classifiers":[
        {
            "category":"Health Services",
            "subcategory":"Nursing And Care Facility",
            "type":"Services"
        }
    ],
    "sg:phone":"+44 1892 523954",
    "sg:postcode":"TN1 2JZ",
    "sg:province":"Kent",
    "sg:tags":[
        "home"
    ],
    "wof:name":"United Care Group Ltd.",
    "wof:placetype":"venue"
},
  "geometry": {"coordinates":[0.2739849985,51.1377067566],"type":"Point"}
}