{
  "type": "Feature",
  "properties": {
    "addr:full":"Unit G3 Old Forge Yard, Swanley Village Road Swanley Kent BR8 7NF",
    "addr:housenumber":"g3",
    "addr:postcode":"br8 7nf",
    "addr:street":"Old;Yard Swanley Village Road",
    "iso:country":"GB",
    "sg:address":"Unit G3 Old Forge Yard, Swanley Village Road",
    "sg:city":"Swanley",
    "sg:classifiers":[
        {
            "category":"Professional",
            "subcategory":"Engineering",
            "type":"Services"
        }
    ],
    "sg:phone":"+44 1322 663949",
    "sg:postcode":"BR8 7NF",
    "sg:province":"Kent",
    "wof:name":"A Cornish Engineering (Swanley) Ltd.",
    "wof:placetype":"venue"
},
  "geometry": {"coordinates":[0.193942,51.404709],"type":"Point"}
}