{
  "type": "Feature",
  "properties": {
    "addr:full":"396 Llangyfelach Rd, Brynhyfryd Swansea Swansea SA5 9LH",
    "addr:housenumber":"396",
    "addr:postcode":"sa5 9lh",
    "addr:street":"Llangyfelach Rd",
    "iso:country":"GB",
    "sg:address":"396 Llangyfelach Rd, Brynhyfryd",
    "sg:city":"Swansea",
    "sg:classifiers":[
        {
            "category":"Building & Trades",
            "subcategory":"Cleaning & Sanitation",
            "type":"Services"
        }
    ],
    "sg:phone":"+44 1792 413366",
    "sg:postcode":"SA5 9LH",
    "sg:province":"Swansea",
    "sg:tags":[
        "commercial"
    ],
    "wof:name":"D.A.S Cleaning Services",
    "wof:placetype":"venue"
},
  "geometry": {"coordinates":[-3.9444420338,51.6422080994],"type":"Point"}
}