{
  "type": "Feature",
  "properties": {
    "addr:full":"117 Market St, Edenfield Bury Lancashire BL0 0JJ",
    "addr:housenumber":"117",
    "addr:postcode":"bl0 0jj",
    "addr:street":"Market St",
    "iso:country":"GB",
    "sg:address":"117 Market St, Edenfield",
    "sg:city":"Bury",
    "sg:classifiers":[
        {
            "category":"Retail",
            "subcategory":"Auto Rental",
            "type":"Services"
        }
    ],
    "sg:phone":"+44 1706 828765",
    "sg:postcode":"BL0 0JJ",
    "sg:province":"Lancashire",
    "sg:tags":[
        "car"
    ],
    "wof:name":"Rainbow Self Drive Hire (Heywood) Ltd",
    "wof:placetype":"venue"
},
  "geometry": {"coordinates":[-2.3058619499,53.6723365784],"type":"Point"}
}