{
  "type": "Feature",
  "properties": {
    "iso:country":"GB",
    "sg:address":"14 Whingrove Avenue, Meltham",
    "sg:city":"Huddersfield",
    "sg:classifiers":[
        {
            "category":"Building & Trades",
            "subcategory":"Cleaning & Sanitation",
            "type":"Services"
        }
    ],
    "sg:postcode":"HD9 5LP",
    "sg:province":"South Yorkshire",
    "sg:tags":[
        "cleaner",
        "window"
    ],
    "wof:name":"Woodcock Window Cleaning Services",
    "wof:placetype":"venue"
},
  "geometry": {"coordinates":[-1.858914,53.590534],"type":"Point"}
}