{
  "type": "Feature",
  "properties": {
    "iso:country":"GB",
    "sg:address":"2 York Terrace",
    "sg:city":"Cambridge",
    "sg:classifiers":[
        {
            "category":"Professional",
            "subcategory":"Computer Services",
            "type":"Services"
        }
    ],
    "sg:phone":"+44 1223 740568",
    "sg:postcode":"CB1 2PR",
    "sg:province":"Cambridgeshire",
    "sg:tags":[
        "system",
        "software"
    ],
    "wof:name":"Pelican Computing",
    "wof:placetype":"venue"
},
  "geometry": {"coordinates":[0.1414700001,52.2037353516],"type":"Point"}
}