{
  "type": "Feature",
  "properties": {
    "iso:country":"GB",
    "sg:address":"283 Stafford Road",
    "sg:city":"Croydon",
    "sg:classifiers":[
        {
            "category":"Building & Trades",
            "subcategory":"Construction",
            "type":"Services"
        }
    ],
    "sg:phone":"+44 20 8730 6200",
    "sg:postcode":"CR0 4NN",
    "sg:province":"Surrey",
    "sg:tags":[
        "builder"
    ],
    "wof:name":"Walter Lilly & Co. Ltd.",
    "wof:placetype":"venue"
},
  "geometry": {"coordinates":[-0.121209003,51.3625793457],"type":"Point"}
}