{
  "type": "Feature",
  "properties": {
    "addr:full":"98 Sandy Lane South Wallington Surrey SM6 9RQ",
    "addr:housenumber":"98",
    "addr:postcode":"sm6 9rq",
    "addr:street":"Sandy Lane South",
    "iso:country":"GB",
    "sg:address":"98 Sandy Lane South",
    "sg:city":"Wallington",
    "sg:classifiers":[
        {
            "category":"Building & Trades",
            "subcategory":"Plumbing",
            "type":"Services"
        }
    ],
    "sg:postcode":"SM6 9RQ",
    "sg:province":"Surrey",
    "sg:tags":[
        "heating"
    ],
    "wof:name":"Hows Building Services",
    "wof:placetype":"venue"
},
  "geometry": {"coordinates":[-0.1432989985,51.3525352478],"type":"Point"}
}