{
  "type": "Feature",
  "properties": {
    "iso:country":"GB",
    "sg:address":"Grand Juction Retail Park, Grand Junction Way",
    "sg:city":"Crewe",
    "sg:classifiers":[
        {
            "category":"Home & Garden",
            "subcategory":"Hardware",
            "type":"Retail Goods"
        }
    ],
    "sg:phone":"+44 1270 252522",
    "sg:postcode":"CW1 2RP",
    "sg:province":"Cheshire",
    "sg:tags":[
        "retailer",
        "diy"
    ],
    "wof:name":"Focus Superstores",
    "wof:placetype":"venue"
},
  "geometry": {"coordinates":[-2.433949,53.097225],"type":"Point"}
}