{
  "type": "Feature",
  "properties": {
    "addr:full":"Hockley Court, Stratford Rd, Hockley Heath Solihull Warwickshire B94 6NW",
    "addr:postcode":"b94 6nw",
    "addr:street":"Hockley Court Stratford Rd",
    "iso:country":"GB",
    "sg:address":"Hockley Court, Stratford Rd, Hockley Heath",
    "sg:city":"Solihull",
    "sg:classifiers":[
        {
            "category":"Insurance",
            "subcategory":"Insurance Agent",
            "type":"Services"
        }
    ],
    "sg:phone":"+44 870 607 1352",
    "sg:postcode":"B94 6NW",
    "sg:province":"Warwickshire",
    "wof:name":"Friends' Provident Customer Information Centre",
    "wof:placetype":"venue"
},
  "geometry": {"coordinates":[-1.7849940062,52.3729743958],"type":"Point"}
}