{
  "type": "Feature",
  "properties": {
    "iso:country":"GB",
    "sg:address":"116 Wigan Road, Euxton",
    "sg:city":"Chorley",
    "sg:classifiers":[
        {
            "category":"Shopping",
            "subcategory":"News",
            "type":"Retail Goods"
        }
    ],
    "sg:phone":"+44 1257 278268",
    "sg:postcode":"PR7 6JH",
    "sg:province":"Lancashire",
    "sg:tags":[
        "newsagent"
    ],
    "wof:name":"Forbuoys Ltd.",
    "wof:placetype":"venue"
},
  "geometry": {"coordinates":[-2.676438,53.670071],"type":"Point"}
}