{
  "type": "Feature",
  "properties": {
    "iso:country":"GB",
    "sg:address":"82 High Street",
    "sg:city":"Elgin",
    "sg:classifiers":[
        {
            "category":"Shopping",
            "subcategory":"Jewelry",
            "type":"Retail Goods"
        },
        {
            "category":"Shopping",
            "subcategory":"Comic Books",
            "type":"Retail Goods"
        }
    ],
    "sg:phone":"+44 1343 542586",
    "sg:postcode":"IV30 1BJ",
    "sg:province":"Moray",
    "sg:tags":[
        "jeweller",
        "sale",
        "jewellery"
    ],
    "wof:name":"Little The Jewellers",
    "wof:placetype":"venue"
},
  "geometry": {"coordinates":[-3.314344,57.648651],"type":"Point"}
}