{
  "type": "Feature",
  "properties": {
    "addr:full":"45 Thorneywood Mount Nottingham Nottinghamshire NG3 2PY",
    "addr:housenumber":"45",
    "addr:postcode":"ng3 2py",
    "addr:street":"Thorneywood Mount",
    "iso:country":"GB",
    "sg:address":"45 Thorneywood Mount",
    "sg:city":"Nottingham",
    "sg:classifiers":[
        {
            "category":"Health Services",
            "subcategory":"Podiatrist",
            "type":"Services"
        }
    ],
    "sg:phone":"+44 115 950 2251",
    "sg:postcode":"NG3 2PY",
    "sg:province":"Nottinghamshire",
    "sg:tags":[
        "podiatrists",
        "chiropodist"
    ],
    "wof:name":"D Varley",
    "wof:placetype":"venue"
},
  "geometry": {"coordinates":[-1.12422,52.965775],"type":"Point"}
}