{
  "type": "Feature",
  "properties": {
    "addr:full":"79 Paul Street London Greater London EC2A 4NQ",
    "addr:housenumber":"79",
    "addr:postcode":"ec2a 4nq",
    "addr:street":"Paul Street",
    "iso:country":"GB",
    "sg:address":"79 Paul Street",
    "sg:city":"London",
    "sg:classifiers":[
        {
            "category":"Professional",
            "subcategory":"Engineering",
            "type":"Services"
        },
        {
            "category":"Wholesale",
            "subcategory":"Construction Materials",
            "type":"Manufacturing & Wholesale Goods"
        }
    ],
    "sg:phone":"+44 20 7251 1336",
    "sg:postcode":"EC2A 4NQ",
    "sg:province":"Greater London",
    "sg:tags":[
        "consulting",
        "lift",
        "engineer"
    ],
    "wof:name":"Dunbar Boardman & French",
    "wof:placetype":"venue"
},
  "geometry": {"coordinates":[-0.0840310007,51.5252304077],"type":"Point"}
}