{
  "type": "Feature",
  "properties": {
    "addr:full":"Unit 2 City Link Industrial Estate, Phoenix Way, Tyersal Bradford West Yorkshire BD4 8JP",
    "addr:housenumber":"unit 2",
    "addr:postcode":"bd4 8jp",
    "addr:street":"City Link Industrial Estate Phoenix Way Tyersal Bradford West",
    "iso:country":"GB",
    "sg:address":"Unit 2 City Link Industrial Estate, Phoenix Way, Tyersal",
    "sg:city":"Bradford",
    "sg:classifiers":[
        {
            "category":"Professional",
            "subcategory":"Printing & Photocopies",
            "type":"Services"
        }
    ],
    "sg:phone":"+44 1274 657800",
    "sg:postcode":"BD4 8JP",
    "sg:province":"West Yorkshire",
    "sg:tags":[
        "printer"
    ],
    "wof:name":"Scientific Games International Ltd.",
    "wof:placetype":"venue"
},
  "geometry": {"coordinates":[-1.711309,53.787689],"type":"Point"}
}