{
  "type": "Feature",
  "properties": {
    "addr:full":"P O Box 1347 Hove East Sussex BN3 6RB",
    "addr:housenumber":"p o",
    "addr:postcode":"1347;bn3 6rb",
    "iso:country":"GB",
    "sg:address":"P O Box 1347",
    "sg:city":"Hove",
    "sg:classifiers":[
        {
            "category":"Shopping",
            "subcategory":"Antiques",
            "type":"Retail Goods"
        }
    ],
    "sg:phone":"+44 1273 500212",
    "sg:postcode":"BN3 6RB",
    "sg:province":"East Sussex",
    "wof:name":"Stone June & Tony Fine Antique Boxes",
    "wof:placetype":"venue"
},
  "geometry": {"coordinates":[-0.182449,50.838943],"type":"Point"}
}