{
  "type": "Feature",
  "properties": {
    "iso:country":"GB",
    "sg:address":"Glanhafren",
    "sg:city":"Welshpool",
    "sg:classifiers":[
        {
            "category":"Farming",
            "subcategory":"Livestock Farm",
            "type":"Manufacturing & Wholesale Goods"
        },
        {
            "category":"Farming",
            "subcategory":"Farm",
            "type":"Manufacturing & Wholesale Goods"
        }
    ],
    "sg:postcode":"SY21 8RS",
    "sg:province":"Shropshire",
    "sg:tags":[
        "mixed",
        "crop",
        "others"
    ],
    "wof:name":"D R & I Cadwallader",
    "wof:placetype":"venue"
},
  "geometry": {"coordinates":[-3.15361,52.634331],"type":"Point"}
}