{
  "type": "Feature",
  "properties": {
    "addr:full":"203 Main Street Larbert Falkirk FK5 4AL",
    "addr:housenumber":"203",
    "addr:postcode":"fk5 4al",
    "addr:street":"Main Street",
    "iso:country":"GB",
    "sg:address":"203 Main Street",
    "sg:city":"Larbert",
    "sg:classifiers":[
        {
            "category":"Real Estate",
            "subcategory":"Real Estate Agent",
            "type":"Services"
        }
    ],
    "sg:phone":"+44 1324 553512",
    "sg:postcode":"FK5 4AL",
    "sg:province":"Falkirk",
    "wof:name":"Ian Gray Estate Agents",
    "wof:placetype":"venue"
},
  "geometry": {"coordinates":[-3.8306360245,56.021774292],"type":"Point"}
}