{
  "type": "Feature",
  "properties": {
    "iso:country":"GB",
    "sg:address":"34 Reighton Avenue",
    "sg:city":"York",
    "sg:classifiers":[
        {
            "category":"Organizations",
            "subcategory":"Non-profit Organization",
            "type":"Services"
        }
    ],
    "sg:postcode":"YO30 5QN",
    "sg:province":"North Yorkshire",
    "sg:tags":[
        "organisation",
        "voluntary",
        "charity"
    ],
    "wof:name":"York Against Motorneurone Disease",
    "wof:placetype":"venue"
},
  "geometry": {"coordinates":[-1.1026580334,53.9786911011],"type":"Point"}
}