{
  "type": "Feature",
  "properties": {
    "iso:country":"GB",
    "sg:address":"20 The Jamb",
    "sg:city":"Corby",
    "sg:classifiers":[
        {
            "category":"Food & Beverages",
            "subcategory":"Candy",
            "type":"Retail Goods"
        }
    ],
    "sg:phone":"+44 1536 203685",
    "sg:postcode":"NN17 1AY",
    "sg:province":"Northamptonshire",
    "sg:tags":[
        "confectioner"
    ],
    "wof:name":"The Chocolate Shop",
    "wof:placetype":"venue"
},
  "geometry": {"coordinates":[-0.68327,52.49118],"type":"Point"}
}