{
  "type": "Feature",
  "properties": {
    "addr:full":"Unit 47 Bell Lane, Bell Lane Industrial Estate Uckfield East Sussex TN22 1QL",
    "addr:housenumber":"unit 47",
    "addr:postcode":"tn22 1ql",
    "addr:street":"Bell Lane Bell Lane Industrial Estate",
    "iso:country":"GB",
    "sg:address":"Unit 47 Bell Lane, Bell Lane Industrial Estate",
    "sg:city":"Uckfield",
    "sg:classifiers":[
        {
            "category":"Shopping",
            "subcategory":"Party Supplies",
            "type":"Retail Goods"
        }
    ],
    "sg:phone":"+44 1825 763348",
    "sg:postcode":"TN22 1QL",
    "sg:province":"East Sussex",
    "sg:tags":[
        "equipment",
        "disco"
    ],
    "wof:name":"Multiform Electronics Ltd.",
    "wof:placetype":"venue"
},
  "geometry": {"coordinates":[0.0948100016,50.9695358276],"type":"Point"}
}