{
  "type": "Feature",
  "properties": {
    "iso:country":"GB",
    "sg:address":"Unit 6, Careys Development",
    "sg:city":"Clevedon",
    "sg:classifiers":[
        {
            "category":"Wholesale",
            "subcategory":"Electrical",
            "type":"Manufacturing & Wholesale Goods"
        }
    ],
    "sg:postcode":"BS21 6RR",
    "sg:province":"Somerset",
    "sg:tags":[
        "equipment",
        "refrigeration"
    ],
    "wof:name":"Mercury Coldrooms Ltd.",
    "wof:placetype":"venue"
},
  "geometry": {"coordinates":[-2.840491,51.441055],"type":"Point"}
}