{
  "type": "Feature",
  "properties": {
    "iso:country":"GB",
    "sg:address":"38 Lodge Road, Orrell",
    "sg:city":"Wigan",
    "sg:classifiers":[
        {
            "category":"Recreation",
            "subcategory":"Fishing",
            "type":"Entertainment"
        }
    ],
    "sg:phone":"+44 1695 625634",
    "sg:postcode":"WN5 7AT",
    "sg:province":"Lancashire",
    "sg:tags":[
        "angling"
    ],
    "wof:name":"Lake View Tackle",
    "wof:placetype":"venue"
},
  "geometry": {"coordinates":[-2.708936,53.528187],"type":"Point"}
}