{
  "type": "Feature",
  "properties": {
    "addr:full":"Church View, Mathry Haverfordwest Pembrokeshire SA62 5HA",
    "addr:postcode":"sa62 5ha",
    "iso:country":"GB",
    "sg:address":"Church View, Mathry",
    "sg:city":"Haverfordwest",
    "sg:classifiers":[
        {
            "category":"Professional",
            "subcategory":"Engineering",
            "type":"Services"
        }
    ],
    "sg:phone":"+44 1348 831391",
    "sg:postcode":"SA62 5HA",
    "sg:province":"Pembrokeshire",
    "wof:name":"Glyn Thomas",
    "wof:placetype":"venue"
},
  "geometry": {"coordinates":[-5.0876488686,51.9459953308],"type":"Point"}
}