{
  "type": "Feature",
  "properties": {
    "addr:full":"121 Winchester Road, Brislington Bristol City of Bristol BS4 3NH",
    "addr:housenumber":"121",
    "addr:postcode":"bs4 3nh",
    "addr:street":"Winchester Road",
    "iso:country":"GB",
    "sg:address":"121 Winchester Road, Brislington",
    "sg:city":"Bristol",
    "sg:classifiers":[
        {
            "category":"Professional",
            "subcategory":"Engineering",
            "type":"Services"
        }
    ],
    "sg:phone":"+44 117 971 1491",
    "sg:postcode":"BS4 3NH",
    "sg:province":"City of Bristol",
    "sg:tags":[
        "contractor",
        "electrical",
        "engineer"
    ],
    "wof:name":"A M P Electrical Ltd.",
    "wof:placetype":"venue"
},
  "geometry": {"coordinates":[-2.553345,51.43742],"type":"Point"}
}