{
  "type": "Feature",
  "properties": {
    "addr:full":"Unit 15, Reflex Industrial Park, Park Road Willenhall West Midlands WV13 1AH",
    "addr:housenumber":"unit 15",
    "addr:postcode":"wv13 1ah",
    "addr:street":"Reflex Industrial Park Park Road",
    "iso:country":"GB",
    "sg:address":"Unit 15, Reflex Industrial Park, Park Road",
    "sg:city":"Willenhall",
    "sg:classifiers":[
        {
            "category":"Shopping",
            "subcategory":"Clothing, Apparel, & Fashions",
            "type":"Retail Goods"
        }
    ],
    "sg:phone":"+44 1902 603217",
    "sg:postcode":"WV13 1AH",
    "sg:province":"West Midlands",
    "sg:tags":[
        "workwear",
        "protective"
    ],
    "wof:name":"Walsall Products",
    "wof:placetype":"venue"
},
  "geometry": {"coordinates":[-2.057104,52.58427],"type":"Point"}
}