{
  "type": "Feature",
  "properties": {
    "addr:full":"34 Windmill Hill Enfield Greater London EN1 3NH",
    "addr:housenumber":"34",
    "addr:postcode":"en1 3nh",
    "addr:street":"Windmill Hill",
    "iso:country":"GB",
    "sg:address":"34 Windmill Hill",
    "sg:city":"Enfield",
    "sg:classifiers":[
        {
            "category":"Professional",
            "subcategory":"Employment Agencies",
            "type":"Services"
        }
    ],
    "sg:phone":"+44 20 8219 2800",
    "sg:postcode":"EN1 3NH",
    "sg:province":"Greater London",
    "sg:tags":[
        "consultant"
    ],
    "wof:name":"Employment Service Jobcentre",
    "wof:placetype":"venue"
},
  "geometry": {"coordinates":[-0.0914430022,51.6537513733],"type":"Point"}
}