{
  "type": "Feature",
  "properties": {
    "addr:full":"169 Old Road Chesterfield Derbyshire S40 3QL",
    "addr:housenumber":"169",
    "addr:postcode":"s40 3ql",
    "addr:street":"Old Road",
    "iso:country":"GB",
    "sg:address":"169 Old Road",
    "sg:city":"Chesterfield",
    "sg:classifiers":[
        {
            "category":"Building & Trades",
            "subcategory":"Plumbing",
            "type":"Services"
        }
    ],
    "sg:phone":"+44 1246 271267",
    "sg:postcode":"S40 3QL",
    "sg:province":"Derbyshire",
    "sg:tags":[
        "heating"
    ],
    "wof:name":"Property & Plumbing Services",
    "wof:placetype":"venue"
},
  "geometry": {"coordinates":[-1.462192,53.235592],"type":"Point"}
}