{
  "type": "Feature",
  "properties": {
    "addr:full":"19 Carrick Street Ayr South Ayrshire KA7 1NS",
    "addr:housenumber":"19",
    "addr:postcode":"ka7 1ns",
    "addr:street":"Carrick Street",
    "iso:country":"GB",
    "sg:address":"19 Carrick Street",
    "sg:city":"Ayr",
    "sg:classifiers":[
        {
            "category":"Personal",
            "subcategory":"Barber",
            "type":"Services"
        }
    ],
    "sg:phone":"+44 1292 263715",
    "sg:postcode":"KA7 1NS",
    "sg:province":"South Ayrshire",
    "sg:tags":[
        "men's",
        "hairdresser"
    ],
    "wof:name":"Bowie's",
    "wof:placetype":"venue"
},
  "geometry": {"coordinates":[-4.630088,55.461658],"type":"Point"}
}