{
  "type": "Feature",
  "properties": {
    "addr:full":"Murivance House, Murivance Shrewsbury Shropshire SY1 1JW",
    "addr:postcode":"sy1 1jw",
    "addr:street":"Murivance",
    "iso:country":"GB",
    "sg:address":"Murivance House, Murivance",
    "sg:city":"Shrewsbury",
    "sg:classifiers":[
        {
            "category":"Professional",
            "subcategory":"Lawyer & Legal Services",
            "type":"Services"
        }
    ],
    "sg:phone":"+44 1743 359933",
    "sg:postcode":"SY1 1JW",
    "sg:province":"Shropshire",
    "wof:name":"Shropshire Associated Lawyer Mediators",
    "wof:placetype":"venue"
},
  "geometry": {"coordinates":[-2.7578940392,52.7060699463],"type":"Point"}
}