{
  "type": "Feature",
  "properties": {
    "addr:full":"53 Bothwell Street Glasgow Glasgow City G2 6TS",
    "addr:housenumber":"53",
    "addr:postcode":"g2 6ts",
    "addr:street":"Bothwell Street",
    "iso:country":"GB",
    "sg:address":"53 Bothwell Street",
    "sg:city":"Glasgow",
    "sg:classifiers":[
        {
            "category":"Real Estate",
            "subcategory":"Surveying",
            "type":"Services"
        }
    ],
    "sg:phone":"+44 141 221 8068",
    "sg:postcode":"G2 6TS",
    "sg:province":"Glasgow City",
    "sg:tags":[
        "surveyor",
        "valuer"
    ],
    "wof:name":"INGLES & PARTNERS",
    "wof:placetype":"venue"
},
  "geometry": {"coordinates":[-4.26091,55.861084],"type":"Point"}
}