{
  "type": "Feature",
  "properties": {
    "iso:country":"GB",
    "sg:address":"110 Lime Gro",
    "sg:city":"Bideford",
    "sg:classifiers":[
        {
            "category":"Shopping",
            "subcategory":"Musical Instruments",
            "type":"Retail Goods"
        }
    ],
    "sg:phone":"+44 1237 477748",
    "sg:postcode":"EX39 3JW",
    "sg:province":"Devon",
    "sg:tags":[
        "organ",
        "accessory"
    ],
    "wof:name":"Musicom Research Ltd.",
    "wof:placetype":"venue"
},
  "geometry": {"coordinates":[-4.211329,51.02013],"type":"Point"}
}