{
  "type": "Feature",
  "properties": {
    "iso:country":"GB",
    "sg:address":"1663 London Rd",
    "sg:city":"Leigh On Sea",
    "sg:classifiers":[
        {
            "category":"Home & Garden",
            "subcategory":"Furniture",
            "type":"Retail Goods"
        }
    ],
    "sg:phone":"+44 1702 476703",
    "sg:postcode":"SS9 2SH",
    "sg:province":"Essex",
    "wof:name":"Furniture Workshop",
    "wof:placetype":"venue"
},
  "geometry": {"coordinates":[0.635229,51.54818],"type":"Point"}
}