{
  "type": "Feature",
  "properties": {
    "addr:full":"Finchley Court Business Centre, 279 Kings Rd Birmingham West Midlands B44 0TE",
    "addr:housenumber":"279",
    "addr:postcode":"b44 0te",
    "addr:street":"Finchley;Kings Rd",
    "iso:country":"GB",
    "sg:address":"Finchley Court Business Centre, 279 Kings Rd",
    "sg:city":"Birmingham",
    "sg:classifiers":[
        {
            "category":"Home & Garden",
            "subcategory":"Carpets & Floor Coverings",
            "type":"Retail Goods"
        }
    ],
    "sg:phone":"+44 121 693 1441",
    "sg:postcode":"B44 0TE",
    "sg:province":"West Midlands",
    "sg:tags":[
        "cleaner",
        "upholstery"
    ],
    "wof:name":"A1 Servicemaster",
    "wof:placetype":"venue"
},
  "geometry": {"coordinates":[-1.87443,52.550968],"type":"Point"}
}