{
  "type": "Feature",
  "properties": {
    "addr:full":"102 Gainsborough Road Leicester Leicestershire LE2 3DF",
    "addr:housenumber":"102",
    "addr:postcode":"le2 3df",
    "addr:street":"Gainsborough Road",
    "iso:country":"GB",
    "sg:address":"102 Gainsborough Road",
    "sg:city":"Leicester",
    "sg:classifiers":[
        {
            "category":"Food & Beverages",
            "subcategory":"Groceries & Convenience Stores",
            "type":"Retail Goods"
        }
    ],
    "sg:phone":"+44 116 270 6153",
    "sg:postcode":"LE2 3DF",
    "sg:province":"Leicestershire",
    "wof:name":"Gainsborough",
    "wof:placetype":"venue"
},
  "geometry": {"coordinates":[-1.1160180569,52.6127166748],"type":"Point"}
}