{
  "type": "Feature",
  "properties": {
    "iso:country":"GB",
    "sg:address":"1a Turnhurst Road",
    "sg:city":"Stoke-on-trent",
    "sg:classifiers":[
        {
            "category":"Social Services",
            "subcategory":"Retirement Home",
            "type":"Services"
        }
    ],
    "sg:phone":"+44 1782 790500",
    "sg:postcode":"ST6 6LA",
    "sg:province":"Staffordshire",
    "sg:tags":[
        "residential",
        "care"
    ],
    "wof:name":"Claybourne (Methodist Homes for the Aged)",
    "wof:placetype":"venue"
},
  "geometry": {"coordinates":[-2.200624,53.075417],"type":"Point"}
}