{
  "type": "Feature",
  "properties": {
    "iso:country":"GB",
    "sg:address":"152 Albion Road, New Mills",
    "sg:city":"High Peak",
    "sg:classifiers":[
        {
            "category":"Manufacturing",
            "subcategory":"Tools & Machinery",
            "type":"Manufacturing & Wholesale Goods"
        }
    ],
    "sg:phone":"+44 1663 741694",
    "sg:postcode":"SK22 3JP",
    "sg:province":"Cheshire",
    "sg:tags":[
        "society",
        "friendly"
    ],
    "wof:name":"Sett Valley Insurance Services",
    "wof:placetype":"venue"
},
  "geometry": {"coordinates":[-2.0018689632,53.3627090454],"type":"Point"}
}