{
  "type": "Feature",
  "properties": {
    "iso:country":"GB",
    "sg:address":"137 Clophill Road, Maulden",
    "sg:city":"Bedford",
    "sg:classifiers":[
        {
            "category":"Building & Trades",
            "subcategory":"Plumbing",
            "type":"Services"
        },
        {
            "category":"Professional",
            "subcategory":"Printing & Photocopies",
            "type":"Services"
        }
    ],
    "sg:href":"http://api.simplegeo.com/1.0/features/SG_3kvlCqoxGpMwEfn8vXkmAZ_52.026924_-0.428295@1300740015.json",
    "sg:phone":"+44 1525 860646",
    "sg:postcode":"MK45 2AF",
    "sg:province":"Bedfordshire",
    "sg:tags":[
        "top",
        "heating",
        "central",
        "publishing",
        "desk"
    ],
    "wof:name":"Leemoll Services",
    "wof:placetype":"venue"
},
  "geometry": {"coordinates":[-0.428295,52.026924],"type":"Point"}
}