{"geometry":{"type":"Point","coordinates":[-0.428295,52.026924]},"type":"Feature","id":102560015,"bbox":[-0.428295,52.026924,-0.428295,52.026924],"properties":{"sg:province":"Bedfordshire","sg:tags":["top","heating","central","publishing","desk"],"geom:longitude":-0.428295,"wof:breaches":[],"sg:href":"http://api.simplegeo.com/1.0/features/SG_3kvlCqoxGpMwEfn8vXkmAZ_52.026924_-0.428295@1300740015.json","sg:owner":"simplegeo","sg:postcode":"MK45 2AF","geom:latitude":52.026924,"sg:classifiers":[{"category":"Building & Trades","type":"Services","subcategory":"Plumbing"},{"category":"Professional","type":"Services","subcategory":"Printing & Photocopies"}],"sg:address":"137 Clophill Road, Maulden","sg:phone":"+44 1525 860646","wof:hierarchy":[{"venue_id":102560015,"country_id":85633159,"region_id":85684591}],"geom:area":0.000000,"sg:city":"Bedford","wof:lastmodified":1438093160,"iso:country":"GB","wof:geomhash":"884ffc816cd1545f984ffaf48a9a74be","wof:name":"Leemoll Services","wof:belongsto":[85633159,85684591],"src:geom":"simplegeo","wof:placetype":"venue","wof:supersedes":[],"wof:id":102560015,"wof:superseded_by":[],"wof:concordances":{"sg:id":"SG_3kvlCqoxGpMwEfn8vXkmAZ_52.026924_-0.428295@1300740015"},"wof:parent_id":85684591}}