{
  "type": "Feature",
  "properties": {
    "iso:country":"GB",
    "sg:address":"23 Main St",
    "sg:city":"Johnstone",
    "sg:classifiers":[
        {
            "category":"Food & Beverages",
            "subcategory":"Fruits & Vegetables",
            "type":"Retail Goods"
        }
    ],
    "sg:postcode":"PA9 1AW",
    "sg:province":"Renfrewshire",
    "sg:tags":[
        "greengrocer"
    ],
    "wof:name":"Stop Shop",
    "wof:placetype":"venue"
},
  "geometry": {"coordinates":[-4.560969,55.80862],"type":"Point"}
}