{
  "type": "Feature",
  "properties": {
    "addr:full":"38-44 St Anns Road Harrow Greater London HA1 1LA",
    "addr:housenumber":"38-44",
    "addr:postcode":"ha1 1la",
    "addr:street":"St Anns Road",
    "iso:country":"GB",
    "sg:address":"38-44 St Anns Road",
    "sg:city":"Harrow",
    "sg:classifiers":[
        {
            "category":"Home & Garden",
            "subcategory":"Household Appliances",
            "type":"Retail Goods"
        }
    ],
    "sg:phone":"+44 20 8427 0664",
    "sg:postcode":"HA1 1LA",
    "sg:province":"Greater London",
    "sg:tags":[
        "electrical",
        "domestic"
    ],
    "wof:name":"Currys",
    "wof:placetype":"venue"
},
  "geometry": {"coordinates":[-0.335656,51.581589],"type":"Point"}
}