{
  "type": "Feature",
  "properties": {
    "addr:full":"Unit 7, Enderby Road Industrial Estate, Whetstone Leicester Leicestershire LE8 6HZ",
    "addr:housenumber":"unit 7",
    "addr:postcode":"le8 6hz",
    "addr:street":"Enderby Road Industrial Estate",
    "iso:country":"GB",
    "sg:address":"Unit 7, Enderby Road Industrial Estate, Whetstone",
    "sg:city":"Leicester",
    "sg:classifiers":[
        {
            "category":"Wholesale",
            "subcategory":"Construction Materials",
            "type":"Manufacturing & Wholesale Goods"
        }
    ],
    "sg:postcode":"LE8 6HZ",
    "sg:province":"Leicestershire",
    "sg:tags":[
        "coating",
        "powder"
    ],
    "wof:name":"Kmh Stove Enamelling & Powder Coater Specialists",
    "wof:placetype":"venue"
},
  "geometry": {"coordinates":[-1.1870139837,52.5795021057],"type":"Point"}
}