{
  "type": "Feature",
  "properties": {
    "addr:full":"145 Capmartin Road Coventry Warwickshire CV6 3FU",
    "addr:housenumber":"145",
    "addr:postcode":"cv6 3fu",
    "addr:street":"Capmartin Road",
    "iso:country":"GB",
    "sg:address":"145 Capmartin Road",
    "sg:city":"Coventry",
    "sg:classifiers":[
        {
            "category":"Building & Trades",
            "subcategory":"Construction",
            "type":"Services"
        }
    ],
    "sg:phone":"+44 24 7659 5389",
    "sg:postcode":"CV6 3FU",
    "sg:province":"Warwickshire",
    "sg:tags":[
        "glazier",
        "decorator",
        "painter"
    ],
    "wof:name":"Robert Wilson Crawford",
    "wof:placetype":"venue"
},
  "geometry": {"coordinates":[-1.511891,52.430969],"type":"Point"}
}