{
  "type": "Feature",
  "properties": {
    "addr:full":"Curlew Cottage, Old Cleish Road Kinross Clackmannanshire KY13 8DG",
    "addr:postcode":"ky13 8dg",
    "addr:street":"Old Cleish Road",
    "iso:country":"GB",
    "sg:address":"Curlew Cottage, Old Cleish Road",
    "sg:city":"Kinross",
    "sg:classifiers":[
        {
            "category":"Professional",
            "subcategory":"Engineering",
            "type":"Services"
        },
        {
            "category":"Building & Trades",
            "subcategory":"Electrical",
            "type":"Services"
        }
    ],
    "sg:postcode":"KY13 8DG",
    "sg:province":"Clackmannanshire",
    "sg:tags":[
        "engineer",
        "electrician",
        "contractor"
    ],
    "wof:name":"HUNTER ELECTRICAL",
    "wof:placetype":"venue"
},
  "geometry": {"coordinates":[-3.4255139828,56.2113265991],"type":"Point"}
}