{
  "type": "Feature",
  "properties": {
    "addr:full":"The Club House, Garforth Leeds North Yorkshire LS25 2DS",
    "addr:postcode":"ls25 2ds",
    "addr:street":"Garforth",
    "iso:country":"GB",
    "sg:address":"The Club House, Garforth",
    "sg:city":"Leeds",
    "sg:classifiers":[
        {
            "category":"Sports & Exercise",
            "subcategory":"Golf",
            "type":"Entertainment"
        }
    ],
    "sg:phone":"+44 113 286 2063",
    "sg:postcode":"LS25 2DS",
    "sg:province":"North Yorkshire",
    "sg:tags":[
        "club",
        "course"
    ],
    "wof:name":"The Garforth Golf Club Ltd.",
    "wof:placetype":"venue"
},
  "geometry": {"coordinates":[-1.3759390116,53.7959594727],"type":"Point"}
}