{
  "type": "Feature",
  "properties": {
    "addr:full":"2 Claystones, Ladybridge Drive Northampton Northamptonshire NN4 9UY",
    "addr:housenumber":"2",
    "addr:postcode":"nn4 9uy",
    "addr:street":"Claystones Ladybridge Drive",
    "iso:country":"GB",
    "sg:address":"2 Claystones, Ladybridge Drive",
    "sg:city":"Northampton",
    "sg:classifiers":[
        {
            "category":"Building & Trades",
            "subcategory":"Plumbing",
            "type":"Services"
        }
    ],
    "sg:phone":"+44 1604 700709",
    "sg:postcode":"NN4 9UY",
    "sg:province":"Northamptonshire",
    "sg:tags":[
        "heating"
    ],
    "wof:name":"Pearson Plumbing & Heating",
    "wof:placetype":"venue"
},
  "geometry": {"coordinates":[-0.93407,52.221157],"type":"Point"}
}