{
  "type": "Feature",
  "properties": {
    "iso:country":"GB",
    "sg:address":"Unit 21a, Winford Farm, The Belbins, Yokesford Hill",
    "sg:city":"Romsey",
    "sg:classifiers":[
        {
            "category":"Wholesale",
            "subcategory":"Scrap",
            "type":"Manufacturing & Wholesale Goods"
        }
    ],
    "sg:phone":"+44 1794 367850",
    "sg:postcode":"SO51 0PE",
    "sg:province":"Hampshire",
    "sg:tags":[
        "car",
        "breaker",
        "dismantlers"
    ],
    "wof:name":"Palmer & Bull Breakers",
    "wof:placetype":"venue"
},
  "geometry": {"coordinates":[-1.495391,50.988583],"type":"Point"}
}