{
  "type": "Feature",
  "properties": {
    "iso:country":"GB",
    "sg:address":"31 Union Street",
    "sg:city":"Hereford",
    "sg:classifiers":[
        {
            "category":"Shopping",
            "subcategory":"Department Store",
            "type":"Retail Goods"
        }
    ],
    "sg:postcode":"HR1 2BT",
    "sg:province":"Herefordshire",
    "wof:name":"Seldona",
    "wof:placetype":"venue"
},
  "geometry": {"coordinates":[-2.713019,52.056644],"type":"Point"}
}