{
  "type": "Feature",
  "properties": {
    "iso:country":"GB",
    "sg:address":"33 High Street, Holbeach",
    "sg:city":"Spalding",
    "sg:classifiers":[
        {
            "category":"Retail",
            "subcategory":"Laundry & Dry Cleaning",
            "type":"Services"
        }
    ],
    "sg:postcode":"PE12 7DY",
    "sg:province":"Cambridgeshire",
    "sg:tags":[
        "alteration"
    ],
    "wof:name":"Camerons Quality Dry Cleaning",
    "wof:placetype":"venue"
},
  "geometry": {"coordinates":[0.015651,52.803902],"type":"Point"}
}