{
  "type": "Feature",
  "properties": {
    "iso:country":"GB",
    "sg:address":"42 Pinehurst Road",
    "sg:city":"Ferndown",
    "sg:classifiers":[
        {
            "category":"Professional",
            "subcategory":"Engineering",
            "type":"Services"
        },
        {
            "category":"Professional",
            "subcategory":"Detective & Security Services",
            "type":"Services"
        }
    ],
    "sg:phone":"+44 1202 896826",
    "sg:postcode":"BH22 0AP",
    "sg:province":"Dorset",
    "sg:tags":[
        "burglar",
        "alarm",
        "system",
        "contractor",
        "electrical",
        "engineer"
    ],
    "wof:name":"Bembar Alarms",
    "wof:placetype":"venue"
},
  "geometry": {"coordinates":[-1.881804,50.820724],"type":"Point"}
}