{
  "type": "Feature",
  "properties": {
    "iso:country":"GB",
    "sg:address":"2 Church Street",
    "sg:city":"Cobham",
    "sg:classifiers":[
        {
            "category":"Shopping",
            "subcategory":"Clothing, Apparel, & Fashions",
            "type":"Retail Goods"
        }
    ],
    "sg:phone":"+44 1932 868384",
    "sg:postcode":"KT11 3EG",
    "sg:province":"Surrey",
    "sg:tags":[
        "lady",
        "fashionwear",
        "ladieswear"
    ],
    "wof:name":"le Papillon",
    "wof:placetype":"venue"
},
  "geometry": {"coordinates":[-0.410360992,51.3271636963],"type":"Point"}
}