{
  "type": "Feature",
  "properties": {
    "addr:full":"Units 36-37 Purfleet Industrial Park, London Road South Ockendon Essex RM15 4YA",
    "addr:housenumber":"units 36-37",
    "addr:postcode":"rm15 4ya",
    "addr:street":"Purfleet Industrial Park London Road",
    "iso:country":"GB",
    "sg:address":"Units 36-37 Purfleet Industrial Park, London Road",
    "sg:city":"South Ockendon",
    "sg:classifiers":[
        {
            "category":"Freight",
            "type":"Transportation"
        },
        {
            "category":"Retail",
            "subcategory":"Storage",
            "type":"Services"
        }
    ],
    "sg:postcode":"RM15 4YA",
    "sg:province":"Essex",
    "sg:tags":[
        "household",
        "overseas",
        "shipping",
        "removal"
    ],
    "wof:name":"Double E Vintage",
    "wof:placetype":"venue"
},
  "geometry": {"coordinates":[0.28365,51.502476],"type":"Point"}
}