{
  "type": "Feature",
  "properties": {
    "addr:full":"1 Kings Arcade Lancaster Lancashire LA1 1LE",
    "addr:housenumber":"1",
    "addr:postcode":"la1 1le",
    "addr:street":"Kings Arcade",
    "iso:country":"GB",
    "sg:address":"1 Kings Arcade",
    "sg:city":"Lancaster",
    "sg:classifiers":[
        {
            "category":"Shopping",
            "subcategory":"Clothing, Apparel, & Fashions",
            "type":"Retail Goods"
        }
    ],
    "sg:phone":"+44 1524 33366",
    "sg:postcode":"LA1 1LE",
    "sg:province":"Lancashire",
    "sg:tags":[
        "menswear"
    ],
    "wof:name":"Lapel Menswear",
    "wof:placetype":"venue"
},
  "geometry": {"coordinates":[-2.802147,54.047871],"type":"Point"}
}