{
  "type": "Feature",
  "properties": {
    "iso:country":"GB",
    "sg:address":"The Firs, Harlow Common",
    "sg:city":"Harlow",
    "sg:classifiers":[
        {
            "category":"Building & Trades",
            "subcategory":"Construction",
            "type":"Services"
        }
    ],
    "sg:phone":"+44 1279 430116",
    "sg:postcode":"CM17 9NE",
    "sg:province":"Essex",
    "sg:tags":[
        "restoration",
        "refurbishment"
    ],
    "wof:name":"Richard Dorsett",
    "wof:placetype":"venue"
},
  "geometry": {"coordinates":[0.1397799999,51.7549095154],"type":"Point"}
}