{
  "type": "Feature",
  "properties": {
    "iso:country":"GB",
    "sg:address":"Marisfield Place, Selsey",
    "sg:city":"Chichester",
    "sg:classifiers":[
        {
            "category":"Health Services",
            "subcategory":"Podiatrist",
            "type":"Services"
        }
    ],
    "sg:phone":"+44 1243 607031",
    "sg:postcode":"PO20 0PD",
    "sg:province":"West Sussex",
    "sg:tags":[
        "podiatrists",
        "chiropodist"
    ],
    "wof:name":"Georgina Brown",
    "wof:placetype":"venue"
},
  "geometry": {"coordinates":[-0.7829189897,50.7417106628],"type":"Point"}
}