{
  "type": "Feature",
  "properties": {
    "addr:full":"295 Sandycombe Road Richmond Greater London TW9 3LU",
    "addr:housenumber":"295",
    "addr:postcode":"tw9 3lu",
    "addr:street":"Sandycombe Road",
    "iso:country":"GB",
    "sg:address":"295 Sandycombe Road",
    "sg:city":"Richmond",
    "sg:classifiers":[
        {
            "category":"Personal",
            "subcategory":"Beauty Salon",
            "type":"Services"
        }
    ],
    "sg:phone":"+44 20 8948 8609",
    "sg:postcode":"TW9 3LU",
    "sg:province":"Greater London",
    "sg:tags":[
        "unisex",
        "hairdresser"
    ],
    "wof:name":"Q-Cut",
    "wof:placetype":"venue"
},
  "geometry": {"coordinates":[-0.286438,51.474804],"type":"Point"}
}