{
  "type": "Feature",
  "properties": {
    "addr:full":"Unit 1/2, Essington Light Industrial Estate, Bognop Road Wolverhampton Staffordshire WV11 2BH",
    "addr:housenumber":"unit 1 / 2",
    "addr:postcode":"wv11 2bh",
    "addr:street":"Bognop Road",
    "iso:country":"GB",
    "sg:address":"Unit 1/2, Essington Light Industrial Estate, Bognop Road",
    "sg:city":"Wolverhampton",
    "sg:classifiers":[
        {
            "category":"Retail",
            "subcategory":"Auto Repair",
            "type":"Services"
        }
    ],
    "sg:phone":"+44 1922 477888",
    "sg:postcode":"WV11 2BH",
    "sg:province":"Staffordshire",
    "sg:tags":[
        "modification",
        "garage"
    ],
    "wof:name":"Mobile Vehicle Services",
    "wof:placetype":"venue"
},
  "geometry": {"coordinates":[-2.121669,52.58865],"type":"Point"}
}