{
  "type": "Feature",
  "properties": {
    "addr:full":"Tring Road Aylesbury Buckinghamshire HP20 1PQ",
    "addr:postcode":"hp20 1pq",
    "addr:street":"Tring Road",
    "iso:country":"GB",
    "sg:address":"Tring Road",
    "sg:city":"Aylesbury",
    "sg:classifiers":[
        {
            "category":"Food & Beverages",
            "subcategory":"Supermarket",
            "type":"Retail Goods"
        }
    ],
    "sg:phone":"+44 1296 552400",
    "sg:postcode":"HP20 1PQ",
    "sg:province":"Buckinghamshire",
    "wof:name":"Tesco Stores Ltd.",
    "wof:placetype":"venue"
},
  "geometry": {"coordinates":[-0.7910450101,51.8151702881],"type":"Point"}
}