{
  "type": "Feature",
  "properties": {
    "iso:country":"GB",
    "sg:address":"202 Chorley Old Road",
    "sg:city":"Bolton",
    "sg:classifiers":[
        {
            "category":"Travel",
            "subcategory":"Travel Agent",
            "type":"Entertainment"
        }
    ],
    "sg:phone":"+44 1204 492413",
    "sg:postcode":"BL1 3BG",
    "sg:province":"Lancashire",
    "wof:name":"St Andrews Travel Centres",
    "wof:placetype":"venue"
},
  "geometry": {"coordinates":[-2.448803,53.585419],"type":"Point"}
}