{
  "type": "Feature",
  "properties": {
    "addr:full":"Tunstead, Leek Road Stoke-on-trent Staffordshire ST9 9NJ",
    "addr:postcode":"st9 9nj",
    "addr:street":"Leek Road",
    "iso:country":"GB",
    "sg:address":"Tunstead, Leek Road",
    "sg:city":"Stoke-on-trent",
    "sg:classifiers":[
        {
            "category":"Home & Garden",
            "subcategory":"Hardware",
            "type":"Retail Goods"
        }
    ],
    "sg:postcode":"ST9 9NJ",
    "sg:province":"Staffordshire",
    "sg:tags":[
        "paint"
    ],
    "wof:name":"Biomastic Ltd.",
    "wof:placetype":"venue"
},
  "geometry": {"coordinates":[-2.11935,53.068241],"type":"Point"}
}