{
  "type": "Feature",
  "properties": {
    "iso:country":"GB",
    "sg:address":"4 Weyside Park, Newman Lane",
    "sg:city":"Alton",
    "sg:classifiers":[
        {
            "category":"Real Estate",
            "subcategory":"Architect",
            "type":"Services"
        }
    ],
    "sg:postcode":"GU34 2PJ",
    "sg:province":"Hampshire",
    "wof:name":"John Graham Associates",
    "wof:placetype":"venue"
},
  "geometry": {"coordinates":[-0.9743289948,51.1475601196],"type":"Point"}
}