{
  "type": "Feature",
  "properties": {
    "iso:country":"GB",
    "sg:address":"207-209 Nantwich Rd",
    "sg:city":"Crewe",
    "sg:classifiers":[
        {
            "category":"Food & Beverages",
            "subcategory":"Groceries & Convenience Stores",
            "type":"Retail Goods"
        }
    ],
    "sg:phone":"+44 1270 500398",
    "sg:postcode":"CW2 6DD",
    "sg:province":"Cheshire",
    "wof:name":"Dawn Til Dusk",
    "wof:placetype":"venue"
},
  "geometry": {"coordinates":[-2.445738,53.087524],"type":"Point"}
}