{
  "type": "Feature",
  "properties": {
    "iso:country":"GB",
    "sg:address":"Unit C, Modern Moulds Business Centre, Commerce Way",
    "sg:city":"Lancing",
    "sg:classifiers":[
        {
            "category":"Building & Trades",
            "subcategory":"Landscaping Services",
            "type":"Services"
        }
    ],
    "sg:phone":"+44 1903 851857",
    "sg:postcode":"BN15 8TA",
    "sg:province":"West Sussex",
    "sg:tags":[
        "pond",
        "aquarium"
    ],
    "wof:name":"Shoreham Fibreglass",
    "wof:placetype":"venue"
},
  "geometry": {"coordinates":[-0.318039,50.8218994141],"type":"Point"}
}