{
  "type": "Feature",
  "properties": {
    "addr:full":"Chapel Lane, Epperstone Nottingham Nottinghamshire NG14 6AQ",
    "addr:postcode":"ng14 6aq",
    "addr:street":"Chapel Lane",
    "iso:country":"GB",
    "sg:address":"Chapel Lane, Epperstone",
    "sg:city":"Nottingham",
    "sg:classifiers":[
        {
            "category":"Shopping",
            "subcategory":"Party Supplies",
            "type":"Retail Goods"
        }
    ],
    "sg:postcode":"NG14 6AQ",
    "sg:province":"Nottinghamshire",
    "sg:tags":[
        "marquees",
        "floor",
        "tent"
    ],
    "wof:name":"Buster Marquees",
    "wof:placetype":"venue"
},
  "geometry": {"coordinates":[-1.028779,53.032711],"type":"Point"}
}