{
  "type": "Feature",
  "properties": {
    "iso:country":"GB",
    "sg:address":"Colne House, 99a Uxbridge Road",
    "sg:city":"Rickmansworth",
    "sg:classifiers":[
        {
            "category":"Health Services",
            "subcategory":"Doctor",
            "type":"Services"
        }
    ],
    "sg:phone":"+44 1923 776295",
    "sg:postcode":"WD3 7DJ",
    "sg:province":"Hertfordshire",
    "sg:tags":[
        "practitioners"
    ],
    "wof:name":"Zane & Partners",
    "wof:placetype":"venue"
},
  "geometry": {"coordinates":[-0.484578,51.635555],"type":"Point"}
}