{
  "type": "Feature",
  "properties": {
    "addr:full":"80 Elmfield Avenue Teddington Greater London TW11 8BT",
    "addr:housenumber":"80",
    "addr:postcode":"tw11 8bt",
    "addr:street":"Elmfield Avenue",
    "iso:country":"GB",
    "sg:address":"80 Elmfield Avenue",
    "sg:city":"Teddington",
    "sg:classifiers":[
        {
            "category":"Professional",
            "subcategory":"Accounting & Tax Preparation",
            "type":"Services"
        }
    ],
    "sg:postcode":"TW11 8BT",
    "sg:province":"Greater London",
    "sg:tags":[
        "accountant"
    ],
    "wof:name":"Modiga Ltd.",
    "wof:placetype":"venue"
},
  "geometry": {"coordinates":[-0.331576,51.430435],"type":"Point"}
}