{
  "type": "Feature",
  "properties": {
    "addr:full":"The Cedars, Elvington Lane, Hawkinge Folkestone Kent CT18 7AD",
    "addr:postcode":"ct18 7ad",
    "addr:street":"Elvington Lane",
    "iso:country":"GB",
    "sg:address":"The Cedars, Elvington Lane, Hawkinge",
    "sg:city":"Folkestone",
    "sg:classifiers":[
        {
            "category":"Professional",
            "subcategory":"Advertising",
            "type":"Services"
        }
    ],
    "sg:phone":"+44 1303 893472",
    "sg:postcode":"CT18 7AD",
    "sg:province":"Kent",
    "wof:name":"Kent & East Sussex Gig Guide",
    "wof:placetype":"venue"
},
  "geometry": {"coordinates":[1.164715,51.115768],"type":"Point"}
}