{
  "type": "Feature",
  "properties": {
    "addr:full":"Magnet Industrial Estate, London Road Grays Essex RM16 1DB",
    "addr:postcode":"rm16 1db",
    "addr:street":"Estate London Road",
    "iso:country":"GB",
    "sg:address":"Magnet Industrial Estate, London Road",
    "sg:city":"Grays",
    "sg:classifiers":[
        {
            "category":"Retail",
            "subcategory":"Auto Repair",
            "type":"Services"
        }
    ],
    "sg:phone":"+44 1375 372952",
    "sg:postcode":"RM16 1DB",
    "sg:province":"Essex",
    "sg:tags":[
        "body",
        "car"
    ],
    "wof:name":"Tomlin International",
    "wof:placetype":"venue"
},
  "geometry": {"coordinates":[0.3427000046,51.5054206848],"type":"Point"}
}