{
  "type": "Feature",
  "properties": {
    "addr:full":"76 Battersea Rise London Greater London SW11 1EH",
    "addr:housenumber":"76",
    "addr:postcode":"sw11 1eh",
    "addr:street":"Battersea Rise",
    "iso:country":"GB",
    "sg:address":"76 Battersea Rise",
    "sg:city":"London",
    "sg:classifiers":[
        {
            "category":"Manufacturing",
            "subcategory":"Rubber & Plastics",
            "type":"Manufacturing & Wholesale Goods"
        },
        {
            "category":"Home & Garden",
            "subcategory":"Home Furnishings",
            "type":"Retail Goods"
        }
    ],
    "sg:phone":"+44 20 7228 0805",
    "sg:postcode":"SW11 1EH",
    "sg:province":"Greater London",
    "sg:tags":[
        "product",
        "foam",
        "soft",
        "sale"
    ],
    "wof:name":"Southern Foam",
    "wof:placetype":"venue"
},
  "geometry": {"coordinates":[-0.167569,51.460926],"type":"Point"}
}