{
  "type": "Feature",
  "properties": {
    "addr:full":"29 Kennard Road New Milton Hampshire BH25 5JR",
    "addr:housenumber":"29",
    "addr:postcode":"bh25 5jr",
    "addr:street":"Kennard Road",
    "iso:country":"GB",
    "sg:address":"29 Kennard Road",
    "sg:city":"New Milton",
    "sg:classifiers":[
        {
            "category":"Social Services",
            "subcategory":"Retirement Home",
            "type":"Services"
        }
    ],
    "sg:phone":"+44 1425 610144",
    "sg:postcode":"BH25 5JR",
    "sg:province":"Hampshire",
    "sg:tags":[
        "residential",
        "care"
    ],
    "wof:name":"Grey Gables",
    "wof:placetype":"venue"
},
  "geometry": {"coordinates":[-1.661723,50.757915],"type":"Point"}
}