{
  "type": "Feature",
  "properties": {
    "iso:country":"GB",
    "sg:address":"26 Jumpers Road",
    "sg:city":"Christchurch",
    "sg:classifiers":[
        {
            "category":"Building & Trades",
            "subcategory":"Cleaning & Sanitation",
            "type":"Services"
        },
        {
            "category":"Home & Garden",
            "subcategory":"Carpets & Floor Coverings",
            "type":"Retail Goods"
        }
    ],
    "sg:phone":"+44 1202 476046",
    "sg:postcode":"BH23 2JT",
    "sg:province":"Dorset",
    "sg:tags":[
        "textile",
        "resurfacing",
        "laying",
        "refinishing",
        "floorcoverings"
    ],
    "wof:name":"M & B Carpet & Flooring Contractors",
    "wof:placetype":"venue"
},
  "geometry": {"coordinates":[-1.7916339636,50.7431716919],"type":"Point"}
}