{
  "type": "Feature",
  "properties": {
    "iso:country":"GB",
    "sg:address":"Somers House, 1 Somers Road",
    "sg:city":"Reigate",
    "sg:classifiers":[
        {
            "category":"Organizations",
            "subcategory":"Membership Organization",
            "type":"Services"
        }
    ],
    "sg:postcode":"RH2 9DU",
    "sg:province":"Surrey",
    "sg:tags":[
        "club"
    ],
    "wof:name":"Manufacture's Agent's Association Of Great Britain",
    "wof:placetype":"venue"
},
  "geometry": {"coordinates":[-0.207418,51.242908],"type":"Point"}
}