{
  "type": "Feature",
  "properties": {
    "iso:country":"GB",
    "sg:address":"368 Cementery Road",
    "sg:city":"Sheffield",
    "sg:classifiers":[
        {
            "category":"Professional",
            "subcategory":"Accounting & Tax Preparation",
            "type":"Services"
        }
    ],
    "sg:phone":"+44 114 266 8030",
    "sg:postcode":"S11 8FT",
    "sg:province":"Derbyshire",
    "sg:tags":[
        "accountant"
    ],
    "wof:name":"Nigel R Hale & Associates",
    "wof:placetype":"venue"
},
  "geometry": {"coordinates":[-1.488791,53.367603],"type":"Point"}
}