{
  "type": "Feature",
  "properties": {
    "addr:full":"10 Denham Rd Sheffield Derbyshire S11 8NE",
    "addr:housenumber":"10",
    "addr:postcode":"s11 8ne",
    "addr:street":"Denham Rd",
    "iso:country":"GB",
    "sg:address":"10 Denham Rd",
    "sg:city":"Sheffield",
    "sg:classifiers":[
        {
            "category":"Professional",
            "type":"Services"
        }
    ],
    "sg:phone":"+44 114 266 1883",
    "sg:postcode":"S11 8NE",
    "sg:province":"Derbyshire",
    "sg:tags":[
        "entertainer"
    ],
    "wof:name":"Louie Van Magic Baloon Man The",
    "wof:placetype":"venue"
},
  "geometry": {"coordinates":[-1.4905860424,53.3705368042],"type":"Point"}
}