{
  "type": "Feature",
  "properties": {
    "addr:full":"118b High St, Billericay Essex CM12 9BY",
    "addr:housenumber":"118b",
    "addr:postcode":"cm12 9by",
    "addr:street":"High St",
    "iso:country":"GB",
    "sg:address":"118b High St,",
    "sg:city":"Billericay",
    "sg:classifiers":[
        {
            "category":"Professional",
            "subcategory":"Testing Lab",
            "type":"Services"
        }
    ],
    "sg:postcode":"CM12 9BY",
    "sg:province":"Essex",
    "sg:tags":[
        "inspection",
        "calibration"
    ],
    "wof:name":"Baker Precision Tools Ltd",
    "wof:placetype":"venue"
},
  "geometry": {"coordinates":[0.416324,51.623917],"type":"Point"}
}