{
  "type": "Feature",
  "properties": {
    "iso:country":"GB",
    "sg:address":"65 Heath Street",
    "sg:city":"London",
    "sg:classifiers":[
        {
            "category":"Home & Garden",
            "subcategory":"Furniture",
            "type":"Retail Goods"
        }
    ],
    "sg:phone":"+44 20 7431 4008",
    "sg:postcode":"NW3 6UG",
    "sg:province":"Greater London",
    "wof:name":"Ruth Aram Shop Ltd.",
    "wof:placetype":"venue"
},
  "geometry": {"coordinates":[-0.178516,51.557037],"type":"Point"}
}