{
  "type": "Feature",
  "properties": {
    "iso:country":"GB",
    "sg:address":"16 Wynn Avenue",
    "sg:city":"Colwyn Bay",
    "sg:classifiers":[
        {
            "category":"Health Services",
            "subcategory":"Doctor",
            "type":"Services"
        }
    ],
    "sg:phone":"+44 1492 515500",
    "sg:postcode":"LL29 9RF",
    "sg:province":"Conwy",
    "sg:tags":[
        "practitioners"
    ],
    "wof:name":"U K & S Bisarya",
    "wof:placetype":"venue"
},
  "geometry": {"coordinates":[-3.695224,53.289921],"type":"Point"}
}