{
  "type": "Feature",
  "properties": {
    "iso:country":"GB",
    "sg:address":"9 Sprays, Burbage",
    "sg:city":"Marlborough",
    "sg:classifiers":[
        {
            "category":"Health Services",
            "subcategory":"Doctor",
            "type":"Services"
        }
    ],
    "sg:phone":"+44 1672 810566",
    "sg:postcode":"SN8 3TA",
    "sg:province":"Berkshire",
    "sg:tags":[
        "practitioners"
    ],
    "wof:name":"Lucinda King",
    "wof:placetype":"venue"
},
  "geometry": {"coordinates":[-1.6697690487,51.348274231],"type":"Point"}
}