{
  "type": "Feature",
  "properties": {
    "iso:country":"GB",
    "sg:address":"Painthorpe Lane, Crigglestone",
    "sg:city":"Wakefield",
    "sg:classifiers":[
        {
            "category":"Education",
            "subcategory":"School",
            "type":"Public Place"
        },
        {
            "category":"Government",
            "subcategory":"Office",
            "type":"Public Place"
        }
    ],
    "sg:phone":"+44 1924 303520",
    "sg:postcode":"WF4 3HW",
    "sg:province":"West Yorkshire",
    "sg:tags":[
        "local",
        "authority"
    ],
    "wof:name":"Mackie Hill Junior & Infants School",
    "wof:placetype":"venue"
},
  "geometry": {"coordinates":[-1.5230180025,53.6342926025],"type":"Point"}
}