{
  "type": "Feature",
  "properties": {
    "addr:full":"Botley Road, Fair Oak Eastleigh Hampshire SO50 7AN",
    "addr:postcode":"so50 7an",
    "addr:street":"Botley Road",
    "iso:country":"GB",
    "sg:address":"Botley Road, Fair Oak",
    "sg:city":"Eastleigh",
    "sg:classifiers":[
        {
            "category":"Education",
            "subcategory":"School",
            "type":"Public Place"
        }
    ],
    "sg:phone":"+44 23 8069 2207",
    "sg:postcode":"SO50 7AN",
    "sg:province":"Hampshire",
    "sg:tags":[
        "local",
        "authority"
    ],
    "wof:name":"Fair Oak County Infants School",
    "wof:placetype":"venue"
},
  "geometry": {"coordinates":[-1.2907940149,50.9654312134],"type":"Point"}
}