{
  "type": "Feature",
  "properties": {
    "iso:country":"GB",
    "sg:address":"27 Swindon Street, Highworth",
    "sg:city":"Swindon",
    "sg:classifiers":[
        {
            "category":"Fast Food",
            "type":"Food & Drink"
        }
    ],
    "sg:phone":"+44 1793 762826",
    "sg:postcode":"SN6 7AH",
    "sg:province":"Gloucestershire",
    "sg:tags":[
        "away",
        "meal",
        "outlet",
        "take"
    ],
    "wof:name":"Sammys Take Away",
    "wof:placetype":"venue"
},
  "geometry": {"coordinates":[-1.7119539976,51.6291923523],"type":"Point"}
}