{
  "type": "Feature",
  "properties": {
    "addr:full":"28 Miller Road Ayr South Ayrshire KA7 2AY",
    "addr:housenumber":"28",
    "addr:postcode":"ka7 2ay",
    "addr:street":"Miller Road",
    "iso:country":"GB",
    "sg:address":"28 Miller Road",
    "sg:city":"Ayr",
    "sg:classifiers":[
        {
            "category":"Professional",
            "subcategory":"Accounting & Tax Preparation",
            "type":"Services"
        }
    ],
    "sg:phone":"+44 1292 266496",
    "sg:postcode":"KA7 2AY",
    "sg:province":"South Ayrshire",
    "sg:tags":[
        "accountant",
        "activity"
    ],
    "wof:name":"K F McKeown & Co",
    "wof:placetype":"venue"
},
  "geometry": {"coordinates":[-4.6326570511,55.4583511353],"type":"Point"}
}