{
  "type": "Feature",
  "properties": {
    "iso:country":"GB",
    "sg:address":"Royal Insurance Buildings, Lonsdale Street",
    "sg:city":"Carlisle",
    "sg:classifiers":[
        {
            "category":"Manufacturing",
            "subcategory":"Tools & Machinery",
            "type":"Manufacturing & Wholesale Goods"
        }
    ],
    "sg:phone":"+44 1228 547232",
    "sg:postcode":"CA1 1BU",
    "sg:province":"Cumbria",
    "sg:tags":[
        "society",
        "friendly"
    ],
    "wof:name":"McLarens Toplis",
    "wof:placetype":"venue"
},
  "geometry": {"coordinates":[-2.93299,54.893902],"type":"Point"}
}