{
  "type": "Feature",
  "properties": {
    "iso:country":"GB",
    "sg:address":"3 Kingston Avenue",
    "sg:city":"Margate",
    "sg:classifiers":[
        {
            "category":"Building & Trades",
            "subcategory":"Construction",
            "type":"Services"
        }
    ],
    "sg:phone":"+44 1843 292310",
    "sg:postcode":"CT9 5NH",
    "sg:province":"Kent",
    "sg:tags":[
        "dry",
        "plastering",
        "plasterers",
        "lining",
        "related",
        "screeders"
    ],
    "wof:name":"Bradley & Parris",
    "wof:placetype":"venue"
},
  "geometry": {"coordinates":[1.358382,51.374928],"type":"Point"}
}