{
  "type": "Feature",
  "properties": {
    "addr:full":"64 Horbury Road Wakefield West Yorkshire WF2 8TU",
    "addr:housenumber":"64",
    "addr:postcode":"wf2 8tu",
    "addr:street":"Horbury Road",
    "iso:country":"GB",
    "sg:address":"64 Horbury Road",
    "sg:city":"Wakefield",
    "sg:classifiers":[
        {
            "category":"Manufacturing",
            "subcategory":"Wood Products",
            "type":"Manufacturing & Wholesale Goods"
        }
    ],
    "sg:phone":"+44 1924 371879",
    "sg:postcode":"WF2 8TU",
    "sg:province":"West Yorkshire",
    "sg:tags":[
        "maker",
        "cabinet"
    ],
    "wof:name":"Goldcross Kitchens Ltd.",
    "wof:placetype":"venue"
},
  "geometry": {"coordinates":[-1.515715,53.677731],"type":"Point"}
}