{
  "type": "Feature",
  "properties": {
    "addr:full":"Annandale Road London Greater London SE10 0JY",
    "addr:postcode":"se10 0jy",
    "addr:street":"Annandale Road",
    "iso:country":"GB",
    "sg:address":"Annandale Road",
    "sg:city":"London",
    "sg:classifiers":[
        {
            "category":"Education",
            "subcategory":"School",
            "type":"Public Place"
        },
        {
            "category":"Government",
            "subcategory":"Office",
            "type":"Public Place"
        }
    ],
    "sg:phone":"+44 20 8858 0394",
    "sg:postcode":"SE10 0JY",
    "sg:province":"Greater London",
    "sg:tags":[
        "local",
        "authority"
    ],
    "wof:name":"Annandale Primary School",
    "wof:placetype":"venue"
},
  "geometry": {"coordinates":[0.011877,51.485126],"type":"Point"}
}