{
  "type": "Feature",
  "properties": {
    "iso:country":"GB",
    "sg:address":"Canterbury Road, Chilham",
    "sg:city":"Canterbury",
    "sg:classifiers":[
        {
            "category":"Building & Trades",
            "subcategory":"Construction",
            "type":"Services"
        }
    ],
    "sg:phone":"+44 1227 732100",
    "sg:postcode":"CT4 8DZ",
    "sg:province":"Kent",
    "sg:tags":[
        "joinery"
    ],
    "wof:name":"Olympia Interiors Ltd.",
    "wof:placetype":"venue"
},
  "geometry": {"coordinates":[0.963739,51.243881],"type":"Point"}
}