{
  "type": "Feature",
  "properties": {
    "iso:country":"GB",
    "sg:address":"Holbrook Tythe Barn, Pondtail Road",
    "sg:city":"Horsham",
    "sg:classifiers":[
        {
            "category":"Farming",
            "subcategory":"Nursery",
            "type":"Manufacturing & Wholesale Goods"
        }
    ],
    "sg:phone":"+44 1403 276336",
    "sg:postcode":"RH12 5HL",
    "sg:province":"West Sussex",
    "sg:tags":[
        "creche"
    ],
    "wof:name":"Wagtail Day Nursery",
    "wof:placetype":"venue"
},
  "geometry": {"coordinates":[-0.329107,51.065182],"type":"Point"}
}