{
  "type": "Feature",
  "properties": {
    "addr:full":"Ky-gwydyr Aberdovey Gwynedd LL35 0NA",
    "addr:postcode":"ll35 0na",
    "addr:street":"Aberdovey",
    "iso:country":"GB",
    "sg:address":"Ky-gwydyr",
    "sg:city":"Aberdovey",
    "sg:classifiers":[
        {
            "category":"Professional",
            "subcategory":"Management & Consulting",
            "type":"Services"
        }
    ],
    "sg:phone":"+44 1654 767740",
    "sg:postcode":"LL35 0NA",
    "sg:province":"Gwynedd",
    "sg:tags":[
        "marketing",
        "consultant"
    ],
    "wof:name":"C B Collier",
    "wof:placetype":"venue"
},
  "geometry": {"coordinates":[-4.044138,52.544083],"type":"Point"}
}