{
  "type": "Feature",
  "properties": {
    "iso:country":"GB",
    "sg:address":"53 Church Avenue",
    "sg:city":"Mortlake",
    "sg:classifiers":[
        {
            "category":"Professional",
            "subcategory":"Employment Agencies",
            "type":"Services"
        }
    ],
    "sg:phone":"+44 20 8876 7039",
    "sg:postcode":"SW14 8NL",
    "sg:province":"Greater London",
    "sg:tags":[
        "consultant"
    ],
    "wof:name":"Bees Knees Agency",
    "wof:placetype":"venue"
},
  "geometry": {"coordinates":[-0.264127,51.467194],"type":"Point"}
}