{
  "type": "Feature",
  "properties": {
    "iso:country":"GB",
    "sg:address":"5 Lentney Clo, Heybrook Bay",
    "sg:city":"Plymouth",
    "sg:classifiers":[
        {
            "category":"Bakery",
            "type":"Food & Drink"
        }
    ],
    "sg:postcode":"PL9 0DU",
    "sg:province":"Devon",
    "sg:tags":[
        "cake",
        "maker"
    ],
    "wof:name":"White,Carol,",
    "wof:placetype":"venue"
},
  "geometry": {"coordinates":[-4.1097841263,50.3236351013],"type":"Point"}
}