{
  "type": "Feature",
  "properties": {
    "addr:full":"Gallantry House, Chapel Lane, Stoke Heath Market Drayton Shropshire TF9 2JT",
    "addr:postcode":"tf9 2jt",
    "addr:street":"Chapel Lane",
    "iso:country":"GB",
    "sg:address":"Gallantry House, Chapel Lane, Stoke Heath",
    "sg:city":"Market Drayton",
    "sg:classifiers":[
        {
            "category":"Professional",
            "type":"Services"
        },
        {
            "category":"Manufacturing",
            "subcategory":"Electronics",
            "type":"Manufacturing & Wholesale Goods"
        }
    ],
    "sg:phone":"+44 1630 638620",
    "sg:postcode":"TF9 2JT",
    "sg:province":"Shropshire",
    "sg:tags":[
        "control",
        "manufacture",
        "system",
        "panel"
    ],
    "wof:name":"Jupiter Control Systems Ltd",
    "wof:placetype":"venue"
},
  "geometry": {"coordinates":[-2.521414,52.860485],"type":"Point"}
}