{
  "type": "Feature",
  "properties": {
    "addr:full":"Haslemere Avenue Mitcham Greater London CR4 3PQ",
    "addr:postcode":"cr4 3pq",
    "addr:street":"Haslemere Avenue",
    "iso:country":"GB",
    "sg:address":"Haslemere Avenue",
    "sg:city":"Mitcham",
    "sg:classifiers":[
        {
            "category":"Education",
            "subcategory":"School",
            "type":"Public Place"
        }
    ],
    "sg:phone":"+44 20 8648 9660",
    "sg:postcode":"CR4 3PQ",
    "sg:province":"Greater London",
    "sg:tags":[
        "local",
        "authority"
    ],
    "wof:name":"Haslemere First School",
    "wof:placetype":"venue"
},
  "geometry": {"coordinates":[-0.1785590053,51.4091300964],"type":"Point"}
}