{
  "type": "Feature",
  "properties": {
    "addr:full":"Oak Hollow Farm, Prestbury Road Wilmslow Cheshire SK9 2LL",
    "addr:postcode":"sk9 2ll",
    "addr:street":"Oak Hollow Farm Prestbury Road",
    "iso:country":"GB",
    "sg:address":"Oak Hollow Farm, Prestbury Road",
    "sg:city":"Wilmslow",
    "sg:classifiers":[
        {
            "category":"Shopping",
            "subcategory":"Hobbies, Toys, & Games",
            "type":"Retail Goods"
        }
    ],
    "sg:phone":"+44 1625 548383",
    "sg:postcode":"SK9 2LL",
    "sg:province":"Cheshire",
    "sg:tags":[
        "toy"
    ],
    "wof:name":"Philip Harrison Ltd.",
    "wof:placetype":"venue"
},
  "geometry": {"coordinates":[-2.2278969288,53.3267974854],"type":"Point"}
}