{
  "type": "Feature",
  "properties": {
    "addr:full":"549 Cricklade Rd Swindon Wiltshire SN2 1AH",
    "addr:housenumber":"549",
    "addr:postcode":"sn2 1ah",
    "addr:street":"Cricklade Rd",
    "iso:country":"GB",
    "sg:address":"549 Cricklade Rd",
    "sg:city":"Swindon",
    "sg:classifiers":[
        {
            "category":"Shopping",
            "subcategory":"News",
            "type":"Retail Goods"
        }
    ],
    "sg:phone":"+44 1793 724276",
    "sg:postcode":"SN2 1AH",
    "sg:province":"Wiltshire",
    "sg:tags":[
        "newsagent"
    ],
    "wof:name":"Brett & Sons (CTN)",
    "wof:placetype":"venue"
},
  "geometry": {"coordinates":[-1.7758289576,51.5811691284],"type":"Point"}
}