{
  "type": "Feature",
  "properties": {
    "iso:country":"GB",
    "sg:address":"2 Victoria Street, Staple Hill",
    "sg:city":"Bristol",
    "sg:classifiers":[
        {
            "category":"Retail",
            "subcategory":"Auto Repair",
            "type":"Services"
        }
    ],
    "sg:phone":"+44 117 975 5570",
    "sg:postcode":"BS16 5JS",
    "sg:province":"City of Bristol",
    "sg:tags":[
        "modification",
        "garage"
    ],
    "wof:name":"A J Autos",
    "wof:placetype":"venue"
},
  "geometry": {"coordinates":[-2.590479,51.453259],"type":"Point"}
}