{
  "type": "Feature",
  "properties": {
    "addr:full":"Glebe Road, Bowness On Windermere Windermere Cumbria LA23 3HE",
    "addr:postcode":"la23 3he",
    "addr:street":"Glebe Road",
    "iso:country":"GB",
    "sg:address":"Glebe Road, Bowness On Windermere",
    "sg:city":"Windermere",
    "sg:classifiers":[
        {
            "category":"Cafe",
            "type":"Food & Drink"
        }
    ],
    "sg:phone":"+44 15394 46560",
    "sg:postcode":"LA23 3HE",
    "sg:province":"Cumbria",
    "sg:tags":[
        "tea",
        "room"
    ],
    "wof:name":"Oaks Cafe",
    "wof:placetype":"venue"
},
  "geometry": {"coordinates":[-2.9228260517,54.3579025269],"type":"Point"}
}