{
  "type": "Feature",
  "properties": {
    "addr:full":"172 Thirlmere Gardens Northwood Greater London HA6 2RU",
    "addr:housenumber":"172",
    "addr:postcode":"ha6 2ru",
    "addr:street":"Thirlmere Gardens",
    "iso:country":"GB",
    "sg:address":"172 Thirlmere Gardens",
    "sg:city":"Northwood",
    "sg:classifiers":[
        {
            "category":"Professional",
            "subcategory":"Computer Services",
            "type":"Services"
        }
    ],
    "sg:phone":"+44 1923 451075",
    "sg:postcode":"HA6 2RU",
    "sg:province":"Greater London",
    "sg:tags":[
        "system",
        "software"
    ],
    "wof:name":"Arp Programming Ltd.",
    "wof:placetype":"venue"
},
  "geometry": {"coordinates":[-0.439209,51.616219],"type":"Point"}
}