{
  "type": "Feature",
  "properties": {
    "addr:full":"1 Merlin Close Guisborough North Yorkshire TS14 8PE",
    "addr:housenumber":"1",
    "addr:postcode":"ts14 8pe",
    "addr:street":"Merlin Close",
    "iso:country":"GB",
    "sg:address":"1 Merlin Close",
    "sg:city":"Guisborough",
    "sg:classifiers":[
        {
            "category":"Building & Trades",
            "subcategory":"Construction",
            "type":"Services"
        }
    ],
    "sg:postcode":"TS14 8PE",
    "sg:province":"North Yorkshire",
    "sg:tags":[
        "tiling",
        "contractor"
    ],
    "wof:name":"Graham Wood Ceramics Floortiling",
    "wof:placetype":"venue"
},
  "geometry": {"coordinates":[-1.082313,54.531563],"type":"Point"}
}