{
  "type": "Feature",
  "properties": {
    "addr:full":"Studio 19, 10-11 Archer St London Greater London W1D 7AZ",
    "addr:housenumber":"10-11",
    "addr:postcode":"w1d 7az",
    "addr:street":"Archer St",
    "iso:country":"GB",
    "sg:address":"Studio 19, 10-11 Archer St",
    "sg:city":"London",
    "sg:classifiers":[
        {
            "category":"Professional",
            "subcategory":"Art Services",
            "type":"Services"
        }
    ],
    "sg:postcode":"W1D 7AZ",
    "sg:province":"Greater London",
    "sg:tags":[
        "graphic",
        "designer"
    ],
    "wof:name":"Harling,Anne,",
    "wof:placetype":"venue"
},
  "geometry": {"coordinates":[-0.13358,51.51181],"type":"Point"}
}