{
  "type": "Feature",
  "properties": {
    "iso:country":"GB",
    "sg:address":"33-35 Market Street",
    "sg:city":"Bacup",
    "sg:classifiers":[
        {
            "category":"Health Services",
            "subcategory":"Optometrist",
            "type":"Services"
        },
        {
            "category":"Shopping",
            "subcategory":"Optician",
            "type":"Retail Goods"
        }
    ],
    "sg:phone":"+44 1706 874631",
    "sg:postcode":"OL13 0AJ",
    "sg:province":"Lancashire",
    "sg:tags":[
        "ophthalmic"
    ],
    "wof:name":"Clive M Crowther",
    "wof:placetype":"venue"
},
  "geometry": {"coordinates":[-2.2011609077,53.7021865845],"type":"Point"}
}