{
  "type": "Feature",
  "properties": {
    "addr:full":"Unit 1 & 2 The Valley Centre Bank St Rossendale Lancashire BB4 7NP",
    "addr:housenumber":"unit 1 & 2",
    "addr:postcode":"bb4 7np",
    "addr:street":"The;Bank St",
    "iso:country":"GB",
    "sg:address":"Unit 1 & 2 The Valley Centre Bank St",
    "sg:city":"Rossendale",
    "sg:classifiers":[
        {
            "category":"Home & Garden",
            "subcategory":"Household Appliances",
            "type":"Retail Goods"
        }
    ],
    "sg:phone":"+44 1706 224315",
    "sg:postcode":"BB4 7NP",
    "sg:province":"Lancashire",
    "sg:tags":[
        "domestic",
        "centre"
    ],
    "wof:name":"Grace Rentals",
    "wof:placetype":"venue"
},
  "geometry": {"coordinates":[-2.2663600445,53.6980209351],"type":"Point"}
}