{
  "type": "Feature",
  "properties": {
    "addr:full":"Unit 5 St Marys Arcade, St Mary Street Chepstow Gloucestershire NP16 5EU",
    "addr:housenumber":"unit 5 st marys arcade",
    "addr:postcode":"np16 5eu",
    "addr:street":"St Mary Street",
    "iso:country":"GB",
    "sg:address":"Unit 5 St Marys Arcade, St Mary Street",
    "sg:city":"Chepstow",
    "sg:classifiers":[
        {
            "category":"Home & Garden",
            "subcategory":"Carpets & Floor Coverings",
            "type":"Retail Goods"
        }
    ],
    "sg:phone":"+44 1291 621144",
    "sg:postcode":"NP16 5EU",
    "sg:province":"Gloucestershire",
    "sg:tags":[
        "carpets",
        "rug",
        "matting"
    ],
    "wof:name":"Manor Carpets",
    "wof:placetype":"venue"
},
  "geometry": {"coordinates":[-2.6798119545,51.637878418],"type":"Point"}
}