{
  "type": "Feature",
  "properties": {
    "iso:country":"GB",
    "sg:address":"Gowanhill, Rathen",
    "sg:city":"Fraserburgh",
    "sg:classifiers":[
        {
            "category":"Shopping",
            "subcategory":"Department Store",
            "type":"Retail Goods"
        },
        {
            "category":"Food & Beverages",
            "subcategory":"Supermarket",
            "type":"Retail Goods"
        },
        {
            "category":"Food & Beverages",
            "subcategory":"Groceries & Convenience Stores",
            "type":"Retail Goods"
        }
    ],
    "sg:phone":"+44 1346 582207",
    "sg:postcode":"AB43 8UX",
    "sg:province":"Aberdeenshire",
    "wof:name":"A Sutherland & Sons",
    "wof:placetype":"venue"
},
  "geometry": {"coordinates":[-2.0047190189,57.6369590759],"type":"Point"}
}