{
  "type": "Feature",
  "properties": {
    "iso:country":"GB",
    "sg:address":"Walker Barn Farm, Old Meadows Road",
    "sg:city":"Bacup",
    "sg:classifiers":[
        {
            "category":"Farming",
            "subcategory":"Livestock Farm",
            "type":"Manufacturing & Wholesale Goods"
        }
    ],
    "sg:phone":"+44 1706 874755",
    "sg:postcode":"OL13 8PX",
    "sg:province":"Lancashire",
    "sg:tags":[
        "others"
    ],
    "wof:name":"A Balshaw",
    "wof:placetype":"venue"
},
  "geometry": {"coordinates":[-2.201104,53.702717],"type":"Point"}
}