{
  "type": "Feature",
  "properties": {
    "addr:full":"Ace Corner, North Circular Rd Willesden Greater London NW10 7UD",
    "addr:postcode":"nw10 7ud",
    "addr:street":"North Circular Rd",
    "iso:country":"GB",
    "sg:address":"Ace Corner, North Circular Rd",
    "sg:city":"Willesden",
    "sg:classifiers":[
        {
            "category":"Retail",
            "subcategory":"Auto Repair",
            "type":"Services"
        }
    ],
    "sg:phone":"+44 20 8961 9442",
    "sg:postcode":"NW10 7UD",
    "sg:province":"Greater London",
    "sg:tags":[
        "body",
        "car"
    ],
    "wof:name":"Ace Alperton Coach Works",
    "wof:placetype":"venue"
},
  "geometry": {"coordinates":[-0.2790899873,51.5400810242],"type":"Point"}
}