{
  "type": "Feature",
  "properties": {
    "addr:full":"40 Church Street Leigh Lancashire WN7 1BB",
    "addr:housenumber":"40",
    "addr:postcode":"wn7 1bb",
    "addr:street":"Church Street Leigh",
    "iso:country":"GB",
    "sg:address":"40 Church Street",
    "sg:city":"Leigh",
    "sg:classifiers":[
        {
            "category":"Professional",
            "subcategory":"Accounting & Tax Preparation",
            "type":"Services"
        }
    ],
    "sg:phone":"+44 1942 671245",
    "sg:postcode":"WN7 1BB",
    "sg:province":"Lancashire",
    "sg:tags":[
        "accountant"
    ],
    "wof:name":"Topping Partnership",
    "wof:placetype":"venue"
},
  "geometry": {"coordinates":[-2.516418,53.498108],"type":"Point"}
}