{
  "type": "Feature",
  "properties": {
    "iso:country":"GB",
    "sg:address":"15 Fell View",
    "sg:city":"Southport",
    "sg:classifiers":[
        {
            "category":"Professional",
            "subcategory":"Management & Consulting",
            "type":"Services"
        }
    ],
    "sg:phone":"+44 1704 505281",
    "sg:postcode":"PR9 8JX",
    "sg:province":"Lancashire",
    "sg:tags":[
        "consultant",
        "business"
    ],
    "wof:name":"Impetus Business Services",
    "wof:placetype":"venue"
},
  "geometry": {"coordinates":[-2.9452910423,53.6776351929],"type":"Point"}
}