{
  "type": "Feature",
  "properties": {
    "addr:full":"Stainderber, Burton-in-lonsdale Carnforth Cumbria LA6 3LX",
    "addr:postcode":"la6 3lx",
    "addr:street":"Carnforth",
    "iso:country":"GB",
    "sg:address":"Stainderber, Burton-in-lonsdale",
    "sg:city":"Carnforth",
    "sg:classifiers":[
        {
            "category":"Farming",
            "subcategory":"Livestock Farm",
            "type":"Manufacturing & Wholesale Goods"
        }
    ],
    "sg:phone":"+44 15242 41201",
    "sg:postcode":"LA6 3LX",
    "sg:province":"Cumbria",
    "sg:tags":[
        "others"
    ],
    "wof:name":"M Fawcett & Sons",
    "wof:placetype":"venue"
},
  "geometry": {"coordinates":[-2.5325899124,54.1450233459],"type":"Point"}
}