{
  "type": "Feature",
  "properties": {
    "addr:full":"5a Merthyr Road Cardiff Cardiff CF14 1DA",
    "addr:housenumber":"5a",
    "addr:postcode":"cf14 1da",
    "addr:street":"Merthyr Road",
    "iso:country":"GB",
    "sg:address":"5a Merthyr Road",
    "sg:city":"Cardiff",
    "sg:classifiers":[
        {
            "category":"Shopping",
            "subcategory":"Optician",
            "type":"Retail Goods"
        },
        {
            "category":"Manufacturing",
            "subcategory":"Glass & Minerals",
            "type":"Manufacturing & Wholesale Goods"
        }
    ],
    "sg:phone":"+44 29 2052 0651",
    "sg:postcode":"CF14 1DA",
    "sg:province":"Cardiff",
    "sg:tags":[
        "mnfr",
        "glassware",
        "china"
    ],
    "wof:name":"Exclusive Rimless Designs",
    "wof:placetype":"venue"
},
  "geometry": {"coordinates":[-3.219979,51.513096],"type":"Point"}
}