{
  "type": "Feature",
  "properties": {
    "addr:full":"214 Lower Blandford Road Broadstone Dorset BH18 8DX",
    "addr:housenumber":"214",
    "addr:postcode":"bh18 8dx",
    "addr:street":"Lower Blandford Road",
    "iso:country":"GB",
    "sg:address":"214 Lower Blandford Road",
    "sg:city":"Broadstone",
    "sg:classifiers":[
        {
            "category":"Health Services",
            "subcategory":"Optometrist",
            "type":"Services"
        },
        {
            "category":"Shopping",
            "subcategory":"Optician",
            "type":"Retail Goods"
        }
    ],
    "sg:phone":"+44 1202 696345",
    "sg:postcode":"BH18 8DX",
    "sg:province":"Dorset",
    "sg:tags":[
        "ophthalmic"
    ],
    "wof:name":"N P & G M West Opticians",
    "wof:placetype":"venue"
},
  "geometry": {"coordinates":[-1.9954940081,50.7612686157],"type":"Point"}
}