{
  "type": "Feature",
  "properties": {
    "addr:full":"5 Water Lane, Camden London Greater London NW1 8NZ",
    "addr:housenumber":"5",
    "addr:postcode":"nw1 8nz",
    "addr:street":"Water Lane",
    "iso:country":"GB",
    "sg:address":"5 Water Lane, Camden",
    "sg:city":"London",
    "sg:classifiers":[
        {
            "category":"Professional",
            "subcategory":"Research",
            "type":"Services"
        }
    ],
    "sg:postcode":"NW1 8NZ",
    "sg:province":"Greater London",
    "sg:tags":[
        "market"
    ],
    "wof:name":"Harris Marketing Service Ltd.",
    "wof:placetype":"venue"
},
  "geometry": {"coordinates":[-0.1420899928,51.5418815613],"type":"Point"}
}