{
  "type": "Feature",
  "properties": {
    "iso:country":"GB",
    "sg:address":"127 Queens Road",
    "sg:city":"Weybridge",
    "sg:classifiers":[
        {
            "category":"Retail",
            "subcategory":"Laundry & Dry Cleaning",
            "type":"Services"
        }
    ],
    "sg:phone":"+44 1932 848478",
    "sg:postcode":"KT13 9UN",
    "sg:province":"Surrey",
    "sg:tags":[
        "cleaner",
        "launderette"
    ],
    "wof:name":"Villager Laundry & Dry Cleaning",
    "wof:placetype":"venue"
},
  "geometry": {"coordinates":[-0.443412,51.366985],"type":"Point"}
}