{
  "type": "Feature",
  "properties": {
    "iso:country":"GB",
    "sg:address":"Avon Road",
    "sg:city":"Cannock",
    "sg:classifiers":[
        {
            "category":"Retail",
            "subcategory":"Event Space",
            "type":"Services"
        }
    ],
    "sg:phone":"+44 1543 503163",
    "sg:postcode":"WS11 1LG",
    "sg:province":"Staffordshire",
    "sg:tags":[
        "function",
        "room"
    ],
    "wof:name":"Avon Business & Leisure Centre",
    "wof:placetype":"venue"
},
  "geometry": {"coordinates":[-2.0318539143,52.6858901978],"type":"Point"}
}