{
  "type": "Feature",
  "properties": {
    "iso:country":"GB",
    "sg:address":"5 Stonewell",
    "sg:city":"Lancaster",
    "sg:classifiers":[
        {
            "category":"Professional",
            "subcategory":"Business Services",
            "type":"Services"
        }
    ],
    "sg:phone":"+44 1524 64308",
    "sg:postcode":"LA1 1NJ",
    "sg:province":"Lancashire",
    "sg:tags":[
        "bookmaker"
    ],
    "wof:name":"W & W Foxcroft",
    "wof:placetype":"venue"
},
  "geometry": {"coordinates":[-2.798075,54.049435],"type":"Point"}
}