{
  "type": "Feature",
  "properties": {
    "iso:country":"GB",
    "sg:address":"55-56 Liquorpond Street",
    "sg:city":"Boston",
    "sg:classifiers":[
        {
            "category":"Food & Beverages",
            "subcategory":"Meat & Fish",
            "type":"Retail Goods"
        }
    ],
    "sg:postcode":"PE21 8UQ",
    "sg:province":"Lincolnshire",
    "sg:tags":[
        "chip"
    ],
    "wof:name":"Brians Fish & Chip Shop",
    "wof:placetype":"venue"
},
  "geometry": {"coordinates":[-0.029739,52.974911],"type":"Point"}
}