{
  "type": "Feature",
  "properties": {
    "addr:full":"Unit 11 Westgate Trading Estate, Aldrich Walsall Staffordshire WS9 8EX",
    "addr:housenumber":"unit 11",
    "addr:postcode":"ws9 8ex",
    "addr:street":"Westgate Trading Estate",
    "iso:country":"GB",
    "sg:address":"Unit 11 Westgate Trading Estate, Aldrich",
    "sg:city":"Walsall",
    "sg:classifiers":[
        {
            "category":"Manufacturing",
            "subcategory":"Signs",
            "type":"Manufacturing & Wholesale Goods"
        }
    ],
    "sg:phone":"+44 1922 745735",
    "sg:postcode":"WS9 8EX",
    "sg:province":"Staffordshire",
    "sg:tags":[
        "nameplate"
    ],
    "wof:name":"N P U K Ltd.",
    "wof:placetype":"venue"
},
  "geometry": {"coordinates":[-1.936004,52.605492],"type":"Point"}
}