{
  "type": "Feature",
  "properties": {
    "iso:country":"GB",
    "sg:address":"7 Barnfield",
    "sg:city":"Cranleigh",
    "sg:classifiers":[
        {
            "category":"Organizations",
            "subcategory":"Religious Organization",
            "type":"Services"
        }
    ],
    "sg:phone":"+44 1483 274979",
    "sg:postcode":"GU6 7BN",
    "sg:province":"Surrey",
    "sg:tags":[
        "organisation"
    ],
    "wof:name":"The Bahai Faith",
    "wof:placetype":"venue"
},
  "geometry": {"coordinates":[-0.4804140031,51.1442489624],"type":"Point"}
}