{
  "type": "Feature",
  "properties": {
    "iso:country":"GB",
    "sg:address":"Unit 2 Brooks Road, Shepherd Industrial Estate",
    "sg:city":"Lewes",
    "sg:classifiers":[
        {
            "category":"Professional",
            "subcategory":"Business Services",
            "type":"Services"
        }
    ],
    "sg:postcode":"BN7 2BY",
    "sg:province":"East Sussex",
    "sg:tags":[
        "house",
        "mailing"
    ],
    "wof:name":"Rockhill Mailing Services Ltd.",
    "wof:placetype":"venue"
},
  "geometry": {"coordinates":[0.016375,50.877686],"type":"Point"}
}