{
  "type": "Feature",
  "properties": {
    "iso:country":"GB",
    "sg:address":"Unit 5 Duke Motors Complex, Bolton St",
    "sg:city":"Chorley",
    "sg:classifiers":[
        {
            "category":"Manufacturing",
            "subcategory":"Furniture",
            "type":"Manufacturing & Wholesale Goods"
        }
    ],
    "sg:phone":"+44 1257 249008",
    "sg:postcode":"PR7 3DY",
    "sg:province":"Lancashire",
    "sg:tags":[
        "mnfr",
        "garden",
        "patio"
    ],
    "wof:name":"Rustic Garden Furniture",
    "wof:placetype":"venue"
},
  "geometry": {"coordinates":[-2.632134,53.652088],"type":"Point"}
}