{
  "type": "Feature",
  "properties": {
    "iso:country":"GB",
    "sg:address":"532 Fishponds Rd, Fishponds",
    "sg:city":"Bristol",
    "sg:classifiers":[
        {
            "category":"Professional",
            "subcategory":"Detective & Security Services",
            "type":"Services"
        }
    ],
    "sg:postcode":"BS16 3DW",
    "sg:province":"City of Bristol",
    "sg:tags":[
        "agency"
    ],
    "wof:name":"Rose,Helen,",
    "wof:placetype":"venue"
},
  "geometry": {"coordinates":[-2.54027,51.475857],"type":"Point"}
}