{
  "type": "Feature",
  "properties": {
    "addr:full":"3 The Parade Helston Cornwall TR13 8RT",
    "addr:housenumber":"3",
    "addr:postcode":"tr13 8rt",
    "addr:street":"The Parade",
    "iso:country":"GB",
    "sg:address":"3 The Parade",
    "sg:city":"Helston",
    "sg:classifiers":[
        {
            "category":"Food & Beverages",
            "subcategory":"Specialty",
            "type":"Retail Goods"
        }
    ],
    "sg:phone":"+44 1326 564226",
    "sg:postcode":"TR13 8RT",
    "sg:province":"Cornwall",
    "sg:tags":[
        "product",
        "health"
    ],
    "wof:name":"The Natural Store",
    "wof:placetype":"venue"
},
  "geometry": {"coordinates":[-5.2714948654,50.0994911194],"type":"Point"}
}