{
  "type": "Feature",
  "properties": {
    "addr:full":"276-280 Byres Rd Glasgow Glasgow City G12 8SH",
    "addr:housenumber":"276-280",
    "addr:postcode":"g12 8sh",
    "addr:street":"Byres Rd",
    "iso:country":"GB",
    "sg:address":"276-280 Byres Rd",
    "sg:city":"Glasgow",
    "sg:classifiers":[
        {
            "category":"Communications",
            "subcategory":"Film & Video Production",
            "type":"Services"
        }
    ],
    "sg:phone":"+44 141 334 6532",
    "sg:postcode":"G12 8SH",
    "sg:province":"Glasgow City",
    "sg:tags":[
        "tv"
    ],
    "wof:name":"Radio Rentals",
    "wof:placetype":"venue"
},
  "geometry": {"coordinates":[-4.2931308746,55.875831604],"type":"Point"}
}