{
  "type": "Feature",
  "properties": {
    "addr:full":"113 London Road Leicester Leicestershire LE2 0RG",
    "addr:housenumber":"113",
    "addr:postcode":"le2 0rg",
    "addr:street":"London Road",
    "iso:country":"GB",
    "sg:address":"113 London Road",
    "sg:city":"Leicester",
    "sg:classifiers":[
        {
            "category":"Professional",
            "subcategory":"Lawyer & Legal Services",
            "type":"Services"
        }
    ],
    "sg:phone":"+44 116 255 1901",
    "sg:postcode":"LE2 0RG",
    "sg:province":"Leicestershire",
    "sg:tags":[
        "solicitor"
    ],
    "wof:name":"Crane & Walton",
    "wof:placetype":"venue"
},
  "geometry": {"coordinates":[-1.1217479706,52.6285591125],"type":"Point"}
}