{
  "type": "Feature",
  "properties": {
    "iso:country":"GB",
    "sg:address":"Moor House Farm, Sands Road, Reighton",
    "sg:city":"Filey",
    "sg:classifiers":[
        {
            "category":"Farming",
            "subcategory":"Farm",
            "type":"Manufacturing & Wholesale Goods"
        }
    ],
    "sg:phone":"+44 1723 890622",
    "sg:postcode":"YO14 9SF",
    "sg:province":"North Yorkshire",
    "sg:tags":[
        "mixed",
        "crop"
    ],
    "wof:name":"P G Hood",
    "wof:placetype":"venue"
},
  "geometry": {"coordinates":[-0.290749,54.211845],"type":"Point"}
}