{
  "type": "Feature",
  "properties": {
    "addr:full":"Galmington Rd Taunton Somerset TA1 5NP",
    "addr:postcode":"ta1 5np",
    "addr:street":"Galmington Rd",
    "iso:country":"GB",
    "sg:address":"Galmington Rd",
    "sg:city":"Taunton",
    "sg:classifiers":[
        {
            "category":"Government",
            "subcategory":"Post Office",
            "type":"Public Place"
        }
    ],
    "sg:phone":"+44 1823 337401",
    "sg:postcode":"TA1 5NP",
    "sg:province":"Somerset",
    "wof:name":"Galmington Post Office",
    "wof:placetype":"venue"
},
  "geometry": {"coordinates":[-3.126755,51.009083],"type":"Point"}
}