{
  "type": "Feature",
  "properties": {
    "addr:full":"26 Southbourne Gro Bournemouth Dorset BH6 3RA",
    "addr:housenumber":"26",
    "addr:postcode":"bh6 3ra",
    "addr:street":"Southbourne Gro",
    "iso:country":"GB",
    "sg:address":"26 Southbourne Gro",
    "sg:city":"Bournemouth",
    "sg:classifiers":[
        {
            "category":"Shopping",
            "subcategory":"Books",
            "type":"Retail Goods"
        },
        {
            "category":"Shopping",
            "subcategory":"News",
            "type":"Retail Goods"
        }
    ],
    "sg:phone":"+44 1202 433334",
    "sg:postcode":"BH6 3RA",
    "sg:province":"Dorset",
    "sg:tags":[
        "bookseller",
        "newsagent"
    ],
    "wof:name":"Book Wise (Bournemouth) Ltd.",
    "wof:placetype":"venue"
},
  "geometry": {"coordinates":[-1.8163490295,50.7263908386],"type":"Point"}
}