{
  "type": "Feature",
  "properties": {
    "addr:full":"Clay Street, Penkridge Stafford Shropshire ST19 5AF",
    "addr:postcode":"st19 5af",
    "addr:street":"Clay Street",
    "iso:country":"GB",
    "sg:address":"Clay Street, Penkridge",
    "sg:city":"Stafford",
    "sg:classifiers":[
        {
            "category":"Shopping",
            "type":"Retail Goods"
        }
    ],
    "sg:phone":"+44 1785 714433",
    "sg:postcode":"ST19 5AF",
    "sg:province":"Shropshire",
    "sg:tags":[
        "part",
        "accessory"
    ],
    "wof:name":"Motorcare",
    "wof:placetype":"venue"
},
  "geometry": {"coordinates":[-2.116339922,52.7226066589],"type":"Point"}
}