{
  "type": "Feature",
  "properties": {
    "addr:full":"1 Steep Hill London Greater London SW16 1UL",
    "addr:housenumber":"1",
    "addr:postcode":"sw16 1ul",
    "addr:street":"Steep Hill",
    "iso:country":"GB",
    "sg:address":"1 Steep Hill",
    "sg:city":"London",
    "sg:classifiers":[
        {
            "category":"Professional",
            "subcategory":"Computer Services",
            "type":"Services"
        }
    ],
    "sg:phone":"+44 20 8677 4789",
    "sg:postcode":"SW16 1UL",
    "sg:province":"Greater London",
    "sg:tags":[
        "bureau",
        "facility"
    ],
    "wof:name":"P & A M  Casselle",
    "wof:placetype":"venue"
},
  "geometry": {"coordinates":[-0.1319849938,51.4322166443],"type":"Point"}
}