{
  "type": "Feature",
  "properties": {
    "iso:country":"GB",
    "sg:address":"Gunn Street, Biddulph",
    "sg:city":"Stoke-on-trent",
    "sg:classifiers":[
        {
            "category":"Education",
            "subcategory":"School",
            "type":"Public Place"
        },
        {
            "category":"Government",
            "subcategory":"Office",
            "type":"Public Place"
        }
    ],
    "sg:postcode":"ST8 6AY",
    "sg:province":"Staffordshire",
    "sg:tags":[
        "local",
        "authority"
    ],
    "wof:name":"Kingsfield First School",
    "wof:placetype":"venue"
},
  "geometry": {"coordinates":[-2.176203,53.115681],"type":"Point"}
}