{
  "type": "Feature",
  "properties": {
    "addr:full":"19 North Walk, Yate Bristol Gloucestershire BS37 4AP",
    "addr:housenumber":"19",
    "addr:postcode":"bs37 4ap",
    "addr:street":"North Walk Yate Bristol",
    "iso:country":"GB",
    "sg:address":"19 North Walk, Yate",
    "sg:city":"Bristol",
    "sg:classifiers":[
        {
            "category":"Health Services",
            "subcategory":"Optometrist",
            "type":"Services"
        }
    ],
    "sg:phone":"+44 1454 325473",
    "sg:postcode":"BS37 4AP",
    "sg:province":"Gloucestershire",
    "sg:tags":[
        "optician"
    ],
    "wof:name":"Specsavers",
    "wof:placetype":"venue"
},
  "geometry": {"coordinates":[-2.4096150398,51.5391998291],"type":"Point"}
}