{
  "type": "Feature",
  "properties": {
    "iso:country":"GB",
    "sg:address":"Station Rd",
    "sg:city":"Sleaford",
    "sg:classifiers":[
        {
            "category":"Manufacturing",
            "subcategory":"Building Materials",
            "type":"Manufacturing & Wholesale Goods"
        }
    ],
    "sg:phone":"+44 1529 460860",
    "sg:postcode":"NG34 9JH",
    "sg:province":"Lincolnshire",
    "sg:tags":[
        "tarmac",
        "asphalt"
    ],
    "wof:name":"Tyrrell Surfacing Contractors",
    "wof:placetype":"venue"
},
  "geometry": {"coordinates":[-0.295896,52.980167],"type":"Point"}
}