{
  "type": "Feature",
  "properties": {
    "iso:country":"GB",
    "sg:address":"Hanover Ho, Hanover Buildings",
    "sg:city":"Southampton",
    "sg:classifiers":[
        {
            "category":"Government",
            "subcategory":"Office",
            "type":"Public Place"
        }
    ],
    "sg:phone":"+44 23 8057 4400",
    "sg:postcode":"SO14 1AN",
    "sg:province":"Hampshire",
    "sg:tags":[
        "inland",
        "revenue"
    ],
    "wof:name":"Inland Revenue",
    "wof:placetype":"venue"
},
  "geometry": {"coordinates":[-1.402089,50.902946],"type":"Point"}
}