{
  "type": "Feature",
  "properties": {
    "iso:country":"GB",
    "sg:address":"Divisional Head Quarters, Market St",
    "sg:city":"Barrow In Furness",
    "sg:classifiers":[
        {
            "category":"Government",
            "subcategory":"Police Station",
            "type":"Public Place"
        }
    ],
    "sg:phone":"+44 1229 824532",
    "sg:postcode":"LA14 2LE",
    "sg:province":"Cumbria",
    "sg:tags":[
        "support"
    ],
    "wof:name":"Barrow Police",
    "wof:placetype":"venue"
},
  "geometry": {"coordinates":[-3.2258470058,54.1110877991],"type":"Point"}
}