{
  "type": "Feature",
  "properties": {
    "iso:country":"GB",
    "sg:address":"Hen Efail, Bethel",
    "sg:city":"Caernarfon",
    "sg:classifiers":[
        {
            "category":"Professional",
            "type":"Services"
        },
        {
            "category":"Professional",
            "subcategory":"Printing & Photocopies",
            "type":"Services"
        }
    ],
    "sg:phone":"+44 1286 870831",
    "sg:postcode":"LL55 1UW",
    "sg:province":"Gwynedd",
    "sg:tags":[
        "directory",
        "printer",
        "pub"
    ],
    "wof:name":"Argraffwr Eryri Printers",
    "wof:placetype":"venue"
},
  "geometry": {"coordinates":[-4.2718091011,53.1425933838],"type":"Point"}
}