{
  "type": "Feature",
  "properties": {
    "addr:full":"The White House, Downfield Stroud Gloucestershire GL5 4HJ",
    "addr:postcode":"gl5 4hj",
    "addr:street":"Downfield",
    "iso:country":"GB",
    "sg:address":"The White House, Downfield",
    "sg:city":"Stroud",
    "sg:classifiers":[
        {
            "category":"Manufacturing",
            "subcategory":"Building Materials",
            "type":"Manufacturing & Wholesale Goods"
        }
    ],
    "sg:postcode":"GL5 4HJ",
    "sg:province":"Gloucestershire",
    "sg:tags":[
        "shutter",
        "supp",
        "door"
    ],
    "wof:name":"Progressive Systems (U K ) Ltd.",
    "wof:placetype":"venue"
},
  "geometry": {"coordinates":[-2.2354431152,51.7481117249],"type":"Point"}
}