{
  "type": "Feature",
  "properties": {
    "addr:full":"33 Upper High Street Wednesbury West Midlands WS10 7HJ",
    "addr:housenumber":"33",
    "addr:postcode":"ws10 7hj",
    "addr:street":"Upper High Street",
    "iso:country":"GB",
    "sg:address":"33 Upper High Street",
    "sg:city":"Wednesbury",
    "sg:classifiers":[
        {
            "category":"Personal",
            "subcategory":"Beauty Salon",
            "type":"Services"
        }
    ],
    "sg:postcode":"WS10 7HJ",
    "sg:province":"West Midlands",
    "sg:tags":[
        "unisex",
        "hairdresser"
    ],
    "wof:name":"St.Dior",
    "wof:placetype":"venue"
},
  "geometry": {"coordinates":[-2.0206799507,52.553565979],"type":"Point"}
}