{
  "type": "Feature",
  "properties": {
    "addr:full":"376-378 North Circular Road London Greater London N13 6BJ",
    "addr:housenumber":"376-378",
    "addr:postcode":"n13 6bj",
    "addr:street":"North Circular Road",
    "iso:country":"GB",
    "sg:address":"376-378 North Circular Road",
    "sg:city":"London",
    "sg:classifiers":[
        {
            "category":"Retail",
            "subcategory":"Auto Repair",
            "type":"Services"
        }
    ],
    "sg:phone":"+44 20 8881 9966",
    "sg:postcode":"N13 6BJ",
    "sg:province":"Greater London",
    "sg:tags":[
        "engine",
        "tuning",
        "car",
        "diagnostic",
        "garage",
        "modification"
    ],
    "wof:name":"Technical Tuning",
    "wof:placetype":"venue"
},
  "geometry": {"coordinates":[-0.1062539965,51.6127090454],"type":"Point"}
}