{
  "type": "Feature",
  "properties": {
    "addr:full":"2 Park Road, Westhoughton Bolton Lancashire BL5 3DE",
    "addr:housenumber":"2",
    "addr:postcode":"bl5 3de",
    "addr:street":"Park Road",
    "iso:country":"GB",
    "sg:address":"2 Park Road, Westhoughton",
    "sg:city":"Bolton",
    "sg:classifiers":[
        {
            "category":"Organizations",
            "subcategory":"Membership Organization",
            "type":"Services"
        }
    ],
    "sg:phone":"+44 1942 811245",
    "sg:postcode":"BL5 3DE",
    "sg:province":"Lancashire",
    "sg:tags":[
        "club"
    ],
    "wof:name":"Westhoughton Reform Club",
    "wof:placetype":"venue"
},
  "geometry": {"coordinates":[-2.5196909904,53.5482902527],"type":"Point"}
}