{
  "type": "Feature",
  "properties": {
    "iso:country":"GB",
    "sg:address":"Whiteway Head, Knowbury",
    "sg:city":"Ludlow",
    "sg:classifiers":[
        {
            "category":"Professional",
            "subcategory":"Management & Consulting",
            "type":"Services"
        }
    ],
    "sg:phone":"+44 1584 890913",
    "sg:postcode":"SY8 3LE",
    "sg:province":"Herefordshire",
    "sg:tags":[
        "marketing",
        "consultant"
    ],
    "wof:name":"Equipment Direct",
    "wof:placetype":"venue"
},
  "geometry": {"coordinates":[-2.62491,52.368076],"type":"Point"}
}