{
  "type": "Feature",
  "properties": {
    "addr:full":"Hareshill Road Heywood Lancashire OL10 2TP",
    "addr:postcode":"ol10 2tp",
    "addr:street":"Hareshill Road",
    "iso:country":"GB",
    "sg:address":"Hareshill Road",
    "sg:city":"Heywood",
    "sg:classifiers":[
        {
            "category":"Food & Beverages",
            "subcategory":"Supermarket",
            "type":"Retail Goods"
        }
    ],
    "sg:phone":"+44 1706 694610",
    "sg:postcode":"OL10 2TP",
    "sg:province":"Lancashire",
    "sg:tags":[
        "frozen"
    ],
    "wof:name":"Belfield Farm Ltd.",
    "wof:placetype":"venue"
},
  "geometry": {"coordinates":[-2.2250139713,53.5782012939],"type":"Point"}
}