{
  "type": "Feature",
  "properties": {
    "addr:full":"12b Sinnot Road, Waltham London Greater London E17 5QB",
    "addr:housenumber":"12b",
    "addr:postcode":"e17 5qb",
    "addr:street":"Sinnot Road",
    "iso:country":"GB",
    "sg:address":"12b Sinnot Road, Waltham",
    "sg:city":"London",
    "sg:classifiers":[
        {
            "category":"Health Services",
            "subcategory":"Doctor",
            "type":"Services"
        }
    ],
    "sg:phone":"+44 20 8531 8272",
    "sg:postcode":"E17 5QB",
    "sg:province":"Greater London",
    "sg:tags":[
        "practitioners"
    ],
    "wof:name":"Dr Shui Surgery",
    "wof:placetype":"venue"
},
  "geometry": {"coordinates":[-0.03968,51.598011],"type":"Point"}
}