{
  "type": "Feature",
  "properties": {
    "addr:full":"104 Councillor Lane Cheadle Cheshire SK8 2LG",
    "addr:housenumber":"104",
    "addr:postcode":"sk8 2lg",
    "addr:street":"Councillor Lane Cheadle",
    "iso:country":"GB",
    "sg:address":"104 Councillor Lane",
    "sg:city":"Cheadle",
    "sg:classifiers":[
        {
            "category":"Home & Garden",
            "subcategory":"Household Appliances",
            "type":"Retail Goods"
        }
    ],
    "sg:postcode":"SK8 2LG",
    "sg:province":"Cheshire",
    "sg:tags":[
        "electrical"
    ],
    "wof:name":"Bailey Domestic Services",
    "wof:placetype":"venue"
},
  "geometry": {"coordinates":[-2.1967790127,53.3913764954],"type":"Point"}
}