{
  "type": "Feature",
  "properties": {
    "addr:full":"204 Science Park, Milton Road Cambridge Cambridgeshire CB4 0GZ",
    "addr:housenumber":"204",
    "addr:postcode":"cb4 0gz",
    "addr:street":"Science Park Milton Road",
    "iso:country":"GB",
    "sg:address":"204 Science Park, Milton Road",
    "sg:city":"Cambridge",
    "sg:classifiers":[
        {
            "category":"Wholesale",
            "subcategory":"Medical Equipment & Supplies",
            "type":"Manufacturing & Wholesale Goods"
        },
        {
            "category":"Organizations",
            "subcategory":"Community Association",
            "type":"Services"
        }
    ],
    "sg:phone":"+44 1223 437400",
    "sg:postcode":"CB4 0GZ",
    "sg:province":"Cambridgeshire",
    "sg:tags":[
        "hospital",
        "relation",
        "public"
    ],
    "wof:name":"Perkin Elmer Life Sciences",
    "wof:placetype":"venue"
},
  "geometry": {"coordinates":[0.1465699971,52.2349090576],"type":"Point"}
}