{
  "type": "Feature",
  "properties": {
    "iso:country":"GB",
    "sg:address":"11a Princes Street",
    "sg:city":"Ipswich",
    "sg:classifiers":[
        {
            "category":"Professional",
            "subcategory":"Employment Agencies",
            "type":"Services"
        }
    ],
    "sg:phone":"+44 1473 233083",
    "sg:postcode":"IP1 1PH",
    "sg:province":"Suffolk",
    "sg:tags":[
        "consultant"
    ],
    "wof:name":"G B N Associates Ltd.",
    "wof:placetype":"venue"
},
  "geometry": {"coordinates":[1.1523230076,52.0567855835],"type":"Point"}
}