{
  "type": "Feature",
  "properties": {
    "addr:full":"24 Regent St Bristol City of Bristol BS15 2JS",
    "addr:housenumber":"24",
    "addr:postcode":"bs15 2js",
    "addr:street":"Regent St",
    "iso:country":"GB",
    "sg:address":"24 Regent St",
    "sg:city":"Bristol",
    "sg:classifiers":[
        {
            "category":"Shopping",
            "subcategory":"Discount & Variety Stores",
            "type":"Retail Goods"
        }
    ],
    "sg:phone":"+44 117 908 3317",
    "sg:postcode":"BS15 2JS",
    "sg:province":"City of Bristol",
    "sg:tags":[
        "centre"
    ],
    "wof:name":"Sound As A Pound",
    "wof:placetype":"venue"
},
  "geometry": {"coordinates":[-2.5914289951,51.453666687],"type":"Point"}
}