{
  "type": "Feature",
  "properties": {
    "iso:country":"GB",
    "sg:address":"55 Clifton Road",
    "sg:city":"Runcorn",
    "sg:classifiers":[
        {
            "category":"Professional",
            "subcategory":"Art Services",
            "type":"Services"
        }
    ],
    "sg:phone":"+44 1928 572366",
    "sg:postcode":"WA7 4TB",
    "sg:province":"Cheshire",
    "sg:tags":[
        "graphic",
        "designer"
    ],
    "wof:name":"Bradburne Creative Design",
    "wof:placetype":"venue"
},
  "geometry": {"coordinates":[-2.7236859798,53.322769165],"type":"Point"}
}