{
  "type": "Feature",
  "properties": {
    "addr:full":"162 Victoria Street Mansfield Nottinghamshire NG18 5RY",
    "addr:housenumber":"162",
    "addr:postcode":"ng18 5ry",
    "addr:street":"Victoria Street",
    "iso:country":"GB",
    "sg:address":"162 Victoria Street",
    "sg:city":"Mansfield",
    "sg:classifiers":[
        {
            "category":"Food & Beverages",
            "subcategory":"Groceries & Convenience Stores",
            "type":"Retail Goods"
        }
    ],
    "sg:postcode":"NG18 5RY",
    "sg:province":"Nottinghamshire",
    "wof:name":"Victoria Stores",
    "wof:placetype":"venue"
},
  "geometry": {"coordinates":[-1.206619,53.139755],"type":"Point"}
}