{
  "type": "Feature",
  "properties": {
    "iso:country":"GB",
    "sg:address":"Unit 8, Waterloo Industrial Park, Waterloo Road",
    "sg:city":"Stratford-upon-avon",
    "sg:classifiers":[
        {
            "category":"Building & Trades",
            "subcategory":"Construction",
            "type":"Services"
        }
    ],
    "sg:phone":"+44 1789 772648",
    "sg:postcode":"B50 4JG",
    "sg:province":"Warwickshire",
    "sg:tags":[
        "joiner",
        "carpenter"
    ],
    "wof:name":"Arden Joinery",
    "wof:placetype":"venue"
},
  "geometry": {"coordinates":[-1.8520699739,52.1733894348],"type":"Point"}
}