{
  "type": "Feature",
  "properties": {
    "addr:full":"Wild Mill Precinct Bridgend Bridgend CF31 1JY",
    "addr:postcode":"cf31 1jy",
    "addr:street":"Wild",
    "iso:country":"GB",
    "sg:address":"Wild Mill Precinct",
    "sg:city":"Bridgend",
    "sg:classifiers":[
        {
            "category":"Personal",
            "subcategory":"Beauty Salon",
            "type":"Services"
        }
    ],
    "sg:postcode":"CF31 1JY",
    "sg:province":"Bridgend",
    "sg:tags":[
        "unisex",
        "hairdresser"
    ],
    "wof:name":"Cut Above",
    "wof:placetype":"venue"
},
  "geometry": {"coordinates":[-3.578263,51.508835],"type":"Point"}
}