{
  "type": "Feature",
  "properties": {
    "addr:full":"Unit 11, Hunslet Trading Estate Leeds West Yorkshire LS10 1QR",
    "addr:housenumber":"unit",
    "addr:postcode":"ls10 1qr",
    "addr:street":"Hunslet Trading Estate",
    "iso:country":"GB",
    "sg:address":"Unit 11, Hunslet Trading Estate",
    "sg:city":"Leeds",
    "sg:classifiers":[
        {
            "category":"Wholesale",
            "subcategory":"Meat",
            "type":"Manufacturing & Wholesale Goods"
        }
    ],
    "sg:phone":"+44 113 277 1907",
    "sg:postcode":"LS10 1QR",
    "sg:province":"West Yorkshire",
    "sg:tags":[
        "-"
    ],
    "wof:name":"Dalziel Ltd.",
    "wof:placetype":"venue"
},
  "geometry": {"coordinates":[-1.5392190218,53.7902145386],"type":"Point"}
}