{
  "type": "Feature",
  "properties": {
    "addr:full":"8 Derwent Close, Woosehill Wokingham Berkshire RG41 3UD",
    "addr:housenumber":"8",
    "addr:postcode":"rg41 3ud",
    "addr:street":"Derwent Close Woosehill",
    "iso:country":"GB",
    "sg:address":"8 Derwent Close, Woosehill",
    "sg:city":"Wokingham",
    "sg:classifiers":[
        {
            "category":"Professional",
            "subcategory":"Computer Services",
            "type":"Services"
        }
    ],
    "sg:postcode":"RG41 3UD",
    "sg:province":"Berkshire",
    "sg:tags":[
        "system",
        "software"
    ],
    "wof:name":"Foresight Enterprises Ltd",
    "wof:placetype":"venue"
},
  "geometry": {"coordinates":[-0.8594989777,51.4134788513],"type":"Point"}
}