{
  "type": "Feature",
  "properties": {
    "addr:full":"14 Cotham Street St Helens Merseyside WA10 1SA",
    "addr:housenumber":"14",
    "addr:postcode":"wa10 1sa",
    "addr:street":"Cotham Street",
    "iso:country":"GB",
    "sg:address":"14 Cotham Street",
    "sg:city":"St Helens",
    "sg:classifiers":[
        {
            "category":"Shopping",
            "subcategory":"Clothing, Apparel, & Fashions",
            "type":"Retail Goods"
        }
    ],
    "sg:postcode":"WA10 1SA",
    "sg:province":"Merseyside",
    "sg:tags":[
        "menswear"
    ],
    "wof:name":"O D S Menswear",
    "wof:placetype":"venue"
},
  "geometry": {"coordinates":[-2.7373239994,53.4537086487],"type":"Point"}
}