{
  "type": "Feature",
  "properties": {
    "iso:country":"GB",
    "sg:address":"14-16 Church Street",
    "sg:city":"Ripley",
    "sg:classifiers":[
        {
            "category":"Shopping",
            "subcategory":"Department Store",
            "type":"Retail Goods"
        },
        {
            "category":"Home & Garden",
            "subcategory":"Hardware",
            "type":"Retail Goods"
        }
    ],
    "sg:phone":"+44 1773 744904",
    "sg:postcode":"DE5 3BU",
    "sg:province":"Derbyshire",
    "sg:tags":[
        "retailer",
        "departmental",
        "diy"
    ],
    "wof:name":"WILKINSON HARDWARE STORES,LTD",
    "wof:placetype":"venue"
},
  "geometry": {"coordinates":[-1.406154,53.050808],"type":"Point"}
}