{
  "type": "Feature",
  "properties": {
    "addr:full":"Unit 4 Polmorla Mews Wadebridge Cornwall PL27 7LZ",
    "addr:housenumber":"unit 4",
    "addr:postcode":"pl27 7lz",
    "addr:street":"Polmorla Mews",
    "iso:country":"GB",
    "sg:address":"Unit 4 Polmorla Mews",
    "sg:city":"Wadebridge",
    "sg:classifiers":[
        {
            "category":"Personal",
            "subcategory":"Barber",
            "type":"Services"
        }
    ],
    "sg:phone":"+44 1208 813960",
    "sg:postcode":"PL27 7LZ",
    "sg:province":"Cornwall",
    "sg:tags":[
        "men's",
        "hairdresser"
    ],
    "wof:name":"Tony's",
    "wof:placetype":"venue"
},
  "geometry": {"coordinates":[-4.8367462158,50.5161094666],"type":"Point"}
}