{
  "type": "Feature",
  "properties": {
    "iso:country":"GB",
    "sg:address":"16 Lower High Street",
    "sg:city":"Merthyr Tydfil",
    "sg:classifiers":[
        {
            "category":"Shopping",
            "type":"Retail Goods"
        }
    ],
    "sg:phone":"+44 1685 373280",
    "sg:postcode":"CF47 8EB",
    "sg:province":"Merthyr Tydfil",
    "sg:tags":[
        "part",
        "accessory"
    ],
    "wof:name":"Auto-Trade (Merthyr)",
    "wof:placetype":"venue"
},
  "geometry": {"coordinates":[-3.377159,51.74239],"type":"Point"}
}