{
  "type": "Feature",
  "properties": {
    "iso:country":"GB",
    "sg:address":"42 North Parade",
    "sg:city":"Whitley Bay",
    "sg:classifiers":[
        {
            "category":"Travel",
            "subcategory":"Hotels & Motels",
            "type":"Entertainment"
        }
    ],
    "sg:phone":"+44 191 291 1724",
    "sg:postcode":"NE26 1PB",
    "sg:province":"Northumberland",
    "sg:tags":[
        "house",
        "guest"
    ],
    "wof:name":"Parade 42",
    "wof:placetype":"venue"
},
  "geometry": {"coordinates":[-1.4435280561,55.0446395874],"type":"Point"}
}