{
  "type": "Feature",
  "properties": {
    "iso:country":"GB",
    "sg:address":"101 Ormskirk Rd, Rainford",
    "sg:city":"St. Helens",
    "sg:classifiers":[
        {
            "category":"Retail",
            "subcategory":"Auto Repair",
            "type":"Services"
        }
    ],
    "sg:phone":"+44 1744 883454",
    "sg:postcode":"WA11 8DD",
    "sg:province":"Lancashire",
    "sg:tags":[
        "modification",
        "garage"
    ],
    "wof:name":"Central Garage",
    "wof:placetype":"venue"
},
  "geometry": {"coordinates":[-2.792497,53.5047],"type":"Point"}
}