{
  "type": "Feature",
  "properties": {
    "iso:country":"GB",
    "sg:address":"2 Dixon Way",
    "sg:city":"Lincoln",
    "sg:classifiers":[
        {
            "category":"Shopping",
            "subcategory":"Bicycles & Sporting Goods",
            "type":"Retail Goods"
        }
    ],
    "sg:phone":"+44 1522 533822",
    "sg:postcode":"LN6 7XN",
    "sg:province":"Lincolnshire",
    "sg:tags":[
        "riding",
        "saddlery",
        "wear"
    ],
    "wof:name":"The Tack Box",
    "wof:placetype":"venue"
},
  "geometry": {"coordinates":[-0.5508319736,53.2187232971],"type":"Point"}
}