{
  "type": "Feature",
  "properties": {
    "addr:full":"Orchard Park Gloucester Gloucestershire GL2 9PL",
    "addr:postcode":"gl2 9pl",
    "addr:street":"Orchard Park",
    "iso:country":"GB",
    "sg:address":"Orchard Park",
    "sg:city":"Gloucester",
    "sg:classifiers":[
        {
            "category":"Shopping",
            "subcategory":"Department Store",
            "type":"Retail Goods"
        },
        {
            "category":"Food & Beverages",
            "subcategory":"Supermarket",
            "type":"Retail Goods"
        },
        {
            "category":"Government",
            "subcategory":"Post Office",
            "type":"Public Place"
        }
    ],
    "sg:phone":"+44 1452 730246",
    "sg:postcode":"GL2 9PL",
    "sg:province":"Gloucestershire",
    "wof:name":"Twigworth Sub Post Office",
    "wof:placetype":"venue"
},
  "geometry": {"coordinates":[-2.2229340076,51.8988647461],"type":"Point"}
}