{
  "type": "Feature",
  "properties": {
    "addr:full":", Witherslack Grange Over Sands Cumbria LA11 6SD",
    "addr:postcode":"la11 6sd",
    "addr:street":"Over Sands",
    "iso:country":"GB",
    "sg:address":", Witherslack",
    "sg:city":"Grange Over Sands",
    "sg:classifiers":[
        {
            "category":"Education",
            "subcategory":"Special Training",
            "type":"Public Place"
        },
        {
            "category":"Education",
            "subcategory":"School",
            "type":"Public Place"
        },
        {
            "category":"Sports & Exercise",
            "subcategory":"Stables",
            "type":"Entertainment"
        }
    ],
    "sg:phone":"+44 15395 52397",
    "sg:postcode":"LA11 6SD",
    "sg:province":"Cumbria",
    "sg:tags":[
        "equestrian"
    ],
    "wof:name":"Witherslack Hall School",
    "wof:placetype":"venue"
},
  "geometry": {"coordinates":[-2.8679900169,54.2690200806],"type":"Point"}
}