{
  "type": "Feature",
  "properties": {
    "iso:country":"GB",
    "sg:address":"St Johns Court, Simpson Road",
    "sg:city":"Portsmouth",
    "sg:classifiers":[
        {
            "category":"Government",
            "subcategory":"Office",
            "type":"Public Place"
        },
        {
            "category":"Social Services",
            "subcategory":"Adult Care",
            "type":"Services"
        },
        {
            "category":"Social Services",
            "subcategory":"Retirement Home",
            "type":"Services"
        }
    ],
    "sg:phone":"+44 23 9269 8011",
    "sg:postcode":"PO2 8NA",
    "sg:province":"Hampshire",
    "sg:tags":[
        "housing",
        "local",
        "accommodation",
        "sheltered"
    ],
    "wof:name":"St John'S Court",
    "wof:placetype":"venue"
},
  "geometry": {"coordinates":[-1.086074,50.815216],"type":"Point"}
}