{
  "type": "Feature",
  "properties": {
    "iso:country":"GB",
    "sg:address":"55 3 Sleigh Drive",
    "sg:city":"Edinburgh",
    "sg:classifiers":[
        {
            "category":"Building & Trades",
            "subcategory":"Cleaning & Sanitation",
            "type":"Services"
        }
    ],
    "sg:phone":"+44 131 467 2656",
    "sg:postcode":"EH7 6ER",
    "sg:province":"City of Edinburgh",
    "sg:tags":[
        "commercial"
    ],
    "wof:name":"City Stair Cleaning",
    "wof:placetype":"venue"
},
  "geometry": {"coordinates":[-3.159261,55.956009],"type":"Point"}
}