{
  "type": "Feature",
  "properties": {
    "iso:country":"GB",
    "sg:address":"32 South View Close, Willand",
    "sg:city":"Cullompton",
    "sg:classifiers":[
        {
            "category":"Home & Garden",
            "subcategory":"Household Appliances",
            "type":"Retail Goods"
        }
    ],
    "sg:phone":"+44 1884 820736",
    "sg:postcode":"EX15 2QP",
    "sg:province":"Devon",
    "sg:tags":[
        "repairs",
        "electrical",
        "domestic",
        "servicing"
    ],
    "wof:name":"Prescotts Electrical",
    "wof:placetype":"venue"
},
  "geometry": {"coordinates":[-3.370959,50.888596],"type":"Point"}
}