{
  "type": "Feature",
  "properties": {
    "iso:country":"GB",
    "sg:address":"190 Wingletye Lane",
    "sg:city":"Hornchurch",
    "sg:classifiers":[
        {
            "category":"Professional",
            "subcategory":"Engineering",
            "type":"Services"
        }
    ],
    "sg:postcode":"RM11 3AL",
    "sg:province":"Essex",
    "sg:tags":[
        "contractor",
        "electrical",
        "engineer"
    ],
    "wof:name":"B J R Electrical Contractors",
    "wof:placetype":"venue"
},
  "geometry": {"coordinates":[0.2378029972,51.5688323975],"type":"Point"}
}