{
  "type": "Feature",
  "properties": {
    "addr:full":"Unit 8, Peerglow Industrial Estate, Olds Approach Watford Hertfordshire WD18 9SR",
    "addr:housenumber":"unit 8",
    "addr:postcode":"wd18 9sr",
    "addr:street":"Peerglow Industrial;Olds Approach",
    "iso:country":"GB",
    "sg:address":"Unit 8, Peerglow Industrial Estate, Olds Approach",
    "sg:city":"Watford",
    "sg:classifiers":[
        {
            "category":"Wholesale",
            "subcategory":"Construction Materials",
            "type":"Manufacturing & Wholesale Goods"
        }
    ],
    "sg:phone":"+44 1923 777305",
    "sg:postcode":"WD18 9SR",
    "sg:province":"Hertfordshire",
    "sg:tags":[
        "supplier",
        "double",
        "glazing"
    ],
    "wof:name":"Cavity Units Ltd.",
    "wof:placetype":"venue"
},
  "geometry": {"coordinates":[-0.44301,51.638401],"type":"Point"}
}