{
  "type": "Feature",
  "properties": {
    "addr:full":"Ipswich Road Service Station, Ipswich Road, Long Stratton Norwich Norfolk NR15 2TG",
    "addr:postcode":"nr15 2tg",
    "addr:street":"Ipswich Road;Ipswich Road",
    "iso:country":"GB",
    "sg:address":"Ipswich Road Service Station, Ipswich Road, Long Stratton",
    "sg:city":"Norwich",
    "sg:classifiers":[
        {
            "category":"Retail",
            "subcategory":"Auto Repair",
            "type":"Services"
        }
    ],
    "sg:phone":"+44 1508 530498",
    "sg:postcode":"NR15 2TG",
    "sg:province":"Norfolk",
    "sg:tags":[
        "modification",
        "garage",
        "related"
    ],
    "wof:name":"Ipswich Road Service Station Ltd.",
    "wof:placetype":"venue"
},
  "geometry": {"coordinates":[1.232493,52.481564],"type":"Point"}
}