{
  "type": "Feature",
  "properties": {
    "addr:full":"Chapel Cottage, Oakwood Road, Warwick Wold Redhill Surrey RH1 3DH",
    "addr:postcode":"rh1 3dh",
    "addr:street":"Oakwood Road;Redhill",
    "iso:country":"GB",
    "sg:address":"Chapel Cottage, Oakwood Road, Warwick Wold",
    "sg:city":"Redhill",
    "sg:classifiers":[
        {
            "category":"Building & Trades",
            "subcategory":"Construction",
            "type":"Services"
        }
    ],
    "sg:phone":"+44 1737 645499",
    "sg:postcode":"RH1 3DH",
    "sg:province":"Surrey",
    "sg:tags":[
        "builder"
    ],
    "wof:name":"Winder Building Services Ltd.",
    "wof:placetype":"venue"
},
  "geometry": {"coordinates":[-0.12021,51.26004],"type":"Point"}
}