{
  "type": "Feature",
  "properties": {
    "addr:full":"Barrys Lane Scarborough North Yorkshire YO12 4HA",
    "addr:postcode":"yo12 4ha",
    "addr:street":"Barrys Lane",
    "iso:country":"GB",
    "sg:address":"Barrys Lane",
    "sg:city":"Scarborough",
    "sg:classifiers":[
        {
            "category":"Food & Beverages",
            "subcategory":"Meat & Fish",
            "type":"Retail Goods"
        }
    ],
    "sg:phone":"+44 1723 360761",
    "sg:postcode":"YO12 4HA",
    "sg:province":"North Yorkshire",
    "sg:tags":[
        "merchant"
    ],
    "wof:name":"Albert Sutton Ltd.",
    "wof:placetype":"venue"
},
  "geometry": {"coordinates":[-0.416539,54.267414],"type":"Point"}
}