{
  "type": "Feature",
  "properties": {
    "addr:full":"1-2 Acton Oaks Shopping Centre, High St Acton Greater London W3 6RE",
    "addr:housenumber":"1-2",
    "addr:postcode":"w3 6re",
    "addr:street":"Acton Oaks;High St",
    "iso:country":"GB",
    "sg:address":"1-2 Acton Oaks Shopping Centre, High St",
    "sg:city":"Acton",
    "sg:classifiers":[
        {
            "category":"Professional",
            "subcategory":"Computer Services",
            "type":"Services"
        }
    ],
    "sg:phone":"+44 20 8993 0836",
    "sg:postcode":"W3 6RE",
    "sg:province":"Greater London",
    "sg:tags":[
        "system",
        "software"
    ],
    "wof:name":"KFC",
    "wof:placetype":"venue"
},
  "geometry": {"coordinates":[-0.2674590051,51.5132408142],"type":"Point"}
}