{
  "type": "Feature",
  "properties": {
    "iso:country":"GB",
    "sg:address":"55/57 Hall Rd",
    "sg:city":"Norwich",
    "sg:classifiers":[
        {
            "category":"Recreation",
            "type":"Entertainment"
        }
    ],
    "sg:postcode":"NR1 3HL",
    "sg:province":"Norfolk",
    "sg:tags":[
        "snooker",
        "billiards",
        "pool"
    ],
    "wof:name":"Pats Pool Club",
    "wof:placetype":"venue"
},
  "geometry": {"coordinates":[1.2978910208,52.6196784973],"type":"Point"}
}