{
  "type": "Feature",
  "properties": {
    "iso:country":"GB",
    "sg:address":"15 Fitzmaurice Av",
    "sg:city":"Eastbourne",
    "sg:classifiers":[
        {
            "category":"Retail",
            "subcategory":"Driving School",
            "type":"Services"
        }
    ],
    "sg:phone":"+44 1323 641720",
    "sg:postcode":"BN22 8PE",
    "sg:province":"East Sussex",
    "wof:name":"E A Carter",
    "wof:placetype":"venue"
},
  "geometry": {"coordinates":[0.2967920005,50.7812232971],"type":"Point"}
}