{
  "type": "Feature",
  "properties": {
    "iso:country":"GB",
    "sg:address":"Grounds Of Bishopswood School, Barlows Road",
    "sg:city":"Tadley",
    "sg:classifiers":[
        {
            "category":"Education",
            "subcategory":"Preschool",
            "type":"Public Place"
        }
    ],
    "sg:phone":"+44 118 981 1010",
    "sg:postcode":"RG26 3NA",
    "sg:province":"Berkshire",
    "sg:tags":[
        "pre-school",
        "playgroups"
    ],
    "wof:name":"Greenacre Pre School Unit",
    "wof:placetype":"venue"
},
  "geometry": {"coordinates":[-1.137541,51.350163],"type":"Point"}
}