{
  "type": "Feature",
  "properties": {
    "addr:full":"46 Edgware Rd Bayswater Greater London W2 2EH",
    "addr:housenumber":"46",
    "addr:postcode":"w2 2eh",
    "addr:street":"Edgware Rd",
    "iso:country":"GB",
    "sg:address":"46 Edgware Rd",
    "sg:city":"Bayswater",
    "sg:classifiers":[
        {
            "category":"Cafe",
            "type":"Food & Drink"
        }
    ],
    "sg:phone":"+44 20 7723 1604",
    "sg:postcode":"W2 2EH",
    "sg:province":"Greater London",
    "sg:tags":[
        "tea",
        "room"
    ],
    "wof:name":"Lindas Sandwich Bar",
    "wof:placetype":"venue"
},
  "geometry": {"coordinates":[-0.167033,51.517883],"type":"Point"}
}