{
  "type": "Feature",
  "properties": {
    "addr:full":"260 St Vincent Street Glasgow Glasgow City G2 5RL",
    "addr:housenumber":"260",
    "addr:postcode":"g2 5rl",
    "addr:street":"St Vincent Street",
    "iso:country":"GB",
    "sg:address":"260 St Vincent Street",
    "sg:city":"Glasgow",
    "sg:classifiers":[
        {
            "category":"Shopping",
            "subcategory":"Computers & Home Electronics",
            "type":"Retail Goods"
        }
    ],
    "sg:postcode":"G2 5RL",
    "sg:province":"Glasgow City",
    "sg:tags":[
        "hi-fi",
        "centre"
    ],
    "wof:name":"Stereo Stereo Ltd.",
    "wof:placetype":"venue"
},
  "geometry": {"coordinates":[-4.264489,55.862473],"type":"Point"}
}