{
  "type": "Feature",
  "properties": {
    "addr:full":"Cumberland, Victoria St Cannock Staffordshire WS12 5BT",
    "addr:postcode":"ws12 5bt",
    "addr:street":"Victoria St",
    "iso:country":"GB",
    "sg:address":"Cumberland, Victoria St",
    "sg:city":"Cannock",
    "sg:classifiers":[
        {
            "category":"Building & Trades",
            "subcategory":"Construction",
            "type":"Services"
        }
    ],
    "sg:phone":"+44 1543 422454",
    "sg:postcode":"WS12 5BT",
    "sg:province":"Staffordshire",
    "sg:tags":[
        "builder"
    ],
    "wof:name":"A H Evans Builder",
    "wof:placetype":"venue"
},
  "geometry": {"coordinates":[-1.9981199503,52.7102012634],"type":"Point"}
}