{
  "type": "Feature",
  "properties": {
    "addr:full":"416 Blurton Road Stoke-on-trent Staffordshire ST3 3AJ",
    "addr:housenumber":"416",
    "addr:postcode":"st3 3aj",
    "addr:street":"Blurton Road",
    "iso:country":"GB",
    "sg:address":"416 Blurton Road",
    "sg:city":"Stoke-on-trent",
    "sg:classifiers":[
        {
            "category":"Food & Beverages",
            "subcategory":"Liquor & Beverages",
            "type":"Retail Goods"
        }
    ],
    "sg:phone":"+44 1782 599079",
    "sg:postcode":"ST3 3AJ",
    "sg:province":"Staffordshire",
    "sg:tags":[
        "beer",
        "spirit",
        "wines"
    ],
    "wof:name":"Victoria Wine",
    "wof:placetype":"venue"
},
  "geometry": {"coordinates":[-2.1531550884,52.9797782898],"type":"Point"}
}