{
  "type": "Feature",
  "properties": {
    "addr:full":"186 Lovers Lane, Atherton Manchester Greater Manchester M46 0PZ",
    "addr:housenumber":"186",
    "addr:postcode":"m46 0pz",
    "addr:street":"Lovers Lane",
    "iso:country":"GB",
    "sg:address":"186 Lovers Lane, Atherton",
    "sg:city":"Manchester",
    "sg:classifiers":[
        {
            "category":"Professional",
            "subcategory":"Engineering",
            "type":"Services"
        },
        {
            "category":"Professional",
            "subcategory":"Art Services",
            "type":"Services"
        }
    ],
    "sg:phone":"+44 1942 799287",
    "sg:postcode":"M46 0PZ",
    "sg:province":"Greater Manchester",
    "sg:tags":[
        "consultant",
        "design",
        "engineer"
    ],
    "wof:name":"Aim Design Services Ltd.",
    "wof:placetype":"venue"
},
  "geometry": {"coordinates":[-2.5156669617,53.5221824646],"type":"Point"}
}