{
  "type": "Feature",
  "properties": {
    "addr:full":"52b Robertson St Hastings East Sussex TN34 1HL",
    "addr:housenumber":"52b",
    "addr:postcode":"tn34 1hl",
    "addr:street":"Robertson St",
    "iso:country":"GB",
    "sg:address":"52b Robertson St",
    "sg:city":"Hastings",
    "sg:classifiers":[
        {
            "category":"Shopping",
            "subcategory":"News",
            "type":"Retail Goods"
        }
    ],
    "sg:phone":"+44 1424 445439",
    "sg:postcode":"TN34 1HL",
    "sg:province":"East Sussex",
    "sg:tags":[
        "newsagent"
    ],
    "wof:name":"Sweet Selection",
    "wof:placetype":"venue"
},
  "geometry": {"coordinates":[0.5778239965,50.8551712036],"type":"Point"}
}