{
  "type": "Feature",
  "properties": {
    "addr:full":"79 High Street, South Normanton Alfreton Derbyshire DE55 2BP",
    "addr:housenumber":"79",
    "addr:postcode":"de55 2bp",
    "addr:street":"High Street",
    "iso:country":"GB",
    "sg:address":"79 High Street, South Normanton",
    "sg:city":"Alfreton",
    "sg:classifiers":[
        {
            "category":"Fast Food",
            "type":"Food & Drink"
        }
    ],
    "sg:phone":"+44 1773 811500",
    "sg:postcode":"DE55 2BP",
    "sg:province":"Derbyshire",
    "sg:tags":[
        "away",
        "take"
    ],
    "wof:name":"China House",
    "wof:placetype":"venue"
},
  "geometry": {"coordinates":[-1.3419179916,53.107093811],"type":"Point"}
}