{
  "type": "Feature",
  "properties": {
    "iso:country":"GB",
    "sg:address":"18 Sulby Gro",
    "sg:city":"Bradford",
    "sg:classifiers":[
        {
            "category":"Building & Trades",
            "subcategory":"Construction",
            "type":"Services"
        }
    ],
    "sg:phone":"+44 1274 614462",
    "sg:postcode":"BD10 0DB",
    "sg:province":"West Yorkshire",
    "sg:tags":[
        "glazier"
    ],
    "wof:name":"Joseph Michael Hartley",
    "wof:placetype":"venue"
},
  "geometry": {"coordinates":[-1.7089259624,53.8293762207],"type":"Point"}
}