{
  "type": "Feature",
  "properties": {
    "addr:full":"Alex House, 26 Felpham Road Bognor Regis West Sussex PO22 7AZ",
    "addr:housenumber":"26",
    "addr:postcode":"po22 7az",
    "addr:street":"Felpham Road",
    "iso:country":"GB",
    "sg:address":"Alex House, 26 Felpham Road",
    "sg:city":"Bognor Regis",
    "sg:classifiers":[
        {
            "category":"Professional",
            "subcategory":"Management & Consulting",
            "type":"Services"
        },
        {
            "category":"Professional",
            "subcategory":"Computer Services",
            "type":"Services"
        }
    ],
    "sg:phone":"+44 1243 861621",
    "sg:postcode":"PO22 7AZ",
    "sg:province":"West Sussex",
    "sg:tags":[
        "consultant",
        "system",
        "business",
        "software"
    ],
    "wof:name":"Keith Pottinger Associates",
    "wof:placetype":"venue"
},
  "geometry": {"coordinates":[-0.655862987,50.7876014709],"type":"Point"}
}