{
  "type": "Feature",
  "properties": {
    "addr:full":"4 Troon Close Bedford Bedfordshire MK41 8AY",
    "addr:housenumber":"4",
    "addr:postcode":"mk41 8ay",
    "addr:street":"Troon Close",
    "iso:country":"GB",
    "sg:address":"4 Troon Close",
    "sg:city":"Bedford",
    "sg:classifiers":[
        {
            "category":"Education",
            "subcategory":"Special Training",
            "type":"Public Place"
        }
    ],
    "sg:phone":"+44 1234 341444",
    "sg:postcode":"MK41 8AY",
    "sg:province":"Bedfordshire",
    "sg:tags":[
        "martial art",
        "instruction"
    ],
    "wof:name":"Tiska Karate",
    "wof:placetype":"venue"
},
  "geometry": {"coordinates":[-0.4511780143,52.1596870422],"type":"Point"}
}