{
  "type": "Feature",
  "properties": {
    "addr:full":"7a Bridge Street, Hatherleigh Okehampton Devon EX20 3HU",
    "addr:housenumber":"7a",
    "addr:postcode":"ex20 3hu",
    "addr:street":"Bridge Street",
    "iso:country":"GB",
    "sg:address":"7a Bridge Street, Hatherleigh",
    "sg:city":"Okehampton",
    "sg:classifiers":[
        {
            "category":"Food & Beverages",
            "subcategory":"Bakery",
            "type":"Retail Goods"
        }
    ],
    "sg:phone":"+44 1837 810234",
    "sg:postcode":"EX20 3HU",
    "sg:province":"Devon",
    "sg:tags":[
        "shop",
        "baker"
    ],
    "wof:name":"PETE'S HOME BAKE",
    "wof:placetype":"venue"
},
  "geometry": {"coordinates":[-4.072108,50.821018],"type":"Point"}
}