{
  "type": "Feature",
  "properties": {
    "addr:full":"Walled Garden Cottage, Wilton Lodge Park Hawick Cumbria TD9 7JL",
    "addr:postcode":"td9 7jl",
    "addr:street":"Walled;Park Hawick",
    "iso:country":"GB",
    "sg:address":"Walled Garden Cottage, Wilton Lodge Park",
    "sg:city":"Hawick",
    "sg:classifiers":[
        {
            "category":"Home & Garden",
            "subcategory":"Household Appliances",
            "type":"Retail Goods"
        }
    ],
    "sg:phone":"+44 1450 375464",
    "sg:postcode":"TD9 7JL",
    "sg:province":"Cumbria",
    "sg:tags":[
        "electrical"
    ],
    "wof:name":"Domestic Appliance Repairs",
    "wof:placetype":"venue"
},
  "geometry": {"coordinates":[-2.787549,55.422146],"type":"Point"}
}