{
  "type": "Feature",
  "properties": {
    "addr:full":"197 Bolton Road Blackburn Lancashire BB2 3QJ",
    "addr:housenumber":"197",
    "addr:postcode":"bb2 3qj",
    "addr:street":"Bolton Road",
    "iso:country":"GB",
    "sg:address":"197 Bolton Road",
    "sg:city":"Blackburn",
    "sg:classifiers":[
        {
            "category":"Bars & Pubs",
            "type":"Food & Drink"
        },
        {
            "category":"Community Center",
            "subcategory":"Social",
            "type":"Public Place"
        }
    ],
    "sg:phone":"+44 1254 670144",
    "sg:postcode":"BB2 3QJ",
    "sg:province":"Lancashire",
    "sg:tags":[
        "pubs",
        "house",
        "inn",
        "activity"
    ],
    "wof:name":"DANIEL THWAITES PLC",
    "wof:placetype":"venue"
},
  "geometry": {"coordinates":[-2.4880490303,53.7376098633],"type":"Point"}
}