{
  "type": "Feature",
  "properties": {
    "addr:full":"5 The Goods Yards, Nightingale Rd Horsham West Sussex RH12 2NW",
    "addr:housenumber":"5",
    "addr:postcode":"rh12 2nw",
    "addr:street":"The;Yards Nightingale Rd",
    "iso:country":"GB",
    "sg:address":"5 The Goods Yards, Nightingale Rd",
    "sg:city":"Horsham",
    "sg:classifiers":[
        {
            "category":"Retail",
            "subcategory":"Auto Repair",
            "type":"Services"
        }
    ],
    "sg:phone":"+44 1403 242479",
    "sg:postcode":"RH12 2NW",
    "sg:province":"West Sussex",
    "sg:tags":[
        "modification",
        "garage"
    ],
    "wof:name":"Shawmans Motors",
    "wof:placetype":"venue"
},
  "geometry": {"coordinates":[-0.329107,51.065182],"type":"Point"}
}