{
  "type": "Feature",
  "properties": {
    "iso:country":"GB",
    "sg:address":"56 Hyde Rd",
    "sg:city":"Paignton",
    "sg:classifiers":[
        {
            "category":"Shopping",
            "subcategory":"Comic Books",
            "type":"Retail Goods"
        }
    ],
    "sg:phone":"+44 1803 556830",
    "sg:postcode":"TQ4 5BY",
    "sg:province":"Devon",
    "sg:tags":[
        "jeweller"
    ],
    "wof:name":"W Bennett",
    "wof:placetype":"venue"
},
  "geometry": {"coordinates":[-3.565626,50.435848],"type":"Point"}
}