{
  "type": "Feature",
  "properties": {
    "addr:full":"Queens Building, Hastings Road Leicester Leicestershire LE5 0HX",
    "addr:postcode":"le5 0hx",
    "addr:street":"Hastings Road",
    "iso:country":"GB",
    "sg:address":"Queens Building, Hastings Road",
    "sg:city":"Leicester",
    "sg:classifiers":[
        {
            "category":"Wholesale",
            "subcategory":"Machinery & Supplies",
            "type":"Manufacturing & Wholesale Goods"
        },
        {
            "category":"Manufacturing",
            "subcategory":"Textiles",
            "type":"Manufacturing & Wholesale Goods"
        }
    ],
    "sg:phone":"+44 116 274 1515",
    "sg:postcode":"LE5 0HX",
    "sg:province":"Leicestershire",
    "sg:tags":[
        "knitwear",
        "industrial",
        "commercial"
    ],
    "wof:name":"Shima Seiki Europe Ltd.",
    "wof:placetype":"venue"
},
  "geometry": {"coordinates":[-1.1003199816,52.6453781128],"type":"Point"}
}