{
  "type": "Feature",
  "properties": {
    "addr:full":", Pontwelly Llandysul Carmarthenshire SA44 4AJ",
    "addr:postcode":"sa44 4aj",
    "iso:country":"GB",
    "sg:address":", Pontwelly",
    "sg:city":"Llandysul",
    "sg:classifiers":[
        {
            "category":"Food & Beverages",
            "subcategory":"Meat & Fish",
            "type":"Retail Goods"
        }
    ],
    "sg:phone":"+44 1559 363316",
    "sg:postcode":"SA44 4AJ",
    "sg:province":"Carmarthenshire",
    "sg:tags":[
        "butcher"
    ],
    "wof:name":"O.J Williams",
    "wof:placetype":"venue"
},
  "geometry": {"coordinates":[-4.3078169823,52.0444793701],"type":"Point"}
}