{
  "type": "Feature",
  "properties": {
    "iso:country":"GB",
    "sg:address":"12 Sawrey Street",
    "sg:city":"Plymouth",
    "sg:classifiers":[
        {
            "category":"Professional",
            "subcategory":"Engineering",
            "type":"Services"
        }
    ],
    "sg:phone":"+44 1752 262776",
    "sg:postcode":"PL1 3LA",
    "sg:province":"Devon",
    "sg:tags":[
        "precision",
        "engineer"
    ],
    "wof:name":"Yeo & Smith",
    "wof:placetype":"venue"
},
  "geometry": {"coordinates":[-4.152496,50.368801],"type":"Point"}
}