{
  "type": "Feature",
  "properties": {
    "addr:full":"91 Station Rd West Drayton Greater London UB7 7LT",
    "addr:housenumber":"91",
    "addr:postcode":"ub7 7lt",
    "addr:street":"Station Rd",
    "iso:country":"GB",
    "sg:address":"91 Station Rd",
    "sg:city":"West Drayton",
    "sg:classifiers":[
        {
            "category":"Taxi",
            "type":"Transportation"
        }
    ],
    "sg:phone":"+44 1895 812000",
    "sg:postcode":"UB7 7LT",
    "sg:province":"Greater London",
    "sg:tags":[
        "mini",
        "cab"
    ],
    "wof:name":"Uxbridge Car Service",
    "wof:placetype":"venue"
},
  "geometry": {"coordinates":[-0.471280992,51.5072669983],"type":"Point"}
}