{
  "type": "Feature",
  "properties": {
    "addr:full":"58a New Church Road Hove East Sussex BN3 4FL",
    "addr:housenumber":"58a",
    "addr:postcode":"bn3 4fl",
    "addr:street":"New Church Road",
    "iso:country":"GB",
    "sg:address":"58a New Church Road",
    "sg:city":"Hove",
    "sg:classifiers":[
        {
            "category":"Health Services",
            "subcategory":"Podiatrist",
            "type":"Services"
        }
    ],
    "sg:phone":"+44 1273 726575",
    "sg:postcode":"BN3 4FL",
    "sg:province":"East Sussex",
    "sg:tags":[
        "podiatrists",
        "chiropodist"
    ],
    "wof:name":"Feetures of Hove",
    "wof:placetype":"venue"
},
  "geometry": {"coordinates":[-0.185909,50.829746],"type":"Point"}
}