{
  "type": "Feature",
  "properties": {
    "addr:full":"Blackwater House, The Street Chelmsford Essex CM3 6QH",
    "addr:postcode":"cm3 6qh",
    "addr:street":"The Street",
    "iso:country":"GB",
    "sg:address":"Blackwater House, The Street",
    "sg:city":"Chelmsford",
    "sg:classifiers":[
        {
            "category":"Building & Trades",
            "subcategory":"Plumbing",
            "type":"Services"
        }
    ],
    "sg:postcode":"CM3 6QH",
    "sg:province":"Essex",
    "sg:tags":[
        "heating"
    ],
    "wof:name":"Wilson Plumbing & Heating Contractors",
    "wof:placetype":"venue"
},
  "geometry": {"coordinates":[0.724312,51.671589],"type":"Point"}
}