{
  "type": "Feature",
  "properties": {
    "iso:country":"GB",
    "sg:address":"288 Ashby High Street, Ashby",
    "sg:city":"Scunthorpe",
    "sg:classifiers":[
        {
            "category":"Shopping",
            "subcategory":"Computers & Home Electronics",
            "type":"Retail Goods"
        },
        {
            "category":"Professional",
            "subcategory":"Computer Services",
            "type":"Services"
        }
    ],
    "sg:phone":"+44 1724 277700",
    "sg:postcode":"DN16 2RS",
    "sg:province":"Lincolnshire",
    "sg:tags":[
        "system",
        "software"
    ],
    "wof:name":"Axiom Computers Ltd.",
    "wof:placetype":"venue"
},
  "geometry": {"coordinates":[-0.652646,53.566689],"type":"Point"}
}