{
  "type": "Feature",
  "properties": {
    "addr:full":"Fleet House, 57-61 Clerkenwell Road London Greater London EC1M 5LA",
    "addr:housenumber":"57-61",
    "addr:postcode":"ec1m 5la",
    "addr:street":"Clerkenwell Road",
    "iso:country":"GB",
    "sg:address":"Fleet House, 57-61 Clerkenwell Road",
    "sg:city":"London",
    "sg:classifiers":[
        {
            "category":"Professional",
            "type":"Services"
        }
    ],
    "sg:phone":"+44 20 7014 8700",
    "sg:postcode":"EC1M 5LA",
    "sg:province":"Greater London",
    "sg:tags":[
        "entertainer"
    ],
    "wof:name":"Music Choice Ltd.",
    "wof:placetype":"venue"
},
  "geometry": {"coordinates":[-0.1008550003,51.5228805542],"type":"Point"}
}