{
  "type": "Feature",
  "properties": {
    "addr:full":"1 Silverdale Stanford-le-hope Essex SS17 8BG",
    "addr:housenumber":"1",
    "addr:postcode":"ss17 8bg",
    "addr:street":"Silverdale Stanford-Le-Hope",
    "iso:country":"GB",
    "sg:address":"1 Silverdale",
    "sg:city":"Stanford-le-hope",
    "sg:classifiers":[
        {
            "category":"Building & Trades",
            "subcategory":"Construction",
            "type":"Services"
        }
    ],
    "sg:phone":"+44 1375 642876",
    "sg:postcode":"SS17 8BG",
    "sg:province":"Essex",
    "sg:tags":[
        "builder"
    ],
    "wof:name":"Alan Calder",
    "wof:placetype":"venue"
},
  "geometry": {"coordinates":[0.43092,51.52639],"type":"Point"}
}