{
  "type": "Feature",
  "properties": {
    "addr:full":"4 High Street Uttoxeter Derbyshire ST14 7HT",
    "addr:housenumber":"4",
    "addr:postcode":"st14 7ht",
    "addr:street":"High Street",
    "iso:country":"GB",
    "sg:address":"4 High Street",
    "sg:city":"Uttoxeter",
    "sg:classifiers":[
        {
            "category":"Shopping",
            "subcategory":"Clothing, Apparel, & Fashions",
            "type":"Retail Goods"
        }
    ],
    "sg:phone":"+44 1889 565633",
    "sg:postcode":"ST14 7HT",
    "sg:province":"Derbyshire",
    "sg:tags":[
        "shop"
    ],
    "wof:name":"Buxton & Bonnett",
    "wof:placetype":"venue"
},
  "geometry": {"coordinates":[-1.86481,52.898697],"type":"Point"}
}