{
  "type": "Feature",
  "properties": {
    "addr:full":"Emerald House, East Street Epsom Surrey KT17 1HS",
    "addr:postcode":"kt17 1hs",
    "addr:street":"East Street",
    "iso:country":"GB",
    "sg:address":"Emerald House, East Street",
    "sg:city":"Epsom",
    "sg:classifiers":[
        {
            "category":"Real Estate",
            "subcategory":"Developer",
            "type":"Services"
        }
    ],
    "sg:postcode":"KT17 1HS",
    "sg:province":"Surrey",
    "sg:tags":[
        "property"
    ],
    "wof:name":"Horsleydown Mansions Ltd",
    "wof:placetype":"venue"
},
  "geometry": {"coordinates":[-0.2556239963,51.339641571],"type":"Point"}
}