{
  "type": "Feature",
  "properties": {
    "addr:full":"Ridge Grn, Shaw Swindon Wiltshire SN5 5PU",
    "addr:postcode":"sn5 5pu",
    "addr:street":"Ridge Grn",
    "iso:country":"GB",
    "sg:address":"Ridge Grn, Shaw",
    "sg:city":"Swindon",
    "sg:classifiers":[
        {
            "category":"Education",
            "subcategory":"School",
            "type":"Public Place"
        },
        {
            "category":"Government",
            "subcategory":"Office",
            "type":"Public Place"
        }
    ],
    "sg:phone":"+44 1793 871601",
    "sg:postcode":"SN5 5PU",
    "sg:province":"Wiltshire",
    "sg:tags":[
        "local",
        "authority"
    ],
    "wof:name":"Shaw Ridge Primary School",
    "wof:placetype":"venue"
},
  "geometry": {"coordinates":[-1.82899,51.565033],"type":"Point"}
}