{
  "type": "Feature",
  "properties": {
    "iso:country":"GB",
    "sg:address":"15-17 Crossgate",
    "sg:city":"Cupar",
    "sg:classifiers":[
        {
            "category":"Shopping",
            "subcategory":"Clothing, Apparel, & Fashions",
            "type":"Retail Goods"
        }
    ],
    "sg:postcode":"KY15 5HA",
    "sg:province":"Fife",
    "sg:tags":[
        "accessory"
    ],
    "wof:name":"Laidlaw,Patrica,",
    "wof:placetype":"venue"
},
  "geometry": {"coordinates":[-3.011922,56.319046],"type":"Point"}
}