{
  "type": "Feature",
  "properties": {
    "addr:full":"43 Lower Road, Breachwood Grn Hitchin Hertfordshire SG4 8NS",
    "addr:housenumber":"43",
    "addr:postcode":"sg4 8ns",
    "addr:street":"Lower Road Breachwood Grn",
    "iso:country":"GB",
    "sg:address":"43 Lower Road, Breachwood Grn",
    "sg:city":"Hitchin",
    "sg:classifiers":[
        {
            "category":"Home & Garden",
            "subcategory":"Building Materials",
            "type":"Retail Goods"
        }
    ],
    "sg:phone":"+44 1438 832098",
    "sg:postcode":"SG4 8NS",
    "sg:province":"Hertfordshire",
    "sg:tags":[
        "fencing"
    ],
    "wof:name":"Paul J Cullen",
    "wof:placetype":"venue"
},
  "geometry": {"coordinates":[-0.325609,51.88496],"type":"Point"}
}