{
  "type": "Feature",
  "properties": {
    "iso:country":"GB",
    "sg:address":"68 Lincoln Rd",
    "sg:city":"Enfield",
    "sg:classifiers":[
        {
            "category":"Professional",
            "type":"Services"
        }
    ],
    "sg:phone":"+44 20 8363 6621",
    "sg:postcode":"EN1 1JU",
    "sg:province":"Greater London",
    "sg:tags":[
        "caterer"
    ],
    "wof:name":"Avalon Caterers",
    "wof:placetype":"venue"
},
  "geometry": {"coordinates":[-0.072376,51.647243],"type":"Point"}
}