{
  "type": "Feature",
  "properties": {
    "iso:country":"GB",
    "sg:address":"30 High Street, Metheringham",
    "sg:city":"Lincoln",
    "sg:classifiers":[
        {
            "category":"Farming",
            "subcategory":"Crops",
            "type":"Manufacturing & Wholesale Goods"
        },
        {
            "category":"Farming",
            "subcategory":"Farm",
            "type":"Manufacturing & Wholesale Goods"
        }
    ],
    "sg:phone":"+44 1526 320539",
    "sg:postcode":"LN4 3EA",
    "sg:province":"Lincolnshire",
    "sg:tags":[
        "mixed",
        "arable"
    ],
    "wof:name":"F S Lamyman & Sons",
    "wof:placetype":"venue"
},
  "geometry": {"coordinates":[-0.325328,53.124382],"type":"Point"}
}