{
  "type": "Feature",
  "properties": {
    "iso:country":"GB",
    "sg:address":"24 Crosshill Drive",
    "sg:city":"Carlisle",
    "sg:classifiers":[
        {
            "category":"Retail",
            "subcategory":"Driving School",
            "type":"Services"
        }
    ],
    "sg:phone":"+44 1228 532595",
    "sg:postcode":"CA2 6RS",
    "sg:province":"Cumbria",
    "wof:name":"ABBEY SCHOOL OF MOTORING",
    "wof:placetype":"venue"
},
  "geometry": {"coordinates":[-2.96644,54.887627],"type":"Point"}
}