{
  "type": "Feature",
  "properties": {
    "addr:full":"Brigella Mills, Little Horton Lane Bradford West Yorkshire BD5 0QA",
    "addr:postcode":"bd5 0qa",
    "addr:street":"Horton Lane",
    "iso:country":"GB",
    "sg:address":"Brigella Mills, Little Horton Lane",
    "sg:city":"Bradford",
    "sg:classifiers":[
        {
            "category":"Manufacturing",
            "subcategory":"Textiles",
            "type":"Manufacturing & Wholesale Goods"
        },
        {
            "category":"Manufacturing",
            "subcategory":"Furniture",
            "type":"Manufacturing & Wholesale Goods"
        }
    ],
    "sg:phone":"+44 1274 571181",
    "sg:postcode":"BD5 0QA",
    "sg:province":"West Yorkshire",
    "sg:tags":[
        "manufacture",
        "made-up",
        "fitting"
    ],
    "sg:website":"http://www.hield.co.uk",
    "wof:name":"Hield Brothers Ltd.",
    "wof:placetype":"venue"
},
  "geometry": {"coordinates":[-1.75742805,53.7906265259],"type":"Point"}
}