{
  "type": "Feature",
  "properties": {
    "iso:country":"GB",
    "sg:address":"Bay Hall Works, Miln Road, Birkby",
    "sg:city":"Huddersfield",
    "sg:classifiers":[
        {
            "category":"Community Center",
            "type":"Public Place"
        }
    ],
    "sg:postcode":"HD1 5EH",
    "sg:province":"West Yorkshire",
    "sg:tags":[
        "recreation",
        "leisure",
        "centre"
    ],
    "wof:name":"Jumping Jacks",
    "wof:placetype":"venue"
},
  "geometry": {"coordinates":[-1.789164,53.65836],"type":"Point"}
}