{
  "type": "Feature",
  "properties": {
    "iso:country":"GB",
    "sg:address":"132 High Street",
    "sg:city":"Newport Pagnell",
    "sg:classifiers":[
        {
            "category":"Building & Trades",
            "subcategory":"Construction",
            "type":"Services"
        }
    ],
    "sg:phone":"+44 1908 612047",
    "sg:postcode":"MK16 8EH",
    "sg:province":"Buckinghamshire",
    "sg:tags":[
        "roofing"
    ],
    "wof:name":"D E R Roofing",
    "wof:placetype":"venue"
},
  "geometry": {"coordinates":[-0.728556,52.085365],"type":"Point"}
}