{
  "type": "Feature",
  "properties": {
    "iso:country":"GB",
    "sg:address":"305-321 Whitegate Drive, Whitegate",
    "sg:city":"Blackpool",
    "sg:classifiers":[
        {
            "category":"Food & Beverages",
            "subcategory":"Supermarket",
            "type":"Retail Goods"
        }
    ],
    "sg:phone":"+44 1253 693375",
    "sg:postcode":"FY3 9JS",
    "sg:province":"Lancashire",
    "wof:name":"Kwik Save Foodstores",
    "wof:placetype":"venue"
},
  "geometry": {"coordinates":[-3.028839,53.806042],"type":"Point"}
}