{
  "type": "Feature",
  "properties": {
    "addr:full":"Oakwell View Barnsley South Yorkshire S71 1HH",
    "addr:postcode":"s71 1hh",
    "addr:street":"Oakwell View;Yorkshire",
    "iso:country":"GB",
    "sg:address":"Oakwell View",
    "sg:city":"Barnsley",
    "sg:classifiers":[
        {
            "category":"Conference Center",
            "type":"Public Place"
        }
    ],
    "sg:phone":"+44 1226 732911",
    "sg:postcode":"S71 1HH",
    "sg:province":"South Yorkshire",
    "sg:tags":[
        "business",
        "centre"
    ],
    "wof:name":"Mount Osborne Business Centre",
    "wof:placetype":"venue"
},
  "geometry": {"coordinates":[-1.465762,53.549374],"type":"Point"}
}