{
  "type": "Feature",
  "properties": {
    "iso:country":"GB",
    "sg:address":"14 Market Walk, King Street",
    "sg:city":"Huddersfield",
    "sg:classifiers":[
        {
            "category":"Education",
            "subcategory":"Dance Studio",
            "type":"Public Place"
        }
    ],
    "sg:phone":"+44 1422 374137",
    "sg:postcode":"HD1 2QA",
    "sg:province":"West Yorkshire",
    "sg:tags":[
        "school",
        "dancing"
    ],
    "wof:name":"Barbara Peters School of Dancing",
    "wof:placetype":"venue"
},
  "geometry": {"coordinates":[-1.782684,53.646954],"type":"Point"}
}