{
  "type": "Feature",
  "properties": {
    "addr:full":"No 1 Beresford Court, Bellevue Road Cinderford Gloucestershire GL14 2BS",
    "addr:postcode":"gl14 2bs",
    "addr:street":"Beresford Court Bellevue Road",
    "iso:country":"GB",
    "sg:address":"No 1 Beresford Court, Bellevue Road",
    "sg:city":"Cinderford",
    "sg:classifiers":[
        {
            "category":"Government",
            "subcategory":"Office",
            "type":"Public Place"
        }
    ],
    "sg:phone":"+44 1594 827478",
    "sg:postcode":"GL14 2BS",
    "sg:province":"Gloucestershire",
    "sg:tags":[
        "development",
        "agency"
    ],
    "wof:name":"Cinderford Partnership",
    "wof:placetype":"venue"
},
  "geometry": {"coordinates":[-2.499834,51.825214],"type":"Point"}
}