{
  "type": "Feature",
  "properties": {
    "iso:country":"GB",
    "sg:address":"22 Front St, Sunnyside",
    "sg:city":"Bishop Auckland",
    "sg:classifiers":[
        {
            "category":"Building & Trades",
            "subcategory":"Construction",
            "type":"Services"
        }
    ],
    "sg:phone":"+44 1388 731638",
    "sg:postcode":"DL13 4LP",
    "sg:province":"Durham",
    "sg:tags":[
        "joinery"
    ],
    "wof:name":"Wico Ltd",
    "wof:placetype":"venue"
},
  "geometry": {"coordinates":[-1.7817889452,54.7406082153],"type":"Point"}
}