{
  "type": "Feature",
  "properties": {
    "addr:full":"2 Sandringham Road Hunstanton Norfolk PE36 5BN",
    "addr:housenumber":"2",
    "addr:postcode":"pe36 5bn",
    "addr:street":"Sandringham Road",
    "iso:country":"GB",
    "sg:address":"2 Sandringham Road",
    "sg:city":"Hunstanton",
    "sg:classifiers":[
        {
            "category":"Place Of Worship",
            "type":"Public Place"
        }
    ],
    "sg:phone":"+44 1485 533309",
    "sg:postcode":"PE36 5BN",
    "sg:province":"Norfolk",
    "wof:name":"Union Church",
    "wof:placetype":"venue"
},
  "geometry": {"coordinates":[0.4891059995,52.9382171631],"type":"Point"}
}