{
  "type": "Feature",
  "properties": {
    "iso:country":"GB",
    "sg:address":"195 Alexandra Road",
    "sg:city":"Ashington",
    "sg:classifiers":[
        {
            "category":"Professional",
            "subcategory":"Printing & Photocopies",
            "type":"Services"
        }
    ],
    "sg:phone":"+44 1670 816407",
    "sg:postcode":"NE63 9LA",
    "sg:province":"Northumberland",
    "sg:tags":[
        "printer"
    ],
    "wof:name":"Crescent Printing Co.",
    "wof:placetype":"venue"
},
  "geometry": {"coordinates":[-1.5550060272,55.1801185608],"type":"Point"}
}