{
  "type": "Feature",
  "properties": {
    "addr:full":"60 Bouldish Farm Rd Ascot Berkshire SL5 9EL",
    "addr:housenumber":"60",
    "addr:postcode":"sl5 9el",
    "addr:street":"Bouldish Farm Rd",
    "iso:country":"GB",
    "sg:address":"60 Bouldish Farm Rd",
    "sg:city":"Ascot",
    "sg:classifiers":[
        {
            "category":"Building & Trades",
            "subcategory":"Plumbing",
            "type":"Services"
        }
    ],
    "sg:phone":"+44 1344 623089",
    "sg:postcode":"SL5 9EL",
    "sg:province":"Berkshire",
    "sg:tags":[
        "heating"
    ],
    "wof:name":"C Stevens",
    "wof:placetype":"venue"
},
  "geometry": {"coordinates":[-0.6796789765,51.4036102295],"type":"Point"}
}