{
  "type": "Feature",
  "properties": {
    "addr:full":"7 Alfred Street Bath Bath and North East Somerset BA1 2QU",
    "addr:housenumber":"7",
    "addr:postcode":"ba1 2qu",
    "addr:street":"Alfred Street",
    "iso:country":"GB",
    "sg:address":"7 Alfred Street",
    "sg:city":"Bath",
    "sg:classifiers":[
        {
            "category":"Professional",
            "subcategory":"Art Services",
            "type":"Services"
        }
    ],
    "sg:phone":"+44 1225 469892",
    "sg:postcode":"BA1 2QU",
    "sg:province":"Bath and North East Somerset",
    "sg:tags":[
        "consultant",
        "graphic",
        "design",
        "designer"
    ],
    "wof:name":"ARMADILLO ASSOCIATES LTD",
    "wof:placetype":"venue"
},
  "geometry": {"coordinates":[-2.3619370461,51.3859214783],"type":"Point"}
}