{
  "type": "Feature",
  "properties": {
    "addr:full":"Unit 19 Hartford Way, Sealand Trading Estate Chester Cheshire CH1 4NT",
    "addr:housenumber":"unit 19",
    "addr:postcode":"ch1 4nt",
    "addr:street":"Hartford Way;Trading Estate",
    "iso:country":"GB",
    "sg:address":"Unit 19 Hartford Way, Sealand Trading Estate",
    "sg:city":"Chester",
    "sg:classifiers":[
        {
            "category":"Autos & Motor Vehicles",
            "subcategory":"Auto Supplies",
            "type":"Retail Goods"
        }
    ],
    "sg:phone":"+44 1244 324034",
    "sg:postcode":"CH1 4NT",
    "sg:province":"Cheshire",
    "sg:tags":[
        "towing",
        "eqpt",
        "trailer"
    ],
    "wof:name":"Chester Towbar & Trailer Centre",
    "wof:placetype":"venue"
},
  "geometry": {"coordinates":[-2.910549,53.194675],"type":"Point"}
}