{
  "type": "Feature",
  "properties": {
    "iso:country":"GB",
    "sg:address":"26 Castle Street",
    "sg:city":"Paisley",
    "sg:classifiers":[
        {
            "category":"Organizations",
            "subcategory":"Community Association",
            "type":"Services"
        },
        {
            "category":"Organizations",
            "subcategory":"Membership Organization",
            "type":"Services"
        }
    ],
    "sg:phone":"+44 141 561 7473",
    "sg:postcode":"PA1 2JP",
    "sg:province":"Renfrewshire",
    "sg:tags":[
        "club",
        "social"
    ],
    "wof:name":"Castle Social Club",
    "wof:placetype":"venue"
},
  "geometry": {"coordinates":[-4.4372048378,55.8424491882],"type":"Point"}
}