{
  "type": "Feature",
  "properties": {
    "addr:full":"10 King Charles Terrace, Sovereign Close Whitechapel Devon E1W3HL",
    "addr:housenumber":"10",
    "addr:postcode":"e1w3hl",
    "addr:street":"King Charles Terrace Sovereign Close",
    "iso:country":"GB",
    "sg:address":"10 King Charles Terrace, Sovereign Close",
    "sg:city":"Whitechapel",
    "sg:classifiers":[
        {
            "category":"Professional",
            "subcategory":"Management & Consulting",
            "type":"Services"
        }
    ],
    "sg:phone":"+44 20 7956 1008",
    "sg:postcode":"E1W3HL",
    "sg:province":"Devon",
    "sg:tags":[
        "consultant",
        "business"
    ],
    "wof:name":"Chatworth Consulting",
    "wof:placetype":"venue"
},
  "geometry": {"coordinates":[-0.05735,51.509022],"type":"Point"}
}