{
  "type": "Feature",
  "properties": {
    "iso:country":"GB",
    "sg:address":"Chailey, Chelveston Road, Raunds",
    "sg:city":"Wellingborough",
    "sg:classifiers":[
        {
            "category":"Building & Trades",
            "subcategory":"Equipment Rental",
            "type":"Services"
        }
    ],
    "sg:postcode":"NN9 6DA",
    "sg:province":"Northamptonshire",
    "sg:tags":[
        "plant",
        "machinery"
    ],
    "wof:name":"David Briggs",
    "wof:placetype":"venue"
},
  "geometry": {"coordinates":[-0.547759,52.315777],"type":"Point"}
}