{
  "type": "Feature",
  "properties": {
    "iso:country":"GB",
    "sg:address":"The Laurels, 296 Collingwood Rd",
    "sg:city":"Sutton",
    "sg:classifiers":[
        {
            "category":"Organizations",
            "subcategory":"Non-profit Organization",
            "type":"Services"
        }
    ],
    "sg:phone":"+44 20 8644 4521",
    "sg:postcode":"SM1 2NX",
    "sg:province":"Surrey",
    "sg:tags":[
        "organisation",
        "voluntary",
        "charity"
    ],
    "wof:name":"Community Services For The Disabled",
    "wof:placetype":"venue"
},
  "geometry": {"coordinates":[-0.197558,51.361191],"type":"Point"}
}