{
  "type": "Feature",
  "properties": {
    "addr:full":"Ickle Cottage, Chewton Hill Bath Somerset BA3 4NQ",
    "addr:postcode":"ba3 4nq",
    "addr:street":"Chewton Hill",
    "iso:country":"GB",
    "sg:address":"Ickle Cottage, Chewton Hill",
    "sg:city":"Bath",
    "sg:classifiers":[
        {
            "category":"Building & Trades",
            "subcategory":"Construction",
            "type":"Services"
        }
    ],
    "sg:phone":"+44 1761 241108",
    "sg:postcode":"BA3 4NQ",
    "sg:province":"Somerset",
    "sg:tags":[
        "joiner",
        "carpenter"
    ],
    "wof:name":"Paul Gane",
    "wof:placetype":"venue"
},
  "geometry": {"coordinates":[-2.5756499767,51.276348114],"type":"Point"}
}