{
  "type": "Feature",
  "properties": {
    "addr:full":"10 Colman Parade, Southbury Road Enfield Greater London EN1 1YY",
    "addr:housenumber":"10",
    "addr:postcode":"en1 1yy",
    "addr:street":"Colman Parade Southbury Road",
    "iso:country":"GB",
    "sg:address":"10 Colman Parade, Southbury Road",
    "sg:city":"Enfield",
    "sg:classifiers":[
        {
            "category":"Shopping",
            "subcategory":"News",
            "type":"Retail Goods"
        }
    ],
    "sg:phone":"+44 20 8363 0471",
    "sg:postcode":"EN1 1YY",
    "sg:province":"Greater London",
    "sg:tags":[
        "newsagent"
    ],
    "wof:name":"News & Chews",
    "wof:placetype":"venue"
},
  "geometry": {"coordinates":[-0.07903,51.652279],"type":"Point"}
}