{
  "type": "Feature",
  "properties": {
    "addr:full":"5 St Alban Street Weymouth Dorset DT4 8BZ",
    "addr:housenumber":"5",
    "addr:postcode":"dt4 8bz",
    "addr:street":"St Alban Street",
    "iso:country":"GB",
    "sg:address":"5 St Alban Street",
    "sg:city":"Weymouth",
    "sg:classifiers":[
        {
            "category":"Shopping",
            "subcategory":"Hobbies, Toys, & Games",
            "type":"Retail Goods"
        }
    ],
    "sg:phone":"+44 1305 780601",
    "sg:postcode":"DT4 8BZ",
    "sg:province":"Dorset",
    "sg:tags":[
        "shop",
        "toy",
        "sale"
    ],
    "wof:name":"Razzamataz",
    "wof:placetype":"venue"
},
  "geometry": {"coordinates":[-2.4535250664,50.6087493896],"type":"Point"}
}