{
  "type": "Feature",
  "properties": {
    "addr:full":"Richmond House Chepstow Gloucestershire NP16 5EP",
    "addr:postcode":"np16 5ep",
    "iso:country":"GB",
    "sg:address":"Richmond House",
    "sg:city":"Chepstow",
    "sg:classifiers":[
        {
            "category":"Banks & Credit Unions",
            "subcategory":"Financial Services",
            "type":"Services"
        }
    ],
    "sg:phone":"+44 1291 622077",
    "sg:postcode":"NP16 5EP",
    "sg:province":"Gloucestershire",
    "sg:tags":[
        "adviser"
    ],
    "wof:name":"Chepstow Financial Services",
    "wof:placetype":"venue"
},
  "geometry": {"coordinates":[-2.6798119545,51.637878418],"type":"Point"}
}