{
  "type": "Feature",
  "properties": {
    "addr:full":"82 Mitchell St Glasgow Glasgow City G1 3NA",
    "addr:housenumber":"82",
    "addr:postcode":"g1 3na",
    "addr:street":"Mitchell St",
    "iso:country":"GB",
    "sg:address":"82 Mitchell St",
    "sg:city":"Glasgow",
    "sg:classifiers":[
        {
            "category":"Shopping",
            "subcategory":"Clothing, Apparel, & Fashions",
            "type":"Retail Goods"
        }
    ],
    "sg:postcode":"G1 3NA",
    "sg:province":"Glasgow City",
    "sg:tags":[
        "dresswear"
    ],
    "wof:name":"Sochart,Gerald,",
    "wof:placetype":"venue"
},
  "geometry": {"coordinates":[-4.255478,55.860004],"type":"Point"}
}