{
  "type": "Feature",
  "properties": {
    "addr:full":"2 The Courtyard, Denmark St Wokingham Berkshire RG40 2AZ",
    "addr:housenumber":"2",
    "addr:postcode":"rg40 2az",
    "addr:street":"The Courtyard Denmark St",
    "iso:country":"GB",
    "sg:address":"2 The Courtyard, Denmark St",
    "sg:city":"Wokingham",
    "sg:classifiers":[
        {
            "category":"Shopping",
            "subcategory":"Hobbies, Toys, & Games",
            "type":"Retail Goods"
        }
    ],
    "sg:postcode":"RG40 2AZ",
    "sg:province":"Berkshire",
    "sg:tags":[
        "computer"
    ],
    "wof:name":"Bizarre Love Triangle Ltd",
    "wof:placetype":"venue"
},
  "geometry": {"coordinates":[-0.8345940113,51.4108009338],"type":"Point"}
}