{
  "type": "Feature",
  "properties": {
    "iso:country":"GB",
    "sg:address":"4 Stoney Street, Beeston",
    "sg:city":"Nottingham",
    "sg:classifiers":[
        {
            "category":"Home & Garden",
            "subcategory":"Kitchen Supply",
            "type":"Retail Goods"
        }
    ],
    "sg:phone":"+44 115 922 0304",
    "sg:postcode":"NG9 2LA",
    "sg:province":"Nottinghamshire",
    "sg:tags":[
        "ware"
    ],
    "wof:name":"Euphoria",
    "wof:placetype":"venue"
},
  "geometry": {"coordinates":[-1.21414,52.928459],"type":"Point"}
}