{
  "type": "Feature",
  "properties": {
    "iso:country":"GB",
    "sg:address":"Block 1 Bandeath Industrial Estate, Throsk",
    "sg:city":"Stirling",
    "sg:classifiers":[
        {
            "category":"Food & Beverages",
            "subcategory":"Liquor & Beverages",
            "type":"Retail Goods"
        }
    ],
    "sg:phone":"+44 1786 813805",
    "sg:postcode":"FK7 7NP",
    "sg:province":"Falkirk",
    "sg:tags":[
        "beer",
        "wine",
        "spirit",
        "wines"
    ],
    "wof:name":"Vicomte Bernard De Romanet",
    "wof:placetype":"venue"
},
  "geometry": {"coordinates":[-3.847524,56.09893],"type":"Point"}
}