{
  "type": "Feature",
  "properties": {
    "iso:country":"GB",
    "sg:address":"Southmeads Road",
    "sg:city":"Leicester",
    "sg:classifiers":[
        {
            "category":"Building & Trades",
            "subcategory":"Construction",
            "type":"Services"
        }
    ],
    "sg:phone":"+44 116 271 9891",
    "sg:postcode":"LE2 2LR",
    "sg:province":"Leicestershire",
    "sg:tags":[
        "builder"
    ],
    "wof:name":"C W R Ireland Builder",
    "wof:placetype":"venue"
},
  "geometry": {"coordinates":[-1.0887659788,52.6071205139],"type":"Point"}
}