{
  "type": "Feature",
  "properties": {
    "addr:full":"Castle Street Telford Shropshire TF1 5YN",
    "addr:postcode":"tf1 5yn",
    "addr:street":"Castle Street",
    "iso:country":"GB",
    "sg:address":"Castle Street",
    "sg:city":"Telford",
    "sg:classifiers":[
        {
            "category":"Autos & Motor Vehicles",
            "subcategory":"Automobile Sales",
            "type":"Retail Goods"
        }
    ],
    "sg:phone":"+44 1952 222666",
    "sg:postcode":"TF1 5YN",
    "sg:province":"Shropshire",
    "sg:tags":[
        "car"
    ],
    "wof:name":"Hylton of Telford Ltd.",
    "wof:placetype":"venue"
},
  "geometry": {"coordinates":[-2.479222,52.70575],"type":"Point"}
}