{
  "type": "Feature",
  "properties": {
    "iso:country":"GB",
    "sg:address":"56 Bellamy St",
    "sg:city":"London",
    "sg:classifiers":[
        {
            "category":"Professional",
            "subcategory":"Management & Consulting",
            "type":"Services"
        }
    ],
    "sg:phone":"+44 20 8673 0679",
    "sg:postcode":"SW12 8BU",
    "sg:province":"Greater London",
    "sg:tags":[
        "marketing",
        "consultant"
    ],
    "wof:name":"Fforde,Diana,",
    "wof:placetype":"venue"
},
  "geometry": {"coordinates":[-0.151022,51.449444],"type":"Point"}
}