{
  "type": "Feature",
  "properties": {
    "iso:country":"GB",
    "sg:address":"49a Warrington Street",
    "sg:city":"Ashton-under-lyne",
    "sg:classifiers":[
        {
            "category":"Travel",
            "subcategory":"Travel Agent",
            "type":"Entertainment"
        }
    ],
    "sg:phone":"+44 161 251 1939",
    "sg:postcode":"OL6 7JG",
    "sg:province":"Greater Manchester",
    "wof:name":"Thomas Cook",
    "wof:placetype":"venue"
},
  "geometry": {"coordinates":[-2.094015,53.488396],"type":"Point"}
}