{
  "type": "Feature",
  "properties": {
    "addr:full":"East Brackenridge Farm Strathaven South Lanarkshire ML10 6QB",
    "addr:postcode":"ml10 6qb",
    "addr:street":"East",
    "iso:country":"GB",
    "sg:address":"East Brackenridge Farm",
    "sg:city":"Strathaven",
    "sg:classifiers":[
        {
            "category":"Farming",
            "subcategory":"Dairy Farm",
            "type":"Manufacturing & Wholesale Goods"
        }
    ],
    "sg:phone":"+44 1357 520247",
    "sg:postcode":"ML10 6QB",
    "sg:province":"South Lanarkshire",
    "wof:name":"East Brackenridge Farm",
    "wof:placetype":"venue"
},
  "geometry": {"coordinates":[-4.066794,55.676979],"type":"Point"}
}