{
  "type": "Feature",
  "properties": {
    "iso:country":"GB",
    "sg:address":"81 Harrow Road, West Bridgford",
    "sg:city":"Nottingham",
    "sg:classifiers":[
        {
            "category":"Retail",
            "subcategory":"Auto Repair",
            "type":"Services"
        }
    ],
    "sg:postcode":"NG2 7DY",
    "sg:province":"Nottinghamshire",
    "sg:tags":[
        "modification",
        "garage"
    ],
    "wof:name":"White City Autos Ltd.",
    "wof:placetype":"venue"
},
  "geometry": {"coordinates":[-1.132611,52.918541],"type":"Point"}
}