{
  "type": "Feature",
  "properties": {
    "addr:full":"2 Pevensey Close North Shields Tyne and Wear NE29 9HW",
    "addr:housenumber":"2",
    "addr:postcode":"ne29 9hw",
    "addr:street":"Pevensey Close",
    "iso:country":"GB",
    "sg:address":"2 Pevensey Close",
    "sg:city":"North Shields",
    "sg:classifiers":[
        {
            "category":"Building & Trades",
            "subcategory":"Construction",
            "type":"Services"
        }
    ],
    "sg:phone":"+44 191 257 2347",
    "sg:postcode":"NE29 9HW",
    "sg:province":"Tyne and Wear",
    "sg:tags":[
        "joiner",
        "carpenter"
    ],
    "wof:name":"Gordon Iles & Son",
    "wof:placetype":"venue"
},
  "geometry": {"coordinates":[-1.4592829943,55.023979187],"type":"Point"}
}