{
  "type": "Feature",
  "properties": {
    "addr:full":"3 Pera Place Bath Bath and North East Somerset BA1 5NX",
    "addr:housenumber":"3",
    "addr:postcode":"ba1 5nx",
    "addr:street":"Pera Place",
    "iso:country":"GB",
    "sg:address":"3 Pera Place",
    "sg:city":"Bath",
    "sg:classifiers":[
        {
            "category":"Building & Trades",
            "subcategory":"Landscaping Services",
            "type":"Services"
        }
    ],
    "sg:phone":"+44 1225 335112",
    "sg:postcode":"BA1 5NX",
    "sg:province":"Bath and North East Somerset",
    "sg:tags":[
        "designer",
        "architect",
        "landscape"
    ],
    "wof:name":"Lavigne Lonsdale",
    "wof:placetype":"venue"
},
  "geometry": {"coordinates":[-2.3588039875,51.3914680481],"type":"Point"}
}