{
  "type": "Feature",
  "properties": {
    "iso:country":"GB",
    "sg:address":"1 Saxon Grn, Escomb",
    "sg:city":"Bishop Auckland",
    "sg:classifiers":[
        {
            "category":"Bars & Pubs",
            "type":"Food & Drink"
        }
    ],
    "sg:phone":"+44 1388 662256",
    "sg:postcode":"DL14 7SY",
    "sg:province":"Durham",
    "sg:tags":[
        "pubs",
        "inn"
    ],
    "wof:name":"Saxon Inn",
    "wof:placetype":"venue"
},
  "geometry": {"coordinates":[-1.708799,54.665581],"type":"Point"}
}