{
  "type": "Feature",
  "properties": {
    "addr:full":"Colchester Road, St Osyth Clacton-on-sea Essex CO16 8HW",
    "addr:postcode":"co16 8hw",
    "addr:street":"Colchester Road",
    "iso:country":"GB",
    "sg:address":"Colchester Road, St Osyth",
    "sg:city":"Clacton-on-sea",
    "sg:classifiers":[
        {
            "category":"Recreation",
            "subcategory":"Campground",
            "type":"Entertainment"
        }
    ],
    "sg:phone":"+44 1255 820432",
    "sg:postcode":"CO16 8HW",
    "sg:province":"Essex",
    "sg:tags":[
        "caravan",
        "park"
    ],
    "wof:name":"Oaklands Caravan Park",
    "wof:placetype":"venue"
},
  "geometry": {"coordinates":[1.0782860518,51.8022727966],"type":"Point"}
}