{
  "type": "Feature",
  "properties": {
    "addr:full":"11b Hatch Road, Pilgrims Hatch Brentwood Essex CM15 9PU",
    "addr:housenumber":"11b",
    "addr:postcode":"cm15 9pu",
    "addr:street":"Hatch Road",
    "iso:country":"GB",
    "sg:address":"11b Hatch Road, Pilgrims Hatch",
    "sg:city":"Brentwood",
    "sg:classifiers":[
        {
            "category":"Manufacturing",
            "subcategory":"Tools & Machinery",
            "type":"Manufacturing & Wholesale Goods"
        }
    ],
    "sg:postcode":"CM15 9PU",
    "sg:province":"Essex",
    "sg:tags":[
        "society",
        "friendly"
    ],
    "wof:name":"Jones Wood Insurance Consultants Limited",
    "wof:placetype":"venue"
},
  "geometry": {"coordinates":[0.28075701,51.6378250122],"type":"Point"}
}