{
  "type": "Feature",
  "properties": {
    "addr:full":"4 Furzedown House, Kings Somborne Stockbridge Hampshire SO20 6QL",
    "addr:housenumber":"4;house kings",
    "addr:postcode":"so20 6ql",
    "iso:country":"GB",
    "sg:address":"4 Furzedown House, Kings Somborne",
    "sg:city":"Stockbridge",
    "sg:classifiers":[
        {
            "category":"Professional",
            "subcategory":"Employment Agencies",
            "type":"Services"
        }
    ],
    "sg:postcode":"SO20 6QL",
    "sg:province":"Hampshire",
    "sg:tags":[
        "consultant"
    ],
    "wof:name":"Good Prospects Select Ltd.",
    "wof:placetype":"venue"
},
  "geometry": {"coordinates":[-1.4853539467,51.0765457153],"type":"Point"}
}