{
  "type": "Feature",
  "properties": {
    "addr:full":"79 Grosvenor Street London Greater London W1K 3JU",
    "addr:housenumber":"79",
    "addr:postcode":"w1k 3ju",
    "addr:street":"Grosvenor Street",
    "iso:country":"GB",
    "sg:address":"79 Grosvenor Street",
    "sg:city":"London",
    "sg:classifiers":[
        {
            "category":"Banks & Credit Unions",
            "subcategory":"Financial Services",
            "type":"Services"
        }
    ],
    "sg:phone":"+44 20 7495 4641",
    "sg:postcode":"W1K 3JU",
    "sg:province":"Greater London",
    "sg:tags":[
        "consultant"
    ],
    "wof:name":"Pyrford International Plc",
    "wof:placetype":"venue"
},
  "geometry": {"coordinates":[-0.1467290074,51.5117988586],"type":"Point"}
}