{
  "type": "Feature",
  "properties": {
    "iso:country":"GB",
    "sg:address":"28-30 College St",
    "sg:city":"Rotherham",
    "sg:classifiers":[
        {
            "category":"Shopping",
            "subcategory":"Gifts & Souvenirs",
            "type":"Retail Goods"
        }
    ],
    "sg:phone":"+44 1709 820970",
    "sg:postcode":"S65 1AG",
    "sg:province":"South Yorkshire",
    "sg:tags":[
        "poster",
        "card"
    ],
    "wof:name":"Sentiments",
    "wof:placetype":"venue"
},
  "geometry": {"coordinates":[-1.3552190065,53.4308242798],"type":"Point"}
}