{
  "type": "Feature",
  "properties": {
    "addr:full":"Brympton Way, Lynx West Trading Estate Yeovil Somerset BA20 2HP",
    "addr:postcode":"ba20 2hp",
    "addr:street":"Brympton Way;Trading",
    "iso:country":"GB",
    "sg:address":"Brympton Way, Lynx West Trading Estate",
    "sg:city":"Yeovil",
    "sg:classifiers":[
        {
            "category":"Home & Garden",
            "subcategory":"Hardware",
            "type":"Retail Goods"
        },
        {
            "category":"Manufacturing",
            "subcategory":"Building Materials",
            "type":"Manufacturing & Wholesale Goods"
        }
    ],
    "sg:phone":"+44 1935 432054",
    "sg:postcode":"BA20 2HP",
    "sg:province":"Somerset",
    "sg:tags":[
        "merchant",
        "builder",
        "retailer",
        "diy"
    ],
    "sg:website":"http://www.wickes.co.uk",
    "wof:name":"Wickes Building Supplies Ltd",
    "wof:placetype":"venue"
},
  "geometry": {"coordinates":[-2.6640639305,50.933971405],"type":"Point"}
}