{
  "type": "Feature",
  "properties": {
    "addr:full":"Ingramgate Thirsk North Yorkshire YO7 1DF",
    "addr:postcode":"yo7 1df",
    "addr:street":"Ingramgate",
    "iso:country":"GB",
    "sg:address":"Ingramgate",
    "sg:city":"Thirsk",
    "sg:classifiers":[
        {
            "category":"Bars & Pubs",
            "type":"Food & Drink"
        }
    ],
    "sg:phone":"+44 1845 522027",
    "sg:postcode":"YO7 1DF",
    "sg:province":"North Yorkshire",
    "sg:tags":[
        "pubs",
        "inn"
    ],
    "wof:name":"Frankland Arms",
    "wof:placetype":"venue"
},
  "geometry": {"coordinates":[-1.337155,54.233162],"type":"Point"}
}