{
  "type": "Feature",
  "properties": {
    "iso:country":"GB",
    "sg:address":"6 High Street",
    "sg:city":"Dunmow",
    "sg:classifiers":[
        {
            "category":"Shopping",
            "subcategory":"News",
            "type":"Retail Goods"
        }
    ],
    "sg:phone":"+44 1371 872878",
    "sg:postcode":"CM6 1AG",
    "sg:province":"Essex",
    "sg:tags":[
        "newsagent"
    ],
    "wof:name":"A Willett & Sons",
    "wof:placetype":"venue"
},
  "geometry": {"coordinates":[0.362404,51.872528],"type":"Point"}
}