{
  "type": "Feature",
  "properties": {
    "addr:full":"108 Stn La, Featherstone Pontefract West Yorkshire WF7 5BA",
    "addr:housenumber":"108;pontefract",
    "addr:postcode":"wf7 5ba",
    "addr:street":"Stn La Featherstone",
    "iso:country":"GB",
    "sg:address":"108 Stn La, Featherstone",
    "sg:city":"Pontefract",
    "sg:classifiers":[
        {
            "category":"Fast Food",
            "type":"Food & Drink"
        }
    ],
    "sg:postcode":"WF7 5BA",
    "sg:province":"West Yorkshire",
    "sg:tags":[
        "away",
        "take"
    ],
    "wof:name":"Ksar,Mohammed,",
    "wof:placetype":"venue"
},
  "geometry": {"coordinates":[-1.3583,53.678322],"type":"Point"}
}