{
  "type": "Feature",
  "properties": {
    "iso:country":"GB",
    "sg:address":"Ellerholme Farm, Wroot Road, Finningley",
    "sg:city":"Doncaster",
    "sg:classifiers":[
        {
            "category":"Farming",
            "subcategory":"Livestock Farm",
            "type":"Manufacturing & Wholesale Goods"
        }
    ],
    "sg:phone":"+44 1302 770598",
    "sg:postcode":"DN9 3EA",
    "sg:province":"Lincolnshire",
    "sg:tags":[
        "others"
    ],
    "wof:name":"T A White & Sons",
    "wof:placetype":"venue"
},
  "geometry": {"coordinates":[-0.989839,53.486202],"type":"Point"}
}