{
  "type": "Feature",
  "properties": {
    "addr:full":"42 Stockton Road Hartlepool Durham TS25 1RW",
    "addr:housenumber":"42",
    "addr:postcode":"ts25 1rw",
    "addr:street":"Stockton Road",
    "iso:country":"GB",
    "sg:address":"42 Stockton Road",
    "sg:city":"Hartlepool",
    "sg:classifiers":[
        {
            "category":"Personal",
            "subcategory":"Beauty Salon",
            "type":"Services"
        }
    ],
    "sg:phone":"+44 1429 869043",
    "sg:postcode":"TS25 1RW",
    "sg:province":"Durham",
    "sg:tags":[
        "unisex",
        "hairdresser"
    ],
    "wof:name":"Cappeli",
    "wof:placetype":"venue"
},
  "geometry": {"coordinates":[-1.2158429623,54.6763496399],"type":"Point"}
}