{
  "type": "Feature",
  "properties": {
    "addr:full":"Franklin Road Stromness Orkney Islands KW16 3AN",
    "addr:postcode":"kw16 3an",
    "addr:street":"Franklin Road",
    "iso:country":"GB",
    "sg:address":"Franklin Road",
    "sg:city":"Stromness",
    "sg:classifiers":[
        {
            "category":"Education",
            "subcategory":"School",
            "type":"Public Place"
        }
    ],
    "sg:phone":"+44 1856 850544",
    "sg:postcode":"KW16 3AN",
    "sg:province":"Orkney Islands",
    "sg:tags":[
        "local",
        "authority"
    ],
    "wof:name":"Stromness Primary School",
    "wof:placetype":"venue"
},
  "geometry": {"coordinates":[-3.299979,58.963467],"type":"Point"}
}