{
  "type": "Feature",
  "properties": {
    "addr:full":"219 High Street Linlithgow Falkirk EH49 7EN",
    "addr:housenumber":"219",
    "addr:postcode":"eh49 7en",
    "addr:street":"High Street",
    "iso:country":"GB",
    "sg:address":"219 High Street",
    "sg:city":"Linlithgow",
    "sg:classifiers":[
        {
            "category":"Professional",
            "subcategory":"Engineering",
            "type":"Services"
        },
        {
            "category":"Building & Trades",
            "subcategory":"Electrical",
            "type":"Services"
        }
    ],
    "sg:phone":"+44 1506 843078",
    "sg:postcode":"EH49 7EN",
    "sg:province":"Falkirk",
    "sg:tags":[
        "engineer",
        "electrician",
        "contractor"
    ],
    "wof:name":"Linlithgow Electrics",
    "wof:placetype":"venue"
},
  "geometry": {"coordinates":[-3.606077,55.97604],"type":"Point"}
}