{
  "type": "Feature",
  "properties": {
    "iso:country":"GB",
    "sg:address":"Unit 7a Old Bridge Wy, Shefford Industrial Estate",
    "sg:city":"Shefford",
    "sg:classifiers":[
        {
            "category":"Autos & Motor Vehicles",
            "subcategory":"Auto Supplies",
            "type":"Retail Goods"
        }
    ],
    "sg:phone":"+44 1462 850731",
    "sg:postcode":"SG17 5HQ",
    "sg:province":"Bedfordshire",
    "sg:tags":[
        "windscreen"
    ],
    "wof:name":"Highway Windscreen & Glass",
    "wof:placetype":"venue"
},
  "geometry": {"coordinates":[-0.335369,52.036621],"type":"Point"}
}