{
  "type": "Feature",
  "properties": {
    "addr:full":"Bressey Osteopathic Clinic, 30 Bressey Gro London Greater London E18 2HU",
    "addr:housenumber":"30",
    "addr:postcode":"e18 2hu",
    "addr:street":"Bressey Gro",
    "iso:country":"GB",
    "sg:address":"Bressey Osteopathic Clinic, 30 Bressey Gro",
    "sg:city":"London",
    "sg:classifiers":[
        {
            "category":"Health Services",
            "subcategory":"Health Practitioner",
            "type":"Services"
        }
    ],
    "sg:phone":"+44 20 8532 9889",
    "sg:postcode":"E18 2HU",
    "sg:province":"Greater London",
    "sg:tags":[
        "osteopath"
    ],
    "wof:name":"Back Into Shape Osteopathic Clinic",
    "wof:placetype":"venue"
},
  "geometry": {"coordinates":[0.01895,51.593121],"type":"Point"}
}