{
  "type": "Feature",
  "properties": {
    "addr:full":"Fleet House, 8-12 New Bridge Street London Greater London EC4V 6AL",
    "addr:housenumber":"8-12",
    "addr:postcode":"ec4v 6al",
    "addr:street":"New Bridge Street",
    "iso:country":"GB",
    "sg:address":"Fleet House, 8-12 New Bridge Street",
    "sg:city":"London",
    "sg:classifiers":[
        {
            "category":"Professional",
            "subcategory":"Accounting & Tax Preparation",
            "type":"Services"
        }
    ],
    "sg:phone":"+44 20 7936 3003",
    "sg:postcode":"EC4V 6AL",
    "sg:province":"Greater London",
    "sg:tags":[
        "consultant"
    ],
    "wof:name":"C W Tax Associates Ltd.",
    "wof:placetype":"venue"
},
  "geometry": {"coordinates":[-0.104339,51.513527],"type":"Point"}
}