{
  "type": "Feature",
  "properties": {
    "addr:full":"7 Terrace Road London Greater London E13 0LP",
    "addr:housenumber":"7",
    "addr:postcode":"e13 0lp",
    "addr:street":"Terrace Road",
    "iso:country":"GB",
    "sg:address":"7 Terrace Road",
    "sg:city":"London",
    "sg:classifiers":[
        {
            "category":"Shopping",
            "subcategory":"News",
            "type":"Retail Goods"
        }
    ],
    "sg:phone":"+44 20 8472 1758",
    "sg:postcode":"E13 0LP",
    "sg:province":"Greater London",
    "sg:tags":[
        "newsagent"
    ],
    "wof:name":"Famous News",
    "wof:placetype":"venue"
},
  "geometry": {"coordinates":[0.02269,51.533081],"type":"Point"}
}