{
  "type": "Feature",
  "properties": {
    "addr:full":"29 Thoroughfare Woodbridge Suffolk IP12 1AA",
    "addr:housenumber":"29",
    "addr:postcode":"ip12 1aa",
    "addr:street":"Thoroughfare",
    "iso:country":"GB",
    "sg:address":"29 Thoroughfare",
    "sg:city":"Woodbridge",
    "sg:classifiers":[
        {
            "category":"Shopping",
            "subcategory":"Shoes",
            "type":"Retail Goods"
        }
    ],
    "sg:phone":"+44 1394 386393",
    "sg:postcode":"IP12 1AA",
    "sg:province":"Suffolk",
    "sg:tags":[
        "shop"
    ],
    "wof:name":"John Ives",
    "wof:placetype":"venue"
},
  "geometry": {"coordinates":[1.32182,52.095638],"type":"Point"}
}