{
  "type": "Feature",
  "properties": {
    "iso:country":"GB",
    "sg:address":"Sinclair Court, Bletchley",
    "sg:city":"Milton Keynes",
    "sg:classifiers":[
        {
            "category":"Manufacturing",
            "subcategory":"Metals",
            "type":"Manufacturing & Wholesale Goods"
        }
    ],
    "sg:phone":"+44 1908 371575",
    "sg:postcode":"MK1 1RB",
    "sg:province":"Buckinghamshire",
    "sg:tags":[
        "work",
        "sheet"
    ],
    "wof:name":"Mantar Sheetmetal Works",
    "wof:placetype":"venue"
},
  "geometry": {"coordinates":[-0.74089,52.008209],"type":"Point"}
}