{
  "type": "Feature",
  "properties": {
    "addr:full":"127-129 The Causeway, Kneesworth Royston Bedfordshire SG8 5JB",
    "addr:housenumber":"127-129",
    "addr:postcode":"sg8 5jb",
    "addr:street":"The Causeway Kneesworth",
    "iso:country":"GB",
    "sg:address":"127-129 The Causeway, Kneesworth",
    "sg:city":"Royston",
    "sg:classifiers":[
        {
            "category":"Manufacturing",
            "subcategory":"Rubber & Plastics",
            "type":"Manufacturing & Wholesale Goods"
        }
    ],
    "sg:phone":"+44 1843 854000",
    "sg:postcode":"SG8 5JB",
    "sg:province":"Bedfordshire",
    "sg:tags":[
        "injection",
        "moulding"
    ],
    "wof:name":"A S P Plastics Ltd.",
    "wof:placetype":"venue"
},
  "geometry": {"coordinates":[-0.0437350012,52.0809631348],"type":"Point"}
}