{
  "type": "Feature",
  "properties": {
    "iso:country":"GB",
    "sg:address":"80 Pinfold Lane",
    "sg:city":"Wolverhampton",
    "sg:classifiers":[
        {
            "category":"Building & Trades",
            "subcategory":"Construction",
            "type":"Services"
        }
    ],
    "sg:postcode":"WV4 4EP",
    "sg:province":"Staffordshire",
    "sg:tags":[
        "welder"
    ],
    "wof:name":"Penn Mobile Auto Repairs",
    "wof:placetype":"venue"
},
  "geometry": {"coordinates":[-2.160881,52.563866],"type":"Point"}
}