{
  "type": "Feature",
  "properties": {
    "addr:full":"Park Hall Farm, Park Lane, High Offley Stafford Staffordshire ST20 0NB",
    "addr:postcode":"st20 0nb",
    "addr:street":"Park Lane",
    "iso:country":"GB",
    "sg:address":"Park Hall Farm, Park Lane, High Offley",
    "sg:city":"Stafford",
    "sg:classifiers":[
        {
            "category":"Farming",
            "subcategory":"Dairy Farm",
            "type":"Manufacturing & Wholesale Goods"
        }
    ],
    "sg:postcode":"ST20 0NB",
    "sg:province":"Staffordshire",
    "wof:name":"R B Jones & Partners",
    "wof:placetype":"venue"
},
  "geometry": {"coordinates":[-2.324266,52.833103],"type":"Point"}
}