{
  "type": "Feature",
  "properties": {
    "addr:full":"2 Elizabeth Avenue, Kirn Dunoon Argyll and Bute PA23 8NW",
    "addr:housenumber":"2",
    "addr:postcode":"pa23 8nw",
    "addr:street":"Elizabeth Avenue",
    "iso:country":"GB",
    "sg:address":"2 Elizabeth Avenue, Kirn",
    "sg:city":"Dunoon",
    "sg:classifiers":[
        {
            "category":"Shopping",
            "subcategory":"Department Store",
            "type":"Retail Goods"
        },
        {
            "category":"Food & Beverages",
            "subcategory":"Groceries & Convenience Stores",
            "type":"Retail Goods"
        }
    ],
    "sg:phone":"+44 1369 704457",
    "sg:postcode":"PA23 8NW",
    "sg:province":"Argyll and Bute",
    "wof:name":"Ardenslate Stores",
    "wof:placetype":"venue"
},
  "geometry": {"coordinates":[-4.9243841171,55.9616546631],"type":"Point"}
}