{
  "type": "Feature",
  "properties": {
    "addr:full":"Po Box 1, Bycards Road, Burslem Stoke-on-trent Staffordshire ST6 4SH",
    "addr:housenumber":"po;1",
    "addr:postcode":"staffordshire st6 4sh",
    "addr:street":"Box;Bycards Road",
    "iso:country":"GB",
    "sg:address":"Po Box 1, Bycards Road, Burslem",
    "sg:city":"Stoke-on-trent",
    "sg:classifiers":[
        {
            "category":"Building & Trades",
            "subcategory":"Plumbing",
            "type":"Services"
        }
    ],
    "sg:phone":"+44 1782 838591",
    "sg:postcode":"ST6 4SH",
    "sg:province":"Staffordshire",
    "sg:tags":[
        "filtration",
        "system"
    ],
    "wof:name":"Heath Filtration Ltd.",
    "wof:placetype":"venue"
},
  "geometry": {"coordinates":[-2.200040102,53.0453109741],"type":"Point"}
}