{"geometry":{"type":"Point","coordinates":[0.371182,51.427078]},"type":"Feature","id":102560041,"bbox":[0.371182,51.427078,0.371182,51.427078],"properties":{"sg:province":"Kent","sg:tags":["plumber","heating"],"geom:longitude":0.371182,"wof:breaches":[],"sg:href":"http://api.simplegeo.com/1.0/features/SG_4QM6LY1bN7Dm9ikBROFfpG_51.427078_0.371182@1300740015.json","sg:owner":"simplegeo","sg:postcode":"DA12 5AD","geom:latitude":51.427078,"sg:classifiers":[{"category":"Building & Trades","type":"Services","subcategory":"Plumbing"}],"sg:address":"76 Central Avenue","sg:phone":"+44 1474 326333","wof:hierarchy":[{"locality_id":101914069,"venue_id":102560041,"country_id":85633159,"neighbourhood_id":85860075,"region_id":85684363}],"geom:area":0.000000,"sg:city":"Gravesend","wof:lastmodified":1438093172,"iso:country":"GB","wof:geomhash":"c6df3163164c200fc95166e9918af90d","wof:name":"Peter L Diggory","wof:belongsto":[101914069,85633159,85860075,85684363],"src:geom":"simplegeo","wof:placetype":"venue","wof:supersedes":[],"wof:id":102560041,"wof:superseded_by":[],"wof:concordances":{"sg:id":"SG_4QM6LY1bN7Dm9ikBROFfpG_51.427078_0.371182@1300740015"},"wof:parent_id":85860075}}