{
  "type": "Feature",
  "properties": {
    "addr:full":"76 Central Avenue Gravesend Kent DA12 5AD",
    "addr:housenumber":"76",
    "addr:postcode":"da12 5ad",
    "addr:street":"Central Avenue",
    "iso:country":"GB",
    "sg:address":"76 Central Avenue",
    "sg:city":"Gravesend",
    "sg:classifiers":[
        {
            "category":"Building & Trades",
            "subcategory":"Plumbing",
            "type":"Services"
        }
    ],
    "sg:href":"http://api.simplegeo.com/1.0/features/SG_4QM6LY1bN7Dm9ikBROFfpG_51.427078_0.371182@1300740015.json",
    "sg:phone":"+44 1474 326333",
    "sg:postcode":"DA12 5AD",
    "sg:province":"Kent",
    "sg:tags":[
        "plumber",
        "heating"
    ],
    "wof:name":"Peter L Diggory",
    "wof:placetype":"venue"
},
  "geometry": {"coordinates":[0.371182,51.427078],"type":"Point"}
}