{
  "type": "Feature",
  "properties": {
    "iso:country":"GB",
    "sg:address":"1b Market Av",
    "sg:city":"Ashton Under Lyne",
    "sg:classifiers":[
        {
            "category":"Real Estate",
            "subcategory":"Architect",
            "type":"Services"
        }
    ],
    "sg:phone":"+44 161 343 2476",
    "sg:postcode":"OL6 6AR",
    "sg:province":"Greater Manchester",
    "wof:name":"Bruce & Bruce",
    "wof:placetype":"venue"
},
  "geometry": {"coordinates":[-2.0922689438,53.4890556335],"type":"Point"}
}