{
  "type": "Feature",
  "properties": {
    "addr:full":"Jack Green Farm, Oram Road, Brindle Chorley Lancashire PR6 8NT",
    "addr:postcode":"pr6 8nt",
    "addr:street":"Jack;Oram Road",
    "iso:country":"GB",
    "sg:address":"Jack Green Farm, Oram Road, Brindle",
    "sg:city":"Chorley",
    "sg:classifiers":[
        {
            "category":"Farming",
            "subcategory":"Livestock Farm",
            "type":"Manufacturing & Wholesale Goods"
        }
    ],
    "sg:phone":"+44 1254 852390",
    "sg:postcode":"PR6 8NT",
    "sg:province":"Lancashire",
    "sg:tags":[
        "others"
    ],
    "wof:name":"R Smalley",
    "wof:placetype":"venue"
},
  "geometry": {"coordinates":[-2.608232,53.713997],"type":"Point"}
}