{
  "type": "Feature",
  "properties": {
    "addr:full":"27 Shirecroft Rd Weymouth Dorset DT4 0NH",
    "addr:housenumber":"27",
    "addr:postcode":"dt4 0nh",
    "addr:street":"Shirecroft Rd",
    "iso:country":"GB",
    "sg:address":"27 Shirecroft Rd",
    "sg:city":"Weymouth",
    "sg:classifiers":[
        {
            "category":"Building & Trades",
            "subcategory":"Plumbing",
            "type":"Services"
        }
    ],
    "sg:postcode":"DT4 0NH",
    "sg:province":"Dorset",
    "sg:tags":[
        "heating"
    ],
    "wof:name":"Noye,Philip John,",
    "wof:placetype":"venue"
},
  "geometry": {"coordinates":[-2.475442,50.611225],"type":"Point"}
}