{
  "type": "Feature",
  "properties": {
    "iso:country":"GB",
    "sg:address":"Unit 17 Mount St Business Park, Nechells",
    "sg:city":"Birmingham",
    "sg:classifiers":[
        {
            "category":"Building & Trades",
            "subcategory":"Landscaping Services",
            "type":"Services"
        }
    ],
    "sg:phone":"+44 121 328 0300",
    "sg:postcode":"B7 5QU",
    "sg:province":"West Midlands",
    "sg:tags":[
        "contractor",
        "drainage"
    ],
    "wof:name":"Jetterways",
    "wof:placetype":"venue"
},
  "geometry": {"coordinates":[-1.861039,52.502571],"type":"Point"}
}