{
  "type": "Feature",
  "properties": {
    "addr:full":"20 Grasmere Close, Black Notley Braintree Essex CM77 7UF",
    "addr:housenumber":"20",
    "addr:postcode":"cm77 7uf",
    "addr:street":"Grasmere Close",
    "iso:country":"GB",
    "sg:address":"20 Grasmere Close, Black Notley",
    "sg:city":"Braintree",
    "sg:classifiers":[
        {
            "category":"Professional",
            "subcategory":"Art Services",
            "type":"Services"
        }
    ],
    "sg:phone":"+44 1376 330334",
    "sg:postcode":"CM77 7UF",
    "sg:province":"Essex",
    "sg:tags":[
        "graphic",
        "designer"
    ],
    "wof:name":"Bruce Long Design",
    "wof:placetype":"venue"
},
  "geometry": {"coordinates":[0.5305209756,51.858089447],"type":"Point"}
}