{
  "type": "Feature",
  "properties": {
    "addr:full":"136 Pall Mall Chorley Lancashire PR7 2LD",
    "addr:housenumber":"136",
    "addr:postcode":"pr7 2ld",
    "addr:street":"Pall Mall",
    "iso:country":"GB",
    "sg:address":"136 Pall Mall",
    "sg:city":"Chorley",
    "sg:classifiers":[
        {
            "category":"Home & Garden",
            "subcategory":"Furniture",
            "type":"Retail Goods"
        }
    ],
    "sg:postcode":"PR7 2LD",
    "sg:province":"Lancashire",
    "wof:name":"Sleepy Hollow Bed Centre",
    "wof:placetype":"venue"
},
  "geometry": {"coordinates":[-2.634866,53.646671],"type":"Point"}
}