{
  "type": "Feature",
  "properties": {
    "iso:country":"GB",
    "sg:address":"9 Sussex Place",
    "sg:city":"Slough",
    "sg:classifiers":[
        {
            "category":"Health Services",
            "subcategory":"Podiatrist",
            "type":"Services"
        }
    ],
    "sg:phone":"+44 1753 522077",
    "sg:postcode":"SL1 1NH",
    "sg:province":"Berkshire",
    "sg:tags":[
        "podiatrists",
        "chiropodist"
    ],
    "wof:name":"Philip R Jones",
    "wof:placetype":"venue"
},
  "geometry": {"coordinates":[-0.582694,51.506931],"type":"Point"}
}