{
  "type": "Feature",
  "properties": {
    "addr:full":"12 Monkton Road, Minster Ramsgate Kent CT12 4EA",
    "addr:housenumber":"12",
    "addr:postcode":"ct12 4ea",
    "addr:street":"Monkton Road;Ramsgate",
    "iso:country":"GB",
    "sg:address":"12 Monkton Road, Minster",
    "sg:city":"Ramsgate",
    "sg:classifiers":[
        {
            "category":"Fast Food",
            "type":"Food & Drink"
        }
    ],
    "sg:phone":"+44 1843 821209",
    "sg:postcode":"CT12 4EA",
    "sg:province":"Kent",
    "sg:tags":[
        "away",
        "meal",
        "outlet",
        "take"
    ],
    "wof:name":"Furamar Chinese Take Away",
    "wof:placetype":"venue"
},
  "geometry": {"coordinates":[1.313661,51.334526],"type":"Point"}
}