{
  "type": "Feature",
  "properties": {
    "addr:full":"Middleaze Drive, Lydiard Tregoze Swindon Wiltshire SN5 5PB",
    "addr:housenumber":"tregoze",
    "addr:postcode":"sn5 5pb",
    "addr:street":"Middleaze Drive Lydiard",
    "iso:country":"GB",
    "sg:address":"Middleaze Drive, Lydiard Tregoze",
    "sg:city":"Swindon",
    "sg:classifiers":[
        {
            "category":"Bars & Pubs",
            "type":"Food & Drink"
        }
    ],
    "sg:phone":"+44 1793 874223",
    "sg:postcode":"SN5 5PB",
    "sg:province":"Wiltshire",
    "sg:tags":[
        "pubs",
        "inn"
    ],
    "wof:name":"Brookhouse Farm",
    "wof:placetype":"venue"
},
  "geometry": {"coordinates":[-1.849641,51.566994],"type":"Point"}
}