{
  "type": "Feature",
  "properties": {
    "addr:full":"24a Deerbarn Road Guildford Surrey GU2 8AT",
    "addr:housenumber":"24a",
    "addr:postcode":"gu2 8at",
    "addr:street":"Deerbarn Road",
    "iso:country":"GB",
    "sg:address":"24a Deerbarn Road",
    "sg:city":"Guildford",
    "sg:classifiers":[
        {
            "category":"Autos & Motor Vehicles",
            "subcategory":"Auto Supplies",
            "type":"Retail Goods"
        }
    ],
    "sg:postcode":"GU2 8AT",
    "sg:province":"Surrey",
    "sg:tags":[
        "towing",
        "eqpt",
        "trailer"
    ],
    "wof:name":"The Trailer Centre",
    "wof:placetype":"venue"
},
  "geometry": {"coordinates":[-0.5889490247,51.2483673096],"type":"Point"}
}