{
  "type": "Feature",
  "properties": {
    "addr:full":"Brentfield Way Penrith Cumbria CA11 8DL",
    "addr:postcode":"ca11 8dl",
    "addr:street":"Brentfield Way",
    "iso:country":"GB",
    "sg:address":"Brentfield Way",
    "sg:city":"Penrith",
    "sg:classifiers":[
        {
            "category":"Community Center",
            "subcategory":"Youth",
            "type":"Public Place"
        }
    ],
    "sg:phone":"+44 1768 868056",
    "sg:postcode":"CA11 8DL",
    "sg:province":"Cumbria",
    "sg:tags":[
        "organisation",
        "centre"
    ],
    "wof:name":"Guide Association The",
    "wof:placetype":"venue"
},
  "geometry": {"coordinates":[-2.7406439781,54.6666564941],"type":"Point"}
}