{
  "type": "Feature",
  "properties": {
    "addr:full":"38 Green Hill Gate High Wycombe Buckinghamshire HP13 5QG",
    "addr:housenumber":"38",
    "addr:postcode":"hp13 5qg",
    "addr:street":"Green Hill Gate",
    "iso:country":"GB",
    "sg:address":"38 Green Hill Gate",
    "sg:city":"High Wycombe",
    "sg:classifiers":[
        {
            "category":"Personal",
            "type":"Services"
        }
    ],
    "sg:phone":"+44 1494 462163",
    "sg:postcode":"HP13 5QG",
    "sg:province":"Buckinghamshire",
    "sg:tags":[
        "wedding"
    ],
    "wof:name":"Aura Television Productions",
    "wof:placetype":"venue"
},
  "geometry": {"coordinates":[-0.745071,51.64119],"type":"Point"}
}