{
  "type": "Feature",
  "properties": {
    "addr:full":"21 Burnley Road, Mytholmroyd Hebden Bridge West Yorkshire HX7 5LN",
    "addr:housenumber":"21",
    "addr:postcode":"hx7 5ln",
    "addr:street":"Burnley Road;West",
    "iso:country":"GB",
    "sg:address":"21 Burnley Road, Mytholmroyd",
    "sg:city":"Hebden Bridge",
    "sg:classifiers":[
        {
            "category":"Organizations",
            "subcategory":"Non-profit Organization",
            "type":"Services"
        }
    ],
    "sg:phone":"+44 1422 885098",
    "sg:postcode":"HX7 5LN",
    "sg:province":"West Yorkshire",
    "sg:tags":[
        "charitable",
        "organisation",
        "voluntary",
        "charity"
    ],
    "wof:name":"Calder Valley Club",
    "wof:placetype":"venue"
},
  "geometry": {"coordinates":[-1.979605,53.730515],"type":"Point"}
}