{
  "type": "Feature",
  "properties": {
    "iso:country":"GB",
    "sg:address":"Corfe",
    "sg:city":"Taunton",
    "sg:classifiers":[
        {
            "category":"Sports & Exercise",
            "subcategory":"Golf",
            "type":"Entertainment"
        }
    ],
    "sg:phone":"+44 1823 421537",
    "sg:postcode":"TA3 7BY",
    "sg:province":"Devon",
    "sg:tags":[
        "club",
        "course"
    ],
    "wof:name":"Taunton & Pickeridge Golf Club",
    "wof:placetype":"venue"
},
  "geometry": {"coordinates":[-3.07996,50.9608],"type":"Point"}
}