{
  "type": "Feature",
  "properties": {
    "iso:country":"GB",
    "sg:address":"65 New Road",
    "sg:city":"London",
    "sg:classifiers":[
        {
            "category":"Professional",
            "subcategory":"Business Services",
            "type":"Services"
        }
    ],
    "sg:postcode":"E1 1HH",
    "sg:province":"Greater London",
    "sg:tags":[
        "accomodation"
    ],
    "wof:name":"Skylink (Gb) Ltd",
    "wof:placetype":"venue"
},
  "geometry": {"coordinates":[-0.062524,51.516533],"type":"Point"}
}