{
  "type": "Feature",
  "properties": {
    "addr:full":"24 St Mary Axe London Greater London EC3A 8DE",
    "addr:housenumber":"24",
    "addr:postcode":"ec3a 8de",
    "addr:street":"St Mary Axe",
    "iso:country":"GB",
    "sg:address":"24 St Mary Axe",
    "sg:city":"London",
    "sg:classifiers":[
        {
            "category":"Transit Center",
            "subcategory":"Passenger",
            "type":"Transportation"
        }
    ],
    "sg:postcode":"EC3A 8DE",
    "sg:province":"Greater London",
    "sg:tags":[
        "ship",
        "broker"
    ],
    "wof:name":"Frank-Symons Ltd.",
    "wof:placetype":"venue"
},
  "geometry": {"coordinates":[-0.0806000009,51.5146903992],"type":"Point"}
}