{
  "type": "Feature",
  "properties": {
    "addr:full":"Fairfield School Hereford Herefordshire HR2 0SG",
    "addr:postcode":"hr2 0sg",
    "iso:country":"GB",
    "sg:address":"Fairfield School",
    "sg:city":"Hereford",
    "sg:classifiers":[
        {
            "category":"Health Services",
            "subcategory":"Clinic",
            "type":"Services"
        }
    ],
    "sg:phone":"+44 1981 550489",
    "sg:postcode":"HR2 0SG",
    "sg:province":"Herefordshire",
    "sg:tags":[
        "nh"
    ],
    "wof:name":"Deirdrie Perkins",
    "wof:placetype":"venue"
},
  "geometry": {"coordinates":[-2.9557199478,52.0375404358],"type":"Point"}
}