{
  "type": "Feature",
  "properties": {
    "addr:full":"282 Chingford Rd Walthamstow Greater London E17 5AL",
    "addr:housenumber":"282",
    "addr:postcode":"e17 5al",
    "addr:street":"Chingford Rd",
    "iso:country":"GB",
    "sg:address":"282 Chingford Rd",
    "sg:city":"Walthamstow",
    "sg:classifiers":[
        {
            "category":"Coffee & Tea",
            "type":"Food & Drink"
        }
    ],
    "sg:phone":"+44 20 8923 6094",
    "sg:postcode":"E17 5AL",
    "sg:province":"Greater London",
    "wof:name":"Capricorn Trading Co",
    "wof:placetype":"venue"
},
  "geometry": {"coordinates":[-0.015853,51.59977],"type":"Point"}
}