{
  "type": "Feature",
  "properties": {
    "addr:full":"Sticker Lane Laisterdyke Bradford West Yorkshire BD4 8AR",
    "addr:postcode":"bd4 8ar",
    "addr:street":"Sticker Lane Laisterdyke Bradford West",
    "iso:country":"GB",
    "sg:address":"Sticker Lane Laisterdyke",
    "sg:city":"Bradford",
    "sg:classifiers":[
        {
            "category":"Manufacturing",
            "subcategory":"Petroleum Products",
            "type":"Manufacturing & Wholesale Goods"
        }
    ],
    "sg:phone":"+44 1274 661636",
    "sg:postcode":"BD4 8AR",
    "sg:province":"West Yorkshire",
    "sg:tags":[
        "double",
        "glazing"
    ],
    "wof:name":"Cash & Carry Windows",
    "wof:placetype":"venue"
},
  "geometry": {"coordinates":[-1.721622,53.780521],"type":"Point"}
}