{
  "type": "Feature",
  "properties": {
    "addr:full":"Gaymers Way North Walsham Norfolk NR28 0AN",
    "addr:postcode":"nr28 0an",
    "addr:street":"Gaymers Way",
    "iso:country":"GB",
    "sg:address":"Gaymers Way",
    "sg:city":"North Walsham",
    "sg:classifiers":[
        {
            "category":"Retail",
            "subcategory":"Auto Repair",
            "type":"Services"
        }
    ],
    "sg:phone":"+44 1692 407366",
    "sg:postcode":"NR28 0AN",
    "sg:province":"Norfolk",
    "sg:tags":[
        "modification",
        "garage"
    ],
    "wof:name":"North Norfolk VW Centre",
    "wof:placetype":"venue"
},
  "geometry": {"coordinates":[1.3812049627,52.8275794983],"type":"Point"}
}