{
  "type": "Feature",
  "properties": {
    "addr:full":"3 Coronation Terr Lochgilphead Argyll and Bute PA31 8NS",
    "addr:housenumber":"3",
    "addr:postcode":"pa31 8ns",
    "addr:street":"Coronation Terr Lochgilphead",
    "iso:country":"GB",
    "sg:address":"3 Coronation Terr",
    "sg:city":"Lochgilphead",
    "sg:classifiers":[
        {
            "category":"Building & Trades",
            "subcategory":"Construction",
            "type":"Services"
        }
    ],
    "sg:phone":"+44 1546 602108",
    "sg:postcode":"PA31 8NS",
    "sg:province":"Argyll and Bute",
    "sg:tags":[
        "builder"
    ],
    "wof:name":"D MacMillan",
    "wof:placetype":"venue"
},
  "geometry": {"coordinates":[-5.485646,56.061081],"type":"Point"}
}