{
  "type": "Feature",
  "properties": {
    "addr:full":"125a Manor Court Road Nuneaton Leicestershire CV11 5HG",
    "addr:housenumber":"125a",
    "addr:postcode":"cv11 5hg",
    "addr:street":"Manor Court Road",
    "iso:country":"GB",
    "sg:address":"125a Manor Court Road",
    "sg:city":"Nuneaton",
    "sg:classifiers":[
        {
            "category":"Retail",
            "subcategory":"Driving School",
            "type":"Services"
        }
    ],
    "sg:phone":"+44 24 7637 3636",
    "sg:postcode":"CV11 5HG",
    "sg:province":"Leicestershire",
    "wof:name":"Logical School of Motoring",
    "wof:placetype":"venue"
},
  "geometry": {"coordinates":[-1.4812200069,52.5237503052],"type":"Point"}
}