{
  "type": "Feature",
  "properties": {
    "iso:country":"GB",
    "sg:address":"9 Longport",
    "sg:city":"Canterbury",
    "sg:classifiers":[
        {
            "category":"Restaurant",
            "type":"Food & Drink"
        }
    ],
    "sg:phone":"+44 1227 463326",
    "sg:postcode":"CT1 1PE",
    "sg:province":"Kent",
    "wof:name":"The Tasty Spice",
    "wof:placetype":"venue"
},
  "geometry": {"coordinates":[1.086794,51.277363],"type":"Point"}
}