{
  "type": "Feature",
  "properties": {
    "addr:full":"55 Hamilton Road Motherwell North Lanarkshire ML1 3DG",
    "addr:housenumber":"55",
    "addr:postcode":"ml1 3dg",
    "addr:street":"Hamilton Road",
    "iso:country":"GB",
    "sg:address":"55 Hamilton Road",
    "sg:city":"Motherwell",
    "sg:classifiers":[
        {
            "category":"Professional",
            "subcategory":"Lawyer & Legal Services",
            "type":"Services"
        }
    ],
    "sg:phone":"+44 1698 263152",
    "sg:postcode":"ML1 3DG",
    "sg:province":"North Lanarkshire",
    "sg:tags":[
        "solicitor"
    ],
    "wof:name":"GIVENS GIVENS & CO",
    "wof:placetype":"venue"
},
  "geometry": {"coordinates":[-3.995594,55.789127],"type":"Point"}
}