{
  "type": "Feature",
  "properties": {
    "iso:country":"GB",
    "sg:address":"24 Darlaston Central Trading Estate, Salisbury Street",
    "sg:city":"Wednesbury",
    "sg:classifiers":[
        {
            "category":"Manufacturing",
            "subcategory":"Metals",
            "type":"Manufacturing & Wholesale Goods"
        }
    ],
    "sg:phone":"+44 121 526 5757",
    "sg:postcode":"WS10 8XB",
    "sg:province":"West Midlands",
    "sg:tags":[
        "steel",
        "stockholder"
    ],
    "wof:name":"Process Steels Ltd.",
    "wof:placetype":"venue"
},
  "geometry": {"coordinates":[-2.019254,52.552731],"type":"Point"}
}