{
  "type": "Feature",
  "properties": {
    "addr:full":"78 Brent Street London Greater London NW4 2ES",
    "addr:housenumber":"78",
    "addr:postcode":"nw4 2es",
    "addr:street":"Brent Street",
    "iso:country":"GB",
    "sg:address":"78 Brent Street",
    "sg:city":"London",
    "sg:classifiers":[
        {
            "category":"Wholesale",
            "subcategory":"Construction Materials",
            "type":"Manufacturing & Wholesale Goods"
        }
    ],
    "sg:postcode":"NW4 2ES",
    "sg:province":"Greater London",
    "sg:tags":[
        "merchant",
        "glass"
    ],
    "wof:name":"Hendon Glazing Co. Ltd.",
    "wof:placetype":"venue"
},
  "geometry": {"coordinates":[-0.21888,51.584724],"type":"Point"}
}