{
  "type": "Feature",
  "properties": {
    "addr:full":"37-42 Compton St Clerkenwell Greater London EC1V 0AP",
    "addr:housenumber":"37-42",
    "addr:postcode":"ec1v 0ap",
    "addr:street":"Compton St",
    "iso:country":"GB",
    "sg:address":"37-42 Compton St",
    "sg:city":"Clerkenwell",
    "sg:classifiers":[
        {
            "category":"Arts & Performance",
            "subcategory":"Arts Center",
            "type":"Entertainment"
        }
    ],
    "sg:phone":"+44 20 7251 8886",
    "sg:postcode":"EC1V 0AP",
    "sg:province":"Greater London",
    "sg:tags":[
        "centre"
    ],
    "wof:name":"Visage",
    "wof:placetype":"venue"
},
  "geometry": {"coordinates":[-0.102718,51.524769],"type":"Point"}
}