{
  "type": "Feature",
  "properties": {
    "addr:full":"Topaz House, 465 Hornsey Road London Greater London N19 4DR",
    "addr:housenumber":"465",
    "addr:postcode":"n19 4dr",
    "addr:street":"Hornsey Road",
    "iso:country":"GB",
    "sg:address":"Topaz House, 465 Hornsey Road",
    "sg:city":"London",
    "sg:classifiers":[
        {
            "category":"Home & Garden",
            "subcategory":"Carpets & Floor Coverings",
            "type":"Retail Goods"
        }
    ],
    "sg:phone":"+44 20 7609 1000",
    "sg:postcode":"N19 4DR",
    "sg:province":"Greater London",
    "sg:tags":[
        "trimming",
        "trimmer"
    ],
    "wof:name":"Topaz Trims (U K) Ltd.",
    "wof:placetype":"venue"
},
  "geometry": {"coordinates":[-0.122795,51.567646],"type":"Point"}
}