{
  "type": "Feature",
  "properties": {
    "addr:full":"35 Gibraltar Road Halifax West Yorkshire HX1 4HE",
    "addr:housenumber":"35",
    "addr:postcode":"hx1 4he",
    "addr:street":"Gibraltar Road",
    "iso:country":"GB",
    "sg:address":"35 Gibraltar Road",
    "sg:city":"Halifax",
    "sg:classifiers":[
        {
            "category":"Health Services",
            "subcategory":"Nursing And Care Facility",
            "type":"Services"
        }
    ],
    "sg:phone":"+44 1422 352418",
    "sg:postcode":"HX1 4HE",
    "sg:province":"West Yorkshire",
    "sg:tags":[
        "home"
    ],
    "wof:name":"Calderdale Mencap",
    "wof:placetype":"venue"
},
  "geometry": {"coordinates":[-1.889498,53.720219],"type":"Point"}
}