{
  "type": "Feature",
  "properties": {
    "addr:full":"Glanrhyd Brecon Powys LD3 9NU",
    "addr:postcode":"ld3 9nu",
    "iso:country":"GB",
    "sg:address":"Glanrhyd",
    "sg:city":"Brecon",
    "sg:classifiers":[
        {
            "category":"Professional",
            "subcategory":"Computer Services",
            "type":"Services"
        }
    ],
    "sg:phone":"+44 1874 624067",
    "sg:postcode":"LD3 9NU",
    "sg:province":"Powys",
    "sg:tags":[
        "aided",
        "design"
    ],
    "wof:name":"Time Tools",
    "wof:placetype":"venue"
},
  "geometry": {"coordinates":[-3.42396,51.984848],"type":"Point"}
}