{
  "type": "Feature",
  "properties": {
    "iso:country":"GB",
    "sg:address":"Odd Fellows Hall, 28 Belmont Close",
    "sg:city":"London",
    "sg:classifiers":[
        {
            "category":"Manufacturing",
            "subcategory":"Tools & Machinery",
            "type":"Manufacturing & Wholesale Goods"
        }
    ],
    "sg:phone":"+44 20 7622 1928",
    "sg:postcode":"SW4 6AN",
    "sg:province":"Greater London",
    "sg:tags":[
        "society",
        "friendly"
    ],
    "wof:name":"Manchester Unity Pride Clapham Lodge",
    "wof:placetype":"venue"
},
  "geometry": {"coordinates":[-0.13135,51.468719],"type":"Point"}
}