{
  "type": "Feature",
  "properties": {
    "addr:full":"53 Main St Callander Stirling FK17 8DX",
    "addr:housenumber":"53",
    "addr:postcode":"fk17 8dx",
    "addr:street":"Main St",
    "iso:country":"GB",
    "sg:address":"53 Main St",
    "sg:city":"Callander",
    "sg:classifiers":[
        {
            "category":"Taxi",
            "type":"Transportation"
        }
    ],
    "sg:phone":"+44 1877 330496",
    "sg:postcode":"FK17 8DX",
    "sg:province":"Stirling",
    "sg:tags":[
        "mini",
        "cab"
    ],
    "wof:name":"J Morgan Taxis",
    "wof:placetype":"venue"
},
  "geometry": {"coordinates":[-4.2153339386,56.2440567017],"type":"Point"}
}