{
  "type": "Feature",
  "properties": {
    "addr:full":"Unit 8b London Greater London SW6 4HH",
    "addr:housenumber":"unit 8b",
    "addr:postcode":"sw6 4hh",
    "iso:country":"GB",
    "sg:address":"Unit 8b",
    "sg:city":"London",
    "sg:classifiers":[
        {
            "category":"Shopping",
            "subcategory":"Party Supplies",
            "type":"Retail Goods"
        }
    ],
    "sg:postcode":"SW6 4HH",
    "sg:province":"Greater London",
    "sg:tags":[
        "marquees",
        "floor",
        "tent"
    ],
    "wof:name":"Minimarkee",
    "wof:placetype":"venue"
},
  "geometry": {"coordinates":[-0.2006600052,51.4758110046],"type":"Point"}
}