{
  "type": "Feature",
  "properties": {
    "addr:full":"Whitegate, Hatfield Heath Bishops Stortford Essex CM22 7ED",
    "addr:postcode":"cm22 7ed",
    "addr:street":"Whitegate Hatfield Heath",
    "iso:country":"GB",
    "sg:address":"Whitegate, Hatfield Heath",
    "sg:city":"Bishops Stortford",
    "sg:classifiers":[
        {
            "category":"Organizations",
            "subcategory":"Professional Association",
            "type":"Services"
        }
    ],
    "sg:phone":"+44 1279 730709",
    "sg:postcode":"CM22 7ED",
    "sg:province":"Essex",
    "sg:tags":[
        "tech",
        "system",
        "automation"
    ],
    "wof:name":"Cannon Electronics & Automation Ltd.",
    "wof:placetype":"venue"
},
  "geometry": {"coordinates":[0.209800005,51.8126945496],"type":"Point"}
}