{
  "type": "Feature",
  "properties": {
    "addr:full":"39 Bloomsbury Street Wolverhampton West Midlands WV2 4BS",
    "addr:housenumber":"39",
    "addr:postcode":"wv2 4bs",
    "addr:street":"Bloomsbury Street",
    "iso:country":"GB",
    "sg:address":"39 Bloomsbury Street",
    "sg:city":"Wolverhampton",
    "sg:classifiers":[
        {
            "category":"Shopping",
            "subcategory":"Clothing, Apparel, & Fashions",
            "type":"Retail Goods"
        }
    ],
    "sg:postcode":"WV2 4BS",
    "sg:province":"West Midlands",
    "sg:tags":[
        "clothing",
        "fabric"
    ],
    "wof:name":"Gill Fashions",
    "wof:placetype":"venue"
},
  "geometry": {"coordinates":[-2.131247,52.579655],"type":"Point"}
}