{
  "type": "Feature",
  "properties": {
    "addr:full":"Mannaberg Way, Bessemer Way Junction Scunthorpe Lincolnshire DN15 8XF",
    "addr:postcode":"dn15 8xf",
    "addr:street":"Mannaberg Way Bessemer Way Junction",
    "iso:country":"GB",
    "sg:address":"Mannaberg Way, Bessemer Way Junction",
    "sg:city":"Scunthorpe",
    "sg:classifiers":[
        {
            "category":"Autos & Motor Vehicles",
            "subcategory":"Automobile Sales",
            "type":"Retail Goods"
        }
    ],
    "sg:phone":"+44 1724 855063",
    "sg:postcode":"DN15 8XF",
    "sg:province":"Lincolnshire",
    "sg:tags":[
        "car"
    ],
    "wof:name":"Gocar Ltd.",
    "wof:placetype":"venue"
},
  "geometry": {"coordinates":[-0.6382989883,53.6055107117],"type":"Point"}
}