{
  "type": "Feature",
  "properties": {
    "addr:full":"89 Barnston Road, Heswall Wirral Merseyside CH61 1BW",
    "addr:housenumber":"89",
    "addr:postcode":"ch61 1bw",
    "addr:street":"Barnston Road",
    "iso:country":"GB",
    "sg:address":"89 Barnston Road, Heswall",
    "sg:city":"Wirral",
    "sg:classifiers":[
        {
            "category":"Government",
            "subcategory":"Post Office",
            "type":"Public Place"
        }
    ],
    "sg:phone":"+44 151 648 1558",
    "sg:postcode":"CH61 1BW",
    "sg:province":"Merseyside",
    "wof:name":"Barnston Post Office",
    "wof:placetype":"venue"
},
  "geometry": {"coordinates":[-3.080981,53.340302],"type":"Point"}
}