{
  "type": "Feature",
  "properties": {
    "iso:country":"GB",
    "sg:address":"Belsham Court, South Street",
    "sg:city":"Totnes",
    "sg:classifiers":[
        {
            "category":"Professional",
            "subcategory":"Engineering",
            "type":"Services"
        }
    ],
    "sg:phone":"+44 1803 865500",
    "sg:postcode":"TQ9 5FZ",
    "sg:province":"Devon",
    "sg:tags":[
        "design",
        "engineer"
    ],
    "wof:name":"Chris Wright Associates",
    "wof:placetype":"venue"
},
  "geometry": {"coordinates":[-3.687297,50.430935],"type":"Point"}
}