{
  "type": "Feature",
  "properties": {
    "iso:country":"GB",
    "sg:address":"28 Rushey Field, Bromley Cross",
    "sg:city":"Bolton",
    "sg:classifiers":[
        {
            "category":"Building & Trades",
            "subcategory":"Construction",
            "type":"Services"
        }
    ],
    "sg:postcode":"BL7 9HQ",
    "sg:province":"Lancashire",
    "sg:tags":[
        "roofing"
    ],
    "wof:name":"P Cooke Heating Engineer",
    "wof:placetype":"venue"
},
  "geometry": {"coordinates":[-2.4285709858,53.6178588867],"type":"Point"}
}