{
  "type": "Feature",
  "properties": {
    "addr:full":"252 Abbey Road, Kirkstall Leeds West Yorkshire LS5 3NE",
    "addr:housenumber":"252",
    "addr:postcode":"ls5 3ne",
    "addr:street":"Abbey Road",
    "iso:country":"GB",
    "sg:address":"252 Abbey Road, Kirkstall",
    "sg:city":"Leeds",
    "sg:classifiers":[
        {
            "category":"Professional",
            "subcategory":"Engineering",
            "type":"Services"
        }
    ],
    "sg:phone":"+44 113 281 8282",
    "sg:postcode":"LS5 3NE",
    "sg:province":"West Yorkshire",
    "sg:tags":[
        "design",
        "engineer"
    ],
    "wof:name":"Arios & Neysari Ltd.",
    "wof:placetype":"venue"
},
  "geometry": {"coordinates":[-1.619012,53.824574],"type":"Point"}
}