{
  "type": "Feature",
  "properties": {
    "iso:country":"GB",
    "sg:address":"Lower Chicks Gro, Tisbury",
    "sg:city":"Salisbury",
    "sg:classifiers":[
        {
            "category":"Bars & Pubs",
            "type":"Food & Drink"
        }
    ],
    "sg:phone":"+44 1722 714318",
    "sg:postcode":"SP3 6NB",
    "sg:province":"Wiltshire",
    "sg:tags":[
        "pubs",
        "inn"
    ],
    "wof:name":"The Compasses Inn",
    "wof:placetype":"venue"
},
  "geometry": {"coordinates":[-2.0803239346,51.0668487549],"type":"Point"}
}