{
  "type": "Feature",
  "properties": {
    "iso:country":"GB",
    "sg:address":"29 Main Street, The Village, East Kilbride",
    "sg:city":"Glasgow",
    "sg:classifiers":[
        {
            "category":"Shopping",
            "subcategory":"Musical Instruments",
            "type":"Retail Goods"
        }
    ],
    "sg:phone":"+44 1355 244562",
    "sg:postcode":"G74 4JU",
    "sg:province":"South Lanarkshire",
    "sg:tags":[
        "retailer",
        "sheet",
        "music"
    ],
    "wof:name":"Village Music",
    "wof:placetype":"venue"
},
  "geometry": {"coordinates":[-4.175954,55.766682],"type":"Point"}
}