{
  "type": "Feature",
  "properties": {
    "addr:full":"37 Magdalen Road Oxford Oxfordshire OX4 1RB",
    "addr:housenumber":"37",
    "addr:postcode":"ox4 1rb",
    "addr:street":"Magdalen Road",
    "iso:country":"GB",
    "sg:address":"37 Magdalen Road",
    "sg:city":"Oxford",
    "sg:classifiers":[
        {
            "category":"Shopping",
            "subcategory":"Department Store",
            "type":"Retail Goods"
        },
        {
            "category":"Food & Beverages",
            "subcategory":"Supermarket",
            "type":"Retail Goods"
        },
        {
            "category":"Food & Beverages",
            "subcategory":"Groceries & Convenience Stores",
            "type":"Retail Goods"
        }
    ],
    "sg:phone":"+44 1865 248900",
    "sg:postcode":"OX4 1RB",
    "sg:province":"Oxfordshire",
    "wof:name":"Macdillon Stores",
    "wof:placetype":"venue"
},
  "geometry": {"coordinates":[-1.2348719835,51.7425079346],"type":"Point"}
}