{
  "type": "Feature",
  "properties": {
    "iso:country":"GB",
    "sg:address":"70 Rydens Gro, Hersham",
    "sg:city":"Walton-on-thames",
    "sg:classifiers":[
        {
            "category":"Building & Trades",
            "subcategory":"Construction",
            "type":"Services"
        }
    ],
    "sg:phone":"+44 1932 246958",
    "sg:postcode":"KT12 5RU",
    "sg:province":"Surrey",
    "sg:tags":[
        "builder"
    ],
    "wof:name":"Mark Hansford",
    "wof:placetype":"venue"
},
  "geometry": {"coordinates":[-0.4207040071,51.3843460083],"type":"Point"}
}