{
  "type": "Feature",
  "properties": {
    "addr:full":"30 Barnstaple Rd Leicester Leicestershire LE5 6XB",
    "addr:housenumber":"30",
    "addr:postcode":"le5 6xb",
    "addr:street":"Barnstaple Rd",
    "iso:country":"GB",
    "sg:address":"30 Barnstaple Rd",
    "sg:city":"Leicester",
    "sg:classifiers":[
        {
            "category":"Manufacturing",
            "subcategory":"Tools & Machinery",
            "type":"Manufacturing & Wholesale Goods"
        }
    ],
    "sg:phone":"+44 116 243 3133",
    "sg:postcode":"LE5 6XB",
    "sg:province":"Leicestershire",
    "sg:tags":[
        "society",
        "friendly"
    ],
    "wof:name":"Athena Insurance Services",
    "wof:placetype":"venue"
},
  "geometry": {"coordinates":[-1.062109,52.622898],"type":"Point"}
}