{
  "type": "Feature",
  "properties": {
    "iso:country":"GB",
    "sg:address":"140 Horn Lane, Acton",
    "sg:city":"London",
    "sg:classifiers":[
        {
            "category":"Real Estate",
            "subcategory":"Real Estate Operator",
            "type":"Services"
        }
    ],
    "sg:phone":"+44 20 8992 7861",
    "sg:postcode":"W3 6PA",
    "sg:province":"Greater London",
    "sg:tags":[
        "letting",
        "agent"
    ],
    "wof:name":"G & T Lettings",
    "wof:placetype":"venue"
},
  "geometry": {"coordinates":[-0.2693209946,51.513874054],"type":"Point"}
}