{
  "type": "Feature",
  "properties": {
    "addr:full":"3 South Cote Close, South Cave Brough East Riding of Yorkshire HU15 2BQ",
    "addr:housenumber":"3",
    "addr:postcode":"hu15 2bq",
    "addr:street":"South Cote Close",
    "iso:country":"GB",
    "sg:address":"3 South Cote Close, South Cave",
    "sg:city":"Brough",
    "sg:classifiers":[
        {
            "category":"Military Area",
            "subcategory":"Air Force Base",
            "type":"Public Place"
        }
    ],
    "sg:phone":"+44 1430 422218",
    "sg:postcode":"HU15 2BQ",
    "sg:province":"East Riding of Yorkshire",
    "sg:tags":[
        "taxi",
        "hire",
        "private"
    ],
    "wof:name":"South Cave Taxis",
    "wof:placetype":"venue"
},
  "geometry": {"coordinates":[-0.572144,53.729919],"type":"Point"}
}