{
  "type": "Feature",
  "properties": {
    "iso:country":"GB",
    "sg:address":"Bank House, 30 Upper Mulgrave Road",
    "sg:city":"Sutton",
    "sg:classifiers":[
        {
            "category":"Professional",
            "subcategory":"Business Services",
            "type":"Services"
        }
    ],
    "sg:postcode":"SM2 7AZ",
    "sg:province":"Surrey",
    "sg:tags":[
        "broker",
        "commodity"
    ],
    "wof:name":"O F L Ltd.",
    "wof:placetype":"venue"
},
  "geometry": {"coordinates":[-0.2138289958,51.3548126221],"type":"Point"}
}