{
  "type": "Feature",
  "properties": {
    "addr:full":"512-514 London Road Westcliff-on-sea Essex SS0 9LE",
    "addr:housenumber":"512-514",
    "addr:postcode":"ss0 9le",
    "addr:street":"London Road",
    "iso:country":"GB",
    "sg:address":"512-514 London Road",
    "sg:city":"Westcliff-on-sea",
    "sg:classifiers":[
        {
            "category":"Building & Trades",
            "subcategory":"Construction",
            "type":"Services"
        }
    ],
    "sg:phone":"+44 1702 332277",
    "sg:postcode":"SS0 9LE",
    "sg:province":"Essex",
    "sg:tags":[
        "decorator",
        "painter"
    ],
    "wof:name":"Accent Wallcoating Ltd.",
    "wof:placetype":"venue"
},
  "geometry": {"coordinates":[0.688861,51.544567],"type":"Point"}
}