{
  "type": "Feature",
  "properties": {
    "addr:full":"Poolstock Lane Wigan Lancashire WN3 5JE",
    "addr:postcode":"wn3 5je",
    "addr:street":"Poolstock Lane",
    "iso:country":"GB",
    "sg:address":"Poolstock Lane",
    "sg:city":"Wigan",
    "sg:classifiers":[
        {
            "category":"Autos & Motor Vehicles",
            "subcategory":"Fuel & Gas Station",
            "type":"Retail Goods"
        }
    ],
    "sg:postcode":"WN3 5JE",
    "sg:province":"Lancashire",
    "sg:tags":[
        "hr",
        "petrol"
    ],
    "wof:name":"Wigan Service Station",
    "wof:placetype":"venue"
},
  "geometry": {"coordinates":[-2.6334440708,53.5376663208],"type":"Point"}
}