{
  "type": "Feature",
  "properties": {
    "addr:full":"Middle Farm Alston Cumbria CA9 3LD",
    "addr:postcode":"ca9 3ld",
    "addr:street":"Middle;Alston",
    "iso:country":"GB",
    "sg:address":"Middle Farm",
    "sg:city":"Alston",
    "sg:classifiers":[
        {
            "category":"Travel",
            "subcategory":"Hotels & Motels",
            "type":"Entertainment"
        }
    ],
    "sg:postcode":"CA9 3LD",
    "sg:province":"Cumbria",
    "sg:tags":[
        "house",
        "guest"
    ],
    "wof:name":"Middle Sell",
    "wof:placetype":"venue"
},
  "geometry": {"coordinates":[-2.438751936,54.8123817444],"type":"Point"}
}