{
  "type": "Feature",
  "properties": {
    "addr:full":"Factory Lane, Barrowford Nelson Lancashire BB9 6ES",
    "addr:postcode":"bb9 6es",
    "addr:street":"Factory Lane",
    "iso:country":"GB",
    "sg:address":"Factory Lane, Barrowford",
    "sg:city":"Nelson",
    "sg:classifiers":[
        {
            "category":"Professional",
            "subcategory":"Engineering",
            "type":"Services"
        }
    ],
    "sg:phone":"+44 1282 613811",
    "sg:postcode":"BB9 6ES",
    "sg:province":"Lancashire",
    "sg:tags":[
        "contractor",
        "electrical",
        "engineer"
    ],
    "wof:name":"Baldwin Haig",
    "wof:placetype":"venue"
},
  "geometry": {"coordinates":[-2.21334,53.835968],"type":"Point"}
}