{
  "type": "Feature",
  "properties": {
    "iso:country":"GB",
    "sg:address":"Hutson Street",
    "sg:city":"Bradford",
    "sg:classifiers":[
        {
            "category":"Manufacturing",
            "subcategory":"Metals",
            "type":"Manufacturing & Wholesale Goods"
        }
    ],
    "sg:phone":"+44 1274 722946",
    "sg:postcode":"BD5 7LY",
    "sg:province":"West Yorkshire",
    "sg:tags":[
        "steel",
        "fabricator",
        "erectors"
    ],
    "wof:name":"Nicholls (Bradford) Ltd.",
    "wof:placetype":"venue"
},
  "geometry": {"coordinates":[-1.760304,53.781746],"type":"Point"}
}