{
  "type": "Feature",
  "properties": {
    "addr:full":"Connellys Yard, Jury Lane, Sidlesham Common Chichester West Sussex PO20 7PX",
    "addr:postcode":"po20 7px",
    "addr:street":"Connellys;Jury Lane",
    "iso:country":"GB",
    "sg:address":"Connellys Yard, Jury Lane, Sidlesham Common",
    "sg:city":"Chichester",
    "sg:classifiers":[
        {
            "category":"Utilities",
            "subcategory":"Refuse",
            "type":"Services"
        }
    ],
    "sg:phone":"+44 1243 641033",
    "sg:postcode":"PO20 7PX",
    "sg:province":"West Sussex",
    "sg:tags":[
        "disposal",
        "waste"
    ],
    "wof:name":"Viking Clearance",
    "wof:placetype":"venue"
},
  "geometry": {"coordinates":[-0.787379,50.776985],"type":"Point"}
}