{
  "type": "Feature",
  "properties": {
    "iso:country":"GB",
    "sg:address":"Bohunt Community School, Longmoor Rd",
    "sg:city":"Liphook",
    "sg:classifiers":[
        {
            "category":"Education",
            "subcategory":"Preschool",
            "type":"Public Place"
        }
    ],
    "sg:phone":"+44 1428 727288",
    "sg:postcode":"GU30 7NY",
    "sg:province":"Hampshire",
    "sg:tags":[
        "pre-school",
        "playgroups"
    ],
    "wof:name":"Bohunt Playschool",
    "wof:placetype":"venue"
},
  "geometry": {"coordinates":[-0.7991999984,51.0776405334],"type":"Point"}
}