{
  "type": "Feature",
  "properties": {
    "addr:full":"Gorrenberry House, Hermitage Water Hawick Cumbria TD9 0LT",
    "addr:postcode":"td9 0lt",
    "iso:country":"GB",
    "sg:address":"Gorrenberry House, Hermitage Water",
    "sg:city":"Hawick",
    "sg:classifiers":[
        {
            "category":"Real Estate",
            "subcategory":"Architect",
            "type":"Services"
        }
    ],
    "sg:phone":"+44 13873 76217",
    "sg:postcode":"TD9 0LT",
    "sg:province":"Cumbria",
    "wof:name":"Clive A Bewley & Associates",
    "wof:placetype":"venue"
},
  "geometry": {"coordinates":[-2.847479,55.339249],"type":"Point"}
}