{
  "type": "Feature",
  "properties": {
    "iso:country":"GB",
    "sg:address":"Moors Farm, Station Rd",
    "sg:city":"Kidderminster",
    "sg:classifiers":[
        {
            "category":"Professional",
            "subcategory":"Detective & Security Services",
            "type":"Services"
        }
    ],
    "sg:phone":"+44 1299 250490",
    "sg:postcode":"DY11 7YJ",
    "sg:province":"Staffordshire",
    "wof:name":"Cotronic Uk Ltd",
    "wof:placetype":"venue"
},
  "geometry": {"coordinates":[-2.2226500511,52.3343505859],"type":"Point"}
}