{
  "type": "Feature",
  "properties": {
    "addr:full":"45 Station Road, Kirkham Preston Lancashire PR4 2HE",
    "addr:housenumber":"45",
    "addr:postcode":"pr4 2he",
    "addr:street":"Station Road",
    "iso:country":"GB",
    "sg:address":"45 Station Road, Kirkham",
    "sg:city":"Preston",
    "sg:classifiers":[
        {
            "category":"Taxi",
            "type":"Transportation"
        },
        {
            "category":"Military Area",
            "subcategory":"Air Force Base",
            "type":"Public Place"
        }
    ],
    "sg:phone":"+44 1772 673737",
    "sg:postcode":"PR4 2HE",
    "sg:province":"Lancashire",
    "sg:tags":[
        "mini",
        "hire",
        "private",
        "cab"
    ],
    "wof:name":"Wesham Taxis",
    "wof:placetype":"venue"
},
  "geometry": {"coordinates":[-2.917028904,53.7779502869],"type":"Point"}
}