{
  "type": "Feature",
  "properties": {
    "addr:full":"73 Everlsey Park Rd Winchmore Hill Greater London N21 1NT",
    "addr:housenumber":"73",
    "addr:postcode":"n21 1nt",
    "addr:street":"Everlsey Park Rd",
    "iso:country":"GB",
    "sg:address":"73 Everlsey Park Rd",
    "sg:city":"Winchmore Hill",
    "sg:classifiers":[
        {
            "category":"Professional",
            "subcategory":"Lawyer & Legal Services",
            "type":"Services"
        }
    ],
    "sg:phone":"+44 20 8360 1707",
    "sg:postcode":"N21 1NT",
    "sg:province":"Greater London",
    "sg:tags":[
        "advice",
        "counselling"
    ],
    "wof:name":"Jager Mr H",
    "wof:placetype":"venue"
},
  "geometry": {"coordinates":[-0.109883,51.644005],"type":"Point"}
}