{
  "type": "Feature",
  "properties": {
    "addr:full":"25 London Road Edinburgh City of Edinburgh EH7 5AY",
    "addr:housenumber":"25",
    "addr:postcode":"eh7 5ay",
    "addr:street":"London Road",
    "iso:country":"GB",
    "sg:address":"25 London Road",
    "sg:city":"Edinburgh",
    "sg:classifiers":[
        {
            "category":"Personal",
            "subcategory":"Beauty Salon",
            "type":"Services"
        }
    ],
    "sg:postcode":"EH7 5AY",
    "sg:province":"City of Edinburgh",
    "sg:tags":[
        "unisex",
        "hairdresser"
    ],
    "wof:name":"Expressions",
    "wof:placetype":"venue"
},
  "geometry": {"coordinates":[-3.1701350212,55.9575614929],"type":"Point"}
}