{
  "type": "Feature",
  "properties": {
    "iso:country":"GB",
    "sg:address":"2 Merchant Street",
    "sg:city":"Bristol",
    "sg:classifiers":[
        {
            "category":"Home & Garden",
            "subcategory":"Kitchen Supply",
            "type":"Retail Goods"
        }
    ],
    "sg:phone":"+44 117 949 7771",
    "sg:postcode":"BS1 3ET",
    "sg:province":"City of Bristol",
    "sg:tags":[
        "glassware",
        "china"
    ],
    "wof:name":"Great Western China & Glass",
    "wof:placetype":"venue"
},
  "geometry": {"coordinates":[-2.588222,51.456795],"type":"Point"}
}