{
  "type": "Feature",
  "properties": {
    "addr:full":"Parc Mawr, Cwmdu Llandeilo Carmarthenshire SA19 7NW",
    "addr:postcode":"sa19 7nw",
    "iso:country":"GB",
    "sg:address":"Parc Mawr, Cwmdu",
    "sg:city":"Llandeilo",
    "sg:classifiers":[
        {
            "category":"Farming",
            "subcategory":"Livestock Farm",
            "type":"Manufacturing & Wholesale Goods"
        }
    ],
    "sg:postcode":"SA19 7NW",
    "sg:province":"Carmarthenshire",
    "sg:tags":[
        "others"
    ],
    "wof:name":"N C Armstrong-Esther",
    "wof:placetype":"venue"
},
  "geometry": {"coordinates":[-3.993792057,51.9515991211],"type":"Point"}
}