{
  "type": "Feature",
  "properties": {
    "addr:full":"B32 Winfrith Technology Centre Dorchester Dorset DT2 8DH",
    "addr:housenumber":"winfrith technology centre",
    "addr:postcode":"b32;dt2 8dh",
    "iso:country":"GB",
    "sg:address":"B32 Winfrith Technology Centre",
    "sg:city":"Dorchester",
    "sg:classifiers":[
        {
            "category":"Professional",
            "subcategory":"Testing Lab",
            "type":"Services"
        }
    ],
    "sg:phone":"+44 1305 852230",
    "sg:postcode":"DT2 8DH",
    "sg:province":"Dorset",
    "sg:tags":[
        "laboratory"
    ],
    "wof:name":"Taywood Environmental Consultancy",
    "wof:placetype":"venue"
},
  "geometry": {"coordinates":[-2.2526,50.682899],"type":"Point"}
}