{
  "type": "Feature",
  "properties": {
    "addr:full":"Unit 14 & 21 Liss Business Centre, Station Rd Liss Hampshire GU33 7AW",
    "addr:housenumber":"unit 14 & 21",
    "addr:postcode":"gu33 7aw",
    "addr:street":"Liss Business Centre Station Rd",
    "iso:country":"GB",
    "sg:address":"Unit 14 & 21 Liss Business Centre, Station Rd",
    "sg:city":"Liss",
    "sg:classifiers":[
        {
            "category":"Professional",
            "subcategory":"Printing & Photocopies",
            "type":"Services"
        }
    ],
    "sg:phone":"+44 1730 895333",
    "sg:postcode":"GU33 7AW",
    "sg:province":"Hampshire",
    "sg:tags":[
        "computer",
        "tag",
        "label"
    ],
    "wof:name":"ACE Trade Labels",
    "wof:placetype":"venue"
},
  "geometry": {"coordinates":[-0.8977900147,51.0480003357],"type":"Point"}
}