{
  "type": "Feature",
  "properties": {
    "addr:full":"139 Malvern Cres Darlington Durham DL3 9UN",
    "addr:housenumber":"139",
    "addr:postcode":"dl3 9un",
    "addr:street":"Malvern Cres",
    "iso:country":"GB",
    "sg:address":"139 Malvern Cres",
    "sg:city":"Darlington",
    "sg:classifiers":[
        {
            "category":"Building & Trades",
            "subcategory":"Construction",
            "type":"Services"
        }
    ],
    "sg:phone":"+44 1325 469662",
    "sg:postcode":"DL3 9UN",
    "sg:province":"Durham",
    "sg:tags":[
        "guttering"
    ],
    "wof:name":"S & M Roofing Contractors",
    "wof:placetype":"venue"
},
  "geometry": {"coordinates":[-1.6031490564,54.5408325195],"type":"Point"}
}