{
  "type": "Feature",
  "properties": {
    "addr:full":"53 Carey Street London Greater London WC2A 2JB",
    "addr:housenumber":"53",
    "addr:postcode":"wc2a 2jb",
    "addr:street":"Carey Street",
    "iso:country":"GB",
    "sg:address":"53 Carey Street",
    "sg:city":"London",
    "sg:classifiers":[
        {
            "category":"Bars & Pubs",
            "type":"Food & Drink"
        }
    ],
    "sg:phone":"+44 20 7242 8521",
    "sg:postcode":"WC2A 2JB",
    "sg:province":"Greater London",
    "sg:tags":[
        "pubs",
        "inn"
    ],
    "wof:name":"Seven Stars",
    "wof:placetype":"venue"
},
  "geometry": {"coordinates":[-0.1126459986,51.5152015686],"type":"Point"}
}