{
  "type": "Feature",
  "properties": {
    "addr:full":"161/163 St Johns Hill London Greater London SW11 1TQ",
    "addr:housenumber":"161 / 163",
    "addr:postcode":"sw11 1tq",
    "addr:street":"St Johns Hill",
    "iso:country":"GB",
    "sg:address":"161/163 St Johns Hill",
    "sg:city":"London",
    "sg:classifiers":[
        {
            "category":"Travel",
            "subcategory":"Travel Agent",
            "type":"Entertainment"
        }
    ],
    "sg:postcode":"SW11 1TQ",
    "sg:province":"Greater London",
    "wof:name":"Grove Travel",
    "wof:placetype":"venue"
},
  "geometry": {"coordinates":[-0.17707,51.460209],"type":"Point"}
}