{
  "type": "Feature",
  "properties": {
    "addr:full":"Craig Road, Old Colwyn Colwyn Bay Conwy LL29 9HN",
    "addr:postcode":"ll29 9hn",
    "addr:street":"Craig Road",
    "iso:country":"GB",
    "sg:address":"Craig Road, Old Colwyn",
    "sg:city":"Colwyn Bay",
    "sg:classifiers":[
        {
            "category":"Education",
            "subcategory":"School",
            "type":"Public Place"
        },
        {
            "category":"Government",
            "subcategory":"Office",
            "type":"Public Place"
        }
    ],
    "sg:phone":"+44 1492 515083",
    "sg:postcode":"LL29 9HN",
    "sg:province":"Conwy",
    "sg:tags":[
        "local",
        "authority"
    ],
    "wof:name":"Penmaenrhos Infant School",
    "wof:placetype":"venue"
},
  "geometry": {"coordinates":[-3.684623003,53.288444519],"type":"Point"}
}