{
  "type": "Feature",
  "properties": {
    "addr:full":"7 Beechfield House, Church Road Preston Lancashire PR25 3SA",
    "addr:housenumber":"7;house",
    "addr:postcode":"pr25 3sa",
    "addr:street":"Beechfield;Church Road",
    "iso:country":"GB",
    "sg:address":"7 Beechfield House, Church Road",
    "sg:city":"Preston",
    "sg:classifiers":[
        {
            "category":"Social Services",
            "subcategory":"Retirement Home",
            "type":"Services"
        }
    ],
    "sg:phone":"+44 1772 623710",
    "sg:postcode":"PR25 3SA",
    "sg:province":"Lancashire",
    "sg:tags":[
        "rest"
    ],
    "wof:name":"Jah-Jireh",
    "wof:placetype":"venue"
},
  "geometry": {"coordinates":[-2.68945,53.688389],"type":"Point"}
}