{
  "type": "Feature",
  "properties": {
    "addr:full":"Atlantic Way, Bronswick Business Park Liverpool Merseyside L3 4BE",
    "addr:postcode":"l3 4be",
    "addr:street":"Atlantic Way Bronswick Business Park",
    "iso:country":"GB",
    "sg:address":"Atlantic Way, Bronswick Business Park",
    "sg:city":"Liverpool",
    "sg:classifiers":[
        {
            "category":"Organizations",
            "subcategory":"Non-profit Organization",
            "type":"Services"
        }
    ],
    "sg:phone":"+44 151 330 4300",
    "sg:postcode":"L3 4BE",
    "sg:province":"Merseyside",
    "sg:tags":[
        "organisation",
        "voluntary",
        "charity"
    ],
    "wof:name":"Furniture Resource Centre Ltd.",
    "wof:placetype":"venue"
},
  "geometry": {"coordinates":[-2.981771946,53.3839454651],"type":"Point"}
}