{
  "type": "Feature",
  "properties": {
    "iso:country":"GB",
    "sg:address":"1 Queen Elizabeth Buildings, Temple",
    "sg:city":"London",
    "sg:classifiers":[
        {
            "category":"Professional",
            "subcategory":"Lawyer & Legal Services",
            "type":"Services"
        }
    ],
    "sg:phone":"+44 20 7797 7837",
    "sg:postcode":"EC4Y 9BS",
    "sg:province":"Greater London",
    "sg:tags":[
        "barrister"
    ],
    "wof:name":"David Bodey",
    "wof:placetype":"venue"
},
  "geometry": {"coordinates":[-0.11157,51.511662],"type":"Point"}
}