{
  "type": "Feature",
  "properties": {
    "iso:country":"GB",
    "sg:address":"1585 Bristol Road South, Longbridge",
    "sg:city":"Birmingham",
    "sg:classifiers":[
        {
            "category":"Professional",
            "subcategory":"Engineering",
            "type":"Services"
        }
    ],
    "sg:phone":"+44 121 460 1297",
    "sg:postcode":"B45 9UA",
    "sg:province":"West Midlands",
    "wof:name":"G P M Engineering Systems (1982) Ltd.",
    "wof:placetype":"venue"
},
  "geometry": {"coordinates":[-1.992853,52.395699],"type":"Point"}
}