{
  "type": "Feature",
  "properties": {
    "addr:full":"14-20 Marshall Street Edinburgh City of Edinburgh EH8 9BJ",
    "addr:housenumber":"14-20",
    "addr:postcode":"eh8 9bj",
    "addr:street":"Marshall Street",
    "iso:country":"GB",
    "sg:address":"14-20 Marshall Street",
    "sg:city":"Edinburgh",
    "sg:classifiers":[
        {
            "category":"Professional",
            "subcategory":"Printing & Photocopies",
            "type":"Services"
        }
    ],
    "sg:postcode":"EH8 9BJ",
    "sg:province":"City of Edinburgh",
    "sg:tags":[
        "duplicating",
        "copying"
    ],
    "wof:name":"Copycat",
    "wof:placetype":"venue"
},
  "geometry": {"coordinates":[-3.1869690418,55.945640564],"type":"Point"}
}