{
  "type": "Feature",
  "properties": {
    "addr:full":"118 Holland Park Avenue London Greater London W11 4UA",
    "addr:housenumber":"118",
    "addr:postcode":"w11 4ua",
    "addr:street":"Holland Park Avenue",
    "iso:country":"GB",
    "sg:address":"118 Holland Park Avenue",
    "sg:city":"London",
    "sg:classifiers":[
        {
            "category":"Professional",
            "subcategory":"Business Services",
            "type":"Services"
        },
        {
            "category":"Casinos & Gambling",
            "type":"Entertainment"
        }
    ],
    "sg:postcode":"W11 4UA",
    "sg:province":"Greater London",
    "sg:tags":[
        "turf",
        "accountant",
        "bookmaker"
    ],
    "wof:name":"I Morris",
    "wof:placetype":"venue"
},
  "geometry": {"coordinates":[-0.209909,51.50602],"type":"Point"}
}