{
  "type": "Feature",
  "properties": {
    "addr:full":"146 Duke Street Edinburgh City of Edinburgh EH6 8HR",
    "addr:housenumber":"146",
    "addr:postcode":"eh6 8hr",
    "addr:street":"Duke Street",
    "iso:country":"GB",
    "sg:address":"146 Duke Street",
    "sg:city":"Edinburgh",
    "sg:classifiers":[
        {
            "category":"Shopping",
            "subcategory":"Pets & Pet Supplies",
            "type":"Retail Goods"
        }
    ],
    "sg:phone":"+44 131 554 3376",
    "sg:postcode":"EH6 8HR",
    "sg:province":"City of Edinburgh",
    "wof:name":"Pets & Things",
    "wof:placetype":"venue"
},
  "geometry": {"coordinates":[-3.1679449081,55.969078064],"type":"Point"}
}