{
  "type": "Feature",
  "properties": {
    "iso:country":"GB",
    "sg:address":"Habergham Hall Farm, Rossendale Road",
    "sg:city":"Burnley",
    "sg:classifiers":[
        {
            "category":"Farming",
            "subcategory":"Livestock Farm",
            "type":"Manufacturing & Wholesale Goods"
        }
    ],
    "sg:phone":"+44 1282 421420",
    "sg:postcode":"BB11 5QA",
    "sg:province":"Lancashire",
    "sg:tags":[
        "others"
    ],
    "wof:name":"Walter Maudsley",
    "wof:placetype":"venue"
},
  "geometry": {"coordinates":[-2.243809,53.78801],"type":"Point"}
}