{
  "type": "Feature",
  "properties": {
    "addr:full":"21 Hilbra Avenue, Haxby York North Yorkshire YO32 3HF",
    "addr:housenumber":"21",
    "addr:postcode":"yo32 3hf",
    "addr:street":"Hilbra Avenue",
    "iso:country":"GB",
    "sg:address":"21 Hilbra Avenue, Haxby",
    "sg:city":"York",
    "sg:classifiers":[
        {
            "category":"Building & Trades",
            "subcategory":"Construction",
            "type":"Services"
        }
    ],
    "sg:postcode":"YO32 3HF",
    "sg:province":"North Yorkshire",
    "sg:tags":[
        "builder"
    ],
    "wof:name":"M J Cooper",
    "wof:placetype":"venue"
},
  "geometry": {"coordinates":[-1.0754929781,54.0048828125],"type":"Point"}
}