{
  "type": "Feature",
  "properties": {
    "addr:full":"14-18 High Street Wooler Northumberland NE71 6BY",
    "addr:housenumber":"14-18",
    "addr:postcode":"ne71 6by",
    "addr:street":"High Street",
    "iso:country":"GB",
    "sg:address":"14-18 High Street",
    "sg:city":"Wooler",
    "sg:classifiers":[
        {
            "category":"Food & Beverages",
            "subcategory":"Supermarket",
            "type":"Retail Goods"
        }
    ],
    "sg:phone":"+44 1668 281528",
    "sg:postcode":"NE71 6BY",
    "sg:province":"Northumberland",
    "wof:name":"Northeastern & Cumbrian Co-Op Food Stores",
    "wof:placetype":"venue"
},
  "geometry": {"coordinates":[-2.0154709816,55.5464286804],"type":"Point"}
}