{
  "type": "Feature",
  "properties": {
    "addr:full":"41 Barlow Moor Road Manchester Greater Manchester M20 6TW",
    "addr:housenumber":"41",
    "addr:postcode":"m20 6tw",
    "addr:street":"Barlow Moor Road",
    "iso:country":"GB",
    "sg:address":"41 Barlow Moor Road",
    "sg:city":"Manchester",
    "sg:classifiers":[
        {
            "category":"Personal",
            "subcategory":"Beauty Salon",
            "type":"Services"
        }
    ],
    "sg:postcode":"M20 6TW",
    "sg:province":"Greater Manchester",
    "sg:tags":[
        "unisex",
        "hairdresser"
    ],
    "wof:name":"Eden",
    "wof:placetype":"venue"
},
  "geometry": {"coordinates":[-2.2335999012,53.4181251526],"type":"Point"}
}