{
  "type": "Feature",
  "properties": {
    "addr:full":"320 Harrow Road Wembley Greater London HA9 6LL",
    "addr:housenumber":"320",
    "addr:postcode":"ha9 6ll",
    "addr:street":"Harrow Road",
    "iso:country":"GB",
    "sg:address":"320 Harrow Road",
    "sg:city":"Wembley",
    "sg:classifiers":[
        {
            "category":"Professional",
            "subcategory":"Computer Services",
            "type":"Services"
        }
    ],
    "sg:postcode":"HA9 6LL",
    "sg:province":"Greater London",
    "sg:tags":[
        "development",
        "system",
        "software"
    ],
    "wof:name":"Jamal & Associates Limited",
    "wof:placetype":"venue"
},
  "geometry": {"coordinates":[-0.285233,51.552921],"type":"Point"}
}