{
  "type": "Feature",
  "properties": {
    "addr:full":"17 Friar Lane Nottingham Nottinghamshire NG1 6DA",
    "addr:housenumber":"17",
    "addr:postcode":"ng1 6da",
    "addr:street":"Friar Lane",
    "iso:country":"GB",
    "sg:address":"17 Friar Lane",
    "sg:city":"Nottingham",
    "sg:classifiers":[
        {
            "category":"Cafe",
            "type":"Food & Drink"
        }
    ],
    "sg:postcode":"NG1 6DA",
    "sg:province":"Nottinghamshire",
    "sg:tags":[
        "tea",
        "room"
    ],
    "wof:name":"Geetz",
    "wof:placetype":"venue"
},
  "geometry": {"coordinates":[-1.1514019966,52.9523468018],"type":"Point"}
}