{
  "type": "Feature",
  "properties": {
    "addr:full":"6 Purbeck Rd Chatham Kent ME4 6ED",
    "addr:housenumber":"6",
    "addr:postcode":"me4 6ed",
    "addr:street":"Purbeck Rd",
    "iso:country":"GB",
    "sg:address":"6 Purbeck Rd",
    "sg:city":"Chatham",
    "sg:classifiers":[
        {
            "category":"Building & Trades",
            "subcategory":"Plumbing",
            "type":"Services"
        }
    ],
    "sg:postcode":"ME4 6ED",
    "sg:province":"Kent",
    "sg:tags":[
        "heating"
    ],
    "wof:name":"Parkhill Plumbing",
    "wof:placetype":"venue"
},
  "geometry": {"coordinates":[0.5198460221,51.3734474182],"type":"Point"}
}