{
  "type": "Feature",
  "properties": {
    "iso:country":"GB",
    "sg:address":"161 Gilmore Pl",
    "sg:city":"Edinburgh",
    "sg:classifiers":[
        {
            "category":"Shopping",
            "subcategory":"Used Merchandise",
            "type":"Retail Goods"
        }
    ],
    "sg:postcode":"EH3 9PW",
    "sg:province":"City of Edinburgh",
    "sg:tags":[
        "shop",
        "second-hand"
    ],
    "wof:name":"Dr Findlays",
    "wof:placetype":"venue"
},
  "geometry": {"coordinates":[-3.213649,55.939079],"type":"Point"}
}