{
  "type": "Feature",
  "properties": {
    "addr:full":"9 Cammach Circle, Portlethen Aberdeen Aberdeen City AB12 4TT",
    "addr:housenumber":"9",
    "addr:postcode":"ab12 4tt",
    "addr:street":"Cammach Circle",
    "iso:country":"GB",
    "sg:address":"9 Cammach Circle, Portlethen",
    "sg:city":"Aberdeen",
    "sg:classifiers":[
        {
            "category":"Farming",
            "subcategory":"Nursery",
            "type":"Manufacturing & Wholesale Goods"
        }
    ],
    "sg:phone":"+44 1224 780527",
    "sg:postcode":"AB12 4TT",
    "sg:province":"Aberdeen City",
    "sg:tags":[
        "creche"
    ],
    "wof:name":"Cammach Nursery",
    "wof:placetype":"venue"
},
  "geometry": {"coordinates":[-2.143858,57.054344],"type":"Point"}
}