{
  "type": "Feature",
  "properties": {
    "addr:full":"53 Lawrence Road Liverpool Merseyside L15 0EE",
    "addr:housenumber":"53",
    "addr:postcode":"l15 0ee",
    "addr:street":"Lawrence Road",
    "iso:country":"GB",
    "sg:address":"53 Lawrence Road",
    "sg:city":"Liverpool",
    "sg:classifiers":[
        {
            "category":"Personal",
            "subcategory":"Beauty Salon",
            "type":"Services"
        },
        {
            "category":"Personal",
            "subcategory":"Barber",
            "type":"Services"
        }
    ],
    "sg:phone":"+44 151 280 8888",
    "sg:postcode":"L15 0EE",
    "sg:province":"Merseyside",
    "sg:tags":[
        "unisex",
        "hairdresser"
    ],
    "wof:name":"Cutting Corner",
    "wof:placetype":"venue"
},
  "geometry": {"coordinates":[-2.9349219799,53.3971061707],"type":"Point"}
}