{
  "type": "Feature",
  "properties": {
    "addr:full":"16 Florence Park Road Oxford Oxfordshire OX4 3PH",
    "addr:housenumber":"16",
    "addr:postcode":"ox4 3ph",
    "addr:street":"Florence Park Road",
    "iso:country":"GB",
    "sg:address":"16 Florence Park Road",
    "sg:city":"Oxford",
    "sg:classifiers":[
        {
            "category":"Shopping",
            "subcategory":"Department Store",
            "type":"Retail Goods"
        },
        {
            "category":"Food & Beverages",
            "subcategory":"Groceries & Convenience Stores",
            "type":"Retail Goods"
        }
    ],
    "sg:phone":"+44 1865 779306",
    "sg:postcode":"OX4 3PH",
    "sg:province":"Oxfordshire",
    "wof:name":"Park Stores",
    "wof:placetype":"venue"
},
  "geometry": {"coordinates":[-1.225077,51.733429],"type":"Point"}
}