{
  "type": "Feature",
  "properties": {
    "addr:full":"Po Box 9000 Leamington Spa Warwickshire CV32 6YD",
    "addr:housenumber":"po",
    "addr:postcode":"cv32 6yd",
    "addr:street":"Box 9000",
    "iso:country":"GB",
    "sg:address":"Po Box 9000",
    "sg:city":"Leamington Spa",
    "sg:classifiers":[
        {
            "category":"Professional",
            "subcategory":"Computer Services",
            "type":"Services"
        }
    ],
    "sg:phone":"+44 1926 421623",
    "sg:postcode":"CV32 6YD",
    "sg:province":"Warwickshire",
    "sg:tags":[
        "system",
        "software"
    ],
    "wof:name":"Public Sector Software Ltd.",
    "wof:placetype":"venue"
},
  "geometry": {"coordinates":[-1.5353239775,52.2891387939],"type":"Point"}
}