{
  "type": "Feature",
  "properties": {
    "addr:full":"Alport Farm, Overton Common Malpas Cheshire SY14 7DG",
    "addr:postcode":"sy14 7dg",
    "addr:street":"Cheshire",
    "iso:country":"GB",
    "sg:address":"Alport Farm, Overton Common",
    "sg:city":"Malpas",
    "sg:classifiers":[
        {
            "category":"Home & Garden",
            "subcategory":"Building Materials",
            "type":"Retail Goods"
        }
    ],
    "sg:postcode":"SY14 7DG",
    "sg:province":"Cheshire",
    "sg:tags":[
        "fencing"
    ],
    "wof:name":"G Taylor",
    "wof:placetype":"venue"
},
  "geometry": {"coordinates":[-2.766258955,53.020980835],"type":"Point"}
}