{
  "type": "Feature",
  "properties": {
    "addr:full":"464 Oldham Road, Failsworth Manchester Lancashire M35 0FH",
    "addr:housenumber":"464",
    "addr:postcode":"m35 0fh",
    "addr:street":"Oldham Road",
    "iso:country":"GB",
    "sg:address":"464 Oldham Road, Failsworth",
    "sg:city":"Manchester",
    "sg:classifiers":[
        {
            "category":"Bars & Pubs",
            "type":"Food & Drink"
        },
        {
            "category":"Community Center",
            "subcategory":"Social",
            "type":"Public Place"
        }
    ],
    "sg:phone":"+44 161 682 3033",
    "sg:postcode":"M35 0FH",
    "sg:province":"Lancashire",
    "sg:tags":[
        "pubs",
        "house",
        "inn",
        "activity"
    ],
    "wof:name":"THE BRIDGE INN",
    "wof:placetype":"venue"
},
  "geometry": {"coordinates":[-2.157998085,53.5105476379],"type":"Point"}
}