{
  "type": "Feature",
  "properties": {
    "addr:full":"Cathedral House Norwich Norfolk NR1 1LX",
    "addr:postcode":"nr1 1lx",
    "addr:street":"Norwich Norfolk",
    "iso:country":"GB",
    "sg:address":"Cathedral House",
    "sg:city":"Norwich",
    "sg:classifiers":[
        {
            "category":"Building & Trades",
            "subcategory":"Construction",
            "type":"Services"
        }
    ],
    "sg:phone":"+44 1603 667058",
    "sg:postcode":"NR1 1LX",
    "sg:province":"Norfolk",
    "sg:tags":[
        "glazier"
    ],
    "wof:name":"Highway Emergency Services Ltd.",
    "wof:placetype":"venue"
},
  "geometry": {"coordinates":[1.2948999405,52.6224937439],"type":"Point"}
}