{
  "type": "Feature",
  "properties": {
    "addr:full":"Unit 9, Glover Wayparkside Industrial Estate Leeds West Yorkshire LS11 5JW",
    "addr:housenumber":"unit 9",
    "addr:postcode":"ls11 5jw",
    "addr:street":"Glover Wayparkside Industrial Estate",
    "iso:country":"GB",
    "sg:address":"Unit 9, Glover Wayparkside Industrial Estate",
    "sg:city":"Leeds",
    "sg:classifiers":[
        {
            "category":"Manufacturing",
            "subcategory":"Glass & Minerals",
            "type":"Manufacturing & Wholesale Goods"
        }
    ],
    "sg:phone":"+44 113 270 2927",
    "sg:postcode":"LS11 5JW",
    "sg:province":"West Yorkshire",
    "sg:tags":[
        "mnfrs",
        "fibre"
    ],
    "wof:name":"Scott Bader Co",
    "wof:placetype":"venue"
},
  "geometry": {"coordinates":[-1.543347,53.769791],"type":"Point"}
}