{
  "type": "Feature",
  "properties": {
    "iso:country":"GB",
    "sg:address":"2 Norfolk Court",
    "sg:city":"Rickmansworth",
    "sg:classifiers":[
        {
            "category":"Real Estate",
            "subcategory":"Surveying",
            "type":"Services"
        }
    ],
    "sg:phone":"+44 1923 710711",
    "sg:postcode":"WD3 1LA",
    "sg:province":"Hertfordshire",
    "sg:tags":[
        "surveyor",
        "valuer"
    ],
    "wof:name":"Nigel Lawrence Ltd.",
    "wof:placetype":"venue"
},
  "geometry": {"coordinates":[-0.468266,51.637604],"type":"Point"}
}