{
  "type": "Feature",
  "properties": {
    "addr:full":"Knowle Farm, Mosterton Road, Misterton Crewkerne Dorset TA18 8NT",
    "addr:postcode":"ta18 8nt",
    "addr:street":"Mosterton Road",
    "iso:country":"GB",
    "sg:address":"Knowle Farm, Mosterton Road, Misterton",
    "sg:city":"Crewkerne",
    "sg:classifiers":[
        {
            "category":"Farming",
            "subcategory":"Livestock Farm",
            "type":"Manufacturing & Wholesale Goods"
        }
    ],
    "sg:phone":"+44 1460 72880",
    "sg:postcode":"TA18 8NT",
    "sg:province":"Dorset",
    "sg:tags":[
        "others"
    ],
    "wof:name":"A R Willmington",
    "wof:placetype":"venue"
},
  "geometry": {"coordinates":[-2.7738559246,50.8702125549],"type":"Point"}
}