{
  "type": "Feature",
  "properties": {
    "addr:full":"112 Jute Rd York North Yorkshire YO26 5EW",
    "addr:housenumber":"112",
    "addr:postcode":"yo26 5ew",
    "addr:street":"Jute Rd",
    "iso:country":"GB",
    "sg:address":"112 Jute Rd",
    "sg:city":"York",
    "sg:classifiers":[
        {
            "category":"Shopping",
            "subcategory":"Computers & Home Electronics",
            "type":"Retail Goods"
        }
    ],
    "sg:phone":"+44 1904 330330",
    "sg:postcode":"YO26 5EW",
    "sg:province":"North Yorkshire",
    "wof:name":"Aicro Jade Computing",
    "wof:placetype":"venue"
},
  "geometry": {"coordinates":[-1.1317789555,53.9594993591],"type":"Point"}
}