{
  "type": "Feature",
  "properties": {
    "addr:full":"Fyfe Gro, Baildon Shipley West Yorkshire BD17 6DN",
    "addr:postcode":"bd17 6dn",
    "addr:street":"Baildon;West",
    "iso:country":"GB",
    "sg:address":"Fyfe Gro, Baildon",
    "sg:city":"Shipley",
    "sg:classifiers":[
        {
            "category":"Education",
            "subcategory":"School",
            "type":"Public Place"
        },
        {
            "category":"Government",
            "subcategory":"Office",
            "type":"Public Place"
        }
    ],
    "sg:phone":"+44 1274 581898",
    "sg:postcode":"BD17 6DN",
    "sg:province":"West Yorkshire",
    "sg:tags":[
        "local",
        "authority"
    ],
    "wof:name":"Hoyle Court First School",
    "wof:placetype":"venue"
},
  "geometry": {"coordinates":[-1.766849041,53.8486709595],"type":"Point"}
}