{
  "type": "Feature",
  "properties": {
    "addr:full":"9 Pk Terr Stoke-on-trent Staffordshire ST6 6BP",
    "addr:housenumber":"9",
    "addr:postcode":"st6 6bp",
    "addr:street":"Pk Terr",
    "iso:country":"GB",
    "sg:address":"9 Pk Terr",
    "sg:city":"Stoke-on-trent",
    "sg:classifiers":[
        {
            "category":"Manufacturing",
            "subcategory":"Pottery",
            "type":"Manufacturing & Wholesale Goods"
        }
    ],
    "sg:phone":"+44 1782 838965",
    "sg:postcode":"ST6 6BP",
    "sg:province":"Staffordshire",
    "wof:name":"Mayflower Studio Pottery",
    "wof:placetype":"venue"
},
  "geometry": {"coordinates":[-2.2076900005,53.0599517822],"type":"Point"}
}