{
  "type": "Feature",
  "properties": {
    "addr:full":"69 Park House Gardens Durham Durham DH6 1DX",
    "addr:housenumber":"69",
    "addr:postcode":"dh6 1dx",
    "addr:street":"Park House Gardens",
    "iso:country":"GB",
    "sg:address":"69 Park House Gardens",
    "sg:city":"Durham",
    "sg:classifiers":[
        {
            "category":"Home & Garden",
            "subcategory":"Home Furnishings",
            "type":"Retail Goods"
        }
    ],
    "sg:phone":"+44 191 372 1525",
    "sg:postcode":"DH6 1DX",
    "sg:province":"Durham",
    "sg:tags":[
        "furnishers",
        "planner",
        "kitchen"
    ],
    "wof:name":"Quality Installations",
    "wof:placetype":"venue"
},
  "geometry": {"coordinates":[-1.505439,54.778759],"type":"Point"}
}