{
  "type": "Feature",
  "properties": {
    "iso:country":"GB",
    "sg:address":"95 Chucksbury Road",
    "sg:city":"Cheltenham",
    "sg:classifiers":[
        {
            "category":"Shopping",
            "subcategory":"Beauty & Cosmetics",
            "type":"Retail Goods"
        }
    ],
    "sg:phone":"+44 1242 512653",
    "sg:postcode":"GL51 9BA",
    "sg:province":"Gloucestershire",
    "sg:tags":[
        "equipment",
        "supply",
        "hairdressing"
    ],
    "wof:name":"Sally Ogee Hair & Beauty Supplies",
    "wof:placetype":"venue"
},
  "geometry": {"coordinates":[-2.08921,51.908352],"type":"Point"}
}