{
  "type": "Feature",
  "properties": {
    "iso:country":"GB",
    "sg:address":"31 Long Street",
    "sg:city":"Tetbury",
    "sg:classifiers":[
        {
            "category":"Shopping",
            "subcategory":"Gifts & Souvenirs",
            "type":"Retail Goods"
        }
    ],
    "sg:postcode":"GL8 8AA",
    "sg:province":"Gloucestershire",
    "sg:tags":[
        "shop"
    ],
    "wof:name":"Pia Taylor",
    "wof:placetype":"venue"
},
  "geometry": {"coordinates":[-2.160771,51.637917],"type":"Point"}
}