{
  "type": "Feature",
  "properties": {
    "iso:country":"GB",
    "sg:address":"3 Devonshire Close",
    "sg:city":"Wellingborough",
    "sg:classifiers":[
        {
            "category":"Utilities",
            "subcategory":"Natural Gas",
            "type":"Services"
        }
    ],
    "sg:postcode":"NN8 5QF",
    "sg:province":"Northamptonshire",
    "sg:tags":[
        "control",
        "energy",
        "management",
        "system"
    ],
    "wof:name":"B G Plumbing & Heating Services",
    "wof:placetype":"venue"
},
  "geometry": {"coordinates":[-0.708488,52.31002],"type":"Point"}
}