{
  "type": "Feature",
  "properties": {
    "addr:full":"10 Front St Consett Durham DH8 9AR",
    "addr:housenumber":"10",
    "addr:postcode":"dh8 9ar",
    "addr:street":"Front St",
    "iso:country":"GB",
    "sg:address":"10 Front St",
    "sg:city":"Consett",
    "sg:classifiers":[
        {
            "category":"Food & Beverages",
            "subcategory":"Liquor & Beverages",
            "type":"Retail Goods"
        }
    ],
    "sg:phone":"+44 1207 502487",
    "sg:postcode":"DH8 9AR",
    "sg:province":"Durham",
    "sg:tags":[
        "beer",
        "spirit",
        "wines"
    ],
    "wof:name":"Blayneys",
    "wof:placetype":"venue"
},
  "geometry": {"coordinates":[-1.8810269833,54.8341407776],"type":"Point"}
}