{
  "type": "Feature",
  "properties": {
    "iso:country":"GB",
    "sg:address":"Cock La",
    "sg:city":"Reading",
    "sg:classifiers":[
        {
            "category":"Health Services",
            "subcategory":"Doctor",
            "type":"Services"
        }
    ],
    "sg:phone":"+44 118 974 4147",
    "sg:postcode":"RG7 6HR",
    "sg:province":"Berkshire",
    "sg:tags":[
        "practitioners"
    ],
    "wof:name":"Bywater, J",
    "wof:placetype":"venue"
},
  "geometry": {"coordinates":[-1.145634,51.43343],"type":"Point"}
}