{
  "type": "Feature",
  "properties": {
    "iso:country":"GB",
    "sg:address":"3 Bullfields",
    "sg:city":"Sawbridgeworth",
    "sg:classifiers":[
        {
            "category":"Retail",
            "subcategory":"Funeral Services",
            "type":"Services"
        }
    ],
    "sg:phone":"+44 1279 722476",
    "sg:postcode":"CM21 9DB",
    "sg:province":"Essex",
    "sg:tags":[
        "director"
    ],
    "wof:name":"Daniel Robinson & Sons",
    "wof:placetype":"venue"
},
  "geometry": {"coordinates":[0.151620999,51.8151817322],"type":"Point"}
}