{
  "type": "Feature",
  "properties": {
    "addr:full":"187 Allerton Road Liverpool Merseyside L18 6HG",
    "addr:housenumber":"187",
    "addr:postcode":"l18 6hg",
    "addr:street":"Allerton Road",
    "iso:country":"GB",
    "sg:address":"187 Allerton Road",
    "sg:city":"Liverpool",
    "sg:classifiers":[
        {
            "category":"Fast Food",
            "type":"Food & Drink"
        }
    ],
    "sg:phone":"+44 151 729 0220",
    "sg:postcode":"L18 6HG",
    "sg:province":"Merseyside",
    "sg:tags":[
        "away",
        "take"
    ],
    "wof:name":"Hussains",
    "wof:placetype":"venue"
},
  "geometry": {"coordinates":[-2.9063870907,53.3838005066],"type":"Point"}
}