{
  "type": "Feature",
  "properties": {
    "iso:country":"GB",
    "sg:address":"13 Mill St",
    "sg:city":"Congleton",
    "sg:classifiers":[
        {
            "category":"Shopping",
            "subcategory":"Luggage & Leather Goods",
            "type":"Retail Goods"
        }
    ],
    "sg:postcode":"CW12 1AB",
    "sg:province":"Cheshire",
    "sg:tags":[
        "shop",
        "leathergoods"
    ],
    "wof:name":"Clifford,Donald,",
    "wof:placetype":"venue"
},
  "geometry": {"coordinates":[-2.214212,53.164211],"type":"Point"}
}