{
  "type": "Feature",
  "properties": {
    "iso:country":"GB",
    "sg:address":"49 North Road, Great Abington",
    "sg:city":"Cambridge",
    "sg:classifiers":[
        {
            "category":"Professional",
            "subcategory":"Employment Agencies",
            "type":"Services"
        }
    ],
    "sg:postcode":"CB1 6AS",
    "sg:province":"Cambridgeshire",
    "sg:tags":[
        "agricultural",
        "advice"
    ],
    "wof:name":"Sw Seed Ltd.",
    "wof:placetype":"venue"
},
  "geometry": {"coordinates":[0.217264,52.111488],"type":"Point"}
}