{
  "type": "Feature",
  "properties": {
    "iso:country":"GB",
    "sg:address":"2130 Paisley Road West",
    "sg:city":"Glasgow",
    "sg:classifiers":[
        {
            "category":"Food & Beverages",
            "subcategory":"Supermarket",
            "type":"Retail Goods"
        }
    ],
    "sg:phone":"+44 141 882 6593",
    "sg:postcode":"G52 3SQ",
    "sg:province":"Glasgow City",
    "wof:name":"Safeway Stores Ltd.",
    "wof:placetype":"venue"
},
  "geometry": {"coordinates":[-4.3550000191,55.8460617065],"type":"Point"}
}