{
  "type": "Feature",
  "properties": {
    "iso:country":"GB",
    "sg:address":"12 Bramble Street",
    "sg:city":"Derby",
    "sg:classifiers":[
        {
            "category":"Manufacturing",
            "subcategory":"Tools & Machinery",
            "type":"Manufacturing & Wholesale Goods"
        },
        {
            "category":"Insurance",
            "subcategory":"Insurance Agent",
            "type":"Services"
        }
    ],
    "sg:phone":"+44 1332 297500",
    "sg:postcode":"DE1 1HU",
    "sg:province":"Derbyshire",
    "sg:tags":[
        "society",
        "friendly"
    ],
    "wof:name":"Glenrose Insurance",
    "wof:placetype":"venue"
},
  "geometry": {"coordinates":[-1.481387,52.922226],"type":"Point"}
}