{
  "type": "Feature",
  "properties": {
    "addr:full":"12a North Street Emsworth Hampshire PO10 7DQ",
    "addr:housenumber":"12a",
    "addr:postcode":"po10 7dq",
    "addr:street":"North Street",
    "iso:country":"GB",
    "sg:address":"12a North Street",
    "sg:city":"Emsworth",
    "sg:classifiers":[
        {
            "category":"Professional",
            "subcategory":"Printing & Photocopies",
            "type":"Services"
        },
        {
            "category":"Government",
            "subcategory":"Post Office",
            "type":"Public Place"
        }
    ],
    "sg:phone":"+44 1243 374523",
    "sg:postcode":"PO10 7DQ",
    "sg:province":"Hampshire",
    "sg:tags":[
        "print",
        "typesetter",
        "typesetting"
    ],
    "wof:name":"Articulate Studio",
    "wof:placetype":"venue"
},
  "geometry": {"coordinates":[-0.937188,50.848442],"type":"Point"}
}