{
  "type": "Feature",
  "properties": {
    "addr:full":"13 Bankside Close, Upper Poppleton York North Yorkshire YO26 6LH",
    "addr:housenumber":"13",
    "addr:postcode":"yo26 6lh",
    "addr:street":"Bankside Close",
    "iso:country":"GB",
    "sg:address":"13 Bankside Close, Upper Poppleton",
    "sg:city":"York",
    "sg:classifiers":[
        {
            "category":"Education",
            "subcategory":"Music School",
            "type":"Public Place"
        }
    ],
    "sg:postcode":"YO26 6LH",
    "sg:province":"North Yorkshire",
    "sg:tags":[
        "conservatory"
    ],
    "wof:name":"David Elks Windows",
    "wof:placetype":"venue"
},
  "geometry": {"coordinates":[-1.154077,53.985592],"type":"Point"}
}