{
  "type": "Feature",
  "properties": {
    "iso:country":"GB",
    "sg:address":"15 Money Hill Pde",
    "sg:city":"Rickmansworth",
    "sg:classifiers":[
        {
            "category":"Recreation",
            "subcategory":"Fishing",
            "type":"Entertainment"
        }
    ],
    "sg:postcode":"WD3 7BE",
    "sg:province":"Hertfordshire",
    "sg:tags":[
        "angling"
    ],
    "wof:name":"Rods and Reels",
    "wof:placetype":"venue"
},
  "geometry": {"coordinates":[-0.4830009937,51.6387863159],"type":"Point"}
}