{
  "type": "Feature",
  "properties": {
    "iso:country":"GB",
    "sg:address":"41 St Johns Hill",
    "sg:city":"Shrewsbury",
    "sg:classifiers":[
        {
            "category":"Shopping",
            "subcategory":"Bicycles & Sporting Goods",
            "type":"Retail Goods"
        },
        {
            "category":"Sports & Exercise",
            "subcategory":"Sports Center",
            "type":"Entertainment"
        }
    ],
    "sg:phone":"+44 1743 233698",
    "sg:postcode":"SY1 1JQ",
    "sg:province":"Shropshire",
    "sg:tags":[
        "shop",
        "retailer"
    ],
    "wof:name":"Sports & Games (Shrewsbury) Ltd.",
    "wof:placetype":"venue"
},
  "geometry": {"coordinates":[-2.7566781044,52.7073249817],"type":"Point"}
}