{
  "type": "Feature",
  "properties": {
    "addr:full":"3 Millington Rd Cambridge Cambridgeshire CB3 9HW",
    "addr:housenumber":"3",
    "addr:postcode":"cb3 9hw",
    "addr:street":"Millington Rd",
    "iso:country":"GB",
    "sg:address":"3 Millington Rd",
    "sg:city":"Cambridge",
    "sg:classifiers":[
        {
            "category":"Health Services",
            "subcategory":"Doctor",
            "type":"Services"
        }
    ],
    "sg:phone":"+44 1223 364114",
    "sg:postcode":"CB3 9HW",
    "sg:province":"Cambridgeshire",
    "sg:tags":[
        "surgeon"
    ],
    "wof:name":"David A Moffat",
    "wof:placetype":"venue"
},
  "geometry": {"coordinates":[0.1077200025,52.1960639954],"type":"Point"}
}