{
  "type": "Feature",
  "properties": {
    "addr:full":"15 Elvet Bridge Durham Durham DH1 3AA",
    "addr:housenumber":"15",
    "addr:postcode":"dh1 3aa",
    "addr:street":"Elvet Bridge",
    "iso:country":"GB",
    "sg:address":"15 Elvet Bridge",
    "sg:city":"Durham",
    "sg:classifiers":[
        {
            "category":"Cafe",
            "type":"Food & Drink"
        }
    ],
    "sg:postcode":"DH1 3AA",
    "sg:province":"Durham",
    "sg:tags":[
        "tea",
        "room"
    ],
    "wof:name":"Brian Burke",
    "wof:placetype":"venue"
},
  "geometry": {"coordinates":[-1.573829,54.776001],"type":"Point"}
}