{
  "type": "Feature",
  "properties": {
    "iso:country":"GB",
    "sg:address":"Unit 2 Rear Of, 5 Fancy Road",
    "sg:city":"Poole",
    "sg:classifiers":[
        {
            "category":"Building & Trades",
            "subcategory":"Construction",
            "type":"Services"
        }
    ],
    "sg:postcode":"BH12 4QZ",
    "sg:province":"Dorset",
    "sg:tags":[
        "welder"
    ],
    "wof:name":"Carson Cars",
    "wof:placetype":"venue"
},
  "geometry": {"coordinates":[-1.95058,50.74374],"type":"Point"}
}