{
  "type": "Feature",
  "properties": {
    "iso:country":"GB",
    "sg:address":"50 Cecil Street",
    "sg:city":"Carlisle",
    "sg:classifiers":[
        {
            "category":"Fast Food",
            "type":"Food & Drink"
        }
    ],
    "sg:phone":"+44 1228 590670",
    "sg:postcode":"CA1 1NT",
    "sg:province":"Cumbria",
    "sg:tags":[
        "away",
        "take"
    ],
    "wof:name":"Roy Pedrosa",
    "wof:placetype":"venue"
},
  "geometry": {"coordinates":[-2.92876,54.891476],"type":"Point"}
}