{
  "type": "Feature",
  "properties": {
    "addr:full":"74 Lumley Road Skegness Lincolnshire PE25 2TH",
    "addr:housenumber":"74",
    "addr:postcode":"pe25 2th",
    "addr:street":"Lumley Road",
    "iso:country":"GB",
    "sg:address":"74 Lumley Road",
    "sg:city":"Skegness",
    "sg:classifiers":[
        {
            "category":"Travel",
            "subcategory":"Travel Agent",
            "type":"Entertainment"
        }
    ],
    "sg:phone":"+44 1746 10370",
    "sg:postcode":"PE25 2TH",
    "sg:province":"Lincolnshire",
    "wof:name":"Lunn Poly Ltd.",
    "wof:placetype":"venue"
},
  "geometry": {"coordinates":[0.3385199904,53.1429901123],"type":"Point"}
}