{
  "type": "Feature",
  "properties": {
    "iso:country":"GB",
    "sg:address":"Unit 9a South Yorkshire",
    "sg:city":"Sheffield",
    "sg:classifiers":[
        {
            "category":"Shopping",
            "subcategory":"Florist",
            "type":"Retail Goods"
        }
    ],
    "sg:phone":"+44 114 243 3360",
    "sg:postcode":"S9 4WN",
    "sg:province":"South Yorkshire",
    "wof:name":"Flowerworld",
    "wof:placetype":"venue"
},
  "geometry": {"coordinates":[-1.42099,53.382591],"type":"Point"}
}