{
  "type": "Feature",
  "properties": {
    "addr:full":"83 Tavistock Street Bedford Bedfordshire MK40 2RR",
    "addr:housenumber":"83",
    "addr:postcode":"mk40 2rr",
    "addr:street":"Tavistock Street",
    "iso:country":"GB",
    "sg:address":"83 Tavistock Street",
    "sg:city":"Bedford",
    "sg:classifiers":[
        {
            "category":"Shopping",
            "subcategory":"News",
            "type":"Retail Goods"
        }
    ],
    "sg:phone":"+44 1234 354379",
    "sg:postcode":"MK40 2RR",
    "sg:province":"Bedfordshire",
    "sg:tags":[
        "newsagent"
    ],
    "wof:name":"Tavistock Newsagency",
    "wof:placetype":"venue"
},
  "geometry": {"coordinates":[-0.4714849889,52.1411170959],"type":"Point"}
}