{
  "type": "Feature",
  "properties": {
    "addr:full":"Warton Farm, Thropton Morpeth Northumberland NE65 7LD",
    "addr:postcode":"ne65 7ld",
    "iso:country":"GB",
    "sg:address":"Warton Farm, Thropton",
    "sg:city":"Morpeth",
    "sg:classifiers":[
        {
            "category":"Farming",
            "subcategory":"Farm",
            "type":"Manufacturing & Wholesale Goods"
        }
    ],
    "sg:phone":"+44 1669 640205",
    "sg:postcode":"NE65 7LD",
    "sg:province":"Northumberland",
    "sg:tags":[
        "mixed",
        "crop"
    ],
    "wof:name":"M Davy",
    "wof:placetype":"venue"
},
  "geometry": {"coordinates":[-1.955799,55.314335],"type":"Point"}
}