{
  "type": "Feature",
  "properties": {
    "addr:full":"7-8 Wharf Rd Grantham Lincolnshire NG31 6BA",
    "addr:housenumber":"7-8",
    "addr:postcode":"ng31 6ba",
    "addr:street":"Wharf Rd",
    "iso:country":"GB",
    "sg:address":"7-8 Wharf Rd",
    "sg:city":"Grantham",
    "sg:classifiers":[
        {
            "category":"Home & Garden",
            "subcategory":"Furniture",
            "type":"Retail Goods"
        }
    ],
    "sg:postcode":"NG31 6BA",
    "sg:province":"Lincolnshire",
    "wof:name":"Millar,William,",
    "wof:placetype":"venue"
},
  "geometry": {"coordinates":[-0.6404740214,52.9092178345],"type":"Point"}
}