{
  "type": "Feature",
  "properties": {
    "iso:country":"GB",
    "sg:address":"66 Culver Lane, Earley",
    "sg:city":"Reading",
    "sg:classifiers":[
        {
            "category":"Social Services",
            "subcategory":"Retirement Home",
            "type":"Services"
        }
    ],
    "sg:phone":"+44 118 966 1569",
    "sg:postcode":"RG6 1DY",
    "sg:province":"Berkshire",
    "sg:tags":[
        "residential",
        "care"
    ],
    "wof:name":"Sutton Court",
    "wof:placetype":"venue"
},
  "geometry": {"coordinates":[-0.9286490083,51.4527206421],"type":"Point"}
}