{
  "type": "Feature",
  "properties": {
    "addr:full":"Industrial Estate, Braintree Road Ruislip Greater London HA4 0XJ",
    "addr:postcode":"ha4 0xj",
    "addr:street":"Industrial Estate Braintree Road",
    "iso:country":"GB",
    "sg:address":"Industrial Estate, Braintree Road",
    "sg:city":"Ruislip",
    "sg:classifiers":[
        {
            "category":"Home & Garden",
            "subcategory":"Carpets & Floor Coverings",
            "type":"Retail Goods"
        }
    ],
    "sg:phone":"+44 20 8845 5275",
    "sg:postcode":"HA4 0XJ",
    "sg:province":"Greater London",
    "sg:tags":[
        "rubber",
        "plastic"
    ],
    "wof:name":"Heathline Ltd.",
    "wof:placetype":"venue"
},
  "geometry": {"coordinates":[-0.4262790084,51.5758857727],"type":"Point"}
}