{
  "type": "Feature",
  "properties": {
    "addr:full":"West La Knutsford Cheshire WA16 6NB",
    "addr:postcode":"wa16 6nb",
    "addr:street":"West La Knutsford",
    "iso:country":"GB",
    "sg:address":"West La",
    "sg:city":"Knutsford",
    "sg:classifiers":[
        {
            "category":"Education",
            "subcategory":"Preschool",
            "type":"Public Place"
        }
    ],
    "sg:phone":"+44 1925 754327",
    "sg:postcode":"WA16 6NB",
    "sg:province":"Cheshire",
    "sg:tags":[
        "pre-school",
        "playgroups"
    ],
    "wof:name":"High Lea Pre School Nursery",
    "wof:placetype":"venue"
},
  "geometry": {"coordinates":[-2.449084,53.358688],"type":"Point"}
}