{
  "type": "Feature",
  "properties": {
    "addr:full":"99 Hillcrest Road Bromley Kent BR1 4SA",
    "addr:housenumber":"99",
    "addr:postcode":"br1 4sa",
    "addr:street":"Hillcrest Road",
    "iso:country":"GB",
    "sg:address":"99 Hillcrest Road",
    "sg:city":"Bromley",
    "sg:classifiers":[
        {
            "category":"Building & Trades",
            "subcategory":"Plumbing",
            "type":"Services"
        }
    ],
    "sg:phone":"+44 20 8857 5902",
    "sg:postcode":"BR1 4SA",
    "sg:province":"Kent",
    "sg:tags":[
        "heating"
    ],
    "wof:name":"Little & Large",
    "wof:placetype":"venue"
},
  "geometry": {"coordinates":[0.01614,51.425251],"type":"Point"}
}