{
  "type": "Feature",
  "properties": {
    "iso:country":"GB",
    "sg:address":"Cooks Lodge Farm, Forest Road, Enderby",
    "sg:city":"Leicester",
    "sg:classifiers":[
        {
            "category":"Farming",
            "subcategory":"Livestock Farm",
            "type":"Manufacturing & Wholesale Goods"
        }
    ],
    "sg:postcode":"LE19 3LD",
    "sg:province":"Leicestershire",
    "sg:tags":[
        "others"
    ],
    "wof:name":"Brenda D Tunnock",
    "wof:placetype":"venue"
},
  "geometry": {"coordinates":[-1.2229,52.587379],"type":"Point"}
}