{
  "type": "Feature",
  "properties": {
    "addr:full":"57 Mansfield Rd Sheffield Derbyshire S12 2AJ",
    "addr:housenumber":"57",
    "addr:postcode":"s12 2aj",
    "addr:street":"Mansfield Rd",
    "iso:country":"GB",
    "sg:address":"57 Mansfield Rd",
    "sg:city":"Sheffield",
    "sg:classifiers":[
        {
            "category":"Shopping",
            "subcategory":"Beauty & Cosmetics",
            "type":"Retail Goods"
        }
    ],
    "sg:postcode":"S12 2AJ",
    "sg:province":"Derbyshire",
    "sg:tags":[
        "equipment",
        "supply",
        "hairdressing"
    ],
    "wof:name":"Embassy,the,",
    "wof:placetype":"venue"
},
  "geometry": {"coordinates":[-1.4185429811,53.3581542969],"type":"Point"}
}