{
  "type": "Feature",
  "properties": {
    "addr:full":"9 Auckland Way Hartlepool Durham TS26 0AN",
    "addr:housenumber":"9",
    "addr:postcode":"ts26 0an",
    "addr:street":"Auckland Way",
    "iso:country":"GB",
    "sg:address":"9 Auckland Way",
    "sg:city":"Hartlepool",
    "sg:classifiers":[
        {
            "category":"Professional",
            "subcategory":"Engineering",
            "type":"Services"
        }
    ],
    "sg:postcode":"TS26 0AN",
    "sg:province":"Durham",
    "sg:tags":[
        "engineer"
    ],
    "wof:name":"System & Technology Services Ltd.",
    "wof:placetype":"venue"
},
  "geometry": {"coordinates":[-1.253586,54.681892],"type":"Point"}
}