{
  "type": "Feature",
  "properties": {
    "addr:full":"8 Hemstead Rd London Greater London E17 3RL",
    "addr:housenumber":"8",
    "addr:postcode":"e17 3rl",
    "addr:street":"Hemstead Rd",
    "iso:country":"GB",
    "sg:address":"8 Hemstead Rd",
    "sg:city":"London",
    "sg:classifiers":[
        {
            "category":"Professional",
            "subcategory":"Business Services",
            "type":"Services"
        }
    ],
    "sg:phone":"+44 20 8520 4005",
    "sg:postcode":"E17 3RL",
    "sg:province":"Greater London",
    "sg:tags":[
        "import",
        "export",
        "agent"
    ],
    "wof:name":"Gexaco Export Ltd",
    "wof:placetype":"venue"
},
  "geometry": {"coordinates":[0.003302,51.591873],"type":"Point"}
}