{
  "type": "Feature",
  "properties": {
    "iso:country":"GB",
    "sg:address":"The Coach House, High Street, Alfriston",
    "sg:city":"Polegate",
    "sg:classifiers":[
        {
            "category":"Shopping",
            "subcategory":"Clothing, Apparel, & Fashions",
            "type":"Retail Goods"
        }
    ],
    "sg:phone":"+44 1323 871402",
    "sg:postcode":"BN26 5TD",
    "sg:province":"East Sussex",
    "sg:tags":[
        "ladieswear"
    ],
    "wof:name":"Belinda",
    "wof:placetype":"venue"
},
  "geometry": {"coordinates":[0.156761,50.806946],"type":"Point"}
}