{
  "type": "Feature",
  "properties": {
    "addr:full":"25 Boulton Rd Stevenage Hertfordshire SG1 4QX",
    "addr:housenumber":"25",
    "addr:postcode":"sg1 4qx",
    "addr:street":"Boulton Rd",
    "iso:country":"GB",
    "sg:address":"25 Boulton Rd",
    "sg:city":"Stevenage",
    "sg:classifiers":[
        {
            "category":"Building & Trades",
            "subcategory":"Construction",
            "type":"Services"
        }
    ],
    "sg:phone":"+44 1438 749182",
    "sg:postcode":"SG1 4QX",
    "sg:province":"Hertfordshire",
    "sg:tags":[
        "joinery"
    ],
    "wof:name":"H MCR (Holdings) Ltd",
    "wof:placetype":"venue"
},
  "geometry": {"coordinates":[-0.1686040014,51.9264373779],"type":"Point"}
}