{
  "type": "Feature",
  "properties": {
    "iso:country":"GB",
    "sg:address":"27 Toads Acre Mill Acre, Longstanton",
    "sg:city":"Cambridge",
    "sg:classifiers":[
        {
            "category":"Building & Trades",
            "subcategory":"Construction",
            "type":"Services"
        }
    ],
    "sg:phone":"+44 1954 789640",
    "sg:postcode":"CB4 5DF",
    "sg:province":"Cambridgeshire",
    "sg:tags":[
        "decorator",
        "painter"
    ],
    "wof:name":"Yellow Ladder Services",
    "wof:placetype":"venue"
},
  "geometry": {"coordinates":[0.04433,52.282825],"type":"Point"}
}