{
  "type": "Feature",
  "properties": {
    "addr:full":"12 Beaufort Av Blackpool Lancashire FY2 9HG",
    "addr:housenumber":"12",
    "addr:postcode":"fy2 9hg",
    "addr:street":"Beaufort Av",
    "iso:country":"GB",
    "sg:address":"12 Beaufort Av",
    "sg:city":"Blackpool",
    "sg:classifiers":[
        {
            "category":"Retail",
            "subcategory":"Veterinary Services",
            "type":"Services"
        }
    ],
    "sg:phone":"+44 1253 354801",
    "sg:postcode":"FY2 9HG",
    "sg:province":"Lancashire",
    "sg:tags":[
        "surgeon"
    ],
    "wof:name":"G M Proctor",
    "wof:placetype":"venue"
},
  "geometry": {"coordinates":[-3.0509479046,53.8508682251],"type":"Point"}
}