{
  "type": "Feature",
  "properties": {
    "addr:full":"Barrow Hill Rd Manchester Greater Manchester M8 8DB",
    "addr:postcode":"m8 8db",
    "addr:street":"Barrow Hill Rd",
    "iso:country":"GB",
    "sg:address":"Barrow Hill Rd",
    "sg:city":"Manchester",
    "sg:classifiers":[
        {
            "category":"Social Services",
            "subcategory":"Retirement Home",
            "type":"Services"
        }
    ],
    "sg:postcode":"M8 8DB",
    "sg:province":"Greater Manchester",
    "sg:tags":[
        "residential",
        "care"
    ],
    "wof:name":"Manchester Care Ltd",
    "wof:placetype":"venue"
},
  "geometry": {"coordinates":[-2.246839,53.499561],"type":"Point"}
}