{
  "type": "Feature",
  "properties": {
    "iso:country":"GB",
    "sg:address":"42 Lee High Road",
    "sg:city":"London",
    "sg:classifiers":[
        {
            "category":"Wholesale",
            "subcategory":"Medical Equipment & Supplies",
            "type":"Manufacturing & Wholesale Goods"
        }
    ],
    "sg:phone":"+44 20 8852 8602",
    "sg:postcode":"SE13 5PT",
    "sg:province":"Greater London",
    "sg:tags":[
        "aid",
        "hearing"
    ],
    "wof:name":"Amplivox-Ultratone Hearing Centre",
    "wof:placetype":"venue"
},
  "geometry": {"coordinates":[-0.005586,51.460762],"type":"Point"}
}