{
  "type": "Feature",
  "properties": {
    "addr:full":"6b Cluny Drive Edinburgh City of Edinburgh EH10 6DN",
    "addr:housenumber":"6b",
    "addr:postcode":"eh10 6dn",
    "addr:street":"Cluny Drive",
    "iso:country":"GB",
    "sg:address":"6b Cluny Drive",
    "sg:city":"Edinburgh",
    "sg:classifiers":[
        {
            "category":"Professional",
            "subcategory":"Computer Services",
            "type":"Services"
        }
    ],
    "sg:postcode":"EH10 6DN",
    "sg:province":"City of Edinburgh",
    "sg:tags":[
        "system",
        "software"
    ],
    "wof:name":"Paulatim Ltd",
    "wof:placetype":"venue"
},
  "geometry": {"coordinates":[-3.2067799568,55.9234199524],"type":"Point"}
}