{
  "type": "Feature",
  "properties": {
    "addr:full":"Ward Avenue Grays Essex RM17 5RW",
    "addr:postcode":"rm17 5rw",
    "addr:street":"Ward Avenue",
    "iso:country":"GB",
    "sg:address":"Ward Avenue",
    "sg:city":"Grays",
    "sg:classifiers":[
        {
            "category":"Education",
            "subcategory":"School",
            "type":"Public Place"
        }
    ],
    "sg:phone":"+44 1375 375826",
    "sg:postcode":"RM17 5RW",
    "sg:province":"Essex",
    "sg:tags":[
        "local",
        "authority"
    ],
    "wof:name":"St Thomas of Canterbury R C Primary School",
    "wof:placetype":"venue"
},
  "geometry": {"coordinates":[0.33372,51.486706],"type":"Point"}
}