{
  "type": "Feature",
  "properties": {
    "iso:country":"GB",
    "sg:address":"2 Long Road, Mistley",
    "sg:city":"Manningtree",
    "sg:classifiers":[
        {
            "category":"Social Services",
            "subcategory":"Retirement Home",
            "type":"Services"
        }
    ],
    "sg:postcode":"CO11 2HN",
    "sg:province":"Essex",
    "sg:tags":[
        "residential",
        "care"
    ],
    "wof:name":"Little Manor Residential Care Home",
    "wof:placetype":"venue"
},
  "geometry": {"coordinates":[1.061227,51.939354],"type":"Point"}
}