{
  "type": "Feature",
  "properties": {
    "addr:full":"110 Mill Street Liverpool Merseyside L8 5UB",
    "addr:housenumber":"110",
    "addr:postcode":"l8 5ub",
    "addr:street":"Mill Street",
    "iso:country":"GB",
    "sg:address":"110 Mill Street",
    "sg:city":"Liverpool",
    "sg:classifiers":[
        {
            "category":"Government",
            "subcategory":"Post Office",
            "type":"Public Place"
        }
    ],
    "sg:phone":"+44 151 707 8131",
    "sg:postcode":"L8 5UB",
    "sg:province":"Merseyside",
    "wof:name":"Mill Street Post Office",
    "wof:placetype":"venue"
},
  "geometry": {"coordinates":[-2.9742949009,53.3913726807],"type":"Point"}
}