{
  "type": "Feature",
  "properties": {
    "iso:country":"GB",
    "sg:address":"Craigendarroch Circle",
    "sg:city":"Ballater",
    "sg:classifiers":[
        {
            "category":"Shopping",
            "subcategory":"Antiques",
            "type":"Retail Goods"
        }
    ],
    "sg:phone":"+44 1224 585000",
    "sg:postcode":"AB35 5ZA",
    "sg:province":"Aberdeenshire",
    "wof:name":"John Bell of Aberdeen Ltd.",
    "wof:placetype":"venue"
},
  "geometry": {"coordinates":[-3.044505,57.051712],"type":"Point"}
}