{
  "type": "Feature",
  "properties": {
    "addr:full":"243a Brook St Birkenhead Merseyside CH41 3SE",
    "addr:housenumber":"243a",
    "addr:postcode":"ch41 3se",
    "addr:street":"Brook St",
    "iso:country":"GB",
    "sg:address":"243a Brook St",
    "sg:city":"Birkenhead",
    "sg:classifiers":[
        {
            "category":"Utilities",
            "subcategory":"Natural Gas",
            "type":"Services"
        }
    ],
    "sg:phone":"+44 151 200 0111",
    "sg:postcode":"CH41 3SE",
    "sg:province":"Merseyside",
    "sg:tags":[
        "injector",
        "diesel"
    ],
    "wof:name":"Car And Commercial Diesels Services",
    "wof:placetype":"venue"
},
  "geometry": {"coordinates":[-3.0282099247,53.3969955444],"type":"Point"}
}