{
  "type": "Feature",
  "properties": {
    "iso:country":"GB",
    "sg:address":"Unit 3 Market Street, Penkridge",
    "sg:city":"Stafford",
    "sg:classifiers":[
        {
            "category":"Shopping",
            "subcategory":"Thrift Store",
            "type":"Retail Goods"
        }
    ],
    "sg:phone":"+44 1785 712754",
    "sg:postcode":"ST19 5DH",
    "sg:province":"Shropshire",
    "sg:tags":[
        "shop",
        "charity"
    ],
    "wof:name":"Catherine House Hospice Shop",
    "wof:placetype":"venue"
},
  "geometry": {"coordinates":[-2.113714,52.724998],"type":"Point"}
}