{
  "type": "Feature",
  "properties": {
    "iso:country":"GB",
    "sg:address":"14 Westgate",
    "sg:city":"Peterborough",
    "sg:classifiers":[
        {
            "category":"Shopping",
            "subcategory":"Pharmacy",
            "type":"Retail Goods"
        }
    ],
    "sg:phone":"+44 1733 554319",
    "sg:postcode":"PE1 1RA",
    "sg:province":"Cambridgeshire",
    "sg:tags":[
        "pharmacist",
        "chemist"
    ],
    "wof:name":"Shrives Chemist",
    "wof:placetype":"venue"
},
  "geometry": {"coordinates":[-0.242749,52.574402],"type":"Point"}
}