{
  "type": "Feature",
  "properties": {
    "addr:full":"398 Coxford Road, Lordswood Southampton Hampshire SO16 5LL",
    "addr:housenumber":"398",
    "addr:postcode":"so16 5ll",
    "addr:street":"Coxford Road",
    "iso:country":"GB",
    "sg:address":"398 Coxford Road, Lordswood",
    "sg:city":"Southampton",
    "sg:classifiers":[
        {
            "category":"Food & Beverages",
            "subcategory":"Groceries & Convenience Stores",
            "type":"Retail Goods"
        }
    ],
    "sg:phone":"+44 23 8077 3712",
    "sg:postcode":"SO16 5LL",
    "sg:province":"Hampshire",
    "wof:name":"One Stop Community Stores Ltd.",
    "wof:placetype":"venue"
},
  "geometry": {"coordinates":[-1.4269690514,50.9407501221],"type":"Point"}
}