{
  "type": "Feature",
  "properties": {
    "addr:full":"Digby Road Sherborne Dorset DT9 3NW",
    "addr:postcode":"dt9 3nw",
    "addr:street":"Digby Road",
    "iso:country":"GB",
    "sg:address":"Digby Road",
    "sg:city":"Sherborne",
    "sg:classifiers":[
        {
            "category":"Manufacturing",
            "subcategory":"Building Materials",
            "type":"Manufacturing & Wholesale Goods"
        }
    ],
    "sg:phone":"+44 1935 813254",
    "sg:postcode":"DT9 3NW",
    "sg:province":"Dorset",
    "sg:tags":[
        "merchant",
        "builder"
    ],
    "wof:name":"Bradfords Building Supplies Ltd",
    "wof:placetype":"venue"
},
  "geometry": {"coordinates":[-2.515193,50.944576],"type":"Point"}
}