{
  "type": "Feature",
  "properties": {
    "addr:full":"24 Shearing Hill, Gedling Nottingham Nottinghamshire NG4 3GX",
    "addr:housenumber":"24",
    "addr:postcode":"ng4 3gx",
    "addr:street":"Shearing Hill",
    "iso:country":"GB",
    "sg:address":"24 Shearing Hill, Gedling",
    "sg:city":"Nottingham",
    "sg:classifiers":[
        {
            "category":"Farming",
            "subcategory":"Poultry Farm",
            "type":"Manufacturing & Wholesale Goods"
        }
    ],
    "sg:phone":"+44 115 961 9001",
    "sg:postcode":"NG4 3GX",
    "sg:province":"Nottinghamshire",
    "wof:name":"W F Horsepool & Son",
    "wof:placetype":"venue"
},
  "geometry": {"coordinates":[-1.074675,52.974136],"type":"Point"}
}