{
  "type": "Feature",
  "properties": {
    "iso:country":"GB",
    "sg:address":"15 Pine Drive, Blackwater",
    "sg:city":"Camberley",
    "sg:classifiers":[
        {
            "category":"Education",
            "subcategory":"Music School",
            "type":"Public Place"
        }
    ],
    "sg:phone":"+44 1276 504666",
    "sg:postcode":"GU17 9BG",
    "sg:province":"Hampshire",
    "wof:name":"Len Tyler Childrens Music School",
    "wof:placetype":"venue"
},
  "geometry": {"coordinates":[-0.776143,51.327122],"type":"Point"}
}