{
  "type": "Feature",
  "properties": {
    "iso:country":"GB",
    "sg:address":"The Shefford Business Centre, 71 Hitchin Road",
    "sg:city":"Shefford",
    "sg:classifiers":[
        {
            "category":"Manufacturing",
            "subcategory":"Lumber",
            "type":"Manufacturing & Wholesale Goods"
        }
    ],
    "sg:postcode":"SG17 5JB",
    "sg:province":"Bedfordshire",
    "sg:tags":[
        "importer",
        "merchants",
        "agent",
        "timber"
    ],
    "wof:name":"Boardcraft Ltd",
    "wof:placetype":"venue"
},
  "geometry": {"coordinates":[-0.334879,52.04134],"type":"Point"}
}