{
  "type": "Feature",
  "properties": {
    "iso:country":"GB",
    "sg:address":"M33 Lancaster Market Hall, Common Garden Street",
    "sg:city":"Lancaster",
    "sg:classifiers":[
        {
            "category":"Home & Garden",
            "subcategory":"Household Appliances",
            "type":"Retail Goods"
        }
    ],
    "sg:phone":"+44 1524 68257",
    "sg:postcode":"LA1 1XD",
    "sg:province":"Lancashire",
    "sg:tags":[
        "electrical"
    ],
    "wof:name":"The Hoover Shop",
    "wof:placetype":"venue"
},
  "geometry": {"coordinates":[-2.799029,54.044537],"type":"Point"}
}