{
  "type": "Feature",
  "properties": {
    "addr:full":"70 Winchmore Hill Road, Southgate London Greater London N14 6PX",
    "addr:housenumber":"70",
    "addr:postcode":"n14 6px",
    "addr:street":"Winchmore Hill Road",
    "iso:country":"GB",
    "sg:address":"70 Winchmore Hill Road, Southgate",
    "sg:city":"London",
    "sg:classifiers":[
        {
            "category":"Real Estate",
            "subcategory":"Architect",
            "type":"Services"
        }
    ],
    "sg:postcode":"N14 6PX",
    "sg:province":"Greater London",
    "wof:name":"Calamity Ltd",
    "wof:placetype":"venue"
},
  "geometry": {"coordinates":[-0.122228,51.634438],"type":"Point"}
}