{
  "type": "Feature",
  "properties": {
    "iso:country":"GB",
    "sg:address":"Athelstan Park",
    "sg:city":"Bodmin",
    "sg:classifiers":[
        {
            "category":"Education",
            "subcategory":"School",
            "type":"Public Place"
        }
    ],
    "sg:phone":"+44 1208 72526",
    "sg:postcode":"PL31 1DS",
    "sg:province":"Cornwall",
    "sg:tags":[
        "local",
        "authority"
    ],
    "wof:name":"St Petrocs Church of England Primary School",
    "wof:placetype":"venue"
},
  "geometry": {"coordinates":[-4.7107548714,50.4662399292],"type":"Point"}
}