{
  "type": "Feature",
  "properties": {
    "iso:country":"GB",
    "sg:address":"154 Station Street",
    "sg:city":"Burton-on-trent",
    "sg:classifiers":[
        {
            "category":"Personal",
            "type":"Services"
        }
    ],
    "sg:phone":"+44 1283 511157",
    "sg:postcode":"DE14 1BG",
    "sg:province":"Derbyshire",
    "sg:tags":[
        "wedding"
    ],
    "wof:name":"Karen Elizabeth Bridal Centre",
    "wof:placetype":"venue"
},
  "geometry": {"coordinates":[-1.635496974,52.8047904968],"type":"Point"}
}