{
  "type": "Feature",
  "properties": {
    "addr:full":"24 Arrad St Liverpool Merseyside L7 7BP",
    "addr:housenumber":"24",
    "addr:postcode":"l7 7bp",
    "addr:street":"Arrad St",
    "iso:country":"GB",
    "sg:address":"24 Arrad St",
    "sg:city":"Liverpool",
    "sg:classifiers":[
        {
            "category":"Building & Trades",
            "subcategory":"Construction",
            "type":"Services"
        }
    ],
    "sg:postcode":"L7 7BP",
    "sg:province":"Merseyside",
    "sg:tags":[
        "joiner",
        "carpenter"
    ],
    "wof:name":"Gregson,John,",
    "wof:placetype":"venue"
},
  "geometry": {"coordinates":[-2.9693949223,53.4025764465],"type":"Point"}
}