{
  "type": "Feature",
  "properties": {
    "addr:full":"17 Kirkgate Newark Nottinghamshire NG24 1AD",
    "addr:housenumber":"17",
    "addr:postcode":"ng24 1ad",
    "addr:street":"Kirkgate",
    "iso:country":"GB",
    "sg:address":"17 Kirkgate",
    "sg:city":"Newark",
    "sg:classifiers":[
        {
            "category":"Professional",
            "subcategory":"Business Services",
            "type":"Services"
        }
    ],
    "sg:postcode":"NG24 1AD",
    "sg:province":"Nottinghamshire",
    "sg:tags":[
        "tile",
        "stockist"
    ],
    "wof:name":"Wall Talk",
    "wof:placetype":"venue"
},
  "geometry": {"coordinates":[-0.8059409857,53.0767173767],"type":"Point"}
}