{
  "type": "Feature",
  "properties": {
    "iso:country":"GB",
    "sg:address":"Hayle Mill, Loose Valley",
    "sg:city":"Maidstone",
    "sg:classifiers":[
        {
            "category":"Building & Trades",
            "subcategory":"Plumbing",
            "type":"Services"
        }
    ],
    "sg:postcode":"ME15 6XQ",
    "sg:province":"Kent",
    "sg:tags":[
        "filtration",
        "system"
    ],
    "wof:name":"Puk Water Filtration Ltd.",
    "wof:placetype":"venue"
},
  "geometry": {"coordinates":[0.5155389905,51.2568359375],"type":"Point"}
}