{
  "type": "Feature",
  "properties": {
    "addr:full":"P O Box 75 Retford Nottinghamshire DN22 8YZ",
    "addr:housenumber":"box 75",
    "addr:postcode":"dn22 8yz",
    "addr:street":"P O",
    "iso:country":"GB",
    "sg:address":"P O Box 75",
    "sg:city":"Retford",
    "sg:classifiers":[
        {
            "category":"Military Area",
            "subcategory":"Air Force Base",
            "type":"Public Place"
        }
    ],
    "sg:phone":"+44 1777 838134",
    "sg:postcode":"DN22 8YZ",
    "sg:province":"Nottinghamshire",
    "sg:tags":[
        "water",
        "treatment"
    ],
    "wof:name":"State of the Art (Technical Services) Ltd.",
    "wof:placetype":"venue"
},
  "geometry": {"coordinates":[-1.026609,53.323021],"type":"Point"}
}