{
  "type": "Feature",
  "properties": {
    "addr:full":"744 Aikenhead Rd Glasgow Glasgow City G42 0NL",
    "addr:housenumber":"744",
    "addr:postcode":"g42 0nl",
    "addr:street":"Aikenhead Rd",
    "iso:country":"GB",
    "sg:address":"744 Aikenhead Rd",
    "sg:city":"Glasgow",
    "sg:classifiers":[
        {
            "category":"Government",
            "subcategory":"Police Station",
            "type":"Public Place"
        }
    ],
    "sg:phone":"+44 141 532 4900",
    "sg:postcode":"G42 0NL",
    "sg:province":"Glasgow City",
    "sg:tags":[
        "support"
    ],
    "wof:name":"Strathclyde Police",
    "wof:placetype":"venue"
},
  "geometry": {"coordinates":[-4.248569,55.832481],"type":"Point"}
}