{
  "type": "Feature",
  "properties": {
    "iso:country":"GB",
    "sg:address":"Mendip Court, Chatfield Rd",
    "sg:city":"Battersea",
    "sg:classifiers":[
        {
            "category":"Travel",
            "subcategory":"Travel Agent",
            "type":"Entertainment"
        }
    ],
    "sg:phone":"+44 20 7924 1200",
    "sg:postcode":"SW11 3UZ",
    "sg:province":"Greater London",
    "wof:name":"Riverside Travel",
    "wof:placetype":"venue"
},
  "geometry": {"coordinates":[-0.181369,51.46542],"type":"Point"}
}