{
  "type": "Feature",
  "properties": {
    "addr:full":"34 Greenfinch Close Eastleigh Hampshire SO50 9JN",
    "addr:housenumber":"34",
    "addr:postcode":"so50 9jn",
    "addr:street":"Greenfinch Close",
    "iso:country":"GB",
    "sg:address":"34 Greenfinch Close",
    "sg:city":"Eastleigh",
    "sg:classifiers":[
        {
            "category":"Building & Trades",
            "subcategory":"Plumbing",
            "type":"Services"
        }
    ],
    "sg:phone":"+44 23 8061 2616",
    "sg:postcode":"SO50 9JN",
    "sg:province":"Hampshire",
    "sg:tags":[
        "heating"
    ],
    "wof:name":"M C Butt",
    "wof:placetype":"venue"
},
  "geometry": {"coordinates":[-1.377092,50.962795],"type":"Point"}
}