{
  "type": "Feature",
  "properties": {
    "iso:country":"GB",
    "sg:address":"108 Aylesbury Road, Bierton",
    "sg:city":"Aylesbury",
    "sg:classifiers":[
        {
            "category":"Home & Garden",
            "subcategory":"Carpets & Floor Coverings",
            "type":"Retail Goods"
        }
    ],
    "sg:phone":"+44 1296 436834",
    "sg:postcode":"HP22 5DL",
    "sg:province":"Buckinghamshire",
    "sg:tags":[
        "cleaner",
        "upholstery"
    ],
    "wof:name":"N S P Cleaning",
    "wof:placetype":"venue"
},
  "geometry": {"coordinates":[-0.783278,51.833263],"type":"Point"}
}