{
  "type": "Feature",
  "properties": {
    "iso:country":"GB",
    "sg:address":"176a Station St",
    "sg:city":"Burton On Trent",
    "sg:classifiers":[
        {
            "category":"Personal",
            "subcategory":"Beauty Salon",
            "type":"Services"
        }
    ],
    "sg:phone":"+44 1283 566227",
    "sg:postcode":"DE14 1BN",
    "sg:province":"Derbyshire",
    "sg:tags":[
        "unisex",
        "hairdresser"
    ],
    "wof:name":"Keith Hall",
    "wof:placetype":"venue"
},
  "geometry": {"coordinates":[-1.632907033,52.8038864136],"type":"Point"}
}