{
  "type": "Feature",
  "properties": {
    "addr:full":"Unit 6 Headfield Mills, Savile Rd Dewsbury West Yorkshire WF12 9LQ",
    "addr:housenumber":"unit 6",
    "addr:postcode":"wf12 9lq",
    "addr:street":"Headfield Mills Savile Rd",
    "iso:country":"GB",
    "sg:address":"Unit 6 Headfield Mills, Savile Rd",
    "sg:city":"Dewsbury",
    "sg:classifiers":[
        {
            "category":"Retail",
            "subcategory":"Auto Repair",
            "type":"Services"
        }
    ],
    "sg:postcode":"WF12 9LQ",
    "sg:province":"West Yorkshire",
    "sg:tags":[
        "modification",
        "garage"
    ],
    "wof:name":"Bolland,Stephen,",
    "wof:placetype":"venue"
},
  "geometry": {"coordinates":[-1.632304,53.682354],"type":"Point"}
}