{
  "type": "Feature",
  "properties": {
    "addr:full":"6-10 Market Square, Wellington Telford Shropshire TF1 1HQ",
    "addr:housenumber":"6-10",
    "addr:postcode":"tf1 1hq",
    "addr:street":"Market Square",
    "iso:country":"GB",
    "sg:address":"6-10 Market Square, Wellington",
    "sg:city":"Telford",
    "sg:classifiers":[
        {
            "category":"Shopping",
            "subcategory":"News",
            "type":"Retail Goods"
        }
    ],
    "sg:phone":"+44 1952 247880",
    "sg:postcode":"TF1 1HQ",
    "sg:province":"Shropshire",
    "sg:tags":[
        "newsagent"
    ],
    "wof:name":"John Menzies (Uk)",
    "wof:placetype":"venue"
},
  "geometry": {"coordinates":[-2.5190730095,52.7012214661],"type":"Point"}
}