{
  "type": "Feature",
  "properties": {
    "addr:full":"13 Heath Lane, Oldswinford Stourbridge Staffordshire DY8 1RF",
    "addr:housenumber":"13",
    "addr:postcode":"dy8 1rf",
    "addr:street":"Heath Lane",
    "iso:country":"GB",
    "sg:address":"13 Heath Lane, Oldswinford",
    "sg:city":"Stourbridge",
    "sg:classifiers":[
        {
            "category":"Health Services",
            "subcategory":"Dentist",
            "type":"Services"
        }
    ],
    "sg:phone":"+44 1384 440219",
    "sg:postcode":"DY8 1RF",
    "sg:province":"Staffordshire",
    "wof:name":"R H Moore Dental Surgeon",
    "wof:placetype":"venue"
},
  "geometry": {"coordinates":[-2.141356,52.448463],"type":"Point"}
}