{
  "type": "Feature",
  "properties": {
    "iso:country":"GB",
    "sg:address":"6 Marsh Farm Road, South Woodham Ferrers",
    "sg:city":"Chelmsford",
    "sg:classifiers":[
        {
            "category":"Building & Trades",
            "subcategory":"Construction",
            "type":"Services"
        }
    ],
    "sg:postcode":"CM3 5WP",
    "sg:province":"Essex",
    "sg:tags":[
        "builder"
    ],
    "wof:name":"P Bines",
    "wof:placetype":"venue"
},
  "geometry": {"coordinates":[0.6131280065,51.635345459],"type":"Point"}
}