{
  "type": "Feature",
  "properties": {
    "addr:full":"343 Fleet Rd Fleet Dorset GU13 8QJ",
    "addr:housenumber":"343",
    "addr:postcode":"gu13 8qj",
    "addr:street":"Fleet Rd",
    "iso:country":"GB",
    "sg:address":"343 Fleet Rd",
    "sg:city":"Fleet",
    "sg:classifiers":[
        {
            "category":"Restaurant",
            "type":"Food & Drink"
        }
    ],
    "sg:phone":"+44 1252 616367",
    "sg:postcode":"GU13 8QJ",
    "sg:province":"Dorset",
    "wof:name":"Bridge Restaurant",
    "wof:placetype":"venue"
},
  "geometry": {"coordinates":[-0.8456689715,51.2782592773],"type":"Point"}
}