{
  "type": "Feature",
  "properties": {
    "iso:country":"GB",
    "sg:address":"106 New Road, Sutton Bridge",
    "sg:city":"Spalding",
    "sg:classifiers":[
        {
            "category":"Building & Trades",
            "subcategory":"Cleaning & Sanitation",
            "type":"Services"
        }
    ],
    "sg:phone":"+44 1406 350803",
    "sg:postcode":"PE12 9QA",
    "sg:province":"Cambridgeshire",
    "sg:tags":[
        "dry",
        "control",
        "damp",
        "rot"
    ],
    "wof:name":"Richard John Morley",
    "wof:placetype":"venue"
},
  "geometry": {"coordinates":[0.192369,52.773735],"type":"Point"}
}