{
  "type": "Feature",
  "properties": {
    "iso:country":"GB",
    "sg:address":"127 Rickerscote Road",
    "sg:city":"Stafford",
    "sg:classifiers":[
        {
            "category":"Utilities",
            "subcategory":"Natural Gas",
            "type":"Services"
        }
    ],
    "sg:phone":"+44 1785 251173",
    "sg:postcode":"ST17 4HB",
    "sg:province":"Staffordshire",
    "sg:tags":[
        "control",
        "energy",
        "management",
        "system"
    ],
    "wof:name":"Browns of Stafford",
    "wof:placetype":"venue"
},
  "geometry": {"coordinates":[-2.1115789413,52.7846107483],"type":"Point"}
}