{
  "type": "Feature",
  "properties": {
    "iso:country":"GB",
    "sg:address":"The Square, Exbourne",
    "sg:city":"Okehampton",
    "sg:classifiers":[
        {
            "category":"Shopping",
            "subcategory":"Department Store",
            "type":"Retail Goods"
        }
    ],
    "sg:phone":"+44 1837 851225",
    "sg:postcode":"EX20 3RP",
    "sg:province":"Devon",
    "wof:name":"Exbourne Post Office",
    "wof:placetype":"venue"
},
  "geometry": {"coordinates":[-3.9854340553,50.7999763489],"type":"Point"}
}