{
  "type": "Feature",
  "properties": {
    "iso:country":"GB",
    "sg:address":"Ansdell Road",
    "sg:city":"Rochdale",
    "sg:classifiers":[
        {
            "category":"Shopping",
            "subcategory":"Department Store",
            "type":"Retail Goods"
        },
        {
            "category":"Government",
            "subcategory":"Post Office",
            "type":"Public Place"
        }
    ],
    "sg:phone":"+44 1706 644302",
    "sg:postcode":"OL16 4TT",
    "sg:province":"Lancashire",
    "wof:name":"TURF HILL POST OFFICE",
    "wof:placetype":"venue"
},
  "geometry": {"coordinates":[-2.1369390488,53.6030349731],"type":"Point"}
}