{
  "type": "Feature",
  "properties": {
    "addr:full":"258 Whitefields Road Solihull West Midlands B91 3PA",
    "addr:housenumber":"258",
    "addr:postcode":"b91 3pa",
    "addr:street":"Whitefields Road",
    "iso:country":"GB",
    "sg:address":"258 Whitefields Road",
    "sg:city":"Solihull",
    "sg:classifiers":[
        {
            "category":"Professional",
            "subcategory":"Management & Consulting",
            "type":"Services"
        }
    ],
    "sg:phone":"+44 121 709 1040",
    "sg:postcode":"B91 3PA",
    "sg:province":"West Midlands",
    "sg:tags":[
        "consultant",
        "business"
    ],
    "wof:name":"Synergy Management Services",
    "wof:placetype":"venue"
},
  "geometry": {"coordinates":[-1.793352,52.402473],"type":"Point"}
}