{
  "type": "Feature",
  "properties": {
    "addr:full":"High Street, Waresley Sandy Bedfordshire SG19 3BS",
    "addr:postcode":"sg19 3bs",
    "addr:street":"High Street",
    "iso:country":"GB",
    "sg:address":"High Street, Waresley",
    "sg:city":"Sandy",
    "sg:classifiers":[
        {
            "category":"Farming",
            "subcategory":"Livestock Farm",
            "type":"Manufacturing & Wholesale Goods"
        }
    ],
    "sg:phone":"+44 1767 650363",
    "sg:postcode":"SG19 3BS",
    "sg:province":"Bedfordshire",
    "sg:tags":[
        "others"
    ],
    "wof:name":"Waresley Farms",
    "wof:placetype":"venue"
},
  "geometry": {"coordinates":[-0.17394,52.175282],"type":"Point"}
}