{
  "type": "Feature",
  "properties": {
    "addr:full":"657 Ecclesall Road Sheffield Derbyshire S11 8PT",
    "addr:housenumber":"657",
    "addr:postcode":"s11 8pt",
    "addr:street":"Ecclesall Road",
    "iso:country":"GB",
    "sg:address":"657 Ecclesall Road",
    "sg:city":"Sheffield",
    "sg:classifiers":[
        {
            "category":"Fast Food",
            "type":"Food & Drink"
        }
    ],
    "sg:phone":"+44 114 267 6122",
    "sg:postcode":"S11 8PT",
    "sg:province":"Derbyshire",
    "sg:tags":[
        "away",
        "meal",
        "outlet",
        "take"
    ],
    "wof:name":"Woody's Sandwich Bar",
    "wof:placetype":"venue"
},
  "geometry": {"coordinates":[-1.501093,53.367859],"type":"Point"}
}