{
  "type": "Feature",
  "properties": {
    "addr:full":"Unit 6 Black Diamond Indust Estate Chester Cheshire CH1 3EX",
    "addr:housenumber":"unit 6",
    "addr:postcode":"ch1 3ex",
    "addr:street":"Indust Estate",
    "iso:country":"GB",
    "sg:address":"Unit 6 Black Diamond Indust Estate",
    "sg:city":"Chester",
    "sg:classifiers":[
        {
            "category":"Professional",
            "type":"Services"
        }
    ],
    "sg:phone":"+44 1244 311634",
    "sg:postcode":"CH1 3EX",
    "sg:province":"Cheshire",
    "sg:tags":[
        "caterer"
    ],
    "wof:name":"All Seasons Catering",
    "wof:placetype":"venue"
},
  "geometry": {"coordinates":[-2.8868689537,53.1978759766],"type":"Point"}
}