{
  "type": "Feature",
  "properties": {
    "iso:country":"GB",
    "sg:address":"36 West Bute Street",
    "sg:city":"Cardiff",
    "sg:classifiers":[
        {
            "category":"Professional",
            "subcategory":"Lawyer & Legal Services",
            "type":"Services"
        }
    ],
    "sg:phone":"+44 29 2046 5959",
    "sg:postcode":"CF10 5UA",
    "sg:province":"Cardiff",
    "sg:tags":[
        "solicitor"
    ],
    "wof:name":"Cartwrights Adams & Black",
    "wof:placetype":"venue"
},
  "geometry": {"coordinates":[-3.166679,51.466282],"type":"Point"}
}