{
  "type": "Feature",
  "properties": {
    "iso:country":"GB",
    "sg:address":"6 Market Place, Caistor",
    "sg:city":"Market Rasen",
    "sg:classifiers":[
        {
            "category":"Professional",
            "subcategory":"Lawyer & Legal Services",
            "type":"Services"
        }
    ],
    "sg:phone":"+44 1472 851224",
    "sg:postcode":"LN7 6TL",
    "sg:province":"Lincolnshire",
    "sg:tags":[
        "solicitor"
    ],
    "wof:name":"Bates & Mountain",
    "wof:placetype":"venue"
},
  "geometry": {"coordinates":[-0.31519,53.496895],"type":"Point"}
}