{
  "type": "Feature",
  "properties": {
    "iso:country":"GB",
    "sg:address":"99 Station Road, Lower Stondon",
    "sg:city":"Henlow",
    "sg:classifiers":[
        {
            "category":"Building & Trades",
            "subcategory":"Pest Control",
            "type":"Services"
        }
    ],
    "sg:postcode":"SG16 6JJ",
    "sg:province":"Bedfordshire",
    "sg:tags":[
        "woodworm"
    ],
    "wof:name":"E F & J F Thompson",
    "wof:placetype":"venue"
},
  "geometry": {"coordinates":[-0.3139440119,52.0060119629],"type":"Point"}
}