{
  "type": "Feature",
  "properties": {
    "iso:country":"GB",
    "sg:address":"20 Trapwood Close, Eccleston",
    "sg:city":"St Helens",
    "sg:classifiers":[
        {
            "category":"Social Services",
            "subcategory":"Adult Care",
            "type":"Services"
        },
        {
            "category":"Government",
            "subcategory":"Office",
            "type":"Public Place"
        }
    ],
    "sg:phone":"+44 1744 753836",
    "sg:postcode":"WA10 5NQ",
    "sg:province":"Merseyside",
    "sg:tags":[
        "housing",
        "local",
        "sheltered"
    ],
    "wof:name":"Pinfold Farm Sheltered Housing",
    "wof:placetype":"venue"
},
  "geometry": {"coordinates":[-2.775957,53.449947],"type":"Point"}
}