{
  "type": "Feature",
  "properties": {
    "addr:full":"The Quay Calstock Cornwall PL18 9QA",
    "addr:postcode":"pl18 9qa",
    "addr:street":"The Quay",
    "iso:country":"GB",
    "sg:address":"The Quay",
    "sg:city":"Calstock",
    "sg:classifiers":[
        {
            "category":"Restaurant",
            "type":"Food & Drink"
        }
    ],
    "sg:phone":"+44 1822 832683",
    "sg:postcode":"PL18 9QA",
    "sg:province":"Cornwall",
    "wof:name":"The Old Bakehouse Bistro",
    "wof:placetype":"venue"
},
  "geometry": {"coordinates":[-4.2053861618,50.4961357117],"type":"Point"}
}