{
  "type": "Feature",
  "properties": {
    "addr:full":"5 Millbridge Close Stoke-on-trent Staffordshire ST3 7US",
    "addr:housenumber":"5",
    "addr:postcode":"st3 7us",
    "addr:street":"Millbridge Close",
    "iso:country":"GB",
    "sg:address":"5 Millbridge Close",
    "sg:city":"Stoke-on-trent",
    "sg:classifiers":[
        {
            "category":"Home & Garden",
            "subcategory":"Garden Supply",
            "type":"Retail Goods"
        }
    ],
    "sg:postcode":"ST3 7US",
    "sg:province":"Staffordshire",
    "sg:tags":[
        "sand",
        "gravel"
    ],
    "wof:name":"J Whitfield & Son",
    "wof:placetype":"venue"
},
  "geometry": {"coordinates":[-2.096546,52.962971],"type":"Point"}
}