{
  "type": "Feature",
  "properties": {
    "iso:country":"GB",
    "sg:address":"The Oaks, Old Nab Rd, Langho",
    "sg:city":"Blackburn",
    "sg:classifiers":[
        {
            "category":"Building & Trades",
            "subcategory":"Cleaning & Sanitation",
            "type":"Services"
        }
    ],
    "sg:phone":"+44 1254 246555",
    "sg:postcode":"BB6 8DY",
    "sg:province":"Lancashire",
    "sg:tags":[
        "commercial"
    ],
    "wof:name":"Ids Blind Cleaning",
    "wof:placetype":"venue"
},
  "geometry": {"coordinates":[-2.451579,53.8018],"type":"Point"}
}