{
  "type": "Feature",
  "properties": {
    "iso:country":"GB",
    "sg:address":"50 Ipswich St",
    "sg:city":"Stowmarket",
    "sg:classifiers":[
        {
            "category":"Retail",
            "subcategory":"Laundry & Dry Cleaning",
            "type":"Services"
        }
    ],
    "sg:phone":"+44 1449 612762",
    "sg:postcode":"IP14 1AD",
    "sg:province":"Suffolk",
    "sg:tags":[
        "alteration"
    ],
    "wof:name":"Johnsons The Cleaners",
    "wof:placetype":"venue"
},
  "geometry": {"coordinates":[0.996892,52.186852],"type":"Point"}
}