{
  "type": "Feature",
  "properties": {
    "addr:full":"Riverside, Mill Lane, Taplow Maidenhead Berkshire SL6 0AA",
    "addr:postcode":"sl6 0aa",
    "addr:street":"Mill Lane",
    "iso:country":"GB",
    "sg:address":"Riverside, Mill Lane, Taplow",
    "sg:city":"Maidenhead",
    "sg:classifiers":[
        {
            "category":"Professional",
            "subcategory":"Computer Services",
            "type":"Services"
        }
    ],
    "sg:phone":"+44 1628 637777",
    "sg:postcode":"SL6 0AA",
    "sg:province":"Berkshire",
    "sg:tags":[
        "system",
        "software"
    ],
    "wof:name":"Softwave Marine Computer Navigation",
    "wof:placetype":"venue"
},
  "geometry": {"coordinates":[-0.687149,51.532169],"type":"Point"}
}