{
  "type": "Feature",
  "properties": {
    "iso:country":"GB",
    "sg:address":"201a Middlewich Road",
    "sg:city":"Northwich",
    "sg:classifiers":[
        {
            "category":"Autos & Motor Vehicles",
            "subcategory":"Automobile Sales",
            "type":"Retail Goods"
        }
    ],
    "sg:phone":"+44 1606 40726",
    "sg:postcode":"CW9 7DN",
    "sg:province":"Cheshire",
    "sg:tags":[
        "car"
    ],
    "wof:name":"Sovereign Car Centre",
    "wof:placetype":"venue"
},
  "geometry": {"coordinates":[-2.4874899387,53.2572441101],"type":"Point"}
}