{
  "type": "Feature",
  "properties": {
    "iso:country":"GB",
    "sg:address":"159 Long Lane",
    "sg:city":"Chester",
    "sg:classifiers":[
        {
            "category":"Government",
            "subcategory":"Post Office",
            "type":"Public Place"
        }
    ],
    "sg:postcode":"CH2 1JF",
    "sg:province":"Cheshire",
    "wof:name":"Upton Heath Post Office & Express Shop",
    "wof:placetype":"venue"
},
  "geometry": {"coordinates":[-2.879958,53.219627],"type":"Point"}
}