{
  "type": "Feature",
  "properties": {
    "addr:full":"Station Garage, Worth Park Avenue, Three Bridges Crawley Surrey RH10 7AB",
    "addr:postcode":"rh10 7ab",
    "addr:street":"Park Avenue",
    "iso:country":"GB",
    "sg:address":"Station Garage, Worth Park Avenue, Three Bridges",
    "sg:city":"Crawley",
    "sg:classifiers":[
        {
            "category":"Autos & Motor Vehicles",
            "subcategory":"Automobile Sales",
            "type":"Retail Goods"
        }
    ],
    "sg:phone":"+44 1293 613361",
    "sg:postcode":"RH10 7AB",
    "sg:province":"Surrey",
    "sg:tags":[
        "car"
    ],
    "wof:name":"Otters Ford",
    "wof:placetype":"venue"
},
  "geometry": {"coordinates":[-0.143459,51.112083],"type":"Point"}
}