{
  "type": "Feature",
  "properties": {
    "addr:full":"37 Camden High St, London Greater London NW1 7JE",
    "addr:housenumber":"37",
    "addr:postcode":"nw1 7je",
    "addr:street":"Camden High St",
    "iso:country":"GB",
    "sg:address":"37 Camden High St,",
    "sg:city":"London",
    "sg:classifiers":[
        {
            "category":"Professional",
            "subcategory":"Art Services",
            "type":"Services"
        }
    ],
    "sg:postcode":"NW1 7JE",
    "sg:province":"Greater London",
    "sg:tags":[
        "photographer"
    ],
    "wof:name":"Space Studios",
    "wof:placetype":"venue"
},
  "geometry": {"coordinates":[-0.139464,51.535343],"type":"Point"}
}