{
  "type": "Feature",
  "properties": {
    "iso:country":"GB",
    "sg:address":"P O Box 29",
    "sg:city":"Torquay",
    "sg:classifiers":[
        {
            "category":"Travel",
            "subcategory":"Travel Agent",
            "type":"Entertainment"
        }
    ],
    "sg:phone":"+44 500 404044",
    "sg:postcode":"TQ2 5YW",
    "sg:province":"Devon",
    "sg:tags":[
        "hotel",
        "agency",
        "booking"
    ],
    "wof:name":"Keylink Holidays",
    "wof:placetype":"venue"
},
  "geometry": {"coordinates":[-3.5385289192,50.4680213928],"type":"Point"}
}