{
  "type": "Feature",
  "properties": {
    "addr:full":"124 Fairview Circle, Danestone Aberdeen Aberdeen City AB22 8YR",
    "addr:housenumber":"124",
    "addr:postcode":"ab22 8yr",
    "addr:street":"Fairview Circle",
    "iso:country":"GB",
    "sg:address":"124 Fairview Circle, Danestone",
    "sg:city":"Aberdeen",
    "sg:classifiers":[
        {
            "category":"Building & Trades",
            "subcategory":"Construction",
            "type":"Services"
        }
    ],
    "sg:phone":"+44 1224 825002",
    "sg:postcode":"AB22 8YR",
    "sg:province":"Aberdeen City",
    "sg:tags":[
        "joinery",
        "joiner",
        "carpenter",
        "carpentry"
    ],
    "wof:name":"A J P Moir & Sons Ltd.",
    "wof:placetype":"venue"
},
  "geometry": {"coordinates":[-2.1459980011,57.1821250916],"type":"Point"}
}