{
  "type": "Feature",
  "properties": {
    "iso:country":"GB",
    "sg:address":"78 Upper St James Street",
    "sg:city":"Newport",
    "sg:classifiers":[
        {
            "category":"Food & Beverages",
            "subcategory":"Meat & Fish",
            "type":"Retail Goods"
        }
    ],
    "sg:phone":"+44 1983 523939",
    "sg:postcode":"PO30 1LG",
    "sg:province":"Isle of Wight",
    "sg:tags":[
        "butcher"
    ],
    "wof:name":"Lanes Butchers",
    "wof:placetype":"venue"
},
  "geometry": {"coordinates":[-1.2952879667,50.6975402832],"type":"Point"}
}