{
  "type": "Feature",
  "properties": {
    "addr:full":"Rumah Saya, Oxcroft Bank, Shepeau Stow Spalding Cambridgeshire PE12 0TY",
    "addr:postcode":"pe12 0ty",
    "addr:street":"Spalding",
    "iso:country":"GB",
    "sg:address":"Rumah Saya, Oxcroft Bank, Shepeau Stow",
    "sg:city":"Spalding",
    "sg:classifiers":[
        {
            "category":"Professional",
            "subcategory":"Engineering",
            "type":"Services"
        }
    ],
    "sg:postcode":"PE12 0TY",
    "sg:province":"Cambridgeshire",
    "sg:tags":[
        "contractor",
        "electrical",
        "engineer"
    ],
    "wof:name":"Pals Electrical",
    "wof:placetype":"venue"
},
  "geometry": {"coordinates":[-0.0773399994,52.6874198914],"type":"Point"}
}