{
  "type": "Feature",
  "properties": {
    "iso:country":"GB",
    "sg:address":"Care Of Beauherne County Primary, School, City View",
    "sg:city":"Canterbury",
    "sg:classifiers":[
        {
            "category":"Farming",
            "subcategory":"Nursery",
            "type":"Manufacturing & Wholesale Goods"
        },
        {
            "category":"Education",
            "subcategory":"Preschool",
            "type":"Public Place"
        }
    ],
    "sg:phone":"+44 1227 784694",
    "sg:postcode":"CT2 8PT",
    "sg:province":"Kent",
    "sg:tags":[
        "school",
        "creche"
    ],
    "wof:name":"City View Pre School",
    "wof:placetype":"venue"
},
  "geometry": {"coordinates":[1.05932,51.277321],"type":"Point"}
}