{
  "type": "Feature",
  "properties": {
    "addr:full":"64 East March St Kirkcaldy Fife KY1 2DP",
    "addr:housenumber":"64",
    "addr:postcode":"ky1 2dp",
    "addr:street":"East March St",
    "iso:country":"GB",
    "sg:address":"64 East March St",
    "sg:city":"Kirkcaldy",
    "sg:classifiers":[
        {
            "category":"Manufacturing",
            "subcategory":"Building Materials",
            "type":"Manufacturing & Wholesale Goods"
        }
    ],
    "sg:phone":"+44 1592 652626",
    "sg:postcode":"KY1 2DP",
    "sg:province":"Fife",
    "sg:tags":[
        "shutter",
        "supp",
        "door"
    ],
    "wof:name":"Garage Door Discount Centre",
    "wof:placetype":"venue"
},
  "geometry": {"coordinates":[-3.140289,56.127625],"type":"Point"}
}