{
  "type": "Feature",
  "properties": {
    "iso:country":"GB",
    "sg:address":"55-57 Delta Dr",
    "sg:city":"Musselburgh",
    "sg:classifiers":[
        {
            "category":"Food & Beverages",
            "subcategory":"Supermarket",
            "type":"Retail Goods"
        }
    ],
    "sg:phone":"+44 131 665 1319",
    "sg:postcode":"EH21 8HL",
    "sg:province":"City of Edinburgh",
    "wof:name":"Raja Food Store",
    "wof:placetype":"venue"
},
  "geometry": {"coordinates":[-3.090819,55.935131],"type":"Point"}
}