{
  "type": "Feature",
  "properties": {
    "iso:country":"GB",
    "sg:address":"Unit, 7 Myrtle Parade",
    "sg:city":"Liverpool",
    "sg:classifiers":[
        {
            "category":"Restaurant",
            "type":"Food & Drink"
        }
    ],
    "sg:phone":"+44 151 709 7225",
    "sg:postcode":"L7 7EL",
    "sg:province":"Merseyside",
    "sg:tags":[
        "greek",
        "-"
    ],
    "wof:name":"Eureka",
    "wof:placetype":"venue"
},
  "geometry": {"coordinates":[-2.965381,53.400604],"type":"Point"}
}