{
  "type": "Feature",
  "properties": {
    "iso:country":"GB",
    "sg:address":"4 Edgehill Close",
    "sg:city":"Basingstoke",
    "sg:classifiers":[
        {
            "category":"Shopping",
            "subcategory":"Florist",
            "type":"Retail Goods"
        }
    ],
    "sg:postcode":"RG22 5AB",
    "sg:province":"Hampshire",
    "wof:name":"The Florist Workshop",
    "wof:placetype":"venue"
},
  "geometry": {"coordinates":[-1.127673,51.259335],"type":"Point"}
}