{
  "type": "Feature",
  "properties": {
    "addr:full":"22 Hainge Road, Tividale Smethwick West Midlands B69 2NQ",
    "addr:housenumber":"22",
    "addr:postcode":"b69 2nq",
    "addr:street":"Hainge Road Tividale Smethwick",
    "iso:country":"GB",
    "sg:address":"22 Hainge Road, Tividale",
    "sg:city":"Smethwick",
    "sg:classifiers":[
        {
            "category":"Building & Trades",
            "subcategory":"Construction",
            "type":"Services"
        }
    ],
    "sg:phone":"+44 121 557 1622",
    "sg:postcode":"B69 2NQ",
    "sg:province":"West Midlands",
    "sg:tags":[
        "window",
        "sale"
    ],
    "wof:name":"Milcote Windows Ltd.",
    "wof:placetype":"venue"
},
  "geometry": {"coordinates":[-2.039055,52.511959],"type":"Point"}
}