{
  "type": "Feature",
  "properties": {
    "addr:full":"Stamford Lodge, Tarvin Road Chester Cheshire CH3 5DH",
    "addr:postcode":"ch3 5dh",
    "addr:street":"Tarvin Road",
    "iso:country":"GB",
    "sg:address":"Stamford Lodge, Tarvin Road",
    "sg:city":"Chester",
    "sg:classifiers":[
        {
            "category":"Manufacturing",
            "subcategory":"Building Materials",
            "type":"Manufacturing & Wholesale Goods"
        }
    ],
    "sg:postcode":"CH3 5DH",
    "sg:province":"Cheshire",
    "sg:tags":[
        "tarmac",
        "asphalt"
    ],
    "wof:name":"Bryan Asphalt",
    "wof:placetype":"venue"
},
  "geometry": {"coordinates":[-2.8496739864,53.1937141418],"type":"Point"}
}