{
  "type": "Feature",
  "properties": {
    "iso:country":"GB",
    "sg:address":"53 Ravensdale, Great Clacton",
    "sg:city":"Clacton-on-sea",
    "sg:classifiers":[
        {
            "category":"Shopping",
            "subcategory":"Used Merchandise",
            "type":"Retail Goods"
        }
    ],
    "sg:postcode":"CO15 4QH",
    "sg:province":"Essex",
    "sg:tags":[
        "shop",
        "second-hand"
    ],
    "wof:name":"Just Right",
    "wof:placetype":"venue"
},
  "geometry": {"coordinates":[1.15575,51.806019],"type":"Point"}
}