{
  "type": "Feature",
  "properties": {
    "addr:full":"241 Osmaston Pk Rd Derby Derbyshire DE24 8BT",
    "addr:housenumber":"241",
    "addr:postcode":"de24 8bt",
    "addr:street":"Osmaston Pk Rd",
    "iso:country":"GB",
    "sg:address":"241 Osmaston Pk Rd",
    "sg:city":"Derby",
    "sg:classifiers":[
        {
            "category":"Arts & Performance",
            "subcategory":"Music",
            "type":"Entertainment"
        }
    ],
    "sg:postcode":"DE24 8BT",
    "sg:province":"Derbyshire",
    "sg:tags":[
        "mobile",
        "disco"
    ],
    "wof:name":"Bassey,David,",
    "wof:placetype":"venue"
},
  "geometry": {"coordinates":[-1.468001,52.896275],"type":"Point"}
}