{
  "type": "Feature",
  "properties": {
    "addr:full":"Chadwick Road, Astmoor Industrial Estate Runcorn Cheshire WA7 1PW",
    "addr:postcode":"wa7 1pw",
    "addr:street":"Chadwick Road Astmoor Industrial Estate",
    "iso:country":"GB",
    "sg:address":"Chadwick Road, Astmoor Industrial Estate",
    "sg:city":"Runcorn",
    "sg:classifiers":[
        {
            "category":"Freight",
            "type":"Transportation"
        }
    ],
    "sg:phone":"+44 1928 562100",
    "sg:postcode":"WA7 1PW",
    "sg:province":"Cheshire",
    "sg:tags":[
        "forwarders"
    ],
    "wof:name":"Geologistics Ltd.",
    "wof:placetype":"venue"
},
  "geometry": {"coordinates":[-2.6988039017,53.3417396545],"type":"Point"}
}