{
  "type": "Feature",
  "properties": {
    "iso:country":"GB",
    "sg:address":"Bradford Rd",
    "sg:city":"Cleckheaton",
    "sg:classifiers":[
        {
            "category":"Shopping",
            "type":"Retail Goods"
        }
    ],
    "sg:phone":"+44 1274 863700",
    "sg:postcode":"BD19 3LN",
    "sg:province":"West Yorkshire",
    "sg:tags":[
        "part",
        "accessory"
    ],
    "wof:name":"Clemo",
    "wof:placetype":"venue"
},
  "geometry": {"coordinates":[-1.718634,53.730701],"type":"Point"}
}