{
  "type": "Feature",
  "properties": {
    "addr:full":"Lower Farm Road, Ringshall Stowmarket Suffolk IP14 2JE",
    "addr:postcode":"ip14 2je",
    "addr:street":"Farm Road",
    "iso:country":"GB",
    "sg:address":"Lower Farm Road, Ringshall",
    "sg:city":"Stowmarket",
    "sg:classifiers":[
        {
            "category":"Farming",
            "subcategory":"Livestock Farm",
            "type":"Manufacturing & Wholesale Goods"
        }
    ],
    "sg:phone":"+44 1473 658302",
    "sg:postcode":"IP14 2JE",
    "sg:province":"Suffolk",
    "sg:tags":[
        "others"
    ],
    "wof:name":"P G & S R Smith",
    "wof:placetype":"venue"
},
  "geometry": {"coordinates":[0.9937000275,52.1235656738],"type":"Point"}
}