{
  "type": "Feature",
  "properties": {
    "addr:full":"Billing Rd Northampton Northamptonshire NN1 5DT",
    "addr:postcode":"nn1 5dt",
    "addr:street":"Billing Rd",
    "iso:country":"GB",
    "sg:address":"Billing Rd",
    "sg:city":"Northampton",
    "sg:classifiers":[
        {
            "category":"Government",
            "subcategory":"Office",
            "type":"Public Place"
        }
    ],
    "sg:phone":"+44 1604 633079",
    "sg:postcode":"NN1 5DT",
    "sg:province":"Northamptonshire",
    "sg:tags":[
        "local"
    ],
    "wof:name":"Woodstock",
    "wof:placetype":"venue"
},
  "geometry": {"coordinates":[-0.863431,52.239967],"type":"Point"}
}