{
  "type": "Feature",
  "properties": {
    "iso:country":"GB",
    "sg:address":"231 Silverleigh Rd",
    "sg:city":"Thornton Heath",
    "sg:classifiers":[
        {
            "category":"Building & Trades",
            "subcategory":"Plumbing",
            "type":"Services"
        }
    ],
    "sg:phone":"+44 20 8684 7331",
    "sg:postcode":"CR7 6DX",
    "sg:province":"Surrey",
    "sg:tags":[
        "central",
        "heating"
    ],
    "wof:name":"Peter Marsland",
    "wof:placetype":"venue"
},
  "geometry": {"coordinates":[-0.122981,51.397518],"type":"Point"}
}