{
  "type": "Feature",
  "properties": {
    "addr:full":"Dryholme Farm, North Cave Brough East Riding of Yorkshire HU15 2PQ",
    "addr:postcode":"hu15 2pq",
    "addr:street":"North Cave",
    "iso:country":"GB",
    "sg:address":"Dryholme Farm, North Cave",
    "sg:city":"Brough",
    "sg:classifiers":[
        {
            "category":"Farming",
            "subcategory":"Farm",
            "type":"Manufacturing & Wholesale Goods"
        }
    ],
    "sg:phone":"+44 1430 422396",
    "sg:postcode":"HU15 2PQ",
    "sg:province":"East Riding of Yorkshire",
    "sg:tags":[
        "mixed",
        "crop"
    ],
    "wof:name":"F A & S Beckett",
    "wof:placetype":"venue"
},
  "geometry": {"coordinates":[-0.6462100148,53.7801513672],"type":"Point"}
}