{
  "type": "Feature",
  "properties": {
    "addr:full":"4-6 Sydney Street London Greater London SW3 6PP",
    "addr:housenumber":"4-6",
    "addr:postcode":"sw3 6pp",
    "addr:street":"Sydney Street",
    "iso:country":"GB",
    "sg:address":"4-6 Sydney Street",
    "sg:city":"London",
    "sg:classifiers":[
        {
            "category":"Restaurant",
            "type":"Food & Drink"
        }
    ],
    "sg:phone":"+44 20 7352 3633",
    "sg:postcode":"SW3 6PP",
    "sg:province":"Greater London",
    "sg:tags":[
        "italian"
    ],
    "wof:name":"Olio E Farina Ltd.",
    "wof:placetype":"venue"
},
  "geometry": {"coordinates":[-0.1717260033,51.4914665222],"type":"Point"}
}