{
  "type": "Feature",
  "properties": {
    "addr:full":"Town Centre St Austell Cornwall PL25 5LJ",
    "addr:postcode":"pl25 5lj",
    "addr:street":"Town Centre",
    "iso:country":"GB",
    "sg:address":"Town Centre",
    "sg:city":"St Austell",
    "sg:classifiers":[
        {
            "category":"Shopping",
            "subcategory":"Shoes",
            "type":"Retail Goods"
        }
    ],
    "sg:phone":"+44 1726 73330",
    "sg:postcode":"PL25 5LJ",
    "sg:province":"Cornwall",
    "sg:tags":[
        "shop"
    ],
    "wof:name":"Goodenough (St Austell) Ltd",
    "wof:placetype":"venue"
},
  "geometry": {"coordinates":[-4.792324,50.337421],"type":"Point"}
}