{
  "type": "Feature",
  "properties": {
    "addr:full":"5 Junction Road London Greater London N19 5QD",
    "addr:housenumber":"5",
    "addr:postcode":"n19 5qd",
    "addr:street":"Junction Road",
    "iso:country":"GB",
    "sg:address":"5 Junction Road",
    "sg:city":"London",
    "sg:classifiers":[
        {
            "category":"Restaurant",
            "type":"Food & Drink"
        }
    ],
    "sg:phone":"+44 20 7561 0330",
    "sg:postcode":"N19 5QD",
    "sg:province":"Greater London",
    "wof:name":"Paris-London Cafes Ltd.",
    "wof:placetype":"venue"
},
  "geometry": {"coordinates":[-0.134493,51.565422],"type":"Point"}
}