{
  "type": "Feature",
  "properties": {
    "addr:full":"72 Main St Dalkeith City of Edinburgh EH22 4NE",
    "addr:housenumber":"72",
    "addr:postcode":"eh22 4ne",
    "addr:street":"Main St",
    "iso:country":"GB",
    "sg:address":"72 Main St",
    "sg:city":"Dalkeith",
    "sg:classifiers":[
        {
            "category":"Retail",
            "subcategory":"Funeral Services",
            "type":"Services"
        }
    ],
    "sg:phone":"+44 131 654 2704",
    "sg:postcode":"EH22 4NE",
    "sg:province":"City of Edinburgh",
    "wof:name":"Dickson Thomas & Son",
    "wof:placetype":"venue"
},
  "geometry": {"coordinates":[-3.065169096,55.8712692261],"type":"Point"}
}