{
  "type": "Feature",
  "properties": {
    "addr:full":"5a The Broadway Woking Surrey GU21 5AP",
    "addr:housenumber":"5a",
    "addr:postcode":"gu21 5ap",
    "addr:street":"The Broadway",
    "iso:country":"GB",
    "sg:address":"5a The Broadway",
    "sg:city":"Woking",
    "sg:classifiers":[
        {
            "category":"Taxi",
            "type":"Transportation"
        }
    ],
    "sg:phone":"+44 1483 724447",
    "sg:postcode":"GU21 5AP",
    "sg:province":"Surrey",
    "sg:tags":[
        "mini",
        "cab"
    ],
    "wof:name":"Car Service",
    "wof:placetype":"venue"
},
  "geometry": {"coordinates":[-0.556669,51.319099],"type":"Point"}
}