{
  "type": "Feature",
  "properties": {
    "iso:country":"GB",
    "sg:address":"5 Richmond Street",
    "sg:city":"Mansfield",
    "sg:classifiers":[
        {
            "category":"Home & Garden",
            "subcategory":"Furniture",
            "type":"Retail Goods"
        }
    ],
    "sg:phone":"+44 1623 635039",
    "sg:postcode":"NG18 3LQ",
    "sg:province":"Nottinghamshire",
    "wof:name":"Curtains Plus",
    "wof:placetype":"venue"
},
  "geometry": {"coordinates":[-1.165185,53.138306],"type":"Point"}
}