{
  "type": "Feature",
  "properties": {
    "iso:country":"GB",
    "sg:address":"37 Woodlands Avenue, Shelton Lock",
    "sg:city":"Derby",
    "sg:classifiers":[
        {
            "category":"Professional",
            "subcategory":"Engineering",
            "type":"Services"
        },
        {
            "category":"Building & Trades",
            "subcategory":"Electrical",
            "type":"Services"
        }
    ],
    "sg:phone":"+44 1332 700409",
    "sg:postcode":"DE24 9FP",
    "sg:province":"Derbyshire",
    "sg:tags":[
        "engineer",
        "electrician",
        "contractor"
    ],
    "wof:name":"J Bowley",
    "wof:placetype":"venue"
},
  "geometry": {"coordinates":[-1.446481,52.882744],"type":"Point"}
}