{
  "type": "Feature",
  "properties": {
    "iso:country":"GB",
    "sg:address":"285 Neath Road, Briton Ferry",
    "sg:city":"Neath",
    "sg:classifiers":[
        {
            "category":"Building & Trades",
            "subcategory":"Construction",
            "type":"Services"
        }
    ],
    "sg:phone":"+44 1639 813115",
    "sg:postcode":"SA11 2SL",
    "sg:province":"Neath Port Talbot",
    "sg:tags":[
        "builder"
    ],
    "wof:name":"Richard Morgan (Contractors) Ltd.",
    "wof:placetype":"venue"
},
  "geometry": {"coordinates":[-3.81776,51.640919],"type":"Point"}
}