{
  "type": "Feature",
  "properties": {
    "addr:full":"Cwmarirog Farm, Dutlas Knighton Shropshire LD7 1RN",
    "addr:postcode":"ld7 1rn",
    "addr:street":"Dutlas",
    "iso:country":"GB",
    "sg:address":"Cwmarirog Farm, Dutlas",
    "sg:city":"Knighton",
    "sg:classifiers":[
        {
            "category":"Farming",
            "subcategory":"Farm",
            "type":"Manufacturing & Wholesale Goods"
        }
    ],
    "sg:postcode":"LD7 1RN",
    "sg:province":"Shropshire",
    "sg:tags":[
        "mixed",
        "crop"
    ],
    "wof:name":"M J Davies",
    "wof:placetype":"venue"
},
  "geometry": {"coordinates":[-3.0477099419,52.3430671692],"type":"Point"}
}