{
  "type": "Feature",
  "properties": {
    "iso:country":"GB",
    "sg:address":"333 Wellington Road North",
    "sg:city":"Stockport",
    "sg:classifiers":[
        {
            "category":"Personal",
            "subcategory":"Nail Salon",
            "type":"Services"
        }
    ],
    "sg:postcode":"SK4 4QG",
    "sg:province":"Cheshire",
    "sg:tags":[
        "solarium",
        "tanning"
    ],
    "wof:name":"Diane & Neil Wilson",
    "wof:placetype":"venue"
},
  "geometry": {"coordinates":[-2.178531,53.428917],"type":"Point"}
}