{
  "type": "Feature",
  "properties": {
    "iso:country":"GB",
    "sg:address":"13 West Wycombe Road",
    "sg:city":"High Wycombe",
    "sg:classifiers":[
        {
            "category":"Organizations",
            "subcategory":"Non-profit Organization",
            "type":"Services"
        }
    ],
    "sg:postcode":"HP11 2LQ",
    "sg:province":"Buckinghamshire",
    "sg:tags":[
        "charitable",
        "organisation",
        "voluntary",
        "charity"
    ],
    "wof:name":"Fixiquip",
    "wof:placetype":"venue"
},
  "geometry": {"coordinates":[-0.7577,51.632561],"type":"Point"}
}