{
  "type": "Feature",
  "properties": {
    "iso:country":"GB",
    "sg:address":"155 Charing Cross Rd",
    "sg:city":"Holborn",
    "sg:classifiers":[
        {
            "category":"Shopping",
            "subcategory":"Party Supplies",
            "type":"Retail Goods"
        }
    ],
    "sg:phone":"+44 1254 609368",
    "sg:postcode":"WC2H 0EE",
    "sg:province":"Greater London",
    "sg:tags":[
        "plan",
        "agent"
    ],
    "wof:name":"Ann Summers",
    "wof:placetype":"venue"
},
  "geometry": {"coordinates":[-0.130255,51.516323],"type":"Point"}
}