{
  "type": "Feature",
  "properties": {
    "addr:full":"155 Charing Cross Rd Holborn Greater London WC2H 0EE",
    "addr:housenumber":"155",
    "addr:postcode":"wc2h 0ee",
    "addr:street":"Charing Cross Rd",
    "iso:country":"GB",
    "sg:address":"155 Charing Cross Rd",
    "sg:city":"Holborn",
    "sg:classifiers":[
        {
            "category":"Shopping",
            "subcategory":"Party Supplies",
            "type":"Retail Goods"
        }
    ],
    "sg:phone":"+44 1254 609368",
    "sg:postcode":"WC2H 0EE",
    "sg:province":"Greater London",
    "sg:tags":[
        "plan",
        "agent"
    ],
    "wof:name":"Ann Summers",
    "wof:placetype":"venue"
},
  "geometry": {"coordinates":[-0.130255,51.516323],"type":"Point"}
}