{
  "type": "Feature",
  "properties": {
    "iso:country":"GB",
    "sg:address":"76 Huntingdon Square, Sighthill",
    "sg:city":"Glasgow",
    "sg:classifiers":[
        {
            "category":"Government",
            "subcategory":"Post Office",
            "type":"Public Place"
        }
    ],
    "sg:phone":"+44 845 722 3344",
    "sg:postcode":"G21 1RL",
    "sg:province":"East Dunbartonshire",
    "wof:name":"Sighthill Post Office",
    "wof:placetype":"venue"
},
  "geometry": {"coordinates":[-4.237054,55.874199],"type":"Point"}
}