{
  "type": "Feature",
  "properties": {
    "addr:full":"283 High Street South East Ham Greater London E6 3PG",
    "addr:housenumber":"283",
    "addr:postcode":"e6 3pg",
    "addr:street":"High Street",
    "iso:country":"GB",
    "sg:address":"283 High Street South",
    "sg:city":"East Ham",
    "sg:classifiers":[
        {
            "category":"Cinema",
            "subcategory":"Movie Rental",
            "type":"Entertainment"
        }
    ],
    "sg:phone":"+44 20 8470 7070",
    "sg:postcode":"E6 3PG",
    "sg:province":"Greater London",
    "sg:tags":[
        "video",
        "library"
    ],
    "wof:name":"1st on Video",
    "wof:placetype":"venue"
},
  "geometry": {"coordinates":[0.0576450005,51.5226287842],"type":"Point"}
}