{
  "type": "Feature",
  "properties": {
    "addr:full":"3a Windmill Street Gravesend Kent DA12 1AD",
    "addr:housenumber":"3a",
    "addr:postcode":"da12 1ad",
    "addr:street":"Windmill Street",
    "iso:country":"GB",
    "sg:address":"3a Windmill Street",
    "sg:city":"Gravesend",
    "sg:classifiers":[
        {
            "category":"Bars & Pubs",
            "type":"Food & Drink"
        }
    ],
    "sg:phone":"+44 1474 536787",
    "sg:postcode":"DA12 1AD",
    "sg:province":"Kent",
    "sg:tags":[
        "pubs",
        "inn"
    ],
    "wof:name":"Ryans Bar",
    "wof:placetype":"venue"
},
  "geometry": {"coordinates":[0.369592,51.442135],"type":"Point"}
}