{
  "type": "Feature",
  "properties": {
    "iso:country":"GB",
    "sg:address":"Torquay Road, Springfield",
    "sg:city":"Chelmsford",
    "sg:classifiers":[
        {
            "category":"Food & Beverages",
            "subcategory":"Supermarket",
            "type":"Retail Goods"
        }
    ],
    "sg:phone":"+44 1245 347868",
    "sg:postcode":"CM1 6PW",
    "sg:province":"Essex",
    "wof:name":"Chelmsford Star Co-Operative Society Ltd.",
    "wof:placetype":"venue"
},
  "geometry": {"coordinates":[0.4883010089,51.7471199036],"type":"Point"}
}