{
  "type": "Feature",
  "properties": {
    "iso:country":"GB",
    "sg:address":"25 Main Street, Barton Under Needwood",
    "sg:city":"Burton-on-trent",
    "sg:classifiers":[
        {
            "category":"Insurance",
            "subcategory":"Insurance Agent",
            "type":"Services"
        }
    ],
    "sg:phone":"+44 1283 713234",
    "sg:postcode":"DE13 8AA",
    "sg:province":"Derbyshire",
    "wof:name":"The National Farmers Union",
    "wof:placetype":"venue"
},
  "geometry": {"coordinates":[-1.72305,52.764492],"type":"Point"}
}