{
  "type": "Feature",
  "properties": {
    "addr:full":"Cripples Ease, Nancledra Penzance Cornwall TR20 8NF",
    "addr:postcode":"tr20 8nf",
    "iso:country":"GB",
    "sg:address":"Cripples Ease, Nancledra",
    "sg:city":"Penzance",
    "sg:classifiers":[
        {
            "category":"Bars & Pubs",
            "type":"Food & Drink"
        }
    ],
    "sg:postcode":"TR20 8NF",
    "sg:province":"Cornwall",
    "sg:tags":[
        "pubs",
        "inn"
    ],
    "wof:name":"The Engine Inn",
    "wof:placetype":"venue"
},
  "geometry": {"coordinates":[-5.5080771446,50.1707229614],"type":"Point"}
}