{
  "type": "Feature",
  "properties": {
    "addr:full":"Priory Barn & Gatehouse Bookshop Grange-over-sands Cumbria LA11 6PX",
    "addr:postcode":"la11 6px",
    "iso:country":"GB",
    "sg:address":"Priory Barn & Gatehouse Bookshop",
    "sg:city":"Grange-over-sands",
    "sg:classifiers":[
        {
            "category":"Shopping",
            "subcategory":"Books",
            "type":"Retail Goods"
        }
    ],
    "sg:postcode":"LA11 6PX",
    "sg:province":"Cumbria",
    "sg:tags":[
        "second-hand"
    ],
    "wof:name":"Norman Kerr",
    "wof:placetype":"venue"
},
  "geometry": {"coordinates":[-2.9526100159,54.2016601562],"type":"Point"}
}