{
  "type": "Feature",
  "properties": {
    "iso:country":"GB",
    "sg:address":"Aldbrough, East Newton",
    "sg:city":"Hull",
    "sg:classifiers":[
        {
            "category":"Farming",
            "subcategory":"Farm",
            "type":"Manufacturing & Wholesale Goods"
        }
    ],
    "sg:postcode":"HU11 4SD",
    "sg:province":"East Riding of Yorkshire",
    "sg:tags":[
        "mixed",
        "crop"
    ],
    "wof:name":"D & M Myhill",
    "wof:placetype":"venue"
},
  "geometry": {"coordinates":[-0.115814,53.828049],"type":"Point"}
}