{
  "type": "Feature",
  "properties": {
    "iso:country":"GB",
    "sg:address":"11 Church Street",
    "sg:city":"Wincanton",
    "sg:classifiers":[
        {
            "category":"Farming",
            "subcategory":"Livestock Farm",
            "type":"Manufacturing & Wholesale Goods"
        }
    ],
    "sg:phone":"+44 1963 32367",
    "sg:postcode":"BA9 9AA",
    "sg:province":"Somerset",
    "sg:tags":[
        "breeder"
    ],
    "wof:name":"Phil Taylor",
    "wof:placetype":"venue"
},
  "geometry": {"coordinates":[-2.413033,51.055393],"type":"Point"}
}