{
  "type": "Feature",
  "properties": {
    "addr:full":"Horsted Retail Park, Maidstone Road Chatham Kent ME5 9SQ",
    "addr:postcode":"me5 9sq",
    "addr:street":"Park Maidstone Road",
    "iso:country":"GB",
    "sg:address":"Horsted Retail Park, Maidstone Road",
    "sg:city":"Chatham",
    "sg:classifiers":[
        {
            "category":"Home & Garden",
            "subcategory":"Furniture",
            "type":"Retail Goods"
        }
    ],
    "sg:phone":"+44 1634 869290",
    "sg:postcode":"ME5 9SQ",
    "sg:province":"Kent",
    "wof:name":"Harveys Furnishing Group Ltd.",
    "wof:placetype":"venue"
},
  "geometry": {"coordinates":[0.5071449876,51.3519096375],"type":"Point"}
}