{
  "type": "Feature",
  "properties": {
    "addr:full":"9-11 Paragon St Hull East Riding of Yorkshire HU1 3RJ",
    "addr:housenumber":"9-11",
    "addr:postcode":"hu1 3rj",
    "addr:street":"Paragon St",
    "iso:country":"GB",
    "sg:address":"9-11 Paragon St",
    "sg:city":"Hull",
    "sg:classifiers":[
        {
            "category":"Sports & Exercise",
            "subcategory":"Sports Center",
            "type":"Entertainment"
        }
    ],
    "sg:phone":"+44 1482 223539",
    "sg:postcode":"HU1 3RJ",
    "sg:province":"East Riding of Yorkshire",
    "sg:tags":[
        "shop",
        "good"
    ],
    "wof:name":"Rawcliffes Sport & Schoolwear",
    "wof:placetype":"venue"
},
  "geometry": {"coordinates":[-0.3395560086,53.7438049316],"type":"Point"}
}