{
  "type": "Feature",
  "properties": {
    "iso:country":"GB",
    "sg:address":"128 Queen Margaret Drive",
    "sg:city":"Glasgow",
    "sg:classifiers":[
        {
            "category":"Food & Beverages",
            "subcategory":"Liquor & Beverages",
            "type":"Retail Goods"
        }
    ],
    "sg:phone":"+44 141 946 2612",
    "sg:postcode":"G20 8NY",
    "sg:province":"Glasgow City",
    "sg:tags":[
        "beer",
        "wine",
        "spirit",
        "wines"
    ],
    "wof:name":"Victoria Wine",
    "wof:placetype":"venue"
},
  "geometry": {"coordinates":[-4.28375,55.880993],"type":"Point"}
}