{
  "type": "Feature",
  "properties": {
    "addr:full":"Park House Annex, Easingwold York North Yorkshire YO61 3BB",
    "addr:postcode":"yo61 3bb",
    "iso:country":"GB",
    "sg:address":"Park House Annex, Easingwold",
    "sg:city":"York",
    "sg:classifiers":[
        {
            "category":"Manufacturing",
            "subcategory":"Wood Products",
            "type":"Manufacturing & Wholesale Goods"
        }
    ],
    "sg:phone":"+44 1347 822324",
    "sg:postcode":"YO61 3BB",
    "sg:province":"North Yorkshire",
    "sg:tags":[
        "maker",
        "cabinet"
    ],
    "wof:name":"Oak Leaf Furniture",
    "wof:placetype":"venue"
},
  "geometry": {"coordinates":[-1.19231,54.121414],"type":"Point"}
}