{
  "type": "Feature",
  "properties": {
    "addr:full":"The Home Fm, Wood Eaton, Church Eaton Stafford Staffordshire ST20 0BB",
    "addr:housenumber":"eaton",
    "addr:postcode":"st20 0bb",
    "addr:street":"Wood;Church",
    "iso:country":"GB",
    "sg:address":"The Home Fm, Wood Eaton, Church Eaton",
    "sg:city":"Stafford",
    "sg:classifiers":[
        {
            "category":"Farming",
            "subcategory":"Farm",
            "type":"Manufacturing & Wholesale Goods"
        }
    ],
    "sg:phone":"+44 1785 822743",
    "sg:postcode":"ST20 0BB",
    "sg:province":"Staffordshire",
    "sg:tags":[
        "mixed",
        "crop"
    ],
    "wof:name":"W.J Massie",
    "wof:placetype":"venue"
},
  "geometry": {"coordinates":[-2.230679,52.75449],"type":"Point"}
}