{
  "type": "Feature",
  "properties": {
    "iso:country":"GB",
    "sg:address":"23 Cairneymount Road",
    "sg:city":"Carluke",
    "sg:classifiers":[
        {
            "category":"Building & Trades",
            "subcategory":"Construction",
            "type":"Services"
        }
    ],
    "sg:postcode":"ML8 4EN",
    "sg:province":"South Lanarkshire",
    "sg:tags":[
        "decorator",
        "painter"
    ],
    "wof:name":"Rainbow Decorators",
    "wof:placetype":"venue"
},
  "geometry": {"coordinates":[-3.8338770866,55.7360267639],"type":"Point"}
}