{
  "type": "Feature",
  "properties": {
    "addr:full":"5-7 Chesterfield Road Belper Derbyshire DE56 1FD",
    "addr:housenumber":"5-7",
    "addr:postcode":"de56 1fd",
    "addr:street":"Chesterfield Road",
    "iso:country":"GB",
    "sg:address":"5-7 Chesterfield Road",
    "sg:city":"Belper",
    "sg:classifiers":[
        {
            "category":"Social Services",
            "subcategory":"Retirement Home",
            "type":"Services"
        }
    ],
    "sg:phone":"+44 1773 820980",
    "sg:postcode":"DE56 1FD",
    "sg:province":"Derbyshire",
    "sg:tags":[
        "residential",
        "care"
    ],
    "wof:name":"Osmaston Grange Christian Retirement Home",
    "wof:placetype":"venue"
},
  "geometry": {"coordinates":[-1.477084,53.026169],"type":"Point"}
}