{
  "type": "Feature",
  "properties": {
    "addr:full":"8 Adrian Rd Bolton Lancashire BL1 3LG",
    "addr:housenumber":"8",
    "addr:postcode":"bl1 3lg",
    "addr:street":"Adrian Rd",
    "iso:country":"GB",
    "sg:address":"8 Adrian Rd",
    "sg:city":"Bolton",
    "sg:classifiers":[
        {
            "category":"Food & Beverages",
            "subcategory":"Bakery",
            "type":"Retail Goods"
        }
    ],
    "sg:phone":"+44 1204 841479",
    "sg:postcode":"BL1 3LG",
    "sg:province":"Lancashire",
    "sg:tags":[
        "baker"
    ],
    "wof:name":"Diane & Brian's Pantry",
    "wof:placetype":"venue"
},
  "geometry": {"coordinates":[-2.450026,53.595325],"type":"Point"}
}