{
  "type": "Feature",
  "properties": {
    "iso:country":"GB",
    "sg:address":"48 Chapel La",
    "sg:city":"Derby",
    "sg:classifiers":[
        {
            "category":"Manufacturing",
            "subcategory":"Electronics",
            "type":"Manufacturing & Wholesale Goods"
        }
    ],
    "sg:phone":"+44 1332 678056",
    "sg:postcode":"DE21 7JU",
    "sg:province":"Derbyshire",
    "sg:tags":[
        "control",
        "component",
        "-",
        "electronic"
    ],
    "wof:name":"Melcher Ltd",
    "wof:placetype":"venue"
},
  "geometry": {"coordinates":[-1.4043289423,52.9231681824],"type":"Point"}
}