{
  "type": "Feature",
  "properties": {
    "addr:full":"Communications Ho, Mayors Rd Altrincham Cheshire WA15 9RP",
    "addr:postcode":"wa15 9rp",
    "addr:street":"Mayors Rd",
    "iso:country":"GB",
    "sg:address":"Communications Ho, Mayors Rd",
    "sg:city":"Altrincham",
    "sg:classifiers":[
        {
            "category":"Professional",
            "subcategory":"Computer Services",
            "type":"Services"
        }
    ],
    "sg:postcode":"WA15 9RP",
    "sg:province":"Cheshire",
    "sg:tags":[
        "system",
        "software"
    ],
    "wof:name":"Wellesmere Ltd",
    "wof:placetype":"venue"
},
  "geometry": {"coordinates":[-2.34455,53.385651],"type":"Point"}
}