{
  "type": "Feature",
  "properties": {
    "addr:full":"12a Fallowcourt Avenue London Greater London N12 0EB",
    "addr:housenumber":"12a",
    "addr:postcode":"n12 0eb",
    "addr:street":"Fallowcourt Avenue",
    "iso:country":"GB",
    "sg:address":"12a Fallowcourt Avenue",
    "sg:city":"London",
    "sg:classifiers":[
        {
            "category":"Health Services",
            "subcategory":"Nursing And Care Facility",
            "type":"Services"
        }
    ],
    "sg:postcode":"N12 0EB",
    "sg:province":"Greater London",
    "sg:tags":[
        "supplier",
        "pharmacist",
        "chemist"
    ],
    "wof:name":"Libra Distributors",
    "wof:placetype":"venue"
},
  "geometry": {"coordinates":[-0.1760309935,51.6089172363],"type":"Point"}
}