{
  "type": "Feature",
  "properties": {
    "addr:full":"58 Sandbach Road South, Alsager Stoke-on-trent Cheshire ST7 2LP",
    "addr:housenumber":"58",
    "addr:postcode":"st7 2lp",
    "addr:street":"Sandbach Road South",
    "iso:country":"GB",
    "sg:address":"58 Sandbach Road South, Alsager",
    "sg:city":"Stoke-on-trent",
    "sg:classifiers":[
        {
            "category":"Shopping",
            "subcategory":"Discount & Variety Stores",
            "type":"Retail Goods"
        }
    ],
    "sg:phone":"+44 1270 882871",
    "sg:postcode":"ST7 2LP",
    "sg:province":"Cheshire",
    "sg:tags":[
        "shop",
        "model"
    ],
    "wof:name":"Alsager Toys & Models",
    "wof:placetype":"venue"
},
  "geometry": {"coordinates":[-2.3043539524,53.0956954956],"type":"Point"}
}