{
  "type": "Feature",
  "properties": {
    "addr:full":"18 Longbeck Way, Thornaby Stockton-on-tees Durham TS17 9RH",
    "addr:housenumber":"18",
    "addr:postcode":"ts17 9rh",
    "addr:street":"Longbeck Way",
    "iso:country":"GB",
    "sg:address":"18 Longbeck Way, Thornaby",
    "sg:city":"Stockton-on-tees",
    "sg:classifiers":[
        {
            "category":"Building & Trades",
            "subcategory":"Construction",
            "type":"Services"
        }
    ],
    "sg:phone":"+44 1642 763540",
    "sg:postcode":"TS17 9RH",
    "sg:province":"Durham",
    "sg:tags":[
        "roofing"
    ],
    "wof:name":"Roof Rite",
    "wof:placetype":"venue"
},
  "geometry": {"coordinates":[-1.288631,54.53043],"type":"Point"}
}