{
  "type": "Feature",
  "properties": {
    "addr:full":"206 Wilson Avenue Rochester Kent ME1 2SN",
    "addr:housenumber":"206",
    "addr:postcode":"me1 2sn",
    "addr:street":"Wilson Avenue",
    "iso:country":"GB",
    "sg:address":"206 Wilson Avenue",
    "sg:city":"Rochester",
    "sg:classifiers":[
        {
            "category":"Building & Trades",
            "subcategory":"Construction",
            "type":"Services"
        }
    ],
    "sg:phone":"+44 1634 845798",
    "sg:postcode":"ME1 2SN",
    "sg:province":"Kent",
    "sg:tags":[
        "dry",
        "plastering",
        "plasterers",
        "lining",
        "related",
        "screeders"
    ],
    "wof:name":"MARK TWEEDLY",
    "wof:placetype":"venue"
},
  "geometry": {"coordinates":[0.512162,51.362747],"type":"Point"}
}