{
  "type": "Feature",
  "properties": {
    "iso:country":"GB",
    "sg:address":"Robin Hood Cottage, Robin Hood Lane, Wrightington Wigan",
    "sg:city":"Wigan",
    "sg:classifiers":[
        {
            "category":"Shopping",
            "subcategory":"Photographic Equipment",
            "type":"Retail Goods"
        }
    ],
    "sg:phone":"+44 1257 252121",
    "sg:postcode":"WN6 9QG",
    "sg:province":"Lancashire",
    "wof:name":"Phillipa Halliwell",
    "wof:placetype":"venue"
},
  "geometry": {"coordinates":[-2.727297,53.595623],"type":"Point"}
}