{
  "type": "Feature",
  "properties": {
    "addr:full":"129 Poplar Road, Bearwood Smethwick West Midlands B66 4AP",
    "addr:housenumber":"129",
    "addr:postcode":"b66 4ap",
    "addr:street":"Poplar Road",
    "iso:country":"GB",
    "sg:address":"129 Poplar Road, Bearwood",
    "sg:city":"Smethwick",
    "sg:classifiers":[
        {
            "category":"Real Estate",
            "subcategory":"Real Estate Agent",
            "type":"Services"
        }
    ],
    "sg:postcode":"B66 4AP",
    "sg:province":"West Midlands",
    "wof:name":"Taylors Estate Agents",
    "wof:placetype":"venue"
},
  "geometry": {"coordinates":[-1.968283,52.472763],"type":"Point"}
}