{
  "type": "Feature",
  "properties": {
    "iso:country":"GB",
    "sg:address":"Office, 8u Elizabeth House, 30-32 Boulevard",
    "sg:city":"Weston Super Mare",
    "sg:classifiers":[
        {
            "category":"Professional",
            "subcategory":"Detective & Security Services",
            "type":"Services"
        }
    ],
    "sg:phone":"+44 1934 642300",
    "sg:postcode":"BS23 1NF",
    "sg:province":"Somerset",
    "sg:tags":[
        "agency"
    ],
    "wof:name":"UK Family Search",
    "wof:placetype":"venue"
},
  "geometry": {"coordinates":[-2.974684,51.3501625061],"type":"Point"}
}