{
  "type": "Feature",
  "properties": {
    "iso:country":"GB",
    "sg:address":"122 Morningside Road",
    "sg:city":"Edinburgh",
    "sg:classifiers":[
        {
            "category":"Wholesale",
            "subcategory":"Photographic Equipment",
            "type":"Manufacturing & Wholesale Goods"
        },
        {
            "category":"Shopping",
            "subcategory":"Photographic Equipment",
            "type":"Retail Goods"
        }
    ],
    "sg:phone":"+44 131 452 9614",
    "sg:postcode":"EH10 4BX",
    "sg:province":"City of Edinburgh",
    "sg:tags":[
        "supply"
    ],
    "wof:name":"Camerabase",
    "wof:placetype":"venue"
},
  "geometry": {"coordinates":[-3.2102,55.931225],"type":"Point"}
}