{
  "type": "Feature",
  "properties": {
    "addr:full":"Coronation Rd High Wycombe Buckinghamshire HP12 3RY",
    "addr:postcode":"hp12 3ry",
    "addr:street":"Coronation Rd",
    "iso:country":"GB",
    "sg:address":"Coronation Rd",
    "sg:city":"High Wycombe",
    "sg:classifiers":[
        {
            "category":"Professional",
            "subcategory":"Business Services",
            "type":"Services"
        }
    ],
    "sg:phone":"+44 1494 529161",
    "sg:postcode":"HP12 3RY",
    "sg:province":"Buckinghamshire",
    "sg:tags":[
        "holding"
    ],
    "wof:name":"Codoc Ltd",
    "wof:placetype":"venue"
},
  "geometry": {"coordinates":[-0.772834,51.620804],"type":"Point"}
}