{
  "type": "Feature",
  "properties": {
    "addr:full":"31 Bank Street Melksham Wiltshire SN12 6LE",
    "addr:housenumber":"31",
    "addr:postcode":"sn12 6le",
    "addr:street":"Bank Street",
    "iso:country":"GB",
    "sg:address":"31 Bank Street",
    "sg:city":"Melksham",
    "sg:classifiers":[
        {
            "category":"Professional",
            "subcategory":"Printing & Photocopies",
            "type":"Services"
        }
    ],
    "sg:postcode":"SN12 6LE",
    "sg:province":"Wiltshire",
    "sg:tags":[
        "printer"
    ],
    "wof:name":"Colour Byte",
    "wof:placetype":"venue"
},
  "geometry": {"coordinates":[-2.1384301186,51.3744621277],"type":"Point"}
}