{
  "type": "Feature",
  "properties": {
    "iso:country":"GB",
    "sg:address":"38a Wellington Rd",
    "sg:city":"Camborne",
    "sg:classifiers":[
        {
            "category":"Building & Trades",
            "subcategory":"Plumbing",
            "type":"Services"
        }
    ],
    "sg:phone":"+44 1209 716178",
    "sg:postcode":"TR14 7LQ",
    "sg:province":"Cornwall",
    "sg:tags":[
        "central",
        "heating"
    ],
    "wof:name":"J K Scorey",
    "wof:placetype":"venue"
},
  "geometry": {"coordinates":[-5.301681,50.214993],"type":"Point"}
}