{
  "type": "Feature",
  "properties": {
    "iso:country":"GB",
    "sg:address":"56 Livingstone Street, Newburgh",
    "sg:city":"Cupar",
    "sg:classifiers":[
        {
            "category":"Building & Trades",
            "subcategory":"Construction",
            "type":"Services"
        }
    ],
    "sg:phone":"+44 1337 840323",
    "sg:postcode":"KY14 6DQ",
    "sg:province":"Fife",
    "sg:tags":[
        "joiner",
        "carpenter"
    ],
    "wof:name":"1st Class Installation Ltd.",
    "wof:placetype":"venue"
},
  "geometry": {"coordinates":[-3.238234,56.34898],"type":"Point"}
}