{
  "type": "Feature",
  "properties": {
    "iso:country":"GB",
    "sg:address":"Elm Tree, Binley",
    "sg:city":"Andover",
    "sg:classifiers":[
        {
            "category":"Utilities",
            "subcategory":"Natural Gas",
            "type":"Services"
        }
    ],
    "sg:phone":"+44 1264 738752",
    "sg:postcode":"SP11 6ER",
    "sg:province":"Hampshire",
    "sg:tags":[
        "windmill",
        "power",
        "wind"
    ],
    "wof:name":"Enercon Systems Ltd.",
    "wof:placetype":"venue"
},
  "geometry": {"coordinates":[-1.397604,51.27697],"type":"Point"}
}