{
  "type": "Feature",
  "properties": {
    "addr:full":"20a The Grn Bradford West Yorkshire BD10 9PR",
    "addr:housenumber":"20a",
    "addr:postcode":"bd10 9pr",
    "addr:street":"The Grn Bradford West",
    "iso:country":"GB",
    "sg:address":"20a The Grn",
    "sg:city":"Bradford",
    "sg:classifiers":[
        {
            "category":"Food & Beverages",
            "subcategory":"Fruits & Vegetables",
            "type":"Retail Goods"
        }
    ],
    "sg:postcode":"BD10 9PR",
    "sg:province":"West Yorkshire",
    "sg:tags":[
        "greengrocer"
    ],
    "wof:name":"Whittle,Lindsey,",
    "wof:placetype":"venue"
},
  "geometry": {"coordinates":[-1.72989,53.831814],"type":"Point"}
}