{
  "type": "Feature",
  "properties": {
    "addr:full":"2 Church Clo Andover Hampshire SP10 1DP",
    "addr:housenumber":"2",
    "addr:postcode":"sp10 1dp",
    "addr:street":"Church Clo",
    "iso:country":"GB",
    "sg:address":"2 Church Clo",
    "sg:city":"Andover",
    "sg:classifiers":[
        {
            "category":"Organizations",
            "subcategory":"Political Organization",
            "type":"Services"
        }
    ],
    "sg:phone":"+44 1264 401401",
    "sg:postcode":"SP10 1DP",
    "sg:province":"Hampshire",
    "sg:tags":[
        "party"
    ],
    "wof:name":"Young Sir George MP",
    "wof:placetype":"venue"
},
  "geometry": {"coordinates":[-1.4774949551,51.2096824646],"type":"Point"}
}