{
  "type": "Feature",
  "properties": {
    "iso:country":"GB",
    "sg:address":"Loamend Farm, Strichen",
    "sg:city":"Fraserburgh",
    "sg:classifiers":[
        {
            "category":"Professional",
            "subcategory":"Management & Consulting",
            "type":"Services"
        }
    ],
    "sg:postcode":"AB43 6RQ",
    "sg:province":"Aberdeenshire",
    "sg:tags":[
        "consultant",
        "business"
    ],
    "wof:name":"Mormarc Ltd.",
    "wof:placetype":"venue"
},
  "geometry": {"coordinates":[-2.0905690193,57.5866203308],"type":"Point"}
}