{
  "type": "Feature",
  "properties": {
    "addr:full":"Prince Of Wales Inn, Cynwyd Corwen Conwy LL21 0LD",
    "addr:postcode":"ll21 0ld",
    "addr:street":"Prince;Corwen",
    "iso:country":"GB",
    "sg:address":"Prince Of Wales Inn, Cynwyd",
    "sg:city":"Corwen",
    "sg:classifiers":[
        {
            "category":"Bars & Pubs",
            "type":"Food & Drink"
        }
    ],
    "sg:phone":"+44 1490 412450",
    "sg:postcode":"LL21 0LD",
    "sg:province":"Conwy",
    "sg:tags":[
        "pubs",
        "inn"
    ],
    "wof:name":"S Roberts",
    "wof:placetype":"venue"
},
  "geometry": {"coordinates":[-3.373668,52.980648],"type":"Point"}
}