{
  "type": "Feature",
  "properties": {
    "iso:country":"GB",
    "sg:address":"Dalby Way, Coulby Newham",
    "sg:city":"Middlesbrough",
    "sg:classifiers":[
        {
            "category":"Retail",
            "subcategory":"Funeral Services",
            "type":"Services"
        }
    ],
    "sg:phone":"+44 1642 596600",
    "sg:postcode":"TS8 0TW",
    "sg:province":"North Yorkshire",
    "wof:name":"Hilda House",
    "wof:placetype":"venue"
},
  "geometry": {"coordinates":[-1.213429,54.524029],"type":"Point"}
}