{
  "type": "Feature",
  "properties": {
    "addr:full":"489a Gloucester Road, Horfield Bristol City of Bristol BS7 8UG",
    "addr:housenumber":"489a",
    "addr:postcode":"bs7 8ug",
    "addr:street":"Gloucester Road",
    "iso:country":"GB",
    "sg:address":"489a Gloucester Road, Horfield",
    "sg:city":"Bristol",
    "sg:classifiers":[
        {
            "category":"Professional",
            "subcategory":"Management & Consulting",
            "type":"Services"
        }
    ],
    "sg:postcode":"BS7 8UG",
    "sg:province":"City of Bristol",
    "sg:tags":[
        "consultant",
        "business"
    ],
    "wof:name":"Holford Consultants Ltd",
    "wof:placetype":"venue"
},
  "geometry": {"coordinates":[-2.585132,51.487106],"type":"Point"}
}