{
  "type": "Feature",
  "properties": {
    "addr:full":"5 Greek St West End Hampshire W1V 6NA",
    "addr:housenumber":"5",
    "addr:postcode":"w1v 6na",
    "addr:street":"Greek St",
    "iso:country":"GB",
    "sg:address":"5 Greek St",
    "sg:city":"West End",
    "sg:classifiers":[
        {
            "category":"Restaurant",
            "type":"Food & Drink"
        }
    ],
    "sg:phone":"+44 20 7437 1816",
    "sg:postcode":"W1V 6NA",
    "sg:province":"Hampshire",
    "sg:tags":[
        "french"
    ],
    "wof:name":"Au Jardin Des Gourmets",
    "wof:placetype":"venue"
},
  "geometry": {"coordinates":[-0.131152,51.51479],"type":"Point"}
}