{
  "type": "Feature",
  "properties": {
    "iso:country":"GB",
    "sg:address":"Unit 5 Almond Court",
    "sg:city":"Falkirk",
    "sg:classifiers":[
        {
            "category":"Autos & Motor Vehicles",
            "subcategory":"Auto Supplies",
            "type":"Retail Goods"
        }
    ],
    "sg:phone":"+44 1324 629427",
    "sg:postcode":"FK2 9HT",
    "sg:province":"Falkirk",
    "sg:tags":[
        "component"
    ],
    "wof:name":"Uni Part Auto",
    "wof:placetype":"venue"
},
  "geometry": {"coordinates":[-3.7651939392,56.0121650696],"type":"Point"}
}