{
  "type": "Feature",
  "properties": {
    "addr:full":"25 Northbrook St Newbury Berkshire RG14 1DJ",
    "addr:housenumber":"25",
    "addr:postcode":"rg14 1dj",
    "addr:street":"Northbrook St",
    "iso:country":"GB",
    "sg:address":"25 Northbrook St",
    "sg:city":"Newbury",
    "sg:classifiers":[
        {
            "category":"Bars & Pubs",
            "type":"Food & Drink"
        }
    ],
    "sg:phone":"+44 1635 523249",
    "sg:postcode":"RG14 1DJ",
    "sg:province":"Berkshire",
    "sg:tags":[
        "pubs",
        "inn"
    ],
    "wof:name":"Captains Cabin The",
    "wof:placetype":"venue"
},
  "geometry": {"coordinates":[-1.324319005,51.4033241272],"type":"Point"}
}