{
  "type": "Feature",
  "properties": {
    "iso:country":"GB",
    "sg:address":"Norwich Rd, Corpusty",
    "sg:city":"Norwich",
    "sg:classifiers":[
        {
            "category":"Education",
            "subcategory":"School",
            "type":"Public Place"
        }
    ],
    "sg:phone":"+44 1263 587320",
    "sg:postcode":"NR11 6QD",
    "sg:province":"Norfolk",
    "sg:tags":[
        "local",
        "authority"
    ],
    "wof:name":"Corpusty County Primary School",
    "wof:placetype":"venue"
},
  "geometry": {"coordinates":[1.2524679899,52.7937507629],"type":"Point"}
}