{
  "type": "Feature",
  "properties": {
    "addr:full":"Mkm Ho, Baron Rd, South Woodham Ferrers Chelmsford Essex CM3 5XQ",
    "addr:postcode":"cm3 5xq",
    "addr:street":"Mkm;Baron Rd",
    "iso:country":"GB",
    "sg:address":"Mkm Ho, Baron Rd, South Woodham Ferrers",
    "sg:city":"Chelmsford",
    "sg:classifiers":[
        {
            "category":"Wholesale",
            "subcategory":"Construction Materials",
            "type":"Manufacturing & Wholesale Goods"
        }
    ],
    "sg:phone":"+44 1245 329114",
    "sg:postcode":"CM3 5XQ",
    "sg:province":"Essex",
    "sg:tags":[
        "lift"
    ],
    "wof:name":"Wood Clarke Ltd",
    "wof:placetype":"venue"
},
  "geometry": {"coordinates":[0.61715,51.645241],"type":"Point"}
}