{
  "type": "Feature",
  "properties": {
    "iso:country":"GB",
    "sg:address":"26 Bennetts Gate",
    "sg:city":"Hemel Hempstead",
    "sg:classifiers":[
        {
            "category":"Retail",
            "subcategory":"Repair Shop",
            "type":"Services"
        }
    ],
    "sg:postcode":"HP3 8EW",
    "sg:province":"Hertfordshire",
    "sg:tags":[
        "radio",
        "television",
        "video"
    ],
    "wof:name":"Lawrence,Malcom,",
    "wof:placetype":"venue"
},
  "geometry": {"coordinates":[-0.449028,51.741917],"type":"Point"}
}