{
  "type": "Feature",
  "properties": {
    "addr:full":"Cobham Hall, Cobham Gravesend Kent DA12 3BL",
    "addr:postcode":"da12 3bl",
    "addr:street":"Cobham",
    "iso:country":"GB",
    "sg:address":"Cobham Hall, Cobham",
    "sg:city":"Gravesend",
    "sg:classifiers":[
        {
            "category":"Education",
            "subcategory":"School",
            "type":"Public Place"
        }
    ],
    "sg:phone":"+44 1474 823371",
    "sg:postcode":"DA12 3BL",
    "sg:province":"Kent",
    "sg:tags":[
        "independent",
        "preparatory"
    ],
    "wof:name":"Cobham Hall",
    "wof:placetype":"venue"
},
  "geometry": {"coordinates":[0.3992320001,51.3903617859],"type":"Point"}
}