{
  "type": "Feature",
  "properties": {
    "addr:full":"90 Somerset Place Plymouth Devon PL3 4BG",
    "addr:housenumber":"90",
    "addr:postcode":"pl3 4bg",
    "addr:street":"Somerset Place",
    "iso:country":"GB",
    "sg:address":"90 Somerset Place",
    "sg:city":"Plymouth",
    "sg:classifiers":[
        {
            "category":"Social Services",
            "subcategory":"Retirement Home",
            "type":"Services"
        }
    ],
    "sg:phone":"+44 1752 562872",
    "sg:postcode":"PL3 4BG",
    "sg:province":"Devon",
    "sg:tags":[
        "residential",
        "care"
    ],
    "wof:name":"Durnsford Lodge",
    "wof:placetype":"venue"
},
  "geometry": {"coordinates":[-4.1649341583,50.3801803589],"type":"Point"}
}