{
  "type": "Feature",
  "properties": {
    "iso:country":"GB",
    "sg:address":"Riverside",
    "sg:city":"Hayle",
    "sg:classifiers":[
        {
            "category":"Professional",
            "subcategory":"Art Services",
            "type":"Services"
        }
    ],
    "sg:postcode":"TR27 5JD",
    "sg:province":"Cornwall",
    "sg:tags":[
        "model",
        "maker"
    ],
    "wof:name":"K W L Models",
    "wof:placetype":"venue"
},
  "geometry": {"coordinates":[-5.3859081268,50.1934204102],"type":"Point"}
}