{
  "type": "Feature",
  "properties": {
    "addr:full":"Holford Drive, Holford Birmingham West Midlands B6 7UG",
    "addr:postcode":"b6 7ug",
    "addr:street":"Holford Drive",
    "iso:country":"GB",
    "sg:address":"Holford Drive, Holford",
    "sg:city":"Birmingham",
    "sg:classifiers":[
        {
            "category":"Autos & Motor Vehicles",
            "subcategory":"Auto Supplies",
            "type":"Retail Goods"
        }
    ],
    "sg:phone":"+44 121 344 5400",
    "sg:postcode":"B6 7UG",
    "sg:province":"West Midlands",
    "sg:tags":[
        "car",
        "audio"
    ],
    "wof:name":"V D O Car Communication U K Ltd.",
    "wof:placetype":"venue"
},
  "geometry": {"coordinates":[-1.885844,52.520031],"type":"Point"}
}