{
  "type": "Feature",
  "properties": {
    "addr:full":"47c Princess Street Luton Bedfordshire LU1 5AT",
    "addr:housenumber":"47c",
    "addr:postcode":"lu1 5at",
    "addr:street":"Princess Street",
    "iso:country":"GB",
    "sg:address":"47c Princess Street",
    "sg:city":"Luton",
    "sg:classifiers":[
        {
            "category":"Organizations",
            "subcategory":"Non-profit Organization",
            "type":"Services"
        }
    ],
    "sg:phone":"+44 1582 458952",
    "sg:postcode":"LU1 5AT",
    "sg:province":"Bedfordshire",
    "sg:tags":[
        "organisation",
        "voluntary",
        "charity"
    ],
    "wof:name":"The Befrienders (Luton)",
    "wof:placetype":"venue"
},
  "geometry": {"coordinates":[-0.4212090075,51.8772125244],"type":"Point"}
}