{
  "type": "Feature",
  "properties": {
    "addr:full":"21 Melksham Close Macclesfield Cheshire SK11 8NH",
    "addr:housenumber":"21",
    "addr:postcode":"sk11 8nh",
    "addr:street":"Melksham Close",
    "iso:country":"GB",
    "sg:address":"21 Melksham Close",
    "sg:city":"Macclesfield",
    "sg:classifiers":[
        {
            "category":"Military Area",
            "subcategory":"Air Force Base",
            "type":"Public Place"
        }
    ],
    "sg:phone":"+44 7778 495553",
    "sg:postcode":"SK11 8NH",
    "sg:province":"Cheshire",
    "sg:tags":[
        "taxi",
        "hire",
        "private"
    ],
    "wof:name":"Dial-A-Car Taxis",
    "wof:placetype":"venue"
},
  "geometry": {"coordinates":[-2.1438140869,53.2554779053],"type":"Point"}
}