{
  "type": "Feature",
  "properties": {
    "addr:full":"71 Castle Road Southsea Hampshire PO5 3AY",
    "addr:housenumber":"71",
    "addr:postcode":"po5 3ay",
    "addr:street":"Castle Road",
    "iso:country":"GB",
    "sg:address":"71 Castle Road",
    "sg:city":"Southsea",
    "sg:classifiers":[
        {
            "category":"Government",
            "subcategory":"Post Office",
            "type":"Public Place"
        }
    ],
    "sg:phone":"+44 23 9282 6220",
    "sg:postcode":"PO5 3AY",
    "sg:province":"Hampshire",
    "wof:name":"Castle Road Post Office",
    "wof:placetype":"venue"
},
  "geometry": {"coordinates":[-1.093751,50.788544],"type":"Point"}
}