{
  "type": "Feature",
  "properties": {
    "iso:country":"GB",
    "sg:address":"Holme Lacy",
    "sg:city":"Hereford",
    "sg:classifiers":[
        {
            "category":"Education",
            "subcategory":"School",
            "type":"Public Place"
        }
    ],
    "sg:phone":"+44 1432 870374",
    "sg:postcode":"HR2 6LW",
    "sg:province":"Herefordshire",
    "sg:tags":[
        "local",
        "authority"
    ],
    "sg:website":"http://www.ikschool.com",
    "wof:name":"Holme Lacy Primary School",
    "wof:placetype":"venue"
},
  "geometry": {"coordinates":[-2.7194499969,52.0440216064],"type":"Point"}
}