{
  "type": "Feature",
  "properties": {
    "iso:country":"GB",
    "sg:address":"14 Eltham Road",
    "sg:city":"London",
    "sg:classifiers":[
        {
            "category":"Retail",
            "subcategory":"Laundry & Dry Cleaning",
            "type":"Services"
        }
    ],
    "sg:phone":"+44 20 8297 8719",
    "sg:postcode":"SE12 8TF",
    "sg:province":"Greater London",
    "sg:tags":[
        "launderette"
    ],
    "wof:name":"J & G Laundrette",
    "wof:placetype":"venue"
},
  "geometry": {"coordinates":[0.012381,51.45615],"type":"Point"}
}