{
  "type": "Feature",
  "properties": {
    "addr:full":"1 De Lunn Building Winchester Hampshire SO23 8SA",
    "addr:housenumber":"1",
    "addr:postcode":"so23 8sa",
    "addr:street":"De",
    "iso:country":"GB",
    "sg:address":"1 De Lunn Building",
    "sg:city":"Winchester",
    "sg:classifiers":[
        {
            "category":"Professional",
            "type":"Services"
        }
    ],
    "sg:postcode":"SO23 8SA",
    "sg:province":"Hampshire",
    "sg:tags":[
        "entertainer"
    ],
    "wof:name":"Winchester Entertainment",
    "wof:placetype":"venue"
},
  "geometry": {"coordinates":[-1.3168090582,51.0630683899],"type":"Point"}
}