{
  "type": "Feature",
  "properties": {
    "iso:country":"GB",
    "sg:address":"The Surgery, Gerrans Hill",
    "sg:city":"Truro",
    "sg:classifiers":[
        {
            "category":"Health Services",
            "subcategory":"Doctor",
            "type":"Services"
        }
    ],
    "sg:phone":"+44 1872 580345",
    "sg:postcode":"TR2 5EE",
    "sg:province":"Cornwall",
    "sg:tags":[
        "practitioners"
    ],
    "wof:name":"Campbell, G F",
    "wof:placetype":"venue"
},
  "geometry": {"coordinates":[-4.97885,50.17794],"type":"Point"}
}