{
  "type": "Feature",
  "properties": {
    "addr:full":"Paddockhurst Road Crawley Surrey RH10 4SB",
    "addr:postcode":"rh10 4sb",
    "addr:street":"Paddockhurst Road",
    "iso:country":"GB",
    "sg:address":"Paddockhurst Road",
    "sg:city":"Crawley",
    "sg:classifiers":[
        {
            "category":"Place Of Worship",
            "type":"Public Place"
        }
    ],
    "sg:phone":"+44 1342 718298",
    "sg:postcode":"RH10 4SB",
    "sg:province":"Surrey",
    "wof:name":"Worth Abbey",
    "wof:placetype":"venue"
},
  "geometry": {"coordinates":[-0.117677,51.094448],"type":"Point"}
}