{
  "type": "Feature",
  "properties": {
    "addr:full":"Unitech House, 25 Bernard Street Edinburgh City of Edinburgh EH6 6SH",
    "addr:housenumber":"25",
    "addr:postcode":"eh6 6sh",
    "addr:street":"Bernard Street",
    "iso:country":"GB",
    "sg:address":"Unitech House, 25 Bernard Street",
    "sg:city":"Edinburgh",
    "sg:classifiers":[
        {
            "category":"Professional",
            "subcategory":"Computer Services",
            "type":"Services"
        }
    ],
    "sg:phone":"+44 131 472 5555",
    "sg:postcode":"EH6 6SH",
    "sg:province":"City of Edinburgh",
    "sg:tags":[
        "system",
        "software"
    ],
    "wof:name":"Universal Information Technology Group Ltd.",
    "wof:placetype":"venue"
},
  "geometry": {"coordinates":[-3.1677689552,55.9757347107],"type":"Point"}
}