{
  "type": "Feature",
  "properties": {
    "addr:full":"Pegasus Works, Roebuck Road Ilford Essex IG6 3UF",
    "addr:postcode":"ig6 3uf",
    "addr:street":"Roebuck Road",
    "iso:country":"GB",
    "sg:address":"Pegasus Works, Roebuck Road",
    "sg:city":"Ilford",
    "sg:classifiers":[
        {
            "category":"Manufacturing",
            "subcategory":"Jewelry",
            "type":"Manufacturing & Wholesale Goods"
        }
    ],
    "sg:phone":"+44 20 8500 2301",
    "sg:postcode":"IG6 3UF",
    "sg:province":"Essex",
    "sg:tags":[
        "repair",
        "jewellery"
    ],
    "wof:name":"Renoir Jewels Ltd.",
    "wof:placetype":"venue"
},
  "geometry": {"coordinates":[0.12092,51.6064],"type":"Point"}
}