{
  "type": "Feature",
  "properties": {
    "addr:full":"Labour Club, Lionel Road Canvey Island Essex SS8 9DE",
    "addr:postcode":"ss8 9de",
    "addr:street":"Lionel Road",
    "iso:country":"GB",
    "sg:address":"Labour Club, Lionel Road",
    "sg:city":"Canvey Island",
    "sg:classifiers":[
        {
            "category":"Organizations",
            "subcategory":"Political Organization",
            "type":"Services"
        }
    ],
    "sg:phone":"+44 1268 514973",
    "sg:postcode":"SS8 9DE",
    "sg:province":"Essex",
    "sg:tags":[
        "party"
    ],
    "wof:name":"Labour Club",
    "wof:placetype":"venue"
},
  "geometry": {"coordinates":[0.59112,51.520374],"type":"Point"}
}