{
  "type": "Feature",
  "properties": {
    "addr:full":"Cornelau Farm, Upper Chapel Brecon Powys LD3 9RG",
    "addr:postcode":"ld3 9rg",
    "addr:street":"Upper",
    "iso:country":"GB",
    "sg:address":"Cornelau Farm, Upper Chapel",
    "sg:city":"Brecon",
    "sg:classifiers":[
        {
            "category":"Farming",
            "subcategory":"Livestock Farm",
            "type":"Manufacturing & Wholesale Goods"
        }
    ],
    "sg:postcode":"LD3 9RG",
    "sg:province":"Powys",
    "sg:tags":[
        "others"
    ],
    "wof:name":"M Price",
    "wof:placetype":"venue"
},
  "geometry": {"coordinates":[-3.448359,52.052673],"type":"Point"}
}