{
  "type": "Feature",
  "properties": {
    "iso:country":"GB",
    "sg:address":"2 Broadway, Coatham Mundeville",
    "sg:city":"Darlington",
    "sg:classifiers":[
        {
            "category":"Building & Trades",
            "subcategory":"Construction",
            "type":"Services"
        }
    ],
    "sg:phone":"+44 1325 319231",
    "sg:postcode":"DL1 3NA",
    "sg:province":"Durham",
    "sg:tags":[
        "ceiling",
        "contractor"
    ],
    "wof:name":"Hi-Line Ceilings",
    "wof:placetype":"venue"
},
  "geometry": {"coordinates":[-1.548894,54.524502],"type":"Point"}
}