{
  "type": "Feature",
  "properties": {
    "iso:country":"GB",
    "sg:address":"25 Tunnel Road",
    "sg:city":"Tunbridge Wells",
    "sg:classifiers":[
        {
            "category":"Manufacturing",
            "subcategory":"Building Materials",
            "type":"Manufacturing & Wholesale Goods"
        }
    ],
    "sg:phone":"+44 1892 522224",
    "sg:postcode":"TN1 2BT",
    "sg:province":"Kent",
    "sg:tags":[
        "merchant",
        "builder"
    ],
    "wof:name":"Travis Perkins Trading Co. Ltd.",
    "wof:placetype":"venue"
},
  "geometry": {"coordinates":[0.265374,51.136784],"type":"Point"}
}