{
  "type": "Feature",
  "properties": {
    "addr:full":"Highgate Kendal Cumbria LA9 4DA",
    "addr:postcode":"la9 4da",
    "addr:street":"Highgate",
    "iso:country":"GB",
    "sg:address":"Highgate",
    "sg:city":"Kendal",
    "sg:classifiers":[
        {
            "category":"Bars & Pubs",
            "subcategory":"Nightclub",
            "type":"Food & Drink"
        }
    ],
    "sg:phone":"+44 1539 724103",
    "sg:postcode":"LA9 4DA",
    "sg:province":"Cumbria",
    "sg:tags":[
        "club",
        "night"
    ],
    "wof:name":"Jazz's Night Club",
    "wof:placetype":"venue"
},
  "geometry": {"coordinates":[-2.747514,54.326534],"type":"Point"}
}