{
  "type": "Feature",
  "properties": {
    "iso:country":"GB",
    "sg:address":"170 Washway Rd",
    "sg:city":"Sale",
    "sg:classifiers":[
        {
            "category":"Professional",
            "subcategory":"Detective & Security Services",
            "type":"Services"
        }
    ],
    "sg:phone":"+44 161 969 1000",
    "sg:postcode":"M33 6RH",
    "sg:province":"Cheshire",
    "sg:tags":[
        "car"
    ],
    "wof:name":"Doppler Car Systems",
    "wof:placetype":"venue"
},
  "geometry": {"coordinates":[-2.330578,53.420963],"type":"Point"}
}