{
  "type": "Feature",
  "properties": {
    "iso:country":"GB",
    "sg:address":"Blue Bell Lane",
    "sg:city":"Wrexham",
    "sg:classifiers":[
        {
            "category":"Utilities",
            "subcategory":"Fuel Oil & Lpg",
            "type":"Services"
        }
    ],
    "sg:phone":"+44 1978 261399",
    "sg:postcode":"LL12 8EE",
    "sg:province":"Wrexham",
    "sg:tags":[
        "coal",
        "smokeless"
    ],
    "wof:name":"C P L Distribution Ltd.",
    "wof:placetype":"venue"
},
  "geometry": {"coordinates":[-2.989594,53.07336],"type":"Point"}
}