{
  "type": "Feature",
  "properties": {
    "addr:full":"9 Grearshill Road, Kingstown Industrial Estate Carlisle Cumbria CA3 0ET",
    "addr:housenumber":"9;estate",
    "addr:postcode":"ca3 0et",
    "addr:street":"Grearshill Road;Industrial",
    "iso:country":"GB",
    "sg:address":"9 Grearshill Road, Kingstown Industrial Estate",
    "sg:city":"Carlisle",
    "sg:classifiers":[
        {
            "category":"Autos & Motor Vehicles",
            "subcategory":"Automobile Sales",
            "type":"Retail Goods"
        }
    ],
    "sg:phone":"+44 1228 544411",
    "sg:postcode":"CA3 0ET",
    "sg:province":"Cumbria",
    "sg:tags":[
        "car"
    ],
    "wof:name":"Lloyd Honda",
    "wof:placetype":"venue"
},
  "geometry": {"coordinates":[-2.946749,54.925461],"type":"Point"}
}