{
  "type": "Feature",
  "properties": {
    "addr:full":"Bolehall House, Amington Road Tamworth Staffordshire B77 3PA",
    "addr:postcode":"b77 3pa",
    "addr:street":"Amington Road",
    "iso:country":"GB",
    "sg:address":"Bolehall House, Amington Road",
    "sg:city":"Tamworth",
    "sg:classifiers":[
        {
            "category":"Autos & Motor Vehicles",
            "subcategory":"Auto Supplies",
            "type":"Retail Goods"
        }
    ],
    "sg:phone":"+44 1827 304160",
    "sg:postcode":"B77 3PA",
    "sg:province":"Staffordshire",
    "sg:tags":[
        "windscreen"
    ],
    "wof:name":"National Windscreens (Replacements) Ltd.",
    "wof:placetype":"venue"
},
  "geometry": {"coordinates":[-1.660529,52.635956],"type":"Point"}
}