{
  "type": "Feature",
  "properties": {
    "addr:full":"71 St. Johns Rd Tunbridge Wells Kent TN4 9TT",
    "addr:housenumber":"71",
    "addr:postcode":"tn4 9tt",
    "addr:street":"St. Johns Rd",
    "iso:country":"GB",
    "sg:address":"71 St. Johns Rd",
    "sg:city":"Tunbridge Wells",
    "sg:classifiers":[
        {
            "category":"Food & Beverages",
            "subcategory":"Liquor & Beverages",
            "type":"Retail Goods"
        }
    ],
    "sg:phone":"+44 1892 510045",
    "sg:postcode":"TN4 9TT",
    "sg:province":"Kent",
    "sg:tags":[
        "beer",
        "spirit",
        "wines"
    ],
    "wof:name":"Victoria Wine",
    "wof:placetype":"venue"
},
  "geometry": {"coordinates":[0.2599290013,51.1414527893],"type":"Point"}
}