{
  "type": "Feature",
  "properties": {
    "addr:full":"The Polygons, Danebank Road Lymm Cheshire WA13 9DQ",
    "addr:postcode":"wa13 9dq",
    "addr:street":"Danebank Road",
    "iso:country":"GB",
    "sg:address":"The Polygons, Danebank Road",
    "sg:city":"Lymm",
    "sg:classifiers":[
        {
            "category":"Real Estate",
            "subcategory":"Architect",
            "type":"Services"
        }
    ],
    "sg:postcode":"WA13 9DQ",
    "sg:province":"Cheshire",
    "wof:name":"Granville Gough",
    "wof:placetype":"venue"
},
  "geometry": {"coordinates":[-2.487556,53.379574],"type":"Point"}
}