{
  "type": "Feature",
  "properties": {
    "addr:full":"P O Box 116 Thatcham Berkshire RG18 4HR",
    "addr:housenumber":"116",
    "addr:postcode":"rg18 4hr",
    "addr:street":"P O Box",
    "iso:country":"GB",
    "sg:address":"P O Box 116",
    "sg:city":"Thatcham",
    "sg:classifiers":[
        {
            "category":"Wholesale",
            "subcategory":"Construction Materials",
            "type":"Manufacturing & Wholesale Goods"
        }
    ],
    "sg:phone":"+44 1635 871878",
    "sg:postcode":"RG18 4HR",
    "sg:province":"Berkshire",
    "sg:tags":[
        "lift"
    ],
    "wof:name":"Lifting Equipment Services",
    "wof:placetype":"venue"
},
  "geometry": {"coordinates":[-1.263599,51.403831],"type":"Point"}
}