{
  "type": "Feature",
  "properties": {
    "iso:country":"GB",
    "sg:address":"Sandy View Buildings, Front Street, Burnopfield",
    "sg:city":"Newcastle-upon-tyne",
    "sg:classifiers":[
        {
            "category":"Building & Trades",
            "subcategory":"Construction",
            "type":"Services"
        }
    ],
    "sg:phone":"+44 1207 270809",
    "sg:postcode":"NE16 6PU",
    "sg:province":"Durham",
    "sg:tags":[
        "roofing"
    ],
    "wof:name":"Hodgson & Allon Ltd.",
    "wof:placetype":"venue"
},
  "geometry": {"coordinates":[-1.727454,54.906704],"type":"Point"}
}