{
  "type": "Feature",
  "properties": {
    "addr:full":"9 Church Road Lytham St Annes Lancashire FY8 5LH",
    "addr:housenumber":"9",
    "addr:postcode":"fy8 5lh",
    "addr:street":"Church Road",
    "iso:country":"GB",
    "sg:address":"9 Church Road",
    "sg:city":"Lytham St Annes",
    "sg:classifiers":[
        {
            "category":"Food & Beverages",
            "subcategory":"Liquor & Beverages",
            "type":"Retail Goods"
        }
    ],
    "sg:postcode":"FY8 5LH",
    "sg:province":"Lancashire",
    "sg:tags":[
        "beer",
        "spirit",
        "wines"
    ],
    "wof:name":"Victoria Wine",
    "wof:placetype":"venue"
},
  "geometry": {"coordinates":[-2.9659368992,53.7369918823],"type":"Point"}
}