{
  "type": "Feature",
  "properties": {
    "addr:full":"8 Union Street Andover Hampshire SP10 1PA",
    "addr:housenumber":"8",
    "addr:postcode":"sp10 1pa",
    "addr:street":"Union Street",
    "iso:country":"GB",
    "sg:address":"8 Union Street",
    "sg:city":"Andover",
    "sg:classifiers":[
        {
            "category":"Retail",
            "subcategory":"Laundry & Dry Cleaning",
            "type":"Services"
        }
    ],
    "sg:phone":"+44 1264 352684",
    "sg:postcode":"SP10 1PA",
    "sg:province":"Hampshire",
    "sg:tags":[
        "alteration"
    ],
    "wof:name":"Sketchley Dry Cleaners",
    "wof:placetype":"venue"
},
  "geometry": {"coordinates":[-1.476779,51.206493],"type":"Point"}
}