{
  "type": "Feature",
  "properties": {
    "addr:full":"60 Charlestown Road St Austell Cornwall PL25 3NN",
    "addr:housenumber":"60",
    "addr:postcode":"pl25 3nn",
    "addr:street":"Charlestown Road",
    "iso:country":"GB",
    "sg:address":"60 Charlestown Road",
    "sg:city":"St Austell",
    "sg:classifiers":[
        {
            "category":"Health Services",
            "subcategory":"Health Practitioner",
            "type":"Services"
        }
    ],
    "sg:postcode":"PL25 3NN",
    "sg:province":"Cornwall",
    "sg:tags":[
        "osteopath"
    ],
    "wof:name":"P A Keilbart",
    "wof:placetype":"venue"
},
  "geometry": {"coordinates":[-4.7638788223,50.336730957],"type":"Point"}
}