{
  "type": "Feature",
  "properties": {
    "addr:full":"First Point, Buckingham Gate, South Terminal Crawley Surrey RH6 0NT",
    "addr:postcode":"rh6 0nt",
    "addr:street":"Buckingham Gate South Terminal",
    "iso:country":"GB",
    "sg:address":"First Point, Buckingham Gate, South Terminal",
    "sg:city":"Crawley",
    "sg:classifiers":[
        {
            "category":"Professional",
            "type":"Services"
        },
        {
            "category":"Airline",
            "type":"Transportation"
        }
    ],
    "sg:phone":"+44 1293 567656",
    "sg:postcode":"RH6 0NT",
    "sg:province":"Surrey",
    "sg:tags":[
        "aircraft",
        "leasing",
        "charter"
    ],
    "wof:name":"Aircraft Leasing & Management Ltd.",
    "wof:placetype":"venue"
},
  "geometry": {"coordinates":[-0.1533199996,51.1582107544],"type":"Point"}
}