{
  "type": "Feature",
  "properties": {
    "iso:country":"GB",
    "sg:address":"Innovation House, 54-56 London Road",
    "sg:city":"Leicester",
    "sg:classifiers":[
        {
            "category":"Professional",
            "subcategory":"Business Services",
            "type":"Services"
        }
    ],
    "sg:phone":"+44 116 292 3663",
    "sg:postcode":"LE2 0QD",
    "sg:province":"Leicestershire",
    "sg:tags":[
        "transfer",
        "agent"
    ],
    "wof:name":"Business Transfer Associates",
    "wof:placetype":"venue"
},
  "geometry": {"coordinates":[-1.124258,52.630241],"type":"Point"}
}