{
  "type": "Feature",
  "properties": {
    "addr:full":"242 High Street, Erdington Birmingham West Midlands B23 6SN",
    "addr:housenumber":"242",
    "addr:postcode":"b23 6sn",
    "addr:street":"High Street",
    "iso:country":"GB",
    "sg:address":"242 High Street, Erdington",
    "sg:city":"Birmingham",
    "sg:classifiers":[
        {
            "category":"Food & Beverages",
            "subcategory":"Fruits & Vegetables",
            "type":"Retail Goods"
        }
    ],
    "sg:phone":"+44 121 373 4621",
    "sg:postcode":"B23 6SN",
    "sg:province":"West Midlands",
    "sg:tags":[
        "greengrocer"
    ],
    "wof:name":"Dewell Ltd.",
    "wof:placetype":"venue"
},
  "geometry": {"coordinates":[-1.8433359861,52.5218925476],"type":"Point"}
}