{
  "type": "Feature",
  "properties": {
    "addr:full":"38 Musard Road Hammersmith Greater London W6 8NW",
    "addr:housenumber":"38",
    "addr:postcode":"w6 8nw",
    "addr:street":"Musard Road",
    "iso:country":"GB",
    "sg:address":"38 Musard Road",
    "sg:city":"Hammersmith",
    "sg:classifiers":[
        {
            "category":"Organizations",
            "subcategory":"Membership Organization",
            "type":"Services"
        }
    ],
    "sg:postcode":"W6 8NW",
    "sg:province":"Greater London",
    "sg:tags":[
        "club"
    ],
    "wof:name":"Baronscourt Ltd",
    "wof:placetype":"venue"
},
  "geometry": {"coordinates":[-0.2109010071,51.485458374],"type":"Point"}
}