{
  "type": "Feature",
  "properties": {
    "addr:full":"1 Marble Alley Studley Warwickshire B80 7LD",
    "addr:housenumber":"1",
    "addr:postcode":"b80 7ld",
    "addr:street":"Marble Alley",
    "iso:country":"GB",
    "sg:address":"1 Marble Alley",
    "sg:city":"Studley",
    "sg:classifiers":[
        {
            "category":"Building & Trades",
            "subcategory":"Plumbing",
            "type":"Services"
        }
    ],
    "sg:phone":"+44 1527 852076",
    "sg:postcode":"B80 7LD",
    "sg:province":"Warwickshire",
    "sg:tags":[
        "heating"
    ],
    "wof:name":"P T M Plumbing & Heating",
    "wof:placetype":"venue"
},
  "geometry": {"coordinates":[-1.8948630095,52.2727012634],"type":"Point"}
}