{
  "type": "Feature",
  "properties": {
    "addr:full":"Unit 9 Weavers Yard, Lane End Rd Bembridge Isle of Wight PO35 5US",
    "addr:housenumber":"unit 9",
    "addr:postcode":"po35 5us",
    "addr:street":"Weavers Yard Lane End Rd",
    "iso:country":"GB",
    "sg:address":"Unit 9 Weavers Yard, Lane End Rd",
    "sg:city":"Bembridge",
    "sg:classifiers":[
        {
            "category":"Professional",
            "subcategory":"Art Services",
            "type":"Services"
        }
    ],
    "sg:phone":"+44 1983 874874",
    "sg:postcode":"PO35 5US",
    "sg:province":"Isle of Wight",
    "sg:tags":[
        "graphic",
        "designer"
    ],
    "wof:name":"Print & Design Services",
    "wof:placetype":"venue"
},
  "geometry": {"coordinates":[-1.0879570246,50.6896095276],"type":"Point"}
}