{
  "type": "Feature",
  "properties": {
    "addr:full":"31 Newport Road, Bedwas Caerphilly Caerphilly CF83 8AA",
    "addr:housenumber":"31",
    "addr:postcode":"cf83 8aa",
    "addr:street":"Newport Road",
    "iso:country":"GB",
    "sg:address":"31 Newport Road, Bedwas",
    "sg:city":"Caerphilly",
    "sg:classifiers":[
        {
            "category":"Retail",
            "subcategory":"Auto Repair",
            "type":"Services"
        }
    ],
    "sg:phone":"+44 29 2088 5205",
    "sg:postcode":"CF83 8AA",
    "sg:province":"Caerphilly",
    "sg:tags":[
        "modification",
        "garage"
    ],
    "wof:name":"John Paul Motors Ltd.",
    "wof:placetype":"venue"
},
  "geometry": {"coordinates":[-3.196658,51.590126],"type":"Point"}
}