{
  "type": "Feature",
  "properties": {
    "iso:country":"GB",
    "sg:address":"11 Chellowfield Court",
    "sg:city":"Bradford",
    "sg:classifiers":[
        {
            "category":"Social Services",
            "subcategory":"Adult Care",
            "type":"Services"
        },
        {
            "category":"Government",
            "subcategory":"Office",
            "type":"Public Place"
        }
    ],
    "sg:phone":"+44 1274 490189",
    "sg:postcode":"BD9 6NW",
    "sg:province":"West Yorkshire",
    "sg:tags":[
        "housing",
        "local",
        "sheltered"
    ],
    "wof:name":"Chellowfield Court Sheltered Housing",
    "wof:placetype":"venue"
},
  "geometry": {"coordinates":[-1.8146560192,53.8152122498],"type":"Point"}
}