{
  "type": "Feature",
  "properties": {
    "iso:country":"GB",
    "sg:address":"11 Grafton Bank, Yetholm",
    "sg:city":"Kelso",
    "sg:classifiers":[
        {
            "category":"Professional",
            "subcategory":"Computer Services",
            "type":"Services"
        }
    ],
    "sg:phone":"+44 1573 420296",
    "sg:postcode":"TD5 8SB",
    "sg:province":"Scottish Borders",
    "sg:tags":[
        "system",
        "software"
    ],
    "wof:name":"G S L (Edinburgh) Ltd.",
    "wof:placetype":"venue"
},
  "geometry": {"coordinates":[-2.28604,55.545609],"type":"Point"}
}