{
  "type": "Feature",
  "properties": {
    "addr:full":"10 Mill Street Cannock Staffordshire WS11 3DL",
    "addr:housenumber":"10",
    "addr:postcode":"ws11 3dl",
    "addr:street":"Mill Street",
    "iso:country":"GB",
    "sg:address":"10 Mill Street",
    "sg:city":"Cannock",
    "sg:classifiers":[
        {
            "category":"Professional",
            "subcategory":"Employment Agencies",
            "type":"Services"
        }
    ],
    "sg:phone":"+44 1543 500177",
    "sg:postcode":"WS11 3DL",
    "sg:province":"Staffordshire",
    "sg:tags":[
        "consultant"
    ],
    "wof:name":"Tudor Employment Agency (2001) Ltd.",
    "wof:placetype":"venue"
},
  "geometry": {"coordinates":[-2.027508,52.688641],"type":"Point"}
}