{
  "type": "Feature",
  "properties": {
    "addr:full":"Sandy La, Little Bealings Woodbridge Suffolk IP13 6LW",
    "addr:housenumber":"bealings woodbridge",
    "addr:postcode":"ip13 6lw",
    "iso:country":"GB",
    "sg:address":"Sandy La, Little Bealings",
    "sg:city":"Woodbridge",
    "sg:classifiers":[
        {
            "category":"Bars & Pubs",
            "type":"Food & Drink"
        }
    ],
    "sg:postcode":"IP13 6LW",
    "sg:province":"Suffolk",
    "sg:tags":[
        "pubs",
        "inn"
    ],
    "wof:name":"Admirals Head (The)",
    "wof:placetype":"venue"
},
  "geometry": {"coordinates":[1.2529790401,52.0851860046],"type":"Point"}
}