{
  "type": "Feature",
  "properties": {
    "iso:country":"GB",
    "sg:address":"Leeming Lane, Leeming Bar",
    "sg:city":"Northallerton",
    "sg:classifiers":[
        {
            "category":"Health Services",
            "subcategory":"Nursing And Care Facility",
            "type":"Services"
        }
    ],
    "sg:phone":"+44 1677 424014",
    "sg:postcode":"DL7 9RT",
    "sg:province":"North Yorkshire",
    "sg:tags":[
        "home"
    ],
    "wof:name":"Leeming Garth Nursing Home",
    "wof:placetype":"venue"
},
  "geometry": {"coordinates":[-1.560231,54.305321],"type":"Point"}
}