{
  "type": "Feature",
  "properties": {
    "addr:full":"147 Liverpool Road Southport Lancashire PR8 4NT",
    "addr:housenumber":"147",
    "addr:postcode":"pr8 4nt",
    "addr:street":"Liverpool Road",
    "iso:country":"GB",
    "sg:address":"147 Liverpool Road",
    "sg:city":"Southport",
    "sg:classifiers":[
        {
            "category":"Health Services",
            "subcategory":"Doctor",
            "type":"Services"
        }
    ],
    "sg:phone":"+44 1704 566277",
    "sg:postcode":"PR8 4NT",
    "sg:province":"Lancashire",
    "sg:tags":[
        "practitioners"
    ],
    "wof:name":"P J Rao",
    "wof:placetype":"venue"
},
  "geometry": {"coordinates":[-3.0124180317,53.6249237061],"type":"Point"}
}