{
  "type": "Feature",
  "properties": {
    "iso:country":"GB",
    "sg:address":"145 Soho Road",
    "sg:city":"Birmingham",
    "sg:classifiers":[
        {
            "category":"Shopping",
            "subcategory":"Gifts & Souvenirs",
            "type":"Retail Goods"
        }
    ],
    "sg:phone":"+44 121 515 3303",
    "sg:postcode":"B21 9ST",
    "sg:province":"West Midlands",
    "sg:tags":[
        "poster",
        "card"
    ],
    "wof:name":"Jolly's Greeting Shop",
    "wof:placetype":"venue"
},
  "geometry": {"coordinates":[-1.930506,52.502419],"type":"Point"}
}