{
  "type": "Feature",
  "properties": {
    "addr:full":"2 Waverley Park Terrace Edinburgh City of Edinburgh EH8 8EP",
    "addr:housenumber":"2",
    "addr:postcode":"eh8 8ep",
    "addr:street":"Waverley Park Terrace",
    "iso:country":"GB",
    "sg:address":"2 Waverley Park Terrace",
    "sg:city":"Edinburgh",
    "sg:classifiers":[
        {
            "category":"Building & Trades",
            "subcategory":"Construction",
            "type":"Services"
        }
    ],
    "sg:phone":"+44 131 661 1510",
    "sg:postcode":"EH8 8EP",
    "sg:province":"City of Edinburgh",
    "sg:tags":[
        "builder"
    ],
    "wof:name":"James Taylor",
    "wof:placetype":"venue"
},
  "geometry": {"coordinates":[-3.166406,55.95512],"type":"Point"}
}