{
  "type": "Feature",
  "properties": {
    "addr:full":"34 Magdalen St Norwich Norfolk NR3 1JE",
    "addr:housenumber":"34",
    "addr:postcode":"nr3 1je",
    "addr:street":"Magdalen St",
    "iso:country":"GB",
    "sg:address":"34 Magdalen St",
    "sg:city":"Norwich",
    "sg:classifiers":[
        {
            "category":"Health Services",
            "subcategory":"Health Practitioner",
            "type":"Services"
        }
    ],
    "sg:phone":"+44 1603 622270",
    "sg:postcode":"NR3 1JE",
    "sg:province":"Norfolk",
    "sg:tags":[
        "acupuncture"
    ],
    "wof:name":"Chinese Medical Center",
    "wof:placetype":"venue"
},
  "geometry": {"coordinates":[1.29636,52.63459],"type":"Point"}
}