{
  "type": "Feature",
  "properties": {
    "iso:country":"GB",
    "sg:address":"39a Back Brighton Street",
    "sg:city":"Barrow-in-furness",
    "sg:classifiers":[
        {
            "category":"Retail",
            "subcategory":"Auto Repair",
            "type":"Services"
        }
    ],
    "sg:phone":"+44 1229 829057",
    "sg:postcode":"LA14 5JJ",
    "sg:province":"Cumbria",
    "sg:tags":[
        "body",
        "car"
    ],
    "wof:name":"Car Repairs & Welding",
    "wof:placetype":"venue"
},
  "geometry": {"coordinates":[-3.220925,54.122761],"type":"Point"}
}