{
  "type": "Feature",
  "properties": {
    "addr:full":"Oatnell Farm, Thorndon Cross Okehampton Devon EX20 4NQ",
    "addr:housenumber":"thorndon",
    "addr:postcode":"ex20 4nq",
    "addr:street":"Cross Okehampton",
    "iso:country":"GB",
    "sg:address":"Oatnell Farm, Thorndon Cross",
    "sg:city":"Okehampton",
    "sg:classifiers":[
        {
            "category":"Farming",
            "subcategory":"Dairy Farm",
            "type":"Manufacturing & Wholesale Goods"
        }
    ],
    "sg:phone":"+44 1837 861371",
    "sg:postcode":"EX20 4NQ",
    "sg:province":"Devon",
    "wof:name":"M A & M E Sizmur",
    "wof:placetype":"venue"
},
  "geometry": {"coordinates":[-4.0817642212,50.7269363403],"type":"Point"}
}