{
  "type": "Feature",
  "properties": {
    "iso:country":"GB",
    "sg:address":"2 Lindenwood, Crockford Lane, Chineham Business Park",
    "sg:city":"Basingstoke",
    "sg:classifiers":[
        {
            "category":"Building & Trades",
            "subcategory":"Construction",
            "type":"Services"
        }
    ],
    "sg:phone":"+44 870 606 1478",
    "sg:postcode":"RG24 8QY",
    "sg:province":"Hampshire",
    "sg:tags":[
        "valve"
    ],
    "wof:name":"Metso Automation Ltd.",
    "wof:placetype":"venue"
},
  "geometry": {"coordinates":[-1.052407,51.289032],"type":"Point"}
}