{
  "type": "Feature",
  "properties": {
    "iso:country":"GB",
    "sg:address":"Hungerhill Road",
    "sg:city":"Nottingham",
    "sg:classifiers":[
        {
            "category":"Bars & Pubs",
            "type":"Food & Drink"
        },
        {
            "category":"Arena",
            "subcategory":"Sports Club",
            "type":"Entertainment"
        }
    ],
    "sg:phone":"+44 115 950 2278",
    "sg:postcode":"NG3 4QA",
    "sg:province":"Nottinghamshire",
    "sg:tags":[
        "pubs",
        "inn"
    ],
    "wof:name":"Sycamore Inn",
    "wof:placetype":"venue"
},
  "geometry": {"coordinates":[-1.142629,52.967815],"type":"Point"}
}