{
  "type": "Feature",
  "properties": {
    "iso:country":"GB",
    "sg:address":"95 Swindon Road, Stratton St Margaret",
    "sg:city":"Swindon",
    "sg:classifiers":[
        {
            "category":"Professional",
            "subcategory":"Management & Consulting",
            "type":"Services"
        }
    ],
    "sg:postcode":"SN3 4PU",
    "sg:province":"Wiltshire",
    "sg:tags":[
        "consultant",
        "specialist"
    ],
    "wof:name":"Michelle Scott Mobile",
    "wof:placetype":"venue"
},
  "geometry": {"coordinates":[-1.751601,51.579487],"type":"Point"}
}