{
  "type": "Feature",
  "properties": {
    "iso:country":"GB",
    "sg:address":"Unit 16 & 17, South Pontypool Industrial Park",
    "sg:city":"Pontypool",
    "sg:classifiers":[
        {
            "category":"Manufacturing",
            "subcategory":"Petroleum Products",
            "type":"Manufacturing & Wholesale Goods"
        }
    ],
    "sg:phone":"+44 1495 762417",
    "sg:postcode":"NP4 0LS",
    "sg:province":"Monmouthshire",
    "sg:tags":[
        "double",
        "glazing"
    ],
    "wof:name":"Beardsley U P V C Products",
    "wof:placetype":"venue"
},
  "geometry": {"coordinates":[-3.01852,51.691811],"type":"Point"}
}