{
  "type": "Feature",
  "properties": {
    "iso:country":"GB",
    "sg:address":"15 Pound Rd",
    "sg:city":"Birmingham",
    "sg:classifiers":[
        {
            "category":"Shopping",
            "subcategory":"News",
            "type":"Retail Goods"
        }
    ],
    "sg:phone":"+44 121 430 5648",
    "sg:postcode":"B14 5SB",
    "sg:province":"West Midlands",
    "sg:tags":[
        "newsagent"
    ],
    "wof:name":"Jays News",
    "wof:placetype":"venue"
},
  "geometry": {"coordinates":[-1.899224,52.404755],"type":"Point"}
}