{
  "type": "Feature",
  "properties": {
    "iso:country":"GB",
    "sg:address":"Station Works, Station Road, Fenny Compton",
    "sg:city":"Southam",
    "sg:classifiers":[
        {
            "category":"Professional",
            "type":"Services"
        }
    ],
    "sg:phone":"+44 1295 770040",
    "sg:postcode":"CV47 2WA",
    "sg:province":"Warwickshire",
    "sg:tags":[
        "car",
        "transportation"
    ],
    "wof:name":"Ontime Automotive (Specialist Operations) Ltd.",
    "wof:placetype":"venue"
},
  "geometry": {"coordinates":[-1.391019,52.16758],"type":"Point"}
}