{
  "type": "Feature",
  "properties": {
    "iso:country":"GB",
    "sg:address":"5 The Craiglands",
    "sg:city":"Sunderland",
    "sg:classifiers":[
        {
            "category":"Social Services",
            "subcategory":"Job Training",
            "type":"Services"
        }
    ],
    "sg:phone":"+44 191 528 1613",
    "sg:postcode":"SR2 9AD",
    "sg:province":"Tyne and Wear",
    "sg:tags":[
        "translator",
        "interpreter"
    ],
    "wof:name":"Walker Angela Interpreting & Translating Services",
    "wof:placetype":"venue"
},
  "geometry": {"coordinates":[-1.391046,54.891621],"type":"Point"}
}