{
  "type": "Feature",
  "properties": {
    "iso:country":"GB",
    "sg:address":"106 Down Street",
    "sg:city":"West Molesey",
    "sg:classifiers":[
        {
            "category":"Wholesale",
            "subcategory":"Machinery & Supplies",
            "type":"Manufacturing & Wholesale Goods"
        }
    ],
    "sg:phone":"+44 20 8941 2818",
    "sg:postcode":"KT8 2TA",
    "sg:province":"Greater London",
    "sg:tags":[
        "industrial",
        "commercial"
    ],
    "wof:name":"Pharmaceutical Machine Sales Ltd.",
    "wof:placetype":"venue"
},
  "geometry": {"coordinates":[-0.374934,51.397102],"type":"Point"}
}