{
  "type": "Feature",
  "properties": {
    "addr:full":"20 Broadway London Greater London W13 0SR",
    "addr:housenumber":"20",
    "addr:postcode":"w13 0sr",
    "addr:street":"Broadway",
    "iso:country":"GB",
    "sg:address":"20 Broadway",
    "sg:city":"London",
    "sg:classifiers":[
        {
            "category":"Shopping",
            "subcategory":"Clothing, Apparel, & Fashions",
            "type":"Retail Goods"
        }
    ],
    "sg:phone":"+44 20 8579 8228",
    "sg:postcode":"W13 0SR",
    "sg:province":"Greater London",
    "sg:tags":[
        "shop"
    ],
    "wof:name":"Mk One",
    "wof:placetype":"venue"
},
  "geometry": {"coordinates":[-0.320836,51.510746],"type":"Point"}
}