{
  "type": "Feature",
  "properties": {
    "addr:full":"Grey's Court, Grey Street Newcastle-upon-tyne Tyne and Wear NE1 6EE",
    "addr:postcode":"ne1 6ee",
    "addr:street":"Grey Street",
    "iso:country":"GB",
    "sg:address":"Grey's Court, Grey Street",
    "sg:city":"Newcastle-upon-tyne",
    "sg:classifiers":[
        {
            "category":"Bars & Pubs",
            "subcategory":"Nightclub",
            "type":"Food & Drink"
        }
    ],
    "sg:phone":"+44 191 261 4066",
    "sg:postcode":"NE1 6EE",
    "sg:province":"Tyne and Wear",
    "sg:tags":[
        "club",
        "night",
        "activity"
    ],
    "wof:name":"EASTEYE LTD",
    "wof:placetype":"venue"
},
  "geometry": {"coordinates":[-1.61175,54.971691],"type":"Point"}
}