{
  "type": "Feature",
  "properties": {
    "addr:full":"155 Marshland Road, Moorends Doncaster East Riding of Yorkshire DN8 4SB",
    "addr:housenumber":"155",
    "addr:postcode":"dn8 4sb",
    "addr:street":"Marshland Road;Riding",
    "iso:country":"GB",
    "sg:address":"155 Marshland Road, Moorends",
    "sg:city":"Doncaster",
    "sg:classifiers":[
        {
            "category":"Fast Food",
            "type":"Food & Drink"
        }
    ],
    "sg:postcode":"DN8 4SB",
    "sg:province":"East Riding of Yorkshire",
    "sg:tags":[
        "away",
        "take"
    ],
    "wof:name":"Balti King",
    "wof:placetype":"venue"
},
  "geometry": {"coordinates":[-0.9512569904,53.6287345886],"type":"Point"}
}