{
  "type": "Feature",
  "properties": {
    "addr:full":"4 Coalway Lane North, Swalwell Newcastle-upon-tyne Durham NE16 3EY",
    "addr:housenumber":"4",
    "addr:postcode":"ne16 3ey",
    "addr:street":"Coalway Lane North",
    "iso:country":"GB",
    "sg:address":"4 Coalway Lane North, Swalwell",
    "sg:city":"Newcastle-upon-tyne",
    "sg:classifiers":[
        {
            "category":"Health Services",
            "subcategory":"Nursing And Care Facility",
            "type":"Services"
        }
    ],
    "sg:phone":"+44 191 488 6877",
    "sg:postcode":"NE16 3EY",
    "sg:province":"Durham",
    "sg:tags":[
        "home"
    ],
    "wof:name":"Coalway Lane Nursing Home",
    "wof:placetype":"venue"
},
  "geometry": {"coordinates":[-1.679254055,54.9532775879],"type":"Point"}
}