{
  "type": "Feature",
  "properties": {
    "addr:full":"4 Thirlmere Gardens, Kirksandall Doncaster South Yorkshire DN3 1LB",
    "addr:housenumber":"4",
    "addr:postcode":"dn3 1lb",
    "addr:street":"Thirlmere Gardens Kirksandall",
    "iso:country":"GB",
    "sg:address":"4 Thirlmere Gardens, Kirksandall",
    "sg:city":"Doncaster",
    "sg:classifiers":[
        {
            "category":"Home & Garden",
            "subcategory":"Home Furnishings",
            "type":"Retail Goods"
        },
        {
            "category":"Professional",
            "subcategory":"Business Services",
            "type":"Services"
        }
    ],
    "sg:postcode":"DN3 1LB",
    "sg:province":"South Yorkshire",
    "sg:tags":[
        "agent",
        "export",
        "awning",
        "import",
        "canopy",
        "blinds"
    ],
    "wof:name":"A T & B Blinds",
    "wof:placetype":"venue"
},
  "geometry": {"coordinates":[-1.0668050051,53.5595321655],"type":"Point"}
}