{
  "type": "Feature",
  "properties": {
    "addr:full":"36 Ashgrove Road Ashford Greater London TW15 1PJ",
    "addr:housenumber":"36",
    "addr:postcode":"tw15 1pj",
    "addr:street":"Ashgrove Road",
    "iso:country":"GB",
    "sg:address":"36 Ashgrove Road",
    "sg:city":"Ashford",
    "sg:classifiers":[
        {
            "category":"Utilities",
            "subcategory":"Refuse",
            "type":"Services"
        }
    ],
    "sg:phone":"+44 1784 257679",
    "sg:postcode":"TW15 1PJ",
    "sg:province":"Greater London",
    "sg:tags":[
        "skip",
        "hire"
    ],
    "wof:name":"A & J Skips",
    "wof:placetype":"venue"
},
  "geometry": {"coordinates":[-0.4379999936,51.4292793274],"type":"Point"}
}