{
  "type": "Feature",
  "properties": {
    "addr:full":"Robin Hood Chase Nottingham Nottinghamshire NG3 4EZ",
    "addr:postcode":"ng3 4ez",
    "addr:street":"Robin Hood Chase",
    "iso:country":"GB",
    "sg:address":"Robin Hood Chase",
    "sg:city":"Nottingham",
    "sg:classifiers":[
        {
            "category":"Education",
            "subcategory":"Library",
            "type":"Public Place"
        }
    ],
    "sg:phone":"+44 115 915 6941",
    "sg:postcode":"NG3 4EZ",
    "sg:province":"Nottinghamshire",
    "sg:tags":[
        "book"
    ],
    "wof:name":"St Anns Library",
    "wof:placetype":"venue"
},
  "geometry": {"coordinates":[-1.1439640522,52.9656982422],"type":"Point"}
}