{
  "type": "Feature",
  "properties": {
    "addr:full":"514 Lordship Lane London Greater London N22 5DD",
    "addr:housenumber":"514",
    "addr:postcode":"n22 5dd",
    "addr:street":"Lordship Lane",
    "iso:country":"GB",
    "sg:address":"514 Lordship Lane",
    "sg:city":"London",
    "sg:classifiers":[
        {
            "category":"Health Services",
            "subcategory":"Optometrist",
            "type":"Services"
        },
        {
            "category":"Shopping",
            "subcategory":"Optician",
            "type":"Retail Goods"
        }
    ],
    "sg:phone":"+44 20 8888 8715",
    "sg:postcode":"N22 5DD",
    "sg:province":"Greater London",
    "sg:tags":[
        "ophthalmic"
    ],
    "wof:name":"Alan Ray",
    "wof:placetype":"venue"
},
  "geometry": {"coordinates":[-0.094418,51.598286],"type":"Point"}
}