{
  "type": "Feature",
  "properties": {
    "iso:country":"GB",
    "sg:address":"103-105 Gilesgate",
    "sg:city":"Durham",
    "sg:classifiers":[
        {
            "category":"Home & Garden",
            "subcategory":"Home Furnishings",
            "type":"Retail Goods"
        }
    ],
    "sg:phone":"+44 191 386 6661",
    "sg:postcode":"DH1 1JA",
    "sg:province":"Durham",
    "sg:tags":[
        "furnishers",
        "planner",
        "kitchen"
    ],
    "wof:name":"First Choice Wholesale Kitchen Appliances",
    "wof:placetype":"venue"
},
  "geometry": {"coordinates":[-1.5571370125,54.7791900635],"type":"Point"}
}