{
  "type": "Feature",
  "properties": {
    "addr:full":"76-78 Church Street Croydon Surrey CR0 1RB",
    "addr:housenumber":"76-78",
    "addr:postcode":"cr0 1rb",
    "addr:street":"Church Street",
    "iso:country":"GB",
    "sg:address":"76-78 Church Street",
    "sg:city":"Croydon",
    "sg:classifiers":[
        {
            "category":"Home & Garden",
            "subcategory":"Hardware",
            "type":"Retail Goods"
        }
    ],
    "sg:phone":"+44 20 8681 0713",
    "sg:postcode":"CR0 1RB",
    "sg:province":"Surrey",
    "sg:tags":[
        "centre",
        "improvement"
    ],
    "wof:name":"A G Stanley Ltd.",
    "wof:placetype":"venue"
},
  "geometry": {"coordinates":[-0.1035630032,51.3735923767],"type":"Point"}
}