{
  "type": "Feature",
  "properties": {
    "addr:full":"119 Egerton Rd Blackpool Lancashire FY1 2NL",
    "addr:housenumber":"119",
    "addr:postcode":"fy1 2nl",
    "addr:street":"Egerton Rd",
    "iso:country":"GB",
    "sg:address":"119 Egerton Rd",
    "sg:city":"Blackpool",
    "sg:classifiers":[
        {
            "category":"Food & Beverages",
            "subcategory":"Fruits & Vegetables",
            "type":"Retail Goods"
        }
    ],
    "sg:postcode":"FY1 2NL",
    "sg:province":"Lancashire",
    "sg:tags":[
        "greengrocer"
    ],
    "wof:name":"Robinson,G J,",
    "wof:placetype":"venue"
},
  "geometry": {"coordinates":[-3.0516529083,53.8252449036],"type":"Point"}
}