{
  "type": "Feature",
  "properties": {
    "addr:full":"85 Milestone Drive, Hagley Stourbridge West Midlands DY9 0LH",
    "addr:housenumber":"85",
    "addr:postcode":"dy9 0lh",
    "addr:street":"Milestone Drive",
    "iso:country":"GB",
    "sg:address":"85 Milestone Drive, Hagley",
    "sg:city":"Stourbridge",
    "sg:classifiers":[
        {
            "category":"Government",
            "subcategory":"Post Office",
            "type":"Public Place"
        }
    ],
    "sg:phone":"+44 1562 720176",
    "sg:postcode":"DY9 0LH",
    "sg:province":"West Midlands",
    "sg:tags":[
        "messenger",
        "courier"
    ],
    "wof:name":"Partridge Transport Services",
    "wof:placetype":"venue"
},
  "geometry": {"coordinates":[-2.151618,52.415962],"type":"Point"}
}