{
  "type": "Feature",
  "properties": {
    "iso:country":"GB",
    "sg:address":"Waterhead",
    "sg:city":"Ambleside",
    "sg:classifiers":[
        {
            "category":"Shopping",
            "subcategory":"Gifts & Souvenirs",
            "type":"Retail Goods"
        }
    ],
    "sg:postcode":"LA22 0EY",
    "sg:province":"Cumbria",
    "sg:tags":[
        "shop"
    ],
    "wof:name":"Waterhead Shell Shop",
    "wof:placetype":"venue"
},
  "geometry": {"coordinates":[-2.9608900547,54.4222068787],"type":"Point"}
}