{
  "type": "Feature",
  "properties": {
    "addr:full":"53 The Maltings St Albans Hertfordshire AL1 3HL",
    "addr:housenumber":"53",
    "addr:postcode":"al1 3hl",
    "addr:street":"The Maltings",
    "iso:country":"GB",
    "sg:address":"53 The Maltings",
    "sg:city":"St Albans",
    "sg:classifiers":[
        {
            "category":"Personal",
            "subcategory":"Beauty Salon",
            "type":"Services"
        }
    ],
    "sg:phone":"+44 1727 866788",
    "sg:postcode":"AL1 3HL",
    "sg:province":"Hertfordshire",
    "sg:tags":[
        "unisex",
        "hairdresser"
    ],
    "wof:name":"Clipso Hairdressers",
    "wof:placetype":"venue"
},
  "geometry": {"coordinates":[-0.3387709856,51.751789093],"type":"Point"}
}