{
  "type": "Feature",
  "properties": {
    "addr:full":"Unit 1 20 Stannington Rd Sheffield South Yorkshire S6 6AB",
    "addr:housenumber":"unit;20",
    "addr:postcode":"s6 6ab",
    "addr:street":"Stannington Rd",
    "iso:country":"GB",
    "sg:address":"Unit 1 20 Stannington Rd",
    "sg:city":"Sheffield",
    "sg:classifiers":[
        {
            "category":"Home & Garden",
            "subcategory":"Building Materials",
            "type":"Retail Goods"
        }
    ],
    "sg:phone":"+44 114 285 3606",
    "sg:postcode":"S6 6AB",
    "sg:province":"South Yorkshire",
    "sg:tags":[
        "ironwork",
        "diy",
        "wrought"
    ],
    "wof:name":"Tudor Gates",
    "wof:placetype":"venue"
},
  "geometry": {"coordinates":[-1.5492990017,53.3944702148],"type":"Point"}
}