{
  "type": "Feature",
  "properties": {
    "addr:full":"12 Mallocks Close, Tipton St John Sidmouth Devon EX10 0AP",
    "addr:housenumber":"12",
    "addr:postcode":"ex10 0ap",
    "addr:street":"Mallocks Close Tipton St",
    "iso:country":"GB",
    "sg:address":"12 Mallocks Close, Tipton St John",
    "sg:city":"Sidmouth",
    "sg:classifiers":[
        {
            "category":"Building & Trades",
            "subcategory":"Construction",
            "type":"Services"
        }
    ],
    "sg:phone":"+44 1404 814149",
    "sg:postcode":"EX10 0AP",
    "sg:province":"Devon",
    "sg:tags":[
        "dry",
        "plastering",
        "plasterers",
        "lining",
        "related",
        "screeders"
    ],
    "wof:name":"P MARLES",
    "wof:placetype":"venue"
},
  "geometry": {"coordinates":[-3.285447,50.719906],"type":"Point"}
}