{
  "type": "Feature",
  "properties": {
    "addr:full":"Market St Plymouth Devon PL8 2EB",
    "addr:postcode":"pl8 2eb",
    "addr:street":"Market St",
    "iso:country":"GB",
    "sg:address":"Market St",
    "sg:city":"Plymouth",
    "sg:classifiers":[
        {
            "category":"Social Services",
            "subcategory":"Retirement Home",
            "type":"Services"
        }
    ],
    "sg:phone":"+44 1752 880445",
    "sg:postcode":"PL8 2EB",
    "sg:province":"Devon",
    "sg:tags":[
        "rest"
    ],
    "wof:name":"Villa The",
    "wof:placetype":"venue"
},
  "geometry": {"coordinates":[-3.9969580173,50.3487701416],"type":"Point"}
}