{
  "type": "Feature",
  "properties": {
    "addr:full":"Waterlip Ho, Waterlip Shepton Mallet Somerset BA4 4RN",
    "addr:postcode":"ba4 4rn",
    "iso:country":"GB",
    "sg:address":"Waterlip Ho, Waterlip",
    "sg:city":"Shepton Mallet",
    "sg:classifiers":[
        {
            "category":"Shopping",
            "subcategory":"Pets & Pet Supplies",
            "type":"Retail Goods"
        }
    ],
    "sg:postcode":"BA4 4RN",
    "sg:province":"Somerset",
    "sg:tags":[
        "food"
    ],
    "wof:name":"Agri-Tech",
    "wof:placetype":"venue"
},
  "geometry": {"coordinates":[-2.4906330109,51.2003746033],"type":"Point"}
}