{
  "type": "Feature",
  "properties": {
    "iso:country":"GB",
    "sg:address":"Berries View, Banks Green",
    "sg:city":"Redditch",
    "sg:classifiers":[
        {
            "category":"Autos & Motor Vehicles",
            "subcategory":"Auto Supplies",
            "type":"Retail Goods"
        }
    ],
    "sg:phone":"+44 1527 545982",
    "sg:postcode":"B97 5SU",
    "sg:province":"Warwickshire",
    "sg:tags":[
        "guard",
        "grille"
    ],
    "wof:name":"H & R (Developments)",
    "wof:placetype":"venue"
},
  "geometry": {"coordinates":[-2.009279,52.300243],"type":"Point"}
}