{
  "type": "Feature",
  "properties": {
    "addr:full":"94 St Andrews Road Malvern Herefordshire WR14 3PP",
    "addr:housenumber":"94",
    "addr:postcode":"wr14 3pp",
    "addr:street":"St Andrews Road",
    "iso:country":"GB",
    "sg:address":"94 St Andrews Road",
    "sg:city":"Malvern",
    "sg:classifiers":[
        {
            "category":"Home & Garden",
            "subcategory":"Carpets & Floor Coverings",
            "type":"Retail Goods"
        }
    ],
    "sg:phone":"+44 1684 563658",
    "sg:postcode":"WR14 3PP",
    "sg:province":"Herefordshire",
    "sg:tags":[
        "carpets",
        "rug",
        "matting"
    ],
    "wof:name":"B M Macey",
    "wof:placetype":"venue"
},
  "geometry": {"coordinates":[-2.320777,52.098282],"type":"Point"}
}