{
  "type": "Feature",
  "properties": {
    "addr:full":"46 Grange Rd Chessington Surrey KT9 1EX",
    "addr:housenumber":"46",
    "addr:postcode":"kt9 1ex",
    "addr:street":"Grange Rd",
    "iso:country":"GB",
    "sg:address":"46 Grange Rd",
    "sg:city":"Chessington",
    "sg:classifiers":[
        {
            "category":"Organizations",
            "subcategory":"Religious Organization",
            "type":"Services"
        }
    ],
    "sg:phone":"+44 20 8397 8427",
    "sg:postcode":"KT9 1EX",
    "sg:province":"Surrey",
    "sg:tags":[
        "organisation",
        "place",
        "worship"
    ],
    "sg:website":"http://www.gideons.org",
    "wof:name":"Gideons International",
    "wof:placetype":"venue"
},
  "geometry": {"coordinates":[-0.303887,51.370682],"type":"Point"}
}