{
  "type": "Feature",
  "properties": {
    "iso:country":"GB",
    "sg:address":"29 Wolfa Street",
    "sg:city":"Derby",
    "sg:classifiers":[
        {
            "category":"Building & Trades",
            "subcategory":"Plumbing",
            "type":"Services"
        }
    ],
    "sg:postcode":"DE22 3SE",
    "sg:province":"Derbyshire",
    "sg:tags":[
        "heating"
    ],
    "wof:name":"A C Hilton & Sons Ltd.",
    "wof:placetype":"venue"
},
  "geometry": {"coordinates":[-1.484978,52.919552],"type":"Point"}
}