{
  "type": "Feature",
  "properties": {
    "iso:country":"GB",
    "sg:address":"Hill Farm, Halse",
    "sg:city":"Brackley",
    "sg:classifiers":[
        {
            "category":"Farming",
            "subcategory":"Farm",
            "type":"Manufacturing & Wholesale Goods"
        }
    ],
    "sg:phone":"+44 1280 703300",
    "sg:postcode":"NN13 6DY",
    "sg:province":"Buckinghamshire",
    "sg:tags":[
        "mixed",
        "crop"
    ],
    "wof:name":"Towler & Partner",
    "wof:placetype":"venue"
},
  "geometry": {"coordinates":[-1.1764489412,52.0595092773],"type":"Point"}
}