{
  "type": "Feature",
  "properties": {
    "addr:full":"P.o. Box 23213 New Cross Greater London SE14 6WF",
    "addr:housenumber":"p.o. box 23213",
    "addr:postcode":"se14 6wf",
    "addr:street":"Cross",
    "iso:country":"GB",
    "sg:address":"P.o. Box 23213",
    "sg:city":"New Cross",
    "sg:classifiers":[
        {
            "category":"Professional",
            "subcategory":"Employment Agencies",
            "type":"Services"
        }
    ],
    "sg:phone":"+44 20 8469 3762",
    "sg:postcode":"SE14 6WF",
    "sg:province":"Greater London",
    "sg:tags":[
        "introduction"
    ],
    "wof:name":"Dates Unlimited",
    "wof:placetype":"venue"
},
  "geometry": {"coordinates":[-0.040459,51.47496],"type":"Point"}
}