{
  "type": "Feature",
  "properties": {
    "iso:country":"GB",
    "sg:address":"5 Vicarage Road",
    "sg:city":"Sidmouth",
    "sg:classifiers":[
        {
            "category":"Building & Trades",
            "subcategory":"Construction",
            "type":"Services"
        }
    ],
    "sg:phone":"+44 1395 577872",
    "sg:postcode":"EX10 8TS",
    "sg:province":"Devon",
    "sg:tags":[
        "builder"
    ],
    "wof:name":"T A G Builders",
    "wof:placetype":"venue"
},
  "geometry": {"coordinates":[-3.238001,50.683456],"type":"Point"}
}