{
  "type": "Feature",
  "properties": {
    "addr:full":"220 Leigh Road Wimborne Dorset BH21 2BZ",
    "addr:housenumber":"220",
    "addr:postcode":"bh21 2bz",
    "addr:street":"Leigh Road",
    "iso:country":"GB",
    "sg:address":"220 Leigh Road",
    "sg:city":"Wimborne",
    "sg:classifiers":[
        {
            "category":"Retail",
            "subcategory":"Auto Repair",
            "type":"Services"
        }
    ],
    "sg:phone":"+44 1202 885200",
    "sg:postcode":"BH21 2BZ",
    "sg:province":"Dorset",
    "sg:tags":[
        "electrician"
    ],
    "wof:name":"A J W Electrics",
    "wof:placetype":"venue"
},
  "geometry": {"coordinates":[-1.9635419846,50.7990455627],"type":"Point"}
}