{
  "type": "Feature",
  "properties": {
    "addr:full":"Desford Crossroads Hinckley Road, Desford Leicester Leicestershire LE9 9JE",
    "addr:postcode":"le9 9je",
    "addr:street":"Desford;Hinckley Road",
    "iso:country":"GB",
    "sg:address":"Desford Crossroads Hinckley Road, Desford",
    "sg:city":"Leicester",
    "sg:classifiers":[
        {
            "category":"Autos & Motor Vehicles",
            "subcategory":"Fuel & Gas Station",
            "type":"Retail Goods"
        }
    ],
    "sg:phone":"+44 1455 822310",
    "sg:postcode":"LE9 9JE",
    "sg:province":"Leicestershire",
    "sg:tags":[
        "petrol",
        "filling"
    ],
    "wof:name":"Desford Crossroads Service Station",
    "wof:placetype":"venue"
},
  "geometry": {"coordinates":[-1.296534,52.625858],"type":"Point"}
}