{
  "type": "Feature",
  "properties": {
    "iso:country":"GB",
    "sg:address":"Titwood Road, Newton Mearns",
    "sg:city":"Glasgow",
    "sg:classifiers":[
        {
            "category":"Transit Center",
            "subcategory":"Passenger",
            "type":"Transportation"
        },
        {
            "category":"Retail",
            "subcategory":"Pet Boarding",
            "type":"Services"
        }
    ],
    "sg:phone":"+44 141 639 7034",
    "sg:postcode":"G77 6RP",
    "sg:province":"East Ayrshire",
    "sg:tags":[
        "kennel",
        "catteries"
    ],
    "wof:name":"Glen Earn Cattery",
    "wof:placetype":"venue"
},
  "geometry": {"coordinates":[-4.331814,55.759621],"type":"Point"}
}