{
  "type": "Feature",
  "properties": {
    "iso:country":"GB",
    "sg:address":"90 Narborough Road",
    "sg:city":"Leicester",
    "sg:classifiers":[
        {
            "category":"Shopping",
            "subcategory":"Musical Instruments",
            "type":"Retail Goods"
        }
    ],
    "sg:phone":"+44 116 233 8333",
    "sg:postcode":"LE3 0BS",
    "sg:province":"Leicestershire",
    "sg:tags":[
        "music",
        "sheet"
    ],
    "wof:name":"The Rock House",
    "wof:placetype":"venue"
},
  "geometry": {"coordinates":[-1.149701,52.627888],"type":"Point"}
}