{
  "type": "Feature",
  "properties": {
    "addr:full":"81-84 Chalk Farm Road London Greater London NW1 8AR",
    "addr:housenumber":"81-84",
    "addr:postcode":"nw1 8ar",
    "addr:street":"Chalk Farm Road",
    "iso:country":"GB",
    "sg:address":"81-84 Chalk Farm Road",
    "sg:city":"London",
    "sg:classifiers":[
        {
            "category":"Sports & Exercise",
            "subcategory":"Gym",
            "type":"Entertainment"
        }
    ],
    "sg:phone":"+44 20 7284 0004",
    "sg:postcode":"NW1 8AR",
    "sg:province":"Greater London",
    "sg:tags":[
        "fitness",
        "health",
        "centre"
    ],
    "wof:name":"Fitness First",
    "wof:placetype":"venue"
},
  "geometry": {"coordinates":[-0.1514189988,51.5434417725],"type":"Point"}
}