{
  "type": "Feature",
  "properties": {
    "addr:full":"Unit 2 Hamilton St Carluke South Lanarkshire ML8 4AB",
    "addr:housenumber":"unit 2",
    "addr:postcode":"ml8 4ab",
    "addr:street":"Hamilton St",
    "iso:country":"GB",
    "sg:address":"Unit 2 Hamilton St",
    "sg:city":"Carluke",
    "sg:classifiers":[
        {
            "category":"Home & Garden",
            "subcategory":"Building Materials",
            "type":"Retail Goods"
        }
    ],
    "sg:phone":"+44 1555 772626",
    "sg:postcode":"ML8 4AB",
    "sg:province":"South Lanarkshire",
    "sg:tags":[
        "furnishers",
        "bathroom",
        "planner"
    ],
    "wof:name":"O-Kay Building Services",
    "wof:placetype":"venue"
},
  "geometry": {"coordinates":[-3.838299036,55.7324905396],"type":"Point"}
}