{
  "type": "Feature",
  "properties": {
    "addr:full":"2nd Floor Offices, 68 High Street Lymington Hampshire SO41 9AL",
    "addr:housenumber":"2nd;68",
    "addr:postcode":"so41 9al",
    "addr:street":"High Street",
    "iso:country":"GB",
    "sg:address":"2nd Floor Offices, 68 High Street",
    "sg:city":"Lymington",
    "sg:classifiers":[
        {
            "category":"Social Services",
            "subcategory":"Retirement Home",
            "type":"Services"
        },
        {
            "category":"Real Estate",
            "subcategory":"Architect",
            "type":"Services"
        }
    ],
    "sg:phone":"+44 1590 672000",
    "sg:postcode":"SO41 9AL",
    "sg:province":"Hampshire",
    "sg:tags":[
        "naval"
    ],
    "wof:name":"Rogers Yacht Design Ltd",
    "wof:placetype":"venue"
},
  "geometry": {"coordinates":[-1.538911,50.758938],"type":"Point"}
}