{
  "type": "Feature",
  "properties": {
    "addr:full":"165 London Road, North End Portsmouth Hampshire PO2 9AA",
    "addr:housenumber":"165",
    "addr:postcode":"hampshire po2 9aa",
    "addr:street":"London Road",
    "iso:country":"GB",
    "sg:address":"165 London Road, North End",
    "sg:city":"Portsmouth",
    "sg:classifiers":[
        {
            "category":"Insurance",
            "subcategory":"Insurance Agent",
            "type":"Services"
        }
    ],
    "sg:phone":"+44 23 9266 4420",
    "sg:postcode":"PO2 9AA",
    "sg:province":"Hampshire",
    "sg:tags":[
        "broker"
    ],
    "wof:name":"Bennetts Insurance",
    "wof:placetype":"venue"
},
  "geometry": {"coordinates":[-1.0788480043,50.8183555603],"type":"Point"}
}