{
  "type": "Feature",
  "properties": {
    "iso:country":"GB",
    "sg:address":"136 Wheathead Lane",
    "sg:city":"Keighley",
    "sg:classifiers":[
        {
            "category":"Building & Trades",
            "subcategory":"Construction",
            "type":"Services"
        }
    ],
    "sg:phone":"+44 1535 607614",
    "sg:postcode":"BD22 6LU",
    "sg:province":"North Yorkshire",
    "sg:tags":[
        "decorator",
        "painter"
    ],
    "wof:name":"Brian Williams",
    "wof:placetype":"venue"
},
  "geometry": {"coordinates":[-1.9327089787,53.8587341309],"type":"Point"}
}