{
  "type": "Feature",
  "properties": {
    "iso:country":"GB",
    "sg:address":"37 Lancaster Avenue",
    "sg:city":"London",
    "sg:classifiers":[
        {
            "category":"Social Services",
            "subcategory":"Retirement Home",
            "type":"Services"
        }
    ],
    "sg:phone":"+44 20 8670 6960",
    "sg:postcode":"SE27 9EL",
    "sg:province":"Greater London",
    "sg:tags":[
        "residential",
        "care"
    ],
    "wof:name":"Merryvale Residential Home",
    "wof:placetype":"venue"
},
  "geometry": {"coordinates":[-0.1016639993,51.4376220703],"type":"Point"}
}