{
  "type": "Feature",
  "properties": {
    "iso:country":"GB",
    "sg:address":"Marshfield, Kirkgate",
    "sg:city":"Settle",
    "sg:classifiers":[
        {
            "category":"Arena",
            "subcategory":"Sports Club",
            "type":"Entertainment"
        }
    ],
    "sg:phone":"+44 1729 822171",
    "sg:postcode":"BD24 9BP",
    "sg:province":"North Yorkshire",
    "wof:name":"Settle Cricket Club",
    "wof:placetype":"venue"
},
  "geometry": {"coordinates":[-2.277606,54.069759],"type":"Point"}
}