{
  "type": "Feature",
  "properties": {
    "iso:country":"GB",
    "sg:address":"Ellerslie House, Queens Road, Edgerton",
    "sg:city":"Huddersfield",
    "sg:classifiers":[
        {
            "category":"Real Estate",
            "subcategory":"Architect",
            "type":"Services"
        }
    ],
    "sg:phone":"+44 1484 544191",
    "sg:postcode":"HD2 2AQ",
    "sg:province":"West Yorkshire",
    "wof:name":"Anthony Dann Associates",
    "wof:placetype":"venue"
},
  "geometry": {"coordinates":[-1.7984529734,53.6549301147],"type":"Point"}
}