{
  "type": "Feature",
  "properties": {
    "addr:full":"Grindahoul, Brae Shetland Shetland Islands ZE2 9XS",
    "addr:postcode":"ze2 9xs",
    "addr:street":"Grindahoul Brae;Shetland",
    "iso:country":"GB",
    "sg:address":"Grindahoul, Brae",
    "sg:city":"Shetland",
    "sg:classifiers":[
        {
            "category":"Government",
            "subcategory":"Office",
            "type":"Public Place"
        },
        {
            "category":"Social Services",
            "subcategory":"Adult Care",
            "type":"Services"
        },
        {
            "category":"Social Services",
            "subcategory":"Retirement Home",
            "type":"Services"
        }
    ],
    "sg:phone":"+44 1806 522573",
    "sg:postcode":"ZE2 9XS",
    "sg:province":"Shetland Islands",
    "sg:tags":[
        "housing",
        "local",
        "accommodation",
        "sheltered"
    ],
    "wof:name":"Grindahoul Sheltered Housing",
    "wof:placetype":"venue"
},
  "geometry": {"coordinates":[-1.235916,60.349518],"type":"Point"}
}