{
  "type": "Feature",
  "properties": {
    "addr:full":"104 Copland Street Dalbeattie Dumfries and Galloway DG5 4EU",
    "addr:housenumber":"104",
    "addr:postcode":"dg5 4eu",
    "addr:street":"Copland Street",
    "iso:country":"GB",
    "sg:address":"104 Copland Street",
    "sg:city":"Dalbeattie",
    "sg:classifiers":[
        {
            "category":"Building & Trades",
            "subcategory":"Construction",
            "type":"Services"
        }
    ],
    "sg:phone":"+44 1556 610836",
    "sg:postcode":"DG5 4EU",
    "sg:province":"Dumfries and Galloway",
    "sg:tags":[
        "builder"
    ],
    "wof:name":"D Warren",
    "wof:placetype":"venue"
},
  "geometry": {"coordinates":[-3.8189539909,54.9300460815],"type":"Point"}
}