{
  "type": "Feature",
  "properties": {
    "addr:full":"Gobions Av Romford Essex RM5 3SP",
    "addr:postcode":"rm5 3sp",
    "addr:street":"Av",
    "iso:country":"GB",
    "sg:address":"Gobions Av",
    "sg:city":"Romford",
    "sg:classifiers":[
        {
            "category":"Bars & Pubs",
            "type":"Food & Drink"
        }
    ],
    "sg:phone":"+44 1708 749995",
    "sg:postcode":"RM5 3SP",
    "sg:province":"Essex",
    "sg:tags":[
        "pubs",
        "inn"
    ],
    "wof:name":"Pickled Newt The",
    "wof:placetype":"venue"
},
  "geometry": {"coordinates":[0.1739799976,51.6015052795],"type":"Point"}
}