{
  "type": "Feature",
  "properties": {
    "addr:full":"Philpot La Woking Surrey GU24 8HE",
    "addr:postcode":"gu24 8he",
    "iso:country":"GB",
    "sg:address":"Philpot La",
    "sg:city":"Woking",
    "sg:classifiers":[
        {
            "category":"Health Services",
            "subcategory":"Nursing And Care Facility",
            "type":"Services"
        }
    ],
    "sg:phone":"+44 1276 857997",
    "sg:postcode":"GU24 8HE",
    "sg:province":"Surrey",
    "sg:tags":[
        "home"
    ],
    "wof:name":"Highfield House Nursing Home",
    "wof:placetype":"venue"
},
  "geometry": {"coordinates":[-0.5747720003,51.3447685242],"type":"Point"}
}