{
  "type": "Feature",
  "properties": {
    "iso:country":"GB",
    "sg:address":"36b Western Road",
    "sg:city":"Bexhill-on-sea",
    "sg:classifiers":[
        {
            "category":"Shopping",
            "subcategory":"Thrift Store",
            "type":"Retail Goods"
        }
    ],
    "sg:phone":"+44 1424 212591",
    "sg:postcode":"TN40 1DY",
    "sg:province":"East Sussex",
    "sg:tags":[
        "shop",
        "charity"
    ],
    "wof:name":"Sue Ryder Foundation",
    "wof:placetype":"venue"
},
  "geometry": {"coordinates":[0.471238,50.84024],"type":"Point"}
}