{
  "type": "Feature",
  "properties": {
    "addr:full":"27 Toronto Rd, Buckland Portsmouth Hampshire PO2 7QB",
    "addr:housenumber":"27",
    "addr:postcode":"hampshire po2 7qb",
    "addr:street":"Toronto Rd",
    "iso:country":"GB",
    "sg:address":"27 Toronto Rd, Buckland",
    "sg:city":"Portsmouth",
    "sg:classifiers":[
        {
            "category":"Professional",
            "subcategory":"Art Services",
            "type":"Services"
        }
    ],
    "sg:phone":"+44 20 8676 8092",
    "sg:postcode":"PO2 7QB",
    "sg:province":"Hampshire",
    "sg:tags":[
        "photographer"
    ],
    "wof:name":"Microfiche Data Systems Ltd",
    "wof:placetype":"venue"
},
  "geometry": {"coordinates":[-1.076445,50.809208],"type":"Point"}
}