{
  "type": "Feature",
  "properties": {
    "addr:full":"Unit 4, Bermondsey Trading Estate, Rotherhite New Road London Greater London SE16 3LL",
    "addr:housenumber":"unit 4",
    "addr:postcode":"se16 3ll",
    "addr:street":"Trading;New Road",
    "iso:country":"GB",
    "sg:address":"Unit 4, Bermondsey Trading Estate, Rotherhite New Road",
    "sg:city":"London",
    "sg:classifiers":[
        {
            "category":"Government",
            "subcategory":"Post Office",
            "type":"Public Place"
        }
    ],
    "sg:phone":"+44 20 7394 7000",
    "sg:postcode":"SE16 3LL",
    "sg:province":"Greater London",
    "sg:tags":[
        "messenger",
        "courier"
    ],
    "wof:name":"Sky Bikes Ltd.",
    "wof:placetype":"venue"
},
  "geometry": {"coordinates":[-0.0550700016,51.489151001],"type":"Point"}
}