{
  "type": "Feature",
  "properties": {
    "iso:country":"GB",
    "sg:address":"51a Houghton Way, St Johns Precinct",
    "sg:city":"Liverpool",
    "sg:classifiers":[
        {
            "category":"Sports & Exercise",
            "subcategory":"Athletic Track",
            "type":"Entertainment"
        },
        {
            "category":"Shopping",
            "subcategory":"Luggage & Leather Goods",
            "type":"Retail Goods"
        }
    ],
    "sg:phone":"+44 151 709 8485",
    "sg:postcode":"L1 1LW",
    "sg:province":"Merseyside",
    "sg:tags":[
        "handbag",
        "bags",
        "belt",
        "retailer",
        "accessory"
    ],
    "wof:name":"Bag Shop",
    "wof:placetype":"venue"
},
  "geometry": {"coordinates":[-2.981759,53.4062],"type":"Point"}
}