{
  "type": "Feature",
  "properties": {
    "iso:country":"GB",
    "sg:address":"72 Station Road, Hadfield",
    "sg:city":"Glossop",
    "sg:classifiers":[
        {
            "category":"Shopping",
            "subcategory":"Gifts & Souvenirs",
            "type":"Retail Goods"
        }
    ],
    "sg:phone":"+44 1457 852881",
    "sg:postcode":"SK13 1DL",
    "sg:province":"Derbyshire",
    "sg:tags":[
        "poster",
        "card"
    ],
    "wof:name":"R E Gregson",
    "wof:placetype":"venue"
},
  "geometry": {"coordinates":[-1.968669,53.463272],"type":"Point"}
}