{
  "type": "Feature",
  "properties": {
    "addr:full":"Tamar Cottage, 3 Chapel Terrace, Harrowbarrow Callington Cornwall PL17 8JF",
    "addr:housenumber":"3",
    "addr:postcode":"pl17 8jf",
    "addr:street":"Chapel Terrace Harrowbarrow",
    "iso:country":"GB",
    "sg:address":"Tamar Cottage, 3 Chapel Terrace, Harrowbarrow",
    "sg:city":"Callington",
    "sg:classifiers":[
        {
            "category":"Shopping",
            "subcategory":"Hobbies, Toys, & Games",
            "type":"Retail Goods"
        }
    ],
    "sg:phone":"+44 1579 350744",
    "sg:postcode":"PL17 8JF",
    "sg:province":"Cornwall",
    "sg:tags":[
        "toy"
    ],
    "wof:name":"Balloons R Fun",
    "wof:placetype":"venue"
},
  "geometry": {"coordinates":[-4.2602920532,50.505443573],"type":"Point"}
}