{
  "type": "Feature",
  "properties": {
    "addr:full":"Bridge Ho, Station Bridge, 150a Victoria St St Albans Hertfordshire AL1 3TF",
    "addr:housenumber":"150a",
    "addr:postcode":"al1 3tf",
    "addr:street":"Bridge;Victoria St",
    "iso:country":"GB",
    "sg:address":"Bridge Ho, Station Bridge, 150a Victoria St",
    "sg:city":"St Albans",
    "sg:classifiers":[
        {
            "category":"Transit Center",
            "subcategory":"Freight",
            "type":"Transportation"
        }
    ],
    "sg:phone":"+44 1727 846410",
    "sg:postcode":"AL1 3TF",
    "sg:province":"Hertfordshire",
    "sg:tags":[
        "shop",
        "craft",
        "centre"
    ],
    "wof:name":"Craftworks",
    "wof:placetype":"venue"
},
  "geometry": {"coordinates":[-0.337752,51.753189],"type":"Point"}
}