{
  "type": "Feature",
  "properties": {
    "iso:country":"GB",
    "sg:address":"1b Kynance Place, Kensington",
    "sg:city":"London",
    "sg:classifiers":[
        {
            "category":"Professional",
            "subcategory":"Employment Agencies",
            "type":"Services"
        }
    ],
    "sg:postcode":"SW7 4QS",
    "sg:province":"Greater London",
    "sg:tags":[
        "consultant"
    ],
    "wof:name":"Archer McGrath Plc",
    "wof:placetype":"venue"
},
  "geometry": {"coordinates":[-0.184758,51.497597],"type":"Point"}
}