{
  "type": "Feature",
  "properties": {
    "addr:full":"13 High Street Hampton Greater London TW12 2SA",
    "addr:housenumber":"13",
    "addr:postcode":"tw12 2sa",
    "addr:street":"High Street",
    "iso:country":"GB",
    "sg:address":"13 High Street",
    "sg:city":"Hampton",
    "sg:classifiers":[
        {
            "category":"Banks & Credit Unions",
            "subcategory":"Financial Services",
            "type":"Services"
        }
    ],
    "sg:phone":"+44 20 8941 4114",
    "sg:postcode":"TW12 2SA",
    "sg:province":"Greater London",
    "sg:tags":[
        "adviser"
    ],
    "wof:name":"N J Associates",
    "wof:placetype":"venue"
},
  "geometry": {"coordinates":[-0.362247,51.413834],"type":"Point"}
}