{
  "type": "Feature",
  "properties": {
    "iso:country":"GB",
    "sg:address":"16 Wood St",
    "sg:city":"Bolton",
    "sg:classifiers":[
        {
            "category":"Professional",
            "subcategory":"Lawyer & Legal Services",
            "type":"Services"
        }
    ],
    "sg:phone":"+44 1204 396560",
    "sg:postcode":"BL1 1DY",
    "sg:province":"Lancashire",
    "sg:tags":[
        "advice",
        "counselling"
    ],
    "wof:name":"Bolton Unemployed (T U C) Advice Centre",
    "wof:placetype":"venue"
},
  "geometry": {"coordinates":[-2.425735,53.578587],"type":"Point"}
}