{
  "type": "Feature",
  "properties": {
    "addr:full":"Twyford Business Centre, 17 London Road Bishops Stortford Essex CM23 3YT",
    "addr:housenumber":"17",
    "addr:postcode":"cm23 3yt",
    "addr:street":"London Road",
    "iso:country":"GB",
    "sg:address":"Twyford Business Centre, 17 London Road",
    "sg:city":"Bishops Stortford",
    "sg:classifiers":[
        {
            "category":"Shopping",
            "subcategory":"Optical Goods",
            "type":"Retail Goods"
        },
        {
            "category":"Government",
            "subcategory":"Office",
            "type":"Public Place"
        }
    ],
    "sg:postcode":"CM23 3YT",
    "sg:province":"Essex",
    "sg:tags":[
        "local"
    ],
    "wof:name":"Tant Laboratories Ltd.",
    "wof:placetype":"venue"
},
  "geometry": {"coordinates":[0.1619559973,51.8723564148],"type":"Point"}
}