{
  "type": "Feature",
  "properties": {
    "addr:full":"Bungay Road Norwich Norfolk NR15 2YL",
    "addr:postcode":"nr15 2yl",
    "addr:street":"Bungay Road Norwich",
    "iso:country":"GB",
    "sg:address":"Bungay Road",
    "sg:city":"Norwich",
    "sg:classifiers":[
        {
            "category":"Farming",
            "subcategory":"Livestock Farm",
            "type":"Manufacturing & Wholesale Goods"
        }
    ],
    "sg:phone":"+44 1508 470730",
    "sg:postcode":"NR15 2YL",
    "sg:province":"Norfolk",
    "sg:tags":[
        "others"
    ],
    "wof:name":"R J Barnes",
    "wof:placetype":"venue"
},
  "geometry": {"coordinates":[1.3019740582,52.500289917],"type":"Point"}
}