{
  "type": "Feature",
  "properties": {
    "addr:full":"The Radnor Business Centre, Radnor Road Bristol City of Bristol BS7 8QS",
    "addr:postcode":"bristol bs7 8qs",
    "addr:street":"Radnor Road",
    "iso:country":"GB",
    "sg:address":"The Radnor Business Centre, Radnor Road",
    "sg:city":"Bristol",
    "sg:classifiers":[
        {
            "category":"Wholesale",
            "subcategory":"Electrical",
            "type":"Manufacturing & Wholesale Goods"
        }
    ],
    "sg:postcode":"BS7 8QS",
    "sg:province":"City of Bristol",
    "sg:tags":[
        "equipment",
        "refrigeration"
    ],
    "wof:name":"Dawsonrentals Display Refrigeration Ltd.",
    "wof:placetype":"venue"
},
  "geometry": {"coordinates":[-2.5885300636,51.4808502197],"type":"Point"}
}