{
  "type": "Feature",
  "properties": {
    "iso:country":"GB",
    "sg:address":"Unit 5 Westerton Road, East Mains Industrial Estate",
    "sg:city":"Broxburn",
    "sg:classifiers":[
        {
            "category":"Shopping",
            "subcategory":"Computers & Home Electronics",
            "type":"Retail Goods"
        }
    ],
    "sg:phone":"+44 1506 859722",
    "sg:postcode":"EH52 5AU",
    "sg:province":"City of Edinburgh",
    "sg:tags":[
        "electrical"
    ],
    "wof:name":"R & M Electrical Wholesalers Ltd.",
    "wof:placetype":"venue"
},
  "geometry": {"coordinates":[-3.443519,55.937901],"type":"Point"}
}