{
  "type": "Feature",
  "properties": {
    "addr:full":"17 Poplar Drive, Marchwood Southampton Hampshire SO40 4XH",
    "addr:housenumber":"17",
    "addr:postcode":"so40 4xh",
    "addr:street":"Poplar Drive",
    "iso:country":"GB",
    "sg:address":"17 Poplar Drive, Marchwood",
    "sg:city":"Southampton",
    "sg:classifiers":[
        {
            "category":"Professional",
            "subcategory":"Accounting & Tax Preparation",
            "type":"Services"
        }
    ],
    "sg:phone":"+44 23 8084 7373",
    "sg:postcode":"SO40 4XH",
    "sg:province":"Hampshire",
    "sg:tags":[
        "accountant"
    ],
    "wof:name":"C M Yates",
    "wof:placetype":"venue"
},
  "geometry": {"coordinates":[-1.4603379965,50.8905906677],"type":"Point"}
}