{
  "type": "Feature",
  "properties": {
    "addr:full":"113 West Blackhall St Greenock Inverclyde PA15 1YD",
    "addr:housenumber":"113",
    "addr:postcode":"pa15 1yd",
    "addr:street":"West Blackhall St Greenock",
    "iso:country":"GB",
    "sg:address":"113 West Blackhall St",
    "sg:city":"Greenock",
    "sg:classifiers":[
        {
            "category":"Social Services",
            "subcategory":"Adult Care",
            "type":"Services"
        }
    ],
    "sg:phone":"+44 1475 723862",
    "sg:postcode":"PA15 1YD",
    "sg:province":"Inverclyde",
    "sg:tags":[
        "mnfr",
        "aid",
        "hearing"
    ],
    "wof:name":"Better Hearing",
    "wof:placetype":"venue"
},
  "geometry": {"coordinates":[-4.7630610466,55.9520378113],"type":"Point"}
}