{
  "type": "Feature",
  "properties": {
    "iso:country":"GB",
    "sg:address":"2 Stoodley Hall Cotts, 2 Stoodley La",
    "sg:city":"Todmorden",
    "sg:classifiers":[
        {
            "category":"Shopping",
            "subcategory":"Gifts & Souvenirs",
            "type":"Retail Goods"
        }
    ],
    "sg:postcode":"OL14 6HA",
    "sg:province":"Lancashire",
    "sg:tags":[
        "greeting",
        "card"
    ],
    "wof:name":"Clarke,Nancy,",
    "wof:placetype":"venue"
},
  "geometry": {"coordinates":[-2.0973079205,53.7143096924],"type":"Point"}
}