{
  "type": "Feature",
  "properties": {
    "iso:country":"GB",
    "sg:address":"Walford Cross",
    "sg:city":"Taunton",
    "sg:classifiers":[
        {
            "category":"Train Station",
            "subcategory":"Rail",
            "type":"Transportation"
        }
    ],
    "sg:phone":"+44 1823 413333",
    "sg:postcode":"TA2 8QR",
    "sg:province":"Somerset",
    "sg:tags":[
        "caravan"
    ],
    "wof:name":"Somerset Caravans Ltd.",
    "wof:placetype":"venue"
},
  "geometry": {"coordinates":[-3.03436,51.04697],"type":"Point"}
}