{
  "type": "Feature",
  "properties": {
    "addr:full":"Shirley Farm, Whiston Stoke-on-trent Staffordshire ST10 2HU",
    "addr:postcode":"st10 2hu",
    "iso:country":"GB",
    "sg:address":"Shirley Farm, Whiston",
    "sg:city":"Stoke-on-trent",
    "sg:classifiers":[
        {
            "category":"Farming",
            "subcategory":"Livestock Farm",
            "type":"Manufacturing & Wholesale Goods"
        }
    ],
    "sg:href":"http://api.simplegeo.com/1.0/features/SG_65ANW7iVrHy1qRVyPoOuhw_53.021713_-1.946147@1300740015.json",
    "sg:phone":"+44 1538 266277",
    "sg:postcode":"ST10 2HU",
    "sg:province":"Staffordshire",
    "sg:tags":[
        "others"
    ],
    "wof:name":"R & M Green & Sons",
    "wof:placetype":"venue"
},
  "geometry": {"coordinates":[-1.946147,53.021713],"type":"Point"}
}