{
  "type": "Feature",
  "properties": {
    "addr:full":"Miramar, Ferndale Road Teignmouth Devon TQ14 8NQ",
    "addr:postcode":"tq14 8nq",
    "addr:street":"Ferndale Road",
    "iso:country":"GB",
    "sg:address":"Miramar, Ferndale Road",
    "sg:city":"Teignmouth",
    "sg:classifiers":[
        {
            "category":"Building & Trades",
            "subcategory":"Construction",
            "type":"Services"
        }
    ],
    "sg:phone":"+44 1626 779893",
    "sg:postcode":"TQ14 8NQ",
    "sg:province":"Devon",
    "sg:tags":[
        "builder"
    ],
    "wof:name":"Rivercoombe Building Co. Ltd.",
    "wof:placetype":"venue"
},
  "geometry": {"coordinates":[-3.49664,50.557037],"type":"Point"}
}