{
  "type": "Feature",
  "properties": {
    "addr:full":"6 Caernarvon Court Cheltenham Gloucestershire GL51 3JA",
    "addr:housenumber":"6",
    "addr:postcode":"gl51 3ja",
    "addr:street":"Caernarvon Court",
    "iso:country":"GB",
    "sg:address":"6 Caernarvon Court",
    "sg:city":"Cheltenham",
    "sg:classifiers":[
        {
            "category":"Cinema",
            "subcategory":"Movie Rental",
            "type":"Entertainment"
        }
    ],
    "sg:phone":"+44 1242 237557",
    "sg:postcode":"GL51 3JA",
    "sg:province":"Gloucestershire",
    "sg:tags":[
        "video",
        "library"
    ],
    "wof:name":"Video Nest",
    "wof:placetype":"venue"
},
  "geometry": {"coordinates":[-2.1122899055,51.8856964111],"type":"Point"}
}