{
  "type": "Feature",
  "properties": {
    "iso:country":"GB",
    "sg:address":"92 New Cavendish St",
    "sg:city":"West End",
    "sg:classifiers":[
        {
            "category":"Professional",
            "subcategory":"Management & Consulting",
            "type":"Services"
        }
    ],
    "sg:phone":"+44 20 7637 2875",
    "sg:postcode":"W1M 7FA",
    "sg:province":"Hampshire",
    "sg:tags":[
        "consultant",
        "business"
    ],
    "wof:name":"Meridian International Consultancy The",
    "wof:placetype":"venue"
},
  "geometry": {"coordinates":[-0.144389,51.519691],"type":"Point"}
}