{
  "type": "Feature",
  "properties": {
    "addr:full":"121 Fonthill Rd Finsbury Park Greater London N4 3HH",
    "addr:housenumber":"121",
    "addr:postcode":"n4 3hh",
    "addr:street":"Fonthill Rd",
    "iso:country":"GB",
    "sg:address":"121 Fonthill Rd",
    "sg:city":"Finsbury Park",
    "sg:classifiers":[
        {
            "category":"Shopping",
            "subcategory":"Clothing, Apparel, & Fashions",
            "type":"Retail Goods"
        }
    ],
    "sg:phone":"+44 20 7281 2491",
    "sg:postcode":"N4 3HH",
    "sg:province":"Greater London",
    "sg:tags":[
        "clothing"
    ],
    "wof:name":"Dame",
    "wof:placetype":"venue"
},
  "geometry": {"coordinates":[-0.1085439995,51.5643882751],"type":"Point"}
}