{
  "type": "Feature",
  "properties": {
    "iso:country":"GB",
    "sg:address":"9 Sycamore Dr",
    "sg:city":"Sunderland",
    "sg:classifiers":[
        {
            "category":"Social Services",
            "subcategory":"Retirement Home",
            "type":"Services"
        }
    ],
    "sg:phone":"+44 191 549 6083",
    "sg:postcode":"SR5 1PP",
    "sg:province":"Tyne and Wear",
    "sg:tags":[
        "residential",
        "care"
    ],
    "wof:name":"Community Integrated Care Ltd",
    "wof:placetype":"venue"
},
  "geometry": {"coordinates":[-1.3948260546,54.9260368347],"type":"Point"}
}