{
  "type": "Feature",
  "properties": {
    "addr:full":"100 Clarence Rd Grays Essex RM17 6RA",
    "addr:housenumber":"100",
    "addr:postcode":"rm17 6ra",
    "addr:street":"Clarence Rd",
    "iso:country":"GB",
    "sg:address":"100 Clarence Rd",
    "sg:city":"Grays",
    "sg:classifiers":[
        {
            "category":"Home & Garden",
            "subcategory":"Home Furnishings",
            "type":"Retail Goods"
        }
    ],
    "sg:postcode":"RM17 6RA",
    "sg:province":"Essex",
    "sg:tags":[
        "blind",
        "curtain",
        "fitting"
    ],
    "wof:name":"Edwards,Sandra,",
    "wof:placetype":"venue"
},
  "geometry": {"coordinates":[0.328047,51.477711],"type":"Point"}
}