{
  "type": "Feature",
  "properties": {
    "iso:country":"GB",
    "sg:address":"16 Dodson Way, Fengate",
    "sg:city":"Peterborough",
    "sg:classifiers":[
        {
            "category":"Professional",
            "subcategory":"Detective & Security Services",
            "type":"Services"
        }
    ],
    "sg:phone":"+44 1733 894334",
    "sg:postcode":"PE1 5XJ",
    "sg:province":"Cambridgeshire",
    "sg:tags":[
        "alarm",
        "burglar",
        "system",
        "activity"
    ],
    "wof:name":"MARRIOTT SECURITY LTD",
    "wof:placetype":"venue"
},
  "geometry": {"coordinates":[-0.2080139965,52.5743408203],"type":"Point"}
}