{
  "type": "Feature",
  "properties": {
    "addr:full":"32 Broad St Fraserburgh Aberdeenshire AB43 9AH",
    "addr:housenumber":"32",
    "addr:postcode":"ab43 9ah",
    "addr:street":"Broad St",
    "iso:country":"GB",
    "sg:address":"32 Broad St",
    "sg:city":"Fraserburgh",
    "sg:classifiers":[
        {
            "category":"Food & Beverages",
            "subcategory":"Liquor & Beverages",
            "type":"Retail Goods"
        }
    ],
    "sg:phone":"+44 1346 512633",
    "sg:postcode":"AB43 9AH",
    "sg:province":"Aberdeenshire",
    "sg:tags":[
        "beer",
        "spirit",
        "wines"
    ],
    "wof:name":"Victoria Wine",
    "wof:placetype":"venue"
},
  "geometry": {"coordinates":[-2.017819,57.687931],"type":"Point"}
}