{
  "type": "Feature",
  "properties": {
    "iso:country":"GB",
    "sg:address":"69 Farnham Road",
    "sg:city":"Guildford",
    "sg:classifiers":[
        {
            "category":"Real Estate",
            "subcategory":"Developer",
            "type":"Services"
        },
        {
            "category":"Building & Trades",
            "subcategory":"Construction",
            "type":"Services"
        }
    ],
    "sg:phone":"+44 1483 576077",
    "sg:postcode":"GU2 7PF",
    "sg:province":"Surrey",
    "sg:tags":[
        "builder",
        "property"
    ],
    "wof:name":"Le Gray Michael & Co",
    "wof:placetype":"venue"
},
  "geometry": {"coordinates":[-0.585915029,51.2347068787],"type":"Point"}
}