{
  "type": "Feature",
  "properties": {
    "iso:country":"GB",
    "sg:address":"Units 7 & 8, Cape Indstl Est, Coal Hill, Farsley",
    "sg:city":"Pudsey",
    "sg:classifiers":[
        {
            "category":"Professional",
            "subcategory":"Detective & Security Services",
            "type":"Services"
        }
    ],
    "sg:postcode":"LS28 5NA",
    "sg:province":"West Yorkshire",
    "sg:tags":[
        "equipment"
    ],
    "wof:name":"Sharp,David,",
    "wof:placetype":"venue"
},
  "geometry": {"coordinates":[-1.6605399847,53.8152084351],"type":"Point"}
}