{
  "type": "Feature",
  "properties": {
    "addr:full":"Melville House, 1-3 Station Road Darlington Durham DL3 6TA",
    "addr:housenumber":"1-3",
    "addr:postcode":"dl3 6ta",
    "addr:street":"Station Road",
    "iso:country":"GB",
    "sg:address":"Melville House, 1-3 Station Road",
    "sg:city":"Darlington",
    "sg:classifiers":[
        {
            "category":"Home & Garden",
            "subcategory":"Hardware",
            "type":"Retail Goods"
        }
    ],
    "sg:phone":"+44 1325 286320",
    "sg:postcode":"DL3 6TA",
    "sg:province":"Durham",
    "sg:tags":[
        "device",
        "fixing",
        "fastener"
    ],
    "wof:name":"B & C Fixings Ltd.",
    "wof:placetype":"venue"
},
  "geometry": {"coordinates":[-1.5530289412,54.5333213806],"type":"Point"}
}