{
  "type": "Feature",
  "properties": {
    "iso:country":"GB",
    "sg:address":"The Beeches, I Glenavon Crescent",
    "sg:city":"Porthcawl",
    "sg:classifiers":[
        {
            "category":"Building & Trades",
            "subcategory":"Plumbing",
            "type":"Services"
        }
    ],
    "sg:phone":"+44 1656 785650",
    "sg:postcode":"CF36 3LP",
    "sg:province":"Bridgend",
    "sg:tags":[
        "heating"
    ],
    "wof:name":"Mal Jones Plumbing & Heating Specialist",
    "wof:placetype":"venue"
},
  "geometry": {"coordinates":[-3.6909189224,51.4876098633],"type":"Point"}
}