{
  "type": "Feature",
  "properties": {
    "iso:country":"GB",
    "sg:address":"46b Gloucester Road",
    "sg:city":"London",
    "sg:classifiers":[
        {
            "category":"Shopping",
            "subcategory":"News",
            "type":"Retail Goods"
        }
    ],
    "sg:postcode":"SW7 4QT",
    "sg:province":"Greater London",
    "sg:tags":[
        "newsagent"
    ],
    "wof:name":"Saggars Newsagent",
    "wof:placetype":"venue"
},
  "geometry": {"coordinates":[-0.18393,51.498222],"type":"Point"}
}