{
  "type": "Feature",
  "properties": {
    "iso:country":"GB",
    "sg:address":"Penrhos Manor, Oak Drive",
    "sg:city":"Colwyn Bay",
    "sg:classifiers":[
        {
            "category":"Building & Trades",
            "subcategory":"Construction",
            "type":"Services"
        }
    ],
    "sg:postcode":"LL29 7YW",
    "sg:province":"Conwy",
    "sg:tags":[
        "builder"
    ],
    "wof:name":"Rochelle Builders",
    "wof:placetype":"venue"
},
  "geometry": {"coordinates":[-3.7254140377,53.2939109802],"type":"Point"}
}