{
  "type": "Feature",
  "properties": {
    "addr:full":"Wentloog Road Cardiff Caerphilly CF3 8YH",
    "addr:postcode":"cf3 8yh",
    "addr:street":"Wentloog Road",
    "iso:country":"GB",
    "sg:address":"Wentloog Road",
    "sg:city":"Cardiff",
    "sg:classifiers":[
        {
            "category":"Health Services",
            "subcategory":"Clinic",
            "type":"Services"
        }
    ],
    "sg:phone":"+44 29 2079 7746",
    "sg:postcode":"CF3 8YH",
    "sg:province":"Caerphilly",
    "sg:tags":[
        "nh"
    ],
    "wof:name":"Daintree Surgery",
    "wof:placetype":"venue"
},
  "geometry": {"coordinates":[-3.0982890129,51.5066719055],"type":"Point"}
}