{
  "type": "Feature",
  "properties": {
    "iso:country":"GB",
    "sg:address":"Emesgate Lane, Silverdale",
    "sg:city":"Carnforth",
    "sg:classifiers":[
        {
            "category":"Education",
            "subcategory":"School",
            "type":"Public Place"
        }
    ],
    "sg:phone":"+44 1524 701467",
    "sg:postcode":"LA5 0RF",
    "sg:province":"Cumbria",
    "sg:tags":[
        "local",
        "authority"
    ],
    "wof:name":"Silverdale C Of E Primary School",
    "wof:placetype":"venue"
},
  "geometry": {"coordinates":[-2.826649,54.16748],"type":"Point"}
}