{
  "type": "Feature",
  "properties": {
    "iso:country":"GB",
    "sg:address":"Enterprise Unit 2 Maes Y Clawdd, Maesbury Road Industrial Estate",
    "sg:city":"Oswestry",
    "sg:classifiers":[
        {
            "category":"Retail",
            "subcategory":"Photofinishing",
            "type":"Services"
        }
    ],
    "sg:phone":"+44 1691 670508",
    "sg:postcode":"SY10 8NN",
    "sg:province":"Shropshire",
    "sg:tags":[
        "photographic",
        "processor"
    ],
    "wof:name":"The Shropshire Photo Labs",
    "wof:placetype":"venue"
},
  "geometry": {"coordinates":[-3.026734,52.82452],"type":"Point"}
}