{
  "type": "Feature",
  "properties": {
    "iso:country":"GB",
    "sg:address":"7 Corbett Close, Bron-y-mor",
    "sg:city":"Tywyn",
    "sg:classifiers":[
        {
            "category":"Professional",
            "subcategory":"Art Services",
            "type":"Services"
        },
        {
            "category":"Building & Trades",
            "subcategory":"Construction",
            "type":"Services"
        }
    ],
    "sg:phone":"+44 1654 711432",
    "sg:postcode":"LL36 0BL",
    "sg:province":"Gwynedd",
    "sg:tags":[
        "glazier",
        "decorator",
        "painter"
    ],
    "wof:name":"RAINBOW DECORATORS",
    "wof:placetype":"venue"
},
  "geometry": {"coordinates":[-4.0949850082,52.5835342407],"type":"Point"}
}