{
  "type": "Feature",
  "properties": {
    "iso:country":"GB",
    "sg:address":"P O Box 1616",
    "sg:city":"Andover",
    "sg:classifiers":[
        {
            "category":"Recreation",
            "subcategory":"Gun Range",
            "type":"Entertainment"
        }
    ],
    "sg:postcode":"SP10 3YH",
    "sg:province":"Hampshire",
    "sg:tags":[
        "operator",
        "tour"
    ],
    "wof:name":"Time Off",
    "wof:placetype":"venue"
},
  "geometry": {"coordinates":[-1.476779,51.206493],"type":"Point"}
}