{
  "type": "Feature",
  "properties": {
    "iso:country":"GB",
    "sg:address":"Henllys School",
    "sg:city":"Cwmbran",
    "sg:classifiers":[
        {
            "category":"Place Of Worship",
            "type":"Public Place"
        }
    ],
    "sg:phone":"+44 1633 489718",
    "sg:postcode":"NP44 3LS",
    "sg:province":"Monmouthshire",
    "wof:name":"Worship Centre Church In Wales",
    "wof:placetype":"venue"
},
  "geometry": {"coordinates":[-3.0230391026,51.6447105408],"type":"Point"}
}