{
  "type": "Feature",
  "properties": {
    "iso:country":"GB",
    "sg:address":"8 Saturday Market",
    "sg:city":"Beverley",
    "sg:classifiers":[
        {
            "category":"Health Services",
            "subcategory":"Optometrist",
            "type":"Services"
        }
    ],
    "sg:phone":"+44 1482 868428",
    "sg:postcode":"HU17 8BB",
    "sg:province":"East Riding of Yorkshire",
    "sg:tags":[
        "optician"
    ],
    "wof:name":"Edwards Opticians",
    "wof:placetype":"venue"
},
  "geometry": {"coordinates":[-0.432959,53.84338],"type":"Point"}
}