{
  "type": "Feature",
  "properties": {
    "iso:country":"GB",
    "sg:address":"Buncefield Lane",
    "sg:city":"Hemel Hempstead",
    "sg:classifiers":[
        {
            "category":"Recreation",
            "subcategory":"Campground",
            "type":"Entertainment"
        }
    ],
    "sg:phone":"+44 1442 68286",
    "sg:postcode":"HP2 7HY",
    "sg:province":"Hertfordshire",
    "sg:tags":[
        "site",
        "camping"
    ],
    "wof:name":"Caravan Club",
    "wof:placetype":"venue"
},
  "geometry": {"coordinates":[-0.4283879995,51.7576828003],"type":"Point"}
}