{
  "type": "Feature",
  "properties": {
    "iso:country":"GB",
    "sg:address":"259 Headfield Rd",
    "sg:city":"Dewsbury",
    "sg:classifiers":[
        {
            "category":"Personal",
            "subcategory":"Beauty Salon",
            "type":"Services"
        }
    ],
    "sg:phone":"+44 1924 465815",
    "sg:postcode":"WF12 9JN",
    "sg:province":"West Yorkshire",
    "sg:tags":[
        "unisex",
        "hairdresser"
    ],
    "wof:name":"Gillian's",
    "wof:placetype":"venue"
},
  "geometry": {"coordinates":[-1.629465,53.674019],"type":"Point"}
}