{
  "type": "Feature",
  "properties": {
    "iso:country":"GB",
    "sg:address":"60 The Mall",
    "sg:city":"Burnley",
    "sg:classifiers":[
        {
            "category":"Retail",
            "subcategory":"Photofinishing",
            "type":"Services"
        },
        {
            "category":"Professional",
            "subcategory":"Art Services",
            "type":"Services"
        }
    ],
    "sg:postcode":"BB11 1BA",
    "sg:province":"Lancashire",
    "sg:tags":[
        "photographer",
        "processing",
        "photographic",
        "processor"
    ],
    "wof:name":"Fotolab",
    "wof:placetype":"venue"
},
  "geometry": {"coordinates":[-2.244601,53.789928],"type":"Point"}
}