{
  "type": "Feature",
  "properties": {
    "iso:country":"GB",
    "sg:address":"Waen Garage, Bangor Rd, Aberconwy",
    "sg:city":"Conwy",
    "sg:classifiers":[
        {
            "category":"Retail",
            "subcategory":"Auto Repair",
            "type":"Services"
        }
    ],
    "sg:phone":"+44 1492 593660",
    "sg:postcode":"LL32 8DR",
    "sg:province":"Conwy",
    "sg:tags":[
        "modification",
        "garage"
    ],
    "wof:name":"E M C Motor Engineers",
    "wof:placetype":"venue"
},
  "geometry": {"coordinates":[-3.832993,53.282036],"type":"Point"}
}