{
  "type": "Feature",
  "properties": {
    "addr:full":"Town Hall, Castle Street Conwy Conwy LL32 8AY",
    "addr:postcode":"ll32 8ay",
    "addr:street":"Castle Street",
    "iso:country":"GB",
    "sg:address":"Town Hall, Castle Street",
    "sg:city":"Conwy",
    "sg:classifiers":[
        {
            "category":"Education",
            "subcategory":"Library",
            "type":"Public Place"
        },
        {
            "category":"Government",
            "subcategory":"Office",
            "type":"Public Place"
        }
    ],
    "sg:phone":"+44 1492 596242",
    "sg:postcode":"LL32 8AY",
    "sg:province":"Conwy",
    "sg:tags":[
        "book",
        "local"
    ],
    "wof:name":"Conwy Library",
    "wof:placetype":"venue"
},
  "geometry": {"coordinates":[-3.832993,53.282036],"type":"Point"}
}