{
  "type": "Feature",
  "properties": {
    "iso:country":"GB",
    "sg:address":"The Watershed, Gables Drive  Hockerton",
    "sg:city":"Southwell",
    "sg:classifiers":[
        {
            "category":"Professional",
            "subcategory":"Management & Consulting",
            "type":"Services"
        }
    ],
    "sg:postcode":"NG25 0QU",
    "sg:province":"Nottinghamshire",
    "sg:tags":[
        "environmental",
        "consultant"
    ],
    "wof:name":"Hockerton Housing Project Trading Ltd",
    "wof:placetype":"venue"
},
  "geometry": {"coordinates":[-0.955189,53.078121],"type":"Point"}
}