{
  "type": "Feature",
  "properties": {
    "iso:country":"GB",
    "sg:address":"Southgate Chambers, 37-39 Southgate Street",
    "sg:city":"Winchester",
    "sg:classifiers":[
        {
            "category":"Manufacturing",
            "subcategory":"Petroleum Products",
            "type":"Manufacturing & Wholesale Goods"
        }
    ],
    "sg:phone":"+44 1962 840011",
    "sg:postcode":"SO23 9EH",
    "sg:province":"Hampshire",
    "sg:tags":[
        "double",
        "glazing"
    ],
    "wof:name":"Trafalgar Home Security",
    "wof:placetype":"venue"
},
  "geometry": {"coordinates":[-1.316809,51.063068],"type":"Point"}
}