{
  "type": "Feature",
  "properties": {
    "addr:full":"191 Bramcote Lane, Wollaton Nottingham Nottinghamshire NG8 2QJ",
    "addr:housenumber":"191",
    "addr:postcode":"ng8 2qj",
    "addr:street":"Bramcote Lane",
    "iso:country":"GB",
    "sg:address":"191 Bramcote Lane, Wollaton",
    "sg:city":"Nottingham",
    "sg:classifiers":[
        {
            "category":"Government",
            "subcategory":"Post Office",
            "type":"Public Place"
        }
    ],
    "sg:phone":"+44 115 928 3544",
    "sg:postcode":"NG8 2QJ",
    "sg:province":"Nottinghamshire",
    "wof:name":"Bramcote Lane Sub Post Office",
    "wof:placetype":"venue"
},
  "geometry": {"coordinates":[-1.2319040298,52.9462394714],"type":"Point"}
}