{
  "type": "Feature",
  "properties": {
    "addr:full":"239 Baldridgeburn Dunfermline Fife KY12 9EG",
    "addr:housenumber":"239",
    "addr:postcode":"ky12 9eg",
    "addr:street":"Baldridgeburn Dunfermline",
    "iso:country":"GB",
    "sg:address":"239 Baldridgeburn",
    "sg:city":"Dunfermline",
    "sg:classifiers":[
        {
            "category":"Fast Food",
            "type":"Food & Drink"
        }
    ],
    "sg:phone":"+44 1383 731085",
    "sg:postcode":"KY12 9EG",
    "sg:province":"Fife",
    "sg:tags":[
        "away",
        "meal",
        "outlet",
        "take"
    ],
    "wof:name":"Wan Lam",
    "wof:placetype":"venue"
},
  "geometry": {"coordinates":[-3.4775810242,56.0772781372],"type":"Point"}
}