{
  "type": "Feature",
  "properties": {
    "iso:country":"GB",
    "sg:address":"239 Bullsmoor La",
    "sg:city":"Enfield",
    "sg:classifiers":[
        {
            "category":"Recreation",
            "subcategory":"Amusement Park",
            "type":"Entertainment"
        }
    ],
    "sg:phone":"+44 1992 710066",
    "sg:postcode":"EN1 4SB",
    "sg:province":"Greater London",
    "sg:tags":[
        "arcade"
    ],
    "wof:name":"Lea Valley Leisure Ltd",
    "wof:placetype":"venue"
},
  "geometry": {"coordinates":[-0.049005,51.680332],"type":"Point"}
}