{
  "type": "Feature",
  "properties": {
    "iso:country":"GB",
    "sg:address":"Unit 7, Avenue Farm Industrial Estate, Birmingham Road",
    "sg:city":"Stratford-upon-avon",
    "sg:classifiers":[
        {
            "category":"Wholesale",
            "subcategory":"Electrical",
            "type":"Manufacturing & Wholesale Goods"
        },
        {
            "category":"Shopping",
            "subcategory":"Computers & Home Electronics",
            "type":"Retail Goods"
        }
    ],
    "sg:phone":"+44 1789 292705",
    "sg:postcode":"CV37 0HR",
    "sg:province":"Warwickshire",
    "sg:tags":[
        "wholesaler"
    ],
    "sg:website":"http://www.eyreandelliston.co.uk",
    "wof:name":"Eyre & Elliston Ltd",
    "wof:placetype":"venue"
},
  "geometry": {"coordinates":[-1.7191640139,52.2022743225],"type":"Point"}
}