{
  "type": "Feature",
  "properties": {
    "addr:full":"Unit 4 Farley Bank Hastings East Sussex TN35 5QF",
    "addr:housenumber":"unit 4 farley",
    "addr:postcode":"tn35 5qf",
    "addr:street":"Hastings",
    "iso:country":"GB",
    "sg:address":"Unit 4 Farley Bank",
    "sg:city":"Hastings",
    "sg:classifiers":[
        {
            "category":"Education",
            "subcategory":"Library",
            "type":"Public Place"
        }
    ],
    "sg:phone":"+44 1424 423833",
    "sg:postcode":"TN35 5QF",
    "sg:province":"East Sussex",
    "sg:tags":[
        "reproduction",
        "furniture"
    ],
    "wof:name":"Rye Associates",
    "wof:placetype":"venue"
},
  "geometry": {"coordinates":[0.5979620218,50.8682861328],"type":"Point"}
}