{
  "type": "Feature",
  "properties": {
    "iso:country":"GB",
    "sg:address":"311 Long Lane",
    "sg:city":"Halesowen",
    "sg:classifiers":[
        {
            "category":"Professional",
            "subcategory":"Management & Consulting",
            "type":"Services"
        }
    ],
    "sg:phone":"+44 121 602 1600",
    "sg:postcode":"B62 9LD",
    "sg:province":"West Midlands",
    "sg:tags":[
        "consultant",
        "business"
    ],
    "wof:name":"Jennings Environmental & Housing Consultants Ltd.",
    "wof:placetype":"venue"
},
  "geometry": {"coordinates":[-2.034434,52.470905],"type":"Point"}
}