{
  "type": "Feature",
  "properties": {
    "addr:full":"P.o. Box 4051 Hornchurch Essex RM12 4DD",
    "addr:housenumber":"p.o. box",
    "addr:postcode":"4051;rm12 4dd",
    "iso:country":"GB",
    "sg:address":"P.o. Box 4051",
    "sg:city":"Hornchurch",
    "sg:classifiers":[
        {
            "category":"Shopping",
            "subcategory":"Music",
            "type":"Retail Goods"
        }
    ],
    "sg:phone":"+44 7961 308889",
    "sg:postcode":"RM12 4DD",
    "sg:province":"Essex",
    "sg:tags":[
        "record",
        "tape",
        "cd"
    ],
    "wof:name":"Beatz & Pieces",
    "wof:placetype":"venue"
},
  "geometry": {"coordinates":[0.2006299943,51.5587005615],"type":"Point"}
}