{
  "type": "Feature",
  "properties": {
    "iso:country":"GB",
    "sg:address":"80e Randolph Avenue",
    "sg:city":"London",
    "sg:classifiers":[
        {
            "category":"Banks & Credit Unions",
            "subcategory":"Financial Services",
            "type":"Services"
        }
    ],
    "sg:postcode":"W9 1BG",
    "sg:province":"Greater London",
    "sg:tags":[
        "agent",
        "tied"
    ],
    "wof:name":"Taupo Associates Ltd",
    "wof:placetype":"venue"
},
  "geometry": {"coordinates":[-0.182086,51.526962],"type":"Point"}
}