{
  "type": "Feature",
  "properties": {
    "iso:country":"GB",
    "sg:address":"Rutland House, 18 Hilton Street",
    "sg:city":"Manchester",
    "sg:classifiers":[
        {
            "category":"Manufacturing",
            "subcategory":"Textiles",
            "type":"Manufacturing & Wholesale Goods"
        }
    ],
    "sg:phone":"+44 161 228 1191",
    "sg:postcode":"M1 1FR",
    "sg:province":"Greater Manchester",
    "sg:tags":[
        "merchant",
        "agent"
    ],
    "wof:name":"Martin Ailion Agencies",
    "wof:placetype":"venue"
},
  "geometry": {"coordinates":[-2.233217001,53.4821624756],"type":"Point"}
}