{
  "type": "Feature",
  "properties": {
    "iso:country":"GB",
    "sg:address":"55 Taverner Close",
    "sg:city":"Poole",
    "sg:classifiers":[
        {
            "category":"Retail",
            "subcategory":"Driving School",
            "type":"Services"
        }
    ],
    "sg:phone":"+44 1202 683885",
    "sg:postcode":"BH15 1UP",
    "sg:province":"Dorset",
    "sg:website":"http://www.poolequay.com",
    "wof:name":"Baiter School Of Motoring",
    "wof:placetype":"venue"
},
  "geometry": {"coordinates":[-1.973869,50.714413],"type":"Point"}
}