{
  "type": "Feature",
  "properties": {
    "iso:country":"GB",
    "sg:address":"Collot House, 20 Severn Street",
    "sg:city":"Welshpool",
    "sg:classifiers":[
        {
            "category":"Professional",
            "subcategory":"Management & Consulting",
            "type":"Services"
        }
    ],
    "sg:phone":"+44 1938 555654",
    "sg:postcode":"SY21 7AD",
    "sg:province":"Shropshire",
    "sg:tags":[
        "conservation"
    ],
    "wof:name":"Montgomeryshire Wildlife Trust Ltd.",
    "wof:placetype":"venue"
},
  "geometry": {"coordinates":[-3.145745,52.658817],"type":"Point"}
}