{
  "type": "Feature",
  "properties": {
    "iso:country":"GB",
    "sg:address":"Lynton House, Dereham Road, Colkirk",
    "sg:city":"Fakenham",
    "sg:classifiers":[
        {
            "category":"Building & Trades",
            "subcategory":"Construction",
            "type":"Services"
        }
    ],
    "sg:phone":"+44 1328 862733",
    "sg:postcode":"NR21 7NH",
    "sg:province":"Norfolk",
    "sg:tags":[
        "builder"
    ],
    "wof:name":"Derek D Easter Ltd.",
    "wof:placetype":"venue"
},
  "geometry": {"coordinates":[0.8424559832,52.8259658813],"type":"Point"}
}