{
  "type": "Feature",
  "properties": {
    "iso:country":"GB",
    "sg:address":"35 Clermiston Gro",
    "sg:city":"Edinburgh",
    "sg:classifiers":[
        {
            "category":"Building & Trades",
            "subcategory":"Cleaning & Sanitation",
            "type":"Services"
        }
    ],
    "sg:postcode":"EH4 7DA",
    "sg:province":"City of Edinburgh",
    "sg:tags":[
        "cleaner",
        "window"
    ],
    "wof:name":"Fordyce,Keith,",
    "wof:placetype":"venue"
},
  "geometry": {"coordinates":[-3.283128,55.95739],"type":"Point"}
}