{
  "type": "Feature",
  "properties": {
    "addr:full":"Jumps Rd Todmorden Lancashire OL14 8HJ",
    "addr:postcode":"ol14 8hj",
    "addr:street":"Jumps Rd",
    "iso:country":"GB",
    "sg:address":"Jumps Rd",
    "sg:city":"Todmorden",
    "sg:classifiers":[
        {
            "category":"Recreation",
            "subcategory":"Campground",
            "type":"Entertainment"
        }
    ],
    "sg:phone":"+44 1706 814554",
    "sg:postcode":"OL14 8HJ",
    "sg:province":"Lancashire",
    "sg:tags":[
        "holiday",
        "centre",
        "camp"
    ],
    "wof:name":"Action Holidays Ltd",
    "wof:placetype":"venue"
},
  "geometry": {"coordinates":[-2.121717,53.727848],"type":"Point"}
}