{
  "type": "Feature",
  "properties": {
    "addr:full":"Coupe Lane, Old Tupton Chesterfield Derbyshire S42 6HA",
    "addr:postcode":"s42 6ha",
    "addr:street":"Coupe Lane",
    "iso:country":"GB",
    "sg:address":"Coupe Lane, Old Tupton",
    "sg:city":"Chesterfield",
    "sg:classifiers":[
        {
            "category":"Bars & Pubs",
            "type":"Food & Drink"
        }
    ],
    "sg:postcode":"S42 6HA",
    "sg:province":"Derbyshire",
    "sg:tags":[
        "pubs",
        "inn"
    ],
    "wof:name":"The Woodthorpe Inn",
    "wof:placetype":"venue"
},
  "geometry": {"coordinates":[-1.4275399446,53.1789741516],"type":"Point"}
}