{
  "type": "Feature",
  "properties": {
    "iso:country":"GB",
    "sg:address":"22 Kempton Rd",
    "sg:city":"Ipswich",
    "sg:classifiers":[
        {
            "category":"Health Services",
            "subcategory":"Health Practitioner",
            "type":"Services"
        }
    ],
    "sg:phone":"+44 1473 743105",
    "sg:postcode":"IP1 6QY",
    "sg:province":"Suffolk",
    "sg:tags":[
        "therapist",
        "speech"
    ],
    "wof:name":"Medicine Wheel",
    "wof:placetype":"venue"
},
  "geometry": {"coordinates":[1.143526,52.082363],"type":"Point"}
}