{
  "type": "Feature",
  "properties": {
    "addr:full":"63 Eastern Road Romford Essex RM1 3PB",
    "addr:housenumber":"63",
    "addr:postcode":"rm1 3pb",
    "addr:street":"Eastern Road",
    "iso:country":"GB",
    "sg:address":"63 Eastern Road",
    "sg:city":"Romford",
    "sg:classifiers":[
        {
            "category":"Health Services",
            "subcategory":"Dentist",
            "type":"Services"
        }
    ],
    "sg:postcode":"RM1 3PB",
    "sg:province":"Essex",
    "wof:name":"Abbey Denture Service",
    "wof:placetype":"venue"
},
  "geometry": {"coordinates":[0.187957,51.57711],"type":"Point"}
}