{
  "type": "Feature",
  "properties": {
    "iso:country":"GB",
    "sg:address":"411-455 Oldham Rd",
    "sg:city":"Manchester",
    "sg:classifiers":[
        {
            "category":"Professional",
            "subcategory":"Printing & Photocopies",
            "type":"Services"
        }
    ],
    "sg:phone":"+44 161 682 7799",
    "sg:postcode":"M35 0AA",
    "sg:province":"Lancashire",
    "sg:tags":[
        "printer"
    ],
    "wof:name":"Portfolio Fine Arts Ltd",
    "wof:placetype":"venue"
},
  "geometry": {"coordinates":[-2.1581408978,53.5108146667],"type":"Point"}
}