{
  "type": "Feature",
  "properties": {
    "iso:country":"GB",
    "sg:address":"St Marys Medical Centre, Wharf Rd",
    "sg:city":"Stamford",
    "sg:classifiers":[
        {
            "category":"Health Services",
            "subcategory":"Doctor",
            "type":"Services"
        }
    ],
    "sg:phone":"+44 1780 764121",
    "sg:postcode":"PE9 2DH",
    "sg:province":"Cambridgeshire",
    "sg:tags":[
        "practitioners"
    ],
    "wof:name":"Hume, N S",
    "wof:placetype":"venue"
},
  "geometry": {"coordinates":[-0.478447,52.651329],"type":"Point"}
}