{
  "type": "Feature",
  "properties": {
    "iso:country":"GB",
    "sg:address":"30 Peffermill Road",
    "sg:city":"Edinburgh",
    "sg:classifiers":[
        {
            "category":"Autos & Motor Vehicles",
            "subcategory":"Automobile Sales",
            "type":"Retail Goods"
        }
    ],
    "sg:postcode":"EH16 5LL",
    "sg:province":"City of Edinburgh",
    "sg:tags":[
        "car"
    ],
    "wof:name":"Capital Motors (Edinburgh) Ltd.",
    "wof:placetype":"venue"
},
  "geometry": {"coordinates":[-3.158947,55.930058],"type":"Point"}
}