{
  "type": "Feature",
  "properties": {
    "addr:full":"The Parsonage, Winford Bristol Somerset BS40 8DW",
    "addr:postcode":"bs40 8dw",
    "iso:country":"GB",
    "sg:address":"The Parsonage, Winford",
    "sg:city":"Bristol",
    "sg:classifiers":[
        {
            "category":"Professional",
            "subcategory":"Advertising",
            "type":"Services"
        }
    ],
    "sg:postcode":"BS40 8DW",
    "sg:province":"Somerset",
    "sg:tags":[
        "agency"
    ],
    "wof:name":"Picador Design International Ltd.",
    "wof:placetype":"venue"
},
  "geometry": {"coordinates":[-2.6620140076,51.3826217651],"type":"Point"}
}