{
  "type": "Feature",
  "properties": {
    "addr:full":"Costhorpe Indstl Est, Doncaster Rd, Costhorpe Worksop Nottinghamshire S81 9QR",
    "addr:postcode":"s81 9qr",
    "addr:street":"Doncaster Rd",
    "iso:country":"GB",
    "sg:address":"Costhorpe Indstl Est, Doncaster Rd, Costhorpe",
    "sg:city":"Worksop",
    "sg:classifiers":[
        {
            "category":"Building & Trades",
            "subcategory":"Construction",
            "type":"Services"
        }
    ],
    "sg:postcode":"S81 9QR",
    "sg:province":"Nottinghamshire",
    "sg:tags":[
        "roofing"
    ],
    "wof:name":"Rooftech Services",
    "wof:placetype":"venue"
},
  "geometry": {"coordinates":[-1.124489,53.36607],"type":"Point"}
}