{
  "type": "Feature",
  "properties": {
    "iso:country":"GB",
    "sg:address":"Unit 2, Prospect Court, Nunn Close",
    "sg:city":"Sutton-in-ashfield",
    "sg:classifiers":[
        {
            "category":"Building & Trades",
            "subcategory":"Construction",
            "type":"Services"
        }
    ],
    "sg:postcode":"NG17 2HW",
    "sg:province":"Nottinghamshire",
    "sg:tags":[
        "flooring"
    ],
    "wof:name":"Floorscape Contracts Ltd.",
    "wof:placetype":"venue"
},
  "geometry": {"coordinates":[-1.307799,53.120644],"type":"Point"}
}