{
  "type": "Feature",
  "properties": {
    "iso:country":"GB",
    "sg:address":"5a Walden Way",
    "sg:city":"Hornchurch",
    "sg:classifiers":[
        {
            "category":"Utilities",
            "subcategory":"Natural Gas",
            "type":"Services"
        }
    ],
    "sg:phone":"+44 1708 458642",
    "sg:postcode":"RM11 2LB",
    "sg:province":"Essex",
    "sg:tags":[
        "supplier",
        "industrial"
    ],
    "wof:name":"Nitrogen Services",
    "wof:placetype":"venue"
},
  "geometry": {"coordinates":[0.2169629931,51.5721588135],"type":"Point"}
}