{
  "type": "Feature",
  "properties": {
    "addr:full":"60-62 Market Street Crewe Cheshire CW1 2HD",
    "addr:housenumber":"60-62",
    "addr:postcode":"cw1 2hd",
    "addr:street":"Market Street",
    "iso:country":"GB",
    "sg:address":"60-62 Market Street",
    "sg:city":"Crewe",
    "sg:classifiers":[
        {
            "category":"Shopping",
            "subcategory":"Bicycles & Sporting Goods",
            "type":"Retail Goods"
        },
        {
            "category":"Wholesale",
            "subcategory":"Sporting Goods",
            "type":"Manufacturing & Wholesale Goods"
        }
    ],
    "sg:phone":"+44 1270 588040",
    "sg:postcode":"CW1 2HD",
    "sg:province":"Cheshire",
    "sg:tags":[
        "supplier",
        "equipment",
        "camping"
    ],
    "wof:name":"Famous Army Stores Ltd.",
    "wof:placetype":"venue"
},
  "geometry": {"coordinates":[-2.441058,53.098614],"type":"Point"}
}