{
  "type": "Feature",
  "properties": {
    "addr:full":"Grange Road, Tiptree Colchester Essex CO5 0QQ",
    "addr:postcode":"co5 0qq",
    "addr:street":"Grange Road",
    "iso:country":"GB",
    "sg:address":"Grange Road, Tiptree",
    "sg:city":"Colchester",
    "sg:classifiers":[
        {
            "category":"Manufacturing",
            "subcategory":"Wood Products",
            "type":"Manufacturing & Wholesale Goods"
        }
    ],
    "sg:phone":"+44 1621 815419",
    "sg:postcode":"CO5 0QQ",
    "sg:province":"Essex",
    "sg:tags":[
        "sawmill",
        "shaving"
    ],
    "wof:name":"Richard Martin",
    "wof:placetype":"venue"
},
  "geometry": {"coordinates":[0.7453340292,51.8164634705],"type":"Point"}
}