{
  "type": "Feature",
  "properties": {
    "addr:full":"Unit 48, The Exchange Shopping Centre Ilford Essex IG1 1LR",
    "addr:housenumber":"unit 48",
    "addr:postcode":"ig1 1lr",
    "addr:street":"The;Shopping;Ilford",
    "iso:country":"GB",
    "sg:address":"Unit 48, The Exchange Shopping Centre",
    "sg:city":"Ilford",
    "sg:classifiers":[
        {
            "category":"Personal",
            "subcategory":"Beauty Salon",
            "type":"Services"
        }
    ],
    "sg:phone":"+44 20 8478 5505",
    "sg:postcode":"IG1 1LR",
    "sg:province":"Essex",
    "wof:name":"Dream Nails",
    "wof:placetype":"venue"
},
  "geometry": {"coordinates":[0.067115,51.563751],"type":"Point"}
}