{
  "type": "Feature",
  "properties": {
    "iso:country":"GB",
    "sg:address":"Unit 5 Flansham Business Centre, Flansham",
    "sg:city":"Bognor Regis",
    "sg:classifiers":[
        {
            "category":"Shopping",
            "subcategory":"Optical Goods",
            "type":"Retail Goods"
        }
    ],
    "sg:postcode":"PO22 8NJ",
    "sg:province":"West Sussex",
    "sg:tags":[
        "medical"
    ],
    "wof:name":"Framewear International Uk",
    "wof:placetype":"venue"
},
  "geometry": {"coordinates":[-0.63921,50.80291],"type":"Point"}
}