{
  "type": "Feature",
  "properties": {
    "addr:full":"50 Wellington Road Ashton-under-lyne Greater Manchester OL6 6XL",
    "addr:housenumber":"50",
    "addr:postcode":"ol6 6xl",
    "addr:street":"Wellington Road",
    "iso:country":"GB",
    "sg:address":"50 Wellington Road",
    "sg:city":"Ashton-under-lyne",
    "sg:classifiers":[
        {
            "category":"Professional",
            "subcategory":"Lawyer & Legal Services",
            "type":"Services"
        }
    ],
    "sg:phone":"+44 161 330 6821",
    "sg:postcode":"OL6 6XL",
    "sg:province":"Greater Manchester",
    "sg:tags":[
        "solicitor"
    ],
    "sg:website":"http://www.bromleys.co.uk",
    "wof:name":"Bromley Hyde & Robinson",
    "wof:placetype":"venue"
},
  "geometry": {"coordinates":[-2.0929040909,53.4878997803],"type":"Point"}
}