{
  "type": "Feature",
  "properties": {
    "addr:full":"Wescoe Close, Orrell Wigan Lancashire WN5 8TF",
    "addr:postcode":"orrell;wn5 8tf",
    "addr:street":"Wescoe Close",
    "iso:country":"GB",
    "sg:address":"Wescoe Close, Orrell",
    "sg:city":"Wigan",
    "sg:classifiers":[
        {
            "category":"Professional",
            "type":"Services"
        }
    ],
    "sg:postcode":"WN5 8TF",
    "sg:province":"Lancashire",
    "sg:tags":[
        "interior",
        "furnishers",
        "designer"
    ],
    "wof:name":"Asbury Interiors",
    "wof:placetype":"venue"
},
  "geometry": {"coordinates":[-2.7137789726,53.5318946838],"type":"Point"}
}