{
  "type": "Feature",
  "properties": {
    "iso:country":"GB",
    "sg:address":"65 Oakhill Road",
    "sg:city":"London",
    "sg:classifiers":[
        {
            "category":"Professional",
            "subcategory":"Management & Consulting",
            "type":"Services"
        }
    ],
    "sg:postcode":"SW15 2QJ",
    "sg:province":"Greater London",
    "sg:tags":[
        "consultant",
        "business"
    ],
    "wof:name":"White Horse Consulting Ltd",
    "wof:placetype":"venue"
},
  "geometry": {"coordinates":[-0.2036940008,51.4597129822],"type":"Point"}
}