{
  "type": "Feature",
  "properties": {
    "iso:country":"GB",
    "sg:address":"Maxwell Road, Pocklington",
    "sg:city":"York",
    "sg:classifiers":[
        {
            "category":"Education",
            "subcategory":"School",
            "type":"Public Place"
        }
    ],
    "sg:phone":"+44 1759 302699",
    "sg:postcode":"YO42 2HE",
    "sg:province":"East Riding of Yorkshire",
    "sg:tags":[
        "local",
        "authority"
    ],
    "wof:name":"Pocklington C of E Infants School",
    "wof:placetype":"venue"
},
  "geometry": {"coordinates":[-0.776484,53.934715],"type":"Point"}
}