{
  "type": "Feature",
  "properties": {
    "addr:full":"Lower Ground, 26 Seymour St West End Greater London W1H 5WD",
    "addr:housenumber":"26",
    "addr:postcode":"w1h 5wd",
    "addr:street":"Lower Ground;Seymour St",
    "iso:country":"GB",
    "sg:address":"Lower Ground, 26 Seymour St",
    "sg:city":"West End",
    "sg:classifiers":[
        {
            "category":"Real Estate",
            "subcategory":"Real Estate Agent",
            "type":"Services"
        }
    ],
    "sg:phone":"+44 20 7723 8800",
    "sg:postcode":"W1H 5WD",
    "sg:province":"Greater London",
    "wof:name":"London Accomodation",
    "wof:placetype":"venue"
},
  "geometry": {"coordinates":[-0.16398,51.516491],"type":"Point"}
}