{
  "type": "Feature",
  "properties": {
    "addr:full":"Ty Hen Farm Hotel, Llwyndafydd Llandysul Carmarthenshire SA44 6BZ",
    "addr:postcode":"sa44 6bz",
    "iso:country":"GB",
    "sg:address":"Ty Hen Farm Hotel, Llwyndafydd",
    "sg:city":"Llandysul",
    "sg:classifiers":[
        {
            "category":"Farming",
            "subcategory":"Livestock Farm",
            "type":"Manufacturing & Wholesale Goods"
        }
    ],
    "sg:postcode":"SA44 6BZ",
    "sg:province":"Carmarthenshire",
    "sg:tags":[
        "others"
    ],
    "wof:name":"Ty-Hen Farm & Cottages",
    "wof:placetype":"venue"
},
  "geometry": {"coordinates":[-4.3829689026,52.1733169556],"type":"Point"}
}