{
  "type": "Feature",
  "properties": {
    "iso:country":"GB",
    "sg:address":"St Johns Hall, Fakenham Rd, Attlebridge",
    "sg:city":"Norwich",
    "sg:classifiers":[
        {
            "category":"Building & Trades",
            "subcategory":"Landscaping Services",
            "type":"Services"
        }
    ],
    "sg:postcode":"NR9 5ST",
    "sg:province":"Norfolk",
    "sg:tags":[
        "horticultural",
        "consultant"
    ],
    "wof:name":"J L Machines",
    "wof:placetype":"venue"
},
  "geometry": {"coordinates":[1.155095,52.704361],"type":"Point"}
}