{
  "type": "Feature",
  "properties": {
    "iso:country":"GB",
    "sg:address":"70 Auchmithie",
    "sg:city":"Arbroath",
    "sg:classifiers":[
        {
            "category":"Real Estate",
            "subcategory":"Architect",
            "type":"Services"
        }
    ],
    "sg:postcode":"DD11 5SQ",
    "sg:province":"Angus",
    "sg:tags":[
        "technologist",
        "architectural"
    ],
    "wof:name":"Arkitecnic Architectural Surveying Services",
    "wof:placetype":"venue"
},
  "geometry": {"coordinates":[-2.52199,56.589699],"type":"Point"}
}