{
  "type": "Feature",
  "properties": {
    "iso:country":"GB",
    "sg:address":"33 Dalmun Avenue",
    "sg:city":"Dalbeattie",
    "sg:classifiers":[
        {
            "category":"Utilities",
            "type":"Services"
        }
    ],
    "sg:phone":"+44 1556 612131",
    "sg:postcode":"DG5 4PW",
    "sg:province":"Dumfries and Galloway",
    "sg:tags":[
        "internet"
    ],
    "wof:name":"Dalbeattie Internet",
    "wof:placetype":"venue"
},
  "geometry": {"coordinates":[-3.8204829693,54.9252815247],"type":"Point"}
}