{
  "type": "Feature",
  "properties": {
    "addr:full":"14 Church Avenue Haywards Heath East Sussex RH16 1ED",
    "addr:housenumber":"14",
    "addr:postcode":"rh16 1ed",
    "addr:street":"Church Avenue",
    "iso:country":"GB",
    "sg:address":"14 Church Avenue",
    "sg:city":"Haywards Heath",
    "sg:classifiers":[
        {
            "category":"Building & Trades",
            "subcategory":"Construction",
            "type":"Services"
        }
    ],
    "sg:phone":"+44 1444 453398",
    "sg:postcode":"RH16 1ED",
    "sg:province":"East Sussex",
    "sg:tags":[
        "ceiling",
        "contractor"
    ],
    "wof:name":"David Hyde",
    "wof:placetype":"venue"
},
  "geometry": {"coordinates":[-0.0998469964,51.0065460205],"type":"Point"}
}