{
  "type": "Feature",
  "properties": {
    "iso:country":"GB",
    "sg:address":"Castle House, Friar Lane",
    "sg:city":"Nottingham",
    "sg:classifiers":[
        {
            "category":"Professional",
            "subcategory":"Lawyer & Legal Services",
            "type":"Services"
        }
    ],
    "sg:phone":"+44 115 947 4326",
    "sg:postcode":"NG1 6EW",
    "sg:province":"Nottinghamshire",
    "sg:tags":[
        "solicitor"
    ],
    "wof:name":"Bernard Wright & Cursham",
    "wof:placetype":"venue"
},
  "geometry": {"coordinates":[-1.151503,52.952492],"type":"Point"}
}