{
  "type": "Feature",
  "properties": {
    "addr:full":"406a Birmingham Road Sutton Coldfield West Midlands B72 1YJ",
    "addr:housenumber":"406a",
    "addr:postcode":"b72 1yj",
    "addr:street":"Birmingham Road",
    "iso:country":"GB",
    "sg:address":"406a Birmingham Road",
    "sg:city":"Sutton Coldfield",
    "sg:classifiers":[
        {
            "category":"Banks & Credit Unions",
            "subcategory":"Bank",
            "type":"Services"
        }
    ],
    "sg:phone":"+44 121 321 1521",
    "sg:postcode":"B72 1YJ",
    "sg:province":"West Midlands",
    "sg:tags":[
        "broker",
        "mortgage"
    ],
    "wof:name":"Warick Night Associates",
    "wof:placetype":"venue"
},
  "geometry": {"coordinates":[-1.826769,52.555779],"type":"Point"}
}