{
  "type": "Feature",
  "properties": {
    "iso:country":"GB",
    "sg:address":"Rashs Green",
    "sg:city":"Dereham",
    "sg:classifiers":[
        {
            "category":"Home & Garden",
            "subcategory":"Hardware",
            "type":"Retail Goods"
        }
    ],
    "sg:phone":"+44 1362 696848",
    "sg:postcode":"NR19 1JG",
    "sg:province":"Norfolk",
    "sg:tags":[
        "device",
        "fixing",
        "fastener"
    ],
    "wof:name":"Norfolk Fasteners",
    "wof:placetype":"venue"
},
  "geometry": {"coordinates":[0.9474740028,52.6690254211],"type":"Point"}
}