{
  "type": "Feature",
  "properties": {
    "iso:country":"GB",
    "sg:address":"82 Woodville Road",
    "sg:city":"Cardiff",
    "sg:classifiers":[
        {
            "category":"Shopping",
            "subcategory":"News",
            "type":"Retail Goods"
        }
    ],
    "sg:phone":"+44 29 2039 4102",
    "sg:postcode":"CF24 4ED",
    "sg:province":"Cardiff",
    "sg:tags":[
        "newsagent"
    ],
    "wof:name":"Julies",
    "wof:placetype":"venue"
},
  "geometry": {"coordinates":[-3.177807,51.492805],"type":"Point"}
}