{
  "type": "Feature",
  "properties": {
    "addr:full":"77 Kingsgate Road London Greater London NW6 4ND",
    "addr:housenumber":"77",
    "addr:postcode":"nw6 4nd",
    "addr:street":"Kingsgate Road",
    "iso:country":"GB",
    "sg:address":"77 Kingsgate Road",
    "sg:city":"London",
    "sg:classifiers":[
        {
            "category":"Communications",
            "type":"Services"
        }
    ],
    "sg:phone":"+44 20 7372 6451",
    "sg:postcode":"NW6 4ND",
    "sg:province":"Greater London",
    "sg:tags":[
        "tv",
        "video",
        "radio"
    ],
    "wof:name":"Lightning Electronics",
    "wof:placetype":"venue"
},
  "geometry": {"coordinates":[-0.0793550014,51.5448112488],"type":"Point"}
}