{
  "type": "Feature",
  "properties": {
    "addr:full":"23 Royal Quays Factory Outlets, Coble Dene Rd North Shields Tyne and Wear NE29 6DW",
    "addr:housenumber":"23",
    "addr:postcode":"coble;ne29 6dw",
    "addr:street":"Royal Quays;Dene Rd",
    "iso:country":"GB",
    "sg:address":"23 Royal Quays Factory Outlets, Coble Dene Rd",
    "sg:city":"North Shields",
    "sg:classifiers":[
        {
            "category":"Shopping",
            "subcategory":"Clothing, Apparel, & Fashions",
            "type":"Retail Goods"
        }
    ],
    "sg:phone":"+44 191 258 7844",
    "sg:postcode":"NE29 6DW",
    "sg:province":"Tyne and Wear",
    "sg:tags":[
        "ladieswear"
    ],
    "wof:name":"Trash Design",
    "wof:placetype":"venue"
},
  "geometry": {"coordinates":[-1.4652099609,54.9952087402],"type":"Point"}
}