{
  "type": "Feature",
  "properties": {
    "iso:country":"GB",
    "sg:address":"10 Coronation Road, Sunniside",
    "sg:city":"Newcastle-upon-tyne",
    "sg:classifiers":[
        {
            "category":"Bus Charters",
            "type":"Transportation"
        }
    ],
    "sg:phone":"+44 191 488 1559",
    "sg:postcode":"NE16 5NR",
    "sg:province":"Durham",
    "sg:tags":[
        "coach"
    ],
    "wof:name":"Lowdons of Sunniside",
    "wof:placetype":"venue"
},
  "geometry": {"coordinates":[-1.6765669584,54.9226913452],"type":"Point"}
}