{
  "type": "Feature",
  "properties": {
    "addr:full":"Drayton Lane Norwich Norfolk NR10 3AN",
    "addr:postcode":"nr10 3an",
    "addr:street":"Drayton Lane",
    "iso:country":"GB",
    "sg:address":"Drayton Lane",
    "sg:city":"Norwich",
    "sg:classifiers":[
        {
            "category":"Transit Center",
            "subcategory":"Passenger",
            "type":"Transportation"
        }
    ],
    "sg:postcode":"NR10 3AN",
    "sg:province":"Norfolk",
    "sg:tags":[
        "boarding",
        "kennel",
        "catteries"
    ],
    "wof:name":"Homestead Cattery",
    "wof:placetype":"venue"
},
  "geometry": {"coordinates":[1.242736,52.687637],"type":"Point"}
}