{
  "type": "Feature",
  "properties": {
    "addr:full":"502 Portswood Road Southampton Hampshire SO17 3SP",
    "addr:housenumber":"502",
    "addr:postcode":"so17 3sp",
    "addr:street":"Portswood Road",
    "iso:country":"GB",
    "sg:address":"502 Portswood Road",
    "sg:city":"Southampton",
    "sg:classifiers":[
        {
            "category":"Retail",
            "subcategory":"Repair Shop",
            "type":"Services"
        }
    ],
    "sg:phone":"+44 23 8055 5888",
    "sg:postcode":"SO17 3SP",
    "sg:province":"Hampshire",
    "sg:tags":[
        "upholsterer"
    ],
    "wof:name":"Dee Cee Upholstery",
    "wof:placetype":"venue"
},
  "geometry": {"coordinates":[-1.3826270103,50.9336128235],"type":"Point"}
}