{
  "type": "Feature",
  "properties": {
    "addr:full":"Viking Street, 3 Fountain Street Hebden Bridge West Yorkshire HX7 6HE",
    "addr:housenumber":"3",
    "addr:postcode":"hx7 6he",
    "addr:street":"Viking Street;Fountain Street",
    "iso:country":"GB",
    "sg:address":"Viking Street, 3 Fountain Street",
    "sg:city":"Hebden Bridge",
    "sg:classifiers":[
        {
            "category":"Wholesale",
            "subcategory":"Books, Periodicals, & Newspapers",
            "type":"Manufacturing & Wholesale Goods"
        }
    ],
    "sg:phone":"+44 1422 844679",
    "sg:postcode":"HX7 6HE",
    "sg:province":"West Yorkshire",
    "sg:tags":[
        "publishing"
    ],
    "wof:name":"Viking Press Northern Ltd.",
    "wof:placetype":"venue"
},
  "geometry": {"coordinates":[-2.0144910812,53.7412261963],"type":"Point"}
}