{
  "type": "Feature",
  "properties": {
    "addr:full":"7 Blackford Road Watford Hertfordshire WD19 6YW",
    "addr:housenumber":"7",
    "addr:postcode":"wd19 6yw",
    "addr:street":"Blackford Road",
    "iso:country":"GB",
    "sg:address":"7 Blackford Road",
    "sg:city":"Watford",
    "sg:classifiers":[
        {
            "category":"Building & Trades",
            "subcategory":"Plumbing",
            "type":"Services"
        }
    ],
    "sg:postcode":"WD19 6YW",
    "sg:province":"Hertfordshire",
    "sg:tags":[
        "central",
        "heating"
    ],
    "wof:name":"Holley Plumbing & Heating",
    "wof:placetype":"venue"
},
  "geometry": {"coordinates":[-0.3897790015,51.6174545288],"type":"Point"}
}