{
  "type": "Feature",
  "properties": {
    "addr:full":"11 Bridge Street Ballater Aberdeenshire AB35 5QP",
    "addr:housenumber":"11",
    "addr:postcode":"ab35 5qp",
    "addr:street":"Bridge Street",
    "iso:country":"GB",
    "sg:address":"11 Bridge Street",
    "sg:city":"Ballater",
    "sg:classifiers":[
        {
            "category":"Food & Beverages",
            "subcategory":"Meat & Fish",
            "type":"Retail Goods"
        }
    ],
    "sg:phone":"+44 1339 755218",
    "sg:postcode":"AB35 5QP",
    "sg:province":"Aberdeenshire",
    "sg:tags":[
        "butcher"
    ],
    "wof:name":"H M Sheridan",
    "wof:placetype":"venue"
},
  "geometry": {"coordinates":[-3.038677,57.047943],"type":"Point"}
}