{
  "type": "Feature",
  "properties": {
    "addr:full":"1-3 Camberwell Church Street London Greater London SE5 8TR",
    "addr:housenumber":"1-3",
    "addr:postcode":"se5 8tr",
    "addr:street":"Camberwell Church Street",
    "iso:country":"GB",
    "sg:address":"1-3 Camberwell Church Street",
    "sg:city":"London",
    "sg:classifiers":[
        {
            "category":"Shopping",
            "subcategory":"Mobile Phones",
            "type":"Retail Goods"
        }
    ],
    "sg:phone":"+44 20 7252 4225",
    "sg:postcode":"SE5 8TR",
    "sg:province":"Greater London",
    "wof:name":"Mobile Phone World Ltd.",
    "wof:placetype":"venue"
},
  "geometry": {"coordinates":[-0.0892369971,51.4739074707],"type":"Point"}
}