{
  "type": "Feature",
  "properties": {
    "iso:country":"GB",
    "sg:address":"Swalwell Close",
    "sg:city":"Prudhoe",
    "sg:classifiers":[
        {
            "category":"Professional",
            "subcategory":"Accounting & Tax Preparation",
            "type":"Services"
        }
    ],
    "sg:postcode":"NE42 6EX",
    "sg:province":"Northumberland",
    "sg:tags":[
        "accountant"
    ],
    "wof:name":"Bassett Herron",
    "wof:placetype":"venue"
},
  "geometry": {"coordinates":[-1.853969,54.959595],"type":"Point"}
}