{
  "type": "Feature",
  "properties": {
    "addr:full":"12 Clay Hill Lyndhurst Hampshire SO43 7DE",
    "addr:housenumber":"12",
    "addr:postcode":"so43 7de",
    "iso:country":"GB",
    "sg:address":"12 Clay Hill",
    "sg:city":"Lyndhurst",
    "sg:classifiers":[
        {
            "category":"Bars & Pubs",
            "type":"Food & Drink"
        }
    ],
    "sg:postcode":"SO43 7DE",
    "sg:province":"Hampshire",
    "sg:tags":[
        "pubs",
        "inn"
    ],
    "wof:name":"Crown & Stirrup",
    "wof:placetype":"venue"
},
  "geometry": {"coordinates":[-1.574469,50.866413],"type":"Point"}
}