{
  "type": "Feature",
  "properties": {
    "iso:country":"GB",
    "sg:address":"Burnt Edge Farm, Blackshawhead",
    "sg:city":"Hebden Bridge",
    "sg:classifiers":[
        {
            "category":"Shopping",
            "subcategory":"Stationery & Office Supplies",
            "type":"Retail Goods"
        }
    ],
    "sg:phone":"+44 1422 845145",
    "sg:postcode":"HX7 7JA",
    "sg:province":"West Yorkshire",
    "sg:tags":[
        "item",
        "promotional"
    ],
    "wof:name":"Promotex",
    "wof:placetype":"venue"
},
  "geometry": {"coordinates":[-2.0645020008,53.7446403503],"type":"Point"}
}