{
  "type": "Feature",
  "properties": {
    "addr:full":"New Street Congleton Cheshire CW12 3AH",
    "addr:postcode":"cw12 3ah",
    "addr:street":"New Street",
    "iso:country":"GB",
    "sg:address":"New Street",
    "sg:city":"Congleton",
    "sg:classifiers":[
        {
            "category":"Education",
            "subcategory":"School",
            "type":"Public Place"
        },
        {
            "category":"Government",
            "subcategory":"Office",
            "type":"Public Place"
        }
    ],
    "sg:phone":"+44 1260 273576",
    "sg:postcode":"CW12 3AH",
    "sg:province":"Cheshire",
    "sg:tags":[
        "local",
        "authority"
    ],
    "wof:name":"Cheshire County Council",
    "wof:placetype":"venue"
},
  "geometry": {"coordinates":[-2.206239,53.160648],"type":"Point"}
}