{
  "type": "Feature",
  "properties": {
    "addr:full":"193 Main Street, Newthorpe Nottingham Derbyshire NG16 2DL",
    "addr:housenumber":"193",
    "addr:postcode":"ng16 2dl",
    "addr:street":"Main Street",
    "iso:country":"GB",
    "sg:address":"193 Main Street, Newthorpe",
    "sg:city":"Nottingham",
    "sg:classifiers":[
        {
            "category":"Social Services",
            "subcategory":"Child Care",
            "type":"Services"
        }
    ],
    "sg:phone":"+44 1773 533422",
    "sg:postcode":"NG16 2DL",
    "sg:province":"Derbyshire",
    "sg:tags":[
        "agency",
        "nanny"
    ],
    "wof:name":"Karens Caring Nanny Agency",
    "wof:placetype":"venue"
},
  "geometry": {"coordinates":[-1.2817989588,53.0119857788],"type":"Point"}
}