{
  "type": "Feature",
  "properties": {
    "iso:country":"GB",
    "sg:address":"Unit 7, Yard 2 Stricklandgate",
    "sg:city":"Kendal",
    "sg:classifiers":[
        {
            "category":"Shopping",
            "subcategory":"Pets & Pet Supplies",
            "type":"Retail Goods"
        }
    ],
    "sg:postcode":"LA9 4ND",
    "sg:province":"Cumbria",
    "wof:name":"Cheeky Monkey's Pets & Aquatics",
    "wof:placetype":"venue"
},
  "geometry": {"coordinates":[-2.7490289211,54.3286705017],"type":"Point"}
}