{
  "type": "Feature",
  "properties": {
    "addr:full":"20 St John Street Bridgwater Somerset TA6 5HS",
    "addr:housenumber":"20",
    "addr:postcode":"ta6 5hs",
    "addr:street":"St John Street",
    "iso:country":"GB",
    "sg:address":"20 St John Street",
    "sg:city":"Bridgwater",
    "sg:classifiers":[
        {
            "category":"Bars & Pubs",
            "type":"Food & Drink"
        }
    ],
    "sg:postcode":"TA6 5HS",
    "sg:province":"Somerset",
    "sg:tags":[
        "pubs",
        "inn"
    ],
    "wof:name":"Rebels Retreat",
    "wof:placetype":"venue"
},
  "geometry": {"coordinates":[-2.996246,51.128754],"type":"Point"}
}