{
  "type": "Feature",
  "properties": {
    "addr:full":"20 Market Place, Pocklington York East Riding of Yorkshire YO42 2AR",
    "addr:housenumber":"20",
    "addr:postcode":"yo42 2ar",
    "addr:street":"Market Place",
    "iso:country":"GB",
    "sg:address":"20 Market Place, Pocklington",
    "sg:city":"York",
    "sg:classifiers":[
        {
            "category":"Retail",
            "subcategory":"Portrait Studio",
            "type":"Services"
        },
        {
            "category":"Professional",
            "subcategory":"Art Services",
            "type":"Services"
        }
    ],
    "sg:phone":"+44 1759 306677",
    "sg:postcode":"YO42 2AR",
    "sg:province":"East Riding of Yorkshire",
    "sg:tags":[
        "photographer",
        "photographic"
    ],
    "wof:name":"Charisma Photographic Studio",
    "wof:placetype":"venue"
},
  "geometry": {"coordinates":[-0.7787140012,53.9302864075],"type":"Point"}
}