{
  "type": "Feature",
  "properties": {
    "addr:full":"202 Painthorpe Lane, Crigglestone Wakefield West Yorkshire WF4 3NX",
    "addr:housenumber":"202",
    "addr:postcode":"wf4 3nx",
    "addr:street":"Painthorpe Lane;West",
    "iso:country":"GB",
    "sg:address":"202 Painthorpe Lane, Crigglestone",
    "sg:city":"Wakefield",
    "sg:classifiers":[
        {
            "category":"Food & Beverages",
            "subcategory":"Groceries & Convenience Stores",
            "type":"Retail Goods"
        }
    ],
    "sg:phone":"+44 1924 240339",
    "sg:postcode":"WF4 3NX",
    "sg:province":"West Yorkshire",
    "wof:name":"Singh & Booze",
    "wof:placetype":"venue"
},
  "geometry": {"coordinates":[-1.5313630104,53.6380500793],"type":"Point"}
}