{
  "type": "Feature",
  "properties": {
    "addr:full":"Church St, Upton Noble Shepton Mallet Somerset BA4 6AS",
    "addr:postcode":"ba4 6as",
    "addr:street":"Church St",
    "iso:country":"GB",
    "sg:address":"Church St, Upton Noble",
    "sg:city":"Shepton Mallet",
    "sg:classifiers":[
        {
            "category":"Government",
            "subcategory":"Post Office",
            "type":"Public Place"
        }
    ],
    "sg:phone":"+44 1749 850309",
    "sg:postcode":"BA4 6AS",
    "sg:province":"Somerset",
    "wof:name":"Upton Noble P.O",
    "wof:placetype":"venue"
},
  "geometry": {"coordinates":[-2.410814,51.153587],"type":"Point"}
}