{
  "type": "Feature",
  "properties": {
    "addr:full":"149 Northumberland Street, Tyneside Newcastle-upon-tyne Tyne and Wear NE1 7AG",
    "addr:housenumber":"149",
    "addr:postcode":"ne1 7ag",
    "addr:street":"Northumberland Street",
    "iso:country":"GB",
    "sg:address":"149 Northumberland Street, Tyneside",
    "sg:city":"Newcastle-upon-tyne",
    "sg:classifiers":[
        {
            "category":"Retail",
            "subcategory":"Photofinishing",
            "type":"Services"
        }
    ],
    "sg:phone":"+44 191 261 2220",
    "sg:postcode":"NE1 7AG",
    "sg:province":"Tyne and Wear",
    "sg:tags":[
        "photographic",
        "processor"
    ],
    "wof:name":"Sketchley Retail Ltd.",
    "wof:placetype":"venue"
},
  "geometry": {"coordinates":[-1.612841,54.976631],"type":"Point"}
}