{
  "type": "Feature",
  "properties": {
    "iso:country":"GB",
    "sg:address":"Little London",
    "sg:city":"Newport",
    "sg:classifiers":[
        {
            "category":"Shopping",
            "subcategory":"Pets & Pet Supplies",
            "type":"Retail Goods"
        }
    ],
    "sg:postcode":"PO30 5BP",
    "sg:province":"Isle of Wight",
    "wof:name":"McIntyre,Arthur,",
    "wof:placetype":"venue"
},
  "geometry": {"coordinates":[-1.2916020155,50.7023735046],"type":"Point"}
}