{
  "type": "Feature",
  "properties": {
    "addr:full":"Bethlehem Llandeilo Carmarthenshire SA19 6YE",
    "addr:postcode":"sa19 6ye",
    "iso:country":"GB",
    "sg:address":"Bethlehem",
    "sg:city":"Llandeilo",
    "sg:classifiers":[
        {
            "category":"Farming",
            "subcategory":"Livestock Farm",
            "type":"Manufacturing & Wholesale Goods"
        }
    ],
    "sg:phone":"+44 1558 823447",
    "sg:postcode":"SA19 6YE",
    "sg:province":"Carmarthenshire",
    "sg:tags":[
        "others"
    ],
    "wof:name":"Glantowy Farm",
    "wof:placetype":"venue"
},
  "geometry": {"coordinates":[-3.9918570518,51.8841362],"type":"Point"}
}