{
  "type": "Feature",
  "properties": {
    "addr:full":"26 Ennismore Gardens Thames Ditton Surrey KT7 0YR",
    "addr:housenumber":"26",
    "addr:postcode":"kt7 0yr",
    "addr:street":"Ennismore Gardens;Ditton",
    "iso:country":"GB",
    "sg:address":"26 Ennismore Gardens",
    "sg:city":"Thames Ditton",
    "sg:classifiers":[
        {
            "category":"Professional",
            "subcategory":"Accounting & Tax Preparation",
            "type":"Services"
        },
        {
            "category":"Professional",
            "subcategory":"Computer Services",
            "type":"Services"
        }
    ],
    "sg:phone":"+44 20 8398 4455",
    "sg:postcode":"KT7 0YR",
    "sg:province":"Surrey",
    "sg:tags":[
        "software",
        "system",
        "activity"
    ],
    "wof:name":"Zanthos Ltd.",
    "wof:placetype":"venue"
},
  "geometry": {"coordinates":[-0.343967,51.392311],"type":"Point"}
}