{
  "type": "Feature",
  "properties": {
    "iso:country":"GB",
    "sg:address":"Worthing Road, Dial Post",
    "sg:city":"Horsham",
    "sg:classifiers":[
        {
            "category":"Bars & Pubs",
            "type":"Food & Drink"
        }
    ],
    "sg:phone":"+44 1403 710902",
    "sg:postcode":"RH13 8NH",
    "sg:province":"West Sussex",
    "sg:tags":[
        "pubs",
        "inn"
    ],
    "wof:name":"The Crown Inn",
    "wof:placetype":"venue"
},
  "geometry": {"coordinates":[-0.354292,50.965206],"type":"Point"}
}