{
  "type": "Feature",
  "properties": {
    "iso:country":"GB",
    "sg:address":"Cranmore Blvd, Shirley",
    "sg:city":"Solihull",
    "sg:classifiers":[
        {
            "category":"Manufacturing",
            "subcategory":"Wood Products",
            "type":"Manufacturing & Wholesale Goods"
        }
    ],
    "sg:phone":"+44 121 733 3030",
    "sg:postcode":"B90 4LJ",
    "sg:province":"West Midlands",
    "sg:tags":[
        "packaging",
        "crate",
        "pallets"
    ],
    "wof:name":"Carrs Paper Ltd.",
    "wof:placetype":"venue"
},
  "geometry": {"coordinates":[-1.8066439629,52.4020347595],"type":"Point"}
}