{
  "type": "Feature",
  "properties": {
    "addr:full":"Shaftesbury Centre, 85 Barlby Rd Ladbroke Grove Greater London W10 6AR",
    "addr:housenumber":"85",
    "addr:postcode":"w10 6ar",
    "addr:street":"Barlby Rd",
    "iso:country":"GB",
    "sg:address":"Shaftesbury Centre, 85 Barlby Rd",
    "sg:city":"Ladbroke Grove",
    "sg:classifiers":[
        {
            "category":"Professional",
            "subcategory":"Printing & Photocopies",
            "type":"Services"
        }
    ],
    "sg:phone":"+44 800 328 1642",
    "sg:postcode":"W10 6AR",
    "sg:province":"Greater London",
    "sg:tags":[
        "printer"
    ],
    "wof:name":"Card Corporation",
    "wof:placetype":"venue"
},
  "geometry": {"coordinates":[-0.2236700058,51.5210189819],"type":"Point"}
}