{
  "type": "Feature",
  "properties": {
    "iso:country":"GB",
    "sg:address":"66 London Rd",
    "sg:city":"Nottingham",
    "sg:classifiers":[
        {
            "category":"Home & Garden",
            "subcategory":"Carpets & Floor Coverings",
            "type":"Retail Goods"
        }
    ],
    "sg:phone":"+44 115 986 7807",
    "sg:postcode":"NG2 3AW",
    "sg:province":"Nottinghamshire",
    "sg:tags":[
        "rubber",
        "plastic"
    ],
    "wof:name":"Nottingham Pattern & Mould Co",
    "wof:placetype":"venue"
},
  "geometry": {"coordinates":[-1.140194,52.945644],"type":"Point"}
}