{
  "type": "Feature",
  "properties": {
    "addr:full":"Holland Park House Bracknell Berkshire RG12 8TQ",
    "addr:postcode":"rg12 8tq",
    "iso:country":"GB",
    "sg:address":"Holland Park House",
    "sg:city":"Bracknell",
    "sg:classifiers":[
        {
            "category":"Shopping",
            "subcategory":"Computers & Home Electronics",
            "type":"Retail Goods"
        }
    ],
    "sg:phone":"+44 1344 446000",
    "sg:postcode":"RG12 8TQ",
    "sg:province":"Berkshire",
    "sg:tags":[
        "equipment",
        "audio-visual"
    ],
    "wof:name":"Leitch Europe Ltd.",
    "wof:placetype":"venue"
},
  "geometry": {"coordinates":[-0.7664800286,51.4126396179],"type":"Point"}
}