{
  "type": "Feature",
  "properties": {
    "addr:full":"Hill View Lake, Skegness Road Skegness Lincolnshire PE24 5NR",
    "addr:postcode":"pe24 5nr",
    "addr:street":"View Lake Skegness Road",
    "iso:country":"GB",
    "sg:address":"Hill View Lake, Skegness Road",
    "sg:city":"Skegness",
    "sg:classifiers":[
        {
            "category":"Recreation",
            "subcategory":"Campground",
            "type":"Entertainment"
        }
    ],
    "sg:phone":"+44 1754 872979",
    "sg:postcode":"PE24 5NR",
    "sg:province":"Lincolnshire",
    "sg:tags":[
        "caravan",
        "park"
    ],
    "wof:name":"Hillview Leisure Ltd.",
    "wof:placetype":"venue"
},
  "geometry": {"coordinates":[0.3054400086,53.2177696228],"type":"Point"}
}