{
  "type": "Feature",
  "properties": {
    "iso:country":"GB",
    "sg:address":"8 Arion Close",
    "sg:city":"Tamworth",
    "sg:classifiers":[
        {
            "category":"Bus Charters",
            "type":"Transportation"
        }
    ],
    "sg:phone":"+44 1827 311744",
    "sg:postcode":"B77 3NS",
    "sg:province":"Staffordshire",
    "sg:tags":[
        "mini",
        "hire",
        "leasing"
    ],
    "wof:name":"Acorn Coach & Mini Bus Hire",
    "wof:placetype":"venue"
},
  "geometry": {"coordinates":[-1.6784590483,52.6362533569],"type":"Point"}
}