{
  "type": "Feature",
  "properties": {
    "addr:full":"133 Dorset Road London Greater London SW19 3EQ",
    "addr:housenumber":"133",
    "addr:postcode":"sw19 3eq",
    "addr:street":"Dorset Road",
    "iso:country":"GB",
    "sg:address":"133 Dorset Road",
    "sg:city":"London",
    "sg:classifiers":[
        {
            "category":"Professional",
            "subcategory":"Art Services",
            "type":"Services"
        },
        {
            "category":"Real Estate",
            "subcategory":"Architect",
            "type":"Services"
        }
    ],
    "sg:postcode":"SW19 3EQ",
    "sg:province":"Greater London",
    "sg:tags":[
        "model",
        "technologist",
        "maker",
        "architectural"
    ],
    "wof:name":"Mallard Models & Effects",
    "wof:placetype":"venue"
},
  "geometry": {"coordinates":[-0.194081,51.408211],"type":"Point"}
}