{
  "type": "Feature",
  "properties": {
    "addr:full":"Blackburn Mains Farm Bathgate North Lanarkshire EH47 7AA",
    "addr:postcode":"eh47 7aa",
    "addr:street":"Bathgate",
    "iso:country":"GB",
    "sg:address":"Blackburn Mains Farm",
    "sg:city":"Bathgate",
    "sg:classifiers":[
        {
            "category":"Farming",
            "subcategory":"Farm",
            "type":"Manufacturing & Wholesale Goods"
        }
    ],
    "sg:phone":"+44 1501 762256",
    "sg:postcode":"EH47 7AA",
    "sg:province":"North Lanarkshire",
    "sg:tags":[
        "mixed",
        "crop"
    ],
    "wof:name":"J B Taylor & Sons",
    "wof:placetype":"venue"
},
  "geometry": {"coordinates":[-3.624277,55.875298],"type":"Point"}
}