{
  "type": "Feature",
  "properties": {
    "addr:full":"Fore Street Lostwithiel Cornwall PL22 0BL",
    "addr:postcode":"pl22 0bl",
    "addr:street":"Fore Street",
    "iso:country":"GB",
    "sg:address":"Fore Street",
    "sg:city":"Lostwithiel",
    "sg:classifiers":[
        {
            "category":"Organizations",
            "subcategory":"Community Association",
            "type":"Services"
        },
        {
            "category":"Organizations",
            "subcategory":"Membership Organization",
            "type":"Services"
        }
    ],
    "sg:phone":"+44 1208 872335",
    "sg:postcode":"PL22 0BL",
    "sg:province":"Cornwall",
    "sg:tags":[
        "club",
        "social"
    ],
    "wof:name":"Lostwithiel Social Club",
    "wof:placetype":"venue"
},
  "geometry": {"coordinates":[-4.6700491905,50.4072494507],"type":"Point"}
}