{
  "type": "Feature",
  "properties": {
    "iso:country":"GB",
    "sg:address":"86 Fortune Green Road",
    "sg:city":"London",
    "sg:classifiers":[
        {
            "category":"Real Estate",
            "subcategory":"Real Estate Agent",
            "type":"Services"
        }
    ],
    "sg:phone":"+44 20 7431 0400",
    "sg:postcode":"NW6 1DS",
    "sg:province":"Greater London",
    "wof:name":"Hayes & Wilson Estates",
    "wof:placetype":"venue"
},
  "geometry": {"coordinates":[-0.1965930015,51.5546073914],"type":"Point"}
}