{
  "type": "Feature",
  "properties": {
    "addr:full":"31 Manor Road New Milton Hampshire BH25 5EW",
    "addr:housenumber":"31",
    "addr:postcode":"bh25 5ew",
    "addr:street":"Manor Road",
    "iso:country":"GB",
    "sg:address":"31 Manor Road",
    "sg:city":"New Milton",
    "sg:classifiers":[
        {
            "category":"Building & Trades",
            "subcategory":"Construction",
            "type":"Services"
        }
    ],
    "sg:postcode":"BH25 5EW",
    "sg:province":"Hampshire",
    "sg:tags":[
        "decorator",
        "painter"
    ],
    "wof:name":"Blackthorn Decorators",
    "wof:placetype":"venue"
},
  "geometry": {"coordinates":[-1.65167,50.758041],"type":"Point"}
}