{
  "type": "Feature",
  "properties": {
    "iso:country":"GB",
    "sg:address":"2a Wonastow Road",
    "sg:city":"Monmouth",
    "sg:classifiers":[
        {
            "category":"Retail",
            "subcategory":"Veterinary Services",
            "type":"Services"
        }
    ],
    "sg:phone":"+44 1600 712206",
    "sg:postcode":"NP25 5AH",
    "sg:province":"Gloucestershire",
    "sg:tags":[
        "surgeon",
        "activity"
    ],
    "wof:name":"ALAN & HIGGINS REDFERN BARRY",
    "wof:placetype":"venue"
},
  "geometry": {"coordinates":[-2.7230639458,51.8093261719],"type":"Point"}
}