{
  "type": "Feature",
  "properties": {
    "iso:country":"GB",
    "sg:address":"University Of Paisley",
    "sg:city":"Paisley",
    "sg:classifiers":[
        {
            "category":"Professional",
            "subcategory":"Management & Consulting",
            "type":"Services"
        }
    ],
    "sg:phone":"+44 141 848 3146",
    "sg:postcode":"PA1 2BE",
    "sg:province":"Renfrewshire",
    "sg:tags":[
        "environmental",
        "consultant"
    ],
    "wof:name":"Centre for Environmental & Waste Management",
    "wof:placetype":"venue"
},
  "geometry": {"coordinates":[-4.45808,55.840508],"type":"Point"}
}