{
  "type": "Feature",
  "properties": {
    "iso:country":"GB",
    "sg:address":"10 Manor Gardens",
    "sg:city":"London",
    "sg:classifiers":[
        {
            "category":"Health Services",
            "subcategory":"Health Practitioner",
            "type":"Services"
        },
        {
            "category":"Organizations",
            "subcategory":"Non-profit Organization",
            "type":"Services"
        }
    ],
    "sg:phone":"+44 20 7263 7860",
    "sg:postcode":"N7 6JS",
    "sg:province":"Greater London",
    "sg:tags":[
        "psychotherapist",
        "organisation",
        "voluntary",
        "charity"
    ],
    "wof:name":"THE WOMEN'S THERAPY CENTRE",
    "wof:placetype":"venue"
},
  "geometry": {"coordinates":[-0.116699,51.55764],"type":"Point"}
}