{
  "type": "Feature",
  "properties": {
    "addr:full":"St.stephens St, Aston Birmingham West Midlands B6 4AB",
    "addr:postcode":"b6 4ab",
    "addr:street":"St",
    "iso:country":"GB",
    "sg:address":"St.stephens St, Aston",
    "sg:city":"Birmingham",
    "sg:classifiers":[
        {
            "category":"Freight",
            "type":"Transportation"
        }
    ],
    "sg:phone":"+44 121 380 4211",
    "sg:postcode":"B6 4AB",
    "sg:province":"West Midlands",
    "sg:tags":[
        "haulage",
        "road"
    ],
    "wof:name":"Royal Mail",
    "wof:placetype":"venue"
},
  "geometry": {"coordinates":[-1.893224,52.494911],"type":"Point"}
}