{
  "type": "Feature",
  "properties": {
    "addr:full":"376 London Road Benfleet Essex SS7 1AX",
    "addr:housenumber":"376",
    "addr:postcode":"ss7 1ax",
    "addr:street":"London Road",
    "iso:country":"GB",
    "sg:address":"376 London Road",
    "sg:city":"Benfleet",
    "sg:classifiers":[
        {
            "category":"Building & Trades",
            "subcategory":"Construction",
            "type":"Services"
        }
    ],
    "sg:postcode":"SS7 1AX",
    "sg:province":"Essex",
    "sg:tags":[
        "decorator",
        "painter"
    ],
    "wof:name":"Trident Maintenance Ltd.",
    "wof:placetype":"venue"
},
  "geometry": {"coordinates":[0.566923,51.564693],"type":"Point"}
}