{
  "type": "Feature",
  "properties": {
    "addr:full":"17-19 Walker Way, Thornbury Bristol Gloucestershire BS35 3US",
    "addr:housenumber":"17-19",
    "addr:postcode":"bs35 3us",
    "addr:street":"Walker Way",
    "iso:country":"GB",
    "sg:address":"17-19 Walker Way, Thornbury",
    "sg:city":"Bristol",
    "sg:classifiers":[
        {
            "category":"Building & Trades",
            "subcategory":"Construction",
            "type":"Services"
        }
    ],
    "sg:phone":"+44 1454 414600",
    "sg:postcode":"BS35 3US",
    "sg:province":"Gloucestershire",
    "sg:tags":[
        "furnace"
    ],
    "wof:name":"Severn Furnaces Ltd.",
    "wof:placetype":"venue"
},
  "geometry": {"coordinates":[-2.524364,51.60247],"type":"Point"}
}