{
  "type": "Feature",
  "properties": {
    "iso:country":"GB",
    "sg:address":"16 High St",
    "sg:city":"Hemel Hempstead",
    "sg:classifiers":[
        {
            "category":"Health Services",
            "subcategory":"Doctor",
            "type":"Services"
        }
    ],
    "sg:phone":"+44 1442 833295",
    "sg:postcode":"HP3 0HG",
    "sg:province":"Hertfordshire",
    "sg:tags":[
        "practitioners"
    ],
    "wof:name":"Cohen, S J",
    "wof:placetype":"venue"
},
  "geometry": {"coordinates":[-0.5343490243,51.7240791321],"type":"Point"}
}