{
  "type": "Feature",
  "properties": {
    "iso:country":"GB",
    "sg:address":"Gloucester Road",
    "sg:city":"Ross-on-wye",
    "sg:classifiers":[
        {
            "category":"Shopping",
            "subcategory":"Antiques",
            "type":"Retail Goods"
        }
    ],
    "sg:phone":"+44 1989 762290",
    "sg:postcode":"HR9 5BU",
    "sg:province":"Gloucestershire",
    "wof:name":"Ross-on-Wye Antique Centre",
    "wof:placetype":"venue"
},
  "geometry": {"coordinates":[-2.5807890892,51.9137649536],"type":"Point"}
}