{
  "type": "Feature",
  "properties": {
    "iso:country":"GB",
    "sg:address":"Unit 3 Hardengreen Industrial Estate, Dalhousie Road, Eskbank",
    "sg:city":"Dalkeith",
    "sg:classifiers":[
        {
            "category":"Building & Trades",
            "subcategory":"Construction",
            "type":"Services"
        }
    ],
    "sg:phone":"+44 131 663 1717",
    "sg:postcode":"EH22 3NY",
    "sg:province":"City of Edinburgh",
    "sg:tags":[
        "flooring"
    ],
    "wof:name":"Caldwell & Hill Flooring Ltd.",
    "wof:placetype":"venue"
},
  "geometry": {"coordinates":[-3.0824279785,55.8762321472],"type":"Point"}
}