{
  "type": "Feature",
  "properties": {
    "addr:full":"Goulding Av Preston Lancashire PR5 2HE",
    "addr:postcode":"pr5 2he",
    "addr:street":"Goulding Av",
    "iso:country":"GB",
    "sg:address":"Goulding Av",
    "sg:city":"Preston",
    "sg:classifiers":[
        {
            "category":"Place Of Worship",
            "type":"Public Place"
        }
    ],
    "sg:phone":"+44 1772 452103",
    "sg:postcode":"PR5 2HE",
    "sg:province":"Lancashire",
    "wof:name":"Turpin Green Leyland Methodist Church",
    "wof:placetype":"venue"
},
  "geometry": {"coordinates":[-2.63084,53.745762],"type":"Point"}
}