{
  "type": "Feature",
  "properties": {
    "addr:full":"The Office, Quinta Clo Torquay Devon TQ1 3RP",
    "addr:postcode":"tq1 3rp",
    "addr:street":"Quinta",
    "iso:country":"GB",
    "sg:address":"The Office, Quinta Clo",
    "sg:city":"Torquay",
    "sg:classifiers":[
        {
            "category":"Building & Trades",
            "subcategory":"Construction",
            "type":"Services"
        }
    ],
    "sg:phone":"+44 1803 315053",
    "sg:postcode":"TQ1 3RP",
    "sg:province":"Devon",
    "sg:tags":[
        "builder"
    ],
    "wof:name":"P J C Construction Ltd",
    "wof:placetype":"venue"
},
  "geometry": {"coordinates":[-3.51678,50.47509],"type":"Point"}
}