{
  "type": "Feature",
  "properties": {
    "iso:country":"GB",
    "sg:address":"42 Kings Road",
    "sg:city":"Immingham",
    "sg:classifiers":[
        {
            "category":"Shopping",
            "subcategory":"Department Store",
            "type":"Retail Goods"
        },
        {
            "category":"Shopping",
            "subcategory":"Bicycles & Sporting Goods",
            "type":"Retail Goods"
        }
    ],
    "sg:postcode":"DN40 1AN",
    "sg:province":"Lincolnshire",
    "sg:tags":[
        "shop",
        "cycle"
    ],
    "wof:name":"DI BURLEY",
    "wof:placetype":"venue"
},
  "geometry": {"coordinates":[-0.198392,53.61935],"type":"Point"}
}