{
  "type": "Feature",
  "properties": {
    "addr:full":"Star St Ryde Isle of Wight PO33 2JH",
    "addr:postcode":"po33 2jh",
    "addr:street":"Star St",
    "iso:country":"GB",
    "sg:address":"Star St",
    "sg:city":"Ryde",
    "sg:classifiers":[
        {
            "category":"Organizations",
            "subcategory":"Political Organization",
            "type":"Services"
        }
    ],
    "sg:phone":"+44 1983 562616",
    "sg:postcode":"PO33 2JH",
    "sg:province":"Isle of Wight",
    "sg:tags":[
        "promoter",
        "pool"
    ],
    "wof:name":"Commodore Bingo Club",
    "wof:placetype":"venue"
},
  "geometry": {"coordinates":[-1.1624079943,50.7276077271],"type":"Point"}
}