{
  "type": "Feature",
  "properties": {
    "iso:country":"GB",
    "sg:address":"53 Dundas Street",
    "sg:city":"Edinburgh",
    "sg:classifiers":[
        {
            "category":"Real Estate",
            "subcategory":"Real Estate Operator",
            "type":"Services"
        }
    ],
    "sg:phone":"+44 131 624 6666",
    "sg:postcode":"EH3 6RS",
    "sg:province":"City of Edinburgh",
    "sg:tags":[
        "letting",
        "agent"
    ],
    "sg:website":"http://www.braemore.co.uk",
    "wof:name":"Braemore Property Management",
    "wof:placetype":"venue"
},
  "geometry": {"coordinates":[-3.199486,55.958115],"type":"Point"}
}