{
  "type": "Feature",
  "properties": {
    "addr:full":"9 Waggon Road Leven Fife KY8 4PT",
    "addr:housenumber":"9",
    "addr:postcode":"ky8 4pt",
    "addr:street":"Waggon Road",
    "iso:country":"GB",
    "sg:address":"9 Waggon Road",
    "sg:city":"Leven",
    "sg:classifiers":[
        {
            "category":"Professional",
            "subcategory":"Employment Agencies",
            "type":"Services"
        }
    ],
    "sg:phone":"+44 1333 593100",
    "sg:postcode":"KY8 4PT",
    "sg:province":"Fife",
    "sg:tags":[
        "consultant"
    ],
    "wof:name":"Leven Jobcentre",
    "wof:placetype":"venue"
},
  "geometry": {"coordinates":[-2.9971930981,56.1979484558],"type":"Point"}
}