{
  "type": "Feature",
  "properties": {
    "iso:country":"GB",
    "sg:address":"Crag Lane",
    "sg:city":"Harrogate",
    "sg:classifiers":[
        {
            "category":"Bars & Pubs",
            "type":"Food & Drink"
        }
    ],
    "sg:phone":"+44 1423 502434",
    "sg:postcode":"HG3 1QA",
    "sg:province":"North Yorkshire",
    "sg:tags":[
        "pubs",
        "inn"
    ],
    "wof:name":"The Harrogate Arms",
    "wof:placetype":"venue"
},
  "geometry": {"coordinates":[-1.573113,53.983196],"type":"Point"}
}