{
  "type": "Feature",
  "properties": {
    "addr:full":"Lonsdale College, Lancaster University, Bailrigg Lancaster Lancashire LA1 4YN",
    "addr:postcode":"la1 4yn",
    "addr:street":"Bailrigg",
    "iso:country":"GB",
    "sg:address":"Lonsdale College, Lancaster University, Bailrigg",
    "sg:city":"Lancaster",
    "sg:classifiers":[
        {
            "category":"Farming",
            "subcategory":"Nursery",
            "type":"Manufacturing & Wholesale Goods"
        },
        {
            "category":"Education",
            "subcategory":"University",
            "type":"Public Place"
        }
    ],
    "sg:phone":"+44 1524 592624",
    "sg:postcode":"LA1 4YN",
    "sg:province":"Lancashire",
    "sg:tags":[
        "creche",
        "adult"
    ],
    "wof:name":"Open Studies Lancaster University",
    "wof:placetype":"venue"
},
  "geometry": {"coordinates":[-2.796544,54.01749],"type":"Point"}
}