{
  "type": "Feature",
  "properties": {
    "addr:full":"Birch Street Bury Lancashire BL9 5AL",
    "addr:postcode":"bl9 5al",
    "addr:street":"Birch Street",
    "iso:country":"GB",
    "sg:address":"Birch Street",
    "sg:city":"Bury",
    "sg:classifiers":[
        {
            "category":"Health Services",
            "subcategory":"Hospital",
            "type":"Services"
        },
        {
            "category":"Retail",
            "subcategory":"Auto Repair",
            "type":"Services"
        }
    ],
    "sg:phone":"+44 161 764 9052",
    "sg:postcode":"BL9 5AL",
    "sg:province":"Lancashire",
    "sg:tags":[
        "modification",
        "garage",
        "ambulance"
    ],
    "wof:name":"Qualisure",
    "wof:placetype":"venue"
},
  "geometry": {"coordinates":[-2.2907938957,53.5989265442],"type":"Point"}
}