{
  "type": "Feature",
  "properties": {
    "addr:full":"71 Park Road Wellingborough Northamptonshire NN8 4QG",
    "addr:housenumber":"71",
    "addr:postcode":"nn8 4qg",
    "addr:street":"Park Road",
    "iso:country":"GB",
    "sg:address":"71 Park Road",
    "sg:city":"Wellingborough",
    "sg:classifiers":[
        {
            "category":"Shopping",
            "subcategory":"Stationery & Office Supplies",
            "type":"Retail Goods"
        },
        {
            "category":"Professional",
            "subcategory":"Printing & Photocopies",
            "type":"Services"
        }
    ],
    "sg:phone":"+44 1933 229779",
    "sg:postcode":"NN8 4QG",
    "sg:province":"Northamptonshire",
    "sg:tags":[
        "machine",
        "facsimile",
        "duplicating",
        "copying"
    ],
    "wof:name":"Office Equipment Servicing",
    "wof:placetype":"venue"
},
  "geometry": {"coordinates":[-0.695463,52.306938],"type":"Point"}
}