{
  "type": "Feature",
  "properties": {
    "addr:full":"133 Clifton Street, Roath Cardiff Cardiff CF24 1LY",
    "addr:housenumber":"133",
    "addr:postcode":"cf24 1ly",
    "addr:street":"Clifton Street",
    "iso:country":"GB",
    "sg:address":"133 Clifton Street, Roath",
    "sg:city":"Cardiff",
    "sg:classifiers":[
        {
            "category":"Autos & Motor Vehicles",
            "subcategory":"Auto Supplies",
            "type":"Retail Goods"
        }
    ],
    "sg:postcode":"CF24 1LY",
    "sg:province":"Cardiff",
    "sg:tags":[
        "component"
    ],
    "wof:name":"Autoparts Cardiff",
    "wof:placetype":"venue"
},
  "geometry": {"coordinates":[-3.1584529877,51.4859275818],"type":"Point"}
}