{
  "type": "Feature",
  "properties": {
    "iso:country":"GB",
    "sg:address":"Pad Farm House, Coombes Road",
    "sg:city":"Lancing",
    "sg:classifiers":[
        {
            "category":"Banks & Credit Unions",
            "subcategory":"Financial Services",
            "type":"Services"
        }
    ],
    "sg:postcode":"BN15 0RJ",
    "sg:province":"West Sussex",
    "sg:tags":[
        "adviser"
    ],
    "wof:name":"H  Y  Financial Planning Ltd.",
    "wof:placetype":"venue"
},
  "geometry": {"coordinates":[-0.295449,50.84259],"type":"Point"}
}