{
  "type": "Feature",
  "properties": {
    "addr:full":"Palace Gardens Enfield Greater London EN2 6SN",
    "addr:postcode":"en2 6sn",
    "addr:street":"Palace Gardens",
    "iso:country":"GB",
    "sg:address":"Palace Gardens",
    "sg:city":"Enfield",
    "sg:classifiers":[
        {
            "category":"Shopping",
            "subcategory":"Gifts & Souvenirs",
            "type":"Retail Goods"
        }
    ],
    "sg:phone":"+44 20 8366 9619",
    "sg:postcode":"EN2 6SN",
    "sg:province":"Greater London",
    "sg:tags":[
        "poster",
        "card"
    ],
    "wof:name":"Birthdays",
    "wof:placetype":"venue"
},
  "geometry": {"coordinates":[-0.087649,51.653107],"type":"Point"}
}