{
  "type": "Feature",
  "properties": {
    "addr:full":"134 South Ealing Road, South Ealing London Greater London W5 4QJ",
    "addr:housenumber":"134",
    "addr:postcode":"w5 4qj",
    "addr:street":"South Ealing Road South",
    "iso:country":"GB",
    "sg:address":"134 South Ealing Road, South Ealing",
    "sg:city":"London",
    "sg:classifiers":[
        {
            "category":"Shopping",
            "subcategory":"Florist",
            "type":"Retail Goods"
        }
    ],
    "sg:phone":"+44 20 8567 5214",
    "sg:postcode":"W5 4QJ",
    "sg:province":"Greater London",
    "wof:name":"Floral Times Ltd.",
    "wof:placetype":"venue"
},
  "geometry": {"coordinates":[-0.3063719869,51.499420166],"type":"Point"}
}