{
  "type": "Feature",
  "properties": {
    "addr:full":"Cowley Mill Road Uxbridge Buckinghamshire UB8 2QE",
    "addr:postcode":"ub8 2qe",
    "addr:street":"Mill Road",
    "iso:country":"GB",
    "sg:address":"Cowley Mill Road",
    "sg:city":"Uxbridge",
    "sg:classifiers":[
        {
            "category":"Bars & Pubs",
            "type":"Food & Drink"
        }
    ],
    "sg:postcode":"UB8 2QE",
    "sg:province":"Buckinghamshire",
    "sg:tags":[
        "pubs",
        "inn"
    ],
    "wof:name":"The Sportsman's Inn",
    "wof:placetype":"venue"
},
  "geometry": {"coordinates":[-0.490699,51.539261],"type":"Point"}
}