{
  "type": "Feature",
  "properties": {
    "iso:country":"GB",
    "sg:address":"102 Camden High Street",
    "sg:city":"London",
    "sg:classifiers":[
        {
            "category":"Restaurant",
            "type":"Food & Drink"
        }
    ],
    "sg:phone":"+44 20 7485 2744",
    "sg:postcode":"NW1 0LU",
    "sg:province":"Greater London",
    "wof:name":"Posh People (U K) Ltd.",
    "wof:placetype":"venue"
},
  "geometry": {"coordinates":[-0.141098,51.537338],"type":"Point"}
}