{
  "type": "Feature",
  "properties": {
    "iso:country":"GB",
    "sg:address":"Gores Road, Kirkby, Knowsley Industrial Park",
    "sg:city":"Liverpool",
    "sg:classifiers":[
        {
            "category":"Building & Trades",
            "subcategory":"Construction",
            "type":"Services"
        }
    ],
    "sg:phone":"+44 151 548 6881",
    "sg:postcode":"L33 7XS",
    "sg:province":"Lancashire",
    "sg:tags":[
        "joinery"
    ],
    "wof:name":"Manorside Joinery Ltd.",
    "wof:placetype":"venue"
},
  "geometry": {"coordinates":[-2.8540821075,53.4752349854],"type":"Point"}
}