{
  "type": "Feature",
  "properties": {
    "iso:country":"GB",
    "sg:address":"83-85 Kirkstall Rd",
    "sg:city":"Leeds",
    "sg:classifiers":[
        {
            "category":"Autos & Motor Vehicles",
            "subcategory":"Automobile Sales",
            "type":"Retail Goods"
        }
    ],
    "sg:phone":"+44 113 243 6606",
    "sg:postcode":"LS3 1HS",
    "sg:province":"West Yorkshire",
    "sg:tags":[
        "car"
    ],
    "wof:name":"Benfield",
    "wof:placetype":"venue"
},
  "geometry": {"coordinates":[-1.568031,53.800735],"type":"Point"}
}