{
  "type": "Feature",
  "properties": {
    "addr:full":"28 Market Place Bishop Auckland Durham DL14 7NP",
    "addr:housenumber":"28",
    "addr:postcode":"dl14 7np",
    "addr:street":"Market Place",
    "iso:country":"GB",
    "sg:address":"28 Market Place",
    "sg:city":"Bishop Auckland",
    "sg:classifiers":[
        {
            "category":"Social Services",
            "subcategory":"Retirement Home",
            "type":"Services"
        }
    ],
    "sg:phone":"+44 1388 606763",
    "sg:postcode":"DL14 7NP",
    "sg:province":"Durham",
    "sg:tags":[
        "residential",
        "care"
    ],
    "wof:name":"Woodland Care Ltd.",
    "wof:placetype":"venue"
},
  "geometry": {"coordinates":[-1.6728630066,54.6661987305],"type":"Point"}
}