{
  "type": "Feature",
  "properties": {
    "addr:full":"The Basement Of Wilson, Queens Elm Parade London Greater London SW3 6EJ",
    "addr:postcode":"sw3 6ej",
    "addr:street":"Queens Elm Parade",
    "iso:country":"GB",
    "sg:address":"The Basement Of Wilson, Queens Elm Parade",
    "sg:city":"London",
    "sg:classifiers":[
        {
            "category":"Shopping",
            "subcategory":"Antiques",
            "type":"Retail Goods"
        }
    ],
    "sg:phone":"+44 20 7352 8441",
    "sg:postcode":"SW3 6EJ",
    "sg:province":"Greater London",
    "wof:name":"John Bellinger",
    "wof:placetype":"venue"
},
  "geometry": {"coordinates":[-0.1752900034,51.4892616272],"type":"Point"}
}