{
  "type": "Feature",
  "properties": {
    "iso:country":"GB",
    "sg:address":"14 Heath Close",
    "sg:city":"Huddersfield",
    "sg:classifiers":[
        {
            "category":"Wholesale",
            "subcategory":"Petroleum",
            "type":"Manufacturing & Wholesale Goods"
        }
    ],
    "sg:phone":"+44 1484 844481",
    "sg:postcode":"HD7 5SX",
    "sg:province":"West Yorkshire",
    "wof:name":"J Robertson Witco",
    "wof:placetype":"venue"
},
  "geometry": {"coordinates":[-1.8493679762,53.6176261902],"type":"Point"}
}