{
  "type": "Feature",
  "properties": {
    "addr:full":"7-9 Coventry Road Market Harborough Leicestershire LE16 9BX",
    "addr:housenumber":"7-9",
    "addr:postcode":"le16 9bx",
    "addr:street":"Coventry Road",
    "iso:country":"GB",
    "sg:address":"7-9 Coventry Road",
    "sg:city":"Market Harborough",
    "sg:classifiers":[
        {
            "category":"Shopping",
            "subcategory":"Pharmacy",
            "type":"Retail Goods"
        }
    ],
    "sg:phone":"+44 1858 462162",
    "sg:postcode":"LE16 9BX",
    "sg:province":"Leicestershire",
    "sg:tags":[
        "pharmacist",
        "dispensing",
        "chemist"
    ],
    "wof:name":"Gordon Davis Chemists Ltd",
    "wof:placetype":"venue"
},
  "geometry": {"coordinates":[-0.928704977,52.4765968323],"type":"Point"}
}