{
  "type": "Feature",
  "properties": {
    "iso:country":"GB",
    "sg:address":"17 Parkstone Dr",
    "sg:city":"Harrow",
    "sg:classifiers":[
        {
            "category":"Education",
            "subcategory":"Special Training",
            "type":"Public Place"
        }
    ],
    "sg:phone":"+44 20 8844 1221",
    "sg:postcode":"HA2 7BU",
    "sg:province":"Greater London",
    "sg:tags":[
        "product",
        "centre"
    ],
    "wof:name":"Airwings International",
    "wof:placetype":"venue"
},
  "geometry": {"coordinates":[-0.363004,51.581673],"type":"Point"}
}