{
  "type": "Feature",
  "properties": {
    "addr:full":"1 Mallory Av Liverpool Lancashire L31 4JS",
    "addr:housenumber":"1",
    "addr:postcode":"l31 4js",
    "addr:street":"Mallory Av Liverpool",
    "iso:country":"GB",
    "sg:address":"1 Mallory Av",
    "sg:city":"Liverpool",
    "sg:classifiers":[
        {
            "category":"Personal",
            "type":"Services"
        }
    ],
    "sg:phone":"+44 151 531 0098",
    "sg:postcode":"L31 4JS",
    "sg:province":"Lancashire",
    "sg:tags":[
        "wedding"
    ],
    "wof:name":"Butler Limousines",
    "wof:placetype":"venue"
},
  "geometry": {"coordinates":[-2.953985,53.528473],"type":"Point"}
}