{
  "type": "Feature",
  "properties": {
    "addr:full":"57 Bdwy West Leigh-on-sea Essex SS9 2BX",
    "addr:housenumber":"57",
    "addr:postcode":"ss9 2bx",
    "addr:street":"Bdwy West",
    "iso:country":"GB",
    "sg:address":"57 Bdwy West",
    "sg:city":"Leigh-on-sea",
    "sg:classifiers":[
        {
            "category":"Shopping",
            "subcategory":"Clothing, Apparel, & Fashions",
            "type":"Retail Goods"
        }
    ],
    "sg:postcode":"SS9 2BX",
    "sg:province":"Essex",
    "sg:tags":[
        "ladieswear"
    ],
    "wof:name":"Pandora",
    "wof:placetype":"venue"
},
  "geometry": {"coordinates":[0.650995,51.548481],"type":"Point"}
}