{
  "type": "Feature",
  "properties": {
    "iso:country":"GB",
    "sg:address":"Unit 4 St Davids Ct, 68 Cowbridge Road East",
    "sg:city":"Cardiff",
    "sg:classifiers":[
        {
            "category":"Real Estate",
            "subcategory":"Surveying",
            "type":"Services"
        }
    ],
    "sg:phone":"+44 29 2022 2377",
    "sg:postcode":"CF1 9YQ",
    "sg:province":"Cardiff",
    "sg:tags":[
        "surveyor",
        "land"
    ],
    "wof:name":"Ordnance Survey",
    "wof:placetype":"venue"
},
  "geometry": {"coordinates":[-3.180670023,51.4812583923],"type":"Point"}
}