{
  "type": "Feature",
  "properties": {
    "addr:full":"Harcourt Close, Dorney Reach Maidenhead Berkshire SL6 0DY",
    "addr:postcode":"sl6 0dy",
    "addr:street":"Harcourt Close Dorney Reach",
    "iso:country":"GB",
    "sg:address":"Harcourt Close, Dorney Reach",
    "sg:city":"Maidenhead",
    "sg:classifiers":[
        {
            "category":"Education",
            "subcategory":"School",
            "type":"Public Place"
        }
    ],
    "sg:phone":"+44 1628 620871",
    "sg:postcode":"SL6 0DY",
    "sg:province":"Berkshire",
    "sg:tags":[
        "local",
        "authority"
    ],
    "wof:name":"Dorney County Combined School",
    "wof:placetype":"venue"
},
  "geometry": {"coordinates":[-0.676279,51.507305],"type":"Point"}
}