{
  "type": "Feature",
  "properties": {
    "iso:country":"GB",
    "sg:address":"Lilac Cottage, Greendown",
    "sg:city":"Axminster",
    "sg:classifiers":[
        {
            "category":"Farming",
            "subcategory":"Farm",
            "type":"Manufacturing & Wholesale Goods"
        }
    ],
    "sg:phone":"+44 1404 881550",
    "sg:postcode":"EX13 7TD",
    "sg:province":"Devon",
    "sg:tags":[
        "mixed",
        "crop"
    ],
    "wof:name":"B.G Hurford",
    "wof:placetype":"venue"
},
  "geometry": {"coordinates":[-3.01964,50.814823],"type":"Point"}
}