{
  "type": "Feature",
  "properties": {
    "iso:country":"GB",
    "sg:address":"8 Higham Lane",
    "sg:city":"Tonbridge",
    "sg:classifiers":[
        {
            "category":"Professional",
            "subcategory":"Accounting & Tax Preparation",
            "type":"Services"
        }
    ],
    "sg:postcode":"TN10 4JA",
    "sg:province":"Kent",
    "sg:tags":[
        "accountant"
    ],
    "wof:name":"G Wratten & Co",
    "wof:placetype":"venue"
},
  "geometry": {"coordinates":[0.292645,51.207432],"type":"Point"}
}