{
  "type": "Feature",
  "properties": {
    "addr:full":"2 Listelow Close, Castle Bromwich Birmingham West Midlands B36 9EA",
    "addr:housenumber":"2",
    "addr:postcode":"b36 9ea",
    "addr:street":"Listelow Close",
    "iso:country":"GB",
    "sg:address":"2 Listelow Close, Castle Bromwich",
    "sg:city":"Birmingham",
    "sg:classifiers":[
        {
            "category":"Professional",
            "subcategory":"Management & Consulting",
            "type":"Services"
        }
    ],
    "sg:phone":"+44 121 705 7077",
    "sg:postcode":"B36 9EA",
    "sg:province":"West Midlands",
    "sg:tags":[
        "consultant",
        "business"
    ],
    "wof:name":"Bateman Consulting Ltd.",
    "wof:placetype":"venue"
},
  "geometry": {"coordinates":[-1.785778,52.507652],"type":"Point"}
}