{
  "type": "Feature",
  "properties": {
    "addr:full":"56 Brunswick Street Cardiff Cardiff CF5 1LJ",
    "addr:housenumber":"56",
    "addr:postcode":"cf5 1lj",
    "addr:street":"Brunswick Street",
    "iso:country":"GB",
    "sg:address":"56 Brunswick Street",
    "sg:city":"Cardiff",
    "sg:classifiers":[
        {
            "category":"Shopping",
            "subcategory":"Musical Instruments",
            "type":"Retail Goods"
        },
        {
            "category":"Retail",
            "subcategory":"Repair Shop",
            "type":"Services"
        }
    ],
    "sg:phone":"+44 29 2023 6763",
    "sg:postcode":"CF5 1LJ",
    "sg:province":"Cardiff",
    "sg:tags":[
        "restoration"
    ],
    "wof:name":"Richard Wood",
    "wof:placetype":"venue"
},
  "geometry": {"coordinates":[-3.206597,51.48127],"type":"Point"}
}