{
  "type": "Feature",
  "properties": {
    "addr:full":"Dane Street Rochdale Lancashire OL11 4EX",
    "addr:postcode":"ol11 4ex",
    "addr:street":"Dane Street",
    "iso:country":"GB",
    "sg:address":"Dane Street",
    "sg:city":"Rochdale",
    "sg:classifiers":[
        {
            "category":"Home & Garden",
            "subcategory":"Household Appliances",
            "type":"Retail Goods"
        }
    ],
    "sg:phone":"+44 1706 638400",
    "sg:postcode":"OL11 4EX",
    "sg:province":"Lancashire",
    "sg:tags":[
        "electrical",
        "domestic"
    ],
    "wof:name":"Currys",
    "wof:placetype":"venue"
},
  "geometry": {"coordinates":[-2.1633141041,53.6146354675],"type":"Point"}
}