{
  "type": "Feature",
  "properties": {
    "addr:full":"22 St Saviours Close, Bamber Bridge Preston Lancashire PR5 6AH",
    "addr:housenumber":"22",
    "addr:postcode":"pr5 6ah",
    "addr:street":"St Saviours Close",
    "iso:country":"GB",
    "sg:address":"22 St Saviours Close, Bamber Bridge",
    "sg:city":"Preston",
    "sg:classifiers":[
        {
            "category":"Building & Trades",
            "subcategory":"Plumbing",
            "type":"Services"
        }
    ],
    "sg:postcode":"PR5 6AH",
    "sg:province":"Lancashire",
    "sg:tags":[
        "heating"
    ],
    "wof:name":"C A Whittle",
    "wof:placetype":"venue"
},
  "geometry": {"coordinates":[-2.6574509144,53.7202033997],"type":"Point"}
}