{
  "type": "Feature",
  "properties": {
    "addr:full":"Fairfax Road Farnborough Hampshire GU14 8LT",
    "addr:postcode":"gu14 8lt",
    "addr:street":"Fairfax Road",
    "iso:country":"GB",
    "sg:address":"Fairfax Road",
    "sg:city":"Farnborough",
    "sg:classifiers":[
        {
            "category":"Social Services",
            "subcategory":"Adult Care",
            "type":"Services"
        }
    ],
    "sg:phone":"+44 1252 513120",
    "sg:postcode":"GU14 8LT",
    "sg:province":"Hampshire",
    "sg:tags":[
        "housing",
        "sheltered"
    ],
    "wof:name":"William Hitchcock House",
    "wof:placetype":"venue"
},
  "geometry": {"coordinates":[-0.754194,51.308014],"type":"Point"}
}