{
  "type": "Feature",
  "properties": {
    "addr:full":"Mount Farm, Choke La Maidenhead Berkshire SL6 6PL",
    "addr:postcode":"sl6 6pl",
    "addr:street":"Choke La Maidenhead",
    "iso:country":"GB",
    "sg:address":"Mount Farm, Choke La",
    "sg:city":"Maidenhead",
    "sg:classifiers":[
        {
            "category":"Farming",
            "subcategory":"Livestock Farm",
            "type":"Manufacturing & Wholesale Goods"
        }
    ],
    "sg:phone":"+44 1628 484696",
    "sg:postcode":"SL6 6PL",
    "sg:province":"Berkshire",
    "sg:tags":[
        "others"
    ],
    "wof:name":"Copas Bros",
    "wof:placetype":"venue"
},
  "geometry": {"coordinates":[-0.727257,51.522373],"type":"Point"}
}