{
  "type": "Feature",
  "properties": {
    "addr:full":"27-28 Terrett Ct, Bell Ct Shopping Centre Stratford-upon-avon Warwickshire CV37 6JP",
    "addr:housenumber":"27-28",
    "addr:postcode":"cv37 6jp",
    "addr:street":"Terrett Ct Bell Ct Shopping",
    "iso:country":"GB",
    "sg:address":"27-28 Terrett Ct, Bell Ct Shopping Centre",
    "sg:city":"Stratford-upon-avon",
    "sg:classifiers":[
        {
            "category":"Shopping",
            "subcategory":"Shoes",
            "type":"Retail Goods"
        }
    ],
    "sg:phone":"+44 1789 205297",
    "sg:postcode":"CV37 6JP",
    "sg:province":"Warwickshire",
    "sg:tags":[
        "shop"
    ],
    "wof:name":"John Richard Shoes",
    "wof:placetype":"venue"
},
  "geometry": {"coordinates":[-1.7072689533,52.1941337585],"type":"Point"}
}