{
  "type": "Feature",
  "properties": {
    "addr:full":"13-15 Blagrave Street Reading Berkshire RG1 1PJ",
    "addr:housenumber":"13-15",
    "addr:postcode":"rg1 1pj",
    "addr:street":"Blagrave Street",
    "iso:country":"GB",
    "sg:address":"13-15 Blagrave Street",
    "sg:city":"Reading",
    "sg:classifiers":[
        {
            "category":"Professional",
            "subcategory":"Employment Agencies",
            "type":"Services"
        }
    ],
    "sg:phone":"+44 118 957 1425",
    "sg:postcode":"RG1 1PJ",
    "sg:province":"Berkshire",
    "sg:tags":[
        "consultant"
    ],
    "wof:name":"Ajilon Finance Ltd.",
    "wof:placetype":"venue"
},
  "geometry": {"coordinates":[-0.970252,51.456951],"type":"Point"}
}