{
  "type": "Feature",
  "properties": {
    "addr:full":"14 - 16 Church Street Atherstone Leicestershire CV9 1HA",
    "addr:housenumber":"16",
    "addr:postcode":"cv9 1ha",
    "addr:street":"Church Street",
    "iso:country":"GB",
    "sg:address":"14 - 16 Church Street",
    "sg:city":"Atherstone",
    "sg:classifiers":[
        {
            "category":"Home & Garden",
            "subcategory":"Carpets & Floor Coverings",
            "type":"Retail Goods"
        }
    ],
    "sg:phone":"+44 1827 715335",
    "sg:postcode":"CV9 1HA",
    "sg:province":"Leicestershire",
    "sg:tags":[
        "carpets",
        "rug",
        "matting"
    ],
    "wof:name":"Atherstone Carpets",
    "wof:placetype":"venue"
},
  "geometry": {"coordinates":[-1.53023,52.569462],"type":"Point"}
}