{
  "type": "Feature",
  "properties": {
    "addr:full":"114 Whetstone La Walsall Staffordshire WS9 0EU",
    "addr:housenumber":"114",
    "addr:postcode":"ws9 0eu",
    "addr:street":"Whetstone La",
    "iso:country":"GB",
    "sg:address":"114 Whetstone La",
    "sg:city":"Walsall",
    "sg:classifiers":[
        {
            "category":"Manufacturing",
            "subcategory":"Building Materials",
            "type":"Manufacturing & Wholesale Goods"
        }
    ],
    "sg:phone":"+44 1922 457937",
    "sg:postcode":"WS9 0EU",
    "sg:province":"Staffordshire",
    "sg:tags":[
        "gate",
        "mnfrs"
    ],
    "wof:name":"Gate Masters",
    "wof:placetype":"venue"
},
  "geometry": {"coordinates":[-1.9172990322,52.5982284546],"type":"Point"}
}