{
  "type": "Feature",
  "properties": {
    "iso:country":"GB",
    "sg:address":"17 Miller Street",
    "sg:city":"Clydebank",
    "sg:classifiers":[
        {
            "category":"Community Center",
            "subcategory":"Youth",
            "type":"Public Place"
        },
        {
            "category":"Organizations",
            "subcategory":"Non-profit Organization",
            "type":"Services"
        }
    ],
    "sg:phone":"+44 141 562 0009",
    "sg:postcode":"G81 1UQ",
    "sg:province":"East Dunbartonshire",
    "sg:tags":[
        "charitable",
        "organisation",
        "charity",
        "centre"
    ],
    "wof:name":"CLYDEBANK SEA CADET CORPS",
    "wof:placetype":"venue"
},
  "geometry": {"coordinates":[-4.407551,55.902298],"type":"Point"}
}