{
  "type": "Feature",
  "properties": {
    "addr:full":"24 Breckland Way Lowestoft Suffolk NR32 4DS",
    "addr:housenumber":"24",
    "addr:postcode":"nr32 4ds",
    "addr:street":"Breckland Way",
    "iso:country":"GB",
    "sg:address":"24 Breckland Way",
    "sg:city":"Lowestoft",
    "sg:classifiers":[
        {
            "category":"Freight",
            "type":"Transportation"
        }
    ],
    "sg:postcode":"NR32 4DS",
    "sg:province":"Suffolk",
    "sg:tags":[
        "haulage",
        "road"
    ],
    "wof:name":"Chris Barnard (Haulage) Ltd.",
    "wof:placetype":"venue"
},
  "geometry": {"coordinates":[1.7289030552,52.489402771],"type":"Point"}
}