{
  "type": "Feature",
  "properties": {
    "iso:country":"GB",
    "sg:address":"Unit 6-7 Suttons Business Park",
    "sg:city":"Reading",
    "sg:classifiers":[
        {
            "category":"Building & Trades",
            "subcategory":"Construction",
            "type":"Services"
        }
    ],
    "sg:phone":"+44 118 975 9765",
    "sg:postcode":"RG6 1AZ",
    "sg:province":"Berkshire",
    "sg:tags":[
        "joinery"
    ],
    "wof:name":"Joinery Plus Ltd.",
    "wof:placetype":"venue"
},
  "geometry": {"coordinates":[-0.943549,51.458336],"type":"Point"}
}