{
  "type": "Feature",
  "properties": {
    "iso:country":"GB",
    "sg:address":"98 Bull Lane, Brindley Ford",
    "sg:city":"Stoke-on-trent",
    "sg:classifiers":[
        {
            "category":"Farming",
            "subcategory":"Livestock Farm",
            "type":"Manufacturing & Wholesale Goods"
        }
    ],
    "sg:phone":"+44 1782 517513",
    "sg:postcode":"ST8 7QN",
    "sg:province":"Staffordshire",
    "sg:tags":[
        "others"
    ],
    "wof:name":"C Smith",
    "wof:placetype":"venue"
},
  "geometry": {"coordinates":[-2.1902089119,53.0895805359],"type":"Point"}
}