{
  "type": "Feature",
  "properties": {
    "addr:full":"4 Sheep Street, Highworth Swindon Gloucestershire SN6 7AA",
    "addr:housenumber":"4",
    "addr:postcode":"sn6 7aa",
    "addr:street":"Sheep Street",
    "iso:country":"GB",
    "sg:address":"4 Sheep Street, Highworth",
    "sg:city":"Swindon",
    "sg:classifiers":[
        {
            "category":"Shopping",
            "subcategory":"Pharmacy",
            "type":"Retail Goods"
        }
    ],
    "sg:phone":"+44 1793 762220",
    "sg:postcode":"SN6 7AA",
    "sg:province":"Gloucestershire",
    "sg:tags":[
        "pharmacist",
        "chemist"
    ],
    "wof:name":"J W H Bran (Chemists) Ltd.",
    "wof:placetype":"venue"
},
  "geometry": {"coordinates":[-1.7092250586,51.6309661865],"type":"Point"}
}