{
  "type": "Feature",
  "properties": {
    "addr:full":"161 Antrobus Road, Handsworth Birmingham West Midlands B21 9NU",
    "addr:housenumber":"161",
    "addr:postcode":"b21 9nu",
    "addr:street":"Antrobus Road",
    "iso:country":"GB",
    "sg:address":"161 Antrobus Road, Handsworth",
    "sg:city":"Birmingham",
    "sg:classifiers":[
        {
            "category":"Organizations",
            "subcategory":"Community Association",
            "type":"Services"
        }
    ],
    "sg:phone":"+44 121 523 0362",
    "sg:postcode":"B21 9NU",
    "sg:province":"West Midlands",
    "sg:tags":[
        "co-operatives",
        "society",
        "housing",
        "trust"
    ],
    "wof:name":"Alpha Housing Co-Operative Ltd",
    "wof:placetype":"venue"
},
  "geometry": {"coordinates":[-1.9370030165,52.5099601746],"type":"Point"}
}