{
  "type": "Feature",
  "properties": {
    "addr:full":"Unit 9 Falkirk Falkirk FK2 7PD",
    "addr:housenumber":"unit 9",
    "addr:postcode":"fk2 7pd",
    "iso:country":"GB",
    "sg:address":"Unit 9",
    "sg:city":"Falkirk",
    "sg:classifiers":[
        {
            "category":"Government",
            "subcategory":"Department Of Motor Vehicles",
            "type":"Public Place"
        },
        {
            "category":"Sports & Exercise",
            "subcategory":"Tennis Court",
            "type":"Entertainment"
        }
    ],
    "sg:phone":"+44 1324 620100",
    "sg:postcode":"FK2 7PD",
    "sg:province":"Falkirk",
    "sg:tags":[
        "breakdown",
        "car",
        "recovery"
    ],
    "wof:name":"Elite Falkirk Ltd.",
    "wof:placetype":"venue"
},
  "geometry": {"coordinates":[-3.7920389175,56.017288208],"type":"Point"}
}