{
  "type": "Feature",
  "properties": {
    "addr:full":"360 Kings Rd Bradford West Yorkshire BD2 1NH",
    "addr:housenumber":"360",
    "addr:postcode":"bd2 1nh",
    "addr:street":"Kings Rd",
    "iso:country":"GB",
    "sg:address":"360 Kings Rd",
    "sg:city":"Bradford",
    "sg:classifiers":[
        {
            "category":"Personal",
            "type":"Services"
        }
    ],
    "sg:postcode":"BD2 1NH",
    "sg:province":"West Yorkshire",
    "sg:tags":[
        "delivery"
    ],
    "wof:name":"Towriss,John,",
    "wof:placetype":"venue"
},
  "geometry": {"coordinates":[-1.7437460423,53.8234481812],"type":"Point"}
}