{
  "type": "Feature",
  "properties": {
    "iso:country":"GB",
    "sg:address":"Arden House, Stratford Court, Cranmore Blvd",
    "sg:city":"Solihull",
    "sg:classifiers":[
        {
            "category":"Professional",
            "subcategory":"Advertising",
            "type":"Services"
        }
    ],
    "sg:phone":"+44 121 745 2772",
    "sg:postcode":"B90 4QT",
    "sg:province":"West Midlands",
    "sg:tags":[
        "agency"
    ],
    "wof:name":"Park Human Resources Ltd.",
    "wof:placetype":"venue"
},
  "geometry": {"coordinates":[-1.8066439629,52.4020347595],"type":"Point"}
}