{
  "type": "Feature",
  "properties": {
    "addr:full":"Heathcote House, 136 Hagley Road Birmingham West Midlands B16 9NX",
    "addr:housenumber":"136",
    "addr:postcode":"b16 9nx",
    "addr:street":"Hagley Road",
    "iso:country":"GB",
    "sg:address":"Heathcote House, 136 Hagley Road",
    "sg:city":"Birmingham",
    "sg:classifiers":[
        {
            "category":"Professional",
            "subcategory":"Credit Reporting & Collection",
            "type":"Services"
        }
    ],
    "sg:phone":"+44 121 454 0955",
    "sg:postcode":"B16 9NX",
    "sg:province":"West Midlands",
    "sg:tags":[
        "collecting",
        "agency",
        "reference"
    ],
    "sg:website":"http://www.cpa.co.uk",
    "wof:name":"The Credit Protection Association Plc",
    "wof:placetype":"venue"
},
  "geometry": {"coordinates":[-1.934038043,52.4717903137],"type":"Point"}
}