{
  "type": "Feature",
  "properties": {
    "iso:country":"GB",
    "sg:address":"15 The Row, Letham",
    "sg:city":"Cupar",
    "sg:classifiers":[
        {
            "category":"Professional",
            "subcategory":"Computer Services",
            "type":"Services"
        }
    ],
    "sg:postcode":"KY15 7RS",
    "sg:province":"Fife",
    "sg:tags":[
        "consultant"
    ],
    "wof:name":"Howard Dewey",
    "wof:placetype":"venue"
},
  "geometry": {"coordinates":[-3.1169359684,56.3154525757],"type":"Point"}
}