{
  "type": "Feature",
  "properties": {
    "addr:full":"Trinity Enterprise Centre, Furness Business Park, Iron Barrow In Furness Cumbria LA14 2PN",
    "addr:postcode":"la14 2pn",
    "iso:country":"GB",
    "sg:address":"Trinity Enterprise Centre, Furness Business Park, Iron",
    "sg:city":"Barrow In Furness",
    "sg:classifiers":[
        {
            "category":"Professional",
            "subcategory":"Lawyer & Legal Services",
            "type":"Services"
        }
    ],
    "sg:phone":"+44 1229 822132",
    "sg:postcode":"LA14 2PN",
    "sg:province":"Cumbria",
    "sg:tags":[
        "advice",
        "counselling"
    ],
    "wof:name":"Business Link Furness",
    "wof:placetype":"venue"
},
  "geometry": {"coordinates":[-3.241699934,54.1181793213],"type":"Point"}
}