{
  "type": "Feature",
  "properties": {
    "iso:country":"GB",
    "sg:address":"330 Old Street",
    "sg:city":"London",
    "sg:classifiers":[
        {
            "category":"Shopping",
            "subcategory":"Clothing, Apparel, & Fashions",
            "type":"Retail Goods"
        }
    ],
    "sg:postcode":"EC1V 9DR",
    "sg:province":"Greater London",
    "sg:tags":[
        "clothing"
    ],
    "wof:name":"Rise Clothing",
    "wof:placetype":"venue"
},
  "geometry": {"coordinates":[-0.085599,51.526161],"type":"Point"}
}