{
  "type": "Feature",
  "properties": {
    "addr:full":"Spark Hagg Farm, Selby Common Selby East Riding of Yorkshire YO8 3RN",
    "addr:postcode":"selby;yo8 3rn",
    "addr:street":"Common",
    "iso:country":"GB",
    "sg:address":"Spark Hagg Farm, Selby Common",
    "sg:city":"Selby",
    "sg:classifiers":[
        {
            "category":"Professional",
            "subcategory":"Employment Agencies",
            "type":"Services"
        },
        {
            "category":"Farming",
            "subcategory":"Farm",
            "type":"Manufacturing & Wholesale Goods"
        }
    ],
    "sg:phone":"+44 1757 703969",
    "sg:postcode":"YO8 3RN",
    "sg:province":"East Riding of Yorkshire",
    "sg:tags":[
        "mixed",
        "agricultural",
        "advice",
        "crop"
    ],
    "wof:name":"David M Rucklidge",
    "wof:placetype":"venue"
},
  "geometry": {"coordinates":[-1.070346,53.783909],"type":"Point"}
}