{
  "type": "Feature",
  "properties": {
    "addr:full":"12 Bradford Road Bournemouth Dorset BH9 3PJ",
    "addr:housenumber":"12",
    "addr:postcode":"bh9 3pj",
    "addr:street":"Bradford Road",
    "iso:country":"GB",
    "sg:address":"12 Bradford Road",
    "sg:city":"Bournemouth",
    "sg:classifiers":[
        {
            "category":"Professional",
            "subcategory":"Engineering",
            "type":"Services"
        },
        {
            "category":"Building & Trades",
            "subcategory":"Construction",
            "type":"Services"
        }
    ],
    "sg:phone":"+44 1202 521526",
    "sg:postcode":"BH9 3PJ",
    "sg:province":"Dorset",
    "sg:tags":[
        "installers",
        "gas",
        "engineer"
    ],
    "wof:name":"Derek Linsley",
    "wof:placetype":"venue"
},
  "geometry": {"coordinates":[-1.8548979759,50.7598762512],"type":"Point"}
}