{
  "type": "Feature",
  "properties": {
    "iso:country":"GB",
    "sg:address":"C/o A B B Mitchell & Company, Albert House",
    "sg:city":"Glasgow",
    "sg:classifiers":[
        {
            "category":"Personal",
            "subcategory":"Beauty Salon",
            "type":"Services"
        }
    ],
    "sg:phone":"+44 141 636 6669",
    "sg:postcode":"G41 5RS",
    "sg:province":"Glasgow City",
    "wof:name":"Face Facts Beauty Salon Ltd.",
    "wof:placetype":"venue"
},
  "geometry": {"coordinates":[-4.27848,55.84325],"type":"Point"}
}