{
  "type": "Feature",
  "properties": {
    "iso:country":"GB",
    "sg:address":"Drove Loan",
    "sg:city":"Denny",
    "sg:classifiers":[
        {
            "category":"Personal",
            "subcategory":"Adult",
            "type":"Services"
        }
    ],
    "sg:phone":"+44 1324 812839",
    "sg:postcode":"FK6 5LH",
    "sg:province":"Falkirk",
    "sg:tags":[
        "equestrian"
    ],
    "wof:name":"Home Farm Riding School",
    "wof:placetype":"venue"
},
  "geometry": {"coordinates":[-3.916404,56.014584],"type":"Point"}
}