{
  "type": "Feature",
  "properties": {
    "iso:country":"GB",
    "sg:address":"26 St Marys Street",
    "sg:city":"Newport",
    "sg:classifiers":[
        {
            "category":"Shopping",
            "subcategory":"Luggage & Leather Goods",
            "type":"Retail Goods"
        }
    ],
    "sg:phone":"+44 1952 812090",
    "sg:postcode":"TF10 7AB",
    "sg:province":"Shropshire",
    "sg:tags":[
        "shop",
        "leathergoods"
    ],
    "wof:name":"Newport Leather",
    "wof:placetype":"venue"
},
  "geometry": {"coordinates":[-2.380094,52.770031],"type":"Point"}
}