{
  "type": "Feature",
  "properties": {
    "iso:country":"GB",
    "sg:address":"18 St Peters Park Rd",
    "sg:city":"Broadstairs",
    "sg:classifiers":[
        {
            "category":"Personal",
            "subcategory":"Beauty Salon",
            "type":"Services"
        }
    ],
    "sg:postcode":"CT10 2BL",
    "sg:province":"Kent",
    "sg:tags":[
        "unisex",
        "hairdresser"
    ],
    "wof:name":"Alce,S,",
    "wof:placetype":"venue"
},
  "geometry": {"coordinates":[1.432261,51.360783],"type":"Point"}
}