{
  "type": "Feature",
  "properties": {
    "addr:full":"Church Row Pershore Worcestershire WR10 1BH",
    "addr:postcode":"wr10 1bh",
    "addr:street":"Row",
    "iso:country":"GB",
    "sg:address":"Church Row",
    "sg:city":"Pershore",
    "sg:classifiers":[
        {
            "category":"Travel",
            "subcategory":"Hotels & Motels",
            "type":"Entertainment"
        }
    ],
    "sg:phone":"+44 1386 552689",
    "sg:postcode":"WR10 1BH",
    "sg:province":"Worcestershire",
    "wof:name":"White Horse Hotel",
    "wof:placetype":"venue"
},
  "geometry": {"coordinates":[-2.0774860382,52.111076355],"type":"Point"}
}