{
  "type": "Feature",
  "properties": {
    "iso:country":"GB",
    "sg:address":"8 Market Place",
    "sg:city":"Belper",
    "sg:classifiers":[
        {
            "category":"Building & Trades",
            "subcategory":"Construction",
            "type":"Services"
        }
    ],
    "sg:phone":"+44 1773 822082",
    "sg:postcode":"DE56 1FZ",
    "sg:province":"Derbyshire",
    "sg:tags":[
        "flooring"
    ],
    "wof:name":"Belper Carpet & Flooring",
    "wof:placetype":"venue"
},
  "geometry": {"coordinates":[-1.479046,53.023487],"type":"Point"}
}