{
  "type": "Feature",
  "properties": {
    "addr:full":"14 Main Street, Spotborough Doncaster South Yorkshire DN5 7RF",
    "addr:housenumber":"14",
    "addr:postcode":"dn5 7rf",
    "addr:street":"Main Street",
    "iso:country":"GB",
    "sg:address":"14 Main Street, Spotborough",
    "sg:city":"Doncaster",
    "sg:classifiers":[
        {
            "category":"Real Estate",
            "subcategory":"Real Estate Agent",
            "type":"Services"
        }
    ],
    "sg:phone":"+44 1302 310310",
    "sg:postcode":"DN5 7RF",
    "sg:province":"South Yorkshire",
    "wof:name":"Robinson Hornsby",
    "wof:placetype":"venue"
},
  "geometry": {"coordinates":[-1.1885329485,53.512424469],"type":"Point"}
}