{
  "type": "Feature",
  "properties": {
    "iso:country":"GB",
    "sg:address":"6 Clematis Place, Blackbird Leys",
    "sg:city":"Oxford",
    "sg:classifiers":[
        {
            "category":"Retail",
            "subcategory":"Driving School",
            "type":"Services"
        }
    ],
    "sg:postcode":"OX4 6RJ",
    "sg:province":"Oxfordshire",
    "wof:name":"David Witherwick",
    "wof:placetype":"venue"
},
  "geometry": {"coordinates":[-1.1918059587,51.720905304],"type":"Point"}
}