{
  "type": "Feature",
  "properties": {
    "addr:full":"Clock Face Quarry, Barkisland Halifax West Yorkshire HX4 0DY",
    "addr:postcode":"hx4 0dy",
    "addr:street":"Clock Face Quarry Barkisland",
    "iso:country":"GB",
    "sg:address":"Clock Face Quarry, Barkisland",
    "sg:city":"Halifax",
    "sg:classifiers":[
        {
            "category":"Manufacturing",
            "subcategory":"Building Materials",
            "type":"Manufacturing & Wholesale Goods"
        }
    ],
    "sg:phone":"+44 1422 822520",
    "sg:postcode":"HX4 0DY",
    "sg:province":"West Yorkshire",
    "sg:tags":[
        "concrete",
        "product"
    ],
    "wof:name":"Marshalls Mono Ltd.",
    "wof:placetype":"venue"
},
  "geometry": {"coordinates":[-1.918054,53.675816],"type":"Point"}
}