{
  "type": "Feature",
  "properties": {
    "iso:country":"GB",
    "sg:address":"Southmead Health Centre, Ullswater Rd",
    "sg:city":"Bristol",
    "sg:classifiers":[
        {
            "category":"Health Services",
            "subcategory":"Doctor",
            "type":"Services"
        }
    ],
    "sg:phone":"+44 117 950 7150",
    "sg:postcode":"BS10 6DF",
    "sg:province":"City of Bristol",
    "sg:tags":[
        "practitioners"
    ],
    "wof:name":"David Kershaw",
    "wof:placetype":"venue"
},
  "geometry": {"coordinates":[-2.60165,51.504719],"type":"Point"}
}