{
  "type": "Feature",
  "properties": {
    "addr:full":"206 Toller Lane Bradford West Yorkshire BD9 5BU",
    "addr:housenumber":"206",
    "addr:postcode":"bd9 5bu",
    "addr:street":"Toller Lane",
    "iso:country":"GB",
    "sg:address":"206 Toller Lane",
    "sg:city":"Bradford",
    "sg:classifiers":[
        {
            "category":"Health Services",
            "subcategory":"Dentist",
            "type":"Services"
        }
    ],
    "sg:phone":"+44 1274 543150",
    "sg:postcode":"BD9 5BU",
    "sg:province":"West Yorkshire",
    "wof:name":"Parker",
    "wof:placetype":"venue"
},
  "geometry": {"coordinates":[-1.791882,53.810276],"type":"Point"}
}