{
  "type": "Feature",
  "properties": {
    "addr:full":"95 Princes St Edinburgh City of Edinburgh EH2 2ER",
    "addr:housenumber":"95",
    "addr:postcode":"eh2 2er",
    "addr:street":"Princes St",
    "iso:country":"GB",
    "sg:address":"95 Princes St",
    "sg:city":"Edinburgh",
    "sg:classifiers":[
        {
            "category":"Food & Beverages",
            "subcategory":"Liquor & Beverages",
            "type":"Retail Goods"
        }
    ],
    "sg:phone":"+44 131 220 5899",
    "sg:postcode":"EH2 2ER",
    "sg:province":"City of Edinburgh",
    "sg:tags":[
        "beer",
        "spirit",
        "wines"
    ],
    "wof:name":"The Whisky Shop",
    "wof:placetype":"venue"
},
  "geometry": {"coordinates":[-3.1993060112,55.9517326355],"type":"Point"}
}