{
  "type": "Feature",
  "properties": {
    "iso:country":"GB",
    "sg:address":"Barnsley House, Barnsley",
    "sg:city":"Cirencester",
    "sg:classifiers":[
        {
            "category":"Shopping",
            "subcategory":"Antiques",
            "type":"Retail Goods"
        }
    ],
    "sg:phone":"+44 1285 740402",
    "sg:postcode":"GL7 5EE",
    "sg:province":"Gloucestershire",
    "wof:name":"Denzil Verey Antiques",
    "wof:placetype":"venue"
},
  "geometry": {"coordinates":[-1.872638,51.719177],"type":"Point"}
}