{
  "type": "Feature",
  "properties": {
    "iso:country":"GB",
    "sg:address":"St John Chandler Hall, Church Rd",
    "sg:city":"Epsom",
    "sg:classifiers":[
        {
            "category":"Place Of Worship",
            "type":"Public Place"
        }
    ],
    "sg:phone":"+44 1372 721325",
    "sg:postcode":"KT17 4AB",
    "sg:province":"Surrey",
    "wof:name":"Elim Pentecostal Church",
    "wof:placetype":"venue"
},
  "geometry": {"coordinates":[-0.25941,51.337181],"type":"Point"}
}