{
  "type": "Feature",
  "properties": {
    "addr:full":"53 Chase Avenue, Charlton Kings Cheltenham Gloucestershire GL52 6YU",
    "addr:housenumber":"53",
    "addr:postcode":"gl52 6yu",
    "addr:street":"Chase Avenue",
    "iso:country":"GB",
    "sg:address":"53 Chase Avenue, Charlton Kings",
    "sg:city":"Cheltenham",
    "sg:classifiers":[
        {
            "category":"Manufacturing",
            "subcategory":"Petroleum Products",
            "type":"Manufacturing & Wholesale Goods"
        }
    ],
    "sg:phone":"+44 1242 230487",
    "sg:postcode":"GL52 6YU",
    "sg:province":"Gloucestershire",
    "sg:tags":[
        "double",
        "glazing"
    ],
    "wof:name":"John Larner Windows",
    "wof:placetype":"venue"
},
  "geometry": {"coordinates":[-2.040733099,51.8846702576],"type":"Point"}
}