{
  "type": "Feature",
  "properties": {
    "iso:country":"GB",
    "sg:address":"94a High St",
    "sg:city":"Tenterden",
    "sg:classifiers":[
        {
            "category":"Shopping",
            "subcategory":"Florist",
            "type":"Retail Goods"
        }
    ],
    "sg:postcode":"TN30 6JB",
    "sg:province":"Kent",
    "wof:name":"Orchid Room Ltd (The)",
    "wof:placetype":"venue"
},
  "geometry": {"coordinates":[0.684587,51.067524],"type":"Point"}
}