{
  "type": "Feature",
  "properties": {
    "addr:full":"1a The Cotswold Court, The Grn Broadway Gloucestershire WR12 7AA",
    "addr:housenumber":"1a",
    "addr:postcode":"wr12 7aa",
    "addr:street":"The Cotswold Court The Grn Broadway",
    "iso:country":"GB",
    "sg:address":"1a The Cotswold Court, The Grn",
    "sg:city":"Broadway",
    "sg:classifiers":[
        {
            "category":"Health Services",
            "subcategory":"Chiropractor",
            "type":"Services"
        }
    ],
    "sg:postcode":"WR12 7AA",
    "sg:province":"Gloucestershire",
    "wof:name":"Yen Yang Co Chiropactor",
    "wof:placetype":"venue"
},
  "geometry": {"coordinates":[-1.855794,52.040409],"type":"Point"}
}