{
  "type": "Feature",
  "properties": {
    "iso:country":"GB",
    "sg:address":"489a Gloucester Road, Horfield",
    "sg:city":"Bristol",
    "sg:classifiers":[
        {
            "category":"Professional",
            "subcategory":"Accounting & Tax Preparation",
            "type":"Services"
        }
    ],
    "sg:phone":"+44 117 951 4124",
    "sg:postcode":"BS7 8UG",
    "sg:province":"City of Bristol",
    "sg:tags":[
        "accountant"
    ],
    "wof:name":"Accounts & Tax Services",
    "wof:placetype":"venue"
},
  "geometry": {"coordinates":[-2.585132,51.487106],"type":"Point"}
}