{
  "type": "Feature",
  "properties": {
    "addr:full":"3 Institute Rd Bradford West Yorkshire BD2 2HY",
    "addr:housenumber":"3",
    "addr:postcode":"bd2 2hy",
    "addr:street":"Institute Rd",
    "iso:country":"GB",
    "sg:address":"3 Institute Rd",
    "sg:city":"Bradford",
    "sg:classifiers":[
        {
            "category":"Shopping",
            "subcategory":"Florist",
            "type":"Retail Goods"
        }
    ],
    "sg:phone":"+44 1274 772149",
    "sg:postcode":"BD2 2HY",
    "sg:province":"West Yorkshire",
    "wof:name":"The Grapevine",
    "wof:placetype":"venue"
},
  "geometry": {"coordinates":[-1.727063,53.820656],"type":"Point"}
}