{
  "type": "Feature",
  "properties": {
    "iso:country":"GB",
    "sg:address":"Atlas Ho, Old Hall St",
    "sg:city":"Macclesfield",
    "sg:classifiers":[
        {
            "category":"Travel",
            "subcategory":"Hotels & Motels",
            "type":"Entertainment"
        }
    ],
    "sg:phone":"+44 1625 869600",
    "sg:postcode":"SK10 2DT",
    "sg:province":"Cheshire",
    "sg:tags":[
        "self",
        "catering"
    ],
    "wof:name":"Prestige Properties Abroad",
    "wof:placetype":"venue"
},
  "geometry": {"coordinates":[-2.12619,53.265251],"type":"Point"}
}