{
  "type": "Feature",
  "properties": {
    "addr:full":"56 Eden St Carlisle Cumbria CA3 9LH",
    "addr:housenumber":"56",
    "addr:postcode":"ca3 9lh",
    "addr:street":"Eden St",
    "iso:country":"GB",
    "sg:address":"56 Eden St",
    "sg:city":"Carlisle",
    "sg:classifiers":[
        {
            "category":"Building & Trades",
            "subcategory":"Construction",
            "type":"Services"
        }
    ],
    "sg:phone":"+44 1228 522147",
    "sg:postcode":"CA3 9LH",
    "sg:province":"Cumbria",
    "sg:tags":[
        "builder"
    ],
    "wof:name":"P.G Nanson",
    "wof:placetype":"venue"
},
  "geometry": {"coordinates":[-2.9437870979,54.9083213806],"type":"Point"}
}