{
  "type": "Feature",
  "properties": {
    "iso:country":"GB",
    "sg:address":"72-76 Pevensey Road",
    "sg:city":"Eastbourne",
    "sg:classifiers":[
        {
            "category":"Travel",
            "subcategory":"Hotels & Motels",
            "type":"Entertainment"
        }
    ],
    "sg:phone":"+44 1323 417184",
    "sg:postcode":"BN21 3HT",
    "sg:province":"East Sussex",
    "wof:name":"The Paron Private Hotel",
    "wof:placetype":"venue"
},
  "geometry": {"coordinates":[0.291914,50.770245],"type":"Point"}
}