{
  "type": "Feature",
  "properties": {
    "addr:full":"2 Parchmore Rd Thornton Heath Surrey CR7 8LU",
    "addr:housenumber":"2",
    "addr:postcode":"cr7 8lu",
    "addr:street":"Parchmore Rd",
    "iso:country":"GB",
    "sg:address":"2 Parchmore Rd",
    "sg:city":"Thornton Heath",
    "sg:classifiers":[
        {
            "category":"Bars & Pubs",
            "type":"Food & Drink"
        }
    ],
    "sg:phone":"+44 20 8653 1586",
    "sg:postcode":"CR7 8LU",
    "sg:province":"Surrey",
    "sg:tags":[
        "pubs",
        "inn"
    ],
    "wof:name":"Prince Of Wales The",
    "wof:placetype":"venue"
},
  "geometry": {"coordinates":[-0.0983069986,51.3991470337],"type":"Point"}
}