{
  "type": "Feature",
  "properties": {
    "iso:country":"GB",
    "sg:address":"86-87 North Street",
    "sg:city":"Chichester",
    "sg:classifiers":[
        {
            "category":"Shopping",
            "subcategory":"Clothing, Apparel, & Fashions",
            "type":"Retail Goods"
        }
    ],
    "sg:phone":"+44 1243 782960",
    "sg:postcode":"PO19 1LQ",
    "sg:province":"West Sussex",
    "sg:tags":[
        "shop"
    ],
    "wof:name":"Kaliko",
    "wof:placetype":"venue"
},
  "geometry": {"coordinates":[-0.7787039876,50.8366737366],"type":"Point"}
}