{
  "type": "Feature",
  "properties": {
    "addr:full":"The Old Corn Mill, Congleton Rd, Siddington Macclesfield Cheshire SK11 9JR",
    "addr:postcode":"sk11 9jr",
    "addr:street":"Corn Mill Congleton Rd",
    "iso:country":"GB",
    "sg:address":"The Old Corn Mill, Congleton Rd, Siddington",
    "sg:city":"Macclesfield",
    "sg:classifiers":[
        {
            "category":"Professional",
            "type":"Services"
        }
    ],
    "sg:phone":"+44 1260 292500",
    "sg:postcode":"SK11 9JR",
    "sg:province":"Cheshire",
    "sg:tags":[
        "shopfitters"
    ],
    "wof:name":"The Sloane Group",
    "wof:placetype":"venue"
},
  "geometry": {"coordinates":[-2.233537,53.236439],"type":"Point"}
}