{
  "type": "Feature",
  "properties": {
    "addr:full":"Moorlands House, 48 Albion St Leeds West Yorkshire LS1 6AB",
    "addr:housenumber":"48",
    "addr:postcode":"ls1 6ab",
    "addr:street":"Albion St",
    "iso:country":"GB",
    "sg:address":"Moorlands House, 48 Albion St",
    "sg:city":"Leeds",
    "sg:classifiers":[
        {
            "category":"Professional",
            "subcategory":"Lawyer & Legal Services",
            "type":"Services"
        }
    ],
    "sg:postcode":"LS1 6AB",
    "sg:province":"West Yorkshire",
    "sg:tags":[
        "patent",
        "agent"
    ],
    "wof:name":"Wilkinson,Andrew,",
    "wof:placetype":"venue"
},
  "geometry": {"coordinates":[-1.5451459885,53.7982444763],"type":"Point"}
}