{
  "type": "Feature",
  "properties": {
    "iso:country":"GB",
    "sg:address":"Altringham Road, Styal",
    "sg:city":"Wilmslow",
    "sg:classifiers":[
        {
            "category":"Government",
            "subcategory":"Post Office",
            "type":"Public Place"
        }
    ],
    "sg:postcode":"SK9 4JE",
    "sg:province":"Cheshire",
    "wof:name":"Styal Post Office",
    "wof:placetype":"venue"
},
  "geometry": {"coordinates":[-2.244332,53.352428],"type":"Point"}
}