{
  "type": "Feature",
  "properties": {
    "iso:country":"GB",
    "sg:address":"22 Beachfield Ave",
    "sg:city":"Newquay",
    "sg:classifiers":[
        {
            "category":"Restaurant",
            "type":"Food & Drink"
        }
    ],
    "sg:postcode":"TR7 1DR",
    "sg:province":"Cornwall",
    "sg:tags":[
        "italian"
    ],
    "wof:name":"Hill,Jane,",
    "wof:placetype":"venue"
},
  "geometry": {"coordinates":[-5.085596,50.414055],"type":"Point"}
}