{
  "type": "Feature",
  "properties": {
    "addr:full":"Hamptworth Road, Redlynch Salisbury Dorset SP5 2PB",
    "addr:postcode":"sp5 2pb",
    "addr:street":"Hamptworth Road",
    "iso:country":"GB",
    "sg:address":"Hamptworth Road, Redlynch",
    "sg:city":"Salisbury",
    "sg:classifiers":[
        {
            "category":"Restaurant",
            "type":"Food & Drink"
        },
        {
            "category":"Building & Trades",
            "subcategory":"Construction",
            "type":"Services"
        }
    ],
    "sg:phone":"+44 1794 390348",
    "sg:postcode":"SP5 2PB",
    "sg:province":"Dorset",
    "sg:tags":[
        "builder"
    ],
    "wof:name":"Langley Wood",
    "wof:placetype":"venue"
},
  "geometry": {"coordinates":[-1.654979,50.973614],"type":"Point"}
}