{
  "type": "Feature",
  "properties": {
    "addr:full":"70 Wilcox Rd, Foxhill Sheffield South Yorkshire S6 1BR",
    "addr:housenumber":"70",
    "addr:postcode":"s6 1br",
    "addr:street":"Wilcox Rd",
    "iso:country":"GB",
    "sg:address":"70 Wilcox Rd, Foxhill",
    "sg:city":"Sheffield",
    "sg:classifiers":[
        {
            "category":"Building & Trades",
            "subcategory":"Construction",
            "type":"Services"
        }
    ],
    "sg:postcode":"S6 1BR",
    "sg:province":"South Yorkshire",
    "sg:tags":[
        "bricklaying"
    ],
    "wof:name":"Hodgson,Ian,",
    "wof:placetype":"venue"
},
  "geometry": {"coordinates":[-1.4987549782,53.4283790588],"type":"Point"}
}