{
  "type": "Feature",
  "properties": {
    "addr:full":"Portpatrick Stranraer Dumfries and Galloway DG9 9AD",
    "addr:postcode":"dg9 9ad",
    "iso:country":"GB",
    "sg:address":"Portpatrick",
    "sg:city":"Stranraer",
    "sg:classifiers":[
        {
            "category":"Travel",
            "subcategory":"Hotels & Motels",
            "type":"Entertainment"
        }
    ],
    "sg:phone":"+44 1776 810471",
    "sg:postcode":"DG9 9AD",
    "sg:province":"Dumfries and Galloway",
    "wof:name":"Knockinaam Lodge Hotel",
    "wof:placetype":"venue"
},
  "geometry": {"coordinates":[-5.07489,54.828201],"type":"Point"}
}