{
  "type": "Feature",
  "properties": {
    "iso:country":"GB",
    "sg:address":"Jollys",
    "sg:city":"Ross-on-wye",
    "sg:classifiers":[
        {
            "category":"Shopping",
            "subcategory":"Department Store",
            "type":"Retail Goods"
        },
        {
            "category":"Food & Beverages",
            "subcategory":"Groceries & Convenience Stores",
            "type":"Retail Goods"
        }
    ],
    "sg:phone":"+44 1600 890352",
    "sg:postcode":"HR9 6HX",
    "sg:province":"Gloucestershire",
    "sg:website":"http://www.jollysofgoodrich.co.uk",
    "wof:name":"Jolly'S Of Goodrich",
    "wof:placetype":"venue"
},
  "geometry": {"coordinates":[-2.581733,51.916481],"type":"Point"}
}