{
  "type": "Feature",
  "properties": {
    "addr:full":"48 North Street, Burwell Cambridge Cambridgeshire CB5 0BA",
    "addr:housenumber":"48",
    "addr:postcode":"cb5 0ba",
    "addr:street":"North Street",
    "iso:country":"GB",
    "sg:address":"48 North Street, Burwell",
    "sg:city":"Cambridge",
    "sg:classifiers":[
        {
            "category":"Military Area",
            "subcategory":"Air Force Base",
            "type":"Public Place"
        }
    ],
    "sg:phone":"+44 1638 741168",
    "sg:postcode":"CB5 0BA",
    "sg:province":"Cambridgeshire",
    "sg:tags":[
        "taxi",
        "hire",
        "private"
    ],
    "wof:name":"Burwell Taxis",
    "wof:placetype":"venue"
},
  "geometry": {"coordinates":[0.325150013,52.28465271],"type":"Point"}
}