{
  "type": "Feature",
  "properties": {
    "iso:country":"GB",
    "sg:address":"Unit 5b, Valley Indstl Est, Hadlow Rd",
    "sg:city":"Tonbridge",
    "sg:classifiers":[
        {
            "category":"Home & Garden",
            "subcategory":"Household Appliances",
            "type":"Retail Goods"
        }
    ],
    "sg:phone":"+44 1732 851860",
    "sg:postcode":"TN11 0AH",
    "sg:province":"Kent",
    "sg:tags":[
        "refrigeration",
        "air conditioning"
    ],
    "wof:name":"Teklima Ltd",
    "wof:placetype":"venue"
},
  "geometry": {"coordinates":[0.31619,51.219769],"type":"Point"}
}