{
  "type": "Feature",
  "properties": {
    "addr:full":"2 Motion Street Lochgelly Fife KY5 9AZ",
    "addr:housenumber":"2",
    "addr:postcode":"ky5 9az",
    "addr:street":"Motion Street",
    "iso:country":"GB",
    "sg:address":"2 Motion Street",
    "sg:city":"Lochgelly",
    "sg:classifiers":[
        {
            "category":"Taxi",
            "type":"Transportation"
        },
        {
            "category":"Military Area",
            "subcategory":"Air Force Base",
            "type":"Public Place"
        }
    ],
    "sg:phone":"+44 1592 781146",
    "sg:postcode":"KY5 9AZ",
    "sg:province":"Fife",
    "sg:tags":[
        "hire",
        "private"
    ],
    "wof:name":"Archie's Taxis",
    "wof:placetype":"venue"
},
  "geometry": {"coordinates":[-3.3178040981,56.1229324341],"type":"Point"}
}