{
  "type": "Feature",
  "properties": {
    "iso:country":"GB",
    "sg:address":"4 Abingdon Road",
    "sg:city":"London",
    "sg:classifiers":[
        {
            "category":"Education",
            "subcategory":"Special Training",
            "type":"Public Place"
        }
    ],
    "sg:phone":"+44 20 7937 3233",
    "sg:postcode":"W8 6AF",
    "sg:province":"Greater London",
    "sg:tags":[
        "school",
        "product",
        "language",
        "centre"
    ],
    "wof:name":"The Canning School Ltd.",
    "wof:placetype":"venue"
},
  "geometry": {"coordinates":[-0.1973150074,51.4991416931],"type":"Point"}
}