{
  "type": "Feature",
  "properties": {
    "addr:full":"8 Manor Road Yeovil Somerset BA20 1UQ",
    "addr:housenumber":"8",
    "addr:postcode":"ba20 1uq",
    "addr:street":"Manor Road",
    "iso:country":"GB",
    "sg:address":"8 Manor Road",
    "sg:city":"Yeovil",
    "sg:classifiers":[
        {
            "category":"Real Estate",
            "subcategory":"Architect",
            "type":"Services"
        }
    ],
    "sg:postcode":"BA20 1UQ",
    "sg:province":"Somerset",
    "wof:name":"Survey Point",
    "wof:placetype":"venue"
},
  "geometry": {"coordinates":[-2.635959,50.939201],"type":"Point"}
}