{
  "type": "Feature",
  "properties": {
    "iso:country":"GB",
    "sg:address":"Hay Street",
    "sg:city":"Perth",
    "sg:classifiers":[
        {
            "category":"Arena",
            "subcategory":"Sports Club",
            "type":"Entertainment"
        }
    ],
    "sg:phone":"+44 1738 450750",
    "sg:postcode":"PH1 5HS",
    "sg:province":"Perth and Kinross",
    "wof:name":"Perth Lawn Tennis Club",
    "wof:placetype":"venue"
},
  "geometry": {"coordinates":[-3.4377140999,56.4042892456],"type":"Point"}
}