{
  "type": "Feature",
  "properties": {
    "addr:full":", Poundsgate Newton Abbot Devon TQ13 7PA",
    "addr:postcode":"tq13 7pa",
    "addr:street":"Poundsgate",
    "iso:country":"GB",
    "sg:address":", Poundsgate",
    "sg:city":"Newton Abbot",
    "sg:classifiers":[
        {
            "category":"Building & Trades",
            "subcategory":"Landscaping Services",
            "type":"Services"
        }
    ],
    "sg:phone":"+44 1364 631316",
    "sg:postcode":"TQ13 7PA",
    "sg:province":"Devon",
    "sg:tags":[
        "forestry",
        "tree"
    ],
    "wof:name":"Fountain Forestry Group",
    "wof:placetype":"venue"
},
  "geometry": {"coordinates":[-3.826,50.536999],"type":"Point"}
}