{
  "type": "Feature",
  "properties": {
    "addr:full":"York House, 10 Haywra Street Harrogate North Yorkshire HG1 5BJ",
    "addr:housenumber":"10",
    "addr:postcode":"hg1 5bj",
    "addr:street":"Haywra Street",
    "iso:country":"GB",
    "sg:address":"York House, 10 Haywra Street",
    "sg:city":"Harrogate",
    "sg:classifiers":[
        {
            "category":"Banks & Credit Unions",
            "subcategory":"Bank",
            "type":"Services"
        }
    ],
    "sg:phone":"+44 1423 564225",
    "sg:postcode":"HG1 5BJ",
    "sg:province":"North Yorkshire",
    "sg:tags":[
        "broker",
        "mortgage"
    ],
    "wof:name":"Accura",
    "wof:placetype":"venue"
},
  "geometry": {"coordinates":[-1.5362319946,53.9949569702],"type":"Point"}
}