{
  "type": "Feature",
  "properties": {
    "iso:country":"GB",
    "sg:address":"Little Brixham, Ashford Road, Bethersden",
    "sg:city":"Ashford",
    "sg:classifiers":[
        {
            "category":"Professional",
            "subcategory":"Art Services",
            "type":"Services"
        }
    ],
    "sg:postcode":"TN26 3AX",
    "sg:province":"Kent",
    "sg:tags":[
        "model",
        "maker"
    ],
    "wof:name":"R T F Models",
    "wof:placetype":"venue"
},
  "geometry": {"coordinates":[0.752973,51.126179],"type":"Point"}
}