{
  "type": "Feature",
  "properties": {
    "addr:full":"388-390 Romford Road London Greater London E7 8BS",
    "addr:housenumber":"388-390",
    "addr:postcode":"e7 8bs",
    "addr:street":"Romford Road",
    "iso:country":"GB",
    "sg:address":"388-390 Romford Road",
    "sg:city":"London",
    "sg:classifiers":[
        {
            "category":"Shopping",
            "subcategory":"Clothing, Apparel, & Fashions",
            "type":"Retail Goods"
        },
        {
            "category":"Shopping",
            "subcategory":"Crafts & Fabrics",
            "type":"Retail Goods"
        }
    ],
    "sg:phone":"+44 20 8472 2410",
    "sg:postcode":"E7 8BS",
    "sg:province":"Greater London",
    "sg:tags":[
        "shop"
    ],
    "wof:name":"Neelan Sarees",
    "wof:placetype":"venue"
},
  "geometry": {"coordinates":[0.032634,51.546982],"type":"Point"}
}