{
  "type": "Feature",
  "properties": {
    "iso:country":"GB",
    "sg:address":"63 Nutfield Road, Merstham",
    "sg:city":"Redhill",
    "sg:classifiers":[
        {
            "category":"Cinema",
            "subcategory":"Movie Rental",
            "type":"Entertainment"
        }
    ],
    "sg:phone":"+44 1737 644388",
    "sg:postcode":"RH1 3ER",
    "sg:province":"Surrey",
    "sg:tags":[
        "video",
        "library"
    ],
    "wof:name":"The Video Shop",
    "wof:placetype":"venue"
},
  "geometry": {"coordinates":[-0.150375,51.257603],"type":"Point"}
}