{
  "type": "Feature",
  "properties": {
    "iso:country":"GB",
    "sg:address":"100 Blakenhale Road, Sheldon",
    "sg:city":"Birmingham",
    "sg:classifiers":[
        {
            "category":"Home & Garden",
            "subcategory":"Building Materials",
            "type":"Retail Goods"
        },
        {
            "category":"Building & Trades",
            "subcategory":"Construction",
            "type":"Services"
        }
    ],
    "sg:phone":"+44 121 786 2482",
    "sg:postcode":"B33 0XA",
    "sg:province":"West Midlands",
    "sg:tags":[
        "insulation",
        "installers",
        "ceiling",
        "contractor"
    ],
    "wof:name":"STEVEN GORDON",
    "wof:placetype":"venue"
},
  "geometry": {"coordinates":[-1.7869490385,52.4733467102],"type":"Point"}
}