{
  "type": "Feature",
  "properties": {
    "addr:full":"115 Regent Road Great Yarmouth Norfolk NR30 2AB",
    "addr:housenumber":"115",
    "addr:postcode":"nr30 2ab",
    "addr:street":"Regent Road",
    "iso:country":"GB",
    "sg:address":"115 Regent Road",
    "sg:city":"Great Yarmouth",
    "sg:classifiers":[
        {
            "category":"Shopping",
            "subcategory":"Department Store",
            "type":"Retail Goods"
        }
    ],
    "sg:phone":"+44 1493 843418",
    "sg:postcode":"NR30 2AB",
    "sg:province":"Norfolk",
    "wof:name":"Bhs",
    "wof:placetype":"venue"
},
  "geometry": {"coordinates":[1.727884,52.606709],"type":"Point"}
}