{
  "type": "Feature",
  "properties": {
    "iso:country":"GB",
    "sg:address":"Freshwater East",
    "sg:city":"Pembroke",
    "sg:classifiers":[
        {
            "category":"Shopping",
            "subcategory":"Department Store",
            "type":"Retail Goods"
        }
    ],
    "sg:postcode":"SA71 5LN",
    "sg:province":"Pembrokeshire",
    "wof:name":"Lakeside Stores",
    "wof:placetype":"venue"
},
  "geometry": {"coordinates":[-4.86865,51.643749],"type":"Point"}
}