{
  "type": "Feature",
  "properties": {
    "addr:full":"7 Broad Street South Molton Devon EX36 3AB",
    "addr:housenumber":"7",
    "addr:postcode":"ex36 3ab",
    "addr:street":"Broad Street South",
    "iso:country":"GB",
    "sg:address":"7 Broad Street",
    "sg:city":"South Molton",
    "sg:classifiers":[
        {
            "category":"Shopping",
            "subcategory":"Clothing, Apparel, & Fashions",
            "type":"Retail Goods"
        }
    ],
    "sg:phone":"+44 1769 572231",
    "sg:postcode":"EX36 3AB",
    "sg:province":"Devon",
    "sg:tags":[
        "haberdasher"
    ],
    "wof:name":"Atkins Drapers",
    "wof:placetype":"venue"
},
  "geometry": {"coordinates":[-3.8344941139,51.0175094604],"type":"Point"}
}