{
  "type": "Feature",
  "properties": {
    "addr:full":"Lyric House, 149 Hammersmith Rd West Kensington Greater London W14 0QL",
    "addr:housenumber":"149",
    "addr:postcode":"w14 0ql",
    "addr:street":"Hammersmith Rd",
    "iso:country":"GB",
    "sg:address":"Lyric House, 149 Hammersmith Rd",
    "sg:city":"West Kensington",
    "sg:classifiers":[
        {
            "category":"Government",
            "subcategory":"Post Office",
            "type":"Public Place"
        }
    ],
    "sg:phone":"+44 20 7855 5800",
    "sg:postcode":"W14 0QL",
    "sg:province":"Greater London",
    "sg:tags":[
        "organisation",
        "soc",
        "research"
    ],
    "wof:name":"Ignite",
    "wof:placetype":"venue"
},
  "geometry": {"coordinates":[-0.2135590017,51.4942703247],"type":"Point"}
}