{
  "type": "Feature",
  "properties": {
    "iso:country":"GB",
    "sg:address":"Westgate House, 31 Ladywood Road",
    "sg:city":"Sutton Coldfield",
    "sg:classifiers":[
        {
            "category":"Professional",
            "subcategory":"Accounting & Tax Preparation",
            "type":"Services"
        }
    ],
    "sg:postcode":"B74 2QN",
    "sg:province":"Staffordshire",
    "sg:tags":[
        "consultant"
    ],
    "wof:name":"A G Rice",
    "wof:placetype":"venue"
},
  "geometry": {"coordinates":[-1.836455,52.576229],"type":"Point"}
}