{
  "type": "Feature",
  "properties": {
    "iso:country":"GB",
    "sg:address":"52 Raymouth Road",
    "sg:city":"London",
    "sg:classifiers":[
        {
            "category":"Building & Trades",
            "subcategory":"Construction",
            "type":"Services"
        }
    ],
    "sg:phone":"+44 20 7232 1433",
    "sg:postcode":"SE16 2DF",
    "sg:province":"Greater London",
    "sg:tags":[
        "contractor"
    ],
    "wof:name":"Ballast Plc",
    "wof:placetype":"venue"
},
  "geometry": {"coordinates":[-0.059177,51.492119],"type":"Point"}
}