{
  "type": "Feature",
  "properties": {
    "iso:country":"GB",
    "sg:address":"161 Main Street",
    "sg:city":"Callander",
    "sg:classifiers":[
        {
            "category":"Government",
            "subcategory":"Post Office",
            "type":"Public Place"
        }
    ],
    "sg:phone":"+44 1877 330227",
    "sg:postcode":"FK17 8BH",
    "sg:province":"Stirling",
    "wof:name":"T Mackenzie",
    "wof:placetype":"venue"
},
  "geometry": {"coordinates":[-4.20854,56.242348],"type":"Point"}
}