{
  "type": "Feature",
  "properties": {
    "addr:full":"37 High Street Bromyard Herefordshire HR7 4AE",
    "addr:housenumber":"37",
    "addr:postcode":"hr7 4ae",
    "addr:street":"High Street",
    "iso:country":"GB",
    "sg:address":"37 High Street",
    "sg:city":"Bromyard",
    "sg:classifiers":[
        {
            "category":"Real Estate",
            "subcategory":"Real Estate Agent",
            "type":"Services"
        }
    ],
    "sg:phone":"+44 1885 488166",
    "sg:postcode":"HR7 4AE",
    "sg:province":"Herefordshire",
    "wof:name":"Flint & Cook",
    "wof:placetype":"venue"
},
  "geometry": {"coordinates":[-2.5077979565,52.1893806458],"type":"Point"}
}