{
  "type": "Feature",
  "properties": {
    "addr:full":"15 Clyde Rd Sheffield Derbyshire S8 0YD",
    "addr:housenumber":"15",
    "addr:postcode":"s8 0yd",
    "addr:street":"Clyde Rd",
    "iso:country":"GB",
    "sg:address":"15 Clyde Rd",
    "sg:city":"Sheffield",
    "sg:classifiers":[
        {
            "category":"Building & Trades",
            "subcategory":"Construction",
            "type":"Services"
        }
    ],
    "sg:postcode":"S8 0YD",
    "sg:province":"Derbyshire",
    "sg:tags":[
        "flooring"
    ],
    "wof:name":"Bulwark (Flooring) Ltd",
    "wof:placetype":"venue"
},
  "geometry": {"coordinates":[-1.4757909775,53.3599662781],"type":"Point"}
}