{
  "type": "Feature",
  "properties": {
    "addr:full":"Unit 15 Notely Enterpriose Park, Raydon Road, Great Wenham Colchester Essex CO7 6QD",
    "addr:housenumber":"unit 15",
    "addr:postcode":"co7 6qd",
    "addr:street":"Raydon Road;Wenham Colchester",
    "iso:country":"GB",
    "sg:address":"Unit 15 Notely Enterpriose Park, Raydon Road, Great Wenham",
    "sg:city":"Colchester",
    "sg:classifiers":[
        {
            "category":"Professional",
            "subcategory":"Engineering",
            "type":"Services"
        }
    ],
    "sg:phone":"+44 1473 312266",
    "sg:postcode":"CO7 6QD",
    "sg:province":"Essex",
    "sg:tags":[
        "engineer"
    ],
    "wof:name":"20-20 Vision",
    "wof:placetype":"venue"
},
  "geometry": {"coordinates":[1.0147720575,52.0031242371],"type":"Point"}
}