{
  "type": "Feature",
  "properties": {
    "iso:country":"GB",
    "sg:address":"83 Hill Road",
    "sg:city":"Barrow-in-furness",
    "sg:classifiers":[
        {
            "category":"Home & Garden",
            "subcategory":"Carpets & Floor Coverings",
            "type":"Retail Goods"
        }
    ],
    "sg:phone":"+44 1229 832369",
    "sg:postcode":"LA14 4EX",
    "sg:province":"Cumbria",
    "sg:tags":[
        "carpets",
        "rug",
        "matting"
    ],
    "wof:name":"Mike Taylor Carpet Specialist",
    "wof:placetype":"venue"
},
  "geometry": {"coordinates":[-3.2154068947,54.1350135803],"type":"Point"}
}