{
  "type": "Feature",
  "properties": {
    "iso:country":"GB",
    "sg:address":"Witton House, Lower Road",
    "sg:city":"Rickmansworth",
    "sg:classifiers":[
        {
            "category":"Home & Garden",
            "subcategory":"Hardware",
            "type":"Retail Goods"
        }
    ],
    "sg:phone":"+44 1923 284232",
    "sg:postcode":"WD3 5LD",
    "sg:province":"Hertfordshire",
    "sg:tags":[
        "retailer",
        "diy"
    ],
    "wof:name":"Poores of Chorleywood",
    "wof:placetype":"venue"
},
  "geometry": {"coordinates":[-0.520579,51.654655],"type":"Point"}
}