{
  "type": "Feature",
  "properties": {
    "iso:country":"GB",
    "sg:address":"Prospect Road",
    "sg:city":"Hythe",
    "sg:classifiers":[
        {
            "category":"Restaurant",
            "type":"Food & Drink"
        }
    ],
    "sg:postcode":"CT21 5NH",
    "sg:province":"Kent",
    "wof:name":"Somerfield Coffee Shop",
    "wof:placetype":"venue"
},
  "geometry": {"coordinates":[1.083052,51.070709],"type":"Point"}
}