{
  "type": "Feature",
  "properties": {
    "addr:full":"Unit 1 Maesteg Business Centre, Heol Ty Gwyn Industrial Estate Maesteg Bridgend CF34 0BQ",
    "addr:housenumber":"unit 1",
    "addr:postcode":"cf34 0bq",
    "addr:street":"Maesteg Business Centre Heol Ty Gwyn Industrial Estate",
    "iso:country":"GB",
    "sg:address":"Unit 1 Maesteg Business Centre, Heol Ty Gwyn Industrial Estate",
    "sg:city":"Maesteg",
    "sg:classifiers":[
        {
            "category":"Home & Garden",
            "subcategory":"Home Furnishings",
            "type":"Retail Goods"
        }
    ],
    "sg:phone":"+44 1656 734800",
    "sg:postcode":"CF34 0BQ",
    "sg:province":"Bridgend",
    "sg:tags":[
        "awning",
        "canopy",
        "blinds"
    ],
    "wof:name":"Premier Blinds (Wales) Ltd.",
    "wof:placetype":"venue"
},
  "geometry": {"coordinates":[-3.658961,51.607841],"type":"Point"}
}