{
  "type": "Feature",
  "properties": {
    "addr:full":"51 Arden Gro, Kilsyth Glasgow East Dunbartonshire G65 9LZ",
    "addr:housenumber":"51",
    "addr:postcode":"g65 9lz",
    "addr:street":"Gro",
    "iso:country":"GB",
    "sg:address":"51 Arden Gro, Kilsyth",
    "sg:city":"Glasgow",
    "sg:classifiers":[
        {
            "category":"Building & Trades",
            "subcategory":"Construction",
            "type":"Services"
        }
    ],
    "sg:postcode":"G65 9LZ",
    "sg:province":"East Dunbartonshire",
    "sg:tags":[
        "roofing"
    ],
    "wof:name":"R S Erskine Roofing",
    "wof:placetype":"venue"
},
  "geometry": {"coordinates":[-4.0615439415,55.9835968018],"type":"Point"}
}