{
  "type": "Feature",
  "properties": {
    "addr:full":"Unit 20 Meat & Fish Market, Charter Arcade Barnsley South Yorkshire S70 1RE",
    "addr:housenumber":"unit 20;arcade",
    "addr:postcode":"s70 1re",
    "addr:street":"Yorkshire",
    "iso:country":"GB",
    "sg:address":"Unit 20 Meat & Fish Market, Charter Arcade",
    "sg:city":"Barnsley",
    "sg:classifiers":[
        {
            "category":"Food & Beverages",
            "subcategory":"Meat & Fish",
            "type":"Retail Goods"
        }
    ],
    "sg:phone":"+44 1226 289247",
    "sg:postcode":"S70 1RE",
    "sg:province":"South Yorkshire",
    "sg:tags":[
        "butcher"
    ],
    "wof:name":"K Birkinshaw",
    "wof:placetype":"venue"
},
  "geometry": {"coordinates":[-1.4773099422,53.549030304],"type":"Point"}
}