{
  "type": "Feature",
  "properties": {
    "addr:full":"Moorside Cleckheaton West Yorkshire BD19 6JX",
    "addr:postcode":"bd19 6jx",
    "addr:street":"West",
    "iso:country":"GB",
    "sg:address":"Moorside",
    "sg:city":"Cleckheaton",
    "sg:classifiers":[
        {
            "category":"Education",
            "subcategory":"School",
            "type":"Public Place"
        }
    ],
    "sg:phone":"+44 1274 335252",
    "sg:postcode":"BD19 6JX",
    "sg:province":"West Yorkshire",
    "sg:tags":[
        "local",
        "authority"
    ],
    "wof:name":"St Lukes C of E First School",
    "wof:placetype":"venue"
},
  "geometry": {"coordinates":[-1.7363699675,53.7194900513],"type":"Point"}
}