{
  "type": "Feature",
  "properties": {
    "addr:full":"88 Old Fallings La, Fallings Park Wolverhampton Staffordshire WV10 8BN",
    "addr:housenumber":"88",
    "addr:postcode":"wv10 8bn",
    "addr:street":"Old;La Fallings Park",
    "iso:country":"GB",
    "sg:address":"88 Old Fallings La, Fallings Park",
    "sg:city":"Wolverhampton",
    "sg:classifiers":[
        {
            "category":"Health Services",
            "subcategory":"Dentist",
            "type":"Services"
        }
    ],
    "sg:phone":"+44 1902 733369",
    "sg:postcode":"WV10 8BN",
    "sg:province":"Staffordshire",
    "wof:name":"K Aulak",
    "wof:placetype":"venue"
},
  "geometry": {"coordinates":[-2.1062939167,52.612121582],"type":"Point"}
}