{
  "type": "Feature",
  "properties": {
    "iso:country":"GB",
    "sg:address":"27 Thorley Hill",
    "sg:city":"Bishop's Stortford",
    "sg:classifiers":[
        {
            "category":"Health Services",
            "subcategory":"Doctor",
            "type":"Services"
        }
    ],
    "sg:phone":"+44 1279 657684",
    "sg:postcode":"CM23 3NE",
    "sg:province":"Essex",
    "sg:tags":[
        "practitioners"
    ],
    "wof:name":"P.J Hickman",
    "wof:placetype":"venue"
},
  "geometry": {"coordinates":[0.161173,51.859161],"type":"Point"}
}