{
  "type": "Feature",
  "properties": {
    "iso:country":"GB",
    "sg:address":"P O Box 95",
    "sg:city":"Cardiff",
    "sg:classifiers":[
        {
            "category":"Banks & Credit Unions",
            "subcategory":"Bank",
            "type":"Services"
        }
    ],
    "sg:phone":"+44 29 2034 4531",
    "sg:postcode":"CF10 2LP",
    "sg:province":"Cardiff",
    "wof:name":"Lloyds Tsb Bank Plc",
    "wof:placetype":"venue"
},
  "geometry": {"coordinates":[-3.180669,51.481258],"type":"Point"}
}