{
  "type": "Feature",
  "properties": {
    "addr:full":"127 Upper Aughton Road Southport Lancashire PR8 5NJ",
    "addr:housenumber":"127",
    "addr:postcode":"pr8 5nj",
    "addr:street":"Upper Aughton Road",
    "iso:country":"GB",
    "sg:address":"127 Upper Aughton Road",
    "sg:city":"Southport",
    "sg:classifiers":[
        {
            "category":"Building & Trades",
            "subcategory":"Landscaping Services",
            "type":"Services"
        }
    ],
    "sg:postcode":"PR8 5NJ",
    "sg:province":"Lancashire",
    "sg:tags":[
        "preservation",
        "timber"
    ],
    "wof:name":"Janus Proofing Co.",
    "wof:placetype":"venue"
},
  "geometry": {"coordinates":[-3.005204916,53.6338272095],"type":"Point"}
}