{
  "type": "Feature",
  "properties": {
    "iso:country":"GB",
    "sg:address":"Unit 14, 59 Weir Road, Durnsford Industrial Estate",
    "sg:city":"London",
    "sg:classifiers":[
        {
            "category":"Manufacturing",
            "subcategory":"Metals",
            "type":"Manufacturing & Wholesale Goods"
        }
    ],
    "sg:phone":"+44 20 8944 5770",
    "sg:postcode":"SW19 8UG",
    "sg:province":"Greater London",
    "sg:tags":[
        "product",
        "fabricated"
    ],
    "wof:name":"Leighton Ironcraft",
    "wof:placetype":"venue"
},
  "geometry": {"coordinates":[-0.1908330023,51.4373207092],"type":"Point"}
}