{
  "type": "Feature",
  "properties": {
    "iso:country":"GB",
    "sg:address":"Unit 3a Ouse Rd Bicton Indstl Pk, Kimbolton",
    "sg:city":"Huntingdon",
    "sg:classifiers":[
        {
            "category":"Professional",
            "subcategory":"Business Services",
            "type":"Services"
        }
    ],
    "sg:postcode":"PE28 0LP",
    "sg:province":"Bedfordshire",
    "sg:tags":[
        "house",
        "mailing"
    ],
    "wof:name":"New Concept Mailing Services",
    "wof:placetype":"venue"
},
  "geometry": {"coordinates":[-0.379494,52.311417],"type":"Point"}
}