{
  "type": "Feature",
  "properties": {
    "addr:full":"13 Crane Clo Bristol City of Bristol BS15 4NT",
    "addr:housenumber":"13",
    "addr:postcode":"bs15 4nt",
    "addr:street":"Crane Clo",
    "iso:country":"GB",
    "sg:address":"13 Crane Clo",
    "sg:city":"Bristol",
    "sg:classifiers":[
        {
            "category":"Professional",
            "subcategory":"Detective & Security Services",
            "type":"Services"
        }
    ],
    "sg:phone":"+44 117 960 6171",
    "sg:postcode":"BS15 4NT",
    "sg:province":"City of Bristol",
    "sg:tags":[
        "alarm",
        "burglar",
        "system"
    ],
    "wof:name":"Homewatch",
    "wof:placetype":"venue"
},
  "geometry": {"coordinates":[-2.4895439148,51.4675445557],"type":"Point"}
}