{
  "type": "Feature",
  "properties": {
    "iso:country":"GB",
    "sg:address":"Hollingdon Depot",
    "sg:city":"Leighton Buzzard",
    "sg:classifiers":[
        {
            "category":"Building & Trades",
            "subcategory":"Construction",
            "type":"Services"
        }
    ],
    "sg:phone":"+44 1525 270923",
    "sg:postcode":"LU7 0DN",
    "sg:province":"Bedfordshire",
    "sg:tags":[
        "platform",
        "work",
        "scaffolding"
    ],
    "wof:name":"Fixright Scaffolding Ltd.",
    "wof:placetype":"venue"
},
  "geometry": {"coordinates":[-0.7318,51.936443],"type":"Point"}
}