{
  "type": "Feature",
  "properties": {
    "addr:full":"1 Cornmarket Pontefract North Yorkshire WF8 1AN",
    "addr:housenumber":"1",
    "addr:postcode":"wf8 1an",
    "addr:street":"Cornmarket Pontefract",
    "iso:country":"GB",
    "sg:address":"1 Cornmarket",
    "sg:city":"Pontefract",
    "sg:classifiers":[
        {
            "category":"Bars & Pubs",
            "type":"Food & Drink"
        },
        {
            "category":"Travel",
            "subcategory":"Hotels & Motels",
            "type":"Entertainment"
        }
    ],
    "sg:phone":"+44 1977 702604",
    "sg:postcode":"WF8 1AN",
    "sg:province":"North Yorkshire",
    "sg:tags":[
        "house",
        "public",
        "activity"
    ],
    "wof:name":"Malt Shovel Hotel",
    "wof:placetype":"venue"
},
  "geometry": {"coordinates":[-1.314669,53.692005],"type":"Point"}
}