{
  "type": "Feature",
  "properties": {
    "iso:country":"GB",
    "sg:address":"Alpha House, North Street",
    "sg:city":"Burnley",
    "sg:classifiers":[
        {
            "category":"Building & Trades",
            "subcategory":"Plumbing",
            "type":"Services"
        }
    ],
    "sg:postcode":"BB12 7LE",
    "sg:province":"Lancashire",
    "sg:tags":[
        "merchant",
        "plumbers'"
    ],
    "wof:name":"Alpha Environmental Tanks Ltd.",
    "wof:placetype":"venue"
},
  "geometry": {"coordinates":[-2.315048933,53.7840156555],"type":"Point"}
}