{
  "type": "Feature",
  "properties": {
    "iso:country":"GB",
    "sg:address":"Moss Road",
    "sg:city":"Bridge Of Weir",
    "sg:classifiers":[
        {
            "category":"Building & Trades",
            "subcategory":"Electrical",
            "type":"Services"
        }
    ],
    "sg:phone":"+44 1505 615222",
    "sg:postcode":"PA11 3LY",
    "sg:province":"Inverclyde",
    "sg:tags":[
        "consultant",
        "lighting"
    ],
    "wof:name":"Associated Asphalt",
    "wof:placetype":"venue"
},
  "geometry": {"coordinates":[-4.582529,55.85672],"type":"Point"}
}