{
  "type": "Feature",
  "properties": {
    "iso:country":"GB",
    "sg:address":"12 Bradfield Rd",
    "sg:city":"Bridgend",
    "sg:classifiers":[
        {
            "category":"Arts & Performance",
            "subcategory":"Music",
            "type":"Entertainment"
        }
    ],
    "sg:postcode":"CF31 4HJ",
    "sg:province":"Bridgend",
    "sg:tags":[
        "mobile",
        "disco"
    ],
    "wof:name":"Astra Mobile Disco",
    "wof:placetype":"venue"
},
  "geometry": {"coordinates":[-3.588891,51.507935],"type":"Point"}
}