{
  "type": "Feature",
  "properties": {
    "iso:country":"GB",
    "sg:address":"6 Tamworth Dr",
    "sg:city":"Bury",
    "sg:classifiers":[
        {
            "category":"Health Services",
            "subcategory":"Health Practitioner",
            "type":"Services"
        }
    ],
    "sg:phone":"+44 161 763 7416",
    "sg:postcode":"BL8 1DP",
    "sg:province":"Lancashire",
    "sg:tags":[
        "hypnotherapists"
    ],
    "wof:name":"Richard O'Neill",
    "wof:placetype":"venue"
},
  "geometry": {"coordinates":[-2.313421011,53.6046562195],"type":"Point"}
}