{
  "type": "Feature",
  "properties": {
    "addr:full":"2a Stonehill Business Pk, Down Hall Rd Harlow Essex CM17 0RA",
    "addr:housenumber":"2a",
    "addr:postcode":"cm17 0ra",
    "addr:street":"Stonehill Business Pk Down Hall Rd",
    "iso:country":"GB",
    "sg:address":"2a Stonehill Business Pk, Down Hall Rd",
    "sg:city":"Harlow",
    "sg:classifiers":[
        {
            "category":"Professional",
            "type":"Services"
        }
    ],
    "sg:postcode":"CM17 0RA",
    "sg:province":"Essex",
    "sg:tags":[
        "display",
        "maker"
    ],
    "wof:name":"Photex Ltd",
    "wof:placetype":"venue"
},
  "geometry": {"coordinates":[0.2160400003,51.7882881165],"type":"Point"}
}