{
  "type": "Feature",
  "properties": {
    "addr:full":"1a Murraysgate Industrial Estate, Whitburn Bathgate North Lanarkshire EH47 0LE",
    "addr:housenumber":"1a",
    "addr:postcode":"eh47 0le",
    "addr:street":"Murraysgate Industrial Estate;Bathgate",
    "iso:country":"GB",
    "sg:address":"1a Murraysgate Industrial Estate, Whitburn",
    "sg:city":"Bathgate",
    "sg:classifiers":[
        {
            "category":"Autos & Motor Vehicles",
            "subcategory":"Fuel & Gas Station",
            "type":"Retail Goods"
        },
        {
            "category":"Manufacturing",
            "subcategory":"Tools & Machinery",
            "type":"Manufacturing & Wholesale Goods"
        }
    ],
    "sg:phone":"+44 1501 743273",
    "sg:postcode":"EH47 0LE",
    "sg:province":"North Lanarkshire",
    "sg:tags":[
        "machine"
    ],
    "wof:name":"Robertson Machine Tool Services",
    "wof:placetype":"venue"
},
  "geometry": {"coordinates":[-3.689629,55.86607],"type":"Point"}
}