{
  "type": "Feature",
  "properties": {
    "addr:full":"Woodlands Farm, Church Road, Catsfield Battle East Sussex TN33 9BG",
    "addr:postcode":"tn33 9bg",
    "addr:street":"Woodlands;Church Road;Battle",
    "iso:country":"GB",
    "sg:address":"Woodlands Farm, Church Road, Catsfield",
    "sg:city":"Battle",
    "sg:classifiers":[
        {
            "category":"Farming",
            "subcategory":"Poultry Farm",
            "type":"Manufacturing & Wholesale Goods"
        }
    ],
    "sg:phone":"+44 1424 892323",
    "sg:postcode":"TN33 9BG",
    "sg:province":"East Sussex",
    "sg:tags":[
        "game"
    ],
    "wof:name":"F K Carter",
    "wof:placetype":"venue"
},
  "geometry": {"coordinates":[0.44803,50.896187],"type":"Point"}
}