{
  "type": "Feature",
  "properties": {
    "addr:full":"Avenue Road Freshwater Isle of Wight PO40 9UU",
    "addr:postcode":"po40 9uu",
    "addr:street":"Avenue Road",
    "iso:country":"GB",
    "sg:address":"Avenue Road",
    "sg:city":"Freshwater",
    "sg:classifiers":[
        {
            "category":"Shopping",
            "subcategory":"Clothing, Apparel, & Fashions",
            "type":"Retail Goods"
        }
    ],
    "sg:phone":"+44 1983 752287",
    "sg:postcode":"PO40 9UU",
    "sg:province":"Isle of Wight",
    "sg:tags":[
        "menswear"
    ],
    "wof:name":"Godwins of Freshwater",
    "wof:placetype":"venue"
},
  "geometry": {"coordinates":[-1.529724,50.684238],"type":"Point"}
}