{
  "type": "Feature",
  "properties": {
    "addr:full":"Northgate Centre Sleaford Lincolnshire NG34 7AQ",
    "addr:postcode":"ng34 7aq",
    "addr:street":"Northgate",
    "iso:country":"GB",
    "sg:address":"Northgate Centre",
    "sg:city":"Sleaford",
    "sg:classifiers":[
        {
            "category":"Home & Garden",
            "subcategory":"Hardware",
            "type":"Retail Goods"
        }
    ],
    "sg:phone":"+44 1529 414475",
    "sg:postcode":"NG34 7AQ",
    "sg:province":"Lincolnshire",
    "sg:tags":[
        "retailer",
        "diy"
    ],
    "wof:name":"Texas Homecare",
    "wof:placetype":"venue"
},
  "geometry": {"coordinates":[-0.411869,52.994587],"type":"Point"}
}