{
  "type": "Feature",
  "properties": {
    "iso:country":"GB",
    "sg:address":"3a Green Lane, Clanfield",
    "sg:city":"Waterlooville",
    "sg:classifiers":[
        {
            "category":"Cinema",
            "subcategory":"Movie Rental",
            "type":"Entertainment"
        }
    ],
    "sg:phone":"+44 23 9259 9406",
    "sg:postcode":"PO8 0JU",
    "sg:province":"Hampshire",
    "sg:tags":[
        "video",
        "library"
    ],
    "wof:name":"Clanfield Video",
    "wof:placetype":"venue"
},
  "geometry": {"coordinates":[-0.999983,50.935928],"type":"Point"}
}