{
  "type": "Feature",
  "properties": {
    "addr:full":"27 South Rd Watchet Somerset TA23 0HE",
    "addr:housenumber":"27",
    "addr:postcode":"ta23 0he",
    "addr:street":"South Rd",
    "iso:country":"GB",
    "sg:address":"27 South Rd",
    "sg:city":"Watchet",
    "sg:classifiers":[
        {
            "category":"Wholesale",
            "subcategory":"Scrap",
            "type":"Manufacturing & Wholesale Goods"
        }
    ],
    "sg:phone":"+44 1984 631157",
    "sg:postcode":"TA23 0HE",
    "sg:province":"Somerset",
    "sg:tags":[
        "waste",
        "metal"
    ],
    "wof:name":"A.K Blackmore",
    "wof:placetype":"venue"
},
  "geometry": {"coordinates":[-3.327878952,51.1774520874],"type":"Point"}
}