{
  "type": "Feature",
  "properties": {
    "addr:full":"589 Downham Way Bromley Kent BR1 5HX",
    "addr:housenumber":"589",
    "addr:postcode":"br1 5hx",
    "addr:street":"Downham Way",
    "iso:country":"GB",
    "sg:address":"589 Downham Way",
    "sg:city":"Bromley",
    "sg:classifiers":[
        {
            "category":"Retail",
            "subcategory":"Funeral Services",
            "type":"Services"
        }
    ],
    "sg:postcode":"BR1 5HX",
    "sg:province":"Kent",
    "wof:name":"Toop Bros",
    "wof:placetype":"venue"
},
  "geometry": {"coordinates":[0.0209819991,51.4307937622],"type":"Point"}
}