{
  "type": "Feature",
  "properties": {
    "iso:country":"GB",
    "sg:address":"75 Mansel Street",
    "sg:city":"Swansea",
    "sg:classifiers":[
        {
            "category":"Banks & Credit Unions",
            "subcategory":"Financial Services",
            "type":"Services"
        }
    ],
    "sg:phone":"+44 1792 654435",
    "sg:postcode":"SA1 5TW",
    "sg:province":"Neath Port Talbot",
    "sg:tags":[
        "claim",
        "assessor"
    ],
    "wof:name":"W D Davies & Son (Management Services) Ltd.",
    "wof:placetype":"venue"
},
  "geometry": {"coordinates":[-3.9501519203,51.6208648682],"type":"Point"}
}