{
  "type": "Feature",
  "properties": {
    "addr:full":"Penyfodau Fawr Farm, Gorseinon Swansea Carmarthenshire SA4 4LN",
    "addr:postcode":"sa4 4ln",
    "iso:country":"GB",
    "sg:address":"Penyfodau Fawr Farm, Gorseinon",
    "sg:city":"Swansea",
    "sg:classifiers":[
        {
            "category":"Farming",
            "subcategory":"Farm",
            "type":"Manufacturing & Wholesale Goods"
        }
    ],
    "sg:phone":"+44 1792 892845",
    "sg:postcode":"SA4 4LN",
    "sg:province":"Carmarthenshire",
    "sg:tags":[
        "mixed",
        "crop"
    ],
    "wof:name":"D M & M Jones",
    "wof:placetype":"venue"
},
  "geometry": {"coordinates":[-4.0412192345,51.6666755676],"type":"Point"}
}