{
  "type": "Feature",
  "properties": {
    "iso:country":"GB",
    "sg:address":"130 Hollingbury Park Avenue",
    "sg:city":"Brighton",
    "sg:classifiers":[
        {
            "category":"Manufacturing",
            "subcategory":"Pottery",
            "type":"Manufacturing & Wholesale Goods"
        }
    ],
    "sg:postcode":"BN1 7JP",
    "sg:province":"East Sussex",
    "wof:name":"Fiveways Studios",
    "wof:placetype":"venue"
},
  "geometry": {"coordinates":[-0.134184,50.846531],"type":"Point"}
}