{
  "type": "Feature",
  "properties": {
    "iso:country":"GB",
    "sg:address":"5 Pump Square",
    "sg:city":"Boston",
    "sg:classifiers":[
        {
            "category":"Health Services",
            "subcategory":"Dentist",
            "type":"Services"
        }
    ],
    "sg:phone":"+44 1205 362816",
    "sg:postcode":"PE21 6QW",
    "sg:province":"Lincolnshire",
    "wof:name":"Ian Alexander Macdonald",
    "wof:placetype":"venue"
},
  "geometry": {"coordinates":[-0.021672,52.977924],"type":"Point"}
}