{
  "type": "Feature",
  "properties": {
    "iso:country":"GB",
    "sg:address":"2a Garner St",
    "sg:city":"London",
    "sg:classifiers":[
        {
            "category":"Manufacturing",
            "subcategory":"Wood Products",
            "type":"Manufacturing & Wholesale Goods"
        }
    ],
    "sg:postcode":"E2 9AQ",
    "sg:province":"Greater London",
    "sg:tags":[
        "sawmill",
        "shaving"
    ],
    "wof:name":"M & K Metal Fabrications",
    "wof:placetype":"venue"
},
  "geometry": {"coordinates":[-0.0073449998,51.5968132019],"type":"Point"}
}