{
  "type": "Feature",
  "properties": {
    "addr:full":"235 Blackburn Rd Bolton Lancashire BL1 8HB",
    "addr:housenumber":"235",
    "addr:postcode":"bl1 8hb",
    "addr:street":"Blackburn Rd",
    "iso:country":"GB",
    "sg:address":"235 Blackburn Rd",
    "sg:city":"Bolton",
    "sg:classifiers":[
        {
            "category":"Communications",
            "type":"Services"
        }
    ],
    "sg:phone":"+44 1204 393900",
    "sg:postcode":"BL1 8HB",
    "sg:province":"Lancashire",
    "sg:tags":[
        "telecommunication"
    ],
    "wof:name":"Livewire",
    "wof:placetype":"venue"
},
  "geometry": {"coordinates":[-2.431501,53.592953],"type":"Point"}
}