{
  "type": "Feature",
  "properties": {
    "iso:country":"GB",
    "sg:address":"Unit 1300, Blueprint Industrial Estate, Dundas Spur",
    "sg:city":"Portsmouth",
    "sg:classifiers":[
        {
            "category":"Food & Beverages",
            "subcategory":"Supermarket",
            "type":"Retail Goods"
        }
    ],
    "sg:phone":"+44 23 9266 0280",
    "sg:postcode":"PO3 5RW",
    "sg:province":"Hampshire",
    "sg:tags":[
        "frozen"
    ],
    "wof:name":"Motu Ghosh Foods Ltd.",
    "wof:placetype":"venue"
},
  "geometry": {"coordinates":[-1.05724,50.819],"type":"Point"}
}