{
  "type": "Feature",
  "properties": {
    "addr:full":"1 Malt Street Knutsford Cheshire WA16 6ES",
    "addr:housenumber":"1",
    "addr:postcode":"wa16 6es",
    "addr:street":"Malt Street",
    "iso:country":"GB",
    "sg:address":"1 Malt Street",
    "sg:city":"Knutsford",
    "sg:classifiers":[
        {
            "category":"Military Area",
            "subcategory":"Air Force Base",
            "type":"Public Place"
        }
    ],
    "sg:phone":"+44 1565 621111",
    "sg:postcode":"WA16 6ES",
    "sg:province":"Cheshire",
    "sg:tags":[
        "taxi",
        "hire",
        "private"
    ],
    "wof:name":"Acorn Cars",
    "wof:placetype":"venue"
},
  "geometry": {"coordinates":[-2.3730080128,53.3048019409],"type":"Point"}
}