{
  "type": "Feature",
  "properties": {
    "iso:country":"GB",
    "sg:address":"Unit 5, Old Priory Works, St Margarets Lane, Titchfield",
    "sg:city":"Fareham",
    "sg:classifiers":[
        {
            "category":"Professional",
            "subcategory":"Art Services",
            "type":"Services"
        }
    ],
    "sg:phone":"+44 1329 844355",
    "sg:postcode":"PO14 4BQ",
    "sg:province":"Hampshire",
    "sg:tags":[
        "consultant",
        "design"
    ],
    "wof:name":"Murray Taylor & Co",
    "wof:placetype":"venue"
},
  "geometry": {"coordinates":[-1.234621048,50.8482818604],"type":"Point"}
}