{
  "type": "Feature",
  "properties": {
    "addr:full":"7 Starnes Court, Union Street Maidstone Kent ME14 1EB",
    "addr:housenumber":"7",
    "addr:postcode":"me14 1eb",
    "addr:street":"Starnes Court Union Street",
    "iso:country":"GB",
    "sg:address":"7 Starnes Court, Union Street",
    "sg:city":"Maidstone",
    "sg:classifiers":[
        {
            "category":"Personal",
            "subcategory":"Barber",
            "type":"Services"
        }
    ],
    "sg:phone":"+44 1622 763582",
    "sg:postcode":"ME14 1EB",
    "sg:province":"Kent",
    "sg:tags":[
        "men's",
        "gents",
        "hairdresser"
    ],
    "wof:name":"A J Hairdressing For Men",
    "wof:placetype":"venue"
},
  "geometry": {"coordinates":[0.523405,51.276165],"type":"Point"}
}