{
  "type": "Feature",
  "properties": {
    "iso:country":"GB",
    "sg:address":"Forge Farm",
    "sg:city":"Carmarthen",
    "sg:classifiers":[
        {
            "category":"Government",
            "subcategory":"Customs House",
            "type":"Public Place"
        }
    ],
    "sg:phone":"+44 1267 281533",
    "sg:postcode":"SA33 6JG",
    "sg:province":"Carmarthenshire",
    "sg:tags":[
        "clearance"
    ],
    "wof:name":"A P & C I Marson",
    "wof:placetype":"venue"
},
  "geometry": {"coordinates":[-4.31378,51.905258],"type":"Point"}
}