{
  "type": "Feature",
  "properties": {
    "addr:full":"5 Station Road Sheringham Norfolk NR26 8RE",
    "addr:housenumber":"5",
    "addr:postcode":"nr26 8re",
    "addr:street":"Station Road",
    "iso:country":"GB",
    "sg:address":"5 Station Road",
    "sg:city":"Sheringham",
    "sg:classifiers":[
        {
            "category":"Shopping",
            "subcategory":"Clothing, Apparel, & Fashions",
            "type":"Retail Goods"
        }
    ],
    "sg:phone":"+44 1263 824260",
    "sg:postcode":"NR26 8RE",
    "sg:province":"Norfolk",
    "sg:tags":[
        "lingerie",
        "hosiery"
    ],
    "wof:name":"Bloomers of Sheringham",
    "wof:placetype":"venue"
},
  "geometry": {"coordinates":[1.2112350464,52.9433670044],"type":"Point"}
}