{
  "type": "Feature",
  "properties": {
    "iso:country":"GB",
    "sg:address":"3 Church Place, Chale",
    "sg:city":"Ventnor",
    "sg:classifiers":[
        {
            "category":"Shopping",
            "subcategory":"Antiques",
            "type":"Retail Goods"
        }
    ],
    "sg:postcode":"PO38 2HA",
    "sg:province":"Isle of Wight",
    "wof:name":"Curios of Chale",
    "wof:placetype":"venue"
},
  "geometry": {"coordinates":[-1.3176699877,50.5966911316],"type":"Point"}
}