{
  "type": "Feature",
  "properties": {
    "iso:country":"GB",
    "sg:address":"Chavasse Court",
    "sg:city":"Liverpool",
    "sg:classifiers":[
        {
            "category":"Professional",
            "subcategory":"Lawyer & Legal Services",
            "type":"Services"
        }
    ],
    "sg:phone":"+44 151 707 1191",
    "sg:postcode":"L2 1TA",
    "sg:province":"Merseyside",
    "sg:tags":[
        "barrister"
    ],
    "wof:name":"Chavasse Court Chambers",
    "wof:placetype":"venue"
},
  "geometry": {"coordinates":[-2.98883,53.40506],"type":"Point"}
}