{
  "type": "Feature",
  "properties": {
    "iso:country":"GB",
    "sg:address":"34 North Street",
    "sg:city":"Rugby",
    "sg:classifiers":[
        {
            "category":"Banks & Credit Unions",
            "subcategory":"Financial Services",
            "type":"Services"
        }
    ],
    "sg:phone":"+44 1788 578311",
    "sg:postcode":"CV21 2AJ",
    "sg:province":"Warwickshire",
    "sg:tags":[
        "building",
        "society"
    ],
    "sg:website":"http://www.hrbs.co.uk",
    "wof:name":"Hinckley & Rugby Building Society",
    "wof:placetype":"venue"
},
  "geometry": {"coordinates":[-1.2622259855,52.3736457825],"type":"Point"}
}