{
  "type": "Feature",
  "properties": {
    "iso:country":"GB",
    "sg:address":"93 Bohemia Road",
    "sg:city":"St Leonards-on-sea",
    "sg:classifiers":[
        {
            "category":"Professional",
            "subcategory":"Accounting & Tax Preparation",
            "type":"Services"
        }
    ],
    "sg:postcode":"TN37 6RJ",
    "sg:province":"East Sussex",
    "sg:tags":[
        "accountant"
    ],
    "wof:name":"Reade Stanley Bryan & Co.",
    "wof:placetype":"venue"
},
  "geometry": {"coordinates":[0.5600000024,50.8622817993],"type":"Point"}
}