{
  "type": "Feature",
  "properties": {
    "iso:country":"GB",
    "sg:address":"162 Queens Road",
    "sg:city":"Buckhurst Hill",
    "sg:classifiers":[
        {
            "category":"Shopping",
            "subcategory":"Florist",
            "type":"Retail Goods"
        }
    ],
    "sg:phone":"+44 20 8504 3004",
    "sg:postcode":"IG9 5BD",
    "sg:province":"Essex",
    "wof:name":"Queens Road Florist",
    "wof:placetype":"venue"
},
  "geometry": {"coordinates":[0.037713,51.62579],"type":"Point"}
}