{
  "type": "Feature",
  "properties": {
    "addr:full":"3 Park Lane Bath Bath and North East Somerset BA1 2XG",
    "addr:housenumber":"3",
    "addr:postcode":"ba1 2xg",
    "addr:street":"Park Lane",
    "iso:country":"GB",
    "sg:address":"3 Park Lane",
    "sg:city":"Bath",
    "sg:classifiers":[
        {
            "category":"Bars & Pubs",
            "type":"Food & Drink"
        }
    ],
    "sg:phone":"+44 1225 425174",
    "sg:postcode":"BA1 2XG",
    "sg:province":"Bath and North East Somerset",
    "sg:tags":[
        "pubs",
        "inn"
    ],
    "wof:name":"The Park Tavern",
    "wof:placetype":"venue"
},
  "geometry": {"coordinates":[-2.378837,51.385998],"type":"Point"}
}