{
  "type": "Feature",
  "properties": {
    "iso:country":"GB",
    "sg:address":"7 Canal Street",
    "sg:city":"Renfrew",
    "sg:classifiers":[
        {
            "category":"Professional",
            "subcategory":"Lawyer & Legal Services",
            "type":"Services"
        }
    ],
    "sg:phone":"+44 141 886 2152",
    "sg:postcode":"PA4 8QF",
    "sg:province":"Renfrewshire",
    "sg:tags":[
        "solicitor"
    ],
    "wof:name":"Walker Laird",
    "wof:placetype":"venue"
},
  "geometry": {"coordinates":[-4.386731,55.879322],"type":"Point"}
}