{
  "type": "Feature",
  "properties": {
    "iso:country":"GB",
    "sg:address":"Unit 8, Latchmore Industrial Park, Low Fields Road",
    "sg:city":"Leeds",
    "sg:classifiers":[
        {
            "category":"Home & Garden",
            "subcategory":"Hardware",
            "type":"Retail Goods"
        }
    ],
    "sg:phone":"+44 113 246 9992",
    "sg:postcode":"LS12 6DN",
    "sg:province":"West Yorkshire",
    "sg:tags":[
        "device",
        "fixing",
        "fastener",
        "nuts",
        "bolt"
    ],
    "wof:name":"Andrews Fasteners Ltd.",
    "wof:placetype":"venue"
},
  "geometry": {"coordinates":[-1.575794,53.7798],"type":"Point"}
}