{
  "type": "Feature",
  "properties": {
    "iso:country":"GB",
    "sg:address":"School Road",
    "sg:city":"Norwich",
    "sg:classifiers":[
        {
            "category":"Autos & Motor Vehicles",
            "subcategory":"Boat Sales",
            "type":"Retail Goods"
        }
    ],
    "sg:phone":"+44 1692 630461",
    "sg:postcode":"NR12 8PS",
    "sg:province":"Norfolk",
    "sg:tags":[
        "repair",
        "builder"
    ],
    "wof:name":"Woods Dyke Boat Yard",
    "wof:placetype":"venue"
},
  "geometry": {"coordinates":[1.423785,52.735485],"type":"Point"}
}