{
  "type": "Feature",
  "properties": {
    "addr:full":"257 North Deeside Road Peterculter Aberdeen City AB14 0UL",
    "addr:housenumber":"257",
    "addr:postcode":"ab14 0ul",
    "addr:street":"North Deeside Road",
    "iso:country":"GB",
    "sg:address":"257 North Deeside Road",
    "sg:city":"Peterculter",
    "sg:classifiers":[
        {
            "category":"Food & Beverages",
            "subcategory":"Meat & Fish",
            "type":"Retail Goods"
        }
    ],
    "sg:phone":"+44 1224 733222",
    "sg:postcode":"AB14 0UL",
    "sg:province":"Aberdeen City",
    "sg:tags":[
        "butcher"
    ],
    "wof:name":"Keith Donald",
    "wof:placetype":"venue"
},
  "geometry": {"coordinates":[-2.269671,57.096085],"type":"Point"}
}