{
  "type": "Feature",
  "properties": {
    "iso:country":"GB",
    "sg:address":"18-190 Edward Street",
    "sg:city":"London",
    "sg:classifiers":[
        {
            "category":"Building & Trades",
            "subcategory":"Construction",
            "type":"Services"
        }
    ],
    "sg:postcode":"SE8 5HD",
    "sg:province":"Greater London",
    "sg:tags":[
        "heating",
        "contractor"
    ],
    "wof:name":"Danterway Ltd.",
    "wof:placetype":"venue"
},
  "geometry": {"coordinates":[-0.035504,51.479118],"type":"Point"}
}