{
  "type": "Feature",
  "properties": {
    "addr:full":"51 Main Street, Long Eaton Nottingham Derbyshire NG10 1GW",
    "addr:housenumber":"51",
    "addr:postcode":"ng10 1gw",
    "addr:street":"Main Street",
    "iso:country":"GB",
    "sg:address":"51 Main Street, Long Eaton",
    "sg:city":"Nottingham",
    "sg:classifiers":[
        {
            "category":"Bars & Pubs",
            "type":"Food & Drink"
        }
    ],
    "sg:phone":"+44 115 973 4058",
    "sg:postcode":"NG10 1GW",
    "sg:province":"Derbyshire",
    "sg:tags":[
        "pubs",
        "inn"
    ],
    "wof:name":"Victoria Inn",
    "wof:placetype":"venue"
},
  "geometry": {"coordinates":[-1.2664430141,52.8950843811],"type":"Point"}
}