{
  "type": "Feature",
  "properties": {
    "iso:country":"GB",
    "sg:address":"Trinity Mews",
    "sg:city":"Bridlington",
    "sg:classifiers":[
        {
            "category":"Recreation",
            "subcategory":"Amusement Park",
            "type":"Entertainment"
        }
    ],
    "sg:postcode":"YO15 2HA",
    "sg:province":"East Riding of Yorkshire",
    "sg:tags":[
        "arcade"
    ],
    "wof:name":"Sadler Automatics",
    "wof:placetype":"venue"
},
  "geometry": {"coordinates":[-0.189339,54.088203],"type":"Point"}
}