{
  "type": "Feature",
  "properties": {
    "addr:full":"28 Austin Friars London Greater London EC2N 2QQ",
    "addr:housenumber":"28",
    "addr:postcode":"ec2n 2qq",
    "addr:street":"Austin Friars",
    "iso:country":"GB",
    "sg:address":"28 Austin Friars",
    "sg:city":"London",
    "sg:classifiers":[
        {
            "category":"Professional",
            "type":"Services"
        }
    ],
    "sg:phone":"+44 20 7628 7555",
    "sg:postcode":"EC2N 2QQ",
    "sg:province":"Greater London",
    "sg:tags":[
        "repair",
        "tech",
        "maintenance"
    ],
    "wof:name":"Prime Finance Solutions Ltd",
    "wof:placetype":"venue"
},
  "geometry": {"coordinates":[-0.085735,51.514957],"type":"Point"}
}