{
  "type": "Feature",
  "properties": {
    "iso:country":"GB",
    "sg:address":"8 Spencer Rd",
    "sg:city":"Coventry",
    "sg:classifiers":[
        {
            "category":"Health Services",
            "subcategory":"Dentist",
            "type":"Services"
        }
    ],
    "sg:phone":"+44 24 7667 7881",
    "sg:postcode":"CV5 6PA",
    "sg:province":"West Midlands",
    "wof:name":"S Moncur",
    "wof:placetype":"venue"
},
  "geometry": {"coordinates":[-1.5202,52.399422],"type":"Point"}
}