{
  "type": "Feature",
  "properties": {
    "addr:full":"5 Somerset Place Glasgow Glasgow City G3 7JT",
    "addr:housenumber":"5",
    "addr:postcode":"g3 7jt",
    "addr:street":"Somerset Place",
    "iso:country":"GB",
    "sg:address":"5 Somerset Place",
    "sg:city":"Glasgow",
    "sg:classifiers":[
        {
            "category":"Retail",
            "subcategory":"Auto Rental",
            "type":"Services"
        },
        {
            "category":"Building & Trades",
            "subcategory":"Construction",
            "type":"Services"
        }
    ],
    "sg:phone":"+44 141 333 0974",
    "sg:postcode":"G3 7JT",
    "sg:province":"Glasgow City",
    "sg:tags":[
        "renting",
        "platform",
        "scaffold",
        "work",
        "scaffolding"
    ],
    "wof:name":"R J R Engineering Co",
    "wof:placetype":"venue"
},
  "geometry": {"coordinates":[-4.2773170471,55.8663635254],"type":"Point"}
}