{
  "type": "Feature",
  "properties": {
    "addr:full":"6 Doncaster Gate Rotherham South Yorkshire S65 1DJ",
    "addr:housenumber":"6",
    "addr:postcode":"s65 1dj",
    "addr:street":"Doncaster Gate",
    "iso:country":"GB",
    "sg:address":"6 Doncaster Gate",
    "sg:city":"Rotherham",
    "sg:classifiers":[
        {
            "category":"Manufacturing",
            "subcategory":"Petroleum Products",
            "type":"Manufacturing & Wholesale Goods"
        }
    ],
    "sg:phone":"+44 1709 829292",
    "sg:postcode":"S65 1DJ",
    "sg:province":"South Yorkshire",
    "sg:tags":[
        "double",
        "glazing"
    ],
    "wof:name":"South Yorkshire Home Improvements",
    "wof:placetype":"venue"
},
  "geometry": {"coordinates":[-1.354245,53.430752],"type":"Point"}
}