{
  "type": "Feature",
  "properties": {
    "iso:country":"GB",
    "sg:address":"34 Bury Walk",
    "sg:city":"Chelsea",
    "sg:classifiers":[
        {
            "category":"Shopping",
            "subcategory":"Books",
            "type":"Retail Goods"
        }
    ],
    "sg:phone":"+44 20 7352 8494",
    "sg:postcode":"SW3 6QB",
    "sg:province":"Greater London",
    "wof:name":"Socotrap",
    "wof:placetype":"venue"
},
  "geometry": {"coordinates":[-0.170888,51.49128],"type":"Point"}
}