{
  "type": "Feature",
  "properties": {
    "iso:country":"GB",
    "sg:address":"2nd Floor 6 South Charlotte Str, Eet",
    "sg:city":"Edinburgh",
    "sg:classifiers":[
        {
            "category":"Professional",
            "subcategory":"Business Services",
            "type":"Services"
        }
    ],
    "sg:phone":"+44 131 226 3322",
    "sg:postcode":"EH2 4AW",
    "sg:province":"City of Edinburgh",
    "sg:tags":[
        "hospitality",
        "corporate"
    ],
    "wof:name":"Hogg Robinson Business Travel International",
    "wof:placetype":"venue"
},
  "geometry": {"coordinates":[-3.20619,55.950771],"type":"Point"}
}