{
  "type": "Feature",
  "properties": {
    "iso:country":"GB",
    "sg:address":"High Street, Cuckfield",
    "sg:city":"Haywards Heath",
    "sg:classifiers":[
        {
            "category":"Bars & Pubs",
            "type":"Food & Drink"
        },
        {
            "category":"Professional",
            "type":"Services"
        },
        {
            "category":"Arts & Performance",
            "subcategory":"Theater",
            "type":"Entertainment"
        }
    ],
    "sg:phone":"+44 1444 413137",
    "sg:postcode":"RH17 5JX",
    "sg:province":"East Sussex",
    "sg:tags":[
        "pubs",
        "theatrical",
        "inn",
        "presentation",
        "entertainer"
    ],
    "wof:name":"John Bosco Entertainments",
    "wof:placetype":"venue"
},
  "geometry": {"coordinates":[-0.1406289935,51.0108146667],"type":"Point"}
}