{
  "type": "Feature",
  "properties": {
    "addr:full":"95 Ronaldsway Preston Lancashire PR1 6EQ",
    "addr:housenumber":"95",
    "addr:postcode":"pr1 6eq",
    "addr:street":"Ronaldsway Preston",
    "iso:country":"GB",
    "sg:address":"95 Ronaldsway",
    "sg:city":"Preston",
    "sg:classifiers":[
        {
            "category":"Wholesale",
            "subcategory":"Office Equipment",
            "type":"Manufacturing & Wholesale Goods"
        },
        {
            "category":"Wholesale",
            "subcategory":"Vending Machines",
            "type":"Manufacturing & Wholesale Goods"
        }
    ],
    "sg:phone":"+44 1772 653755",
    "sg:postcode":"PR1 6EQ",
    "sg:province":"Lancashire",
    "sg:tags":[
        "supplier",
        "business",
        "furniture"
    ],
    "wof:name":"Bosson Business Machines",
    "wof:placetype":"venue"
},
  "geometry": {"coordinates":[-2.676413,53.775745],"type":"Point"}
}