{
  "type": "Feature",
  "properties": {
    "iso:country":"GB",
    "sg:address":"9 Duke Street, Formby",
    "sg:city":"Liverpool",
    "sg:classifiers":[
        {
            "category":"Restaurant",
            "type":"Food & Drink"
        }
    ],
    "sg:phone":"+44 1704 877771",
    "sg:postcode":"L37 4AL",
    "sg:province":"Lancashire",
    "sg:tags":[
        "-",
        "chinese"
    ],
    "wof:name":"Golden Bridge",
    "wof:placetype":"venue"
},
  "geometry": {"coordinates":[-3.068808,53.553455],"type":"Point"}
}