{
  "type": "Feature",
  "properties": {
    "iso:country":"GB",
    "sg:address":"98-100 Hythe Rd",
    "sg:city":"Ashford",
    "sg:classifiers":[
        {
            "category":"Home & Garden",
            "subcategory":"Home Furnishings",
            "type":"Retail Goods"
        }
    ],
    "sg:phone":"+44 1233 638343",
    "sg:postcode":"TN24 8PR",
    "sg:province":"Kent",
    "sg:tags":[
        "beds",
        "bedding",
        "blanket"
    ],
    "wof:name":"Ashford Bedding Centre Ltd",
    "wof:placetype":"venue"
},
  "geometry": {"coordinates":[0.883561,51.147366],"type":"Point"}
}