{
  "type": "Feature",
  "properties": {
    "iso:country":"GB",
    "sg:address":"Amen Alley",
    "sg:city":"Derby",
    "sg:classifiers":[
        {
            "category":"Professional",
            "subcategory":"Lawyer & Legal Services",
            "type":"Services"
        }
    ],
    "sg:phone":"+44 1332 372211",
    "sg:postcode":"DE1 3GT",
    "sg:province":"Derbyshire",
    "sg:tags":[
        "solicitor"
    ],
    "wof:name":"J H Powell & Co",
    "wof:placetype":"venue"
},
  "geometry": {"coordinates":[-1.4772139788,52.9245910645],"type":"Point"}
}