{
  "type": "Feature",
  "properties": {
    "iso:country":"GB",
    "sg:address":"8 Alder Drive, Hoghton",
    "sg:city":"Preston",
    "sg:classifiers":[
        {
            "category":"Shopping",
            "subcategory":"News",
            "type":"Retail Goods"
        }
    ],
    "sg:phone":"+44 1254 852726",
    "sg:postcode":"PR5 0AD",
    "sg:province":"Lancashire",
    "sg:tags":[
        "newsagent"
    ],
    "wof:name":"Peter Bretherton",
    "wof:placetype":"venue"
},
  "geometry": {"coordinates":[-2.620196,53.732971],"type":"Point"}
}