{
  "type": "Feature",
  "properties": {
    "addr:full":"11 Kenilworth Close, Padiham Burnley Lancashire BB12 8SG",
    "addr:housenumber":"11",
    "addr:postcode":"bb12 8sg",
    "addr:street":"Kenilworth Close",
    "iso:country":"GB",
    "sg:address":"11 Kenilworth Close, Padiham",
    "sg:city":"Burnley",
    "sg:classifiers":[
        {
            "category":"Building & Trades",
            "subcategory":"Plumbing",
            "type":"Services"
        }
    ],
    "sg:postcode":"BB12 8SG",
    "sg:province":"Lancashire",
    "sg:tags":[
        "central",
        "heating"
    ],
    "wof:name":"Wade Damp Proof Specialist",
    "wof:placetype":"venue"
},
  "geometry": {"coordinates":[-2.3044970036,53.7998771667],"type":"Point"}
}