{
  "type": "Feature",
  "properties": {
    "addr:full":"Old Church Street Manchester Greater Manchester M40 2JE",
    "addr:postcode":"m40 2je",
    "addr:street":"Old Church Street",
    "iso:country":"GB",
    "sg:address":"Old Church Street",
    "sg:city":"Manchester",
    "sg:classifiers":[
        {
            "category":"Food & Beverages",
            "subcategory":"Fruits & Vegetables",
            "type":"Retail Goods"
        }
    ],
    "sg:postcode":"M40 2JE",
    "sg:province":"Greater Manchester",
    "sg:tags":[
        "greengrocer"
    ],
    "wof:name":"Corballys Fruit & Veg",
    "wof:placetype":"venue"
},
  "geometry": {"coordinates":[-2.183874,53.502415],"type":"Point"}
}