{
  "type": "Feature",
  "properties": {
    "iso:country":"GB",
    "sg:address":"Ashleigh Terrace, Jersey Marine",
    "sg:city":"Neath",
    "sg:classifiers":[
        {
            "category":"Travel",
            "subcategory":"Hotels & Motels",
            "type":"Entertainment"
        }
    ],
    "sg:phone":"+44 1792 814155",
    "sg:postcode":"SA10 6JL",
    "sg:province":"Neath Port Talbot",
    "wof:name":"New Tower Hotel",
    "wof:placetype":"venue"
},
  "geometry": {"coordinates":[-3.859569,51.632065],"type":"Point"}
}