{
  "type": "Feature",
  "properties": {
    "addr:full":"Norton House Nelson Street Market Harborough Leicestershire LE16 9AX",
    "addr:postcode":"le16 9ax",
    "addr:street":"Nelson Street",
    "iso:country":"GB",
    "sg:address":"Norton House Nelson Street",
    "sg:city":"Market Harborough",
    "sg:classifiers":[
        {
            "category":"Real Estate",
            "subcategory":"Developer",
            "type":"Services"
        }
    ],
    "sg:phone":"+44 1858 433883",
    "sg:postcode":"LE16 9AX",
    "sg:province":"Leicestershire",
    "sg:tags":[
        "property"
    ],
    "wof:name":"H D Gee Consultants",
    "wof:placetype":"venue"
},
  "geometry": {"coordinates":[-0.925477,52.478092],"type":"Point"}
}