{
  "type": "Feature",
  "properties": {
    "addr:full":"Westlands Estate, Baglan Moors Port Talbot Neath Port Talbot SA12 7DE",
    "addr:postcode":"sa12 7de",
    "addr:street":"Moors Port Talbot",
    "iso:country":"GB",
    "sg:address":"Westlands Estate, Baglan Moors",
    "sg:city":"Port Talbot",
    "sg:classifiers":[
        {
            "category":"Building & Trades",
            "subcategory":"Plumbing",
            "type":"Services"
        }
    ],
    "sg:phone":"+44 1639 812947",
    "sg:postcode":"SA12 7DE",
    "sg:province":"Neath Port Talbot",
    "sg:tags":[
        "plumber",
        "heating"
    ],
    "wof:name":"Royston A Johnson",
    "wof:placetype":"venue"
},
  "geometry": {"coordinates":[-3.802369,51.591385],"type":"Point"}
}