{
  "type": "Feature",
  "properties": {
    "addr:full":"21-23 Station Rd London Greater London SE20 7BE",
    "addr:housenumber":"21-23",
    "addr:postcode":"se20 7be",
    "addr:street":"Station Rd",
    "iso:country":"GB",
    "sg:address":"21-23 Station Rd",
    "sg:city":"London",
    "sg:classifiers":[
        {
            "category":"Food & Beverages",
            "subcategory":"Liquor & Beverages",
            "type":"Retail Goods"
        }
    ],
    "sg:postcode":"SE20 7BE",
    "sg:province":"Greater London",
    "sg:tags":[
        "beer",
        "spirit",
        "wines"
    ],
    "wof:name":"Mukjerjee,Dilip,",
    "wof:placetype":"venue"
},
  "geometry": {"coordinates":[-0.0552869998,51.4191207886],"type":"Point"}
}