{
  "type": "Feature",
  "properties": {
    "iso:country":"GB",
    "sg:address":"3 Aberfeldy Road, Kenmore",
    "sg:city":"Aberfeldy",
    "sg:classifiers":[
        {
            "category":"Communications",
            "subcategory":"Newspaper",
            "type":"Services"
        }
    ],
    "sg:phone":"+44 1887 830526",
    "sg:postcode":"PH15 2HF",
    "sg:province":"Perth and Kinross",
    "sg:tags":[
        "magazine"
    ],
    "wof:name":"Rolling River",
    "wof:placetype":"venue"
},
  "geometry": {"coordinates":[-3.996419,56.584126],"type":"Point"}
}