{
  "type": "Feature",
  "properties": {
    "addr:full":"Bradley Street Grimsby Lincolnshire DN32 9BL",
    "addr:postcode":"dn32 9bl",
    "addr:street":"Bradley Street",
    "iso:country":"GB",
    "sg:address":"Bradley Street",
    "sg:city":"Grimsby",
    "sg:classifiers":[
        {
            "category":"Wholesale",
            "subcategory":"Fruits & Vegetables",
            "type":"Manufacturing & Wholesale Goods"
        }
    ],
    "sg:phone":"+44 1472 232222",
    "sg:postcode":"DN32 9BL",
    "sg:province":"Lincolnshire",
    "wof:name":"S Clift (Grimsby) Ltd.",
    "wof:placetype":"venue"
},
  "geometry": {"coordinates":[-0.0763339996,53.566734314],"type":"Point"}
}