{
  "type": "Feature",
  "properties": {
    "addr:full":"Mill Hill Edenbridge East Sussex TN8 5DA",
    "addr:postcode":"tn8 5da",
    "iso:country":"GB",
    "sg:address":"Mill Hill",
    "sg:city":"Edenbridge",
    "sg:classifiers":[
        {
            "category":"Communications",
            "type":"Services"
        }
    ],
    "sg:postcode":"TN8 5DA",
    "sg:province":"East Sussex",
    "sg:tags":[
        "audio-visual"
    ],
    "wof:name":"Meadowbank Productions",
    "wof:placetype":"venue"
},
  "geometry": {"coordinates":[0.067898,51.187897],"type":"Point"}
}