{
  "type": "Feature",
  "properties": {
    "iso:country":"GB",
    "sg:address":"50 Conyngham Road",
    "sg:city":"Northampton",
    "sg:classifiers":[
        {
            "category":"Home & Garden",
            "subcategory":"Hardware",
            "type":"Retail Goods"
        }
    ],
    "sg:phone":"+44 1604 411175",
    "sg:postcode":"NN3 9TA",
    "sg:province":"Northamptonshire",
    "sg:tags":[
        "equipment",
        "welding"
    ],
    "wof:name":"Comet Welding Services Ltd.",
    "wof:placetype":"venue"
},
  "geometry": {"coordinates":[-0.8309999704,52.2551231384],"type":"Point"}
}