{
  "type": "Feature",
  "properties": {
    "iso:country":"GB",
    "sg:address":"Halton Rd",
    "sg:city":"Runcorn",
    "sg:classifiers":[
        {
            "category":"Utilities",
            "subcategory":"Fuel Oil & Lpg",
            "type":"Services"
        }
    ],
    "sg:phone":"+44 1928 566631",
    "sg:postcode":"WA7 5QP",
    "sg:province":"Cheshire",
    "wof:name":"Martindales Fuels Services",
    "wof:placetype":"venue"
},
  "geometry": {"coordinates":[-2.722839,53.3409],"type":"Point"}
}