{
  "type": "Feature",
  "properties": {
    "addr:full":"16 Highmeres Road Leicester Leicestershire LE4 9LZ",
    "addr:housenumber":"16",
    "addr:postcode":"le4 9lz",
    "addr:street":"Highmeres Road",
    "iso:country":"GB",
    "sg:address":"16 Highmeres Road",
    "sg:city":"Leicester",
    "sg:classifiers":[
        {
            "category":"Professional",
            "subcategory":"Engineering",
            "type":"Services"
        }
    ],
    "sg:phone":"+44 116 276 9953",
    "sg:postcode":"LE4 9LZ",
    "sg:province":"Leicestershire",
    "sg:tags":[
        "precision",
        "engineer"
    ],
    "wof:name":"Springfield Pressings Ltd.",
    "wof:placetype":"venue"
},
  "geometry": {"coordinates":[-1.0858689547,52.6598548889],"type":"Point"}
}