{
  "type": "Feature",
  "properties": {
    "iso:country":"GB",
    "sg:address":"61 Newgate St",
    "sg:city":"Morpeth",
    "sg:classifiers":[
        {
            "category":"Communications",
            "type":"Services"
        }
    ],
    "sg:phone":"+44 1670 514415",
    "sg:postcode":"NE61 1AY",
    "sg:province":"Northumberland",
    "sg:tags":[
        "tv",
        "video",
        "radio"
    ],
    "wof:name":"A E Okon",
    "wof:placetype":"venue"
},
  "geometry": {"coordinates":[-1.691954,55.169552],"type":"Point"}
}