{
  "type": "Feature",
  "properties": {
    "iso:country":"GB",
    "sg:address":"205 Stretham High Rd",
    "sg:city":"Streatham",
    "sg:classifiers":[
        {
            "category":"Real Estate",
            "subcategory":"Real Estate Operator",
            "type":"Services"
        }
    ],
    "sg:phone":"+44 7956 915553",
    "sg:postcode":"SW16 6EG",
    "sg:province":"Greater London",
    "sg:tags":[
        "letting",
        "agent"
    ],
    "wof:name":"Alpha Letting Services",
    "wof:placetype":"venue"
},
  "geometry": {"coordinates":[-0.130875,51.427608],"type":"Point"}
}