{
  "type": "Feature",
  "properties": {
    "iso:country":"GB",
    "sg:address":"Unit 11 Flemington Industrial Estate, Cambuslange",
    "sg:city":"Glasgow",
    "sg:classifiers":[
        {
            "category":"Real Estate",
            "subcategory":"Architect",
            "type":"Services"
        }
    ],
    "sg:postcode":"G72 7TN",
    "sg:province":"South Lanarkshire",
    "wof:name":"George Watt & Stewart",
    "wof:placetype":"venue"
},
  "geometry": {"coordinates":[-4.1365,55.810741],"type":"Point"}
}