{
  "type": "Feature",
  "properties": {
    "iso:country":"GB",
    "sg:address":"Hanley Business Park, Cooper Street, Hanley",
    "sg:city":"Stoke-on-trent",
    "sg:classifiers":[
        {
            "category":"Home & Garden",
            "subcategory":"Building Materials",
            "type":"Retail Goods"
        }
    ],
    "sg:phone":"+44 1782 214676",
    "sg:postcode":"ST1 4DW",
    "sg:province":"Staffordshire",
    "sg:tags":[
        "furnishers",
        "bathroom",
        "planner"
    ],
    "wof:name":"Dealkent Ltd.",
    "wof:placetype":"venue"
},
  "geometry": {"coordinates":[-2.179723978,53.0196533203],"type":"Point"}
}