{
  "type": "Feature",
  "properties": {
    "iso:country":"GB",
    "sg:address":"105 Acre Lane",
    "sg:city":"Cheadle",
    "sg:classifiers":[
        {
            "category":"Building & Trades",
            "subcategory":"Construction",
            "type":"Services"
        }
    ],
    "sg:postcode":"SK8 7PA",
    "sg:province":"Cheshire",
    "sg:tags":[
        "builder"
    ],
    "wof:name":"B H C Builders",
    "wof:placetype":"venue"
},
  "geometry": {"coordinates":[-2.178565,53.359291],"type":"Point"}
}