{
  "type": "Feature",
  "properties": {
    "iso:country":"GB",
    "sg:address":"Unit 23 Park Royal Rd",
    "sg:city":"Willesden",
    "sg:classifiers":[
        {
            "category":"Home & Garden",
            "subcategory":"Home Furnishings",
            "type":"Retail Goods"
        }
    ],
    "sg:phone":"+44 20 8965 5287",
    "sg:postcode":"NW10 7JH",
    "sg:province":"Greater London",
    "sg:tags":[
        "awning",
        "canopy",
        "blinds"
    ],
    "wof:name":"Contact Blinds",
    "wof:placetype":"venue"
},
  "geometry": {"coordinates":[-0.2661789954,51.5259628296],"type":"Point"}
}