{
  "type": "Feature",
  "properties": {
    "iso:country":"GB",
    "sg:address":"11 Bishops Close, Fernhurst",
    "sg:city":"Haslemere",
    "sg:classifiers":[
        {
            "category":"Arts & Performance",
            "subcategory":"Music",
            "type":"Entertainment"
        }
    ],
    "sg:postcode":"GU27 3NY",
    "sg:province":"Hampshire",
    "sg:tags":[
        "mobile",
        "disco"
    ],
    "wof:name":"Spellbound Disco",
    "wof:placetype":"venue"
},
  "geometry": {"coordinates":[-0.72631,51.050949],"type":"Point"}
}