{
  "type": "Feature",
  "properties": {
    "addr:full":"304-306 Valley Road Nottingham Nottinghamshire NG5 1HW",
    "addr:housenumber":"304-306",
    "addr:postcode":"ng5 1hw",
    "addr:street":"Valley Road",
    "iso:country":"GB",
    "sg:address":"304-306 Valley Road",
    "sg:city":"Nottingham",
    "sg:classifiers":[
        {
            "category":"Government",
            "subcategory":"Post Office",
            "type":"Public Place"
        }
    ],
    "sg:phone":"+44 115 978 7099",
    "sg:postcode":"NG5 1HW",
    "sg:province":"Nottinghamshire",
    "wof:name":"Western Valley Sub Post Office",
    "wof:placetype":"venue"
},
  "geometry": {"coordinates":[-1.1695870161,52.9848480225],"type":"Point"}
}