{
  "type": "Feature",
  "properties": {
    "addr:full":"31 Claremont Avenue Woking Surrey GU22 7SF",
    "addr:housenumber":"31",
    "addr:postcode":"gu22 7sf",
    "addr:street":"Claremont Avenue",
    "iso:country":"GB",
    "sg:address":"31 Claremont Avenue",
    "sg:city":"Woking",
    "sg:classifiers":[
        {
            "category":"Farming",
            "subcategory":"Nursery",
            "type":"Manufacturing & Wholesale Goods"
        }
    ],
    "sg:phone":"+44 1483 757507",
    "sg:postcode":"GU22 7SF",
    "sg:province":"Surrey",
    "sg:tags":[
        "creche"
    ],
    "wof:name":"Christopher Robin Day Nursery",
    "wof:placetype":"venue"
},
  "geometry": {"coordinates":[-0.561213,51.308411],"type":"Point"}
}