{
  "type": "Feature",
  "properties": {
    "iso:country":"GB",
    "sg:address":"105 Littlemoor Road",
    "sg:city":"Pudsey",
    "sg:classifiers":[
        {
            "category":"Travel",
            "subcategory":"Hotels & Motels",
            "type":"Entertainment"
        }
    ],
    "sg:phone":"+44 113 257 4397",
    "sg:postcode":"LS28 8AP",
    "sg:province":"West Yorkshire",
    "sg:tags":[
        "house",
        "guest"
    ],
    "wof:name":"Heatherlea House",
    "wof:placetype":"venue"
},
  "geometry": {"coordinates":[-1.657726,53.787102],"type":"Point"}
}