{
  "type": "Feature",
  "properties": {
    "addr:full":"Newark Mill, Newark Lane, Ripley Woking Surrey GU23 6DP",
    "addr:postcode":"gu23 6dp",
    "addr:street":"Newark;Newark Lane",
    "iso:country":"GB",
    "sg:address":"Newark Mill, Newark Lane, Ripley",
    "sg:city":"Woking",
    "sg:classifiers":[
        {
            "category":"Farming",
            "subcategory":"Livestock Farm",
            "type":"Manufacturing & Wholesale Goods"
        }
    ],
    "sg:phone":"+44 1483 224464",
    "sg:postcode":"GU23 6DP",
    "sg:province":"Surrey",
    "sg:tags":[
        "others"
    ],
    "wof:name":"Grayshott Farm Ltd.",
    "wof:placetype":"venue"
},
  "geometry": {"coordinates":[-0.4905689955,51.3010597229],"type":"Point"}
}