{
  "type": "Feature",
  "properties": {
    "addr:full":"509 Lordship Lane London Greater London SE22 8JY",
    "addr:housenumber":"509",
    "addr:postcode":"se22 8jy",
    "addr:street":"Lordship Lane",
    "iso:country":"GB",
    "sg:address":"509 Lordship Lane",
    "sg:city":"London",
    "sg:classifiers":[
        {
            "category":"Retail",
            "subcategory":"Veterinary Services",
            "type":"Services"
        }
    ],
    "sg:phone":"+44 20 8693 4677",
    "sg:postcode":"SE22 8JY",
    "sg:province":"Greater London",
    "sg:tags":[
        "surgeon"
    ],
    "wof:name":"Lomax & Partners",
    "wof:placetype":"venue"
},
  "geometry": {"coordinates":[-0.067845,51.443764],"type":"Point"}
}