{
  "type": "Feature",
  "properties": {
    "iso:country":"GB",
    "sg:address":"58 Argyle St South",
    "sg:city":"Birkenhead",
    "sg:classifiers":[
        {
            "category":"Coffee & Tea",
            "type":"Food & Drink"
        }
    ],
    "sg:phone":"+44 151 647 4210",
    "sg:postcode":"CH41 9BX",
    "sg:province":"Merseyside",
    "wof:name":"Gold Crest Food & Beverages Ltd.",
    "wof:placetype":"venue"
},
  "geometry": {"coordinates":[-3.023593,53.385105],"type":"Point"}
}