{
  "type": "Feature",
  "properties": {
    "iso:country":"GB",
    "sg:address":"2 Arthurs Court",
    "sg:city":"Burton-on-trent",
    "sg:classifiers":[
        {
            "category":"Professional",
            "subcategory":"Engineering",
            "type":"Services"
        }
    ],
    "sg:phone":"+44 1283 547694",
    "sg:postcode":"DE13 0GS",
    "sg:province":"Derbyshire",
    "sg:tags":[
        "contractor",
        "electrical",
        "engineer"
    ],
    "wof:name":"J R Electrical Services",
    "wof:placetype":"venue"
},
  "geometry": {"coordinates":[-1.626403,52.836903],"type":"Point"}
}