{
  "type": "Feature",
  "properties": {
    "addr:full":"27 Norfolk St Sunderland Tyne and Wear SR1 1EE",
    "addr:housenumber":"27",
    "addr:postcode":"sr1 1ee",
    "addr:street":"Norfolk St",
    "iso:country":"GB",
    "sg:address":"27 Norfolk St",
    "sg:city":"Sunderland",
    "sg:classifiers":[
        {
            "category":"Health Services",
            "subcategory":"Doctor",
            "type":"Services"
        }
    ],
    "sg:phone":"+44 191 565 3040",
    "sg:postcode":"SR1 1EE",
    "sg:province":"Tyne and Wear",
    "sg:tags":[
        "practitioners"
    ],
    "wof:name":"Nathan, J R",
    "wof:placetype":"venue"
},
  "geometry": {"coordinates":[-1.3772059679,54.9058876038],"type":"Point"}
}