{
  "type": "Feature",
  "properties": {
    "addr:full":"6 Old Bond St West End Hampshire W1X 3TA",
    "addr:housenumber":"6",
    "addr:postcode":"w1x 3ta",
    "addr:street":"Old Bond St",
    "iso:country":"GB",
    "sg:address":"6 Old Bond St",
    "sg:city":"West End",
    "sg:classifiers":[
        {
            "category":"Shopping",
            "subcategory":"Clothing, Apparel, & Fashions",
            "type":"Retail Goods"
        }
    ],
    "sg:phone":"+44 20 7499 8660",
    "sg:postcode":"W1X 3TA",
    "sg:province":"Hampshire",
    "sg:tags":[
        "shop"
    ],
    "wof:name":"A N A Trading & Takashimaya U K Ltd",
    "wof:placetype":"venue"
},
  "geometry": {"coordinates":[-0.1401789933,51.5084915161],"type":"Point"}
}