{
  "type": "Feature",
  "properties": {
    "addr:full":"Havenlea, New Pound, Wisborough Grn Billingshurst West Sussex RH14 0EJ",
    "addr:postcode":"rh14 0ej",
    "addr:street":"Havenlea;Wisborough Grn",
    "iso:country":"GB",
    "sg:address":"Havenlea, New Pound, Wisborough Grn",
    "sg:city":"Billingshurst",
    "sg:classifiers":[
        {
            "category":"Home & Garden",
            "subcategory":"Building Materials",
            "type":"Retail Goods"
        }
    ],
    "sg:postcode":"RH14 0EJ",
    "sg:province":"West Sussex",
    "sg:tags":[
        "fencing"
    ],
    "wof:name":"Philip Juniper",
    "wof:placetype":"venue"
},
  "geometry": {"coordinates":[-0.4524280131,51.0211830139],"type":"Point"}
}