{
  "type": "Feature",
  "properties": {
    "addr:full":"13 South Pde Bristol Gloucestershire BS37 4BB",
    "addr:housenumber":"13",
    "addr:postcode":"bs37 4bb",
    "addr:street":"South Pde",
    "iso:country":"GB",
    "sg:address":"13 South Pde",
    "sg:city":"Bristol",
    "sg:classifiers":[
        {
            "category":"Communications",
            "subcategory":"Film & Video Production",
            "type":"Services"
        }
    ],
    "sg:phone":"+44 1454 318247",
    "sg:postcode":"BS37 4BB",
    "sg:province":"Gloucestershire",
    "sg:tags":[
        "tv"
    ],
    "wof:name":"Granada Home Technology",
    "wof:placetype":"venue"
},
  "geometry": {"coordinates":[-2.548884,51.5625],"type":"Point"}
}