{
  "type": "Feature",
  "properties": {
    "addr:full":"Unit 3a V P Square, Storeys Bar Road Peterborough Cambridgeshire PE1 5YS",
    "addr:housenumber":"unit 3a",
    "addr:postcode":"pe1 5ys",
    "addr:street":"V P Square;Bar Road",
    "iso:country":"GB",
    "sg:address":"Unit 3a V P Square, Storeys Bar Road",
    "sg:city":"Peterborough",
    "sg:classifiers":[
        {
            "category":"Building & Trades",
            "subcategory":"Construction",
            "type":"Services"
        }
    ],
    "sg:phone":"+44 1733 315619",
    "sg:postcode":"PE1 5YS",
    "sg:province":"Cambridgeshire",
    "sg:tags":[
        "dry",
        "lining",
        "plasterers",
        "screeders"
    ],
    "wof:name":"Westwall Estates Ltd.",
    "wof:placetype":"venue"
},
  "geometry": {"coordinates":[-0.20674,52.577728],"type":"Point"}
}