{
  "type": "Feature",
  "properties": {
    "iso:country":"GB",
    "sg:address":"Abbeyfield House, 19 Marine Drive, Hest Bank",
    "sg:city":"Lancaster",
    "sg:classifiers":[
        {
            "category":"Organizations",
            "subcategory":"Community Association",
            "type":"Services"
        }
    ],
    "sg:phone":"+44 1524 823762",
    "sg:postcode":"LA2 6DY",
    "sg:province":"Lancashire",
    "sg:tags":[
        "society",
        "housing"
    ],
    "wof:name":"Abbeyfield Slyne With Hest Society",
    "wof:placetype":"venue"
},
  "geometry": {"coordinates":[-2.815158,54.090172],"type":"Point"}
}