{
  "type": "Feature",
  "properties": {
    "addr:full":"11 Church Street, Haxey Doncaster Lincolnshire DN9 2HY",
    "addr:housenumber":"11",
    "addr:postcode":"dn9 2hy",
    "addr:street":"Church Street",
    "iso:country":"GB",
    "sg:address":"11 Church Street, Haxey",
    "sg:city":"Doncaster",
    "sg:classifiers":[
        {
            "category":"Health Services",
            "subcategory":"Nursing And Care Facility",
            "type":"Services"
        }
    ],
    "sg:phone":"+44 1427 752862",
    "sg:postcode":"DN9 2HY",
    "sg:province":"Lincolnshire",
    "sg:tags":[
        "home"
    ],
    "wof:name":"Nicholas House Residential Nursing Home",
    "wof:placetype":"venue"
},
  "geometry": {"coordinates":[-0.846895,53.489986],"type":"Point"}
}