{
  "type": "Feature",
  "properties": {
    "addr:full":"Holland House, 1-5 Oakfield Sale Cheshire M33 6TT",
    "addr:housenumber":"1-5",
    "addr:postcode":"m33 6tt",
    "addr:street":"Oakfield Sale Cheshire",
    "iso:country":"GB",
    "sg:address":"Holland House, 1-5 Oakfield",
    "sg:city":"Sale",
    "sg:classifiers":[
        {
            "category":"Professional",
            "subcategory":"Accounting & Tax Preparation",
            "type":"Services"
        }
    ],
    "sg:phone":"+44 161 905 1616",
    "sg:postcode":"M33 6TT",
    "sg:province":"Cheshire",
    "sg:tags":[
        "accountant"
    ],
    "wof:name":"Harold Sharp Son & Gresty",
    "wof:placetype":"venue"
},
  "geometry": {"coordinates":[-2.329015,53.422649],"type":"Point"}
}