{
  "type": "Feature",
  "properties": {
    "addr:full":"93 Cato Street Birmingham West Midlands B7 4TS",
    "addr:housenumber":"93",
    "addr:postcode":"b7 4ts",
    "addr:street":"Cato Street",
    "iso:country":"GB",
    "sg:address":"93 Cato Street",
    "sg:city":"Birmingham",
    "sg:classifiers":[
        {
            "category":"Building & Trades",
            "subcategory":"Construction",
            "type":"Services"
        },
        {
            "category":"Manufacturing",
            "subcategory":"Building Materials",
            "type":"Manufacturing & Wholesale Goods"
        }
    ],
    "sg:phone":"+44 121 359 2623",
    "sg:postcode":"B7 4TS",
    "sg:province":"West Midlands",
    "sg:tags":[
        "fork",
        "equipment",
        "lift",
        "handling",
        "truck"
    ],
    "wof:name":"Abex Ltd",
    "wof:placetype":"venue"
},
  "geometry": {"coordinates":[-1.868677,52.491714],"type":"Point"}
}