{
  "type": "Feature",
  "properties": {
    "iso:country":"GB",
    "sg:address":"The Square",
    "sg:city":"Port Ellen",
    "sg:classifiers":[
        {
            "category":"Bars & Pubs",
            "type":"Food & Drink"
        }
    ],
    "sg:phone":"+44 1496 810330",
    "sg:postcode":"PA43 7JR",
    "sg:province":"Argyll and Bute",
    "sg:tags":[
        "pubs",
        "inn"
    ],
    "wof:name":"The Harbour Inn",
    "wof:placetype":"venue"
},
  "geometry": {"coordinates":[-6.288484,55.757504],"type":"Point"}
}