{
  "type": "Feature",
  "properties": {
    "iso:country":"GB",
    "sg:address":"Hatchgate Cottage, Steventon",
    "sg:city":"Basingstoke",
    "sg:classifiers":[
        {
            "category":"Bus Charters",
            "type":"Transportation"
        }
    ],
    "sg:phone":"+44 1256 397270",
    "sg:postcode":"RG25 3BJ",
    "sg:province":"Hampshire",
    "sg:tags":[
        "hire",
        "coach"
    ],
    "wof:name":"Steventon Transport Services Ltd.",
    "wof:placetype":"venue"
},
  "geometry": {"coordinates":[-1.220016,51.228638],"type":"Point"}
}