{
  "type": "Feature",
  "properties": {
    "addr:full":"68 Lancaster Road Blackpool Lancashire FY3 9ST",
    "addr:housenumber":"68",
    "addr:postcode":"fy3 9st",
    "addr:street":"Lancaster Road",
    "iso:country":"GB",
    "sg:address":"68 Lancaster Road",
    "sg:city":"Blackpool",
    "sg:classifiers":[
        {
            "category":"Professional",
            "subcategory":"Art Services",
            "type":"Services"
        }
    ],
    "sg:phone":"+44 1253 692340",
    "sg:postcode":"FY3 9ST",
    "sg:province":"Lancashire",
    "sg:tags":[
        "photographer"
    ],
    "wof:name":"Brian Jones",
    "wof:placetype":"venue"
},
  "geometry": {"coordinates":[-3.01338,53.807976],"type":"Point"}
}