{
  "type": "Feature",
  "properties": {
    "addr:full":"7 High Street Lutterworth Leicestershire LE17 4AT",
    "addr:housenumber":"7",
    "addr:postcode":"le17 4at",
    "addr:street":"High Street",
    "iso:country":"GB",
    "sg:address":"7 High Street",
    "sg:city":"Lutterworth",
    "sg:classifiers":[
        {
            "category":"Travel",
            "subcategory":"Travel Agent",
            "type":"Entertainment"
        }
    ],
    "sg:phone":"+44 1455 554042",
    "sg:postcode":"LE17 4AT",
    "sg:province":"Leicestershire",
    "sg:tags":[
        "agency",
        "activity"
    ],
    "wof:name":"MIDLANDS CO-OPERATIVE SOCIETY LTD",
    "wof:placetype":"venue"
},
  "geometry": {"coordinates":[-1.199769,52.455364],"type":"Point"}
}