{
  "type": "Feature",
  "properties": {
    "addr:full":"616 Hitchin Rd Luton Bedfordshire LU2 7UG",
    "addr:housenumber":"616",
    "addr:postcode":"lu2 7ug",
    "addr:street":"Hitchin Rd",
    "iso:country":"GB",
    "sg:address":"616 Hitchin Rd",
    "sg:city":"Luton",
    "sg:classifiers":[
        {
            "category":"Social Services",
            "type":"Services"
        }
    ],
    "sg:phone":"+44 1582 738235",
    "sg:postcode":"LU2 7UG",
    "sg:province":"Bedfordshire",
    "wof:name":"Stopsley Curry Centre",
    "wof:placetype":"venue"
},
  "geometry": {"coordinates":[-0.3981640041,51.9015884399],"type":"Point"}
}