{
  "type": "Feature",
  "properties": {
    "addr:full":"Lindisfarne Brentwood Essex CM15 0HB",
    "addr:postcode":"cm15 0hb",
    "iso:country":"GB",
    "sg:address":"Lindisfarne",
    "sg:city":"Brentwood",
    "sg:classifiers":[
        {
            "category":"Building & Trades",
            "subcategory":"Construction",
            "type":"Services"
        }
    ],
    "sg:phone":"+44 1277 821662",
    "sg:postcode":"CM15 0HB",
    "sg:province":"Essex",
    "sg:tags":[
        "builder"
    ],
    "wof:name":"Hyatt Building Services",
    "wof:placetype":"venue"
},
  "geometry": {"coordinates":[0.2848899961,51.6689987183],"type":"Point"}
}