{
  "type": "Feature",
  "properties": {
    "addr:full":"253 Hoxton St London Greater London N1 5LG",
    "addr:housenumber":"253",
    "addr:postcode":"n1 5lg",
    "addr:street":"Hoxton St",
    "iso:country":"GB",
    "sg:address":"253 Hoxton St",
    "sg:city":"London",
    "sg:classifiers":[
        {
            "category":"Cafe",
            "type":"Food & Drink"
        }
    ],
    "sg:phone":"+44 20 7739 4162",
    "sg:postcode":"N1 5LG",
    "sg:province":"Greater London",
    "sg:tags":[
        "tea",
        "room"
    ],
    "wof:name":"Laimeys",
    "wof:placetype":"venue"
},
  "geometry": {"coordinates":[-0.0802920014,51.5338897705],"type":"Point"}
}