{
  "type": "Feature",
  "properties": {
    "iso:country":"GB",
    "sg:address":"16 Appletree Close, Allerton",
    "sg:city":"Liverpool",
    "sg:classifiers":[
        {
            "category":"Professional",
            "subcategory":"Computer Services",
            "type":"Services"
        }
    ],
    "sg:postcode":"L18 9XN",
    "sg:province":"Merseyside",
    "sg:tags":[
        "information"
    ],
    "wof:name":"Imaco Ltd.",
    "wof:placetype":"venue"
},
  "geometry": {"coordinates":[-2.9021790028,53.3688850403],"type":"Point"}
}