{
  "type": "Feature",
  "properties": {
    "addr:full":"173 High Street Maldon Essex CM9 5BS",
    "addr:housenumber":"173",
    "addr:postcode":"cm9 5bs",
    "addr:street":"High Street",
    "iso:country":"GB",
    "sg:address":"173 High Street",
    "sg:city":"Maldon",
    "sg:classifiers":[
        {
            "category":"Social Services",
            "type":"Services"
        }
    ],
    "sg:phone":"+44 1621 843344",
    "sg:postcode":"CM9 5BS",
    "sg:province":"Essex",
    "sg:tags":[
        "disability"
    ],
    "wof:name":"East Anglian Mobility Ltd.",
    "wof:placetype":"venue"
},
  "geometry": {"coordinates":[0.684426,51.729683],"type":"Point"}
}