{
  "type": "Feature",
  "properties": {
    "addr:full":"6 Newfield Place Stourbridge West Midlands DY9 0FB",
    "addr:housenumber":"6",
    "addr:postcode":"dy9 0fb",
    "addr:street":"Newfield Place",
    "iso:country":"GB",
    "sg:address":"6 Newfield Place",
    "sg:city":"Stourbridge",
    "sg:classifiers":[
        {
            "category":"Professional",
            "subcategory":"Computer Services",
            "type":"Services"
        }
    ],
    "sg:postcode":"DY9 0FB",
    "sg:province":"West Midlands",
    "sg:tags":[
        "system",
        "software"
    ],
    "wof:name":"D I P S",
    "wof:placetype":"venue"
},
  "geometry": {"coordinates":[-2.145241,52.415672],"type":"Point"}
}