{
  "type": "Feature",
  "properties": {
    "addr:full":"59 Derby Road, Huyton Liverpool Merseyside L36 9UQ",
    "addr:housenumber":"59",
    "addr:postcode":"l36 9uq",
    "addr:street":"Derby Road",
    "iso:country":"GB",
    "sg:address":"59 Derby Road, Huyton",
    "sg:city":"Liverpool",
    "sg:classifiers":[
        {
            "category":"Shopping",
            "subcategory":"Gifts & Souvenirs",
            "type":"Retail Goods"
        }
    ],
    "sg:postcode":"L36 9UQ",
    "sg:province":"Merseyside",
    "sg:tags":[
        "poster",
        "card"
    ],
    "wof:name":"Carolyn E Parry",
    "wof:placetype":"venue"
},
  "geometry": {"coordinates":[-2.8390820026,53.4113197327],"type":"Point"}
}