{
  "type": "Feature",
  "properties": {
    "addr:full":"Green Lane Depot, Ecclesfield Sheffield South Yorkshire S35 9WY",
    "addr:postcode":"s35 9wy",
    "addr:street":"Green Lane",
    "iso:country":"GB",
    "sg:address":"Green Lane Depot, Ecclesfield",
    "sg:city":"Sheffield",
    "sg:classifiers":[
        {
            "category":"Freight",
            "type":"Transportation"
        },
        {
            "category":"Building & Trades",
            "subcategory":"Equipment Rental",
            "type":"Services"
        }
    ],
    "sg:phone":"+44 114 245 5757",
    "sg:postcode":"S35 9WY",
    "sg:province":"South Yorkshire",
    "sg:tags":[
        "haulage",
        "plant",
        "transport",
        "machinery",
        "road"
    ],
    "wof:name":"G Fisher Transport",
    "wof:placetype":"venue"
},
  "geometry": {"coordinates":[-1.4519549608,53.4402160645],"type":"Point"}
}