{
  "type": "Feature",
  "properties": {
    "addr:full":"70 Terminus Road Eastbourne East Sussex BN21 3LX",
    "addr:housenumber":"70",
    "addr:postcode":"bn21 3lx",
    "addr:street":"Terminus Road",
    "iso:country":"GB",
    "sg:address":"70 Terminus Road",
    "sg:city":"Eastbourne",
    "sg:classifiers":[
        {
            "category":"Banks & Credit Unions",
            "subcategory":"Financial Services",
            "type":"Services"
        }
    ],
    "sg:phone":"+44 1323 731049",
    "sg:postcode":"BN21 3LX",
    "sg:province":"East Sussex",
    "sg:tags":[
        "building",
        "society"
    ],
    "wof:name":"Yorkshire Building Society",
    "wof:placetype":"venue"
},
  "geometry": {"coordinates":[0.282429,50.768639],"type":"Point"}
}