{
  "type": "Feature",
  "properties": {
    "addr:full":"59 East Rd Bridport Dorset DT6 4AL",
    "addr:housenumber":"59",
    "addr:postcode":"dt6 4al",
    "addr:street":"East Rd",
    "iso:country":"GB",
    "sg:address":"59 East Rd",
    "sg:city":"Bridport",
    "sg:classifiers":[
        {
            "category":"Building & Trades",
            "subcategory":"Construction",
            "type":"Services"
        }
    ],
    "sg:phone":"+44 1308 456590",
    "sg:postcode":"DT6 4AL",
    "sg:province":"Dorset",
    "sg:tags":[
        "joiner",
        "carpenter"
    ],
    "wof:name":"D E Allum",
    "wof:placetype":"venue"
},
  "geometry": {"coordinates":[-2.743142,50.73497],"type":"Point"}
}