{
  "type": "Feature",
  "properties": {
    "addr:full":"Penylan Farm, Cwrt-yr-ala Road, Cyntwell Cardiff Cardiff CF5 5QS",
    "addr:postcode":"cf5 5qs",
    "addr:street":"Penylan;Cwrt-Yr-Ala Road Cyntwell",
    "iso:country":"GB",
    "sg:address":"Penylan Farm, Cwrt-yr-ala Road, Cyntwell",
    "sg:city":"Cardiff",
    "sg:classifiers":[
        {
            "category":"Farming",
            "subcategory":"Livestock Farm",
            "type":"Manufacturing & Wholesale Goods"
        }
    ],
    "sg:phone":"+44 29 2059 1524",
    "sg:postcode":"CF5 5QS",
    "sg:province":"Cardiff",
    "sg:tags":[
        "others"
    ],
    "wof:name":"R E David",
    "wof:placetype":"venue"
},
  "geometry": {"coordinates":[-3.253944,51.467941],"type":"Point"}
}