{
  "type": "Feature",
  "properties": {
    "addr:full":"163 Earls Court Rd Earl's Court Greater London SW5 9RF",
    "addr:housenumber":"163",
    "addr:postcode":"sw5 9rf",
    "addr:street":"Earls Court Rd Earl'S Court",
    "iso:country":"GB",
    "sg:address":"163 Earls Court Rd",
    "sg:city":"Earl's Court",
    "sg:classifiers":[
        {
            "category":"Banks & Credit Unions",
            "subcategory":"Bureau De Change",
            "type":"Services"
        }
    ],
    "sg:phone":"+44 20 7370 4049",
    "sg:postcode":"SW5 9RF",
    "sg:province":"Greater London",
    "wof:name":"Exchange International",
    "wof:placetype":"venue"
},
  "geometry": {"coordinates":[-0.193558,51.492744],"type":"Point"}
}