{
  "type": "Feature",
  "properties": {
    "iso:country":"GB",
    "sg:address":"C/o Griffith Williams & Co 36, High Street,",
    "sg:city":"Pwllheli",
    "sg:classifiers":[
        {
            "category":"Travel",
            "subcategory":"Travel Agent",
            "type":"Entertainment"
        }
    ],
    "sg:postcode":"LL53 5RT",
    "sg:province":"Gwynedd",
    "wof:name":"Spear Travels Ltd",
    "wof:placetype":"venue"
},
  "geometry": {"coordinates":[-4.41565,52.889801],"type":"Point"}
}