{
  "type": "Feature",
  "properties": {
    "iso:country":"GB",
    "sg:address":"11 John Street",
    "sg:city":"Royston",
    "sg:classifiers":[
        {
            "category":"Professional",
            "subcategory":"Computer Services",
            "type":"Services"
        }
    ],
    "sg:postcode":"SG8 9BE",
    "sg:province":"Bedfordshire",
    "sg:tags":[
        "system",
        "software"
    ],
    "wof:name":"A8 Ltd",
    "wof:placetype":"venue"
},
  "geometry": {"coordinates":[-0.023556,52.047333],"type":"Point"}
}