{
  "type": "Feature",
  "properties": {
    "addr:full":"Unit 15 Tyseley Industrial Estate, Seeleys Road Birmingham West Midlands B11 2LQ",
    "addr:housenumber":"unit 15",
    "addr:postcode":"b11 2lq",
    "addr:street":"Industrial Estate Seeleys Road",
    "iso:country":"GB",
    "sg:address":"Unit 15 Tyseley Industrial Estate, Seeleys Road",
    "sg:city":"Birmingham",
    "sg:classifiers":[
        {
            "category":"Home & Garden",
            "subcategory":"Building Materials",
            "type":"Retail Goods"
        }
    ],
    "sg:phone":"+44 121 708 0111",
    "sg:postcode":"B11 2LQ",
    "sg:province":"West Midlands",
    "sg:tags":[
        "furnishers",
        "bathroom",
        "planner"
    ],
    "wof:name":"Bathroom City Ltd.",
    "wof:placetype":"venue"
},
  "geometry": {"coordinates":[-1.854278,52.454506],"type":"Point"}
}