{
  "type": "Feature",
  "properties": {
    "addr:full":"23 Eliot Street Bootle Merseyside L20 4PD",
    "addr:housenumber":"23",
    "addr:postcode":"l20 4pd",
    "addr:street":"Eliot Street",
    "iso:country":"GB",
    "sg:address":"23 Eliot Street",
    "sg:city":"Bootle",
    "sg:phone":"+44 151 922 3243",
    "sg:postcode":"L20 4PD",
    "sg:province":"Merseyside",
    "wof:name":"Engineering Plastic Services",
    "wof:placetype":"venue"
},
  "geometry": {"coordinates":[-3.0009410381,53.4603118896],"type":"Point"}
}