{
  "type": "Feature",
  "properties": {
    "iso:country":"GB",
    "sg:address":"4 Bramble Street",
    "sg:city":"Derby",
    "sg:classifiers":[
        {
            "category":"Real Estate",
            "subcategory":"Architect",
            "type":"Services"
        }
    ],
    "sg:phone":"+44 1332 340707",
    "sg:postcode":"DE1 1HU",
    "sg:province":"Derbyshire",
    "wof:name":"Flanders & Gilbert",
    "wof:placetype":"venue"
},
  "geometry": {"coordinates":[-1.481537,52.92197],"type":"Point"}
}