{
  "type": "Feature",
  "properties": {
    "iso:country":"GB",
    "sg:address":"21 Fairmile Drive",
    "sg:city":"Sunderland",
    "sg:classifiers":[
        {
            "category":"Building & Trades",
            "subcategory":"Construction",
            "type":"Services"
        }
    ],
    "sg:postcode":"SR3 2XJ",
    "sg:province":"Tyne and Wear",
    "sg:tags":[
        "tiling",
        "contractor"
    ],
    "wof:name":"Classic Plastering",
    "wof:placetype":"venue"
},
  "geometry": {"coordinates":[-1.404761,54.861195],"type":"Point"}
}