{
  "type": "Feature",
  "properties": {
    "addr:full":"17-23 Lansdowne Lane Charlton Greater London SE7 8TQ",
    "addr:housenumber":"17-23",
    "addr:postcode":"se7 8tq",
    "addr:street":"Lansdowne Lane",
    "iso:country":"GB",
    "sg:address":"17-23 Lansdowne Lane",
    "sg:city":"Charlton",
    "sg:classifiers":[
        {
            "category":"Personal",
            "type":"Services"
        }
    ],
    "sg:phone":"+44 20 8858 6041",
    "sg:postcode":"SE7 8TQ",
    "sg:province":"Greater London",
    "sg:tags":[
        "delivery"
    ],
    "wof:name":"Royal Mail",
    "wof:placetype":"venue"
},
  "geometry": {"coordinates":[0.0375339985,51.4827651978],"type":"Point"}
}