{
  "type": "Feature",
  "properties": {
    "iso:country":"GB",
    "sg:address":"Old Horse Ford, High Street",
    "sg:city":"Oxford",
    "sg:classifiers":[
        {
            "category":"Recreation",
            "subcategory":"Boat Charter",
            "type":"Entertainment"
        },
        {
            "category":"Recreation",
            "subcategory":"Sailing Club",
            "type":"Entertainment"
        }
    ],
    "sg:phone":"+44 1865 761586",
    "sg:postcode":"OX1 4AX",
    "sg:province":"Oxfordshire",
    "sg:tags":[
        "excursion"
    ],
    "wof:name":"C Howard & Son",
    "wof:placetype":"venue"
},
  "geometry": {"coordinates":[-1.259489,51.756207],"type":"Point"}
}