{
  "type": "Feature",
  "properties": {
    "addr:full":"Park Gate, Stourbridge Road, Wolverley Kidderminster Staffordshire DY10 3PT",
    "addr:postcode":"dy10 3pt",
    "addr:street":"Park Gate Stourbridge Road",
    "iso:country":"GB",
    "sg:address":"Park Gate, Stourbridge Road, Wolverley",
    "sg:city":"Kidderminster",
    "sg:classifiers":[
        {
            "category":"Building & Trades",
            "subcategory":"Construction",
            "type":"Services"
        }
    ],
    "sg:phone":"+44 1562 851290",
    "sg:postcode":"DY10 3PT",
    "sg:province":"Staffordshire",
    "sg:tags":[
        "furnace"
    ],
    "wof:name":"Farr Furnaces",
    "wof:placetype":"venue"
},
  "geometry": {"coordinates":[-2.221325,52.405472],"type":"Point"}
}