{
  "type": "Feature",
  "properties": {
    "addr:full":"41 Ashbury Dr Camberley Hampshire GU17 9HH",
    "addr:housenumber":"41",
    "addr:postcode":"gu17 9hh",
    "addr:street":"Ashbury Dr",
    "iso:country":"GB",
    "sg:address":"41 Ashbury Dr",
    "sg:city":"Camberley",
    "sg:classifiers":[
        {
            "category":"Building & Trades",
            "subcategory":"Construction",
            "type":"Services"
        }
    ],
    "sg:phone":"+44 1276 33176",
    "sg:postcode":"GU17 9HH",
    "sg:province":"Hampshire",
    "sg:tags":[
        "builder"
    ],
    "wof:name":"Boyd-Phillips",
    "wof:placetype":"venue"
},
  "geometry": {"coordinates":[-0.764005,51.316483],"type":"Point"}
}