{
  "type": "Feature",
  "properties": {
    "addr:full":"32 Trevethick Street Merthyr Tydfil Merthyr Tydfil CF47 0HX",
    "addr:housenumber":"32",
    "addr:postcode":"cf47 0hx",
    "addr:street":"Trevethick Street",
    "iso:country":"GB",
    "sg:address":"32 Trevethick Street",
    "sg:city":"Merthyr Tydfil",
    "sg:classifiers":[
        {
            "category":"Retail",
            "subcategory":"Auto Repair",
            "type":"Services"
        }
    ],
    "sg:postcode":"CF47 0HX",
    "sg:province":"Merthyr Tydfil",
    "sg:tags":[
        "engine",
        "car",
        "specialist"
    ],
    "wof:name":"Mobile Total Tune",
    "wof:placetype":"venue"
},
  "geometry": {"coordinates":[-3.372917,51.752441],"type":"Point"}
}