{
  "type": "Feature",
  "properties": {
    "iso:country":"GB",
    "sg:address":"21 Grafton St",
    "sg:city":"West End",
    "sg:classifiers":[
        {
            "category":"Professional",
            "subcategory":"Management & Consulting",
            "type":"Services"
        }
    ],
    "sg:phone":"+44 20 7493 6363",
    "sg:postcode":"W1X 3LD",
    "sg:province":"Hampshire",
    "sg:tags":[
        "consultant"
    ],
    "wof:name":"Telecoms Co Ltd The",
    "wof:placetype":"venue"
},
  "geometry": {"coordinates":[-0.1433829963,51.5098266602],"type":"Point"}
}