{
  "type": "Feature",
  "properties": {
    "iso:country":"GB",
    "sg:address":"Beech Av",
    "sg:city":"Nottingham",
    "sg:classifiers":[
        {
            "category":"Shopping",
            "subcategory":"Crafts & Fabrics",
            "type":"Retail Goods"
        }
    ],
    "sg:phone":"+44 115 978 9351",
    "sg:postcode":"NG7 7LU",
    "sg:province":"Nottinghamshire",
    "sg:tags":[
        "lace"
    ],
    "wof:name":"Birkins Ltd",
    "wof:placetype":"venue"
},
  "geometry": {"coordinates":[-1.1654980183,52.9721603394],"type":"Point"}
}