{
  "type": "Feature",
  "properties": {
    "addr:full":"429 Wanstead Park Road Ilford Essex IG1 3TT",
    "addr:housenumber":"429",
    "addr:postcode":"ig1 3tt",
    "addr:street":"Wanstead Park Road",
    "iso:country":"GB",
    "sg:address":"429 Wanstead Park Road",
    "sg:city":"Ilford",
    "sg:classifiers":[
        {
            "category":"Government",
            "subcategory":"Office",
            "type":"Public Place"
        }
    ],
    "sg:phone":"+44 20 8554 3473",
    "sg:postcode":"IG1 3TT",
    "sg:province":"Essex",
    "sg:tags":[
        "education",
        "agency",
        "authority"
    ],
    "wof:name":"The Scout Association",
    "wof:placetype":"venue"
},
  "geometry": {"coordinates":[0.0523229986,51.5696372986],"type":"Point"}
}