{
  "type": "Feature",
  "properties": {
    "addr:full":"163 Victoria Road Horley Surrey RH6 7AR",
    "addr:housenumber":"163",
    "addr:postcode":"rh6 7ar",
    "addr:street":"Victoria Road",
    "iso:country":"GB",
    "sg:address":"163 Victoria Road",
    "sg:city":"Horley",
    "sg:classifiers":[
        {
            "category":"Retail",
            "subcategory":"Auto Rental",
            "type":"Services"
        },
        {
            "category":"Autos & Motor Vehicles",
            "subcategory":"Motorcycle Sales",
            "type":"Retail Goods"
        }
    ],
    "sg:phone":"+44 1293 436464",
    "sg:postcode":"RH6 7AR",
    "sg:province":"Surrey",
    "sg:tags":[
        "chauffeur",
        "driven",
        "hire",
        "car"
    ],
    "wof:name":"Voyager Travel",
    "wof:placetype":"venue"
},
  "geometry": {"coordinates":[-0.169226,51.173588],"type":"Point"}
}