{
  "type": "Feature",
  "properties": {
    "iso:country":"GB",
    "sg:address":"34 Gordon Road",
    "sg:city":"Blackwood",
    "sg:classifiers":[
        {
            "category":"Personal",
            "subcategory":"Barber",
            "type":"Services"
        }
    ],
    "sg:postcode":"NP12 1DG",
    "sg:province":"Caerphilly",
    "sg:tags":[
        "men's",
        "hairdresser"
    ],
    "wof:name":"Off the Top",
    "wof:placetype":"venue"
},
  "geometry": {"coordinates":[-3.195938,51.663879],"type":"Point"}
}