{
  "type": "Feature",
  "properties": {
    "addr:full":"2 Saville Road Industrial Estate, Westwood Peterborough Cambridgeshire PE3 7PR",
    "addr:housenumber":"2",
    "addr:postcode":"pe3 7pr",
    "addr:street":"Saville Road Industrial Estate",
    "iso:country":"GB",
    "sg:address":"2 Saville Road Industrial Estate, Westwood",
    "sg:city":"Peterborough",
    "sg:classifiers":[
        {
            "category":"Autos & Motor Vehicles",
            "subcategory":"Auto Supplies",
            "type":"Retail Goods"
        }
    ],
    "sg:phone":"+44 1733 260494",
    "sg:postcode":"PE3 7PR",
    "sg:province":"Cambridgeshire",
    "sg:tags":[
        "tyre"
    ],
    "wof:name":"Tom Russo Tyre & Exhaust Centre",
    "wof:placetype":"venue"
},
  "geometry": {"coordinates":[-0.2647289932,52.5844535828],"type":"Point"}
}