{
  "type": "Feature",
  "properties": {
    "iso:country":"GB",
    "sg:address":"Unit 4, Quicksave Precinct, Boundary Road",
    "sg:city":"St Helens",
    "sg:classifiers":[
        {
            "category":"Shopping",
            "subcategory":"Baby Store",
            "type":"Retail Goods"
        }
    ],
    "sg:phone":"+44 1744 733200",
    "sg:postcode":"WA10 2PX",
    "sg:province":"Merseyside",
    "sg:tags":[
        "babywear",
        "childrens"
    ],
    "wof:name":"Ethel Austin Ltd.",
    "wof:placetype":"venue"
},
  "geometry": {"coordinates":[-2.738868,53.451687],"type":"Point"}
}