{
  "type": "Feature",
  "properties": {
    "addr:full":"Valley View, Newton In Cartmel Grange-over-sands Cumbria LA11 6JQ",
    "addr:postcode":"la11 6jq",
    "iso:country":"GB",
    "sg:address":"Valley View, Newton In Cartmel",
    "sg:city":"Grange-over-sands",
    "sg:classifiers":[
        {
            "category":"Transit Center",
            "subcategory":"Passenger",
            "type":"Transportation"
        },
        {
            "category":"Retail",
            "subcategory":"Pet Boarding",
            "type":"Services"
        }
    ],
    "sg:phone":"+44 15395 31263",
    "sg:postcode":"LA11 6JQ",
    "sg:province":"Cumbria",
    "sg:tags":[
        "kennel",
        "catteries"
    ],
    "wof:name":"Kilncroft Boarding Kennels and Catterey",
    "wof:placetype":"venue"
},
  "geometry": {"coordinates":[-2.92164,54.184158],"type":"Point"}
}