{
  "type": "Feature",
  "properties": {
    "iso:country":"GB",
    "sg:address":"27 Upper Bond St",
    "sg:city":"Hinckley",
    "sg:classifiers":[
        {
            "category":"Social Services",
            "type":"Services"
        }
    ],
    "sg:phone":"+44 1455 636964",
    "sg:postcode":"LE10 1RH",
    "sg:province":"Leicestershire",
    "wof:name":"Social Services Department",
    "wof:placetype":"venue"
},
  "geometry": {"coordinates":[-1.3734430075,52.5444221497],"type":"Point"}
}