{
  "type": "Feature",
  "properties": {
    "iso:country":"GB",
    "sg:address":"Dene Ho, 17 Dene Vale",
    "sg:city":"Brighton",
    "sg:classifiers":[
        {
            "category":"Manufacturing",
            "subcategory":"Electronics",
            "type":"Manufacturing & Wholesale Goods"
        }
    ],
    "sg:phone":"+44 1273 555556",
    "sg:postcode":"BN1 5ED",
    "sg:province":"East Sussex",
    "sg:tags":[
        "control",
        "component",
        "-",
        "electronic"
    ],
    "wof:name":"DGR Technologies (Soldering Materials) Ltd",
    "wof:placetype":"venue"
},
  "geometry": {"coordinates":[-0.15896,50.857868],"type":"Point"}
}