{
  "type": "Feature",
  "properties": {
    "iso:country":"GB",
    "sg:address":"Bloemfontein Street",
    "sg:city":"Barnsley",
    "sg:classifiers":[
        {
            "category":"Autos & Motor Vehicles",
            "subcategory":"Automobile Sales",
            "type":"Retail Goods"
        }
    ],
    "sg:postcode":"S72 8UN",
    "sg:province":"South Yorkshire",
    "sg:tags":[
        "car",
        "specialist",
        "sales",
        "classic"
    ],
    "wof:name":"C H R Classic Cars",
    "wof:placetype":"venue"
},
  "geometry": {"coordinates":[-1.4199370146,53.5757522583],"type":"Point"}
}