{
  "type": "Feature",
  "properties": {
    "addr:full":"42 Cotwell Avenue Waterlooville Hampshire PO8 9AW",
    "addr:housenumber":"42",
    "addr:postcode":"po8 9aw",
    "addr:street":"Cotwell Avenue",
    "iso:country":"GB",
    "sg:address":"42 Cotwell Avenue",
    "sg:city":"Waterlooville",
    "sg:classifiers":[
        {
            "category":"Building & Trades",
            "subcategory":"Cleaning & Sanitation",
            "type":"Services"
        }
    ],
    "sg:postcode":"PO8 9AW",
    "sg:province":"Hampshire",
    "sg:tags":[
        "commercial"
    ],
    "wof:name":"J R Cleaning",
    "wof:placetype":"venue"
},
  "geometry": {"coordinates":[-1.009927,50.901161],"type":"Point"}
}