{
  "type": "Feature",
  "properties": {
    "addr:full":"21 Hedgerows, Singleton Ashford Kent TN23 5WL",
    "addr:housenumber":"21",
    "addr:postcode":"tn23 5wl",
    "addr:street":"Hedgerows Singleton",
    "iso:country":"GB",
    "sg:address":"21 Hedgerows, Singleton",
    "sg:city":"Ashford",
    "sg:classifiers":[
        {
            "category":"Retail",
            "subcategory":"Driving School",
            "type":"Services"
        }
    ],
    "sg:postcode":"TN23 5WL",
    "sg:province":"Kent",
    "wof:name":"D F S School of Motoring",
    "wof:placetype":"venue"
},
  "geometry": {"coordinates":[0.8415510058,51.1359291077],"type":"Point"}
}