{
  "type": "Feature",
  "properties": {
    "addr:full":"Crossing House, Abererch Road Pwllheli Gwynedd LL53 5YU",
    "addr:postcode":"ll53 5yu",
    "addr:street":"Abererch Road",
    "iso:country":"GB",
    "sg:address":"Crossing House, Abererch Road",
    "sg:city":"Pwllheli",
    "sg:classifiers":[
        {
            "category":"Building & Trades",
            "subcategory":"Plumbing",
            "type":"Services"
        }
    ],
    "sg:phone":"+44 1758 613220",
    "sg:postcode":"LL53 5YU",
    "sg:province":"Gwynedd",
    "sg:tags":[
        "plumber",
        "heating"
    ],
    "wof:name":"E J Jones",
    "wof:placetype":"venue"
},
  "geometry": {"coordinates":[-4.4030561447,52.8935317993],"type":"Point"}
}