{
  "type": "Feature",
  "properties": {
    "iso:country":"GB",
    "sg:address":"56 Green Hill Road",
    "sg:city":"Leeds",
    "sg:classifiers":[
        {
            "category":"Professional",
            "subcategory":"Engineering",
            "type":"Services"
        },
        {
            "category":"Building & Trades",
            "subcategory":"Construction",
            "type":"Services"
        }
    ],
    "sg:phone":"+44 113 279 3461",
    "sg:postcode":"LS12 3QA",
    "sg:province":"West Yorkshire",
    "sg:tags":[
        "builder",
        "contractor",
        "electrical",
        "engineer"
    ],
    "wof:name":"M Cosgrove",
    "wof:placetype":"venue"
},
  "geometry": {"coordinates":[-1.613764,53.803383],"type":"Point"}
}