{
  "type": "Feature",
  "properties": {
    "addr:full":"9 High Street Passage Ely Cambridgeshire CB7 4NB",
    "addr:housenumber":"9",
    "addr:postcode":"cb7 4nb",
    "addr:street":"High Street Passage Ely",
    "iso:country":"GB",
    "sg:address":"9 High Street Passage",
    "sg:city":"Ely",
    "sg:classifiers":[
        {
            "category":"Shopping",
            "subcategory":"Books",
            "type":"Retail Goods"
        }
    ],
    "sg:phone":"+44 1353 669759",
    "sg:postcode":"CB7 4NB",
    "sg:province":"Cambridgeshire",
    "sg:tags":[
        "bookseller",
        "retailer"
    ],
    "wof:name":"Burrows Bookshop",
    "wof:placetype":"venue"
},
  "geometry": {"coordinates":[0.2651199996,52.3998603821],"type":"Point"}
}