{
  "type": "Feature",
  "properties": {
    "iso:country":"GB",
    "sg:address":"Westminster Buildings, Theatre Square",
    "sg:city":"Nottingham",
    "sg:classifiers":[
        {
            "category":"Professional",
            "subcategory":"Accounting & Tax Preparation",
            "type":"Services"
        }
    ],
    "sg:phone":"+44 115 941 7517",
    "sg:postcode":"NG1 6LG",
    "sg:province":"Nottinghamshire",
    "sg:tags":[
        "accountant",
        "activity"
    ],
    "wof:name":"F C R Moule & Co",
    "wof:placetype":"venue"
},
  "geometry": {"coordinates":[-1.1439239979,52.9492263794],"type":"Point"}
}