{
  "type": "Feature",
  "properties": {
    "iso:country":"GB",
    "sg:address":"6 Duke Street, Penn Fields",
    "sg:city":"Wolverhampton",
    "sg:classifiers":[
        {
            "category":"Home & Garden",
            "subcategory":"Household Appliances",
            "type":"Retail Goods"
        }
    ],
    "sg:phone":"+44 1902 345254",
    "sg:postcode":"WV3 7DT",
    "sg:province":"Staffordshire",
    "sg:tags":[
        "electrical"
    ],
    "wof:name":"E G P Domestic Appliances",
    "wof:placetype":"venue"
},
  "geometry": {"coordinates":[-2.146406889,52.5712547302],"type":"Point"}
}