{
  "type": "Feature",
  "properties": {
    "addr:full":"27 Tan Bank Telford Shropshire TF1 1HJ",
    "addr:housenumber":"27",
    "addr:postcode":"tf1 1hj",
    "addr:street":"Tan Bank",
    "iso:country":"GB",
    "sg:address":"27 Tan Bank",
    "sg:city":"Telford",
    "sg:classifiers":[
        {
            "category":"Home & Garden",
            "subcategory":"Hardware",
            "type":"Retail Goods"
        }
    ],
    "sg:phone":"+44 1952 240505",
    "sg:postcode":"TF1 1HJ",
    "sg:province":"Shropshire",
    "sg:tags":[
        "retailer",
        "lighting"
    ],
    "wof:name":"Wrekin Lights",
    "wof:placetype":"venue"
},
  "geometry": {"coordinates":[-2.5175418854,52.6995544434],"type":"Point"}
}