{
  "type": "Feature",
  "properties": {
    "addr:full":"Chell Road Stafford Staffordshire ST16 2TF",
    "addr:postcode":"st16 2tf",
    "addr:street":"Chell Road",
    "iso:country":"GB",
    "sg:address":"Chell Road",
    "sg:city":"Stafford",
    "sg:classifiers":[
        {
            "category":"Food & Beverages",
            "subcategory":"Supermarket",
            "type":"Retail Goods"
        }
    ],
    "sg:phone":"+44 1785 225711",
    "sg:postcode":"ST16 2TF",
    "sg:province":"Staffordshire",
    "wof:name":"Sainsbury's Supermarkets Ltd.",
    "wof:placetype":"venue"
},
  "geometry": {"coordinates":[-2.119494,52.80909],"type":"Point"}
}