{
  "type": "Feature",
  "properties": {
    "addr:full":"Netherfield Mills, Guiseley Leeds West Yorkshire LS20 9PA",
    "addr:postcode":"ls20 9pa",
    "addr:street":"West",
    "iso:country":"GB",
    "sg:address":"Netherfield Mills, Guiseley",
    "sg:city":"Leeds",
    "sg:classifiers":[
        {
            "category":"Shopping",
            "subcategory":"Clothing, Apparel, & Fashions",
            "type":"Retail Goods"
        },
        {
            "category":"Manufacturing",
            "subcategory":"Textiles",
            "type":"Manufacturing & Wholesale Goods"
        }
    ],
    "sg:phone":"+44 1943 873181",
    "sg:postcode":"LS20 9PA",
    "sg:province":"West Yorkshire",
    "sg:tags":[
        "clothing",
        "fabric",
        "manufacturer"
    ],
    "sg:website":"http://www.moon.co.uk",
    "wof:name":"Abraham Moon & Sons Ltd",
    "wof:placetype":"venue"
},
  "geometry": {"coordinates":[-1.7138589621,53.8759536743],"type":"Point"}
}