{
  "type": "Feature",
  "properties": {
    "addr:full":"83 Cherry Orchard Road, East Croydon Croydon Surrey CR0 6BE",
    "addr:housenumber":"83",
    "addr:postcode":"cr0 6be",
    "addr:street":"Cherry Orchard Road East",
    "iso:country":"GB",
    "sg:address":"83 Cherry Orchard Road, East Croydon",
    "sg:city":"Croydon",
    "sg:classifiers":[
        {
            "category":"Retail",
            "subcategory":"Auto Rental",
            "type":"Services"
        }
    ],
    "sg:phone":"+44 20 8681 2885",
    "sg:postcode":"CR0 6BE",
    "sg:province":"Surrey",
    "sg:tags":[
        "car"
    ],
    "wof:name":"The Garage Car Rental",
    "wof:placetype":"venue"
},
  "geometry": {"coordinates":[-0.090168,51.378551],"type":"Point"}
}