{
  "type": "Feature",
  "properties": {
    "addr:full":"Balvonie Conference Centre, Halketburn Road Skelmorlie North Ayrshire PA17 5BP",
    "addr:postcode":"pa17 5bp",
    "addr:street":"Halketburn Road",
    "iso:country":"GB",
    "sg:address":"Balvonie Conference Centre, Halketburn Road",
    "sg:city":"Skelmorlie",
    "sg:classifiers":[
        {
            "category":"Community Center",
            "type":"Public Place"
        }
    ],
    "sg:phone":"+44 1475 520122",
    "sg:postcode":"PA17 5BP",
    "sg:province":"North Ayrshire",
    "sg:tags":[
        "conference",
        "room",
        "centre"
    ],
    "wof:name":"The Salvation Army",
    "wof:placetype":"venue"
},
  "geometry": {"coordinates":[-4.889642,55.856186],"type":"Point"}
}