{
  "type": "Feature",
  "properties": {
    "iso:country":"GB",
    "sg:address":"6 Grove Road",
    "sg:city":"Bury St Edmunds",
    "sg:classifiers":[
        {
            "category":"Travel",
            "subcategory":"Hostel",
            "type":"Entertainment"
        }
    ],
    "sg:phone":"+44 1284 760945",
    "sg:postcode":"IP33 3BE",
    "sg:province":"Suffolk",
    "wof:name":"St.Matthew Housing",
    "wof:placetype":"venue"
},
  "geometry": {"coordinates":[0.7029569745,52.2486457825],"type":"Point"}
}