{
  "type": "Feature",
  "properties": {
    "iso:country":"GB",
    "sg:address":"Charmwood Paddock Clo, Newlands Farm Cusworth",
    "sg:city":"Doncaster",
    "sg:classifiers":[
        {
            "category":"Professional",
            "type":"Services"
        }
    ],
    "sg:postcode":"DN5 8JD",
    "sg:province":"South Yorkshire",
    "sg:tags":[
        "interior",
        "furnishers",
        "designer"
    ],
    "wof:name":"Wooll,Christina,",
    "wof:placetype":"venue"
},
  "geometry": {"coordinates":[-1.16481,53.533619],"type":"Point"}
}