{
  "type": "Feature",
  "properties": {
    "addr:full":"11 Mowll St Brixton Greater London SW9 6BG",
    "addr:housenumber":"11",
    "addr:postcode":"sw9 6bg",
    "addr:street":"Mowll St",
    "iso:country":"GB",
    "sg:address":"11 Mowll St",
    "sg:city":"Brixton",
    "sg:classifiers":[
        {
            "category":"Professional",
            "subcategory":"Business Services",
            "type":"Services"
        }
    ],
    "sg:phone":"+44 20 7582 0324",
    "sg:postcode":"SW9 6BG",
    "sg:province":"Greater London",
    "sg:tags":[
        "accomodation"
    ],
    "wof:name":"The Co-op Centre",
    "wof:placetype":"venue"
},
  "geometry": {"coordinates":[-0.109363,51.476166],"type":"Point"}
}