{
  "type": "Feature",
  "properties": {
    "iso:country":"GB",
    "sg:address":"4 Hanworth Clo",
    "sg:city":"Luton",
    "sg:classifiers":[
        {
            "category":"Manufacturing",
            "subcategory":"Petroleum Products",
            "type":"Manufacturing & Wholesale Goods"
        }
    ],
    "sg:phone":"+44 1582 560073",
    "sg:postcode":"LU2 7ED",
    "sg:province":"Bedfordshire",
    "sg:tags":[
        "double",
        "glazing"
    ],
    "wof:name":"Apex UPVC Specialist",
    "wof:placetype":"venue"
},
  "geometry": {"coordinates":[-0.4217680097,51.9170608521],"type":"Point"}
}