{
  "type": "Feature",
  "properties": {
    "addr:full":"53 Market Pl Chippenham Wiltshire SN15 3HU",
    "addr:housenumber":"53",
    "addr:postcode":"sn15 3hu",
    "addr:street":"Market Pl",
    "iso:country":"GB",
    "sg:address":"53 Market Pl",
    "sg:city":"Chippenham",
    "sg:classifiers":[
        {
            "category":"Shopping",
            "subcategory":"Clothing, Apparel, & Fashions",
            "type":"Retail Goods"
        }
    ],
    "sg:phone":"+44 1249 652154",
    "sg:postcode":"SN15 3HU",
    "sg:province":"Wiltshire",
    "sg:tags":[
        "ladieswear"
    ],
    "wof:name":"Jenny Emms",
    "wof:placetype":"venue"
},
  "geometry": {"coordinates":[-2.114562,51.458263],"type":"Point"}
}