{
  "type": "Feature",
  "properties": {
    "iso:country":"GB",
    "sg:address":"53 Market Pl",
    "sg:city":"Chippenham",
    "sg:classifiers":[
        {
            "category":"Shopping",
            "subcategory":"Clothing, Apparel, & Fashions",
            "type":"Retail Goods"
        }
    ],
    "sg:phone":"+44 1249 652154",
    "sg:postcode":"SN15 3HU",
    "sg:province":"Wiltshire",
    "sg:tags":[
        "ladieswear"
    ],
    "wof:name":"Jenny Emms",
    "wof:placetype":"venue"
},
  "geometry": {"coordinates":[-2.114562,51.458263],"type":"Point"}
}