{
  "type": "Feature",
  "properties": {
    "iso:country":"GB",
    "sg:address":"Victoria Crescent",
    "sg:city":"Burton-on-trent",
    "sg:classifiers":[
        {
            "category":"Shopping",
            "subcategory":"Pets & Pet Supplies",
            "type":"Retail Goods"
        }
    ],
    "sg:phone":"+44 1283 537581",
    "sg:postcode":"DE14 2QF",
    "sg:province":"Derbyshire",
    "sg:tags":[
        "food"
    ],
    "wof:name":"Thackers Pet Products Ltd.",
    "wof:placetype":"venue"
},
  "geometry": {"coordinates":[-1.640109,52.815796],"type":"Point"}
}