{
  "type": "Feature",
  "properties": {
    "addr:full":"Unit B19 Pemberton Business Cent, Re, Richmond Hill Pemberton Wigan Lancashire WN5 8AA",
    "addr:housenumber":"b19",
    "addr:postcode":"wn5 8aa",
    "addr:street":"Pemberton",
    "iso:country":"GB",
    "sg:address":"Unit B19 Pemberton Business Cent, Re, Richmond Hill Pemberton",
    "sg:city":"Wigan",
    "sg:classifiers":[
        {
            "category":"Professional",
            "subcategory":"Detective & Security Services",
            "type":"Services"
        }
    ],
    "sg:phone":"+44 1942 216515",
    "sg:postcode":"WN5 8AA",
    "sg:province":"Lancashire",
    "wof:name":"Identislot Ltd.",
    "wof:placetype":"venue"
},
  "geometry": {"coordinates":[-2.6803500652,53.5366592407],"type":"Point"}
}