{
  "type": "Feature",
  "properties": {
    "addr:full":"Trinity Road Library, Old Market Bristol City of Bristol BS2 0NW",
    "addr:postcode":"bs2 0nw",
    "addr:street":"Trinity",
    "iso:country":"GB",
    "sg:address":"Trinity Road Library, Old Market",
    "sg:city":"Bristol",
    "sg:classifiers":[
        {
            "category":"Professional",
            "subcategory":"Art Services",
            "type":"Services"
        }
    ],
    "sg:postcode":"BS2 0NW",
    "sg:province":"City of Bristol",
    "sg:tags":[
        "consultant",
        "design"
    ],
    "wof:name":"Print Project Limited (The)",
    "wof:placetype":"venue"
},
  "geometry": {"coordinates":[-2.5766289234,51.4582443237],"type":"Point"}
}