{
  "type": "Feature",
  "properties": {
    "addr:full":"Bridgewell House Woking Surrey GU22 7SF",
    "addr:postcode":"gu22 7sf",
    "iso:country":"GB",
    "sg:address":"Bridgewell House",
    "sg:city":"Woking",
    "sg:classifiers":[
        {
            "category":"Health Services",
            "subcategory":"Clinic",
            "type":"Services"
        },
        {
            "category":"Government",
            "subcategory":"Office",
            "type":"Public Place"
        }
    ],
    "sg:phone":"+44 1483 756318",
    "sg:postcode":"GU22 7SF",
    "sg:province":"Surrey",
    "sg:tags":[
        "nh",
        "project",
        "gov",
        "community"
    ],
    "wof:name":"Woking Community Mental Health Team",
    "wof:placetype":"venue"
},
  "geometry": {"coordinates":[-0.56112,51.308479],"type":"Point"}
}