{
  "type": "Feature",
  "properties": {
    "addr:full":"Unit 8 Heath Industrial Park, Heath Street Smethwick West Midlands B66 2QY",
    "addr:housenumber":"unit 8",
    "addr:postcode":"b66 2qy",
    "addr:street":"Heath Industrial Park Heath Street",
    "iso:country":"GB",
    "sg:address":"Unit 8 Heath Industrial Park, Heath Street",
    "sg:city":"Smethwick",
    "sg:classifiers":[
        {
            "category":"Retail",
            "subcategory":"Auto Repair",
            "type":"Services"
        }
    ],
    "sg:phone":"+44 121 558 9881",
    "sg:postcode":"B66 2QY",
    "sg:province":"West Midlands",
    "sg:tags":[
        "modification",
        "garage"
    ],
    "wof:name":"Clive Davies",
    "wof:placetype":"venue"
},
  "geometry": {"coordinates":[-1.944394,52.490253],"type":"Point"}
}