{
  "type": "Feature",
  "properties": {
    "addr:full":"Chapel Street Tregaron Ceredigion SY25 6HA",
    "addr:postcode":"sy25 6ha",
    "addr:street":"Chapel Street",
    "iso:country":"GB",
    "sg:address":"Chapel Street",
    "sg:city":"Tregaron",
    "sg:classifiers":[
        {
            "category":"Shopping",
            "subcategory":"Pharmacy",
            "type":"Retail Goods"
        }
    ],
    "sg:postcode":"SY25 6HA",
    "sg:province":"Ceredigion",
    "sg:tags":[
        "pharmacist",
        "chemist"
    ],
    "wof:name":"Glanfon Pharmacy",
    "wof:placetype":"venue"
},
  "geometry": {"coordinates":[-3.936046,52.219116],"type":"Point"}
}