{
  "type": "Feature",
  "properties": {
    "iso:country":"GB",
    "sg:address":"91 Norbury Hill",
    "sg:city":"London",
    "sg:classifiers":[
        {
            "category":"Building & Trades",
            "subcategory":"Plumbing",
            "type":"Services"
        }
    ],
    "sg:phone":"+44 7956 288128",
    "sg:postcode":"SW16 3RU",
    "sg:province":"Greater London",
    "sg:tags":[
        "heating"
    ],
    "wof:name":"A D S Plumbing & Heating Engineer",
    "wof:placetype":"venue"
},
  "geometry": {"coordinates":[-0.10708,51.418312],"type":"Point"}
}