{
  "type": "Feature",
  "properties": {
    "addr:full":"Top Floor, Unit 1, Darley Abbey Mills Derby Derbyshire DE22 1DZ",
    "addr:housenumber":"unit 1",
    "addr:postcode":"de22 1dz",
    "iso:country":"GB",
    "sg:address":"Top Floor, Unit 1, Darley Abbey Mills",
    "sg:city":"Derby",
    "sg:classifiers":[
        {
            "category":"Shopping",
            "subcategory":"Catalog Store",
            "type":"Retail Goods"
        }
    ],
    "sg:phone":"+44 845 130 0666",
    "sg:postcode":"DE22 1DZ",
    "sg:province":"Derbyshire",
    "sg:tags":[
        "mail",
        "order"
    ],
    "wof:name":"Rollersnakes Ltd.",
    "wof:placetype":"venue"
},
  "geometry": {"coordinates":[-1.479403,52.942657],"type":"Point"}
}