{
  "type": "Feature",
  "properties": {
    "iso:country":"GB",
    "sg:address":"12 Aqualate Close",
    "sg:city":"Newport",
    "sg:classifiers":[
        {
            "category":"Professional",
            "subcategory":"Management & Consulting",
            "type":"Services"
        }
    ],
    "sg:postcode":"TF10 7TF",
    "sg:province":"Shropshire",
    "sg:tags":[
        "consultant",
        "business"
    ],
    "wof:name":"Apex Consultancy Ltd",
    "wof:placetype":"venue"
},
  "geometry": {"coordinates":[-2.368746,52.773933],"type":"Point"}
}