{
  "type": "Feature",
  "properties": {
    "addr:full":"186 Brookhouse Lane Stoke-on-trent Staffordshire ST2 8ND",
    "addr:housenumber":"186",
    "addr:postcode":"st2 8nd",
    "addr:street":"Brookhouse Lane",
    "iso:country":"GB",
    "sg:address":"186 Brookhouse Lane",
    "sg:city":"Stoke-on-trent",
    "sg:classifiers":[
        {
            "category":"Transit Center",
            "subcategory":"Passenger",
            "type":"Transportation"
        }
    ],
    "sg:phone":"+44 1782 302539",
    "sg:postcode":"ST2 8ND",
    "sg:province":"Staffordshire",
    "sg:tags":[
        "boarding",
        "kennel",
        "catteries"
    ],
    "wof:name":"Brookhouse Boarding Kennels",
    "wof:placetype":"venue"
},
  "geometry": {"coordinates":[-2.112924099,53.0280075073],"type":"Point"}
}