{
  "type": "Feature",
  "properties": {
    "addr:full":"35-37 Clarence Street Staines Berkshire TW18 4SY",
    "addr:housenumber":"35-37",
    "addr:postcode":"tw18 4sy",
    "addr:street":"Clarence Street",
    "iso:country":"GB",
    "sg:address":"35-37 Clarence Street",
    "sg:city":"Staines",
    "sg:classifiers":[
        {
            "category":"Shopping",
            "subcategory":"Mobile Phones",
            "type":"Retail Goods"
        }
    ],
    "sg:postcode":"TW18 4SY",
    "sg:province":"Berkshire",
    "wof:name":"Prestige Communications",
    "wof:placetype":"venue"
},
  "geometry": {"coordinates":[-0.515395999,51.4339637756],"type":"Point"}
}