{
  "type": "Feature",
  "properties": {
    "addr:full":"Unit 1 London Greater London E15 2LH",
    "addr:housenumber":"unit 1",
    "addr:postcode":"e15 2lh",
    "iso:country":"GB",
    "sg:address":"Unit 1",
    "sg:city":"London",
    "sg:classifiers":[
        {
            "category":"Shopping",
            "subcategory":"Clothing, Apparel, & Fashions",
            "type":"Retail Goods"
        },
        {
            "category":"Wholesale",
            "subcategory":"Apparel",
            "type":"Manufacturing & Wholesale Goods"
        }
    ],
    "sg:phone":"+44 20 8534 3777",
    "sg:postcode":"E15 2LH",
    "sg:province":"Greater London",
    "sg:tags":[
        "supplier",
        "clothing",
        "wear",
        "leisure"
    ],
    "wof:name":"Euro Leisurewear Ltd.",
    "wof:placetype":"venue"
},
  "geometry": {"coordinates":[0.017715,51.530567],"type":"Point"}
}