{
  "type": "Feature",
  "properties": {
    "iso:country":"GB",
    "sg:address":"5 Clapgate, Romley",
    "sg:city":"Stockport",
    "sg:classifiers":[
        {
            "category":"Shopping",
            "subcategory":"News",
            "type":"Retail Goods"
        }
    ],
    "sg:phone":"+44 161 430 5818",
    "sg:postcode":"SK6 3DG",
    "sg:province":"Cheshire",
    "sg:tags":[
        "newsagent"
    ],
    "wof:name":"Korya News Newsagent",
    "wof:placetype":"venue"
},
  "geometry": {"coordinates":[-2.106347084,53.4108085632],"type":"Point"}
}