{
  "type": "Feature",
  "properties": {
    "addr:full":"Black Moss Farm, Black Moss Road Altrincham Cheshire WA14 5RG",
    "addr:postcode":"wa14 5rg",
    "addr:street":"Black Moss Farm Black Moss Road",
    "iso:country":"GB",
    "sg:address":"Black Moss Farm, Black Moss Road",
    "sg:city":"Altrincham",
    "sg:classifiers":[
        {
            "category":"Real Estate",
            "subcategory":"Surveying",
            "type":"Services"
        }
    ],
    "sg:phone":"+44 161 927 7562",
    "sg:postcode":"WA14 5RG",
    "sg:province":"Cheshire",
    "sg:tags":[
        "surveyor",
        "valuer"
    ],
    "wof:name":"Berrys",
    "wof:placetype":"venue"
},
  "geometry": {"coordinates":[-2.375429,53.396343],"type":"Point"}
}