{
  "type": "Feature",
  "properties": {
    "addr:full":"100 Church Street Blackpool Lancashire FY1 1JA",
    "addr:housenumber":"100",
    "addr:postcode":"fy1 1ja",
    "addr:street":"Church Street",
    "iso:country":"GB",
    "sg:address":"100 Church Street",
    "sg:city":"Blackpool",
    "sg:classifiers":[
        {
            "category":"Shopping",
            "subcategory":"Pawn Shop",
            "type":"Retail Goods"
        }
    ],
    "sg:phone":"+44 1253 296059",
    "sg:postcode":"FY1 1JA",
    "sg:province":"Lancashire",
    "sg:tags":[
        "pawnbroker"
    ],
    "wof:name":"Gemcabin Ltd.",
    "wof:placetype":"venue"
},
  "geometry": {"coordinates":[-3.0498900414,53.8180618286],"type":"Point"}
}