{
  "type": "Feature",
  "properties": {
    "addr:full":"Musgrave Hall, Burras Lane Otley North Yorkshire LS21 3HS",
    "addr:postcode":"ls21 3hs",
    "addr:street":"Burras Lane",
    "iso:country":"GB",
    "sg:address":"Musgrave Hall, Burras Lane",
    "sg:city":"Otley",
    "sg:classifiers":[
        {
            "category":"Home & Garden",
            "subcategory":"Kitchen Supply",
            "type":"Retail Goods"
        }
    ],
    "sg:postcode":"LS21 3HS",
    "sg:province":"North Yorkshire",
    "sg:tags":[
        "equipment",
        "catering"
    ],
    "wof:name":"Ken Pollard",
    "wof:placetype":"venue"
},
  "geometry": {"coordinates":[-1.694953,53.90572],"type":"Point"}
}