{
  "type": "Feature",
  "properties": {
    "addr:full":"25 Thomas Street, Radcliffe Manchester Greater Manchester M26 2UH",
    "addr:housenumber":"25",
    "addr:postcode":"m26 2uh",
    "addr:street":"Thomas Street",
    "iso:country":"GB",
    "sg:address":"25 Thomas Street, Radcliffe",
    "sg:city":"Manchester",
    "sg:classifiers":[
        {
            "category":"Bars & Pubs",
            "type":"Food & Drink"
        }
    ],
    "sg:phone":"+44 161 723 5517",
    "sg:postcode":"M26 2UH",
    "sg:province":"Greater Manchester",
    "sg:tags":[
        "pubs",
        "inn"
    ],
    "wof:name":"The Morning Star",
    "wof:placetype":"venue"
},
  "geometry": {"coordinates":[-2.3253879547,53.5598564148],"type":"Point"}
}