{
  "type": "Feature",
  "properties": {
    "addr:full":"164 Priory Road, Hall Grn Birmingham West Midlands B28 0TB",
    "addr:housenumber":"164",
    "addr:postcode":"b28 0tb",
    "addr:street":"Priory Road Hall Grn",
    "iso:country":"GB",
    "sg:address":"164 Priory Road, Hall Grn",
    "sg:city":"Birmingham",
    "sg:classifiers":[
        {
            "category":"Retail",
            "subcategory":"Emissions Testing",
            "type":"Services"
        },
        {
            "category":"Professional",
            "subcategory":"Testing Lab",
            "type":"Services"
        }
    ],
    "sg:phone":"+44 121 474 5449",
    "sg:postcode":"B28 0TB",
    "sg:province":"West Midlands",
    "sg:tags":[
        "mot"
    ],
    "wof:name":"Priory Service Station",
    "wof:placetype":"venue"
},
  "geometry": {"coordinates":[-1.855635047,52.4137687683],"type":"Point"}
}