{
  "type": "Feature",
  "properties": {
    "addr:full":"Graphic House, Bank Street Macclesfield Cheshire SK11 7BR",
    "addr:postcode":"sk11 7br",
    "addr:street":"Bank Street",
    "iso:country":"GB",
    "sg:address":"Graphic House, Bank Street",
    "sg:city":"Macclesfield",
    "sg:classifiers":[
        {
            "category":"Shopping",
            "subcategory":"Stationery & Office Supplies",
            "type":"Retail Goods"
        }
    ],
    "sg:phone":"+44 1625 429211",
    "sg:postcode":"SK11 7BR",
    "sg:province":"Cheshire",
    "sg:tags":[
        "printing",
        "equipment",
        "printers'",
        "mech"
    ],
    "wof:name":"Stanley Press Equipment Ltd.",
    "wof:placetype":"venue"
},
  "geometry": {"coordinates":[-2.118509,53.255489],"type":"Point"}
}