{
  "type": "Feature",
  "properties": {
    "addr:full":"Service Road Forfar Angus DD8 3HY",
    "addr:postcode":"dd8 3hy",
    "addr:street":"Service Road",
    "iso:country":"GB",
    "sg:address":"Service Road",
    "sg:city":"Forfar",
    "sg:classifiers":[
        {
            "category":"Professional",
            "subcategory":"Employment Agencies",
            "type":"Services"
        }
    ],
    "sg:phone":"+44 1307 452800",
    "sg:postcode":"DD8 3HY",
    "sg:province":"Angus",
    "sg:tags":[
        "consultant"
    ],
    "wof:name":"Jobcentre",
    "wof:placetype":"venue"
},
  "geometry": {"coordinates":[-2.88024,56.649857],"type":"Point"}
}