{
  "type": "Feature",
  "properties": {
    "iso:country":"GB",
    "sg:address":"209 Bloxham Road",
    "sg:city":"Banbury",
    "sg:classifiers":[
        {
            "category":"Building & Trades",
            "subcategory":"Construction",
            "type":"Services"
        }
    ],
    "sg:phone":"+44 1295 265391",
    "sg:postcode":"OX16 9JU",
    "sg:province":"Oxfordshire",
    "sg:tags":[
        "builder"
    ],
    "wof:name":"Ellis Hill",
    "wof:placetype":"venue"
},
  "geometry": {"coordinates":[-1.350152,52.049328],"type":"Point"}
}