{
  "type": "Feature",
  "properties": {
    "iso:country":"GB",
    "sg:address":"112/114 Whitegate Dr",
    "sg:city":"Blackpool",
    "sg:classifiers":[
        {
            "category":"Fast Food",
            "type":"Food & Drink"
        }
    ],
    "sg:postcode":"FY3 9XH",
    "sg:province":"Lancashire",
    "sg:tags":[
        "away",
        "take"
    ],
    "wof:name":"Grab City Ltd",
    "wof:placetype":"venue"
},
  "geometry": {"coordinates":[-3.035101,53.813698],"type":"Point"}
}