{
  "type": "Feature",
  "properties": {
    "addr:full":"10 North Street Melton Mowbray Leicestershire LE13 1NL",
    "addr:housenumber":"10",
    "addr:postcode":"le13 1nl",
    "addr:street":"North Street",
    "iso:country":"GB",
    "sg:address":"10 North Street",
    "sg:city":"Melton Mowbray",
    "sg:classifiers":[
        {
            "category":"Home & Garden",
            "subcategory":"Hardware",
            "type":"Retail Goods"
        }
    ],
    "sg:phone":"+44 1664 482822",
    "sg:postcode":"LE13 1NL",
    "sg:province":"Leicestershire",
    "wof:name":"Melton Hardware Ltd",
    "wof:placetype":"venue"
},
  "geometry": {"coordinates":[-0.8848029971,52.768283844],"type":"Point"}
}