{
  "type": "Feature",
  "properties": {
    "iso:country":"GB",
    "sg:address":"1 Elizabeth Slinger Rd",
    "sg:city":"Manchester",
    "sg:classifiers":[
        {
            "category":"Government",
            "subcategory":"Office",
            "type":"Public Place"
        }
    ],
    "sg:phone":"+44 161 434 5254",
    "sg:postcode":"M20 2XA",
    "sg:province":"Greater Manchester",
    "sg:tags":[
        "education",
        "agency",
        "authority"
    ],
    "wof:name":"Residential Resource",
    "wof:placetype":"venue"
},
  "geometry": {"coordinates":[-2.24762,53.426006],"type":"Point"}
}