{
  "type": "Feature",
  "properties": {
    "iso:country":"GB",
    "sg:address":"2 Bridge Street",
    "sg:city":"Taunton",
    "sg:classifiers":[
        {
            "category":"Sports & Exercise",
            "subcategory":"Sports Center",
            "type":"Entertainment"
        }
    ],
    "sg:postcode":"TA1 1UB",
    "sg:province":"Somerset",
    "sg:tags":[
        "shop",
        "good"
    ],
    "wof:name":"Tony Pryce Sports",
    "wof:placetype":"venue"
},
  "geometry": {"coordinates":[-3.104588,51.018185],"type":"Point"}
}