{
  "type": "Feature",
  "properties": {
    "iso:country":"GB",
    "sg:address":"Hillside Garage, Cargo Beck",
    "sg:city":"Carlisle",
    "sg:classifiers":[
        {
            "category":"Retail",
            "subcategory":"Auto Repair",
            "type":"Services"
        }
    ],
    "sg:phone":"+44 1228 674664",
    "sg:postcode":"CA6 4BB",
    "sg:province":"Cumbria",
    "sg:tags":[
        "modification",
        "garage"
    ],
    "wof:name":"M Irving",
    "wof:placetype":"venue"
},
  "geometry": {"coordinates":[-2.990855,54.923618],"type":"Point"}
}