{
  "type": "Feature",
  "properties": {
    "addr:full":"Scout Hall, Woodland Ave Porthcawl Bridgend CF36 5HT",
    "addr:postcode":"cf36 5ht",
    "addr:street":"Woodland Ave",
    "iso:country":"GB",
    "sg:address":"Scout Hall, Woodland Ave",
    "sg:city":"Porthcawl",
    "sg:classifiers":[
        {
            "category":"Education",
            "subcategory":"Preschool",
            "type":"Public Place"
        }
    ],
    "sg:postcode":"CF36 5HT",
    "sg:province":"Bridgend",
    "sg:tags":[
        "pre-school",
        "playgroups"
    ],
    "wof:name":"Deeks,Heather,",
    "wof:placetype":"venue"
},
  "geometry": {"coordinates":[-3.690919,51.48761],"type":"Point"}
}