{
  "type": "Feature",
  "properties": {
    "iso:country":"GB",
    "sg:address":"85 Coles Avenue",
    "sg:city":"Poole",
    "sg:classifiers":[
        {
            "category":"Shopping",
            "subcategory":"News",
            "type":"Retail Goods"
        }
    ],
    "sg:phone":"+44 1202 674596",
    "sg:postcode":"BH15 4HJ",
    "sg:province":"Dorset",
    "sg:tags":[
        "newsagent"
    ],
    "wof:name":"Hamworthy News",
    "wof:placetype":"venue"
},
  "geometry": {"coordinates":[-2.0142419338,50.7147941589],"type":"Point"}
}