{
  "type": "Feature",
  "properties": {
    "addr:full":"86 Chapel Street Thatcham Berkshire RG18 4QN",
    "addr:housenumber":"86",
    "addr:postcode":"rg18 4qn",
    "addr:street":"Chapel Street",
    "iso:country":"GB",
    "sg:address":"86 Chapel Street",
    "sg:city":"Thatcham",
    "sg:classifiers":[
        {
            "category":"Professional",
            "subcategory":"Employment Agencies",
            "type":"Services"
        }
    ],
    "sg:phone":"+44 1635 860400",
    "sg:postcode":"RG18 4QN",
    "sg:province":"Berkshire",
    "sg:tags":[
        "consultant"
    ],
    "wof:name":"Anglo Prodrive",
    "wof:placetype":"venue"
},
  "geometry": {"coordinates":[-1.2526270151,51.4039077759],"type":"Point"}
}