{
  "type": "Feature",
  "properties": {
    "addr:full":"Office 7 Leigh Ho, 7 Station Approach Bexleyheath Kent DA7 4QP",
    "addr:housenumber":"7;7",
    "addr:postcode":"da7 4qp",
    "addr:street":"Leigh Ho;Station Approach",
    "iso:country":"GB",
    "sg:address":"Office 7 Leigh Ho, 7 Station Approach",
    "sg:city":"Bexleyheath",
    "sg:classifiers":[
        {
            "category":"Professional",
            "subcategory":"Accounting & Tax Preparation",
            "type":"Services"
        }
    ],
    "sg:postcode":"DA7 4QP",
    "sg:province":"Kent",
    "sg:tags":[
        "accountant"
    ],
    "wof:name":"Sterling,Mark,",
    "wof:placetype":"venue"
},
  "geometry": {"coordinates":[0.138045,51.460136],"type":"Point"}
}