{
  "type": "Feature",
  "properties": {
    "addr:full":"1 Waterhen Cotts, Poverty Lane, Tathwell Louth Lincolnshire LN11 9SY",
    "addr:housenumber":"1;cotts",
    "addr:postcode":"ln11 9sy",
    "addr:street":"Waterhen;Poverty Lane;Louth",
    "iso:country":"GB",
    "sg:address":"1 Waterhen Cotts, Poverty Lane, Tathwell",
    "sg:city":"Louth",
    "sg:classifiers":[
        {
            "category":"Real Estate",
            "subcategory":"Architect",
            "type":"Services"
        }
    ],
    "sg:phone":"+44 1507 605941",
    "sg:postcode":"LN11 9SY",
    "sg:province":"Lincolnshire",
    "wof:name":"John Stainton Architect",
    "wof:placetype":"venue"
},
  "geometry": {"coordinates":[-0.007391,53.366497],"type":"Point"}
}