{
  "type": "Feature",
  "properties": {
    "iso:country":"GB",
    "sg:address":"Long Green, Forthampton",
    "sg:city":"Gloucester",
    "sg:classifiers":[
        {
            "category":"Home & Garden",
            "subcategory":"Household Appliances",
            "type":"Retail Goods"
        }
    ],
    "sg:postcode":"GL19 4QH",
    "sg:province":"Gloucestershire",
    "sg:tags":[
        "electrical"
    ],
    "wof:name":"Trl Emc Ltd.",
    "wof:placetype":"venue"
},
  "geometry": {"coordinates":[-2.209526,51.991806],"type":"Point"}
}