{
  "type": "Feature",
  "properties": {
    "addr:full":"6c Low Rd, Low Seaton Workington Cumbria CA14 1PP",
    "addr:housenumber":"6c",
    "addr:postcode":"ca14 1pp",
    "addr:street":"Low Rd",
    "iso:country":"GB",
    "sg:address":"6c Low Rd, Low Seaton",
    "sg:city":"Workington",
    "sg:classifiers":[
        {
            "category":"Building & Trades",
            "subcategory":"Construction",
            "type":"Services"
        }
    ],
    "sg:phone":"+44 1900 870466",
    "sg:postcode":"CA14 1PP",
    "sg:province":"Cumbria",
    "sg:tags":[
        "roofing"
    ],
    "wof:name":"North Lakes Roofing Contractor",
    "wof:placetype":"venue"
},
  "geometry": {"coordinates":[-3.5249290466,54.6620101929],"type":"Point"}
}