{
  "type": "Feature",
  "properties": {
    "iso:country":"GB",
    "sg:address":"17 Front Street",
    "sg:city":"Blaydon-on-tyne",
    "sg:classifiers":[
        {
            "category":"Retail",
            "subcategory":"Auto Repair",
            "type":"Services"
        }
    ],
    "sg:phone":"+44 191 414 7936",
    "sg:postcode":"NE21 4RF",
    "sg:province":"Tyne and Wear",
    "sg:tags":[
        "body",
        "car"
    ],
    "wof:name":"Winlaton Coach Works",
    "wof:placetype":"venue"
},
  "geometry": {"coordinates":[-1.724364996,54.9549942017],"type":"Point"}
}