{
  "type": "Feature",
  "properties": {
    "addr:full":"77 Queens Rd Leicester Leicestershire LE2 1TT",
    "addr:housenumber":"77",
    "addr:postcode":"le2 1tt",
    "addr:street":"Queens Rd",
    "iso:country":"GB",
    "sg:address":"77 Queens Rd",
    "sg:city":"Leicester",
    "sg:classifiers":[
        {
            "category":"Personal",
            "subcategory":"Beauty Salon",
            "type":"Services"
        }
    ],
    "sg:postcode":"LE2 1TT",
    "sg:province":"Leicestershire",
    "sg:tags":[
        "unisex",
        "hairdresser"
    ],
    "wof:name":"Tate,Brian,",
    "wof:placetype":"venue"
},
  "geometry": {"coordinates":[-1.117518,52.617943],"type":"Point"}
}