{
  "type": "Feature",
  "properties": {
    "iso:country":"GB",
    "sg:address":"Sutherland House, 108-114 Dundath St",
    "sg:city":"Edinburgh",
    "sg:classifiers":[
        {
            "category":"Manufacturing",
            "subcategory":"Tools & Machinery",
            "type":"Manufacturing & Wholesale Goods"
        }
    ],
    "sg:phone":"+44 1592 201394",
    "sg:postcode":"EH3 5DQ",
    "sg:province":"City of Edinburgh",
    "sg:tags":[
        "society",
        "friendly"
    ],
    "wof:name":"Mclarens",
    "wof:placetype":"venue"
},
  "geometry": {"coordinates":[-3.205111,55.962589],"type":"Point"}
}