{
  "type": "Feature",
  "properties": {
    "iso:country":"GB",
    "sg:address":"Unit 1 The Furze, Dunt Avenue, Hurst",
    "sg:city":"Reading",
    "sg:classifiers":[
        {
            "category":"Professional",
            "subcategory":"Management & Consulting",
            "type":"Services"
        }
    ],
    "sg:postcode":"RG10 0SY",
    "sg:province":"Berkshire",
    "sg:tags":[
        "consultant",
        "safety"
    ],
    "wof:name":"T M Facilities Services Ltd.",
    "wof:placetype":"venue"
},
  "geometry": {"coordinates":[-0.8528860211,51.4585494995],"type":"Point"}
}