{
  "type": "Feature",
  "properties": {
    "addr:full":"17 Wraysbury Park Drive Emsworth Hampshire PO10 7UU",
    "addr:housenumber":"17",
    "addr:postcode":"po10 7uu",
    "addr:street":"Wraysbury Park Drive",
    "iso:country":"GB",
    "sg:address":"17 Wraysbury Park Drive",
    "sg:city":"Emsworth",
    "sg:classifiers":[
        {
            "category":"Shopping",
            "subcategory":"Computers & Home Electronics",
            "type":"Retail Goods"
        }
    ],
    "sg:postcode":"PO10 7UU",
    "sg:province":"Hampshire",
    "sg:tags":[
        "aerial",
        "television",
        "radio"
    ],
    "wof:name":"G B Aerials",
    "wof:placetype":"venue"
},
  "geometry": {"coordinates":[-0.9376400113,50.8648986816],"type":"Point"}
}