{
  "type": "Feature",
  "properties": {
    "addr:full":"33 Oakfield Rd Bristol City of Bristol BS8 2AT",
    "addr:housenumber":"33",
    "addr:postcode":"bs8 2at",
    "addr:street":"Oakfield Rd",
    "iso:country":"GB",
    "sg:address":"33 Oakfield Rd",
    "sg:city":"Bristol",
    "sg:classifiers":[
        {
            "category":"Professional",
            "subcategory":"Business Services",
            "type":"Services"
        }
    ],
    "sg:phone":"+44 117 970 6557",
    "sg:postcode":"BS8 2AT",
    "sg:province":"City of Bristol",
    "sg:tags":[
        "trade"
    ],
    "wof:name":"Renault Dealer Association Trading Co",
    "wof:placetype":"venue"
},
  "geometry": {"coordinates":[-2.611951,51.460873],"type":"Point"}
}