{
  "type": "Feature",
  "properties": {
    "iso:country":"GB",
    "sg:address":"15a Talbot St",
    "sg:city":"Maesteg",
    "sg:classifiers":[
        {
            "category":"Shopping",
            "subcategory":"Department Store",
            "type":"Retail Goods"
        }
    ],
    "sg:postcode":"CF34 9BW",
    "sg:province":"Bridgend",
    "wof:name":"Griffiths,E,",
    "wof:placetype":"venue"
},
  "geometry": {"coordinates":[-3.658984,51.609089],"type":"Point"}
}