{
  "type": "Feature",
  "properties": {
    "addr:full":"The Pastures, Littlemoor Lane, Sibsey Boston Lincolnshire PE22 0TU",
    "addr:postcode":"pe22 0tu",
    "addr:street":"The;Littlemoor Lane",
    "iso:country":"GB",
    "sg:address":"The Pastures, Littlemoor Lane, Sibsey",
    "sg:city":"Boston",
    "sg:classifiers":[
        {
            "category":"Communications",
            "type":"Services"
        }
    ],
    "sg:postcode":"PE22 0TU",
    "sg:province":"Lincolnshire",
    "sg:tags":[
        "audio-visual"
    ],
    "wof:name":"Charity Slide Photo-Digital",
    "wof:placetype":"venue"
},
  "geometry": {"coordinates":[0.016275,53.037117],"type":"Point"}
}