{
  "type": "Feature",
  "properties": {
    "iso:country":"GB",
    "sg:address":"Suite 401, 302 Regent Street",
    "sg:city":"London",
    "sg:classifiers":[
        {
            "category":"Professional",
            "subcategory":"Management & Consulting",
            "type":"Services"
        }
    ],
    "sg:postcode":"W1R 6HH",
    "sg:province":"Greater London",
    "sg:tags":[
        "marketing",
        "consultant"
    ],
    "wof:name":"Links Marketing Ltd",
    "wof:placetype":"venue"
},
  "geometry": {"coordinates":[-0.142385,51.516544],"type":"Point"}
}