{
  "type": "Feature",
  "properties": {
    "addr:full":"9 Market Place Houghton-le-spring Durham DH5 8AH",
    "addr:housenumber":"9",
    "addr:postcode":"dh5 8ah",
    "addr:street":"Market Place",
    "iso:country":"GB",
    "sg:address":"9 Market Place",
    "sg:city":"Houghton-le-spring",
    "sg:classifiers":[
        {
            "category":"Bars & Pubs",
            "type":"Food & Drink"
        }
    ],
    "sg:phone":"+44 191 512 0270",
    "sg:postcode":"DH5 8AH",
    "sg:province":"Durham",
    "sg:tags":[
        "pubs",
        "inn"
    ],
    "wof:name":"The Spring Inn",
    "wof:placetype":"venue"
},
  "geometry": {"coordinates":[-1.4619979858,54.8430137634],"type":"Point"}
}