{
  "type": "Feature",
  "properties": {
    "addr:full":"Unit 1a Howe Moss Drive, Kirkhill Industrial Estate, Dyce Aberdeen Aberdeen City AB21 0GL",
    "addr:housenumber":"unit 1a",
    "addr:postcode":"ab21 0gl",
    "addr:street":"Moss Drive;Industrial Estate",
    "iso:country":"GB",
    "sg:address":"Unit 1a Howe Moss Drive, Kirkhill Industrial Estate, Dyce",
    "sg:city":"Aberdeen",
    "sg:classifiers":[
        {
            "category":"Professional",
            "subcategory":"Engineering",
            "type":"Services"
        }
    ],
    "sg:phone":"+44 1224 255900",
    "sg:postcode":"AB21 0GL",
    "sg:province":"Aberdeen City",
    "sg:tags":[
        "consulting",
        "engineer"
    ],
    "wof:name":"Rhomax Engineering Ltd.",
    "wof:placetype":"venue"
},
  "geometry": {"coordinates":[-2.214522,57.207512],"type":"Point"}
}