{
  "type": "Feature",
  "properties": {
    "addr:full":"283 Malden Road Sutton Surrey SM3 8ET",
    "addr:housenumber":"283",
    "addr:postcode":"sm3 8et",
    "addr:street":"Malden Road",
    "iso:country":"GB",
    "sg:address":"283 Malden Road",
    "sg:city":"Sutton",
    "sg:classifiers":[
        {
            "category":"Real Estate",
            "subcategory":"Real Estate Agent",
            "type":"Services"
        }
    ],
    "sg:phone":"+44 20 8644 0511",
    "sg:postcode":"SM3 8ET",
    "sg:province":"Surrey",
    "wof:name":"Granvilles",
    "wof:placetype":"venue"
},
  "geometry": {"coordinates":[-0.227672,51.370556],"type":"Point"}
}