{
  "type": "Feature",
  "properties": {
    "addr:full":"Denor, Farrington Road, Paulton Bristol Somerset BS39 7LP",
    "addr:postcode":"bs39 7lp",
    "addr:street":"Farrington Road",
    "iso:country":"GB",
    "sg:address":"Denor, Farrington Road, Paulton",
    "sg:city":"Bristol",
    "sg:classifiers":[
        {
            "category":"Freight",
            "type":"Transportation"
        }
    ],
    "sg:postcode":"BS39 7LP",
    "sg:province":"Somerset",
    "sg:tags":[
        "haulage",
        "road"
    ],
    "wof:name":"D J & K J Parfitt",
    "wof:placetype":"venue"
},
  "geometry": {"coordinates":[-2.500631,51.305626],"type":"Point"}
}