{
  "type": "Feature",
  "properties": {
    "iso:country":"GB",
    "sg:address":"9 Elm Ct, Copse Dr",
    "sg:city":"Coventry",
    "sg:classifiers":[
        {
            "category":"Professional",
            "subcategory":"Lawyer & Legal Services",
            "type":"Services"
        }
    ],
    "sg:phone":"+44 1676 522202",
    "sg:postcode":"CV5 9RG",
    "sg:province":"West Midlands",
    "wof:name":"Turner & Townsend",
    "wof:placetype":"venue"
},
  "geometry": {"coordinates":[-1.6049690247,52.4338798523],"type":"Point"}
}