{
  "type": "Feature",
  "properties": {
    "iso:country":"GB",
    "sg:address":"11-13 Shropshire Street, Audlam",
    "sg:city":"Crewe",
    "sg:classifiers":[
        {
            "category":"Professional",
            "subcategory":"Engineering",
            "type":"Services"
        }
    ],
    "sg:phone":"+44 1270 811576",
    "sg:postcode":"CW3 0AE",
    "sg:province":"Cheshire",
    "sg:tags":[
        "contractor",
        "electrical",
        "engineer"
    ],
    "wof:name":"J D Walley",
    "wof:placetype":"venue"
},
  "geometry": {"coordinates":[-2.508555,52.9884],"type":"Point"}
}