{
  "type": "Feature",
  "properties": {
    "addr:full":"Hillsborough Road, Glen Parva Leicester Leicestershire LE2 9PT",
    "addr:postcode":"le2 9pt",
    "addr:street":"Hillsborough Road",
    "iso:country":"GB",
    "sg:address":"Hillsborough Road, Glen Parva",
    "sg:city":"Leicester",
    "sg:classifiers":[
        {
            "category":"Education",
            "subcategory":"School",
            "type":"Public Place"
        }
    ],
    "sg:phone":"+44 116 278 6400",
    "sg:postcode":"LE2 9PT",
    "sg:province":"Leicestershire",
    "sg:tags":[
        "local",
        "authority"
    ],
    "wof:name":"Rolleston Infant School",
    "wof:placetype":"venue"
},
  "geometry": {"coordinates":[-1.1471639872,52.5875053406],"type":"Point"}
}