{
  "type": "Feature",
  "properties": {
    "addr:full":"Margate, Cordinham Wood Bodmin Cornwall PL30 4AL",
    "addr:housenumber":"bodmin",
    "addr:postcode":"pl30 4al",
    "addr:street":"Margate;Wood",
    "iso:country":"GB",
    "sg:address":"Margate, Cordinham Wood",
    "sg:city":"Bodmin",
    "sg:classifiers":[
        {
            "category":"Sports & Exercise",
            "subcategory":"Bicycle Rental",
            "type":"Entertainment"
        }
    ],
    "sg:postcode":"PL30 4AL",
    "sg:province":"Cornwall",
    "sg:tags":[
        "renting",
        "cycle"
    ],
    "wof:name":"Glynn Valley Cycle Hire",
    "wof:placetype":"venue"
},
  "geometry": {"coordinates":[-4.686154,50.462776],"type":"Point"}
}