{
  "type": "Feature",
  "properties": {
    "iso:country":"GB",
    "sg:address":"15 Coed Coch Rd",
    "sg:city":"Colwyn Bay",
    "sg:classifiers":[
        {
            "category":"Farming",
            "subcategory":"Fish & Marine Products",
            "type":"Manufacturing & Wholesale Goods"
        }
    ],
    "sg:postcode":"LL29 9UR",
    "sg:province":"Conwy",
    "sg:tags":[
        "fisherman"
    ],
    "wof:name":"Roberts,M E & J R,",
    "wof:placetype":"venue"
},
  "geometry": {"coordinates":[-3.699379921,53.2886123657],"type":"Point"}
}