{
  "type": "Feature",
  "properties": {
    "addr:full":"1 Ingmels Court, Off Endingurgh Way, Leifield Corsham Wiltshire SN13 9BZ",
    "addr:housenumber":"1",
    "addr:postcode":"sn13 9bz",
    "addr:street":"Ingmels Court Off Endingurgh Way Leifield Corsham",
    "iso:country":"GB",
    "sg:address":"1 Ingmels Court, Off Endingurgh Way, Leifield",
    "sg:city":"Corsham",
    "sg:classifiers":[
        {
            "category":"Professional",
            "subcategory":"Business Services",
            "type":"Services"
        }
    ],
    "sg:phone":"+44 1249 713796",
    "sg:postcode":"SN13 9BZ",
    "sg:province":"Wiltshire",
    "sg:tags":[
        "import",
        "export",
        "agent"
    ],
    "wof:name":"Coombe Castle International Ltd.",
    "wof:placetype":"venue"
},
  "geometry": {"coordinates":[-2.187239,51.431484],"type":"Point"}
}