{
  "type": "Feature",
  "properties": {
    "iso:country":"GB",
    "sg:address":"57 Charlotte Street",
    "sg:city":"London",
    "sg:classifiers":[
        {
            "category":"Restaurant",
            "type":"Food & Drink"
        }
    ],
    "sg:phone":"+44 20 7580 3289",
    "sg:postcode":"W1T 4PD",
    "sg:province":"Greater London",
    "sg:tags":[
        "italian"
    ],
    "wof:name":"Pescatori",
    "wof:placetype":"venue"
},
  "geometry": {"coordinates":[-0.136429,51.520111],"type":"Point"}
}