{
  "type": "Feature",
  "properties": {
    "addr:full":"Suite 2, 59 High St Sittingbourne Kent ME10 4AW",
    "addr:housenumber":"suite 2 59",
    "addr:postcode":"me10 4aw",
    "addr:street":"High St",
    "iso:country":"GB",
    "sg:address":"Suite 2, 59 High St",
    "sg:city":"Sittingbourne",
    "sg:classifiers":[
        {
            "category":"Professional",
            "subcategory":"Employment Agencies",
            "type":"Services"
        }
    ],
    "sg:postcode":"ME10 4AW",
    "sg:province":"Kent",
    "sg:tags":[
        "consultant"
    ],
    "wof:name":"Silver Stream Organisation (The)",
    "wof:placetype":"venue"
},
  "geometry": {"coordinates":[0.736785,51.339748],"type":"Point"}
}