{
  "type": "Feature",
  "properties": {
    "addr:full":"7 Caldmore Green Walsall West Midlands WS1 3RL",
    "addr:housenumber":"7",
    "addr:postcode":"ws1 3rl",
    "addr:street":"Caldmore Green",
    "iso:country":"GB",
    "sg:address":"7 Caldmore Green",
    "sg:city":"Walsall",
    "sg:classifiers":[
        {
            "category":"Real Estate",
            "subcategory":"Real Estate Agent",
            "type":"Services"
        }
    ],
    "sg:phone":"+44 1922 723621",
    "sg:postcode":"WS1 3RL",
    "sg:province":"West Midlands",
    "wof:name":"The Moore Group",
    "wof:placetype":"venue"
},
  "geometry": {"coordinates":[-1.9823980331,52.5766906738],"type":"Point"}
}