{
  "type": "Feature",
  "properties": {
    "iso:country":"GB",
    "sg:address":"Front Street",
    "sg:city":"Durham",
    "sg:classifiers":[
        {
            "category":"Retail",
            "subcategory":"Auto Repair",
            "type":"Services"
        }
    ],
    "sg:postcode":"DH6 2LT",
    "sg:province":"Durham",
    "sg:tags":[
        "modification",
        "garage"
    ],
    "wof:name":"Front Street Garages",
    "wof:placetype":"venue"
},
  "geometry": {"coordinates":[-1.4177039862,54.7848548889],"type":"Point"}
}