{
  "type": "Feature",
  "properties": {
    "addr:full":"35 Parkfield Road, Aigburth Liverpool Merseyside L17 8UQ",
    "addr:housenumber":"35",
    "addr:postcode":"l17 8uq",
    "addr:street":"Parkfield Road",
    "iso:country":"GB",
    "sg:address":"35 Parkfield Road, Aigburth",
    "sg:city":"Liverpool",
    "sg:classifiers":[
        {
            "category":"Personal",
            "subcategory":"Psychics & Astrologers",
            "type":"Services"
        }
    ],
    "sg:phone":"+44 151 727 1080",
    "sg:postcode":"L17 8UQ",
    "sg:province":"Merseyside",
    "wof:name":"North West Astro Studio",
    "wof:placetype":"venue"
},
  "geometry": {"coordinates":[-2.949483,53.382355],"type":"Point"}
}