{
  "type": "Feature",
  "properties": {
    "iso:country":"GB",
    "sg:address":"35 Ryhope St South",
    "sg:city":"Sunderland",
    "sg:classifiers":[
        {
            "category":"Personal",
            "subcategory":"Beauty Salon",
            "type":"Services"
        }
    ],
    "sg:postcode":"SR2 0RW",
    "sg:province":"Tyne and Wear",
    "sg:tags":[
        "unisex",
        "hairdresser"
    ],
    "wof:name":"Shapes Hair Group",
    "wof:placetype":"venue"
},
  "geometry": {"coordinates":[-1.3677710295,54.8710784912],"type":"Point"}
}