{
  "type": "Feature",
  "properties": {
    "addr:full":"11 Threipmuir Place Balerno City of Edinburgh EH14 7HA",
    "addr:housenumber":"11",
    "addr:postcode":"eh14 7ha",
    "addr:street":"Threipmuir Place",
    "iso:country":"GB",
    "sg:address":"11 Threipmuir Place",
    "sg:city":"Balerno",
    "sg:classifiers":[
        {
            "category":"Building & Trades",
            "subcategory":"Construction",
            "type":"Services"
        }
    ],
    "sg:phone":"+44 131 449 5736",
    "sg:postcode":"EH14 7HA",
    "sg:province":"City of Edinburgh",
    "sg:tags":[
        "builder"
    ],
    "wof:name":"Downie & Jones",
    "wof:placetype":"venue"
},
  "geometry": {"coordinates":[-3.339366,55.877796],"type":"Point"}
}