{
  "type": "Feature",
  "properties": {
    "addr:full":"9 Layton Rd Leicester Leicestershire LE5 0PU",
    "addr:housenumber":"9",
    "addr:postcode":"le5 0pu",
    "addr:street":"Layton Rd",
    "iso:country":"GB",
    "sg:address":"9 Layton Rd",
    "sg:city":"Leicester",
    "sg:classifiers":[
        {
            "category":"Professional",
            "subcategory":"Printing & Photocopies",
            "type":"Services"
        }
    ],
    "sg:phone":"+44 116 246 1106",
    "sg:postcode":"LE5 0PU",
    "sg:province":"Leicestershire",
    "sg:tags":[
        "computer",
        "tag",
        "label"
    ],
    "wof:name":"S W Labels Ltd",
    "wof:placetype":"venue"
},
  "geometry": {"coordinates":[-1.098589,52.642555],"type":"Point"}
}