{
  "type": "Feature",
  "properties": {
    "addr:full":"1a Ronsons Way, Williams Yard St. Albans Rd, Sandridge St. Albans Hertfordshire AL4 9PZ",
    "addr:housenumber":"1a",
    "addr:postcode":"al4 9pz",
    "addr:street":"Ronsons Way;Yard St. Albans Rd;Albans",
    "iso:country":"GB",
    "sg:address":"1a Ronsons Way, Williams Yard St. Albans Rd, Sandridge",
    "sg:city":"St. Albans",
    "sg:classifiers":[
        {
            "category":"Building & Trades",
            "subcategory":"Construction",
            "type":"Services"
        }
    ],
    "sg:phone":"+44 1727 837269",
    "sg:postcode":"AL4 9PZ",
    "sg:province":"Hertfordshire",
    "sg:tags":[
        "joinery"
    ],
    "wof:name":"Darfen Durafencing",
    "wof:placetype":"venue"
},
  "geometry": {"coordinates":[-0.307021,51.779224],"type":"Point"}
}