{
  "type": "Feature",
  "properties": {
    "addr:full":"13 Blackheath Business Centre, Blackheath Hill London Greater London SE10 8BA",
    "addr:housenumber":"13",
    "addr:postcode":"se10 8ba",
    "addr:street":"Blackheath Business Centre Blackheath Hill",
    "iso:country":"GB",
    "sg:address":"13 Blackheath Business Centre, Blackheath Hill",
    "sg:city":"London",
    "sg:classifiers":[
        {
            "category":"Manufacturing",
            "subcategory":"Petroleum Products",
            "type":"Manufacturing & Wholesale Goods"
        }
    ],
    "sg:postcode":"SE10 8BA",
    "sg:province":"Greater London",
    "sg:tags":[
        "double",
        "glazing"
    ],
    "wof:name":"Warmview Windows",
    "wof:placetype":"venue"
},
  "geometry": {"coordinates":[-0.01994,51.473869],"type":"Point"}
}