{
  "type": "Feature",
  "properties": {
    "iso:country":"GB",
    "sg:address":"Broomhill Road, Brislington",
    "sg:city":"Bristol",
    "sg:classifiers":[
        {
            "category":"Food & Beverages",
            "subcategory":"Supermarket",
            "type":"Retail Goods"
        }
    ],
    "sg:phone":"+44 117 972 1318",
    "sg:postcode":"BS4 4NZ",
    "sg:province":"City of Bristol",
    "wof:name":"C R S",
    "wof:placetype":"venue"
},
  "geometry": {"coordinates":[-2.541519,51.4412],"type":"Point"}
}