{
  "type": "Feature",
  "properties": {
    "addr:full":"4 The Courtyard, Harris Business Park Bromsgrove Worcestershire B60 4DJ",
    "addr:housenumber":"4",
    "addr:postcode":"b60 4dj",
    "addr:street":"The Courtyard;Business Park",
    "iso:country":"GB",
    "sg:address":"4 The Courtyard, Harris Business Park",
    "sg:city":"Bromsgrove",
    "sg:classifiers":[
        {
            "category":"Professional",
            "subcategory":"Employment Agencies",
            "type":"Services"
        }
    ],
    "sg:phone":"+44 1527 577234",
    "sg:postcode":"B60 4DJ",
    "sg:province":"Worcestershire",
    "sg:tags":[
        "consultant"
    ],
    "wof:name":"Bbe Associates Ltd.",
    "wof:placetype":"venue"
},
  "geometry": {"coordinates":[-2.07829,52.315601],"type":"Point"}
}