{
  "type": "Feature",
  "properties": {
    "addr:full":"4 St Andrews Road Carshalton Surrey SM5 2DY",
    "addr:housenumber":"4",
    "addr:postcode":"sm5 2dy",
    "addr:street":"St Andrews Road",
    "iso:country":"GB",
    "sg:address":"4 St Andrews Road",
    "sg:city":"Carshalton",
    "sg:classifiers":[
        {
            "category":"Retail",
            "subcategory":"Driving School",
            "type":"Services"
        }
    ],
    "sg:postcode":"SM5 2DY",
    "sg:province":"Surrey",
    "wof:name":"Nicholls School of Motoring",
    "wof:placetype":"venue"
},
  "geometry": {"coordinates":[-0.171466,51.37294],"type":"Point"}
}