{
  "type": "Feature",
  "properties": {
    "addr:full":"64 Brook Street Chorley Lancashire PR7 3BE",
    "addr:housenumber":"64",
    "addr:postcode":"pr7 3be",
    "addr:street":"Brook Street",
    "iso:country":"GB",
    "sg:address":"64 Brook Street",
    "sg:city":"Chorley",
    "sg:classifiers":[
        {
            "category":"Restaurant",
            "type":"Food & Drink"
        }
    ],
    "sg:phone":"+44 1257 234235",
    "sg:postcode":"PR7 3BE",
    "sg:province":"Lancashire",
    "sg:tags":[
        "indian"
    ],
    "wof:name":"Veena (Indian Cuisine)",
    "wof:placetype":"venue"
},
  "geometry": {"coordinates":[-2.624637,53.649281],"type":"Point"}
}