{
  "type": "Feature",
  "properties": {
    "iso:country":"GB",
    "sg:address":"250 Smithdown Road",
    "sg:city":"Liverpool",
    "sg:classifiers":[
        {
            "category":"Fast Food",
            "type":"Food & Drink"
        }
    ],
    "sg:phone":"+44 151 733 3555",
    "sg:postcode":"L15 5AH",
    "sg:province":"Merseyside",
    "sg:tags":[
        "away",
        "take"
    ],
    "wof:name":"Zains Pizza & Kebab House",
    "wof:placetype":"venue"
},
  "geometry": {"coordinates":[-2.92571,53.389729],"type":"Point"}
}