{
  "type": "Feature",
  "properties": {
    "addr:full":"1b Vaughan Court Middlesbrough North Yorkshire TS6 7BJ",
    "addr:housenumber":"1b",
    "addr:postcode":"ts6 7bj",
    "addr:street":"Vaughan Court",
    "iso:country":"GB",
    "sg:address":"1b Vaughan Court",
    "sg:city":"Middlesbrough",
    "sg:classifiers":[
        {
            "category":"Retail",
            "subcategory":"Auto Repair",
            "type":"Services"
        }
    ],
    "sg:postcode":"TS6 7BJ",
    "sg:province":"North Yorkshire",
    "sg:tags":[
        "bodybuilder",
        "repairer"
    ],
    "wof:name":"Gary Harker & Gary Brown",
    "wof:placetype":"venue"
},
  "geometry": {"coordinates":[-1.1454709768,54.5810890198],"type":"Point"}
}