{
  "type": "Feature",
  "properties": {
    "iso:country":"GB",
    "sg:address":"School Green",
    "sg:city":"Lasswade",
    "sg:classifiers":[
        {
            "category":"Farming",
            "subcategory":"Nursery",
            "type":"Manufacturing & Wholesale Goods"
        }
    ],
    "sg:phone":"+44 131 654 2914",
    "sg:postcode":"EH18 1NB",
    "sg:province":"City of Edinburgh",
    "sg:tags":[
        "creche"
    ],
    "wof:name":"Pinocchio's Childrens Nurseries Ltd.",
    "wof:placetype":"venue"
},
  "geometry": {"coordinates":[-3.115752,55.882702],"type":"Point"}
}