{
  "type": "Feature",
  "properties": {
    "addr:full":"255a Finchley Road London Greater London NW3 6LU",
    "addr:housenumber":"255a",
    "addr:postcode":"nw3 6lu",
    "addr:street":"Finchley Road",
    "iso:country":"GB",
    "sg:address":"255a Finchley Road",
    "sg:city":"London",
    "sg:classifiers":[
        {
            "category":"Sports & Exercise",
            "subcategory":"Gym",
            "type":"Entertainment"
        }
    ],
    "sg:phone":"+44 20 7644 2400",
    "sg:postcode":"NW3 6LU",
    "sg:province":"Greater London",
    "sg:tags":[
        "fitness",
        "health",
        "centre"
    ],
    "wof:name":"Esporta Stoke Health & Fitness Club",
    "wof:placetype":"venue"
},
  "geometry": {"coordinates":[-0.180990994,51.5482025146],"type":"Point"}
}