{
  "type": "Feature",
  "properties": {
    "iso:country":"GB",
    "sg:address":"Alexandra Court, 25 St Leonards Road",
    "sg:city":"Windsor",
    "sg:classifiers":[
        {
            "category":"Food & Beverages",
            "subcategory":"Liquor & Beverages",
            "type":"Retail Goods"
        }
    ],
    "sg:phone":"+44 1753 752600",
    "sg:postcode":"SL4 3BP",
    "sg:province":"Berkshire",
    "sg:tags":[
        "beer",
        "spirit",
        "wines"
    ],
    "wof:name":"Phoebus Business Services Ltd.",
    "wof:placetype":"venue"
},
  "geometry": {"coordinates":[-0.612175,51.479324],"type":"Point"}
}