{
  "type": "Feature",
  "properties": {
    "addr:full":"Poolside Farm Keith Moray AB55 5HX",
    "addr:postcode":"ab55 5hx",
    "addr:street":"Poolside;Keith",
    "iso:country":"GB",
    "sg:address":"Poolside Farm",
    "sg:city":"Keith",
    "sg:classifiers":[
        {
            "category":"Farming",
            "subcategory":"Livestock Farm",
            "type":"Manufacturing & Wholesale Goods"
        }
    ],
    "sg:phone":"+44 1542 810251",
    "sg:postcode":"AB55 5HX",
    "sg:province":"Moray",
    "sg:tags":[
        "others"
    ],
    "wof:name":"P & G Cox",
    "wof:placetype":"venue"
},
  "geometry": {"coordinates":[-2.9504199028,57.5432357788],"type":"Point"}
}