{
  "type": "Feature",
  "properties": {
    "addr:full":"Manor Rd Chesterfield Derbyshire S43 1NT",
    "addr:postcode":"s43 1nt",
    "addr:street":"Manor Rd",
    "iso:country":"GB",
    "sg:address":"Manor Rd",
    "sg:city":"Chesterfield",
    "sg:classifiers":[
        {
            "category":"Education",
            "subcategory":"School",
            "type":"Public Place"
        }
    ],
    "sg:phone":"+44 1246 234078",
    "sg:postcode":"S43 1NT",
    "sg:province":"Derbyshire",
    "sg:tags":[
        "local",
        "authority"
    ],
    "wof:name":"Brimington Manor Infant School",
    "wof:placetype":"venue"
},
  "geometry": {"coordinates":[-1.393392,53.255844],"type":"Point"}
}