{
  "type": "Feature",
  "properties": {
    "addr:full":"1 Diamond Way, Stone Business Park Stone Staffordshire ST15 0SD",
    "addr:housenumber":"1",
    "addr:postcode":"st15 0sd",
    "addr:street":"Diamond Way Stone Business Park",
    "iso:country":"GB",
    "sg:address":"1 Diamond Way, Stone Business Park",
    "sg:city":"Stone",
    "sg:classifiers":[
        {
            "category":"Real Estate",
            "subcategory":"Developer",
            "type":"Services"
        }
    ],
    "sg:phone":"+44 1785 286868",
    "sg:postcode":"ST15 0SD",
    "sg:province":"Staffordshire",
    "sg:tags":[
        "property"
    ],
    "wof:name":"H & H Holman Properties Ltd.",
    "wof:placetype":"venue"
},
  "geometry": {"coordinates":[-2.139394,52.886532],"type":"Point"}
}