{
  "type": "Feature",
  "properties": {
    "iso:country":"GB",
    "sg:address":"33 The Street, Shelford",
    "sg:city":"Guildford",
    "sg:classifiers":[
        {
            "category":"Professional",
            "subcategory":"Management & Consulting",
            "type":"Services"
        }
    ],
    "sg:phone":"+44 1483 739400",
    "sg:postcode":"GU4 8EU",
    "sg:province":"Surrey",
    "sg:tags":[
        "consultant",
        "business"
    ],
    "wof:name":"Blue Sky Consulting",
    "wof:placetype":"venue"
},
  "geometry": {"coordinates":[-0.568929,51.219105],"type":"Point"}
}