{
  "type": "Feature",
  "properties": {
    "addr:full":"319 Mile Oak Rd, Portslade Brighton East Sussex BN41 2RB",
    "addr:housenumber":"319",
    "addr:postcode":"bn41 2rb",
    "addr:street":"Mile Oak Rd",
    "iso:country":"GB",
    "sg:address":"319 Mile Oak Rd, Portslade",
    "sg:city":"Brighton",
    "sg:classifiers":[
        {
            "category":"Personal",
            "subcategory":"Beauty Salon",
            "type":"Services"
        }
    ],
    "sg:phone":"+44 1273 418001",
    "sg:postcode":"BN41 2RB",
    "sg:province":"East Sussex",
    "sg:tags":[
        "lady",
        "hairdresser"
    ],
    "wof:name":"Town & Country",
    "wof:placetype":"venue"
},
  "geometry": {"coordinates":[-0.231639,50.851009],"type":"Point"}
}