{
  "type": "Feature",
  "properties": {
    "addr:full":"50 Frinton Road, Kirby Cross Frinton-on-sea Essex CO13 0LE",
    "addr:housenumber":"50",
    "addr:postcode":"co13 0le",
    "addr:street":"Frinton Road",
    "iso:country":"GB",
    "sg:address":"50 Frinton Road, Kirby Cross",
    "sg:city":"Frinton-on-sea",
    "sg:classifiers":[
        {
            "category":"Building & Trades",
            "subcategory":"Construction",
            "type":"Services"
        }
    ],
    "sg:postcode":"CO13 0LE",
    "sg:province":"Essex",
    "sg:tags":[
        "builder"
    ],
    "wof:name":"Alpha Building Co. Ltd.",
    "wof:placetype":"venue"
},
  "geometry": {"coordinates":[1.223924,51.842049],"type":"Point"}
}