{
  "type": "Feature",
  "properties": {
    "addr:full":"33 Sandford Road Weston-super-mare Somerset BS23 3EX",
    "addr:housenumber":"33",
    "addr:postcode":"bs23 3ex",
    "addr:street":"Sandford Road",
    "iso:country":"GB",
    "sg:address":"33 Sandford Road",
    "sg:city":"Weston-super-mare",
    "sg:classifiers":[
        {
            "category":"Sports & Exercise",
            "subcategory":"Stables",
            "type":"Entertainment"
        }
    ],
    "sg:phone":"+44 1934 622395",
    "sg:postcode":"BS23 3EX",
    "sg:province":"Somerset",
    "sg:tags":[
        "education",
        "equestrian"
    ],
    "wof:name":"Vowles Riding Stables",
    "wof:placetype":"venue"
},
  "geometry": {"coordinates":[-2.962663,51.346512],"type":"Point"}
}