{
  "type": "Feature",
  "properties": {
    "addr:full":"The Airfield Indstl Est, Beverley Rd, Hutton, Cranswick Driffield East Riding of Yorkshire YO25 9QE",
    "addr:postcode":"yo25 9qe",
    "addr:street":"Beverley Rd",
    "iso:country":"GB",
    "sg:address":"The Airfield Indstl Est, Beverley Rd, Hutton, Cranswick",
    "sg:city":"Driffield",
    "sg:classifiers":[
        {
            "category":"Cemetery",
            "type":"Public Place"
        }
    ],
    "sg:phone":"+44 1377 270222",
    "sg:postcode":"YO25 9QE",
    "sg:province":"East Riding of Yorkshire",
    "sg:tags":[
        "coffin"
    ],
    "wof:name":"Carrwood Funeral Supplies Ltd",
    "wof:placetype":"venue"
},
  "geometry": {"coordinates":[-0.44507,53.957504],"type":"Point"}
}