{
  "type": "Feature",
  "properties": {
    "addr:full":"6a Glazbury Rd West Kensington Greater London W14 9AS",
    "addr:housenumber":"6a",
    "addr:postcode":"w14 9as",
    "addr:street":"Glazbury Rd",
    "iso:country":"GB",
    "sg:address":"6a Glazbury Rd",
    "sg:city":"West Kensington",
    "sg:classifiers":[
        {
            "category":"Building & Trades",
            "subcategory":"Landscaping Services",
            "type":"Services"
        }
    ],
    "sg:phone":"+44 20 7603 8025",
    "sg:postcode":"W14 9AS",
    "sg:province":"Greater London",
    "sg:tags":[
        "landscape",
        "contractor"
    ],
    "wof:name":"Simon Fraser",
    "wof:placetype":"venue"
},
  "geometry": {"coordinates":[-0.211342,51.491653],"type":"Point"}
}