{
  "type": "Feature",
  "properties": {
    "addr:full":"13 St Georges Place Brighton East Sussex BN1 4GB",
    "addr:housenumber":"13",
    "addr:postcode":"bn1 4gb",
    "addr:street":"St Georges Place",
    "iso:country":"GB",
    "sg:address":"13 St Georges Place",
    "sg:city":"Brighton",
    "sg:classifiers":[
        {
            "category":"Health Services",
            "subcategory":"Dentist",
            "type":"Services"
        }
    ],
    "sg:phone":"+44 1273 683233",
    "sg:postcode":"BN1 4GB",
    "sg:province":"East Sussex",
    "wof:name":"K Mayall & Associates",
    "wof:placetype":"venue"
},
  "geometry": {"coordinates":[-0.1364289969,50.8271865845],"type":"Point"}
}