{
  "type": "Feature",
  "properties": {
    "addr:full":"11 West Close Norwich Norfolk NR5 0NH",
    "addr:housenumber":"11",
    "addr:postcode":"nr5 0nh",
    "addr:street":"West Close",
    "iso:country":"GB",
    "sg:address":"11 West Close",
    "sg:city":"Norwich",
    "sg:classifiers":[
        {
            "category":"Retail",
            "subcategory":"Repair Shop",
            "type":"Services"
        }
    ],
    "sg:postcode":"NR5 0NH",
    "sg:province":"Norfolk",
    "sg:tags":[
        "radio",
        "television",
        "video"
    ],
    "wof:name":"Brighton Television",
    "wof:placetype":"venue"
},
  "geometry": {"coordinates":[1.223776,52.649273],"type":"Point"}
}