{
  "type": "Feature",
  "properties": {
    "iso:country":"GB",
    "sg:address":"Calder Road",
    "sg:city":"Edinburgh",
    "sg:classifiers":[
        {
            "category":"Bars & Pubs",
            "type":"Food & Drink"
        }
    ],
    "sg:phone":"+44 131 443 3599",
    "sg:postcode":"EH11 4AH",
    "sg:province":"City of Edinburgh",
    "sg:tags":[
        "pubs",
        "inn"
    ],
    "wof:name":"Silver Wing",
    "wof:placetype":"venue"
},
  "geometry": {"coordinates":[-3.271134,55.926102],"type":"Point"}
}