{
  "type": "Feature",
  "properties": {
    "addr:full":"St Peters Square Ruthin Denbighshire LL15 1DH",
    "addr:postcode":"ll15 1dh",
    "addr:street":"Square",
    "iso:country":"GB",
    "sg:address":"St Peters Square",
    "sg:city":"Ruthin",
    "sg:classifiers":[
        {
            "category":"Shopping",
            "subcategory":"Baby Store",
            "type":"Retail Goods"
        }
    ],
    "sg:phone":"+44 1824 702329",
    "sg:postcode":"LL15 1DH",
    "sg:province":"Denbighshire",
    "sg:tags":[
        "babywear",
        "childrens"
    ],
    "wof:name":"Ethel Austin",
    "wof:placetype":"venue"
},
  "geometry": {"coordinates":[-3.3108038902,53.1147155762],"type":"Point"}
}