{
  "type": "Feature",
  "properties": {
    "addr:full":"Beresford Clo Benfleet Essex SS7 2SB",
    "addr:postcode":"ss7 2sb",
    "addr:street":"Benfleet",
    "iso:country":"GB",
    "sg:address":"Beresford Clo",
    "sg:city":"Benfleet",
    "sg:classifiers":[
        {
            "category":"Health Services",
            "subcategory":"Nursing And Care Facility",
            "type":"Services"
        }
    ],
    "sg:phone":"+44 1702 554194",
    "sg:postcode":"SS7 2SB",
    "sg:province":"Essex",
    "sg:tags":[
        "home"
    ],
    "wof:name":"John Groom Association For Disabled People",
    "wof:placetype":"venue"
},
  "geometry": {"coordinates":[0.604391,51.558514],"type":"Point"}
}