{
  "type": "Feature",
  "properties": {
    "iso:country":"GB",
    "sg:address":"18 Victoria Street",
    "sg:city":"Wolverhampton",
    "sg:classifiers":[
        {
            "category":"Shopping",
            "subcategory":"Bicycles & Sporting Goods",
            "type":"Retail Goods"
        }
    ],
    "sg:phone":"+44 1902 423513",
    "sg:postcode":"WV1 3NP",
    "sg:province":"West Midlands",
    "sg:tags":[
        "cycle",
        "accessory"
    ],
    "wof:name":"Bd Price",
    "wof:placetype":"venue"
},
  "geometry": {"coordinates":[-2.129735,52.584396],"type":"Point"}
}