{
  "type": "Feature",
  "properties": {
    "addr:full":"4 St Owen St Hereford Herefordshire HR1 2JB",
    "addr:housenumber":"4",
    "addr:postcode":"hr1 2jb",
    "addr:street":"St Owen St",
    "iso:country":"GB",
    "sg:address":"4 St Owen St",
    "sg:city":"Hereford",
    "sg:classifiers":[
        {
            "category":"Education",
            "subcategory":"Music School",
            "type":"Public Place"
        }
    ],
    "sg:phone":"+44 1432 267099",
    "sg:postcode":"HR1 2JB",
    "sg:province":"Herefordshire",
    "wof:name":"Yamaha Music School",
    "wof:placetype":"venue"
},
  "geometry": {"coordinates":[-2.7133591175,52.0558509827],"type":"Point"}
}