{
  "type": "Feature",
  "properties": {
    "iso:country":"GB",
    "sg:address":"2 Pobs Drive, Corpach",
    "sg:city":"Fort William",
    "sg:classifiers":[
        {
            "category":"Communications",
            "subcategory":"Film & Video Production",
            "type":"Services"
        }
    ],
    "sg:phone":"+44 1397 772464",
    "sg:postcode":"PH33 7JP",
    "sg:province":"Highland",
    "sg:tags":[
        "illustrator",
        "artist"
    ],
    "wof:name":"Felicity Nightingale",
    "wof:placetype":"venue"
},
  "geometry": {"coordinates":[-5.1278648376,56.8438072205],"type":"Point"}
}