{
  "type": "Feature",
  "properties": {
    "iso:country":"GB",
    "sg:address":"9a Railway Rd",
    "sg:city":"Darwen",
    "sg:classifiers":[
        {
            "category":"Fast Food",
            "type":"Food & Drink"
        }
    ],
    "sg:postcode":"BB3 2RG",
    "sg:province":"Lancashire",
    "sg:tags":[
        "away",
        "take"
    ],
    "wof:name":"Swaad Indian Restaurant & Takeaway",
    "wof:placetype":"venue"
},
  "geometry": {"coordinates":[-2.465647,53.69614],"type":"Point"}
}