{
  "type": "Feature",
  "properties": {
    "addr:full":"47 Market Street, Nailsworth Stroud Gloucestershire GL6 0BX",
    "addr:housenumber":"47",
    "addr:postcode":"gl6 0bx",
    "addr:street":"Market Street",
    "iso:country":"GB",
    "sg:address":"47 Market Street, Nailsworth",
    "sg:city":"Stroud",
    "sg:classifiers":[
        {
            "category":"Personal",
            "subcategory":"Beauty Salon",
            "type":"Services"
        }
    ],
    "sg:phone":"+44 1453 835750",
    "sg:postcode":"GL6 0BX",
    "sg:province":"Gloucestershire",
    "sg:tags":[
        "unisex",
        "hairdresser"
    ],
    "wof:name":"Gyles & Allen",
    "wof:placetype":"venue"
},
  "geometry": {"coordinates":[-2.219175,51.694183],"type":"Point"}
}