{
  "type": "Feature",
  "properties": {
    "addr:full":"Brook Farm Wellingborough Northamptonshire NN8 4BW",
    "addr:postcode":"nn8 4bw",
    "addr:street":"Brook",
    "iso:country":"GB",
    "sg:address":"Brook Farm",
    "sg:city":"Wellingborough",
    "sg:classifiers":[
        {
            "category":"Wholesale",
            "subcategory":"Scrap",
            "type":"Manufacturing & Wholesale Goods"
        }
    ],
    "sg:postcode":"NN8 4BW",
    "sg:province":"Northamptonshire",
    "sg:tags":[
        "car",
        "breaker",
        "dismantlers"
    ],
    "wof:name":"Hicklins Car Breakers",
    "wof:placetype":"venue"
},
  "geometry": {"coordinates":[-0.696296,52.302422],"type":"Point"}
}