{
  "type": "Feature",
  "properties": {
    "addr:full":"6 Greenacre Close Chatham Kent ME5 7JJ",
    "addr:housenumber":"6",
    "addr:postcode":"me5 7jj",
    "addr:street":"Greenacre Close",
    "iso:country":"GB",
    "sg:address":"6 Greenacre Close",
    "sg:city":"Chatham",
    "sg:classifiers":[
        {
            "category":"Professional",
            "subcategory":"Lawyer & Legal Services",
            "type":"Services"
        }
    ],
    "sg:phone":"+44 1634 301811",
    "sg:postcode":"ME5 7JJ",
    "sg:province":"Kent",
    "sg:tags":[
        "advice",
        "counselling"
    ],
    "wof:name":"Rosaline Bleasdale",
    "wof:placetype":"venue"
},
  "geometry": {"coordinates":[0.52737,51.348579],"type":"Point"}
}