{
  "type": "Feature",
  "properties": {
    "addr:full":"71 Thomson Drive, Bearsden Glasgow East Dunbartonshire G61 3PB",
    "addr:housenumber":"71",
    "addr:postcode":"g61 3pb",
    "addr:street":"Thomson Drive",
    "iso:country":"GB",
    "sg:address":"71 Thomson Drive, Bearsden",
    "sg:city":"Glasgow",
    "sg:classifiers":[
        {
            "category":"Utilities",
            "subcategory":"Mobile Phone",
            "type":"Services"
        }
    ],
    "sg:phone":"+44 141 956 5575",
    "sg:postcode":"G61 3PB",
    "sg:province":"East Dunbartonshire",
    "sg:tags":[
        "battery",
        "supplier"
    ],
    "wof:name":"Battery Services (Standby) Ltd.",
    "wof:placetype":"venue"
},
  "geometry": {"coordinates":[-4.3261270523,55.9274406433],"type":"Point"}
}