{
  "type": "Feature",
  "properties": {
    "addr:full":"Unit 3g, Nevendon Trading Estate, Harvey Road Basildon Essex SS13 1DA",
    "addr:postcode":"ss13 1da",
    "addr:street":"Harvey Road",
    "iso:country":"GB",
    "sg:address":"Unit 3g, Nevendon Trading Estate, Harvey Road",
    "sg:city":"Basildon",
    "sg:classifiers":[
        {
            "category":"Shopping",
            "subcategory":"Stationery & Office Supplies",
            "type":"Retail Goods"
        }
    ],
    "sg:phone":"+44 1268 729811",
    "sg:postcode":"SS13 1DA",
    "sg:province":"Essex",
    "sg:tags":[
        "printers'"
    ],
    "wof:name":"Onform (Dies) Ltd.",
    "wof:placetype":"venue"
},
  "geometry": {"coordinates":[0.50823,51.585159],"type":"Point"}
}