{
  "type": "Feature",
  "properties": {
    "addr:full":"1 Chieveley Parade, Mayplace Road East Bexleyheath Kent DA7 6EB",
    "addr:housenumber":"1",
    "addr:postcode":"da7 6eb",
    "addr:street":"Chieveley Parade Mayplace Road East",
    "iso:country":"GB",
    "sg:address":"1 Chieveley Parade, Mayplace Road East",
    "sg:city":"Bexleyheath",
    "sg:classifiers":[
        {
            "category":"Food & Beverages",
            "subcategory":"Fruits & Vegetables",
            "type":"Retail Goods"
        }
    ],
    "sg:phone":"+44 1322 529904",
    "sg:postcode":"DA7 6EB",
    "sg:province":"Kent",
    "sg:tags":[
        "greengrocer"
    ],
    "wof:name":"E & C Fruiterers",
    "wof:placetype":"venue"
},
  "geometry": {"coordinates":[0.1531179994,51.4589729309],"type":"Point"}
}