{
  "type": "Feature",
  "properties": {
    "addr:full":"11 Wells Road Ilkley North Yorkshire LS29 9JB",
    "addr:housenumber":"11",
    "addr:postcode":"ls29 9jb",
    "addr:street":"Wells Road",
    "iso:country":"GB",
    "sg:address":"11 Wells Road",
    "sg:city":"Ilkley",
    "sg:classifiers":[
        {
            "category":"Health Services",
            "subcategory":"Doctor",
            "type":"Services"
        },
        {
            "category":"Health Services",
            "subcategory":"Podiatrist",
            "type":"Services"
        }
    ],
    "sg:phone":"+44 1943 816911",
    "sg:postcode":"LS29 9JB",
    "sg:province":"North Yorkshire",
    "sg:tags":[
        "podiatrists",
        "chiropodist"
    ],
    "wof:name":"Dale Halford",
    "wof:placetype":"venue"
},
  "geometry": {"coordinates":[-1.823769,53.923672],"type":"Point"}
}