{
  "type": "Feature",
  "properties": {
    "addr:full":"40 Kings Road, Cowplain Waterlooville Hampshire PO8 8UR",
    "addr:housenumber":"40",
    "addr:postcode":"po8 8ur",
    "addr:street":"Kings Road",
    "iso:country":"GB",
    "sg:address":"40 Kings Road, Cowplain",
    "sg:city":"Waterlooville",
    "sg:classifiers":[
        {
            "category":"Building & Trades",
            "subcategory":"Construction",
            "type":"Services"
        }
    ],
    "sg:phone":"+44 23 9226 2386",
    "sg:postcode":"PO8 8UR",
    "sg:province":"Hampshire",
    "sg:tags":[
        "heating",
        "contractor"
    ],
    "wof:name":"Dregaire (Waterlooville) Ltd.",
    "wof:placetype":"venue"
},
  "geometry": {"coordinates":[-1.0226830244,50.8947715759],"type":"Point"}
}