{
  "type": "Feature",
  "properties": {
    "addr:full":"2 Cartsdyke Avenue Greenock Inverclyde PA15 1DT",
    "addr:housenumber":"2",
    "addr:postcode":"pa15 1dt",
    "addr:street":"Cartsdyke Avenue Greenock",
    "iso:country":"GB",
    "sg:address":"2 Cartsdyke Avenue",
    "sg:city":"Greenock",
    "sg:classifiers":[
        {
            "category":"Professional",
            "subcategory":"Computer Services",
            "type":"Services"
        }
    ],
    "sg:phone":"+44 1475 787878",
    "sg:postcode":"PA15 1DT",
    "sg:province":"Inverclyde",
    "sg:tags":[
        "system",
        "software"
    ],
    "wof:name":"Systemax Europe Ltd.",
    "wof:placetype":"venue"
},
  "geometry": {"coordinates":[-4.7371459007,55.9451026917],"type":"Point"}
}