{
  "type": "Feature",
  "properties": {
    "iso:country":"GB",
    "sg:address":"Well House, Well Lane",
    "sg:city":"Haslemere",
    "sg:classifiers":[
        {
            "category":"Building & Trades",
            "subcategory":"Cleaning & Sanitation",
            "type":"Services"
        },
        {
            "category":"Professional",
            "subcategory":"Business Services",
            "type":"Services"
        }
    ],
    "sg:phone":"+44 1428 658903",
    "sg:postcode":"GU27 2LB",
    "sg:province":"Hampshire",
    "sg:tags":[
        "shop",
        "contracting",
        "commercial",
        "contractor"
    ],
    "wof:name":"Excalibur Cleaning Ltd",
    "wof:placetype":"venue"
},
  "geometry": {"coordinates":[-0.70791,51.08902],"type":"Point"}
}