{
  "type": "Feature",
  "properties": {
    "addr:full":"Lowerside Road Glastonbury Somerset BA6 9BH",
    "addr:postcode":"ba6 9bh",
    "addr:street":"Lowerside Road",
    "iso:country":"GB",
    "sg:address":"Lowerside Road",
    "sg:city":"Glastonbury",
    "sg:classifiers":[
        {
            "category":"Arena",
            "subcategory":"Sports Club",
            "type":"Entertainment"
        }
    ],
    "sg:phone":"+44 1458 832236",
    "sg:postcode":"BA6 9BH",
    "sg:province":"Somerset",
    "wof:name":"Tor Rugby Club",
    "wof:placetype":"venue"
},
  "geometry": {"coordinates":[-2.7155439854,51.1558837891],"type":"Point"}
}