{
  "type": "Feature",
  "properties": {
    "addr:full":"1103 Bristol Road Birmingham West Midlands B29 6LX",
    "addr:housenumber":"1103",
    "addr:postcode":"b29 6lx",
    "addr:street":"Bristol Road",
    "iso:country":"GB",
    "sg:address":"1103 Bristol Road",
    "sg:city":"Birmingham",
    "sg:classifiers":[
        {
            "category":"Retail",
            "subcategory":"Auto Repair",
            "type":"Services"
        }
    ],
    "sg:phone":"+44 121 477 0900",
    "sg:postcode":"B29 6LX",
    "sg:province":"West Midlands",
    "sg:tags":[
        "modification",
        "garage"
    ],
    "wof:name":"Witherford Garage",
    "wof:placetype":"venue"
},
  "geometry": {"coordinates":[-1.9496070147,52.4313697815],"type":"Point"}
}