{
  "type": "Feature",
  "properties": {
    "addr:full":"11 St Marys Way, Thornbury Bristol Gloucestershire BS35 2BH",
    "addr:housenumber":"11",
    "addr:postcode":"bs35 2bh",
    "addr:street":"St Marys Way",
    "iso:country":"GB",
    "sg:address":"11 St Marys Way, Thornbury",
    "sg:city":"Bristol",
    "sg:classifiers":[
        {
            "category":"Shopping",
            "subcategory":"Gifts & Souvenirs",
            "type":"Retail Goods"
        }
    ],
    "sg:phone":"+44 1454 419997",
    "sg:postcode":"BS35 2BH",
    "sg:province":"Gloucestershire",
    "sg:tags":[
        "poster",
        "card"
    ],
    "wof:name":"Occasions & Papertree",
    "wof:placetype":"venue"
},
  "geometry": {"coordinates":[-2.525036,51.606609],"type":"Point"}
}