{
  "type": "Feature",
  "properties": {
    "addr:full":"Oakmount Road, Chandlers Ford Eastleigh Hampshire SO53 2LN",
    "addr:postcode":"so53 2ln",
    "addr:street":"Oakmount Road",
    "iso:country":"GB",
    "sg:address":"Oakmount Road, Chandlers Ford",
    "sg:city":"Eastleigh",
    "sg:classifiers":[
        {
            "category":"Education",
            "subcategory":"School",
            "type":"Public Place"
        }
    ],
    "sg:phone":"+44 23 8026 5931",
    "sg:postcode":"SO53 2LN",
    "sg:province":"Hampshire",
    "sg:tags":[
        "local",
        "authority"
    ],
    "wof:name":"Fryern Infant School",
    "wof:placetype":"venue"
},
  "geometry": {"coordinates":[-1.3737529516,50.9875831604],"type":"Point"}
}