{
  "type": "Feature",
  "properties": {
    "addr:full":"9 Burns Crescent Chelmsford Essex CM2 0TS",
    "addr:housenumber":"9",
    "addr:postcode":"cm2 0ts",
    "addr:street":"Burns Crescent",
    "iso:country":"GB",
    "sg:address":"9 Burns Crescent",
    "sg:city":"Chelmsford",
    "sg:classifiers":[
        {
            "category":"Retail",
            "subcategory":"Driving School",
            "type":"Services"
        }
    ],
    "sg:phone":"+44 1245 354913",
    "sg:postcode":"CM2 0TS",
    "sg:province":"Essex",
    "wof:name":"R F CANT",
    "wof:placetype":"venue"
},
  "geometry": {"coordinates":[0.475573,51.725143],"type":"Point"}
}