{
  "type": "Feature",
  "properties": {
    "iso:country":"GB",
    "sg:address":"Hills Lane, Unsworth",
    "sg:city":"Bury",
    "sg:classifiers":[
        {
            "category":"Sports & Exercise",
            "subcategory":"Golf",
            "type":"Entertainment"
        }
    ],
    "sg:postcode":"BL9 8QP",
    "sg:province":"Lancashire",
    "sg:tags":[
        "club",
        "course"
    ],
    "wof:name":"Pike Fold Golf Club",
    "wof:placetype":"venue"
},
  "geometry": {"coordinates":[-2.26826,53.55743],"type":"Point"}
}