{
  "type": "Feature",
  "properties": {
    "addr:full":"1 Millindale, Maltby Rotherham South Yorkshire S66 7LE",
    "addr:housenumber":"1",
    "addr:postcode":"s66 7le",
    "addr:street":"Millindale Maltby",
    "iso:country":"GB",
    "sg:address":"1 Millindale, Maltby",
    "sg:city":"Rotherham",
    "sg:classifiers":[
        {
            "category":"Professional",
            "subcategory":"Engineering",
            "type":"Services"
        }
    ],
    "sg:phone":"+44 1709 817411",
    "sg:postcode":"S66 7LE",
    "sg:province":"South Yorkshire",
    "sg:tags":[
        "contractor",
        "electrical",
        "engineer"
    ],
    "wof:name":"Len J 0'NEILE Electrician",
    "wof:placetype":"venue"
},
  "geometry": {"coordinates":[-1.202226,53.42178],"type":"Point"}
}