{
  "type": "Feature",
  "properties": {
    "addr:full":"The Crescent Truro Cornwall TR1 3ES",
    "addr:postcode":"tr1 3es",
    "addr:street":"The Crescent",
    "iso:country":"GB",
    "sg:address":"The Crescent",
    "sg:city":"Truro",
    "sg:classifiers":[
        {
            "category":"Health Services",
            "subcategory":"Nursing And Care Facility",
            "type":"Services"
        }
    ],
    "sg:phone":"+44 1872 271921",
    "sg:postcode":"TR1 3ES",
    "sg:province":"Cornwall",
    "sg:tags":[
        "home"
    ],
    "wof:name":"Dove Care Homes Ltd.",
    "wof:placetype":"venue"
},
  "geometry": {"coordinates":[-5.063718,50.26292],"type":"Point"}
}