{
  "type": "Feature",
  "properties": {
    "addr:full":"34 Sandling Rd Maidstone Kent ME14 2RF",
    "addr:housenumber":"34",
    "addr:postcode":"me14 2rf",
    "addr:street":"Sandling Rd",
    "iso:country":"GB",
    "sg:address":"34 Sandling Rd",
    "sg:city":"Maidstone",
    "sg:classifiers":[
        {
            "category":"Insurance",
            "subcategory":"Insurance Agent",
            "type":"Services"
        }
    ],
    "sg:phone":"+44 1622 688271",
    "sg:postcode":"ME14 2RF",
    "sg:province":"Kent",
    "sg:tags":[
        "broker"
    ],
    "wof:name":"Sheldwich Insurance Agencies Ltd",
    "wof:placetype":"venue"
},
  "geometry": {"coordinates":[0.520166,51.279713],"type":"Point"}
}