{
  "type": "Feature",
  "properties": {
    "iso:country":"GB",
    "sg:address":"2 Granville Road",
    "sg:city":"Totland Bay",
    "sg:classifiers":[
        {
            "category":"Shopping",
            "subcategory":"Department Store",
            "type":"Retail Goods"
        },
        {
            "category":"Professional",
            "subcategory":"Business Services",
            "type":"Services"
        }
    ],
    "sg:postcode":"PO39 0AX",
    "sg:province":"Isle of Wight",
    "sg:tags":[
        "import",
        "export",
        "agent"
    ],
    "wof:name":"Granville Export Import Marketing",
    "wof:placetype":"venue"
},
  "geometry": {"coordinates":[-1.546521,50.678787],"type":"Point"}
}