{
  "type": "Feature",
  "properties": {
    "iso:country":"GB",
    "sg:address":"Westborough Road",
    "sg:city":"Maidenhead",
    "sg:classifiers":[
        {
            "category":"Education",
            "subcategory":"School",
            "type":"Public Place"
        }
    ],
    "sg:phone":"+44 1628 622596",
    "sg:postcode":"SL6 4AR",
    "sg:province":"Berkshire",
    "sg:tags":[
        "local",
        "authority"
    ],
    "wof:name":"All Saints C of E Junior School",
    "wof:placetype":"venue"
},
  "geometry": {"coordinates":[-0.742288,51.518997],"type":"Point"}
}