{
  "type": "Feature",
  "properties": {
    "addr:full":"6 The Gro Ilkley North Yorkshire LS29 9EG",
    "addr:housenumber":"6",
    "addr:postcode":"ls29 9eg",
    "addr:street":"The Gro",
    "iso:country":"GB",
    "sg:address":"6 The Gro",
    "sg:city":"Ilkley",
    "sg:classifiers":[
        {
            "category":"Home & Garden",
            "subcategory":"Furniture",
            "type":"Retail Goods"
        }
    ],
    "sg:postcode":"LS29 9EG",
    "sg:province":"North Yorkshire",
    "wof:name":"The Woodrooms",
    "wof:placetype":"venue"
},
  "geometry": {"coordinates":[-1.8238199949,53.9246826172],"type":"Point"}
}