{
  "type": "Feature",
  "properties": {
    "iso:country":"GB",
    "sg:address":"274 Bath Road",
    "sg:city":"Hounslow",
    "sg:classifiers":[
        {
            "category":"Restaurant",
            "type":"Food & Drink"
        }
    ],
    "sg:phone":"+44 20 8569 6196",
    "sg:postcode":"TW4 7DF",
    "sg:province":"Greater London",
    "sg:tags":[
        "indian"
    ],
    "wof:name":"Chillies",
    "wof:placetype":"venue"
},
  "geometry": {"coordinates":[-0.385021,51.472473],"type":"Point"}
}