{
  "type": "Feature",
  "properties": {
    "iso:country":"GB",
    "sg:address":"Sussex Ho, 143 Long Acre",
    "sg:city":"Holborn",
    "sg:classifiers":[
        {
            "category":"Professional",
            "subcategory":"Computer Services",
            "type":"Services"
        }
    ],
    "sg:phone":"+44 20 7240 5911",
    "sg:postcode":"WC2E 9AD",
    "sg:province":"Greater London",
    "sg:tags":[
        "system",
        "software"
    ],
    "wof:name":"Envisage Virtual Reality Systems Ltd",
    "wof:placetype":"venue"
},
  "geometry": {"coordinates":[-0.1268499941,51.5120010376],"type":"Point"}
}