{
  "type": "Feature",
  "properties": {
    "iso:country":"GB",
    "sg:address":"2 Clare Street",
    "sg:city":"Bristol",
    "sg:classifiers":[
        {
            "category":"Professional",
            "subcategory":"Art Services",
            "type":"Services"
        }
    ],
    "sg:phone":"+44 117 317 9253",
    "sg:postcode":"BS1 1XR",
    "sg:province":"City of Bristol",
    "sg:tags":[
        "graphic",
        "designer"
    ],
    "wof:name":"Co:Media Design Ltd.",
    "wof:placetype":"venue"
},
  "geometry": {"coordinates":[-2.595967,51.453865],"type":"Point"}
}