{
  "type": "Feature",
  "properties": {
    "addr:full":"The Ibis Centre, 5c Church St Tetbury Gloucestershire GL8 8JG",
    "addr:housenumber":"5c",
    "addr:postcode":"gl8 8jg",
    "addr:street":"Church St",
    "iso:country":"GB",
    "sg:address":"The Ibis Centre, 5c Church St",
    "sg:city":"Tetbury",
    "sg:classifiers":[
        {
            "category":"Professional",
            "type":"Services"
        }
    ],
    "sg:phone":"+44 1666 502898",
    "sg:postcode":"GL8 8JG",
    "sg:province":"Gloucestershire",
    "sg:tags":[
        "reflexologists"
    ],
    "wof:name":"Lawler Mr Roger & Mrs Gillian",
    "wof:placetype":"venue"
},
  "geometry": {"coordinates":[-2.1609759331,51.6378593445],"type":"Point"}
}