{
  "type": "Feature",
  "properties": {
    "iso:country":"GB",
    "sg:address":"Unit 5, Myson Way, Off Raynham Close",
    "sg:city":"Bishops Stortford",
    "sg:classifiers":[
        {
            "category":"Home & Garden",
            "subcategory":"Building Materials",
            "type":"Retail Goods"
        },
        {
            "category":"Communications",
            "type":"Services"
        }
    ],
    "sg:phone":"+44 1279 757775",
    "sg:postcode":"CM23 5JZ",
    "sg:province":"Essex",
    "sg:tags":[
        "network",
        "crate",
        "pallet",
        "packing",
        "supplier",
        "data"
    ],
    "wof:name":"MINITRAN LTD",
    "wof:placetype":"venue"
},
  "geometry": {"coordinates":[0.1774760038,51.8713417053],"type":"Point"}
}