{
  "type": "Feature",
  "properties": {
    "iso:country":"GB",
    "sg:address":"63 The Verne",
    "sg:city":"Fleet",
    "sg:classifiers":[
        {
            "category":"Health Services",
            "subcategory":"Podiatrist",
            "type":"Services"
        }
    ],
    "sg:phone":"+44 1252 621717",
    "sg:postcode":"GU13 0LY",
    "sg:province":"Dorset",
    "sg:tags":[
        "podiatrists",
        "chiropodist"
    ],
    "wof:name":"Alan G Robertson",
    "wof:placetype":"venue"
},
  "geometry": {"coordinates":[-0.8387870193,51.2637214661],"type":"Point"}
}