{
  "type": "Feature",
  "properties": {
    "addr:full":"Hamond Road Norwich Norfolk NR6 5RR",
    "addr:postcode":"nr6 5rr",
    "addr:street":"Hamond Road Norwich Norfolk",
    "iso:country":"GB",
    "sg:address":"Hamond Road",
    "sg:city":"Norwich",
    "sg:classifiers":[
        {
            "category":"Government",
            "subcategory":"Department Of Motor Vehicles",
            "type":"Public Place"
        }
    ],
    "sg:postcode":"NR6 5RR",
    "sg:province":"Norfolk",
    "sg:tags":[
        "inspection"
    ],
    "wof:name":"High Level Service Station",
    "wof:placetype":"venue"
},
  "geometry": {"coordinates":[1.2524549961,52.661945343],"type":"Point"}
}