{
  "type": "Feature",
  "properties": {
    "addr:full":"19 Station Parade Virginia Water Surrey GU25 4AE",
    "addr:housenumber":"19",
    "addr:postcode":"gu25 4ae",
    "addr:street":"Station Parade",
    "iso:country":"GB",
    "sg:address":"19 Station Parade",
    "sg:city":"Virginia Water",
    "sg:classifiers":[
        {
            "category":"Wholesale",
            "subcategory":"Fruits & Vegetables",
            "type":"Manufacturing & Wholesale Goods"
        }
    ],
    "sg:postcode":"GU25 4AE",
    "sg:province":"Surrey",
    "wof:name":"Richard's",
    "wof:placetype":"venue"
},
  "geometry": {"coordinates":[-0.5674880147,51.4033622742],"type":"Point"}
}