{
  "type": "Feature",
  "properties": {
    "addr:full":"Gonsal Farm, Gonsal Shrewsbury Shropshire SY5 7ET",
    "addr:postcode":"sy5 7et",
    "addr:street":"Gonsal",
    "iso:country":"GB",
    "sg:address":"Gonsal Farm, Gonsal",
    "sg:city":"Shrewsbury",
    "sg:classifiers":[
        {
            "category":"Travel",
            "subcategory":"Hotels & Motels",
            "type":"Entertainment"
        }
    ],
    "sg:phone":"+44 1743 718007",
    "sg:postcode":"SY5 7ET",
    "sg:province":"Shropshire",
    "sg:tags":[
        "house",
        "guest"
    ],
    "wof:name":"Gonsal Farm Guest House",
    "wof:placetype":"venue"
},
  "geometry": {"coordinates":[-2.76906,52.632858],"type":"Point"}
}