{
  "type": "Feature",
  "properties": {
    "iso:country":"GB",
    "sg:address":"Castle, New Cumnock",
    "sg:city":"Cumnock",
    "sg:classifiers":[
        {
            "category":"Government",
            "subcategory":"Office",
            "type":"Public Place"
        },
        {
            "category":"Sports & Exercise",
            "subcategory":"Swimming Pool",
            "type":"Entertainment"
        }
    ],
    "sg:phone":"+44 1290 338818",
    "sg:postcode":"KA18 4AN",
    "sg:province":"East Ayrshire",
    "sg:tags":[
        "local"
    ],
    "wof:name":"East Ayrshire Council",
    "wof:placetype":"venue"
},
  "geometry": {"coordinates":[-4.1835689545,55.3990058899],"type":"Point"}
}