{
  "type": "Feature",
  "properties": {
    "addr:full":"121 Boroughbridge Rd York East Riding of Yorkshire YO2 6AA",
    "addr:housenumber":"121",
    "addr:postcode":"yo2 6aa",
    "addr:street":"Boroughbridge Rd",
    "iso:country":"GB",
    "sg:address":"121 Boroughbridge Rd",
    "sg:city":"York",
    "sg:classifiers":[
        {
            "category":"Military Area",
            "subcategory":"Air Force Base",
            "type":"Public Place"
        }
    ],
    "sg:phone":"+44 1904 794930",
    "sg:postcode":"YO2 6AA",
    "sg:province":"East Riding of Yorkshire",
    "sg:tags":[
        "taxi",
        "hire",
        "private"
    ],
    "wof:name":"Poppleton Private Hire",
    "wof:placetype":"venue"
},
  "geometry": {"coordinates":[-1.1258759499,53.9660873413],"type":"Point"}
}