{
  "type": "Feature",
  "properties": {
    "addr:full":"64 Muswell Hill Broadway London Greater London N10 3RT",
    "addr:housenumber":"64",
    "addr:postcode":"n10 3rt",
    "addr:street":"Muswell Hill Broadway",
    "iso:country":"GB",
    "sg:address":"64 Muswell Hill Broadway",
    "sg:city":"London",
    "sg:classifiers":[
        {
            "category":"Shopping",
            "subcategory":"Optical Goods",
            "type":"Retail Goods"
        },
        {
            "category":"Health Services",
            "subcategory":"Optometrist",
            "type":"Services"
        },
        {
            "category":"Shopping",
            "subcategory":"Optician",
            "type":"Retail Goods"
        }
    ],
    "sg:phone":"+44 20 8444 0445",
    "sg:postcode":"N10 3RT",
    "sg:province":"Greater London",
    "sg:tags":[
        "medical",
        "ophthalmic"
    ],
    "wof:name":"Observatory the Opticians",
    "wof:placetype":"venue"
},
  "geometry": {"coordinates":[-0.146111995,51.5826683044],"type":"Point"}
}