{
  "type": "Feature",
  "properties": {
    "iso:country":"GB",
    "sg:address":"141 Portland Road, Selston",
    "sg:city":"Nottingham",
    "sg:classifiers":[
        {
            "category":"Personal",
            "subcategory":"Beauty Salon",
            "type":"Services"
        },
        {
            "category":"Personal",
            "subcategory":"Barber",
            "type":"Services"
        }
    ],
    "sg:phone":"+44 1773 810378",
    "sg:postcode":"NG16 6AL",
    "sg:province":"Derbyshire",
    "sg:tags":[
        "unisex",
        "hairdresser"
    ],
    "wof:name":"Arthur Webb Hair Design",
    "wof:placetype":"venue"
},
  "geometry": {"coordinates":[-1.291918993,53.0708503723],"type":"Point"}
}