{
  "type": "Feature",
  "properties": {
    "iso:country":"GB",
    "sg:address":"21 Essex Gardens",
    "sg:city":"Leigh-on-sea",
    "sg:classifiers":[
        {
            "category":"Building & Trades",
            "subcategory":"Construction",
            "type":"Services"
        }
    ],
    "sg:phone":"+44 1702 478983",
    "sg:postcode":"SS9 4HG",
    "sg:province":"Essex",
    "sg:tags":[
        "dry",
        "lining",
        "plasterers",
        "screeders"
    ],
    "wof:name":"N J Wheaton",
    "wof:placetype":"venue"
},
  "geometry": {"coordinates":[0.657078,51.557446],"type":"Point"}
}