{
  "type": "Feature",
  "properties": {
    "iso:country":"GB",
    "sg:address":"Stables Farm, Marshread, Little Kimble",
    "sg:city":"Aylesbury",
    "sg:classifiers":[
        {
            "category":"Building & Trades",
            "subcategory":"Landscaping Services",
            "type":"Services"
        }
    ],
    "sg:postcode":"HP17 8TP",
    "sg:province":"Buckinghamshire",
    "sg:tags":[
        "forestry",
        "tree"
    ],
    "wof:name":"Barnes & Wells Tree Surgeons",
    "wof:placetype":"venue"
},
  "geometry": {"coordinates":[-0.90904,51.775902],"type":"Point"}
}