{
  "type": "Feature",
  "properties": {
    "iso:country":"GB",
    "sg:address":"Front Of Caldew Business Park, Shaddongate",
    "sg:city":"Carlisle",
    "sg:classifiers":[
        {
            "category":"Home & Garden",
            "subcategory":"Hardware",
            "type":"Retail Goods"
        },
        {
            "category":"Shopping",
            "subcategory":"Crafts & Fabrics",
            "type":"Retail Goods"
        }
    ],
    "sg:postcode":"CA2 5TT",
    "sg:province":"Cumbria",
    "sg:tags":[
        "ceramic",
        "retailer",
        "diy"
    ],
    "wof:name":"Caldew Marketing",
    "wof:placetype":"venue"
},
  "geometry": {"coordinates":[-2.9454200268,54.8935203552],"type":"Point"}
}