{
  "type": "Feature",
  "properties": {
    "addr:full":"1 Falsgrave Crescent York North Yorkshire YO30 7AZ",
    "addr:housenumber":"1",
    "addr:postcode":"yo30 7az",
    "addr:street":"Falsgrave Crescent",
    "iso:country":"GB",
    "sg:address":"1 Falsgrave Crescent",
    "sg:city":"York",
    "sg:classifiers":[
        {
            "category":"Fast Food",
            "type":"Food & Drink"
        }
    ],
    "sg:postcode":"YO30 7AZ",
    "sg:province":"North Yorkshire",
    "sg:tags":[
        "away",
        "take"
    ],
    "wof:name":"Sonali Tasty House",
    "wof:placetype":"venue"
},
  "geometry": {"coordinates":[-1.0875790119,53.971321106],"type":"Point"}
}