{
  "type": "Feature",
  "properties": {
    "addr:full":"The Rectory, Main Rd Bristol Somerset BS48 3QJ",
    "addr:postcode":"bs48 3qj",
    "addr:street":"Main Rd",
    "iso:country":"GB",
    "sg:address":"The Rectory, Main Rd",
    "sg:city":"Bristol",
    "sg:classifiers":[
        {
            "category":"Place Of Worship",
            "type":"Public Place"
        }
    ],
    "sg:phone":"+44 1275 462582",
    "sg:postcode":"BS48 3QJ",
    "sg:province":"Somerset",
    "wof:name":"The Parishes Of Barrow Gurney & Flax Bourton",
    "wof:placetype":"venue"
},
  "geometry": {"coordinates":[-2.724131,51.407387],"type":"Point"}
}