{
  "type": "Feature",
  "properties": {
    "addr:full":"23 Leicester Road, Anstey Leicester Leicestershire LE7 7AT",
    "addr:housenumber":"23",
    "addr:postcode":"le7 7at",
    "addr:street":"Leicester Road",
    "iso:country":"GB",
    "sg:address":"23 Leicester Road, Anstey",
    "sg:city":"Leicester",
    "sg:classifiers":[
        {
            "category":"Manufacturing",
            "subcategory":"Tools & Machinery",
            "type":"Manufacturing & Wholesale Goods"
        }
    ],
    "sg:phone":"+44 116 236 6565",
    "sg:postcode":"LE7 7AT",
    "sg:province":"Leicestershire",
    "sg:tags":[
        "design",
        "maker"
    ],
    "wof:name":"Michael Davis Tooling",
    "wof:placetype":"venue"
},
  "geometry": {"coordinates":[-1.151691,52.689346],"type":"Point"}
}