{
  "type": "Feature",
  "properties": {
    "addr:full":"91 Clough Lane, Mixenden Halifax West Yorkshire HX2 8SH",
    "addr:housenumber":"91",
    "addr:postcode":"hx2 8sh",
    "addr:street":"Clough Lane",
    "iso:country":"GB",
    "sg:address":"91 Clough Lane, Mixenden",
    "sg:city":"Halifax",
    "sg:classifiers":[
        {
            "category":"Retail",
            "subcategory":"Repair Shop",
            "type":"Services"
        }
    ],
    "sg:phone":"+44 1422 247363",
    "sg:postcode":"HX2 8SH",
    "sg:province":"West Yorkshire",
    "sg:tags":[
        "upholsterer"
    ],
    "wof:name":"Robert Raywood",
    "wof:placetype":"venue"
},
  "geometry": {"coordinates":[-1.9090000391,53.7539253235],"type":"Point"}
}