{
  "type": "Feature",
  "properties": {
    "addr:full":"65 Stirling St Grimsby Lincolnshire DN31 3AE",
    "addr:housenumber":"65",
    "addr:postcode":"dn31 3ae",
    "addr:street":"Stirling St",
    "iso:country":"GB",
    "sg:address":"65 Stirling St",
    "sg:city":"Grimsby",
    "sg:classifiers":[
        {
            "category":"Wholesale",
            "subcategory":"Scrap",
            "type":"Manufacturing & Wholesale Goods"
        }
    ],
    "sg:postcode":"DN31 3AE",
    "sg:province":"Lincolnshire",
    "sg:tags":[
        "breaker",
        "dismantlers"
    ],
    "wof:name":"A A Kar Breakers",
    "wof:placetype":"venue"
},
  "geometry": {"coordinates":[-0.060168,53.57357],"type":"Point"}
}