{
  "type": "Feature",
  "properties": {
    "iso:country":"GB",
    "sg:address":"The Hurlingham Studios, Ranelagh Gardens",
    "sg:city":"London",
    "sg:classifiers":[
        {
            "category":"Shopping",
            "subcategory":"Photographic Equipment",
            "type":"Retail Goods"
        }
    ],
    "sg:postcode":"SW6 3PA",
    "sg:province":"Greater London",
    "wof:name":"Rockit Promotions Ltd",
    "wof:placetype":"venue"
},
  "geometry": {"coordinates":[-0.20858,51.467751],"type":"Point"}
}