{
  "type": "Feature",
  "properties": {
    "addr:full":"18 Queen Street Louth Lincolnshire LN11 9AU",
    "addr:housenumber":"18",
    "addr:postcode":"ln11 9au",
    "addr:street":"Queen Street Louth",
    "iso:country":"GB",
    "sg:address":"18 Queen Street",
    "sg:city":"Louth",
    "sg:classifiers":[
        {
            "category":"Taxi",
            "type":"Transportation"
        },
        {
            "category":"Military Area",
            "subcategory":"Air Force Base",
            "type":"Public Place"
        }
    ],
    "sg:phone":"+44 1507 609629",
    "sg:postcode":"LN11 9AU",
    "sg:province":"Lincolnshire",
    "sg:tags":[
        "mini",
        "hire",
        "private",
        "cab"
    ],
    "wof:name":"Danny's Taxis",
    "wof:placetype":"venue"
},
  "geometry": {"coordinates":[-0.00322,53.366528],"type":"Point"}
}