{
  "type": "Feature",
  "properties": {
    "iso:country":"GB",
    "sg:address":"Underriver Vineyard, Underriver",
    "sg:city":"Sevenoaks",
    "sg:classifiers":[
        {
            "category":"Food & Beverages",
            "subcategory":"Liquor & Beverages",
            "type":"Retail Goods"
        }
    ],
    "sg:postcode":"TN15 0SL",
    "sg:province":"Kent",
    "sg:tags":[
        "beer",
        "spirit",
        "wines"
    ],
    "wof:name":"Underriver Vineyard",
    "wof:placetype":"venue"
},
  "geometry": {"coordinates":[0.228619,51.248272],"type":"Point"}
}