{
  "type": "Feature",
  "properties": {
    "iso:country":"GB",
    "sg:address":"4 Westbourne Gro",
    "sg:city":"Chesterfield",
    "sg:classifiers":[
        {
            "category":"Retail",
            "subcategory":"Driving School",
            "type":"Services"
        }
    ],
    "sg:postcode":"S40 3QD",
    "sg:province":"Derbyshire",
    "wof:name":"David A McElvaney",
    "wof:placetype":"venue"
},
  "geometry": {"coordinates":[-1.466579,53.235283],"type":"Point"}
}