{
  "type": "Feature",
  "properties": {
    "addr:full":"91 Whitebeck Ct, Moorway Dr Manchester Greater Manchester M9 7HR",
    "addr:housenumber":"91",
    "addr:postcode":"m9 7hr",
    "addr:street":"Whitebeck Ct Moorway Dr",
    "iso:country":"GB",
    "sg:address":"91 Whitebeck Ct, Moorway Dr",
    "sg:city":"Manchester",
    "sg:classifiers":[
        {
            "category":"Wholesale",
            "subcategory":"Books, Periodicals, & Newspapers",
            "type":"Manufacturing & Wholesale Goods"
        }
    ],
    "sg:phone":"+44 161 682 9659",
    "sg:postcode":"M9 7HR",
    "sg:province":"Greater Manchester",
    "sg:tags":[
        "publishing"
    ],
    "wof:name":"Istlia Eldonejo Esperantista",
    "wof:placetype":"venue"
},
  "geometry": {"coordinates":[-2.1910738945,53.5286750793],"type":"Point"}
}