{
  "type": "Feature",
  "properties": {
    "iso:country":"GB",
    "sg:address":"12 Sewell Place, Currock",
    "sg:city":"Carlisle",
    "sg:classifiers":[
        {
            "category":"Freight",
            "type":"Transportation"
        }
    ],
    "sg:phone":"+44 1228 528223",
    "sg:postcode":"CA2 4QR",
    "sg:province":"Cumbria",
    "sg:tags":[
        "haulage",
        "road"
    ],
    "wof:name":"D Young Removals & Light Haulage",
    "wof:placetype":"venue"
},
  "geometry": {"coordinates":[-2.930944,54.876999],"type":"Point"}
}