{
  "type": "Feature",
  "properties": {
    "iso:country":"GB",
    "sg:address":"33 High Street",
    "sg:city":"Denbigh",
    "sg:classifiers":[
        {
            "category":"Shopping",
            "subcategory":"Books",
            "type":"Retail Goods"
        }
    ],
    "sg:phone":"+44 1745 813431",
    "sg:postcode":"LL16 3HY",
    "sg:province":"Conwy",
    "sg:tags":[
        "bookseller",
        "retailer"
    ],
    "wof:name":"Siop Clwyd",
    "wof:placetype":"venue"
},
  "geometry": {"coordinates":[-3.4200439453,53.1834259033],"type":"Point"}
}