{
  "type": "Feature",
  "properties": {
    "addr:full":"24 Glumangate Chesterfield Derbyshire S40 1UA",
    "addr:housenumber":"24",
    "addr:postcode":"s40 1ua",
    "addr:street":"Glumangate",
    "iso:country":"GB",
    "sg:address":"24 Glumangate",
    "sg:city":"Chesterfield",
    "sg:classifiers":[
        {
            "category":"Professional",
            "subcategory":"Lawyer & Legal Services",
            "type":"Services"
        }
    ],
    "sg:phone":"+44 1246 208081",
    "sg:postcode":"S40 1UA",
    "sg:province":"Derbyshire",
    "sg:tags":[
        "solicitor"
    ],
    "wof:name":"Banner Jones Middleton Solicitors",
    "wof:placetype":"venue"
},
  "geometry": {"coordinates":[-1.429479,53.236671],"type":"Point"}
}