{
  "type": "Feature",
  "properties": {
    "addr:full":"Classice Car Reterations Market Drayton Shropshire TF9 2ST",
    "addr:postcode":"tf9 2st",
    "iso:country":"GB",
    "sg:address":"Classice Car Reterations",
    "sg:city":"Market Drayton",
    "sg:classifiers":[
        {
            "category":"Autos & Motor Vehicles",
            "subcategory":"Automobile Sales",
            "type":"Retail Goods"
        }
    ],
    "sg:postcode":"TF9 2ST",
    "sg:province":"Shropshire",
    "sg:tags":[
        "car",
        "specialist",
        "sales",
        "classic"
    ],
    "wof:name":"Hinstock",
    "wof:placetype":"venue"
},
  "geometry": {"coordinates":[-2.4861719608,52.9040908813],"type":"Point"}
}