{
  "type": "Feature",
  "properties": {
    "addr:full":"Unit 3a The Potteries, Woodgreen Road Waltham Abbey Essex EN9 3SA",
    "addr:housenumber":"unit 3a",
    "addr:postcode":"en9 3sa",
    "addr:street":"Woodgreen Road",
    "iso:country":"GB",
    "sg:address":"Unit 3a The Potteries, Woodgreen Road",
    "sg:city":"Waltham Abbey",
    "sg:classifiers":[
        {
            "category":"Communications",
            "type":"Services"
        }
    ],
    "sg:phone":"+44 1992 764430",
    "sg:postcode":"EN9 3SA",
    "sg:province":"Essex",
    "sg:tags":[
        "tv",
        "video",
        "radio"
    ],
    "wof:name":"Lee Leather",
    "wof:placetype":"venue"
},
  "geometry": {"coordinates":[0.0014900001,51.6864204407],"type":"Point"}
}