{
  "type": "Feature",
  "properties": {
    "addr:full":"275 Melrosegate York North Yorkshire YO10 3SN",
    "addr:housenumber":"275",
    "addr:postcode":"yo10 3sn",
    "addr:street":"Melrosegate",
    "iso:country":"GB",
    "sg:address":"275 Melrosegate",
    "sg:city":"York",
    "sg:classifiers":[
        {
            "category":"Personal",
            "subcategory":"Beauty Salon",
            "type":"Services"
        }
    ],
    "sg:phone":"+44 1904 413851",
    "sg:postcode":"YO10 3SN",
    "sg:province":"North Yorkshire",
    "sg:tags":[
        "unisex",
        "ladies",
        "hairdresser"
    ],
    "wof:name":"TRESSES HAIR SALON",
    "wof:placetype":"venue"
},
  "geometry": {"coordinates":[-1.0589590073,53.9559707642],"type":"Point"}
}