{
  "type": "Feature",
  "properties": {
    "addr:full":"Devon & Cornwall Un'd Dis Office Plymouth Devon PL4 8JW",
    "addr:postcode":"pl4 8jw",
    "iso:country":"GB",
    "sg:address":"Devon & Cornwall Un'd Dis Office",
    "sg:city":"Plymouth",
    "sg:classifiers":[
        {
            "category":"Manufacturing",
            "subcategory":"Tools & Machinery",
            "type":"Manufacturing & Wholesale Goods"
        }
    ],
    "sg:phone":"+44 1752 664860",
    "sg:postcode":"PL4 8JW",
    "sg:province":"Devon",
    "sg:tags":[
        "society",
        "friendly"
    ],
    "wof:name":"Ancient Order of Foresters Friendly Society",
    "wof:placetype":"venue"
},
  "geometry": {"coordinates":[-4.1339302063,50.3790588379],"type":"Point"}
}