{
  "type": "Feature",
  "properties": {
    "iso:country":"GB",
    "sg:address":"60 Hall Gate",
    "sg:city":"Doncaster",
    "sg:classifiers":[
        {
            "category":"Shopping",
            "subcategory":"Bicycles & Sporting Goods",
            "type":"Retail Goods"
        },
        {
            "category":"Wholesale",
            "subcategory":"Sporting Goods",
            "type":"Manufacturing & Wholesale Goods"
        }
    ],
    "sg:phone":"+44 1302 321949",
    "sg:postcode":"DN1 3PB",
    "sg:province":"South Yorkshire",
    "sg:tags":[
        "supplier",
        "equipment",
        "camping"
    ],
    "wof:name":"FAMOUS ARMY STORES LTD",
    "wof:placetype":"venue"
},
  "geometry": {"coordinates":[-1.131510973,53.5224647522],"type":"Point"}
}