{
  "type": "Feature",
  "properties": {
    "addr:full":"Darkgate Buildings, 3 Red St Carmarthen Carmarthenshire SA31 1QL",
    "addr:housenumber":"3",
    "addr:postcode":"sa31 1ql",
    "addr:street":"Darkgate;Red St",
    "iso:country":"GB",
    "sg:address":"Darkgate Buildings, 3 Red St",
    "sg:city":"Carmarthen",
    "sg:classifiers":[
        {
            "category":"Government",
            "subcategory":"Office",
            "type":"Public Place"
        }
    ],
    "sg:phone":"+44 1267 232823",
    "sg:postcode":"SA31 1QL",
    "sg:province":"Carmarthenshire",
    "sg:tags":[
        "local"
    ],
    "wof:name":"Health & Safety Executive",
    "wof:placetype":"venue"
},
  "geometry": {"coordinates":[-4.2994041443,51.8602752686],"type":"Point"}
}