{
  "type": "Feature",
  "properties": {
    "iso:country":"GB",
    "sg:address":"Ash Court Moorgreen Industrial Park, Engine Lane, Newthorpe",
    "sg:city":"Nottingham",
    "sg:classifiers":[
        {
            "category":"Building & Trades",
            "subcategory":"Landscaping Services",
            "type":"Services"
        }
    ],
    "sg:phone":"+44 1773 711666",
    "sg:postcode":"NG16 3QU",
    "sg:province":"Derbyshire",
    "sg:tags":[
        "steel"
    ],
    "wof:name":"Tiger Buildings Ltd.",
    "wof:placetype":"venue"
},
  "geometry": {"coordinates":[-1.290999,53.02607],"type":"Point"}
}