{
  "type": "Feature",
  "properties": {
    "iso:country":"GB",
    "sg:address":"Unit 2f",
    "sg:city":"Wishaw",
    "sg:classifiers":[
        {
            "category":"Personal",
            "type":"Services"
        }
    ],
    "sg:phone":"+44 1698 351343",
    "sg:postcode":"ML2 0RY",
    "sg:province":"North Lanarkshire",
    "sg:tags":[
        "delivery"
    ],
    "wof:name":"G C N (Scotland) Ltd.",
    "wof:placetype":"venue"
},
  "geometry": {"coordinates":[-3.9100089073,55.7544441223],"type":"Point"}
}