{
  "type": "Feature",
  "properties": {
    "addr:full":"32 Lickey Coppice, Rednal Birmingham West Midlands B45 8PQ",
    "addr:housenumber":"32",
    "addr:postcode":"b45 8pq",
    "addr:street":"Lickey Coppice Rednal",
    "iso:country":"GB",
    "sg:address":"32 Lickey Coppice, Rednal",
    "sg:city":"Birmingham",
    "sg:classifiers":[
        {
            "category":"Building & Trades",
            "subcategory":"Construction",
            "type":"Services"
        }
    ],
    "sg:phone":"+44 121 447 8177",
    "sg:postcode":"B45 8PQ",
    "sg:province":"West Midlands",
    "sg:tags":[
        "fork",
        "lift",
        "truck"
    ],
    "wof:name":"Philip Hutter Training",
    "wof:placetype":"venue"
},
  "geometry": {"coordinates":[-2.0000081062,52.3804473877],"type":"Point"}
}