{
  "type": "Feature",
  "properties": {
    "addr:full":"Unit 1, Orchard St Salford Greater Manchester M6 6FL",
    "addr:housenumber":"unit 1",
    "addr:postcode":"m6 6fl",
    "addr:street":"Orchard St",
    "iso:country":"GB",
    "sg:address":"Unit 1, Orchard St",
    "sg:city":"Salford",
    "sg:classifiers":[
        {
            "category":"Home & Garden",
            "subcategory":"Kitchen Supply",
            "type":"Retail Goods"
        }
    ],
    "sg:phone":"+44 161 745 8890",
    "sg:postcode":"M6 6FL",
    "sg:province":"Greater Manchester",
    "sg:tags":[
        "ware"
    ],
    "wof:name":"Andy's Warehouse",
    "wof:placetype":"venue"
},
  "geometry": {"coordinates":[-2.282004118,53.4941749573],"type":"Point"}
}