{
  "type": "Feature",
  "properties": {
    "iso:country":"GB",
    "sg:address":"1 Chantry Wynd, Finkle Street",
    "sg:city":"Richmond",
    "sg:classifiers":[
        {
            "category":"Shopping",
            "subcategory":"Thrift Store",
            "type":"Retail Goods"
        }
    ],
    "sg:phone":"+44 1748 826475",
    "sg:postcode":"DL10 4QB",
    "sg:province":"North Yorkshire",
    "sg:tags":[
        "shop",
        "charity"
    ],
    "wof:name":"Help the Aged",
    "wof:placetype":"venue"
},
  "geometry": {"coordinates":[-1.7385259867,54.4033584595],"type":"Point"}
}