{
  "type": "Feature",
  "properties": {
    "iso:country":"GB",
    "sg:address":"Colomendy House, 6 Bath Street",
    "sg:city":"Rhyl",
    "sg:classifiers":[
        {
            "category":"Professional",
            "subcategory":"Art Services",
            "type":"Services"
        }
    ],
    "sg:phone":"+44 1942 275853",
    "sg:postcode":"LL18 3EB",
    "sg:province":"Conwy",
    "sg:tags":[
        "photographer"
    ],
    "wof:name":"S W P P  Ltd.",
    "wof:placetype":"venue"
},
  "geometry": {"coordinates":[-3.489039,53.322899],"type":"Point"}
}