{
  "type": "Feature",
  "properties": {
    "addr:full":"1st Floor, 4 Sherrard Street Melton Mowbray Leicestershire LE13 1XJ",
    "addr:postcode":"le13 1xj",
    "addr:street":"Sherrard Street",
    "iso:country":"GB",
    "sg:address":"1st Floor, 4 Sherrard Street",
    "sg:city":"Melton Mowbray",
    "sg:classifiers":[
        {
            "category":"Manufacturing",
            "subcategory":"Tools & Machinery",
            "type":"Manufacturing & Wholesale Goods"
        }
    ],
    "sg:postcode":"LE13 1XJ",
    "sg:province":"Leicestershire",
    "sg:tags":[
        "society",
        "friendly"
    ],
    "wof:name":"Disabled Persons Insurance Services Ltd",
    "wof:placetype":"venue"
},
  "geometry": {"coordinates":[-0.8854320049,52.7643966675],"type":"Point"}
}