{
  "type": "Feature",
  "properties": {
    "addr:full":"54-56 Queen Street Market Rasen Lincolnshire LN8 3EN",
    "addr:housenumber":"54-56",
    "addr:postcode":"ln8 3en",
    "addr:street":"Queen Street",
    "iso:country":"GB",
    "sg:address":"54-56 Queen Street",
    "sg:city":"Market Rasen",
    "sg:classifiers":[
        {
            "category":"Home & Garden",
            "subcategory":"Home Furnishings",
            "type":"Retail Goods"
        },
        {
            "category":"Building & Trades",
            "subcategory":"Construction",
            "type":"Services"
        }
    ],
    "sg:phone":"+44 1673 843787",
    "sg:postcode":"LN8 3EN",
    "sg:province":"Lincolnshire",
    "sg:tags":[
        "installers",
        "planner",
        "kitchen",
        "furnishers"
    ],
    "sg:website":"http://www.peterrhodes.co.uk",
    "wof:name":"Rhodes Fitted Kitchens Ltd",
    "wof:placetype":"venue"
},
  "geometry": {"coordinates":[-0.3342649937,53.3869781494],"type":"Point"}
}