{
  "type": "Feature",
  "properties": {
    "iso:country":"GB",
    "sg:address":"Park Foot Holiday Homes, Bentham Road, Ingleton",
    "sg:city":"Carnforth",
    "sg:classifiers":[
        {
            "category":"Recreation",
            "subcategory":"Campground",
            "type":"Entertainment"
        }
    ],
    "sg:postcode":"LA6 3HR",
    "sg:province":"Cumbria",
    "sg:tags":[
        "caravan",
        "park"
    ],
    "wof:name":"Brewer Properties Ltd.",
    "wof:placetype":"venue"
},
  "geometry": {"coordinates":[-2.471084,54.150227],"type":"Point"}
}