{
  "type": "Feature",
  "properties": {
    "addr:full":"178 Park Lane London Greater London N17 0JN",
    "addr:housenumber":"178",
    "addr:postcode":"n17 0jn",
    "addr:street":"Park Lane",
    "iso:country":"GB",
    "sg:address":"178 Park Lane",
    "sg:city":"London",
    "sg:classifiers":[
        {
            "category":"Retail",
            "subcategory":"Laundry & Dry Cleaning",
            "type":"Services"
        }
    ],
    "sg:postcode":"N17 0JN",
    "sg:province":"Greater London",
    "sg:tags":[
        "launderette"
    ],
    "wof:name":"Aristodemou Launderettes",
    "wof:placetype":"venue"
},
  "geometry": {"coordinates":[-0.0582059994,51.6022567749],"type":"Point"}
}