{
  "type": "Feature",
  "properties": {
    "iso:country":"GB",
    "sg:address":"Seaton Crescent, Staithes",
    "sg:city":"Saltburn-by-the-sea",
    "sg:classifiers":[
        {
            "category":"Health Services",
            "subcategory":"Doctor",
            "type":"Services"
        }
    ],
    "sg:phone":"+44 1947 840480",
    "sg:postcode":"TS13 5AY",
    "sg:province":"North Yorkshire",
    "sg:tags":[
        "practitioners"
    ],
    "wof:name":"Staithes Surgery",
    "wof:placetype":"venue"
},
  "geometry": {"coordinates":[-0.7948489785,54.5523986816],"type":"Point"}
}