{
  "type": "Feature",
  "properties": {
    "iso:country":"GB",
    "sg:address":"14 Sandhurst Court, Acre Lane",
    "sg:city":"London",
    "sg:classifiers":[
        {
            "category":"Organizations",
            "subcategory":"Membership Organization",
            "type":"Services"
        }
    ],
    "sg:phone":"+44 20 7845 6427",
    "sg:postcode":"SW2 5TX",
    "sg:province":"Greater London",
    "sg:tags":[
        "club"
    ],
    "wof:name":"Sandhurst Court Ltd.",
    "wof:placetype":"venue"
},
  "geometry": {"coordinates":[-0.126976,51.459602],"type":"Point"}
}