{
  "type": "Feature",
  "properties": {
    "addr:full":"29 Hurstdene Avenue Staines Berkshire TW18 1JG",
    "addr:housenumber":"29",
    "addr:postcode":"tw18 1jg",
    "addr:street":"Hurstdene Avenue",
    "iso:country":"GB",
    "sg:address":"29 Hurstdene Avenue",
    "sg:city":"Staines",
    "sg:classifiers":[
        {
            "category":"Autos & Motor Vehicles",
            "subcategory":"Motorcycle Sales",
            "type":"Retail Goods"
        }
    ],
    "sg:phone":"+44 1784 456356",
    "sg:postcode":"TW18 1JG",
    "sg:province":"Berkshire",
    "sg:tags":[
        "chauffeur",
        "driven",
        "car"
    ],
    "wof:name":"Laleham Executive Cars",
    "wof:placetype":"venue"
},
  "geometry": {"coordinates":[-0.491905,51.425285],"type":"Point"}
}