{
  "type": "Feature",
  "properties": {
    "iso:country":"GB",
    "sg:address":"79 Denham Walk",
    "sg:city":"Newcastle-upon-tyne",
    "sg:classifiers":[
        {
            "category":"Retail",
            "subcategory":"Repair Shop",
            "type":"Services"
        }
    ],
    "sg:postcode":"NE5 1JE",
    "sg:province":"Tyne and Wear",
    "sg:tags":[
        "plant",
        "machinery"
    ],
    "wof:name":"Farrell's Mobile Breakdown Services",
    "wof:placetype":"venue"
},
  "geometry": {"coordinates":[-1.719138,54.998974],"type":"Point"}
}