{
  "type": "Feature",
  "properties": {
    "addr:full":"Morrison Road Barking Essex IG11 0UA",
    "addr:postcode":"ig11 0ua",
    "addr:street":"Morrison Road",
    "iso:country":"GB",
    "sg:address":"Morrison Road",
    "sg:city":"Barking",
    "sg:classifiers":[
        {
            "category":"Organizations",
            "subcategory":"Community Association",
            "type":"Services"
        },
        {
            "category":"Organizations",
            "subcategory":"Membership Organization",
            "type":"Services"
        }
    ],
    "sg:phone":"+44 20 8592 7487",
    "sg:postcode":"IG11 0UA",
    "sg:province":"Essex",
    "sg:tags":[
        "club",
        "social"
    ],
    "wof:name":"Scrattons Sports & Social Club",
    "wof:placetype":"venue"
},
  "geometry": {"coordinates":[0.132665,51.529781],"type":"Point"}
}