{
  "type": "Feature",
  "properties": {
    "addr:full":"380 Brigstock Road Thornton Heath Surrey CR7 7JF",
    "addr:housenumber":"380",
    "addr:postcode":"cr7 7jf",
    "addr:street":"Brigstock Road",
    "iso:country":"GB",
    "sg:address":"380 Brigstock Road",
    "sg:city":"Thornton Heath",
    "sg:classifiers":[
        {
            "category":"Personal",
            "subcategory":"Beauty Salon",
            "type":"Services"
        }
    ],
    "sg:phone":"+44 20 8684 2963",
    "sg:postcode":"CR7 7JF",
    "sg:province":"Surrey",
    "sg:tags":[
        "unisex",
        "hairdresser"
    ],
    "wof:name":"Lazaris Ltd.",
    "wof:placetype":"venue"
},
  "geometry": {"coordinates":[-0.113912,51.393494],"type":"Point"}
}