{
  "type": "Feature",
  "properties": {
    "addr:full":"10 High Mkt Ashington Northumberland NE63 8PD",
    "addr:housenumber":"10",
    "addr:postcode":"ne63 8pd",
    "addr:street":"High Mkt;Northumberland",
    "iso:country":"GB",
    "sg:address":"10 High Mkt",
    "sg:city":"Ashington",
    "sg:classifiers":[
        {
            "category":"Shopping",
            "subcategory":"News",
            "type":"Retail Goods"
        }
    ],
    "sg:postcode":"NE63 8PD",
    "sg:province":"Northumberland",
    "sg:tags":[
        "newsagent"
    ],
    "wof:name":"Tudor,Moira,",
    "wof:placetype":"venue"
},
  "geometry": {"coordinates":[-1.589393,55.183098],"type":"Point"}
}