{
  "type": "Feature",
  "properties": {
    "addr:full":"Hawthorn Way Cambridge Cambridgeshire CB4 1AX",
    "addr:postcode":"cb4 1ax",
    "addr:street":"Hawthorn Way",
    "iso:country":"GB",
    "sg:address":"Hawthorn Way",
    "sg:city":"Cambridge",
    "sg:classifiers":[
        {
            "category":"Social Services",
            "type":"Services"
        },
        {
            "category":"Social Services",
            "subcategory":"Adult Care",
            "type":"Services"
        }
    ],
    "sg:phone":"+44 1223 478601",
    "sg:postcode":"CB4 1AX",
    "sg:province":"Cambridgeshire",
    "sg:tags":[
        "disability",
        "day",
        "centre"
    ],
    "wof:name":"Hester Adrian Centre",
    "wof:placetype":"venue"
},
  "geometry": {"coordinates":[0.1330350041,52.2175064087],"type":"Point"}
}