{
  "type": "Feature",
  "properties": {
    "addr:full":"Lundwood Medical Centre, Pontefract Road Barnsley South Yorkshire S71 5PN",
    "addr:postcode":"s71 5pn",
    "addr:street":"Pontefract Road;Yorkshire",
    "iso:country":"GB",
    "sg:address":"Lundwood Medical Centre, Pontefract Road",
    "sg:city":"Barnsley",
    "sg:classifiers":[
        {
            "category":"Shopping",
            "subcategory":"Pharmacy",
            "type":"Retail Goods"
        }
    ],
    "sg:phone":"+44 1226 240893",
    "sg:postcode":"S71 5PN",
    "sg:province":"South Yorkshire",
    "sg:tags":[
        "pharmacist",
        "dispensing",
        "chemist"
    ],
    "wof:name":"Medichem Pharmacy",
    "wof:placetype":"venue"
},
  "geometry": {"coordinates":[-1.435239,53.562721],"type":"Point"}
}