{
  "type": "Feature",
  "properties": {
    "iso:country":"GB",
    "sg:address":"37-39 King Street",
    "sg:city":"Southall",
    "sg:classifiers":[
        {
            "category":"Bars & Pubs",
            "type":"Food & Drink"
        },
        {
            "category":"Community Center",
            "subcategory":"Social",
            "type":"Public Place"
        }
    ],
    "sg:phone":"+44 20 8571 9009",
    "sg:postcode":"UB2 4DQ",
    "sg:province":"Greater London",
    "sg:tags":[
        "pubs",
        "house",
        "inn",
        "activity"
    ],
    "wof:name":"The Havelock Arms",
    "wof:placetype":"venue"
},
  "geometry": {"coordinates":[-0.378203,51.504074],"type":"Point"}
}