{
  "type": "Feature",
  "properties": {
    "addr:full":"25 Devonshire Place London Greater London W1G 6JD",
    "addr:housenumber":"25",
    "addr:postcode":"w1g 6jd",
    "addr:street":"Devonshire Place",
    "iso:country":"GB",
    "sg:address":"25 Devonshire Place",
    "sg:city":"London",
    "sg:classifiers":[
        {
            "category":"Health Services",
            "subcategory":"Dentist",
            "type":"Services"
        }
    ],
    "sg:phone":"+44 20 7935 9687",
    "sg:postcode":"W1G 6JD",
    "sg:province":"Greater London",
    "wof:name":"Ivor Newman",
    "wof:placetype":"venue"
},
  "geometry": {"coordinates":[-0.1502300054,51.5221290588],"type":"Point"}
}