{
  "type": "Feature",
  "properties": {
    "iso:country":"GB",
    "sg:address":"5 Market Street",
    "sg:city":"Tenbury Wells",
    "sg:classifiers":[
        {
            "category":"Food & Beverages",
            "subcategory":"Bakery",
            "type":"Retail Goods"
        }
    ],
    "sg:phone":"+44 1584 811062",
    "sg:postcode":"WR15 8BQ",
    "sg:province":"Herefordshire",
    "sg:tags":[
        "baker"
    ],
    "wof:name":"Richard C Swift",
    "wof:placetype":"venue"
},
  "geometry": {"coordinates":[-2.594017,52.31089],"type":"Point"}
}