{
  "type": "Feature",
  "properties": {
    "iso:country":"GB",
    "sg:address":"21 Commercial Road",
    "sg:city":"Hereford",
    "sg:classifiers":[
        {
            "category":"Restaurant",
            "type":"Food & Drink"
        }
    ],
    "sg:phone":"+44 1432 270183",
    "sg:postcode":"HR1 2BD",
    "sg:province":"Herefordshire",
    "sg:tags":[
        "italian"
    ],
    "wof:name":"Ristorante Pizzeria Firenze",
    "wof:placetype":"venue"
},
  "geometry": {"coordinates":[-2.710898,52.058472],"type":"Point"}
}