{
  "type": "Feature",
  "properties": {
    "addr:full":", Foston York North Yorkshire YO60 7QB",
    "addr:postcode":"yo60 7qb",
    "iso:country":"GB",
    "sg:address":", Foston",
    "sg:city":"York",
    "sg:classifiers":[
        {
            "category":"Education",
            "subcategory":"School",
            "type":"Public Place"
        }
    ],
    "sg:phone":"+44 1653 618265",
    "sg:postcode":"YO60 7QB",
    "sg:province":"North Yorkshire",
    "sg:tags":[
        "local",
        "authority"
    ],
    "wof:name":"Foston C.E School",
    "wof:placetype":"venue"
},
  "geometry": {"coordinates":[-0.9295459986,54.0637054443],"type":"Point"}
}