{
  "type": "Feature",
  "properties": {
    "iso:country":"GB",
    "sg:address":"Blay's House, Churchfield Road, Chalfont St Peter",
    "sg:city":"Gerrards Cross",
    "sg:classifiers":[
        {
            "category":"Professional",
            "subcategory":"Printing & Photocopies",
            "type":"Services"
        }
    ],
    "sg:phone":"+44 1753 880482",
    "sg:postcode":"SL9 9EW",
    "sg:province":"Buckinghamshire",
    "sg:tags":[
        "printer"
    ],
    "wof:name":"Blay's Guides Ltd.",
    "wof:placetype":"venue"
},
  "geometry": {"coordinates":[-0.5589100122,51.6072311401],"type":"Point"}
}