{
  "type": "Feature",
  "properties": {
    "addr:full":"16 Park Crescent London Greater London W1B 1AH",
    "addr:housenumber":"16",
    "addr:postcode":"w1b 1ah",
    "addr:street":"Park Crescent",
    "iso:country":"GB",
    "sg:address":"16 Park Crescent",
    "sg:city":"London",
    "sg:classifiers":[
        {
            "category":"Education",
            "subcategory":"Special Training",
            "type":"Public Place"
        }
    ],
    "sg:phone":"+44 20 7580 4741",
    "sg:postcode":"W1B 1AH",
    "sg:province":"Greater London",
    "sg:tags":[
        "product",
        "centre"
    ],
    "wof:name":"Institute of Business Administration Ltd.",
    "wof:placetype":"venue"
},
  "geometry": {"coordinates":[-0.1464540064,51.5227279663],"type":"Point"}
}