{
  "type": "Feature",
  "properties": {
    "iso:country":"GB",
    "sg:address":"Dene Road, Didsbury",
    "sg:city":"Manchester",
    "sg:classifiers":[
        {
            "category":"Education",
            "subcategory":"University",
            "type":"Public Place"
        }
    ],
    "sg:phone":"+44 161 445 3063",
    "sg:postcode":"M20 2GU",
    "sg:province":"Greater Manchester",
    "sg:tags":[
        "college",
        "higher"
    ],
    "sg:website":"http://www.nazarene.ac.uk",
    "wof:name":"Nazarene Theological College",
    "wof:placetype":"venue"
},
  "geometry": {"coordinates":[-2.240924,53.416443],"type":"Point"}
}