{
  "type": "Feature",
  "properties": {
    "iso:country":"GB",
    "sg:address":"35 Kingsbridge Cres",
    "sg:city":"Leicester",
    "sg:classifiers":[
        {
            "category":"Building & Trades",
            "subcategory":"Construction",
            "type":"Services"
        }
    ],
    "sg:phone":"+44 116 235 0892",
    "sg:postcode":"LE4 1EG",
    "sg:province":"Leicestershire",
    "sg:tags":[
        "joiner",
        "carpenter"
    ],
    "wof:name":"Kingsbridge Joinery",
    "wof:placetype":"venue"
},
  "geometry": {"coordinates":[-1.1622929573,52.6762657166],"type":"Point"}
}