{
  "type": "Feature",
  "properties": {
    "iso:country":"GB",
    "sg:address":"499 Barking Road",
    "sg:city":"London",
    "sg:classifiers":[
        {
            "category":"Health Services",
            "subcategory":"Dentist",
            "type":"Services"
        }
    ],
    "sg:phone":"+44 20 8472 3769",
    "sg:postcode":"E13 8PS",
    "sg:province":"Greater London",
    "wof:name":"Pran Krishna Ghosh",
    "wof:placetype":"venue"
},
  "geometry": {"coordinates":[0.028491,51.525585],"type":"Point"}
}