{
  "type": "Feature",
  "properties": {
    "addr:full":"Gill Fm, Gill Lane, Longton Preston Lancashire PR4 4SR",
    "addr:postcode":"pr4 4sr",
    "addr:street":"Gill Lane",
    "iso:country":"GB",
    "sg:address":"Gill Fm, Gill Lane, Longton",
    "sg:city":"Preston",
    "sg:classifiers":[
        {
            "category":"Building & Trades",
            "subcategory":"Plumbing",
            "type":"Services"
        }
    ],
    "sg:phone":"+44 1772 613578",
    "sg:postcode":"PR4 4SR",
    "sg:province":"Lancashire",
    "sg:tags":[
        "heating"
    ],
    "wof:name":"W.E Bridge",
    "wof:placetype":"venue"
},
  "geometry": {"coordinates":[-2.7756400108,53.7121200562],"type":"Point"}
}