{
  "type": "Feature",
  "properties": {
    "iso:country":"GB",
    "sg:address":"132 Plumstead Common Road, Plumstead",
    "sg:city":"London",
    "sg:classifiers":[
        {
            "category":"Real Estate",
            "subcategory":"Real Estate Agent",
            "type":"Services"
        }
    ],
    "sg:phone":"+44 20 8854 6363",
    "sg:postcode":"SE18 2UL",
    "sg:province":"Greater London",
    "wof:name":"David Evans & Company",
    "wof:placetype":"venue"
},
  "geometry": {"coordinates":[0.0777830034,51.4809494019],"type":"Point"}
}