{
  "type": "Feature",
  "properties": {
    "addr:full":"2 Castle Bow Taunton Somerset TA1 1JQ",
    "addr:housenumber":"2",
    "addr:postcode":"ta1 1jq",
    "addr:street":"Castle Bow",
    "iso:country":"GB",
    "sg:address":"2 Castle Bow",
    "sg:city":"Taunton",
    "sg:classifiers":[
        {
            "category":"Government",
            "subcategory":"Office",
            "type":"Public Place"
        }
    ],
    "sg:phone":"+44 1823 331052",
    "sg:postcode":"TA1 1JQ",
    "sg:province":"Somerset",
    "sg:tags":[
        "local"
    ],
    "wof:name":"Rent Officer Service",
    "wof:placetype":"venue"
},
  "geometry": {"coordinates":[-3.103349,51.015202],"type":"Point"}
}