{
  "type": "Feature",
  "properties": {
    "iso:country":"GB",
    "sg:address":"Spiral House, 32-34 Fairview Road Norbury",
    "sg:city":"London",
    "sg:classifiers":[
        {
            "category":"Professional",
            "subcategory":"Printing & Photocopies",
            "type":"Services"
        }
    ],
    "sg:postcode":"SW16 5PT",
    "sg:province":"Greater London",
    "sg:tags":[
        "t-shirt"
    ],
    "wof:name":"Classic T-Shirts Ltd",
    "wof:placetype":"venue"
},
  "geometry": {"coordinates":[-0.1244179979,51.411529541],"type":"Point"}
}