{
  "type": "Feature",
  "properties": {
    "iso:country":"GB",
    "sg:address":"Barton Road, Butleigh",
    "sg:city":"Glastonbury",
    "sg:classifiers":[
        {
            "category":"Communications",
            "subcategory":"Film & Video Production",
            "type":"Services"
        }
    ],
    "sg:postcode":"BA6 8TL",
    "sg:province":"Somerset",
    "sg:tags":[
        "illustrator",
        "artist"
    ],
    "wof:name":"Roger Frood",
    "wof:placetype":"venue"
},
  "geometry": {"coordinates":[-2.6844511032,51.0954322815],"type":"Point"}
}