{
  "type": "Feature",
  "properties": {
    "addr:full":"Walsdene, Wrafton Braunton Devon EX33 2DE",
    "addr:housenumber":"braunton",
    "addr:postcode":"ex33 2de",
    "addr:street":"Devon",
    "iso:country":"GB",
    "sg:address":"Walsdene, Wrafton",
    "sg:city":"Braunton",
    "sg:classifiers":[
        {
            "category":"Building & Trades",
            "subcategory":"Construction",
            "type":"Services"
        }
    ],
    "sg:phone":"+44 1271 812690",
    "sg:postcode":"EX33 2DE",
    "sg:province":"Devon",
    "sg:tags":[
        "joiner",
        "carpenter"
    ],
    "wof:name":"K J Hillier",
    "wof:placetype":"venue"
},
  "geometry": {"coordinates":[-4.1616492271,51.1098175049],"type":"Point"}
}