{
  "type": "Feature",
  "properties": {
    "addr:full":"Liverpool Branch, 1 Bold Street Liverpool Merseyside L2 7UE",
    "addr:housenumber":"1",
    "addr:postcode":"l2 7ue",
    "addr:street":"Bold Street",
    "iso:country":"GB",
    "sg:address":"Liverpool Branch, 1 Bold Street",
    "sg:city":"Liverpool",
    "sg:classifiers":[
        {
            "category":"Banks & Credit Unions",
            "subcategory":"Bank",
            "type":"Services"
        }
    ],
    "sg:postcode":"L2 7UE",
    "sg:province":"Merseyside",
    "wof:name":"Co-Operative Bank Plc (The)",
    "wof:placetype":"venue"
},
  "geometry": {"coordinates":[-2.9916000366,53.4049797058],"type":"Point"}
}