{
  "type": "Feature",
  "properties": {
    "iso:country":"GB",
    "sg:address":"The Hollies, Forest Road, Little Budworth",
    "sg:city":"Tarporley",
    "sg:classifiers":[
        {
            "category":"Food & Beverages",
            "subcategory":"Supermarket",
            "type":"Retail Goods"
        }
    ],
    "sg:phone":"+44 1829 760414",
    "sg:postcode":"CW6 9ES",
    "sg:province":"Cheshire",
    "wof:name":"R & H Cowap",
    "wof:placetype":"venue"
},
  "geometry": {"coordinates":[-2.6013839245,53.1825180054],"type":"Point"}
}