{
  "type": "Feature",
  "properties": {
    "iso:country":"GB",
    "sg:address":"12 High Street, Twerton On Avon",
    "sg:city":"Bath",
    "sg:classifiers":[
        {
            "category":"Personal",
            "subcategory":"Beauty Salon",
            "type":"Services"
        }
    ],
    "sg:phone":"+44 1225 465054",
    "sg:postcode":"BA2 1BZ",
    "sg:province":"Somerset",
    "sg:tags":[
        "unisex",
        "hairdresser"
    ],
    "wof:name":"Howard Miller Hairdressing",
    "wof:placetype":"venue"
},
  "geometry": {"coordinates":[-2.392124,51.380058],"type":"Point"}
}