{
  "type": "Feature",
  "properties": {
    "iso:country":"GB",
    "sg:address":"363 Liverpool Road, Eccles",
    "sg:city":"Manchester",
    "sg:classifiers":[
        {
            "category":"Home & Garden",
            "subcategory":"Furniture",
            "type":"Retail Goods"
        }
    ],
    "sg:postcode":"M30 8GF",
    "sg:province":"Greater Manchester",
    "wof:name":"The Pine Factory Centre",
    "wof:placetype":"venue"
},
  "geometry": {"coordinates":[-2.3617210388,53.480091095],"type":"Point"}
}