{
  "type": "Feature",
  "properties": {
    "iso:country":"GB",
    "sg:address":"9a Power Court",
    "sg:city":"Luton",
    "sg:classifiers":[
        {
            "category":"Wholesale",
            "subcategory":"Medical Equipment & Supplies",
            "type":"Manufacturing & Wholesale Goods"
        }
    ],
    "sg:phone":"+44 1582 749748",
    "sg:postcode":"LU1 3JJ",
    "sg:province":"Bedfordshire",
    "sg:tags":[
        "hospital"
    ],
    "wof:name":"Sks Biomedical Instruments Ltd",
    "wof:placetype":"venue"
},
  "geometry": {"coordinates":[-0.4096460044,51.8804283142],"type":"Point"}
}