{
  "type": "Feature",
  "properties": {
    "iso:country":"GB",
    "sg:address":"Greengarth, Little Broughton",
    "sg:city":"Cockermouth",
    "sg:classifiers":[
        {
            "category":"Building & Trades",
            "subcategory":"Construction",
            "type":"Services"
        }
    ],
    "sg:postcode":"CA13 0YG",
    "sg:province":"Cumbria",
    "sg:tags":[
        "joiner",
        "carpenter"
    ],
    "wof:name":"G C & J Weir",
    "wof:placetype":"venue"
},
  "geometry": {"coordinates":[-3.432495,54.673355],"type":"Point"}
}