{
  "type": "Feature",
  "properties": {
    "iso:country":"GB",
    "sg:address":"34 Vulcan Gardens",
    "sg:city":"Dewsbury",
    "sg:classifiers":[
        {
            "category":"Personal",
            "subcategory":"Beauty Salon",
            "type":"Services"
        }
    ],
    "sg:postcode":"WF13 2PP",
    "sg:province":"West Yorkshire",
    "sg:tags":[
        "unisex",
        "hairdresser"
    ],
    "wof:name":"Designs Hair Salon",
    "wof:placetype":"venue"
},
  "geometry": {"coordinates":[-1.637004,53.691475],"type":"Point"}
}