{
  "type": "Feature",
  "properties": {
    "addr:full":"2 North Charlotte St Edinburgh City of Edinburgh EH2 4HR",
    "addr:housenumber":"2",
    "addr:postcode":"eh2 4hr",
    "addr:street":"North Charlotte St Edinburgh",
    "iso:country":"GB",
    "sg:address":"2 North Charlotte St",
    "sg:city":"Edinburgh",
    "sg:classifiers":[
        {
            "category":"Banks & Credit Unions",
            "subcategory":"Bank",
            "type":"Services"
        }
    ],
    "sg:phone":"+44 131 220 1660",
    "sg:postcode":"EH2 4HR",
    "sg:province":"City of Edinburgh",
    "wof:name":"ABN Amro Bank N.V",
    "wof:placetype":"venue"
},
  "geometry": {"coordinates":[-3.2096970081,55.9494895935],"type":"Point"}
}