{
  "type": "Feature",
  "properties": {
    "iso:country":"GB",
    "sg:address":"Minicom, West St",
    "sg:city":"Chesterfield",
    "sg:classifiers":[
        {
            "category":"Social Services",
            "type":"Services"
        }
    ],
    "sg:phone":"+44 1246 277249",
    "sg:postcode":"S40 4TZ",
    "sg:province":"Derbyshire",
    "wof:name":"Chesterfield Social Services",
    "wof:placetype":"venue"
},
  "geometry": {"coordinates":[-1.43743,53.239151],"type":"Point"}
}