{
  "type": "Feature",
  "properties": {
    "iso:country":"GB",
    "sg:address":"6 Anderson Street",
    "sg:city":"Kirkcaldy",
    "sg:classifiers":[
        {
            "category":"Autos & Motor Vehicles",
            "subcategory":"Auto Supplies",
            "type":"Retail Goods"
        }
    ],
    "sg:phone":"+44 1592 260237",
    "sg:postcode":"KY1 2AQ",
    "sg:province":"Fife",
    "sg:tags":[
        "exhaust",
        "absorber",
        "shock"
    ],
    "wof:name":"Budget Exhausts & Tyres Ltd.",
    "wof:placetype":"venue"
},
  "geometry": {"coordinates":[-3.1407139301,56.1238059998],"type":"Point"}
}