{
  "type": "Feature",
  "properties": {
    "iso:country":"GB",
    "sg:address":"27 Surrey Rd",
    "sg:city":"Stoke On Trent",
    "sg:classifiers":[
        {
            "category":"Home & Garden",
            "subcategory":"Household Appliances",
            "type":"Retail Goods"
        }
    ],
    "sg:phone":"+44 1782 775993",
    "sg:postcode":"ST7 4AR",
    "sg:province":"Cheshire",
    "sg:tags":[
        "electrical"
    ],
    "wof:name":"Air-Con",
    "wof:placetype":"venue"
},
  "geometry": {"coordinates":[-2.234319,53.090317],"type":"Point"}
}