{
  "type": "Feature",
  "properties": {
    "iso:country":"GB",
    "sg:address":"2 Massey Walk, Peel Hall",
    "sg:city":"Manchester",
    "sg:classifiers":[
        {
            "category":"Professional",
            "subcategory":"Detective & Security Services",
            "type":"Services"
        }
    ],
    "sg:phone":"+44 161 437 9357",
    "sg:postcode":"M22 5JY",
    "sg:province":"Greater Manchester",
    "sg:tags":[
        "alarm",
        "burglar",
        "system"
    ],
    "wof:name":"Digitec Installations Ltd",
    "wof:placetype":"venue"
},
  "geometry": {"coordinates":[-2.243638,53.373901],"type":"Point"}
}