{
  "type": "Feature",
  "properties": {
    "addr:full":"Gaer Farm, Cwmcou Newcastle Emlyn Carmarthenshire SA38 9PR",
    "addr:postcode":"sa38 9pr",
    "addr:street":"Cwmcou",
    "iso:country":"GB",
    "sg:address":"Gaer Farm, Cwmcou",
    "sg:city":"Newcastle Emlyn",
    "sg:classifiers":[
        {
            "category":"Farming",
            "subcategory":"Livestock Farm",
            "type":"Manufacturing & Wholesale Goods"
        }
    ],
    "sg:postcode":"SA38 9PR",
    "sg:province":"Carmarthenshire",
    "sg:tags":[
        "others"
    ],
    "wof:name":"Messrs Brookin",
    "wof:placetype":"venue"
},
  "geometry": {"coordinates":[-4.467984,52.035919],"type":"Point"}
}