{
  "type": "Feature",
  "properties": {
    "addr:full":"40 Regent Rd Aylesbury Buckinghamshire HP21 7AB",
    "addr:housenumber":"40",
    "addr:postcode":"hp21 7ab",
    "addr:street":"Regent Rd",
    "iso:country":"GB",
    "sg:address":"40 Regent Rd",
    "sg:city":"Aylesbury",
    "sg:classifiers":[
        {
            "category":"Professional",
            "subcategory":"Art Services",
            "type":"Services"
        }
    ],
    "sg:phone":"+44 1296 483924",
    "sg:postcode":"HP21 7AB",
    "sg:province":"Buckinghamshire",
    "sg:tags":[
        "graphic",
        "designer"
    ],
    "wof:name":"Designers Couch",
    "wof:placetype":"venue"
},
  "geometry": {"coordinates":[-0.7845889926,51.8112335205],"type":"Point"}
}