{
  "type": "Feature",
  "properties": {
    "iso:country":"GB",
    "sg:address":"37 High Street, Barrow On Soar",
    "sg:city":"Loughborough",
    "sg:classifiers":[
        {
            "category":"Shopping",
            "subcategory":"News",
            "type":"Retail Goods"
        }
    ],
    "sg:phone":"+44 1509 412310",
    "sg:postcode":"LE12 8PY",
    "sg:province":"Leicestershire",
    "sg:tags":[
        "newsagent"
    ],
    "wof:name":"Barrow News",
    "wof:placetype":"venue"
},
  "geometry": {"coordinates":[-1.172509,52.74416],"type":"Point"}
}