{
  "type": "Feature",
  "properties": {
    "iso:country":"GB",
    "sg:address":"The Nursery, Hall Road",
    "sg:city":"Rochford",
    "sg:classifiers":[
        {
            "category":"Building & Trades",
            "subcategory":"Landscaping Services",
            "type":"Services"
        }
    ],
    "sg:postcode":"SS4 1PD",
    "sg:province":"Essex",
    "sg:tags":[
        "forestry",
        "tree"
    ],
    "wof:name":"Intercounty Tree Service",
    "wof:placetype":"venue"
},
  "geometry": {"coordinates":[0.701389,51.583221],"type":"Point"}
}