{
  "type": "Feature",
  "properties": {
    "addr:full":"34 Tinkle Street, Grimoldby Louth Lincolnshire LN11 8SW",
    "addr:housenumber":"34",
    "addr:postcode":"ln11 8sw",
    "addr:street":"Tinkle Street;Louth",
    "iso:country":"GB",
    "sg:address":"34 Tinkle Street, Grimoldby",
    "sg:city":"Louth",
    "sg:classifiers":[
        {
            "category":"Education",
            "subcategory":"School",
            "type":"Public Place"
        },
        {
            "category":"Government",
            "subcategory":"Post Office",
            "type":"Public Place"
        }
    ],
    "sg:phone":"+44 1507 327297",
    "sg:postcode":"LN11 8SW",
    "sg:province":"Lincolnshire",
    "sg:tags":[
        "college"
    ],
    "wof:name":"Grimoldby Post Office",
    "wof:placetype":"venue"
},
  "geometry": {"coordinates":[0.091095,53.369938],"type":"Point"}
}