{
  "type": "Feature",
  "properties": {
    "addr:full":"Mount Pleasant, Aspley Guise Milton Keynes Bedfordshire MK17 8JZ",
    "addr:postcode":"mk17 8jz",
    "addr:street":"Mount Pleasant;Guise",
    "iso:country":"GB",
    "sg:address":"Mount Pleasant, Aspley Guise",
    "sg:city":"Milton Keynes",
    "sg:classifiers":[
        {
            "category":"Bars & Pubs",
            "type":"Food & Drink"
        }
    ],
    "sg:postcode":"MK17 8JZ",
    "sg:province":"Bedfordshire",
    "sg:tags":[
        "pubs",
        "inn"
    ],
    "wof:name":"The Wheatsheaf",
    "wof:placetype":"venue"
},
  "geometry": {"coordinates":[-0.6454610229,52.0093955994],"type":"Point"}
}