{
  "type": "Feature",
  "properties": {
    "addr:full":"20 Paradise Grove, Horsforth Leeds West Yorkshire LS18 4RN",
    "addr:housenumber":"20",
    "addr:postcode":"ls18 4rn",
    "addr:street":"Paradise Grove",
    "iso:country":"GB",
    "sg:address":"20 Paradise Grove, Horsforth",
    "sg:city":"Leeds",
    "sg:classifiers":[
        {
            "category":"Building & Trades",
            "subcategory":"Landscaping Services",
            "type":"Services"
        }
    ],
    "sg:phone":"+44 113 258 9775",
    "sg:postcode":"LS18 4RN",
    "sg:province":"West Yorkshire",
    "sg:tags":[
        "designer",
        "architect",
        "landscape"
    ],
    "wof:name":"Colm Mcatarsney",
    "wof:placetype":"venue"
},
  "geometry": {"coordinates":[-1.619549036,53.8353271484],"type":"Point"}
}