{
  "type": "Feature",
  "properties": {
    "addr:full":"4 New Mill Lane, Fazeley Tamworth Staffordshire B78 3RX",
    "addr:housenumber":"4",
    "addr:postcode":"b78 3rx",
    "addr:street":"New Mill Lane",
    "iso:country":"GB",
    "sg:address":"4 New Mill Lane, Fazeley",
    "sg:city":"Tamworth",
    "sg:classifiers":[
        {
            "category":"Building & Trades",
            "subcategory":"Plumbing",
            "type":"Services"
        }
    ],
    "sg:phone":"+44 1827 251060",
    "sg:postcode":"B78 3RX",
    "sg:province":"Staffordshire",
    "sg:tags":[
        "plumber",
        "heating"
    ],
    "wof:name":"Keith Storer",
    "wof:placetype":"venue"
},
  "geometry": {"coordinates":[-1.69658,52.611092],"type":"Point"}
}