{
  "type": "Feature",
  "properties": {
    "addr:full":"Unit 3, Sherriff Street Industrial Estat Worcester Worcestershire WR4 9AB",
    "addr:housenumber":"unit 3",
    "addr:postcode":"wr4 9ab",
    "addr:street":"Sherriff Street;Estat",
    "iso:country":"GB",
    "sg:address":"Unit 3, Sherriff Street Industrial Estat",
    "sg:city":"Worcester",
    "sg:classifiers":[
        {
            "category":"Professional",
            "subcategory":"Computer Services",
            "type":"Services"
        }
    ],
    "sg:phone":"+44 1458 273888",
    "sg:postcode":"WR4 9AB",
    "sg:province":"Worcestershire",
    "sg:tags":[
        "consultant"
    ],
    "wof:name":"Cornhull Associates Ltd.",
    "wof:placetype":"venue"
},
  "geometry": {"coordinates":[-2.206969,52.195171],"type":"Point"}
}