{
  "type": "Feature",
  "properties": {
    "addr:full":"54 Templeway West Lydney Gloucestershire GL15 5JD",
    "addr:housenumber":"54",
    "addr:postcode":"gl15 5jd",
    "addr:street":"Templeway West",
    "iso:country":"GB",
    "sg:address":"54 Templeway West",
    "sg:city":"Lydney",
    "sg:classifiers":[
        {
            "category":"Retail",
            "subcategory":"Driving School",
            "type":"Services"
        }
    ],
    "sg:phone":"+44 1594 841217",
    "sg:postcode":"GL15 5JD",
    "sg:province":"Gloucestershire",
    "wof:name":"G M G School of Motoring",
    "wof:placetype":"venue"
},
  "geometry": {"coordinates":[-2.536719,51.72559],"type":"Point"}
}