{
  "type": "Feature",
  "properties": {
    "addr:full":"27 Market Jew Street Penzance Cornwall TR18 2HR",
    "addr:housenumber":"27",
    "addr:postcode":"tr18 2hr",
    "addr:street":"Market Jew Street",
    "iso:country":"GB",
    "sg:address":"27 Market Jew Street",
    "sg:city":"Penzance",
    "sg:classifiers":[
        {
            "category":"Food & Beverages",
            "subcategory":"Bakery",
            "type":"Retail Goods"
        }
    ],
    "sg:phone":"+44 1736 331582",
    "sg:postcode":"TR18 2HR",
    "sg:province":"Cornwall",
    "sg:tags":[
        "baker"
    ],
    "wof:name":"Andrews Hot Bread Shop",
    "wof:placetype":"venue"
},
  "geometry": {"coordinates":[-5.5347619057,50.1203346252],"type":"Point"}
}