{
  "type": "Feature",
  "properties": {
    "iso:country":"GB",
    "sg:address":"Unit 12a Pondersnend Industrial Estate, Ducklees Lane",
    "sg:city":"Ware",
    "sg:classifiers":[
        {
            "category":"Retail",
            "subcategory":"Storage",
            "type":"Services"
        }
    ],
    "sg:phone":"+44 1920 467408",
    "sg:postcode":"EN3 7SR",
    "sg:province":"Greater London",
    "sg:tags":[
        "household",
        "removal"
    ],
    "wof:name":"Marsh & Sons",
    "wof:placetype":"venue"
},
  "geometry": {"coordinates":[-0.02677,51.646931],"type":"Point"}
}