{
  "type": "Feature",
  "properties": {
    "iso:country":"GB",
    "sg:address":"19 Whitehorse Street",
    "sg:city":"Baldock",
    "sg:classifiers":[
        {
            "category":"Real Estate",
            "subcategory":"Real Estate Agent",
            "type":"Services"
        }
    ],
    "sg:phone":"+44 1462 894945",
    "sg:postcode":"SG7 6QB",
    "sg:province":"Bedfordshire",
    "wof:name":"Putterills",
    "wof:placetype":"venue"
},
  "geometry": {"coordinates":[-0.187757,51.990616],"type":"Point"}
}