{
  "type": "Feature",
  "properties": {
    "addr:full":"Hilliard Ho, Lester Way Wallingford Oxfordshire OX10 9TA",
    "addr:postcode":"ox10 9ta",
    "addr:street":"Lester Way",
    "iso:country":"GB",
    "sg:address":"Hilliard Ho, Lester Way",
    "sg:city":"Wallingford",
    "sg:classifiers":[
        {
            "category":"Home & Garden",
            "subcategory":"Carpets & Floor Coverings",
            "type":"Retail Goods"
        }
    ],
    "sg:postcode":"OX10 9TA",
    "sg:province":"Oxfordshire",
    "sg:tags":[
        "carpets",
        "rug",
        "matting"
    ],
    "wof:name":"Nomax International Ltd",
    "wof:placetype":"venue"
},
  "geometry": {"coordinates":[-1.125623,51.60091],"type":"Point"}
}