{
  "type": "Feature",
  "properties": {
    "addr:full":"Botloes Grn Newent Gloucestershire GL18 1DW",
    "addr:postcode":"gl18 1dw",
    "addr:street":"Botloes Grn",
    "iso:country":"GB",
    "sg:address":"Botloes Grn",
    "sg:city":"Newent",
    "sg:classifiers":[
        {
            "category":"Building & Trades",
            "subcategory":"Landscaping Services",
            "type":"Services"
        }
    ],
    "sg:postcode":"GL18 1DW",
    "sg:province":"Gloucestershire",
    "sg:tags":[
        "contractor",
        "drainage"
    ],
    "wof:name":"Hyett,R, & Sons",
    "wof:placetype":"venue"
},
  "geometry": {"coordinates":[-2.4061338902,51.9308280945],"type":"Point"}
}