{
  "type": "Feature",
  "properties": {
    "addr:full":"Church Farm, Front Street Thirsk North Yorkshire YO7 1JF",
    "addr:postcode":"yo7 1jf",
    "addr:street":"Front Street",
    "iso:country":"GB",
    "sg:address":"Church Farm, Front Street",
    "sg:city":"Thirsk",
    "sg:classifiers":[
        {
            "category":"Restaurant",
            "type":"Food & Drink"
        }
    ],
    "sg:phone":"+44 1845 523655",
    "sg:postcode":"YO7 1JF",
    "sg:province":"North Yorkshire",
    "wof:name":"Oswalds",
    "wof:placetype":"venue"
},
  "geometry": {"coordinates":[-1.3422529697,54.2326889038],"type":"Point"}
}