{
  "type": "Feature",
  "properties": {
    "iso:country":"GB",
    "sg:address":"18 Phillip St",
    "sg:city":"Newport",
    "sg:classifiers":[
        {
            "category":"Professional",
            "subcategory":"Engineering",
            "type":"Services"
        }
    ],
    "sg:postcode":"NP19 0EE",
    "sg:province":"Newport",
    "sg:tags":[
        "contractor",
        "electrical",
        "engineer"
    ],
    "wof:name":"A & B Electrical Engineering",
    "wof:placetype":"venue"
},
  "geometry": {"coordinates":[-2.978194,51.587494],"type":"Point"}
}