{
  "type": "Feature",
  "properties": {
    "addr:full":"113 Harewood Rd Harrogate North Yorkshire HG3 2TJ",
    "addr:housenumber":"113",
    "addr:postcode":"hg3 2tj",
    "addr:street":"Harewood Rd",
    "iso:country":"GB",
    "sg:address":"113 Harewood Rd",
    "sg:city":"Harrogate",
    "sg:classifiers":[
        {
            "category":"Building & Trades",
            "subcategory":"Construction",
            "type":"Services"
        }
    ],
    "sg:postcode":"HG3 2TJ",
    "sg:province":"North Yorkshire",
    "sg:tags":[
        "roofing"
    ],
    "wof:name":"O'Brien,Mark,",
    "wof:placetype":"venue"
},
  "geometry": {"coordinates":[-1.559518,54.004276],"type":"Point"}
}