{
  "type": "Feature",
  "properties": {
    "addr:full":"11 Station Road Fowey Cornwall PL23 1DF",
    "addr:housenumber":"11",
    "addr:postcode":"pl23 1df",
    "addr:street":"Station Road",
    "iso:country":"GB",
    "sg:address":"11 Station Road",
    "sg:city":"Fowey",
    "sg:classifiers":[
        {
            "category":"Shopping",
            "subcategory":"Antiques",
            "type":"Retail Goods"
        }
    ],
    "sg:postcode":"PL23 1DF",
    "sg:province":"Cornwall",
    "wof:name":"Serendipity",
    "wof:placetype":"venue"
},
  "geometry": {"coordinates":[-4.6347050667,50.3395729065],"type":"Point"}
}