{
  "type": "Feature",
  "properties": {
    "addr:full":"Otford Lane, Halstead Sevenoaks Kent TN14 7EA",
    "addr:postcode":"tn14 7ea",
    "addr:street":"Otford Lane",
    "iso:country":"GB",
    "sg:address":"Otford Lane, Halstead",
    "sg:city":"Sevenoaks",
    "sg:classifiers":[
        {
            "category":"Education",
            "subcategory":"School",
            "type":"Public Place"
        }
    ],
    "sg:phone":"+44 1959 532224",
    "sg:postcode":"TN14 7EA",
    "sg:province":"Kent",
    "sg:tags":[
        "local",
        "authority"
    ],
    "wof:name":"Halstead County Primary School",
    "wof:placetype":"venue"
},
  "geometry": {"coordinates":[0.1336809993,51.3286056519],"type":"Point"}
}