{
  "type": "Feature",
  "properties": {
    "addr:full":"151 Lozells Road Birmingham West Midlands B19 2TP",
    "addr:housenumber":"151",
    "addr:postcode":"b19 2tp",
    "addr:street":"Lozells Road",
    "iso:country":"GB",
    "sg:address":"151 Lozells Road",
    "sg:city":"Birmingham",
    "sg:classifiers":[
        {
            "category":"Shopping",
            "subcategory":"Pharmacy",
            "type":"Retail Goods"
        }
    ],
    "sg:phone":"+44 121 523 7672",
    "sg:postcode":"B19 2TP",
    "sg:province":"West Midlands",
    "sg:tags":[
        "pharmacist",
        "chemist"
    ],
    "wof:name":"Calstar Ltd.",
    "wof:placetype":"venue"
},
  "geometry": {"coordinates":[-1.9083559513,52.5031051636],"type":"Point"}
}