{
  "type": "Feature",
  "properties": {
    "addr:full":"6 Glade Rd Marlow Berkshire SL7 1DX",
    "addr:housenumber":"6",
    "addr:postcode":"sl7 1dx",
    "addr:street":"Glade Rd",
    "iso:country":"GB",
    "sg:address":"6 Glade Rd",
    "sg:city":"Marlow",
    "sg:classifiers":[
        {
            "category":"Building & Trades",
            "subcategory":"Construction",
            "type":"Services"
        }
    ],
    "sg:phone":"+44 1628 475767",
    "sg:postcode":"SL7 1DX",
    "sg:province":"Berkshire",
    "sg:tags":[
        "roofing"
    ],
    "wof:name":"K M Rowe Roofing Services",
    "wof:placetype":"venue"
},
  "geometry": {"coordinates":[-0.769272,51.572159],"type":"Point"}
}