{
  "type": "Feature",
  "properties": {
    "addr:full":"142 Sandgate Road Folkestone Kent CT20 2EY",
    "addr:housenumber":"142",
    "addr:postcode":"ct20 2ey",
    "addr:street":"Sandgate Road",
    "iso:country":"GB",
    "sg:address":"142 Sandgate Road",
    "sg:city":"Folkestone",
    "sg:classifiers":[
        {
            "category":"Travel",
            "subcategory":"Hotels & Motels",
            "type":"Entertainment"
        }
    ],
    "sg:postcode":"CT20 2EY",
    "sg:province":"Kent",
    "wof:name":"Garden House Hotel",
    "wof:placetype":"venue"
},
  "geometry": {"coordinates":[1.1684559584,51.0766487122],"type":"Point"}
}