{
  "type": "Feature",
  "properties": {
    "addr:full":"Invision House Hitchin Hertfordshire SG4 0XE",
    "addr:postcode":"sg4 0xe",
    "addr:street":"Hitchin",
    "iso:country":"GB",
    "sg:address":"Invision House",
    "sg:city":"Hitchin",
    "sg:classifiers":[
        {
            "category":"Professional",
            "subcategory":"Business Services",
            "type":"Services"
        }
    ],
    "sg:phone":"+44 20 7865 0660",
    "sg:postcode":"SG4 0XE",
    "sg:province":"Hertfordshire",
    "sg:tags":[
        "registrar"
    ],
    "wof:name":"Mossack Fonseca & Co. (U K) Ltd.",
    "wof:placetype":"venue"
},
  "geometry": {"coordinates":[-0.25299,51.95956],"type":"Point"}
}