{
  "type": "Feature",
  "properties": {
    "addr:full":"52b High Street Middlesbrough North Yorkshire TS9 5AX",
    "addr:housenumber":"52b",
    "addr:postcode":"ts9 5ax",
    "addr:street":"High Street",
    "iso:country":"GB",
    "sg:address":"52b High Street",
    "sg:city":"Middlesbrough",
    "sg:classifiers":[
        {
            "category":"Professional",
            "subcategory":"Art Services",
            "type":"Services"
        }
    ],
    "sg:postcode":"TS9 5AX",
    "sg:province":"North Yorkshire",
    "sg:tags":[
        "graphic",
        "designer"
    ],
    "wof:name":"J S Designs",
    "wof:placetype":"venue"
},
  "geometry": {"coordinates":[-1.1945589781,54.4697113037],"type":"Point"}
}