{
  "type": "Feature",
  "properties": {
    "addr:full":"22 Victoria Parade Morecambe Lancashire LA4 5NY",
    "addr:housenumber":"22",
    "addr:postcode":"la4 5ny",
    "addr:street":"Victoria Parade",
    "iso:country":"GB",
    "sg:address":"22 Victoria Parade",
    "sg:city":"Morecambe",
    "sg:classifiers":[
        {
            "category":"Building & Trades",
            "subcategory":"Cleaning & Sanitation",
            "type":"Services"
        }
    ],
    "sg:phone":"+44 1524 412865",
    "sg:postcode":"LA4 5NY",
    "sg:province":"Lancashire",
    "sg:tags":[
        "cleaner",
        "window"
    ],
    "wof:name":"A.B Waterhouse",
    "wof:placetype":"venue"
},
  "geometry": {"coordinates":[-2.8549220562,54.0758171082],"type":"Point"}
}