{
  "type": "Feature",
  "properties": {
    "iso:country":"GB",
    "sg:address":"87 Main Street",
    "sg:city":"Ayr",
    "sg:classifiers":[
        {
            "category":"Shopping",
            "subcategory":"Department Store",
            "type":"Retail Goods"
        },
        {
            "category":"Shopping",
            "subcategory":"Bicycles & Sporting Goods",
            "type":"Retail Goods"
        }
    ],
    "sg:phone":"+44 1292 269822",
    "sg:postcode":"KA8 8BU",
    "sg:province":"South Ayrshire",
    "sg:tags":[
        "shop",
        "cycle",
        "accessory"
    ],
    "wof:name":"Carrick Cycles",
    "wof:placetype":"venue"
},
  "geometry": {"coordinates":[-4.630296,55.467468],"type":"Point"}
}