{
  "type": "Feature",
  "properties": {
    "addr:full":"Cauldon Rd Stoke On Trent Staffordshire ST4 2DZ",
    "addr:postcode":"st4 2dz",
    "addr:street":"Cauldon Rd",
    "iso:country":"GB",
    "sg:address":"Cauldon Rd",
    "sg:city":"Stoke On Trent",
    "sg:classifiers":[
        {
            "category":"Community Center",
            "type":"Public Place"
        }
    ],
    "sg:phone":"+44 1782 234790",
    "sg:postcode":"ST4 2DZ",
    "sg:province":"Staffordshire",
    "sg:tags":[
        "centre"
    ],
    "wof:name":"Shelton Community Centre",
    "wof:placetype":"venue"
},
  "geometry": {"coordinates":[-2.1817440987,53.0124511719],"type":"Point"}
}