{
  "type": "Feature",
  "properties": {
    "addr:full":"7 Whincroft Drive Ferndown Dorset BH22 9LH",
    "addr:housenumber":"7",
    "addr:postcode":"bh22 9lh",
    "addr:street":"Whincroft Drive",
    "iso:country":"GB",
    "sg:address":"7 Whincroft Drive",
    "sg:city":"Ferndown",
    "sg:classifiers":[
        {
            "category":"Building & Trades",
            "subcategory":"Construction",
            "type":"Services"
        }
    ],
    "sg:postcode":"BH22 9LH",
    "sg:province":"Dorset",
    "sg:tags":[
        "joinery",
        "joiner",
        "carpenter",
        "carpentry"
    ],
    "wof:name":"Eric Lavell",
    "wof:placetype":"venue"
},
  "geometry": {"coordinates":[-1.885807991,50.8090362549],"type":"Point"}
}