{
  "type": "Feature",
  "properties": {
    "addr:full":"64 St Johns St Folkestone Kent CT20 1HX",
    "addr:housenumber":"64",
    "addr:postcode":"ct20 1hx",
    "addr:street":"St Johns St",
    "iso:country":"GB",
    "sg:address":"64 St Johns St",
    "sg:city":"Folkestone",
    "sg:classifiers":[
        {
            "category":"Travel",
            "subcategory":"Hotels & Motels",
            "type":"Entertainment"
        }
    ],
    "sg:phone":"+44 1303 251529",
    "sg:postcode":"CT20 1HX",
    "sg:province":"Kent",
    "sg:tags":[
        "house",
        "guest"
    ],
    "wof:name":"The Old School House",
    "wof:placetype":"venue"
},
  "geometry": {"coordinates":[1.1806730032,51.0836334229],"type":"Point"}
}