{
  "type": "Feature",
  "properties": {
    "addr:full":"Rocks Farm, Eakley Lanes, Stoke Golddington Newport Pagnell Buckinghamshire MK16 8PA",
    "addr:postcode":"mk16 8pa",
    "addr:street":"Rocks;Eakley;Stoke",
    "iso:country":"GB",
    "sg:address":"Rocks Farm, Eakley Lanes, Stoke Golddington",
    "sg:city":"Newport Pagnell",
    "sg:classifiers":[
        {
            "category":"Professional",
            "subcategory":"Art Services",
            "type":"Services"
        }
    ],
    "sg:phone":"+44 1908 551065",
    "sg:postcode":"MK16 8PA",
    "sg:province":"Buckinghamshire",
    "sg:tags":[
        "photographer"
    ],
    "wof:name":"Geoff Stanton Photography",
    "wof:placetype":"venue"
},
  "geometry": {"coordinates":[-0.7230190039,52.0866966248],"type":"Point"}
}