{
  "type": "Feature",
  "properties": {
    "addr:full":"30 Reading Road South Fleet Dorset GU13 9QL",
    "addr:housenumber":"30",
    "addr:postcode":"gu13 9ql",
    "addr:street":"Reading Road South",
    "iso:country":"GB",
    "sg:address":"30 Reading Road South",
    "sg:city":"Fleet",
    "sg:classifiers":[
        {
            "category":"Utilities",
            "subcategory":"Fuel Oil & Lpg",
            "type":"Services"
        }
    ],
    "sg:phone":"+44 1252 620203",
    "sg:postcode":"GU13 9QL",
    "sg:province":"Dorset",
    "sg:tags":[
        "distributor"
    ],
    "wof:name":"Peter Douglas Services Ltd",
    "wof:placetype":"venue"
},
  "geometry": {"coordinates":[-0.844047,51.277618],"type":"Point"}
}