{
  "type": "Feature",
  "properties": {
    "iso:country":"GB",
    "sg:address":"30 High Street",
    "sg:city":"Chorley",
    "sg:classifiers":[
        {
            "category":"Banks & Credit Unions",
            "subcategory":"Financial Services",
            "type":"Services"
        }
    ],
    "sg:phone":"+44 1257 279373",
    "sg:postcode":"PR7 1DW",
    "sg:province":"Lancashire",
    "sg:tags":[
        "building",
        "society"
    ],
    "wof:name":"Chorley & District Building Society",
    "wof:placetype":"venue"
},
  "geometry": {"coordinates":[-2.6305990219,53.6537094116],"type":"Point"}
}