{
  "type": "Feature",
  "properties": {
    "iso:country":"GB",
    "sg:address":"Constituency Of Vale Of Clwyd, 47 Kinmel St",
    "sg:city":"Rhyl",
    "sg:classifiers":[
        {
            "category":"Government",
            "subcategory":"Office",
            "type":"Public Place"
        }
    ],
    "sg:phone":"+44 1745 354626",
    "sg:postcode":"LL18 1AG",
    "sg:province":"Conwy",
    "sg:tags":[
        "mp",
        "meps"
    ],
    "wof:name":"Chris Ruane MP (Lab)",
    "wof:placetype":"venue"
},
  "geometry": {"coordinates":[-3.472384,53.311581],"type":"Point"}
}