{
  "type": "Feature",
  "properties": {
    "addr:full":"45 High Street Emsworth Hampshire PO10 7AL",
    "addr:housenumber":"45",
    "addr:postcode":"po10 7al",
    "addr:street":"High Street",
    "iso:country":"GB",
    "sg:address":"45 High Street",
    "sg:city":"Emsworth",
    "sg:classifiers":[
        {
            "category":"Restaurant",
            "type":"Food & Drink"
        }
    ],
    "sg:phone":"+44 1243 376669",
    "sg:postcode":"PO10 7AL",
    "sg:province":"Hampshire",
    "sg:tags":[
        "indian"
    ],
    "wof:name":"The Standard",
    "wof:placetype":"venue"
},
  "geometry": {"coordinates":[-0.935859,50.845974],"type":"Point"}
}