{
  "type": "Feature",
  "properties": {
    "addr:full":"The Grange, Grange Road, Grange Valley, Haydock St. Helens Lancashire WA11 0XH",
    "addr:postcode":"wa11 0xh",
    "addr:street":"Grange Road;Haydock",
    "iso:country":"GB",
    "sg:address":"The Grange, Grange Road, Grange Valley, Haydock",
    "sg:city":"St. Helens",
    "sg:classifiers":[
        {
            "category":"Building & Trades",
            "subcategory":"Construction",
            "type":"Services"
        }
    ],
    "sg:phone":"+44 1925 224570",
    "sg:postcode":"WA11 0XH",
    "sg:province":"Lancashire",
    "sg:tags":[
        "builder"
    ],
    "wof:name":"Alan Walter Green",
    "wof:placetype":"venue"
},
  "geometry": {"coordinates":[-2.6844389439,53.467628479],"type":"Point"}
}