{
  "type": "Feature",
  "properties": {
    "addr:full":"Stall 52-53 Market Hall Preston Lancashire PR1 2DR",
    "addr:housenumber":"52-53",
    "addr:postcode":"pr1 2dr",
    "addr:street":"Market Hall",
    "iso:country":"GB",
    "sg:address":"Stall 52-53 Market Hall",
    "sg:city":"Preston",
    "sg:classifiers":[
        {
            "category":"Food & Beverages",
            "subcategory":"Bakery",
            "type":"Retail Goods"
        }
    ],
    "sg:postcode":"PR1 2DR",
    "sg:province":"Lancashire",
    "sg:tags":[
        "baker"
    ],
    "wof:name":"David Rees Instore Bakery",
    "wof:placetype":"venue"
},
  "geometry": {"coordinates":[-2.7057290077,53.7579612732],"type":"Point"}
}