{
  "type": "Feature",
  "properties": {
    "addr:full":"Victoria House, 24 London Road (a13) Benfleet Essex SS7 2QP",
    "addr:housenumber":"24",
    "addr:postcode":"ss7 2qp",
    "addr:street":"London Road A13 Benfleet",
    "iso:country":"GB",
    "sg:address":"Victoria House, 24 London Road (a13)",
    "sg:city":"Benfleet",
    "sg:classifiers":[
        {
            "category":"Building & Trades",
            "subcategory":"Construction",
            "type":"Services"
        }
    ],
    "sg:phone":"+44 1702 553112",
    "sg:postcode":"SS7 2QP",
    "sg:province":"Essex",
    "sg:tags":[
        "joinery"
    ],
    "wof:name":"Magnet Ltd.",
    "wof:placetype":"venue"
},
  "geometry": {"coordinates":[0.6024900079,51.5555458069],"type":"Point"}
}