{
  "type": "Feature",
  "properties": {
    "addr:full":"100 Newhaven Rd Edinburgh City of Edinburgh EH6 4BS",
    "addr:housenumber":"100",
    "addr:postcode":"eh6 4bs",
    "addr:street":"Newhaven Rd",
    "iso:country":"GB",
    "sg:address":"100 Newhaven Rd",
    "sg:city":"Edinburgh",
    "sg:classifiers":[
        {
            "category":"Wholesale",
            "subcategory":"Books, Periodicals, & Newspapers",
            "type":"Manufacturing & Wholesale Goods"
        }
    ],
    "sg:phone":"+44 131 553 2195",
    "sg:postcode":"EH6 4BS",
    "sg:province":"City of Edinburgh",
    "sg:tags":[
        "newsagent"
    ],
    "wof:name":"M.L Hanif",
    "wof:placetype":"venue"
},
  "geometry": {"coordinates":[-3.1879460812,55.9799232483],"type":"Point"}
}