{
  "type": "Feature",
  "properties": {
    "addr:full":"Unit 11, Coltswood Road Coatbridge North Lanarkshire ML5 2AF",
    "addr:housenumber":"unit 11",
    "addr:postcode":"ml5 2af",
    "addr:street":"Coltswood Road",
    "iso:country":"GB",
    "sg:address":"Unit 11, Coltswood Road",
    "sg:city":"Coatbridge",
    "sg:classifiers":[
        {
            "category":"Building & Trades",
            "subcategory":"Landscaping Services",
            "type":"Services"
        }
    ],
    "sg:phone":"+44 1236 627205",
    "sg:postcode":"ML5 2AF",
    "sg:province":"North Lanarkshire",
    "sg:tags":[
        "contractor",
        "drainage"
    ],
    "wof:name":"John McShannock Contractors Ltd.",
    "wof:placetype":"venue"
},
  "geometry": {"coordinates":[-4.025489,55.870949],"type":"Point"}
}