{
  "type": "Feature",
  "properties": {
    "addr:full":"Kingsgate House, Church Road, Kingswood Bristol City of Bristol BS15 4NN",
    "addr:postcode":"bs15 4nn",
    "addr:street":"Kingsgate;Church Road",
    "iso:country":"GB",
    "sg:address":"Kingsgate House, Church Road, Kingswood",
    "sg:city":"Bristol",
    "sg:classifiers":[
        {
            "category":"Organizations",
            "subcategory":"Non-profit Organization",
            "type":"Services"
        }
    ],
    "sg:phone":"+44 117 940 1111",
    "sg:postcode":"BS15 4NN",
    "sg:province":"City of Bristol",
    "sg:tags":[
        "organisation",
        "voluntary",
        "charity"
    ],
    "wof:name":"The Rescue - Foundation for the Brain Injured Infant",
    "wof:placetype":"venue"
},
  "geometry": {"coordinates":[-2.5016019344,51.4655685425],"type":"Point"}
}