{
  "type": "Feature",
  "properties": {
    "addr:full":"338 High St Orpington Kent BR6 0NQ",
    "addr:housenumber":"338",
    "addr:postcode":"br6 0nq",
    "addr:street":"High St",
    "iso:country":"GB",
    "sg:address":"338 High St",
    "sg:city":"Orpington",
    "sg:classifiers":[
        {
            "category":"Manufacturing",
            "subcategory":"Tools & Machinery",
            "type":"Manufacturing & Wholesale Goods"
        }
    ],
    "sg:phone":"+44 1689 837997",
    "sg:postcode":"BR6 0NQ",
    "sg:province":"Kent",
    "sg:tags":[
        "society",
        "friendly"
    ],
    "wof:name":"Tony Pillow",
    "wof:placetype":"venue"
},
  "geometry": {"coordinates":[0.097522,51.373676],"type":"Point"}
}