{
  "type": "Feature",
  "properties": {
    "iso:country":"GB",
    "sg:address":"4a Church St",
    "sg:city":"Gainsborough",
    "sg:classifiers":[
        {
            "category":"Shopping",
            "subcategory":"Shoes",
            "type":"Retail Goods"
        }
    ],
    "sg:phone":"+44 1427 616604",
    "sg:postcode":"DN21 2JH",
    "sg:province":"Lincolnshire",
    "wof:name":"Singleton Services",
    "wof:placetype":"venue"
},
  "geometry": {"coordinates":[-0.775491,53.399944],"type":"Point"}
}