{
  "type": "Feature",
  "properties": {
    "addr:full":"30 The Avenue Watford Hertfordshire WD17 4AE",
    "addr:housenumber":"30",
    "addr:postcode":"wd17 4ae",
    "addr:street":"The Avenue",
    "iso:country":"GB",
    "sg:address":"30 The Avenue",
    "sg:city":"Watford",
    "sg:classifiers":[
        {
            "category":"Real Estate",
            "subcategory":"Surveying",
            "type":"Services"
        }
    ],
    "sg:postcode":"WD17 4AE",
    "sg:province":"Hertfordshire",
    "sg:tags":[
        "surveyor",
        "valuer"
    ],
    "wof:name":"Bradford & Bingley Dormant 5 Ltd.",
    "wof:placetype":"venue"
},
  "geometry": {"coordinates":[-0.404305,51.661598],"type":"Point"}
}