{
  "type": "Feature",
  "properties": {
    "addr:full":"131 Totteridge Lane High Wycombe Buckinghamshire HP13 7PG",
    "addr:housenumber":"131",
    "addr:postcode":"hp13 7pg",
    "addr:street":"Totteridge Lane",
    "iso:country":"GB",
    "sg:address":"131 Totteridge Lane",
    "sg:city":"High Wycombe",
    "sg:classifiers":[
        {
            "category":"Professional",
            "subcategory":"Detective & Security Services",
            "type":"Services"
        },
        {
            "category":"Communications",
            "type":"Services"
        }
    ],
    "sg:postcode":"HP13 7PG",
    "sg:province":"Buckinghamshire",
    "sg:tags":[
        "tv",
        "radio",
        "video"
    ],
    "wof:name":"Atlas Aerials and Satellites",
    "wof:placetype":"venue"
},
  "geometry": {"coordinates":[-0.728282,51.643616],"type":"Point"}
}