{
  "type": "Feature",
  "properties": {
    "addr:full":"Unit 6 Garngoch Industrial Estate Swansea Carmarthenshire SA4 9WF",
    "addr:housenumber":"unit 6",
    "addr:postcode":"sa4 9wf",
    "addr:street":"Garngoch Industrial Estate",
    "iso:country":"GB",
    "sg:address":"Unit 6 Garngoch Industrial Estate",
    "sg:city":"Swansea",
    "sg:classifiers":[
        {
            "category":"Professional",
            "subcategory":"Engineering",
            "type":"Services"
        }
    ],
    "sg:postcode":"SA4 9WF",
    "sg:province":"Carmarthenshire",
    "sg:tags":[
        "engineer"
    ],
    "wof:name":"Universal Engineering Supplies Ltd.",
    "wof:placetype":"venue"
},
  "geometry": {"coordinates":[-4.018136,51.665321],"type":"Point"}
}