{
  "type": "Feature",
  "properties": {
    "addr:full":"57 Christchurch Road Bournemouth Dorset BH1 3PA",
    "addr:housenumber":"57",
    "addr:postcode":"bh1 3pa",
    "addr:street":"Christchurch Road",
    "iso:country":"GB",
    "sg:address":"57 Christchurch Road",
    "sg:city":"Bournemouth",
    "sg:classifiers":[
        {
            "category":"Travel",
            "subcategory":"Hotels & Motels",
            "type":"Entertainment"
        }
    ],
    "sg:phone":"+44 1202 393439",
    "sg:postcode":"BH1 3PA",
    "sg:province":"Dorset",
    "wof:name":"EAST CLIFF LODGE HOTEL",
    "wof:placetype":"venue"
},
  "geometry": {"coordinates":[-1.8513330221,50.7229309082],"type":"Point"}
}