{
  "type": "Feature",
  "properties": {
    "addr:full":"Frizinghall Post Office, 304 Keighley Road Bradford West Yorkshire BD9 4EY",
    "addr:housenumber":"304",
    "addr:postcode":"bd9 4ey",
    "addr:street":"Keighley Road",
    "iso:country":"GB",
    "sg:address":"Frizinghall Post Office, 304 Keighley Road",
    "sg:city":"Bradford",
    "sg:classifiers":[
        {
            "category":"Government",
            "subcategory":"Post Office",
            "type":"Public Place"
        }
    ],
    "sg:phone":"+44 1274 542833",
    "sg:postcode":"BD9 4EY",
    "sg:province":"West Yorkshire",
    "wof:name":"Frizinghall Post Office",
    "wof:placetype":"venue"
},
  "geometry": {"coordinates":[-1.774174,53.819717],"type":"Point"}
}