{
  "type": "Feature",
  "properties": {
    "addr:full":"77 Onslow Road Blackpool Lancashire FY3 7EP",
    "addr:housenumber":"77",
    "addr:postcode":"fy3 7ep",
    "addr:street":"Onslow Road",
    "iso:country":"GB",
    "sg:address":"77 Onslow Road",
    "sg:city":"Blackpool",
    "sg:classifiers":[
        {
            "category":"Food & Beverages",
            "subcategory":"Meat & Fish",
            "type":"Retail Goods"
        }
    ],
    "sg:phone":"+44 1253 391120",
    "sg:postcode":"FY3 7EP",
    "sg:province":"Lancashire",
    "sg:tags":[
        "chip"
    ],
    "wof:name":"Onslow Road Chippy",
    "wof:placetype":"venue"
},
  "geometry": {"coordinates":[-3.0271499157,53.8293190002],"type":"Point"}
}