{
  "type": "Feature",
  "properties": {
    "addr:full":"Newhaven Bus. Park Lowergate, Milnsbridge Huddersfield West Yorkshire HD3 4HS",
    "addr:postcode":"hd3 4hs",
    "addr:street":"Lowergate;West",
    "iso:country":"GB",
    "sg:address":"Newhaven Bus. Park Lowergate, Milnsbridge",
    "sg:city":"Huddersfield",
    "sg:classifiers":[
        {
            "category":"Freight",
            "type":"Transportation"
        }
    ],
    "sg:phone":"+44 1484 461717",
    "sg:postcode":"HD3 4HS",
    "sg:province":"West Yorkshire",
    "sg:tags":[
        "haulage",
        "road"
    ],
    "wof:name":"S & A Booth Transport",
    "wof:placetype":"venue"
},
  "geometry": {"coordinates":[-1.827694,53.637772],"type":"Point"}
}