{
  "type": "Feature",
  "properties": {
    "addr:full":"Mwyndy Business Park, Mwyndy Pontyclun Bridgend CF72 8PN",
    "addr:postcode":"cf72 8pn",
    "addr:street":"Business Park Mwyndy Pontyclun",
    "iso:country":"GB",
    "sg:address":"Mwyndy Business Park, Mwyndy",
    "sg:city":"Pontyclun",
    "sg:classifiers":[
        {
            "category":"Sports & Exercise",
            "subcategory":"Gym",
            "type":"Entertainment"
        }
    ],
    "sg:postcode":"CF72 8PN",
    "sg:province":"Bridgend",
    "sg:tags":[
        "fitness",
        "health",
        "centre"
    ],
    "wof:name":"Vale Health & Racquets Club Ltd.",
    "wof:placetype":"venue"
},
  "geometry": {"coordinates":[-3.373349,51.532742],"type":"Point"}
}