{
  "type": "Feature",
  "properties": {
    "iso:country":"GB",
    "sg:address":"53 Highfield Rd",
    "sg:city":"Doncaster",
    "sg:classifiers":[
        {
            "category":"Education",
            "subcategory":"Special Training",
            "type":"Public Place"
        }
    ],
    "sg:phone":"+44 1302 360160",
    "sg:postcode":"DN1 2NB",
    "sg:province":"South Yorkshire",
    "sg:tags":[
        "product",
        "centre"
    ],
    "wof:name":"Yorkshire Training Centre Ltd",
    "wof:placetype":"venue"
},
  "geometry": {"coordinates":[-1.124565,53.527641],"type":"Point"}
}