{
  "type": "Feature",
  "properties": {
    "addr:full":"78 High Street London Greater London SW19 5EG",
    "addr:housenumber":"78",
    "addr:postcode":"sw19 5eg",
    "addr:street":"High Street",
    "iso:country":"GB",
    "sg:address":"78 High Street",
    "sg:city":"London",
    "sg:classifiers":[
        {
            "category":"Shopping",
            "subcategory":"Clothing, Apparel, & Fashions",
            "type":"Retail Goods"
        }
    ],
    "sg:phone":"+44 20 8946 6288",
    "sg:postcode":"SW19 5EG",
    "sg:province":"Greater London",
    "sg:tags":[
        "shop"
    ],
    "wof:name":"Question Air",
    "wof:placetype":"venue"
},
  "geometry": {"coordinates":[-0.21643,51.424931],"type":"Point"}
}