{
  "type": "Feature",
  "properties": {
    "addr:full":"454 Babbacombe Road Torquay Devon TQ1 1HW",
    "addr:housenumber":"454",
    "addr:postcode":"tq1 1hw",
    "addr:street":"Babbacombe Road",
    "iso:country":"GB",
    "sg:address":"454 Babbacombe Road",
    "sg:city":"Torquay",
    "sg:classifiers":[
        {
            "category":"Health Services",
            "subcategory":"Nursing And Care Facility",
            "type":"Services"
        },
        {
            "category":"Social Services",
            "subcategory":"Retirement Home",
            "type":"Services"
        }
    ],
    "sg:phone":"+44 1803 292762",
    "sg:postcode":"TQ1 1HW",
    "sg:province":"Devon",
    "sg:tags":[
        "residential"
    ],
    "wof:name":"Amersham House Residential Home",
    "wof:placetype":"venue"
},
  "geometry": {"coordinates":[-3.5112259388,50.4646606445],"type":"Point"}
}