{
  "type": "Feature",
  "properties": {
    "addr:full":"12 Montenotte Road London Greater London N8 8RL",
    "addr:housenumber":"12",
    "addr:postcode":"n8 8rl",
    "addr:street":"Montenotte Road",
    "iso:country":"GB",
    "sg:address":"12 Montenotte Road",
    "sg:city":"London",
    "sg:classifiers":[
        {
            "category":"Freight",
            "type":"Transportation"
        },
        {
            "category":"Professional",
            "subcategory":"Business Services",
            "type":"Services"
        }
    ],
    "sg:phone":"+44 20 8374 8720",
    "sg:postcode":"N8 8RL",
    "sg:province":"Greater London",
    "sg:tags":[
        "import",
        "export",
        "agent",
        "forwarders"
    ],
    "wof:name":"TRINITY MANAGEMENT LTD",
    "wof:placetype":"venue"
},
  "geometry": {"coordinates":[-0.132663,51.580849],"type":"Point"}
}