{
  "type": "Feature",
  "properties": {
    "addr:full":"219 Waterloo Road London Greater London SE1 8XH",
    "addr:housenumber":"219",
    "addr:postcode":"se1 8xh",
    "addr:street":"Waterloo Road",
    "iso:country":"GB",
    "sg:address":"219 Waterloo Road",
    "sg:city":"London",
    "sg:classifiers":[
        {
            "category":"Personal",
            "subcategory":"Beauty Salon",
            "type":"Services"
        }
    ],
    "sg:phone":"+44 20 7928 6558",
    "sg:postcode":"SE1 8XH",
    "sg:province":"Greater London",
    "sg:tags":[
        "unisex",
        "hairdresser"
    ],
    "wof:name":"Step by Step",
    "wof:placetype":"venue"
},
  "geometry": {"coordinates":[-0.106889002,51.4998245239],"type":"Point"}
}