{
  "type": "Feature",
  "properties": {
    "iso:country":"GB",
    "sg:address":"Bowling Green Road, Thatcham",
    "sg:city":"Newbury",
    "sg:classifiers":[
        {
            "category":"Travel",
            "subcategory":"Hotels & Motels",
            "type":"Entertainment"
        }
    ],
    "sg:phone":"+44 1635 871555",
    "sg:postcode":"RG18 3RP",
    "sg:province":"Berkshire",
    "wof:name":"Regency Park Hotel",
    "wof:placetype":"venue"
},
  "geometry": {"coordinates":[-1.263599,51.403831],"type":"Point"}
}