{
  "type": "Feature",
  "properties": {
    "addr:full":"Jubilee House, Abbotswell Road Fordingbridge Dorset SP6 2JA",
    "addr:postcode":"sp6 2ja",
    "addr:street":"Abbotswell Road",
    "iso:country":"GB",
    "sg:address":"Jubilee House, Abbotswell Road",
    "sg:city":"Fordingbridge",
    "sg:classifiers":[
        {
            "category":"Building & Trades",
            "subcategory":"Construction",
            "type":"Services"
        }
    ],
    "sg:postcode":"SP6 2JA",
    "sg:province":"Dorset",
    "sg:tags":[
        "builder"
    ],
    "wof:name":"New Forest Building Contractors",
    "wof:placetype":"venue"
},
  "geometry": {"coordinates":[-1.749592,50.918316],"type":"Point"}
}