{
  "type": "Feature",
  "properties": {
    "iso:country":"GB",
    "sg:address":"Unit 11, Claggy Road Industrial Estate, Kimpton",
    "sg:city":"Hitchin",
    "sg:classifiers":[
        {
            "category":"Retail",
            "subcategory":"Auto Repair",
            "type":"Services"
        }
    ],
    "sg:phone":"+44 1438 832995",
    "sg:postcode":"SG4 8QA",
    "sg:province":"Hertfordshire",
    "sg:tags":[
        "body",
        "car"
    ],
    "wof:name":"Kimpton Coachworks",
    "wof:placetype":"venue"
},
  "geometry": {"coordinates":[-0.3009589911,51.8524551392],"type":"Point"}
}