{
  "type": "Feature",
  "properties": {
    "iso:country":"GB",
    "sg:address":"3 Stafford House, 1 Maida Avenue",
    "sg:city":"London",
    "sg:classifiers":[
        {
            "category":"Communications",
            "type":"Services"
        }
    ],
    "sg:postcode":"W2 1JE",
    "sg:province":"Greater London",
    "sg:tags":[
        "audio-visual"
    ],
    "wof:name":"Borderland Productions Ltd.",
    "wof:placetype":"venue"
},
  "geometry": {"coordinates":[-0.1767559946,51.5243453979],"type":"Point"}
}