{
  "type": "Feature",
  "properties": {
    "addr:full":"Dagger La West Bromwich West Midlands B71 4BU",
    "addr:postcode":"b71 4bu",
    "addr:street":"Dagger La West",
    "iso:country":"GB",
    "sg:address":"Dagger La",
    "sg:city":"West Bromwich",
    "sg:classifiers":[
        {
            "category":"Education",
            "subcategory":"School",
            "type":"Public Place"
        }
    ],
    "sg:phone":"+44 121 553 3374",
    "sg:postcode":"B71 4BU",
    "sg:province":"West Midlands",
    "sg:tags":[
        "local",
        "authority"
    ],
    "wof:name":"Albright Home & Hospital Tuition Service",
    "wof:placetype":"venue"
},
  "geometry": {"coordinates":[-1.9844889641,52.5270957947],"type":"Point"}
}