{
  "type": "Feature",
  "properties": {
    "addr:full":"15a-15d Leighton Place London Greater London NW5 2QL",
    "addr:housenumber":"15a-15d",
    "addr:postcode":"nw5 2ql",
    "addr:street":"Leighton Place",
    "iso:country":"GB",
    "sg:address":"15a-15d Leighton Place",
    "sg:city":"London",
    "sg:classifiers":[
        {
            "category":"Shopping",
            "subcategory":"Clothing, Apparel, & Fashions",
            "type":"Retail Goods"
        }
    ],
    "sg:postcode":"NW5 2QL",
    "sg:province":"Greater London",
    "sg:tags":[
        "clothing"
    ],
    "wof:name":"Photograph Wholesale Ltd.",
    "wof:placetype":"venue"
},
  "geometry": {"coordinates":[-0.134921,51.551949],"type":"Point"}
}