{
  "type": "Feature",
  "properties": {
    "addr:full":"34d Fairview Road, Norbury London Greater London SW16 5PT",
    "addr:housenumber":"34d",
    "addr:postcode":"sw16 5pt",
    "addr:street":"Fairview Road",
    "iso:country":"GB",
    "sg:address":"34d Fairview Road, Norbury",
    "sg:city":"London",
    "sg:classifiers":[
        {
            "category":"Retail",
            "subcategory":"Auto Repair",
            "type":"Services"
        }
    ],
    "sg:phone":"+44 20 8679 7090",
    "sg:postcode":"SW16 5PT",
    "sg:province":"Greater London",
    "sg:tags":[
        "modification",
        "garage"
    ],
    "wof:name":"T H Motors",
    "wof:placetype":"venue"
},
  "geometry": {"coordinates":[-0.1245300025,51.4117012024],"type":"Point"}
}