{
  "type": "Feature",
  "properties": {
    "iso:country":"GB",
    "sg:address":"128 Lordship La, East Dulwich",
    "sg:city":"East Dulwich",
    "sg:classifiers":[
        {
            "category":"Shopping",
            "subcategory":"Clothing, Apparel, & Fashions",
            "type":"Retail Goods"
        }
    ],
    "sg:phone":"+44 20 8299 4164",
    "sg:postcode":"SE22 8HD",
    "sg:province":"Greater London",
    "sg:tags":[
        "ladieswear"
    ],
    "wof:name":"Family Tree The",
    "wof:placetype":"venue"
},
  "geometry": {"coordinates":[-0.07655,51.45583],"type":"Point"}
}