{
  "type": "Feature",
  "properties": {
    "iso:country":"GB",
    "sg:address":"Kantersted Road, Lerwick",
    "sg:city":"Shetland",
    "sg:classifiers":[
        {
            "category":"Social Services",
            "type":"Services"
        },
        {
            "category":"Government",
            "subcategory":"Office",
            "type":"Public Place"
        }
    ],
    "sg:phone":"+44 1595 694647",
    "sg:postcode":"ZE1 0RJ",
    "sg:province":"Shetland Islands",
    "sg:tags":[
        "local",
        "ds"
    ],
    "wof:name":"Eric Gray Centre",
    "wof:placetype":"venue"
},
  "geometry": {"coordinates":[-1.145224,60.151829],"type":"Point"}
}