{
  "type": "Feature",
  "properties": {
    "addr:full":"Old Georges School, Green Dragon La Brentford Greater London TW8 0DN",
    "addr:postcode":"tw8 0dn",
    "addr:street":"Old;Brentford",
    "iso:country":"GB",
    "sg:address":"Old Georges School, Green Dragon La",
    "sg:city":"Brentford",
    "sg:classifiers":[
        {
            "category":"Community Center",
            "type":"Public Place"
        }
    ],
    "sg:phone":"+44 20 8568 7727",
    "sg:postcode":"TW8 0DN",
    "sg:province":"Greater London",
    "sg:tags":[
        "centre"
    ],
    "wof:name":"St Georges Community Association",
    "wof:placetype":"venue"
},
  "geometry": {"coordinates":[-0.3067240119,51.4841346741],"type":"Point"}
}