{
  "type": "Feature",
  "properties": {
    "iso:country":"GB",
    "sg:address":"Porth Y Post, Lon Isallt, Trearddur Bay",
    "sg:city":"Holyhead",
    "sg:classifiers":[
        {
            "category":"Sports & Exercise",
            "subcategory":"Stables",
            "type":"Entertainment"
        },
        {
            "category":"Personal",
            "subcategory":"Adult",
            "type":"Services"
        }
    ],
    "sg:phone":"+44 1407 861358",
    "sg:postcode":"LL65 2UP",
    "sg:province":"Isle of Anglesey",
    "sg:tags":[
        "schools",
        "riding",
        "livery",
        "equestrian",
        "centre"
    ],
    "wof:name":"Porth-y-Post Riding Stables",
    "wof:placetype":"venue"
},
  "geometry": {"coordinates":[-4.630714,53.30637],"type":"Point"}
}