{
  "type": "Feature",
  "properties": {
    "addr:full":"205-207 Uxbridge Road London Greater London W7 3TH",
    "addr:housenumber":"205-207",
    "addr:postcode":"w7 3th",
    "addr:street":"Uxbridge Road",
    "iso:country":"GB",
    "sg:address":"205-207 Uxbridge Road",
    "sg:city":"London",
    "sg:classifiers":[
        {
            "category":"Professional",
            "subcategory":"Computer Services",
            "type":"Services"
        }
    ],
    "sg:phone":"+44 20 8248 5665",
    "sg:postcode":"W7 3TH",
    "sg:province":"Greater London",
    "sg:tags":[
        "system",
        "software"
    ],
    "wof:name":"Computer Corporates",
    "wof:placetype":"venue"
},
  "geometry": {"coordinates":[-0.340985,51.5084],"type":"Point"}
}