{
  "type": "Feature",
  "properties": {
    "iso:country":"GB",
    "sg:address":"63 Kimberley Road",
    "sg:city":"Bournemouth",
    "sg:classifiers":[
        {
            "category":"Food & Beverages",
            "subcategory":"Meat & Fish",
            "type":"Retail Goods"
        }
    ],
    "sg:phone":"+44 1202 425073",
    "sg:postcode":"BH6 5DD",
    "sg:province":"Dorset",
    "sg:tags":[
        "chip"
    ],
    "wof:name":"Maxi's Plaice",
    "wof:placetype":"venue"
},
  "geometry": {"coordinates":[-1.8111929893,50.7306938171],"type":"Point"}
}