{
  "type": "Feature",
  "properties": {
    "iso:country":"GB",
    "sg:address":"188-194 Green Lane, Greatlever",
    "sg:city":"Bolton",
    "sg:classifiers":[
        {
            "category":"Wholesale",
            "subcategory":"Scrap",
            "type":"Manufacturing & Wholesale Goods"
        }
    ],
    "sg:phone":"+44 1204 534726",
    "sg:postcode":"BL3 2LX",
    "sg:province":"Lancashire",
    "sg:tags":[
        "waste",
        "metal"
    ],
    "wof:name":"Belroy",
    "wof:placetype":"venue"
},
  "geometry": {"coordinates":[-2.4123558998,53.5585327148],"type":"Point"}
}