{
  "type": "Feature",
  "properties": {
    "addr:full":"Colesdon Road, Wilden Bedford Bedfordshire MK40 3YD",
    "addr:postcode":"mk40 3yd",
    "addr:street":"Colesdon Road",
    "iso:country":"GB",
    "sg:address":"Colesdon Road, Wilden",
    "sg:city":"Bedford",
    "sg:classifiers":[
        {
            "category":"Autos & Motor Vehicles",
            "subcategory":"Automobile Sales",
            "type":"Retail Goods"
        }
    ],
    "sg:phone":"+44 1933 358888",
    "sg:postcode":"MK40 3YD",
    "sg:province":"Bedfordshire",
    "sg:tags":[
        "car"
    ],
    "wof:name":"Wavetone Ltd.",
    "wof:placetype":"venue"
},
  "geometry": {"coordinates":[-0.4649580121,52.1389732361],"type":"Point"}
}