{
  "type": "Feature",
  "properties": {
    "addr:full":"Main Rd King's Lynn Norfolk PE31 8BY",
    "addr:postcode":"pe31 8by",
    "addr:street":"Main Rd",
    "iso:country":"GB",
    "sg:address":"Main Rd",
    "sg:city":"King's Lynn",
    "sg:classifiers":[
        {
            "category":"Bars & Pubs",
            "type":"Food & Drink"
        }
    ],
    "sg:phone":"+44 1485 210262",
    "sg:postcode":"PE31 8BY",
    "sg:province":"Norfolk",
    "sg:tags":[
        "pubs",
        "inn"
    ],
    "wof:name":"Lobster Pot The",
    "wof:placetype":"venue"
},
  "geometry": {"coordinates":[0.6800500154,52.9659118652],"type":"Point"}
}