{
  "type": "Feature",
  "properties": {
    "iso:country":"GB",
    "sg:address":"64 Princes Street",
    "sg:city":"Stockport",
    "sg:classifiers":[
        {
            "category":"Shopping",
            "subcategory":"Clothing, Apparel, & Fashions",
            "type":"Retail Goods"
        }
    ],
    "sg:phone":"+44 161 480 4764",
    "sg:postcode":"SK1 1RY",
    "sg:province":"Cheshire",
    "sg:tags":[
        "lingerie",
        "hosiery"
    ],
    "wof:name":"Contessa (Ladieswear) Ltd.",
    "wof:placetype":"venue"
},
  "geometry": {"coordinates":[-2.1620719433,53.411277771],"type":"Point"}
}