{
  "type": "Feature",
  "properties": {
    "iso:country":"GB",
    "sg:address":"28 Eastern Way",
    "sg:city":"Bury St Edmunds",
    "sg:classifiers":[
        {
            "category":"Professional",
            "subcategory":"Engineering",
            "type":"Services"
        }
    ],
    "sg:phone":"+44 1284 761528",
    "sg:postcode":"IP32 7AB",
    "sg:province":"Suffolk",
    "sg:tags":[
        "contractor",
        "electrical",
        "engineer"
    ],
    "wof:name":"Glasswell & Last Ltd",
    "wof:placetype":"venue"
},
  "geometry": {"coordinates":[0.7256249785,52.2514762878],"type":"Point"}
}