{
  "type": "Feature",
  "properties": {
    "iso:country":"GB",
    "sg:address":"13 Melbourne Rd",
    "sg:city":"Ibstock",
    "sg:classifiers":[
        {
            "category":"Real Estate",
            "subcategory":"Real Estate Agent",
            "type":"Services"
        }
    ],
    "sg:postcode":"LE67 6JS",
    "sg:province":"Leicestershire",
    "wof:name":"M E D Properties",
    "wof:placetype":"venue"
},
  "geometry": {"coordinates":[-1.403737,52.685089],"type":"Point"}
}