{
  "type": "Feature",
  "properties": {
    "iso:country":"GB",
    "sg:address":"Unit 2 202 Pershore Road South",
    "sg:city":"Birmingham",
    "sg:classifiers":[
        {
            "category":"Government",
            "subcategory":"Post Office",
            "type":"Public Place"
        }
    ],
    "sg:phone":"+44 121 486 2994",
    "sg:postcode":"B30 3EU",
    "sg:province":"West Midlands",
    "sg:tags":[
        "messenger",
        "courier"
    ],
    "wof:name":"Elite Express Services",
    "wof:placetype":"venue"
},
  "geometry": {"coordinates":[-1.928808,52.410728],"type":"Point"}
}