{
  "type": "Feature",
  "properties": {
    "addr:full":"163-167a Yorkshire Street Rochdale Lancashire OL12 0DR",
    "addr:housenumber":"163-167a",
    "addr:postcode":"ol12 0dr",
    "addr:street":"Yorkshire Street",
    "iso:country":"GB",
    "sg:address":"163-167a Yorkshire Street",
    "sg:city":"Rochdale",
    "sg:classifiers":[
        {
            "category":"Home & Garden",
            "subcategory":"Furniture",
            "type":"Retail Goods"
        }
    ],
    "sg:phone":"+44 1706 645344",
    "sg:postcode":"OL12 0DR",
    "sg:province":"Lancashire",
    "sg:tags":[
        "outlet"
    ],
    "wof:name":"LOVICKS LTD",
    "wof:placetype":"venue"
},
  "geometry": {"coordinates":[-2.1509180069,53.6213302612],"type":"Point"}
}