{
  "type": "Feature",
  "properties": {
    "addr:full":"14a Ash Road, Horfield Bristol City of Bristol BS7 8RN",
    "addr:housenumber":"14a",
    "addr:postcode":"bs7 8rn",
    "addr:street":"Ash Road",
    "iso:country":"GB",
    "sg:address":"14a Ash Road, Horfield",
    "sg:city":"Bristol",
    "sg:classifiers":[
        {
            "category":"Professional",
            "subcategory":"Engineering",
            "type":"Services"
        }
    ],
    "sg:phone":"+44 117 942 2381",
    "sg:postcode":"BS7 8RN",
    "sg:province":"City of Bristol",
    "sg:tags":[
        "contractor",
        "electrical",
        "engineer"
    ],
    "wof:name":"Bristol & Avon Contractors Ltd.",
    "wof:placetype":"venue"
},
  "geometry": {"coordinates":[-2.5889570713,51.4835128784],"type":"Point"}
}