{
  "type": "Feature",
  "properties": {
    "addr:full":"Carlton House, 17-19 Carlton Street Liverpool Merseyside L3 7ED",
    "addr:housenumber":"17-19",
    "addr:postcode":"l3 7ed",
    "addr:street":"Carlton Street",
    "iso:country":"GB",
    "sg:address":"Carlton House, 17-19 Carlton Street",
    "sg:city":"Liverpool",
    "sg:classifiers":[
        {
            "category":"Education",
            "subcategory":"Special Training",
            "type":"Public Place"
        }
    ],
    "sg:postcode":"L3 7ED",
    "sg:province":"Merseyside",
    "sg:tags":[
        "diving",
        "school"
    ],
    "wof:name":"Riverside Diving School",
    "wof:placetype":"venue"
},
  "geometry": {"coordinates":[-2.9968791008,53.4181938171],"type":"Point"}
}