{
  "type": "Feature",
  "properties": {
    "addr:full":"Brynteg Llandovery Carmarthenshire SA20 0ET",
    "addr:postcode":"sa20 0et",
    "iso:country":"GB",
    "sg:address":"Brynteg",
    "sg:city":"Llandovery",
    "sg:classifiers":[
        {
            "category":"Organizations",
            "subcategory":"Non-profit Organization",
            "type":"Services"
        }
    ],
    "sg:postcode":"SA20 0ET",
    "sg:province":"Carmarthenshire",
    "sg:tags":[
        "organisation",
        "voluntary",
        "charity"
    ],
    "wof:name":"Countrywide Workshops",
    "wof:placetype":"venue"
},
  "geometry": {"coordinates":[-3.8001549244,51.9940872192],"type":"Point"}
}