{
  "type": "Feature",
  "properties": {
    "addr:full":"Oundle Road, Lutton Peterborough Cambridgeshire PE8 5ND",
    "addr:postcode":"pe8 5nd",
    "addr:street":"Oundle Road",
    "iso:country":"GB",
    "sg:address":"Oundle Road, Lutton",
    "sg:city":"Peterborough",
    "sg:classifiers":[
        {
            "category":"Building & Trades",
            "subcategory":"Landscaping Services",
            "type":"Services"
        }
    ],
    "sg:phone":"+44 1832 272450",
    "sg:postcode":"PE8 5ND",
    "sg:province":"Cambridgeshire",
    "sg:tags":[
        "irrigation",
        "system"
    ],
    "wof:name":"I L S Irrigation Systems & Equipment",
    "wof:placetype":"venue"
},
  "geometry": {"coordinates":[-0.3631669879,52.4769821167],"type":"Point"}
}