{
  "type": "Feature",
  "properties": {
    "iso:country":"GB",
    "sg:address":"42a Preston St",
    "sg:city":"Brighton",
    "sg:classifiers":[
        {
            "category":"Personal",
            "subcategory":"Nail Salon",
            "type":"Services"
        }
    ],
    "sg:phone":"+44 1273 207500",
    "sg:postcode":"BN1 2HP",
    "sg:province":"East Sussex",
    "sg:tags":[
        "solarium",
        "tanning"
    ],
    "wof:name":"Tanarama",
    "wof:placetype":"venue"
},
  "geometry": {"coordinates":[-0.150835,50.823997],"type":"Point"}
}