{
  "type": "Feature",
  "properties": {
    "addr:full":"St Paul's Church Office, Darwall Street Walsall West Midlands WS1 1DA",
    "addr:postcode":"ws1 1da",
    "addr:street":"St;Darwall Street",
    "iso:country":"GB",
    "sg:address":"St Paul's Church Office, Darwall Street",
    "sg:city":"Walsall",
    "sg:classifiers":[
        {
            "category":"Farming",
            "subcategory":"Nursery",
            "type":"Manufacturing & Wholesale Goods"
        },
        {
            "category":"Commercial Area",
            "type":"Public Place"
        }
    ],
    "sg:phone":"+44 1922 645992",
    "sg:postcode":"WS1 1DA",
    "sg:province":"West Midlands",
    "sg:tags":[
        "shop",
        "creche",
        "centre"
    ],
    "wof:name":"St. Paul's Enterprises Ltd.",
    "wof:placetype":"venue"
},
  "geometry": {"coordinates":[-1.9815100431,52.585319519],"type":"Point"}
}