{
  "type": "Feature",
  "properties": {
    "addr:full":"24 Avenue Road Sandown Isle of Wight PO36 8BN",
    "addr:housenumber":"24",
    "addr:postcode":"po36 8bn",
    "addr:street":"Avenue Road",
    "iso:country":"GB",
    "sg:address":"24 Avenue Road",
    "sg:city":"Sandown",
    "sg:classifiers":[
        {
            "category":"Food & Beverages",
            "subcategory":"Meat & Fish",
            "type":"Retail Goods"
        }
    ],
    "sg:postcode":"PO36 8BN",
    "sg:province":"Isle of Wight",
    "sg:tags":[
        "butcher"
    ],
    "wof:name":"Brians Family Butchers",
    "wof:placetype":"venue"
},
  "geometry": {"coordinates":[-1.1503139734,50.6575050354],"type":"Point"}
}