{
  "type": "Feature",
  "properties": {
    "addr:full":"Bell Hill, Norton St Philip Bath Somerset BA2 7LT",
    "addr:postcode":"ba2 7lt",
    "addr:street":"Bell Hill Norton St",
    "iso:country":"GB",
    "sg:address":"Bell Hill, Norton St Philip",
    "sg:city":"Bath",
    "sg:classifiers":[
        {
            "category":"Government",
            "subcategory":"Post Office",
            "type":"Public Place"
        }
    ],
    "sg:postcode":"BA2 7LT",
    "sg:province":"Somerset",
    "wof:name":"NORTON ST PHILIP POST OFFICE",
    "wof:placetype":"venue"
},
  "geometry": {"coordinates":[-2.3261899948,51.3018989563],"type":"Point"}
}