{
  "type": "Feature",
  "properties": {
    "addr:full":"7 Carlos Place London Greater London W1K 3AR",
    "addr:housenumber":"7",
    "addr:postcode":"w1k 3ar",
    "addr:street":"Carlos Place",
    "iso:country":"GB",
    "sg:address":"7 Carlos Place",
    "sg:city":"London",
    "sg:classifiers":[
        {
            "category":"Professional",
            "subcategory":"Detective & Security Services",
            "type":"Services"
        }
    ],
    "sg:phone":"+44 20 7297 6700",
    "sg:postcode":"W1K 3AR",
    "sg:province":"Greater London",
    "wof:name":"Group 4 Total Security Ltd.",
    "wof:placetype":"venue"
},
  "geometry": {"coordinates":[-0.149292,51.510429],"type":"Point"}
}