{
  "type": "Feature",
  "properties": {
    "addr:full":"194 Leigh Road Leigh-on-sea Essex SS9 1BS",
    "addr:housenumber":"194",
    "addr:postcode":"ss9 1bs",
    "addr:street":"Leigh Road",
    "iso:country":"GB",
    "sg:address":"194 Leigh Road",
    "sg:city":"Leigh-on-sea",
    "sg:classifiers":[
        {
            "category":"Restaurant",
            "type":"Food & Drink"
        }
    ],
    "sg:phone":"+44 1702 714204",
    "sg:postcode":"SS9 1BS",
    "sg:province":"Essex",
    "wof:name":"Goldstar Consulting Ltd.",
    "wof:placetype":"venue"
},
  "geometry": {"coordinates":[0.664813,51.543026],"type":"Point"}
}