{
  "type": "Feature",
  "properties": {
    "addr:full":"Bryony Place, Conniburrow Milton Keynes Buckinghamshire MK14 7AR",
    "addr:postcode":"mk14 7ar",
    "addr:street":"Bryony Place Conniburrow",
    "iso:country":"GB",
    "sg:address":"Bryony Place, Conniburrow",
    "sg:city":"Milton Keynes",
    "sg:classifiers":[
        {
            "category":"Education",
            "subcategory":"School",
            "type":"Public Place"
        }
    ],
    "sg:phone":"+44 1908 678366",
    "sg:postcode":"MK14 7AR",
    "sg:province":"Buckinghamshire",
    "sg:tags":[
        "local",
        "authority"
    ],
    "wof:name":"Southwood Middle School",
    "wof:placetype":"venue"
},
  "geometry": {"coordinates":[-0.755972,52.05167],"type":"Point"}
}