{
  "type": "Feature",
  "properties": {
    "addr:full":"5 Drummers Corner Peterhead Aberdeenshire AB42 6ZP",
    "addr:housenumber":"5",
    "addr:postcode":"ab42 6zp",
    "addr:street":"Drummers Corner",
    "iso:country":"GB",
    "sg:address":"5 Drummers Corner",
    "sg:city":"Peterhead",
    "sg:classifiers":[
        {
            "category":"Shopping",
            "subcategory":"Thrift Store",
            "type":"Retail Goods"
        }
    ],
    "sg:phone":"+44 1779 476881",
    "sg:postcode":"AB42 6ZP",
    "sg:province":"Aberdeenshire",
    "sg:tags":[
        "shop",
        "charity"
    ],
    "wof:name":"Imperial Cancer Research Fund",
    "wof:placetype":"venue"
},
  "geometry": {"coordinates":[-1.797219038,57.5065345764],"type":"Point"}
}