{
  "type": "Feature",
  "properties": {
    "addr:full":"Dounby Orkney Orkney Islands KW17 2HX",
    "addr:housenumber":"orkney orkney",
    "addr:postcode":"kw17 2hx",
    "iso:country":"GB",
    "sg:address":"Dounby",
    "sg:city":"Orkney",
    "sg:classifiers":[
        {
            "category":"Retail",
            "subcategory":"Auto Repair",
            "type":"Services"
        }
    ],
    "sg:phone":"+44 1856 771240",
    "sg:postcode":"KW17 2HX",
    "sg:province":"Orkney Islands",
    "sg:tags":[
        "modification",
        "garage"
    ],
    "wof:name":"Dounby Garage",
    "wof:placetype":"venue"
},
  "geometry": {"coordinates":[-3.2253899574,59.0718917847],"type":"Point"}
}