{
  "type": "Feature",
  "properties": {
    "iso:country":"GB",
    "sg:address":"4 Wellington Court",
    "sg:city":"Cambridge",
    "sg:classifiers":[
        {
            "category":"Professional",
            "subcategory":"Computer Services",
            "type":"Services"
        }
    ],
    "sg:phone":"+44 1223 510500",
    "sg:postcode":"CB1 1HZ",
    "sg:province":"Cambridgeshire",
    "sg:tags":[
        "system",
        "software"
    ],
    "wof:name":"Tessella Support Services",
    "wof:placetype":"venue"
},
  "geometry": {"coordinates":[0.135089,52.207932],"type":"Point"}
}