{
  "type": "Feature",
  "properties": {
    "iso:country":"GB",
    "sg:address":"Peace And Plenty, Water Newton",
    "sg:city":"Peterborough",
    "sg:classifiers":[
        {
            "category":"Home & Garden",
            "subcategory":"Building Materials",
            "type":"Retail Goods"
        }
    ],
    "sg:phone":"+44 1733 233601",
    "sg:postcode":"PE8 6LZ",
    "sg:province":"Cambridgeshire",
    "sg:tags":[
        "fencing"
    ],
    "wof:name":"John Bradley",
    "wof:placetype":"venue"
},
  "geometry": {"coordinates":[-0.3641900122,52.5615081787],"type":"Point"}
}