{
  "type": "Feature",
  "properties": {
    "iso:country":"GB",
    "sg:address":"35 The Slade, Plumstead",
    "sg:city":"Woolwich",
    "sg:classifiers":[
        {
            "category":"Bars & Pubs",
            "type":"Food & Drink"
        }
    ],
    "sg:phone":"+44 20 8333 0602",
    "sg:postcode":"SE18 2NB",
    "sg:province":"Greater London",
    "sg:tags":[
        "pubs",
        "inn"
    ],
    "wof:name":"The Woodman",
    "wof:placetype":"venue"
},
  "geometry": {"coordinates":[0.0891100019,51.480255127],"type":"Point"}
}