{
  "type": "Feature",
  "properties": {
    "iso:country":"GB",
    "sg:address":"38 High Street",
    "sg:city":"Leiston",
    "sg:classifiers":[
        {
            "category":"Shopping",
            "subcategory":"Bicycles & Sporting Goods",
            "type":"Retail Goods"
        }
    ],
    "sg:phone":"+44 1728 830199",
    "sg:postcode":"IP16 4EW",
    "sg:province":"Suffolk",
    "sg:tags":[
        "cycle",
        "accessory"
    ],
    "wof:name":"Road Runner",
    "wof:placetype":"venue"
},
  "geometry": {"coordinates":[1.577097,52.206711],"type":"Point"}
}