{
  "type": "Feature",
  "properties": {
    "addr:full":"King Street Wimborne Dorset BH21 1AY",
    "addr:postcode":"bh21 1ay",
    "addr:street":"King Street",
    "iso:country":"GB",
    "sg:address":"King Street",
    "sg:city":"Wimborne",
    "sg:classifiers":[
        {
            "category":"Place Of Worship",
            "type":"Public Place"
        }
    ],
    "sg:phone":"+44 1202 884474",
    "sg:postcode":"BH21 1AY",
    "sg:province":"Dorset",
    "wof:name":"Wimborne Methodist Church",
    "wof:placetype":"venue"
},
  "geometry": {"coordinates":[-1.987568,50.798599],"type":"Point"}
}