{
  "type": "Feature",
  "properties": {
    "iso:country":"GB",
    "sg:address":"15 Drumhead Road, Glasgow East Investment Park",
    "sg:city":"Glasgow",
    "sg:classifiers":[
        {
            "category":"Manufacturing",
            "subcategory":"Rubber & Plastics",
            "type":"Manufacturing & Wholesale Goods"
        }
    ],
    "sg:phone":"+44 141 646 1144",
    "sg:postcode":"G32 8EX",
    "sg:province":"Glasgow City",
    "sg:tags":[
        "product"
    ],
    "wof:name":"Scotplast (Containers) Ltd.",
    "wof:placetype":"venue"
},
  "geometry": {"coordinates":[-4.176847,55.834614],"type":"Point"}
}