{
  "type": "Feature",
  "properties": {
    "iso:country":"GB",
    "sg:address":"3a Moniton Estate, West Ham Lane",
    "sg:city":"Basingstoke",
    "sg:classifiers":[
        {
            "category":"Home & Garden",
            "subcategory":"Building Materials",
            "type":"Retail Goods"
        }
    ],
    "sg:phone":"+44 1256 814484",
    "sg:postcode":"RG22 6NQ",
    "sg:province":"Hampshire",
    "sg:tags":[
        "window",
        "frame"
    ],
    "wof:name":"Easiglass & Glazing",
    "wof:placetype":"venue"
},
  "geometry": {"coordinates":[-1.13235,51.262932],"type":"Point"}
}