{
  "type": "Feature",
  "properties": {
    "addr:full":"1a Coronado Rd Gosport Hampshire PO12 4RE",
    "addr:housenumber":"1a",
    "addr:postcode":"po12 4re",
    "addr:street":"Coronado Rd",
    "iso:country":"GB",
    "sg:address":"1a Coronado Rd",
    "sg:city":"Gosport",
    "sg:classifiers":[
        {
            "category":"Professional",
            "subcategory":"Management & Consulting",
            "type":"Services"
        }
    ],
    "sg:phone":"+44 23 9260 2938",
    "sg:postcode":"PO12 4RE",
    "sg:province":"Hampshire",
    "sg:tags":[
        "consultant",
        "business"
    ],
    "wof:name":"Rayford Associates",
    "wof:placetype":"venue"
},
  "geometry": {"coordinates":[-1.14212,50.805145],"type":"Point"}
}