{
  "type": "Feature",
  "properties": {
    "addr:full":"Station App Pewsey Wiltshire SN9 5EL",
    "addr:postcode":"sn9 5el",
    "addr:street":"Pewsey",
    "iso:country":"GB",
    "sg:address":"Station App",
    "sg:city":"Pewsey",
    "sg:classifiers":[
        {
            "category":"Recreation",
            "subcategory":"Amusement Park",
            "type":"Entertainment"
        }
    ],
    "sg:phone":"+44 1672 562345",
    "sg:postcode":"SN9 5EL",
    "sg:province":"Wiltshire",
    "sg:tags":[
        "arcade"
    ],
    "wof:name":"Three Services Automatics Ltd.",
    "wof:placetype":"venue"
},
  "geometry": {"coordinates":[-1.762319,51.340286],"type":"Point"}
}