{
  "type": "Feature",
  "properties": {
    "addr:full":"Merrose Farm, Illogan Redruth Cornwall TR15 3UZ",
    "addr:postcode":"tr15 3uz",
    "iso:country":"GB",
    "sg:address":"Merrose Farm, Illogan",
    "sg:city":"Redruth",
    "sg:classifiers":[
        {
            "category":"Farming",
            "subcategory":"Farm",
            "type":"Manufacturing & Wholesale Goods"
        }
    ],
    "sg:phone":"+44 1209 842257",
    "sg:postcode":"TR15 3UZ",
    "sg:province":"Cornwall",
    "sg:tags":[
        "mixed",
        "crop"
    ],
    "wof:name":"J G D Richards & Son",
    "wof:placetype":"venue"
},
  "geometry": {"coordinates":[-5.2294340134,50.232509613],"type":"Point"}
}