{
  "type": "Feature",
  "properties": {
    "iso:country":"GB",
    "sg:address":"P O Box 42",
    "sg:city":"Middlesbrough",
    "sg:classifiers":[
        {
            "category":"Building & Trades",
            "subcategory":"Construction",
            "type":"Services"
        }
    ],
    "sg:phone":"+44 1642 588748",
    "sg:postcode":"TS1 4AR",
    "sg:province":"North Yorkshire",
    "sg:tags":[
        "equipment"
    ],
    "wof:name":"A M",
    "wof:placetype":"venue"
},
  "geometry": {"coordinates":[-1.236569,54.572971],"type":"Point"}
}