{
  "type": "Feature",
  "properties": {
    "addr:full":"School Street, Howden Le Wear Crook Durham DL15 8HJ",
    "addr:postcode":"dl15 8hj",
    "addr:street":"School Street",
    "iso:country":"GB",
    "sg:address":"School Street, Howden Le Wear",
    "sg:city":"Crook",
    "sg:classifiers":[
        {
            "category":"Education",
            "subcategory":"School",
            "type":"Public Place"
        },
        {
            "category":"Government",
            "subcategory":"Office",
            "type":"Public Place"
        }
    ],
    "sg:phone":"+44 1388 763287",
    "sg:postcode":"DL15 8HJ",
    "sg:province":"Durham",
    "sg:tags":[
        "local",
        "authority"
    ],
    "wof:name":"Howden Le Wear Primary School",
    "wof:placetype":"venue"
},
  "geometry": {"coordinates":[-1.7508939505,54.6948204041],"type":"Point"}
}