{
  "type": "Feature",
  "properties": {
    "addr:full":"H F M House, New Road Weybridge Surrey KT13 9BW",
    "addr:postcode":"kt13 9bw",
    "addr:street":"New Road",
    "iso:country":"GB",
    "sg:address":"H F M House, New Road",
    "sg:city":"Weybridge",
    "sg:classifiers":[
        {
            "category":"Banks & Credit Unions",
            "subcategory":"Financial Services",
            "type":"Services"
        }
    ],
    "sg:phone":"+44 1932 870000",
    "sg:postcode":"KT13 9BW",
    "sg:province":"Surrey",
    "sg:tags":[
        "adviser",
        "independent"
    ],
    "wof:name":"Hoyland Financial Management",
    "wof:placetype":"venue"
},
  "geometry": {"coordinates":[-0.4493289888,51.3670806885],"type":"Point"}
}