{
  "type": "Feature",
  "properties": {
    "iso:country":"GB",
    "sg:address":"184a Kensington Park Road",
    "sg:city":"London",
    "sg:classifiers":[
        {
            "category":"Restaurant",
            "type":"Food & Drink"
        }
    ],
    "sg:phone":"+44 20 7221 1150",
    "sg:postcode":"W11 2ES",
    "sg:province":"Greater London",
    "wof:name":"Cafe med Ltd.",
    "wof:placetype":"venue"
},
  "geometry": {"coordinates":[-0.2051980048,51.5148468018],"type":"Point"}
}