{
  "type": "Feature",
  "properties": {
    "addr:full":"1 Hazelwood Road, Chaddesden Derby Derbyshire DE21 4HT",
    "addr:housenumber":"1",
    "addr:postcode":"de21 4ht",
    "addr:street":"Hazelwood Road",
    "iso:country":"GB",
    "sg:address":"1 Hazelwood Road, Chaddesden",
    "sg:city":"Derby",
    "sg:classifiers":[
        {
            "category":"Professional",
            "subcategory":"Engineering",
            "type":"Services"
        }
    ],
    "sg:phone":"+44 1332 740719",
    "sg:postcode":"DE21 4HT",
    "sg:province":"Derbyshire",
    "sg:tags":[
        "contractor",
        "electrical",
        "engineer"
    ],
    "wof:name":"Mike Whittingham",
    "wof:placetype":"venue"
},
  "geometry": {"coordinates":[-1.4383909702,52.9377670288],"type":"Point"}
}