{
  "type": "Feature",
  "properties": {
    "addr:full":"31 Ruvigny Gardens London Greater London SW15 1JR",
    "addr:housenumber":"31",
    "addr:postcode":"sw15 1jr",
    "addr:street":"Ruvigny Gardens",
    "iso:country":"GB",
    "sg:address":"31 Ruvigny Gardens",
    "sg:city":"London",
    "sg:classifiers":[
        {
            "category":"Professional",
            "subcategory":"Management & Consulting",
            "type":"Services"
        },
        {
            "category":"Wholesale",
            "subcategory":"Music Publishers",
            "type":"Manufacturing & Wholesale Goods"
        }
    ],
    "sg:phone":"+44 20 8785 6262",
    "sg:postcode":"SW15 1JR",
    "sg:province":"Greater London",
    "wof:name":"Roger Waters Music U K Ltd.",
    "wof:placetype":"venue"
},
  "geometry": {"coordinates":[-0.2191060036,51.467464447],"type":"Point"}
}