{
  "type": "Feature",
  "properties": {
    "iso:country":"GB",
    "sg:address":"20 Beeches Road",
    "sg:city":"Sutton",
    "sg:classifiers":[
        {
            "category":"Professional",
            "subcategory":"Computer Services",
            "type":"Services"
        }
    ],
    "sg:phone":"+44 20 8543 6550",
    "sg:postcode":"SM3 9NA",
    "sg:province":"Surrey",
    "sg:tags":[
        "system",
        "software"
    ],
    "wof:name":"The Beeches Consultancy Ltd.",
    "wof:placetype":"venue"
},
  "geometry": {"coordinates":[-0.2139230072,51.3808746338],"type":"Point"}
}