{
  "type": "Feature",
  "properties": {
    "addr:full":"145 Cowick Street Exeter Devon EX4 1AS",
    "addr:housenumber":"145",
    "addr:postcode":"ex4 1as",
    "addr:street":"Cowick Street",
    "iso:country":"GB",
    "sg:address":"145 Cowick Street",
    "sg:city":"Exeter",
    "sg:classifiers":[
        {
            "category":"Food & Beverages",
            "subcategory":"Liquor & Beverages",
            "type":"Retail Goods"
        }
    ],
    "sg:phone":"+44 1392 431923",
    "sg:postcode":"EX4 1AS",
    "sg:province":"Devon",
    "sg:tags":[
        "beer",
        "spirit",
        "wines"
    ],
    "wof:name":"Thresher Wine Shop",
    "wof:placetype":"venue"
},
  "geometry": {"coordinates":[-3.542735,50.715939],"type":"Point"}
}