{
  "type": "Feature",
  "properties": {
    "addr:full":"19 Applecross Road, Kirkintilloch Glasgow East Dunbartonshire G66 3TJ",
    "addr:housenumber":"19",
    "addr:postcode":"g66 3tj",
    "addr:street":"Applecross Road",
    "iso:country":"GB",
    "sg:address":"19 Applecross Road, Kirkintilloch",
    "sg:city":"Glasgow",
    "sg:classifiers":[
        {
            "category":"Retail",
            "subcategory":"Driving School",
            "type":"Services"
        }
    ],
    "sg:phone":"+44 141 777 7671",
    "sg:postcode":"G66 3TJ",
    "sg:province":"East Dunbartonshire",
    "wof:name":"Popular School of Motoring",
    "wof:placetype":"venue"
},
  "geometry": {"coordinates":[-4.1197781563,55.9422416687],"type":"Point"}
}