{
  "type": "Feature",
  "properties": {
    "iso:country":"GB",
    "sg:address":"12 Goodwood Square, Teesside Retail Park",
    "sg:city":"Stockton-on-tees",
    "sg:classifiers":[
        {
            "category":"Home & Garden",
            "subcategory":"Home Furnishings",
            "type":"Retail Goods"
        }
    ],
    "sg:phone":"+44 1642 617665",
    "sg:postcode":"TS17 7BU",
    "sg:province":"Durham",
    "sg:tags":[
        "blind",
        "curtain",
        "fitting"
    ],
    "wof:name":"Mostyn Group Ltd.",
    "wof:placetype":"venue"
},
  "geometry": {"coordinates":[-1.275138,54.556126],"type":"Point"}
}