{
  "type": "Feature",
  "properties": {
    "iso:country":"GB",
    "sg:address":"Greasby Library, Greasby Rd",
    "sg:city":"Wirral",
    "sg:classifiers":[
        {
            "category":"Government",
            "subcategory":"Office",
            "type":"Public Place"
        }
    ],
    "sg:phone":"+44 151 677 5714",
    "sg:postcode":"CH49 3NH",
    "sg:province":"Merseyside",
    "sg:tags":[
        "local"
    ],
    "wof:name":"Metropolitan Borough of Wirral",
    "wof:placetype":"venue"
},
  "geometry": {"coordinates":[-3.126784,53.377766],"type":"Point"}
}