{
  "type": "Feature",
  "properties": {
    "addr:full":"Riverbank House, 1 Putney Bridge App London Greater London SW6 3JD",
    "addr:housenumber":"1",
    "addr:postcode":"sw6 3jd",
    "addr:street":"Putney Bridge",
    "iso:country":"GB",
    "sg:address":"Riverbank House, 1 Putney Bridge App",
    "sg:city":"London",
    "sg:classifiers":[
        {
            "category":"Professional",
            "subcategory":"Computer Services",
            "type":"Services"
        }
    ],
    "sg:phone":"+44 20 7751 9858",
    "sg:postcode":"SW6 3JD",
    "sg:province":"Greater London",
    "sg:tags":[
        "consultant"
    ],
    "wof:name":"N S L (Internet) Ltd.",
    "wof:placetype":"venue"
},
  "geometry": {"coordinates":[-0.113013,51.526512],"type":"Point"}
}