{
  "type": "Feature",
  "properties": {
    "addr:full":"146 Masefield Drive Tamworth Staffordshire B79 8JA",
    "addr:housenumber":"146",
    "addr:postcode":"b79 8ja",
    "addr:street":"Masefield Drive",
    "iso:country":"GB",
    "sg:address":"146 Masefield Drive",
    "sg:city":"Tamworth",
    "sg:classifiers":[
        {
            "category":"Shopping",
            "subcategory":"Pharmacy",
            "type":"Retail Goods"
        }
    ],
    "sg:postcode":"B79 8JA",
    "sg:province":"Staffordshire",
    "sg:tags":[
        "pharmacist",
        "chemist"
    ],
    "wof:name":"Siswick Pharmacy",
    "wof:placetype":"venue"
},
  "geometry": {"coordinates":[-1.701856,52.6432],"type":"Point"}
}