{
  "type": "Feature",
  "properties": {
    "addr:full":"Marsh La Off Middleton Rd Salisbury Wiltshire SP2 7AZ",
    "addr:postcode":"sp2 7az",
    "addr:street":"Marsh;Off Middleton Rd",
    "iso:country":"GB",
    "sg:address":"Marsh La Off Middleton Rd",
    "sg:city":"Salisbury",
    "sg:classifiers":[
        {
            "category":"Autos & Motor Vehicles",
            "subcategory":"Fuel & Gas Station",
            "type":"Retail Goods"
        }
    ],
    "sg:postcode":"SP2 7AZ",
    "sg:province":"Wiltshire",
    "sg:tags":[
        "aga",
        "cooker"
    ],
    "wof:name":"Salisbury's Cooker Centre",
    "wof:placetype":"venue"
},
  "geometry": {"coordinates":[-1.8002840281,51.0695381165],"type":"Point"}
}