{
  "type": "Feature",
  "properties": {
    "addr:full":"7 High St East Glossop Derbyshire SK13 8DA",
    "addr:housenumber":"7",
    "addr:postcode":"sk13 8da",
    "addr:street":"High St",
    "iso:country":"GB",
    "sg:address":"7 High St East",
    "sg:city":"Glossop",
    "sg:classifiers":[
        {
            "category":"Professional",
            "subcategory":"Lawyer & Legal Services",
            "type":"Services"
        }
    ],
    "sg:phone":"+44 1457 854645",
    "sg:postcode":"SK13 8DA",
    "sg:province":"Derbyshire",
    "sg:tags":[
        "solicitor"
    ],
    "wof:name":"William Hall & Co",
    "wof:placetype":"venue"
},
  "geometry": {"coordinates":[-1.9484499693,53.4434585571],"type":"Point"}
}