{
  "type": "Feature",
  "properties": {
    "addr:full":"16 Morley Road Blackpool Lancashire FY4 4EP",
    "addr:housenumber":"16",
    "addr:postcode":"fy4 4ep",
    "addr:street":"Morley Road",
    "iso:country":"GB",
    "sg:address":"16 Morley Road",
    "sg:city":"Blackpool",
    "sg:classifiers":[
        {
            "category":"Building & Trades",
            "subcategory":"Construction",
            "type":"Services"
        }
    ],
    "sg:phone":"+44 1253 791502",
    "sg:postcode":"FY4 4EP",
    "sg:province":"Lancashire",
    "sg:tags":[
        "decorator",
        "painter"
    ],
    "wof:name":"Paul Roberts",
    "wof:placetype":"venue"
},
  "geometry": {"coordinates":[-3.0281350613,53.7986335754],"type":"Point"}
}