{
  "type": "Feature",
  "properties": {
    "iso:country":"GB",
    "sg:address":"13 Front Street, Colliery Row",
    "sg:city":"Houghton-le-spring",
    "sg:classifiers":[
        {
            "category":"Personal",
            "subcategory":"Beauty Salon",
            "type":"Services"
        }
    ],
    "sg:phone":"+44 191 385 6930",
    "sg:postcode":"DH4 6LR",
    "sg:province":"Durham",
    "sg:tags":[
        "unisex",
        "hairdresser"
    ],
    "wof:name":"Croppers",
    "wof:placetype":"venue"
},
  "geometry": {"coordinates":[-1.495168,54.841396],"type":"Point"}
}