{
  "type": "Feature",
  "properties": {
    "addr:full":"Neil's Produce Trading Estate, Town St Upwell Wisbech Cambridgeshire PE14 9AD",
    "addr:postcode":"pe14 9ad",
    "addr:street":"Trading Estate Town St",
    "iso:country":"GB",
    "sg:address":"Neil's Produce Trading Estate, Town St Upwell",
    "sg:city":"Wisbech",
    "sg:classifiers":[
        {
            "category":"Shopping",
            "subcategory":"Pets & Pet Supplies",
            "type":"Retail Goods"
        }
    ],
    "sg:postcode":"PE14 9AD",
    "sg:province":"Cambridgeshire",
    "sg:tags":[
        "food"
    ],
    "wof:name":"Snax 'N Pax (Uk)",
    "wof:placetype":"venue"
},
  "geometry": {"coordinates":[0.22259,52.603168],"type":"Point"}
}