{
  "type": "Feature",
  "properties": {
    "addr:full":"5-6 Lilybank Gdns Glasgow Glasgow City G12 8RX",
    "addr:housenumber":"5-6",
    "addr:postcode":"g12 8rx",
    "addr:street":"Lilybank Gdns",
    "iso:country":"GB",
    "sg:address":"5-6 Lilybank Gdns",
    "sg:city":"Glasgow",
    "sg:classifiers":[
        {
            "category":"Government",
            "subcategory":"Post Office",
            "type":"Public Place"
        }
    ],
    "sg:phone":"+44 141 357 3949",
    "sg:postcode":"G12 8RX",
    "sg:province":"Glasgow City",
    "sg:tags":[
        "organisation",
        "soc",
        "research"
    ],
    "wof:name":"Medical Research Council",
    "wof:placetype":"venue"
},
  "geometry": {"coordinates":[-4.2913579941,55.8749961853],"type":"Point"}
}