{
  "type": "Feature",
  "properties": {
    "addr:full":"Scottish Regional Organiser, 4 Hepburn Way, Lawthorn Irvine East Ayrshire KA11 2EE",
    "addr:housenumber":"4",
    "addr:postcode":"ka11 2ee",
    "addr:street":"Hepburn Way Lawthorn",
    "iso:country":"GB",
    "sg:address":"Scottish Regional Organiser, 4 Hepburn Way, Lawthorn",
    "sg:city":"Irvine",
    "sg:classifiers":[
        {
            "category":"Organizations",
            "subcategory":"Non-profit Organization",
            "type":"Services"
        }
    ],
    "sg:postcode":"KA11 2EE",
    "sg:province":"East Ayrshire",
    "sg:tags":[
        "organisation",
        "voluntary",
        "charity"
    ],
    "wof:name":"Child Infertility Support Network",
    "wof:placetype":"venue"
},
  "geometry": {"coordinates":[-4.624129,55.633839],"type":"Point"}
}