{
  "type": "Feature",
  "properties": {
    "addr:full":"Netherbank 9 Routenburn Rd Largs North Ayrshire KA30 8QA",
    "addr:housenumber":"9",
    "addr:postcode":"ka30 8qa",
    "addr:street":"Netherbank;Routenburn Rd",
    "iso:country":"GB",
    "sg:address":"Netherbank 9 Routenburn Rd",
    "sg:city":"Largs",
    "sg:classifiers":[
        {
            "category":"Building & Trades",
            "subcategory":"Construction",
            "type":"Services"
        }
    ],
    "sg:phone":"+44 1475 686795",
    "sg:postcode":"KA30 8QA",
    "sg:province":"North Ayrshire",
    "sg:tags":[
        "joiner",
        "carpenter"
    ],
    "wof:name":"Hodge Builders",
    "wof:placetype":"venue"
},
  "geometry": {"coordinates":[-4.860015,55.788734],"type":"Point"}
}