{
  "type": "Feature",
  "properties": {
    "iso:country":"GB",
    "sg:address":"Ickworth, Woodstock Road, Yarnton",
    "sg:city":"Oxford",
    "sg:classifiers":[
        {
            "category":"Professional",
            "subcategory":"Detective & Security Services",
            "type":"Services"
        }
    ],
    "sg:phone":"+44 1865 373508",
    "sg:postcode":"OX5 1PH",
    "sg:province":"Buckinghamshire",
    "wof:name":"Harris Enterprises Security Services",
    "wof:placetype":"venue"
},
  "geometry": {"coordinates":[-1.309754,51.809246],"type":"Point"}
}