{
  "type": "Feature",
  "properties": {
    "iso:country":"GB",
    "sg:address":"1 Lockwood Square",
    "sg:city":"London",
    "sg:classifiers":[
        {
            "category":"Shopping",
            "subcategory":"News",
            "type":"Retail Goods"
        }
    ],
    "sg:phone":"+44 20 7231 0556",
    "sg:postcode":"SE16 2HS",
    "sg:province":"Greater London",
    "sg:tags":[
        "newsagent"
    ],
    "wof:name":"Lockwood Stores",
    "wof:placetype":"venue"
},
  "geometry": {"coordinates":[-0.0602939986,51.4964561462],"type":"Point"}
}