{
  "type": "Feature",
  "properties": {
    "addr:full":"13 Bell Centre, Nottingham Street Melton Mowbray Leicestershire LE13 1PJ",
    "addr:housenumber":"13",
    "addr:postcode":"le13 1pj",
    "addr:street":"Bell Centre Nottingham Street",
    "iso:country":"GB",
    "sg:address":"13 Bell Centre, Nottingham Street",
    "sg:city":"Melton Mowbray",
    "sg:classifiers":[
        {
            "category":"Retail",
            "subcategory":"Laundry & Dry Cleaning",
            "type":"Services"
        }
    ],
    "sg:phone":"+44 1664 63142",
    "sg:postcode":"LE13 1PJ",
    "sg:province":"Leicestershire",
    "sg:tags":[
        "alteration"
    ],
    "wof:name":"Harris Clean",
    "wof:placetype":"venue"
},
  "geometry": {"coordinates":[-0.8879609704,52.7656364441],"type":"Point"}
}