{
  "type": "Feature",
  "properties": {
    "addr:full":"Church Farm, North Killingholme Immingham Lincolnshire DN40 3JW",
    "addr:housenumber":"killingholme",
    "addr:postcode":"dn40 3jw",
    "addr:street":"North",
    "iso:country":"GB",
    "sg:address":"Church Farm, North Killingholme",
    "sg:city":"Immingham",
    "sg:classifiers":[
        {
            "category":"Organizations",
            "subcategory":"Non-profit Organization",
            "type":"Services"
        }
    ],
    "sg:phone":"+44 1469 541666",
    "sg:postcode":"DN40 3JW",
    "sg:province":"Lincolnshire",
    "sg:tags":[
        "organisation",
        "animal",
        "welfare"
    ],
    "wof:name":"Humberside Animal Rescue",
    "wof:placetype":"venue"
},
  "geometry": {"coordinates":[-0.2752439976,53.6421661377],"type":"Point"}
}