{
  "type": "Feature",
  "properties": {
    "addr:full":"1 Parrock Road Gravesend Kent DA12 1PY",
    "addr:housenumber":"1",
    "addr:postcode":"da12 1py",
    "addr:street":"Parrock Road",
    "iso:country":"GB",
    "sg:address":"1 Parrock Road",
    "sg:city":"Gravesend",
    "sg:classifiers":[
        {
            "category":"Travel",
            "subcategory":"Hotels & Motels",
            "type":"Entertainment"
        }
    ],
    "sg:phone":"+44 1474 352929",
    "sg:postcode":"DA12 1PY",
    "sg:province":"Kent",
    "sg:tags":[
        "house",
        "guest"
    ],
    "wof:name":"South Hill Bank Bed & Breakfast",
    "wof:placetype":"venue"
},
  "geometry": {"coordinates":[0.373926,51.435867],"type":"Point"}
}