{
  "type": "Feature",
  "properties": {
    "iso:country":"GB",
    "sg:address":"Dalton Road",
    "sg:city":"Port Talbot",
    "sg:classifiers":[
        {
            "category":"Organizations",
            "subcategory":"Membership Organization",
            "type":"Services"
        }
    ],
    "sg:phone":"+44 1639 884309",
    "sg:postcode":"SA12 6SL",
    "sg:province":"Neath Port Talbot",
    "sg:tags":[
        "club"
    ],
    "wof:name":"Seaside Social & Labour Club & Institute Ltd.",
    "wof:placetype":"venue"
},
  "geometry": {"coordinates":[-3.812764,51.594669],"type":"Point"}
}