{
  "type": "Feature",
  "properties": {
    "addr:full":"457 Soundwell Road Bristol City of Bristol BS15 1JT",
    "addr:housenumber":"457",
    "addr:postcode":"bs15 1jt",
    "addr:street":"Soundwell Road",
    "iso:country":"GB",
    "sg:address":"457 Soundwell Road",
    "sg:city":"Bristol",
    "sg:classifiers":[
        {
            "category":"Health Services",
            "subcategory":"Dentist",
            "type":"Services"
        }
    ],
    "sg:phone":"+44 117 967 3207",
    "sg:postcode":"BS15 1JT",
    "sg:province":"City of Bristol",
    "wof:name":"R J A Cutler & Associates",
    "wof:placetype":"venue"
},
  "geometry": {"coordinates":[-2.514318943,51.4637451172],"type":"Point"}
}