{
  "type": "Feature",
  "properties": {
    "iso:country":"GB",
    "sg:address":"3 St James Close",
    "sg:city":"New Malden",
    "sg:classifiers":[
        {
            "category":"Professional",
            "type":"Services"
        }
    ],
    "sg:postcode":"KT3 6DU",
    "sg:province":"Surrey",
    "sg:tags":[
        "leasing"
    ],
    "wof:name":"Watersfield Projects Ltd",
    "wof:placetype":"venue"
},
  "geometry": {"coordinates":[-0.2534,51.39558],"type":"Point"}
}