{
  "type": "Feature",
  "properties": {
    "addr:full":"3 Pine Tree Close Cowes Isle of Wight PO31 8DX",
    "addr:housenumber":"3",
    "addr:postcode":"po31 8dx",
    "addr:street":"Pine Tree Close",
    "iso:country":"GB",
    "sg:address":"3 Pine Tree Close",
    "sg:city":"Cowes",
    "sg:classifiers":[
        {
            "category":"Building & Trades",
            "subcategory":"Construction",
            "type":"Services"
        }
    ],
    "sg:postcode":"PO31 8DX",
    "sg:province":"Isle of Wight",
    "sg:tags":[
        "builder"
    ],
    "wof:name":"Attrill & Daish",
    "wof:placetype":"venue"
},
  "geometry": {"coordinates":[-1.3142969608,50.7640953064],"type":"Point"}
}