{
  "type": "Feature",
  "properties": {
    "iso:country":"GB",
    "sg:address":"Carlton Lane, Lofthouse",
    "sg:city":"Wakefield",
    "sg:classifiers":[
        {
            "category":"Education",
            "subcategory":"Library",
            "type":"Public Place"
        }
    ],
    "sg:phone":"+44 1924 823907",
    "sg:postcode":"WF3 3LJ",
    "sg:province":"West Yorkshire",
    "sg:tags":[
        "book"
    ],
    "wof:name":"Lofthouse Library",
    "wof:placetype":"venue"
},
  "geometry": {"coordinates":[-1.4906680584,53.7400856018],"type":"Point"}
}