{
  "type": "Feature",
  "properties": {
    "addr:full":"11 Lower Mall East, Lakeside Shopping Centre, West Thurrock Grays Essex RM16 1ZF",
    "addr:housenumber":"11",
    "addr:postcode":"rm16 1zf",
    "addr:street":"Lower Mall East;Shopping;West",
    "iso:country":"GB",
    "sg:address":"11 Lower Mall East, Lakeside Shopping Centre, West Thurrock",
    "sg:city":"Grays",
    "sg:classifiers":[
        {
            "category":"Shopping",
            "subcategory":"Gifts & Souvenirs",
            "type":"Retail Goods"
        }
    ],
    "sg:phone":"+44 1708 890193",
    "sg:postcode":"RM16 1ZF",
    "sg:province":"Essex",
    "sg:tags":[
        "poster",
        "card"
    ],
    "wof:name":"Robins Cards",
    "wof:placetype":"venue"
},
  "geometry": {"coordinates":[0.28655,51.48045],"type":"Point"}
}