{
  "type": "Feature",
  "properties": {
    "iso:country":"GB",
    "sg:address":"Highfield, Lenham Heath Road, Lenham Heath",
    "sg:city":"Maidstone",
    "sg:classifiers":[
        {
            "category":"Freight",
            "type":"Transportation"
        },
        {
            "category":"Retail",
            "subcategory":"Animal Services",
            "type":"Services"
        }
    ],
    "sg:postcode":"ME17 2BU",
    "sg:province":"Kent",
    "sg:tags":[
        "haulage",
        "carrier",
        "transport",
        "road"
    ],
    "wof:name":"R Butler",
    "wof:placetype":"venue"
},
  "geometry": {"coordinates":[0.7408649921,51.2150115967],"type":"Point"}
}