{
  "type": "Feature",
  "properties": {
    "iso:country":"GB",
    "sg:address":"15 Blythe Close",
    "sg:city":"Sittingbourne",
    "sg:classifiers":[
        {
            "category":"Building & Trades",
            "subcategory":"Construction",
            "type":"Services"
        }
    ],
    "sg:phone":"+44 1795 426721",
    "sg:postcode":"ME10 3PG",
    "sg:province":"Kent",
    "sg:tags":[
        "excavation",
        "groundwork",
        "contractor"
    ],
    "wof:name":"G & R Groundwork",
    "wof:placetype":"venue"
},
  "geometry": {"coordinates":[0.75967,51.343697],"type":"Point"}
}