{
  "type": "Feature",
  "properties": {
    "addr:full":"Unit 33 Hardwick Industrial Estate, Hardwick Lane Bury St Edmunds Suffolk IP33 2QH",
    "addr:housenumber":"unit 33;estate",
    "addr:postcode":"ip33 2qh",
    "addr:street":"Hardwick Industrial;Hardwick Lane",
    "iso:country":"GB",
    "sg:address":"Unit 33 Hardwick Industrial Estate, Hardwick Lane",
    "sg:city":"Bury St Edmunds",
    "sg:classifiers":[
        {
            "category":"Retail",
            "subcategory":"Auto Repair",
            "type":"Services"
        }
    ],
    "sg:phone":"+44 1284 704183",
    "sg:postcode":"IP33 2QH",
    "sg:province":"Suffolk",
    "sg:tags":[
        "electrician"
    ],
    "wof:name":"Carletrics",
    "wof:placetype":"venue"
},
  "geometry": {"coordinates":[0.70932,52.249905],"type":"Point"}
}