{
  "type": "Feature",
  "properties": {
    "addr:full":"65 Buckingham Gate, Off Victoria Street London Greater London SW1E 6AP",
    "addr:housenumber":"65",
    "addr:postcode":"sw1e 6ap",
    "addr:street":"Buckingham Gate Off Victoria Street",
    "iso:country":"GB",
    "sg:address":"65 Buckingham Gate, Off Victoria Street",
    "sg:city":"London",
    "sg:classifiers":[
        {
            "category":"Utilities",
            "subcategory":"Fuel Oil & Lpg",
            "type":"Services"
        }
    ],
    "sg:phone":"+44 20 7222 9717",
    "sg:postcode":"SW1E 6AP",
    "sg:province":"Greater London",
    "wof:name":"British Nuclear Fuels Plc",
    "wof:placetype":"venue"
},
  "geometry": {"coordinates":[-0.1356859952,51.497959137],"type":"Point"}
}