{
  "type": "Feature",
  "properties": {
    "addr:full":"Tividale Rd Oldbury West Midlands B69 2LQ",
    "addr:postcode":"b69 2lq",
    "addr:street":"Tividale Rd",
    "iso:country":"GB",
    "sg:address":"Tividale Rd",
    "sg:city":"Oldbury",
    "sg:classifiers":[
        {
            "category":"Place Of Worship",
            "type":"Public Place"
        }
    ],
    "sg:phone":"+44 121 520 7766",
    "sg:postcode":"B69 2LQ",
    "sg:province":"West Midlands",
    "wof:name":"St Michael The Archangel C Of E Church",
    "wof:placetype":"venue"
},
  "geometry": {"coordinates":[-2.0606648922,52.5138626099],"type":"Point"}
}