{
  "type": "Feature",
  "properties": {
    "iso:country":"GB",
    "sg:address":"Botney Hill",
    "sg:city":"Billericay",
    "sg:classifiers":[
        {
            "category":"Farming",
            "subcategory":"Livestock Farm",
            "type":"Manufacturing & Wholesale Goods"
        }
    ],
    "sg:phone":"+44 1277 624979",
    "sg:postcode":"CM12 9SJ",
    "sg:province":"Essex",
    "sg:tags":[
        "others"
    ],
    "wof:name":"Cullen A & Sons",
    "wof:placetype":"venue"
},
  "geometry": {"coordinates":[0.398674,51.602844],"type":"Point"}
}