{
  "type": "Feature",
  "properties": {
    "iso:country":"GB",
    "sg:address":"292 Chiswick High Road",
    "sg:city":"London",
    "sg:classifiers":[
        {
            "category":"Real Estate",
            "subcategory":"Developer",
            "type":"Services"
        }
    ],
    "sg:phone":"+44 20 8995 8788",
    "sg:postcode":"W4 1PA",
    "sg:province":"Greater London",
    "sg:tags":[
        "property"
    ],
    "wof:name":"Raydip Housing Developments Ltd.",
    "wof:placetype":"venue"
},
  "geometry": {"coordinates":[-0.260344,51.492599],"type":"Point"}
}