{
  "type": "Feature",
  "properties": {
    "iso:country":"GB",
    "sg:address":"80 High Street",
    "sg:city":"Shepperton",
    "sg:classifiers":[
        {
            "category":"Sports & Exercise",
            "subcategory":"Sports Center",
            "type":"Entertainment"
        }
    ],
    "sg:phone":"+44 1932 225718",
    "sg:postcode":"TW17 9AU",
    "sg:province":"Surrey",
    "sg:tags":[
        "shop",
        "good"
    ],
    "wof:name":"Shepperton Swim Ltd.",
    "wof:placetype":"venue"
},
  "geometry": {"coordinates":[-0.448927,51.392605],"type":"Point"}
}