{
  "type": "Feature",
  "properties": {
    "iso:country":"GB",
    "sg:address":"228 Richmond Road",
    "sg:city":"Kingston-upon-thames",
    "sg:classifiers":[
        {
            "category":"Health Services",
            "subcategory":"Health Practitioner",
            "type":"Services"
        }
    ],
    "sg:postcode":"KT2 5HG",
    "sg:province":"Greater London",
    "sg:tags":[
        "physiotherapist"
    ],
    "wof:name":"The Vine Clinic",
    "wof:placetype":"venue"
},
  "geometry": {"coordinates":[-0.3027740121,51.4224662781],"type":"Point"}
}