{
  "type": "Feature",
  "properties": {
    "iso:country":"GB",
    "sg:address":"55 Station Road, Hadfield",
    "sg:city":"Glossop",
    "sg:classifiers":[
        {
            "category":"Professional",
            "subcategory":"Business Services",
            "type":"Services"
        }
    ],
    "sg:phone":"+44 1457 853632",
    "sg:postcode":"SK13 1DB",
    "sg:province":"Derbyshire",
    "sg:tags":[
        "bookmaker"
    ],
    "wof:name":"Dick Fisher",
    "wof:placetype":"venue"
},
  "geometry": {"coordinates":[-1.968975,53.463863],"type":"Point"}
}