{
  "type": "Feature",
  "properties": {
    "addr:full":"17 Brendan Close Birmingham Warwickshire B46 3EF",
    "addr:housenumber":"17",
    "addr:postcode":"b46 3ef",
    "addr:street":"Brendan Close",
    "iso:country":"GB",
    "sg:address":"17 Brendan Close",
    "sg:city":"Birmingham",
    "sg:classifiers":[
        {
            "category":"Building & Trades",
            "subcategory":"Construction",
            "type":"Services"
        }
    ],
    "sg:phone":"+44 1675 463117",
    "sg:postcode":"B46 3EF",
    "sg:province":"Warwickshire",
    "sg:tags":[
        "builder"
    ],
    "wof:name":"Chestnut Design",
    "wof:placetype":"venue"
},
  "geometry": {"coordinates":[-1.703463,52.489922],"type":"Point"}
}