{
  "type": "Feature",
  "properties": {
    "iso:country":"GB",
    "sg:address":"Stantons Farm, Assington",
    "sg:city":"Sudbury",
    "sg:classifiers":[
        {
            "category":"Farming",
            "subcategory":"Livestock Farm",
            "type":"Manufacturing & Wholesale Goods"
        }
    ],
    "sg:phone":"+44 1787 228079",
    "sg:postcode":"CO10 5NG",
    "sg:province":"Essex",
    "sg:tags":[
        "others"
    ],
    "wof:name":"D A & M Hodge",
    "wof:placetype":"venue"
},
  "geometry": {"coordinates":[0.81761,52.011089],"type":"Point"}
}