{
  "type": "Feature",
  "properties": {
    "addr:full":"Pen Y Binc, Old Highway, Mochdre Colwyn Bay Conwy LL28 5YF",
    "addr:postcode":"ll28 5yf",
    "addr:street":"Old Highway",
    "iso:country":"GB",
    "sg:address":"Pen Y Binc, Old Highway, Mochdre",
    "sg:city":"Colwyn Bay",
    "sg:classifiers":[
        {
            "category":"Shopping",
            "subcategory":"Bicycles & Sporting Goods",
            "type":"Retail Goods"
        }
    ],
    "sg:phone":"+44 1492 545309",
    "sg:postcode":"LL28 5YF",
    "sg:province":"Conwy",
    "sg:tags":[
        "riding",
        "saddlery",
        "wear"
    ],
    "wof:name":"Pen-y-Binc Farm Feeds & Saddlery",
    "wof:placetype":"venue"
},
  "geometry": {"coordinates":[-3.7623240948,53.291809082],"type":"Point"}
}