{
  "type": "Feature",
  "properties": {
    "addr:full":"1st Floor, 46 High Street, Burnham Slough Berkshire SL1 7JR",
    "addr:housenumber":"46",
    "addr:postcode":"sl1 7jr",
    "addr:street":"High Street",
    "iso:country":"GB",
    "sg:address":"1st Floor, 46 High Street, Burnham",
    "sg:city":"Slough",
    "sg:classifiers":[
        {
            "category":"Building & Trades",
            "subcategory":"Construction",
            "type":"Services"
        }
    ],
    "sg:phone":"+44 1628 663727",
    "sg:postcode":"SL1 7JR",
    "sg:province":"Berkshire",
    "sg:tags":[
        "builder"
    ],
    "wof:name":"William Nicholls Ltd.",
    "wof:placetype":"venue"
},
  "geometry": {"coordinates":[-0.658319,51.53413],"type":"Point"}
}