{
  "type": "Feature",
  "properties": {
    "iso:country":"GB",
    "sg:address":"32 Cobham Street",
    "sg:city":"Gravesend",
    "sg:classifiers":[
        {
            "category":"Travel",
            "subcategory":"Travel Agent",
            "type":"Entertainment"
        }
    ],
    "sg:phone":"+44 1474 333277",
    "sg:postcode":"DA11 0SA",
    "sg:province":"Kent",
    "wof:name":"D C Travel",
    "wof:placetype":"venue"
},
  "geometry": {"coordinates":[0.36506,51.440685],"type":"Point"}
}