{
  "type": "Feature",
  "properties": {
    "addr:full":"Selwyn House, Cleveland Row London Greater London SW1A 1DN",
    "addr:housenumber":"selwyn",
    "addr:postcode":"sw1a 1dn",
    "addr:street":"Cleveland Row",
    "iso:country":"GB",
    "sg:address":"Selwyn House, Cleveland Row",
    "sg:city":"London",
    "sg:classifiers":[
        {
            "category":"Manufacturing",
            "subcategory":"Glass & Minerals",
            "type":"Manufacturing & Wholesale Goods"
        }
    ],
    "sg:phone":"+44 20 7747 6000",
    "sg:postcode":"SW1A 1DN",
    "sg:province":"Greater London",
    "sg:tags":[
        "product"
    ],
    "wof:name":"Pilkington Plc",
    "wof:placetype":"venue"
},
  "geometry": {"coordinates":[-0.138734,51.504684],"type":"Point"}
}