{
  "type": "Feature",
  "properties": {
    "addr:full":"27 Hantone Hill Bath Somerset BA2 6XD",
    "addr:housenumber":"27",
    "addr:postcode":"ba2 6xd",
    "addr:street":"Hantone Hill",
    "iso:country":"GB",
    "sg:address":"27 Hantone Hill",
    "sg:city":"Bath",
    "sg:classifiers":[
        {
            "category":"Professional",
            "subcategory":"Accounting & Tax Preparation",
            "type":"Services"
        }
    ],
    "sg:postcode":"BA2 6XD",
    "sg:province":"Somerset",
    "sg:tags":[
        "accountant"
    ],
    "wof:name":"Haddrell Window & Co",
    "wof:placetype":"venue"
},
  "geometry": {"coordinates":[-2.3201320171,51.3899765015],"type":"Point"}
}