{
  "type": "Feature",
  "properties": {
    "iso:country":"GB",
    "sg:address":"57 Station Road",
    "sg:city":"Redcar",
    "sg:classifiers":[
        {
            "category":"Food & Beverages",
            "subcategory":"Bakery",
            "type":"Retail Goods"
        }
    ],
    "sg:phone":"+44 1642 474489",
    "sg:postcode":"TS10 1DT",
    "sg:province":"North Yorkshire",
    "sg:tags":[
        "pizza"
    ],
    "wof:name":"Vino's Pizzeria",
    "wof:placetype":"venue"
},
  "geometry": {"coordinates":[-1.069893,54.617973],"type":"Point"}
}