{
  "type": "Feature",
  "properties": {
    "addr:full":"Unit 11 Hirwaun Industrial Estate Aberdare Neath Port Talbot CF44 9UP",
    "addr:housenumber":"unit 11",
    "addr:postcode":"cf44 9up",
    "addr:street":"Industrial Estate",
    "iso:country":"GB",
    "sg:address":"Unit 11 Hirwaun Industrial Estate",
    "sg:city":"Aberdare",
    "sg:classifiers":[
        {
            "category":"Manufacturing",
            "subcategory":"Paper Products",
            "type":"Manufacturing & Wholesale Goods"
        }
    ],
    "sg:phone":"+44 1685 814078",
    "sg:postcode":"CF44 9UP",
    "sg:province":"Neath Port Talbot",
    "sg:tags":[
        "material",
        "drawing",
        "writing"
    ],
    "wof:name":"Innova Precision Writing Points Ltd",
    "wof:placetype":"venue"
},
  "geometry": {"coordinates":[-3.503904,51.734619],"type":"Point"}
}