{
  "type": "Feature",
  "properties": {
    "addr:full":"Cromwell Road Cambridge Cambridgeshire CB1 3EB",
    "addr:postcode":"cb1 3eb",
    "addr:street":"Cromwell Road",
    "iso:country":"GB",
    "sg:address":"Cromwell Road",
    "sg:city":"Cambridge",
    "sg:classifiers":[
        {
            "category":"Building & Trades",
            "subcategory":"Equipment Rental",
            "type":"Services"
        }
    ],
    "sg:phone":"+44 1223 466153",
    "sg:postcode":"CB1 3EB",
    "sg:province":"Cambridgeshire",
    "sg:tags":[
        "plant",
        "tool",
        "hire",
        "centre"
    ],
    "wof:name":"Ridge Hire",
    "wof:placetype":"venue"
},
  "geometry": {"coordinates":[0.147005,52.202206],"type":"Point"}
}