{
  "type": "Feature",
  "properties": {
    "addr:full":"9 High St Buckingham Buckinghamshire MK18 1NT",
    "addr:housenumber":"9",
    "addr:postcode":"mk18 1nt",
    "addr:street":"High St",
    "iso:country":"GB",
    "sg:address":"9 High St",
    "sg:city":"Buckingham",
    "sg:classifiers":[
        {
            "category":"Restaurant",
            "type":"Food & Drink"
        }
    ],
    "sg:phone":"+44 1280 821550",
    "sg:postcode":"MK18 1NT",
    "sg:province":"Buckinghamshire",
    "sg:tags":[
        "indian"
    ],
    "wof:name":"Spice of India",
    "wof:placetype":"venue"
},
  "geometry": {"coordinates":[-0.9853,52.001331],"type":"Point"}
}