{
  "type": "Feature",
  "properties": {
    "addr:full":"Lottbridge Drove Eastbourne East Sussex BN23 6PX",
    "addr:postcode":"bn23 6px",
    "addr:street":"Lottbridge",
    "iso:country":"GB",
    "sg:address":"Lottbridge Drove",
    "sg:city":"Eastbourne",
    "sg:classifiers":[
        {
            "category":"Autos & Motor Vehicles",
            "subcategory":"Automobile Sales",
            "type":"Retail Goods"
        }
    ],
    "sg:postcode":"BN23 6PX",
    "sg:province":"East Sussex",
    "sg:tags":[
        "car"
    ],
    "wof:name":"Birchwood Eastbourne Ltd.",
    "wof:placetype":"venue"
},
  "geometry": {"coordinates":[0.3054609895,50.7869682312],"type":"Point"}
}