{
  "type": "Feature",
  "properties": {
    "addr:full":"Hadrian House, Front St Chester Le Street Durham DH3 3DB",
    "addr:postcode":"dh3 3db",
    "addr:street":"Front St;Le Street",
    "iso:country":"GB",
    "sg:address":"Hadrian House, Front St",
    "sg:city":"Chester Le Street",
    "sg:classifiers":[
        {
            "category":"Manufacturing",
            "subcategory":"Petroleum Products",
            "type":"Manufacturing & Wholesale Goods"
        }
    ],
    "sg:phone":"+44 191 296 3939",
    "sg:postcode":"DH3 3DB",
    "sg:province":"Durham",
    "sg:tags":[
        "double",
        "glazing"
    ],
    "wof:name":"The Window Advisory Centre",
    "wof:placetype":"venue"
},
  "geometry": {"coordinates":[-1.5743089914,54.8584899902],"type":"Point"}
}