{
  "type": "Feature",
  "properties": {
    "iso:country":"GB",
    "sg:address":"17 Cadzow Pl",
    "sg:city":"Edinburgh",
    "sg:classifiers":[
        {
            "category":"Fast Food",
            "type":"Food & Drink"
        }
    ],
    "sg:phone":"+44 131 661 4722",
    "sg:postcode":"EH7 5SN",
    "sg:province":"City of Edinburgh",
    "sg:tags":[
        "away",
        "take"
    ],
    "wof:name":"Moonlighting",
    "wof:placetype":"venue"
},
  "geometry": {"coordinates":[-3.173795,55.957458],"type":"Point"}
}