{
  "type": "Feature",
  "properties": {
    "addr:full":"20 The Down Trowbridge Wiltshire BA14 8QW",
    "addr:housenumber":"20",
    "addr:postcode":"ba14 8qw",
    "addr:street":"The Down",
    "iso:country":"GB",
    "sg:address":"20 The Down",
    "sg:city":"Trowbridge",
    "sg:classifiers":[
        {
            "category":"Health Services",
            "subcategory":"Health Practitioner",
            "type":"Services"
        }
    ],
    "sg:phone":"+44 1225 351257",
    "sg:postcode":"BA14 8QW",
    "sg:province":"Wiltshire",
    "sg:tags":[
        "therapist",
        "speech"
    ],
    "wof:name":"Tonks S",
    "wof:placetype":"venue"
},
  "geometry": {"coordinates":[-2.2037250996,51.3278236389],"type":"Point"}
}