{
  "type": "Feature",
  "properties": {
    "addr:full":"30 Oak Avenue Morecambe Lancashire LA4 6HS",
    "addr:housenumber":"30",
    "addr:postcode":"la4 6hs",
    "addr:street":"Oak Avenue",
    "iso:country":"GB",
    "sg:address":"30 Oak Avenue",
    "sg:city":"Morecambe",
    "sg:classifiers":[
        {
            "category":"Retail",
            "subcategory":"Repair Shop",
            "type":"Services"
        }
    ],
    "sg:phone":"+44 1524 414468",
    "sg:postcode":"LA4 6HS",
    "sg:province":"Lancashire",
    "sg:tags":[
        "television",
        "good",
        "video",
        "servicing",
        "maintenance",
        "radio"
    ],
    "wof:name":"Hillingdon Tv & Video Services",
    "wof:placetype":"venue"
},
  "geometry": {"coordinates":[-2.8308870792,54.0774002075],"type":"Point"}
}