{
  "type": "Feature",
  "properties": {
    "addr:full":"157 Blendon Road Bexley Kent DA5 1BT",
    "addr:housenumber":"157",
    "addr:postcode":"da5 1bt",
    "addr:street":"Blendon Road",
    "iso:country":"GB",
    "sg:address":"157 Blendon Road",
    "sg:city":"Bexley",
    "sg:classifiers":[
        {
            "category":"Building & Trades",
            "subcategory":"Plumbing",
            "type":"Services"
        },
        {
            "category":"Home & Garden",
            "subcategory":"Building Materials",
            "type":"Retail Goods"
        }
    ],
    "sg:phone":"+44 20 8304 9970",
    "sg:postcode":"DA5 1BT",
    "sg:province":"Kent",
    "sg:tags":[
        "furnishers",
        "plumber",
        "planner",
        "bathroom"
    ],
    "wof:name":"Builders Supplies (Blendon) Ltd.",
    "wof:placetype":"venue"
},
  "geometry": {"coordinates":[0.1208920032,51.4480018616],"type":"Point"}
}