{
  "type": "Feature",
  "properties": {
    "iso:country":"GB",
    "sg:address":"72 Victoria Street",
    "sg:city":"Newton Stewart",
    "sg:classifiers":[
        {
            "category":"Shopping",
            "subcategory":"Clothing, Apparel, & Fashions",
            "type":"Retail Goods"
        }
    ],
    "sg:phone":"+44 1671 404423",
    "sg:postcode":"DG8 6DB",
    "sg:province":"Dumfries and Galloway",
    "sg:tags":[
        "shop"
    ],
    "wof:name":"Essentials",
    "wof:placetype":"venue"
},
  "geometry": {"coordinates":[-4.482949,54.958179],"type":"Point"}
}