{
  "type": "Feature",
  "properties": {
    "addr:full":"Unit 1, Pennant Park, Standard Way Fareham Hampshire PO16 8XU",
    "addr:housenumber":"unit 1 pennant",
    "addr:postcode":"po16 8xu",
    "addr:street":"Park Standard Way",
    "iso:country":"GB",
    "sg:address":"Unit 1, Pennant Park, Standard Way",
    "sg:city":"Fareham",
    "sg:classifiers":[
        {
            "category":"Professional",
            "subcategory":"Engineering",
            "type":"Services"
        }
    ],
    "sg:phone":"+44 1329 231245",
    "sg:postcode":"PO16 8XU",
    "sg:province":"Hampshire",
    "sg:tags":[
        "precision",
        "engineer"
    ],
    "sg:website":"http://www.hillcresteng.co.uk",
    "wof:name":"Hillcrest Machinery & Engineering (Portchester) Ltd.",
    "wof:placetype":"venue"
},
  "geometry": {"coordinates":[-1.1740989685,50.8527336121],"type":"Point"}
}