{
  "type": "Feature",
  "properties": {
    "addr:full":"The Old Foundry, Norwich Road, Watton Thetford Norfolk IP25 6TJ",
    "addr:postcode":"ip25 6tj",
    "addr:street":"Norwich Road",
    "iso:country":"GB",
    "sg:address":"The Old Foundry, Norwich Road, Watton",
    "sg:city":"Thetford",
    "sg:classifiers":[
        {
            "category":"Retail",
            "subcategory":"Auto Repair",
            "type":"Services"
        }
    ],
    "sg:phone":"+44 1953 881448",
    "sg:postcode":"IP25 6TJ",
    "sg:province":"Norfolk",
    "sg:tags":[
        "modification",
        "garage"
    ],
    "wof:name":"Shire Quality Commercial Finishers",
    "wof:placetype":"venue"
},
  "geometry": {"coordinates":[0.8296499848,52.5707168579],"type":"Point"}
}