{
  "type": "Feature",
  "properties": {
    "addr:full":"2 Sutton Road, Admaston Telford Shropshire TF5 0AY",
    "addr:housenumber":"2",
    "addr:postcode":"tf5 0ay",
    "addr:street":"Sutton Road",
    "iso:country":"GB",
    "sg:address":"2 Sutton Road, Admaston",
    "sg:city":"Telford",
    "sg:classifiers":[
        {
            "category":"Government",
            "subcategory":"Post Office",
            "type":"Public Place"
        }
    ],
    "sg:phone":"+44 1952 244030",
    "sg:postcode":"TF5 0AY",
    "sg:province":"Shropshire",
    "wof:name":"Admaston Sub Post Office",
    "wof:placetype":"venue"
},
  "geometry": {"coordinates":[-2.545118,52.712879],"type":"Point"}
}