{
  "type": "Feature",
  "properties": {
    "addr:full":"The Shrublands, Burgh St Peter Beccles Norfolk NR34 0BB",
    "addr:postcode":"nr34 0bb",
    "iso:country":"GB",
    "sg:address":"The Shrublands, Burgh St Peter",
    "sg:city":"Beccles",
    "sg:classifiers":[
        {
            "category":"Farming",
            "subcategory":"Farm",
            "type":"Manufacturing & Wholesale Goods"
        }
    ],
    "sg:phone":"+44 1502 677241",
    "sg:postcode":"NR34 0BB",
    "sg:province":"Norfolk",
    "sg:tags":[
        "mixed",
        "crop"
    ],
    "wof:name":"P R & A CLARKE",
    "wof:placetype":"venue"
},
  "geometry": {"coordinates":[1.567245,52.453667],"type":"Point"}
}