{
  "type": "Feature",
  "properties": {
    "addr:full":"22-24 Dyer Street Cirencester Gloucestershire GL7 2PF",
    "addr:housenumber":"22-24",
    "addr:postcode":"gl7 2pf",
    "addr:street":"Dyer Street",
    "iso:country":"GB",
    "sg:address":"22-24 Dyer Street",
    "sg:city":"Cirencester",
    "sg:classifiers":[
        {
            "category":"Home & Garden",
            "subcategory":"Garden Supply",
            "type":"Retail Goods"
        },
        {
            "category":"Shopping",
            "subcategory":"Pets & Pet Supplies",
            "type":"Retail Goods"
        }
    ],
    "sg:phone":"+44 1285 654500",
    "sg:postcode":"GL7 2PF",
    "sg:province":"Gloucestershire",
    "sg:tags":[
        "shop",
        "nursery",
        "centre"
    ],
    "wof:name":"Toomers",
    "wof:placetype":"venue"
},
  "geometry": {"coordinates":[-1.964799,51.716305],"type":"Point"}
}