{
  "type": "Feature",
  "properties": {
    "iso:country":"GB",
    "sg:address":"Compass House, 30 - 36 East Street",
    "sg:city":"Bromley",
    "sg:classifiers":[
        {
            "category":"Professional",
            "subcategory":"Printing & Photocopies",
            "type":"Services"
        }
    ],
    "sg:phone":"+44 20 8402 5252",
    "sg:postcode":"BR1 1QU",
    "sg:province":"Kent",
    "sg:tags":[
        "typesetter"
    ],
    "wof:name":"Sphinx Inc Ltd.",
    "wof:placetype":"venue"
},
  "geometry": {"coordinates":[0.016375,51.407085],"type":"Point"}
}