{
  "type": "Feature",
  "properties": {
    "addr:full":"Liverpool Rd Newcastle Staffordshire ST5 9ER",
    "addr:postcode":"st5 9er",
    "addr:street":"Liverpool Rd",
    "iso:country":"GB",
    "sg:address":"Liverpool Rd",
    "sg:city":"Newcastle",
    "sg:classifiers":[
        {
            "category":"Bars & Pubs",
            "type":"Food & Drink"
        }
    ],
    "sg:phone":"+44 1782 626727",
    "sg:postcode":"ST5 9ER",
    "sg:province":"Staffordshire",
    "sg:tags":[
        "pubs",
        "inn"
    ],
    "wof:name":"Hanging Gate",
    "wof:placetype":"venue"
},
  "geometry": {"coordinates":[-2.23744,53.0298],"type":"Point"}
}