{
  "type": "Feature",
  "properties": {
    "iso:country":"GB",
    "sg:address":"150 Polmadie Road",
    "sg:city":"Glasgow",
    "sg:classifiers":[
        {
            "category":"Utilities",
            "subcategory":"Natural Gas",
            "type":"Services"
        }
    ],
    "sg:phone":"+44 141 424 4477",
    "sg:postcode":"G5 0HN",
    "sg:province":"Glasgow City",
    "sg:tags":[
        "supplier"
    ],
    "wof:name":"Boc Gases",
    "wof:placetype":"venue"
},
  "geometry": {"coordinates":[-4.241959095,55.8372688293],"type":"Point"}
}