{
  "type": "Feature",
  "properties": {
    "addr:full":"Foley Farm, Snake Lane, Stockcross Newbury Berkshire RG20 8JX",
    "addr:postcode":"rg20 8jx",
    "addr:street":"Foley;Snake Lane",
    "iso:country":"GB",
    "sg:address":"Foley Farm, Snake Lane, Stockcross",
    "sg:city":"Newbury",
    "sg:classifiers":[
        {
            "category":"Farming",
            "subcategory":"Livestock Farm",
            "type":"Manufacturing & Wholesale Goods"
        }
    ],
    "sg:phone":"+44 1488 608318",
    "sg:postcode":"RG20 8JX",
    "sg:province":"Berkshire",
    "sg:tags":[
        "others"
    ],
    "wof:name":"B A WERNHAM",
    "wof:placetype":"venue"
},
  "geometry": {"coordinates":[-1.378848,51.411091],"type":"Point"}
}