{
  "type": "Feature",
  "properties": {
    "addr:full":"6 Redlodge Road West Wickham Kent BR4 0EL",
    "addr:housenumber":"6",
    "addr:postcode":"br4 0el",
    "addr:street":"Redlodge Road",
    "iso:country":"GB",
    "sg:address":"6 Redlodge Road",
    "sg:city":"West Wickham",
    "sg:classifiers":[
        {
            "category":"Professional",
            "subcategory":"Engineering",
            "type":"Services"
        }
    ],
    "sg:phone":"+44 20 8776 0423",
    "sg:postcode":"BR4 0EL",
    "sg:province":"Kent",
    "sg:tags":[
        "gas",
        "engineer"
    ],
    "wof:name":"Gas-Tite",
    "wof:placetype":"venue"
},
  "geometry": {"coordinates":[-0.013799,51.38031],"type":"Point"}
}