{
  "type": "Feature",
  "properties": {
    "addr:full":"84 Beal Lane, Shaw Oldham Lancashire OL2 8PH",
    "addr:housenumber":"84",
    "addr:postcode":"ol2 8ph",
    "addr:street":"Beal Lane",
    "iso:country":"GB",
    "sg:address":"84 Beal Lane, Shaw",
    "sg:city":"Oldham",
    "sg:classifiers":[
        {
            "category":"Professional",
            "subcategory":"Computer Services",
            "type":"Services"
        }
    ],
    "sg:phone":"+44 1706 292700",
    "sg:postcode":"OL2 8PH",
    "sg:province":"Lancashire",
    "sg:tags":[
        "system",
        "software"
    ],
    "wof:name":"C A R L Communications Ltd.",
    "wof:placetype":"venue"
},
  "geometry": {"coordinates":[-2.088057,53.576714],"type":"Point"}
}