{
  "type": "Feature",
  "properties": {
    "addr:full":"Lane Grange Stables, Snailwell Road Newmarket Cambridgeshire CB8 7DP",
    "addr:postcode":"cb8 7dp",
    "addr:street":"Lane;Snailwell Road",
    "iso:country":"GB",
    "sg:address":"Lane Grange Stables, Snailwell Road",
    "sg:city":"Newmarket",
    "sg:classifiers":[
        {
            "category":"Professional",
            "subcategory":"Business Services",
            "type":"Services"
        },
        {
            "category":"Personal",
            "subcategory":"Adult",
            "type":"Services"
        }
    ],
    "sg:phone":"+44 1638 660696",
    "sg:postcode":"CB8 7DP",
    "sg:province":"Cambridgeshire",
    "sg:tags":[
        "bookmaker",
        "equestrian"
    ],
    "wof:name":"Sean Woods Racing",
    "wof:placetype":"venue"
},
  "geometry": {"coordinates":[0.408188,52.28133],"type":"Point"}
}