{
  "type": "Feature",
  "properties": {
    "addr:full":"Kendal Hill Farm, Glassondock Lancaster Lancashire LA2 0AU",
    "addr:postcode":"la2 0au",
    "addr:street":"Kendal Hill;Glassondock",
    "iso:country":"GB",
    "sg:address":"Kendal Hill Farm, Glassondock",
    "sg:city":"Lancaster",
    "sg:classifiers":[
        {
            "category":"Farming",
            "subcategory":"Dairy Farm",
            "type":"Manufacturing & Wholesale Goods"
        }
    ],
    "sg:postcode":"LA2 0AU",
    "sg:province":"Lancashire",
    "wof:name":"J G & Son",
    "wof:placetype":"venue"
},
  "geometry": {"coordinates":[-2.8502299786,53.9929199219],"type":"Point"}
}