{
  "type": "Feature",
  "properties": {
    "iso:country":"GB",
    "sg:address":"53 Clydesdale Road, Appleton",
    "sg:city":"Warrington",
    "sg:classifiers":[
        {
            "category":"Building & Trades",
            "subcategory":"Construction",
            "type":"Services"
        }
    ],
    "sg:postcode":"WA4 3AY",
    "sg:province":"Cheshire",
    "sg:tags":[
        "joiner",
        "carpenter"
    ],
    "wof:name":"John Daley",
    "wof:placetype":"venue"
},
  "geometry": {"coordinates":[-2.572711,53.367268],"type":"Point"}
}