{
  "type": "Feature",
  "properties": {
    "iso:country":"GB",
    "sg:address":"Panstar House, 13-15 Swakeleys Rd",
    "sg:city":"Uxbridge",
    "sg:classifiers":[
        {
            "category":"Professional",
            "subcategory":"Engineering",
            "type":"Services"
        }
    ],
    "sg:phone":"+44 1895 622374",
    "sg:postcode":"UB10 8DF",
    "sg:province":"Greater London",
    "sg:tags":[
        "engineer"
    ],
    "wof:name":"Power Mechanical Engineering Services",
    "wof:placetype":"venue"
},
  "geometry": {"coordinates":[-0.4447669983,51.5643959045],"type":"Point"}
}