{
  "type": "Feature",
  "properties": {
    "iso:country":"GB",
    "sg:address":"32 Mill Green Rd",
    "sg:city":"Mitcham",
    "sg:classifiers":[
        {
            "category":"Utilities",
            "subcategory":"Fuel Oil & Lpg",
            "type":"Services"
        }
    ],
    "sg:phone":"+44 20 8648 1334",
    "sg:postcode":"CR4 4HY",
    "sg:province":"Greater London",
    "sg:tags":[
        "coal",
        "smokeless"
    ],
    "wof:name":"W.J Brown",
    "wof:placetype":"venue"
},
  "geometry": {"coordinates":[-0.1606200039,51.3863143921],"type":"Point"}
}