{
  "type": "Feature",
  "properties": {
    "addr:full":"28 Gilman Place Stoke-on-trent Staffordshire ST1 3PG",
    "addr:housenumber":"28",
    "addr:postcode":"st1 3pg",
    "addr:street":"Gilman Place",
    "iso:country":"GB",
    "sg:address":"28 Gilman Place",
    "sg:city":"Stoke-on-trent",
    "sg:classifiers":[
        {
            "category":"Professional",
            "subcategory":"Management & Consulting",
            "type":"Services"
        }
    ],
    "sg:phone":"+44 1782 283323",
    "sg:postcode":"ST1 3PG",
    "sg:province":"Staffordshire",
    "sg:tags":[
        "consultant",
        "business"
    ],
    "wof:name":"Unique Business Solutions",
    "wof:placetype":"venue"
},
  "geometry": {"coordinates":[-2.1721038818,53.0249671936],"type":"Point"}
}