{
  "type": "Feature",
  "properties": {
    "iso:country":"GB",
    "sg:address":"17 Long Mead",
    "sg:city":"Fleet",
    "sg:classifiers":[
        {
            "category":"Organizations",
            "subcategory":"Non-profit Organization",
            "type":"Services"
        }
    ],
    "sg:postcode":"GU52 7TX",
    "sg:province":"Hampshire",
    "sg:tags":[
        "organisation",
        "voluntary",
        "charity"
    ],
    "wof:name":"Fleet Pond Society",
    "wof:placetype":"venue"
},
  "geometry": {"coordinates":[-0.836417,51.270859],"type":"Point"}
}