{
  "type": "Feature",
  "properties": {
    "iso:country":"GB",
    "sg:address":"Oakfield Court, Consort Way",
    "sg:city":"Horley",
    "sg:classifiers":[
        {
            "category":"Freight",
            "type":"Transportation"
        },
        {
            "category":"Airline",
            "type":"Transportation"
        }
    ],
    "sg:phone":"+44 1293 778400",
    "sg:postcode":"RH6 7AF",
    "sg:province":"Surrey",
    "sg:tags":[
        "haulage",
        "transport",
        "road"
    ],
    "wof:name":"Northwest Airlines Inc",
    "wof:placetype":"venue"
},
  "geometry": {"coordinates":[-0.164516,51.172405],"type":"Point"}
}