{
  "type": "Feature",
  "properties": {
    "iso:country":"GB",
    "sg:address":"C67 Northbridge Centre, Elm Street",
    "sg:city":"Burnley",
    "sg:classifiers":[
        {
            "category":"Professional",
            "subcategory":"Engineering",
            "type":"Services"
        }
    ],
    "sg:postcode":"BB10 1PD",
    "sg:province":"Lancashire",
    "sg:tags":[
        "design",
        "engineer"
    ],
    "wof:name":"Total Solutions",
    "wof:placetype":"venue"
},
  "geometry": {"coordinates":[-2.24168,53.79863],"type":"Point"}
}