{
  "type": "Feature",
  "properties": {
    "addr:full":"West End Garage, Leggs Lusty Bridge Bruton Somerset BA10 0BQ",
    "addr:postcode":"ba10 0bq",
    "addr:street":"Lusty Bridge",
    "iso:country":"GB",
    "sg:address":"West End Garage, Leggs Lusty Bridge",
    "sg:city":"Bruton",
    "sg:classifiers":[
        {
            "category":"Food & Beverages",
            "subcategory":"Groceries & Convenience Stores",
            "type":"Retail Goods"
        }
    ],
    "sg:phone":"+44 1749 812753",
    "sg:postcode":"BA10 0BQ",
    "sg:province":"Somerset",
    "wof:name":"Alldays Stores Ltd.",
    "wof:placetype":"venue"
},
  "geometry": {"coordinates":[-2.458782,51.109402],"type":"Point"}
}