{
  "type": "Feature",
  "properties": {
    "iso:country":"GB",
    "sg:address":"146-148 Coombs Road",
    "sg:city":"Halesowen",
    "sg:classifiers":[
        {
            "category":"Health Services",
            "subcategory":"Doctor",
            "type":"Services"
        }
    ],
    "sg:phone":"+44 121 561 4275",
    "sg:postcode":"B62 8AF",
    "sg:province":"West Midlands",
    "sg:tags":[
        "practitioners"
    ],
    "wof:name":"Dr Humphrey N Akufo-Tetteh",
    "wof:placetype":"venue"
},
  "geometry": {"coordinates":[-2.048899,52.461552],"type":"Point"}
}