{
  "type": "Feature",
  "properties": {
    "iso:country":"GB",
    "sg:address":"96 Front Street",
    "sg:city":"Chester-le-street",
    "sg:classifiers":[
        {
            "category":"Food & Beverages",
            "subcategory":"Bakery",
            "type":"Retail Goods"
        }
    ],
    "sg:phone":"+44 191 388 6292",
    "sg:postcode":"DH3 3BB",
    "sg:province":"Durham",
    "sg:tags":[
        "baker"
    ],
    "wof:name":"Carricks",
    "wof:placetype":"venue"
},
  "geometry": {"coordinates":[-1.5735830069,54.8560829163],"type":"Point"}
}