{
  "type": "Feature",
  "properties": {
    "addr:full":"Unit 3a 500 Purley Way Croydon Surrey CR0 4NZ",
    "addr:housenumber":"unit 3a 500",
    "addr:postcode":"cr0 4nz",
    "addr:street":"Purley Way",
    "iso:country":"GB",
    "sg:address":"Unit 3a 500 Purley Way",
    "sg:city":"Croydon",
    "sg:classifiers":[
        {
            "category":"Home & Garden",
            "subcategory":"Furniture",
            "type":"Retail Goods"
        }
    ],
    "sg:phone":"+44 20 8688 3797",
    "sg:postcode":"CR0 4NZ",
    "sg:province":"Surrey",
    "wof:name":"Furniture Workshop",
    "wof:placetype":"venue"
},
  "geometry": {"coordinates":[-0.1180960014,51.3693084717],"type":"Point"}
}