{
  "type": "Feature",
  "properties": {
    "iso:country":"GB",
    "sg:address":"64 Preston New Road",
    "sg:city":"Blackburn",
    "sg:classifiers":[
        {
            "category":"Health Services",
            "subcategory":"Dentist",
            "type":"Services"
        }
    ],
    "sg:phone":"+44 1254 697000",
    "sg:postcode":"BB2 6BH",
    "sg:province":"Lancashire",
    "wof:name":"Smile Designers",
    "wof:placetype":"venue"
},
  "geometry": {"coordinates":[-2.494317,53.751671],"type":"Point"}
}