{
  "type": "Feature",
  "properties": {
    "addr:full":"464 London Road Portsmouth Hampshire PO2 9LE",
    "addr:housenumber":"464",
    "addr:postcode":"hampshire po2 9le",
    "addr:street":"London Road",
    "iso:country":"GB",
    "sg:address":"464 London Road",
    "sg:city":"Portsmouth",
    "sg:classifiers":[
        {
            "category":"Social Services",
            "subcategory":"Retirement Home",
            "type":"Services"
        },
        {
            "category":"Organizations",
            "subcategory":"Community Association",
            "type":"Services"
        }
    ],
    "sg:phone":"+44 23 9266 5641",
    "sg:postcode":"PO2 9LE",
    "sg:province":"Hampshire",
    "sg:tags":[
        "society",
        "housing",
        "sheltered",
        "accommodation"
    ],
    "wof:name":"Abbeyfield Portsmouth Society Ltd",
    "wof:placetype":"venue"
},
  "geometry": {"coordinates":[-1.07173,50.826572],"type":"Point"}
}