{
  "type": "Feature",
  "properties": {
    "addr:full":"21 Station Rd Clacton On Sea Essex CO15 1TD",
    "addr:housenumber":"21",
    "addr:postcode":"co15 1td",
    "addr:street":"Station Rd",
    "iso:country":"GB",
    "sg:address":"21 Station Rd",
    "sg:city":"Clacton On Sea",
    "sg:classifiers":[
        {
            "category":"Shopping",
            "subcategory":"Pharmacy",
            "type":"Retail Goods"
        }
    ],
    "sg:phone":"+44 1255 428724",
    "sg:postcode":"CO15 1TD",
    "sg:province":"Essex",
    "sg:tags":[
        "store",
        "drug"
    ],
    "wof:name":"Lloyds Supersave Drugstore",
    "wof:placetype":"venue"
},
  "geometry": {"coordinates":[1.1530790329,51.7890853882],"type":"Point"}
}