{
  "type": "Feature",
  "properties": {
    "addr:full":"No2 The Io Centre, Lea Road Waltham Cross Essex EN8 7PG",
    "addr:postcode":"en8 7pg",
    "addr:street":"The;Lea Road",
    "iso:country":"GB",
    "sg:address":"No2 The Io Centre, Lea Road",
    "sg:city":"Waltham Cross",
    "sg:classifiers":[
        {
            "category":"Shopping",
            "subcategory":"Stationery & Office Supplies",
            "type":"Retail Goods"
        },
        {
            "category":"Shopping",
            "subcategory":"Crafts & Fabrics",
            "type":"Retail Goods"
        }
    ],
    "sg:phone":"+44 1992 704900",
    "sg:postcode":"EN8 7PG",
    "sg:province":"Essex",
    "sg:tags":[
        "material",
        "graphic",
        "art",
        "printers'"
    ],
    "wof:name":"M C S I Ltd.",
    "wof:placetype":"venue"
},
  "geometry": {"coordinates":[-0.033814,51.69051],"type":"Point"}
}