{
  "type": "Feature",
  "properties": {
    "iso:country":"GB",
    "sg:address":"Donaldson Place, Kirkintilloch",
    "sg:city":"Glasgow",
    "sg:classifiers":[
        {
            "category":"Education",
            "subcategory":"University",
            "type":"Public Place"
        }
    ],
    "sg:phone":"+44 141 777 6043",
    "sg:postcode":"G66 1XA",
    "sg:province":"East Dunbartonshire",
    "sg:tags":[
        "adult"
    ],
    "wof:name":"Strathkelvin Further Education Centre",
    "wof:placetype":"venue"
},
  "geometry": {"coordinates":[-4.153566,55.935589],"type":"Point"}
}