{
  "type": "Feature",
  "properties": {
    "iso:country":"GB",
    "sg:address":"Unit 15 Kettlestring La",
    "sg:city":"York",
    "sg:classifiers":[
        {
            "category":"Shopping",
            "subcategory":"Stationery & Office Supplies",
            "type":"Retail Goods"
        }
    ],
    "sg:phone":"+44 1904 693916",
    "sg:postcode":"YO3 4XF",
    "sg:province":"East Riding of Yorkshire",
    "sg:tags":[
        "equipment"
    ],
    "wof:name":"Wallis Service Centre",
    "wof:placetype":"venue"
},
  "geometry": {"coordinates":[-1.100093,53.987988],"type":"Point"}
}