{
  "type": "Feature",
  "properties": {
    "addr:full":"The Abbey, Ramsey Huntingdon Cambridgeshire PE26 1DH",
    "addr:postcode":"pe26 1dh",
    "addr:street":"Huntingdon",
    "iso:country":"GB",
    "sg:address":"The Abbey, Ramsey",
    "sg:city":"Huntingdon",
    "sg:classifiers":[
        {
            "category":"Education",
            "subcategory":"School",
            "type":"Public Place"
        },
        {
            "category":"Government",
            "subcategory":"Office",
            "type":"Public Place"
        }
    ],
    "sg:phone":"+44 1487 813285",
    "sg:postcode":"PE26 1DH",
    "sg:province":"Cambridgeshire",
    "sg:tags":[
        "local",
        "authority"
    ],
    "wof:name":"Ramsey Abbey School",
    "wof:placetype":"venue"
},
  "geometry": {"coordinates":[-0.1069070026,52.4481582642],"type":"Point"}
}