{
  "type": "Feature",
  "properties": {
    "addr:full":"50 Finland Street London Greater London SE16 7TP",
    "addr:housenumber":"50",
    "addr:postcode":"se16 7tp",
    "addr:street":"Finland Street",
    "iso:country":"GB",
    "sg:address":"50 Finland Street",
    "sg:city":"London",
    "sg:classifiers":[
        {
            "category":"Professional",
            "subcategory":"Accounting & Tax Preparation",
            "type":"Services"
        }
    ],
    "sg:postcode":"SE16 7TP",
    "sg:province":"Greater London",
    "sg:tags":[
        "accountant"
    ],
    "wof:name":"Uprite Enterprises Ltd",
    "wof:placetype":"venue"
},
  "geometry": {"coordinates":[-0.0429419987,51.4628257751],"type":"Point"}
}