{
  "type": "Feature",
  "properties": {
    "addr:full":"27 Shenfield Rd Brentwood Essex CM15 8AG",
    "addr:housenumber":"27",
    "addr:postcode":"cm15 8ag",
    "addr:street":"Shenfield Rd",
    "iso:country":"GB",
    "sg:address":"27 Shenfield Rd",
    "sg:city":"Brentwood",
    "sg:classifiers":[
        {
            "category":"Shopping",
            "subcategory":"Pharmacy",
            "type":"Retail Goods"
        }
    ],
    "sg:phone":"+44 1277 219728",
    "sg:postcode":"CM15 8AG",
    "sg:province":"Essex",
    "sg:tags":[
        "pharmacist",
        "dispensing",
        "chemist"
    ],
    "wof:name":"Burntwood Pharmacy",
    "wof:placetype":"venue"
},
  "geometry": {"coordinates":[0.30724,51.622105],"type":"Point"}
}