{
  "type": "Feature",
  "properties": {
    "addr:full":"7a St Georges Circus Southwark Greater London SE1 6HS",
    "addr:housenumber":"7a",
    "addr:postcode":"se1 6hs",
    "addr:street":"St Georges Circus",
    "iso:country":"GB",
    "sg:address":"7a St Georges Circus",
    "sg:city":"Southwark",
    "sg:classifiers":[
        {
            "category":"Personal",
            "subcategory":"Beauty Salon",
            "type":"Services"
        }
    ],
    "sg:phone":"+44 20 7401 3242",
    "sg:postcode":"SE1 6HS",
    "sg:province":"Greater London",
    "sg:tags":[
        "unisex",
        "hairdresser"
    ],
    "wof:name":"Golden Scissors",
    "wof:placetype":"venue"
},
  "geometry": {"coordinates":[-0.10488,51.498322],"type":"Point"}
}