{
  "type": "Feature",
  "properties": {
    "iso:country":"GB",
    "sg:address":"Bednall Head Farm, Cannock Rd",
    "sg:city":"Stafford",
    "sg:classifiers":[
        {
            "category":"Professional",
            "subcategory":"Engineering",
            "type":"Services"
        }
    ],
    "sg:phone":"+44 1785 665195",
    "sg:postcode":"ST17 0SG",
    "sg:province":"Staffordshire",
    "sg:tags":[
        "engineer",
        "structural"
    ],
    "wof:name":"C M Engineering Services",
    "wof:placetype":"venue"
},
  "geometry": {"coordinates":[-2.052888,52.759136],"type":"Point"}
}