{
  "type": "Feature",
  "properties": {
    "addr:full":"10 Enterprise Court, Newton Close, Park Farm Industrial Estate Wellingborough Northamptonshire NN8 6UW",
    "addr:housenumber":"10;estate",
    "addr:postcode":"nn8 6uw",
    "addr:street":"Enterprise Court Newton Close Park Farm Industrial",
    "iso:country":"GB",
    "sg:address":"10 Enterprise Court, Newton Close, Park Farm Industrial Estate",
    "sg:city":"Wellingborough",
    "sg:classifiers":[
        {
            "category":"Home & Garden",
            "subcategory":"Home Furnishings",
            "type":"Retail Goods"
        },
        {
            "category":"Home & Garden",
            "subcategory":"Hardware",
            "type":"Retail Goods"
        }
    ],
    "sg:phone":"+44 1933 678666",
    "sg:postcode":"NN8 6UW",
    "sg:province":"Northamptonshire",
    "sg:tags":[
        "merchant",
        "paint",
        "diy",
        "decorators'"
    ],
    "wof:name":"Dulux Decorator Centre",
    "wof:placetype":"venue"
},
  "geometry": {"coordinates":[-0.736899,52.305222],"type":"Point"}
}