{
  "type": "Feature",
  "properties": {
    "addr:full":"15 Riverside High Street Lewes East Sussex BN7 2AD",
    "addr:housenumber":"15",
    "addr:postcode":"bn7 2ad",
    "addr:street":"Riverside High Street",
    "iso:country":"GB",
    "sg:address":"15 Riverside High Street",
    "sg:city":"Lewes",
    "sg:classifiers":[
        {
            "category":"Shopping",
            "subcategory":"Pharmacy",
            "type":"Retail Goods"
        }
    ],
    "sg:postcode":"BN7 2AD",
    "sg:province":"East Sussex",
    "sg:tags":[
        "medicine",
        "therapy"
    ],
    "wof:name":"Spellbound & Spirits",
    "wof:placetype":"venue"
},
  "geometry": {"coordinates":[0.01062,50.873203],"type":"Point"}
}