{
  "type": "Feature",
  "properties": {
    "addr:full":"107 Tankerton Road Whitstable Kent CT5 2JA",
    "addr:housenumber":"107",
    "addr:postcode":"ct5 2ja",
    "addr:street":"Tankerton Road",
    "iso:country":"GB",
    "sg:address":"107 Tankerton Road",
    "sg:city":"Whitstable",
    "sg:classifiers":[
        {
            "category":"Sports & Exercise",
            "subcategory":"Gym",
            "type":"Entertainment"
        }
    ],
    "sg:postcode":"CT5 2JA",
    "sg:province":"Kent",
    "sg:tags":[
        "fitness",
        "health",
        "centre"
    ],
    "wof:name":"Flex Appeal",
    "wof:placetype":"venue"
},
  "geometry": {"coordinates":[1.043482,51.363819],"type":"Point"}
}