{
  "type": "Feature",
  "properties": {
    "addr:full":"King Edward Street, Kirton Lindsey Gainsborough Lincolnshire DN21 4NF",
    "addr:postcode":"dn21 4nf",
    "addr:street":"King Edward Street",
    "iso:country":"GB",
    "sg:address":"King Edward Street, Kirton Lindsey",
    "sg:city":"Gainsborough",
    "sg:classifiers":[
        {
            "category":"Bars & Pubs",
            "type":"Food & Drink"
        }
    ],
    "sg:phone":"+44 1652 648014",
    "sg:postcode":"DN21 4NF",
    "sg:province":"Lincolnshire",
    "sg:tags":[
        "pubs",
        "inn"
    ],
    "wof:name":"The Queens Head",
    "wof:placetype":"venue"
},
  "geometry": {"coordinates":[-0.587453,53.475845],"type":"Point"}
}