{
  "type": "Feature",
  "properties": {
    "addr:full":"2 Babmaes Street London Greater London SW1Y 6NT",
    "addr:housenumber":"2",
    "addr:postcode":"sw1y 6nt",
    "addr:street":"Babmaes Street",
    "iso:country":"GB",
    "sg:address":"2 Babmaes Street",
    "sg:city":"London",
    "sg:classifiers":[
        {
            "category":"Banks & Credit Unions",
            "subcategory":"Financial Services",
            "type":"Services"
        }
    ],
    "sg:postcode":"SW1Y 6NT",
    "sg:province":"Greater London",
    "sg:tags":[
        "consultant"
    ],
    "wof:name":"Commerce & Finance International Limited",
    "wof:placetype":"venue"
},
  "geometry": {"coordinates":[-0.134963,51.508778],"type":"Point"}
}