{
  "type": "Feature",
  "properties": {
    "addr:full":"30a Elm Hill Norwich Norfolk NR3 1HG",
    "addr:housenumber":"30a",
    "addr:postcode":"nr3 1hg",
    "addr:street":"Elm Hill Norwich Norfolk",
    "iso:country":"GB",
    "sg:address":"30a Elm Hill",
    "sg:city":"Norwich",
    "sg:classifiers":[
        {
            "category":"Communications",
            "type":"Services"
        }
    ],
    "sg:postcode":"NR3 1HG",
    "sg:province":"Norfolk",
    "sg:tags":[
        "telecommunication"
    ],
    "wof:name":"Advanced Visual Communications Plc",
    "wof:placetype":"venue"
},
  "geometry": {"coordinates":[1.297112,52.632042],"type":"Point"}
}