{
  "type": "Feature",
  "properties": {
    "addr:full":"29 Orgreave Drive, Handsworth Sheffield South Yorkshire S13 9NR",
    "addr:housenumber":"29",
    "addr:postcode":"s13 9nr",
    "addr:street":"Orgreave Drive",
    "iso:country":"GB",
    "sg:address":"29 Orgreave Drive, Handsworth",
    "sg:city":"Sheffield",
    "sg:classifiers":[
        {
            "category":"Professional",
            "subcategory":"Computer Services",
            "type":"Services"
        }
    ],
    "sg:phone":"+44 114 201 2970",
    "sg:postcode":"S13 9NR",
    "sg:province":"South Yorkshire",
    "sg:tags":[
        "system",
        "software"
    ],
    "wof:name":"Quad Microtech Ltd.",
    "wof:placetype":"venue"
},
  "geometry": {"coordinates":[-1.3676179647,53.3712882996],"type":"Point"}
}