{
  "type": "Feature",
  "properties": {
    "iso:country":"GB",
    "sg:address":"Sinclair Court, Darrell St, Brunswick Village",
    "sg:city":"Newcastle Upon Tyne",
    "sg:classifiers":[
        {
            "category":"Professional",
            "subcategory":"Management & Consulting",
            "type":"Services"
        }
    ],
    "sg:phone":"+44 191 217 1110",
    "sg:postcode":"NE13 7DS",
    "sg:province":"Northumberland",
    "sg:tags":[
        "marketing",
        "consultant"
    ],
    "wof:name":"M C M Associates",
    "wof:placetype":"venue"
},
  "geometry": {"coordinates":[-1.63531,55.047798],"type":"Point"}
}