{
  "type": "Feature",
  "properties": {
    "iso:country":"GB",
    "sg:address":"262 Harehills Lane",
    "sg:city":"Leeds",
    "sg:classifiers":[
        {
            "category":"Shopping",
            "subcategory":"Pharmacy",
            "type":"Retail Goods"
        }
    ],
    "sg:phone":"+44 113 249 2311",
    "sg:postcode":"LS9 7BD",
    "sg:province":"West Yorkshire",
    "sg:tags":[
        "pharmacist",
        "dispensing",
        "chemist"
    ],
    "wof:name":"Selles Dispensing Chemists Ltd",
    "wof:placetype":"venue"
},
  "geometry": {"coordinates":[-1.5112240314,53.810546875],"type":"Point"}
}