{
  "type": "Feature",
  "properties": {
    "addr:full":"70 Barker Street Norwich Norfolk NR2 4UE",
    "addr:housenumber":"70",
    "addr:postcode":"nr2 4ue",
    "addr:street":"Barker Street",
    "iso:country":"GB",
    "sg:address":"70 Barker Street",
    "sg:city":"Norwich",
    "sg:classifiers":[
        {
            "category":"Home & Garden",
            "subcategory":"Building Materials",
            "type":"Retail Goods"
        }
    ],
    "sg:phone":"+44 1603 665150",
    "sg:postcode":"NR2 4UE",
    "sg:province":"Norfolk",
    "sg:tags":[
        "furnishers",
        "bathroom",
        "planner"
    ],
    "wof:name":"Holdom Lister & Co. Ltd.",
    "wof:placetype":"venue"
},
  "geometry": {"coordinates":[1.282495,52.638515],"type":"Point"}
}