{
  "type": "Feature",
  "properties": {
    "iso:country":"GB",
    "sg:address":"Unit 20, Broomhouse Lane Industrial Estate",
    "sg:city":"Doncaster",
    "sg:classifiers":[
        {
            "category":"Manufacturing",
            "subcategory":"Motor Vehicles & Parts",
            "type":"Manufacturing & Wholesale Goods"
        }
    ],
    "sg:phone":"+44 1709 869999",
    "sg:postcode":"DN12 1EQ",
    "sg:province":"South Yorkshire",
    "sg:tags":[
        "bearing"
    ],
    "wof:name":"Bearing Co. Ltd.",
    "wof:placetype":"venue"
},
  "geometry": {"coordinates":[-1.181608,53.483177],"type":"Point"}
}