{
  "type": "Feature",
  "properties": {
    "addr:full":"644 Lytham Road Blackpool Lancashire FY4 1QU",
    "addr:housenumber":"644",
    "addr:postcode":"fy4 1qu",
    "addr:street":"Lytham Road",
    "iso:country":"GB",
    "sg:address":"644 Lytham Road",
    "sg:city":"Blackpool",
    "sg:classifiers":[
        {
            "category":"Organizations",
            "subcategory":"Membership Organization",
            "type":"Services"
        }
    ],
    "sg:postcode":"FY4 1QU",
    "sg:province":"Lancashire",
    "sg:tags":[
        "club"
    ],
    "wof:name":"Meridian Lodge",
    "wof:placetype":"venue"
},
  "geometry": {"coordinates":[-3.046332,53.781601],"type":"Point"}
}