{
  "type": "Feature",
  "properties": {
    "iso:country":"GB",
    "sg:address":"65 Melbourne Road",
    "sg:city":"Chester",
    "sg:classifiers":[
        {
            "category":"Home & Garden",
            "subcategory":"Household Appliances",
            "type":"Retail Goods"
        }
    ],
    "sg:postcode":"CH1 5JQ",
    "sg:province":"Cheshire",
    "sg:tags":[
        "domestic",
        "oven",
        "microwave"
    ],
    "wof:name":"Cheshire Microwave Services",
    "wof:placetype":"venue"
},
  "geometry": {"coordinates":[-2.932232,53.203079],"type":"Point"}
}