{
  "type": "Feature",
  "properties": {
    "addr:full":"Chilwell Retail Park, Nottingham Rdbeeston Nottingham Nottinghamshire NG9 6DS",
    "addr:postcode":"ng9 6ds",
    "addr:street":"Park",
    "iso:country":"GB",
    "sg:address":"Chilwell Retail Park, Nottingham Rdbeeston",
    "sg:city":"Nottingham",
    "sg:classifiers":[
        {
            "category":"Fast Food",
            "type":"Food & Drink"
        }
    ],
    "sg:phone":"+44 115 946 9939",
    "sg:postcode":"NG9 6DS",
    "sg:province":"Nottinghamshire",
    "sg:tags":[
        "away",
        "take"
    ],
    "wof:name":"McDonalds Restaurants Ltd.",
    "wof:placetype":"venue"
},
  "geometry": {"coordinates":[-1.243619,52.903976],"type":"Point"}
}