{
  "type": "Feature",
  "properties": {
    "iso:country":"GB",
    "sg:address":"8 Windmill Row",
    "sg:city":"Lambeth",
    "sg:classifiers":[
        {
            "category":"Professional",
            "type":"Services"
        }
    ],
    "sg:phone":"+44 20 7735 1346",
    "sg:postcode":"SE11 5DW",
    "sg:province":"Greater London",
    "sg:tags":[
        "repair",
        "tech",
        "maintenance"
    ],
    "wof:name":"Addodiscs Simplicity System",
    "wof:placetype":"venue"
},
  "geometry": {"coordinates":[-0.111885,51.487164],"type":"Point"}
}