{
  "type": "Feature",
  "properties": {
    "addr:full":"Mo Dhachaid, Farr Inverness Highland IV2 6XG",
    "addr:postcode":"iv2 6xg",
    "addr:street":"Farr Inverness",
    "iso:country":"GB",
    "sg:address":"Mo Dhachaid, Farr",
    "sg:city":"Inverness",
    "sg:classifiers":[
        {
            "category":"Retail",
            "subcategory":"Repair Shop",
            "type":"Services"
        }
    ],
    "sg:phone":"+44 1808 521360",
    "sg:postcode":"IV2 6XG",
    "sg:province":"Highland",
    "sg:tags":[
        "plant",
        "machinery"
    ],
    "wof:name":"Ian Gordon Plant Hire",
    "wof:placetype":"venue"
},
  "geometry": {"coordinates":[-4.19021,57.36964],"type":"Point"}
}