{
  "type": "Feature",
  "properties": {
    "addr:full":"16 Haddon Court Harpenden Hertfordshire AL5 5NB",
    "addr:housenumber":"16",
    "addr:postcode":"al5 5nb",
    "addr:street":"Haddon Court",
    "iso:country":"GB",
    "sg:address":"16 Haddon Court",
    "sg:city":"Harpenden",
    "sg:classifiers":[
        {
            "category":"Professional",
            "subcategory":"Management & Consulting",
            "type":"Services"
        }
    ],
    "sg:phone":"+44 1582 623153",
    "sg:postcode":"AL5 5NB",
    "sg:province":"Hertfordshire",
    "sg:tags":[
        "marketing",
        "consultant"
    ],
    "wof:name":"Cheek David & Associates",
    "wof:placetype":"venue"
},
  "geometry": {"coordinates":[-0.356559,51.816216],"type":"Point"}
}