{
  "type": "Feature",
  "properties": {
    "iso:country":"GB",
    "sg:address":"35 Southfield Lane",
    "sg:city":"Bradford",
    "sg:classifiers":[
        {
            "category":"Food & Beverages",
            "subcategory":"Liquor & Beverages",
            "type":"Retail Goods"
        }
    ],
    "sg:phone":"+44 1274 573533",
    "sg:postcode":"BD5 9HU",
    "sg:province":"West Yorkshire",
    "sg:tags":[
        "beer",
        "spirit",
        "wines"
    ],
    "wof:name":"T S & B Food Store",
    "wof:placetype":"venue"
},
  "geometry": {"coordinates":[-1.774546,53.776291],"type":"Point"}
}