{
  "type": "Feature",
  "properties": {
    "addr:full":"Main Road, Millfield Wooler Northumberland NE71 6JD",
    "addr:postcode":"ne71 6jd",
    "addr:street":"Main Road",
    "iso:country":"GB",
    "sg:address":"Main Road, Millfield",
    "sg:city":"Wooler",
    "sg:classifiers":[
        {
            "category":"Cafe",
            "type":"Food & Drink"
        }
    ],
    "sg:phone":"+44 1668 216323",
    "sg:postcode":"NE71 6JD",
    "sg:province":"Northumberland",
    "sg:tags":[
        "tea",
        "room"
    ],
    "wof:name":"Milfield Country Cafe",
    "wof:placetype":"venue"
},
  "geometry": {"coordinates":[-2.011584,55.547771],"type":"Point"}
}