{
  "type": "Feature",
  "properties": {
    "iso:country":"GB",
    "sg:address":"20 High Street",
    "sg:city":"Pinner",
    "sg:classifiers":[
        {
            "category":"Personal",
            "subcategory":"Beauty Salon",
            "type":"Services"
        },
        {
            "category":"Personal",
            "subcategory":"Barber",
            "type":"Services"
        }
    ],
    "sg:phone":"+44 20 8866 5898",
    "sg:postcode":"HA5 5PW",
    "sg:province":"Greater London",
    "sg:tags":[
        "unisex",
        "hairdresser"
    ],
    "wof:name":"The Hair & Face Place",
    "wof:placetype":"venue"
},
  "geometry": {"coordinates":[-0.381298,51.593903],"type":"Point"}
}