{
  "type": "Feature",
  "properties": {
    "iso:country":"GB",
    "sg:address":"Unit 1 Silk Bridge Buildings, 1 The Hyde, Hendon",
    "sg:city":"London",
    "sg:classifiers":[
        {
            "category":"Shopping",
            "type":"Retail Goods"
        }
    ],
    "sg:phone":"+44 20 8200 8588",
    "sg:postcode":"NW9 6LE",
    "sg:province":"Greater London",
    "sg:tags":[
        "part",
        "accessory"
    ],
    "wof:name":"Halfords",
    "wof:placetype":"venue"
},
  "geometry": {"coordinates":[-0.252299,51.58876],"type":"Point"}
}