{
  "type": "Feature",
  "properties": {
    "addr:full":"Hatch Farm, Chertsey Road Addlestone Surrey KT15 2EH",
    "addr:postcode":"kt15 2eh",
    "addr:street":"Chertsey Road",
    "iso:country":"GB",
    "sg:address":"Hatch Farm, Chertsey Road",
    "sg:city":"Addlestone",
    "sg:classifiers":[
        {
            "category":"Communications",
            "subcategory":"Film & Video Production",
            "type":"Services"
        }
    ],
    "sg:phone":"+44 1932 831030",
    "sg:postcode":"KT15 2EH",
    "sg:province":"Surrey",
    "sg:tags":[
        "recording",
        "studio"
    ],
    "wof:name":"M M P",
    "wof:placetype":"venue"
},
  "geometry": {"coordinates":[-0.492654,51.378761],"type":"Point"}
}