{
  "type": "Feature",
  "properties": {
    "iso:country":"GB",
    "sg:address":"Lower Road, Bookham",
    "sg:city":"Leatherhead",
    "sg:classifiers":[
        {
            "category":"Health Services",
            "subcategory":"Doctor",
            "type":"Services"
        }
    ],
    "sg:phone":"+44 1372 455450",
    "sg:postcode":"KT23 4DP",
    "sg:province":"Surrey",
    "sg:tags":[
        "practitioners"
    ],
    "wof:name":"The Fairfield Medical Cenre",
    "wof:placetype":"venue"
},
  "geometry": {"coordinates":[-0.363142,51.284817],"type":"Point"}
}