{
  "type": "Feature",
  "properties": {
    "iso:country":"GB",
    "sg:address":"71 Westmoor Street, Charlton",
    "sg:city":"London",
    "sg:classifiers":[
        {
            "category":"Professional",
            "subcategory":"Testing Lab",
            "type":"Services"
        }
    ],
    "sg:phone":"+44 20 8858 0444",
    "sg:postcode":"SE7 8NQ",
    "sg:province":"Greater London",
    "sg:tags":[
        "mot"
    ],
    "wof:name":"Valley Service Station",
    "wof:placetype":"venue"
},
  "geometry": {"coordinates":[0.038181,51.491901],"type":"Point"}
}