{
  "type": "Feature",
  "properties": {
    "addr:full":"47 High Street Uckfield East Sussex TN22 1AJ",
    "addr:housenumber":"47",
    "addr:postcode":"tn22 1aj",
    "addr:street":"High Street",
    "iso:country":"GB",
    "sg:address":"47 High Street",
    "sg:city":"Uckfield",
    "sg:classifiers":[
        {
            "category":"Shopping",
            "subcategory":"Comic Books",
            "type":"Retail Goods"
        }
    ],
    "sg:phone":"+44 1825 762831",
    "sg:postcode":"TN22 1AJ",
    "sg:province":"East Sussex",
    "sg:tags":[
        "jeweller",
        "sale",
        "jewellery"
    ],
    "wof:name":"Gale & Woolgar",
    "wof:placetype":"venue"
},
  "geometry": {"coordinates":[0.096059,50.970715],"type":"Point"}
}