{
  "type": "Feature",
  "properties": {
    "iso:country":"GB",
    "sg:address":"9 Finkle Street",
    "sg:city":"Malton",
    "sg:classifiers":[
        {
            "category":"Farming",
            "subcategory":"Livestock Farm",
            "type":"Manufacturing & Wholesale Goods"
        },
        {
            "category":"Shopping",
            "subcategory":"Florist",
            "type":"Retail Goods"
        }
    ],
    "sg:phone":"+44 1653 692671",
    "sg:postcode":"YO17 7JD",
    "sg:province":"North Yorkshire",
    "sg:tags":[
        "breeder"
    ],
    "wof:name":"The Topiary Tree",
    "wof:placetype":"venue"
},
  "geometry": {"coordinates":[-0.797951,54.136391],"type":"Point"}
}