{
  "type": "Feature",
  "properties": {
    "addr:full":"20a The Warren, Manor Park London Greater London E12 5HY",
    "addr:housenumber":"20a",
    "addr:postcode":"e12 5hy",
    "addr:street":"The Warren Manor Park",
    "iso:country":"GB",
    "sg:address":"20a The Warren, Manor Park",
    "sg:city":"London",
    "sg:classifiers":[
        {
            "category":"Building & Trades",
            "subcategory":"Construction",
            "type":"Services"
        }
    ],
    "sg:postcode":"E12 5HY",
    "sg:province":"Greater London",
    "sg:tags":[
        "monumental",
        "mason"
    ],
    "wof:name":"C B Memorials",
    "wof:placetype":"venue"
},
  "geometry": {"coordinates":[0.0523440018,51.5535316467],"type":"Point"}
}