{
  "type": "Feature",
  "properties": {
    "addr:full":"Josselin Road Basildon Essex SS13 1EW",
    "addr:postcode":"ss13 1ew",
    "addr:street":"Josselin Road",
    "iso:country":"GB",
    "sg:address":"Josselin Road",
    "sg:city":"Basildon",
    "sg:classifiers":[
        {
            "category":"Personal",
            "type":"Services"
        }
    ],
    "sg:postcode":"SS13 1EW",
    "sg:province":"Essex",
    "sg:tags":[
        "delivery"
    ],
    "wof:name":"Amtrak Express Parcels",
    "wof:placetype":"venue"
},
  "geometry": {"coordinates":[0.5159050226,51.5875968933],"type":"Point"}
}