{
  "type": "Feature",
  "properties": {
    "addr:full":"Southey Rd London Greater London N15 5LL",
    "addr:postcode":"n15 5ll",
    "addr:street":"Southey Rd",
    "iso:country":"GB",
    "sg:address":"Southey Rd",
    "sg:city":"London",
    "sg:classifiers":[
        {
            "category":"Shopping",
            "subcategory":"Clothing, Apparel, & Fashions",
            "type":"Retail Goods"
        }
    ],
    "sg:postcode":"N15 5LL",
    "sg:province":"Greater London",
    "sg:tags":[
        "ladieswear"
    ],
    "wof:name":"Fiesta Fashions",
    "wof:placetype":"venue"
},
  "geometry": {"coordinates":[-0.0785500035,51.5821609497],"type":"Point"}
}