{
  "type": "Feature",
  "properties": {
    "addr:full":"Cawsey Way Woking Surrey GU21 1YB",
    "addr:postcode":"gu21 1yb",
    "addr:street":"Cawsey Way",
    "iso:country":"GB",
    "sg:address":"Cawsey Way",
    "sg:city":"Woking",
    "sg:classifiers":[
        {
            "category":"Sports & Exercise",
            "subcategory":"Sports Center",
            "type":"Entertainment"
        }
    ],
    "sg:phone":"+44 1483 727107",
    "sg:postcode":"GU21 1YB",
    "sg:province":"Surrey",
    "sg:tags":[
        "shop",
        "good"
    ],
    "wof:name":"J J B Sports Plc",
    "wof:placetype":"venue"
},
  "geometry": {"coordinates":[-0.561303,51.318619],"type":"Point"}
}