{
  "type": "Feature",
  "properties": {
    "addr:full":"37 High Street Tunbridge Wells Kent TN1 1XL",
    "addr:housenumber":"37",
    "addr:postcode":"tn1 1xl",
    "addr:street":"High Street",
    "iso:country":"GB",
    "sg:address":"37 High Street",
    "sg:city":"Tunbridge Wells",
    "sg:classifiers":[
        {
            "category":"Shopping",
            "subcategory":"Jewelry",
            "type":"Retail Goods"
        }
    ],
    "sg:phone":"+44 1892 525874",
    "sg:postcode":"TN1 1XL",
    "sg:province":"Kent",
    "sg:tags":[
        "gold",
        "silversmith"
    ],
    "wof:name":"Payne & Son (Silversmiths) Ltd.",
    "wof:placetype":"venue"
},
  "geometry": {"coordinates":[0.2619740069,51.1280555725],"type":"Point"}
}