{
  "type": "Feature",
  "properties": {
    "addr:full":"221 Park Avenue, Newcastle Newcastle Upon Tyne Tyne and Wear NE3 2LH",
    "addr:housenumber":"221",
    "addr:postcode":"ne3 2lh",
    "addr:street":"Park Avenue",
    "iso:country":"GB",
    "sg:address":"221 Park Avenue, Newcastle",
    "sg:city":"Newcastle Upon Tyne",
    "sg:classifiers":[
        {
            "category":"Retail",
            "subcategory":"Driving School",
            "type":"Services"
        }
    ],
    "sg:phone":"+44 191 285 9222",
    "sg:postcode":"NE3 2LH",
    "sg:province":"Tyne and Wear",
    "wof:name":"Gemini School of Motoring",
    "wof:placetype":"venue"
},
  "geometry": {"coordinates":[-1.634228,55.014839],"type":"Point"}
}