{
  "type": "Feature",
  "properties": {
    "addr:full":"Acorn Bank Garden, Watermill Temple Sowerby Penrith Cumbria CA10 1SP",
    "addr:postcode":"ca10 1sp",
    "iso:country":"GB",
    "sg:address":"Acorn Bank Garden, Watermill Temple Sowerby",
    "sg:city":"Penrith",
    "sg:classifiers":[
        {
            "category":"Landmark",
            "subcategory":"Tourist Attraction",
            "type":"Public Place"
        }
    ],
    "sg:phone":"+44 1428 642673",
    "sg:postcode":"CA10 1SP",
    "sg:province":"Cumbria",
    "sg:tags":[
        "interest"
    ],
    "wof:name":"National Trust",
    "wof:placetype":"venue"
},
  "geometry": {"coordinates":[-2.603439,54.637119],"type":"Point"}
}