{
  "type": "Feature",
  "properties": {
    "addr:full":"Adelaide Ho, 626 Chiswick High Rd London Greater London W4 5RY",
    "addr:housenumber":"626",
    "addr:postcode":"w4 5ry",
    "addr:street":"Chiswick High Rd",
    "iso:country":"GB",
    "sg:address":"Adelaide Ho, 626 Chiswick High Rd",
    "sg:city":"London",
    "sg:classifiers":[
        {
            "category":"Communications",
            "type":"Services"
        }
    ],
    "sg:postcode":"W4 5RY",
    "sg:province":"Greater London",
    "sg:tags":[
        "telecommunication"
    ],
    "wof:name":"Associated Telecommunications Operators",
    "wof:placetype":"venue"
},
  "geometry": {"coordinates":[-0.2780599892,51.4922599792],"type":"Point"}
}