{
  "type": "Feature",
  "properties": {
    "iso:country":"GB",
    "sg:address":"Unit 6 Knight House, Lenthall Road",
    "sg:city":"Loughton",
    "sg:classifiers":[
        {
            "category":"Manufacturing",
            "subcategory":"Wood Products",
            "type":"Manufacturing & Wholesale Goods"
        }
    ],
    "sg:phone":"+44 20 8502 1831",
    "sg:postcode":"IG10 3UD",
    "sg:province":"Essex",
    "sg:tags":[
        "packaging",
        "crate",
        "pallets"
    ],
    "wof:name":"Sackraft Supply Co",
    "wof:placetype":"venue"
},
  "geometry": {"coordinates":[0.087836,51.645473],"type":"Point"}
}