{
  "type": "Feature",
  "properties": {
    "iso:country":"GB",
    "sg:address":"64 Woodlands Road",
    "sg:city":"Lytham St Annes",
    "sg:classifiers":[
        {
            "category":"Shopping",
            "subcategory":"News",
            "type":"Retail Goods"
        }
    ],
    "sg:postcode":"FY8 4BX",
    "sg:province":"Lancashire",
    "sg:tags":[
        "newsagent"
    ],
    "wof:name":"T & B Blundell",
    "wof:placetype":"venue"
},
  "geometry": {"coordinates":[-2.99221,53.741802],"type":"Point"}
}