{
  "type": "Feature",
  "properties": {
    "iso:country":"GB",
    "sg:address":"42 Rosemount Drive, Uphall",
    "sg:city":"Broxburn",
    "sg:classifiers":[
        {
            "category":"Manufacturing",
            "subcategory":"Metals",
            "type":"Manufacturing & Wholesale Goods"
        }
    ],
    "sg:phone":"+44 1506 853092",
    "sg:postcode":"EH52 6DE",
    "sg:province":"City of Edinburgh",
    "sg:tags":[
        "blacksmith",
        "forgemasters"
    ],
    "wof:name":"D M Young",
    "wof:placetype":"venue"
},
  "geometry": {"coordinates":[-3.515728,55.929672],"type":"Point"}
}