{
  "type": "Feature",
  "properties": {
    "iso:country":"GB",
    "sg:address":"10 Woodend Mill, South Hill",
    "sg:city":"Oldham",
    "sg:classifiers":[
        {
            "category":"Professional",
            "subcategory":"Engineering",
            "type":"Services"
        }
    ],
    "sg:phone":"+44 161 633 9669",
    "sg:postcode":"OL4 5DR",
    "sg:province":"Lancashire",
    "sg:tags":[
        "engineer"
    ],
    "wof:name":"S M D Engineering Services",
    "wof:placetype":"venue"
},
  "geometry": {"coordinates":[-2.056873,53.537067],"type":"Point"}
}