{
  "type": "Feature",
  "properties": {
    "addr:full":"Unit 8 Pool St Macclesfield Cheshire SK11 7NX",
    "addr:housenumber":"unit 8",
    "addr:postcode":"sk11 7nx",
    "addr:street":"Pool St",
    "iso:country":"GB",
    "sg:address":"Unit 8 Pool St",
    "sg:city":"Macclesfield",
    "sg:classifiers":[
        {
            "category":"Shopping",
            "subcategory":"Clothing, Apparel, & Fashions",
            "type":"Retail Goods"
        }
    ],
    "sg:phone":"+44 1625 435355",
    "sg:postcode":"SK11 7NX",
    "sg:province":"Cheshire",
    "sg:tags":[
        "sport",
        "clothing"
    ],
    "wof:name":"Sports Apparel International",
    "wof:placetype":"venue"
},
  "geometry": {"coordinates":[-2.121044,53.253666],"type":"Point"}
}