{
  "type": "Feature",
  "properties": {
    "iso:country":"GB",
    "sg:address":"Stoneyheugh Farm, Ellerbeck Lane",
    "sg:city":"Workington",
    "sg:classifiers":[
        {
            "category":"Farming",
            "subcategory":"Livestock Farm",
            "type":"Manufacturing & Wholesale Goods"
        }
    ],
    "sg:postcode":"CA14 4HF",
    "sg:province":"Cumbria",
    "sg:tags":[
        "others"
    ],
    "wof:name":"T & D Stamper",
    "wof:placetype":"venue"
},
  "geometry": {"coordinates":[-3.550002,54.638981],"type":"Point"}
}