{
  "type": "Feature",
  "properties": {
    "iso:country":"GB",
    "sg:address":"The Vinery, Harford Sq",
    "sg:city":"Bristol",
    "sg:classifiers":[
        {
            "category":"Health Services",
            "subcategory":"Dentist",
            "type":"Services"
        }
    ],
    "sg:phone":"+44 1275 332371",
    "sg:postcode":"BS18 8RD",
    "sg:province":"City of Bristol",
    "wof:name":"G W Morris",
    "wof:placetype":"venue"
},
  "geometry": {"coordinates":[-2.611371994,51.3659515381],"type":"Point"}
}