{
  "type": "Feature",
  "properties": {
    "iso:country":"GB",
    "sg:address":"16 Commercial Rd, Oldmeldrum",
    "sg:city":"Inverurie",
    "sg:classifiers":[
        {
            "category":"Taxi",
            "type":"Transportation"
        }
    ],
    "sg:phone":"+44 1651 872378",
    "sg:postcode":"AB51 0DT",
    "sg:province":"Aberdeenshire",
    "sg:tags":[
        "mini",
        "cab"
    ],
    "wof:name":"Oldmeldrum Taxis",
    "wof:placetype":"venue"
},
  "geometry": {"coordinates":[-2.32309,57.33469],"type":"Point"}
}