{
  "type": "Feature",
  "properties": {
    "addr:full":"13 Lyndrick Road Plymouth Devon PL3 5TA",
    "addr:housenumber":"13",
    "addr:postcode":"pl3 5ta",
    "addr:street":"Lyndrick Road",
    "iso:country":"GB",
    "sg:address":"13 Lyndrick Road",
    "sg:city":"Plymouth",
    "sg:classifiers":[
        {
            "category":"Professional",
            "subcategory":"Art Services",
            "type":"Services"
        },
        {
            "category":"Building & Trades",
            "subcategory":"Construction",
            "type":"Services"
        }
    ],
    "sg:postcode":"PL3 5TA",
    "sg:province":"Devon",
    "sg:tags":[
        "decorator",
        "painter"
    ],
    "wof:name":"M W Duffin",
    "wof:placetype":"venue"
},
  "geometry": {"coordinates":[-4.1362891197,50.3950157166],"type":"Point"}
}