{
  "type": "Feature",
  "properties": {
    "addr:full":"Unit 3 Siberia Mill, Holgate Street, Briercliffe Burnley Lancashire BB10 2HQ",
    "addr:housenumber":"unit 3",
    "addr:postcode":"bb10 2hq",
    "addr:street":"Siberia Mill Holgate Street",
    "iso:country":"GB",
    "sg:address":"Unit 3 Siberia Mill, Holgate Street, Briercliffe",
    "sg:city":"Burnley",
    "sg:classifiers":[
        {
            "category":"Professional",
            "subcategory":"Art Services",
            "type":"Services"
        }
    ],
    "sg:postcode":"BB10 2HQ",
    "sg:province":"Lancashire",
    "sg:tags":[
        "framing"
    ],
    "wof:name":"The Pub Picture Co",
    "wof:placetype":"venue"
},
  "geometry": {"coordinates":[-2.20533,53.81205],"type":"Point"}
}