{
  "type": "Feature",
  "properties": {
    "addr:full":"56 Church Lane Wakefield West Yorkshire WF1 2JT",
    "addr:housenumber":"56",
    "addr:postcode":"wf1 2jt",
    "addr:street":"Church Lane",
    "iso:country":"GB",
    "sg:address":"56 Church Lane",
    "sg:city":"Wakefield",
    "sg:classifiers":[
        {
            "category":"Building & Trades",
            "subcategory":"Construction",
            "type":"Services"
        }
    ],
    "sg:phone":"+44 1924 823236",
    "sg:postcode":"WF1 2JT",
    "sg:province":"West Yorkshire",
    "sg:tags":[
        "dry",
        "lining",
        "plasterers",
        "screeders"
    ],
    "wof:name":"M C Plastering",
    "wof:placetype":"venue"
},
  "geometry": {"coordinates":[-1.5049799681,53.7133560181],"type":"Point"}
}