{
  "type": "Feature",
  "properties": {
    "addr:full":"17 Pindock Mews London Greater London W9 2PY",
    "addr:housenumber":"17",
    "addr:postcode":"w9 2py",
    "addr:street":"Pindock Mews",
    "iso:country":"GB",
    "sg:address":"17 Pindock Mews",
    "sg:city":"London",
    "sg:classifiers":[
        {
            "category":"Wholesale",
            "subcategory":"Construction Materials",
            "type":"Manufacturing & Wholesale Goods"
        },
        {
            "category":"Utilities",
            "subcategory":"Cable",
            "type":"Services"
        }
    ],
    "sg:postcode":"W9 2PY",
    "sg:province":"Greater London",
    "sg:tags":[
        "rope",
        "merchant",
        "stone",
        "hawser"
    ],
    "wof:name":"Sterling Croft Ltd",
    "wof:placetype":"venue"
},
  "geometry": {"coordinates":[-0.1871999949,51.525100708],"type":"Point"}
}