{
  "type": "Feature",
  "properties": {
    "addr:full":"22 Birchwood Lane Alfreton Derbyshire DE55 4LZ",
    "addr:housenumber":"22",
    "addr:postcode":"de55 4lz",
    "addr:street":"Birchwood Lane",
    "iso:country":"GB",
    "sg:address":"22 Birchwood Lane",
    "sg:city":"Alfreton",
    "sg:classifiers":[
        {
            "category":"Fast Food",
            "type":"Food & Drink"
        },
        {
            "category":"Food & Beverages",
            "subcategory":"Meat & Fish",
            "type":"Retail Goods"
        },
        {
            "category":"Food & Beverages",
            "subcategory":"Groceries & Convenience Stores",
            "type":"Retail Goods"
        }
    ],
    "sg:phone":"+44 1773 602372",
    "sg:postcode":"DE55 4LZ",
    "sg:province":"Derbyshire",
    "sg:tags":[
        "shop",
        "away",
        "take",
        "chip"
    ],
    "wof:name":"JO F OLIVEIRA",
    "wof:placetype":"venue"
},
  "geometry": {"coordinates":[-1.366814971,53.0800666809],"type":"Point"}
}