{
  "type": "Feature",
  "properties": {
    "addr:full":"176 Harrow Road Wembley Greater London HA9 6QQ",
    "addr:housenumber":"176",
    "addr:postcode":"ha9 6qq",
    "addr:street":"Harrow Road",
    "iso:country":"GB",
    "sg:address":"176 Harrow Road",
    "sg:city":"Wembley",
    "sg:classifiers":[
        {
            "category":"Health Services",
            "subcategory":"Podiatrist",
            "type":"Services"
        },
        {
            "category":"Health Services",
            "subcategory":"Chiropractor",
            "type":"Services"
        }
    ],
    "sg:phone":"+44 20 8902 5143",
    "sg:postcode":"HA9 6QQ",
    "sg:province":"Greater London",
    "sg:tags":[
        "podiatrists",
        "chiropodist"
    ],
    "wof:name":"Vijay K Patel",
    "wof:placetype":"venue"
},
  "geometry": {"coordinates":[-0.279581,51.548878],"type":"Point"}
}