{
  "type": "Feature",
  "properties": {
    "addr:full":"47 Paget Avenue, Birstall Leicester Leicestershire LE4 4HY",
    "addr:housenumber":"47",
    "addr:postcode":"le4 4hy",
    "addr:street":"Paget Avenue",
    "iso:country":"GB",
    "sg:address":"47 Paget Avenue, Birstall",
    "sg:city":"Leicester",
    "sg:classifiers":[
        {
            "category":"Professional",
            "subcategory":"Printing & Photocopies",
            "type":"Services"
        }
    ],
    "sg:phone":"+44 116 267 7239",
    "sg:postcode":"LE4 4HY",
    "sg:province":"Leicestershire",
    "sg:tags":[
        "printer"
    ],
    "wof:name":"Northlight Promotions",
    "wof:placetype":"venue"
},
  "geometry": {"coordinates":[-1.120447,52.68008],"type":"Point"}
}