{
  "type": "Feature",
  "properties": {
    "iso:country":"GB",
    "sg:address":"Fimberfield Farm, Fridaythorpe",
    "sg:city":"Driffield",
    "sg:classifiers":[
        {
            "category":"Farming",
            "subcategory":"Farm",
            "type":"Manufacturing & Wholesale Goods"
        }
    ],
    "sg:phone":"+44 1377 236696",
    "sg:postcode":"YO25 9RZ",
    "sg:province":"East Riding of Yorkshire",
    "sg:tags":[
        "mixed",
        "crop"
    ],
    "wof:name":"A J Chapman",
    "wof:placetype":"venue"
},
  "geometry": {"coordinates":[-0.6640580297,54.0201683044],"type":"Point"}
}