{
  "type": "Feature",
  "properties": {
    "iso:country":"GB",
    "sg:address":"6 Littlemoor",
    "sg:city":"Chesterfield",
    "sg:classifiers":[
        {
            "category":"Retail",
            "subcategory":"Laundry & Dry Cleaning",
            "type":"Services"
        }
    ],
    "sg:phone":"+44 1246 278642",
    "sg:postcode":"S41 8QN",
    "sg:province":"Derbyshire",
    "sg:tags":[
        "alteration"
    ],
    "wof:name":"H E M Dry Cleaners",
    "wof:placetype":"venue"
},
  "geometry": {"coordinates":[-1.4459990263,53.2568359375],"type":"Point"}
}