{
  "type": "Feature",
  "properties": {
    "addr:full":"2 Pottery Units, Forde Road Newton Abbot Devon TQ12 4AD",
    "addr:housenumber":"2",
    "addr:postcode":"tq12 4ad",
    "addr:street":"Pottery Units Forde Road",
    "iso:country":"GB",
    "sg:address":"2 Pottery Units, Forde Road",
    "sg:city":"Newton Abbot",
    "sg:classifiers":[
        {
            "category":"Professional",
            "type":"Services"
        }
    ],
    "sg:phone":"+44 1626 355091",
    "sg:postcode":"TQ12 4AD",
    "sg:province":"Devon",
    "sg:tags":[
        "repair",
        "tech",
        "maintenance"
    ],
    "wof:name":"Lynx Technology Ltd.",
    "wof:placetype":"venue"
},
  "geometry": {"coordinates":[-3.6076591015,50.5288696289],"type":"Point"}
}