{
  "type": "Feature",
  "properties": {
    "iso:country":"GB",
    "sg:address":"139a Craven St",
    "sg:city":"Birkenhead",
    "sg:classifiers":[
        {
            "category":"Home & Garden",
            "subcategory":"Building Materials",
            "type":"Retail Goods"
        }
    ],
    "sg:phone":"+44 151 653 6771",
    "sg:postcode":"L41 4BW",
    "sg:province":"Merseyside",
    "sg:tags":[
        "gate",
        "door",
        "barrier"
    ],
    "wof:name":"G A Carr",
    "wof:placetype":"venue"
},
  "geometry": {"coordinates":[-3.030449,53.393188],"type":"Point"}
}