{
  "type": "Feature",
  "properties": {
    "iso:country":"GB",
    "sg:address":"North Valley Road",
    "sg:city":"Colne",
    "sg:classifiers":[
        {
            "category":"Autos & Motor Vehicles",
            "subcategory":"Automobile Sales",
            "type":"Retail Goods"
        }
    ],
    "sg:phone":"+44 1282 866550",
    "sg:postcode":"BB8 9HD",
    "sg:province":"Lancashire",
    "sg:tags":[
        "car"
    ],
    "wof:name":"A J Cars",
    "wof:placetype":"venue"
},
  "geometry": {"coordinates":[-2.173588,53.859253],"type":"Point"}
}