{
  "type": "Feature",
  "properties": {
    "addr:full":"Orchard Bungalow, Huxtables Lane, Fordham Heath Colchester Essex CO3 9TJ",
    "addr:postcode":"co3 9tj",
    "addr:street":"Huxtables Lane",
    "iso:country":"GB",
    "sg:address":"Orchard Bungalow, Huxtables Lane, Fordham Heath",
    "sg:city":"Colchester",
    "sg:classifiers":[
        {
            "category":"Recreation",
            "subcategory":"Dog Park",
            "type":"Entertainment"
        }
    ],
    "sg:postcode":"CO3 9TJ",
    "sg:province":"Essex",
    "wof:name":"Woofers",
    "wof:placetype":"venue"
},
  "geometry": {"coordinates":[0.81344,51.901814],"type":"Point"}
}