{
  "type": "Feature",
  "properties": {
    "iso:country":"GB",
    "sg:address":"38 North Marine Road",
    "sg:city":"Scarborough",
    "sg:classifiers":[
        {
            "category":"Food & Beverages",
            "subcategory":"Groceries & Convenience Stores",
            "type":"Retail Goods"
        }
    ],
    "sg:phone":"+44 1723 364605",
    "sg:postcode":"YO12 7PE",
    "sg:province":"North Yorkshire",
    "wof:name":"Joe's Mini Market",
    "wof:placetype":"venue"
},
  "geometry": {"coordinates":[-0.4013879895,54.2866363525],"type":"Point"}
}