{
  "type": "Feature",
  "properties": {
    "iso:country":"GB",
    "sg:address":"Fort Brockhurst Gunners Way, Elson",
    "sg:city":"Gosport",
    "sg:classifiers":[
        {
            "category":"Landmark",
            "subcategory":"Tourist Attraction",
            "type":"Public Place"
        }
    ],
    "sg:phone":"+44 23 9258 1059",
    "sg:postcode":"PO12 4DS",
    "sg:province":"Hampshire",
    "sg:tags":[
        "interest"
    ],
    "wof:name":"English Heritage",
    "wof:placetype":"venue"
},
  "geometry": {"coordinates":[-1.15139,50.815041],"type":"Point"}
}