{
  "type": "Feature",
  "properties": {
    "iso:country":"GB",
    "sg:address":"First Floor Offices, 2-4 Church Street, Chirk",
    "sg:city":"Wrexham",
    "sg:classifiers":[
        {
            "category":"Utilities",
            "type":"Services"
        }
    ],
    "sg:postcode":"LL14 5HA",
    "sg:province":"Wrexham",
    "sg:tags":[
        "internet"
    ],
    "wof:name":"Pfi Solutions Ltd",
    "wof:placetype":"venue"
},
  "geometry": {"coordinates":[-3.056989,52.932957],"type":"Point"}
}