{
  "type": "Feature",
  "properties": {
    "iso:country":"GB",
    "sg:address":"4 Forest Dr",
    "sg:city":"Epping",
    "sg:classifiers":[
        {
            "category":"Real Estate",
            "subcategory":"Real Estate Agent",
            "type":"Services"
        }
    ],
    "sg:phone":"+44 1992 812929",
    "sg:postcode":"CM16 7EY",
    "sg:province":"Essex",
    "wof:name":"Bairstow Eves",
    "wof:placetype":"venue"
},
  "geometry": {"coordinates":[0.101574,51.671658],"type":"Point"}
}