{
  "type": "Feature",
  "properties": {
    "iso:country":"GB",
    "sg:address":"Charles Street",
    "sg:city":"Bingley",
    "sg:classifiers":[
        {
            "category":"Organizations",
            "subcategory":"Community Association",
            "type":"Services"
        },
        {
            "category":"Organizations",
            "subcategory":"Membership Organization",
            "type":"Services"
        }
    ],
    "sg:phone":"+44 1274 564477",
    "sg:postcode":"BD16 4LG",
    "sg:province":"West Yorkshire",
    "sg:tags":[
        "club",
        "social"
    ],
    "wof:name":"Masonic Hall",
    "wof:placetype":"venue"
},
  "geometry": {"coordinates":[-1.835349,53.851101],"type":"Point"}
}