{
  "type": "Feature",
  "properties": {
    "addr:full":"Church Landway, Bearsted Maidstone Kent ME14 4LB",
    "addr:postcode":"me14 4lb",
    "iso:country":"GB",
    "sg:address":"Church Landway, Bearsted",
    "sg:city":"Maidstone",
    "sg:classifiers":[
        {
            "category":"Arena",
            "subcategory":"Sports Club",
            "type":"Entertainment"
        }
    ],
    "sg:phone":"+44 1622 736005",
    "sg:postcode":"ME14 4LB",
    "sg:province":"Kent",
    "wof:name":"Bearsted & Thurnham Lawn Tennis Club",
    "wof:placetype":"venue"
},
  "geometry": {"coordinates":[0.5740839839,51.2672576904],"type":"Point"}
}