{
  "type": "Feature",
  "properties": {
    "iso:country":"GB",
    "sg:address":"The Old Rectory Offices, Stoke Abbott",
    "sg:city":"Beaminster",
    "sg:classifiers":[
        {
            "category":"Shopping",
            "subcategory":"Books",
            "type":"Retail Goods"
        },
        {
            "category":"Wholesale",
            "subcategory":"Books, Periodicals, & Newspapers",
            "type":"Manufacturing & Wholesale Goods"
        }
    ],
    "sg:phone":"+44 1308 868118",
    "sg:postcode":"DT8 3JT",
    "sg:province":"Dorset",
    "sg:tags":[
        "publisher"
    ],
    "wof:name":"Thomas Harmsworth Publishing Co",
    "wof:placetype":"venue"
},
  "geometry": {"coordinates":[-2.738894,50.809006],"type":"Point"}
}