{
  "type": "Feature",
  "properties": {
    "iso:country":"GB",
    "sg:address":"Unit 25, 25 Marlow Road",
    "sg:city":"Leicester",
    "sg:classifiers":[
        {
            "category":"Professional",
            "type":"Services"
        },
        {
            "category":"Manufacturing",
            "subcategory":"Wood Products",
            "type":"Manufacturing & Wholesale Goods"
        }
    ],
    "sg:phone":"+44 116 282 6796",
    "sg:postcode":"LE3 2BQ",
    "sg:province":"Leicestershire",
    "sg:tags":[
        "joinery",
        "shopfitters",
        "manufacturer"
    ],
    "wof:name":"Standard Woodworking Ltd",
    "wof:placetype":"venue"
},
  "geometry": {"coordinates":[-1.167129,52.612209],"type":"Point"}
}