{
  "type": "Feature",
  "properties": {
    "addr:full":"8th Floor, 20 Berkeley Square London Greater London W1J 6EQ",
    "addr:housenumber":"8th floor 20",
    "addr:postcode":"w1j 6eq",
    "addr:street":"Berkeley Square",
    "iso:country":"GB",
    "sg:address":"8th Floor, 20 Berkeley Square",
    "sg:city":"London",
    "sg:classifiers":[
        {
            "category":"Professional",
            "subcategory":"Management & Consulting",
            "type":"Services"
        }
    ],
    "sg:phone":"+44 20 7495 5802",
    "sg:postcode":"W1J 6EQ",
    "sg:province":"Greater London",
    "sg:tags":[
        "consultant",
        "business"
    ],
    "wof:name":"Kelmer & Partners Ltd.",
    "wof:placetype":"venue"
},
  "geometry": {"coordinates":[-0.144557,51.508991],"type":"Point"}
}