{
  "type": "Feature",
  "properties": {
    "iso:country":"GB",
    "sg:address":"Castlebank House",
    "sg:city":"Dingwall",
    "sg:classifiers":[
        {
            "category":"Building & Trades",
            "subcategory":"Landscaping Services",
            "type":"Services"
        }
    ],
    "sg:phone":"+44 1349 861610",
    "sg:postcode":"IV15 9HL",
    "sg:province":"Highland",
    "sg:tags":[
        "forestry",
        "tree"
    ],
    "wof:name":"Cornerstone Construction (Highland) Ltd.",
    "wof:placetype":"venue"
},
  "geometry": {"coordinates":[-4.4314479828,57.5961799622],"type":"Point"}
}