{
  "type": "Feature",
  "properties": {
    "iso:country":"GB",
    "sg:address":"82 Coleshill Road",
    "sg:city":"Atherstone",
    "sg:classifiers":[
        {
            "category":"Autos & Motor Vehicles",
            "subcategory":"Auto Supplies",
            "type":"Retail Goods"
        },
        {
            "category":"Shopping",
            "type":"Retail Goods"
        }
    ],
    "sg:phone":"+44 1827 714286",
    "sg:postcode":"CV9 2AD",
    "sg:province":"Leicestershire",
    "sg:tags":[
        "car",
        "part",
        "accessory"
    ],
    "wof:name":"A B Car Spares",
    "wof:placetype":"venue"
},
  "geometry": {"coordinates":[-1.54983,52.573944],"type":"Point"}
}