{
  "type": "Feature",
  "properties": {
    "addr:full":"1st Floor 225 High Street Eastleigh Hampshire SO50 5LX",
    "addr:housenumber":"225",
    "addr:postcode":"so50 5lx",
    "addr:street":"High Street",
    "iso:country":"GB",
    "sg:address":"1st Floor 225 High Street",
    "sg:city":"Eastleigh",
    "sg:classifiers":[
        {
            "category":"Professional",
            "type":"Services"
        }
    ],
    "sg:phone":"+44 23 8045 6149",
    "sg:postcode":"SO50 5LX",
    "sg:province":"Hampshire",
    "sg:tags":[
        "entertainer"
    ],
    "wof:name":"Les Hart (Southampton) Entertainments",
    "wof:placetype":"venue"
},
  "geometry": {"coordinates":[-1.354763,50.963547],"type":"Point"}
}