{
  "type": "Feature",
  "properties": {
    "addr:full":"20 Wintermans Road, Chorlton Cum Hardy Manchester Cheshire M21 7UF",
    "addr:housenumber":"20",
    "addr:postcode":"m21 7uf",
    "addr:street":"Wintermans Road",
    "iso:country":"GB",
    "sg:address":"20 Wintermans Road, Chorlton Cum Hardy",
    "sg:city":"Manchester",
    "sg:classifiers":[
        {
            "category":"Building & Trades",
            "subcategory":"Cleaning & Sanitation",
            "type":"Services"
        }
    ],
    "sg:phone":"+44 161 860 7287",
    "sg:postcode":"M21 7UF",
    "sg:province":"Cheshire",
    "sg:tags":[
        "commercial"
    ],
    "wof:name":"Gleam Window Cleaning Services",
    "wof:placetype":"venue"
},
  "geometry": {"coordinates":[-2.255665,53.434559],"type":"Point"}
}