{
  "type": "Feature",
  "properties": {
    "iso:country":"GB",
    "sg:address":"5-6 Bernard Way",
    "sg:city":"Newport",
    "sg:classifiers":[
        {
            "category":"Home & Garden",
            "subcategory":"Hardware",
            "type":"Retail Goods"
        }
    ],
    "sg:phone":"+44 1983 822711",
    "sg:postcode":"PO30 5YL",
    "sg:province":"Isle of Wight",
    "sg:tags":[
        "equipment",
        "welding"
    ],
    "wof:name":"Weldwise (I O W)",
    "wof:placetype":"venue"
},
  "geometry": {"coordinates":[-1.294539,50.7066],"type":"Point"}
}