{
  "type": "Feature",
  "properties": {
    "addr:full":"43 Holm Road, Crossford Carluke South Lanarkshire ML8 5RG",
    "addr:housenumber":"43",
    "addr:postcode":"ml8 5rg",
    "addr:street":"Holm Road",
    "iso:country":"GB",
    "sg:address":"43 Holm Road, Crossford",
    "sg:city":"Carluke",
    "sg:classifiers":[
        {
            "category":"Banks & Credit Unions",
            "subcategory":"Investment Brokerage",
            "type":"Services"
        }
    ],
    "sg:phone":"+44 1555 860122",
    "sg:postcode":"ML8 5RG",
    "sg:province":"South Lanarkshire",
    "sg:tags":[
        "contractor"
    ],
    "wof:name":"Clyde West Machinery Ring",
    "wof:placetype":"venue"
},
  "geometry": {"coordinates":[-3.870161,55.701855],"type":"Point"}
}