{
  "type": "Feature",
  "properties": {
    "iso:country":"GB",
    "sg:address":"338 Dumbarton Road",
    "sg:city":"Glasgow",
    "sg:classifiers":[
        {
            "category":"Home & Garden",
            "subcategory":"Building Materials",
            "type":"Retail Goods"
        }
    ],
    "sg:phone":"+44 141 339 9201",
    "sg:postcode":"G11 6TG",
    "sg:province":"Glasgow City",
    "sg:tags":[
        "insulation",
        "installers"
    ],
    "wof:name":"Holt Insulation Ltd.",
    "wof:placetype":"venue"
},
  "geometry": {"coordinates":[-4.306653,55.870995],"type":"Point"}
}