{
  "type": "Feature",
  "properties": {
    "iso:country":"GB",
    "sg:address":"117 Restalrig Avenue",
    "sg:city":"Edinburgh",
    "sg:classifiers":[
        {
            "category":"Professional",
            "subcategory":"Engineering",
            "type":"Services"
        }
    ],
    "sg:postcode":"EH7 6PN",
    "sg:province":"City of Edinburgh",
    "sg:tags":[
        "contractor",
        "electrical",
        "engineer"
    ],
    "wof:name":"Enterprise Electrics",
    "wof:placetype":"venue"
},
  "geometry": {"coordinates":[-3.145941,55.957169],"type":"Point"}
}