{
  "type": "Feature",
  "properties": {
    "addr:full":"83 Victoria Rd Chislehurst Kent BR7 6DE",
    "addr:housenumber":"83",
    "addr:postcode":"br7 6de",
    "addr:street":"Victoria Rd",
    "iso:country":"GB",
    "sg:address":"83 Victoria Rd",
    "sg:city":"Chislehurst",
    "sg:classifiers":[
        {
            "category":"Professional",
            "subcategory":"Management & Consulting",
            "type":"Services"
        }
    ],
    "sg:postcode":"BR7 6DE",
    "sg:province":"Kent",
    "sg:tags":[
        "marketing",
        "consultant"
    ],
    "wof:name":"Marcomm",
    "wof:placetype":"venue"
},
  "geometry": {"coordinates":[0.061733,51.4219436646],"type":"Point"}
}