{
  "type": "Feature",
  "properties": {
    "addr:full":"6 Duckpool Rd Newport Newport NP19 8FH",
    "addr:housenumber":"6",
    "addr:postcode":"np19 8fh",
    "addr:street":"Duckpool Rd",
    "iso:country":"GB",
    "sg:address":"6 Duckpool Rd",
    "sg:city":"Newport",
    "sg:classifiers":[
        {
            "category":"Transit Center",
            "subcategory":"Freight",
            "type":"Transportation"
        }
    ],
    "sg:postcode":"NP19 8FH",
    "sg:province":"Newport",
    "sg:tags":[
        "shop",
        "craft",
        "centre"
    ],
    "wof:name":"Atyniad",
    "wof:placetype":"venue"
},
  "geometry": {"coordinates":[-2.9795210361,51.5904693604],"type":"Point"}
}