{
  "type": "Feature",
  "properties": {
    "addr:full":"The Quay, Crown Quay Lane Sittingbourne Kent ME10 3JN",
    "addr:postcode":"me10 3jn",
    "addr:street":"The Quay Crown Quay Lane",
    "iso:country":"GB",
    "sg:address":"The Quay, Crown Quay Lane",
    "sg:city":"Sittingbourne",
    "sg:classifiers":[
        {
            "category":"Organizations",
            "subcategory":"Community Association",
            "type":"Services"
        }
    ],
    "sg:phone":"+44 1795 471376",
    "sg:postcode":"ME10 3JN",
    "sg:province":"Kent",
    "sg:tags":[
        "co-operatives",
        "society",
        "housing",
        "trust"
    ],
    "sg:website":"http://www.echg.org.uk",
    "wof:name":"English Churches Housing Group",
    "wof:placetype":"venue"
},
  "geometry": {"coordinates":[0.741155982,51.3449325562],"type":"Point"}
}