{
  "type": "Feature",
  "properties": {
    "addr:full":"18 Sparkle Street Manchester Greater Manchester M1 2NA",
    "addr:housenumber":"18",
    "addr:postcode":"m1 2na",
    "addr:street":"Sparkle Street",
    "iso:country":"GB",
    "sg:address":"18 Sparkle Street",
    "sg:city":"Manchester",
    "sg:classifiers":[
        {
            "category":"Professional",
            "subcategory":"Management & Consulting",
            "type":"Services"
        }
    ],
    "sg:phone":"+44 161 273 3435",
    "sg:postcode":"M1 2NA",
    "sg:province":"Greater Manchester",
    "sg:tags":[
        "music"
    ],
    "wof:name":"Potential Development",
    "wof:placetype":"venue"
},
  "geometry": {"coordinates":[-2.228965044,53.4786453247],"type":"Point"}
}