{
  "type": "Feature",
  "properties": {
    "addr:full":"Tudor House, Hibbert Road, Bray Maidenhead Berkshire SL6 2AD",
    "addr:postcode":"sl6 2ad",
    "addr:street":"Hibbert Road",
    "iso:country":"GB",
    "sg:address":"Tudor House, Hibbert Road, Bray",
    "sg:city":"Maidenhead",
    "sg:classifiers":[
        {
            "category":"Professional",
            "type":"Services"
        }
    ],
    "sg:phone":"+44 1628 624688",
    "sg:postcode":"SL6 2AD",
    "sg:province":"Berkshire",
    "sg:tags":[
        "entertainer"
    ],
    "wof:name":"Lee Summers",
    "wof:placetype":"venue"
},
  "geometry": {"coordinates":[-0.70148,51.507195],"type":"Point"}
}