{
  "type": "Feature",
  "properties": {
    "addr:full":"The White House, Swan Lane Ipswich Suffolk IP6 9AH",
    "addr:postcode":"ip6 9ah",
    "addr:street":"Swan Lane",
    "iso:country":"GB",
    "sg:address":"The White House, Swan Lane",
    "sg:city":"Ipswich",
    "sg:classifiers":[
        {
            "category":"Retail",
            "subcategory":"Repair Shop",
            "type":"Services"
        }
    ],
    "sg:phone":"+44 1473 219060",
    "sg:postcode":"IP6 9AH",
    "sg:province":"Suffolk",
    "sg:tags":[
        "furniture"
    ],
    "wof:name":"D G Grabham",
    "wof:placetype":"venue"
},
  "geometry": {"coordinates":[1.1711629629,52.0859565735],"type":"Point"}
}