{
  "type": "Feature",
  "properties": {
    "iso:country":"GB",
    "sg:address":"8 Winsford Way, Sealand Industrial Estate",
    "sg:city":"Chester",
    "sg:classifiers":[
        {
            "category":"Building & Trades",
            "subcategory":"Cleaning & Sanitation",
            "type":"Services"
        }
    ],
    "sg:phone":"+44 1244 372111",
    "sg:postcode":"CH1 4NL",
    "sg:province":"Cheshire",
    "sg:tags":[
        "hygiene",
        "cleansing"
    ],
    "wof:name":"Initial Textile Services",
    "wof:placetype":"venue"
},
  "geometry": {"coordinates":[-2.917064,53.193176],"type":"Point"}
}