{
  "type": "Feature",
  "properties": {
    "addr:full":"469 Stratford Road, Sparkhill Birmingham West Midlands B11 4LD",
    "addr:housenumber":"469",
    "addr:postcode":"b11 4ld",
    "addr:street":"Stratford Road",
    "iso:country":"GB",
    "sg:address":"469 Stratford Road, Sparkhill",
    "sg:city":"Birmingham",
    "sg:classifiers":[
        {
            "category":"Shopping",
            "subcategory":"Jewelry",
            "type":"Retail Goods"
        },
        {
            "category":"Shopping",
            "subcategory":"Comic Books",
            "type":"Retail Goods"
        }
    ],
    "sg:phone":"+44 121 772 7574",
    "sg:postcode":"B11 4LD",
    "sg:province":"West Midlands",
    "sg:tags":[
        "jeweller",
        "sale",
        "jewellery"
    ],
    "wof:name":"Mohanlal Bhimji Pattni",
    "wof:placetype":"venue"
},
  "geometry": {"coordinates":[-1.8673789501,52.4549331665],"type":"Point"}
}