{
  "type": "Feature",
  "properties": {
    "addr:full":"97 Meadow Street Preston Lancashire PR1 1TS",
    "addr:housenumber":"97",
    "addr:postcode":"pr1 1ts",
    "addr:street":"Meadow Street",
    "iso:country":"GB",
    "sg:address":"97 Meadow Street",
    "sg:city":"Preston",
    "sg:classifiers":[
        {
            "category":"Home & Garden",
            "subcategory":"Building Materials",
            "type":"Retail Goods"
        }
    ],
    "sg:phone":"+44 1772 203249",
    "sg:postcode":"PR1 1TS",
    "sg:province":"Lancashire",
    "sg:tags":[
        "wire",
        "cable"
    ],
    "wof:name":"Hanna Electrical Supplies",
    "wof:placetype":"venue"
},
  "geometry": {"coordinates":[-2.693379,53.764404],"type":"Point"}
}