{
  "type": "Feature",
  "properties": {
    "iso:country":"GB",
    "sg:address":"20 Jermyn Avenue",
    "sg:city":"Bury St Edmunds",
    "sg:classifiers":[
        {
            "category":"Building & Trades",
            "subcategory":"Construction",
            "type":"Services"
        }
    ],
    "sg:phone":"+44 1284 769227",
    "sg:postcode":"IP32 7LJ",
    "sg:province":"Suffolk",
    "sg:tags":[
        "roofing"
    ],
    "wof:name":"Ian W Wallis Roofing",
    "wof:placetype":"venue"
},
  "geometry": {"coordinates":[0.7495849729,52.2468223572],"type":"Point"}
}