{
  "type": "Feature",
  "properties": {
    "addr:full":"20 Duke Street Huntly Aberdeenshire AB54 8DL",
    "addr:housenumber":"20",
    "addr:postcode":"ab54 8dl",
    "addr:street":"Duke Street",
    "iso:country":"GB",
    "sg:address":"20 Duke Street",
    "sg:city":"Huntly",
    "sg:classifiers":[
        {
            "category":"Shopping",
            "subcategory":"Gifts & Souvenirs",
            "type":"Retail Goods"
        }
    ],
    "sg:phone":"+44 1466 792789",
    "sg:postcode":"AB54 8DL",
    "sg:province":"Aberdeenshire",
    "sg:tags":[
        "poster",
        "card"
    ],
    "wof:name":"Discovery",
    "wof:placetype":"venue"
},
  "geometry": {"coordinates":[-2.7852020264,57.4473876953],"type":"Point"}
}