{
  "type": "Feature",
  "properties": {
    "addr:full":"1c Aberdeen Studios, 22 Highbury Gro London Greater London N5 2DQ",
    "addr:housenumber":"1c;22",
    "addr:postcode":"gro;n5 2dq",
    "addr:street":"Highbury",
    "iso:country":"GB",
    "sg:address":"1c Aberdeen Studios, 22 Highbury Gro",
    "sg:city":"London",
    "sg:classifiers":[
        {
            "category":"Organizations",
            "subcategory":"Non-profit Organization",
            "type":"Services"
        }
    ],
    "sg:phone":"+44 20 7354 8318",
    "sg:postcode":"N5 2DQ",
    "sg:province":"Greater London",
    "sg:tags":[
        "organisation",
        "voluntary",
        "charity"
    ],
    "wof:name":"Advisory Centre for Education (A C E) Ltd.",
    "wof:placetype":"venue"
},
  "geometry": {"coordinates":[-0.09702,51.550369],"type":"Point"}
}