{
  "type": "Feature",
  "properties": {
    "addr:full":"Newman House, Russell Parade, Golders Green Road London Greater London NW11 9NN",
    "addr:postcode":"nw11 9nn",
    "addr:street":"Russell Parade Golders Green Road",
    "iso:country":"GB",
    "sg:address":"Newman House, Russell Parade, Golders Green Road",
    "sg:city":"London",
    "sg:classifiers":[
        {
            "category":"Professional",
            "subcategory":"Lawyer & Legal Services",
            "type":"Services"
        }
    ],
    "sg:phone":"+44 20 8458 9266",
    "sg:postcode":"NW11 9NN",
    "sg:province":"Greater London",
    "sg:tags":[
        "solicitor"
    ],
    "wof:name":"Pearlman Neuberger & Co.",
    "wof:placetype":"venue"
},
  "geometry": {"coordinates":[-0.20694,51.577679],"type":"Point"}
}