{
  "type": "Feature",
  "properties": {
    "iso:country":"GB",
    "sg:address":"174 Northenden Rd",
    "sg:city":"Sale",
    "sg:classifiers":[
        {
            "category":"Shopping",
            "type":"Retail Goods"
        }
    ],
    "sg:phone":"+44 161 969 1644",
    "sg:postcode":"M33 2SR",
    "sg:province":"Cheshire",
    "sg:tags":[
        "part",
        "accessory"
    ],
    "wof:name":"Motorland",
    "wof:placetype":"venue"
},
  "geometry": {"coordinates":[-2.303314,53.419674],"type":"Point"}
}