{
  "type": "Feature",
  "properties": {
    "iso:country":"GB",
    "sg:address":"134 Raven Meols Lane, Formby",
    "sg:city":"Liverpool",
    "sg:classifiers":[
        {
            "category":"Building & Trades",
            "subcategory":"Construction",
            "type":"Services"
        }
    ],
    "sg:phone":"+44 1704 877765",
    "sg:postcode":"L37 4DQ",
    "sg:province":"Lancashire",
    "sg:tags":[
        "joiner",
        "carpenter"
    ],
    "wof:name":"Gordon V Aindow",
    "wof:placetype":"venue"
},
  "geometry": {"coordinates":[-3.057628,53.550747],"type":"Point"}
}