{
  "type": "Feature",
  "properties": {
    "addr:full":"163e Plashet Grove East Ham Greater London E6 1AA",
    "addr:housenumber":"163e",
    "addr:postcode":"e6 1aa",
    "addr:street":"Plashet Grove",
    "iso:country":"GB",
    "sg:address":"163e Plashet Grove",
    "sg:city":"East Ham",
    "sg:classifiers":[
        {
            "category":"Shopping",
            "type":"Retail Goods"
        }
    ],
    "sg:phone":"+44 20 8471 7837",
    "sg:postcode":"E6 1AA",
    "sg:province":"Greater London",
    "sg:tags":[
        "part",
        "accessory"
    ],
    "wof:name":"C B A Unicar Parts",
    "wof:placetype":"venue"
},
  "geometry": {"coordinates":[0.0417580009,51.5383262634],"type":"Point"}
}