{
  "type": "Feature",
  "properties": {
    "iso:country":"GB",
    "sg:address":"St Olaf Street, Lerwick",
    "sg:city":"Shetland",
    "sg:classifiers":[
        {
            "category":"Personal",
            "type":"Services"
        },
        {
            "category":"Professional",
            "subcategory":"Lawyer & Legal Services",
            "type":"Services"
        }
    ],
    "sg:phone":"+44 1595 692070",
    "sg:postcode":"ZE1 0ES",
    "sg:province":"Shetland Islands",
    "sg:tags":[
        "advice",
        "counselling"
    ],
    "wof:name":"Shetland Women's Aid",
    "wof:placetype":"venue"
},
  "geometry": {"coordinates":[-1.170289,60.144829],"type":"Point"}
}