{
  "type": "Feature",
  "properties": {
    "addr:full":"Duchy, Kelly Bray Callington Cornwall PL17 8EX",
    "addr:postcode":"pl17 8ex",
    "iso:country":"GB",
    "sg:address":"Duchy, Kelly Bray",
    "sg:city":"Callington",
    "sg:classifiers":[
        {
            "category":"Professional",
            "subcategory":"Art Services",
            "type":"Services"
        }
    ],
    "sg:phone":"+44 1579 384533",
    "sg:postcode":"PL17 8EX",
    "sg:province":"Cornwall",
    "sg:tags":[
        "picture",
        "restoration"
    ],
    "wof:name":"Art Frame Products",
    "wof:placetype":"venue"
},
  "geometry": {"coordinates":[-4.3160738945,50.5203666687],"type":"Point"}
}