{
  "type": "Feature",
  "properties": {
    "iso:country":"GB",
    "sg:address":"5 Mordaunt St",
    "sg:city":"Glasgow",
    "sg:classifiers":[
        {
            "category":"Building & Trades",
            "subcategory":"Electrical",
            "type":"Services"
        }
    ],
    "sg:phone":"+44 141 554 4005",
    "sg:postcode":"G40 3JZ",
    "sg:province":"Glasgow City",
    "sg:tags":[
        "consultant",
        "lighting"
    ],
    "wof:name":"Total Quality Lighting Ltd",
    "wof:placetype":"venue"
},
  "geometry": {"coordinates":[-4.214335,55.844784],"type":"Point"}
}