{
  "type": "Feature",
  "properties": {
    "iso:country":"GB",
    "sg:address":"Abbey Close",
    "sg:city":"Abingdon",
    "sg:classifiers":[
        {
            "category":"Education",
            "subcategory":"Music School",
            "type":"Public Place"
        }
    ],
    "sg:phone":"+44 1235 533633",
    "sg:postcode":"OX14 3JE",
    "sg:province":"Oxfordshire",
    "wof:name":"Abingdon Music Centre",
    "wof:placetype":"venue"
},
  "geometry": {"coordinates":[-1.280449,51.670666],"type":"Point"}
}