{
  "type": "Feature",
  "properties": {
    "addr:full":"327 Long Rd Canvey Island Essex SS8 0JQ",
    "addr:housenumber":"327",
    "addr:postcode":"ss8 0jq",
    "addr:street":"Long Rd",
    "iso:country":"GB",
    "sg:address":"327 Long Rd",
    "sg:city":"Canvey Island",
    "sg:classifiers":[
        {
            "category":"Professional",
            "subcategory":"Management & Consulting",
            "type":"Services"
        }
    ],
    "sg:phone":"+44 1268 696222",
    "sg:postcode":"SS8 0JQ",
    "sg:province":"Essex",
    "sg:tags":[
        "consultant",
        "business"
    ],
    "wof:name":"Tipton Consultants Ltd",
    "wof:placetype":"venue"
},
  "geometry": {"coordinates":[0.5707479715,51.519733429],"type":"Point"}
}