{
  "type": "Feature",
  "properties": {
    "addr:full":"2 Old Hall Gardens, Brooke Norwich Norfolk NR15 1JZ",
    "addr:housenumber":"2",
    "addr:postcode":"nr15 1jz",
    "addr:street":"Old Hall Gardens",
    "iso:country":"GB",
    "sg:address":"2 Old Hall Gardens, Brooke",
    "sg:city":"Norwich",
    "sg:classifiers":[
        {
            "category":"Real Estate",
            "subcategory":"Architect",
            "type":"Services"
        }
    ],
    "sg:postcode":"NR15 1JZ",
    "sg:province":"Norfolk",
    "sg:tags":[
        "architectural"
    ],
    "wof:name":"Property Projects (Uk) Ltd",
    "wof:placetype":"venue"
},
  "geometry": {"coordinates":[1.381685,52.546394],"type":"Point"}
}