{
  "type": "Feature",
  "properties": {
    "addr:full":"Suite 8, Westminster Palace Gdn(s), 1-7 Artillery Row London Greater London SW1P 1RL",
    "addr:housenumber":"suite 8;1-7",
    "addr:postcode":"sw1p 1rl",
    "addr:street":"Westminster Palace Gdn S;Artillery Row",
    "iso:country":"GB",
    "sg:address":"Suite 8, Westminster Palace Gdn(s), 1-7 Artillery Row",
    "sg:city":"London",
    "sg:classifiers":[
        {
            "category":"Professional",
            "subcategory":"Accounting & Tax Preparation",
            "type":"Services"
        }
    ],
    "sg:phone":"+44 20 7222 6220",
    "sg:postcode":"SW1P 1RL",
    "sg:province":"Greater London",
    "sg:tags":[
        "accountant"
    ],
    "wof:name":"L & H Organization Ltd",
    "wof:placetype":"venue"
},
  "geometry": {"coordinates":[-0.13489,51.497002],"type":"Point"}
}