{
  "type": "Feature",
  "properties": {
    "iso:country":"GB",
    "sg:address":"14 Okeburn Road",
    "sg:city":"London",
    "sg:classifiers":[
        {
            "category":"Wholesale",
            "subcategory":"Construction Materials",
            "type":"Manufacturing & Wholesale Goods"
        }
    ],
    "sg:postcode":"SW17 8NJ",
    "sg:province":"Greater London",
    "sg:tags":[
        "lift"
    ],
    "wof:name":"M D Mobile Repairs Ltd.",
    "wof:placetype":"venue"
},
  "geometry": {"coordinates":[-0.157289,51.428032],"type":"Point"}
}