{
  "type": "Feature",
  "properties": {
    "iso:country":"GB",
    "sg:address":"Fairfield Cottage, Charmouth Road",
    "sg:city":"Lyme Regis",
    "sg:classifiers":[
        {
            "category":"Real Estate",
            "subcategory":"Real Estate Operator",
            "type":"Services"
        },
        {
            "category":"Travel",
            "subcategory":"Hotels & Motels",
            "type":"Entertainment"
        }
    ],
    "sg:phone":"+44 1297 445362",
    "sg:postcode":"DT7 3HH",
    "sg:province":"Devon",
    "sg:tags":[
        "letting",
        "self",
        "agent",
        "catering"
    ],
    "wof:name":"Seven Springs",
    "wof:placetype":"venue"
},
  "geometry": {"coordinates":[-2.943626,50.727894],"type":"Point"}
}