{
  "type": "Feature",
  "properties": {
    "iso:country":"GB",
    "sg:address":"St Michaels House, 14 Market Cross",
    "sg:city":"Malmesbury",
    "sg:classifiers":[
        {
            "category":"Organizations",
            "subcategory":"Non-profit Organization",
            "type":"Services"
        }
    ],
    "sg:phone":"+44 1666 822873",
    "sg:postcode":"SN16 9AS",
    "sg:province":"Wiltshire",
    "sg:tags":[
        "organisation",
        "voluntary",
        "charity"
    ],
    "wof:name":"Waverley Trust",
    "wof:placetype":"venue"
},
  "geometry": {"coordinates":[-2.057234,51.603401],"type":"Point"}
}