{
  "type": "Feature",
  "properties": {
    "addr:full":"13 Queen Square Leeds West Yorkshire LS2 8AJ",
    "addr:housenumber":"13",
    "addr:postcode":"ls2 8aj",
    "addr:street":"Queen Square Leeds West",
    "iso:country":"GB",
    "sg:address":"13 Queen Square",
    "sg:city":"Leeds",
    "sg:classifiers":[
        {
            "category":"Professional",
            "subcategory":"Accounting & Tax Preparation",
            "type":"Services"
        }
    ],
    "sg:postcode":"LS2 8AJ",
    "sg:province":"West Yorkshire",
    "sg:tags":[
        "accountant"
    ],
    "wof:name":"Hall Hayes & Co",
    "wof:placetype":"venue"
},
  "geometry": {"coordinates":[-1.544593,53.803627],"type":"Point"}
}