{
  "type": "Feature",
  "properties": {
    "addr:full":"2-4 Union Street Blyth Northumberland NE24 2DX",
    "addr:housenumber":"2-4",
    "addr:postcode":"ne24 2dx",
    "addr:street":"Union Street;Northumberland",
    "iso:country":"GB",
    "sg:address":"2-4 Union Street",
    "sg:city":"Blyth",
    "sg:classifiers":[
        {
            "category":"Shopping",
            "subcategory":"News",
            "type":"Retail Goods"
        }
    ],
    "sg:phone":"+44 1670 353273",
    "sg:postcode":"NE24 2DX",
    "sg:province":"Northumberland",
    "sg:tags":[
        "newsagent"
    ],
    "wof:name":"Mackenzie News",
    "wof:placetype":"venue"
},
  "geometry": {"coordinates":[-1.5077389479,55.127281189],"type":"Point"}
}