{
  "type": "Feature",
  "properties": {
    "addr:full":"4 Harley Street London Greater London W1G 9PB",
    "addr:housenumber":"4",
    "addr:postcode":"w1g 9pb",
    "addr:street":"Harley Street",
    "iso:country":"GB",
    "sg:address":"4 Harley Street",
    "sg:city":"London",
    "sg:classifiers":[
        {
            "category":"Shopping",
            "subcategory":"Pharmacy",
            "type":"Retail Goods"
        }
    ],
    "sg:phone":"+44 20 7631 0080",
    "sg:postcode":"W1G 9PB",
    "sg:province":"Greater London",
    "sg:tags":[
        "pharmaceutical"
    ],
    "wof:name":"Merck Generics Ltd.",
    "wof:placetype":"venue"
},
  "geometry": {"coordinates":[-0.145886,51.517132],"type":"Point"}
}