{
  "type": "Feature",
  "properties": {
    "addr:full":"56 Grey Street Newcastle-upon-tyne Tyne and Wear NE1 6AH",
    "addr:housenumber":"56",
    "addr:postcode":"ne1 6ah",
    "addr:street":"Grey Street",
    "iso:country":"GB",
    "sg:address":"56 Grey Street",
    "sg:city":"Newcastle-upon-tyne",
    "sg:classifiers":[
        {
            "category":"Professional",
            "subcategory":"Employment Agencies",
            "type":"Services"
        }
    ],
    "sg:phone":"+44 191 232 1222",
    "sg:postcode":"NE1 6AH",
    "sg:province":"Tyne and Wear",
    "sg:tags":[
        "consultant",
        "recruitment"
    ],
    "wof:name":"Northern Recruitment Group Ltd",
    "wof:placetype":"venue"
},
  "geometry": {"coordinates":[-1.611399,54.971737],"type":"Point"}
}