{
  "type": "Feature",
  "properties": {
    "addr:full":"Bitterne Park Surgery, 28 Cobden Av Southampton Hampshire SO18 1BW",
    "addr:housenumber":"28",
    "addr:postcode":"so18 1bw",
    "addr:street":"Cobden Av",
    "iso:country":"GB",
    "sg:address":"Bitterne Park Surgery, 28 Cobden Av",
    "sg:city":"Southampton",
    "sg:classifiers":[
        {
            "category":"Health Services",
            "subcategory":"Doctor",
            "type":"Services"
        }
    ],
    "sg:phone":"+44 23 8058 5655",
    "sg:postcode":"SO18 1BW",
    "sg:province":"Hampshire",
    "sg:tags":[
        "practitioners"
    ],
    "wof:name":"Littlejohns, P A",
    "wof:placetype":"venue"
},
  "geometry": {"coordinates":[-1.3742300272,50.9228401184],"type":"Point"}
}