{
  "type": "Feature",
  "properties": {
    "addr:full":"198 Euston Road Morecambe Lancashire LA4 5LE",
    "addr:housenumber":"198",
    "addr:postcode":"la4 5le",
    "addr:street":"Euston Road",
    "iso:country":"GB",
    "sg:address":"198 Euston Road",
    "sg:city":"Morecambe",
    "sg:classifiers":[
        {
            "category":"Health Services",
            "subcategory":"Optometrist",
            "type":"Services"
        }
    ],
    "sg:phone":"+44 1524 418822",
    "sg:postcode":"LA4 5LE",
    "sg:province":"Lancashire",
    "sg:tags":[
        "optician"
    ],
    "wof:name":"Moon & Coxhill",
    "wof:placetype":"venue"
},
  "geometry": {"coordinates":[-2.8587698936,54.0716590881],"type":"Point"}
}