{
  "type": "Feature",
  "properties": {
    "iso:country":"GB",
    "sg:address":"12 Tontine Hill, Ironbridge",
    "sg:city":"Telford",
    "sg:classifiers":[
        {
            "category":"Food & Beverages",
            "subcategory":"Candy",
            "type":"Retail Goods"
        }
    ],
    "sg:phone":"+44 1952 432428",
    "sg:postcode":"TF8 7AL",
    "sg:province":"Shropshire",
    "sg:tags":[
        "confectioner"
    ],
    "wof:name":"Aroma Round",
    "wof:placetype":"venue"
},
  "geometry": {"coordinates":[-2.485319,52.627918],"type":"Point"}
}