{
  "type": "Feature",
  "properties": {
    "iso:country":"GB",
    "sg:address":"4 The Sleeve",
    "sg:city":"Leek",
    "sg:classifiers":[
        {
            "category":"Building & Trades",
            "subcategory":"Cleaning & Sanitation",
            "type":"Services"
        }
    ],
    "sg:phone":"+44 1538 385367",
    "sg:postcode":"ST13 8HR",
    "sg:province":"Staffordshire",
    "sg:tags":[
        "sweep",
        "chimney"
    ],
    "wof:name":"A.A Chesters Electric Chimney Sweep",
    "wof:placetype":"venue"
},
  "geometry": {"coordinates":[-2.0396990776,53.1005325317],"type":"Point"}
}