{
  "type": "Feature",
  "properties": {
    "iso:country":"GB",
    "sg:address":"2b The Square",
    "sg:city":"Sawbridgeworth",
    "sg:classifiers":[
        {
            "category":"Health Services",
            "subcategory":"Clinic",
            "type":"Services"
        }
    ],
    "sg:phone":"+44 1279 722339",
    "sg:postcode":"CM21 9AE",
    "sg:province":"Essex",
    "sg:tags":[
        "nh"
    ],
    "wof:name":"Sawbridgeworth Health Clinic",
    "wof:placetype":"venue"
},
  "geometry": {"coordinates":[0.151055,51.81155],"type":"Point"}
}