{
  "type": "Feature",
  "properties": {
    "addr:full":"Dealston Road, Barrhead Glasgow East Ayrshire G78 1NL",
    "addr:postcode":"g78 1nl",
    "addr:street":"Dealston Road",
    "iso:country":"GB",
    "sg:address":"Dealston Road, Barrhead",
    "sg:city":"Glasgow",
    "sg:classifiers":[
        {
            "category":"Mining & Drilling",
            "type":"Manufacturing & Wholesale Goods"
        }
    ],
    "sg:phone":"+44 141 881 9421",
    "sg:postcode":"G78 1NL",
    "sg:province":"East Ayrshire",
    "sg:tags":[
        "contractor"
    ],
    "wof:name":"Rocklift Ltd.",
    "wof:placetype":"venue"
},
  "geometry": {"coordinates":[-4.4044981003,55.7953147888],"type":"Point"}
}