{
  "type": "Feature",
  "properties": {
    "addr:full":"Woodham Rd, Aycliffe Indust Est Newton Aycliffe Durham DL5 6HT",
    "addr:postcode":"dl5 6ht",
    "addr:street":"Woodham Rd;Indust",
    "iso:country":"GB",
    "sg:address":"Woodham Rd, Aycliffe Indust Est",
    "sg:city":"Newton Aycliffe",
    "sg:classifiers":[
        {
            "category":"Retail",
            "subcategory":"Auto Repair",
            "type":"Services"
        }
    ],
    "sg:phone":"+44 1325 317731",
    "sg:postcode":"DL5 6HT",
    "sg:province":"Durham",
    "sg:tags":[
        "bodybuilder",
        "repairer"
    ],
    "wof:name":"Aycliffe Paint & Body Ltd",
    "wof:placetype":"venue"
},
  "geometry": {"coordinates":[-1.5686839819,54.6049537659],"type":"Point"}
}