{
  "type": "Feature",
  "properties": {
    "addr:full":"Eaglescliffe Logistics Centre, Durham Lane, Eaglescliffe Stockton-on-tees Durham TS16 0RW",
    "addr:postcode":"ts16 0rw",
    "addr:street":"Durham Lane",
    "iso:country":"GB",
    "sg:address":"Eaglescliffe Logistics Centre, Durham Lane, Eaglescliffe",
    "sg:city":"Stockton-on-tees",
    "sg:classifiers":[
        {
            "category":"Utilities",
            "type":"Services"
        }
    ],
    "sg:phone":"+44 1642 881088",
    "sg:postcode":"TS16 0RW",
    "sg:province":"Durham",
    "sg:tags":[
        "internet"
    ],
    "wof:name":"Mi International Ltd.",
    "wof:placetype":"venue"
},
  "geometry": {"coordinates":[-1.347854,54.528481],"type":"Point"}
}