{
  "type": "Feature",
  "properties": {
    "addr:full":"Cupar Rd, Pitlessie Cupar Fife KY15 7SU",
    "addr:postcode":"ky15 7su",
    "addr:street":"Cupar Rd",
    "iso:country":"GB",
    "sg:address":"Cupar Rd, Pitlessie",
    "sg:city":"Cupar",
    "sg:classifiers":[
        {
            "category":"Travel",
            "subcategory":"Hotels & Motels",
            "type":"Entertainment"
        }
    ],
    "sg:phone":"+44 1337 830595",
    "sg:postcode":"KY15 7SU",
    "sg:province":"Fife",
    "wof:name":"Village Inn",
    "wof:placetype":"venue"
},
  "geometry": {"coordinates":[-3.115149,56.256054],"type":"Point"}
}