{
  "type": "Feature",
  "properties": {
    "addr:full":"11a Blencathra Street Keswick Cumbria CA12 4HP",
    "addr:housenumber":"11a",
    "addr:postcode":"ca12 4hp",
    "addr:street":"Blencathra Street",
    "iso:country":"GB",
    "sg:address":"11a Blencathra Street",
    "sg:city":"Keswick",
    "sg:classifiers":[
        {
            "category":"Professional",
            "subcategory":"Engineering",
            "type":"Services"
        }
    ],
    "sg:phone":"+44 17687 73159",
    "sg:postcode":"CA12 4HP",
    "sg:province":"Cumbria",
    "sg:tags":[
        "contractor",
        "electrical",
        "engineer"
    ],
    "wof:name":"Shu-le-Crow Engineering",
    "wof:placetype":"venue"
},
  "geometry": {"coordinates":[-3.0477089882,54.612071991],"type":"Point"}
}