{
  "type": "Feature",
  "properties": {
    "addr:full":", Daviot Inverness Highland IV2 5XQ",
    "addr:postcode":"iv2 5xq",
    "addr:street":"Daviot Inverness",
    "iso:country":"GB",
    "sg:address":", Daviot",
    "sg:city":"Inverness",
    "sg:classifiers":[
        {
            "category":"Travel",
            "subcategory":"Hotels & Motels",
            "type":"Entertainment"
        }
    ],
    "sg:phone":"+44 1463 772208",
    "sg:postcode":"IV2 5XQ",
    "sg:province":"Highland",
    "sg:tags":[
        "house",
        "guest"
    ],
    "wof:name":"Torguish Guest House",
    "wof:placetype":"venue"
},
  "geometry": {"coordinates":[-4.2136278152,57.4631767273],"type":"Point"}
}