{
  "type": "Feature",
  "properties": {
    "iso:country":"GB",
    "sg:address":"175 Balmoral Drive",
    "sg:city":"Borehamwood",
    "sg:classifiers":[
        {
            "category":"Real Estate",
            "subcategory":"Real Estate Agent",
            "type":"Services"
        }
    ],
    "sg:postcode":"WD6 2QP",
    "sg:province":"Hertfordshire",
    "wof:name":"Threshold Properties Ltd",
    "wof:placetype":"venue"
},
  "geometry": {"coordinates":[-0.255308,51.649399],"type":"Point"}
}