{
  "type": "Feature",
  "properties": {
    "addr:full":"25 Templar Rd Oxford Oxfordshire OX2 8LR",
    "addr:housenumber":"25",
    "addr:postcode":"ox2 8lr",
    "addr:street":"Templar Rd",
    "iso:country":"GB",
    "sg:address":"25 Templar Rd",
    "sg:city":"Oxford",
    "sg:classifiers":[
        {
            "category":"Professional",
            "subcategory":"Management & Consulting",
            "type":"Services"
        }
    ],
    "sg:phone":"+44 1865 428426",
    "sg:postcode":"OX2 8LR",
    "sg:province":"Oxfordshire",
    "sg:tags":[
        "consultant",
        "business"
    ],
    "wof:name":"Oxford Development Centre The",
    "wof:placetype":"venue"
},
  "geometry": {"coordinates":[-1.267975,51.790646],"type":"Point"}
}