{
  "type": "Feature",
  "properties": {
    "addr:full":"146 Bruntsfield Place Edinburgh City of Edinburgh EH10 4ER",
    "addr:housenumber":"146",
    "addr:postcode":"eh10 4er",
    "addr:street":"Bruntsfield Place Edinburgh",
    "iso:country":"GB",
    "sg:address":"146 Bruntsfield Place",
    "sg:city":"Edinburgh",
    "sg:classifiers":[
        {
            "category":"Shopping",
            "subcategory":"Florist",
            "type":"Retail Goods"
        }
    ],
    "sg:phone":"+44 800 298 9497",
    "sg:postcode":"EH10 4ER",
    "sg:province":"City of Edinburgh",
    "wof:name":"Honeysuckle",
    "wof:placetype":"venue"
},
  "geometry": {"coordinates":[-3.208382,55.936657],"type":"Point"}
}