{
  "type": "Feature",
  "properties": {
    "addr:full":"57-61 Grahams Road Falkirk Falkirk FK2 7DJ",
    "addr:housenumber":"57-61",
    "addr:postcode":"fk2 7dj",
    "addr:street":"Grahams Road",
    "iso:country":"GB",
    "sg:address":"57-61 Grahams Road",
    "sg:city":"Falkirk",
    "sg:classifiers":[
        {
            "category":"Shopping",
            "subcategory":"Baby Store",
            "type":"Retail Goods"
        },
        {
            "category":"Shopping",
            "subcategory":"Bicycles & Sporting Goods",
            "type":"Retail Goods"
        }
    ],
    "sg:phone":"+44 1324 621961",
    "sg:postcode":"FK2 7DJ",
    "sg:province":"Falkirk",
    "sg:tags":[
        "shop",
        "nursery",
        "cycle",
        "accessory"
    ],
    "wof:name":"Malleys Cycle & Pram Store",
    "wof:placetype":"venue"
},
  "geometry": {"coordinates":[-3.7841560841,56.0054779053],"type":"Point"}
}