{
  "type": "Feature",
  "properties": {
    "addr:full":"Wallbrook Court, Rotherwas Industrial Estate Hereford Herefordshire HR2 6JG",
    "addr:housenumber":"estate",
    "addr:postcode":"hr2 6jg",
    "addr:street":"Wallbrook;Industrial",
    "iso:country":"GB",
    "sg:address":"Wallbrook Court, Rotherwas Industrial Estate",
    "sg:city":"Hereford",
    "sg:classifiers":[
        {
            "category":"Professional",
            "subcategory":"Engineering",
            "type":"Services"
        }
    ],
    "sg:postcode":"HR2 6JG",
    "sg:province":"Herefordshire",
    "sg:tags":[
        "precision",
        "engineer"
    ],
    "wof:name":"Acorn Developments",
    "wof:placetype":"venue"
},
  "geometry": {"coordinates":[-2.6853840351,52.0371704102],"type":"Point"}
}