{
  "type": "Feature",
  "properties": {
    "iso:country":"GB",
    "sg:address":"15 Horsley Road, Kingsthorpe Hollow",
    "sg:city":"Northampton",
    "sg:classifiers":[
        {
            "category":"Manufacturing",
            "subcategory":"Metals",
            "type":"Manufacturing & Wholesale Goods"
        }
    ],
    "sg:phone":"+44 1604 719803",
    "sg:postcode":"NN2 6LJ",
    "sg:province":"Northamptonshire",
    "sg:tags":[
        "work",
        "sheet"
    ],
    "wof:name":"Trinity Engineering (Northampton) Ltd.",
    "wof:placetype":"venue"
},
  "geometry": {"coordinates":[-0.903016,52.251965],"type":"Point"}
}