{
  "type": "Feature",
  "properties": {
    "addr:full":"2 Cranleigh Avenue, Sneyd Grn Stoke-on-trent Staffordshire ST1 6EE",
    "addr:housenumber":"2",
    "addr:postcode":"st1 6ee",
    "addr:street":"Cranleigh Avenue Sneyd Grn",
    "iso:country":"GB",
    "sg:address":"2 Cranleigh Avenue, Sneyd Grn",
    "sg:city":"Stoke-on-trent",
    "sg:classifiers":[
        {
            "category":"Shopping",
            "subcategory":"Computers & Home Electronics",
            "type":"Retail Goods"
        }
    ],
    "sg:phone":"+44 1782 280071",
    "sg:postcode":"ST1 6EE",
    "sg:province":"Staffordshire",
    "sg:tags":[
        "aerial",
        "television",
        "radio"
    ],
    "wof:name":"C A S Mobile Satellites",
    "wof:placetype":"venue"
},
  "geometry": {"coordinates":[-2.169402,53.043922],"type":"Point"}
}