{
  "type": "Feature",
  "properties": {
    "addr:full":"South William Street Workington Cumbria CA14 2ED",
    "addr:postcode":"ca14 2ed",
    "addr:street":"South William Street",
    "iso:country":"GB",
    "sg:address":"South William Street",
    "sg:city":"Workington",
    "sg:classifiers":[
        {
            "category":"Health Services",
            "subcategory":"Doctor",
            "type":"Services"
        }
    ],
    "sg:phone":"+44 1900 605258",
    "sg:postcode":"CA14 2ED",
    "sg:province":"Cumbria",
    "sg:tags":[
        "practitioners"
    ],
    "wof:name":"Ann Burrow Thomas Health Centre",
    "wof:placetype":"venue"
},
  "geometry": {"coordinates":[-3.550627,54.645191],"type":"Point"}
}