{
  "type": "Feature",
  "properties": {
    "addr:full":"48 Bitteswell Rd Lutterworth Leicestershire LE17 4EX",
    "addr:housenumber":"48",
    "addr:postcode":"le17 4ex",
    "addr:street":"Bitteswell Rd",
    "iso:country":"GB",
    "sg:address":"48 Bitteswell Rd",
    "sg:city":"Lutterworth",
    "sg:classifiers":[
        {
            "category":"Building & Trades",
            "subcategory":"Construction",
            "type":"Services"
        }
    ],
    "sg:phone":"+44 1455 550886",
    "sg:postcode":"LE17 4EX",
    "sg:province":"Leicestershire",
    "sg:tags":[
        "contractor"
    ],
    "wof:name":"C S Keogh & Son",
    "wof:placetype":"venue"
},
  "geometry": {"coordinates":[-1.2053500414,52.4595832825],"type":"Point"}
}