{
  "type": "Feature",
  "properties": {
    "iso:country":"GB",
    "sg:address":"38a Aston Road",
    "sg:city":"Waterlooville",
    "sg:classifiers":[
        {
            "category":"Communications",
            "type":"Services"
        }
    ],
    "sg:phone":"+44 23 9223 3332",
    "sg:postcode":"PO7 7XF",
    "sg:province":"Hampshire",
    "sg:tags":[
        "system",
        "music",
        "public",
        "address"
    ],
    "wof:name":"Loudspeaker Services Ltd.",
    "wof:placetype":"venue"
},
  "geometry": {"coordinates":[-1.035794,50.886002],"type":"Point"}
}