{
  "type": "Feature",
  "properties": {
    "iso:country":"GB",
    "sg:address":"West Benhar Road, Harthill",
    "sg:city":"Shotts",
    "sg:classifiers":[
        {
            "category":"Wholesale",
            "subcategory":"Scrap",
            "type":"Manufacturing & Wholesale Goods"
        }
    ],
    "sg:phone":"+44 1501 751932",
    "sg:postcode":"ML7 5TG",
    "sg:province":"North Lanarkshire",
    "sg:tags":[
        "breaker",
        "dismantlers"
    ],
    "wof:name":"Auto Salvage Centre",
    "wof:placetype":"venue"
},
  "geometry": {"coordinates":[-3.7517290115,55.8603363037],"type":"Point"}
}