{
  "type": "Feature",
  "properties": {
    "addr:full":"Princes Road, The Green Weybridge Surrey KT13 9BY",
    "addr:postcode":"kt13 9by",
    "addr:street":"Princes Road The",
    "iso:country":"GB",
    "sg:address":"Princes Road, The Green",
    "sg:city":"Weybridge",
    "sg:classifiers":[
        {
            "category":"Arena",
            "subcategory":"Sports Club",
            "type":"Entertainment"
        }
    ],
    "sg:phone":"+44 1932 842484",
    "sg:postcode":"KT13 9BY",
    "sg:province":"Surrey",
    "wof:name":"Weybridge Cricket Club",
    "wof:placetype":"venue"
},
  "geometry": {"coordinates":[-0.4496990144,51.3685188293],"type":"Point"}
}