{
  "type": "Feature",
  "properties": {
    "iso:country":"GB",
    "sg:address":"Greyhound Walk, The Galleries, Broadmead",
    "sg:city":"Bristol",
    "sg:classifiers":[
        {
            "category":"Shopping",
            "subcategory":"Mobile Phones",
            "type":"Retail Goods"
        }
    ],
    "sg:phone":"+44 117 929 4699",
    "sg:postcode":"BS1 3XA",
    "sg:province":"City of Bristol",
    "wof:name":"Vodafone Retail",
    "wof:placetype":"venue"
},
  "geometry": {"coordinates":[-2.586429,51.456871],"type":"Point"}
}