{
  "type": "Feature",
  "properties": {
    "addr:full":"Asda Store, Castle Lane Bournemouth Dorset BH8 9UN",
    "addr:postcode":"bh8 9un",
    "addr:street":"Castle Lane",
    "iso:country":"GB",
    "sg:address":"Asda Store, Castle Lane",
    "sg:city":"Bournemouth",
    "sg:classifiers":[
        {
            "category":"Communications",
            "type":"Services"
        }
    ],
    "sg:phone":"+44 1202 511126",
    "sg:postcode":"BH8 9UN",
    "sg:province":"Dorset",
    "sg:tags":[
        "telecommunication"
    ],
    "wof:name":"First Call Mobiles",
    "wof:placetype":"venue"
},
  "geometry": {"coordinates":[-1.8566520214,50.7539978027],"type":"Point"}
}