{
  "type": "Feature",
  "properties": {
    "addr:full":"22 The Grn, Thorne Doncaster East Riding of Yorkshire DN8 5AT",
    "addr:housenumber":"22",
    "addr:postcode":"dn8 5at",
    "addr:street":"The Grn;Riding",
    "iso:country":"GB",
    "sg:address":"22 The Grn, Thorne",
    "sg:city":"Doncaster",
    "sg:classifiers":[
        {
            "category":"Community Center",
            "subcategory":"Social",
            "type":"Public Place"
        },
        {
            "category":"Food & Beverages",
            "subcategory":"Groceries & Convenience Stores",
            "type":"Retail Goods"
        }
    ],
    "sg:phone":"+44 1405 817289",
    "sg:postcode":"DN8 5AT",
    "sg:province":"East Riding of Yorkshire",
    "sg:tags":[
        "frozen",
        "retailer",
        "freezer",
        "centre"
    ],
    "wof:name":"Heron Frozen Foods Ltd.",
    "wof:placetype":"venue"
},
  "geometry": {"coordinates":[-0.961637,53.611591],"type":"Point"}
}