{
  "type": "Feature",
  "properties": {
    "iso:country":"GB",
    "sg:address":"Chester City Baths Union St",
    "sg:city":"Chester",
    "sg:classifiers":[
        {
            "category":"Education",
            "subcategory":"Vocational School",
            "type":"Public Place"
        }
    ],
    "sg:phone":"+44 1244 317300",
    "sg:postcode":"CH1 1QP",
    "sg:province":"Cheshire",
    "sg:tags":[
        "swimming"
    ],
    "wof:name":"City of Chester Swimming Club",
    "wof:placetype":"venue"
},
  "geometry": {"coordinates":[-2.894369,53.188129],"type":"Point"}
}