{
  "type": "Feature",
  "properties": {
    "iso:country":"GB",
    "sg:address":"P O Box 2 Mill Lane",
    "sg:city":"Alton",
    "sg:classifiers":[
        {
            "category":"Manufacturing",
            "subcategory":"Metals",
            "type":"Manufacturing & Wholesale Goods"
        }
    ],
    "sg:phone":"+44 1420 544410",
    "sg:postcode":"GU34 2YA",
    "sg:province":"Hampshire",
    "sg:tags":[
        "steel",
        "stockholder"
    ],
    "wof:name":"Brown & Tawse Steelstock Ltd.",
    "wof:placetype":"venue"
},
  "geometry": {"coordinates":[-0.974329,51.14756],"type":"Point"}
}