{
  "type": "Feature",
  "properties": {
    "addr:full":"Unit 5 Enterprise Warehouse, Chain Caul Way Preston Lancashire PR2 2YL",
    "addr:housenumber":"unit 5",
    "addr:postcode":"pr2 2yl",
    "addr:street":"Enterprise;Caul Way",
    "iso:country":"GB",
    "sg:address":"Unit 5 Enterprise Warehouse, Chain Caul Way",
    "sg:city":"Preston",
    "sg:classifiers":[
        {
            "category":"Wholesale",
            "subcategory":"Groceries",
            "type":"Manufacturing & Wholesale Goods"
        }
    ],
    "sg:phone":"+44 1772 732109",
    "sg:postcode":"PR2 2YL",
    "sg:province":"Lancashire",
    "sg:tags":[
        "food",
        "supplier",
        "drink"
    ],
    "wof:name":"J L M Catering Distributors",
    "wof:placetype":"venue"
},
  "geometry": {"coordinates":[-2.7502000332,53.7609100342],"type":"Point"}
}