{
  "type": "Feature",
  "properties": {
    "addr:full":"70 St Thomas Rd Sheffield South Yorkshire S10 1UX",
    "addr:housenumber":"70",
    "addr:postcode":"s10 1ux",
    "addr:street":"St Thomas Rd",
    "iso:country":"GB",
    "sg:address":"70 St Thomas Rd",
    "sg:city":"Sheffield",
    "sg:classifiers":[
        {
            "category":"Military Area",
            "subcategory":"Air Force Base",
            "type":"Public Place"
        }
    ],
    "sg:phone":"+44 114 266 3877",
    "sg:postcode":"S10 1UX",
    "sg:province":"South Yorkshire",
    "sg:tags":[
        "taxi",
        "hire",
        "private"
    ],
    "wof:name":"Aircars",
    "wof:placetype":"venue"
},
  "geometry": {"coordinates":[-1.5114530325,53.3826217651],"type":"Point"}
}