{
  "type": "Feature",
  "properties": {
    "addr:full":"335 Stockfield Rd, Yardley Birmingham West Midlands B25 8JP",
    "addr:housenumber":"335",
    "addr:postcode":"b25 8jp",
    "addr:street":"Stockfield Rd",
    "iso:country":"GB",
    "sg:address":"335 Stockfield Rd, Yardley",
    "sg:city":"Birmingham",
    "sg:classifiers":[
        {
            "category":"Food & Beverages",
            "subcategory":"Meat & Fish",
            "type":"Retail Goods"
        }
    ],
    "sg:postcode":"B25 8JP",
    "sg:province":"West Midlands",
    "sg:tags":[
        "chip"
    ],
    "wof:name":"Singh,Kulbinder,",
    "wof:placetype":"venue"
},
  "geometry": {"coordinates":[-1.8219900131,52.4579353333],"type":"Point"}
}