{
  "type": "Feature",
  "properties": {
    "iso:country":"GB",
    "sg:address":"Unit 9, Barclay Hill Place, Port Lethen Industrial Estate",
    "sg:city":"Aberdeen",
    "sg:classifiers":[
        {
            "category":"Manufacturing",
            "subcategory":"Petroleum Products",
            "type":"Manufacturing & Wholesale Goods"
        }
    ],
    "sg:phone":"+44 1224 782332",
    "sg:postcode":"AB12 3PE",
    "sg:province":"Aberdeen City",
    "sg:tags":[
        "double",
        "glazing"
    ],
    "wof:name":"North East Window & Door Systems Ltd.",
    "wof:placetype":"venue"
},
  "geometry": {"coordinates":[-2.08114,57.10054],"type":"Point"}
}