{
  "type": "Feature",
  "properties": {
    "addr:full":"105 Fermor Way Crowborough East Sussex TN6 3BH",
    "addr:housenumber":"105",
    "addr:postcode":"tn6 3bh",
    "addr:street":"Fermor Way",
    "iso:country":"GB",
    "sg:address":"105 Fermor Way",
    "sg:city":"Crowborough",
    "sg:classifiers":[
        {
            "category":"Communications",
            "type":"Services"
        }
    ],
    "sg:postcode":"TN6 3BH",
    "sg:province":"East Sussex",
    "sg:tags":[
        "system",
        "music",
        "public",
        "address"
    ],
    "wof:name":"Electrical & Acoustic Services Ltd.",
    "wof:placetype":"venue"
},
  "geometry": {"coordinates":[0.1671430022,51.0466308594],"type":"Point"}
}