{
  "type": "Feature",
  "properties": {
    "addr:full":"20 Chassey Close, Poulner Ringwood Dorset BH24 3EU",
    "addr:housenumber":"20",
    "addr:postcode":"bh24 3eu",
    "addr:street":"Chassey Close",
    "iso:country":"GB",
    "sg:address":"20 Chassey Close, Poulner",
    "sg:city":"Ringwood",
    "sg:classifiers":[
        {
            "category":"Insurance",
            "subcategory":"Health Insurance",
            "type":"Services"
        }
    ],
    "sg:phone":"+44 1425 479078",
    "sg:postcode":"BH24 3EU",
    "sg:province":"Dorset",
    "wof:name":"The Brokerage",
    "wof:placetype":"venue"
},
  "geometry": {"coordinates":[-1.764949,50.848545],"type":"Point"}
}