{
  "type": "Feature",
  "properties": {
    "addr:full":"47 Holland Villas Road, Holland Park London Greater London W14 8DH",
    "addr:housenumber":"47",
    "addr:postcode":"w14 8dh",
    "addr:street":"Holland Villas Road",
    "iso:country":"GB",
    "sg:address":"47 Holland Villas Road, Holland Park",
    "sg:city":"London",
    "sg:classifiers":[
        {
            "category":"Real Estate",
            "subcategory":"Architect",
            "type":"Services"
        }
    ],
    "sg:postcode":"W14 8DH",
    "sg:province":"Greater London",
    "wof:name":"Land & Architectural Services Ltd.",
    "wof:placetype":"venue"
},
  "geometry": {"coordinates":[-0.2082230002,51.4980926514],"type":"Point"}
}