{
  "type": "Feature",
  "properties": {
    "iso:country":"GB",
    "sg:address":"47 Holland Villas Road, Holland Park",
    "sg:city":"London",
    "sg:classifiers":[
        {
            "category":"Real Estate",
            "subcategory":"Architect",
            "type":"Services"
        }
    ],
    "sg:postcode":"W14 8DH",
    "sg:province":"Greater London",
    "wof:name":"Land & Architectural Services Ltd.",
    "wof:placetype":"venue"
},
  "geometry": {"coordinates":[-0.2082230002,51.4980926514],"type":"Point"}
}