{
  "type": "Feature",
  "properties": {
    "addr:full":"8 The Courtyard, Gaulby Lane Leicester Leicestershire LE2 2FL",
    "addr:housenumber":"8",
    "addr:postcode":"le2 2fl",
    "addr:street":"The Courtyard Gaulby Lane",
    "iso:country":"GB",
    "sg:address":"8 The Courtyard, Gaulby Lane",
    "sg:city":"Leicester",
    "sg:classifiers":[
        {
            "category":"Real Estate",
            "subcategory":"Architect",
            "type":"Services"
        }
    ],
    "sg:phone":"+44 116 271 5557",
    "sg:postcode":"LE2 2FL",
    "sg:province":"Leicestershire",
    "sg:tags":[
        "technologist",
        "architectural"
    ],
    "wof:name":"Malcolm Hart",
    "wof:placetype":"venue"
},
  "geometry": {"coordinates":[-1.0489799976,52.6133499146],"type":"Point"}
}