{
  "type": "Feature",
  "properties": {
    "iso:country":"GB",
    "sg:address":"20 Oxford Street",
    "sg:city":"Wellingborough",
    "sg:classifiers":[
        {
            "category":"Government",
            "subcategory":"Office",
            "type":"Public Place"
        }
    ],
    "sg:phone":"+44 1933 303680",
    "sg:postcode":"NN8 4HY",
    "sg:province":"Northamptonshire",
    "sg:tags":[
        "central"
    ],
    "wof:name":"The Probation Service",
    "wof:placetype":"venue"
},
  "geometry": {"coordinates":[-0.699506,52.300262],"type":"Point"}
}