{
  "type": "Feature",
  "properties": {
    "addr:full":"7 Crescent Parade, Uxbridge Road Uxbridge Greater London UB10 0LG",
    "addr:housenumber":"7",
    "addr:postcode":"ub10 0lg",
    "addr:street":"Crescent Parade Uxbridge Road",
    "iso:country":"GB",
    "sg:address":"7 Crescent Parade, Uxbridge Road",
    "sg:city":"Uxbridge",
    "sg:classifiers":[
        {
            "category":"Food & Beverages",
            "subcategory":"Fruits & Vegetables",
            "type":"Retail Goods"
        }
    ],
    "sg:phone":"+44 1895 237956",
    "sg:postcode":"UB10 0LG",
    "sg:province":"Greater London",
    "sg:tags":[
        "greengrocer"
    ],
    "wof:name":"Brian's Greengrocers",
    "wof:placetype":"venue"
},
  "geometry": {"coordinates":[-0.45297,51.533199],"type":"Point"}
}