{
  "type": "Feature",
  "properties": {
    "iso:country":"GB",
    "sg:address":"Shepperton Marina",
    "sg:city":"Shepperton",
    "sg:classifiers":[
        {
            "category":"Professional",
            "subcategory":"Management & Consulting",
            "type":"Services"
        }
    ],
    "sg:phone":"+44 1932 267654",
    "sg:postcode":"TW17 8NS",
    "sg:province":"Surrey",
    "sg:tags":[
        "marketing",
        "consultant"
    ],
    "wof:name":"Windsor Creative Communications",
    "wof:placetype":"venue"
},
  "geometry": {"coordinates":[-0.4520120025,51.3966064453],"type":"Point"}
}