{
  "type": "Feature",
  "properties": {
    "addr:full":"Parkside, Walderslade Road Chatham Kent ME5 0JA",
    "addr:postcode":"me5 0ja",
    "addr:street":"Walderslade Road",
    "iso:country":"GB",
    "sg:address":"Parkside, Walderslade Road",
    "sg:city":"Chatham",
    "sg:classifiers":[
        {
            "category":"Home & Garden",
            "subcategory":"Garden Supply",
            "type":"Retail Goods"
        }
    ],
    "sg:phone":"+44 1634 841942",
    "sg:postcode":"ME5 0JA",
    "sg:province":"Kent",
    "sg:tags":[
        "turfing"
    ],
    "wof:name":"Quality Turf Supplies",
    "wof:placetype":"venue"
},
  "geometry": {"coordinates":[0.521202,51.355305],"type":"Point"}
}