{
  "type": "Feature",
  "properties": {
    "iso:country":"GB",
    "sg:address":"P O Box 699",
    "sg:city":"Swansea",
    "sg:classifiers":[
        {
            "category":"Autos & Motor Vehicles",
            "subcategory":"Motorcycle Sales",
            "type":"Retail Goods"
        }
    ],
    "sg:phone":"+44 1792 881231",
    "sg:postcode":"SA4 1ZA",
    "sg:province":"Carmarthenshire",
    "sg:tags":[
        "chauffeur",
        "driven",
        "car"
    ],
    "wof:name":"Executive Transport UK",
    "wof:placetype":"venue"
},
  "geometry": {"coordinates":[-4.06857,51.684792],"type":"Point"}
}