{
  "type": "Feature",
  "properties": {
    "addr:full":"48 South Street Alderley Edge Cheshire SK9 7ES",
    "addr:housenumber":"48",
    "addr:postcode":"sk9 7es",
    "addr:street":"South Street",
    "iso:country":"GB",
    "sg:address":"48 South Street",
    "sg:city":"Alderley Edge",
    "sg:classifiers":[
        {
            "category":"Organizations",
            "subcategory":"Non-profit Organization",
            "type":"Services"
        }
    ],
    "sg:phone":"+44 1625 590010",
    "sg:postcode":"SK9 7ES",
    "sg:province":"Cheshire",
    "sg:tags":[
        "charitable",
        "organisation",
        "voluntary",
        "charity"
    ],
    "sg:website":"http://scfs.org",
    "wof:name":"The Seamen's Christian Friend Society",
    "wof:placetype":"venue"
},
  "geometry": {"coordinates":[-2.237726,53.300739],"type":"Point"}
}