{
  "type": "Feature",
  "properties": {
    "addr:full":"35 Friar Road Orpington Kent BR5 2BN",
    "addr:housenumber":"35",
    "addr:postcode":"br5 2bn",
    "addr:street":"Friar Road",
    "iso:country":"GB",
    "sg:address":"35 Friar Road",
    "sg:city":"Orpington",
    "sg:classifiers":[
        {
            "category":"Professional",
            "subcategory":"Engineering",
            "type":"Services"
        }
    ],
    "sg:phone":"+44 1689 870094",
    "sg:postcode":"BR5 2BN",
    "sg:province":"Kent",
    "sg:tags":[
        "contractor",
        "electrical",
        "engineer"
    ],
    "wof:name":"M J Gill Electrical",
    "wof:placetype":"venue"
},
  "geometry": {"coordinates":[0.102051,51.388733],"type":"Point"}
}