{
  "type": "Feature",
  "properties": {
    "addr:full":"11 Silver Street, Masham Ripon North Yorkshire HG4 4DX",
    "addr:housenumber":"11",
    "addr:postcode":"hg4 4dx",
    "addr:street":"Silver Street",
    "iso:country":"GB",
    "sg:address":"11 Silver Street, Masham",
    "sg:city":"Ripon",
    "sg:classifiers":[
        {
            "category":"Food & Beverages",
            "subcategory":"Meat & Fish",
            "type":"Retail Goods"
        }
    ],
    "sg:phone":"+44 1765 689269",
    "sg:postcode":"HG4 4DX",
    "sg:province":"North Yorkshire",
    "sg:tags":[
        "butcher"
    ],
    "wof:name":"Beavers Butchers",
    "wof:placetype":"venue"
},
  "geometry": {"coordinates":[-1.656883955,54.2223968506],"type":"Point"}
}