{
  "type": "Feature",
  "properties": {
    "addr:full":"56 Salisbury Gro, Mytchett Camberley Hampshire GU16 6DA",
    "addr:housenumber":"56",
    "addr:postcode":"gu16 6da",
    "addr:street":"Gro Mytchett",
    "iso:country":"GB",
    "sg:address":"56 Salisbury Gro, Mytchett",
    "sg:city":"Camberley",
    "sg:classifiers":[
        {
            "category":"Personal",
            "subcategory":"Beauty Salon",
            "type":"Services"
        }
    ],
    "sg:phone":"+44 1252 546913",
    "sg:postcode":"GU16 6DA",
    "sg:province":"Hampshire",
    "sg:tags":[
        "unisex",
        "hairdresser"
    ],
    "wof:name":"Ria Tansley",
    "wof:placetype":"venue"
},
  "geometry": {"coordinates":[-0.724175,51.287975],"type":"Point"}
}