{
  "type": "Feature",
  "properties": {
    "iso:country":"GB",
    "sg:address":"54-58 Cow Wynd",
    "sg:city":"Falkirk",
    "sg:classifiers":[
        {
            "category":"Retail",
            "subcategory":"Laundry & Dry Cleaning",
            "type":"Services"
        },
        {
            "category":"Retail",
            "subcategory":"Repair Shop",
            "type":"Services"
        }
    ],
    "sg:phone":"+44 1324 612201",
    "sg:postcode":"FK1 1PU",
    "sg:province":"Falkirk",
    "sg:tags":[
        "clothing",
        "alteration"
    ],
    "wof:name":"Elizabeth Alterations",
    "wof:placetype":"venue"
},
  "geometry": {"coordinates":[-3.783569,55.997078],"type":"Point"}
}