{
  "type": "Feature",
  "properties": {
    "iso:country":"GB",
    "sg:address":"Hunts Rise, South Marston Park",
    "sg:city":"Swindon",
    "sg:classifiers":[
        {
            "category":"Wholesale",
            "subcategory":"Machinery & Supplies",
            "type":"Manufacturing & Wholesale Goods"
        }
    ],
    "sg:phone":"+44 1793 823241",
    "sg:postcode":"SN3 4TQ",
    "sg:province":"Wiltshire",
    "sg:tags":[
        "system",
        "hydraulic"
    ],
    "wof:name":"Forward Industries Ltd.",
    "wof:placetype":"venue"
},
  "geometry": {"coordinates":[-1.7378,51.602242],"type":"Point"}
}