{
  "type": "Feature",
  "properties": {
    "iso:country":"GB",
    "sg:address":"Budworth, Shay Lane",
    "sg:city":"Altrincham",
    "sg:classifiers":[
        {
            "category":"Shopping",
            "subcategory":"Pharmacy",
            "type":"Retail Goods"
        }
    ],
    "sg:phone":"+44 161 980 6453",
    "sg:postcode":"WA15 8UE",
    "sg:province":"Cheshire",
    "sg:tags":[
        "medicine",
        "therapy"
    ],
    "wof:name":"The Reiki School",
    "wof:placetype":"venue"
},
  "geometry": {"coordinates":[-2.30039,53.3741],"type":"Point"}
}