{
  "type": "Feature",
  "properties": {
    "iso:country":"GB",
    "sg:address":"1 Timberholm",
    "sg:city":"Hawick",
    "sg:classifiers":[
        {
            "category":"Building & Trades",
            "subcategory":"Construction",
            "type":"Services"
        }
    ],
    "sg:phone":"+44 1450 870544",
    "sg:postcode":"TD9 8TD",
    "sg:province":"Cumbria",
    "sg:tags":[
        "builder"
    ],
    "wof:name":"Slaters",
    "wof:placetype":"venue"
},
  "geometry": {"coordinates":[-2.714619,55.453648],"type":"Point"}
}