{
  "type": "Feature",
  "properties": {
    "iso:country":"GB",
    "sg:address":"379 Regents Park Road, Finchley",
    "sg:city":"London",
    "sg:classifiers":[
        {
            "category":"Shopping",
            "subcategory":"Mobile Phones",
            "type":"Retail Goods"
        },
        {
            "category":"Professional",
            "subcategory":"Printing & Photocopies",
            "type":"Services"
        }
    ],
    "sg:phone":"+44 20 8343 4469",
    "sg:postcode":"N3 1DE",
    "sg:province":"Greater London",
    "sg:tags":[
        "trophy",
        "medal"
    ],
    "wof:name":"Southern Sports Ltd.",
    "wof:placetype":"venue"
},
  "geometry": {"coordinates":[-0.194229,51.601082],"type":"Point"}
}