{
  "type": "Feature",
  "properties": {
    "addr:full":"Queen St, Northwich Cheshire CW9 5JN",
    "addr:postcode":"cw9 5jn",
    "addr:street":"Queen St",
    "iso:country":"GB",
    "sg:address":"Queen St,",
    "sg:city":"Northwich",
    "sg:classifiers":[
        {
            "category":"Shopping",
            "subcategory":"Antiques",
            "type":"Retail Goods"
        }
    ],
    "sg:postcode":"CW9 5JN",
    "sg:province":"Cheshire",
    "wof:name":"Antique Centre (Northwich)",
    "wof:placetype":"venue"
},
  "geometry": {"coordinates":[-2.5140390396,53.2578163147],"type":"Point"}
}