{
  "type": "Feature",
  "properties": {
    "iso:country":"GB",
    "sg:address":"Grange Farm, Roxton Road, Immingham",
    "sg:city":"Grimsby",
    "sg:classifiers":[
        {
            "category":"Farming",
            "subcategory":"Farm",
            "type":"Manufacturing & Wholesale Goods"
        }
    ],
    "sg:phone":"+44 1469 578122",
    "sg:postcode":"DN40 1NS",
    "sg:province":"Lincolnshire",
    "sg:tags":[
        "mixed",
        "crop"
    ],
    "wof:name":"E W Pickering",
    "wof:placetype":"venue"
},
  "geometry": {"coordinates":[-0.223969996,53.6114807129],"type":"Point"}
}