{
  "type": "Feature",
  "properties": {
    "addr:full":"2-4 John Brannan Way Bellshill North Lanarkshire ML4 3HD",
    "addr:housenumber":"2-4",
    "addr:postcode":"ml4 3hd",
    "addr:street":"John Brannan Way",
    "iso:country":"GB",
    "sg:address":"2-4 John Brannan Way",
    "sg:city":"Bellshill",
    "sg:classifiers":[
        {
            "category":"Social Services",
            "subcategory":"Job Training",
            "type":"Services"
        },
        {
            "category":"Organizations",
            "subcategory":"Non-profit Organization",
            "type":"Services"
        }
    ],
    "sg:phone":"+44 1698 749933",
    "sg:postcode":"ML4 3HD",
    "sg:province":"North Lanarkshire",
    "sg:tags":[
        "organisation",
        "voluntary",
        "charity"
    ],
    "wof:name":"Right Track",
    "wof:placetype":"venue"
},
  "geometry": {"coordinates":[-4.0358009338,55.8203048706],"type":"Point"}
}