{
  "type": "Feature",
  "properties": {
    "iso:country":"GB",
    "sg:address":"620 Oldham Road, Failsworth",
    "sg:city":"Manchester",
    "sg:classifiers":[
        {
            "category":"Insurance",
            "subcategory":"Insurance Agent",
            "type":"Services"
        }
    ],
    "sg:postcode":"M35 9DQ",
    "sg:province":"Lancashire",
    "wof:name":"Lee Marsden",
    "wof:placetype":"venue"
},
  "geometry": {"coordinates":[-2.151204,53.514423],"type":"Point"}
}