{
  "type": "Feature",
  "properties": {
    "addr:full":"47 Corporation Street Birmingham West Midlands B2 4LS",
    "addr:housenumber":"47",
    "addr:postcode":"b2 4ls",
    "addr:street":"Corporation Street",
    "iso:country":"GB",
    "sg:address":"47 Corporation Street",
    "sg:city":"Birmingham",
    "sg:classifiers":[
        {
            "category":"Shopping",
            "subcategory":"Shoes",
            "type":"Retail Goods"
        }
    ],
    "sg:postcode":"B2 4LS",
    "sg:province":"West Midlands",
    "sg:tags":[
        "shop"
    ],
    "wof:name":"Stylo Barratt Shoes Ltd.",
    "wof:placetype":"venue"
},
  "geometry": {"coordinates":[-1.8968219757,52.4801139832],"type":"Point"}
}