{
  "type": "Feature",
  "properties": {
    "addr:full":"Patches Farm Waltham Abbey Essex EN9 2AJ",
    "addr:postcode":"en9 2aj",
    "addr:street":"Waltham Abbey",
    "iso:country":"GB",
    "sg:address":"Patches Farm",
    "sg:city":"Waltham Abbey",
    "sg:classifiers":[
        {
            "category":"Recreation",
            "type":"Entertainment"
        }
    ],
    "sg:phone":"+44 7973 432075",
    "sg:postcode":"EN9 2AJ",
    "sg:province":"Essex",
    "sg:tags":[
        "outdoor",
        "pursuit"
    ],
    "wof:name":"Big Bang Promotions Ltd.",
    "wof:placetype":"venue"
},
  "geometry": {"coordinates":[0.0014900001,51.6864204407],"type":"Point"}
}