{
  "type": "Feature",
  "properties": {
    "addr:full":"Bridge Farm Chester Cheshire CH2 4DA",
    "addr:postcode":"ch2 4da",
    "addr:street":"Bridge",
    "iso:country":"GB",
    "sg:address":"Bridge Farm",
    "sg:city":"Chester",
    "sg:classifiers":[
        {
            "category":"Manufacturing",
            "subcategory":"Wood Products",
            "type":"Manufacturing & Wholesale Goods"
        },
        {
            "category":"Home & Garden",
            "subcategory":"Building Materials",
            "type":"Retail Goods"
        },
        {
            "category":"Manufacturing",
            "subcategory":"Furniture",
            "type":"Manufacturing & Wholesale Goods"
        }
    ],
    "sg:phone":"+44 1244 390921",
    "sg:postcode":"CH2 4DA",
    "sg:province":"Cheshire",
    "sg:tags":[
        "wooden",
        "roofing",
        "rafter",
        "beams"
    ],
    "wof:name":"Sabeka Timber Products",
    "wof:placetype":"venue"
},
  "geometry": {"coordinates":[-2.8377289772,53.264919281],"type":"Point"}
}