{
  "type": "Feature",
  "properties": {
    "addr:full":"Mount Vernon Green,hall La, Kensington Liverpool Merseyside L7 8TF",
    "addr:postcode":"l7 8tf",
    "addr:street":"Mount Vernon Green Hall La Kensington",
    "iso:country":"GB",
    "sg:address":"Mount Vernon Green,hall La, Kensington",
    "sg:city":"Liverpool",
    "sg:classifiers":[
        {
            "category":"Retail",
            "subcategory":"Auto Repair",
            "type":"Services"
        }
    ],
    "sg:postcode":"L7 8TF",
    "sg:province":"Merseyside",
    "sg:tags":[
        "modification",
        "garage"
    ],
    "wof:name":"Use,Ray,",
    "wof:placetype":"venue"
},
  "geometry": {"coordinates":[-2.9583890438,53.4075241089],"type":"Point"}
}