{
  "type": "Feature",
  "properties": {
    "iso:country":"GB",
    "sg:address":"P O Box 70",
    "sg:city":"Salisbury",
    "sg:classifiers":[
        {
            "category":"Recreation",
            "subcategory":"Gun Range",
            "type":"Entertainment"
        }
    ],
    "sg:phone":"+44 1722 415525",
    "sg:postcode":"SP2 7SB",
    "sg:province":"Wiltshire",
    "sg:tags":[
        "operator",
        "tour"
    ],
    "wof:name":"London Travel Desk",
    "wof:placetype":"venue"
},
  "geometry": {"coordinates":[-1.808489,51.072971],"type":"Point"}
}