{
  "type": "Feature",
  "properties": {
    "addr:full":"2 Mains View, Westhill Aberdeen Aberdeen City AB32 6NZ",
    "addr:housenumber":"2",
    "addr:postcode":"ab32 6nz",
    "addr:street":"Mains View",
    "iso:country":"GB",
    "sg:address":"2 Mains View, Westhill",
    "sg:city":"Aberdeen",
    "sg:classifiers":[
        {
            "category":"Communications",
            "type":"Services"
        }
    ],
    "sg:postcode":"AB32 6NZ",
    "sg:province":"Aberdeen City",
    "sg:tags":[
        "data",
        "network"
    ],
    "wof:name":"Versatile Data Ltd.",
    "wof:placetype":"venue"
},
  "geometry": {"coordinates":[-2.2709200382,57.1567153931],"type":"Point"}
}