{
  "type": "Feature",
  "properties": {
    "addr:full":"13 Prince Albert Street Brighton East Sussex BN1 1JJ",
    "addr:housenumber":"13",
    "addr:postcode":"bn1 1jj",
    "addr:street":"Prince Albert Street",
    "iso:country":"GB",
    "sg:address":"13 Prince Albert Street",
    "sg:city":"Brighton",
    "sg:classifiers":[
        {
            "category":"Professional",
            "subcategory":"Lawyer & Legal Services",
            "type":"Services"
        }
    ],
    "sg:phone":"+44 1273 329438",
    "sg:postcode":"BN1 1JJ",
    "sg:province":"East Sussex",
    "sg:tags":[
        "solicitor"
    ],
    "wof:name":"James McPherson & Co.",
    "wof:placetype":"venue"
},
  "geometry": {"coordinates":[-0.1416469961,50.8216667175],"type":"Point"}
}