{
  "type": "Feature",
  "properties": {
    "iso:country":"GB",
    "sg:address":"115 Langwith Road, Langwith Junction",
    "sg:city":"Mansfield",
    "sg:classifiers":[
        {
            "category":"Farming",
            "subcategory":"Nursery",
            "type":"Manufacturing & Wholesale Goods"
        }
    ],
    "sg:phone":"+44 1623 747473",
    "sg:postcode":"NG20 9RN",
    "sg:province":"Derbyshire",
    "sg:tags":[
        "creche"
    ],
    "wof:name":"Little Acorns Day Nursery",
    "wof:placetype":"venue"
},
  "geometry": {"coordinates":[-1.212223,53.211658],"type":"Point"}
}