{
  "type": "Feature",
  "properties": {
    "iso:country":"GB",
    "sg:address":"Mall Villa Mall Road, Brading",
    "sg:city":"Sandown",
    "sg:classifiers":[
        {
            "category":"Health Services",
            "subcategory":"Health Practitioner",
            "type":"Services"
        }
    ],
    "sg:postcode":"PO36 0BT",
    "sg:province":"Isle of Wight",
    "sg:tags":[
        "physiotherapist"
    ],
    "wof:name":"Associated Physiotherapists",
    "wof:placetype":"venue"
},
  "geometry": {"coordinates":[-1.1432939768,50.6819496155],"type":"Point"}
}