{
  "type": "Feature",
  "properties": {
    "addr:full":"30-32 Priestley Close Doncaster South Yorkshire DN4 9DQ",
    "addr:housenumber":"30-32",
    "addr:postcode":"dn4 9dq",
    "addr:street":"Priestley Close",
    "iso:country":"GB",
    "sg:address":"30-32 Priestley Close",
    "sg:city":"Doncaster",
    "sg:classifiers":[
        {
            "category":"Health Services",
            "subcategory":"Nursing And Care Facility",
            "type":"Services"
        },
        {
            "category":"Social Services",
            "subcategory":"Retirement Home",
            "type":"Services"
        },
        {
            "category":"Government",
            "subcategory":"Office",
            "type":"Public Place"
        }
    ],
    "sg:phone":"+44 1302 853421",
    "sg:postcode":"DN4 9DQ",
    "sg:province":"South Yorkshire",
    "sg:tags":[
        "residential",
        "local"
    ],
    "wof:name":"Preistley Close",
    "wof:placetype":"venue"
},
  "geometry": {"coordinates":[-1.1587250233,53.4963150024],"type":"Point"}
}