{
  "type": "Feature",
  "properties": {
    "iso:country":"GB",
    "sg:address":"111 Arundel Avenue",
    "sg:city":"Liverpool",
    "sg:classifiers":[
        {
            "category":"Retail",
            "subcategory":"Auto Repair",
            "type":"Services"
        }
    ],
    "sg:phone":"+44 151 734 5353",
    "sg:postcode":"L17 2AT",
    "sg:province":"Merseyside",
    "sg:tags":[
        "modification",
        "garage",
        "related"
    ],
    "wof:name":"Double S Motors Ltd",
    "wof:placetype":"venue"
},
  "geometry": {"coordinates":[-2.93344,53.3922],"type":"Point"}
}