{
  "type": "Feature",
  "properties": {
    "iso:country":"GB",
    "sg:address":"Granville Drive",
    "sg:city":"Brierley Hill",
    "sg:classifiers":[
        {
            "category":"Education",
            "subcategory":"School",
            "type":"Public Place"
        },
        {
            "category":"Government",
            "subcategory":"Office",
            "type":"Public Place"
        }
    ],
    "sg:postcode":"DY6 8LW",
    "sg:province":"Staffordshire",
    "sg:tags":[
        "local",
        "authority"
    ],
    "wof:name":"Bromley Hills Primary School",
    "wof:placetype":"venue"
},
  "geometry": {"coordinates":[-2.15396,52.49118],"type":"Point"}
}