{
  "type": "Feature",
  "properties": {
    "addr:full":"250 Rishton Lane Bolton Lancashire BL3 2EH",
    "addr:housenumber":"250",
    "addr:postcode":"bl3 2eh",
    "addr:street":"Rishton Lane",
    "iso:country":"GB",
    "sg:address":"250 Rishton Lane",
    "sg:city":"Bolton",
    "sg:classifiers":[
        {
            "category":"Building & Trades",
            "subcategory":"Cleaning & Sanitation",
            "type":"Services"
        }
    ],
    "sg:phone":"+44 1204 394966",
    "sg:postcode":"BL3 2EH",
    "sg:province":"Lancashire",
    "sg:tags":[
        "dry",
        "control",
        "damp",
        "rot"
    ],
    "wof:name":"C & B Damp Proofing",
    "wof:placetype":"venue"
},
  "geometry": {"coordinates":[-2.4285969734,53.5601501465],"type":"Point"}
}