{
  "type": "Feature",
  "properties": {
    "addr:full":"24 Abbotsbury Rd Broadstone Dorset BH18 9DA",
    "addr:housenumber":"24",
    "addr:postcode":"bh18 9da",
    "addr:street":"Abbotsbury Rd",
    "iso:country":"GB",
    "sg:address":"24 Abbotsbury Rd",
    "sg:city":"Broadstone",
    "sg:classifiers":[
        {
            "category":"Professional",
            "subcategory":"Engineering",
            "type":"Services"
        }
    ],
    "sg:phone":"+44 1202 699441",
    "sg:postcode":"BH18 9DA",
    "sg:province":"Dorset",
    "sg:tags":[
        "design",
        "engineer"
    ],
    "wof:name":"ANS Industrial Services",
    "wof:placetype":"venue"
},
  "geometry": {"coordinates":[-2.005101,50.764446],"type":"Point"}
}