{
  "type": "Feature",
  "properties": {
    "addr:full":"Station Road Stansted Essex CM24 8BE",
    "addr:postcode":"cm24 8be",
    "addr:street":"Station Road",
    "iso:country":"GB",
    "sg:address":"Station Road",
    "sg:city":"Stansted",
    "sg:classifiers":[
        {
            "category":"Travel",
            "subcategory":"Hotels & Motels",
            "type":"Entertainment"
        }
    ],
    "sg:phone":"+44 1279 812948",
    "sg:postcode":"CM24 8BE",
    "sg:province":"Essex",
    "wof:name":"Kings Arms Hotel",
    "wof:placetype":"venue"
},
  "geometry": {"coordinates":[0.1995480061,51.9018249512],"type":"Point"}
}