{
  "type": "Feature",
  "properties": {
    "iso:country":"GB",
    "sg:address":"13 Market St",
    "sg:city":"Cannock",
    "sg:classifiers":[
        {
            "category":"Shopping",
            "subcategory":"Florist",
            "type":"Retail Goods"
        }
    ],
    "sg:phone":"+44 1543 422565",
    "sg:postcode":"WS12 5AY",
    "sg:province":"Staffordshire",
    "wof:name":"Elliotts Of Hednesford",
    "wof:placetype":"venue"
},
  "geometry": {"coordinates":[-1.997625,52.707767],"type":"Point"}
}