{
  "type": "Feature",
  "properties": {
    "addr:full":"Willowmee, The Mount Gateshead Tyne and Wear NE9 7YP",
    "addr:postcode":"ne9 7yp",
    "addr:street":"Mount",
    "iso:country":"GB",
    "sg:address":"Willowmee, The Mount",
    "sg:city":"Gateshead",
    "sg:classifiers":[
        {
            "category":"Retail",
            "subcategory":"Storage",
            "type":"Services"
        }
    ],
    "sg:phone":"+44 191 416 3355",
    "sg:postcode":"NE9 7YP",
    "sg:province":"Tyne and Wear",
    "sg:tags":[
        "household",
        "removal"
    ],
    "wof:name":"Springwell Removals",
    "wof:placetype":"venue"
},
  "geometry": {"coordinates":[-1.5606700182,54.9146881104],"type":"Point"}
}