{
  "type": "Feature",
  "properties": {
    "iso:country":"GB",
    "sg:address":"51 Winser Drive",
    "sg:city":"Reading",
    "sg:classifiers":[
        {
            "category":"Shopping",
            "subcategory":"Books",
            "type":"Retail Goods"
        }
    ],
    "sg:postcode":"RG30 3EG",
    "sg:province":"Berkshire",
    "sg:tags":[
        "second-hand"
    ],
    "wof:name":"Victoria Books",
    "wof:placetype":"venue"
},
  "geometry": {"coordinates":[-0.9979460239,51.4421730042],"type":"Point"}
}