{
  "type": "Feature",
  "properties": {
    "addr:full":"6 Strathdene Parade, Blackheath London Greater London SE3 7SX",
    "addr:housenumber":"6",
    "addr:postcode":"se3 7sx",
    "addr:street":"Strathdene Parade",
    "iso:country":"GB",
    "sg:address":"6 Strathdene Parade, Blackheath",
    "sg:city":"London",
    "sg:classifiers":[
        {
            "category":"Cinema",
            "subcategory":"Movie Rental",
            "type":"Entertainment"
        }
    ],
    "sg:phone":"+44 20 8858 4210",
    "sg:postcode":"SE3 7SX",
    "sg:province":"Greater London",
    "sg:tags":[
        "video",
        "library"
    ],
    "wof:name":"Dave & Gina Ltd.",
    "wof:placetype":"venue"
},
  "geometry": {"coordinates":[0.0186420009,51.4764785767],"type":"Point"}
}