{
  "type": "Feature",
  "properties": {
    "addr:full":"61 St Christopher Road Colchester Essex CO4 0NF",
    "addr:housenumber":"61",
    "addr:postcode":"co4 0nf",
    "addr:street":"St Christopher Road Colchester",
    "iso:country":"GB",
    "sg:address":"61 St Christopher Road",
    "sg:city":"Colchester",
    "sg:classifiers":[
        {
            "category":"Building & Trades",
            "subcategory":"Construction",
            "type":"Services"
        }
    ],
    "sg:postcode":"CO4 0NF",
    "sg:province":"Essex",
    "sg:tags":[
        "joiner",
        "carpenter"
    ],
    "wof:name":"Michael Foster & Co",
    "wof:placetype":"venue"
},
  "geometry": {"coordinates":[0.928329,51.902821],"type":"Point"}
}