{
  "type": "Feature",
  "properties": {
    "addr:full":"9 Craigmillar Castle Road Edinburgh City of Edinburgh EH16 4BY",
    "addr:housenumber":"9",
    "addr:postcode":"eh16 4by",
    "addr:street":"Craigmillar Castle Road",
    "iso:country":"GB",
    "sg:address":"9 Craigmillar Castle Road",
    "sg:city":"Edinburgh",
    "sg:classifiers":[
        {
            "category":"Professional",
            "subcategory":"Lawyer & Legal Services",
            "type":"Services"
        }
    ],
    "sg:phone":"+44 131 661 9779",
    "sg:postcode":"EH16 4BY",
    "sg:province":"City of Edinburgh",
    "sg:tags":[
        "solicitor"
    ],
    "wof:name":"McKay & Norwell",
    "wof:placetype":"venue"
},
  "geometry": {"coordinates":[-3.1445391178,55.9309387207],"type":"Point"}
}