{
  "type": "Feature",
  "properties": {
    "addr:full":"393-395 Hook Road Chessington Surrey KT9 1NA",
    "addr:housenumber":"393-395",
    "addr:postcode":"kt9 1na",
    "addr:street":"Hook Road",
    "iso:country":"GB",
    "sg:address":"393-395 Hook Road",
    "sg:city":"Chessington",
    "sg:classifiers":[
        {
            "category":"Cinema",
            "subcategory":"Movie Rental",
            "type":"Entertainment"
        }
    ],
    "sg:phone":"+44 20 8974 1987",
    "sg:postcode":"KT9 1NA",
    "sg:province":"Surrey",
    "sg:tags":[
        "video",
        "library"
    ],
    "wof:name":"Apollo Video Film Hire Ltd.",
    "wof:placetype":"venue"
},
  "geometry": {"coordinates":[-0.306814,51.367016],"type":"Point"}
}