{
  "type": "Feature",
  "properties": {
    "iso:country":"GB",
    "sg:address":"41-43 Mill Road",
    "sg:city":"Cambridge",
    "sg:classifiers":[
        {
            "category":"Communications",
            "type":"Services"
        }
    ],
    "sg:postcode":"CB1 2AW",
    "sg:province":"Cambridgeshire",
    "sg:tags":[
        "tv",
        "video",
        "radio"
    ],
    "wof:name":"M G Tec Computers",
    "wof:placetype":"venue"
},
  "geometry": {"coordinates":[0.1349560022,52.201007843],"type":"Point"}
}