{
  "type": "Feature",
  "properties": {
    "iso:country":"GB",
    "sg:address":"Nelson Hill Farm, Plumpton",
    "sg:city":"Penrith",
    "sg:classifiers":[
        {
            "category":"Military Area",
            "subcategory":"Army Base",
            "type":"Public Place"
        },
        {
            "category":"Freight",
            "type":"Transportation"
        }
    ],
    "sg:phone":"+44 1768 894274",
    "sg:postcode":"CA11 9NP",
    "sg:province":"Cumbria",
    "sg:tags":[
        "haulage",
        "road",
        "livestock",
        "transport"
    ],
    "wof:name":"Brian J Johnston",
    "wof:placetype":"venue"
},
  "geometry": {"coordinates":[-2.7803390026,54.7255516052],"type":"Point"}
}