{
  "type": "Feature",
  "properties": {
    "addr:full":"Eastgate Office Centre, Eastgate Rd Bristol City of Bristol BS5 6XX",
    "addr:postcode":"bs5 6xx",
    "addr:street":"Eastgate;Eastgate Rd",
    "iso:country":"GB",
    "sg:address":"Eastgate Office Centre, Eastgate Rd",
    "sg:city":"Bristol",
    "sg:classifiers":[
        {
            "category":"Autos & Motor Vehicles",
            "subcategory":"Automobile Sales",
            "type":"Retail Goods"
        }
    ],
    "sg:phone":"+44 117 952 0000",
    "sg:postcode":"BS5 6XX",
    "sg:province":"City of Bristol",
    "sg:tags":[
        "car"
    ],
    "wof:name":"Cowie Bristol Honda",
    "wof:placetype":"venue"
},
  "geometry": {"coordinates":[-2.567869,51.473293],"type":"Point"}
}