{
  "type": "Feature",
  "properties": {
    "iso:country":"GB",
    "sg:address":"56 West Street",
    "sg:city":"Chichester",
    "sg:classifiers":[
        {
            "category":"Real Estate",
            "subcategory":"Surveying",
            "type":"Services"
        }
    ],
    "sg:phone":"+44 1243 783863",
    "sg:postcode":"PO19 1RP",
    "sg:province":"West Sussex",
    "sg:tags":[
        "surveyor",
        "valuer"
    ],
    "wof:name":"Puddle & Co",
    "wof:placetype":"venue"
},
  "geometry": {"coordinates":[-0.784036,50.836868],"type":"Point"}
}