{
  "type": "Feature",
  "properties": {
    "addr:full":"Unit 23/24, Bamfurlong Industrial Park, Staverton Cheltenham Gloucestershire GL51 6SX",
    "addr:housenumber":"unit 23 / 24",
    "addr:postcode":"gl51 6sx",
    "addr:street":"Bamfurlong Industrial Park",
    "iso:country":"GB",
    "sg:address":"Unit 23/24, Bamfurlong Industrial Park, Staverton",
    "sg:city":"Cheltenham",
    "sg:classifiers":[
        {
            "category":"Manufacturing",
            "subcategory":"Metals",
            "type":"Manufacturing & Wholesale Goods"
        }
    ],
    "sg:phone":"+44 1452 713722",
    "sg:postcode":"GL51 6SX",
    "sg:province":"Gloucestershire",
    "sg:tags":[
        "product",
        "fabricated"
    ],
    "wof:name":"Stace-Yates Ltd.",
    "wof:placetype":"venue"
},
  "geometry": {"coordinates":[-2.160394,51.898495],"type":"Point"}
}