{
  "type": "Feature",
  "properties": {
    "addr:full":"7 Royal Arcade London Greater London W1S 4SG",
    "addr:housenumber":"7",
    "addr:postcode":"w1s 4sg",
    "addr:street":"Royal Arcade",
    "iso:country":"GB",
    "sg:address":"7 Royal Arcade",
    "sg:city":"London",
    "sg:classifiers":[
        {
            "category":"Arts & Performance",
            "subcategory":"Art Gallery",
            "type":"Entertainment"
        }
    ],
    "sg:phone":"+44 20 7493 0722",
    "sg:postcode":"W1S 4SG",
    "sg:province":"Greater London",
    "wof:name":"William Weston Gallery Ltd.",
    "wof:placetype":"venue"
},
  "geometry": {"coordinates":[-0.1416960061,51.5089607239],"type":"Point"}
}