{
  "type": "Feature",
  "properties": {
    "addr:full":"Unit 22, Solent Industrial Estate, Shamblehurst Lane Southampton Hampshire SO30 2FX",
    "addr:housenumber":"unit 22",
    "addr:postcode":"so30 2fx",
    "addr:street":"Solent Industrial;Shamblehurst Lane",
    "iso:country":"GB",
    "sg:address":"Unit 22, Solent Industrial Estate, Shamblehurst Lane",
    "sg:city":"Southampton",
    "sg:classifiers":[
        {
            "category":"Shopping",
            "type":"Retail Goods"
        }
    ],
    "sg:phone":"+44 1489 780808",
    "sg:postcode":"SO30 2FX",
    "sg:province":"Hampshire",
    "sg:tags":[
        "equipment",
        "clothing",
        "safety"
    ],
    "wof:name":"Epec Ltd.",
    "wof:placetype":"venue"
},
  "geometry": {"coordinates":[-1.307174,50.925949],"type":"Point"}
}