{
  "type": "Feature",
  "properties": {
    "iso:country":"GB",
    "sg:address":"Unit 22, Solent Industrial Estate, Shamblehurst Lane",
    "sg:city":"Southampton",
    "sg:classifiers":[
        {
            "category":"Shopping",
            "type":"Retail Goods"
        }
    ],
    "sg:phone":"+44 1489 780808",
    "sg:postcode":"SO30 2FX",
    "sg:province":"Hampshire",
    "sg:tags":[
        "equipment",
        "clothing",
        "safety"
    ],
    "wof:name":"Epec Ltd.",
    "wof:placetype":"venue"
},
  "geometry": {"coordinates":[-1.307174,50.925949],"type":"Point"}
}