{
  "type": "Feature",
  "properties": {
    "addr:full":"10 Woodside Harrogate North Yorkshire HG1 5NG",
    "addr:housenumber":"10",
    "addr:postcode":"hg1 5ng",
    "addr:street":"Woodside",
    "iso:country":"GB",
    "sg:address":"10 Woodside",
    "sg:city":"Harrogate",
    "sg:classifiers":[
        {
            "category":"Professional",
            "subcategory":"Computer Services",
            "type":"Services"
        }
    ],
    "sg:phone":"+44 1423 524573",
    "sg:postcode":"HG1 5NG",
    "sg:province":"North Yorkshire",
    "sg:tags":[
        "consultant"
    ],
    "wof:name":"H C G Systems Ltd.",
    "wof:placetype":"venue"
},
  "geometry": {"coordinates":[-1.5328359604,53.9942398071],"type":"Point"}
}