{
  "type": "Feature",
  "properties": {
    "addr:full":"30 London Road Coalville Leicestershire LE67 3JA",
    "addr:housenumber":"30",
    "addr:postcode":"le67 3ja",
    "addr:street":"London Road",
    "iso:country":"GB",
    "sg:address":"30 London Road",
    "sg:city":"Coalville",
    "sg:classifiers":[
        {
            "category":"Utilities",
            "subcategory":"Natural Gas",
            "type":"Services"
        }
    ],
    "sg:phone":"+44 1530 832778",
    "sg:postcode":"LE67 3JA",
    "sg:province":"Leicestershire",
    "sg:tags":[
        "supplier"
    ],
    "wof:name":"J B Jackson & Co.",
    "wof:placetype":"venue"
},
  "geometry": {"coordinates":[-1.3681639433,52.7235488892],"type":"Point"}
}