{
  "type": "Feature",
  "properties": {
    "iso:country":"GB",
    "sg:address":"53 Colesbourne Drive, Downhead Park",
    "sg:city":"Milton Keynes",
    "sg:classifiers":[
        {
            "category":"Professional",
            "subcategory":"Management & Consulting",
            "type":"Services"
        }
    ],
    "sg:postcode":"MK15 9AW",
    "sg:province":"Buckinghamshire",
    "sg:tags":[
        "consultant",
        "business"
    ],
    "wof:name":"The Quality Consortium",
    "wof:placetype":"venue"
},
  "geometry": {"coordinates":[-0.734547019,52.0575065613],"type":"Point"}
}