{
  "type": "Feature",
  "properties": {
    "iso:country":"GB",
    "sg:address":"Manchester Road",
    "sg:city":"Huddersfield",
    "sg:classifiers":[
        {
            "category":"Manufacturing",
            "subcategory":"Buildings",
            "type":"Manufacturing & Wholesale Goods"
        }
    ],
    "sg:phone":"+44 1484 846934",
    "sg:postcode":"HD7 5QX",
    "sg:province":"West Yorkshire",
    "sg:tags":[
        "shed",
        "greenhouse"
    ],
    "wof:name":"Huddersfield Shed & Fence Centre",
    "wof:placetype":"venue"
},
  "geometry": {"coordinates":[-1.8410680294,53.6341819763],"type":"Point"}
}