{
  "type": "Feature",
  "properties": {
    "addr:full":"Worth Matravers Swanage Dorset BH19 3LQ",
    "addr:housenumber":"matravers",
    "addr:postcode":"bh19 3lq",
    "addr:street":"Worth",
    "iso:country":"GB",
    "sg:address":"Worth Matravers",
    "sg:city":"Swanage",
    "sg:classifiers":[
        {
            "category":"Transit Center",
            "subcategory":"Freight",
            "type":"Transportation"
        },
        {
            "category":"Cafe",
            "type":"Food & Drink"
        }
    ],
    "sg:phone":"+44 1929 439360",
    "sg:postcode":"BH19 3LQ",
    "sg:province":"Dorset",
    "sg:tags":[
        "shop",
        "tea",
        "craft",
        "room",
        "centre"
    ],
    "wof:name":"Worth Cafe & Craft Centre",
    "wof:placetype":"venue"
},
  "geometry": {"coordinates":[-1.964066,50.611984],"type":"Point"}
}