{
  "type": "Feature",
  "properties": {
    "addr:full":"24 Main Street, Breadon On The Hills Derby Derbyshire DE73 1AN",
    "addr:housenumber":"24",
    "addr:postcode":"de73 1an",
    "addr:street":"Main Street",
    "iso:country":"GB",
    "sg:address":"24 Main Street, Breadon On The Hills",
    "sg:city":"Derby",
    "sg:classifiers":[
        {
            "category":"Professional",
            "subcategory":"Management & Consulting",
            "type":"Services"
        }
    ],
    "sg:phone":"+44 1332 864565",
    "sg:postcode":"DE73 1AN",
    "sg:province":"Derbyshire",
    "sg:tags":[
        "consultant",
        "training"
    ],
    "wof:name":"Stanford Consulting Network",
    "wof:placetype":"venue"
},
  "geometry": {"coordinates":[-1.426395,52.831657],"type":"Point"}
}