{
  "type": "Feature",
  "properties": {
    "addr:full":"Club House, Stirling Road, Ely Cardiff Cardiff CF5 4SR",
    "addr:postcode":"cf5 4sr",
    "addr:street":"Club;Stirling Road",
    "iso:country":"GB",
    "sg:address":"Club House, Stirling Road, Ely",
    "sg:city":"Cardiff",
    "sg:classifiers":[
        {
            "category":"Arena",
            "subcategory":"Sports Club",
            "type":"Entertainment"
        }
    ],
    "sg:postcode":"CF5 4SR",
    "sg:province":"Cardiff",
    "wof:name":"Wanderers Association",
    "wof:placetype":"venue"
},
  "geometry": {"coordinates":[-3.2660338879,51.4766769409],"type":"Point"}
}