{
  "type": "Feature",
  "properties": {
    "addr:full":"30-32 Pasture Road Goole East Riding of Yorkshire DN14 6EZ",
    "addr:housenumber":"30-32",
    "addr:postcode":"dn14 6ez",
    "addr:street":"Pasture Road",
    "iso:country":"GB",
    "sg:address":"30-32 Pasture Road",
    "sg:city":"Goole",
    "sg:classifiers":[
        {
            "category":"Home & Garden",
            "subcategory":"Hardware",
            "type":"Retail Goods"
        }
    ],
    "sg:phone":"+44 1405 763431",
    "sg:postcode":"DN14 6EZ",
    "sg:province":"East Riding of Yorkshire",
    "sg:tags":[
        "retailer",
        "lighting"
    ],
    "wof:name":"G S Tune",
    "wof:placetype":"venue"
},
  "geometry": {"coordinates":[-0.8749970198,53.7060050964],"type":"Point"}
}