{
  "type": "Feature",
  "properties": {
    "addr:full":"Mayfield, Mayes Lane, Butt Grn Chelmsford Essex CM2 7RP",
    "addr:postcode":"cm2 7rp",
    "addr:street":"Mayes Lane;Grn",
    "iso:country":"GB",
    "sg:address":"Mayfield, Mayes Lane, Butt Grn",
    "sg:city":"Chelmsford",
    "sg:classifiers":[
        {
            "category":"Farming",
            "subcategory":"Livestock Farm",
            "type":"Manufacturing & Wholesale Goods"
        }
    ],
    "sg:postcode":"CM2 7RP",
    "sg:province":"Essex",
    "sg:tags":[
        "others"
    ],
    "wof:name":"John A Jennings",
    "wof:placetype":"venue"
},
  "geometry": {"coordinates":[0.477891,51.731918],"type":"Point"}
}