{
  "type": "Feature",
  "properties": {
    "iso:country":"GB",
    "sg:address":"134 Market Square, St John Shopping Centre",
    "sg:city":"Liverpool",
    "sg:classifiers":[
        {
            "category":"Shopping",
            "subcategory":"Clothing, Apparel, & Fashions",
            "type":"Retail Goods"
        }
    ],
    "sg:phone":"+44 151 708 7185",
    "sg:postcode":"L1 1LZ",
    "sg:province":"Merseyside",
    "sg:tags":[
        "shop"
    ],
    "wof:name":"Movetop Ltd.",
    "wof:placetype":"venue"
},
  "geometry": {"coordinates":[-2.978481,53.409775],"type":"Point"}
}