{
  "type": "Feature",
  "properties": {
    "iso:country":"GB",
    "sg:address":"10 Park Road, Raunds",
    "sg:city":"Northampton",
    "sg:classifiers":[
        {
            "category":"Government",
            "subcategory":"Post Office",
            "type":"Public Place"
        }
    ],
    "sg:phone":"+44 1933 624079",
    "sg:postcode":"NN9 6JL",
    "sg:province":"Northamptonshire",
    "sg:tags":[
        "window",
        "display",
        "dressing"
    ],
    "wof:name":"Harber Display Ltd.",
    "wof:placetype":"venue"
},
  "geometry": {"coordinates":[-0.532709,52.344181],"type":"Point"}
}