{
  "type": "Feature",
  "properties": {
    "addr:full":"Westgate Centre, 8-10 Main Street Rotherham South Yorkshire S60 1AJ",
    "addr:housenumber":"8-10",
    "addr:postcode":"s60 1aj",
    "addr:street":"Westgate;Main Street",
    "iso:country":"GB",
    "sg:address":"Westgate Centre, 8-10 Main Street",
    "sg:city":"Rotherham",
    "sg:classifiers":[
        {
            "category":"Sports & Exercise",
            "subcategory":"Gym",
            "type":"Entertainment"
        }
    ],
    "sg:phone":"+44 1709 510001",
    "sg:postcode":"S60 1AJ",
    "sg:province":"South Yorkshire",
    "sg:tags":[
        "fitness",
        "health",
        "centre"
    ],
    "wof:name":"The Ultimate Fitness Centres Body Tec Ltd.",
    "wof:placetype":"venue"
},
  "geometry": {"coordinates":[-1.354243,53.429874],"type":"Point"}
}