{
  "type": "Feature",
  "properties": {
    "iso:country":"GB",
    "sg:address":"27 Larch Rd",
    "sg:city":"Milford Haven",
    "sg:classifiers":[
        {
            "category":"Social Services",
            "type":"Services"
        }
    ],
    "sg:phone":"+44 1646 698562",
    "sg:postcode":"SA73 1BY",
    "sg:province":"Pembrokeshire",
    "wof:name":"Larch Road Family Centre",
    "wof:placetype":"venue"
},
  "geometry": {"coordinates":[-5.021162,51.718998],"type":"Point"}
}