{
  "type": "Feature",
  "properties": {
    "iso:country":"GB",
    "sg:address":"Unit 1, Sandy La, Little Rissington",
    "sg:city":"Cheltenham",
    "sg:classifiers":[
        {
            "category":"Education",
            "subcategory":"Music School",
            "type":"Public Place"
        }
    ],
    "sg:phone":"+44 1451 821850",
    "sg:postcode":"GL54 2NB",
    "sg:province":"Gloucestershire",
    "sg:tags":[
        "conservatory"
    ],
    "wof:name":"Craftwood Products Ltd",
    "wof:placetype":"venue"
},
  "geometry": {"coordinates":[-1.710774,51.876011],"type":"Point"}
}