{
  "type": "Feature",
  "properties": {
    "iso:country":"GB",
    "sg:address":"Unit 9 Manor Industrial Estate",
    "sg:city":"Flint",
    "sg:classifiers":[
        {
            "category":"Wholesale",
            "subcategory":"Construction Materials",
            "type":"Manufacturing & Wholesale Goods"
        }
    ],
    "sg:phone":"+44 1352 733568",
    "sg:postcode":"CH6 5UY",
    "sg:province":"Flintshire",
    "sg:tags":[
        "lift"
    ],
    "wof:name":"Lloyds British",
    "wof:placetype":"venue"
},
  "geometry": {"coordinates":[-3.162394,53.265236],"type":"Point"}
}