{
  "type": "Feature",
  "properties": {
    "iso:country":"GB",
    "sg:address":"26 Melton Road",
    "sg:city":"Wymondham",
    "sg:classifiers":[
        {
            "category":"Professional",
            "subcategory":"Management & Consulting",
            "type":"Services"
        }
    ],
    "sg:postcode":"NR18 0DB",
    "sg:province":"Norfolk",
    "sg:tags":[
        "marketing",
        "consultant"
    ],
    "wof:name":"The Jarvis Webster Partnership",
    "wof:placetype":"venue"
},
  "geometry": {"coordinates":[1.110302,52.577175],"type":"Point"}
}