{
  "type": "Feature",
  "properties": {
    "iso:country":"GB",
    "sg:address":"33a Market Place",
    "sg:city":"Doncaster",
    "sg:classifiers":[
        {
            "category":"Recreation",
            "type":"Entertainment"
        }
    ],
    "sg:phone":"+44 1302 360892",
    "sg:postcode":"DN1 1NE",
    "sg:province":"South Yorkshire",
    "sg:tags":[
        "snooker",
        "billiards",
        "pool"
    ],
    "wof:name":"Doncaster Snooker Club",
    "wof:placetype":"venue"
},
  "geometry": {"coordinates":[-1.131869,53.524048],"type":"Point"}
}