{
  "type": "Feature",
  "properties": {
    "iso:country":"GB",
    "sg:address":"28-5 Donaldson St, Kirkintilloch",
    "sg:city":"Glasgow",
    "sg:classifiers":[
        {
            "category":"Building & Trades",
            "subcategory":"Construction",
            "type":"Services"
        }
    ],
    "sg:phone":"+44 141 775 3491",
    "sg:postcode":"G66 1XB",
    "sg:province":"East Dunbartonshire",
    "sg:tags":[
        "roofing"
    ],
    "wof:name":"McPhee Roofing",
    "wof:placetype":"venue"
},
  "geometry": {"coordinates":[-4.15528,55.935169],"type":"Point"}
}