{
  "type": "Feature",
  "properties": {
    "addr:full":"Marsh Lane, Stanstead Abbotts Ware Hertfordshire SG12 8HH",
    "addr:postcode":"sg12 8hh",
    "addr:street":"Marsh Lane",
    "iso:country":"GB",
    "sg:address":"Marsh Lane, Stanstead Abbotts",
    "sg:city":"Ware",
    "sg:classifiers":[
        {
            "category":"Arena",
            "subcategory":"Sports Club",
            "type":"Entertainment"
        }
    ],
    "sg:phone":"+44 1920 870485",
    "sg:postcode":"SG12 8HH",
    "sg:province":"Hertfordshire",
    "wof:name":"Hertford County Yacht Club",
    "wof:placetype":"venue"
},
  "geometry": {"coordinates":[0.0101680001,51.7853927612],"type":"Point"}
}