{
  "type": "Feature",
  "properties": {
    "addr:full":"25 Victoria Road Ruislip Greater London HA4 9AB",
    "addr:housenumber":"25",
    "addr:postcode":"ha4 9ab",
    "addr:street":"Victoria Road",
    "iso:country":"GB",
    "sg:address":"25 Victoria Road",
    "sg:city":"Ruislip",
    "sg:classifiers":[
        {
            "category":"Professional",
            "subcategory":"Engineering",
            "type":"Services"
        }
    ],
    "sg:phone":"+44 1895 673302",
    "sg:postcode":"HA4 9AB",
    "sg:province":"Greater London",
    "sg:tags":[
        "contractor",
        "electrical",
        "engineer"
    ],
    "wof:name":"M S W Engineering Services Ltd.",
    "wof:placetype":"venue"
},
  "geometry": {"coordinates":[-0.412705,51.573071],"type":"Point"}
}