{
  "type": "Feature",
  "properties": {
    "addr:full":"B M P House, 21 Mansion Close, Moulton Park Industrial Estate Northampton Northamptonshire NN3 6RU",
    "addr:housenumber":"21;estate",
    "addr:postcode":"northampton;nn3 6ru",
    "addr:street":"Mansion Close;Park Industrial",
    "iso:country":"GB",
    "sg:address":"B M P House, 21 Mansion Close, Moulton Park Industrial Estate",
    "sg:city":"Northampton",
    "sg:classifiers":[
        {
            "category":"Shopping",
            "subcategory":"Pharmacy",
            "type":"Retail Goods"
        }
    ],
    "sg:phone":"+44 1604 499427",
    "sg:postcode":"NN3 6RU",
    "sg:province":"Northamptonshire",
    "sg:tags":[
        "medical"
    ],
    "wof:name":"Beaver Medical Plc",
    "wof:placetype":"venue"
},
  "geometry": {"coordinates":[-0.872449,52.277611],"type":"Point"}
}