{
  "type": "Feature",
  "properties": {
    "iso:country":"GB",
    "sg:address":"72 Elder Rd, Bisley",
    "sg:city":"Woking",
    "sg:classifiers":[
        {
            "category":"Building & Trades",
            "subcategory":"Construction",
            "type":"Services"
        }
    ],
    "sg:phone":"+44 1483 475544",
    "sg:postcode":"GU24 9SA",
    "sg:province":"Surrey",
    "sg:tags":[
        "builder"
    ],
    "wof:name":"Stillwell Bros",
    "wof:placetype":"venue"
},
  "geometry": {"coordinates":[-0.6320660114,51.328338623],"type":"Point"}
}