{
  "type": "Feature",
  "properties": {
    "iso:country":"GB",
    "sg:address":"8-9 Stephen Mews",
    "sg:city":"London",
    "sg:classifiers":[
        {
            "category":"Professional",
            "subcategory":"Art Services",
            "type":"Services"
        }
    ],
    "sg:phone":"+44 20 7436 5535",
    "sg:postcode":"W1T 1AF",
    "sg:province":"Greater London",
    "sg:tags":[
        "consultant",
        "design"
    ],
    "wof:name":"The Oyster Group",
    "wof:placetype":"venue"
},
  "geometry": {"coordinates":[-0.132569,51.518204],"type":"Point"}
}