{
  "type": "Feature",
  "properties": {
    "iso:country":"GB",
    "sg:address":"The Old Mill Colne Valley, Alvington",
    "sg:city":"Lydney",
    "sg:classifiers":[
        {
            "category":"Sports & Exercise",
            "subcategory":"Race Track",
            "type":"Entertainment"
        }
    ],
    "sg:phone":"+44 1594 528185",
    "sg:postcode":"GL15 6AD",
    "sg:province":"Gloucestershire",
    "sg:tags":[
        "motor"
    ],
    "wof:name":"Simpson Engineering",
    "wof:placetype":"venue"
},
  "geometry": {"coordinates":[-2.5760490894,51.7048912048],"type":"Point"}
}