{
  "type": "Feature",
  "properties": {
    "addr:full":"1 Vallance Rd Whitechapel Greater London E1 5HS",
    "addr:housenumber":"1",
    "addr:postcode":"e1 5hs",
    "addr:street":"Vallance Rd",
    "iso:country":"GB",
    "sg:address":"1 Vallance Rd",
    "sg:city":"Whitechapel",
    "sg:classifiers":[
        {
            "category":"Restaurant",
            "type":"Food & Drink"
        }
    ],
    "sg:phone":"+44 20 7247 2623",
    "sg:postcode":"E1 5HS",
    "sg:province":"Greater London",
    "sg:tags":[
        "indian"
    ],
    "wof:name":"Shalamar Restaurant",
    "wof:placetype":"venue"
},
  "geometry": {"coordinates":[-0.0629549995,51.5185241699],"type":"Point"}
}