{
  "type": "Feature",
  "properties": {
    "addr:full":"183 Northolt Road Harrow Greater London HA2 0LY",
    "addr:housenumber":"183",
    "addr:postcode":"ha2 0ly",
    "addr:street":"Northolt Road",
    "iso:country":"GB",
    "sg:address":"183 Northolt Road",
    "sg:city":"Harrow",
    "sg:classifiers":[
        {
            "category":"Taxi",
            "type":"Transportation"
        }
    ],
    "sg:phone":"+44 20 8422 2222",
    "sg:postcode":"HA2 0LY",
    "sg:province":"Greater London",
    "sg:tags":[
        "mini",
        "cab"
    ],
    "wof:name":"Harrow Mini Cabs",
    "wof:placetype":"venue"
},
  "geometry": {"coordinates":[-0.351127,51.565933],"type":"Point"}
}