{
  "type": "Feature",
  "properties": {
    "iso:country":"GB",
    "sg:address":"1 Priory Centre",
    "sg:city":"Worksop",
    "sg:classifiers":[
        {
            "category":"Shopping",
            "subcategory":"Thrift Store",
            "type":"Retail Goods"
        }
    ],
    "sg:phone":"+44 1909 531063",
    "sg:postcode":"S80 1JR",
    "sg:province":"Nottinghamshire",
    "sg:tags":[
        "shop",
        "charity"
    ],
    "wof:name":"Quit Charity Shop",
    "wof:placetype":"venue"
},
  "geometry": {"coordinates":[-1.123189,53.30661],"type":"Point"}
}