{
  "type": "Feature",
  "properties": {
    "addr:full":"9 Tyr Owen Row, Cwmavon Port Talbot Neath Port Talbot SA12 9BE",
    "addr:housenumber":"9",
    "addr:postcode":"sa12 9be",
    "addr:street":"Tyr Owen Row",
    "iso:country":"GB",
    "sg:address":"9 Tyr Owen Row, Cwmavon",
    "sg:city":"Port Talbot",
    "sg:classifiers":[
        {
            "category":"Shopping",
            "subcategory":"News",
            "type":"Retail Goods"
        }
    ],
    "sg:postcode":"SA12 9BE",
    "sg:province":"Neath Port Talbot",
    "sg:tags":[
        "newsagent"
    ],
    "wof:name":"George F Richardson",
    "wof:placetype":"venue"
},
  "geometry": {"coordinates":[-3.8023691177,51.5913848877],"type":"Point"}
}