{
  "type": "Feature",
  "properties": {
    "addr:full":"6 -10 Axwell House, Westerton Rd Broxburn City of Edinburgh EH52 5AU",
    "addr:housenumber":"-10",
    "addr:postcode":"eh52 5au",
    "addr:street":"6;Westerton Rd",
    "iso:country":"GB",
    "sg:address":"6 -10 Axwell House, Westerton Rd",
    "sg:city":"Broxburn",
    "sg:classifiers":[
        {
            "category":"Professional",
            "subcategory":"Employment Agencies",
            "type":"Services"
        }
    ],
    "sg:phone":"+44 1506 507000",
    "sg:postcode":"EH52 5AU",
    "sg:province":"City of Edinburgh",
    "sg:tags":[
        "consultant"
    ],
    "wof:name":"Driver Hire Workforce",
    "wof:placetype":"venue"
},
  "geometry": {"coordinates":[-3.471884,55.934235],"type":"Point"}
}