{
  "type": "Feature",
  "properties": {
    "iso:country":"GB",
    "sg:address":"22 Bowland Rd",
    "sg:city":"Stockport",
    "sg:classifiers":[
        {
            "category":"Personal",
            "subcategory":"Beauty Salon",
            "type":"Services"
        }
    ],
    "sg:phone":"+44 161 430 4720",
    "sg:postcode":"SK6 1LJ",
    "sg:province":"Cheshire",
    "sg:tags":[
        "unisex",
        "hairdresser"
    ],
    "wof:name":"Raffles",
    "wof:placetype":"venue"
},
  "geometry": {"coordinates":[-2.091745,53.426613],"type":"Point"}
}