{
  "type": "Feature",
  "properties": {
    "addr:full":"26 Dawberry Rd Birmingham West Midlands B14 6RX",
    "addr:housenumber":"26",
    "addr:postcode":"b14 6rx",
    "addr:street":"Dawberry Rd",
    "iso:country":"GB",
    "sg:address":"26 Dawberry Rd",
    "sg:city":"Birmingham",
    "sg:classifiers":[
        {
            "category":"Home & Garden",
            "subcategory":"Building Materials",
            "type":"Retail Goods"
        }
    ],
    "sg:postcode":"B14 6RX",
    "sg:province":"West Midlands",
    "sg:tags":[
        "insulation",
        "installers"
    ],
    "wof:name":"Plaster Crafts & Designs",
    "wof:placetype":"venue"
},
  "geometry": {"coordinates":[-1.910104,52.422661],"type":"Point"}
}