{
  "type": "Feature",
  "properties": {
    "addr:full":"30 Vale Royal Holloway Greater London N7 9AP",
    "addr:housenumber":"30",
    "addr:postcode":"n7 9ap",
    "addr:street":"Vale Royal",
    "iso:country":"GB",
    "sg:address":"30 Vale Royal",
    "sg:city":"Holloway",
    "sg:classifiers":[
        {
            "category":"Food & Beverages",
            "subcategory":"Meat & Fish",
            "type":"Retail Goods"
        }
    ],
    "sg:phone":"+44 20 7700 3622",
    "sg:postcode":"N7 9AP",
    "sg:province":"Greater London",
    "sg:tags":[
        "butcher"
    ],
    "wof:name":"D & R Butchers",
    "wof:placetype":"venue"
},
  "geometry": {"coordinates":[-0.123852998,51.5419540405],"type":"Point"}
}