{
  "type": "Feature",
  "properties": {
    "addr:full":"23 High Street Brentwood Essex CM14 4RG",
    "addr:housenumber":"23",
    "addr:postcode":"cm14 4rg",
    "addr:street":"High Street",
    "iso:country":"GB",
    "sg:address":"23 High Street",
    "sg:city":"Brentwood",
    "sg:classifiers":[
        {
            "category":"Restaurant",
            "type":"Food & Drink"
        }
    ],
    "sg:phone":"+44 1277 214111",
    "sg:postcode":"CM14 4RG",
    "sg:province":"Essex",
    "sg:tags":[
        "italian"
    ],
    "wof:name":"Cafe Uno",
    "wof:placetype":"venue"
},
  "geometry": {"coordinates":[0.3045229912,51.6210823059],"type":"Point"}
}