{
  "type": "Feature",
  "properties": {
    "addr:full":"266 Oxford Street London Greater London W1N 9DD",
    "addr:housenumber":"266",
    "addr:postcode":"w1n 9dd",
    "addr:street":"Oxford Street",
    "iso:country":"GB",
    "sg:address":"266 Oxford Street",
    "sg:city":"London",
    "sg:classifiers":[
        {
            "category":"Shopping",
            "subcategory":"Clothing, Apparel, & Fashions",
            "type":"Retail Goods"
        }
    ],
    "sg:phone":"+44 20 7408 1131",
    "sg:postcode":"W1N 9DD",
    "sg:province":"Greater London",
    "sg:tags":[
        "shop"
    ],
    "wof:name":"Ann Harvey",
    "wof:placetype":"venue"
},
  "geometry": {"coordinates":[-0.1438000053,51.5151863098],"type":"Point"}
}