{
  "type": "Feature",
  "properties": {
    "addr:full":"16 Youngs Park Road, Goodrington Paignton Devon TQ4 6BU",
    "addr:housenumber":"16",
    "addr:postcode":"tq4 6bu",
    "addr:street":"Youngs Park Road",
    "iso:country":"GB",
    "sg:address":"16 Youngs Park Road, Goodrington",
    "sg:city":"Paignton",
    "sg:classifiers":[
        {
            "category":"Travel",
            "subcategory":"Hotels & Motels",
            "type":"Entertainment"
        }
    ],
    "sg:postcode":"TQ4 6BU",
    "sg:province":"Devon",
    "wof:name":"The Cranmere Hotel",
    "wof:placetype":"venue"
},
  "geometry": {"coordinates":[-3.562621,50.428181],"type":"Point"}
}