{
  "type": "Feature",
  "properties": {
    "iso:country":"GB",
    "sg:address":"Oak Ho, Waterside Clo",
    "sg:city":"Crawley",
    "sg:classifiers":[
        {
            "category":"Social Services",
            "type":"Services"
        }
    ],
    "sg:phone":"+44 1293 560078",
    "sg:postcode":"RH11 6BL",
    "sg:province":"West Sussex",
    "sg:tags":[
        "need",
        "disability",
        "special"
    ],
    "wof:name":"Chichester Priority Care Services N H S Trust",
    "wof:placetype":"venue"
},
  "geometry": {"coordinates":[-0.226778,51.107296],"type":"Point"}
}