{
  "type": "Feature",
  "properties": {
    "addr:full":"Hall Farm Garage, Broad Lane Leeds West Yorkshire LS5 3EB",
    "addr:postcode":"ls5 3eb",
    "addr:street":"Hall;Broad Lane",
    "iso:country":"GB",
    "sg:address":"Hall Farm Garage, Broad Lane",
    "sg:city":"Leeds",
    "sg:classifiers":[
        {
            "category":"Retail",
            "subcategory":"Auto Repair",
            "type":"Services"
        }
    ],
    "sg:phone":"+44 113 275 8712",
    "sg:postcode":"LS5 3EB",
    "sg:province":"West Yorkshire",
    "sg:tags":[
        "modification",
        "garage"
    ],
    "wof:name":"Miller (Leeds) Ltd.",
    "wof:placetype":"venue"
},
  "geometry": {"coordinates":[-1.60818,53.81501],"type":"Point"}
}