{
  "type": "Feature",
  "properties": {
    "addr:full":"23 Ferndale Avenue Chertsey Surrey KT16 9RB",
    "addr:housenumber":"23",
    "addr:postcode":"kt16 9rb",
    "addr:street":"Ferndale Avenue",
    "iso:country":"GB",
    "sg:address":"23 Ferndale Avenue",
    "sg:city":"Chertsey",
    "sg:classifiers":[
        {
            "category":"Shopping",
            "subcategory":"Computers & Home Electronics",
            "type":"Retail Goods"
        }
    ],
    "sg:phone":"+44 1932 569448",
    "sg:postcode":"KT16 9RB",
    "sg:province":"Surrey",
    "sg:tags":[
        "consumables"
    ],
    "wof:name":"Evalex Eurotoner Ltd.",
    "wof:placetype":"venue"
},
  "geometry": {"coordinates":[-0.518614,51.376667],"type":"Point"}
}