{
  "type": "Feature",
  "properties": {
    "addr:full":"28 Northcote Street Northampton Northamptonshire NN2 6BG",
    "addr:housenumber":"28",
    "addr:postcode":"nn2 6bg",
    "addr:street":"Northcote Street",
    "iso:country":"GB",
    "sg:address":"28 Northcote Street",
    "sg:city":"Northampton",
    "sg:classifiers":[
        {
            "category":"Building & Trades",
            "subcategory":"Construction",
            "type":"Services"
        }
    ],
    "sg:phone":"+44 1604 631216",
    "sg:postcode":"NN2 6BG",
    "sg:province":"Northamptonshire",
    "sg:tags":[
        "builder"
    ],
    "wof:name":"B L Greenfield",
    "wof:placetype":"venue"
},
  "geometry": {"coordinates":[-0.895849,52.257404],"type":"Point"}
}