{
  "type": "Feature",
  "properties": {
    "iso:country":"GB",
    "sg:address":"65-69 Nether Hall Road",
    "sg:city":"Doncaster",
    "sg:classifiers":[
        {
            "category":"Home & Garden",
            "subcategory":"Carpets & Floor Coverings",
            "type":"Retail Goods"
        }
    ],
    "sg:phone":"+44 1302 363101",
    "sg:postcode":"DN1 2QA",
    "sg:province":"South Yorkshire",
    "sg:tags":[
        "textile",
        "floorcoverings"
    ],
    "wof:name":"Stephen Jones",
    "wof:placetype":"venue"
},
  "geometry": {"coordinates":[-1.128509,53.525742],"type":"Point"}
}