{
  "type": "Feature",
  "properties": {
    "iso:country":"GB",
    "sg:address":"59 High Road, Chilwell",
    "sg:city":"Nottingham",
    "sg:classifiers":[
        {
            "category":"Real Estate",
            "subcategory":"Real Estate Agent",
            "type":"Services"
        }
    ],
    "sg:phone":"+44 115 925 7766",
    "sg:postcode":"NG9 4AJ",
    "sg:province":"Nottinghamshire",
    "wof:name":"Barton Transport Plc",
    "wof:placetype":"venue"
},
  "geometry": {"coordinates":[-1.223289,52.920956],"type":"Point"}
}