{
  "type": "Feature",
  "properties": {
    "addr:full":"190 Scraptoft Lane Leicester Leicestershire LE5 1HX",
    "addr:housenumber":"190",
    "addr:postcode":"le5 1hx",
    "addr:street":"Scraptoft Lane",
    "iso:country":"GB",
    "sg:address":"190 Scraptoft Lane",
    "sg:city":"Leicester",
    "sg:classifiers":[
        {
            "category":"Building & Trades",
            "subcategory":"Plumbing",
            "type":"Services"
        }
    ],
    "sg:phone":"+44 116 243 1301",
    "sg:postcode":"LE5 1HX",
    "sg:province":"Leicestershire",
    "sg:tags":[
        "plumber",
        "heating"
    ],
    "wof:name":"Eric R Gibbins",
    "wof:placetype":"venue"
},
  "geometry": {"coordinates":[-1.078849,52.64267],"type":"Point"}
}