{
  "type": "Feature",
  "properties": {
    "addr:full":"Clifford House, Towcester Road, Bow London Greater London E3 3ND",
    "addr:postcode":"e3 3nd",
    "addr:street":"Towcester Road",
    "iso:country":"GB",
    "sg:address":"Clifford House, Towcester Road, Bow",
    "sg:city":"London",
    "sg:classifiers":[
        {
            "category":"Building & Trades",
            "subcategory":"Construction",
            "type":"Services"
        }
    ],
    "sg:postcode":"E3 3ND",
    "sg:province":"Greater London",
    "sg:tags":[
        "demolition",
        "contractor"
    ],
    "wof:name":"Clifford Devlin (Holdings) Ltd.",
    "wof:placetype":"venue"
},
  "geometry": {"coordinates":[-0.0113599999,51.5214805603],"type":"Point"}
}