{
  "type": "Feature",
  "properties": {
    "addr:full":"116 Narborough Road Leicester Leicestershire LE3 0BS",
    "addr:housenumber":"116",
    "addr:postcode":"le3 0bs",
    "addr:street":"Narborough Road",
    "iso:country":"GB",
    "sg:address":"116 Narborough Road",
    "sg:city":"Leicester",
    "sg:classifiers":[
        {
            "category":"Wholesale",
            "subcategory":"Machinery & Supplies",
            "type":"Manufacturing & Wholesale Goods"
        },
        {
            "category":"Shopping",
            "subcategory":"Crafts & Fabrics",
            "type":"Retail Goods"
        }
    ],
    "sg:phone":"+44 116 254 9029",
    "sg:postcode":"LE3 0BS",
    "sg:province":"Leicestershire",
    "sg:tags":[
        "machine",
        "supplier",
        "sewing",
        "knitting"
    ],
    "wof:name":"Supreme Sewing & Knitting Machines Ltd",
    "wof:placetype":"venue"
},
  "geometry": {"coordinates":[-1.150336,52.627232],"type":"Point"}
}