{
  "type": "Feature",
  "properties": {
    "addr:full":"96 High Street, Selsey Chichester West Sussex PO20 0QG",
    "addr:housenumber":"96",
    "addr:postcode":"po20 0qg",
    "addr:street":"High Street",
    "iso:country":"GB",
    "sg:address":"96 High Street, Selsey",
    "sg:city":"Chichester",
    "sg:classifiers":[
        {
            "category":"Retail",
            "subcategory":"Auto Repair",
            "type":"Services"
        }
    ],
    "sg:phone":"+44 1243 607855",
    "sg:postcode":"PO20 0QG",
    "sg:province":"West Sussex",
    "sg:tags":[
        "modification",
        "garage",
        "related"
    ],
    "wof:name":"Hillfield Garage",
    "wof:placetype":"venue"
},
  "geometry": {"coordinates":[-0.7912889719,50.7335014343],"type":"Point"}
}