{
  "type": "Feature",
  "properties": {
    "iso:country":"GB",
    "sg:address":"35 York Road",
    "sg:city":"Stamford",
    "sg:classifiers":[
        {
            "category":"Building & Trades",
            "subcategory":"Plumbing",
            "type":"Services"
        }
    ],
    "sg:phone":"+44 1780 753279",
    "sg:postcode":"PE9 1LL",
    "sg:province":"Cambridgeshire",
    "sg:tags":[
        "heating"
    ],
    "wof:name":"Tony Greaves Plumbing & Heating",
    "wof:placetype":"venue"
},
  "geometry": {"coordinates":[-0.483878,52.656143],"type":"Point"}
}