{
  "type": "Feature",
  "properties": {
    "addr:full":"240 Bradford Road Liversedge West Yorkshire WF15 6EF",
    "addr:housenumber":"240",
    "addr:postcode":"wf15 6ef",
    "addr:street":"Bradford Road",
    "iso:country":"GB",
    "sg:address":"240 Bradford Road",
    "sg:city":"Liversedge",
    "sg:classifiers":[
        {
            "category":"Food & Beverages",
            "subcategory":"Meat & Fish",
            "type":"Retail Goods"
        }
    ],
    "sg:postcode":"WF15 6EF",
    "sg:province":"West Yorkshire",
    "sg:tags":[
        "butcher"
    ],
    "wof:name":"Jackson Butchers",
    "wof:placetype":"venue"
},
  "geometry": {"coordinates":[-1.6937170029,53.7146377563],"type":"Point"}
}