{
  "type": "Feature",
  "properties": {
    "iso:country":"GB",
    "sg:address":"Norwich Union House, 31 Waterloo Road",
    "sg:city":"Wolverhampton",
    "sg:classifiers":[
        {
            "category":"Professional",
            "subcategory":"Employment Agencies",
            "type":"Services"
        }
    ],
    "sg:phone":"+44 1902 717581",
    "sg:postcode":"WV1 4DJ",
    "sg:province":"West Midlands",
    "sg:tags":[
        "consultant"
    ],
    "wof:name":"The Pyrah Harris Partnership",
    "wof:placetype":"venue"
},
  "geometry": {"coordinates":[-2.1328310966,52.587348938],"type":"Point"}
}