{
  "type": "Feature",
  "properties": {
    "addr:full":"Charter House, 29a London Road Croydon Surrey CR0 2RE",
    "addr:housenumber":"29a",
    "addr:postcode":"cr0 2re",
    "addr:street":"Charter;London Road",
    "iso:country":"GB",
    "sg:address":"Charter House, 29a London Road",
    "sg:city":"Croydon",
    "sg:classifiers":[
        {
            "category":"Professional",
            "subcategory":"Employment Agencies",
            "type":"Services"
        }
    ],
    "sg:phone":"+44 20 8760 9929",
    "sg:postcode":"CR0 2RE",
    "sg:province":"Surrey",
    "sg:tags":[
        "cv"
    ],
    "wof:name":"Kings Business Services",
    "wof:placetype":"venue"
},
  "geometry": {"coordinates":[-0.1045309976,51.3797416687],"type":"Point"}
}