{
  "type": "Feature",
  "properties": {
    "addr:full":"Princes House 5 Shandwick Place Edinburgh City of Edinburgh EH2 4RG",
    "addr:housenumber":"5",
    "addr:postcode":"eh2 4rg",
    "addr:street":"Shandwick Place Edinburgh",
    "iso:country":"GB",
    "sg:address":"Princes House 5 Shandwick Place",
    "sg:city":"Edinburgh",
    "sg:classifiers":[
        {
            "category":"Organizations",
            "subcategory":"Non-profit Organization",
            "type":"Services"
        }
    ],
    "sg:postcode":"EH2 4RG",
    "sg:province":"City of Edinburgh",
    "sg:tags":[
        "organisation",
        "voluntary",
        "charity"
    ],
    "wof:name":"James Powell Uk Trust",
    "wof:placetype":"venue"
},
  "geometry": {"coordinates":[-3.2093141079,55.949836731],"type":"Point"}
}