{
  "type": "Feature",
  "properties": {
    "addr:full":"Coventry Road Bedworth Warwickshire CV12 8NN",
    "addr:postcode":"cv12 8nn",
    "addr:street":"Coventry Road",
    "iso:country":"GB",
    "sg:address":"Coventry Road",
    "sg:city":"Bedworth",
    "sg:classifiers":[
        {
            "category":"Arena",
            "subcategory":"Sports Club",
            "type":"Entertainment"
        }
    ],
    "sg:phone":"+44 24 7631 4302",
    "sg:postcode":"CV12 8NN",
    "sg:province":"Warwickshire",
    "sg:tags":[
        "ground"
    ],
    "wof:name":"Bedworth United Football & Social Club",
    "wof:placetype":"venue"
},
  "geometry": {"coordinates":[-1.476929,52.473961],"type":"Point"}
}