{
  "type": "Feature",
  "properties": {
    "addr:full":"Thornton Hall, The Village, Thornton-le-moors Chester Cheshire CH2 4HU",
    "addr:postcode":"ch2 4hu",
    "addr:street":"The;Chester",
    "iso:country":"GB",
    "sg:address":"Thornton Hall, The Village, Thornton-le-moors",
    "sg:city":"Chester",
    "sg:classifiers":[
        {
            "category":"Farming",
            "subcategory":"Dairy Farm",
            "type":"Manufacturing & Wholesale Goods"
        },
        {
            "category":"Farming",
            "subcategory":"Livestock Farm",
            "type":"Manufacturing & Wholesale Goods"
        }
    ],
    "sg:postcode":"CH2 4HU",
    "sg:province":"Cheshire",
    "sg:tags":[
        "others",
        "farmer"
    ],
    "wof:name":"R W & J N Peate",
    "wof:placetype":"venue"
},
  "geometry": {"coordinates":[-2.838824,53.266834],"type":"Point"}
}