{
  "type": "Feature",
  "properties": {
    "addr:full":"59 Chatsworth Avenue Haslemere Hampshire GU27 1ED",
    "addr:housenumber":"59",
    "addr:postcode":"gu27 1ed",
    "addr:street":"Chatsworth Avenue",
    "iso:country":"GB",
    "sg:address":"59 Chatsworth Avenue",
    "sg:city":"Haslemere",
    "sg:classifiers":[
        {
            "category":"Building & Trades",
            "subcategory":"Cleaning & Sanitation",
            "type":"Services"
        },
        {
            "category":"Professional",
            "subcategory":"Business Services",
            "type":"Services"
        }
    ],
    "sg:phone":"+44 1428 652528",
    "sg:postcode":"GU27 1ED",
    "sg:province":"Hampshire",
    "sg:tags":[
        "shop",
        "contracting",
        "commercial"
    ],
    "wof:name":"A J CLEANING SERVICES",
    "wof:placetype":"venue"
},
  "geometry": {"coordinates":[-0.7114779949,51.097946167],"type":"Point"}
}