{
  "type": "Feature",
  "properties": {
    "addr:full":"14 Sydenham Road London Greater London SE26 5QT",
    "addr:housenumber":"14",
    "addr:postcode":"se26 5qt",
    "addr:street":"Sydenham Road",
    "iso:country":"GB",
    "sg:address":"14 Sydenham Road",
    "sg:city":"London",
    "sg:classifiers":[
        {
            "category":"Banks & Credit Unions",
            "subcategory":"Bank",
            "type":"Services"
        }
    ],
    "sg:phone":"+44 20 8919 4333",
    "sg:postcode":"SE26 5QT",
    "sg:province":"Greater London",
    "wof:name":"Hsbc Bank Plc",
    "wof:placetype":"venue"
},
  "geometry": {"coordinates":[-0.0539360009,51.4263687134],"type":"Point"}
}