{
  "type": "Feature",
  "properties": {
    "addr:full":"Friston Business Centre, Aldeburgh Rd, Friston Saxmundham Suffolk IP17 1NP",
    "addr:housenumber":"friston",
    "addr:postcode":"ip17 1np",
    "addr:street":"Aldeburgh Rd",
    "iso:country":"GB",
    "sg:address":"Friston Business Centre, Aldeburgh Rd, Friston",
    "sg:city":"Saxmundham",
    "sg:classifiers":[
        {
            "category":"Food & Beverages",
            "subcategory":"Supermarket",
            "type":"Retail Goods"
        }
    ],
    "sg:phone":"+44 1728 689197",
    "sg:postcode":"IP17 1NP",
    "sg:province":"Suffolk",
    "sg:tags":[
        "frozen"
    ],
    "wof:name":"Lawncourt Harvest",
    "wof:placetype":"venue"
},
  "geometry": {"coordinates":[1.4895329475,52.2167129517],"type":"Point"}
}