{
  "type": "Feature",
  "properties": {
    "addr:full":"5 Birkdale Mews, Liverpool Rd Southport Lancashire PR8 4AS",
    "addr:housenumber":"5",
    "addr:postcode":"pr8 4as",
    "addr:street":"Birkdale Mews Liverpool Rd",
    "iso:country":"GB",
    "sg:address":"5 Birkdale Mews, Liverpool Rd",
    "sg:city":"Southport",
    "sg:classifiers":[
        {
            "category":"Professional",
            "subcategory":"Art Services",
            "type":"Services"
        }
    ],
    "sg:phone":"+44 1704 566642",
    "sg:postcode":"PR8 4AS",
    "sg:province":"Lancashire",
    "sg:tags":[
        "graphic",
        "designer"
    ],
    "wof:name":"Allied Communications",
    "wof:placetype":"venue"
},
  "geometry": {"coordinates":[-3.006304,53.647915],"type":"Point"}
}