{
  "type": "Feature",
  "properties": {
    "addr:full":"82 Park Street London Greater London W1K 6NH",
    "addr:housenumber":"82",
    "addr:postcode":"w1k 6nh",
    "addr:street":"Park Street",
    "iso:country":"GB",
    "sg:address":"82 Park Street",
    "sg:city":"London",
    "sg:classifiers":[
        {
            "category":"Real Estate",
            "subcategory":"Real Estate Agent",
            "type":"Services"
        }
    ],
    "sg:phone":"+44 20 7409 3080",
    "sg:postcode":"W1K 6NH",
    "sg:province":"Greater London",
    "wof:name":"Blandford Goldsmith & Co. Ltd.",
    "wof:placetype":"venue"
},
  "geometry": {"coordinates":[-0.1547809988,51.5116615295],"type":"Point"}
}