{
  "type": "Feature",
  "properties": {
    "addr:full":"18 Wyatts Lane, Walton Stowe London Greater London E17 3JD",
    "addr:housenumber":"18",
    "addr:postcode":"e17 3jd",
    "addr:street":"Wyatts Lane",
    "iso:country":"GB",
    "sg:address":"18 Wyatts Lane, Walton Stowe",
    "sg:city":"London",
    "sg:classifiers":[
        {
            "category":"Home & Garden",
            "subcategory":"Carpets & Floor Coverings",
            "type":"Retail Goods"
        }
    ],
    "sg:phone":"+44 20 8926 7488",
    "sg:postcode":"E17 3JD",
    "sg:province":"Greater London",
    "sg:tags":[
        "cleaner",
        "upholstery"
    ],
    "wof:name":"Joseph's Carpet & Upholstery Cleaning Service",
    "wof:placetype":"venue"
},
  "geometry": {"coordinates":[-0.005581,51.58997],"type":"Point"}
}