{
  "type": "Feature",
  "properties": {
    "addr:full":"Drudge Road, Gorleston Great Yarmouth Norfolk NR31 6BD",
    "addr:postcode":"nr31 6bd",
    "addr:street":"Drudge Road",
    "iso:country":"GB",
    "sg:address":"Drudge Road, Gorleston",
    "sg:city":"Great Yarmouth",
    "sg:classifiers":[
        {
            "category":"Shopping",
            "subcategory":"Computers & Home Electronics",
            "type":"Retail Goods"
        }
    ],
    "sg:phone":"+44 1493 650194",
    "sg:postcode":"NR31 6BD",
    "sg:province":"Norfolk",
    "sg:tags":[
        "equipment",
        "radio"
    ],
    "wof:name":"Anglia Telecommunications",
    "wof:placetype":"venue"
},
  "geometry": {"coordinates":[1.7265150547,52.5690307617],"type":"Point"}
}