{
  "type": "Feature",
  "properties": {
    "addr:full":"64 Coombe Rd Kingston Upon Thames Greater London KT2 7AE",
    "addr:housenumber":"64",
    "addr:postcode":"kt2 7ae",
    "addr:street":"Coombe Rd",
    "iso:country":"GB",
    "sg:address":"64 Coombe Rd",
    "sg:city":"Kingston Upon Thames",
    "sg:classifiers":[
        {
            "category":"Food & Beverages",
            "subcategory":"Liquor & Beverages",
            "type":"Retail Goods"
        }
    ],
    "sg:phone":"+44 20 8546 9398",
    "sg:postcode":"KT2 7AE",
    "sg:province":"Greater London",
    "sg:tags":[
        "beer",
        "spirit",
        "wines"
    ],
    "wof:name":"Unwins Wine Merchants",
    "wof:placetype":"venue"
},
  "geometry": {"coordinates":[-0.2864440084,51.4124832153],"type":"Point"}
}