{
  "type": "Feature",
  "properties": {
    "addr:full":"The Old Workshops Abingdon Oxfordshire OX13 6QU",
    "addr:postcode":"ox13 6qu",
    "iso:country":"GB",
    "sg:address":"The Old Workshops",
    "sg:city":"Abingdon",
    "sg:classifiers":[
        {
            "category":"Retail",
            "subcategory":"Auto Repair",
            "type":"Services"
        }
    ],
    "sg:postcode":"OX13 6QU",
    "sg:province":"Oxfordshire",
    "sg:tags":[
        "modification",
        "garage"
    ],
    "wof:name":"Lewis Auto Services",
    "wof:placetype":"venue"
},
  "geometry": {"coordinates":[-1.3432090282,51.6689949036],"type":"Point"}
}