{
  "type": "Feature",
  "properties": {
    "iso:country":"GB",
    "sg:address":"Smithy Bridge Road",
    "sg:city":"Littleborough",
    "sg:classifiers":[
        {
            "category":"Government",
            "subcategory":"Post Office",
            "type":"Public Place"
        },
        {
            "category":"Manufacturing",
            "subcategory":"Building Materials",
            "type":"Manufacturing & Wholesale Goods"
        }
    ],
    "sg:phone":"+44 1706 378185",
    "sg:postcode":"OL15 0DY",
    "sg:province":"Lancashire",
    "sg:tags":[
        "merchant",
        "builder"
    ],
    "wof:name":"J A Mills & Sons (Smithybridge) Ltd.",
    "wof:placetype":"venue"
},
  "geometry": {"coordinates":[-2.112809,53.633217],"type":"Point"}
}