{
  "type": "Feature",
  "properties": {
    "addr:full":"60 Quantock Road, Long Eaton Nottingham Derbyshire NG10 4GZ",
    "addr:housenumber":"60",
    "addr:postcode":"ng10 4gz",
    "addr:street":"Quantock Road",
    "iso:country":"GB",
    "sg:address":"60 Quantock Road, Long Eaton",
    "sg:city":"Nottingham",
    "sg:classifiers":[
        {
            "category":"Retail",
            "subcategory":"Driving School",
            "type":"Services"
        },
        {
            "category":"Education",
            "subcategory":"School",
            "type":"Public Place"
        }
    ],
    "sg:phone":"+44 115 973 5180",
    "sg:postcode":"NG10 4GZ",
    "sg:province":"Derbyshire",
    "sg:tags":[
        "local",
        "authority"
    ],
    "wof:name":"T S M Driving School",
    "wof:placetype":"venue"
},
  "geometry": {"coordinates":[-1.298761,52.904346],"type":"Point"}
}