{
  "type": "Feature",
  "properties": {
    "iso:country":"GB",
    "sg:address":"44 Calamint Road",
    "sg:city":"Witham",
    "sg:classifiers":[
        {
            "category":"Building & Trades",
            "subcategory":"Construction",
            "type":"Services"
        }
    ],
    "sg:phone":"+44 1376 512530",
    "sg:postcode":"CM8 2XU",
    "sg:province":"Essex",
    "sg:tags":[
        "roofing"
    ],
    "wof:name":"Tryus Construction",
    "wof:placetype":"venue"
},
  "geometry": {"coordinates":[0.622671,51.808155],"type":"Point"}
}