{
  "type": "Feature",
  "properties": {
    "iso:country":"GB",
    "sg:address":"1 Deane Av",
    "sg:city":"Gillingham",
    "sg:classifiers":[
        {
            "category":"Banks & Credit Unions",
            "subcategory":"Investment Brokerage",
            "type":"Services"
        }
    ],
    "sg:phone":"+44 1747 822447",
    "sg:postcode":"SP8 4SH",
    "sg:province":"Dorset",
    "sg:tags":[
        "contractor"
    ],
    "wof:name":"Merritt T B & L E",
    "wof:placetype":"venue"
},
  "geometry": {"coordinates":[-2.284501,51.036762],"type":"Point"}
}