{
  "type": "Feature",
  "properties": {
    "iso:country":"GB",
    "sg:address":"30 Denton Rd",
    "sg:city":"Wokingham",
    "sg:classifiers":[
        {
            "category":"Retail",
            "subcategory":"Veterinary Services",
            "type":"Services"
        }
    ],
    "sg:phone":"+44 118 978 6086",
    "sg:postcode":"RG40 2DX",
    "sg:province":"Berkshire",
    "sg:tags":[
        "surgeon"
    ],
    "wof:name":"D Spackman",
    "wof:placetype":"venue"
},
  "geometry": {"coordinates":[-0.831691,51.409824],"type":"Point"}
}