{
  "type": "Feature",
  "properties": {
    "addr:full":"35 Jansel Square Aylesbury Buckinghamshire HP21 7ET",
    "addr:housenumber":"35",
    "addr:postcode":"hp21 7et",
    "addr:street":"Jansel Square",
    "iso:country":"GB",
    "sg:address":"35 Jansel Square",
    "sg:city":"Aylesbury",
    "sg:classifiers":[
        {
            "category":"Shopping",
            "subcategory":"News",
            "type":"Retail Goods"
        }
    ],
    "sg:phone":"+44 1296 395677",
    "sg:postcode":"HP21 7ET",
    "sg:province":"Buckinghamshire",
    "sg:tags":[
        "newsagent"
    ],
    "wof:name":"Martin the Newsagent",
    "wof:placetype":"venue"
},
  "geometry": {"coordinates":[-0.7845600247,51.8065490723],"type":"Point"}
}