{
  "type": "Feature",
  "properties": {
    "addr:full":"2 Hampton Bank Ellesmere Shropshire SY12 0PX",
    "addr:housenumber":"2",
    "addr:postcode":"sy12 0px",
    "addr:street":"Hampton Bank Ellesmere Shropshire",
    "iso:country":"GB",
    "sg:address":"2 Hampton Bank",
    "sg:city":"Ellesmere",
    "sg:classifiers":[
        {
            "category":"Professional",
            "subcategory":"Management & Consulting",
            "type":"Services"
        }
    ],
    "sg:phone":"+44 1948 710472",
    "sg:postcode":"SY12 0PX",
    "sg:province":"Shropshire",
    "sg:tags":[
        "consultant",
        "business"
    ],
    "wof:name":"J E Thommesen",
    "wof:placetype":"venue"
},
  "geometry": {"coordinates":[-2.8967549801,52.9076843262],"type":"Point"}
}