{
  "type": "Feature",
  "properties": {
    "iso:country":"GB",
    "sg:address":"Thorp Arch Trading Estate, Thorp Arch",
    "sg:city":"Wetherby",
    "sg:classifiers":[
        {
            "category":"Home & Garden",
            "subcategory":"Furniture",
            "type":"Retail Goods"
        }
    ],
    "sg:phone":"+44 1937 842740",
    "sg:postcode":"LS23 7BW",
    "sg:province":"West Yorkshire",
    "wof:name":"The Dining Room Centre",
    "wof:placetype":"venue"
},
  "geometry": {"coordinates":[-1.3422989845,53.9077148438],"type":"Point"}
}