{
  "type": "Feature",
  "properties": {
    "addr:full":"102 Long Lane, Stanwell Staines Berkshire TW19 7AE",
    "addr:housenumber":"102",
    "addr:postcode":"tw19 7ae",
    "addr:street":"Long Lane",
    "iso:country":"GB",
    "sg:address":"102 Long Lane, Stanwell",
    "sg:city":"Staines",
    "sg:classifiers":[
        {
            "category":"Building & Trades",
            "subcategory":"Construction",
            "type":"Services"
        }
    ],
    "sg:phone":"+44 1784 243187",
    "sg:postcode":"TW19 7AE",
    "sg:province":"Berkshire",
    "sg:tags":[
        "builder"
    ],
    "wof:name":"Galower Builders Ltd.",
    "wof:placetype":"venue"
},
  "geometry": {"coordinates":[-0.4669579864,51.4498214722],"type":"Point"}
}