{
  "type": "Feature",
  "properties": {
    "addr:full":"1-8 The Circus Plymouth Devon PL1 1PF",
    "addr:housenumber":"1-8",
    "addr:postcode":"pl1 1pf",
    "addr:street":"The Circus",
    "iso:country":"GB",
    "sg:address":"1-8 The Circus",
    "sg:city":"Plymouth",
    "sg:classifiers":[
        {
            "category":"Professional",
            "subcategory":"Business Services",
            "type":"Services"
        }
    ],
    "sg:phone":"+44 1752 256100",
    "sg:postcode":"PL1 1PF",
    "sg:province":"Devon",
    "sg:tags":[
        "accomodation"
    ],
    "wof:name":"Money Centre The",
    "wof:placetype":"venue"
},
  "geometry": {"coordinates":[-4.14551,50.372551],"type":"Point"}
}