{
  "type": "Feature",
  "properties": {
    "addr:full":"28 Camden Road London Greater London NW1 9DP",
    "addr:housenumber":"28",
    "addr:postcode":"nw1 9dp",
    "addr:street":"Camden Road",
    "iso:country":"GB",
    "sg:address":"28 Camden Road",
    "sg:city":"London",
    "sg:classifiers":[
        {
            "category":"Personal",
            "subcategory":"Beauty Salon",
            "type":"Services"
        }
    ],
    "sg:phone":"+44 20 7267 5930",
    "sg:postcode":"NW1 9DP",
    "sg:province":"Greater London",
    "sg:tags":[
        "unisex",
        "hairdresser"
    ],
    "wof:name":"Flickers",
    "wof:placetype":"venue"
},
  "geometry": {"coordinates":[-0.1411260068,51.5398254395],"type":"Point"}
}