{
  "type": "Feature",
  "properties": {
    "addr:full":"67 High Street Banchory Aberdeen City AB31 3TJ",
    "addr:housenumber":"67",
    "addr:postcode":"ab31 3tj",
    "addr:street":"High Street;Aberdeen",
    "iso:country":"GB",
    "sg:address":"67 High Street",
    "sg:city":"Banchory",
    "sg:classifiers":[
        {
            "category":"Shopping",
            "subcategory":"Pharmacy",
            "type":"Retail Goods"
        }
    ],
    "sg:postcode":"AB31 3TJ",
    "sg:province":"Aberdeen City",
    "sg:tags":[
        "pharmacist",
        "chemist"
    ],
    "wof:name":"Charles Michie",
    "wof:placetype":"venue"
},
  "geometry": {"coordinates":[-2.502942,57.051422],"type":"Point"}
}