{
  "type": "Feature",
  "properties": {
    "addr:full":"131-133 Wilmslow Road, Rusholme Manchester Greater Manchester M14 5AW",
    "addr:housenumber":"131-133",
    "addr:postcode":"m14 5aw",
    "addr:street":"Wilmslow Road",
    "iso:country":"GB",
    "sg:address":"131-133 Wilmslow Road, Rusholme",
    "sg:city":"Manchester",
    "sg:classifiers":[
        {
            "category":"Restaurant",
            "type":"Food & Drink"
        }
    ],
    "sg:phone":"+44 161 224 2329",
    "sg:postcode":"M14 5AW",
    "sg:province":"Greater Manchester",
    "sg:tags":[
        "indian"
    ],
    "wof:name":"Tandoori Kitchen",
    "wof:placetype":"venue"
},
  "geometry": {"coordinates":[-2.224664,53.454468],"type":"Point"}
}