{
  "type": "Feature",
  "properties": {
    "addr:full":"65-67 Parkfield Road, Aigburth Liverpool Merseyside L17 4LE",
    "addr:housenumber":"65-67",
    "addr:postcode":"l17 4le",
    "addr:street":"Parkfield Road",
    "iso:country":"GB",
    "sg:address":"65-67 Parkfield Road, Aigburth",
    "sg:city":"Liverpool",
    "sg:classifiers":[
        {
            "category":"Health Services",
            "subcategory":"Nursing And Care Facility",
            "type":"Services"
        }
    ],
    "sg:phone":"+44 151 727 4949",
    "sg:postcode":"L17 4LE",
    "sg:province":"Merseyside",
    "sg:tags":[
        "home"
    ],
    "wof:name":"United Care Group Ltd.",
    "wof:placetype":"venue"
},
  "geometry": {"coordinates":[-2.9487440586,53.3795928955],"type":"Point"}
}