{
  "type": "Feature",
  "properties": {
    "addr:full":"Longsight La Bolton Lancashire BL2 4JX",
    "addr:postcode":"bl2 4jx",
    "addr:street":"La Bolton",
    "iso:country":"GB",
    "sg:address":"Longsight La",
    "sg:city":"Bolton",
    "sg:classifiers":[
        {
            "category":"Sports & Exercise",
            "subcategory":"Golf",
            "type":"Entertainment"
        }
    ],
    "sg:phone":"+44 1204 597659",
    "sg:postcode":"BL2 4JX",
    "sg:province":"Lancashire",
    "sg:tags":[
        "club",
        "course"
    ],
    "wof:name":"Bolton Golf & Leisure Ltd",
    "wof:placetype":"venue"
},
  "geometry": {"coordinates":[-2.3949530125,53.5949935913],"type":"Point"}
}