{
  "type": "Feature",
  "properties": {
    "addr:full":"Old Rectory Lane, Alvechurch Birmingham Worcestershire B48 7SU",
    "addr:postcode":"b48 7su",
    "addr:street":"Rectory Lane",
    "iso:country":"GB",
    "sg:address":"Old Rectory Lane, Alvechurch",
    "sg:city":"Birmingham",
    "sg:classifiers":[
        {
            "category":"Community Center",
            "type":"Public Place"
        }
    ],
    "sg:phone":"+44 121 447 7316",
    "sg:postcode":"B48 7SU",
    "sg:province":"Worcestershire",
    "sg:tags":[
        "nursery",
        "centre"
    ],
    "wof:name":"Alvechurch Nurseries Ltd.",
    "wof:placetype":"venue"
},
  "geometry": {"coordinates":[-1.9616140127,52.3511695862],"type":"Point"}
}