{
  "type": "Feature",
  "properties": {
    "iso:country":"GB",
    "sg:address":"2 Station Rd",
    "sg:city":"Letchworth",
    "sg:classifiers":[
        {
            "category":"Social Services",
            "type":"Services"
        }
    ],
    "sg:phone":"+44 1462 662590",
    "sg:postcode":"SG6 3AZ",
    "sg:province":"Hertfordshire",
    "sg:tags":[
        "benefit",
        "agency"
    ],
    "wof:name":"Benefits Agency",
    "wof:placetype":"venue"
},
  "geometry": {"coordinates":[-0.2281920016,51.9798240662],"type":"Point"}
}