{
  "type": "Feature",
  "properties": {
    "addr:full":"2 Station Rd Letchworth Hertfordshire SG6 3AZ",
    "addr:housenumber":"2",
    "addr:postcode":"sg6 3az",
    "addr:street":"Station Rd",
    "iso:country":"GB",
    "sg:address":"2 Station Rd",
    "sg:city":"Letchworth",
    "sg:classifiers":[
        {
            "category":"Social Services",
            "type":"Services"
        }
    ],
    "sg:phone":"+44 1462 662590",
    "sg:postcode":"SG6 3AZ",
    "sg:province":"Hertfordshire",
    "sg:tags":[
        "benefit",
        "agency"
    ],
    "wof:name":"Benefits Agency",
    "wof:placetype":"venue"
},
  "geometry": {"coordinates":[-0.2281920016,51.9798240662],"type":"Point"}
}