{
  "type": "Feature",
  "properties": {
    "addr:full":"112 Turnbull Drive Leicester Leicestershire LE3 2JW",
    "addr:housenumber":"112",
    "addr:postcode":"le3 2jw",
    "addr:street":"Turnbull Drive",
    "iso:country":"GB",
    "sg:address":"112 Turnbull Drive",
    "sg:city":"Leicester",
    "sg:classifiers":[
        {
            "category":"Shopping",
            "subcategory":"News",
            "type":"Retail Goods"
        }
    ],
    "sg:phone":"+44 116 289 7176",
    "sg:postcode":"LE3 2JW",
    "sg:province":"Leicestershire",
    "sg:tags":[
        "newsagent"
    ],
    "wof:name":"Mercury News",
    "wof:placetype":"venue"
},
  "geometry": {"coordinates":[-1.1780849695,52.6099128723],"type":"Point"}
}