{
  "type": "Feature",
  "properties": {
    "iso:country":"GB",
    "sg:address":"Nook Farm, Fowler La, Farrington",
    "sg:city":"Leyland",
    "sg:classifiers":[
        {
            "category":"Building & Trades",
            "subcategory":"Landscaping Services",
            "type":"Services"
        }
    ],
    "sg:postcode":"PR25 3RJ",
    "sg:province":"Lancashire",
    "sg:tags":[
        "landscape",
        "contractor"
    ],
    "wof:name":"Spink,Julia,",
    "wof:placetype":"venue"
},
  "geometry": {"coordinates":[-2.68964,53.71389],"type":"Point"}
}