{
  "type": "Feature",
  "properties": {
    "iso:country":"GB",
    "sg:address":"43 Brookside",
    "sg:city":"Hinckley",
    "sg:classifiers":[
        {
            "category":"Shopping",
            "subcategory":"Department Store",
            "type":"Retail Goods"
        },
        {
            "category":"Food & Beverages",
            "subcategory":"Supermarket",
            "type":"Retail Goods"
        }
    ],
    "sg:phone":"+44 1455 251216",
    "sg:postcode":"LE10 2TG",
    "sg:province":"Leicestershire",
    "wof:name":"A & J Stores",
    "wof:placetype":"venue"
},
  "geometry": {"coordinates":[-1.370067,52.533878],"type":"Point"}
}