{
  "type": "Feature",
  "properties": {
    "iso:country":"GB",
    "sg:address":"13 Allan Street",
    "sg:city":"Blairgowrie",
    "sg:classifiers":[
        {
            "category":"Home & Garden",
            "subcategory":"Carpets & Floor Coverings",
            "type":"Retail Goods"
        }
    ],
    "sg:phone":"+44 1250 874598",
    "sg:postcode":"PH10 6AB",
    "sg:province":"Perth and Kinross",
    "sg:tags":[
        "carpets",
        "rug",
        "matting"
    ],
    "wof:name":"Robert Gray Carpets",
    "wof:placetype":"venue"
},
  "geometry": {"coordinates":[-3.337912,56.592403],"type":"Point"}
}