{
  "type": "Feature",
  "properties": {
    "iso:country":"GB",
    "sg:address":"35 Little Russell Street",
    "sg:city":"Bloomsbury",
    "sg:classifiers":[
        {
            "category":"Communications",
            "type":"Services"
        }
    ],
    "sg:phone":"+44 20 7636 8343",
    "sg:postcode":"WC1A 2HH",
    "sg:province":"Greater London",
    "sg:tags":[
        "broadcasting"
    ],
    "wof:name":"Mandy Wheeler Sound Production",
    "wof:placetype":"venue"
},
  "geometry": {"coordinates":[-0.1243090034,51.5181274414],"type":"Point"}
}