{
  "type": "Feature",
  "properties": {
    "iso:country":"GB",
    "sg:address":"202 Chichester Road",
    "sg:city":"Portsmouth",
    "sg:classifiers":[
        {
            "category":"Personal",
            "subcategory":"Beauty Salon",
            "type":"Services"
        }
    ],
    "sg:phone":"+44 23 9266 1942",
    "sg:postcode":"PO2 0AX",
    "sg:province":"Hampshire",
    "sg:tags":[
        "unisex",
        "hairdresser"
    ],
    "wof:name":"Barry's Place",
    "wof:placetype":"venue"
},
  "geometry": {"coordinates":[-1.070375,50.813934],"type":"Point"}
}