{
  "type": "Feature",
  "properties": {
    "addr:full":"46 Welford Road Leicester Leicestershire LE2 7AA",
    "addr:housenumber":"46",
    "addr:postcode":"le2 7aa",
    "addr:street":"Welford Road",
    "iso:country":"GB",
    "sg:address":"46 Welford Road",
    "sg:city":"Leicester",
    "sg:classifiers":[
        {
            "category":"Fast Food",
            "type":"Food & Drink"
        }
    ],
    "sg:phone":"+44 116 247 0067",
    "sg:postcode":"LE2 7AA",
    "sg:province":"Leicestershire",
    "sg:tags":[
        "away",
        "take"
    ],
    "wof:name":"Gourmet Express Ltd.",
    "wof:placetype":"venue"
},
  "geometry": {"coordinates":[-1.132676,52.626781],"type":"Point"}
}