{
  "type": "Feature",
  "properties": {
    "addr:full":"262 Holderness Road Hull East Riding of Yorkshire HU9 2HX",
    "addr:housenumber":"262",
    "addr:postcode":"hu9 2hx",
    "addr:street":"Holderness Road",
    "iso:country":"GB",
    "sg:address":"262 Holderness Road",
    "sg:city":"Hull",
    "sg:classifiers":[
        {
            "category":"Food & Beverages",
            "subcategory":"Meat & Fish",
            "type":"Retail Goods"
        }
    ],
    "sg:phone":"+44 1482 329737",
    "sg:postcode":"HU9 2HX",
    "sg:province":"East Riding of Yorkshire",
    "sg:tags":[
        "butcher"
    ],
    "wof:name":"Yorkshire Fresh Foods",
    "wof:placetype":"venue"
},
  "geometry": {"coordinates":[-0.311842,53.754772],"type":"Point"}
}