{
  "type": "Feature",
  "properties": {
    "iso:country":"GB",
    "sg:address":"Unit 6 Newgate Shopping Centre, Newgate St",
    "sg:city":"Newcastle Upon Tyne",
    "sg:classifiers":[
        {
            "category":"Professional",
            "subcategory":"Employment Agencies",
            "type":"Services"
        }
    ],
    "sg:phone":"+44 191 222 1101",
    "sg:postcode":"NE1 5RE",
    "sg:province":"Tyne and Wear",
    "sg:tags":[
        "consultant"
    ],
    "wof:name":"Adecco Alfred Marks",
    "wof:placetype":"venue"
},
  "geometry": {"coordinates":[-1.6152670383,54.9714736938],"type":"Point"}
}