{
  "type": "Feature",
  "properties": {
    "iso:country":"GB",
    "sg:address":"Warstones Drive",
    "sg:city":"Wolverhampton",
    "sg:classifiers":[
        {
            "category":"Social Services",
            "subcategory":"Retirement Home",
            "type":"Services"
        }
    ],
    "sg:phone":"+44 1902 553419",
    "sg:postcode":"WV4 4PG",
    "sg:province":"Staffordshire",
    "sg:tags":[
        "residential",
        "care"
    ],
    "wof:name":"Warstones Resource Centre",
    "wof:placetype":"venue"
},
  "geometry": {"coordinates":[-2.168434,52.568531],"type":"Point"}
}