{
  "type": "Feature",
  "properties": {
    "addr:full":"7 Bridge Street Kelso Scottish Borders TD5 7HT",
    "addr:housenumber":"7",
    "addr:postcode":"td5 7ht",
    "addr:street":"Bridge Street",
    "iso:country":"GB",
    "sg:address":"7 Bridge Street",
    "sg:city":"Kelso",
    "sg:classifiers":[
        {
            "category":"Shopping",
            "subcategory":"Gifts & Souvenirs",
            "type":"Retail Goods"
        }
    ],
    "sg:postcode":"TD5 7HT",
    "sg:province":"Scottish Borders",
    "sg:tags":[
        "shop"
    ],
    "wof:name":"Baker Street",
    "wof:placetype":"venue"
},
  "geometry": {"coordinates":[-2.4337921143,55.5977363586],"type":"Point"}
}