{
  "type": "Feature",
  "properties": {
    "addr:full":"55 Fore Street Totnes Devon TQ9 5NJ",
    "addr:housenumber":"55",
    "addr:postcode":"tq9 5nj",
    "addr:street":"Fore Street",
    "iso:country":"GB",
    "sg:address":"55 Fore Street",
    "sg:city":"Totnes",
    "sg:classifiers":[
        {
            "category":"Shopping",
            "subcategory":"Clothing, Apparel, & Fashions",
            "type":"Retail Goods"
        }
    ],
    "sg:postcode":"TQ9 5NJ",
    "sg:province":"Devon",
    "sg:tags":[
        "menswear"
    ],
    "wof:name":"Totnes Menswear",
    "wof:placetype":"venue"
},
  "geometry": {"coordinates":[-3.686097,50.431419],"type":"Point"}
}