{
  "type": "Feature",
  "properties": {
    "addr:full":"81 North Street Ripon North Yorkshire HG4 1DP",
    "addr:housenumber":"81",
    "addr:postcode":"hg4 1dp",
    "addr:street":"North Street",
    "iso:country":"GB",
    "sg:address":"81 North Street",
    "sg:city":"Ripon",
    "sg:classifiers":[
        {
            "category":"Shopping",
            "subcategory":"Pharmacy",
            "type":"Retail Goods"
        }
    ],
    "sg:phone":"+44 1765 602031",
    "sg:postcode":"HG4 1DP",
    "sg:province":"North Yorkshire",
    "sg:tags":[
        "store",
        "drug"
    ],
    "wof:name":"J A Spilman (R S Marsden)",
    "wof:placetype":"venue"
},
  "geometry": {"coordinates":[-1.524055,54.138229],"type":"Point"}
}