{
  "type": "Feature",
  "properties": {
    "iso:country":"GB",
    "sg:address":"Crombie Lodge, Campus 2, Balgonie Drive",
    "sg:city":"Aberdeen",
    "sg:classifiers":[
        {
            "category":"Utilities",
            "subcategory":"Sewage",
            "type":"Services"
        }
    ],
    "sg:phone":"+44 1224 332190",
    "sg:postcode":"AB22 8GU",
    "sg:province":"Aberdeen City",
    "sg:tags":[
        "acoustic",
        "consultant"
    ],
    "wof:name":"Piezo Composite Transducers Ltd.",
    "wof:placetype":"venue"
},
  "geometry": {"coordinates":[-2.1109399796,57.1795043945],"type":"Point"}
}