{
  "type": "Feature",
  "properties": {
    "iso:country":"GB",
    "sg:address":"St Peters Place, Western Road",
    "sg:city":"Lancing",
    "sg:classifiers":[
        {
            "category":"Manufacturing",
            "subcategory":"Signs",
            "type":"Manufacturing & Wholesale Goods"
        }
    ],
    "sg:phone":"+44 1903 750710",
    "sg:postcode":"BN15 8SB",
    "sg:province":"West Sussex",
    "sg:tags":[
        "nameplate"
    ],
    "wof:name":"Tara Signs Ltd.",
    "wof:placetype":"venue"
},
  "geometry": {"coordinates":[-0.318039,50.821899],"type":"Point"}
}