{
  "type": "Feature",
  "properties": {
    "iso:country":"GB",
    "sg:address":"6 Lower Northdown Avenue",
    "sg:city":"Margate",
    "sg:classifiers":[
        {
            "category":"Health Services",
            "subcategory":"Nursing And Care Facility",
            "type":"Services"
        },
        {
            "category":"Social Services",
            "subcategory":"Retirement Home",
            "type":"Services"
        }
    ],
    "sg:postcode":"CT9 2NJ",
    "sg:province":"Kent",
    "sg:tags":[
        "residential"
    ],
    "wof:name":"Claremont Care Home",
    "wof:placetype":"venue"
},
  "geometry": {"coordinates":[1.400818,51.384846],"type":"Point"}
}