{
  "type": "Feature",
  "properties": {
    "addr:full":"381 Edgware Road London Greater London NW9 6NJ",
    "addr:housenumber":"381",
    "addr:postcode":"nw9 6nj",
    "addr:street":"Edgware Road",
    "iso:country":"GB",
    "sg:address":"381 Edgware Road",
    "sg:city":"London",
    "sg:classifiers":[
        {
            "category":"Shopping",
            "subcategory":"Computers & Home Electronics",
            "type":"Retail Goods"
        }
    ],
    "sg:phone":"+44 20 8205 5666",
    "sg:postcode":"NW9 6NJ",
    "sg:province":"Greater London",
    "sg:tags":[
        "electrical"
    ],
    "wof:name":"Amperfield Ltd.",
    "wof:placetype":"venue"
},
  "geometry": {"coordinates":[-0.256124,51.591095],"type":"Point"}
}