{
  "type": "Feature",
  "properties": {
    "addr:full":"23 Gruneisen Rd London Greater London N3 1LS",
    "addr:housenumber":"23",
    "addr:postcode":"n3 1ls",
    "addr:street":"Gruneisen Rd",
    "iso:country":"GB",
    "sg:address":"23 Gruneisen Rd",
    "sg:city":"London",
    "sg:classifiers":[
        {
            "category":"Retail",
            "subcategory":"Auto Repair",
            "type":"Services"
        }
    ],
    "sg:postcode":"N3 1LS",
    "sg:province":"Greater London",
    "sg:tags":[
        "modification",
        "garage"
    ],
    "wof:name":"Boweri,S N,",
    "wof:placetype":"venue"
},
  "geometry": {"coordinates":[-0.1876569986,51.6069946289],"type":"Point"}
}