{
  "type": "Feature",
  "properties": {
    "addr:full":"21 Cranleigh Court Road, Yate Bristol Gloucestershire BS37 5DQ",
    "addr:housenumber":"21",
    "addr:postcode":"bs37 5dq",
    "addr:street":"Cranleigh Court Road Yate",
    "iso:country":"GB",
    "sg:address":"21 Cranleigh Court Road, Yate",
    "sg:city":"Bristol",
    "sg:classifiers":[
        {
            "category":"Shopping",
            "subcategory":"News",
            "type":"Retail Goods"
        }
    ],
    "sg:phone":"+44 1454 322407",
    "sg:postcode":"BS37 5DQ",
    "sg:province":"Gloucestershire",
    "sg:tags":[
        "newsagent"
    ],
    "wof:name":"Forbuoys Ltd.",
    "wof:placetype":"venue"
},
  "geometry": {"coordinates":[-2.425186,51.54147],"type":"Point"}
}