{
  "type": "Feature",
  "properties": {
    "addr:full":"Windy Rise, Beulah Newcastle Emlyn Carmarthenshire SA38 9QJ",
    "addr:postcode":"sa38 9qj",
    "addr:street":"Windy Rise",
    "iso:country":"GB",
    "sg:address":"Windy Rise, Beulah",
    "sg:city":"Newcastle Emlyn",
    "sg:classifiers":[
        {
            "category":"Manufacturing",
            "subcategory":"Apparel",
            "type":"Manufacturing & Wholesale Goods"
        }
    ],
    "sg:phone":"+44 1239 851474",
    "sg:postcode":"SA38 9QJ",
    "sg:province":"Carmarthenshire",
    "sg:tags":[
        "garment",
        "designer"
    ],
    "wof:name":"New Orleans Bridal Gowns",
    "wof:placetype":"venue"
},
  "geometry": {"coordinates":[-4.467984,52.035919],"type":"Point"}
}