{
  "type": "Feature",
  "properties": {
    "iso:country":"GB",
    "sg:address":"Unit 2, Green La, Cadishead",
    "sg:city":"Manchester",
    "sg:classifiers":[
        {
            "category":"Shopping",
            "subcategory":"Department Store",
            "type":"Retail Goods"
        },
        {
            "category":"Wholesale",
            "subcategory":"Toys & Hobbies",
            "type":"Manufacturing & Wholesale Goods"
        }
    ],
    "sg:postcode":"M44 5XF",
    "sg:province":"Greater Manchester",
    "sg:tags":[
        "balloon",
        "novelty"
    ],
    "wof:name":"Dawson,A,& Sons",
    "wof:placetype":"venue"
},
  "geometry": {"coordinates":[-2.437613,53.424423],"type":"Point"}
}