{
  "type": "Feature",
  "properties": {
    "addr:full":"12 High St Abertillery Blaenau Gwent NP3 2RB",
    "addr:housenumber":"12",
    "addr:postcode":"np3 2rb",
    "addr:street":"High St",
    "iso:country":"GB",
    "sg:address":"12 High St",
    "sg:city":"Abertillery",
    "sg:classifiers":[
        {
            "category":"Military Area",
            "subcategory":"Air Force Base",
            "type":"Public Place"
        }
    ],
    "sg:phone":"+44 1495 320489",
    "sg:postcode":"NP3 2RB",
    "sg:province":"Blaenau Gwent",
    "sg:tags":[
        "taxi",
        "hire",
        "private"
    ],
    "wof:name":"Donna's Private Hire",
    "wof:placetype":"venue"
},
  "geometry": {"coordinates":[-3.1295239925,51.6989746094],"type":"Point"}
}