{
  "type": "Feature",
  "properties": {
    "addr:full":"13 Musbury Road Axminster Devon EX13 5JJ",
    "addr:housenumber":"13",
    "addr:postcode":"ex13 5jj",
    "addr:street":"Musbury Road",
    "iso:country":"GB",
    "sg:address":"13 Musbury Road",
    "sg:city":"Axminster",
    "sg:classifiers":[
        {
            "category":"Health Services",
            "subcategory":"Dentist",
            "type":"Services"
        }
    ],
    "sg:phone":"+44 1297 32982",
    "sg:postcode":"EX13 5JJ",
    "sg:province":"Devon",
    "sg:tags":[
        "technician",
        "dental"
    ],
    "wof:name":"George House Dental Laboratory",
    "wof:placetype":"venue"
},
  "geometry": {"coordinates":[-3.000886,50.778282],"type":"Point"}
}