{
  "type": "Feature",
  "properties": {
    "iso:country":"GB",
    "sg:address":"193c Auckland Hill, West Norwood",
    "sg:city":"London",
    "sg:classifiers":[
        {
            "category":"Professional",
            "subcategory":"Testing Lab",
            "type":"Services"
        }
    ],
    "sg:phone":"+44 20 8670 0897",
    "sg:postcode":"SE27 9PD",
    "sg:province":"Greater London",
    "sg:tags":[
        "mot"
    ],
    "wof:name":"Gauden Motors",
    "wof:placetype":"venue"
},
  "geometry": {"coordinates":[-0.100619,51.43108],"type":"Point"}
}