{
  "type": "Feature",
  "properties": {
    "iso:country":"GB",
    "sg:address":"53a Lower Hall Lane",
    "sg:city":"Walsall",
    "sg:classifiers":[
        {
            "category":"Shopping",
            "subcategory":"Pets & Pet Supplies",
            "type":"Retail Goods"
        }
    ],
    "sg:phone":"+44 1922 746281",
    "sg:postcode":"WS1 1RJ",
    "sg:province":"West Midlands",
    "wof:name":"The Amazon Jungle",
    "wof:placetype":"venue"
},
  "geometry": {"coordinates":[-1.9819940329,52.5830307007],"type":"Point"}
}