{
  "type": "Feature",
  "properties": {
    "addr:full":"Upper Grange Farm, Magor Caldicot Monmouthshire NP26 3AT",
    "addr:postcode":"np26 3at",
    "addr:street":"Upper;Magor",
    "iso:country":"GB",
    "sg:address":"Upper Grange Farm, Magor",
    "sg:city":"Caldicot",
    "sg:classifiers":[
        {
            "category":"Farming",
            "subcategory":"Livestock Farm",
            "type":"Manufacturing & Wholesale Goods"
        }
    ],
    "sg:phone":"+44 1633 880605",
    "sg:postcode":"NP26 3AT",
    "sg:province":"Monmouthshire",
    "sg:tags":[
        "others"
    ],
    "wof:name":"M & L J Williams",
    "wof:placetype":"venue"
},
  "geometry": {"coordinates":[-2.8255200386,51.602809906],"type":"Point"}
}