{
  "type": "Feature",
  "properties": {
    "iso:country":"GB",
    "sg:address":"111 Oxford Road",
    "sg:city":"High Wycombe",
    "sg:classifiers":[
        {
            "category":"Shopping",
            "subcategory":"Florist",
            "type":"Retail Goods"
        }
    ],
    "sg:phone":"+44 1494 528594",
    "sg:postcode":"HP11 2DN",
    "sg:province":"Buckinghamshire",
    "wof:name":"G F Stacey",
    "wof:placetype":"venue"
},
  "geometry": {"coordinates":[-0.755366,51.631866],"type":"Point"}
}