{
  "type": "Feature",
  "properties": {
    "addr:full":"10 Adrian Avenue London Greater London NW2 1LX",
    "addr:housenumber":"10",
    "addr:postcode":"nw2 1lx",
    "addr:street":"Adrian Avenue",
    "iso:country":"GB",
    "sg:address":"10 Adrian Avenue",
    "sg:city":"London",
    "sg:classifiers":[
        {
            "category":"Retail",
            "subcategory":"Auto Repair",
            "type":"Services"
        }
    ],
    "sg:phone":"+44 20 8830 5776",
    "sg:postcode":"NW2 1LX",
    "sg:province":"Greater London",
    "sg:tags":[
        "body",
        "car"
    ],
    "wof:name":"Galaxy Coachworks",
    "wof:placetype":"venue"
},
  "geometry": {"coordinates":[-0.231061,51.571728],"type":"Point"}
}