{
  "type": "Feature",
  "properties": {
    "addr:full":"14-16 Derby Road, Kirkdale Liverpool Merseyside L20 8EE",
    "addr:housenumber":"14-16",
    "addr:postcode":"l20 8ee",
    "addr:street":"Derby Road",
    "iso:country":"GB",
    "sg:address":"14-16 Derby Road, Kirkdale",
    "sg:city":"Liverpool",
    "sg:classifiers":[
        {
            "category":"Manufacturing",
            "subcategory":"Rubber & Plastics",
            "type":"Manufacturing & Wholesale Goods"
        }
    ],
    "sg:phone":"+44 151 207 6221",
    "sg:postcode":"L20 8EE",
    "sg:province":"Merseyside",
    "sg:tags":[
        "raw",
        "product",
        "material"
    ],
    "wof:name":"Centriforce Products Ltd.",
    "wof:placetype":"venue"
},
  "geometry": {"coordinates":[-2.9942479134,53.4325866699],"type":"Point"}
}