{
  "type": "Feature",
  "properties": {
    "iso:country":"GB",
    "sg:address":"18 London Road, Holmes Chapel",
    "sg:city":"Crewe",
    "sg:classifiers":[
        {
            "category":"Personal",
            "subcategory":"Beauty Salon",
            "type":"Services"
        }
    ],
    "sg:phone":"+44 1477 533259",
    "sg:postcode":"CW4 7AJ",
    "sg:province":"Cheshire",
    "sg:tags":[
        "unisex",
        "ladies",
        "lady",
        "hairdresser"
    ],
    "wof:name":"John Alexander",
    "wof:placetype":"venue"
},
  "geometry": {"coordinates":[-2.357938,53.202343],"type":"Point"}
}