{
  "type": "Feature",
  "properties": {
    "iso:country":"GB",
    "sg:address":"51 Mayfield Clo",
    "sg:city":"St Austell",
    "sg:classifiers":[
        {
            "category":"Personal",
            "type":"Services"
        }
    ],
    "sg:phone":"+44 1726 68917",
    "sg:postcode":"PL25 3PD",
    "sg:province":"Cornwall",
    "sg:tags":[
        "delivery"
    ],
    "wof:name":"Speedee Couriers",
    "wof:placetype":"venue"
},
  "geometry": {"coordinates":[-4.766267,50.342087],"type":"Point"}
}