{
  "type": "Feature",
  "properties": {
    "addr:full":"Block 3a Unit 5, Caponacre Industrial Estate Cumnock East Ayrshire KA18 1SH",
    "addr:housenumber":"3a unit 5",
    "addr:postcode":"ka18 1sh",
    "addr:street":"Block;Caponacre Industrial Estate Cumnock East",
    "iso:country":"GB",
    "sg:address":"Block 3a Unit 5, Caponacre Industrial Estate",
    "sg:city":"Cumnock",
    "sg:classifiers":[
        {
            "category":"Home & Garden",
            "subcategory":"Home Furnishings",
            "type":"Retail Goods"
        }
    ],
    "sg:postcode":"KA18 1SH",
    "sg:province":"East Ayrshire",
    "sg:tags":[
        "blind",
        "curtain",
        "fitting"
    ],
    "wof:name":"Curtainwise",
    "wof:placetype":"venue"
},
  "geometry": {"coordinates":[-4.264099,55.453255],"type":"Point"}
}