{
  "type": "Feature",
  "properties": {
    "addr:full":"Benchill Road, Wythenshawe Manchester Greater Manchester M22 8EJ",
    "addr:postcode":"m22 8ej",
    "addr:street":"Benchill Road",
    "iso:country":"GB",
    "sg:address":"Benchill Road, Wythenshawe",
    "sg:city":"Manchester",
    "sg:classifiers":[
        {
            "category":"Education",
            "subcategory":"School",
            "type":"Public Place"
        }
    ],
    "sg:phone":"+44 161 998 3075",
    "sg:postcode":"M22 8EJ",
    "sg:province":"Greater Manchester",
    "sg:tags":[
        "local",
        "authority"
    ],
    "wof:name":"Benchill Junior School",
    "wof:placetype":"venue"
},
  "geometry": {"coordinates":[-2.2671339512,53.3945503235],"type":"Point"}
}