{
  "type": "Feature",
  "properties": {
    "addr:full":"Kingmoor Park Heathlands Estate Carlisle Cumbria CA6 4RN",
    "addr:postcode":"ca6 4rn",
    "addr:street":"Heathlands",
    "iso:country":"GB",
    "sg:address":"Kingmoor Park Heathlands Estate",
    "sg:city":"Carlisle",
    "sg:classifiers":[
        {
            "category":"Building & Trades",
            "subcategory":"Plumbing",
            "type":"Services"
        }
    ],
    "sg:postcode":"CA6 4RN",
    "sg:province":"Cumbria",
    "sg:tags":[
        "drain",
        "clearance",
        "sewer"
    ],
    "wof:name":"Andidrain",
    "wof:placetype":"venue"
},
  "geometry": {"coordinates":[-2.823059082,54.9315795898],"type":"Point"}
}