{
  "type": "Feature",
  "properties": {
    "addr:full":"91 Vittoria Street Birmingham West Midlands B1 3NU",
    "addr:housenumber":"91",
    "addr:postcode":"b1 3nu",
    "addr:street":"Vittoria Street",
    "iso:country":"GB",
    "sg:address":"91 Vittoria Street",
    "sg:city":"Birmingham",
    "sg:classifiers":[
        {
            "category":"Manufacturing",
            "subcategory":"Jewelry",
            "type":"Manufacturing & Wholesale Goods"
        }
    ],
    "sg:phone":"+44 121 236 2136",
    "sg:postcode":"B1 3NU",
    "sg:province":"West Midlands",
    "sg:tags":[
        "manufacture",
        "repair",
        "jewellery"
    ],
    "wof:name":"Peadron Polishing",
    "wof:placetype":"venue"
},
  "geometry": {"coordinates":[-1.91119802,52.4868621826],"type":"Point"}
}