{
  "type": "Feature",
  "properties": {
    "iso:country":"GB",
    "sg:address":"Redroofs, Moor Lane, Gotham",
    "sg:city":"Nottingham",
    "sg:classifiers":[
        {
            "category":"Shopping",
            "subcategory":"Pets & Pet Supplies",
            "type":"Retail Goods"
        }
    ],
    "sg:phone":"+44 115 983 0727",
    "sg:postcode":"NG11 0LH",
    "sg:province":"Nottinghamshire",
    "wof:name":"Moors Cattery",
    "wof:placetype":"venue"
},
  "geometry": {"coordinates":[-1.204924,52.869099],"type":"Point"}
}