{
  "type": "Feature",
  "properties": {
    "addr:full":"3 Squires Yard, Old Cherry Orchard, Common Rd Evesham Gloucestershire WR11 6PR",
    "addr:housenumber":"3",
    "addr:postcode":"wr11 6pr",
    "addr:street":"Squires Yard Old;Common Rd",
    "iso:country":"GB",
    "sg:address":"3 Squires Yard, Old Cherry Orchard, Common Rd",
    "sg:city":"Evesham",
    "sg:classifiers":[
        {
            "category":"Manufacturing",
            "subcategory":"Metals",
            "type":"Manufacturing & Wholesale Goods"
        }
    ],
    "sg:phone":"+44 1386 423186",
    "sg:postcode":"WR11 6PR",
    "sg:province":"Gloucestershire",
    "sg:tags":[
        "steel",
        "fabricator",
        "erectors"
    ],
    "wof:name":"Vale Fabrications",
    "wof:placetype":"venue"
},
  "geometry": {"coordinates":[-1.943969,52.106392],"type":"Point"}
}