{
  "type": "Feature",
  "properties": {
    "addr:full":"5 Norwich Road, Lingwood Norwich Norfolk NR13 4BH",
    "addr:housenumber":"5",
    "addr:postcode":"nr13 4bh",
    "addr:street":"Norwich Road;Norwich",
    "iso:country":"GB",
    "sg:address":"5 Norwich Road, Lingwood",
    "sg:city":"Norwich",
    "sg:classifiers":[
        {
            "category":"Wholesale",
            "subcategory":"Painting Supplies",
            "type":"Manufacturing & Wholesale Goods"
        }
    ],
    "sg:phone":"+44 1603 713972",
    "sg:postcode":"NR13 4BH",
    "sg:province":"Norfolk",
    "sg:tags":[
        "carbon",
        "product"
    ],
    "wof:name":"H Q Fibre Products",
    "wof:placetype":"venue"
},
  "geometry": {"coordinates":[1.4827200174,52.6188011169],"type":"Point"}
}