{
  "type": "Feature",
  "properties": {
    "iso:country":"GB",
    "sg:address":"305 Borough High Street",
    "sg:city":"London",
    "sg:classifiers":[
        {
            "category":"Health Services",
            "subcategory":"Dentist",
            "type":"Services"
        }
    ],
    "sg:phone":"+44 20 7407 3883",
    "sg:postcode":"SE1 1JH",
    "sg:province":"Greater London",
    "wof:name":"Edward N Chater",
    "wof:placetype":"venue"
},
  "geometry": {"coordinates":[-0.09632,51.499378],"type":"Point"}
}