{
  "type": "Feature",
  "properties": {
    "addr:full":"47 The Sunny Road Enfield Greater London EN3 5EF",
    "addr:housenumber":"47",
    "addr:postcode":"en3 5ef",
    "addr:street":"The Sunny Road",
    "iso:country":"GB",
    "sg:address":"47 The Sunny Road",
    "sg:city":"Enfield",
    "sg:classifiers":[
        {
            "category":"Building & Trades",
            "subcategory":"Construction",
            "type":"Services"
        }
    ],
    "sg:postcode":"EN3 5EF",
    "sg:province":"Greater London",
    "sg:tags":[
        "glazier"
    ],
    "wof:name":"D Saunders Glass & Glazing",
    "wof:placetype":"venue"
},
  "geometry": {"coordinates":[-0.036456,51.661377],"type":"Point"}
}