{
  "type": "Feature",
  "properties": {
    "addr:full":"8 Devonshire Place Harrogate North Yorkshire HG1 4AA",
    "addr:housenumber":"8",
    "addr:postcode":"hg1 4aa",
    "addr:street":"Devonshire Place",
    "iso:country":"GB",
    "sg:address":"8 Devonshire Place",
    "sg:city":"Harrogate",
    "sg:classifiers":[
        {
            "category":"Food & Beverages",
            "subcategory":"Supermarket",
            "type":"Retail Goods"
        }
    ],
    "sg:phone":"+44 1423 502772",
    "sg:postcode":"HG1 4AA",
    "sg:province":"North Yorkshire",
    "wof:name":"Mills",
    "wof:placetype":"venue"
},
  "geometry": {"coordinates":[-1.528408,53.997486],"type":"Point"}
}