{
  "type": "Feature",
  "properties": {
    "addr:full":"1 Freshfield Way Brighton East Sussex BN2 0LE",
    "addr:housenumber":"1",
    "addr:postcode":"bn2 0le",
    "addr:street":"Freshfield Way",
    "iso:country":"GB",
    "sg:address":"1 Freshfield Way",
    "sg:city":"Brighton",
    "sg:classifiers":[
        {
            "category":"Organizations",
            "subcategory":"Membership Organization",
            "type":"Services"
        }
    ],
    "sg:phone":"+44 1273 621884",
    "sg:postcode":"BN2 0LE",
    "sg:province":"East Sussex",
    "sg:tags":[
        "club"
    ],
    "wof:name":"Gala Club",
    "wof:placetype":"venue"
},
  "geometry": {"coordinates":[-0.126508,50.823177],"type":"Point"}
}