{
  "type": "Feature",
  "properties": {
    "addr:full":"Failand Rd Bristol Somerset BS48 1PG",
    "addr:postcode":"bs48 1pg",
    "addr:street":"Failand Rd",
    "iso:country":"GB",
    "sg:address":"Failand Rd",
    "sg:city":"Bristol",
    "sg:classifiers":[
        {
            "category":"Communications",
            "type":"Services"
        }
    ],
    "sg:phone":"+44 1275 851222",
    "sg:postcode":"BS48 1PG",
    "sg:province":"Somerset",
    "sg:tags":[
        "audio-visual"
    ],
    "wof:name":"Christian Television Association",
    "wof:placetype":"venue"
},
  "geometry": {"coordinates":[-2.744791,51.435825],"type":"Point"}
}