{
  "type": "Feature",
  "properties": {
    "addr:full":"94 Forest Hill Road London Greater London SE22 0RS",
    "addr:housenumber":"94",
    "addr:postcode":"se22 0rs",
    "addr:street":"Forest Hill Road",
    "iso:country":"GB",
    "sg:address":"94 Forest Hill Road",
    "sg:city":"London",
    "sg:classifiers":[
        {
            "category":"Personal",
            "subcategory":"Beauty Salon",
            "type":"Services"
        }
    ],
    "sg:phone":"+44 20 8693 8507",
    "sg:postcode":"SE22 0RS",
    "sg:province":"Greater London",
    "sg:tags":[
        "unisex",
        "hairdresser"
    ],
    "wof:name":"The Hair Centre",
    "wof:placetype":"venue"
},
  "geometry": {"coordinates":[-0.0603969991,51.4522171021],"type":"Point"}
}