{
  "type": "Feature",
  "properties": {
    "addr:full":"Ringsfield Hall Beccles Norfolk NR34 8JR",
    "addr:postcode":"nr34 8jr",
    "iso:country":"GB",
    "sg:address":"Ringsfield Hall",
    "sg:city":"Beccles",
    "sg:classifiers":[
        {
            "category":"Organizations",
            "subcategory":"Non-profit Organization",
            "type":"Services"
        }
    ],
    "sg:phone":"+44 1502 713020",
    "sg:postcode":"NR34 8JR",
    "sg:province":"Norfolk",
    "sg:tags":[
        "organisation",
        "voluntary",
        "charity"
    ],
    "wof:name":"Ringsfield Hall Centre",
    "wof:placetype":"venue"
},
  "geometry": {"coordinates":[1.5345220566,52.4414138794],"type":"Point"}
}