{
  "type": "Feature",
  "properties": {
    "addr:full":"71 Lambeth Walk, Lambeth London Greater London SE11 6DX",
    "addr:housenumber":"71",
    "addr:postcode":"se11 6dx",
    "addr:street":"Lambeth Walk",
    "iso:country":"GB",
    "sg:address":"71 Lambeth Walk, Lambeth",
    "sg:city":"London",
    "sg:classifiers":[
        {
            "category":"Professional",
            "subcategory":"Art Services",
            "type":"Services"
        }
    ],
    "sg:phone":"+44 20 7582 4303",
    "sg:postcode":"SE11 6DX",
    "sg:province":"Greater London",
    "sg:tags":[
        "model",
        "maker"
    ],
    "wof:name":"Mimesis",
    "wof:placetype":"venue"
},
  "geometry": {"coordinates":[-0.114564,51.494343],"type":"Point"}
}