{
  "type": "Feature",
  "properties": {
    "addr:full":"Avis Way Newhaven East Sussex BN9 0DJ",
    "addr:postcode":"bn9 0dj",
    "addr:street":"Avis Way",
    "iso:country":"GB",
    "sg:address":"Avis Way",
    "sg:city":"Newhaven",
    "sg:classifiers":[
        {
            "category":"Shopping",
            "subcategory":"Discount & Variety Stores",
            "type":"Retail Goods"
        }
    ],
    "sg:phone":"+44 1273 513566",
    "sg:postcode":"BN9 0DJ",
    "sg:province":"East Sussex",
    "sg:tags":[
        "cleaning",
        "supply"
    ],
    "wof:name":"Ferryfield Mouldings",
    "wof:placetype":"venue"
},
  "geometry": {"coordinates":[0.056043,50.798885],"type":"Point"}
}