{
  "type": "Feature",
  "properties": {
    "addr:full":"63-75 Glenthorne Road London Greater London W6 0LJ",
    "addr:housenumber":"63-75",
    "addr:postcode":"w6 0lj",
    "addr:street":"Glenthorne Road",
    "iso:country":"GB",
    "sg:address":"63-75 Glenthorne Road",
    "sg:city":"London",
    "sg:classifiers":[
        {
            "category":"Health Services",
            "subcategory":"Clinic",
            "type":"Services"
        }
    ],
    "sg:phone":"+44 20 8600 0200",
    "sg:postcode":"W6 0LJ",
    "sg:province":"Greater London",
    "sg:tags":[
        "medical"
    ],
    "wof:name":"Philips Medical Systems",
    "wof:placetype":"venue"
},
  "geometry": {"coordinates":[-0.231205,51.494579],"type":"Point"}
}