{
  "type": "Feature",
  "properties": {
    "addr:full":"52 Stoke Newington Church Street London Greater London N16 0NB",
    "addr:housenumber":"52",
    "addr:postcode":"n16 0nb",
    "addr:street":"Stoke Newington Church Street",
    "iso:country":"GB",
    "sg:address":"52 Stoke Newington Church Street",
    "sg:city":"London",
    "sg:classifiers":[
        {
            "category":"Health Services",
            "subcategory":"Health Practitioner",
            "type":"Services"
        }
    ],
    "sg:phone":"+44 20 7249 9671",
    "sg:postcode":"N16 0NB",
    "sg:province":"Greater London",
    "sg:tags":[
        "herbalist"
    ],
    "wof:name":"WISTY HOYLAND",
    "wof:placetype":"venue"
},
  "geometry": {"coordinates":[-0.0761820003,51.5620613098],"type":"Point"}
}