{
  "type": "Feature",
  "properties": {
    "addr:full":"Bridley Moor Road Redditch Warwickshire B97 6HS",
    "addr:postcode":"b97 6hs",
    "addr:street":"Bridley Moor Road",
    "iso:country":"GB",
    "sg:address":"Bridley Moor Road",
    "sg:city":"Redditch",
    "sg:classifiers":[
        {
            "category":"Organizations",
            "subcategory":"Community Association",
            "type":"Services"
        },
        {
            "category":"Organizations",
            "subcategory":"Membership Organization",
            "type":"Services"
        }
    ],
    "sg:phone":"+44 1527 62961",
    "sg:postcode":"B97 6HS",
    "sg:province":"Warwickshire",
    "sg:tags":[
        "club",
        "social"
    ],
    "wof:name":"BRIDLEY MOOR & BATCHLEY SOCIAL CLUB",
    "wof:placetype":"venue"
},
  "geometry": {"coordinates":[-1.949429,52.310856],"type":"Point"}
}