{
  "type": "Feature",
  "properties": {
    "addr:full":"Tarka Lodge, Coombe St Austell Cornwall PL26 7LJ",
    "addr:postcode":"pl26 7lj",
    "addr:street":"Coombe",
    "iso:country":"GB",
    "sg:address":"Tarka Lodge, Coombe",
    "sg:city":"St Austell",
    "sg:classifiers":[
        {
            "category":"Professional",
            "subcategory":"Engineering",
            "type":"Services"
        },
        {
            "category":"Wholesale",
            "subcategory":"Machinery & Supplies",
            "type":"Manufacturing & Wholesale Goods"
        }
    ],
    "sg:phone":"+44 1726 884644",
    "sg:postcode":"PL26 7LJ",
    "sg:province":"Cornwall",
    "sg:tags":[
        "electronic",
        "industrial",
        "commercial",
        "engineer"
    ],
    "wof:name":"C J S Electronic Services",
    "wof:placetype":"venue"
},
  "geometry": {"coordinates":[-4.8791298866,50.3293800354],"type":"Point"}
}