{
  "type": "Feature",
  "properties": {
    "iso:country":"GB",
    "sg:address":"Dhamma Dipa, Harewood End",
    "sg:city":"Hereford",
    "sg:classifiers":[
        {
            "category":"Organizations",
            "subcategory":"Non-profit Organization",
            "type":"Services"
        }
    ],
    "sg:phone":"+44 1989 730234",
    "sg:postcode":"HR2 8JS",
    "sg:province":"Herefordshire",
    "sg:tags":[
        "charitable",
        "organisation",
        "voluntary",
        "charity"
    ],
    "wof:name":"Vipassana Trust Meditation Centre",
    "wof:placetype":"venue"
},
  "geometry": {"coordinates":[-2.69526,51.94693],"type":"Point"}
}