{
  "type": "Feature",
  "properties": {
    "iso:country":"GB",
    "sg:address":"352 York Road",
    "sg:city":"Leeds",
    "sg:classifiers":[
        {
            "category":"Professional",
            "subcategory":"Engineering",
            "type":"Services"
        }
    ],
    "sg:postcode":"LS9 9DN",
    "sg:province":"West Yorkshire",
    "sg:tags":[
        "contractor",
        "electrical",
        "engineer"
    ],
    "wof:name":"Shaw Electrical Services Ltd.",
    "wof:placetype":"venue"
},
  "geometry": {"coordinates":[-1.50805,53.798874],"type":"Point"}
}