{
  "type": "Feature",
  "properties": {
    "iso:country":"GB",
    "sg:address":"Brandon House, 75 Hamilton Road",
    "sg:city":"Motherwell",
    "sg:classifiers":[
        {
            "category":"Professional",
            "subcategory":"Management & Consulting",
            "type":"Services"
        }
    ],
    "sg:phone":"+44 1698 266161",
    "sg:postcode":"ML1 3DG",
    "sg:province":"North Lanarkshire",
    "sg:tags":[
        "consultant",
        "safety"
    ],
    "wof:name":"Macsafe Ltd.",
    "wof:placetype":"venue"
},
  "geometry": {"coordinates":[-3.995335,55.789467],"type":"Point"}
}