{
  "type": "Feature",
  "properties": {
    "addr:full":"43 Regnum Drive, Kiln Road, Shaw Newbury Berkshire RG14 2HF",
    "addr:housenumber":"43",
    "addr:postcode":"rg14 2hf",
    "addr:street":"Regnum Drive Kiln Road",
    "iso:country":"GB",
    "sg:address":"43 Regnum Drive, Kiln Road, Shaw",
    "sg:city":"Newbury",
    "sg:classifiers":[
        {
            "category":"Shopping",
            "subcategory":"Florist",
            "type":"Retail Goods"
        }
    ],
    "sg:phone":"+44 1635 33481",
    "sg:postcode":"RG14 2HF",
    "sg:province":"Berkshire",
    "wof:name":"Sumo Flowers",
    "wof:placetype":"venue"
},
  "geometry": {"coordinates":[-1.3124489784,51.410118103],"type":"Point"}
}