{
  "type": "Feature",
  "properties": {
    "addr:full":"27 Longford Dr, Bradway Sheffield Derbyshire S17 4LN",
    "addr:housenumber":"27",
    "addr:postcode":"s17 4ln",
    "addr:street":"Longford Dr",
    "iso:country":"GB",
    "sg:address":"27 Longford Dr, Bradway",
    "sg:city":"Sheffield",
    "sg:classifiers":[
        {
            "category":"Professional",
            "subcategory":"Computer Services",
            "type":"Services"
        }
    ],
    "sg:phone":"+44 114 262 0127",
    "sg:postcode":"S17 4LN",
    "sg:province":"Derbyshire",
    "sg:tags":[
        "consultant"
    ],
    "wof:name":"Snowball I T Ltd",
    "wof:placetype":"venue"
},
  "geometry": {"coordinates":[-1.5217959881,53.3147544861],"type":"Point"}
}