{
  "type": "Feature",
  "properties": {
    "addr:full":"2 Mough Lane, Chadderton Oldham Lancashire OL9 9NT",
    "addr:housenumber":"2",
    "addr:postcode":"ol9 9nt",
    "addr:street":"Mough Lane",
    "iso:country":"GB",
    "sg:address":"2 Mough Lane, Chadderton",
    "sg:city":"Oldham",
    "sg:classifiers":[
        {
            "category":"Food & Beverages",
            "subcategory":"Meat & Fish",
            "type":"Retail Goods"
        }
    ],
    "sg:postcode":"OL9 9NT",
    "sg:province":"Lancashire",
    "sg:tags":[
        "chip"
    ],
    "wof:name":"J B Chippy",
    "wof:placetype":"venue"
},
  "geometry": {"coordinates":[-2.162871,53.52541],"type":"Point"}
}