{
  "type": "Feature",
  "properties": {
    "iso:country":"GB",
    "sg:address":"2 Greens Road",
    "sg:city":"Cambridge",
    "sg:classifiers":[
        {
            "category":"Professional",
            "subcategory":"Engineering",
            "type":"Services"
        }
    ],
    "sg:phone":"+44 1223 364655",
    "sg:postcode":"CB4 3EQ",
    "sg:province":"Cambridgeshire",
    "wof:name":"Cambridge Repetition Engineers Ltd.",
    "wof:placetype":"venue"
},
  "geometry": {"coordinates":[0.1214099973,52.2147789001],"type":"Point"}
}