{
  "type": "Feature",
  "properties": {
    "iso:country":"GB",
    "sg:address":"19 Victory Street",
    "sg:city":"Sheerness",
    "sg:classifiers":[
        {
            "category":"Bars & Pubs",
            "type":"Food & Drink"
        },
        {
            "category":"Community Center",
            "subcategory":"Social",
            "type":"Public Place"
        }
    ],
    "sg:phone":"+44 1795 662376",
    "sg:postcode":"ME12 1NZ",
    "sg:province":"Kent",
    "sg:tags":[
        "pubs",
        "house",
        "inn",
        "activity"
    ],
    "wof:name":"Ye Olde True Briton",
    "wof:placetype":"venue"
},
  "geometry": {"coordinates":[0.759258,51.44051],"type":"Point"}
}