{
  "type": "Feature",
  "properties": {
    "iso:country":"GB",
    "sg:address":"117 Church Street",
    "sg:city":"London",
    "sg:classifiers":[
        {
            "category":"Shopping",
            "subcategory":"Shoes",
            "type":"Retail Goods"
        }
    ],
    "sg:phone":"+44 20 7723 5888",
    "sg:postcode":"NW8 8HA",
    "sg:province":"Greater London",
    "sg:tags":[
        "shop"
    ],
    "wof:name":"Shoe World",
    "wof:placetype":"venue"
},
  "geometry": {"coordinates":[-0.1717720032,51.522228241],"type":"Point"}
}