{
  "type": "Feature",
  "properties": {
    "iso:country":"GB",
    "sg:address":"Monsall Mill, Monsall Road",
    "sg:city":"Manchester",
    "sg:classifiers":[
        {
            "category":"Home & Garden",
            "subcategory":"Home Furnishings",
            "type":"Retail Goods"
        }
    ],
    "sg:postcode":"M40 8NQ",
    "sg:province":"Greater Manchester",
    "sg:tags":[
        "soft"
    ],
    "wof:name":"Hi-Style",
    "wof:placetype":"venue"
},
  "geometry": {"coordinates":[-2.210644,53.501717],"type":"Point"}
}