{
  "type": "Feature",
  "properties": {
    "addr:full":"34 Main Street West Calder South Lanarkshire EH55 8DR",
    "addr:housenumber":"34",
    "addr:postcode":"eh55 8dr",
    "addr:street":"Main Street",
    "iso:country":"GB",
    "sg:address":"34 Main Street",
    "sg:city":"West Calder",
    "sg:classifiers":[
        {
            "category":"Shopping",
            "subcategory":"Pharmacy",
            "type":"Retail Goods"
        }
    ],
    "sg:phone":"+44 1506 873555",
    "sg:postcode":"EH55 8DR",
    "sg:province":"South Lanarkshire",
    "sg:tags":[
        "pharmacist",
        "dispensing",
        "chemist"
    ],
    "wof:name":"G R & P C MACBRIDE",
    "wof:placetype":"venue"
},
  "geometry": {"coordinates":[-3.5715239048,55.8514442444],"type":"Point"}
}