{
  "type": "Feature",
  "properties": {
    "addr:full":"Suite 4, 4 Culver Walk Colchester Essex CO1 1XJ",
    "addr:housenumber":"suite 4 4",
    "addr:postcode":"co1 1xj",
    "addr:street":"Culver Walk Colchester",
    "iso:country":"GB",
    "sg:address":"Suite 4, 4 Culver Walk",
    "sg:city":"Colchester",
    "sg:classifiers":[
        {
            "category":"Professional",
            "subcategory":"Business Services",
            "type":"Services"
        }
    ],
    "sg:postcode":"CO1 1XJ",
    "sg:province":"Essex",
    "sg:tags":[
        "registrar"
    ],
    "wof:name":"Intech Global Services Ltd.",
    "wof:placetype":"venue"
},
  "geometry": {"coordinates":[0.8965970278,51.8889656067],"type":"Point"}
}