{
  "type": "Feature",
  "properties": {
    "iso:country":"GB",
    "sg:address":"17-18 Peascod Street",
    "sg:city":"Windsor",
    "sg:classifiers":[
        {
            "category":"Shopping",
            "subcategory":"Department Store",
            "type":"Retail Goods"
        }
    ],
    "sg:phone":"+44 1753 864044",
    "sg:postcode":"SL4 1DX",
    "sg:province":"Berkshire",
    "sg:tags":[
        "departmental"
    ],
    "wof:name":"Woolworths plc",
    "wof:placetype":"venue"
},
  "geometry": {"coordinates":[-0.608851,51.481873],"type":"Point"}
}