{
  "type": "Feature",
  "properties": {
    "addr:full":"Midway Depot, Stanbridge Rd Leighton Buzzard Bedfordshire LU7 8PZ",
    "addr:postcode":"lu7 8pz",
    "addr:street":"Midway Depot Stanbridge Rd",
    "iso:country":"GB",
    "sg:address":"Midway Depot, Stanbridge Rd",
    "sg:city":"Leighton Buzzard",
    "sg:classifiers":[
        {
            "category":"Home & Garden",
            "subcategory":"Hardware",
            "type":"Retail Goods"
        }
    ],
    "sg:phone":"+44 1525 217181",
    "sg:postcode":"LU7 8PZ",
    "sg:province":"Bedfordshire",
    "sg:tags":[
        "part",
        "accessory"
    ],
    "wof:name":"S J B Motorcycles",
    "wof:placetype":"venue"
},
  "geometry": {"coordinates":[-0.663909018,51.917350769],"type":"Point"}
}