{
  "type": "Feature",
  "properties": {
    "iso:country":"GB",
    "sg:address":"Dencora Ho, Montpelier Business Pk, Leacon Rd",
    "sg:city":"Hythe",
    "sg:classifiers":[
        {
            "category":"Building & Trades",
            "subcategory":"Construction",
            "type":"Services"
        },
        {
            "category":"Utilities",
            "type":"Services"
        }
    ],
    "sg:phone":"+44 1233 660101",
    "sg:postcode":"TN23 4FG",
    "sg:province":"Kent",
    "sg:tags":[
        "construd",
        "contractor"
    ],
    "wof:name":"Radmount Construction (South) Ltd",
    "wof:placetype":"venue"
},
  "geometry": {"coordinates":[0.8571,51.145859],"type":"Point"}
}