{
  "type": "Feature",
  "properties": {
    "addr:full":"Cherry Lodge Malton Road, Cherry Burton Beverley East Riding of Yorkshire HU17 7RA",
    "addr:postcode":"hu17 7ra",
    "addr:street":"Malton Road",
    "iso:country":"GB",
    "sg:address":"Cherry Lodge Malton Road, Cherry Burton",
    "sg:city":"Beverley",
    "sg:classifiers":[
        {
            "category":"Travel",
            "subcategory":"Travel Agent",
            "type":"Entertainment"
        }
    ],
    "sg:postcode":"HU17 7RA",
    "sg:province":"East Riding of Yorkshire",
    "wof:name":"Toolbox Traveller Ltd",
    "wof:placetype":"venue"
},
  "geometry": {"coordinates":[-0.4981549978,53.8662223816],"type":"Point"}
}