{
  "type": "Feature",
  "properties": {
    "addr:full":"32 St James Street South Petherton Somerset TA13 5BW",
    "addr:housenumber":"32",
    "addr:postcode":"ta13 5bw",
    "addr:street":"St James Street",
    "iso:country":"GB",
    "sg:address":"32 St James Street",
    "sg:city":"South Petherton",
    "sg:classifiers":[
        {
            "category":"Food & Beverages",
            "subcategory":"Meat & Fish",
            "type":"Retail Goods"
        }
    ],
    "sg:phone":"+44 1460 240569",
    "sg:postcode":"TA13 5BW",
    "sg:province":"Somerset",
    "sg:tags":[
        "butcher"
    ],
    "wof:name":"K Churchill Butchers",
    "wof:placetype":"venue"
},
  "geometry": {"coordinates":[-2.8098471165,50.9497909546],"type":"Point"}
}