{
  "type": "Feature",
  "properties": {
    "iso:country":"GB",
    "sg:address":"4 The Parade, Valley Drive",
    "sg:city":"Brighton",
    "sg:classifiers":[
        {
            "category":"Shopping",
            "subcategory":"Antiques",
            "type":"Retail Goods"
        }
    ],
    "sg:phone":"+44 1273 557418",
    "sg:postcode":"BN1 5FQ",
    "sg:province":"East Sussex",
    "wof:name":"Artisans Products",
    "wof:placetype":"venue"
},
  "geometry": {"coordinates":[-0.16876,50.856541],"type":"Point"}
}