{
  "type": "Feature",
  "properties": {
    "addr:full":"5 Brick Kiln Lane, Great Horkesley Colchester Essex CO6 4EU",
    "addr:housenumber":"5",
    "addr:postcode":"co6 4eu",
    "addr:street":"Brick Kiln Lane",
    "iso:country":"GB",
    "sg:address":"5 Brick Kiln Lane, Great Horkesley",
    "sg:city":"Colchester",
    "sg:classifiers":[
        {
            "category":"Building & Trades",
            "subcategory":"Construction",
            "type":"Services"
        }
    ],
    "sg:phone":"+44 1206 273599",
    "sg:postcode":"CO6 4EU",
    "sg:province":"Essex",
    "sg:tags":[
        "builder"
    ],
    "wof:name":"H & C  Welton",
    "wof:placetype":"venue"
},
  "geometry": {"coordinates":[0.878843,51.925091],"type":"Point"}
}