{
  "type": "Feature",
  "properties": {
    "iso:country":"GB",
    "sg:address":"Benwick Road, Doddington",
    "sg:city":"March",
    "sg:classifiers":[
        {
            "category":"Health Services",
            "subcategory":"Hospital",
            "type":"Services"
        }
    ],
    "sg:phone":"+44 1354 740481",
    "sg:postcode":"PE15 0UG",
    "sg:province":"Cambridgeshire",
    "wof:name":"DONNINGTON COMMUNITY HOSPITAL",
    "wof:placetype":"venue"
},
  "geometry": {"coordinates":[-0.0238940008,52.4963150024],"type":"Point"}
}