{
  "type": "Feature",
  "properties": {
    "addr:full":"1 Northend Road London Greater London W14 8ST",
    "addr:housenumber":"1",
    "addr:postcode":"w14 8st",
    "addr:street":"Northend Road",
    "iso:country":"GB",
    "sg:address":"1 Northend Road",
    "sg:city":"London",
    "sg:classifiers":[
        {
            "category":"Real Estate",
            "subcategory":"Real Estate Agent",
            "type":"Services"
        }
    ],
    "sg:phone":"+44 20 7602 5678",
    "sg:postcode":"W14 8ST",
    "sg:province":"Greater London",
    "wof:name":"David Dixon & Co",
    "wof:placetype":"venue"
},
  "geometry": {"coordinates":[-0.2112389952,51.4950180054],"type":"Point"}
}