{
  "type": "Feature",
  "properties": {
    "iso:country":"GB",
    "sg:address":"459 Crow Road",
    "sg:city":"Glasgow",
    "sg:classifiers":[
        {
            "category":"Autos & Motor Vehicles",
            "subcategory":"Automobile Sales",
            "type":"Retail Goods"
        }
    ],
    "sg:phone":"+44 141 954 1577",
    "sg:postcode":"G11 7DN",
    "sg:province":"Glasgow City",
    "sg:tags":[
        "car"
    ],
    "wof:name":"Arnold Clark Finance Ltd.",
    "wof:placetype":"venue"
},
  "geometry": {"coordinates":[-4.326584,55.881634],"type":"Point"}
}