{
  "type": "Feature",
  "properties": {
    "addr:full":"Commercial St, Ystrad Mynach Hengoed Caerphilly CF82 7DY",
    "addr:postcode":"cf82 7dy",
    "addr:street":"Commercial St",
    "iso:country":"GB",
    "sg:address":"Commercial St, Ystrad Mynach",
    "sg:city":"Hengoed",
    "sg:classifiers":[
        {
            "category":"Sports & Exercise",
            "subcategory":"Gym",
            "type":"Entertainment"
        }
    ],
    "sg:phone":"+44 1443 862418",
    "sg:postcode":"CF82 7DY",
    "sg:province":"Caerphilly",
    "sg:tags":[
        "fitness",
        "health",
        "centre"
    ],
    "wof:name":"Club 2000",
    "wof:placetype":"venue"
},
  "geometry": {"coordinates":[-3.231799,51.648319],"type":"Point"}
}