{
  "type": "Feature",
  "properties": {
    "iso:country":"GB",
    "sg:address":"148 Newton Rd, Newton",
    "sg:city":"Swansea",
    "sg:classifiers":[
        {
            "category":"Retail",
            "subcategory":"Auto Repair",
            "type":"Services"
        }
    ],
    "sg:phone":"+44 1792 366378",
    "sg:postcode":"SA3 4ST",
    "sg:province":"Swansea",
    "sg:tags":[
        "modification",
        "garage"
    ],
    "wof:name":"Newton Garage",
    "wof:placetype":"venue"
},
  "geometry": {"coordinates":[-4.0150017738,51.5748558044],"type":"Point"}
}