{
  "type": "Feature",
  "properties": {
    "addr:full":"Ford Farm Taunton Devon TA4 1HS",
    "addr:postcode":"ta4 1hs",
    "iso:country":"GB",
    "sg:address":"Ford Farm",
    "sg:city":"Taunton",
    "sg:classifiers":[
        {
            "category":"Manufacturing",
            "subcategory":"Building Materials",
            "type":"Manufacturing & Wholesale Goods"
        }
    ],
    "sg:phone":"+44 1823 461238",
    "sg:postcode":"TA4 1HS",
    "sg:province":"Devon",
    "sg:tags":[
        "distributor",
        "concrete",
        "mnfrs"
    ],
    "wof:name":"Anchor Stone",
    "wof:placetype":"venue"
},
  "geometry": {"coordinates":[-3.2094540596,51.0258407593],"type":"Point"}
}