{
  "type": "Feature",
  "properties": {
    "addr:full":"21 Cambridge Crescent Teddington Greater London TW11 8DX",
    "addr:housenumber":"21",
    "addr:postcode":"tw11 8dx",
    "addr:street":"Cambridge Crescent",
    "iso:country":"GB",
    "sg:address":"21 Cambridge Crescent",
    "sg:city":"Teddington",
    "sg:classifiers":[
        {
            "category":"Home & Garden",
            "subcategory":"Home Furnishings",
            "type":"Retail Goods"
        }
    ],
    "sg:postcode":"TW11 8DX",
    "sg:province":"Greater London",
    "sg:tags":[
        "blind",
        "curtain",
        "fitting"
    ],
    "wof:name":"Edwina Laurie Home Furnishings",
    "wof:placetype":"venue"
},
  "geometry": {"coordinates":[-0.3302339911,51.428768158],"type":"Point"}
}