{
  "type": "Feature",
  "properties": {
    "iso:country":"GB",
    "sg:address":"33 Westbourne Street",
    "sg:city":"High Wycombe",
    "sg:classifiers":[
        {
            "category":"Retail",
            "subcategory":"Auto Repair",
            "type":"Services"
        }
    ],
    "sg:phone":"+44 1494 452014",
    "sg:postcode":"HP11 2PZ",
    "sg:province":"Buckinghamshire",
    "sg:tags":[
        "modification",
        "garage",
        "related"
    ],
    "wof:name":"Furnwood Sales & Service",
    "wof:placetype":"venue"
},
  "geometry": {"coordinates":[-0.7597249746,51.6314315796],"type":"Point"}
}