{
  "type": "Feature",
  "properties": {
    "iso:country":"GB",
    "sg:address":"35 Great Dockray",
    "sg:city":"Penrith",
    "sg:classifiers":[
        {
            "category":"Farming",
            "subcategory":"Fish & Marine Products",
            "type":"Manufacturing & Wholesale Goods"
        },
        {
            "category":"Food & Beverages",
            "subcategory":"Meat & Fish",
            "type":"Retail Goods"
        }
    ],
    "sg:phone":"+44 1768 863374",
    "sg:postcode":"CA11 7BN",
    "sg:province":"Cumbria",
    "sg:tags":[
        "fishmonger",
        "butcher"
    ],
    "wof:name":"K & J MACKAY",
    "wof:placetype":"venue"
},
  "geometry": {"coordinates":[-2.752756,54.663094],"type":"Point"}
}