{
  "type": "Feature",
  "properties": {
    "addr:full":"10 Morton Avenue Ayr South Ayrshire KA7 2NQ",
    "addr:housenumber":"10",
    "addr:postcode":"ka7 2nq",
    "addr:street":"Morton Avenue",
    "iso:country":"GB",
    "sg:address":"10 Morton Avenue",
    "sg:city":"Ayr",
    "sg:classifiers":[
        {
            "category":"Building & Trades",
            "subcategory":"Cleaning & Sanitation",
            "type":"Services"
        }
    ],
    "sg:phone":"+44 1292 269515",
    "sg:postcode":"KA7 2NQ",
    "sg:province":"South Ayrshire",
    "sg:tags":[
        "contracting",
        "commercial"
    ],
    "wof:name":"Eldon Commercial Cleaning Services",
    "wof:placetype":"venue"
},
  "geometry": {"coordinates":[-4.621240139,55.4491958618],"type":"Point"}
}