{
  "type": "Feature",
  "properties": {
    "addr:full":"Unit 5, Wilton Rd Grimsby Lincolnshire DN36 4AW",
    "addr:housenumber":"unit 5",
    "addr:postcode":"dn36 4aw",
    "addr:street":"Wilton Rd",
    "iso:country":"GB",
    "sg:address":"Unit 5, Wilton Rd",
    "sg:city":"Grimsby",
    "sg:classifiers":[
        {
            "category":"Professional",
            "type":"Services"
        }
    ],
    "sg:phone":"+44 1472 234234",
    "sg:postcode":"DN36 4AW",
    "sg:province":"Lincolnshire",
    "sg:tags":[
        "repair",
        "tech",
        "maintenance"
    ],
    "wof:name":"Orion Pc Services",
    "wof:placetype":"venue"
},
  "geometry": {"coordinates":[-0.0466170013,53.5354614258],"type":"Point"}
}