{
  "type": "Feature",
  "properties": {
    "iso:country":"GB",
    "sg:address":"Flat 12a Devonshire House, School Road",
    "sg:city":"Hounslow",
    "sg:classifiers":[
        {
            "category":"Manufacturing",
            "subcategory":"Tools & Machinery",
            "type":"Manufacturing & Wholesale Goods"
        }
    ],
    "sg:phone":"+44 20 8572 0822",
    "sg:postcode":"TW3 1QX",
    "sg:province":"Greater London",
    "sg:tags":[
        "society",
        "friendly"
    ],
    "wof:name":"Bedi International Ltd.",
    "wof:placetype":"venue"
},
  "geometry": {"coordinates":[-0.366534,51.467236],"type":"Point"}
}