{
  "type": "Feature",
  "properties": {
    "addr:full":"Flat 12a Devonshire House, School Road Hounslow Greater London TW3 1QX",
    "addr:housenumber":"12a devonshire",
    "addr:postcode":"tw3 1qx",
    "addr:street":"School Road",
    "iso:country":"GB",
    "sg:address":"Flat 12a Devonshire House, School Road",
    "sg:city":"Hounslow",
    "sg:classifiers":[
        {
            "category":"Manufacturing",
            "subcategory":"Tools & Machinery",
            "type":"Manufacturing & Wholesale Goods"
        }
    ],
    "sg:phone":"+44 20 8572 0822",
    "sg:postcode":"TW3 1QX",
    "sg:province":"Greater London",
    "sg:tags":[
        "society",
        "friendly"
    ],
    "wof:name":"Bedi International Ltd.",
    "wof:placetype":"venue"
},
  "geometry": {"coordinates":[-0.366534,51.467236],"type":"Point"}
}