{
  "type": "Feature",
  "properties": {
    "addr:full":"Mill House, Nottingham Road, Nether Broughton Melton Mowbray Leicestershire LE14 3HB",
    "addr:postcode":"le14 3hb",
    "addr:street":"Nottingham Road",
    "iso:country":"GB",
    "sg:address":"Mill House, Nottingham Road, Nether Broughton",
    "sg:city":"Melton Mowbray",
    "sg:classifiers":[
        {
            "category":"Building & Trades",
            "subcategory":"Construction",
            "type":"Services"
        }
    ],
    "sg:postcode":"LE14 3HB",
    "sg:province":"Leicestershire",
    "sg:tags":[
        "builder"
    ],
    "wof:name":"Mill House Associates (East Midlands) Ltd.",
    "wof:placetype":"venue"
},
  "geometry": {"coordinates":[-0.925561,52.802677],"type":"Point"}
}