{
  "type": "Feature",
  "properties": {
    "addr:full":"443d Stanley Rd Bootle Merseyside L20 5DN",
    "addr:housenumber":"443d",
    "addr:postcode":"l20 5dn",
    "addr:street":"Stanley Rd",
    "iso:country":"GB",
    "sg:address":"443d Stanley Rd",
    "sg:city":"Bootle",
    "sg:classifiers":[
        {
            "category":"Arena",
            "subcategory":"Sports Club",
            "type":"Entertainment"
        }
    ],
    "sg:phone":"+44 151 922 6979",
    "sg:postcode":"L20 5DN",
    "sg:province":"Merseyside",
    "wof:name":"Qudos",
    "wof:placetype":"venue"
},
  "geometry": {"coordinates":[-2.994139,53.459969],"type":"Point"}
}