{
  "type": "Feature",
  "properties": {
    "addr:full":"11 Regent St Great Yarmouth Norfolk NR30 2AE",
    "addr:housenumber":"11",
    "addr:postcode":"nr30 2ae",
    "addr:street":"Regent St",
    "iso:country":"GB",
    "sg:address":"11 Regent St",
    "sg:city":"Great Yarmouth",
    "sg:classifiers":[
        {
            "category":"Food & Beverages",
            "subcategory":"Meat & Fish",
            "type":"Retail Goods"
        }
    ],
    "sg:phone":"+44 1493 842747",
    "sg:postcode":"NR30 2AE",
    "sg:province":"Norfolk",
    "sg:tags":[
        "chip"
    ],
    "wof:name":"Masterson,W,& Son",
    "wof:placetype":"venue"
},
  "geometry": {"coordinates":[1.7297409773,52.6071586609],"type":"Point"}
}