{
  "type": "Feature",
  "properties": {
    "iso:country":"GB",
    "sg:address":"Stirchley",
    "sg:city":"Telford",
    "sg:classifiers":[
        {
            "category":"Health Services",
            "subcategory":"Doctor",
            "type":"Services"
        }
    ],
    "sg:phone":"+44 1952 592658",
    "sg:postcode":"TF3 1FB",
    "sg:province":"Shropshire",
    "sg:tags":[
        "practitioners"
    ],
    "wof:name":"Stirchley Dental Practice",
    "wof:placetype":"venue"
},
  "geometry": {"coordinates":[-2.43384,52.655102],"type":"Point"}
}