{
  "type": "Feature",
  "properties": {
    "addr:full":"Fore Street Garage, Trowbridge Road Westbury Wiltshire BA13 3AY",
    "addr:postcode":"ba13 3ay",
    "addr:street":"Fore;Trowbridge Road",
    "iso:country":"GB",
    "sg:address":"Fore Street Garage, Trowbridge Road",
    "sg:city":"Westbury",
    "sg:classifiers":[
        {
            "category":"Retail",
            "subcategory":"Auto Repair",
            "type":"Services"
        }
    ],
    "sg:phone":"+44 1373 827922",
    "sg:postcode":"BA13 3AY",
    "sg:province":"Wiltshire",
    "sg:tags":[
        "modification",
        "garage",
        "related"
    ],
    "wof:name":"John Boynton Motors Westbury Ltd",
    "wof:placetype":"venue"
},
  "geometry": {"coordinates":[-2.1824629307,51.263458252],"type":"Point"}
}