{
  "type": "Feature",
  "properties": {
    "addr:full":"Taddington Buxton Derbyshire SK17 9TJ",
    "addr:postcode":"sk17 9tj",
    "iso:country":"GB",
    "sg:address":"Taddington",
    "sg:city":"Buxton",
    "sg:classifiers":[
        {
            "category":"Travel",
            "subcategory":"Hotels & Motels",
            "type":"Entertainment"
        }
    ],
    "sg:phone":"+44 1298 85230",
    "sg:postcode":"SK17 9TJ",
    "sg:province":"Derbyshire",
    "wof:name":"The Waterloo Hotel",
    "wof:placetype":"venue"
},
  "geometry": {"coordinates":[-1.80389,53.239391],"type":"Point"}
}