{
  "type": "Feature",
  "properties": {
    "addr:full":"30 Cote Lane, Allerton Bradford West Yorkshire BD15 8LA",
    "addr:housenumber":"30",
    "addr:postcode":"bd15 8la",
    "addr:street":"Cote Lane",
    "iso:country":"GB",
    "sg:address":"30 Cote Lane, Allerton",
    "sg:city":"Bradford",
    "sg:classifiers":[
        {
            "category":"Building & Trades",
            "subcategory":"Construction",
            "type":"Services"
        }
    ],
    "sg:phone":"+44 1274 491429",
    "sg:postcode":"BD15 8LA",
    "sg:province":"West Yorkshire",
    "sg:tags":[
        "roofing",
        "contracting"
    ],
    "wof:name":"Heaton Roofing",
    "wof:placetype":"venue"
},
  "geometry": {"coordinates":[-1.832857,53.804447],"type":"Point"}
}