{
  "type": "Feature",
  "properties": {
    "iso:country":"GB",
    "sg:address":"Abbey House Farm, Abbey Town",
    "sg:city":"Wigton",
    "sg:classifiers":[
        {
            "category":"Home & Garden",
            "subcategory":"Garden Supply",
            "type":"Retail Goods"
        }
    ],
    "sg:postcode":"CA7 4SZ",
    "sg:province":"Cumbria",
    "sg:tags":[
        "bulb",
        "grower"
    ],
    "wof:name":"R & D Harrison",
    "wof:placetype":"venue"
},
  "geometry": {"coordinates":[-3.1607589722,54.8243484497],"type":"Point"}
}