{
  "type": "Feature",
  "properties": {
    "iso:country":"GB",
    "sg:address":"35 Bridgegate",
    "sg:city":"Irvine",
    "sg:classifiers":[
        {
            "category":"Food & Beverages",
            "subcategory":"Bakery",
            "type":"Retail Goods"
        }
    ],
    "sg:phone":"+44 1294 276160",
    "sg:postcode":"KA12 8BQ",
    "sg:province":"North Ayrshire",
    "sg:tags":[
        "baker"
    ],
    "wof:name":"John Short & Sons (Bakers) Ltd.",
    "wof:placetype":"venue"
},
  "geometry": {"coordinates":[-4.6679620743,55.6144638062],"type":"Point"}
}