{
  "type": "Feature",
  "properties": {
    "addr:full":"78 Trafalgar Rd, Portslade Brighton East Sussex BN41 1GR",
    "addr:housenumber":"78",
    "addr:postcode":"bn41 1gr",
    "addr:street":"Trafalgar Rd",
    "iso:country":"GB",
    "sg:address":"78 Trafalgar Rd, Portslade",
    "sg:city":"Brighton",
    "sg:classifiers":[
        {
            "category":"Retail",
            "subcategory":"Laundry & Dry Cleaning",
            "type":"Services"
        }
    ],
    "sg:postcode":"BN41 1GR",
    "sg:province":"East Sussex",
    "sg:tags":[
        "launderette"
    ],
    "wof:name":"Launderette",
    "wof:placetype":"venue"
},
  "geometry": {"coordinates":[-0.2166070044,50.8364448547],"type":"Point"}
}