{
  "type": "Feature",
  "properties": {
    "iso:country":"GB",
    "sg:address":"Atlas Works, Norwich Road, Lenwade",
    "sg:city":"Norwich",
    "sg:classifiers":[
        {
            "category":"Building & Trades",
            "subcategory":"Construction",
            "type":"Services"
        }
    ],
    "sg:phone":"+44 1603 876900",
    "sg:postcode":"NR9 5SW",
    "sg:province":"Norfolk",
    "sg:tags":[
        "window",
        "replacement"
    ],
    "wof:name":"Aspen Windows Ltd.",
    "wof:placetype":"venue"
},
  "geometry": {"coordinates":[1.10755,52.721939],"type":"Point"}
}