{
  "type": "Feature",
  "properties": {
    "iso:country":"GB",
    "sg:address":"Imber Court Trading Estate, Orchard Lane",
    "sg:city":"East Molesey",
    "sg:classifiers":[
        {
            "category":"Professional",
            "subcategory":"Management & Consulting",
            "type":"Services"
        }
    ],
    "sg:phone":"+44 20 8957 5000",
    "sg:postcode":"KT8 0BN",
    "sg:province":"Greater London",
    "sg:tags":[
        "marketing",
        "consultant"
    ],
    "wof:name":"Delta Marketing Group",
    "wof:placetype":"venue"
},
  "geometry": {"coordinates":[-0.344541,51.401962],"type":"Point"}
}