{
  "type": "Feature",
  "properties": {
    "addr:full":"Glenrothes Depot, Flemington Road Glenrothes Fife KY7 5QF",
    "addr:postcode":"ky7 5qf",
    "addr:street":"Flemington Road",
    "iso:country":"GB",
    "sg:address":"Glenrothes Depot, Flemington Road",
    "sg:city":"Glenrothes",
    "sg:classifiers":[
        {
            "category":"Bus Charters",
            "type":"Transportation"
        }
    ],
    "sg:phone":"+44 1592 757378",
    "sg:postcode":"KY7 5QF",
    "sg:province":"Fife",
    "sg:tags":[
        "coach"
    ],
    "wof:name":"Fife Scottish Omnibuses Ltd.",
    "wof:placetype":"venue"
},
  "geometry": {"coordinates":[-3.1737439632,56.1972084045],"type":"Point"}
}