{
  "type": "Feature",
  "properties": {
    "addr:full":"28-32 Baron Rd, South Woodham Ferrers Chelmsford Essex CM3 5FE",
    "addr:housenumber":"28-32",
    "addr:postcode":"cm3 5fe",
    "addr:street":"Baron Rd",
    "iso:country":"GB",
    "sg:address":"28-32 Baron Rd, South Woodham Ferrers",
    "sg:city":"Chelmsford",
    "sg:classifiers":[
        {
            "category":"Manufacturing",
            "subcategory":"Tools & Machinery",
            "type":"Manufacturing & Wholesale Goods"
        }
    ],
    "sg:phone":"+44 1245 322611",
    "sg:postcode":"CM3 5FE",
    "sg:province":"Essex",
    "sg:tags":[
        "society",
        "friendly"
    ],
    "wof:name":"I T F (Documentation) Ltd",
    "wof:placetype":"venue"
},
  "geometry": {"coordinates":[0.617443,51.645123],"type":"Point"}
}