{
  "type": "Feature",
  "properties": {
    "addr:full":"203 Common Road, Kensworth Dunstable Bedfordshire LU6 2PW",
    "addr:housenumber":"203",
    "addr:postcode":"lu6 2pw",
    "addr:street":"Common Road",
    "iso:country":"GB",
    "sg:address":"203 Common Road, Kensworth",
    "sg:city":"Dunstable",
    "sg:classifiers":[
        {
            "category":"Real Estate",
            "subcategory":"Real Estate Agent",
            "type":"Services"
        }
    ],
    "sg:postcode":"LU6 2PW",
    "sg:province":"Bedfordshire",
    "wof:name":"Banda Property Management Ltd.",
    "wof:placetype":"venue"
},
  "geometry": {"coordinates":[-0.5135009885,51.853843689],"type":"Point"}
}