{
  "type": "Feature",
  "properties": {
    "iso:country":"GB",
    "sg:address":"58 The Linkway, Middlebrook Retail Park",
    "sg:city":"Bolton",
    "sg:classifiers":[
        {
            "category":"Shopping",
            "subcategory":"Pets & Pet Supplies",
            "type":"Retail Goods"
        }
    ],
    "sg:phone":"+44 1204 469477",
    "sg:postcode":"BL6 6JA",
    "sg:province":"Lancashire",
    "wof:name":"Pets At Home",
    "wof:placetype":"venue"
},
  "geometry": {"coordinates":[-2.533229,53.584095],"type":"Point"}
}