{
  "type": "Feature",
  "properties": {
    "iso:country":"GB",
    "sg:address":"Nocton, Old Av",
    "sg:city":"Weybridge",
    "sg:classifiers":[
        {
            "category":"Health Services",
            "subcategory":"Doctor",
            "type":"Services"
        }
    ],
    "sg:phone":"+44 1932 843724",
    "sg:postcode":"KT13 0PG",
    "sg:province":"Surrey",
    "sg:tags":[
        "practitioners"
    ],
    "wof:name":"Howard, J S",
    "wof:placetype":"venue"
},
  "geometry": {"coordinates":[-0.4580650032,51.3727493286],"type":"Point"}
}