{
  "type": "Feature",
  "properties": {
    "addr:full":"Profile House Barrow-in-furness Cumbria LA14 1XT",
    "addr:postcode":"la14 1xt",
    "iso:country":"GB",
    "sg:address":"Profile House",
    "sg:city":"Barrow-in-furness",
    "sg:classifiers":[
        {
            "category":"Manufacturing",
            "subcategory":"Petroleum Products",
            "type":"Manufacturing & Wholesale Goods"
        }
    ],
    "sg:phone":"+44 1229 870131",
    "sg:postcode":"LA14 1XT",
    "sg:province":"Cumbria",
    "sg:tags":[
        "double",
        "glazing"
    ],
    "wof:name":"Windoors",
    "wof:placetype":"venue"
},
  "geometry": {"coordinates":[-3.225847,54.111088],"type":"Point"}
}