{
  "type": "Feature",
  "properties": {
    "iso:country":"GB",
    "sg:address":"Caeaugwynion",
    "sg:city":"Pencader",
    "sg:classifiers":[
        {
            "category":"Building & Trades",
            "subcategory":"Construction",
            "type":"Services"
        }
    ],
    "sg:phone":"+44 1559 384667",
    "sg:postcode":"SA39 9HP",
    "sg:province":"Carmarthenshire",
    "sg:tags":[
        "equipment"
    ],
    "wof:name":"Jag Plant",
    "wof:placetype":"venue"
},
  "geometry": {"coordinates":[-4.2658638954,52.0002288818],"type":"Point"}
}