{
  "type": "Feature",
  "properties": {
    "iso:country":"GB",
    "sg:address":"Ladcastle Farm, Ladcastle Road, Uppermill",
    "sg:city":"Oldham",
    "sg:classifiers":[
        {
            "category":"Building & Trades",
            "subcategory":"Landscaping Services",
            "type":"Services"
        }
    ],
    "sg:postcode":"OL3 6LT",
    "sg:province":"Lancashire",
    "sg:tags":[
        "gardening"
    ],
    "wof:name":"Gardenaid",
    "wof:placetype":"venue"
},
  "geometry": {"coordinates":[-2.006526,53.547478],"type":"Point"}
}