{
  "type": "Feature",
  "properties": {
    "addr:full":"704-705 Havelock Terrace London Greater London SW8 4AR",
    "addr:housenumber":"704-705",
    "addr:postcode":"sw8 4ar",
    "addr:street":"Havelock Terrace",
    "iso:country":"GB",
    "sg:address":"704-705 Havelock Terrace",
    "sg:city":"London",
    "sg:classifiers":[
        {
            "category":"Retail",
            "subcategory":"Auto Repair",
            "type":"Services"
        }
    ],
    "sg:phone":"+44 20 7622 1999",
    "sg:postcode":"SW8 4AR",
    "sg:province":"Greater London",
    "sg:tags":[
        "body",
        "car"
    ],
    "wof:name":"Archway Auto & Marine",
    "wof:placetype":"venue"
},
  "geometry": {"coordinates":[-0.144181,51.47718],"type":"Point"}
}