{
  "type": "Feature",
  "properties": {
    "iso:country":"GB",
    "sg:address":"295 Main Road",
    "sg:city":"Sidcup",
    "sg:classifiers":[
        {
            "category":"Manufacturing",
            "subcategory":"Tools & Machinery",
            "type":"Manufacturing & Wholesale Goods"
        }
    ],
    "sg:postcode":"DA14 6QL",
    "sg:province":"Kent",
    "sg:tags":[
        "society",
        "friendly"
    ],
    "wof:name":"Richard Goodfellow",
    "wof:placetype":"venue"
},
  "geometry": {"coordinates":[0.084626,51.430557],"type":"Point"}
}