{
  "type": "Feature",
  "properties": {
    "iso:country":"GB",
    "sg:address":"25 Oxford Square, Watchfield",
    "sg:city":"Swindon",
    "sg:classifiers":[
        {
            "category":"Retail",
            "subcategory":"Driving School",
            "type":"Services"
        }
    ],
    "sg:postcode":"SN6 8TB",
    "sg:province":"Gloucestershire",
    "wof:name":"Highworth School of Motoring",
    "wof:placetype":"venue"
},
  "geometry": {"coordinates":[-1.650406,51.609772],"type":"Point"}
}