{
  "type": "Feature",
  "properties": {
    "addr:full":"Boundary Ho, 7-17 Jewry St London Greater London EC3N 2JH",
    "addr:housenumber":"7-17",
    "addr:postcode":"ec3n 2jh",
    "addr:street":"Boundary;Jewry St",
    "iso:country":"GB",
    "sg:address":"Boundary Ho, 7-17 Jewry St",
    "sg:city":"London",
    "sg:classifiers":[
        {
            "category":"Manufacturing",
            "subcategory":"Tools & Machinery",
            "type":"Manufacturing & Wholesale Goods"
        }
    ],
    "sg:phone":"+44 20 7680 1083",
    "sg:postcode":"EC3N 2JH",
    "sg:province":"Greater London",
    "sg:tags":[
        "society",
        "friendly"
    ],
    "wof:name":"Iron Trades Insurance Co Ltd",
    "wof:placetype":"venue"
},
  "geometry": {"coordinates":[-0.0768600032,51.5125007629],"type":"Point"}
}