{
  "type": "Feature",
  "properties": {
    "addr:full":"The Dome, Marine Pde Folkestone Kent CT20 1PU",
    "addr:postcode":"ct20 1pu",
    "addr:street":"Pde",
    "iso:country":"GB",
    "sg:address":"The Dome, Marine Pde",
    "sg:city":"Folkestone",
    "sg:classifiers":[
        {
            "category":"Cafe",
            "type":"Food & Drink"
        }
    ],
    "sg:phone":"+44 1303 241896",
    "sg:postcode":"CT20 1PU",
    "sg:province":"Kent",
    "sg:tags":[
        "tea",
        "room"
    ],
    "wof:name":"Cafe Catering",
    "wof:placetype":"venue"
},
  "geometry": {"coordinates":[1.1779450178,51.0844306946],"type":"Point"}
}