{
  "type": "Feature",
  "properties": {
    "addr:full":"79 Bridge Street, Wye Ashford Kent TN25 5ED",
    "addr:housenumber":"79",
    "addr:postcode":"tn25 5ed",
    "addr:street":"Bridge Street",
    "iso:country":"GB",
    "sg:address":"79 Bridge Street, Wye",
    "sg:city":"Ashford",
    "sg:classifiers":[
        {
            "category":"Manufacturing",
            "subcategory":"Metals",
            "type":"Manufacturing & Wholesale Goods"
        }
    ],
    "sg:phone":"+44 1233 812542",
    "sg:postcode":"TN25 5ED",
    "sg:province":"Kent",
    "wof:name":"Mirror Image Metal Polishing",
    "wof:placetype":"venue"
},
  "geometry": {"coordinates":[0.933347,51.183498],"type":"Point"}
}