{
  "type": "Feature",
  "properties": {
    "iso:country":"GB",
    "sg:address":"20 Central Av",
    "sg:city":"Kilmarnock",
    "sg:classifiers":[
        {
            "category":"Food & Beverages",
            "subcategory":"Meat & Fish",
            "type":"Retail Goods"
        }
    ],
    "sg:phone":"+44 1563 521401",
    "sg:postcode":"KA1 4PS",
    "sg:province":"East Ayrshire",
    "sg:tags":[
        "butcher"
    ],
    "wof:name":"Lauchlan Bros",
    "wof:placetype":"venue"
},
  "geometry": {"coordinates":[-4.500099,55.587921],"type":"Point"}
}