{
  "type": "Feature",
  "properties": {
    "addr:full":"12 Uplands Avenue, Clayton Heights Bradford West Yorkshire BD13 1EN",
    "addr:housenumber":"12",
    "addr:postcode":"bd13 1en",
    "addr:street":"Uplands Avenue",
    "iso:country":"GB",
    "sg:address":"12 Uplands Avenue, Clayton Heights",
    "sg:city":"Bradford",
    "sg:classifiers":[
        {
            "category":"Personal",
            "subcategory":"Psychics & Astrologers",
            "type":"Services"
        }
    ],
    "sg:postcode":"BD13 1EN",
    "sg:province":"West Yorkshire",
    "wof:name":"Christine Leveridge Astrologer",
    "wof:placetype":"venue"
},
  "geometry": {"coordinates":[-1.821857,53.772232],"type":"Point"}
}