{
  "type": "Feature",
  "properties": {
    "addr:full":"61 Wilton Way London Greater London E8 1BG",
    "addr:housenumber":"61",
    "addr:postcode":"e8 1bg",
    "addr:street":"Wilton Way",
    "iso:country":"GB",
    "sg:address":"61 Wilton Way",
    "sg:city":"London",
    "sg:classifiers":[
        {
            "category":"Shopping",
            "subcategory":"Shoes",
            "type":"Retail Goods"
        }
    ],
    "sg:phone":"+44 20 7254 5803",
    "sg:postcode":"E8 1BG",
    "sg:province":"Greater London",
    "sg:tags":[
        "shop"
    ],
    "wof:name":"L H Brown (Footwear) Ltd.",
    "wof:placetype":"venue"
},
  "geometry": {"coordinates":[-0.0616180003,51.5457344055],"type":"Point"}
}