{
  "type": "Feature",
  "properties": {
    "addr:full":"573-577 Stratford Road, Sparkhill Birmingham West Midlands B11 4LS",
    "addr:housenumber":"573-577",
    "addr:postcode":"b11 4ls",
    "addr:street":"Stratford Road",
    "iso:country":"GB",
    "sg:address":"573-577 Stratford Road, Sparkhill",
    "sg:city":"Birmingham",
    "sg:classifiers":[
        {
            "category":"Sports & Exercise",
            "subcategory":"Sports Center",
            "type":"Entertainment"
        },
        {
            "category":"Shopping",
            "subcategory":"Shoes",
            "type":"Retail Goods"
        }
    ],
    "sg:phone":"+44 121 772 2637",
    "sg:postcode":"B11 4LS",
    "sg:province":"West Midlands",
    "sg:tags":[
        "shop",
        "retailer",
        "footwear"
    ],
    "wof:name":"Viram Sports",
    "wof:placetype":"venue"
},
  "geometry": {"coordinates":[-1.8655420542,52.4523773193],"type":"Point"}
}