{
  "type": "Feature",
  "properties": {
    "iso:country":"GB",
    "sg:address":"18 Manor House Estate, Hutton Henry",
    "sg:city":"Hartlepool",
    "sg:classifiers":[
        {
            "category":"Farming",
            "subcategory":"Dairy Farm",
            "type":"Manufacturing & Wholesale Goods"
        }
    ],
    "sg:phone":"+44 1429 836592",
    "sg:postcode":"TS27 4RX",
    "sg:province":"Durham",
    "sg:tags":[
        "farmer"
    ],
    "wof:name":"D E & I Lovegreen",
    "wof:placetype":"venue"
},
  "geometry": {"coordinates":[-1.348757,54.722034],"type":"Point"}
}