{
  "type": "Feature",
  "properties": {
    "iso:country":"GB",
    "sg:address":"19-21 High St",
    "sg:city":"Fraserburgh",
    "sg:classifiers":[
        {
            "category":"Retail",
            "subcategory":"Veterinary Services",
            "type":"Services"
        }
    ],
    "sg:phone":"+44 1771 637219",
    "sg:postcode":"AB43 6SQ",
    "sg:province":"Aberdeenshire",
    "sg:tags":[
        "surgeon"
    ],
    "wof:name":"Fotheringham & Partners",
    "wof:placetype":"venue"
},
  "geometry": {"coordinates":[-2.183879,57.5989],"type":"Point"}
}