{
  "type": "Feature",
  "properties": {
    "addr:full":"26 Gracemount Drive Edinburgh City of Edinburgh EH16 6RN",
    "addr:housenumber":"26",
    "addr:postcode":"eh16 6rn",
    "addr:street":"Gracemount Drive",
    "iso:country":"GB",
    "sg:address":"26 Gracemount Drive",
    "sg:city":"Edinburgh",
    "sg:classifiers":[
        {
            "category":"Organizations",
            "subcategory":"Non-profit Organization",
            "type":"Services"
        }
    ],
    "sg:phone":"+44 131 664 7424",
    "sg:postcode":"EH16 6RN",
    "sg:province":"City of Edinburgh",
    "sg:tags":[
        "organisation",
        "voluntary",
        "charity"
    ],
    "wof:name":"L A H A - Liberton Area Handicapped Association Ltd.",
    "wof:placetype":"venue"
},
  "geometry": {"coordinates":[-3.155843,55.903217],"type":"Point"}
}