{
  "type": "Feature",
  "properties": {
    "iso:country":"GB",
    "sg:address":"9 Kelvin Road, Cumbernauld",
    "sg:city":"Glasgow",
    "sg:classifiers":[
        {
            "category":"Home & Garden",
            "subcategory":"Household Appliances",
            "type":"Retail Goods"
        }
    ],
    "sg:phone":"+44 1236 725947",
    "sg:postcode":"G67 2BA",
    "sg:province":"Falkirk",
    "sg:tags":[
        "electrical"
    ],
    "wof:name":"Berverley William Gauld",
    "wof:placetype":"venue"
},
  "geometry": {"coordinates":[-3.980936,55.939831],"type":"Point"}
}