{
  "type": "Feature",
  "properties": {
    "addr:full":"5 New Broadway, Tarring Road Worthing West Sussex BN11 4HP",
    "addr:housenumber":"5",
    "addr:postcode":"bn11 4hp",
    "addr:street":"New Broadway Tarring Road",
    "iso:country":"GB",
    "sg:address":"5 New Broadway, Tarring Road",
    "sg:city":"Worthing",
    "sg:classifiers":[
        {
            "category":"Retail",
            "subcategory":"Driving School",
            "type":"Services"
        }
    ],
    "sg:phone":"+44 1903 238980",
    "sg:postcode":"BN11 4HP",
    "sg:province":"West Sussex",
    "wof:name":"Worthing Driver Training Services",
    "wof:placetype":"venue"
},
  "geometry": {"coordinates":[-0.3754239976,50.8136253357],"type":"Point"}
}