{
  "type": "Feature",
  "properties": {
    "iso:country":"GB",
    "sg:address":"53 Queen Anne Street",
    "sg:city":"London",
    "sg:classifiers":[
        {
            "category":"Real Estate",
            "subcategory":"Surveying",
            "type":"Services"
        }
    ],
    "sg:phone":"+44 20 7224 3888",
    "sg:postcode":"W1G 9HR",
    "sg:province":"Greater London",
    "sg:tags":[
        "surveyor",
        "valuer"
    ],
    "wof:name":"Martin Clarke Associates",
    "wof:placetype":"venue"
},
  "geometry": {"coordinates":[-0.1465789974,51.5181312561],"type":"Point"}
}