{
  "type": "Feature",
  "properties": {
    "iso:country":"GB",
    "sg:address":"Linton House, 164-180 Union Street",
    "sg:city":"London",
    "sg:classifiers":[
        {
            "category":"Utilities",
            "type":"Services"
        }
    ],
    "sg:phone":"+44 20 7633 9399",
    "sg:postcode":"SE1 0LH",
    "sg:province":"Greater London",
    "sg:tags":[
        "internet"
    ],
    "wof:name":"Extend Solutions Ltd.",
    "wof:placetype":"venue"
},
  "geometry": {"coordinates":[-0.099219,51.503857],"type":"Point"}
}