{
  "type": "Feature",
  "properties": {
    "iso:country":"GB",
    "sg:address":"1 Richs Rd",
    "sg:city":"Cardiff",
    "sg:classifiers":[
        {
            "category":"Professional",
            "type":"Services"
        }
    ],
    "sg:phone":"+44 29 2052 1480",
    "sg:postcode":"CF4 4AA",
    "sg:province":"Cardiff",
    "sg:tags":[
        "shopfitters"
    ],
    "wof:name":"Ret-Com Designs",
    "wof:placetype":"venue"
},
  "geometry": {"coordinates":[-3.20195,51.508892],"type":"Point"}
}