{
  "type": "Feature",
  "properties": {
    "iso:country":"GB",
    "sg:address":"24 Alnwick Drive",
    "sg:city":"Bury",
    "sg:classifiers":[
        {
            "category":"Building & Trades",
            "subcategory":"Construction",
            "type":"Services"
        }
    ],
    "sg:phone":"+44 161 796 7361",
    "sg:postcode":"BL9 8BZ",
    "sg:province":"Lancashire",
    "sg:tags":[
        "ceiling",
        "contractor"
    ],
    "wof:name":"North West Building Services",
    "wof:placetype":"venue"
},
  "geometry": {"coordinates":[-2.288568,53.571049],"type":"Point"}
}