{
  "type": "Feature",
  "properties": {
    "iso:country":"GB",
    "sg:address":"25 Barns Street",
    "sg:city":"Ayr",
    "sg:classifiers":[
        {
            "category":"Professional",
            "subcategory":"Lawyer & Legal Services",
            "type":"Services"
        }
    ],
    "sg:phone":"+44 1292 267956",
    "sg:postcode":"KA7 1XB",
    "sg:province":"South Ayrshire",
    "sg:tags":[
        "solicitor"
    ],
    "wof:name":"GARDINER & NOBLE",
    "wof:placetype":"venue"
},
  "geometry": {"coordinates":[-4.6330227852,55.4607086182],"type":"Point"}
}