{
  "type": "Feature",
  "properties": {
    "addr:full":"25 Mizzy Road Rochdale Lancashire OL12 6HW",
    "addr:housenumber":"25",
    "addr:postcode":"ol12 6hw",
    "addr:street":"Mizzy Road",
    "iso:country":"GB",
    "sg:address":"25 Mizzy Road",
    "sg:city":"Rochdale",
    "sg:classifiers":[
        {
            "category":"Professional",
            "subcategory":"Accounting & Tax Preparation",
            "type":"Services"
        }
    ],
    "sg:phone":"+44 1706 647727",
    "sg:postcode":"OL12 6HW",
    "sg:province":"Lancashire",
    "sg:tags":[
        "accountant",
        "activity"
    ],
    "wof:name":"Ian D A Walker",
    "wof:placetype":"venue"
},
  "geometry": {"coordinates":[-2.1617660522,53.6265983582],"type":"Point"}
}