{
  "type": "Feature",
  "properties": {
    "addr:full":"Old Rectory, East Lambrook South Petherton Somerset TA13 5HH",
    "addr:postcode":"ta13 5hh",
    "addr:street":"East Lambrook",
    "iso:country":"GB",
    "sg:address":"Old Rectory, East Lambrook",
    "sg:city":"South Petherton",
    "sg:classifiers":[
        {
            "category":"Professional",
            "subcategory":"Accounting & Tax Preparation",
            "type":"Services"
        }
    ],
    "sg:phone":"+44 1460 242289",
    "sg:postcode":"TA13 5HH",
    "sg:province":"Somerset",
    "sg:tags":[
        "accountant"
    ],
    "wof:name":"H A Bean & Co",
    "wof:placetype":"venue"
},
  "geometry": {"coordinates":[-2.805539,50.949532],"type":"Point"}
}