{
  "type": "Feature",
  "properties": {
    "addr:full":"Po Box 205 Darlington Durham DL3 7XP",
    "addr:housenumber":"po;205",
    "addr:postcode":"dl3 7xp",
    "addr:street":"Box",
    "iso:country":"GB",
    "sg:address":"Po Box 205",
    "sg:city":"Darlington",
    "sg:classifiers":[
        {
            "category":"Utilities",
            "type":"Services"
        }
    ],
    "sg:phone":"+44 1325 361729",
    "sg:postcode":"DL3 7XP",
    "sg:province":"Durham",
    "sg:tags":[
        "internet"
    ],
    "wof:name":"Intermedia Solutions Ltd.",
    "wof:placetype":"venue"
},
  "geometry": {"coordinates":[-1.5624799728,54.5241203308],"type":"Point"}
}