{
  "type": "Feature",
  "properties": {
    "addr:full":"48 Vicarage Rd, Mickleover Derby Derbyshire DE3 5ED",
    "addr:housenumber":"48",
    "addr:postcode":"de3 5ed",
    "addr:street":"Vicarage Rd",
    "iso:country":"GB",
    "sg:address":"48 Vicarage Rd, Mickleover",
    "sg:city":"Derby",
    "sg:classifiers":[
        {
            "category":"Retail",
            "subcategory":"Auto Repair",
            "type":"Services"
        }
    ],
    "sg:phone":"+44 1332 517778",
    "sg:postcode":"DE3 5ED",
    "sg:province":"Derbyshire",
    "sg:tags":[
        "car",
        "upholsterer"
    ],
    "wof:name":"David Beswick Coach Trimmers",
    "wof:placetype":"venue"
},
  "geometry": {"coordinates":[-1.5503900051,52.9061088562],"type":"Point"}
}