{
  "type": "Feature",
  "properties": {
    "addr:full":"Midland Road Bradford West Yorkshire BD1 3EQ",
    "addr:postcode":"bd1 3eq",
    "addr:street":"Midland Road",
    "iso:country":"GB",
    "sg:address":"Midland Road",
    "sg:city":"Bradford",
    "sg:classifiers":[
        {
            "category":"Autos & Motor Vehicles",
            "subcategory":"Automobile Sales",
            "type":"Retail Goods"
        }
    ],
    "sg:phone":"+44 1274 774444",
    "sg:postcode":"BD1 3EQ",
    "sg:province":"West Yorkshire",
    "sg:tags":[
        "auction",
        "car"
    ],
    "wof:name":"Bradford City Motor Auctions Ltd.",
    "wof:placetype":"venue"
},
  "geometry": {"coordinates":[-1.7571940422,53.8026161194],"type":"Point"}
}