{
  "type": "Feature",
  "properties": {
    "iso:country":"GB",
    "sg:address":"26 Shaftesbury Av",
    "sg:city":"Stourbridge",
    "sg:classifiers":[
        {
            "category":"Building & Trades",
            "subcategory":"Construction",
            "type":"Services"
        }
    ],
    "sg:phone":"+44 1384 393998",
    "sg:postcode":"DY9 0YP",
    "sg:province":"West Midlands",
    "sg:tags":[
        "builder"
    ],
    "wof:name":"R G Knight",
    "wof:placetype":"venue"
},
  "geometry": {"coordinates":[-2.128521,52.445656],"type":"Point"}
}