{
  "type": "Feature",
  "properties": {
    "addr:full":"24 Mountjoy Road Huddersfield West Yorkshire HD1 5PZ",
    "addr:housenumber":"24",
    "addr:postcode":"hd1 5pz",
    "addr:street":"Mountjoy Road",
    "iso:country":"GB",
    "sg:address":"24 Mountjoy Road",
    "sg:city":"Huddersfield",
    "sg:classifiers":[
        {
            "category":"Social Services",
            "subcategory":"Retirement Home",
            "type":"Services"
        }
    ],
    "sg:phone":"+44 1484 432471",
    "sg:postcode":"HD1 5PZ",
    "sg:province":"West Yorkshire",
    "sg:tags":[
        "residential",
        "care"
    ],
    "wof:name":"The Bridgewood Trust",
    "wof:placetype":"venue"
},
  "geometry": {"coordinates":[-1.794454,53.650589],"type":"Point"}
}