{
  "type": "Feature",
  "properties": {
    "addr:full":"7 Station Road Newton Abbot Devon TQ13 9AL",
    "addr:housenumber":"7",
    "addr:postcode":"tq13 9al",
    "addr:street":"Station Road",
    "iso:country":"GB",
    "sg:address":"7 Station Road",
    "sg:city":"Newton Abbot",
    "sg:classifiers":[
        {
            "category":"Food & Beverages",
            "subcategory":"Bakery",
            "type":"Retail Goods"
        }
    ],
    "sg:phone":"+44 1626 834463",
    "sg:postcode":"TQ13 9AL",
    "sg:province":"Devon",
    "sg:tags":[
        "baker"
    ],
    "wof:name":"Thomas's of Bovey",
    "wof:placetype":"venue"
},
  "geometry": {"coordinates":[-3.678321,50.591263],"type":"Point"}
}