{
  "type": "Feature",
  "properties": {
    "addr:full":"Brooks's Bar, Shewsbury St, Old Trafford Manchester Cheshire M16 7WU",
    "addr:postcode":"m16 7wu",
    "addr:street":"Shewsbury St",
    "iso:country":"GB",
    "sg:address":"Brooks's Bar, Shewsbury St, Old Trafford",
    "sg:city":"Manchester",
    "sg:classifiers":[
        {
            "category":"Manufacturing",
            "subcategory":"Lumber",
            "type":"Manufacturing & Wholesale Goods"
        }
    ],
    "sg:phone":"+44 161 226 9190",
    "sg:postcode":"M16 7WU",
    "sg:province":"Cheshire",
    "sg:tags":[
        "importer",
        "merchants",
        "agent",
        "timber"
    ],
    "wof:name":"Moores Timber Merchants Ltd",
    "wof:placetype":"venue"
},
  "geometry": {"coordinates":[-2.25989,53.45937],"type":"Point"}
}