{
  "type": "Feature",
  "properties": {
    "addr:full":"Chetwode Priory, Buckingham Buckingham Buckinghamshire MK18 4LB",
    "addr:housenumber":"chetwode",
    "addr:postcode":"mk18 4lb",
    "addr:street":"Priory",
    "iso:country":"GB",
    "sg:address":"Chetwode Priory, Buckingham",
    "sg:city":"Buckingham",
    "sg:classifiers":[
        {
            "category":"Real Estate",
            "subcategory":"Surveying",
            "type":"Services"
        }
    ],
    "sg:phone":"+44 1280 847775",
    "sg:postcode":"MK18 4LB",
    "sg:province":"Buckinghamshire",
    "sg:tags":[
        "surveyor",
        "valuer"
    ],
    "wof:name":"Landframe Securities Ltd.",
    "wof:placetype":"venue"
},
  "geometry": {"coordinates":[-1.0660339594,51.9605064392],"type":"Point"}
}