{
  "type": "Feature",
  "properties": {
    "addr:full":"27 Union Road, Low Moor Bradford West Yorkshire BD12 0DX",
    "addr:housenumber":"27",
    "addr:postcode":"bd12 0dx",
    "addr:street":"Union Road",
    "iso:country":"GB",
    "sg:address":"27 Union Road, Low Moor",
    "sg:city":"Bradford",
    "sg:classifiers":[
        {
            "category":"Food & Beverages",
            "subcategory":"Supermarket",
            "type":"Retail Goods"
        }
    ],
    "sg:phone":"+44 1274 605640",
    "sg:postcode":"BD12 0DX",
    "sg:province":"West Yorkshire",
    "wof:name":"J B`S",
    "wof:placetype":"venue"
},
  "geometry": {"coordinates":[-1.77156,53.756214],"type":"Point"}
}