{
  "type": "Feature",
  "properties": {
    "iso:country":"GB",
    "sg:address":"Bookham Industrial Estate, Bookham",
    "sg:city":"Leatherhead",
    "sg:classifiers":[
        {
            "category":"Shopping",
            "subcategory":"Discount & Variety Stores",
            "type":"Retail Goods"
        }
    ],
    "sg:postcode":"KT23 3EU",
    "sg:province":"Surrey",
    "sg:tags":[
        "cleaning",
        "supply"
    ],
    "wof:name":"Symbio",
    "wof:placetype":"venue"
},
  "geometry": {"coordinates":[-0.3867970109,51.2851791382],"type":"Point"}
}