{
  "type": "Feature",
  "properties": {
    "addr:full":"31 Alder Drive, Hoghton Preston Lancashire PR5 0AD",
    "addr:housenumber":"31",
    "addr:postcode":"pr5 0ad",
    "addr:street":"Alder Drive",
    "iso:country":"GB",
    "sg:address":"31 Alder Drive, Hoghton",
    "sg:city":"Preston",
    "sg:classifiers":[
        {
            "category":"Retail",
            "subcategory":"Driving School",
            "type":"Services"
        }
    ],
    "sg:postcode":"PR5 0AD",
    "sg:province":"Lancashire",
    "wof:name":"Ray Buckley",
    "wof:placetype":"venue"
},
  "geometry": {"coordinates":[-2.621339,53.732487],"type":"Point"}
}