{
  "type": "Feature",
  "properties": {
    "iso:country":"GB",
    "sg:address":"9 Acorn Close",
    "sg:city":"Ebbw Vale",
    "sg:classifiers":[
        {
            "category":"Home & Garden",
            "subcategory":"Home Furnishings",
            "type":"Retail Goods"
        }
    ],
    "sg:phone":"+44 1495 350975",
    "sg:postcode":"NP3 5UP",
    "sg:province":"Blaenau Gwent",
    "sg:tags":[
        "awning",
        "canopy",
        "blinds"
    ],
    "wof:name":"Oriel Blinds",
    "wof:placetype":"venue"
},
  "geometry": {"coordinates":[-3.217057,51.803993],"type":"Point"}
}