{
  "type": "Feature",
  "properties": {
    "addr:full":"9 Park Crescent Edinburgh City of Edinburgh EH16 6JD",
    "addr:housenumber":"9",
    "addr:postcode":"eh16 6jd",
    "addr:street":"Park Crescent",
    "iso:country":"GB",
    "sg:address":"9 Park Crescent",
    "sg:city":"Edinburgh",
    "sg:classifiers":[
        {
            "category":"Professional",
            "subcategory":"Engineering",
            "type":"Services"
        },
        {
            "category":"Real Estate",
            "subcategory":"Architect",
            "type":"Services"
        }
    ],
    "sg:phone":"+44 131 664 5176",
    "sg:postcode":"EH16 6JD",
    "sg:province":"City of Edinburgh",
    "sg:tags":[
        "consulting",
        "engineer"
    ],
    "wof:name":"David Elder Partnership",
    "wof:placetype":"venue"
},
  "geometry": {"coordinates":[-3.157713,55.913204],"type":"Point"}
}