{
  "type": "Feature",
  "properties": {
    "addr:full":"91-93 Moorgate London Greater London EC2M 6SJ",
    "addr:housenumber":"91-93",
    "addr:postcode":"ec2m 6sj",
    "addr:street":"Moorgate",
    "iso:country":"GB",
    "sg:address":"91-93 Moorgate",
    "sg:city":"London",
    "sg:classifiers":[
        {
            "category":"Bars & Pubs",
            "subcategory":"Wine Bar",
            "type":"Food & Drink"
        }
    ],
    "sg:phone":"+44 20 7588 2581",
    "sg:postcode":"EC2M 6SJ",
    "sg:province":"Greater London",
    "wof:name":"Davys Bishops Parlour",
    "wof:placetype":"venue"
},
  "geometry": {"coordinates":[-0.088704,51.517803],"type":"Point"}
}