{
  "type": "Feature",
  "properties": {
    "addr:full":"16-17 Regency Square Brighton East Sussex BN1 2FG",
    "addr:housenumber":"16-17",
    "addr:postcode":"bn1 2fg",
    "addr:street":"Regency Square",
    "iso:country":"GB",
    "sg:address":"16-17 Regency Square",
    "sg:city":"Brighton",
    "sg:classifiers":[
        {
            "category":"Travel",
            "subcategory":"Hotels & Motels",
            "type":"Entertainment"
        }
    ],
    "sg:phone":"+44 1273 729334",
    "sg:postcode":"BN1 2FG",
    "sg:province":"East Sussex",
    "wof:name":"Paul Collins",
    "wof:placetype":"venue"
},
  "geometry": {"coordinates":[-0.150889,50.822891],"type":"Point"}
}