{
  "type": "Feature",
  "properties": {
    "iso:country":"GB",
    "sg:address":"4 Chapel Street",
    "sg:city":"Marlow",
    "sg:classifiers":[
        {
            "category":"Utilities",
            "subcategory":"Fuel Oil & Lpg",
            "type":"Services"
        }
    ],
    "sg:phone":"+44 1628 478222",
    "sg:postcode":"SL7 1DD",
    "sg:province":"Berkshire",
    "sg:tags":[
        "gas"
    ],
    "wof:name":"Genesis Energy Ltd",
    "wof:placetype":"venue"
},
  "geometry": {"coordinates":[-0.775859,51.573029],"type":"Point"}
}