{
  "type": "Feature",
  "properties": {
    "addr:full":"15 Cunningham Crescent Bournemouth Dorset BH11 8DN",
    "addr:housenumber":"15",
    "addr:postcode":"bh11 8dn",
    "addr:street":"Cunningham Crescent",
    "iso:country":"GB",
    "sg:address":"15 Cunningham Crescent",
    "sg:city":"Bournemouth",
    "sg:classifiers":[
        {
            "category":"Retail",
            "subcategory":"Driving School",
            "type":"Services"
        },
        {
            "category":"Education",
            "subcategory":"University",
            "type":"Public Place"
        }
    ],
    "sg:postcode":"BH11 8DN",
    "sg:province":"Dorset",
    "sg:tags":[
        "higher"
    ],
    "wof:name":"Holland School of Motoring",
    "wof:placetype":"venue"
},
  "geometry": {"coordinates":[-1.9097019434,50.7585220337],"type":"Point"}
}