{
  "type": "Feature",
  "properties": {
    "iso:country":"GB",
    "sg:address":"23 Haslingden Close",
    "sg:city":"Harpenden",
    "sg:classifiers":[
        {
            "category":"Building & Trades",
            "subcategory":"Construction",
            "type":"Services"
        }
    ],
    "sg:phone":"+44 1582 760545",
    "sg:postcode":"AL5 3EW",
    "sg:province":"Hertfordshire",
    "sg:tags":[
        "builder"
    ],
    "wof:name":"Pearce Homes Ltd.",
    "wof:placetype":"venue"
},
  "geometry": {"coordinates":[-0.380533,51.82436],"type":"Point"}
}