{
  "type": "Feature",
  "properties": {
    "addr:full":"32 Brownswall Road, Sedgley Dudley Staffordshire DY3 3NR",
    "addr:housenumber":"32",
    "addr:postcode":"dy3 3nr",
    "addr:street":"Brownswall Road",
    "iso:country":"GB",
    "sg:address":"32 Brownswall Road, Sedgley",
    "sg:city":"Dudley",
    "sg:classifiers":[
        {
            "category":"Education",
            "subcategory":"Dance Studio",
            "type":"Public Place"
        }
    ],
    "sg:phone":"+44 1902 663654",
    "sg:postcode":"DY3 3NR",
    "sg:province":"Staffordshire",
    "sg:tags":[
        "school",
        "dancing"
    ],
    "wof:name":"The Marilyn Harris School of Dancing",
    "wof:placetype":"venue"
},
  "geometry": {"coordinates":[-2.1331579685,52.5390815735],"type":"Point"}
}