{
  "type": "Feature",
  "properties": {
    "addr:full":"Unit 8, Youngs Industrial Estate, Paices Hill Reading Berkshire RG7 4PW",
    "addr:housenumber":"unit 8",
    "addr:postcode":"rg7 4pw",
    "addr:street":"Youngs Industrial Estate Paices Hill",
    "iso:country":"GB",
    "sg:address":"Unit 8, Youngs Industrial Estate, Paices Hill",
    "sg:city":"Reading",
    "sg:classifiers":[
        {
            "category":"Professional",
            "subcategory":"Engineering",
            "type":"Services"
        }
    ],
    "sg:postcode":"RG7 4PW",
    "sg:province":"Berkshire",
    "sg:tags":[
        "precision",
        "engineer"
    ],
    "wof:name":"W Franks Engineering",
    "wof:placetype":"venue"
},
  "geometry": {"coordinates":[-1.1544400454,51.3704910278],"type":"Point"}
}