{
  "type": "Feature",
  "properties": {
    "iso:country":"GB",
    "sg:address":"Abertillery Rd",
    "sg:city":"Blaina",
    "sg:classifiers":[
        {
            "category":"Recreation",
            "subcategory":"Amusement Park",
            "type":"Entertainment"
        }
    ],
    "sg:phone":"+44 1495 291771",
    "sg:postcode":"NP13 3DN",
    "sg:province":"Blaenau Gwent",
    "sg:tags":[
        "arcade"
    ],
    "wof:name":"A B Leisure",
    "wof:placetype":"venue"
},
  "geometry": {"coordinates":[-3.1590418816,51.7604904175],"type":"Point"}
}