{
  "type": "Feature",
  "properties": {
    "addr:full":"3 Southwick Square, Southwick Brighton West Sussex BN42 4FP",
    "addr:housenumber":"3",
    "addr:postcode":"bn42 4fp",
    "addr:street":"Southwick Square",
    "iso:country":"GB",
    "sg:address":"3 Southwick Square, Southwick",
    "sg:city":"Brighton",
    "sg:classifiers":[
        {
            "category":"Professional",
            "subcategory":"Art Services",
            "type":"Services"
        }
    ],
    "sg:postcode":"BN42 4FP",
    "sg:province":"West Sussex",
    "sg:tags":[
        "decorating",
        "painting"
    ],
    "wof:name":"Bryter Colours",
    "wof:placetype":"venue"
},
  "geometry": {"coordinates":[-0.235387,50.834106],"type":"Point"}
}