{
  "type": "Feature",
  "properties": {
    "addr:full":"Merlin Crescent, Buckhaven Leven Fife KY8 1HJ",
    "addr:postcode":"ky8 1hj",
    "addr:street":"Merlin Crescent Buckhaven Leven",
    "iso:country":"GB",
    "sg:address":"Merlin Crescent, Buckhaven",
    "sg:city":"Leven",
    "sg:classifiers":[
        {
            "category":"Health Services",
            "subcategory":"Doctor",
            "type":"Services"
        }
    ],
    "sg:phone":"+44 1592 713299",
    "sg:postcode":"KY8 1HJ",
    "sg:province":"Fife",
    "sg:tags":[
        "practitioners"
    ],
    "wof:name":"Muiredge Surgery",
    "wof:placetype":"venue"
},
  "geometry": {"coordinates":[-3.038649,56.175171],"type":"Point"}
}