{
  "type": "Feature",
  "properties": {
    "addr:full":"15a West Avenue Filey North Yorkshire YO14 9AA",
    "addr:housenumber":"15a",
    "addr:postcode":"yo14 9aa",
    "addr:street":"West Avenue",
    "iso:country":"GB",
    "sg:address":"15a West Avenue",
    "sg:city":"Filey",
    "sg:classifiers":[
        {
            "category":"Real Estate",
            "subcategory":"Real Estate Agent",
            "type":"Services"
        }
    ],
    "sg:phone":"+44 1723 515527",
    "sg:postcode":"YO14 9AA",
    "sg:province":"North Yorkshire",
    "wof:name":"D M A ESTATE AGENTS",
    "wof:placetype":"venue"
},
  "geometry": {"coordinates":[-0.288854003,54.2090034485],"type":"Point"}
}