{
  "type": "Feature",
  "properties": {
    "iso:country":"GB",
    "sg:address":"5 Quorn Way, Grafton St Industrial Estate",
    "sg:city":"Northampton",
    "sg:classifiers":[
        {
            "category":"Autos & Motor Vehicles",
            "subcategory":"Auto Supplies",
            "type":"Retail Goods"
        }
    ],
    "sg:phone":"+44 1604 602061",
    "sg:postcode":"NN1 2PN",
    "sg:province":"Northamptonshire",
    "sg:tags":[
        "windscreen"
    ],
    "wof:name":"Autoglass",
    "wof:placetype":"venue"
},
  "geometry": {"coordinates":[-0.9025620222,52.2429618835],"type":"Point"}
}