{
  "type": "Feature",
  "properties": {
    "addr:full":"50a Bridge St Northampton Northamptonshire NN1 1PA",
    "addr:housenumber":"50a",
    "addr:postcode":"nn1 1pa",
    "addr:street":"Bridge St",
    "iso:country":"GB",
    "sg:address":"50a Bridge St",
    "sg:city":"Northampton",
    "sg:classifiers":[
        {
            "category":"Professional",
            "subcategory":"Employment Agencies",
            "type":"Services"
        }
    ],
    "sg:phone":"+44 1604 622116",
    "sg:postcode":"NN1 1PA",
    "sg:province":"Northamptonshire",
    "sg:tags":[
        "consultant"
    ],
    "wof:name":"Taskmaster (Midlands) Ltd",
    "wof:placetype":"venue"
},
  "geometry": {"coordinates":[-0.8974270225,52.2353515625],"type":"Point"}
}