{
  "type": "Feature",
  "properties": {
    "iso:country":"GB",
    "sg:address":"67 Norwich Street",
    "sg:city":"Dereham",
    "sg:classifiers":[
        {
            "category":"Organizations",
            "subcategory":"Community Association",
            "type":"Services"
        }
    ],
    "sg:phone":"+44 1362 699655",
    "sg:postcode":"NR19 1AD",
    "sg:province":"Norfolk",
    "sg:tags":[
        "society",
        "housing"
    ],
    "wof:name":"St.Matthew Housing",
    "wof:placetype":"venue"
},
  "geometry": {"coordinates":[0.94663,52.679859],"type":"Point"}
}