{
  "type": "Feature",
  "properties": {
    "iso:country":"GB",
    "sg:address":"118 Watson Road",
    "sg:city":"Blackpool",
    "sg:classifiers":[
        {
            "category":"Wholesale",
            "subcategory":"Meat",
            "type":"Manufacturing & Wholesale Goods"
        }
    ],
    "sg:phone":"+44 1253 402710",
    "sg:postcode":"FY4 2BP",
    "sg:province":"Lancashire",
    "sg:tags":[
        "product"
    ],
    "wof:name":"P McGough",
    "wof:placetype":"venue"
},
  "geometry": {"coordinates":[-3.041661,53.792789],"type":"Point"}
}