{
  "type": "Feature",
  "properties": {
    "iso:country":"GB",
    "sg:address":"Logic Ho, 143 Newmarket Rd",
    "sg:city":"Cambridge",
    "sg:classifiers":[
        {
            "category":"Professional",
            "subcategory":"Computer Services",
            "type":"Services"
        }
    ],
    "sg:postcode":"CB5 8HA",
    "sg:province":"Cambridgeshire",
    "sg:tags":[
        "consultant"
    ],
    "wof:name":"Micrologic Solutions Ltd",
    "wof:placetype":"venue"
},
  "geometry": {"coordinates":[0.1747249961,52.2108001709],"type":"Point"}
}