{
  "type": "Feature",
  "properties": {
    "addr:full":"Logic Ho, 143 Newmarket Rd Cambridge Cambridgeshire CB5 8HA",
    "addr:housenumber":"143",
    "addr:postcode":"cb5 8ha",
    "addr:street":"Newmarket Rd",
    "iso:country":"GB",
    "sg:address":"Logic Ho, 143 Newmarket Rd",
    "sg:city":"Cambridge",
    "sg:classifiers":[
        {
            "category":"Professional",
            "subcategory":"Computer Services",
            "type":"Services"
        }
    ],
    "sg:postcode":"CB5 8HA",
    "sg:province":"Cambridgeshire",
    "sg:tags":[
        "consultant"
    ],
    "wof:name":"Micrologic Solutions Ltd",
    "wof:placetype":"venue"
},
  "geometry": {"coordinates":[0.1747249961,52.2108001709],"type":"Point"}
}