{
  "type": "Feature",
  "properties": {
    "iso:country":"GB",
    "sg:address":"7 Ruckles Way",
    "sg:city":"Amersham",
    "sg:classifiers":[
        {
            "category":"Professional",
            "subcategory":"Accounting & Tax Preparation",
            "type":"Services"
        }
    ],
    "sg:phone":"+44 1494 725880",
    "sg:postcode":"HP7 0BZ",
    "sg:province":"Buckinghamshire",
    "sg:tags":[
        "accountant"
    ],
    "wof:name":"Metropolitan Bureau of Accounting Ltd.",
    "wof:placetype":"venue"
},
  "geometry": {"coordinates":[-0.608162,51.667053],"type":"Point"}
}