{
  "type": "Feature",
  "properties": {
    "addr:full":"Linchmere Road London Greater London SE12 0NB",
    "addr:postcode":"se12 0nb",
    "addr:street":"Linchmere Road",
    "iso:country":"GB",
    "sg:address":"Linchmere Road",
    "sg:city":"London",
    "sg:classifiers":[
        {
            "category":"Education",
            "subcategory":"School",
            "type":"Public Place"
        }
    ],
    "sg:phone":"+44 20 8857 5637",
    "sg:postcode":"SE12 0NB",
    "sg:province":"Greater London",
    "sg:tags":[
        "local",
        "authority"
    ],
    "wof:name":"Baring Primary School",
    "wof:placetype":"venue"
},
  "geometry": {"coordinates":[0.012752,51.444618],"type":"Point"}
}