{
  "type": "Feature",
  "properties": {
    "addr:full":"39 Burstead Close Brighton East Sussex BN1 7HT",
    "addr:housenumber":"39",
    "addr:postcode":"bn1 7ht",
    "addr:street":"Burstead Close",
    "iso:country":"GB",
    "sg:address":"39 Burstead Close",
    "sg:city":"Brighton",
    "sg:classifiers":[
        {
            "category":"Manufacturing",
            "subcategory":"Metals",
            "type":"Manufacturing & Wholesale Goods"
        },
        {
            "category":"Retail",
            "subcategory":"Repair Shop",
            "type":"Services"
        }
    ],
    "sg:postcode":"BN1 7HT",
    "sg:province":"East Sussex",
    "sg:tags":[
        "heat",
        "-",
        "treatment",
        "furniture"
    ],
    "wof:name":"D Willson's French Polishing",
    "wof:placetype":"venue"
},
  "geometry": {"coordinates":[-0.130319,50.849415],"type":"Point"}
}