{
  "type": "Feature",
  "properties": {
    "iso:country":"GB",
    "sg:address":"77 Lochend Road",
    "sg:city":"Glasgow",
    "sg:classifiers":[
        {
            "category":"Shopping",
            "subcategory":"Pharmacy",
            "type":"Retail Goods"
        }
    ],
    "sg:phone":"+44 141 773 2003",
    "sg:postcode":"G34 0JZ",
    "sg:province":"Glasgow City",
    "sg:tags":[
        "pharmacist",
        "chemist"
    ],
    "wof:name":"E Moss",
    "wof:placetype":"venue"
},
  "geometry": {"coordinates":[-4.107231,55.87048],"type":"Point"}
}