{
  "type": "Feature",
  "properties": {
    "addr:full":"Unit 1 Eaton Court High Street, Long Eaton Nottingham Derbyshire NG10 1LP",
    "addr:housenumber":"unit 1",
    "addr:postcode":"ng10 1lp",
    "addr:street":"Eaton Court High Street",
    "iso:country":"GB",
    "sg:address":"Unit 1 Eaton Court High Street, Long Eaton",
    "sg:city":"Nottingham",
    "sg:classifiers":[
        {
            "category":"Shopping",
            "subcategory":"Catalog Store",
            "type":"Retail Goods"
        }
    ],
    "sg:phone":"+44 115 946 2315",
    "sg:postcode":"NG10 1LP",
    "sg:province":"Derbyshire",
    "sg:tags":[
        "catalogue",
        "showroom"
    ],
    "wof:name":"Argos Ltd.",
    "wof:placetype":"venue"
},
  "geometry": {"coordinates":[-1.270273,52.897491],"type":"Point"}
}