{
  "type": "Feature",
  "properties": {
    "iso:country":"GB",
    "sg:address":"1-2 Market Street",
    "sg:city":"Carlisle",
    "sg:classifiers":[
        {
            "category":"Shopping",
            "subcategory":"Bicycles & Sporting Goods",
            "type":"Retail Goods"
        }
    ],
    "sg:postcode":"CA3 8QJ",
    "sg:province":"Cumbria",
    "sg:tags":[
        "equipment",
        "camping"
    ],
    "wof:name":"Freetime Climb & Ski",
    "wof:placetype":"venue"
},
  "geometry": {"coordinates":[-2.9370179176,54.896572113],"type":"Point"}
}