{
  "type": "Feature",
  "properties": {
    "iso:country":"GB",
    "sg:address":"Woodford Road, Great Addington",
    "sg:city":"Kettering",
    "sg:classifiers":[
        {
            "category":"Education",
            "subcategory":"School",
            "type":"Public Place"
        }
    ],
    "sg:phone":"+44 1536 330642",
    "sg:postcode":"NN14 4BS",
    "sg:province":"Northamptonshire",
    "sg:tags":[
        "local",
        "authority"
    ],
    "wof:name":"Great Addington C of E Primary School",
    "wof:placetype":"venue"
},
  "geometry": {"coordinates":[-0.593128,52.365059],"type":"Point"}
}