{
  "type": "Feature",
  "properties": {
    "addr:full":"Unit 362a, Walton Summit Centre, Bamber Bridge Preston Lancashire PR5 8AS",
    "addr:housenumber":"362a",
    "addr:postcode":"pr5 8as",
    "addr:street":"Walton Summit Centre",
    "iso:country":"GB",
    "sg:address":"Unit 362a, Walton Summit Centre, Bamber Bridge",
    "sg:city":"Preston",
    "sg:classifiers":[
        {
            "category":"Manufacturing",
            "subcategory":"Tools & Machinery",
            "type":"Manufacturing & Wholesale Goods"
        }
    ],
    "sg:phone":"+44 870 062 1030",
    "sg:postcode":"PR5 8AS",
    "sg:province":"Lancashire",
    "sg:tags":[
        "stone",
        "cutting"
    ],
    "wof:name":"Cutting Edge Services Ltd.",
    "wof:placetype":"venue"
},
  "geometry": {"coordinates":[-2.6527190208,53.7184486389],"type":"Point"}
}