{
  "type": "Feature",
  "properties": {
    "addr:full":"The Guildhall, Fore Street, East Looe Looe Cornwall PL13 1AA",
    "addr:postcode":"pl13 1aa",
    "addr:street":"Fore Street",
    "iso:country":"GB",
    "sg:address":"The Guildhall, Fore Street, East Looe",
    "sg:city":"Looe",
    "sg:classifiers":[
        {
            "category":"Landmark",
            "subcategory":"Tourist Information",
            "type":"Public Place"
        }
    ],
    "sg:phone":"+44 1503 262072",
    "sg:postcode":"PL13 1AA",
    "sg:province":"Cornwall",
    "wof:name":"Tourist Information Centre",
    "wof:placetype":"venue"
},
  "geometry": {"coordinates":[-4.4551510811,50.3570518494],"type":"Point"}
}