{
  "type": "Feature",
  "properties": {
    "addr:full":"Unit 26 Hewitt Business Park, Winstanley Road, Billinge Wigan Lancashire WN5 7XB",
    "addr:housenumber":"unit 26",
    "addr:postcode":"wn5 7xb",
    "addr:street":"Hewitt Business Park Winstanley Road",
    "iso:country":"GB",
    "sg:address":"Unit 26 Hewitt Business Park, Winstanley Road, Billinge",
    "sg:city":"Wigan",
    "sg:classifiers":[
        {
            "category":"Professional",
            "subcategory":"Management & Consulting",
            "type":"Services"
        }
    ],
    "sg:phone":"+44 1942 208101",
    "sg:postcode":"WN5 7XB",
    "sg:province":"Lancashire",
    "sg:tags":[
        "fire",
        "consultant",
        "protection"
    ],
    "wof:name":"Guardian Technical Maintenance Ltd.",
    "wof:placetype":"venue"
},
  "geometry": {"coordinates":[-2.7059409618,53.529083252],"type":"Point"}
}