{
  "type": "Feature",
  "properties": {
    "addr:full":"38a Aviary Road Leeds West Yorkshire LS12 2NS",
    "addr:housenumber":"38a",
    "addr:postcode":"ls12 2ns",
    "addr:street":"Aviary Road",
    "iso:country":"GB",
    "sg:address":"38a Aviary Road",
    "sg:city":"Leeds",
    "sg:classifiers":[
        {
            "category":"Retail",
            "subcategory":"Auto Repair",
            "type":"Services"
        }
    ],
    "sg:postcode":"LS12 2NS",
    "sg:province":"West Yorkshire",
    "sg:tags":[
        "modification",
        "garage"
    ],
    "wof:name":"Ark-Well Motors",
    "wof:placetype":"venue"
},
  "geometry": {"coordinates":[-1.587454,53.801701],"type":"Point"}
}