{
  "type": "Feature",
  "properties": {
    "addr:full":"387 Green Street London Greater London E13 9AU",
    "addr:housenumber":"387",
    "addr:postcode":"e13 9au",
    "addr:street":"Green Street",
    "iso:country":"GB",
    "sg:address":"387 Green Street",
    "sg:city":"London",
    "sg:classifiers":[
        {
            "category":"Shopping",
            "subcategory":"Beauty & Cosmetics",
            "type":"Retail Goods"
        }
    ],
    "sg:phone":"+44 20 8471 1699",
    "sg:postcode":"E13 9AU",
    "sg:province":"Greater London",
    "sg:tags":[
        "product"
    ],
    "wof:name":"Queens Cosmetics",
    "wof:placetype":"venue"
},
  "geometry": {"coordinates":[0.03588,51.534744],"type":"Point"}
}