{
  "type": "Feature",
  "properties": {
    "addr:full":"15 Didsbury Bank Stockport Cheshire SK4 2DB",
    "addr:housenumber":"15",
    "addr:postcode":"sk4 2db",
    "addr:street":"Stockport",
    "iso:country":"GB",
    "sg:address":"15 Didsbury Bank",
    "sg:city":"Stockport",
    "sg:classifiers":[
        {
            "category":"Food & Beverages",
            "subcategory":"Liquor & Beverages",
            "type":"Retail Goods"
        }
    ],
    "sg:phone":"+44 161 443 2821",
    "sg:postcode":"SK4 2DB",
    "sg:province":"Cheshire",
    "sg:tags":[
        "beer",
        "spirit",
        "wines"
    ],
    "wof:name":"Victoria Wine",
    "wof:placetype":"venue"
},
  "geometry": {"coordinates":[-2.18151,53.410534],"type":"Point"}
}