{
  "type": "Feature",
  "properties": {
    "iso:country":"GB",
    "sg:address":"Unit 6 Leech Lane",
    "sg:city":"Mexborough",
    "sg:classifiers":[
        {
            "category":"Home & Garden",
            "subcategory":"Furniture",
            "type":"Retail Goods"
        }
    ],
    "sg:phone":"+44 1709 590446",
    "sg:postcode":"S64 0DQ",
    "sg:province":"South Yorkshire",
    "wof:name":"White Rose Headboards Ltd.",
    "wof:placetype":"venue"
},
  "geometry": {"coordinates":[-1.299808979,53.4953536987],"type":"Point"}
}