{
  "type": "Feature",
  "properties": {
    "iso:country":"GB",
    "sg:address":"47 Fore St",
    "sg:city":"Ivybridge",
    "sg:classifiers":[
        {
            "category":"Banks & Credit Unions",
            "subcategory":"Financial Services",
            "type":"Services"
        }
    ],
    "sg:phone":"+44 1752 893045",
    "sg:postcode":"PL21 9AE",
    "sg:province":"Devon",
    "sg:tags":[
        "consultant"
    ],
    "wof:name":"Brent Reversions Ltd",
    "wof:placetype":"venue"
},
  "geometry": {"coordinates":[-3.9219839573,50.3891105652],"type":"Point"}
}