{
  "type": "Feature",
  "properties": {
    "addr:full":"Lone Vine, Murray Street Tain Highland IV19 1HS",
    "addr:postcode":"iv19 1hs",
    "addr:street":"Lone Vine Murray Street",
    "iso:country":"GB",
    "sg:address":"Lone Vine, Murray Street",
    "sg:city":"Tain",
    "sg:classifiers":[
        {
            "category":"Retail",
            "subcategory":"Driving School",
            "type":"Services"
        }
    ],
    "sg:phone":"+44 1862 894218",
    "sg:postcode":"IV19 1HS",
    "sg:province":"Highland",
    "wof:name":"Parrs Way School of Motoring",
    "wof:placetype":"venue"
},
  "geometry": {"coordinates":[-4.0532450676,57.8113594055],"type":"Point"}
}