{
  "type": "Feature",
  "properties": {
    "addr:full":"42b Chester St Chesterfield Derbyshire S40 1DW",
    "addr:housenumber":"42b",
    "addr:postcode":"s40 1dw",
    "addr:street":"Chester St",
    "iso:country":"GB",
    "sg:address":"42b Chester St",
    "sg:city":"Chesterfield",
    "sg:classifiers":[
        {
            "category":"Manufacturing",
            "subcategory":"Textiles",
            "type":"Manufacturing & Wholesale Goods"
        }
    ],
    "sg:phone":"+44 1246 221174",
    "sg:postcode":"S40 1DW",
    "sg:province":"Derbyshire",
    "sg:tags":[
        "made-up"
    ],
    "wof:name":"Howard & Co",
    "wof:placetype":"venue"
},
  "geometry": {"coordinates":[-1.441017,53.236259],"type":"Point"}
}