{
  "type": "Feature",
  "properties": {
    "addr:full":"Unit 2 Culland St Works, Off Culland Street Crewe Cheshire CW2 6DQ",
    "addr:housenumber":"unit 2",
    "addr:postcode":"cw2 6dq",
    "addr:street":"Culland St;Off Culland Street",
    "iso:country":"GB",
    "sg:address":"Unit 2 Culland St Works, Off Culland Street",
    "sg:city":"Crewe",
    "sg:classifiers":[
        {
            "category":"Wholesale",
            "subcategory":"Sporting Goods",
            "type":"Manufacturing & Wholesale Goods"
        }
    ],
    "sg:phone":"+44 1270 580006",
    "sg:postcode":"CW2 6DQ",
    "sg:province":"Cheshire",
    "sg:tags":[
        "mnfr",
        "sport",
        "equipment"
    ],
    "wof:name":"Christopher Manifold",
    "wof:placetype":"venue"
},
  "geometry": {"coordinates":[-2.4434890747,53.087348938],"type":"Point"}
}