{
  "type": "Feature",
  "properties": {
    "addr:full":"Flat 2, 6 Kew Gardens Rd, Kew Richmond Greater London TW9 3HL",
    "addr:housenumber":"6",
    "addr:postcode":"tw9 3hl",
    "addr:street":"Kew Gardens Rd",
    "iso:country":"GB",
    "sg:address":"Flat 2, 6 Kew Gardens Rd, Kew",
    "sg:city":"Richmond",
    "sg:classifiers":[
        {
            "category":"Social Services",
            "subcategory":"Job Training",
            "type":"Services"
        },
        {
            "category":"Education",
            "subcategory":"School",
            "type":"Public Place"
        }
    ],
    "sg:phone":"+44 20 8940 6422",
    "sg:postcode":"TW9 3HL",
    "sg:province":"Greater London",
    "sg:tags":[
        "translator",
        "interpreter",
        "local",
        "authority"
    ],
    "wof:name":"Harrison-French,Margaret Jane,",
    "wof:placetype":"venue"
},
  "geometry": {"coordinates":[-0.2878200114,51.4799995422],"type":"Point"}
}