{
  "type": "Feature",
  "properties": {
    "iso:country":"GB",
    "sg:address":"2-4 Glengate",
    "sg:city":"Kirriemuir",
    "sg:classifiers":[
        {
            "category":"Shopping",
            "subcategory":"Florist",
            "type":"Retail Goods"
        }
    ],
    "sg:postcode":"DD8 4HD",
    "sg:province":"Angus",
    "wof:name":"Oakfield",
    "wof:placetype":"venue"
},
  "geometry": {"coordinates":[-3.004989,56.673412],"type":"Point"}
}