{
  "type": "Feature",
  "properties": {
    "addr:full":"The Oaks,rag Hill, Aldermaston Reading Berkshire RG7 4NT",
    "addr:postcode":"rg7 4nt",
    "iso:country":"GB",
    "sg:address":"The Oaks,rag Hill, Aldermaston",
    "sg:city":"Reading",
    "sg:classifiers":[
        {
            "category":"Building & Trades",
            "subcategory":"Construction",
            "type":"Services"
        }
    ],
    "sg:postcode":"RG7 4NT",
    "sg:province":"Berkshire",
    "sg:tags":[
        "joiner",
        "carpenter"
    ],
    "wof:name":"Abinger,Colin F,",
    "wof:placetype":"venue"
},
  "geometry": {"coordinates":[-1.152579,51.382935],"type":"Point"}
}