{
  "type": "Feature",
  "properties": {
    "iso:country":"GB",
    "sg:address":"48 Stourcliffe Avenue",
    "sg:city":"Bournemouth",
    "sg:classifiers":[
        {
            "category":"Social Services",
            "subcategory":"Retirement Home",
            "type":"Services"
        }
    ],
    "sg:phone":"+44 1202 432597",
    "sg:postcode":"BH6 3PX",
    "sg:province":"Dorset",
    "sg:tags":[
        "rest"
    ],
    "wof:name":"Southlea Rest Home",
    "wof:placetype":"venue"
},
  "geometry": {"coordinates":[-1.8114579916,50.7227478027],"type":"Point"}
}