{
  "type": "Feature",
  "properties": {
    "iso:country":"GB",
    "sg:address":"48-49 Ettrick Gro",
    "sg:city":"Sunderland",
    "sg:classifiers":[
        {
            "category":"Farming",
            "subcategory":"Nursery",
            "type":"Manufacturing & Wholesale Goods"
        }
    ],
    "sg:phone":"+44 191 528 5951",
    "sg:postcode":"SR3 4AW",
    "sg:province":"Tyne and Wear",
    "sg:tags":[
        "creche"
    ],
    "wof:name":"Little Learners Day Nursery",
    "wof:placetype":"venue"
},
  "geometry": {"coordinates":[-1.413606,54.891739],"type":"Point"}
}