{
  "type": "Feature",
  "properties": {
    "iso:country":"GB",
    "sg:address":"104 Shrub End Road",
    "sg:city":"Colchester",
    "sg:classifiers":[
        {
            "category":"Farming",
            "subcategory":"Nursery",
            "type":"Manufacturing & Wholesale Goods"
        },
        {
            "category":"Education",
            "subcategory":"Preschool",
            "type":"Public Place"
        }
    ],
    "sg:phone":"+44 1206 764801",
    "sg:postcode":"CO3 4RX",
    "sg:province":"Essex",
    "sg:tags":[
        "school",
        "creche"
    ],
    "wof:name":"Holly Corner Montessori Kindergarten",
    "wof:placetype":"venue"
},
  "geometry": {"coordinates":[0.871487,51.876923],"type":"Point"}
}