{
  "type": "Feature",
  "properties": {
    "addr:full":"59 Barnes High Street London Greater London SW13 9LF",
    "addr:housenumber":"59",
    "addr:postcode":"sw13 9lf",
    "addr:street":"Barnes High Street",
    "iso:country":"GB",
    "sg:address":"59 Barnes High Street",
    "sg:city":"London",
    "sg:classifiers":[
        {
            "category":"Retail",
            "subcategory":"Laundry & Dry Cleaning",
            "type":"Services"
        }
    ],
    "sg:postcode":"SW13 9LF",
    "sg:province":"Greater London",
    "sg:tags":[
        "alteration"
    ],
    "wof:name":"Classy Cleaners",
    "wof:placetype":"venue"
},
  "geometry": {"coordinates":[-0.248865,51.473801],"type":"Point"}
}