{
  "type": "Feature",
  "properties": {
    "iso:country":"GB",
    "sg:address":"Farm View, 180 Everton Road, Hordle",
    "sg:city":"Lymington",
    "sg:classifiers":[
        {
            "category":"Professional",
            "subcategory":"Engineering",
            "type":"Services"
        }
    ],
    "sg:postcode":"SO41 0HB",
    "sg:province":"Hampshire",
    "sg:tags":[
        "contractor",
        "electrical",
        "engineer"
    ],
    "wof:name":"Robert J Stephens",
    "wof:placetype":"venue"
},
  "geometry": {"coordinates":[-1.621339,50.760376],"type":"Point"}
}