{
  "type": "Feature",
  "properties": {
    "addr:full":"1 Albyn Terr Aberdeen Aberdeen City AB10 1YP",
    "addr:housenumber":"1",
    "addr:postcode":"ab10 1yp",
    "addr:street":"Albyn Terr",
    "iso:country":"GB",
    "sg:address":"1 Albyn Terr",
    "sg:city":"Aberdeen",
    "sg:classifiers":[
        {
            "category":"Professional",
            "subcategory":"Art Services",
            "type":"Services"
        }
    ],
    "sg:phone":"+44 1224 627396",
    "sg:postcode":"AB10 1YP",
    "sg:province":"Aberdeen City",
    "sg:tags":[
        "consultant",
        "design"
    ],
    "wof:name":"Lighthouse",
    "wof:placetype":"venue"
},
  "geometry": {"coordinates":[-2.121563,57.143082],"type":"Point"}
}