{
  "type": "Feature",
  "properties": {
    "addr:full":"55 Birkbeck Road Sidcup Kent DA14 4DB",
    "addr:housenumber":"55",
    "addr:postcode":"da14 4db",
    "addr:street":"Birkbeck Road",
    "iso:country":"GB",
    "sg:address":"55 Birkbeck Road",
    "sg:city":"Sidcup",
    "sg:classifiers":[
        {
            "category":"Personal",
            "subcategory":"Beauty Salon",
            "type":"Services"
        }
    ],
    "sg:postcode":"DA14 4DB",
    "sg:province":"Kent",
    "sg:tags":[
        "unisex",
        "hairdresser"
    ],
    "wof:name":"Hair by Figaro",
    "wof:placetype":"venue"
},
  "geometry": {"coordinates":[0.1052939966,51.4292488098],"type":"Point"}
}