{
  "type": "Feature",
  "properties": {
    "iso:country":"GB",
    "sg:address":"8 Lowndes Avenue",
    "sg:city":"Chesham",
    "sg:classifiers":[
        {
            "category":"Professional",
            "type":"Services"
        }
    ],
    "sg:phone":"+44 1494 783225",
    "sg:postcode":"HP5 2HH",
    "sg:province":"Buckinghamshire",
    "sg:tags":[
        "caterer"
    ],
    "wof:name":"Alpine Caterers",
    "wof:placetype":"venue"
},
  "geometry": {"coordinates":[-0.6138150096,51.7108726501],"type":"Point"}
}