{
  "type": "Feature",
  "properties": {
    "iso:country":"GB",
    "sg:address":"Orchards House, Holtye Road",
    "sg:city":"East Grinstead",
    "sg:classifiers":[
        {
            "category":"Real Estate",
            "subcategory":"Architect",
            "type":"Services"
        }
    ],
    "sg:postcode":"RH19 3PP",
    "sg:province":"East Sussex",
    "wof:name":"Parkers Ltd",
    "wof:placetype":"venue"
},
  "geometry": {"coordinates":[-0.002649,51.131577],"type":"Point"}
}