{
  "type": "Feature",
  "properties": {
    "iso:country":"GB",
    "sg:address":"Unit 5, Tower Industrial Estate, 67 Albert Road",
    "sg:city":"London",
    "sg:classifiers":[
        {
            "category":"Recreation",
            "subcategory":"Fishing",
            "type":"Entertainment"
        }
    ],
    "sg:phone":"+44 20 8656 6716",
    "sg:postcode":"SE25 4JD",
    "sg:province":"Greater London",
    "sg:tags":[
        "equipment",
        "angling"
    ],
    "wof:name":"Anchor Tackle Ltd.",
    "wof:placetype":"venue"
},
  "geometry": {"coordinates":[-0.069765,51.399063],"type":"Point"}
}