{
  "type": "Feature",
  "properties": {
    "addr:full":"High Street, Hartley Whitney Hook Berkshire RG27 8NY",
    "addr:postcode":"rg27 8ny",
    "addr:street":"High Street",
    "iso:country":"GB",
    "sg:address":"High Street, Hartley Whitney",
    "sg:city":"Hook",
    "sg:classifiers":[
        {
            "category":"Shopping",
            "subcategory":"Antiques",
            "type":"Retail Goods"
        }
    ],
    "sg:phone":"+44 1252 843222",
    "sg:postcode":"RG27 8NY",
    "sg:province":"Berkshire",
    "wof:name":"Cedar Antiques Centre Ltd.",
    "wof:placetype":"venue"
},
  "geometry": {"coordinates":[-0.898549,51.307217],"type":"Point"}
}