{
  "type": "Feature",
  "properties": {
    "addr:full":"Belgrave Road Hounslow Greater London TW4 7AG",
    "addr:postcode":"tw4 7ag",
    "addr:street":"Belgrave Road",
    "iso:country":"GB",
    "sg:address":"Belgrave Road",
    "sg:city":"Hounslow",
    "sg:classifiers":[
        {
            "category":"Education",
            "subcategory":"School",
            "type":"Public Place"
        }
    ],
    "sg:phone":"+44 20 8572 9658",
    "sg:postcode":"TW4 7AG",
    "sg:province":"Greater London",
    "sg:tags":[
        "local",
        "authority"
    ],
    "wof:name":"St Michael & St Martins R C Primary School",
    "wof:placetype":"venue"
},
  "geometry": {"coordinates":[-0.3806380033,51.4686126709],"type":"Point"}
}