{
  "type": "Feature",
  "properties": {
    "iso:country":"GB",
    "sg:address":"Turkey Road",
    "sg:city":"Bexhill-on-sea",
    "sg:classifiers":[
        {
            "category":"Bars & Pubs",
            "type":"Food & Drink"
        }
    ],
    "sg:phone":"+44 1424 214625",
    "sg:postcode":"TN39 5HH",
    "sg:province":"East Sussex",
    "sg:tags":[
        "pubs",
        "house",
        "inn",
        "public",
        "activity"
    ],
    "sg:website":"http://www.hungryhorse.co.uk",
    "wof:name":"Rose & Crown",
    "wof:placetype":"venue"
},
  "geometry": {"coordinates":[0.459708,50.857258],"type":"Point"}
}