{
  "type": "Feature",
  "properties": {
    "iso:country":"GB",
    "sg:address":"Wheatley Road, Garsington",
    "sg:city":"Oxford",
    "sg:classifiers":[
        {
            "category":"Education",
            "subcategory":"School",
            "type":"Public Place"
        }
    ],
    "sg:phone":"+44 1865 361263",
    "sg:postcode":"OX44 9EW",
    "sg:province":"Oxfordshire",
    "sg:tags":[
        "local",
        "authority"
    ],
    "wof:name":"Garsington C Of E Primary School",
    "wof:placetype":"venue"
},
  "geometry": {"coordinates":[-1.1602590084,51.7172050476],"type":"Point"}
}