{
  "type": "Feature",
  "properties": {
    "addr:full":"18 Chapel Street Buckfastleigh Devon TQ11 0AQ",
    "addr:housenumber":"18",
    "addr:postcode":"tq11 0aq",
    "addr:street":"Chapel Street",
    "iso:country":"GB",
    "sg:address":"18 Chapel Street",
    "sg:city":"Buckfastleigh",
    "sg:classifiers":[
        {
            "category":"Personal",
            "type":"Services"
        }
    ],
    "sg:phone":"+44 1364 643135",
    "sg:postcode":"TQ11 0AQ",
    "sg:province":"Devon",
    "sg:tags":[
        "wedding"
    ],
    "wof:name":"Cornucopia",
    "wof:placetype":"venue"
},
  "geometry": {"coordinates":[-3.7817599773,50.4814605713],"type":"Point"}
}