{
  "type": "Feature",
  "properties": {
    "iso:country":"GB",
    "sg:address":"107 Harley Street",
    "sg:city":"London",
    "sg:classifiers":[
        {
            "category":"Health Services",
            "subcategory":"Doctor",
            "type":"Services"
        }
    ],
    "sg:phone":"+44 20 7935 9521",
    "sg:postcode":"W1G 6AL",
    "sg:province":"Greater London",
    "sg:tags":[
        "practitioners"
    ],
    "wof:name":"Andrew M Jackson",
    "wof:placetype":"venue"
},
  "geometry": {"coordinates":[-0.148153,51.521206],"type":"Point"}
}