{
  "type": "Feature",
  "properties": {
    "iso:country":"GB",
    "sg:address":"Woodlands Cottage, Summerbridge",
    "sg:city":"Harrogate",
    "sg:classifiers":[
        {
            "category":"Building & Trades",
            "subcategory":"Landscaping Services",
            "type":"Services"
        }
    ],
    "sg:phone":"+44 1423 780765",
    "sg:postcode":"HG3 4BT",
    "sg:province":"North Yorkshire",
    "sg:tags":[
        "designer",
        "architect",
        "landscape"
    ],
    "wof:name":"Ann Stark",
    "wof:placetype":"venue"
},
  "geometry": {"coordinates":[-1.693886,54.057629],"type":"Point"}
}