{
  "type": "Feature",
  "properties": {
    "addr:full":"Unit 4 Lanimer Centre, High St Lanark South Lanarkshire ML11 7EX",
    "addr:housenumber":"unit 4",
    "addr:postcode":"ml11 7ex",
    "addr:street":"High St",
    "iso:country":"GB",
    "sg:address":"Unit 4 Lanimer Centre, High St",
    "sg:city":"Lanark",
    "sg:classifiers":[
        {
            "category":"Food & Beverages",
            "subcategory":"Liquor & Beverages",
            "type":"Retail Goods"
        }
    ],
    "sg:phone":"+44 1555 664651",
    "sg:postcode":"ML11 7EX",
    "sg:province":"South Lanarkshire",
    "sg:tags":[
        "beer",
        "spirit",
        "wines"
    ],
    "wof:name":"Thresher",
    "wof:placetype":"venue"
},
  "geometry": {"coordinates":[-3.8048288822,55.6955566406],"type":"Point"}
}