{
  "type": "Feature",
  "properties": {
    "iso:country":"GB",
    "sg:address":"100-102 Rose Street",
    "sg:city":"Edinburgh",
    "sg:classifiers":[
        {
            "category":"Bars & Pubs",
            "type":"Food & Drink"
        },
        {
            "category":"Community Center",
            "subcategory":"Social",
            "type":"Public Place"
        }
    ],
    "sg:phone":"+44 131 225 1809",
    "sg:postcode":"EH2 2NN",
    "sg:province":"City of Edinburgh",
    "sg:tags":[
        "pubs",
        "house",
        "inn",
        "activity"
    ],
    "wof:name":"ALLOA PUBS & RESTAURANTS LTD",
    "wof:placetype":"venue"
},
  "geometry": {"coordinates":[-3.1997470856,55.9522399902],"type":"Point"}
}