{
  "type": "Feature",
  "properties": {
    "iso:country":"GB",
    "sg:address":"27 Cowick Street",
    "sg:city":"Exeter",
    "sg:classifiers":[
        {
            "category":"Manufacturing",
            "subcategory":"Petroleum Products",
            "type":"Manufacturing & Wholesale Goods"
        }
    ],
    "sg:phone":"+44 1392 216050",
    "sg:postcode":"EX4 1AL",
    "sg:province":"Devon",
    "sg:tags":[
        "double",
        "glazing"
    ],
    "wof:name":"A G S Home Improvements",
    "wof:placetype":"venue"
},
  "geometry": {"coordinates":[-3.540114,50.716808],"type":"Point"}
}