{
  "type": "Feature",
  "properties": {
    "iso:country":"GB",
    "sg:address":"12-14 Market Place",
    "sg:city":"Clitheroe",
    "sg:classifiers":[
        {
            "category":"Landmark",
            "subcategory":"Tourist Information",
            "type":"Public Place"
        },
        {
            "category":"Professional",
            "subcategory":"Computer Services",
            "type":"Services"
        }
    ],
    "sg:phone":"+44 1200 442226",
    "sg:postcode":"BB7 2DA",
    "sg:province":"Lancashire",
    "wof:name":"County Information Centre",
    "wof:placetype":"venue"
},
  "geometry": {"coordinates":[-2.391029,53.872677],"type":"Point"}
}