{
  "type": "Feature",
  "properties": {
    "iso:country":"GB",
    "sg:address":"7 Wenlock Road",
    "sg:city":"Shrewsbury",
    "sg:classifiers":[
        {
            "category":"Bars & Pubs",
            "type":"Food & Drink"
        }
    ],
    "sg:phone":"+44 1743 356339",
    "sg:postcode":"SY2 6JJ",
    "sg:province":"Shropshire",
    "sg:tags":[
        "pubs",
        "inn"
    ],
    "wof:name":"Punch Retail (Holdings) Ltd.",
    "wof:placetype":"venue"
},
  "geometry": {"coordinates":[-2.7315618992,52.7032089233],"type":"Point"}
}