{
  "type": "Feature",
  "properties": {
    "addr:full":"Clipsley Lane, Haydock St Helens Lancashire WA11 0JG",
    "addr:postcode":"wa11 0jg",
    "addr:street":"Clipsley Lane Haydock",
    "iso:country":"GB",
    "sg:address":"Clipsley Lane, Haydock",
    "sg:city":"St Helens",
    "sg:classifiers":[
        {
            "category":"Bars & Pubs",
            "type":"Food & Drink"
        }
    ],
    "sg:phone":"+44 1744 606603",
    "sg:postcode":"WA11 0JG",
    "sg:province":"Lancashire",
    "sg:tags":[
        "pubs",
        "inn"
    ],
    "wof:name":"Greenalls Management Ltd.",
    "wof:placetype":"venue"
},
  "geometry": {"coordinates":[-2.686689,53.467896],"type":"Point"}
}