{
  "type": "Feature",
  "properties": {
    "addr:full":"66 Canford Bottom Wimborne Dorset BH21 2HF",
    "addr:housenumber":"66",
    "addr:postcode":"bh21 2hf",
    "addr:street":"Canford Bottom",
    "iso:country":"GB",
    "sg:address":"66 Canford Bottom",
    "sg:city":"Wimborne",
    "sg:classifiers":[
        {
            "category":"Building & Trades",
            "subcategory":"Plumbing",
            "type":"Services"
        }
    ],
    "sg:phone":"+44 1202 883667",
    "sg:postcode":"BH21 2HF",
    "sg:province":"Dorset",
    "sg:tags":[
        "plumber",
        "heating"
    ],
    "wof:name":"A B C Plumbing Services",
    "wof:placetype":"venue"
},
  "geometry": {"coordinates":[-1.9429869652,50.8049583435],"type":"Point"}
}