{
  "type": "Feature",
  "properties": {
    "addr:full":"10 Finch Road Birmingham West Midlands B19 1HS",
    "addr:housenumber":"10",
    "addr:postcode":"b19 1hs",
    "addr:street":"Finch Road",
    "iso:country":"GB",
    "sg:address":"10 Finch Road",
    "sg:city":"Birmingham",
    "sg:classifiers":[
        {
            "category":"Bars & Pubs",
            "type":"Food & Drink"
        }
    ],
    "sg:phone":"+44 121 554 4954",
    "sg:postcode":"B19 1HS",
    "sg:province":"West Midlands",
    "sg:tags":[
        "pubs",
        "inn"
    ],
    "wof:name":"Pubmaster Ltd.",
    "wof:placetype":"venue"
},
  "geometry": {"coordinates":[-1.910174,52.503132],"type":"Point"}
}