{
  "type": "Feature",
  "properties": {
    "addr:full":"1 Earlsdon St, Earlsdon Coventry West Midlands CV5 6EP",
    "addr:housenumber":"1",
    "addr:postcode":"cv5 6ep",
    "addr:street":"Earlsdon St",
    "iso:country":"GB",
    "sg:address":"1 Earlsdon St, Earlsdon",
    "sg:city":"Coventry",
    "sg:classifiers":[
        {
            "category":"Restaurant",
            "type":"Food & Drink"
        }
    ],
    "sg:postcode":"CV5 6EP",
    "sg:province":"West Midlands",
    "wof:name":"Brophy,H,",
    "wof:placetype":"venue"
},
  "geometry": {"coordinates":[-1.5306090117,52.3998718262],"type":"Point"}
}