{
  "type": "Feature",
  "properties": {
    "iso:country":"GB",
    "sg:address":"12 Pine View Villas, Esh Winning",
    "sg:city":"Durham",
    "sg:classifiers":[
        {
            "category":"Building & Trades",
            "subcategory":"Construction",
            "type":"Services"
        }
    ],
    "sg:phone":"+44 1388 766824",
    "sg:postcode":"DH7 9PW",
    "sg:province":"Durham",
    "sg:tags":[
        "contractor",
        "paving",
        "driveway"
    ],
    "wof:name":"Weir Plant Hire & Contractors",
    "wof:placetype":"venue"
},
  "geometry": {"coordinates":[-1.696453,54.770882],"type":"Point"}
}