{
  "type": "Feature",
  "properties": {
    "addr:full":"Little Hulton Community School, Longshaw Dr Manchester Greater Manchester M28 0AZ",
    "addr:postcode":"m28 0az",
    "addr:street":"Longshaw",
    "iso:country":"GB",
    "sg:address":"Little Hulton Community School, Longshaw Dr",
    "sg:city":"Manchester",
    "sg:classifiers":[
        {
            "category":"Education",
            "subcategory":"University",
            "type":"Public Place"
        }
    ],
    "sg:phone":"+44 161 790 0272",
    "sg:postcode":"M28 0AZ",
    "sg:province":"Greater Manchester",
    "sg:tags":[
        "adult"
    ],
    "wof:name":"Salford College Little Hulton LAC",
    "wof:placetype":"venue"
},
  "geometry": {"coordinates":[-2.4217898846,53.5284614563],"type":"Point"}
}