{
  "type": "Feature",
  "properties": {
    "addr:full":"Kingsmead, Upton Road Birkenhead Merseyside CH43 7QQ",
    "addr:postcode":"ch43 7qq",
    "addr:street":"Upton Road",
    "iso:country":"GB",
    "sg:address":"Kingsmead, Upton Road",
    "sg:city":"Birkenhead",
    "sg:classifiers":[
        {
            "category":"Professional",
            "subcategory":"Accounting & Tax Preparation",
            "type":"Services"
        }
    ],
    "sg:phone":"+44 151 652 4724",
    "sg:postcode":"CH43 7QQ",
    "sg:province":"Merseyside",
    "sg:tags":[
        "accountant"
    ],
    "wof:name":"Cooks Chartered Accountants",
    "wof:placetype":"venue"
},
  "geometry": {"coordinates":[-3.072920084,53.3926582336],"type":"Point"}
}