{
  "type": "Feature",
  "properties": {
    "addr:full":"Cross Street Dudley West Midlands DY1 1RN",
    "addr:postcode":"dy1 1rn",
    "addr:street":"Cross Street",
    "iso:country":"GB",
    "sg:address":"Cross Street",
    "sg:city":"Dudley",
    "sg:classifiers":[
        {
            "category":"Health Services",
            "subcategory":"Doctor",
            "type":"Services"
        },
        {
            "category":"Health Services",
            "subcategory":"Clinic",
            "type":"Services"
        }
    ],
    "sg:phone":"+44 1384 459090",
    "sg:postcode":"DY1 1RN",
    "sg:province":"West Midlands",
    "sg:tags":[
        "nh",
        "practitioners"
    ],
    "wof:name":"Dudley Health Authority",
    "wof:placetype":"venue"
},
  "geometry": {"coordinates":[-2.0891010761,52.509979248],"type":"Point"}
}