{
  "type": "Feature",
  "properties": {
    "addr:full":"Spencers Crossing Mill Lane, Great Alne Alcester Warwickshire B49 6JA",
    "addr:postcode":"b49 6ja",
    "addr:street":"Crossing Mill Lane",
    "iso:country":"GB",
    "sg:address":"Spencers Crossing Mill Lane, Great Alne",
    "sg:city":"Alcester",
    "sg:classifiers":[
        {
            "category":"Professional",
            "subcategory":"Engineering",
            "type":"Services"
        }
    ],
    "sg:postcode":"B49 6JA",
    "sg:province":"Warwickshire",
    "sg:tags":[
        "consultant",
        "structural"
    ],
    "wof:name":"Robert Smith Associates Ltd.",
    "wof:placetype":"venue"
},
  "geometry": {"coordinates":[-1.8609919548,52.2217979431],"type":"Point"}
}