{
  "type": "Feature",
  "properties": {
    "addr:full":"222 Clock Face Road, Clock Face St Helens Cheshire WA9 4LU",
    "addr:housenumber":"222",
    "addr:postcode":"face;wa9 4lu",
    "addr:street":"Clock Face Road Clock",
    "iso:country":"GB",
    "sg:address":"222 Clock Face Road, Clock Face",
    "sg:city":"St Helens",
    "sg:classifiers":[
        {
            "category":"Personal",
            "subcategory":"Beauty Salon",
            "type":"Services"
        }
    ],
    "sg:phone":"+44 1744 811088",
    "sg:postcode":"WA9 4LU",
    "sg:province":"Cheshire",
    "sg:tags":[
        "unisex",
        "hairdresser"
    ],
    "wof:name":"K M G Hair Studio",
    "wof:placetype":"venue"
},
  "geometry": {"coordinates":[-2.7133910656,53.419834137],"type":"Point"}
}