{
  "type": "Feature",
  "properties": {
    "addr:full":"12 Madeira Lane Greenock Inverclyde PA16 7UL",
    "addr:housenumber":"12",
    "addr:postcode":"pa16 7ul",
    "addr:street":"Madeira Lane Greenock",
    "iso:country":"GB",
    "sg:address":"12 Madeira Lane",
    "sg:city":"Greenock",
    "sg:classifiers":[
        {
            "category":"Retail",
            "subcategory":"Driving School",
            "type":"Services"
        }
    ],
    "sg:phone":"+44 1475 726376",
    "sg:postcode":"PA16 7UL",
    "sg:province":"Inverclyde",
    "wof:name":"Scotia School Of Motoring",
    "wof:placetype":"venue"
},
  "geometry": {"coordinates":[-4.779794,55.95892],"type":"Point"}
}