{
  "type": "Feature",
  "properties": {
    "iso:country":"GB",
    "sg:address":"383 Edgware Road",
    "sg:city":"London",
    "sg:classifiers":[
        {
            "category":"Cafe",
            "type":"Food & Drink"
        }
    ],
    "sg:phone":"+44 20 8200 8378",
    "sg:postcode":"NW9 6NJ",
    "sg:province":"Greater London",
    "sg:tags":[
        "tea",
        "room"
    ],
    "wof:name":"Cafe Kismet",
    "wof:placetype":"venue"
},
  "geometry": {"coordinates":[-0.256124,51.591095],"type":"Point"}
}