{
  "type": "Feature",
  "properties": {
    "iso:country":"GB",
    "sg:address":"190 Langwith Road, Langwith Junction",
    "sg:city":"Mansfield",
    "sg:classifiers":[
        {
            "category":"Farming",
            "subcategory":"Fish & Marine Products",
            "type":"Manufacturing & Wholesale Goods"
        }
    ],
    "sg:postcode":"NG20 9RN",
    "sg:province":"Derbyshire",
    "sg:tags":[
        "fishmonger"
    ],
    "wof:name":"R J Paling",
    "wof:placetype":"venue"
},
  "geometry": {"coordinates":[-1.212543,53.21143],"type":"Point"}
}