{
  "type": "Feature",
  "properties": {
    "addr:full":"122 Middlesex St Whitechapel Greater London E1 7HY",
    "addr:housenumber":"122",
    "addr:postcode":"e1 7hy",
    "addr:street":"Middlesex St",
    "iso:country":"GB",
    "sg:address":"122 Middlesex St",
    "sg:city":"Whitechapel",
    "sg:classifiers":[
        {
            "category":"Professional",
            "subcategory":"Advertising",
            "type":"Services"
        }
    ],
    "sg:phone":"+44 20 7375 0495",
    "sg:postcode":"E1 7HY",
    "sg:province":"Greater London",
    "sg:tags":[
        "agency"
    ],
    "wof:name":"Apex Advertising",
    "wof:placetype":"venue"
},
  "geometry": {"coordinates":[-0.079225,51.518284],"type":"Point"}
}