{
  "type": "Feature",
  "properties": {
    "iso:country":"GB",
    "sg:address":"93 Queens Rd, East Sheen",
    "sg:city":"London",
    "sg:classifiers":[
        {
            "category":"Professional",
            "subcategory":"Accounting & Tax Preparation",
            "type":"Services"
        }
    ],
    "sg:postcode":"SW14 8PH",
    "sg:province":"Greater London",
    "sg:tags":[
        "accountant"
    ],
    "wof:name":"Shacklewell Enterprises Ltd",
    "wof:placetype":"venue"
},
  "geometry": {"coordinates":[-0.2591109872,51.4652481079],"type":"Point"}
}