{
  "type": "Feature",
  "properties": {
    "iso:country":"GB",
    "sg:address":"9th Floor, 80 Cannon Street",
    "sg:city":"London",
    "sg:classifiers":[
        {
            "category":"Professional",
            "subcategory":"Computer Services",
            "type":"Services"
        }
    ],
    "sg:postcode":"EC4N 6HL",
    "sg:province":"Greater London",
    "sg:tags":[
        "consultant"
    ],
    "wof:name":"Iconics Ltd.",
    "wof:placetype":"venue"
},
  "geometry": {"coordinates":[-0.0894550011,51.5114021301],"type":"Point"}
}