{
  "type": "Feature",
  "properties": {
    "iso:country":"GB",
    "sg:address":"17 Wyvis Avenue, Bearsden",
    "sg:city":"Glasgow",
    "sg:classifiers":[
        {
            "category":"Utilities",
            "subcategory":"Electric",
            "type":"Services"
        }
    ],
    "sg:postcode":"G61 4RD",
    "sg:province":"East Dunbartonshire",
    "sg:tags":[
        "electricity"
    ],
    "wof:name":"Tom Love & Co. Ltd",
    "wof:placetype":"venue"
},
  "geometry": {"coordinates":[-4.3523402214,55.9311599731],"type":"Point"}
}