{
  "type": "Feature",
  "properties": {
    "addr:full":"154 Western Street Swansea Neath Port Talbot SA1 3JY",
    "addr:housenumber":"154",
    "addr:postcode":"sa1 3jy",
    "addr:street":"Western Street",
    "iso:country":"GB",
    "sg:address":"154 Western Street",
    "sg:city":"Swansea",
    "sg:classifiers":[
        {
            "category":"Shopping",
            "subcategory":"Crafts & Fabrics",
            "type":"Retail Goods"
        }
    ],
    "sg:phone":"+44 1792 655928",
    "sg:postcode":"SA1 3JY",
    "sg:province":"Neath Port Talbot",
    "sg:tags":[
        "machine",
        "sewing",
        "knitting"
    ],
    "wof:name":"Cliffords Port Talbot",
    "wof:placetype":"venue"
},
  "geometry": {"coordinates":[-3.9502789974,51.6177406311],"type":"Point"}
}