{
  "type": "Feature",
  "properties": {
    "addr:full":"171 Well Street London Greater London E9 7LJ",
    "addr:housenumber":"171",
    "addr:postcode":"e9 7lj",
    "addr:street":"Well Street",
    "iso:country":"GB",
    "sg:address":"171 Well Street",
    "sg:city":"London",
    "sg:classifiers":[
        {
            "category":"Bars & Pubs",
            "type":"Food & Drink"
        }
    ],
    "sg:postcode":"E9 7LJ",
    "sg:province":"Greater London",
    "sg:tags":[
        "pubs",
        "inn"
    ],
    "wof:name":"Thirty Nine Steps",
    "wof:placetype":"venue"
},
  "geometry": {"coordinates":[-0.048663,51.54287],"type":"Point"}
}