{
  "type": "Feature",
  "properties": {
    "iso:country":"GB",
    "sg:address":"20 Dobson Terrace",
    "sg:city":"Wingate",
    "sg:classifiers":[
        {
            "category":"Professional",
            "type":"Services"
        },
        {
            "category":"Building & Trades",
            "subcategory":"Cleaning & Sanitation",
            "type":"Services"
        }
    ],
    "sg:phone":"+44 1429 837026",
    "sg:postcode":"TS28 5JA",
    "sg:province":"Durham",
    "sg:tags":[
        "dry",
        "control",
        "damp",
        "rot",
        "preservation"
    ],
    "wof:name":"Fir Tree Damp Proofing",
    "wof:placetype":"venue"
},
  "geometry": {"coordinates":[-1.381566,54.73579],"type":"Point"}
}