{
  "type": "Feature",
  "properties": {
    "addr:full":"Wynne St, Rear Dones Betting Shop, Cleggs La Manchester Greater Manchester M38 9WP",
    "addr:postcode":"m38 9wp",
    "addr:street":"Wynne St;Dones;La",
    "iso:country":"GB",
    "sg:address":"Wynne St, Rear Dones Betting Shop, Cleggs La",
    "sg:city":"Manchester",
    "sg:classifiers":[
        {
            "category":"Professional",
            "subcategory":"Art Services",
            "type":"Services"
        }
    ],
    "sg:phone":"+44 161 799 6900",
    "sg:postcode":"M38 9WP",
    "sg:province":"Greater Manchester",
    "sg:tags":[
        "decorating",
        "painting"
    ],
    "wof:name":"Worsley Decor Centre",
    "wof:placetype":"venue"
},
  "geometry": {"coordinates":[-2.4228889942,53.5313606262],"type":"Point"}
}