{
  "type": "Feature",
  "properties": {
    "addr:full":"5 St Marks Road, Pennington Lymington Hampshire SO41 8HA",
    "addr:housenumber":"5",
    "addr:postcode":"so41 8ha",
    "addr:street":"St Marks Road",
    "iso:country":"GB",
    "sg:address":"5 St Marks Road, Pennington",
    "sg:city":"Lymington",
    "sg:classifiers":[
        {
            "category":"Building & Trades",
            "subcategory":"Construction",
            "type":"Services"
        }
    ],
    "sg:phone":"+44 1590 674193",
    "sg:postcode":"SO41 8HA",
    "sg:province":"Hampshire",
    "sg:tags":[
        "joiner",
        "carpenter"
    ],
    "wof:name":"P S & A Soffe & Sons",
    "wof:placetype":"venue"
},
  "geometry": {"coordinates":[-1.566775,50.757706],"type":"Point"}
}