{
  "type": "Feature",
  "properties": {
    "addr:full":"30 Vyne Cres Milton Keynes Buckinghamshire MK8 9EJ",
    "addr:housenumber":"30",
    "addr:postcode":"mk8 9ej",
    "addr:street":"Vyne Cres",
    "iso:country":"GB",
    "sg:address":"30 Vyne Cres",
    "sg:city":"Milton Keynes",
    "sg:classifiers":[
        {
            "category":"Building & Trades",
            "subcategory":"Construction",
            "type":"Services"
        }
    ],
    "sg:phone":"+44 1908 260628",
    "sg:postcode":"MK8 9EJ",
    "sg:province":"Buckinghamshire",
    "sg:tags":[
        "roofing"
    ],
    "wof:name":"Excelsior Roofing Services",
    "wof:placetype":"venue"
},
  "geometry": {"coordinates":[-0.7930949926,52.0351867676],"type":"Point"}
}