{
  "type": "Feature",
  "properties": {
    "addr:full":"43 Southside Street Plymouth Devon PL1 2LD",
    "addr:housenumber":"43",
    "addr:postcode":"pl1 2ld",
    "addr:street":"Southside Street",
    "iso:country":"GB",
    "sg:address":"43 Southside Street",
    "sg:city":"Plymouth",
    "sg:classifiers":[
        {
            "category":"Shopping",
            "subcategory":"Shoes",
            "type":"Retail Goods"
        }
    ],
    "sg:phone":"+44 1752 256667",
    "sg:postcode":"PL1 2LD",
    "sg:province":"Devon",
    "sg:tags":[
        "shop",
        "retailer",
        "footwear"
    ],
    "wof:name":"Richard Marris Stores",
    "wof:placetype":"venue"
},
  "geometry": {"coordinates":[-4.1357498169,50.3673667908],"type":"Point"}
}