{
  "type": "Feature",
  "properties": {
    "iso:country":"GB",
    "sg:address":"2 Maple Clo, Little Stoke",
    "sg:city":"Bristol",
    "sg:classifiers":[
        {
            "category":"Home & Garden",
            "subcategory":"Home Furnishings",
            "type":"Retail Goods"
        },
        {
            "category":"Building & Trades",
            "subcategory":"Construction",
            "type":"Services"
        }
    ],
    "sg:postcode":"BS34 6HQ",
    "sg:province":"Gloucestershire",
    "sg:tags":[
        "builder",
        "loose",
        "cover"
    ],
    "wof:name":"Shapland,Betsy,",
    "wof:placetype":"venue"
},
  "geometry": {"coordinates":[-2.55779,51.528069],"type":"Point"}
}