{
  "type": "Feature",
  "properties": {
    "iso:country":"GB",
    "sg:address":"Elvington Industrial Estate, Elvington",
    "sg:city":"York",
    "sg:classifiers":[
        {
            "category":"Manufacturing",
            "subcategory":"Metals",
            "type":"Manufacturing & Wholesale Goods"
        }
    ],
    "sg:phone":"+44 1904 608571",
    "sg:postcode":"YO41 4AR",
    "sg:province":"East Riding of Yorkshire",
    "sg:tags":[
        "steel",
        "fabricator",
        "erectors"
    ],
    "wof:name":"M Robinson Steel Fabrication",
    "wof:placetype":"venue"
},
  "geometry": {"coordinates":[-0.954421,53.926426],"type":"Point"}
}