{
  "type": "Feature",
  "properties": {
    "addr:full":"Liverpool Road, Longton Preston Lancashire PR4 5NB",
    "addr:postcode":"pr4 5nb",
    "addr:street":"Liverpool Road",
    "iso:country":"GB",
    "sg:address":"Liverpool Road, Longton",
    "sg:city":"Preston",
    "sg:classifiers":[
        {
            "category":"Food & Beverages",
            "subcategory":"Supermarket",
            "type":"Retail Goods"
        }
    ],
    "sg:phone":"+44 1772 613192",
    "sg:postcode":"PR4 5NB",
    "sg:province":"Lancashire",
    "sg:website":"http://www.booths-supermarkets.co.uk",
    "wof:name":"E H Booth & Co Ltd",
    "wof:placetype":"venue"
},
  "geometry": {"coordinates":[-2.7583310604,53.7358894348],"type":"Point"}
}