{
  "type": "Feature",
  "properties": {
    "addr:full":"The Windmill, Millwrights, Tiptree Colchester Essex CO5 0LG",
    "addr:postcode":"co5 0lg",
    "addr:street":"Tiptree Colchester",
    "iso:country":"GB",
    "sg:address":"The Windmill, Millwrights, Tiptree",
    "sg:city":"Colchester",
    "sg:classifiers":[
        {
            "category":"Building & Trades",
            "subcategory":"Construction",
            "type":"Services"
        }
    ],
    "sg:phone":"+44 1621 819777",
    "sg:postcode":"CO5 0LG",
    "sg:province":"Essex",
    "sg:tags":[
        "builder"
    ],
    "wof:name":"Swan",
    "wof:placetype":"venue"
},
  "geometry": {"coordinates":[0.7453340292,51.8164634705],"type":"Point"}
}