{
  "type": "Feature",
  "properties": {
    "iso:country":"GB",
    "sg:address":"Unit 9, Swallow Mill, Swallow St",
    "sg:city":"Stockport",
    "sg:classifiers":[
        {
            "category":"Manufacturing",
            "subcategory":"Printing",
            "type":"Manufacturing & Wholesale Goods"
        }
    ],
    "sg:phone":"+44 161 355 7678",
    "sg:postcode":"SK1 3HJ",
    "sg:province":"Cheshire",
    "sg:tags":[
        "bookbinder"
    ],
    "wof:name":"Kingsley Bindery",
    "wof:placetype":"venue"
},
  "geometry": {"coordinates":[-2.1528949738,53.4021186829],"type":"Point"}
}