{
  "type": "Feature",
  "properties": {
    "addr:full":"29 Badminton Road, Downend Bristol City of Bristol BS16 6BB",
    "addr:housenumber":"29",
    "addr:postcode":"bs16 6bb",
    "addr:street":"Badminton Road",
    "iso:country":"GB",
    "sg:address":"29 Badminton Road, Downend",
    "sg:city":"Bristol",
    "sg:classifiers":[
        {
            "category":"Professional",
            "subcategory":"Lawyer & Legal Services",
            "type":"Services"
        }
    ],
    "sg:phone":"+44 117 957 4118",
    "sg:postcode":"BS16 6BB",
    "sg:province":"City of Bristol",
    "sg:tags":[
        "solicitor"
    ],
    "wof:name":"Peter Burrows Solicitor",
    "wof:placetype":"venue"
},
  "geometry": {"coordinates":[-2.5033650398,51.4892196655],"type":"Point"}
}