{
  "type": "Feature",
  "properties": {
    "addr:full":"176 Wilmslow Road, Heald Grn Cheadle Cheshire SK8 3BG",
    "addr:housenumber":"176",
    "addr:postcode":"sk8 3bg",
    "addr:street":"Wilmslow Road",
    "iso:country":"GB",
    "sg:address":"176 Wilmslow Road, Heald Grn",
    "sg:city":"Cheadle",
    "sg:classifiers":[
        {
            "category":"Health Services",
            "subcategory":"Dentist",
            "type":"Services"
        }
    ],
    "sg:phone":"+44 161 437 1594",
    "sg:postcode":"SK8 3BG",
    "sg:province":"Cheshire",
    "wof:name":"Long Lane Dental Practice",
    "wof:placetype":"venue"
},
  "geometry": {"coordinates":[-2.216958046,53.3705635071],"type":"Point"}
}