{
  "type": "Feature",
  "properties": {
    "addr:full":"Bendrigg Lodge, Old Hutton Kendal Cumbria LA8 0NR",
    "addr:postcode":"la8 0nr",
    "addr:street":"Old Hutton",
    "iso:country":"GB",
    "sg:address":"Bendrigg Lodge, Old Hutton",
    "sg:city":"Kendal",
    "sg:classifiers":[
        {
            "category":"Organizations",
            "subcategory":"Non-profit Organization",
            "type":"Services"
        }
    ],
    "sg:phone":"+44 1539 723766",
    "sg:postcode":"LA8 0NR",
    "sg:province":"Cumbria",
    "sg:tags":[
        "charitable",
        "organisation",
        "voluntary",
        "charity"
    ],
    "wof:name":"Bendrigg Trust Ltd",
    "wof:placetype":"venue"
},
  "geometry": {"coordinates":[-2.6796689034,54.2908401489],"type":"Point"}
}