{
  "type": "Feature",
  "properties": {
    "addr:full":"78b Silver Road Norwich Norfolk NR3 4TE",
    "addr:housenumber":"78b",
    "addr:postcode":"nr3 4te",
    "addr:street":"Silver Road Norwich Norfolk",
    "iso:country":"GB",
    "sg:address":"78b Silver Road",
    "sg:city":"Norwich",
    "sg:classifiers":[
        {
            "category":"Manufacturing",
            "subcategory":"Wood Products",
            "type":"Manufacturing & Wholesale Goods"
        }
    ],
    "sg:phone":"+44 1603 632400",
    "sg:postcode":"NR3 4TE",
    "sg:province":"Norfolk",
    "sg:tags":[
        "craftsman"
    ],
    "wof:name":"Against the Grain",
    "wof:placetype":"venue"
},
  "geometry": {"coordinates":[1.302791,52.638973],"type":"Point"}
}