{
  "type": "Feature",
  "properties": {
    "addr:full":"1 Frederick Terrace, Frederick Place Brighton East Sussex BN1 1AX",
    "addr:housenumber":"1",
    "addr:postcode":"bn1 1ax",
    "addr:street":"Frederick Terrace Frederick Place",
    "iso:country":"GB",
    "sg:address":"1 Frederick Terrace, Frederick Place",
    "sg:city":"Brighton",
    "sg:classifiers":[
        {
            "category":"Professional",
            "subcategory":"Lawyer & Legal Services",
            "type":"Services"
        }
    ],
    "sg:phone":"+44 1273 326295",
    "sg:postcode":"BN1 1AX",
    "sg:province":"East Sussex",
    "sg:tags":[
        "solicitor"
    ],
    "wof:name":"Burstows",
    "wof:placetype":"venue"
},
  "geometry": {"coordinates":[-0.14065,50.828079],"type":"Point"}
}