{
  "type": "Feature",
  "properties": {
    "addr:full":"Severn House, Lower Forge, Eardington Bridgnorth Shropshire WV16 5LQ",
    "addr:postcode":"wv16 5lq",
    "addr:street":"Lower",
    "iso:country":"GB",
    "sg:address":"Severn House, Lower Forge, Eardington",
    "sg:city":"Bridgnorth",
    "sg:classifiers":[
        {
            "category":"Real Estate",
            "subcategory":"Developer",
            "type":"Services"
        }
    ],
    "sg:phone":"+44 1746 768847",
    "sg:postcode":"WV16 5LQ",
    "sg:province":"Shropshire",
    "sg:tags":[
        "property"
    ],
    "wof:name":"The Bunch Woodcock Partnership",
    "wof:placetype":"venue"
},
  "geometry": {"coordinates":[-2.4117939472,52.5135345459],"type":"Point"}
}