{
  "type": "Feature",
  "properties": {
    "addr:full":"533 Kingsbury Road London Greater London NW9 9EG",
    "addr:housenumber":"533",
    "addr:postcode":"nw9 9eg",
    "addr:street":"Kingsbury Road",
    "iso:country":"GB",
    "sg:address":"533 Kingsbury Road",
    "sg:city":"London",
    "sg:classifiers":[
        {
            "category":"Shopping",
            "subcategory":"Pharmacy",
            "type":"Retail Goods"
        }
    ],
    "sg:phone":"+44 20 8204 8651",
    "sg:postcode":"NW9 9EG",
    "sg:province":"Greater London",
    "sg:tags":[
        "pharmacist",
        "chemist"
    ],
    "wof:name":"Dale Chemist",
    "wof:placetype":"venue"
},
  "geometry": {"coordinates":[-0.2792800069,51.5847702026],"type":"Point"}
}