{
  "type": "Feature",
  "properties": {
    "iso:country":"GB",
    "sg:address":"64-66 High St",
    "sg:city":"West Bromwich",
    "sg:classifiers":[
        {
            "category":"Home & Garden",
            "subcategory":"Kitchen Supply",
            "type":"Retail Goods"
        }
    ],
    "sg:phone":"+44 121 580 3476",
    "sg:postcode":"B70 6JT",
    "sg:province":"West Midlands",
    "sg:tags":[
        "ware"
    ],
    "wof:name":"The Kitchen & Bedroom Factory",
    "wof:placetype":"venue"
},
  "geometry": {"coordinates":[-1.9861010313,52.5137863159],"type":"Point"}
}