{
  "type": "Feature",
  "properties": {
    "iso:country":"GB",
    "sg:address":"Southend Road, Rettendon Common",
    "sg:city":"Chelmsford",
    "sg:classifiers":[
        {
            "category":"Building & Trades",
            "subcategory":"Construction",
            "type":"Services"
        }
    ],
    "sg:phone":"+44 1245 401007",
    "sg:postcode":"CM3 8DZ",
    "sg:province":"Essex",
    "sg:tags":[
        "roofing"
    ],
    "wof:name":"Southern Counties Flat Roofing Ltd.",
    "wof:placetype":"venue"
},
  "geometry": {"coordinates":[0.54842,51.65139],"type":"Point"}
}