{
  "type": "Feature",
  "properties": {
    "iso:country":"GB",
    "sg:address":"128 Seabank Rd",
    "sg:city":"Wallasey",
    "sg:classifiers":[
        {
            "category":"Personal",
            "subcategory":"Beauty Salon",
            "type":"Services"
        }
    ],
    "sg:phone":"+44 151 639 2079",
    "sg:postcode":"L45 1HG",
    "sg:province":"Merseyside",
    "sg:tags":[
        "unisex",
        "hairdresser"
    ],
    "wof:name":"Antoinette's",
    "wof:placetype":"venue"
},
  "geometry": {"coordinates":[-3.0392329693,53.4310836792],"type":"Point"}
}