{
  "type": "Feature",
  "properties": {
    "addr:full":"St Andrews Road, Holesmouth Avonmouth Bristol City of Bristol BS11 9BP",
    "addr:postcode":"bs11 9bp",
    "addr:street":"St Andrews Road Holesmouth",
    "iso:country":"GB",
    "sg:address":"St Andrews Road, Holesmouth Avonmouth",
    "sg:city":"Bristol",
    "sg:classifiers":[
        {
            "category":"Freight",
            "type":"Transportation"
        }
    ],
    "sg:postcode":"BS11 9BP",
    "sg:province":"City of Bristol",
    "sg:tags":[
        "haulage",
        "road"
    ],
    "wof:name":"Frank Robbins Transport Ltd.",
    "wof:placetype":"venue"
},
  "geometry": {"coordinates":[-2.6980540752,51.5028686523],"type":"Point"}
}