{
  "type": "Feature",
  "properties": {
    "addr:full":"345 Palatine Road, Northenden Manchester Greater Manchester M22 4FY",
    "addr:housenumber":"345",
    "addr:postcode":"m22 4fy",
    "addr:street":"Palatine Road",
    "iso:country":"GB",
    "sg:address":"345 Palatine Road, Northenden",
    "sg:city":"Manchester",
    "sg:classifiers":[
        {
            "category":"Restaurant",
            "type":"Food & Drink"
        }
    ],
    "sg:phone":"+44 161 946 0501",
    "sg:postcode":"M22 4FY",
    "sg:province":"Greater Manchester",
    "wof:name":"Jai Kathmandu",
    "wof:placetype":"venue"
},
  "geometry": {"coordinates":[-2.2569279671,53.4085197449],"type":"Point"}
}