{
  "type": "Feature",
  "properties": {
    "addr:full":"1 Mount Radford Crescent Exeter Devon EX2 4EW",
    "addr:housenumber":"1",
    "addr:postcode":"ex2 4ew",
    "addr:street":"Mount Radford Crescent",
    "iso:country":"GB",
    "sg:address":"1 Mount Radford Crescent",
    "sg:city":"Exeter",
    "sg:classifiers":[
        {
            "category":"Education",
            "subcategory":"Special Training",
            "type":"Public Place"
        }
    ],
    "sg:phone":"+44 1392 254102",
    "sg:postcode":"EX2 4EW",
    "sg:province":"Devon",
    "sg:tags":[
        "school",
        "language"
    ],
    "wof:name":"International School of English",
    "wof:placetype":"venue"
},
  "geometry": {"coordinates":[-3.52216,50.719856],"type":"Point"}
}