{
  "type": "Feature",
  "properties": {
    "addr:full":"Bowling Grn, King George Recreation Ground Watford Hertfordshire WD23 4PY",
    "addr:postcode":"wd23 4py",
    "iso:country":"GB",
    "sg:address":"Bowling Grn, King George Recreation Ground",
    "sg:city":"Watford",
    "sg:classifiers":[
        {
            "category":"Sports & Exercise",
            "subcategory":"Bowling",
            "type":"Entertainment"
        }
    ],
    "sg:phone":"+44 20 8950 0424",
    "sg:postcode":"WD23 4PY",
    "sg:province":"Hertfordshire",
    "wof:name":"Bushey Bowling Club",
    "wof:placetype":"venue"
},
  "geometry": {"coordinates":[-0.3526299894,51.645111084],"type":"Point"}
}