{
  "type": "Feature",
  "properties": {
    "addr:full":"12 Stortford Road Dunmow Essex CM6 1DA",
    "addr:housenumber":"12",
    "addr:postcode":"cm6 1da",
    "addr:street":"Stortford Road",
    "iso:country":"GB",
    "sg:address":"12 Stortford Road",
    "sg:city":"Dunmow",
    "sg:classifiers":[
        {
            "category":"Organizations",
            "subcategory":"Non-profit Organization",
            "type":"Services"
        }
    ],
    "sg:phone":"+44 1371 872519",
    "sg:postcode":"CM6 1DA",
    "sg:province":"Essex",
    "sg:tags":[
        "organisation",
        "voluntary",
        "charity"
    ],
    "wof:name":"Alzheimers Disease Society",
    "wof:placetype":"venue"
},
  "geometry": {"coordinates":[0.3605130017,51.8731231689],"type":"Point"}
}