{
  "type": "Feature",
  "properties": {
    "addr:full":"23 Bridge Street, Helmsley York North Yorkshire YO62 5BG",
    "addr:housenumber":"23",
    "addr:postcode":"yo62 5bg",
    "addr:street":"Bridge Street",
    "iso:country":"GB",
    "sg:address":"23 Bridge Street, Helmsley",
    "sg:city":"York",
    "sg:classifiers":[
        {
            "category":"Government",
            "subcategory":"Post Office",
            "type":"Public Place"
        }
    ],
    "sg:phone":"+44 1439 770237",
    "sg:postcode":"YO62 5BG",
    "sg:province":"North Yorkshire",
    "wof:name":"Helmsley Post Office",
    "wof:placetype":"venue"
},
  "geometry": {"coordinates":[-1.060689,54.245869],"type":"Point"}
}