{
  "type": "Feature",
  "properties": {
    "addr:full":"12-16 Craigdale Road Hornchurch Essex RM11 1AE",
    "addr:housenumber":"12-16",
    "addr:postcode":"rm11 1ae",
    "addr:street":"Craigdale Road",
    "iso:country":"GB",
    "sg:address":"12-16 Craigdale Road",
    "sg:city":"Hornchurch",
    "sg:classifiers":[
        {
            "category":"Retail",
            "subcategory":"Auto Repair",
            "type":"Services"
        }
    ],
    "sg:phone":"+44 1708 747287",
    "sg:postcode":"RM11 1AE",
    "sg:province":"Essex",
    "sg:tags":[
        "modification",
        "garage"
    ],
    "wof:name":"Autocare",
    "wof:placetype":"venue"
},
  "geometry": {"coordinates":[0.1893920004,51.5713119507],"type":"Point"}
}