{
  "type": "Feature",
  "properties": {
    "iso:country":"GB",
    "sg:address":"21 Hunter Place",
    "sg:city":"Stonehaven",
    "sg:classifiers":[
        {
            "category":"Retail",
            "subcategory":"Driving School",
            "type":"Services"
        }
    ],
    "sg:phone":"+44 1569 764231",
    "sg:postcode":"AB39 2AZ",
    "sg:province":"Aberdeenshire",
    "wof:name":"Sutherland Driving School",
    "wof:placetype":"venue"
},
  "geometry": {"coordinates":[-2.225591,56.968678],"type":"Point"}
}