{
  "type": "Feature",
  "properties": {
    "addr:full":"503 Smithdown Road Liverpool Merseyside L15 5AE",
    "addr:housenumber":"503",
    "addr:postcode":"l15 5ae",
    "addr:street":"Smithdown Road",
    "iso:country":"GB",
    "sg:address":"503 Smithdown Road",
    "sg:city":"Liverpool",
    "sg:classifiers":[
        {
            "category":"Professional",
            "subcategory":"Accounting & Tax Preparation",
            "type":"Services"
        }
    ],
    "sg:phone":"+44 151 734 3000",
    "sg:postcode":"L15 5AE",
    "sg:province":"Merseyside",
    "sg:tags":[
        "accountant",
        "activity"
    ],
    "wof:name":"S Samuels & Co",
    "wof:placetype":"venue"
},
  "geometry": {"coordinates":[-2.925909,53.389919],"type":"Point"}
}