{
  "type": "Feature",
  "properties": {
    "addr:full":"Hayley Grn Farm, Hagley Road Halesowen West Midlands B63 1DZ",
    "addr:postcode":"b63 1dz",
    "addr:street":"Hayley Grn Farm Hagley Road",
    "iso:country":"GB",
    "sg:address":"Hayley Grn Farm, Hagley Road",
    "sg:city":"Halesowen",
    "sg:classifiers":[
        {
            "category":"Retail",
            "subcategory":"Auto Repair",
            "type":"Services"
        }
    ],
    "sg:postcode":"B63 1DZ",
    "sg:province":"West Midlands",
    "sg:tags":[
        "car",
        "assembler",
        "kit"
    ],
    "wof:name":"Vindicator Cars",
    "wof:placetype":"venue"
},
  "geometry": {"coordinates":[-2.0854570866,52.4344902039],"type":"Point"}
}