{
  "type": "Feature",
  "properties": {
    "addr:full":"Earlstone Common, Burghclere Newbury Berkshire RG20 9HP",
    "addr:housenumber":"burghclere",
    "addr:postcode":"rg20 9hp",
    "addr:street":"Earlstone Common;Newbury",
    "iso:country":"GB",
    "sg:address":"Earlstone Common, Burghclere",
    "sg:city":"Newbury",
    "sg:classifiers":[
        {
            "category":"Education",
            "subcategory":"School",
            "type":"Public Place"
        },
        {
            "category":"Community Center",
            "type":"Public Place"
        }
    ],
    "sg:phone":"+44 1635 278372",
    "sg:postcode":"RG20 9HP",
    "sg:province":"Berkshire",
    "sg:tags":[
        "local",
        "authority",
        "centre"
    ],
    "wof:name":"The Clere School",
    "wof:placetype":"venue"
},
  "geometry": {"coordinates":[-1.324039,51.348267],"type":"Point"}
}