{
  "type": "Feature",
  "properties": {
    "addr:full":"Unit 37a Norfolk Street Sunderland Tyne and Wear SR5 3JG",
    "addr:housenumber":"unit 37a",
    "addr:postcode":"sr5 3jg",
    "addr:street":"Norfolk Street",
    "iso:country":"GB",
    "sg:address":"Unit 37a Norfolk Street",
    "sg:city":"Sunderland",
    "sg:classifiers":[
        {
            "category":"Manufacturing",
            "subcategory":"Signs",
            "type":"Manufacturing & Wholesale Goods"
        }
    ],
    "sg:postcode":"SR5 3JG",
    "sg:province":"Tyne and Wear",
    "sg:tags":[
        "nameplate"
    ],
    "wof:name":"Portland Signs",
    "wof:placetype":"venue"
},
  "geometry": {"coordinates":[-1.3785640001,54.9075202942],"type":"Point"}
}