{
  "type": "Feature",
  "properties": {
    "addr:full":"161 Rotterdam Road Lowestoft Suffolk NR32 2EZ",
    "addr:housenumber":"161",
    "addr:postcode":"nr32 2ez",
    "addr:street":"Rotterdam Road",
    "iso:country":"GB",
    "sg:address":"161 Rotterdam Road",
    "sg:city":"Lowestoft",
    "sg:classifiers":[
        {
            "category":"Government",
            "subcategory":"Office",
            "type":"Public Place"
        },
        {
            "category":"Organizations",
            "subcategory":"Non-profit Organization",
            "type":"Services"
        }
    ],
    "sg:phone":"+44 1502 405454",
    "sg:postcode":"NR32 2EZ",
    "sg:province":"Suffolk",
    "sg:tags":[
        "organisation",
        "local",
        "voluntary",
        "charity"
    ],
    "wof:name":"Waveney Centre for Independent Living",
    "wof:placetype":"venue"
},
  "geometry": {"coordinates":[1.739039,52.479675],"type":"Point"}
}