{
  "type": "Feature",
  "properties": {
    "iso:country":"GB",
    "sg:address":"3 Westshore Road, Granton",
    "sg:city":"Edinburgh",
    "sg:classifiers":[
        {
            "category":"Building & Trades",
            "subcategory":"Construction",
            "type":"Services"
        }
    ],
    "sg:phone":"+44 131 551 4431",
    "sg:postcode":"EH5 1QB",
    "sg:province":"City of Edinburgh",
    "sg:tags":[
        "platform",
        "work",
        "scaffolding"
    ],
    "wof:name":"Double Grip (Contracts) Ltd.",
    "wof:placetype":"venue"
},
  "geometry": {"coordinates":[-3.231144,55.978073],"type":"Point"}
}