{
  "type": "Feature",
  "properties": {
    "iso:country":"GB",
    "sg:address":"Warden, 85 Repton Rd",
    "sg:city":"Doncaster",
    "sg:classifiers":[
        {
            "category":"Organizations",
            "subcategory":"Community Association",
            "type":"Services"
        }
    ],
    "sg:phone":"+44 1302 727199",
    "sg:postcode":"DN6 8JG",
    "sg:province":"North Yorkshire",
    "sg:tags":[
        "society",
        "housing"
    ],
    "wof:name":"Michelle Eyre",
    "wof:placetype":"venue"
},
  "geometry": {"coordinates":[-1.18901,53.582771],"type":"Point"}
}