{
  "type": "Feature",
  "properties": {
    "iso:country":"GB",
    "sg:address":"83 St James Road",
    "sg:city":"Derby",
    "sg:classifiers":[
        {
            "category":"Food & Beverages",
            "subcategory":"Liquor & Beverages",
            "type":"Retail Goods"
        }
    ],
    "sg:phone":"+44 1332 766875",
    "sg:postcode":"DE23 8QW",
    "sg:province":"Derbyshire",
    "sg:tags":[
        "beer",
        "spirit",
        "wines"
    ],
    "wof:name":"Bal Krishan",
    "wof:placetype":"venue"
},
  "geometry": {"coordinates":[-1.4807349443,52.9056549072],"type":"Point"}
}