{
  "type": "Feature",
  "properties": {
    "addr:full":"Regent House, Regent Way Chepstow Gloucestershire NP16 5BY",
    "addr:postcode":"np16 5by",
    "addr:street":"Regent Way",
    "iso:country":"GB",
    "sg:address":"Regent House, Regent Way",
    "sg:city":"Chepstow",
    "sg:classifiers":[
        {
            "category":"Organizations",
            "subcategory":"Non-profit Organization",
            "type":"Services"
        }
    ],
    "sg:phone":"+44 1291 629436",
    "sg:postcode":"NP16 5BY",
    "sg:province":"Gloucestershire",
    "sg:tags":[
        "organisation",
        "voluntary",
        "charity"
    ],
    "wof:name":"Monmouthshire County Council Social Services Department",
    "wof:placetype":"venue"
},
  "geometry": {"coordinates":[-2.679097,51.640457],"type":"Point"}
}