{
  "type": "Feature",
  "properties": {
    "iso:country":"GB",
    "sg:address":"191 Squires Gate Lane",
    "sg:city":"Blackpool",
    "sg:classifiers":[
        {
            "category":"Building & Trades",
            "subcategory":"Construction",
            "type":"Services"
        }
    ],
    "sg:postcode":"FY4 2QG",
    "sg:province":"Lancashire",
    "sg:tags":[
        "joiner",
        "carpenter"
    ],
    "wof:name":"ROBERT SENIOR",
    "wof:placetype":"venue"
},
  "geometry": {"coordinates":[-3.038577,53.779957],"type":"Point"}
}