{
  "type": "Feature",
  "properties": {
    "iso:country":"GB",
    "sg:address":"588 Roman Rd",
    "sg:city":"Bow",
    "sg:classifiers":[
        {
            "category":"Shopping",
            "subcategory":"Clothing, Apparel, & Fashions",
            "type":"Retail Goods"
        }
    ],
    "sg:phone":"+44 20 8980 3207",
    "sg:postcode":"E3 5ES",
    "sg:province":"Greater London",
    "sg:tags":[
        "shop"
    ],
    "wof:name":"Zone 2",
    "wof:placetype":"venue"
},
  "geometry": {"coordinates":[-0.028532,51.533318],"type":"Point"}
}