{
  "type": "Feature",
  "properties": {
    "iso:country":"GB",
    "sg:address":"28 Harbour Road",
    "sg:city":"Inverness",
    "sg:classifiers":[
        {
            "category":"Manufacturing",
            "subcategory":"Building Materials",
            "type":"Manufacturing & Wholesale Goods"
        }
    ],
    "sg:phone":"+44 1463 712666",
    "sg:postcode":"IV1 1UA",
    "sg:province":"Highland",
    "sg:tags":[
        "merchant",
        "builder"
    ],
    "wof:name":"Highland Steel & Building Supplies Ltd.",
    "wof:placetype":"venue"
},
  "geometry": {"coordinates":[-4.216269,57.484871],"type":"Point"}
}