{
  "type": "Feature",
  "properties": {
    "iso:country":"GB",
    "sg:address":"96 King George Road",
    "sg:city":"Ware",
    "sg:classifiers":[
        {
            "category":"Fast Food",
            "type":"Food & Drink"
        }
    ],
    "sg:phone":"+44 1920 469862",
    "sg:postcode":"SG12 7DT",
    "sg:province":"Hertfordshire",
    "sg:tags":[
        "shop",
        "fish",
        "take",
        "chip",
        "away"
    ],
    "wof:name":"Bill Fish Bar",
    "wof:placetype":"venue"
},
  "geometry": {"coordinates":[-0.022916,51.81419],"type":"Point"}
}