{
  "type": "Feature",
  "properties": {
    "addr:full":"67 Market Street Abergele Conwy LL22 7AF",
    "addr:housenumber":"67",
    "addr:postcode":"ll22 7af",
    "addr:street":"Market Street",
    "iso:country":"GB",
    "sg:address":"67 Market Street",
    "sg:city":"Abergele",
    "sg:classifiers":[
        {
            "category":"Communications",
            "subcategory":"Newspaper",
            "type":"Services"
        }
    ],
    "sg:phone":"+44 1745 832230",
    "sg:postcode":"LL22 7AF",
    "sg:province":"Conwy",
    "sg:tags":[
        "magazine"
    ],
    "wof:name":"North Wales Weekly News",
    "wof:placetype":"venue"
},
  "geometry": {"coordinates":[-3.5862030983,53.2848014832],"type":"Point"}
}