{
  "type": "Feature",
  "properties": {
    "addr:full":"7 Ruskin Close, Fairwater Cwmbran Monmouthshire NP44 4QX",
    "addr:housenumber":"7",
    "addr:postcode":"np44 4qx",
    "addr:street":"Ruskin Close",
    "iso:country":"GB",
    "sg:address":"7 Ruskin Close, Fairwater",
    "sg:city":"Cwmbran",
    "sg:classifiers":[
        {
            "category":"Professional",
            "subcategory":"Accounting & Tax Preparation",
            "type":"Services"
        }
    ],
    "sg:postcode":"NP44 4QX",
    "sg:province":"Monmouthshire",
    "sg:tags":[
        "accountant"
    ],
    "wof:name":"John E Sargent",
    "wof:placetype":"venue"
},
  "geometry": {"coordinates":[-3.0503358841,51.6460418701],"type":"Point"}
}