{
  "type": "Feature",
  "properties": {
    "iso:country":"GB",
    "sg:address":"33 Ridgeway Park Rd",
    "sg:city":"Newport",
    "sg:classifiers":[
        {
            "category":"Organizations",
            "subcategory":"Non-profit Organization",
            "type":"Services"
        }
    ],
    "sg:phone":"+44 1633 212349",
    "sg:postcode":"NP20 5AL",
    "sg:province":"Newport",
    "sg:tags":[
        "organisation",
        "voluntary",
        "charity"
    ],
    "wof:name":"Leukaemia Research Appeal for Wales",
    "wof:placetype":"venue"
},
  "geometry": {"coordinates":[-3.018934,51.588497],"type":"Point"}
}