{
  "type": "Feature",
  "properties": {
    "iso:country":"GB",
    "sg:address":"23 Highway Road, Thurmaston",
    "sg:city":"Leicester",
    "sg:classifiers":[
        {
            "category":"Real Estate",
            "subcategory":"Architect",
            "type":"Services"
        }
    ],
    "sg:phone":"+44 116 269 4270",
    "sg:postcode":"LE4 8FR",
    "sg:province":"Leicestershire",
    "sg:tags":[
        "technician",
        "technologist",
        "architectural"
    ],
    "wof:name":"Amatco Design Services",
    "wof:placetype":"venue"
},
  "geometry": {"coordinates":[-1.087727,52.682755],"type":"Point"}
}