{
  "type": "Feature",
  "properties": {
    "addr:full":"5a Bushey Hill Road London Greater London SE5 8QF",
    "addr:housenumber":"5a",
    "addr:postcode":"se5 8qf",
    "addr:street":"Bushey Hill Road",
    "iso:country":"GB",
    "sg:address":"5a Bushey Hill Road",
    "sg:city":"London",
    "sg:classifiers":[
        {
            "category":"Autos & Motor Vehicles",
            "subcategory":"Auto Supplies",
            "type":"Retail Goods"
        }
    ],
    "sg:phone":"+44 20 7703 9451",
    "sg:postcode":"SE5 8QF",
    "sg:province":"Greater London",
    "sg:tags":[
        "taxi",
        "equipment"
    ],
    "wof:name":"Bright Taxi Parts",
    "wof:placetype":"venue"
},
  "geometry": {"coordinates":[-0.0791660026,51.4734649658],"type":"Point"}
}