{
  "type": "Feature",
  "properties": {
    "addr:full":"The Parade, Prestwick Road Watford Hertfordshire WD19 7DX",
    "addr:postcode":"wd19 7dx",
    "addr:street":"The Parade Prestwick Road",
    "iso:country":"GB",
    "sg:address":"The Parade, Prestwick Road",
    "sg:city":"Watford",
    "sg:classifiers":[
        {
            "category":"Fast Food",
            "type":"Food & Drink"
        }
    ],
    "sg:phone":"+44 20 8421 0262",
    "sg:postcode":"WD19 7DX",
    "sg:province":"Hertfordshire",
    "sg:tags":[
        "delivery"
    ],
    "wof:name":"Pizza Pino",
    "wof:placetype":"venue"
},
  "geometry": {"coordinates":[-0.3870890141,51.6277351379],"type":"Point"}
}