{
  "type": "Feature",
  "properties": {
    "addr:full":"Stonegate Street King's Lynn Norfolk PE30 5EF",
    "addr:postcode":"pe30 5ef",
    "addr:street":"Stonegate Street",
    "iso:country":"GB",
    "sg:address":"Stonegate Street",
    "sg:city":"King's Lynn",
    "sg:classifiers":[
        {
            "category":"Home & Garden",
            "subcategory":"Building Materials",
            "type":"Retail Goods"
        }
    ],
    "sg:phone":"+44 1553 775046",
    "sg:postcode":"PE30 5EF",
    "sg:province":"Norfolk",
    "sg:tags":[
        "furnishers",
        "bathroom",
        "planner"
    ],
    "wof:name":"J T C Warehouse Ltd.",
    "wof:placetype":"venue"
},
  "geometry": {"coordinates":[0.39673,52.7505],"type":"Point"}
}