{
  "type": "Feature",
  "properties": {
    "iso:country":"GB",
    "sg:address":"Millennium Ho, 366 Chester Rd",
    "sg:city":"Manchester",
    "sg:classifiers":[
        {
            "category":"Building & Trades",
            "subcategory":"Cleaning & Sanitation",
            "type":"Services"
        }
    ],
    "sg:postcode":"M16 9FH",
    "sg:province":"Cheshire",
    "sg:tags":[
        "commercial"
    ],
    "wof:name":"P C M S Northern",
    "wof:placetype":"venue"
},
  "geometry": {"coordinates":[-2.26703,53.466],"type":"Point"}
}