{
  "type": "Feature",
  "properties": {
    "iso:country":"GB",
    "sg:address":"81 York Road",
    "sg:city":"Tadcaster",
    "sg:classifiers":[
        {
            "category":"Government",
            "subcategory":"Post Office",
            "type":"Public Place"
        }
    ],
    "sg:phone":"+44 1937 833168",
    "sg:postcode":"LS24 8AR",
    "sg:province":"North Yorkshire",
    "wof:name":"Hill Top Post Office",
    "wof:placetype":"venue"
},
  "geometry": {"coordinates":[-1.253021,53.888214],"type":"Point"}
}