{
  "type": "Feature",
  "properties": {
    "iso:country":"GB",
    "sg:address":"30 New Road",
    "sg:city":"Brighton",
    "sg:classifiers":[
        {
            "category":"Organizations",
            "subcategory":"Membership Organization",
            "type":"Services"
        }
    ],
    "sg:postcode":"BN1 1BN",
    "sg:province":"East Sussex",
    "sg:tags":[
        "club"
    ],
    "wof:name":"Courthouse (Brighton) Ltd",
    "wof:placetype":"venue"
},
  "geometry": {"coordinates":[-0.1393849999,50.8230895996],"type":"Point"}
}