{
  "type": "Feature",
  "properties": {
    "addr:full":"Glenfall Stables, Ham Road, Charlton Kings Cheltenham Gloucestershire GL52 6NH",
    "addr:postcode":"gl52 6nh",
    "addr:street":"Ham Road",
    "iso:country":"GB",
    "sg:address":"Glenfall Stables, Ham Road, Charlton Kings",
    "sg:city":"Cheltenham",
    "sg:classifiers":[
        {
            "category":"Personal",
            "subcategory":"Adult",
            "type":"Services"
        }
    ],
    "sg:phone":"+44 1242 244713",
    "sg:postcode":"GL52 6NH",
    "sg:province":"Gloucestershire",
    "sg:tags":[
        "equestrian"
    ],
    "wof:name":"Andrew James Wilson",
    "wof:placetype":"venue"
},
  "geometry": {"coordinates":[-2.044046,51.883915],"type":"Point"}
}