{
  "type": "Feature",
  "properties": {
    "addr:full":"Highcroft, Blackpool Rd Preston Lancashire PR4 0XL",
    "addr:postcode":"pr4 0xl",
    "addr:street":"Blackpool Rd",
    "iso:country":"GB",
    "sg:address":"Highcroft, Blackpool Rd",
    "sg:city":"Preston",
    "sg:classifiers":[
        {
            "category":"Home & Garden",
            "subcategory":"Carpets & Floor Coverings",
            "type":"Retail Goods"
        }
    ],
    "sg:phone":"+44 1772 671733",
    "sg:postcode":"PR4 0XL",
    "sg:province":"Lancashire",
    "sg:tags":[
        "cleaner",
        "upholstery"
    ],
    "wof:name":"A1 Home 'n' Dry",
    "wof:placetype":"venue"
},
  "geometry": {"coordinates":[-2.8245620728,53.7709121704],"type":"Point"}
}