{
  "type": "Feature",
  "properties": {
    "iso:country":"GB",
    "sg:address":"48 Gaydon House, Bourne Terrace",
    "sg:city":"London",
    "sg:classifiers":[
        {
            "category":"Building & Trades",
            "subcategory":"Construction",
            "type":"Services"
        }
    ],
    "sg:phone":"+44 20 7286 7958",
    "sg:postcode":"W2 5TG",
    "sg:province":"Greater London",
    "sg:tags":[
        "builder"
    ],
    "wof:name":"Steve Clarke",
    "wof:placetype":"venue"
},
  "geometry": {"coordinates":[-0.18924,51.520802],"type":"Point"}
}