{
  "type": "Feature",
  "properties": {
    "iso:country":"GB",
    "sg:address":"21 Chestnut Avenue, Gosfield",
    "sg:city":"Halstead",
    "sg:classifiers":[
        {
            "category":"Professional",
            "subcategory":"Computer Services",
            "type":"Services"
        }
    ],
    "sg:phone":"+44 1787 475278",
    "sg:postcode":"CO9 1TD",
    "sg:province":"Essex",
    "sg:tags":[
        "aided",
        "design"
    ],
    "wof:name":"Scorpio Engineering Design",
    "wof:placetype":"venue"
},
  "geometry": {"coordinates":[0.5900840163,51.9399909973],"type":"Point"}
}