{
  "type": "Feature",
  "properties": {
    "addr:full":"54-56 Shaftesbury Avenue London Greater London W1D 6LD",
    "addr:housenumber":"54-56",
    "addr:postcode":"w1d 6ld",
    "addr:street":"Shaftesbury Avenue",
    "iso:country":"GB",
    "sg:address":"54-56 Shaftesbury Avenue",
    "sg:city":"London",
    "sg:classifiers":[
        {
            "category":"Shopping",
            "subcategory":"Clothing, Apparel, & Fashions",
            "type":"Retail Goods"
        }
    ],
    "sg:phone":"+44 20 7434 2606",
    "sg:postcode":"W1D 6LD",
    "sg:province":"Greater London",
    "sg:tags":[
        "menswear"
    ],
    "wof:name":"John Anthony",
    "wof:placetype":"venue"
},
  "geometry": {"coordinates":[-0.132657,51.51152],"type":"Point"}
}