{
  "type": "Feature",
  "properties": {
    "addr:full":"7 Penlline Rd, Whitchurch Cardiff Cardiff CF14 2AA",
    "addr:housenumber":"7",
    "addr:postcode":"cf14 2aa",
    "addr:street":"Penlline Rd",
    "iso:country":"GB",
    "sg:address":"7 Penlline Rd, Whitchurch",
    "sg:city":"Cardiff",
    "sg:classifiers":[
        {
            "category":"Cafe",
            "type":"Food & Drink"
        }
    ],
    "sg:postcode":"CF14 2AA",
    "sg:province":"Cardiff",
    "sg:tags":[
        "tea",
        "room"
    ],
    "wof:name":"Hicklin,Gayle,",
    "wof:placetype":"venue"
},
  "geometry": {"coordinates":[-3.220304966,51.5133323669],"type":"Point"}
}