{
  "type": "Feature",
  "properties": {
    "iso:country":"GB",
    "sg:address":"Kevin Mitchell, 25 Roundyhill, Monifieth",
    "sg:city":"Dundee",
    "sg:classifiers":[
        {
            "category":"Building & Trades",
            "subcategory":"Plumbing",
            "type":"Services"
        }
    ],
    "sg:phone":"+44 1382 534648",
    "sg:postcode":"DD5 4RY",
    "sg:province":"Angus",
    "sg:tags":[
        "heating"
    ],
    "wof:name":"Adams Heating & Plumbing Ltd.",
    "wof:placetype":"venue"
},
  "geometry": {"coordinates":[-2.820031,56.480404],"type":"Point"}
}