{
  "type": "Feature",
  "properties": {
    "addr:full":"4 Lyon Road London Greater London SW19 2RL",
    "addr:housenumber":"4",
    "addr:postcode":"sw19 2rl",
    "addr:street":"Lyon Road",
    "iso:country":"GB",
    "sg:address":"4 Lyon Road",
    "sg:city":"London",
    "sg:classifiers":[
        {
            "category":"Wholesale",
            "subcategory":"Groceries",
            "type":"Manufacturing & Wholesale Goods"
        }
    ],
    "sg:phone":"+44 20 8542 5055",
    "sg:postcode":"SW19 2RL",
    "sg:province":"Greater London",
    "sg:tags":[
        "sausage",
        "product"
    ],
    "wof:name":"Graham White & Co. Ltd.",
    "wof:placetype":"venue"
},
  "geometry": {"coordinates":[-0.185528,51.411301],"type":"Point"}
}