{
  "type": "Feature",
  "properties": {
    "iso:country":"GB",
    "sg:address":"1a Woodhouse Road",
    "sg:city":"Mansfield",
    "sg:classifiers":[
        {
            "category":"Home & Garden",
            "subcategory":"Home Furnishings",
            "type":"Retail Goods"
        },
        {
            "category":"Home & Garden",
            "subcategory":"Building Materials",
            "type":"Retail Goods"
        }
    ],
    "sg:phone":"+44 1623 422322",
    "sg:postcode":"NG18 2AD",
    "sg:province":"Nottinghamshire",
    "sg:tags":[
        "installers",
        "planner",
        "kitchen",
        "furnishers"
    ],
    "wof:name":"Simmons Kitchens & Bathrooms",
    "wof:placetype":"venue"
},
  "geometry": {"coordinates":[-1.193854,53.151592],"type":"Point"}
}