{
  "type": "Feature",
  "properties": {
    "addr:full":"Park Terrace, Dunmow Road, Hatfield Broad Oak Bishops Stortford Essex CM22 7JQ",
    "addr:postcode":"cm22 7jq",
    "addr:street":"Park Terrace Dunmow Road",
    "iso:country":"GB",
    "sg:address":"Park Terrace, Dunmow Road, Hatfield Broad Oak",
    "sg:city":"Bishops Stortford",
    "sg:classifiers":[
        {
            "category":"Building & Trades",
            "subcategory":"Construction",
            "type":"Services"
        }
    ],
    "sg:phone":"+44 1279 718266",
    "sg:postcode":"CM22 7JQ",
    "sg:province":"Essex",
    "sg:tags":[
        "builder"
    ],
    "wof:name":"P Reed",
    "wof:placetype":"venue"
},
  "geometry": {"coordinates":[0.2148700058,51.8118133545],"type":"Point"}
}