{
  "type": "Feature",
  "properties": {
    "addr:full":"49 Singleton Close London Greater London SW17 9JZ",
    "addr:housenumber":"49",
    "addr:postcode":"sw17 9jz",
    "addr:street":"Singleton Close",
    "iso:country":"GB",
    "sg:address":"49 Singleton Close",
    "sg:city":"London",
    "sg:classifiers":[
        {
            "category":"Shopping",
            "subcategory":"Musical Instruments",
            "type":"Retail Goods"
        }
    ],
    "sg:phone":"+44 20 8646 4347",
    "sg:postcode":"SW17 9JZ",
    "sg:province":"Greater London",
    "wof:name":"Graham A Richards",
    "wof:placetype":"venue"
},
  "geometry": {"coordinates":[-0.166842,51.418373],"type":"Point"}
}