{
  "type": "Feature",
  "properties": {
    "addr:full":"53 Waller Avenue Luton Bedfordshire LU4 9RP",
    "addr:housenumber":"53",
    "addr:postcode":"lu4 9rp",
    "addr:street":"Waller Avenue",
    "iso:country":"GB",
    "sg:address":"53 Waller Avenue",
    "sg:city":"Luton",
    "sg:classifiers":[
        {
            "category":"Personal",
            "subcategory":"Beauty Salon",
            "type":"Services"
        }
    ],
    "sg:postcode":"LU4 9RP",
    "sg:province":"Bedfordshire",
    "sg:tags":[
        "unisex",
        "hairdresser"
    ],
    "wof:name":"Michele's",
    "wof:placetype":"venue"
},
  "geometry": {"coordinates":[-0.4524010122,51.8944854736],"type":"Point"}
}