{
  "type": "Feature",
  "properties": {
    "iso:country":"GB",
    "sg:address":"Wells Road",
    "sg:city":"Malvern",
    "sg:classifiers":[
        {
            "category":"Travel",
            "subcategory":"Hotels & Motels",
            "type":"Entertainment"
        }
    ],
    "sg:postcode":"WR14 4RH",
    "sg:province":"Herefordshire",
    "wof:name":"Tudor Hotel",
    "wof:placetype":"venue"
},
  "geometry": {"coordinates":[-2.330153,52.108006],"type":"Point"}
}