{
  "type": "Feature",
  "properties": {
    "addr:full":"81-83 Cutlers Road, South Woodham Ferrers Chelmsford Essex CM3 5WA",
    "addr:housenumber":"81-83",
    "addr:postcode":"cm3 5wa",
    "addr:street":"Cutlers Road",
    "iso:country":"GB",
    "sg:address":"81-83 Cutlers Road, South Woodham Ferrers",
    "sg:city":"Chelmsford",
    "sg:classifiers":[
        {
            "category":"Home & Garden",
            "subcategory":"Hardware",
            "type":"Retail Goods"
        }
    ],
    "sg:phone":"+44 1245 323123",
    "sg:postcode":"CM3 5WA",
    "sg:province":"Essex",
    "sg:tags":[
        "merchant",
        "ironmonger"
    ],
    "wof:name":"M & H Supplies",
    "wof:placetype":"venue"
},
  "geometry": {"coordinates":[0.621165,51.648598],"type":"Point"}
}