{
  "type": "Feature",
  "properties": {
    "addr:full":"2 West St Cambridge Cambridgeshire CB3 7DS",
    "addr:housenumber":"2",
    "addr:postcode":"cb3 7ds",
    "addr:street":"West St",
    "iso:country":"GB",
    "sg:address":"2 West St",
    "sg:city":"Cambridge",
    "sg:classifiers":[
        {
            "category":"Professional",
            "subcategory":"Management & Consulting",
            "type":"Services"
        }
    ],
    "sg:phone":"+44 1223 263789",
    "sg:postcode":"CB3 7DS",
    "sg:province":"Cambridgeshire",
    "sg:tags":[
        "consultant",
        "business"
    ],
    "wof:name":"James Turnball Management Services",
    "wof:placetype":"venue"
},
  "geometry": {"coordinates":[0.0187289994,52.1871070862],"type":"Point"}
}