{
  "type": "Feature",
  "properties": {
    "iso:country":"GB",
    "sg:address":"16 Myatt Avenue, Aldridge",
    "sg:city":"Walsall",
    "sg:classifiers":[
        {
            "category":"Wholesale",
            "subcategory":"Groceries",
            "type":"Manufacturing & Wholesale Goods"
        }
    ],
    "sg:phone":"+44 1922 451307",
    "sg:postcode":"WS9 0DR",
    "sg:province":"Staffordshire",
    "sg:tags":[
        "food",
        "supplier",
        "drink"
    ],
    "wof:name":"Myatt Supermarket",
    "wof:placetype":"venue"
},
  "geometry": {"coordinates":[-1.93288,52.600525],"type":"Point"}
}