{
  "type": "Feature",
  "properties": {
    "addr:full":"35 High Street Yarm North Yorkshire TS15 9BW",
    "addr:housenumber":"35",
    "addr:postcode":"ts15 9bw",
    "addr:street":"High Street",
    "iso:country":"GB",
    "sg:address":"35 High Street",
    "sg:city":"Yarm",
    "sg:classifiers":[
        {
            "category":"Health Services",
            "subcategory":"Optometrist",
            "type":"Services"
        }
    ],
    "sg:postcode":"TS15 9BW",
    "sg:province":"North Yorkshire",
    "sg:tags":[
        "optician"
    ],
    "wof:name":"Clifford T Rees",
    "wof:placetype":"venue"
},
  "geometry": {"coordinates":[-1.3540719748,54.5081825256],"type":"Point"}
}