{
  "type": "Feature",
  "properties": {
    "iso:country":"GB",
    "sg:address":"7 Crown Street, Wellington",
    "sg:city":"Telford",
    "sg:classifiers":[
        {
            "category":"Shopping",
            "subcategory":"Gifts & Souvenirs",
            "type":"Retail Goods"
        },
        {
            "category":"Shopping",
            "subcategory":"Comic Books",
            "type":"Retail Goods"
        }
    ],
    "sg:phone":"+44 1952 245707",
    "sg:postcode":"TF1 1LP",
    "sg:province":"Shropshire",
    "sg:tags":[
        "shop",
        "jeweller"
    ],
    "sg:website":"http://www.sevencrowns.co.uk",
    "wof:name":"Seven Crowns",
    "wof:placetype":"venue"
},
  "geometry": {"coordinates":[-2.518219,52.700649],"type":"Point"}
}