{
  "type": "Feature",
  "properties": {
    "addr:full":"21 Newbiggen Street, Thaxted Dunmow Essex CM6 2QS",
    "addr:housenumber":"21",
    "addr:postcode":"cm6 2qs",
    "addr:street":"Newbiggen Street",
    "iso:country":"GB",
    "sg:address":"21 Newbiggen Street, Thaxted",
    "sg:city":"Dunmow",
    "sg:classifiers":[
        {
            "category":"Banks & Credit Unions",
            "subcategory":"Financial Services",
            "type":"Services"
        },
        {
            "category":"Professional",
            "subcategory":"Computer Services",
            "type":"Services"
        }
    ],
    "sg:phone":"+44 1371 831444",
    "sg:postcode":"CM6 2QS",
    "sg:province":"Essex",
    "sg:tags":[
        "information",
        "pension",
        "business",
        "consultant"
    ],
    "wof:name":"T J Green (Pension Consultants) Ltd.",
    "wof:placetype":"venue"
},
  "geometry": {"coordinates":[0.340955,51.955601],"type":"Point"}
}