{
  "type": "Feature",
  "properties": {
    "addr:full":"Terminal Building Christchurch Dorset BH23 6SE",
    "addr:postcode":"bh23 6se",
    "iso:country":"GB",
    "sg:address":"Terminal Building",
    "sg:city":"Christchurch",
    "sg:classifiers":[
        {
            "category":"Transit Center",
            "subcategory":"Passenger",
            "type":"Transportation"
        },
        {
            "category":"Freight",
            "type":"Transportation"
        },
        {
            "category":"Professional",
            "subcategory":"Employment Agencies",
            "type":"Services"
        },
        {
            "category":"Airline",
            "type":"Transportation"
        }
    ],
    "sg:phone":"+44 1202 364252",
    "sg:postcode":"BH23 6SE",
    "sg:province":"Dorset",
    "sg:tags":[
        "cargo",
        "airport",
        "handling"
    ],
    "wof:name":"Servisair U K",
    "wof:placetype":"venue"
},
  "geometry": {"coordinates":[-1.776564002,50.7340698242],"type":"Point"}
}