{
  "type": "Feature",
  "properties": {
    "iso:country":"GB",
    "sg:address":"11 Whitehall Rd",
    "sg:city":"Rugby",
    "sg:classifiers":[
        {
            "category":"Health Services",
            "subcategory":"Doctor",
            "type":"Services"
        }
    ],
    "sg:phone":"+44 1788 544264",
    "sg:postcode":"CV21 3AQ",
    "sg:province":"Warwickshire",
    "sg:tags":[
        "practitioners"
    ],
    "wof:name":"Draper, I B",
    "wof:placetype":"venue"
},
  "geometry": {"coordinates":[-1.2542510033,52.3705101013],"type":"Point"}
}