{
  "type": "Feature",
  "properties": {
    "addr:full":"1 Greenfield Avenue, Guiseley Leeds West Yorkshire LS20 8HG",
    "addr:housenumber":"1",
    "addr:postcode":"ls20 8hg",
    "addr:street":"Greenfield Avenue",
    "iso:country":"GB",
    "sg:address":"1 Greenfield Avenue, Guiseley",
    "sg:city":"Leeds",
    "sg:classifiers":[
        {
            "category":"Utilities",
            "type":"Services"
        }
    ],
    "sg:postcode":"LS20 8HG",
    "sg:province":"West Yorkshire",
    "sg:tags":[
        "internet"
    ],
    "wof:name":"Amayzing Web Design Ltd",
    "wof:placetype":"venue"
},
  "geometry": {"coordinates":[-1.731886,53.868061],"type":"Point"}
}