{
  "type": "Feature",
  "properties": {
    "addr:full":"5 Manor Row Bradford West Yorkshire BD1 4PB",
    "addr:housenumber":"5",
    "addr:postcode":"bd1 4pb",
    "addr:street":"Manor Row Bradford West",
    "iso:country":"GB",
    "sg:address":"5 Manor Row",
    "sg:city":"Bradford",
    "sg:classifiers":[
        {
            "category":"Professional",
            "subcategory":"Employment Agencies",
            "type":"Services"
        }
    ],
    "sg:phone":"+44 1274 400200",
    "sg:postcode":"BD1 4PB",
    "sg:province":"West Yorkshire",
    "sg:tags":[
        "consultant"
    ],
    "wof:name":"A S C Employment & Training Group",
    "wof:placetype":"venue"
},
  "geometry": {"coordinates":[-1.7538830042,53.7965660095],"type":"Point"}
}