{
  "type": "Feature",
  "properties": {
    "addr:full":"18-20 Dawlish Rd Birmingham West Midlands B29 7AE",
    "addr:housenumber":"18-20",
    "addr:postcode":"b29 7ae",
    "addr:street":"Dawlish Rd",
    "iso:country":"GB",
    "sg:address":"18-20 Dawlish Rd",
    "sg:city":"Birmingham",
    "sg:classifiers":[
        {
            "category":"Shopping",
            "subcategory":"Catalog Store",
            "type":"Retail Goods"
        }
    ],
    "sg:phone":"+44 121 471 3322",
    "sg:postcode":"B29 7AE",
    "sg:province":"West Midlands",
    "sg:tags":[
        "catalogue",
        "showroom"
    ],
    "wof:name":"Bbs Superstores",
    "wof:placetype":"venue"
},
  "geometry": {"coordinates":[-1.93006,52.441734],"type":"Point"}
}