{
  "type": "Feature",
  "properties": {
    "iso:country":"GB",
    "sg:address":"Windmill Farm Workshop, Rolvenden",
    "sg:city":"Cranbrook",
    "sg:classifiers":[
        {
            "category":"Building & Trades",
            "subcategory":"Construction",
            "type":"Services"
        }
    ],
    "sg:phone":"+44 1580 243161",
    "sg:postcode":"TN17 4PS",
    "sg:province":"Kent",
    "sg:tags":[
        "welder"
    ],
    "wof:name":"M Reeve",
    "wof:placetype":"venue"
},
  "geometry": {"coordinates":[0.629959,51.052315],"type":"Point"}
}