{
  "type": "Feature",
  "properties": {
    "addr:full":"C/o Kidsons Impey, Elgar House Hereford Herefordshire HR4 9SF",
    "addr:postcode":"hr4 9sf",
    "addr:street":"C",
    "iso:country":"GB",
    "sg:address":"C/o Kidsons Impey, Elgar House",
    "sg:city":"Hereford",
    "sg:classifiers":[
        {
            "category":"Professional",
            "subcategory":"Engineering",
            "type":"Services"
        }
    ],
    "sg:phone":"+44 7966 424131",
    "sg:postcode":"HR4 9SF",
    "sg:province":"Herefordshire",
    "sg:tags":[
        "contractor",
        "electrical",
        "engineer"
    ],
    "wof:name":"Lee Electrical Services Ltd.",
    "wof:placetype":"venue"
},
  "geometry": {"coordinates":[-2.7317609787,52.0592041016],"type":"Point"}
}