{
  "type": "Feature",
  "properties": {
    "addr:full":"20 Arden Road Birmingham West Midlands B45 0JA",
    "addr:housenumber":"20",
    "addr:postcode":"b45 0ja",
    "addr:street":"Arden Road",
    "iso:country":"GB",
    "sg:address":"20 Arden Road",
    "sg:city":"Birmingham",
    "sg:classifiers":[
        {
            "category":"Professional",
            "subcategory":"Accounting & Tax Preparation",
            "type":"Services"
        }
    ],
    "sg:phone":"+44 121 687 7000",
    "sg:postcode":"B45 0JA",
    "sg:province":"West Midlands",
    "sg:tags":[
        "accountant"
    ],
    "wof:name":"Omco Frankley Ltd.",
    "wof:placetype":"venue"
},
  "geometry": {"coordinates":[-2.015288,52.403294],"type":"Point"}
}