{
  "type": "Feature",
  "properties": {
    "addr:full":"2 Market Square Luton Bedfordshire LU1 5RD",
    "addr:housenumber":"2",
    "addr:postcode":"lu1 5rd",
    "addr:street":"Market Square",
    "iso:country":"GB",
    "sg:address":"2 Market Square",
    "sg:city":"Luton",
    "sg:classifiers":[
        {
            "category":"Shopping",
            "subcategory":"News",
            "type":"Retail Goods"
        }
    ],
    "sg:phone":"+44 1582 726352",
    "sg:postcode":"LU1 5RD",
    "sg:province":"Bedfordshire",
    "sg:tags":[
        "newsagent"
    ],
    "wof:name":"Barretts",
    "wof:placetype":"venue"
},
  "geometry": {"coordinates":[-0.4369609952,51.8758964539],"type":"Point"}
}