{
  "type": "Feature",
  "properties": {
    "addr:full":"107 London Road Sevenoaks Kent TN13 1BH",
    "addr:housenumber":"107",
    "addr:postcode":"tn13 1bh",
    "addr:street":"London Road",
    "iso:country":"GB",
    "sg:address":"107 London Road",
    "sg:city":"Sevenoaks",
    "sg:classifiers":[
        {
            "category":"Restaurant",
            "type":"Food & Drink"
        }
    ],
    "sg:phone":"+44 1732 741043",
    "sg:postcode":"TN13 1BH",
    "sg:province":"Kent",
    "sg:tags":[
        "indian"
    ],
    "wof:name":"The Asia Cuisine Tandoori Restaurant",
    "wof:placetype":"venue"
},
  "geometry": {"coordinates":[0.18935,51.273544],"type":"Point"}
}