{
  "type": "Feature",
  "properties": {
    "addr:full":"Old Mill Service Station, Rochdale Road Oldham Lancashire OL1 2HD",
    "addr:postcode":"ol1 2hd",
    "addr:street":"Rochdale Road",
    "iso:country":"GB",
    "sg:address":"Old Mill Service Station, Rochdale Road",
    "sg:city":"Oldham",
    "sg:classifiers":[
        {
            "category":"Retail",
            "subcategory":"Auto Repair",
            "type":"Services"
        }
    ],
    "sg:phone":"+44 161 633 6190",
    "sg:postcode":"OL1 2HD",
    "sg:province":"Lancashire",
    "sg:tags":[
        "modification",
        "garage"
    ],
    "wof:name":"Oldham Reliant",
    "wof:placetype":"venue"
},
  "geometry": {"coordinates":[-2.1123290062,53.540309906],"type":"Point"}
}