{
  "type": "Feature",
  "properties": {
    "addr:full":"The Square Buxton Derbyshire SK17 6AZ",
    "addr:postcode":"sk17 6az",
    "addr:street":"The Square",
    "iso:country":"GB",
    "sg:address":"The Square",
    "sg:city":"Buxton",
    "sg:classifiers":[
        {
            "category":"Travel",
            "subcategory":"Hotels & Motels",
            "type":"Entertainment"
        }
    ],
    "sg:phone":"+44 1298 24711",
    "sg:postcode":"SK17 6AZ",
    "sg:province":"Derbyshire",
    "wof:name":"The George",
    "wof:placetype":"venue"
},
  "geometry": {"coordinates":[-1.9157660007,53.2582168579],"type":"Point"}
}