{
  "type": "Feature",
  "properties": {
    "iso:country":"GB",
    "sg:address":"Centre For Community Health, Frank Street, Highgate",
    "sg:city":"Birmingham",
    "sg:classifiers":[
        {
            "category":"Social Services",
            "type":"Services"
        }
    ],
    "sg:phone":"+44 121 446 1010",
    "sg:postcode":"B12 0YA",
    "sg:province":"West Midlands",
    "sg:tags":[
        "health",
        "authority"
    ],
    "wof:name":"Southern Birmingham Community Health N H S Trust",
    "wof:placetype":"venue"
},
  "geometry": {"coordinates":[-1.908604,52.478596],"type":"Point"}
}