{
  "type": "Feature",
  "properties": {
    "iso:country":"GB",
    "sg:address":"Hopton Farm, Little Cressingham",
    "sg:city":"Thetford",
    "sg:classifiers":[
        {
            "category":"Farming",
            "subcategory":"Livestock Farm",
            "type":"Manufacturing & Wholesale Goods"
        },
        {
            "category":"Shopping",
            "type":"Retail Goods"
        }
    ],
    "sg:postcode":"IP25 6NX",
    "sg:province":"Norfolk",
    "sg:tags":[
        "merchant",
        "others"
    ],
    "wof:name":"Trevor C Cobbold (Agricultural) Ltd.",
    "wof:placetype":"venue"
},
  "geometry": {"coordinates":[0.7644129992,52.5649795532],"type":"Point"}
}