{
  "type": "Feature",
  "properties": {
    "addr:full":"32 Queens Road Brighton East Sussex BN1 3YE",
    "addr:housenumber":"32",
    "addr:postcode":"bn1 3ye",
    "addr:street":"Queens Road",
    "iso:country":"GB",
    "sg:address":"32 Queens Road",
    "sg:city":"Brighton",
    "sg:classifiers":[
        {
            "category":"Real Estate",
            "subcategory":"Real Estate Agent",
            "type":"Services"
        }
    ],
    "sg:phone":"+44 1273 326171",
    "sg:postcode":"BN1 3YE",
    "sg:province":"East Sussex",
    "wof:name":"Parsons Son & Basley",
    "wof:placetype":"venue"
},
  "geometry": {"coordinates":[-0.141869,50.827183],"type":"Point"}
}