{
  "type": "Feature",
  "properties": {
    "addr:full":"Appleton Village Widnes Cheshire WA8 6EQ",
    "addr:postcode":"wa8 6eq",
    "iso:country":"GB",
    "sg:address":"Appleton Village",
    "sg:city":"Widnes",
    "sg:classifiers":[
        {
            "category":"Organizations",
            "subcategory":"Membership Organization",
            "type":"Services"
        }
    ],
    "sg:phone":"+44 151 424 3657",
    "sg:postcode":"WA8 6EQ",
    "sg:province":"Cheshire",
    "sg:tags":[
        "club"
    ],
    "wof:name":"The Village Social Club",
    "wof:placetype":"venue"
},
  "geometry": {"coordinates":[-2.7322840691,53.3718566895],"type":"Point"}
}