{
  "type": "Feature",
  "properties": {
    "addr:full":"5 Coxheath Road, Crookham Fleet Hampshire GU51 5QH",
    "addr:housenumber":"5",
    "addr:postcode":"gu51 5qh",
    "addr:street":"Coxheath Road",
    "iso:country":"GB",
    "sg:address":"5 Coxheath Road, Crookham",
    "sg:city":"Fleet",
    "sg:classifiers":[
        {
            "category":"Retail",
            "subcategory":"Auto Repair",
            "type":"Services"
        }
    ],
    "sg:phone":"+44 1252 616551",
    "sg:postcode":"GU51 5QH",
    "sg:province":"Hampshire",
    "sg:tags":[
        "modification",
        "car",
        "vehicle",
        "commercial",
        "garage"
    ],
    "wof:name":"Fleet Automotive Ltd.",
    "wof:placetype":"venue"
},
  "geometry": {"coordinates":[-0.8509579897,51.2671165466],"type":"Point"}
}