{
  "type": "Feature",
  "properties": {
    "iso:country":"GB",
    "sg:address":"Ideford Combe",
    "sg:city":"Newton Abbot",
    "sg:classifiers":[
        {
            "category":"Home & Garden",
            "subcategory":"Garden Supply",
            "type":"Retail Goods"
        }
    ],
    "sg:phone":"+44 1626 354567",
    "sg:postcode":"TQ12 3GR",
    "sg:province":"Devon",
    "sg:tags":[
        "nursery",
        "centre"
    ],
    "wof:name":"Briartor Nurseries",
    "wof:placetype":"venue"
},
  "geometry": {"coordinates":[-3.59495,50.568901],"type":"Point"}
}