{
  "type": "Feature",
  "properties": {
    "iso:country":"GB",
    "sg:address":"The Furze, Dunt Avenue, Hurst",
    "sg:city":"Reading",
    "sg:classifiers":[
        {
            "category":"Professional",
            "subcategory":"Printing & Photocopies",
            "type":"Services"
        }
    ],
    "sg:phone":"+44 118 934 1548",
    "sg:postcode":"RG10 0SY",
    "sg:province":"Berkshire",
    "sg:tags":[
        "printer"
    ],
    "wof:name":"918 Cutting House",
    "wof:placetype":"venue"
},
  "geometry": {"coordinates":[-0.8528860211,51.4585494995],"type":"Point"}
}