{
  "type": "Feature",
  "properties": {
    "addr:full":"15 Trelawney Gardens, Pensilva Liskeard Cornwall PL14 5PL",
    "addr:housenumber":"15",
    "addr:postcode":"pl14 5pl",
    "addr:street":"Trelawney Gardens",
    "iso:country":"GB",
    "sg:address":"15 Trelawney Gardens, Pensilva",
    "sg:city":"Liskeard",
    "sg:classifiers":[
        {
            "category":"Taxi",
            "type":"Transportation"
        }
    ],
    "sg:phone":"+44 1579 363739",
    "sg:postcode":"PL14 5PL",
    "sg:province":"Cornwall",
    "sg:tags":[
        "mini",
        "cab"
    ],
    "wof:name":"Pensilva Taxis",
    "wof:placetype":"venue"
},
  "geometry": {"coordinates":[-4.422378,50.502342],"type":"Point"}
}