{
  "type": "Feature",
  "properties": {
    "iso:country":"GB",
    "sg:address":"159 Lee Rd",
    "sg:city":"Blackheath",
    "sg:classifiers":[
        {
            "category":"Bars & Pubs",
            "type":"Food & Drink"
        }
    ],
    "sg:phone":"+44 20 8318 1879",
    "sg:postcode":"SE3 9DJ",
    "sg:province":"Greater London",
    "sg:tags":[
        "pubs",
        "inn"
    ],
    "wof:name":"New Tigers Head",
    "wof:placetype":"venue"
},
  "geometry": {"coordinates":[0.008444,51.463715],"type":"Point"}
}