{
  "type": "Feature",
  "properties": {
    "iso:country":"GB",
    "sg:address":"12 Upper Gough Street",
    "sg:city":"Birmingham",
    "sg:classifiers":[
        {
            "category":"Professional",
            "subcategory":"Engineering",
            "type":"Services"
        }
    ],
    "sg:phone":"+44 121 643 1922",
    "sg:postcode":"B1 1JG",
    "sg:province":"West Midlands",
    "sg:tags":[
        "precision",
        "engineer"
    ],
    "wof:name":"Watson Engineering",
    "wof:placetype":"venue"
},
  "geometry": {"coordinates":[-1.9042110443,52.4748497009],"type":"Point"}
}