{
  "type": "Feature",
  "properties": {
    "addr:full":"43a Brown Street Manchester Greater Manchester M2 2JJ",
    "addr:housenumber":"43a",
    "addr:postcode":"m2 2jj",
    "addr:street":"Brown Street",
    "iso:country":"GB",
    "sg:address":"43a Brown Street",
    "sg:city":"Manchester",
    "sg:classifiers":[
        {
            "category":"Restaurant",
            "type":"Food & Drink"
        },
        {
            "category":"Food & Beverages",
            "subcategory":"Bakery",
            "type":"Retail Goods"
        }
    ],
    "sg:phone":"+44 161 834 2670",
    "sg:postcode":"M2 2JJ",
    "sg:province":"Greater Manchester",
    "sg:tags":[
        "-",
        "pizza"
    ],
    "wof:name":"ABRAHAM MACADAM",
    "wof:placetype":"venue"
},
  "geometry": {"coordinates":[-2.2424030304,53.4806213379],"type":"Point"}
}