{
  "type": "Feature",
  "properties": {
    "iso:country":"GB",
    "sg:address":"Thistledene Avenue",
    "sg:city":"Romford",
    "sg:classifiers":[
        {
            "category":"Education",
            "subcategory":"School",
            "type":"Public Place"
        }
    ],
    "sg:phone":"+44 1708 743000",
    "sg:postcode":"RM5 2TX",
    "sg:province":"Essex",
    "sg:tags":[
        "local",
        "authority"
    ],
    "wof:name":"Pinewood Primary School",
    "wof:placetype":"venue"
},
  "geometry": {"coordinates":[0.1616899967,51.6106758118],"type":"Point"}
}