{
  "type": "Feature",
  "properties": {
    "iso:country":"GB",
    "sg:address":"Cyril Noall Square, Fore Street",
    "sg:city":"St Ives",
    "sg:classifiers":[
        {
            "category":"Shopping",
            "subcategory":"Gifts & Souvenirs",
            "type":"Retail Goods"
        }
    ],
    "sg:phone":"+44 1736 798809",
    "sg:postcode":"TR26 1HE",
    "sg:province":"Cornwall",
    "sg:tags":[
        "shop"
    ],
    "wof:name":"Courtyard Collectables",
    "wof:placetype":"venue"
},
  "geometry": {"coordinates":[-5.48574,50.210361],"type":"Point"}
}