{
  "type": "Feature",
  "properties": {
    "iso:country":"GB",
    "sg:address":"162 Tomswood Hill",
    "sg:city":"Ilford",
    "sg:classifiers":[
        {
            "category":"Health Services",
            "subcategory":"Medical Lab",
            "type":"Services"
        }
    ],
    "sg:phone":"+44 20 8559 8612",
    "sg:postcode":"IG6 2QP",
    "sg:province":"Essex",
    "sg:tags":[
        "laboratory",
        "dental"
    ],
    "wof:name":"G S V Dental Laboratory",
    "wof:placetype":"venue"
},
  "geometry": {"coordinates":[0.077327,51.600555],"type":"Point"}
}