{
  "type": "Feature",
  "properties": {
    "iso:country":"GB",
    "sg:address":"Banks Rd",
    "sg:city":"Darlington",
    "sg:classifiers":[
        {
            "category":"Wholesale",
            "subcategory":"Non-durable Goods",
            "type":"Manufacturing & Wholesale Goods"
        }
    ],
    "sg:phone":"+44 1325 468438",
    "sg:postcode":"DL1 1YB",
    "sg:province":"Durham",
    "sg:tags":[
        "carry",
        "cash"
    ],
    "wof:name":"Booker Cash & Carry",
    "wof:placetype":"venue"
},
  "geometry": {"coordinates":[-1.52462,54.528465],"type":"Point"}
}