{
  "type": "Feature",
  "properties": {
    "addr:full":"58 Conway Cres Greenford Greater London UB6 8JA",
    "addr:housenumber":"58",
    "addr:postcode":"ub6 8ja",
    "addr:street":"Conway Cres",
    "iso:country":"GB",
    "sg:address":"58 Conway Cres",
    "sg:city":"Greenford",
    "sg:classifiers":[
        {
            "category":"Professional",
            "subcategory":"Art Services",
            "type":"Services"
        }
    ],
    "sg:postcode":"UB6 8JA",
    "sg:province":"Greater London",
    "sg:tags":[
        "photographer"
    ],
    "wof:name":"Taylor,Christine,",
    "wof:placetype":"venue"
},
  "geometry": {"coordinates":[-0.3362759948,51.5355377197],"type":"Point"}
}