{
  "type": "Feature",
  "properties": {
    "iso:country":"GB",
    "sg:address":"50 Viaduct Rd",
    "sg:city":"Chelmsford",
    "sg:classifiers":[
        {
            "category":"Organizations",
            "subcategory":"Membership Organization",
            "type":"Services"
        }
    ],
    "sg:phone":"+44 1245 352752",
    "sg:postcode":"CM1 1TS",
    "sg:province":"Essex",
    "sg:tags":[
        "club"
    ],
    "wof:name":"Railway Club",
    "wof:placetype":"venue"
},
  "geometry": {"coordinates":[0.466038,51.735012],"type":"Point"}
}