{
  "type": "Feature",
  "properties": {
    "iso:country":"GB",
    "sg:address":"Market Street, Winterton",
    "sg:city":"Scunthorpe",
    "sg:classifiers":[
        {
            "category":"Recreation",
            "subcategory":"Fishing",
            "type":"Entertainment"
        }
    ],
    "sg:phone":"+44 1724 734810",
    "sg:postcode":"DN15 9PT",
    "sg:province":"Lincolnshire",
    "sg:tags":[
        "angling"
    ],
    "wof:name":"Market Hill Fisheries",
    "wof:placetype":"venue"
},
  "geometry": {"coordinates":[-0.601383,53.655563],"type":"Point"}
}