{
  "type": "Feature",
  "properties": {
    "iso:country":"GB",
    "sg:address":"100 London Rd",
    "sg:city":"Bognor Regis",
    "sg:classifiers":[
        {
            "category":"Shopping",
            "subcategory":"Discount & Variety Stores",
            "type":"Retail Goods"
        },
        {
            "category":"Building & Trades",
            "subcategory":"Construction",
            "type":"Services"
        }
    ],
    "sg:phone":"+44 1243 842424",
    "sg:postcode":"PO21 1DD",
    "sg:province":"West Sussex",
    "sg:tags":[
        "shop",
        "paint",
        "model",
        "household",
        "spraying"
    ],
    "wof:name":"Squires Model And Craft Tools",
    "wof:placetype":"venue"
},
  "geometry": {"coordinates":[-0.673857,50.787338],"type":"Point"}
}