{
  "type": "Feature",
  "properties": {
    "iso:country":"GB",
    "sg:address":"52-54 Kempock Street",
    "sg:city":"Gourock",
    "sg:classifiers":[
        {
            "category":"Building & Trades",
            "subcategory":"Construction",
            "type":"Services"
        }
    ],
    "sg:phone":"+44 1475 637032",
    "sg:postcode":"PA19 1ND",
    "sg:province":"Inverclyde",
    "sg:tags":[
        "joiner",
        "carpenter"
    ],
    "wof:name":"Beech Construction",
    "wof:placetype":"venue"
},
  "geometry": {"coordinates":[-4.820249,55.961937],"type":"Point"}
}