{
  "type": "Feature",
  "properties": {
    "iso:country":"GB",
    "sg:address":"Elmtree Farm, Washmere Grn, Great Waldingfield",
    "sg:city":"Sudbury",
    "sg:classifiers":[
        {
            "category":"Farming",
            "subcategory":"Livestock Farm",
            "type":"Manufacturing & Wholesale Goods"
        }
    ],
    "sg:phone":"+44 1787 247292",
    "sg:postcode":"CO10 0TE",
    "sg:province":"Essex",
    "sg:tags":[
        "others"
    ],
    "wof:name":"P D H Services",
    "wof:placetype":"venue"
},
  "geometry": {"coordinates":[0.7753300071,52.0577049255],"type":"Point"}
}