{
  "type": "Feature",
  "properties": {
    "iso:country":"GB",
    "sg:address":"70 Gloucester Pl",
    "sg:city":"London",
    "sg:classifiers":[
        {
            "category":"Real Estate",
            "subcategory":"Developer",
            "type":"Services"
        }
    ],
    "sg:postcode":"W1U 8HW",
    "sg:province":"Greater London",
    "sg:tags":[
        "property"
    ],
    "wof:name":"Cavfield Ltd",
    "wof:placetype":"venue"
},
  "geometry": {"coordinates":[-0.1581559926,51.5189666748],"type":"Point"}
}