{
  "type": "Feature",
  "properties": {
    "iso:country":"GB",
    "sg:address":"41 The Broadway",
    "sg:city":"Herne Bay",
    "sg:classifiers":[
        {
            "category":"Personal",
            "subcategory":"Beauty Salon",
            "type":"Services"
        }
    ],
    "sg:phone":"+44 1227 375179",
    "sg:postcode":"CT6 8SL",
    "sg:province":"Kent",
    "sg:tags":[
        "unisex",
        "ladies",
        "lady",
        "hairdresser"
    ],
    "wof:name":"Nicky's Hair Fashions",
    "wof:placetype":"venue"
},
  "geometry": {"coordinates":[1.112941,51.370693],"type":"Point"}
}