{
  "type": "Feature",
  "properties": {
    "iso:country":"GB",
    "sg:address":"Wilden Works, Wilden La",
    "sg:city":"Stourport On Severn",
    "sg:classifiers":[
        {
            "category":"Freight",
            "type":"Transportation"
        }
    ],
    "sg:phone":"+44 1299 825446",
    "sg:postcode":"DY13 9GP",
    "sg:province":"Worcestershire",
    "sg:tags":[
        "haulage",
        "road"
    ],
    "wof:name":"W M Sargeant",
    "wof:placetype":"venue"
},
  "geometry": {"coordinates":[-2.281167,52.338997],"type":"Point"}
}