{
  "type": "Feature",
  "properties": {
    "iso:country":"GB",
    "sg:address":"13 Kynaston Road",
    "sg:city":"Bromley",
    "sg:classifiers":[
        {
            "category":"Professional",
            "subcategory":"Engineering",
            "type":"Services"
        }
    ],
    "sg:phone":"+44 20 8851 8079",
    "sg:postcode":"BR1 5AN",
    "sg:province":"Kent",
    "sg:tags":[
        "contractor",
        "electrical",
        "engineer"
    ],
    "wof:name":"R & D Electrics",
    "wof:placetype":"venue"
},
  "geometry": {"coordinates":[0.019051,51.422844],"type":"Point"}
}