{
  "type": "Feature",
  "properties": {
    "iso:country":"GB",
    "sg:address":"Dewsbury District Hospital, Halifax Rd",
    "sg:city":"Dewsbury",
    "sg:classifiers":[
        {
            "category":"Health Services",
            "subcategory":"Hospital",
            "type":"Services"
        },
        {
            "category":"Health Services",
            "subcategory":"Health Practitioner",
            "type":"Services"
        }
    ],
    "sg:phone":"+44 1924 512000",
    "sg:postcode":"WF13 4HS",
    "sg:province":"West Yorkshire",
    "sg:tags":[
        "therapist",
        "speech"
    ],
    "wof:name":"Dewsbury Health Care Nhs Trust",
    "wof:placetype":"venue"
},
  "geometry": {"coordinates":[-1.631339,53.693256],"type":"Point"}
}