{
  "type": "Feature",
  "properties": {
    "addr:full":"6-7 Headley Road, Grayshott Hindhead Hampshire GU26 6LE",
    "addr:housenumber":"6-7",
    "addr:postcode":"gu26 6le",
    "addr:street":"Headley Road",
    "iso:country":"GB",
    "sg:address":"6-7 Headley Road, Grayshott",
    "sg:city":"Hindhead",
    "sg:classifiers":[
        {
            "category":"Fast Food",
            "type":"Food & Drink"
        }
    ],
    "sg:phone":"+44 1428 605885",
    "sg:postcode":"GU26 6LE",
    "sg:province":"Hampshire",
    "sg:tags":[
        "away",
        "take"
    ],
    "wof:name":"Rainbow Chinese Takeaway",
    "wof:placetype":"venue"
},
  "geometry": {"coordinates":[-0.7533739805,51.1105003357],"type":"Point"}
}