{
  "type": "Feature",
  "properties": {
    "iso:country":"GB",
    "sg:address":"11 Maitland Road",
    "sg:city":"Reading",
    "sg:classifiers":[
        {
            "category":"Social Services",
            "subcategory":"Retirement Home",
            "type":"Services"
        }
    ],
    "sg:phone":"+44 118 957 2826",
    "sg:postcode":"RG1 6NL",
    "sg:province":"Berkshire",
    "sg:tags":[
        "residential",
        "care"
    ],
    "wof:name":"Abbeyfield Reading Society",
    "wof:placetype":"venue"
},
  "geometry": {"coordinates":[-0.9870409966,51.4519233704],"type":"Point"}
}