{
  "type": "Feature",
  "properties": {
    "iso:country":"GB",
    "sg:address":"41a High Street",
    "sg:city":"Weybridge",
    "sg:classifiers":[
        {
            "category":"Real Estate",
            "subcategory":"Real Estate Agent",
            "type":"Services"
        }
    ],
    "sg:phone":"+44 1932 820222",
    "sg:postcode":"KT13 8BB",
    "sg:province":"Surrey",
    "wof:name":"Pennytek Ltd.",
    "wof:placetype":"venue"
},
  "geometry": {"coordinates":[-0.456662,51.373329],"type":"Point"}
}