{
  "type": "Feature",
  "properties": {
    "addr:full":"57 Denmark Hill London Greater London SE5 8RS",
    "addr:housenumber":"57",
    "addr:postcode":"se5 8rs",
    "addr:street":"Denmark Hill",
    "iso:country":"GB",
    "sg:address":"57 Denmark Hill",
    "sg:city":"London",
    "sg:classifiers":[
        {
            "category":"Food & Beverages",
            "subcategory":"Bakery",
            "type":"Retail Goods"
        }
    ],
    "sg:phone":"+44 20 7277 0674",
    "sg:postcode":"SE5 8RS",
    "sg:province":"Greater London",
    "sg:tags":[
        "pizza"
    ],
    "wof:name":"Pizza Hut",
    "wof:placetype":"venue"
},
  "geometry": {"coordinates":[-0.092798,51.471874],"type":"Point"}
}