{
  "type": "Feature",
  "properties": {
    "iso:country":"GB",
    "sg:address":"1 Bridge House, North Road",
    "sg:city":"Durham",
    "sg:classifiers":[
        {
            "category":"Professional",
            "subcategory":"Art Services",
            "type":"Services"
        }
    ],
    "sg:phone":"+44 191 386 0956",
    "sg:postcode":"DH1 4PW",
    "sg:province":"Durham",
    "sg:tags":[
        "photographer"
    ],
    "wof:name":"Klick Photopoint",
    "wof:placetype":"venue"
},
  "geometry": {"coordinates":[-1.584265,54.778111],"type":"Point"}
}