{
  "type": "Feature",
  "properties": {
    "iso:country":"GB",
    "sg:address":"2 Anthony Court",
    "sg:city":"Stanley",
    "sg:classifiers":[
        {
            "category":"Building & Trades",
            "subcategory":"Construction",
            "type":"Services"
        }
    ],
    "sg:phone":"+44 1207 231008",
    "sg:postcode":"DH9 8AG",
    "sg:province":"Durham",
    "sg:tags":[
        "builder"
    ],
    "wof:name":"J Conroy",
    "wof:placetype":"venue"
},
  "geometry": {"coordinates":[-1.6991870403,54.8721427917],"type":"Point"}
}