{
  "type": "Feature",
  "properties": {
    "addr:full":"120 Ashburton Rd Newton Abbot Devon TQ12 1RJ",
    "addr:housenumber":"120",
    "addr:postcode":"tq12 1rj",
    "addr:street":"Ashburton Rd",
    "iso:country":"GB",
    "sg:address":"120 Ashburton Rd",
    "sg:city":"Newton Abbot",
    "sg:classifiers":[
        {
            "category":"Social Services",
            "subcategory":"Retirement Home",
            "type":"Services"
        }
    ],
    "sg:phone":"+44 1626 368070",
    "sg:postcode":"TQ12 1RJ",
    "sg:province":"Devon",
    "sg:tags":[
        "rest"
    ],
    "wof:name":"The Lindons",
    "wof:placetype":"venue"
},
  "geometry": {"coordinates":[-3.6359159946,50.5355072021],"type":"Point"}
}