{
  "type": "Feature",
  "properties": {
    "addr:full":"Western Heights Dover Kent CT17 9DF",
    "addr:postcode":"ct17 9df",
    "addr:street":"Western",
    "iso:country":"GB",
    "sg:address":"Western Heights",
    "sg:city":"Dover",
    "sg:classifiers":[
        {
            "category":"Freight",
            "type":"Transportation"
        }
    ],
    "sg:phone":"+44 1304 202266",
    "sg:postcode":"CT17 9DF",
    "sg:province":"Kent",
    "sg:tags":[
        "forwarders"
    ],
    "wof:name":"European Freight Services Ltd.",
    "wof:placetype":"venue"
},
  "geometry": {"coordinates":[1.3023300171,51.1198196411],"type":"Point"}
}