{
  "type": "Feature",
  "properties": {
    "iso:country":"GB",
    "sg:address":"44 Spital Street",
    "sg:city":"Dartford",
    "sg:classifiers":[
        {
            "category":"Real Estate",
            "subcategory":"Real Estate Agent",
            "type":"Services"
        }
    ],
    "sg:phone":"+44 1322 228090",
    "sg:postcode":"DA1 2DT",
    "sg:province":"Kent",
    "wof:name":"Livermores the Estate Agents",
    "wof:placetype":"venue"
},
  "geometry": {"coordinates":[0.214314,51.444866],"type":"Point"}
}