{
  "type": "Feature",
  "properties": {
    "addr:full":"161 Bedford Street North Leicester Leicestershire LE1 3JQ",
    "addr:housenumber":"161",
    "addr:postcode":"le1 3jq",
    "addr:street":"Bedford Street North",
    "iso:country":"GB",
    "sg:address":"161 Bedford Street North",
    "sg:city":"Leicester",
    "sg:classifiers":[
        {
            "category":"Fast Food",
            "type":"Food & Drink"
        }
    ],
    "sg:phone":"+44 116 253 7332",
    "sg:postcode":"LE1 3JQ",
    "sg:province":"Leicestershire",
    "sg:tags":[
        "away",
        "take"
    ],
    "wof:name":"Tasty Snax",
    "wof:placetype":"venue"
},
  "geometry": {"coordinates":[-1.126773,52.641823],"type":"Point"}
}