{
  "type": "Feature",
  "properties": {
    "iso:country":"GB",
    "sg:address":"Matford Lane",
    "sg:city":"Exeter",
    "sg:classifiers":[
        {
            "category":"Organizations",
            "subcategory":"Membership Organization",
            "type":"Services"
        }
    ],
    "sg:phone":"+44 1392 383335",
    "sg:postcode":"EX2 4PS",
    "sg:province":"Devon",
    "sg:tags":[
        "club"
    ],
    "wof:name":"Coaver Club",
    "wof:placetype":"venue"
},
  "geometry": {"coordinates":[-3.518217,50.717583],"type":"Point"}
}