{
  "type": "Feature",
  "properties": {
    "iso:country":"GB",
    "sg:address":"Unit D, Stephenson Road",
    "sg:city":"Swindon",
    "sg:classifiers":[
        {
            "category":"Shopping",
            "subcategory":"Florist",
            "type":"Retail Goods"
        }
    ],
    "sg:postcode":"SN25 5AX",
    "sg:province":"Wiltshire",
    "wof:name":"Blackwell Bros (International Plants) Ltd.",
    "wof:placetype":"venue"
},
  "geometry": {"coordinates":[-1.776728,51.599728],"type":"Point"}
}