{
  "type": "Feature",
  "properties": {
    "addr:full":"High St, Earls Barton Northampton Northamptonshire NN6 0JG",
    "addr:postcode":"nn6 0jg",
    "addr:street":"High St",
    "iso:country":"GB",
    "sg:address":"High St, Earls Barton",
    "sg:city":"Northampton",
    "sg:classifiers":[
        {
            "category":"Bars & Pubs",
            "type":"Food & Drink"
        }
    ],
    "sg:phone":"+44 1604 810520",
    "sg:postcode":"NN6 0JG",
    "sg:province":"Northamptonshire",
    "sg:tags":[
        "pubs",
        "inn"
    ],
    "wof:name":"The Stags Head",
    "wof:placetype":"venue"
},
  "geometry": {"coordinates":[-0.7520880103,52.2658538818],"type":"Point"}
}