{
  "type": "Feature",
  "properties": {
    "addr:full":"Tree Farm, Cooks Drove, West Row Bury St Edmunds Cambridgeshire IP28 8QN",
    "addr:postcode":"ip28 8qn",
    "addr:street":"Cooks Drove West Row;St",
    "iso:country":"GB",
    "sg:address":"Tree Farm, Cooks Drove, West Row",
    "sg:city":"Bury St Edmunds",
    "sg:classifiers":[
        {
            "category":"Farming",
            "subcategory":"Livestock Farm",
            "type":"Manufacturing & Wholesale Goods"
        },
        {
            "category":"Farming",
            "subcategory":"Farm",
            "type":"Manufacturing & Wholesale Goods"
        }
    ],
    "sg:phone":"+44 1638 715201",
    "sg:postcode":"IP28 8QN",
    "sg:province":"Cambridgeshire",
    "sg:tags":[
        "mixed",
        "others"
    ],
    "wof:name":"W F & J N THOROGOOD",
    "wof:placetype":"venue"
},
  "geometry": {"coordinates":[0.41854,52.376701],"type":"Point"}
}