{
  "type": "Feature",
  "properties": {
    "iso:country":"GB",
    "sg:address":"Barling Road, Barling Magna",
    "sg:city":"Southend-on-sea",
    "sg:classifiers":[
        {
            "category":"Building & Trades",
            "subcategory":"Construction",
            "type":"Services"
        }
    ],
    "sg:phone":"+44 1702 218661",
    "sg:postcode":"SS3 0ND",
    "sg:province":"Essex",
    "sg:tags":[
        "builder"
    ],
    "wof:name":"Belhan Construction Co. Ltd.",
    "wof:placetype":"venue"
},
  "geometry": {"coordinates":[0.75837,51.554592],"type":"Point"}
}