{
  "type": "Feature",
  "properties": {
    "addr:full":"18 Empire House, Thurloe Place London Greater London SW7 2RU",
    "addr:housenumber":"18",
    "addr:postcode":"sw7 2ru",
    "addr:street":"Empire;Thurloe Place",
    "iso:country":"GB",
    "sg:address":"18 Empire House, Thurloe Place",
    "sg:city":"London",
    "sg:classifiers":[
        {
            "category":"Social Services",
            "subcategory":"Adult Care",
            "type":"Services"
        }
    ],
    "sg:postcode":"SW7 2RU",
    "sg:province":"Greater London",
    "sg:tags":[
        "domestic",
        "cleaning"
    ],
    "wof:name":"Scrubbers the Original",
    "wof:placetype":"venue"
},
  "geometry": {"coordinates":[-0.1696999967,51.4960708618],"type":"Point"}
}