{
  "type": "Feature",
  "properties": {
    "iso:country":"GB",
    "sg:address":"Gales Garage, Aldermaston Rd",
    "sg:city":"Basingstoke",
    "sg:classifiers":[
        {
            "category":"Autos & Motor Vehicles",
            "subcategory":"Automobile Sales",
            "type":"Retail Goods"
        }
    ],
    "sg:phone":"+44 7956 893467",
    "sg:postcode":"RG24 9JY",
    "sg:province":"Hampshire",
    "sg:tags":[
        "car"
    ],
    "wof:name":"Tim Wood Cars",
    "wof:placetype":"venue"
},
  "geometry": {"coordinates":[-1.1133090258,51.2855911255],"type":"Point"}
}