{
  "type": "Feature",
  "properties": {
    "addr:full":"18 Stanley Street Blyth Northumberland NE24 2BU",
    "addr:housenumber":"18",
    "addr:postcode":"ne24 2bu",
    "addr:street":"Stanley Street;Northumberland",
    "iso:country":"GB",
    "sg:address":"18 Stanley Street",
    "sg:city":"Blyth",
    "sg:classifiers":[
        {
            "category":"Professional",
            "subcategory":"Advertising",
            "type":"Services"
        }
    ],
    "sg:phone":"+44 1670 364422",
    "sg:postcode":"NE24 2BU",
    "sg:province":"Northumberland",
    "sg:tags":[
        "agency"
    ],
    "wof:name":"Med-E-Man Ltd.",
    "wof:placetype":"venue"
},
  "geometry": {"coordinates":[-1.5061089993,55.1267814636],"type":"Point"}
}