{
  "type": "Feature",
  "properties": {
    "addr:full":"Benson Wallingford Oxfordshire OX10 6PP",
    "addr:postcode":"ox10 6pp",
    "iso:country":"GB",
    "sg:address":"Benson",
    "sg:city":"Wallingford",
    "sg:classifiers":[
        {
            "category":"Transit Center",
            "subcategory":"Passenger",
            "type":"Transportation"
        }
    ],
    "sg:phone":"+44 1491 836103",
    "sg:postcode":"OX10 6PP",
    "sg:province":"Oxfordshire",
    "sg:tags":[
        "boarding",
        "kennel",
        "catteries"
    ],
    "wof:name":"Avalon Kennels",
    "wof:placetype":"venue"
},
  "geometry": {"coordinates":[-1.1036390066,51.6116447449],"type":"Point"}
}