{
  "type": "Feature",
  "properties": {
    "addr:full":"20 High Street Bideford Devon EX39 2AA",
    "addr:housenumber":"20",
    "addr:postcode":"ex39 2aa",
    "addr:street":"High Street",
    "iso:country":"GB",
    "sg:address":"20 High Street",
    "sg:city":"Bideford",
    "sg:classifiers":[
        {
            "category":"Home & Garden",
            "subcategory":"Carpets & Floor Coverings",
            "type":"Retail Goods"
        }
    ],
    "sg:phone":"+44 1237 475626",
    "sg:postcode":"EX39 2AA",
    "sg:province":"Devon",
    "sg:tags":[
        "carpets",
        "rug",
        "matting"
    ],
    "wof:name":"Brian Littlejohns Carpets",
    "wof:placetype":"venue"
},
  "geometry": {"coordinates":[-4.2069530487,51.0177230835],"type":"Point"}
}