{
  "type": "Feature",
  "properties": {
    "addr:full":"46-50 Winterstoke Road Bristol City of Bristol BS3 2NW",
    "addr:housenumber":"46-50",
    "addr:postcode":"bs3 2nw",
    "addr:street":"Winterstoke Road",
    "iso:country":"GB",
    "sg:address":"46-50 Winterstoke Road",
    "sg:city":"Bristol",
    "sg:classifiers":[
        {
            "category":"Retail",
            "subcategory":"Auto Repair",
            "type":"Services"
        }
    ],
    "sg:phone":"+44 117 966 2211",
    "sg:postcode":"BS3 2NW",
    "sg:province":"City of Bristol",
    "sg:tags":[
        "body",
        "car"
    ],
    "wof:name":"Winterstoke Garage 95",
    "wof:placetype":"venue"
},
  "geometry": {"coordinates":[-2.6108589172,51.4332618713],"type":"Point"}
}