{
  "type": "Feature",
  "properties": {
    "addr:full":"227 Dunstall Rd Wolverhampton Shropshire WV6 0NZ",
    "addr:housenumber":"227",
    "addr:postcode":"wv6 0nz",
    "addr:street":"Dunstall Rd",
    "iso:country":"GB",
    "sg:address":"227 Dunstall Rd",
    "sg:city":"Wolverhampton",
    "sg:classifiers":[
        {
            "category":"Fast Food",
            "type":"Food & Drink"
        }
    ],
    "sg:phone":"+44 1902 422858",
    "sg:postcode":"WV6 0NZ",
    "sg:province":"Shropshire",
    "sg:tags":[
        "away",
        "take"
    ],
    "wof:name":"Dragon Palace",
    "wof:placetype":"venue"
},
  "geometry": {"coordinates":[-2.1406788826,52.6003494263],"type":"Point"}
}