{
  "type": "Feature",
  "properties": {
    "addr:full":"Station Road, Deganwy Conwy Conwy LL31 9DB",
    "addr:postcode":"ll31 9db",
    "addr:street":"Station Road",
    "iso:country":"GB",
    "sg:address":"Station Road, Deganwy",
    "sg:city":"Conwy",
    "sg:classifiers":[
        {
            "category":"Government",
            "subcategory":"Post Office",
            "type":"Public Place"
        }
    ],
    "sg:phone":"+44 1492 583215",
    "sg:postcode":"LL31 9DB",
    "sg:province":"Conwy",
    "wof:name":"P.O Deganwy",
    "wof:placetype":"venue"
},
  "geometry": {"coordinates":[-3.8358290195,53.2969818115],"type":"Point"}
}