{
  "type": "Feature",
  "properties": {
    "addr:full":"7 Queens Road Erith Kent DA8 1TW",
    "addr:housenumber":"7",
    "addr:postcode":"da8 1tw",
    "addr:street":"Queens Road",
    "iso:country":"GB",
    "sg:address":"7 Queens Road",
    "sg:city":"Erith",
    "sg:classifiers":[
        {
            "category":"Professional",
            "subcategory":"Employment Agencies",
            "type":"Services"
        }
    ],
    "sg:phone":"+44 1322 484600",
    "sg:postcode":"DA8 1TW",
    "sg:province":"Kent",
    "sg:tags":[
        "consultant"
    ],
    "wof:name":"Erith Job Centre",
    "wof:placetype":"venue"
},
  "geometry": {"coordinates":[0.180974,51.477364],"type":"Point"}
}