{
  "type": "Feature",
  "properties": {
    "iso:country":"GB",
    "sg:address":"6 Portland Rd, Langho",
    "sg:city":"Blackburn",
    "sg:classifiers":[
        {
            "category":"Building & Trades",
            "subcategory":"Plumbing",
            "type":"Services"
        }
    ],
    "sg:postcode":"BB6 8EL",
    "sg:province":"Lancashire",
    "sg:tags":[
        "heating"
    ],
    "wof:name":"Morris,P R,",
    "wof:placetype":"venue"
},
  "geometry": {"coordinates":[-2.452354,53.799797],"type":"Point"}
}