{
  "type": "Feature",
  "properties": {
    "addr:full":"Foster Wheeler Ho, Station Rd Reading Berkshire RG1 1LX",
    "addr:postcode":"rg1 1lx",
    "addr:street":"Station Rd",
    "iso:country":"GB",
    "sg:address":"Foster Wheeler Ho, Station Rd",
    "sg:city":"Reading",
    "sg:classifiers":[
        {
            "category":"Professional",
            "subcategory":"Engineering",
            "type":"Services"
        }
    ],
    "sg:phone":"+44 118 958 5211",
    "sg:postcode":"RG1 1LX",
    "sg:province":"Berkshire",
    "sg:tags":[
        "consulting",
        "engineer"
    ],
    "wof:name":"Foster Wheeler (Malysia) Sdn Bhd",
    "wof:placetype":"venue"
},
  "geometry": {"coordinates":[-0.963009,51.453522],"type":"Point"}
}