{
  "type": "Feature",
  "properties": {
    "addr:full":"The Royal Garrison Church, Penny St Portsmouth Hampshire PO1 2NJ",
    "addr:postcode":"hampshire po1 2nj",
    "addr:street":"St",
    "iso:country":"GB",
    "sg:address":"The Royal Garrison Church, Penny St",
    "sg:city":"Portsmouth",
    "sg:classifiers":[
        {
            "category":"Landmark",
            "subcategory":"Tourist Attraction",
            "type":"Public Place"
        }
    ],
    "sg:phone":"+44 23 9282 3973",
    "sg:postcode":"PO1 2NJ",
    "sg:province":"Hampshire",
    "sg:tags":[
        "interest"
    ],
    "wof:name":"English Heritage",
    "wof:placetype":"venue"
},
  "geometry": {"coordinates":[-1.087284,50.804008],"type":"Point"}
}