{
  "type": "Feature",
  "properties": {
    "iso:country":"GB",
    "sg:address":"The Belyars",
    "sg:city":"St Ives",
    "sg:classifiers":[
        {
            "category":"Travel",
            "subcategory":"Hotels & Motels",
            "type":"Entertainment"
        }
    ],
    "sg:postcode":"TR26 2DA",
    "sg:province":"Cornwall",
    "wof:name":"Woodside Hotel",
    "wof:placetype":"venue"
},
  "geometry": {"coordinates":[-5.480913,50.206615],"type":"Point"}
}