{
  "type": "Feature",
  "properties": {
    "addr:full":"14 Moorbridge Road, Kirkhill Industrial Estate Nottingham Leicestershire NG13 8GG",
    "addr:housenumber":"14",
    "addr:postcode":"ng13 8gg",
    "addr:street":"Moorbridge Road;Industrial Estate",
    "iso:country":"GB",
    "sg:address":"14 Moorbridge Road, Kirkhill Industrial Estate",
    "sg:city":"Nottingham",
    "sg:classifiers":[
        {
            "category":"Recreation",
            "subcategory":"Amusement Park",
            "type":"Entertainment"
        }
    ],
    "sg:phone":"+44 1949 839214",
    "sg:postcode":"NG13 8GG",
    "sg:province":"Leicestershire",
    "sg:tags":[
        "arcade"
    ],
    "wof:name":"Kunick Leisure Ltd.",
    "wof:placetype":"venue"
},
  "geometry": {"coordinates":[-0.955456,52.95657],"type":"Point"}
}