{
  "type": "Feature",
  "properties": {
    "addr:full":"1 Webster St Derby Derbyshire DE1 1PT",
    "addr:housenumber":"1",
    "addr:postcode":"de1 1pt",
    "addr:street":"Webster St",
    "iso:country":"GB",
    "sg:address":"1 Webster St",
    "sg:city":"Derby",
    "sg:classifiers":[
        {
            "category":"Retail",
            "subcategory":"Repair Shop",
            "type":"Services"
        }
    ],
    "sg:phone":"+44 1332 345985",
    "sg:postcode":"DE1 1PT",
    "sg:province":"Derbyshire",
    "sg:tags":[
        "upholsterer"
    ],
    "wof:name":"Nash Interiors",
    "wof:placetype":"venue"
},
  "geometry": {"coordinates":[-1.4819079638,52.9171295166],"type":"Point"}
}