{
  "type": "Feature",
  "properties": {
    "addr:full":"59 Lorne Rd Forest Gate Greater London E7 0LL",
    "addr:housenumber":"59",
    "addr:postcode":"e7 0ll",
    "addr:street":"Lorne Rd;Gate",
    "iso:country":"GB",
    "sg:address":"59 Lorne Rd",
    "sg:city":"Forest Gate",
    "sg:classifiers":[
        {
            "category":"Professional",
            "subcategory":"Engineering",
            "type":"Services"
        }
    ],
    "sg:phone":"+44 20 8534 3364",
    "sg:postcode":"E7 0LL",
    "sg:province":"Greater London",
    "sg:tags":[
        "contractor",
        "electrical",
        "engineer"
    ],
    "wof:name":"V.G Anglin",
    "wof:placetype":"venue"
},
  "geometry": {"coordinates":[0.0243100002,51.5512809753],"type":"Point"}
}