{
  "type": "Feature",
  "properties": {
    "addr:full":"Church Barn Claypit Lane, Ledsham South Milford Leeds North Yorkshire LS25 5LP",
    "addr:postcode":"ls25 5lp",
    "addr:street":"Claypit Lane",
    "iso:country":"GB",
    "sg:address":"Church Barn Claypit Lane, Ledsham South Milford",
    "sg:city":"Leeds",
    "sg:classifiers":[
        {
            "category":"Real Estate",
            "subcategory":"Developer",
            "type":"Services"
        }
    ],
    "sg:phone":"+44 1977 681984",
    "sg:postcode":"LS25 5LP",
    "sg:province":"North Yorkshire",
    "sg:tags":[
        "property"
    ],
    "wof:name":"McHale Developments",
    "wof:placetype":"venue"
},
  "geometry": {"coordinates":[-1.25042,53.778824],"type":"Point"}
}