{
  "type": "Feature",
  "properties": {
    "addr:full":"17 Horsefair Rugeley Staffordshire WS15 2EJ",
    "addr:housenumber":"17",
    "addr:postcode":"ws15 2ej",
    "addr:street":"Horsefair",
    "iso:country":"GB",
    "sg:address":"17 Horsefair",
    "sg:city":"Rugeley",
    "sg:classifiers":[
        {
            "category":"Home & Garden",
            "subcategory":"Furniture",
            "type":"Retail Goods"
        }
    ],
    "sg:phone":"+44 1889 582543",
    "sg:postcode":"WS15 2EJ",
    "sg:province":"Staffordshire",
    "wof:name":"Frank James (Furnishers) Ltd.",
    "wof:placetype":"venue"
},
  "geometry": {"coordinates":[-1.935583,52.757927],"type":"Point"}
}