{
  "type": "Feature",
  "properties": {
    "addr:full":"28 Loughbrow Park Hexham Northumberland NE46 2QD",
    "addr:housenumber":"28",
    "addr:postcode":"ne46 2qd",
    "addr:street":"Loughbrow Park",
    "iso:country":"GB",
    "sg:address":"28 Loughbrow Park",
    "sg:city":"Hexham",
    "sg:classifiers":[
        {
            "category":"Conference Center",
            "type":"Public Place"
        }
    ],
    "sg:phone":"+44 1434 608820",
    "sg:postcode":"NE46 2QD",
    "sg:province":"Northumberland",
    "wof:name":"G N P Ltd.",
    "wof:placetype":"venue"
},
  "geometry": {"coordinates":[-2.1006400585,54.9612770081],"type":"Point"}
}