{
  "type": "Feature",
  "properties": {
    "iso:country":"GB",
    "sg:address":"144 Lea Bridge Road",
    "sg:city":"London",
    "sg:classifiers":[
        {
            "category":"Bars & Pubs",
            "type":"Food & Drink"
        }
    ],
    "sg:phone":"+44 20 8985 5273",
    "sg:postcode":"E5 9RB",
    "sg:province":"Greater London",
    "sg:tags":[
        "pubs",
        "inn"
    ],
    "wof:name":"Ship Aground",
    "wof:placetype":"venue"
},
  "geometry": {"coordinates":[-0.046102,51.561569],"type":"Point"}
}