{
  "type": "Feature",
  "properties": {
    "iso:country":"GB",
    "sg:address":"St Margarets, 1461 London Rd",
    "sg:city":"Leigh-on-sea",
    "sg:classifiers":[
        {
            "category":"Organizations",
            "subcategory":"Community Association",
            "type":"Services"
        }
    ],
    "sg:phone":"+44 1702 74311",
    "sg:postcode":"SS9 2SB",
    "sg:province":"Essex",
    "sg:tags":[
        "society",
        "housing"
    ],
    "wof:name":"Abbeyfield Southend & South East Essex S",
    "wof:placetype":"venue"
},
  "geometry": {"coordinates":[0.650995,51.548481],"type":"Point"}
}