{
  "type": "Feature",
  "properties": {
    "iso:country":"GB",
    "sg:address":"64 Broadwater Rd",
    "sg:city":"Worthing",
    "sg:classifiers":[
        {
            "category":"Food & Beverages",
            "subcategory":"Liquor & Beverages",
            "type":"Retail Goods"
        }
    ],
    "sg:phone":"+44 1903 820406",
    "sg:postcode":"BN14 8AG",
    "sg:province":"West Sussex",
    "sg:tags":[
        "beer",
        "spirit",
        "wines"
    ],
    "wof:name":"Thresher Wine Shop",
    "wof:placetype":"venue"
},
  "geometry": {"coordinates":[-0.372614,50.821812],"type":"Point"}
}