{
  "type": "Feature",
  "properties": {
    "iso:country":"GB",
    "sg:address":"5 High Street",
    "sg:city":"Hawick",
    "sg:classifiers":[
        {
            "category":"Fast Food",
            "type":"Food & Drink"
        }
    ],
    "sg:phone":"+44 1450 376365",
    "sg:postcode":"TD9 9BZ",
    "sg:province":"Cumbria",
    "sg:tags":[
        "away",
        "take"
    ],
    "wof:name":"New Lamwah",
    "wof:placetype":"venue"
},
  "geometry": {"coordinates":[-2.78789,55.421864],"type":"Point"}
}