{
  "type": "Feature",
  "properties": {
    "addr:full":"London Street Reading Berkshire RG1 4QA",
    "addr:postcode":"rg1 4qa",
    "addr:street":"London Street",
    "iso:country":"GB",
    "sg:address":"London Street",
    "sg:city":"Reading",
    "sg:classifiers":[
        {
            "category":"Organizations",
            "subcategory":"Political Organization",
            "type":"Services"
        }
    ],
    "sg:postcode":"RG1 4QA",
    "sg:province":"Berkshire",
    "sg:tags":[
        "party"
    ],
    "wof:name":"Reading East Conservative Association",
    "wof:placetype":"venue"
},
  "geometry": {"coordinates":[-0.967649,51.451416],"type":"Point"}
}