{
  "type": "Feature",
  "properties": {
    "addr:full":"Brigade Ho, 8 Parsons Green Fulham Greater London SW6 4TN",
    "addr:housenumber":"8",
    "addr:postcode":"sw6 4tn",
    "addr:street":"Brigade;Parsons Green",
    "iso:country":"GB",
    "sg:address":"Brigade Ho, 8 Parsons Green",
    "sg:city":"Fulham",
    "sg:classifiers":[
        {
            "category":"Professional",
            "subcategory":"Management & Consulting",
            "type":"Services"
        }
    ],
    "sg:phone":"+44 20 7371 9311",
    "sg:postcode":"SW6 4TN",
    "sg:province":"Greater London",
    "sg:tags":[
        "consultant",
        "business"
    ],
    "wof:name":"W R P O Ltd",
    "wof:placetype":"venue"
},
  "geometry": {"coordinates":[-0.20117,51.474319],"type":"Point"}
}