{
  "type": "Feature",
  "properties": {
    "addr:full":"490 Thornton Road, Thorton Bradford West Yorkshire BD13 3JD",
    "addr:housenumber":"490",
    "addr:postcode":"bd13 3jd",
    "addr:street":"Thornton Road",
    "iso:country":"GB",
    "sg:address":"490 Thornton Road, Thorton",
    "sg:city":"Bradford",
    "sg:classifiers":[
        {
            "category":"Personal",
            "type":"Services"
        },
        {
            "category":"Shopping",
            "subcategory":"Florist",
            "type":"Retail Goods"
        }
    ],
    "sg:phone":"+44 1274 830300",
    "sg:postcode":"BD13 3JD",
    "sg:province":"West Yorkshire",
    "sg:tags":[
        "wedding"
    ],
    "wof:name":"Thornton Flower Shop",
    "wof:placetype":"venue"
},
  "geometry": {"coordinates":[-1.8521440029,53.7905845642],"type":"Point"}
}