{
  "type": "Feature",
  "properties": {
    "addr:full":"1480 London Rd Streatham Greater London SW16 4BT",
    "addr:housenumber":"1480",
    "addr:postcode":"sw16 4bt",
    "addr:street":"London Rd",
    "iso:country":"GB",
    "sg:address":"1480 London Rd",
    "sg:city":"Streatham",
    "sg:classifiers":[
        {
            "category":"Shopping",
            "subcategory":"Florist",
            "type":"Retail Goods"
        }
    ],
    "sg:phone":"+44 20 8765 0707",
    "sg:postcode":"SW16 4BT",
    "sg:province":"Greater London",
    "wof:name":"Iris & Christine",
    "wof:placetype":"venue"
},
  "geometry": {"coordinates":[-0.12346,51.411942],"type":"Point"}
}