{
  "type": "Feature",
  "properties": {
    "addr:full":"520 Sauchiehall Street Glasgow Glasgow City G2 3LW",
    "addr:housenumber":"520",
    "addr:postcode":"g2 3lw",
    "addr:street":"Sauchiehall Street",
    "iso:country":"GB",
    "sg:address":"520 Sauchiehall Street",
    "sg:city":"Glasgow",
    "sg:classifiers":[
        {
            "category":"Bars & Pubs",
            "subcategory":"Nightclub",
            "type":"Food & Drink"
        }
    ],
    "sg:postcode":"G2 3LW",
    "sg:province":"Glasgow City",
    "sg:tags":[
        "club",
        "night",
        "activity"
    ],
    "wof:name":"Lamal Ltd.",
    "wof:placetype":"venue"
},
  "geometry": {"coordinates":[-4.269557,55.866272],"type":"Point"}
}