{
  "type": "Feature",
  "properties": {
    "addr:full":"21 Bentinck Street London Greater London W1U 2EX",
    "addr:housenumber":"21",
    "addr:postcode":"w1u 2ex",
    "addr:street":"Bentinck Street",
    "iso:country":"GB",
    "sg:address":"21 Bentinck Street",
    "sg:city":"London",
    "sg:classifiers":[
        {
            "category":"Professional",
            "subcategory":"Lawyer & Legal Services",
            "type":"Services"
        }
    ],
    "sg:phone":"+44 20 7486 2566",
    "sg:postcode":"W1U 2EX",
    "sg:province":"Greater London",
    "sg:tags":[
        "solicitor"
    ],
    "wof:name":"Philippsohn Crawfords Berwald",
    "wof:placetype":"venue"
},
  "geometry": {"coordinates":[-0.149816,51.517036],"type":"Point"}
}