{
  "type": "Feature",
  "properties": {
    "addr:full":"28a High Street Wickford Essex SS12 9AZ",
    "addr:housenumber":"28a",
    "addr:postcode":"ss12 9az",
    "addr:street":"High Street",
    "iso:country":"GB",
    "sg:address":"28a High Street",
    "sg:city":"Wickford",
    "sg:classifiers":[
        {
            "category":"Personal",
            "subcategory":"Beauty Salon",
            "type":"Services"
        }
    ],
    "sg:phone":"+44 1268 733600",
    "sg:postcode":"SS12 9AZ",
    "sg:province":"Essex",
    "sg:tags":[
        "unisex",
        "hairdresser"
    ],
    "wof:name":"Oasis Hair & Beauty",
    "wof:placetype":"venue"
},
  "geometry": {"coordinates":[0.5207949877,51.6126441956],"type":"Point"}
}