{
  "type": "Feature",
  "properties": {
    "iso:country":"GB",
    "sg:address":"164 Shaftesbury Avenue",
    "sg:city":"Holborn",
    "sg:classifiers":[
        {
            "category":"Professional",
            "type":"Services"
        }
    ],
    "sg:postcode":"WC2H 8HL",
    "sg:province":"Greater London",
    "sg:tags":[
        "exhibition"
    ],
    "wof:name":"Bgla Ltd",
    "wof:placetype":"venue"
},
  "geometry": {"coordinates":[-0.1277990043,51.5141944885],"type":"Point"}
}