{
  "type": "Feature",
  "properties": {
    "addr:full":"62 Wynchgate London Greater London N14 6RL",
    "addr:housenumber":"62",
    "addr:postcode":"n14 6rl",
    "addr:street":"Wynchgate",
    "iso:country":"GB",
    "sg:address":"62 Wynchgate",
    "sg:city":"London",
    "sg:classifiers":[
        {
            "category":"Building & Trades",
            "subcategory":"Cleaning & Sanitation",
            "type":"Services"
        },
        {
            "category":"Retail",
            "subcategory":"Repair Shop",
            "type":"Services"
        }
    ],
    "sg:postcode":"N14 6RL",
    "sg:province":"Greater London",
    "sg:tags":[
        "commercial",
        "maintenance"
    ],
    "wof:name":"A T P Maintance",
    "wof:placetype":"venue"
},
  "geometry": {"coordinates":[-0.120894,51.633869],"type":"Point"}
}