{
  "type": "Feature",
  "properties": {
    "addr:full":"110 Kingsbury Road, Erdington Birmingham West Midlands B24 8QU",
    "addr:housenumber":"110",
    "addr:postcode":"b24 8qu",
    "addr:street":"Kingsbury Road",
    "iso:country":"GB",
    "sg:address":"110 Kingsbury Road, Erdington",
    "sg:city":"Birmingham",
    "sg:classifiers":[
        {
            "category":"Freight",
            "type":"Transportation"
        }
    ],
    "sg:phone":"+44 121 377 8837",
    "sg:postcode":"B24 8QU",
    "sg:province":"West Midlands",
    "sg:tags":[
        "haulage",
        "transport",
        "road"
    ],
    "wof:name":"G B X DISTRIBUTION",
    "wof:placetype":"venue"
},
  "geometry": {"coordinates":[-1.8448810577,52.5156478882],"type":"Point"}
}