{
  "type": "Feature",
  "properties": {
    "iso:country":"GB",
    "sg:address":"44-46 Cavendish Road",
    "sg:city":"Leicester",
    "sg:classifiers":[
        {
            "category":"Cafe",
            "type":"Food & Drink"
        }
    ],
    "sg:postcode":"LE2 7PH",
    "sg:province":"Leicestershire",
    "sg:tags":[
        "tea",
        "room"
    ],
    "wof:name":"The Mitey Bite",
    "wof:placetype":"venue"
},
  "geometry": {"coordinates":[-1.140224,52.612751],"type":"Point"}
}