{
  "type": "Feature",
  "properties": {
    "addr:full":"Hillcommon Taunton Devon TA4 1DW",
    "addr:postcode":"ta4 1dw",
    "iso:country":"GB",
    "sg:address":"Hillcommon",
    "sg:city":"Taunton",
    "sg:classifiers":[
        {
            "category":"Food & Beverages",
            "subcategory":"Farmers Market",
            "type":"Retail Goods"
        }
    ],
    "sg:postcode":"TA4 1DW",
    "sg:province":"Devon",
    "sg:tags":[
        "farm",
        "shop",
        "pyo"
    ],
    "wof:name":"Taunton Deane Orchards Ltd",
    "wof:placetype":"venue"
},
  "geometry": {"coordinates":[-3.20967,51.029598],"type":"Point"}
}