{
  "type": "Feature",
  "properties": {
    "addr:full":"5 Ladycroft Balerno City of Edinburgh EH14 7AG",
    "addr:housenumber":"5",
    "addr:postcode":"eh14 7ag",
    "addr:street":"Ladycroft Balerno",
    "iso:country":"GB",
    "sg:address":"5 Ladycroft",
    "sg:city":"Balerno",
    "sg:classifiers":[
        {
            "category":"Arena",
            "subcategory":"Sports Club",
            "type":"Entertainment"
        }
    ],
    "sg:phone":"+44 131 449 3789",
    "sg:postcode":"EH14 7AG",
    "sg:province":"City of Edinburgh",
    "wof:name":"Balerno Bowling Club",
    "wof:placetype":"venue"
},
  "geometry": {"coordinates":[-3.3392379284,55.8845977783],"type":"Point"}
}