{
  "type": "Feature",
  "properties": {
    "addr:full":"31 Kingston Road Portsmouth Hampshire PO2 7DP",
    "addr:housenumber":"31",
    "addr:postcode":"hampshire po2 7dp",
    "addr:street":"Kingston Road",
    "iso:country":"GB",
    "sg:address":"31 Kingston Road",
    "sg:city":"Portsmouth",
    "sg:classifiers":[
        {
            "category":"Retail",
            "subcategory":"Laundry & Dry Cleaning",
            "type":"Services"
        }
    ],
    "sg:phone":"+44 23 9261 1818",
    "sg:postcode":"PO2 7DP",
    "sg:province":"Hampshire",
    "sg:tags":[
        "cleaner",
        "alteration"
    ],
    "wof:name":"Kingston Cleaners",
    "wof:placetype":"venue"
},
  "geometry": {"coordinates":[-1.077487,50.807671],"type":"Point"}
}