{
  "type": "Feature",
  "properties": {
    "addr:full":"11 Jameson Road Birmingham West Midlands B6 7SJ",
    "addr:housenumber":"11",
    "addr:postcode":"b6 7sj",
    "addr:street":"Jameson Road",
    "iso:country":"GB",
    "sg:address":"11 Jameson Road",
    "sg:city":"Birmingham",
    "sg:classifiers":[
        {
            "category":"Shopping",
            "subcategory":"Stationery & Office Supplies",
            "type":"Retail Goods"
        }
    ],
    "sg:phone":"+44 121 327 2960",
    "sg:postcode":"B6 7SJ",
    "sg:province":"West Midlands",
    "wof:name":"Metro Looseleaf Ltd.",
    "wof:placetype":"venue"
},
  "geometry": {"coordinates":[-1.865226984,52.5064582825],"type":"Point"}
}