{
  "type": "Feature",
  "properties": {
    "addr:full":"161a Eastbank Street Southport Lancashire PR8 6TH",
    "addr:housenumber":"161a",
    "addr:postcode":"pr8 6th",
    "addr:street":"Eastbank Street",
    "iso:country":"GB",
    "sg:address":"161a Eastbank Street",
    "sg:city":"Southport",
    "sg:classifiers":[
        {
            "category":"Taxi",
            "type":"Transportation"
        },
        {
            "category":"Military Area",
            "subcategory":"Air Force Base",
            "type":"Public Place"
        }
    ],
    "sg:phone":"+44 1704 544414",
    "sg:postcode":"PR8 6TH",
    "sg:province":"Lancashire",
    "sg:tags":[
        "mini",
        "hire",
        "private",
        "cab"
    ],
    "wof:name":"Central Cabs",
    "wof:placetype":"venue"
},
  "geometry": {"coordinates":[-3.0008609295,53.642162323],"type":"Point"}
}