{
  "type": "Feature",
  "properties": {
    "addr:full":"2 Sylvan Road, Wanstead London Greater London E11 1QN",
    "addr:housenumber":"2",
    "addr:postcode":"e11 1qn",
    "addr:street":"Sylvan Road",
    "iso:country":"GB",
    "sg:address":"2 Sylvan Road, Wanstead",
    "sg:city":"London",
    "sg:classifiers":[
        {
            "category":"Home & Garden",
            "subcategory":"Building Materials",
            "type":"Retail Goods"
        }
    ],
    "sg:phone":"+44 20 8989 5125",
    "sg:postcode":"E11 1QN",
    "sg:province":"Greater London",
    "sg:tags":[
        "insulation",
        "installers"
    ],
    "wof:name":"Startin & Co. Ltd.",
    "wof:placetype":"venue"
},
  "geometry": {"coordinates":[0.0222820006,51.5811500549],"type":"Point"}
}