{
  "type": "Feature",
  "properties": {
    "addr:full":"Derby Rd Ripley Derbyshire DE5 8JN",
    "addr:postcode":"de5 8jn",
    "addr:street":"Derby Rd",
    "iso:country":"GB",
    "sg:address":"Derby Rd",
    "sg:city":"Ripley",
    "sg:classifiers":[
        {
            "category":"Autos & Motor Vehicles",
            "subcategory":"Automobile Sales",
            "type":"Retail Goods"
        }
    ],
    "sg:postcode":"DE5 8JN",
    "sg:province":"Derbyshire",
    "sg:tags":[
        "car"
    ],
    "wof:name":"Thompson,Ian,",
    "wof:placetype":"venue"
},
  "geometry": {"coordinates":[-1.405081,53.041195],"type":"Point"}
}