{
  "type": "Feature",
  "properties": {
    "addr:full":"12 Wyndham Crescent, Elm Park Cranleigh Surrey GU6 8UQ",
    "addr:housenumber":"12",
    "addr:postcode":"gu6 8uq",
    "addr:street":"Wyndham Crescent Elm",
    "iso:country":"GB",
    "sg:address":"12 Wyndham Crescent, Elm Park",
    "sg:city":"Cranleigh",
    "sg:classifiers":[
        {
            "category":"Professional",
            "type":"Services"
        }
    ],
    "sg:phone":"+44 1483 267583",
    "sg:postcode":"GU6 8UQ",
    "sg:province":"Surrey",
    "sg:tags":[
        "caterer"
    ],
    "wof:name":"Malcolm Harris & Anne Shute",
    "wof:placetype":"venue"
},
  "geometry": {"coordinates":[-0.5101600289,51.1410331726],"type":"Point"}
}