{
  "type": "Feature",
  "properties": {
    "addr:full":"55 Sussex Road Petersfield Hampshire GU31 4JX",
    "addr:housenumber":"55",
    "addr:postcode":"gu31 4jx",
    "addr:street":"Sussex Road",
    "iso:country":"GB",
    "sg:address":"55 Sussex Road",
    "sg:city":"Petersfield",
    "sg:classifiers":[
        {
            "category":"Manufacturing",
            "subcategory":"Paper Products",
            "type":"Manufacturing & Wholesale Goods"
        }
    ],
    "sg:postcode":"GU31 4JX",
    "sg:province":"Hampshire",
    "sg:tags":[
        "cardboard"
    ],
    "wof:name":"Douglas Whiting",
    "wof:placetype":"venue"
},
  "geometry": {"coordinates":[-0.9347469807,51.0003318787],"type":"Point"}
}