{
  "type": "Feature",
  "properties": {
    "addr:full":"West End Farm, Thornholme Driffield East Riding of Yorkshire YO25 4NN",
    "addr:postcode":"yo25 4nn",
    "addr:street":"Thornholme",
    "iso:country":"GB",
    "sg:address":"West End Farm, Thornholme",
    "sg:city":"Driffield",
    "sg:classifiers":[
        {
            "category":"Home & Garden",
            "subcategory":"Garden Supply",
            "type":"Retail Goods"
        },
        {
            "category":"Farming",
            "subcategory":"Farm",
            "type":"Manufacturing & Wholesale Goods"
        }
    ],
    "sg:phone":"+44 1262 490375",
    "sg:postcode":"YO25 4NN",
    "sg:province":"East Riding of Yorkshire",
    "sg:tags":[
        "mixed",
        "bulb",
        "grower"
    ],
    "wof:name":"B R Wood & Co.",
    "wof:placetype":"venue"
},
  "geometry": {"coordinates":[-0.2917929888,54.060256958],"type":"Point"}
}