{
  "type": "Feature",
  "properties": {
    "iso:country":"GB",
    "sg:address":"Stanshawes Court, Yate",
    "sg:city":"Bristol",
    "sg:classifiers":[
        {
            "category":"Manufacturing",
            "subcategory":"Wood Products",
            "type":"Manufacturing & Wholesale Goods"
        }
    ],
    "sg:phone":"+44 1454 325525",
    "sg:postcode":"BS37 4DZ",
    "sg:province":"Gloucestershire",
    "sg:tags":[
        "woodturning"
    ],
    "wof:name":"Grooms House Turnery",
    "wof:placetype":"venue"
},
  "geometry": {"coordinates":[-2.41297,51.535168],"type":"Point"}
}