{
  "type": "Feature",
  "properties": {
    "addr:full":"48 New Chapel St Blackburn Lancashire BB2 4DT",
    "addr:housenumber":"48",
    "addr:postcode":"bb2 4dt",
    "addr:street":"New Chapel St",
    "iso:country":"GB",
    "sg:address":"48 New Chapel St",
    "sg:city":"Blackburn",
    "sg:classifiers":[
        {
            "category":"Fast Food",
            "type":"Food & Drink"
        }
    ],
    "sg:phone":"+44 1254 661877",
    "sg:postcode":"BB2 4DT",
    "sg:province":"Lancashire",
    "sg:tags":[
        "away",
        "take"
    ],
    "wof:name":"U-CHEWS",
    "wof:placetype":"venue"
},
  "geometry": {"coordinates":[-2.502902,53.734749],"type":"Point"}
}