{
  "type": "Feature",
  "properties": {
    "addr:full":"44 Meadowside Abingdon Oxfordshire OX14 5DX",
    "addr:postcode":"ox14 5dx",
    "iso:country":"GB",
    "sg:address":"44 Meadowside",
    "sg:city":"Abingdon",
    "sg:classifiers":[
        {
            "category":"Building & Trades",
            "subcategory":"Construction",
            "type":"Services"
        }
    ],
    "sg:phone":"+44 1235 538094",
    "sg:postcode":"OX14 5DX",
    "sg:province":"Oxfordshire",
    "sg:tags":[
        "ceiling",
        "contractor"
    ],
    "wof:name":"Abingdon Artexing & Dry Lining",
    "wof:placetype":"venue"
},
  "geometry": {"coordinates":[-1.289047,51.668732],"type":"Point"}
}