{
  "type": "Feature",
  "properties": {
    "iso:country":"GB",
    "sg:address":"18 Thorpe Lane, Sprotbrough",
    "sg:city":"Doncaster",
    "sg:classifiers":[
        {
            "category":"Professional",
            "subcategory":"Art Services",
            "type":"Services"
        },
        {
            "category":"Building & Trades",
            "subcategory":"Construction",
            "type":"Services"
        }
    ],
    "sg:phone":"+44 1302 853968",
    "sg:postcode":"DN5 7QP",
    "sg:province":"South Yorkshire",
    "sg:tags":[
        "decorator",
        "painter"
    ],
    "wof:name":"DAVID JONES",
    "wof:placetype":"venue"
},
  "geometry": {"coordinates":[-1.188919,53.513443],"type":"Point"}
}