{
  "type": "Feature",
  "properties": {
    "addr:full":"30 Regent Street Cambridge Cambridgeshire CB2 1DB",
    "addr:housenumber":"30",
    "addr:postcode":"cb2 1db",
    "addr:street":"Regent Street",
    "iso:country":"GB",
    "sg:address":"30 Regent Street",
    "sg:city":"Cambridge",
    "sg:classifiers":[
        {
            "category":"Shopping",
            "subcategory":"Thrift Store",
            "type":"Retail Goods"
        }
    ],
    "sg:phone":"+44 1223 462452",
    "sg:postcode":"CB2 1DB",
    "sg:province":"Cambridgeshire",
    "sg:tags":[
        "shop",
        "charity"
    ],
    "wof:name":"The Hospice Shop",
    "wof:placetype":"venue"
},
  "geometry": {"coordinates":[0.1253139973,52.2012557983],"type":"Point"}
}