{
  "type": "Feature",
  "properties": {
    "addr:full":"Westcott Venture Park, Ashendon Road, Westcott Aylesbury Buckinghamshire HP18 0NY",
    "addr:postcode":"hp18 0ny",
    "addr:street":"Ashendon Road",
    "iso:country":"GB",
    "sg:address":"Westcott Venture Park, Ashendon Road, Westcott",
    "sg:city":"Aylesbury",
    "sg:classifiers":[
        {
            "category":"Government",
            "subcategory":"Post Office",
            "type":"Public Place"
        }
    ],
    "sg:postcode":"HP18 0NY",
    "sg:province":"Buckinghamshire",
    "sg:tags":[
        "messenger",
        "courier"
    ],
    "wof:name":"J D'S Delivery Service",
    "wof:placetype":"venue"
},
  "geometry": {"coordinates":[-0.979529,51.821098],"type":"Point"}
}