{
  "type": "Feature",
  "properties": {
    "addr:full":"1 Station Road, St Neots Huntingdon Bedfordshire PE19 1QH",
    "addr:housenumber":"1",
    "addr:postcode":"pe19 1qh",
    "addr:street":"Station Road",
    "iso:country":"GB",
    "sg:address":"1 Station Road, St Neots",
    "sg:city":"Huntingdon",
    "sg:classifiers":[
        {
            "category":"Wholesale",
            "subcategory":"Machinery & Supplies",
            "type":"Manufacturing & Wholesale Goods"
        }
    ],
    "sg:phone":"+44 1480 226800",
    "sg:postcode":"PE19 1QH",
    "sg:province":"Bedfordshire",
    "wof:name":"Lely (U K) Ltd.",
    "wof:placetype":"venue"
},
  "geometry": {"coordinates":[-0.249132,52.229321],"type":"Point"}
}