{
  "type": "Feature",
  "properties": {
    "addr:full":"20 Fenlake Business Centre, Fengate Peterborough Cambridgeshire PE1 5BQ",
    "addr:housenumber":"20",
    "addr:postcode":"pe1 5bq",
    "addr:street":"Fenlake Business Centre",
    "iso:country":"GB",
    "sg:address":"20 Fenlake Business Centre, Fengate",
    "sg:city":"Peterborough",
    "sg:classifiers":[
        {
            "category":"Social Services",
            "type":"Services"
        },
        {
            "category":"Manufacturing",
            "subcategory":"Tobacco Products",
            "type":"Manufacturing & Wholesale Goods"
        }
    ],
    "sg:phone":"+44 1733 893006",
    "sg:postcode":"PE1 5BQ",
    "sg:province":"Cambridgeshire",
    "sg:tags":[
        "equipment",
        "suppliers",
        "disability",
        "manufacturers"
    ],
    "wof:name":"EQUIPMENT FOR EQUALITY",
    "wof:placetype":"venue"
},
  "geometry": {"coordinates":[-0.2209589928,52.5749130249],"type":"Point"}
}