{
  "type": "Feature",
  "properties": {
    "addr:full":"28 Haddington Place Edinburgh City of Edinburgh EH7 4AF",
    "addr:housenumber":"28",
    "addr:postcode":"eh7 4af",
    "addr:street":"Haddington Place Edinburgh",
    "iso:country":"GB",
    "sg:address":"28 Haddington Place",
    "sg:city":"Edinburgh",
    "sg:classifiers":[
        {
            "category":"Shopping",
            "subcategory":"Music",
            "type":"Retail Goods"
        }
    ],
    "sg:postcode":"EH7 4AF",
    "sg:province":"City of Edinburgh",
    "sg:tags":[
        "record",
        "tape",
        "cd"
    ],
    "wof:name":"D W Amos",
    "wof:placetype":"venue"
},
  "geometry": {"coordinates":[-3.1820390224,55.9603118896],"type":"Point"}
}