{
  "type": "Feature",
  "properties": {
    "iso:country":"GB",
    "sg:address":"86 Church Rd",
    "sg:city":"London",
    "sg:classifiers":[
        {
            "category":"Food & Beverages",
            "subcategory":"Supermarket",
            "type":"Retail Goods"
        }
    ],
    "sg:postcode":"SW13 0DQ",
    "sg:province":"Greater London",
    "wof:name":"Edwards,W H,",
    "wof:placetype":"venue"
},
  "geometry": {"coordinates":[-0.240641,51.47485],"type":"Point"}
}