{
  "type": "Feature",
  "properties": {
    "iso:country":"GB",
    "sg:address":"1-3 Little Belmont St",
    "sg:city":"Aberdeen",
    "sg:classifiers":[
        {
            "category":"Professional",
            "subcategory":"Employment Agencies",
            "type":"Services"
        }
    ],
    "sg:phone":"+44 1224 646809",
    "sg:postcode":"AB10 1JG",
    "sg:province":"Aberdeen City",
    "sg:tags":[
        "consultant"
    ],
    "wof:name":"McPherson Associates",
    "wof:placetype":"venue"
},
  "geometry": {"coordinates":[-2.100099,57.147079],"type":"Point"}
}