{
  "type": "Feature",
  "properties": {
    "iso:country":"GB",
    "sg:address":"101 North Street, Burwell",
    "sg:city":"Cambridge",
    "sg:classifiers":[
        {
            "category":"Professional",
            "subcategory":"Management & Consulting",
            "type":"Services"
        }
    ],
    "sg:phone":"+44 1638 600606",
    "sg:postcode":"CB5 0BB",
    "sg:province":"Cambridgeshire",
    "sg:tags":[
        "consultant"
    ],
    "wof:name":"Luttrell Associates Ltd.",
    "wof:placetype":"venue"
},
  "geometry": {"coordinates":[0.3261449933,52.2863006592],"type":"Point"}
}