{
  "type": "Feature",
  "properties": {
    "addr:full":"Unit 7a, Cooksland Indstl Est Bodmin Cornwall PL31 2PZ",
    "addr:housenumber":"unit 7a",
    "addr:postcode":"pl31 2pz",
    "addr:street":"Indstl Est",
    "iso:country":"GB",
    "sg:address":"Unit 7a, Cooksland Indstl Est",
    "sg:city":"Bodmin",
    "sg:classifiers":[
        {
            "category":"Wholesale",
            "subcategory":"Scrap",
            "type":"Manufacturing & Wholesale Goods"
        }
    ],
    "sg:postcode":"PL31 2PZ",
    "sg:province":"Cornwall",
    "sg:tags":[
        "breaker",
        "dismantlers"
    ],
    "wof:name":"Rowe,J,",
    "wof:placetype":"venue"
},
  "geometry": {"coordinates":[-4.716369,50.471046],"type":"Point"}
}