{
  "type": "Feature",
  "properties": {
    "addr:full":"8 Victoria Avenue Harrogate North Yorkshire HG1 1ED",
    "addr:housenumber":"8",
    "addr:postcode":"hg1 1ed",
    "addr:street":"Victoria Avenue",
    "iso:country":"GB",
    "sg:address":"8 Victoria Avenue",
    "sg:city":"Harrogate",
    "sg:classifiers":[
        {
            "category":"Utilities",
            "type":"Services"
        }
    ],
    "sg:phone":"+44 1423 528827",
    "sg:postcode":"HG1 1ED",
    "sg:province":"North Yorkshire",
    "sg:tags":[
        "internet"
    ],
    "wof:name":"INFORM",
    "wof:placetype":"venue"
},
  "geometry": {"coordinates":[-1.53815,53.990643],"type":"Point"}
}