{
  "type": "Feature",
  "properties": {
    "iso:country":"GB",
    "sg:address":"Inland Clearance Depots, Waterbrook Avenue",
    "sg:city":"Ashford",
    "sg:classifiers":[
        {
            "category":"Government",
            "subcategory":"Customs House",
            "type":"Public Place"
        }
    ],
    "sg:phone":"+44 1233 502169",
    "sg:postcode":"TN24 0LH",
    "sg:province":"Kent",
    "sg:tags":[
        "excise"
    ],
    "wof:name":"H M Customs & Excise",
    "wof:placetype":"venue"
},
  "geometry": {"coordinates":[0.8975,51.124538],"type":"Point"}
}