{
  "type": "Feature",
  "properties": {
    "addr:full":"Pentrebach Rd Merthyr Tydfil Caerphilly CF48 1YA",
    "addr:postcode":"cf48 1ya",
    "addr:street":"Pentrebach Rd",
    "iso:country":"GB",
    "sg:address":"Pentrebach Rd",
    "sg:city":"Merthyr Tydfil",
    "sg:classifiers":[
        {
            "category":"Retail",
            "subcategory":"Auto Repair",
            "type":"Services"
        }
    ],
    "sg:phone":"+44 1685 374111",
    "sg:postcode":"CF48 1YA",
    "sg:province":"Caerphilly",
    "sg:tags":[
        "modification",
        "garage"
    ],
    "wof:name":"Dragon Ford (merthyr Tydfil) Ltd",
    "wof:placetype":"venue"
},
  "geometry": {"coordinates":[-3.368889,51.732994],"type":"Point"}
}