{
  "type": "Feature",
  "properties": {
    "iso:country":"GB",
    "sg:address":"Mill Road, Queenzieburn, Kilsyth",
    "sg:city":"Glasgow",
    "sg:classifiers":[
        {
            "category":"Education",
            "subcategory":"School",
            "type":"Public Place"
        }
    ],
    "sg:phone":"+44 1236 822242",
    "sg:postcode":"G65 9EF",
    "sg:province":"East Dunbartonshire",
    "sg:tags":[
        "local",
        "authority"
    ],
    "wof:name":"Chapelgreen Primary School",
    "wof:placetype":"venue"
},
  "geometry": {"coordinates":[-4.0962572098,55.9719276428],"type":"Point"}
}