{
  "type": "Feature",
  "properties": {
    "iso:country":"GB",
    "sg:address":"240 Chichester Road",
    "sg:city":"Portsmouth",
    "sg:classifiers":[
        {
            "category":"Shopping",
            "subcategory":"Pharmacy",
            "type":"Retail Goods"
        }
    ],
    "sg:phone":"+44 23 9266 3434",
    "sg:postcode":"PO2 0AU",
    "sg:province":"Hampshire",
    "sg:tags":[
        "pharmacist",
        "chemist"
    ],
    "wof:name":"Heywood Baker Ltd.",
    "wof:placetype":"venue"
},
  "geometry": {"coordinates":[-1.068732,50.813786],"type":"Point"}
}