{
  "type": "Feature",
  "properties": {
    "addr:full":"Fursdon, Sparkwell Plymouth Devon PL7 5DF",
    "addr:postcode":"pl7 5df",
    "iso:country":"GB",
    "sg:address":"Fursdon, Sparkwell",
    "sg:city":"Plymouth",
    "sg:classifiers":[
        {
            "category":"Professional",
            "subcategory":"Lawyer & Legal Services",
            "type":"Services"
        }
    ],
    "sg:phone":"+44 1752 837220",
    "sg:postcode":"PL7 5DF",
    "sg:province":"Devon",
    "sg:tags":[
        "solicitor"
    ],
    "wof:name":"David Crowley Solicitor",
    "wof:placetype":"venue"
},
  "geometry": {"coordinates":[-3.9985730648,50.4032325745],"type":"Point"}
}