{
  "type": "Feature",
  "properties": {
    "addr:full":"2 Victoria Cottages, Cadleigh Plymouth Devon PL2 1JW",
    "addr:housenumber":"2",
    "addr:postcode":"pl2 1jw",
    "addr:street":"Victoria Cottages Cadleigh",
    "iso:country":"GB",
    "sg:address":"2 Victoria Cottages, Cadleigh",
    "sg:city":"Plymouth",
    "sg:classifiers":[
        {
            "category":"Retail",
            "subcategory":"Storage",
            "type":"Services"
        }
    ],
    "sg:phone":"+44 1752 894900",
    "sg:postcode":"PL2 1JW",
    "sg:province":"Devon",
    "sg:tags":[
        "household",
        "removal"
    ],
    "wof:name":"Rawden Removals",
    "wof:placetype":"venue"
},
  "geometry": {"coordinates":[-4.1724948883,50.3791236877],"type":"Point"}
}