{
  "type": "Feature",
  "properties": {
    "iso:country":"GB",
    "sg:address":"267 Luton Road",
    "sg:city":"Dunstable",
    "sg:classifiers":[
        {
            "category":"Manufacturing",
            "subcategory":"Textiles",
            "type":"Manufacturing & Wholesale Goods"
        }
    ],
    "sg:phone":"+44 1582 605510",
    "sg:postcode":"LU5 4LR",
    "sg:province":"Bedfordshire",
    "sg:tags":[
        "dyer"
    ],
    "wof:name":"Gavand Enterprises",
    "wof:placetype":"venue"
},
  "geometry": {"coordinates":[-0.492062,51.88979],"type":"Point"}
}