{
  "type": "Feature",
  "properties": {
    "iso:country":"GB",
    "sg:address":"The White Ho, Hockliffe St",
    "sg:city":"Leighton Buzzard",
    "sg:classifiers":[
        {
            "category":"Professional",
            "subcategory":"Management & Consulting",
            "type":"Services"
        }
    ],
    "sg:phone":"+44 1525 854500",
    "sg:postcode":"LU7 8HD",
    "sg:province":"Bedfordshire",
    "sg:tags":[
        "marketing",
        "consultant"
    ],
    "wof:name":"Success Media Ltd",
    "wof:placetype":"venue"
},
  "geometry": {"coordinates":[-0.663909,51.917351],"type":"Point"}
}