{
  "type": "Feature",
  "properties": {
    "iso:country":"GB",
    "sg:address":"Nook Farm, Shap",
    "sg:city":"Penrith",
    "sg:classifiers":[
        {
            "category":"Farming",
            "subcategory":"Livestock Farm",
            "type":"Manufacturing & Wholesale Goods"
        }
    ],
    "sg:postcode":"CA10 3LZ",
    "sg:province":"Cumbria",
    "sg:tags":[
        "others"
    ],
    "wof:name":"W B & S M Atkinson",
    "wof:placetype":"venue"
},
  "geometry": {"coordinates":[-2.6762759686,54.5289459229],"type":"Point"}
}