{
  "type": "Feature",
  "properties": {
    "iso:country":"GB",
    "sg:address":"Trephilip, Devynock",
    "sg:city":"Brecon",
    "sg:classifiers":[
        {
            "category":"Farming",
            "subcategory":"Livestock Farm",
            "type":"Manufacturing & Wholesale Goods"
        }
    ],
    "sg:phone":"+44 1874 636747",
    "sg:postcode":"LD3 8SA",
    "sg:province":"Powys",
    "sg:tags":[
        "others"
    ],
    "wof:name":"T G & E G Morgan",
    "wof:placetype":"venue"
},
  "geometry": {"coordinates":[-3.560327,51.937061],"type":"Point"}
}