{
  "type": "Feature",
  "properties": {
    "iso:country":"GB",
    "sg:address":"27 High Street",
    "sg:city":"Lincoln",
    "sg:classifiers":[
        {
            "category":"Shopping",
            "subcategory":"Department Store",
            "type":"Retail Goods"
        },
        {
            "category":"Government",
            "subcategory":"Post Office",
            "type":"Public Place"
        }
    ],
    "sg:postcode":"LN4 4RB",
    "sg:province":"Lincolnshire",
    "wof:name":"Martin Post Office",
    "wof:placetype":"venue"
},
  "geometry": {"coordinates":[-0.275961,53.0783],"type":"Point"}
}