{
  "type": "Feature",
  "properties": {
    "iso:country":"GB",
    "sg:address":"30 Princes Avenue",
    "sg:city":"Nuneaton",
    "sg:classifiers":[
        {
            "category":"Food & Beverages",
            "subcategory":"Fruits & Vegetables",
            "type":"Retail Goods"
        }
    ],
    "sg:postcode":"CV11 5NU",
    "sg:province":"Leicestershire",
    "sg:tags":[
        "greengrocer"
    ],
    "wof:name":"Asha Food Store",
    "wof:placetype":"venue"
},
  "geometry": {"coordinates":[-1.474127,52.518814],"type":"Point"}
}