{
  "type": "Feature",
  "properties": {
    "addr:full":"2a Dunlop Road, Barrmill Beith North Ayrshire KA15 1HN",
    "addr:housenumber":"2a",
    "addr:postcode":"ka15 1hn",
    "addr:street":"Dunlop Road;Beith",
    "iso:country":"GB",
    "sg:address":"2a Dunlop Road, Barrmill",
    "sg:city":"Beith",
    "sg:classifiers":[
        {
            "category":"Building & Trades",
            "subcategory":"Landscaping Services",
            "type":"Services"
        }
    ],
    "sg:phone":"+44 7986 323252",
    "sg:postcode":"KA15 1HN",
    "sg:province":"North Ayrshire",
    "sg:tags":[
        "landscape",
        "contractor"
    ],
    "wof:name":"D Tipping Landscape Gardening",
    "wof:placetype":"venue"
},
  "geometry": {"coordinates":[-4.6014490128,55.7291145325],"type":"Point"}
}