{
  "type": "Feature",
  "properties": {
    "addr:full":"Howley Farm, Howley Chard Devon TA20 3DX",
    "addr:postcode":"ta20 3dx",
    "iso:country":"GB",
    "sg:address":"Howley Farm, Howley",
    "sg:city":"Chard",
    "sg:classifiers":[
        {
            "category":"Farming",
            "subcategory":"Livestock Farm",
            "type":"Manufacturing & Wholesale Goods"
        }
    ],
    "sg:phone":"+44 1460 62245",
    "sg:postcode":"TA20 3DX",
    "sg:province":"Devon",
    "sg:tags":[
        "others"
    ],
    "wof:name":"P A & C E Edwards",
    "wof:placetype":"venue"
},
  "geometry": {"coordinates":[-3.044711113,50.8824653625],"type":"Point"}
}