{
  "type": "Feature",
  "properties": {
    "addr:full":"36 Upper Wickham Lane Welling Kent DA16 3HF",
    "addr:housenumber":"36",
    "addr:postcode":"da16 3hf",
    "addr:street":"Upper Wickham Lane",
    "iso:country":"GB",
    "sg:address":"36 Upper Wickham Lane",
    "sg:city":"Welling",
    "sg:classifiers":[
        {
            "category":"Cafe",
            "type":"Food & Drink"
        }
    ],
    "sg:phone":"+44 20 8301 4388",
    "sg:postcode":"DA16 3HF",
    "sg:province":"Kent",
    "sg:tags":[
        "tea",
        "snack",
        "bar",
        "room"
    ],
    "wof:name":"Mum's Cafe",
    "wof:placetype":"venue"
},
  "geometry": {"coordinates":[0.1080989987,51.4635887146],"type":"Point"}
}