{
  "type": "Feature",
  "properties": {
    "addr:full":"11 Welby Street Grantham Lincolnshire NG31 6DY",
    "addr:housenumber":"11",
    "addr:postcode":"ng31 6dy",
    "addr:street":"Welby Street",
    "iso:country":"GB",
    "sg:address":"11 Welby Street",
    "sg:city":"Grantham",
    "sg:classifiers":[
        {
            "category":"Shopping",
            "subcategory":"Clothing, Apparel, & Fashions",
            "type":"Retail Goods"
        }
    ],
    "sg:phone":"+44 1476 577511",
    "sg:postcode":"NG31 6DY",
    "sg:province":"Lincolnshire",
    "sg:tags":[
        "lingerie",
        "hosiery"
    ],
    "wof:name":"Shadowlines Lingerie & Underwear",
    "wof:placetype":"venue"
},
  "geometry": {"coordinates":[-0.643653,52.910637],"type":"Point"}
}