{
  "type": "Feature",
  "properties": {
    "iso:country":"GB",
    "sg:address":"13 Belgrave Blvd",
    "sg:city":"Leicester",
    "sg:classifiers":[
        {
            "category":"Shopping",
            "type":"Retail Goods"
        }
    ],
    "sg:phone":"+44 116 235 8579",
    "sg:postcode":"LE4 2JD",
    "sg:province":"Leicestershire",
    "sg:tags":[
        "part",
        "accessory"
    ],
    "wof:name":"Raja Auto Spares",
    "wof:placetype":"venue"
},
  "geometry": {"coordinates":[-1.137821,52.66613],"type":"Point"}
}