{
  "type": "Feature",
  "properties": {
    "addr:full":"48a Barnby Gate Newark Nottinghamshire NG24 1QD",
    "addr:housenumber":"48a",
    "addr:postcode":"ng24 1qd",
    "addr:street":"Barnby Gate",
    "iso:country":"GB",
    "sg:address":"48a Barnby Gate",
    "sg:city":"Newark",
    "sg:classifiers":[
        {
            "category":"Shopping",
            "subcategory":"Pharmacy",
            "type":"Retail Goods"
        }
    ],
    "sg:postcode":"NG24 1QD",
    "sg:province":"Nottinghamshire",
    "sg:tags":[
        "pharmacist",
        "chemist"
    ],
    "wof:name":"Manor Pharmacy",
    "wof:placetype":"venue"
},
  "geometry": {"coordinates":[-0.805548,53.075245],"type":"Point"}
}