{
  "type": "Feature",
  "properties": {
    "iso:country":"GB",
    "sg:address":"134a Portobello High Street",
    "sg:city":"Edinburgh",
    "sg:classifiers":[
        {
            "category":"Food & Beverages",
            "subcategory":"Fruits & Vegetables",
            "type":"Retail Goods"
        }
    ],
    "sg:phone":"+44 131 669 7808",
    "sg:postcode":"EH15 1AH",
    "sg:province":"City of Edinburgh",
    "sg:tags":[
        "greengrocer"
    ],
    "wof:name":"Budget Fruit Supplies",
    "wof:placetype":"venue"
},
  "geometry": {"coordinates":[-3.114962,55.953457],"type":"Point"}
}