{
  "type": "Feature",
  "properties": {
    "addr:full":"Buckwell Farm, Ashburnham Battle East Sussex TN33 9PE",
    "addr:postcode":"tn33 9pe",
    "addr:street":"Battle",
    "iso:country":"GB",
    "sg:address":"Buckwell Farm, Ashburnham",
    "sg:city":"Battle",
    "sg:classifiers":[
        {
            "category":"Farming",
            "subcategory":"Livestock Farm",
            "type":"Manufacturing & Wholesale Goods"
        }
    ],
    "sg:postcode":"TN33 9PE",
    "sg:province":"East Sussex",
    "sg:tags":[
        "others"
    ],
    "wof:name":"V K Baker & Sons",
    "wof:placetype":"venue"
},
  "geometry": {"coordinates":[0.4890249968,50.9146156311],"type":"Point"}
}