{
  "type": "Feature",
  "properties": {
    "iso:country":"GB",
    "sg:address":"135 High Street",
    "sg:city":"London",
    "sg:classifiers":[
        {
            "category":"Food & Beverages",
            "subcategory":"Meat & Fish",
            "type":"Retail Goods"
        }
    ],
    "sg:phone":"+44 20 8520 3301",
    "sg:postcode":"E17 7DB",
    "sg:province":"Greater London",
    "sg:tags":[
        "butcher"
    ],
    "wof:name":"Mr Meats",
    "wof:placetype":"venue"
},
  "geometry": {"coordinates":[-0.0276350006,51.5831642151],"type":"Point"}
}