{
  "type": "Feature",
  "properties": {
    "addr:full":"12 Whitecross Way, Eldon Sq Newcastle-upon-tyne Tyne and Wear NE1 7XL",
    "addr:housenumber":"12",
    "addr:postcode":"ne1 7xl",
    "addr:street":"Whitecross Way;Sq",
    "iso:country":"GB",
    "sg:address":"12 Whitecross Way, Eldon Sq",
    "sg:city":"Newcastle-upon-tyne",
    "sg:classifiers":[
        {
            "category":"Food & Beverages",
            "subcategory":"Bakery",
            "type":"Retail Goods"
        }
    ],
    "sg:postcode":"NE1 7XL",
    "sg:province":"Tyne and Wear",
    "sg:tags":[
        "baker"
    ],
    "wof:name":"Peters Cathedral Bakers Ltd",
    "wof:placetype":"venue"
},
  "geometry": {"coordinates":[-1.6123689413,54.9779167175],"type":"Point"}
}