{
  "type": "Feature",
  "properties": {
    "addr:full":"26 London Road Hemel Hempstead Hertfordshire HP3 9SB",
    "addr:housenumber":"26",
    "addr:postcode":"hp3 9sb",
    "addr:street":"London Road",
    "iso:country":"GB",
    "sg:address":"26 London Road",
    "sg:city":"Hemel Hempstead",
    "sg:classifiers":[
        {
            "category":"Insurance",
            "subcategory":"Insurance Agent",
            "type":"Services"
        }
    ],
    "sg:phone":"+44 1442 251001",
    "sg:postcode":"HP3 9SB",
    "sg:province":"Hertfordshire",
    "wof:name":"Gade Insurance Services",
    "wof:placetype":"venue"
},
  "geometry": {"coordinates":[-0.468843,51.737514],"type":"Point"}
}