{
  "type": "Feature",
  "properties": {
    "addr:full":"Unit 2 East Side Industrial Estate, Mead Road Cheltenham Gloucestershire GL53 7EF",
    "addr:housenumber":"unit 2",
    "addr:postcode":"gl53 7ef",
    "addr:street":"Side Industrial Estate Mead Road",
    "iso:country":"GB",
    "sg:address":"Unit 2 East Side Industrial Estate, Mead Road",
    "sg:city":"Cheltenham",
    "sg:classifiers":[
        {
            "category":"Retail",
            "subcategory":"Auto Repair",
            "type":"Services"
        }
    ],
    "sg:postcode":"GL53 7EF",
    "sg:province":"Gloucestershire",
    "sg:tags":[
        "body",
        "car"
    ],
    "wof:name":"Cheltenham Body Repairs",
    "wof:placetype":"venue"
},
  "geometry": {"coordinates":[-2.0703799725,51.8808288574],"type":"Point"}
}