{
  "type": "Feature",
  "properties": {
    "iso:country":"GB",
    "sg:address":"Newton Street",
    "sg:city":"Paisley",
    "sg:classifiers":[
        {
            "category":"Farming",
            "subcategory":"Nursery",
            "type":"Manufacturing & Wholesale Goods"
        },
        {
            "category":"Education",
            "subcategory":"Preschool",
            "type":"Public Place"
        },
        {
            "category":"Government",
            "subcategory":"Office",
            "type":"Public Place"
        }
    ],
    "sg:phone":"+44 141 889 5350",
    "sg:postcode":"PA1 2RL",
    "sg:province":"Renfrewshire",
    "sg:tags":[
        "local",
        "school",
        "creche"
    ],
    "wof:name":"West Nursery School",
    "wof:placetype":"venue"
},
  "geometry": {"coordinates":[-4.440318,55.841442],"type":"Point"}
}