{
  "type": "Feature",
  "properties": {
    "addr:full":"32 Kings Clo Hendon Greater London NW4 2JT",
    "addr:housenumber":"32",
    "addr:postcode":"nw4 2jt",
    "addr:street":"Kings;Hendon",
    "iso:country":"GB",
    "sg:address":"32 Kings Clo",
    "sg:city":"Hendon",
    "sg:classifiers":[
        {
            "category":"Professional",
            "subcategory":"Employment Agencies",
            "type":"Services"
        }
    ],
    "sg:phone":"+44 20 8202 1246",
    "sg:postcode":"NW4 2JT",
    "sg:province":"Greater London",
    "sg:tags":[
        "consultant"
    ],
    "wof:name":"O D M Consultants",
    "wof:placetype":"venue"
},
  "geometry": {"coordinates":[-0.2116180062,51.5882225037],"type":"Point"}
}