{
  "type": "Feature",
  "properties": {
    "iso:country":"GB",
    "sg:address":"3a Maple Road",
    "sg:city":"Harpenden",
    "sg:classifiers":[
        {
            "category":"Banks & Credit Unions",
            "subcategory":"Investment Brokerage",
            "type":"Services"
        }
    ],
    "sg:postcode":"AL5 2DX",
    "sg:province":"Hertfordshire",
    "wof:name":"Paxton & Associates Ltd.",
    "wof:placetype":"venue"
},
  "geometry": {"coordinates":[-0.366505,51.816677],"type":"Point"}
}