{
  "type": "Feature",
  "properties": {
    "iso:country":"GB",
    "sg:address":"213 East India Dock Rd",
    "sg:city":"Poplar",
    "sg:classifiers":[
        {
            "category":"Social Services",
            "subcategory":"Retirement Home",
            "type":"Services"
        }
    ],
    "sg:phone":"+44 20 7538 2344",
    "sg:postcode":"E14 0ED",
    "sg:province":"Greater London",
    "sg:tags":[
        "care"
    ],
    "wof:name":"Cleshar Ltd",
    "wof:placetype":"venue"
},
  "geometry": {"coordinates":[-0.0110360002,51.5113792419],"type":"Point"}
}