{
  "type": "Feature",
  "properties": {
    "addr:full":"15 High Street Barry The Vale of Glamorgan CF62 7EA",
    "addr:housenumber":"15",
    "addr:postcode":"cf62 7ea",
    "addr:street":"High Street;Vale",
    "iso:country":"GB",
    "sg:address":"15 High Street",
    "sg:city":"Barry",
    "sg:classifiers":[
        {
            "category":"Real Estate",
            "subcategory":"Real Estate Agent",
            "type":"Services"
        }
    ],
    "sg:phone":"+44 1446 420600",
    "sg:postcode":"CF62 7EA",
    "sg:province":"The Vale of Glamorgan",
    "wof:name":"Park Estates",
    "wof:placetype":"venue"
},
  "geometry": {"coordinates":[-3.2841091156,51.3998222351],"type":"Point"}
}