{
  "type": "Feature",
  "properties": {
    "addr:full":"38 Boston Road, Gorse Hill Industrial Estate Leicester Leicestershire LE4 1AU",
    "addr:housenumber":"38;estate",
    "addr:postcode":"le4 1au",
    "addr:street":"Boston Road",
    "iso:country":"GB",
    "sg:address":"38 Boston Road, Gorse Hill Industrial Estate",
    "sg:city":"Leicester",
    "sg:classifiers":[
        {
            "category":"Manufacturing",
            "subcategory":"Metals",
            "type":"Manufacturing & Wholesale Goods"
        },
        {
            "category":"Professional",
            "subcategory":"Engineering",
            "type":"Services"
        }
    ],
    "sg:phone":"+44 116 236 8622",
    "sg:postcode":"LE4 1AU",
    "sg:province":"Leicestershire",
    "sg:tags":[
        "work",
        "sheet",
        "engineer"
    ],
    "wof:name":"J D Fabrications Leicester Ltd",
    "wof:placetype":"venue"
},
  "geometry": {"coordinates":[-1.1745380163,52.6651573181],"type":"Point"}
}