{
  "type": "Feature",
  "properties": {
    "addr:full":"Battery Grn Rd Lowestoft Suffolk NR32 1DH",
    "addr:postcode":"nr32 1dh",
    "addr:street":"Battery Grn Rd",
    "iso:country":"GB",
    "sg:address":"Battery Grn Rd",
    "sg:city":"Lowestoft",
    "sg:classifiers":[
        {
            "category":"Autos & Motor Vehicles",
            "subcategory":"Fuel & Gas Station",
            "type":"Retail Goods"
        }
    ],
    "sg:postcode":"NR32 1DH",
    "sg:province":"Suffolk",
    "sg:tags":[
        "petrol",
        "filling"
    ],
    "wof:name":"Battery Green Service Station",
    "wof:placetype":"venue"
},
  "geometry": {"coordinates":[1.753352046,52.4743881226],"type":"Point"}
}