{
  "type": "Feature",
  "properties": {
    "iso:country":"GB",
    "sg:address":"The Oast Ho, 5 Mead La",
    "sg:city":"Farnham",
    "sg:classifiers":[
        {
            "category":"Professional",
            "subcategory":"Business Services",
            "type":"Services"
        }
    ],
    "sg:phone":"+44 1252 733933",
    "sg:postcode":"GU9 7DY",
    "sg:province":"Surrey",
    "sg:tags":[
        "broker",
        "commodity"
    ],
    "wof:name":"Apex Minerals Ltd",
    "wof:placetype":"venue"
},
  "geometry": {"coordinates":[-0.800837,51.214321],"type":"Point"}
}