{
  "type": "Feature",
  "properties": {
    "addr:full":"21 Beaufort Road Newport Newport NP19 7ND",
    "addr:housenumber":"21",
    "addr:postcode":"np19 7nd",
    "addr:street":"Beaufort Road",
    "iso:country":"GB",
    "sg:address":"21 Beaufort Road",
    "sg:city":"Newport",
    "sg:classifiers":[
        {
            "category":"Bus Charters",
            "type":"Transportation"
        }
    ],
    "sg:phone":"+44 1633 258654",
    "sg:postcode":"NP19 7ND",
    "sg:province":"Newport",
    "sg:tags":[
        "hire",
        "coach"
    ],
    "wof:name":"Welsh Dragon Travel",
    "wof:placetype":"venue"
},
  "geometry": {"coordinates":[-2.969879,51.602154],"type":"Point"}
}