{
  "type": "Feature",
  "properties": {
    "addr:full":"St Margarets Gro London Greater London SE18 7RL",
    "addr:postcode":"se18 7rl",
    "addr:street":"Gro",
    "iso:country":"GB",
    "sg:address":"St Margarets Gro",
    "sg:city":"London",
    "sg:classifiers":[
        {
            "category":"Education",
            "subcategory":"School",
            "type":"Public Place"
        },
        {
            "category":"Government",
            "subcategory":"Office",
            "type":"Public Place"
        }
    ],
    "sg:phone":"+44 20 8854 3924",
    "sg:postcode":"SE18 7RL",
    "sg:province":"Greater London",
    "sg:tags":[
        "local",
        "authority"
    ],
    "wof:name":"St Margarets C of E Primary School",
    "wof:placetype":"venue"
},
  "geometry": {"coordinates":[0.0746100023,51.482460022],"type":"Point"}
}