{
  "type": "Feature",
  "properties": {
    "addr:full":"148 Marsh Road Luton Bedfordshire LU3 2NL",
    "addr:housenumber":"148",
    "addr:postcode":"lu3 2nl",
    "addr:street":"Marsh Road",
    "iso:country":"GB",
    "sg:address":"148 Marsh Road",
    "sg:city":"Luton",
    "sg:classifiers":[
        {
            "category":"Professional",
            "type":"Services"
        }
    ],
    "sg:phone":"+44 1582 570058",
    "sg:postcode":"LU3 2NL",
    "sg:province":"Bedfordshire",
    "sg:tags":[
        "repair",
        "tech",
        "maintenance"
    ],
    "wof:name":"P C Clinic",
    "wof:placetype":"venue"
},
  "geometry": {"coordinates":[-0.4512679875,51.9028816223],"type":"Point"}
}