{
  "type": "Feature",
  "properties": {
    "addr:full":"Telford Centre Telford Shropshire TF3 4BP",
    "addr:postcode":"tf3 4bp",
    "iso:country":"GB",
    "sg:address":"Telford Centre",
    "sg:city":"Telford",
    "sg:classifiers":[
        {
            "category":"Shopping",
            "subcategory":"Music",
            "type":"Retail Goods"
        }
    ],
    "sg:phone":"+44 1952 201079",
    "sg:postcode":"TF3 4BP",
    "sg:province":"Shropshire",
    "sg:tags":[
        "record",
        "tape",
        "cd"
    ],
    "wof:name":"Virgin Megastore",
    "wof:placetype":"venue"
},
  "geometry": {"coordinates":[-2.452487,52.67968],"type":"Point"}
}