{
  "type": "Feature",
  "properties": {
    "addr:full":"5-11 Oxford Rd Middlesbrough North Yorkshire TS5 5DY",
    "addr:housenumber":"5-11",
    "addr:postcode":"ts5 5dy",
    "addr:street":"Oxford Rd",
    "iso:country":"GB",
    "sg:address":"5-11 Oxford Rd",
    "sg:city":"Middlesbrough",
    "sg:classifiers":[
        {
            "category":"Home & Garden",
            "subcategory":"Furniture",
            "type":"Retail Goods"
        }
    ],
    "sg:postcode":"TS5 5DY",
    "sg:province":"North Yorkshire",
    "wof:name":"Mandale Reproductions",
    "wof:placetype":"venue"
},
  "geometry": {"coordinates":[-1.248044,54.557102],"type":"Point"}
}