{
  "type": "Feature",
  "properties": {
    "addr:full":"Dalfaber Rd Aviemore Highland PH22 1PX",
    "addr:postcode":"ph22 1px",
    "addr:street":"Dalfaber Rd",
    "iso:country":"GB",
    "sg:address":"Dalfaber Rd",
    "sg:city":"Aviemore",
    "sg:classifiers":[
        {
            "category":"Travel",
            "subcategory":"Hotels & Motels",
            "type":"Entertainment"
        }
    ],
    "sg:phone":"+44 1479 810236",
    "sg:postcode":"PH22 1PX",
    "sg:province":"Highland",
    "sg:tags":[
        "self",
        "catering"
    ],
    "wof:name":"Speyside Highland Leisure Park",
    "wof:placetype":"venue"
},
  "geometry": {"coordinates":[-3.8291120529,57.1856575012],"type":"Point"}
}