{
  "type": "Feature",
  "properties": {
    "addr:full":"16 Whitehill Drive, Brinsworth Rotherham South Yorkshire S60 5JN",
    "addr:housenumber":"16",
    "addr:postcode":"s60 5jn",
    "addr:street":"Whitehill Drive",
    "iso:country":"GB",
    "sg:address":"16 Whitehill Drive, Brinsworth",
    "sg:city":"Rotherham",
    "sg:classifiers":[
        {
            "category":"Building & Trades",
            "subcategory":"Landscaping Services",
            "type":"Services"
        }
    ],
    "sg:phone":"+44 1709 364442",
    "sg:postcode":"S60 5JN",
    "sg:province":"South Yorkshire",
    "sg:tags":[
        "gardening"
    ],
    "wof:name":"Cut Above Garden Services",
    "wof:placetype":"venue"
},
  "geometry": {"coordinates":[-1.3628269434,53.3995399475],"type":"Point"}
}