{
  "type": "Feature",
  "properties": {
    "addr:full":"90 Union Street Farnborough Hampshire GU14 7PY",
    "addr:housenumber":"90",
    "addr:postcode":"gu14 7py",
    "addr:street":"Union Street",
    "iso:country":"GB",
    "sg:address":"90 Union Street",
    "sg:city":"Farnborough",
    "sg:classifiers":[
        {
            "category":"Manufacturing",
            "subcategory":"Wood Products",
            "type":"Manufacturing & Wholesale Goods"
        },
        {
            "category":"Building & Trades",
            "subcategory":"Construction",
            "type":"Services"
        }
    ],
    "sg:phone":"+44 1252 512753",
    "sg:postcode":"GU14 7PY",
    "sg:province":"Hampshire",
    "sg:tags":[
        "joinery",
        "sawmill",
        "shaving"
    ],
    "wof:name":"A P M & Son",
    "wof:placetype":"venue"
},
  "geometry": {"coordinates":[-0.760637,51.295326],"type":"Point"}
}