{
  "type": "Feature",
  "properties": {
    "addr:full":"Unit 3 Crown Works, Worth Way Keighley West Yorkshire BD21 5LR",
    "addr:housenumber":"unit 3",
    "addr:postcode":"bd21 5lr",
    "addr:street":"Crown Works Worth Way",
    "iso:country":"GB",
    "sg:address":"Unit 3 Crown Works, Worth Way",
    "sg:city":"Keighley",
    "sg:classifiers":[
        {
            "category":"Building & Trades",
            "subcategory":"Construction",
            "type":"Services"
        }
    ],
    "sg:phone":"+44 1535 611116",
    "sg:postcode":"BD21 5LR",
    "sg:province":"West Yorkshire",
    "sg:tags":[
        "roofing"
    ],
    "wof:name":"Craft Ltd",
    "wof:placetype":"venue"
},
  "geometry": {"coordinates":[-1.909674,53.866364],"type":"Point"}
}