{
  "type": "Feature",
  "properties": {
    "iso:country":"GB",
    "sg:address":"Mill St",
    "sg:city":"Wincanton",
    "sg:classifiers":[
        {
            "category":"Place Of Worship",
            "type":"Public Place"
        }
    ],
    "sg:phone":"+44 1963 34477",
    "sg:postcode":"BA9 9AP",
    "sg:province":"Somerset",
    "wof:name":"Wincanton Baptist Church",
    "wof:placetype":"venue"
},
  "geometry": {"coordinates":[-2.4138629436,51.0559234619],"type":"Point"}
}