{
  "type": "Feature",
  "properties": {
    "addr:full":"Fire Safety, Parr Stocks Rd St Helens Cheshire WA9 1NU",
    "addr:postcode":"wa9 1nu",
    "addr:street":"Stocks Rd",
    "iso:country":"GB",
    "sg:address":"Fire Safety, Parr Stocks Rd",
    "sg:city":"St Helens",
    "sg:classifiers":[
        {
            "category":"Professional",
            "subcategory":"Management & Consulting",
            "type":"Services"
        }
    ],
    "sg:phone":"+44 1744 29126",
    "sg:postcode":"WA9 1NU",
    "sg:province":"Cheshire",
    "sg:tags":[
        "fire",
        "consultant",
        "protection"
    ],
    "wof:name":"Merseyside Fire & Civil Defence Authority",
    "wof:placetype":"venue"
},
  "geometry": {"coordinates":[-2.7112240791,53.4507064819],"type":"Point"}
}