{
  "type": "Feature",
  "properties": {
    "iso:country":"GB",
    "sg:address":"The Old Priory, 17-19 Church Square, Midsomer Norton",
    "sg:city":"Bath",
    "sg:classifiers":[
        {
            "category":"Restaurant",
            "type":"Food & Drink"
        }
    ],
    "sg:phone":"+44 1761 416784",
    "sg:postcode":"BA3 2HX",
    "sg:province":"Somerset",
    "wof:name":"Listed Hotels Ltd.",
    "wof:placetype":"venue"
},
  "geometry": {"coordinates":[-2.4871239662,51.2867698669],"type":"Point"}
}