{
  "type": "Feature",
  "properties": {
    "addr:full":"Aveland Clo Bourne Lincolnshire PE10 9EJ",
    "addr:postcode":"pe10 9ej",
    "addr:street":"Bourne",
    "iso:country":"GB",
    "sg:address":"Aveland Clo",
    "sg:city":"Bourne",
    "sg:classifiers":[
        {
            "category":"Building & Trades",
            "subcategory":"Landscaping Services",
            "type":"Services"
        }
    ],
    "sg:phone":"+44 1778 394679",
    "sg:postcode":"PE10 9EJ",
    "sg:province":"Lincolnshire",
    "sg:tags":[
        "landscape",
        "contractor"
    ],
    "wof:name":"Greenthumb Lawn Treatment Services",
    "wof:placetype":"venue"
},
  "geometry": {"coordinates":[-0.38352,52.769279],"type":"Point"}
}