{
  "type": "Feature",
  "properties": {
    "iso:country":"GB",
    "sg:address":"109 Deepcut Bridge Road, Deepcut",
    "sg:city":"Camberley",
    "sg:classifiers":[
        {
            "category":"Retail",
            "subcategory":"Auto Repair",
            "type":"Services"
        }
    ],
    "sg:phone":"+44 1252 835475",
    "sg:postcode":"GU16 6SD",
    "sg:province":"Hampshire",
    "sg:tags":[
        "modification",
        "garage"
    ],
    "wof:name":"W Koster Ltd.",
    "wof:placetype":"venue"
},
  "geometry": {"coordinates":[-0.7035809755,51.3090705872],"type":"Point"}
}