{
  "type": "Feature",
  "properties": {
    "addr:full":"Under Brow Farm, Cribden Side, Haslingden Rossendale Lancashire BB4 5UB",
    "addr:postcode":"bb4 5ub",
    "addr:street":"Under Brow;Cribden Side",
    "iso:country":"GB",
    "sg:address":"Under Brow Farm, Cribden Side, Haslingden",
    "sg:city":"Rossendale",
    "sg:classifiers":[
        {
            "category":"Utilities",
            "subcategory":"Refuse",
            "type":"Services"
        }
    ],
    "sg:phone":"+44 1706 210485",
    "sg:postcode":"BB4 5UB",
    "sg:province":"Lancashire",
    "sg:tags":[
        "disposal",
        "waste",
        "retail"
    ],
    "wof:name":"Alternative Waste Management",
    "wof:placetype":"venue"
},
  "geometry": {"coordinates":[-2.325394,53.704639],"type":"Point"}
}