{
  "type": "Feature",
  "properties": {
    "iso:country":"GB",
    "sg:address":"25 Market Place",
    "sg:city":"Heywood",
    "sg:classifiers":[
        {
            "category":"Professional",
            "subcategory":"Lawyer & Legal Services",
            "type":"Services"
        }
    ],
    "sg:phone":"+44 1706 367442",
    "sg:postcode":"OL10 1LA",
    "sg:province":"Lancashire",
    "sg:tags":[
        "solicitor"
    ],
    "wof:name":"H.S Wild & Co",
    "wof:placetype":"venue"
},
  "geometry": {"coordinates":[-2.22025,53.593559],"type":"Point"}
}