{
  "type": "Feature",
  "properties": {
    "iso:country":"GB",
    "sg:address":"Woodstock, Worfield",
    "sg:city":"Bridgnorth",
    "sg:classifiers":[
        {
            "category":"Freight",
            "type":"Transportation"
        }
    ],
    "sg:phone":"+44 1746 765299",
    "sg:postcode":"WV15 5NR",
    "sg:province":"Shropshire",
    "sg:tags":[
        "haulage",
        "road"
    ],
    "wof:name":"P & G Marsh",
    "wof:placetype":"venue"
},
  "geometry": {"coordinates":[-2.358624,52.556946],"type":"Point"}
}