{
  "type": "Feature",
  "properties": {
    "addr:full":"14 Lumley Road Skegness Lincolnshire PE25 3NG",
    "addr:housenumber":"14",
    "addr:postcode":"pe25 3ng",
    "addr:street":"Lumley Road",
    "iso:country":"GB",
    "sg:address":"14 Lumley Road",
    "sg:city":"Skegness",
    "sg:classifiers":[
        {
            "category":"Food & Beverages",
            "subcategory":"Bakery",
            "type":"Retail Goods"
        }
    ],
    "sg:postcode":"PE25 3NG",
    "sg:province":"Lincolnshire",
    "sg:tags":[
        "baker",
        "confectionery"
    ],
    "wof:name":"The Bakers Choice Ltd.",
    "wof:placetype":"venue"
},
  "geometry": {"coordinates":[0.3368200064,53.1433792114],"type":"Point"}
}