{
  "type": "Feature",
  "properties": {
    "addr:full":"Edward House, Tenter Street Rotherham South Yorkshire S60 1LB",
    "addr:postcode":"s60 1lb",
    "addr:street":"Tenter Street",
    "iso:country":"GB",
    "sg:address":"Edward House, Tenter Street",
    "sg:city":"Rotherham",
    "sg:classifiers":[
        {
            "category":"Shopping",
            "subcategory":"Clothing, Apparel, & Fashions",
            "type":"Retail Goods"
        }
    ],
    "sg:phone":"+44 1709 365005",
    "sg:postcode":"S60 1LB",
    "sg:province":"South Yorkshire",
    "sg:tags":[
        "staff",
        "wear",
        "uniform"
    ],
    "wof:name":"E Russum & Sons Ltd.",
    "wof:placetype":"venue"
},
  "geometry": {"coordinates":[-1.367311,53.434864],"type":"Point"}
}