{
  "type": "Feature",
  "properties": {
    "iso:country":"GB",
    "sg:address":"Nash House, St.george St",
    "sg:city":"West End",
    "sg:classifiers":[
        {
            "category":"Banks & Credit Unions",
            "subcategory":"Bank",
            "type":"Services"
        }
    ],
    "sg:phone":"+44 20 7493 1445",
    "sg:postcode":"W1R 9DQ",
    "sg:province":"Hampshire",
    "wof:name":"State Bank of India",
    "wof:placetype":"venue"
},
  "geometry": {"coordinates":[-0.142851,51.511974],"type":"Point"}
}