{
  "type": "Feature",
  "properties": {
    "addr:full":"Unit 10, Bridge St Development Ellon Aberdeenshire AB41 9AA",
    "addr:housenumber":"unit 10",
    "addr:postcode":"ab41 9aa",
    "addr:street":"Bridge St",
    "iso:country":"GB",
    "sg:address":"Unit 10, Bridge St Development",
    "sg:city":"Ellon",
    "sg:classifiers":[
        {
            "category":"Sports & Exercise",
            "subcategory":"Sports Center",
            "type":"Entertainment"
        }
    ],
    "sg:phone":"+44 1358 721173",
    "sg:postcode":"AB41 9AA",
    "sg:province":"Aberdeenshire",
    "sg:tags":[
        "shop",
        "good"
    ],
    "wof:name":"Excell Sports & Leisure",
    "wof:placetype":"venue"
},
  "geometry": {"coordinates":[-2.074669,57.365395],"type":"Point"}
}