{
  "type": "Feature",
  "properties": {
    "iso:country":"GB",
    "sg:address":"1st Floor Woburn Ct, 8 Guildhall Hill",
    "sg:city":"Norwich",
    "sg:classifiers":[
        {
            "category":"Health Services",
            "subcategory":"Health Practitioner",
            "type":"Services"
        }
    ],
    "sg:phone":"+44 1603 219254",
    "sg:postcode":"NR2 1JG",
    "sg:province":"Norfolk",
    "sg:tags":[
        "acupuncture"
    ],
    "wof:name":"A F Farrant",
    "wof:placetype":"venue"
},
  "geometry": {"coordinates":[1.29317,52.629292],"type":"Point"}
}