{
  "type": "Feature",
  "properties": {
    "iso:country":"GB",
    "sg:address":"Dovecote Farm, Wainfleet St Mary",
    "sg:city":"Skegness",
    "sg:classifiers":[
        {
            "category":"Farming",
            "subcategory":"Livestock Farm",
            "type":"Manufacturing & Wholesale Goods"
        }
    ],
    "sg:postcode":"PE24 4AG",
    "sg:province":"Lincolnshire",
    "sg:tags":[
        "others"
    ],
    "wof:name":"T Peak & Son",
    "wof:placetype":"venue"
},
  "geometry": {"coordinates":[0.25091,53.10466],"type":"Point"}
}