{
  "type": "Feature",
  "properties": {
    "addr:full":"Unit B1 Hartford House, Weston Street Bolton Lancashire BL3 2AW",
    "addr:postcode":"bl3 2aw",
    "addr:street":"Weston Street",
    "iso:country":"GB",
    "sg:address":"Unit B1 Hartford House, Weston Street",
    "sg:city":"Bolton",
    "sg:classifiers":[
        {
            "category":"Retail",
            "subcategory":"Auto Repair",
            "type":"Services"
        }
    ],
    "sg:phone":"+44 1204 396434",
    "sg:postcode":"BL3 2AW",
    "sg:province":"Lancashire",
    "sg:tags":[
        "modification",
        "garage"
    ],
    "wof:name":"Haworth's Body & Chassis Repairs",
    "wof:placetype":"venue"
},
  "geometry": {"coordinates":[-2.417979002,53.5669898987],"type":"Point"}
}