{
  "type": "Feature",
  "properties": {
    "addr:full":"Priestley Road, Worsley Manchester Greater Manchester M28 2UT",
    "addr:postcode":"m28 2ut",
    "addr:street":"Priestley Road",
    "iso:country":"GB",
    "sg:address":"Priestley Road, Worsley",
    "sg:city":"Manchester",
    "sg:classifiers":[
        {
            "category":"Utilities",
            "subcategory":"Natural Gas",
            "type":"Services"
        }
    ],
    "sg:phone":"+44 161 794 4651",
    "sg:postcode":"M28 2UT",
    "sg:province":"Greater Manchester",
    "sg:tags":[
        "supplier"
    ],
    "wof:name":"Boc Gases",
    "wof:placetype":"venue"
},
  "geometry": {"coordinates":[-2.3551719189,53.5149917603],"type":"Point"}
}