{
  "type": "Feature",
  "properties": {
    "addr:full":"Wesley Court High Wycombe Buckinghamshire HP13 6SE",
    "addr:postcode":"hp13 6se",
    "addr:street":"Wesley;High",
    "iso:country":"GB",
    "sg:address":"Wesley Court",
    "sg:city":"High Wycombe",
    "sg:classifiers":[
        {
            "category":"Professional",
            "subcategory":"Advertising",
            "type":"Services"
        }
    ],
    "sg:phone":"+44 1494 442900",
    "sg:postcode":"HP13 6SE",
    "sg:province":"Buckinghamshire",
    "sg:tags":[
        "mail",
        "direct"
    ],
    "wof:name":"Data Quality Management Group Ltd.",
    "wof:placetype":"venue"
},
  "geometry": {"coordinates":[-0.7477890253,51.628944397],"type":"Point"}
}