{
  "type": "Feature",
  "properties": {
    "addr:full":"12 Guildford St Chertsey Surrey KT16 9BQ",
    "addr:housenumber":"12",
    "addr:postcode":"kt16 9bq",
    "addr:street":"Guildford St",
    "iso:country":"GB",
    "sg:address":"12 Guildford St",
    "sg:city":"Chertsey",
    "sg:classifiers":[
        {
            "category":"Organizations",
            "subcategory":"Non-profit Organization",
            "type":"Services"
        }
    ],
    "sg:phone":"+44 1932 570888",
    "sg:postcode":"KT16 9BQ",
    "sg:province":"Surrey",
    "sg:tags":[
        "organisation",
        "voluntary",
        "charity"
    ],
    "wof:name":"NACRO",
    "wof:placetype":"venue"
},
  "geometry": {"coordinates":[-0.5080720186,51.3873901367],"type":"Point"}
}