{
  "type": "Feature",
  "properties": {
    "addr:full":"4 Lowgate Lane, Surfleet Spalding Lincolnshire PE11 4AS",
    "addr:housenumber":"4",
    "addr:postcode":"pe11 4as",
    "addr:street":"Lowgate Lane",
    "iso:country":"GB",
    "sg:address":"4 Lowgate Lane, Surfleet",
    "sg:city":"Spalding",
    "sg:classifiers":[
        {
            "category":"Taxi",
            "type":"Transportation"
        }
    ],
    "sg:phone":"+44 1775 680993",
    "sg:postcode":"PE11 4AS",
    "sg:province":"Lincolnshire",
    "sg:tags":[
        "mini",
        "cab"
    ],
    "wof:name":"Mel's Taxis",
    "wof:placetype":"venue"
},
  "geometry": {"coordinates":[-0.144253,52.837387],"type":"Point"}
}