{
  "type": "Feature",
  "properties": {
    "addr:full":"35 Wharf Road, Wraysbury Staines Berkshire TW19 5JQ",
    "addr:housenumber":"35",
    "addr:postcode":"tw19 5jq",
    "addr:street":"Wharf Road",
    "iso:country":"GB",
    "sg:address":"35 Wharf Road, Wraysbury",
    "sg:city":"Staines",
    "sg:classifiers":[
        {
            "category":"Recreation",
            "subcategory":"Boat Charter",
            "type":"Entertainment"
        }
    ],
    "sg:phone":"+44 1784 482439",
    "sg:postcode":"TW19 5JQ",
    "sg:province":"Berkshire",
    "sg:tags":[
        "rental",
        "leasing",
        "excursion"
    ],
    "sg:website":"http://www.gobarging.com",
    "wof:name":"European Waterways Ltd.",
    "wof:placetype":"venue"
},
  "geometry": {"coordinates":[-0.5701760054,51.455242157],"type":"Point"}
}