{
  "type": "Feature",
  "properties": {
    "iso:country":"GB",
    "sg:address":"Rykneld Street, Alrewas",
    "sg:city":"Burton-on-trent",
    "sg:classifiers":[
        {
            "category":"Organizations",
            "subcategory":"Membership Organization",
            "type":"Services"
        }
    ],
    "sg:phone":"+44 1283 790962",
    "sg:postcode":"DE13 7AX",
    "sg:province":"Derbyshire",
    "sg:tags":[
        "club"
    ],
    "wof:name":"Alrewas & District Royal British Legion Club Ltd.",
    "wof:placetype":"venue"
},
  "geometry": {"coordinates":[-1.741962,52.729996],"type":"Point"}
}