{
  "type": "Feature",
  "properties": {
    "addr:full":"Coach House, North Road, West Bridgeford Nottingham Nottinghamshire NG2 7NH",
    "addr:postcode":"ng2 7nh",
    "addr:street":"North Road West",
    "iso:country":"GB",
    "sg:address":"Coach House, North Road, West Bridgeford",
    "sg:city":"Nottingham",
    "sg:classifiers":[
        {
            "category":"Education",
            "subcategory":"Special Training",
            "type":"Public Place"
        }
    ],
    "sg:phone":"+44 115 981 5346",
    "sg:postcode":"NG2 7NH",
    "sg:province":"Nottinghamshire",
    "sg:tags":[
        "product",
        "centre"
    ],
    "wof:name":"John Boardman Training Ltd",
    "wof:placetype":"venue"
},
  "geometry": {"coordinates":[-1.1364740133,52.927116394],"type":"Point"}
}