{
  "type": "Feature",
  "properties": {
    "iso:country":"GB",
    "sg:address":"High Street, South Hylton",
    "sg:city":"Sunderland",
    "sg:classifiers":[
        {
            "category":"Bars & Pubs",
            "type":"Food & Drink"
        }
    ],
    "sg:phone":"+44 191 534 6049",
    "sg:postcode":"SR4 0PZ",
    "sg:province":"Tyne and Wear",
    "sg:tags":[
        "pubs",
        "inn"
    ],
    "wof:name":"The Jolly Potter",
    "wof:placetype":"venue"
},
  "geometry": {"coordinates":[-1.4523340464,54.9058113098],"type":"Point"}
}