{
  "type": "Feature",
  "properties": {
    "iso:country":"GB",
    "sg:address":"27b Main Street",
    "sg:city":"Cowdenbeath",
    "sg:classifiers":[
        {
            "category":"Food & Beverages",
            "subcategory":"Bakery",
            "type":"Retail Goods"
        }
    ],
    "sg:postcode":"KY4 8AJ",
    "sg:province":"Fife",
    "sg:tags":[
        "baker"
    ],
    "wof:name":"J Wilson Bakers",
    "wof:placetype":"venue"
},
  "geometry": {"coordinates":[-3.375386,56.084332],"type":"Point"}
}