{
  "type": "Feature",
  "properties": {
    "iso:country":"GB",
    "sg:address":"257 Hagley Road",
    "sg:city":"Birmingham",
    "sg:classifiers":[
        {
            "category":"Travel",
            "subcategory":"Hotels & Motels",
            "type":"Entertainment"
        }
    ],
    "sg:phone":"+44 121 454 6061",
    "sg:postcode":"B16 8LA",
    "sg:province":"West Midlands",
    "wof:name":"Choice Hotels Europe",
    "wof:placetype":"venue"
},
  "geometry": {"coordinates":[-1.931549,52.471951],"type":"Point"}
}