{
  "type": "Feature",
  "properties": {
    "addr:full":"77 Burnley Road London Greater London NW10 1EE",
    "addr:housenumber":"77",
    "addr:postcode":"nw10 1ee",
    "addr:street":"Burnley Road",
    "iso:country":"GB",
    "sg:address":"77 Burnley Road",
    "sg:city":"London",
    "sg:classifiers":[
        {
            "category":"Health Services",
            "subcategory":"Doctor",
            "type":"Services"
        }
    ],
    "sg:phone":"+44 20 8452 7689",
    "sg:postcode":"NW10 1EE",
    "sg:province":"Greater London",
    "sg:tags":[
        "practitioners"
    ],
    "wof:name":"S C Woko",
    "wof:placetype":"venue"
},
  "geometry": {"coordinates":[-0.239869,51.55257],"type":"Point"}
}