{
  "type": "Feature",
  "properties": {
    "iso:country":"GB",
    "sg:address":"Old Fire Station, South Nelson Road, South Nelson Industrial Estate",
    "sg:city":"Cramlington",
    "sg:classifiers":[
        {
            "category":"Manufacturing",
            "subcategory":"Petroleum Products",
            "type":"Manufacturing & Wholesale Goods"
        },
        {
            "category":"Retail",
            "subcategory":"Event Space",
            "type":"Services"
        }
    ],
    "sg:phone":"+44 1670 739999",
    "sg:postcode":"NE23 1WF",
    "sg:province":"Northumberland",
    "sg:tags":[
        "pipeline",
        "manufacturer"
    ],
    "wof:name":"Advanced Engineering Solutions Ltd",
    "wof:placetype":"venue"
},
  "geometry": {"coordinates":[-1.608504,55.095196],"type":"Point"}
}