{
  "type": "Feature",
  "properties": {
    "iso:country":"GB",
    "sg:address":"48 Wigan Lane",
    "sg:city":"Wigan",
    "sg:classifiers":[
        {
            "category":"Home & Garden",
            "subcategory":"Household Appliances",
            "type":"Retail Goods"
        }
    ],
    "sg:phone":"+44 1942 246205",
    "sg:postcode":"WN1 1XS",
    "sg:province":"Lancashire",
    "sg:tags":[
        "electrical"
    ],
    "wof:name":"New World Washing Machine Engineers",
    "wof:placetype":"venue"
},
  "geometry": {"coordinates":[-2.627789,53.552799],"type":"Point"}
}