{
  "type": "Feature",
  "properties": {
    "addr:full":"11a Hannell Road London Greater London SW6 7RA",
    "addr:housenumber":"11a",
    "addr:postcode":"sw6 7ra",
    "addr:street":"Hannell Road",
    "iso:country":"GB",
    "sg:address":"11a Hannell Road",
    "sg:city":"London",
    "sg:classifiers":[
        {
            "category":"Autos & Motor Vehicles",
            "subcategory":"Automobile Sales",
            "type":"Retail Goods"
        }
    ],
    "sg:phone":"+44 20 7610 0500",
    "sg:postcode":"SW6 7RA",
    "sg:province":"Greater London",
    "sg:tags":[
        "car",
        "specialist",
        "sales",
        "classic"
    ],
    "wof:name":"Autotoy Ltd.",
    "wof:placetype":"venue"
},
  "geometry": {"coordinates":[-0.210892,51.481213],"type":"Point"}
}