{
  "type": "Feature",
  "properties": {
    "iso:country":"GB",
    "sg:address":"87 Sandys Road",
    "sg:city":"Basingstoke",
    "sg:classifiers":[
        {
            "category":"Home & Garden",
            "subcategory":"Household Appliances",
            "type":"Retail Goods"
        }
    ],
    "sg:postcode":"RG22 6AU",
    "sg:province":"Hampshire",
    "sg:tags":[
        "electrical",
        "domestic"
    ],
    "wof:name":"Pyro Control Ltd.",
    "wof:placetype":"venue"
},
  "geometry": {"coordinates":[-1.108681,51.256863],"type":"Point"}
}