{
  "type": "Feature",
  "properties": {
    "iso:country":"GB",
    "sg:address":"68 George St",
    "sg:city":"Hastings",
    "sg:classifiers":[
        {
            "category":"Arts & Performance",
            "subcategory":"Arts Center",
            "type":"Entertainment"
        }
    ],
    "sg:phone":"+44 1424 435711",
    "sg:postcode":"TN34 3EE",
    "sg:province":"East Sussex",
    "sg:tags":[
        "centre"
    ],
    "wof:name":"Same Sky",
    "wof:placetype":"venue"
},
  "geometry": {"coordinates":[0.590207,50.864445],"type":"Point"}
}