{
  "type": "Feature",
  "properties": {
    "addr:full":"4 North Street, Portslade Brighton East Sussex BN41 1DG",
    "addr:housenumber":"4",
    "addr:postcode":"bn41 1dg",
    "addr:street":"North Street",
    "iso:country":"GB",
    "sg:address":"4 North Street, Portslade",
    "sg:city":"Brighton",
    "sg:classifiers":[
        {
            "category":"Personal",
            "subcategory":"Beauty Salon",
            "type":"Services"
        }
    ],
    "sg:phone":"+44 1273 418481",
    "sg:postcode":"BN41 1DG",
    "sg:province":"East Sussex",
    "sg:tags":[
        "lady",
        "hairdresser"
    ],
    "wof:name":"Stewart Hair Care",
    "wof:placetype":"venue"
},
  "geometry": {"coordinates":[-0.2085410058,50.8305931091],"type":"Point"}
}