{
  "type": "Feature",
  "properties": {
    "addr:full":"9 Westgate Kendal Cumbria LA9 6HX",
    "addr:housenumber":"9",
    "addr:postcode":"la9 6hx",
    "addr:street":"Westgate",
    "iso:country":"GB",
    "sg:address":"9 Westgate",
    "sg:city":"Kendal",
    "sg:classifiers":[
        {
            "category":"Home & Garden",
            "subcategory":"Household Appliances",
            "type":"Retail Goods"
        }
    ],
    "sg:phone":"+44 1539 726372",
    "sg:postcode":"LA9 6HX",
    "sg:province":"Cumbria",
    "sg:tags":[
        "repairs",
        "electrical",
        "domestic",
        "servicing"
    ],
    "wof:name":"Frank P Sharpe",
    "wof:placetype":"venue"
},
  "geometry": {"coordinates":[-2.735789,54.331333],"type":"Point"}
}