{
  "type": "Feature",
  "properties": {
    "addr:full":"52a Green La London Greater London W7 2PB",
    "addr:housenumber":"52a",
    "addr:postcode":"w7 2pb",
    "addr:street":"Green La",
    "iso:country":"GB",
    "sg:address":"52a Green La",
    "sg:city":"London",
    "sg:classifiers":[
        {
            "category":"Professional",
            "subcategory":"Detective & Security Services",
            "type":"Services"
        }
    ],
    "sg:postcode":"W7 2PB",
    "sg:province":"Greater London",
    "sg:tags":[
        "alarm",
        "burglar",
        "system"
    ],
    "wof:name":"Ironside Security Services",
    "wof:placetype":"venue"
},
  "geometry": {"coordinates":[-0.342848,51.505051],"type":"Point"}
}