{
  "type": "Feature",
  "properties": {
    "iso:country":"GB",
    "sg:address":"199 Shaftesbury Avenue",
    "sg:city":"London",
    "sg:classifiers":[
        {
            "category":"Home & Garden",
            "subcategory":"Hardware",
            "type":"Retail Goods"
        }
    ],
    "sg:postcode":"WC2H 8JR",
    "sg:province":"Greater London",
    "sg:tags":[
        "retailer",
        "lighting"
    ],
    "wof:name":"Christopher Wrays Lighting Emporium Ltd.",
    "wof:placetype":"venue"
},
  "geometry": {"coordinates":[-0.1269759983,51.5154724121],"type":"Point"}
}