{
  "type": "Feature",
  "properties": {
    "addr:full":"255 London Road, Horndean Waterlooville Hampshire PO8 0HW",
    "addr:housenumber":"255",
    "addr:postcode":"po8 0hw",
    "addr:street":"London Road",
    "iso:country":"GB",
    "sg:address":"255 London Road, Horndean",
    "sg:city":"Waterlooville",
    "sg:classifiers":[
        {
            "category":"Building & Trades",
            "subcategory":"Construction",
            "type":"Services"
        }
    ],
    "sg:phone":"+44 23 9259 8303",
    "sg:postcode":"PO8 0HW",
    "sg:province":"Hampshire",
    "sg:tags":[
        "dry",
        "plastering",
        "plasterers",
        "lining",
        "related",
        "screeders"
    ],
    "wof:name":"K A Othen",
    "wof:placetype":"venue"
},
  "geometry": {"coordinates":[-0.996859014,50.9296302795],"type":"Point"}
}