{
  "type": "Feature",
  "properties": {
    "addr:full":"110 Ferney Road Barnet Hertfordshire EN4 8LE",
    "addr:housenumber":"110",
    "addr:postcode":"en4 8le",
    "addr:street":"Ferney Road",
    "iso:country":"GB",
    "sg:address":"110 Ferney Road",
    "sg:city":"Barnet",
    "sg:classifiers":[
        {
            "category":"Home & Garden",
            "subcategory":"Building Materials",
            "type":"Retail Goods"
        }
    ],
    "sg:phone":"+44 20 8368 3388",
    "sg:postcode":"EN4 8LE",
    "sg:province":"Hertfordshire",
    "sg:tags":[
        "fencing"
    ],
    "wof:name":"Kenneth Allen Fencing",
    "wof:placetype":"venue"
},
  "geometry": {"coordinates":[-0.145648,51.633125],"type":"Point"}
}