{
  "type": "Feature",
  "properties": {
    "addr:full":"153 St.georges Rd Coventry West Midlands CV1 2DH",
    "addr:housenumber":"153",
    "addr:postcode":"cv1 2dh",
    "addr:street":"St.Georges Rd",
    "iso:country":"GB",
    "sg:address":"153 St.georges Rd",
    "sg:city":"Coventry",
    "sg:classifiers":[
        {
            "category":"Fast Food",
            "type":"Food & Drink"
        }
    ],
    "sg:postcode":"CV1 2DH",
    "sg:province":"West Midlands",
    "sg:tags":[
        "away",
        "take"
    ],
    "wof:name":"Momin,Ali,",
    "wof:placetype":"venue"
},
  "geometry": {"coordinates":[-1.4904739857,52.4039039612],"type":"Point"}
}