{
  "type": "Feature",
  "properties": {
    "addr:full":"10 Southdown Avenue Chesterfield Derbyshire S40 4QL",
    "addr:housenumber":"10",
    "addr:postcode":"s40 4ql",
    "addr:street":"Southdown Avenue",
    "iso:country":"GB",
    "sg:address":"10 Southdown Avenue",
    "sg:city":"Chesterfield",
    "sg:classifiers":[
        {
            "category":"Building & Trades",
            "subcategory":"Plumbing",
            "type":"Services"
        }
    ],
    "sg:postcode":"S40 4QL",
    "sg:province":"Derbyshire",
    "sg:tags":[
        "heating"
    ],
    "wof:name":"Ted Gibbions Plumber",
    "wof:placetype":"venue"
},
  "geometry": {"coordinates":[-1.4605870247,53.2440681458],"type":"Point"}
}