{
  "type": "Feature",
  "properties": {
    "iso:country":"GB",
    "sg:address":"Norway Drive",
    "sg:city":"Slough",
    "sg:classifiers":[
        {
            "category":"Arena",
            "subcategory":"Sports Club",
            "type":"Entertainment"
        }
    ],
    "sg:phone":"+44 1753 694972",
    "sg:postcode":"SL2 5QP",
    "sg:province":"Berkshire",
    "wof:name":"Wexham Bowls Club",
    "wof:placetype":"venue"
},
  "geometry": {"coordinates":[-0.5764459968,51.5260047913],"type":"Point"}
}