{
  "type": "Feature",
  "properties": {
    "addr:full":"1 Byron Avenue Sowerby Bridge West Yorkshire HX6 2HF",
    "addr:housenumber":"1",
    "addr:postcode":"hx6 2hf",
    "addr:street":"Byron Avenue",
    "iso:country":"GB",
    "sg:address":"1 Byron Avenue",
    "sg:city":"Sowerby Bridge",
    "sg:classifiers":[
        {
            "category":"Personal",
            "subcategory":"Beauty Salon",
            "type":"Services"
        }
    ],
    "sg:phone":"+44 1422 831001",
    "sg:postcode":"HX6 2HF",
    "sg:province":"West Yorkshire",
    "sg:tags":[
        "unisex",
        "hairdresser"
    ],
    "wof:name":"Focus",
    "wof:placetype":"venue"
},
  "geometry": {"coordinates":[-1.913524,53.713539],"type":"Point"}
}