{
  "type": "Feature",
  "properties": {
    "addr:full":"22 Village Drive, Ribbleton Preston Lancashire PR2 6JH",
    "addr:housenumber":"22",
    "addr:postcode":"pr2 6jh",
    "addr:street":"Village Drive",
    "iso:country":"GB",
    "sg:address":"22 Village Drive, Ribbleton",
    "sg:city":"Preston",
    "sg:classifiers":[
        {
            "category":"Professional",
            "subcategory":"Secretarial Services",
            "type":"Services"
        }
    ],
    "sg:phone":"+44 1772 496875",
    "sg:postcode":"PR2 6JH",
    "sg:province":"Lancashire",
    "wof:name":"Admin Express",
    "wof:placetype":"venue"
},
  "geometry": {"coordinates":[-2.6557629108,53.7703666687],"type":"Point"}
}