{
  "type": "Feature",
  "properties": {
    "addr:full":"Fleet Garage, Rear Of 399 Bradford West Yorkshire BD3 7JF",
    "addr:housenumber":"399",
    "addr:postcode":"bd3 7jf",
    "addr:street":"Bradford West",
    "iso:country":"GB",
    "sg:address":"Fleet Garage, Rear Of 399",
    "sg:city":"Bradford",
    "sg:classifiers":[
        {
            "category":"Shopping",
            "type":"Retail Goods"
        }
    ],
    "sg:phone":"+44 1274 667270",
    "sg:postcode":"BD3 7JF",
    "sg:province":"West Yorkshire",
    "sg:tags":[
        "part",
        "accessory"
    ],
    "wof:name":"V.A.S",
    "wof:placetype":"venue"
},
  "geometry": {"coordinates":[-1.7108880281,53.8014297485],"type":"Point"}
}