{
  "type": "Feature",
  "properties": {
    "addr:full":"Holmleigh The Barrows Cheddar Somerset BS27 3BE",
    "addr:postcode":"bs27 3be",
    "addr:street":"Barrows",
    "iso:country":"GB",
    "sg:address":"Holmleigh The Barrows",
    "sg:city":"Cheddar",
    "sg:classifiers":[
        {
            "category":"Health Services",
            "subcategory":"Dentist",
            "type":"Services"
        }
    ],
    "sg:phone":"+44 1934 742259",
    "sg:postcode":"BS27 3BE",
    "sg:province":"Somerset",
    "wof:name":"Cheddar Dental Practise",
    "wof:placetype":"venue"
},
  "geometry": {"coordinates":[-2.7776589394,51.2796592712],"type":"Point"}
}