{
  "type": "Feature",
  "properties": {
    "iso:country":"GB",
    "sg:address":"35 Long Acre",
    "sg:city":"London",
    "sg:classifiers":[
        {
            "category":"Travel",
            "subcategory":"Travel Agent",
            "type":"Entertainment"
        }
    ],
    "sg:phone":"+44 20 7836 9000",
    "sg:postcode":"WC2E 9JT",
    "sg:province":"Greater London",
    "wof:name":"T T T Travel Centre",
    "wof:placetype":"venue"
},
  "geometry": {"coordinates":[-0.1244480014,51.512878418],"type":"Point"}
}