{
  "type": "Feature",
  "properties": {
    "addr:full":"2 Townsend Ely Cambridgeshire CB7 5DB",
    "addr:housenumber":"2",
    "addr:postcode":"cb7 5db",
    "addr:street":"Townsend Ely",
    "iso:country":"GB",
    "sg:address":"2 Townsend",
    "sg:city":"Ely",
    "sg:classifiers":[
        {
            "category":"Shopping",
            "subcategory":"Computers & Home Electronics",
            "type":"Retail Goods"
        }
    ],
    "sg:phone":"+44 1353 722732",
    "sg:postcode":"CB7 5DB",
    "sg:province":"Cambridgeshire",
    "wof:name":"Hille Ltd",
    "wof:placetype":"venue"
},
  "geometry": {"coordinates":[0.3338350058,52.3414764404],"type":"Point"}
}