{
  "type": "Feature",
  "properties": {
    "addr:full":"Bryant Street Birmingham West Midlands B18 4BJ",
    "addr:postcode":"b18 4bj",
    "addr:street":"Bryant Street",
    "iso:country":"GB",
    "sg:address":"Bryant Street",
    "sg:city":"Birmingham",
    "sg:classifiers":[
        {
            "category":"Manufacturing",
            "subcategory":"Signs",
            "type":"Manufacturing & Wholesale Goods"
        }
    ],
    "sg:phone":"+44 121 682 5184",
    "sg:postcode":"B18 4BJ",
    "sg:province":"West Midlands",
    "sg:tags":[
        "writer"
    ],
    "wof:name":"Targett Signs",
    "wof:placetype":"venue"
},
  "geometry": {"coordinates":[-1.938544035,52.4899787903],"type":"Point"}
}