{
  "type": "Feature",
  "properties": {
    "iso:country":"GB",
    "sg:address":"Trinity Medical Centre, New George St",
    "sg:city":"South Shields",
    "sg:classifiers":[
        {
            "category":"Health Services",
            "subcategory":"Doctor",
            "type":"Services"
        }
    ],
    "sg:phone":"+44 191 454 7775",
    "sg:postcode":"NE33 5DU",
    "sg:province":"Tyne and Wear",
    "sg:tags":[
        "practitioners"
    ],
    "wof:name":"Ruth Jenkinson",
    "wof:placetype":"venue"
},
  "geometry": {"coordinates":[-1.43678,54.987759],"type":"Point"}
}