{
  "type": "Feature",
  "properties": {
    "addr:full":"Unit 1, The Match Factory, 140 Speke Rd, Garston Liverpool Merseyside L19 2PH",
    "addr:housenumber":"unit 1;140",
    "addr:postcode":"l19 2ph",
    "addr:street":"The;Speke Rd",
    "iso:country":"GB",
    "sg:address":"Unit 1, The Match Factory, 140 Speke Rd, Garston",
    "sg:city":"Liverpool",
    "sg:classifiers":[
        {
            "category":"Retail",
            "subcategory":"Auto Rental",
            "type":"Services"
        }
    ],
    "sg:phone":"+44 151 427 0600",
    "sg:postcode":"L19 2PH",
    "sg:province":"Merseyside",
    "sg:tags":[
        "truck",
        "hire",
        "van"
    ],
    "wof:name":"Nicholas Van Hire",
    "wof:placetype":"venue"
},
  "geometry": {"coordinates":[-2.8957960606,53.3534851074],"type":"Point"}
}