{
  "type": "Feature",
  "properties": {
    "iso:country":"GB",
    "sg:address":"Spring House, Bury Hill Lane",
    "sg:city":"Bristol",
    "sg:classifiers":[
        {
            "category":"Building & Trades",
            "subcategory":"Construction",
            "type":"Services"
        }
    ],
    "sg:postcode":"BS37 7QN",
    "sg:province":"Gloucestershire",
    "sg:tags":[
        "roofing"
    ],
    "wof:name":"Industrial Roofing Products Ltd.",
    "wof:placetype":"venue"
},
  "geometry": {"coordinates":[-2.403214,51.568111],"type":"Point"}
}