{
  "type": "Feature",
  "properties": {
    "addr:full":"461b Alexandra Avenue Harrow Greater London HA2 9RY",
    "addr:housenumber":"461b",
    "addr:postcode":"ha2 9ry",
    "addr:street":"Alexandra Avenue",
    "iso:country":"GB",
    "sg:address":"461b Alexandra Avenue",
    "sg:city":"Harrow",
    "sg:classifiers":[
        {
            "category":"Retail",
            "subcategory":"Repair Shop",
            "type":"Services"
        }
    ],
    "sg:postcode":"HA2 9RY",
    "sg:province":"Greater London",
    "sg:tags":[
        "furniture"
    ],
    "wof:name":"John Pullin",
    "wof:placetype":"venue"
},
  "geometry": {"coordinates":[-0.371116,51.574516],"type":"Point"}
}