{
  "type": "Feature",
  "properties": {
    "addr:full":"45 Walm Lane London Greater London NW2 4QU",
    "addr:housenumber":"45",
    "addr:postcode":"nw2 4qu",
    "addr:street":"Walm Lane",
    "iso:country":"GB",
    "sg:address":"45 Walm Lane",
    "sg:city":"London",
    "sg:classifiers":[
        {
            "category":"Real Estate",
            "subcategory":"Real Estate Operator",
            "type":"Services"
        }
    ],
    "sg:postcode":"NW2 4QU",
    "sg:province":"Greater London",
    "sg:tags":[
        "letting",
        "agent"
    ],
    "wof:name":"S R B Lets",
    "wof:placetype":"venue"
},
  "geometry": {"coordinates":[-0.220689,51.549332],"type":"Point"}
}