{
  "type": "Feature",
  "properties": {
    "addr:full":"Starr Farm, Chippenham Road, Marshfield Chippenham Gloucestershire SN14 8LH",
    "addr:postcode":"sn14 8lh",
    "addr:street":"Starr Farm Chippenham Road",
    "iso:country":"GB",
    "sg:address":"Starr Farm, Chippenham Road, Marshfield",
    "sg:city":"Chippenham",
    "sg:classifiers":[
        {
            "category":"Utilities",
            "subcategory":"Refuse",
            "type":"Services"
        },
        {
            "category":"Building & Trades",
            "subcategory":"Cleaning & Sanitation",
            "type":"Services"
        }
    ],
    "sg:phone":"+44 1225 891591",
    "sg:postcode":"SN14 8LH",
    "sg:province":"Gloucestershire",
    "sg:tags":[
        "disposal",
        "retail",
        "waste",
        "commercial",
        "contracting"
    ],
    "wof:name":"Micheal J Church",
    "wof:placetype":"venue"
},
  "geometry": {"coordinates":[-2.3111989498,51.4630432129],"type":"Point"}
}