{
  "type": "Feature",
  "properties": {
    "addr:full":"Somerset House, Bath Road, Swineford Bitton Bristol Gloucestershire BS30 6LW",
    "addr:postcode":"bs30 6lw",
    "addr:street":"Bath Road",
    "iso:country":"GB",
    "sg:address":"Somerset House, Bath Road, Swineford Bitton",
    "sg:city":"Bristol",
    "sg:classifiers":[
        {
            "category":"Building & Trades",
            "subcategory":"Construction",
            "type":"Services"
        }
    ],
    "sg:phone":"+44 1454 620200",
    "sg:postcode":"BS30 6LW",
    "sg:province":"Gloucestershire",
    "sg:tags":[
        "builder"
    ],
    "wof:name":"Property Services Group Ltd",
    "wof:placetype":"venue"
},
  "geometry": {"coordinates":[-2.4591040611,51.4245185852],"type":"Point"}
}