{
  "type": "Feature",
  "properties": {
    "iso:country":"GB",
    "sg:address":"16a Newgate Street",
    "sg:city":"Morpeth",
    "sg:classifiers":[
        {
            "category":"Military Area",
            "subcategory":"Air Force Base",
            "type":"Public Place"
        }
    ],
    "sg:phone":"+44 1670 519898",
    "sg:postcode":"NE61 1BA",
    "sg:province":"Northumberland",
    "sg:tags":[
        "taxi",
        "hire",
        "private"
    ],
    "wof:name":"Castle Taxis",
    "wof:placetype":"venue"
},
  "geometry": {"coordinates":[-1.6904779673,55.16796875],"type":"Point"}
}