{
  "type": "Feature",
  "properties": {
    "iso:country":"GB",
    "sg:address":"8 Alderwood Rd",
    "sg:city":"Swansea",
    "sg:classifiers":[
        {
            "category":"Shopping",
            "subcategory":"Pharmacy",
            "type":"Retail Goods"
        }
    ],
    "sg:phone":"+44 1792 405747",
    "sg:postcode":"SA3 5JD",
    "sg:province":"Swansea",
    "sg:tags":[
        "pharmacist",
        "chemist"
    ],
    "wof:name":"David Beynon",
    "wof:placetype":"venue"
},
  "geometry": {"coordinates":[-4.001148,51.586639],"type":"Point"}
}