{
  "type": "Feature",
  "properties": {
    "addr:full":"397 Fulham Palace Road, Fulham London Greater London SW6 6TA",
    "addr:housenumber":"397",
    "addr:postcode":"sw6 6ta",
    "addr:street":"Fulham Palace Road",
    "iso:country":"GB",
    "sg:address":"397 Fulham Palace Road, Fulham",
    "sg:city":"London",
    "sg:classifiers":[
        {
            "category":"Shopping",
            "subcategory":"Computers & Home Electronics",
            "type":"Retail Goods"
        }
    ],
    "sg:phone":"+44 20 7603 1980",
    "sg:postcode":"SW6 6TA",
    "sg:province":"Greater London",
    "wof:name":"Excellane Ltd",
    "wof:placetype":"venue"
},
  "geometry": {"coordinates":[-0.213312,51.4741210938],"type":"Point"}
}