{
  "type": "Feature",
  "properties": {
    "iso:country":"GB",
    "sg:address":"1 Ladysmith Av",
    "sg:city":"Colchester",
    "sg:classifiers":[
        {
            "category":"Health Services",
            "subcategory":"Doctor",
            "type":"Services"
        }
    ],
    "sg:phone":"+44 1206 305577",
    "sg:postcode":"CO7 0JB",
    "sg:province":"Essex",
    "sg:tags":[
        "practitioners"
    ],
    "wof:name":"Morris, A H",
    "wof:placetype":"venue"
},
  "geometry": {"coordinates":[1.0239729881,51.811164856],"type":"Point"}
}