{
  "type": "Feature",
  "properties": {
    "iso:country":"GB",
    "sg:address":"Tonderghie Rd, Isle Of Whithorn",
    "sg:city":"Newton Stewart",
    "sg:classifiers":[
        {
            "category":"Shopping",
            "subcategory":"Department Store",
            "type":"Retail Goods"
        }
    ],
    "sg:postcode":"DG8 8LQ",
    "sg:province":"Dumfries and Galloway",
    "wof:name":"Isle Craft",
    "wof:placetype":"venue"
},
  "geometry": {"coordinates":[-4.3676519394,54.699798584],"type":"Point"}
}