{
  "type": "Feature",
  "properties": {
    "addr:full":"46 Holdenhurst Avenue, Finchley London Greater London N12 0JB",
    "addr:housenumber":"46",
    "addr:postcode":"n12 0jb",
    "addr:street":"Holdenhurst Avenue",
    "iso:country":"GB",
    "sg:address":"46 Holdenhurst Avenue, Finchley",
    "sg:city":"London",
    "sg:classifiers":[
        {
            "category":"Professional",
            "subcategory":"Accounting & Tax Preparation",
            "type":"Services"
        }
    ],
    "sg:phone":"+44 20 8346 7248",
    "sg:postcode":"N12 0JB",
    "sg:province":"Greater London",
    "sg:tags":[
        "accountant"
    ],
    "wof:name":"Wickham Lawson & Associates",
    "wof:placetype":"venue"
},
  "geometry": {"coordinates":[-0.1800490022,51.6057777405],"type":"Point"}
}