{
  "type": "Feature",
  "properties": {
    "addr:full":"8 Faversham Rd, Lenham Maidstone Kent ME17 2PN",
    "addr:housenumber":"8",
    "addr:postcode":"me17 2pn",
    "addr:street":"Faversham Rd",
    "iso:country":"GB",
    "sg:address":"8 Faversham Rd, Lenham",
    "sg:city":"Maidstone",
    "sg:classifiers":[
        {
            "category":"Retail",
            "subcategory":"Auto Repair",
            "type":"Services"
        }
    ],
    "sg:postcode":"ME17 2PN",
    "sg:province":"Kent",
    "sg:tags":[
        "modification",
        "garage"
    ],
    "wof:name":"Barnes,Shirley,",
    "wof:placetype":"venue"
},
  "geometry": {"coordinates":[0.71964,51.238499],"type":"Point"}
}