{
  "type": "Feature",
  "properties": {
    "iso:country":"GB",
    "sg:address":"Mounds Court Farm, Siston Hill",
    "sg:city":"Bristol",
    "sg:classifiers":[
        {
            "category":"Farming",
            "subcategory":"Livestock Farm",
            "type":"Manufacturing & Wholesale Goods"
        }
    ],
    "sg:phone":"+44 117 967 4201",
    "sg:postcode":"BS30 5LU",
    "sg:province":"Gloucestershire",
    "sg:tags":[
        "others"
    ],
    "wof:name":"Peter J Davies",
    "wof:placetype":"venue"
},
  "geometry": {"coordinates":[-2.4782540798,51.4684638977],"type":"Point"}
}