{
  "type": "Feature",
  "properties": {
    "addr:full":"Knowsley House, Billinge End Road, Pleasington Blackburn Lancashire BB2 6RA",
    "addr:postcode":"bb2 6ra",
    "addr:street":"Billinge End Road",
    "iso:country":"GB",
    "sg:address":"Knowsley House, Billinge End Road, Pleasington",
    "sg:city":"Blackburn",
    "sg:classifiers":[
        {
            "category":"Professional",
            "subcategory":"Printing & Photocopies",
            "type":"Services"
        }
    ],
    "sg:postcode":"BB2 6RA",
    "sg:province":"Lancashire",
    "sg:tags":[
        "duplicating",
        "copying"
    ],
    "wof:name":"Pennine Print Services",
    "wof:placetype":"venue"
},
  "geometry": {"coordinates":[-2.515364,53.750572],"type":"Point"}
}