{
  "type": "Feature",
  "properties": {
    "iso:country":"GB",
    "sg:address":"Rankine Rd",
    "sg:city":"Basingstoke",
    "sg:classifiers":[
        {
            "category":"Building & Trades",
            "subcategory":"Construction",
            "type":"Services"
        }
    ],
    "sg:phone":"+44 1256 354025",
    "sg:postcode":"RG24 8SH",
    "sg:province":"Hampshire",
    "sg:tags":[
        "equipment"
    ],
    "wof:name":"Keyline Tool Hire",
    "wof:placetype":"venue"
},
  "geometry": {"coordinates":[-1.071405,51.277031],"type":"Point"}
}