{
  "type": "Feature",
  "properties": {
    "addr:full":"Provost Fraser Drive Aberdeen Aberdeen City AB2 5LQ",
    "addr:postcode":"ab2 5lq",
    "addr:street":"Provost Fraser Drive",
    "iso:country":"GB",
    "sg:address":"Provost Fraser Drive",
    "sg:city":"Aberdeen",
    "sg:classifiers":[
        {
            "category":"Building & Trades",
            "subcategory":"Landscaping Services",
            "type":"Services"
        }
    ],
    "sg:phone":"+44 1224 685920",
    "sg:postcode":"AB2 5LQ",
    "sg:province":"Aberdeen City",
    "sg:tags":[
        "contractor",
        "sport",
        "ground"
    ],
    "wof:name":"Northfield Sports Centre",
    "wof:placetype":"venue"
},
  "geometry": {"coordinates":[-2.154859,57.162113],"type":"Point"}
}