{
  "type": "Feature",
  "properties": {
    "iso:country":"GB",
    "sg:address":"33 Newton Street",
    "sg:city":"Millom",
    "sg:classifiers":[
        {
            "category":"Bus Charters",
            "type":"Transportation"
        },
        {
            "category":"Bus Stop",
            "subcategory":"None",
            "type":"Transportation"
        }
    ],
    "sg:phone":"+44 1229 772321",
    "sg:postcode":"LA18 4DR",
    "sg:province":"Cumbria",
    "sg:tags":[
        "operator",
        "coach"
    ],
    "wof:name":"Hodgson Coaches",
    "wof:placetype":"venue"
},
  "geometry": {"coordinates":[-3.265853,54.208683],"type":"Point"}
}