{
  "type": "Feature",
  "properties": {
    "addr:full":"Unit 2 Rainbow Wks, 21 Markfield Rd London Greater London N15 4RG",
    "addr:housenumber":"unit 2;21",
    "addr:postcode":"n15 4rg",
    "addr:street":"Rainbow Wks;Markfield Rd",
    "iso:country":"GB",
    "sg:address":"Unit 2 Rainbow Wks, 21 Markfield Rd",
    "sg:city":"London",
    "sg:classifiers":[
        {
            "category":"Wholesale",
            "subcategory":"Machinery & Supplies",
            "type":"Manufacturing & Wholesale Goods"
        }
    ],
    "sg:phone":"+44 20 8885 2400",
    "sg:postcode":"N15 4RG",
    "sg:province":"Greater London",
    "sg:tags":[
        "theatrical"
    ],
    "wof:name":"Decoupe Ltd",
    "wof:placetype":"venue"
},
  "geometry": {"coordinates":[-0.0646,51.584782],"type":"Point"}
}