{
  "type": "Feature",
  "properties": {
    "addr:full":"779 Newport Road, Rumney Cardiff Caerphilly CF3 4AJ",
    "addr:housenumber":"779",
    "addr:postcode":"cf3 4aj",
    "addr:street":"Newport Road",
    "iso:country":"GB",
    "sg:address":"779 Newport Road, Rumney",
    "sg:city":"Cardiff",
    "sg:classifiers":[
        {
            "category":"Restaurant",
            "type":"Food & Drink"
        }
    ],
    "sg:phone":"+44 29 2077 8262",
    "sg:postcode":"CF3 4AJ",
    "sg:province":"Caerphilly",
    "sg:tags":[
        "indian",
        "-",
        "french"
    ],
    "wof:name":"Spice Island",
    "wof:placetype":"venue"
},
  "geometry": {"coordinates":[-3.131739,51.509129],"type":"Point"}
}