{
  "type": "Feature",
  "properties": {
    "iso:country":"GB",
    "sg:address":"25 Northwich Road, Weaverham",
    "sg:city":"Northwich",
    "sg:classifiers":[
        {
            "category":"Retail",
            "subcategory":"Laundry & Dry Cleaning",
            "type":"Services"
        }
    ],
    "sg:postcode":"CW8 3EU",
    "sg:province":"Cheshire",
    "sg:tags":[
        "alteration"
    ],
    "wof:name":"Russet Clothes Care Centre",
    "wof:placetype":"venue"
},
  "geometry": {"coordinates":[-2.577053,53.262192],"type":"Point"}
}