{
  "type": "Feature",
  "properties": {
    "iso:country":"GB",
    "sg:address":"7-13 Market Street",
    "sg:city":"Holyhead",
    "sg:classifiers":[
        {
            "category":"Retail",
            "subcategory":"Laundry & Dry Cleaning",
            "type":"Services"
        }
    ],
    "sg:phone":"+44 1407 762012",
    "sg:postcode":"LL65 1UL",
    "sg:province":"Isle of Anglesey",
    "sg:tags":[
        "alteration"
    ],
    "wof:name":"Pritchard Cleaners",
    "wof:placetype":"venue"
},
  "geometry": {"coordinates":[-4.633309,53.310753],"type":"Point"}
}