{
  "type": "Feature",
  "properties": {
    "iso:country":"GB",
    "sg:address":"Purfleet Quay",
    "sg:city":"King's Lynn",
    "sg:classifiers":[
        {
            "category":"Government",
            "subcategory":"Police Station",
            "type":"Public Place"
        },
        {
            "category":"Government",
            "subcategory":"Office",
            "type":"Public Place"
        }
    ],
    "sg:phone":"+44 1553 669000",
    "sg:postcode":"PE30 1HP",
    "sg:province":"Norfolk",
    "sg:tags":[
        "support",
        "local"
    ],
    "wof:name":"The Probation Service",
    "wof:placetype":"venue"
},
  "geometry": {"coordinates":[0.39214,52.75428],"type":"Point"}
}