{
  "type": "Feature",
  "properties": {
    "addr:full":"Flat 6 Kingsgate, Waterdale Centre Doncaster South Yorkshire DN1 3JX",
    "addr:postcode":"dn1 3jx",
    "addr:street":"Kingsgate",
    "iso:country":"GB",
    "sg:address":"Flat 6 Kingsgate, Waterdale Centre",
    "sg:city":"Doncaster",
    "sg:classifiers":[
        {
            "category":"Commercial Area",
            "type":"Public Place"
        }
    ],
    "sg:phone":"+44 1302 363751",
    "sg:postcode":"DN1 3JX",
    "sg:province":"South Yorkshire",
    "sg:tags":[
        "shop",
        "centre"
    ],
    "wof:name":"Probus Estates Plc",
    "wof:placetype":"venue"
},
  "geometry": {"coordinates":[-1.130565,53.524391],"type":"Point"}
}