{
  "type": "Feature",
  "properties": {
    "addr:full":"Western Road Maidstone Kent ME16 8UP",
    "addr:postcode":"me16 8up",
    "addr:street":"Western Road",
    "iso:country":"GB",
    "sg:address":"Western Road",
    "sg:city":"Maidstone",
    "sg:classifiers":[
        {
            "category":"Social Services",
            "subcategory":"Adult Care",
            "type":"Services"
        }
    ],
    "sg:postcode":"ME16 8UP",
    "sg:province":"Kent",
    "sg:tags":[
        "housing",
        "sheltered"
    ],
    "wof:name":"Knowlton Gardens",
    "wof:placetype":"venue"
},
  "geometry": {"coordinates":[0.493215,51.267139],"type":"Point"}
}