{
  "type": "Feature",
  "properties": {
    "addr:full":"Lawrence House, 5-8 River Front Enfield Greater London EN1 3SY",
    "addr:housenumber":"5-8",
    "addr:postcode":"en1 3sy",
    "addr:street":"River Front",
    "iso:country":"GB",
    "sg:address":"Lawrence House, 5-8 River Front",
    "sg:city":"Enfield",
    "sg:classifiers":[
        {
            "category":"Building & Trades",
            "subcategory":"Construction",
            "type":"Services"
        }
    ],
    "sg:phone":"+44 20 8367 2999",
    "sg:postcode":"EN1 3SY",
    "sg:province":"Greater London",
    "sg:tags":[
        "contractor"
    ],
    "wof:name":"Hall & Tawse City",
    "wof:placetype":"venue"
},
  "geometry": {"coordinates":[-0.0783139989,51.6525039673],"type":"Point"}
}