{
  "type": "Feature",
  "properties": {
    "iso:country":"GB",
    "sg:address":"60 Upney Lane",
    "sg:city":"Barking",
    "sg:classifiers":[
        {
            "category":"Health Services",
            "subcategory":"Doctor",
            "type":"Services"
        },
        {
            "category":"Health Services",
            "subcategory":"Health Practitioner",
            "type":"Services"
        }
    ],
    "sg:phone":"+44 20 8594 3667",
    "sg:postcode":"IG11 9LP",
    "sg:province":"Essex",
    "sg:tags":[
        "homoeopathic",
        "practitioners"
    ],
    "wof:name":"Faircross Complementary Medical Centre (The)",
    "wof:placetype":"venue"
},
  "geometry": {"coordinates":[0.095094,51.543762],"type":"Point"}
}