{
  "type": "Feature",
  "properties": {
    "addr:full":"103 Carnethie Street Rosewell Midlothian EH24 9AJ",
    "addr:housenumber":"103",
    "addr:postcode":"eh24 9aj",
    "addr:street":"Carnethie Street",
    "iso:country":"GB",
    "sg:address":"103 Carnethie Street",
    "sg:city":"Rosewell",
    "sg:classifiers":[
        {
            "category":"Professional",
            "subcategory":"Accounting & Tax Preparation",
            "type":"Services"
        },
        {
            "category":"Utilities",
            "type":"Services"
        }
    ],
    "sg:phone":"+44 131 440 2755",
    "sg:postcode":"EH24 9AJ",
    "sg:province":"Midlothian",
    "sg:tags":[
        "pattern",
        "maker",
        "internet"
    ],
    "wof:name":"Colourways",
    "wof:placetype":"venue"
},
  "geometry": {"coordinates":[-3.1358170509,55.8518409729],"type":"Point"}
}