{
  "type": "Feature",
  "properties": {
    "addr:full":"Hill House, Much Marcle Ledbury Gloucestershire HR8 2NX",
    "addr:postcode":"hr8 2nx",
    "addr:street":"Marcle",
    "iso:country":"GB",
    "sg:address":"Hill House, Much Marcle",
    "sg:city":"Ledbury",
    "sg:classifiers":[
        {
            "category":"Travel",
            "subcategory":"Travel Agent",
            "type":"Entertainment"
        },
        {
            "category":"Recreation",
            "subcategory":"Gun Range",
            "type":"Entertainment"
        }
    ],
    "sg:phone":"+44 1531 660210",
    "sg:postcode":"HR8 2NX",
    "sg:province":"Gloucestershire",
    "sg:tags":[
        "operator",
        "tour"
    ],
    "wof:name":"Al La Carte Tours",
    "wof:placetype":"venue"
},
  "geometry": {"coordinates":[-2.499424,51.99316],"type":"Point"}
}