{
  "type": "Feature",
  "properties": {
    "iso:country":"GB",
    "sg:address":"7 North Square",
    "sg:city":"Dorchester",
    "sg:classifiers":[
        {
            "category":"Government",
            "subcategory":"Prison",
            "type":"Public Place"
        }
    ],
    "sg:phone":"+44 1305 214500",
    "sg:postcode":"DT1 1JD",
    "sg:province":"Dorset",
    "wof:name":"H M Prison Dorchester",
    "wof:placetype":"venue"
},
  "geometry": {"coordinates":[-2.436721,50.716278],"type":"Point"}
}