{
  "type": "Feature",
  "properties": {
    "addr:full":"100 Bridge Lane London Greater London NW11 0ER",
    "addr:housenumber":"100",
    "addr:postcode":"nw11 0er",
    "addr:street":"Bridge Lane",
    "iso:country":"GB",
    "sg:address":"100 Bridge Lane",
    "sg:city":"London",
    "sg:classifiers":[
        {
            "category":"Shopping",
            "subcategory":"Stationery & Office Supplies",
            "type":"Retail Goods"
        }
    ],
    "sg:phone":"+44 20 8458 9039",
    "sg:postcode":"NW11 0ER",
    "sg:province":"Greater London",
    "sg:tags":[
        "mobile",
        "catering"
    ],
    "wof:name":"Finchley Kosher Lunch Service",
    "wof:placetype":"venue"
},
  "geometry": {"coordinates":[-0.2051739991,51.5853233337],"type":"Point"}
}