{
  "type": "Feature",
  "properties": {
    "iso:country":"GB",
    "sg:address":"59 Lucknow Street, Fratton",
    "sg:city":"Portsmouth",
    "sg:classifiers":[
        {
            "category":"Organizations",
            "subcategory":"Community Association",
            "type":"Services"
        }
    ],
    "sg:postcode":"PO1 1PT",
    "sg:province":"Hampshire",
    "sg:tags":[
        "society",
        "housing"
    ],
    "wof:name":"Southsea Self Help Housing Limited",
    "wof:placetype":"venue"
},
  "geometry": {"coordinates":[-1.077927,50.797295],"type":"Point"}
}