{
  "type": "Feature",
  "properties": {
    "addr:full":"Gale Joinery Works, Todmorden Road Littleborough Lancashire OL15 9EW",
    "addr:postcode":"ol15 9ew",
    "addr:street":"Todmorden Road",
    "iso:country":"GB",
    "sg:address":"Gale Joinery Works, Todmorden Road",
    "sg:city":"Littleborough",
    "sg:classifiers":[
        {
            "category":"Building & Trades",
            "subcategory":"Construction",
            "type":"Services"
        }
    ],
    "sg:phone":"+44 1706 374477",
    "sg:postcode":"OL15 9EW",
    "sg:province":"Lancashire",
    "sg:tags":[
        "platform",
        "work",
        "scaffolding"
    ],
    "wof:name":"Rochdale Scaffolding & Construction Co. Ltd.",
    "wof:placetype":"venue"
},
  "geometry": {"coordinates":[-2.0969130993,53.643787384],"type":"Point"}
}