{
  "type": "Feature",
  "properties": {
    "addr:full":"85 New Road Gravesend Kent DA11 0AF",
    "addr:housenumber":"85",
    "addr:postcode":"da11 0af",
    "addr:street":"New Road",
    "iso:country":"GB",
    "sg:address":"85 New Road",
    "sg:city":"Gravesend",
    "sg:classifiers":[
        {
            "category":"Fast Food",
            "type":"Food & Drink"
        },
        {
            "category":"Restaurant",
            "type":"Food & Drink"
        }
    ],
    "sg:phone":"+44 1474 323153",
    "sg:postcode":"DA11 0AF",
    "sg:province":"Kent",
    "sg:tags":[
        "american",
        "-",
        "away",
        "take"
    ],
    "wof:name":"McDonald's Restaurants Ltd",
    "wof:placetype":"venue"
},
  "geometry": {"coordinates":[0.366406,51.44244],"type":"Point"}
}