{
  "type": "Feature",
  "properties": {
    "iso:country":"GB",
    "sg:address":"Plawsworth Road, Sacriston",
    "sg:city":"Durham",
    "sg:classifiers":[
        {
            "category":"Place Of Worship",
            "type":"Public Place"
        }
    ],
    "sg:phone":"+44 191 371 0001",
    "sg:postcode":"DH7 6PD",
    "sg:province":"Durham",
    "wof:name":"The Salvation Army",
    "wof:placetype":"venue"
},
  "geometry": {"coordinates":[-1.621499,54.820034],"type":"Point"}
}