{
  "type": "Feature",
  "properties": {
    "addr:full":"92 Cornishway Manchester Greater Manchester M22 0JX",
    "addr:housenumber":"92",
    "addr:postcode":"m22 0jx",
    "addr:street":"Cornishway",
    "iso:country":"GB",
    "sg:address":"92 Cornishway",
    "sg:city":"Manchester",
    "sg:classifiers":[
        {
            "category":"Government",
            "subcategory":"Post Office",
            "type":"Public Place"
        }
    ],
    "sg:phone":"+44 161 437 2460",
    "sg:postcode":"M22 0JX",
    "sg:province":"Greater Manchester",
    "wof:name":"Woodhouse Park Post Office & Greengrocery",
    "wof:placetype":"venue"
},
  "geometry": {"coordinates":[-2.2581460476,53.3701553345],"type":"Point"}
}