{
  "type": "Feature",
  "properties": {
    "addr:full":"50 Llewellyn Street, Pontygwaith Ferndale Rhondda, Cynon, Taff CF43 3LF",
    "addr:housenumber":"50",
    "addr:postcode":"cf43 3lf",
    "addr:street":"Llewellyn Street;Cynon Taff",
    "iso:country":"GB",
    "sg:address":"50 Llewellyn Street, Pontygwaith",
    "sg:city":"Ferndale",
    "sg:classifiers":[
        {
            "category":"Personal",
            "subcategory":"Beauty Salon",
            "type":"Services"
        },
        {
            "category":"Personal",
            "subcategory":"Barber",
            "type":"Services"
        }
    ],
    "sg:phone":"+44 1443 731340",
    "sg:postcode":"CF43 3LF",
    "sg:province":"Rhondda, Cynon, Taff",
    "sg:tags":[
        "unisex",
        "hairdresser"
    ],
    "wof:name":"Ruth & Patricia's Hairdressers",
    "wof:placetype":"venue"
},
  "geometry": {"coordinates":[-3.431798,51.63789],"type":"Point"}
}