{
  "type": "Feature",
  "properties": {
    "iso:country":"GB",
    "sg:address":"367 Regents Park Road",
    "sg:city":"London",
    "sg:classifiers":[
        {
            "category":"Personal",
            "subcategory":"Beauty Salon",
            "type":"Services"
        }
    ],
    "sg:phone":"+44 20 8349 9137",
    "sg:postcode":"N3 1DE",
    "sg:province":"Greater London",
    "sg:tags":[
        "unisex",
        "hairdresser"
    ],
    "wof:name":"Christopha",
    "wof:placetype":"venue"
},
  "geometry": {"coordinates":[-0.1944,51.600941],"type":"Point"}
}