{
  "type": "Feature",
  "properties": {
    "addr:full":"78 Main St, East Leake Loughborough Leicestershire LE12 6PG",
    "addr:housenumber":"78",
    "addr:postcode":"le12 6pg",
    "addr:street":"Main St",
    "iso:country":"GB",
    "sg:address":"78 Main St, East Leake",
    "sg:city":"Loughborough",
    "sg:classifiers":[
        {
            "category":"Bars & Pubs",
            "type":"Food & Drink"
        },
        {
            "category":"Community Center",
            "subcategory":"Social",
            "type":"Public Place"
        }
    ],
    "sg:phone":"+44 1509 852393",
    "sg:postcode":"LE12 6PG",
    "sg:province":"Leicestershire",
    "sg:tags":[
        "pubs",
        "house",
        "inn",
        "activity"
    ],
    "wof:name":"The Bulls Head",
    "wof:placetype":"venue"
},
  "geometry": {"coordinates":[-1.17602,52.831207],"type":"Point"}
}