{
  "type": "Feature",
  "properties": {
    "addr:full":"110 Fincale Road Hebburn Tyne and Wear NE31 2JS",
    "addr:housenumber":"110",
    "addr:postcode":"ne31 2js",
    "addr:street":"Fincale Road",
    "iso:country":"GB",
    "sg:address":"110 Fincale Road",
    "sg:city":"Hebburn",
    "sg:classifiers":[
        {
            "category":"Food & Beverages",
            "subcategory":"Meat & Fish",
            "type":"Retail Goods"
        }
    ],
    "sg:phone":"+44 191 483 2713",
    "sg:postcode":"NE31 2JS",
    "sg:province":"Tyne and Wear",
    "sg:tags":[
        "chip"
    ],
    "wof:name":"K Tam",
    "wof:placetype":"venue"
},
  "geometry": {"coordinates":[-1.511391,54.963287],"type":"Point"}
}