{
  "type": "Feature",
  "properties": {
    "iso:country":"GB",
    "sg:address":"126/128 Erith Rd",
    "sg:city":"Bexleyheath",
    "sg:classifiers":[
        {
            "category":"Professional",
            "subcategory":"Computer Services",
            "type":"Services"
        }
    ],
    "sg:phone":"+44 1322 559111",
    "sg:postcode":"DA7 6BU",
    "sg:province":"Kent",
    "sg:tags":[
        "system",
        "software"
    ],
    "wof:name":"C O M Systems Ltd",
    "wof:placetype":"venue"
},
  "geometry": {"coordinates":[0.153048,51.459419],"type":"Point"}
}