{
  "type": "Feature",
  "properties": {
    "iso:country":"GB",
    "sg:address":"Flaxfield, Stuckton",
    "sg:city":"Fordingbridge",
    "sg:classifiers":[
        {
            "category":"Farming",
            "subcategory":"Livestock Farm",
            "type":"Manufacturing & Wholesale Goods"
        }
    ],
    "sg:phone":"+44 1425 653284",
    "sg:postcode":"SP6 2HE",
    "sg:province":"Dorset",
    "sg:tags":[
        "others"
    ],
    "wof:name":"C C Marlow",
    "wof:placetype":"venue"
},
  "geometry": {"coordinates":[-1.77283,50.919338],"type":"Point"}
}