{
  "type": "Feature",
  "properties": {
    "addr:full":"2 Glebe St Stoke On Trent Staffordshire ST4 1HG",
    "addr:housenumber":"2",
    "addr:postcode":"st4 1hg",
    "addr:street":"Glebe St",
    "iso:country":"GB",
    "sg:address":"2 Glebe St",
    "sg:city":"Stoke On Trent",
    "sg:classifiers":[
        {
            "category":"Professional",
            "subcategory":"Advertising",
            "type":"Services"
        }
    ],
    "sg:phone":"+44 1782 846119",
    "sg:postcode":"ST4 1HG",
    "sg:province":"Staffordshire",
    "sg:tags":[
        "agency"
    ],
    "wof:name":"Intergrated Publicity Ltd",
    "wof:placetype":"venue"
},
  "geometry": {"coordinates":[-2.181344,53.004745],"type":"Point"}
}