{
  "type": "Feature",
  "properties": {
    "iso:country":"GB",
    "sg:address":"Ascot Road, Nuptown",
    "sg:city":"Bracknell",
    "sg:classifiers":[
        {
            "category":"Farming",
            "subcategory":"Livestock Farm",
            "type":"Manufacturing & Wholesale Goods"
        }
    ],
    "sg:postcode":"RG42 6HS",
    "sg:province":"Berkshire",
    "sg:tags":[
        "others"
    ],
    "wof:name":"Honeywood Farm",
    "wof:placetype":"venue"
},
  "geometry": {"coordinates":[-0.7387980223,51.4581451416],"type":"Point"}
}