{
  "type": "Feature",
  "properties": {
    "iso:country":"GB",
    "sg:address":"21 Beach Road",
    "sg:city":"South Shields",
    "sg:classifiers":[
        {
            "category":"Banks & Credit Unions",
            "subcategory":"Financial Services",
            "type":"Services"
        }
    ],
    "sg:phone":"+44 191 456 1897",
    "sg:postcode":"NE33 2QA",
    "sg:province":"Tyne and Wear",
    "sg:tags":[
        "consultant"
    ],
    "wof:name":"Shopacheck Financial Services Ltd.",
    "wof:placetype":"venue"
},
  "geometry": {"coordinates":[-1.42869699,54.9957809448],"type":"Point"}
}