{
  "type": "Feature",
  "properties": {
    "addr:full":"4 Chantry Court, Sovereign Way Chester Cheshire CH1 4QN",
    "addr:housenumber":"4",
    "addr:postcode":"ch1 4qn",
    "addr:street":"Chantry Court Sovereign Way",
    "iso:country":"GB",
    "sg:address":"4 Chantry Court, Sovereign Way",
    "sg:city":"Chester",
    "sg:classifiers":[
        {
            "category":"Conference Center",
            "type":"Public Place"
        }
    ],
    "sg:phone":"+44 1244 316992",
    "sg:postcode":"CH1 4QN",
    "sg:province":"Cheshire",
    "wof:name":"Amersham Associates Ltd.",
    "wof:placetype":"venue"
},
  "geometry": {"coordinates":[-2.927282,53.193825],"type":"Point"}
}