{
  "type": "Feature",
  "properties": {
    "iso:country":"GB",
    "sg:address":"Rowdown Farm, Peasemore",
    "sg:city":"Newbury",
    "sg:classifiers":[
        {
            "category":"Farming",
            "subcategory":"Farm",
            "type":"Manufacturing & Wholesale Goods"
        }
    ],
    "sg:postcode":"RG20 7JP",
    "sg:province":"Berkshire",
    "sg:tags":[
        "mixed",
        "crop"
    ],
    "wof:name":"Marcham Farms Ltd.",
    "wof:placetype":"venue"
},
  "geometry": {"coordinates":[-1.3417840004,51.4925537109],"type":"Point"}
}