{
  "type": "Feature",
  "properties": {
    "iso:country":"GB",
    "sg:address":"St. James Square",
    "sg:city":"Grimsby",
    "sg:classifiers":[
        {
            "category":"Bars & Pubs",
            "type":"Food & Drink"
        }
    ],
    "sg:postcode":"DN31 1EP",
    "sg:province":"Lincolnshire",
    "sg:tags":[
        "pubs",
        "inn"
    ],
    "wof:name":"Scorchers Rock Cafe",
    "wof:placetype":"venue"
},
  "geometry": {"coordinates":[-0.09594,53.560749],"type":"Point"}
}