{
  "type": "Feature",
  "properties": {
    "addr:full":"3 Broad Lane, Southdene, Kirby Liverpool Merseyside L32 6QA",
    "addr:housenumber":"3",
    "addr:postcode":"l32 6qa",
    "addr:street":"Broad Lane",
    "iso:country":"GB",
    "sg:address":"3 Broad Lane, Southdene, Kirby",
    "sg:city":"Liverpool",
    "sg:classifiers":[
        {
            "category":"Utilities",
            "subcategory":"Mobile Phone",
            "type":"Services"
        }
    ],
    "sg:phone":"+44 151 546 3984",
    "sg:postcode":"L32 6QA",
    "sg:province":"Merseyside",
    "sg:tags":[
        "battery"
    ],
    "wof:name":"Auto Aids",
    "wof:placetype":"venue"
},
  "geometry": {"coordinates":[-2.8819949627,53.4708595276],"type":"Point"}
}