{
  "type": "Feature",
  "properties": {
    "addr:full":"44 East Street Bromley Kent BR1 1QW",
    "addr:housenumber":"44",
    "addr:postcode":"br1 1qw",
    "addr:street":"East Street",
    "iso:country":"GB",
    "sg:address":"44 East Street",
    "sg:city":"Bromley",
    "sg:classifiers":[
        {
            "category":"Professional",
            "subcategory":"Lawyer & Legal Services",
            "type":"Services"
        }
    ],
    "sg:phone":"+44 20 8466 8840",
    "sg:postcode":"BR1 1QW",
    "sg:province":"Kent",
    "sg:tags":[
        "solicitor"
    ],
    "wof:name":"Charman & Gore Solicitors",
    "wof:placetype":"venue"
},
  "geometry": {"coordinates":[0.0166289993,51.4073791504],"type":"Point"}
}