{
  "type": "Feature",
  "properties": {
    "iso:country":"GB",
    "sg:address":"2 High Street, Pitlessie",
    "sg:city":"Cupar",
    "sg:classifiers":[
        {
            "category":"Professional",
            "subcategory":"Management & Consulting",
            "type":"Services"
        },
        {
            "category":"Utilities",
            "type":"Services"
        }
    ],
    "sg:phone":"+44 1337 831799",
    "sg:postcode":"KY15 7ST",
    "sg:province":"Fife",
    "sg:tags":[
        "marketing",
        "consultant",
        "internet"
    ],
    "wof:name":"Malcolm Mactavish Consulting",
    "wof:placetype":"venue"
},
  "geometry": {"coordinates":[-3.075011,56.274471],"type":"Point"}
}