{
  "type": "Feature",
  "properties": {
    "addr:full":"Barlborough Links, Chesterfield Rd Chesterfield Derbyshire S43 4XA",
    "addr:housenumber":"barlborough",
    "addr:postcode":"s43 4xa",
    "addr:street":"Links Chesterfield Rd",
    "iso:country":"GB",
    "sg:address":"Barlborough Links, Chesterfield Rd",
    "sg:city":"Chesterfield",
    "sg:classifiers":[
        {
            "category":"Bars & Pubs",
            "type":"Food & Drink"
        }
    ],
    "sg:phone":"+44 1246 813005",
    "sg:postcode":"S43 4XA",
    "sg:province":"Derbyshire",
    "sg:tags":[
        "pubs",
        "inn"
    ],
    "wof:name":"Treble Bob",
    "wof:placetype":"venue"
},
  "geometry": {"coordinates":[-1.2885940075,53.2861557007],"type":"Point"}
}