{
  "type": "Feature",
  "properties": {
    "addr:full":"33 Market Place, East Finchley London Greater London N2 8BQ",
    "addr:housenumber":"33",
    "addr:postcode":"n2 8bq",
    "addr:street":"Market Place",
    "iso:country":"GB",
    "sg:address":"33 Market Place, East Finchley",
    "sg:city":"London",
    "sg:classifiers":[
        {
            "category":"Personal",
            "type":"Services"
        }
    ],
    "sg:phone":"+44 20 8883 2828",
    "sg:postcode":"N2 8BQ",
    "sg:province":"Greater London",
    "sg:tags":[
        "delivery"
    ],
    "wof:name":"The Post Office",
    "wof:placetype":"venue"
},
  "geometry": {"coordinates":[-0.167335,51.590637],"type":"Point"}
}