{
  "type": "Feature",
  "properties": {
    "addr:full":"Brankstone, Bogside Station Alloa Clackmannanshire FK10 3QD",
    "addr:postcode":"fk10 3qd",
    "iso:country":"GB",
    "sg:address":"Brankstone, Bogside Station",
    "sg:city":"Alloa",
    "sg:classifiers":[
        {
            "category":"Banks & Credit Unions",
            "subcategory":"Financial Services",
            "type":"Services"
        }
    ],
    "sg:postcode":"FK10 3QD",
    "sg:province":"Clackmannanshire",
    "sg:tags":[
        "consultant"
    ],
    "wof:name":"Monarch Financial Solutions",
    "wof:placetype":"venue"
},
  "geometry": {"coordinates":[-3.7951939106,56.1163215637],"type":"Point"}
}