{
  "type": "Feature",
  "properties": {
    "addr:full":"76 Promenade Cheltenham Gloucestershire GL50 1NB",
    "addr:housenumber":"76",
    "addr:postcode":"gl50 1nb",
    "addr:street":"Promenade",
    "iso:country":"GB",
    "sg:address":"76 Promenade",
    "sg:city":"Cheltenham",
    "sg:classifiers":[
        {
            "category":"Shopping",
            "subcategory":"Shoes",
            "type":"Retail Goods"
        }
    ],
    "sg:phone":"+44 1242 522598",
    "sg:postcode":"GL50 1NB",
    "sg:province":"Gloucestershire",
    "sg:tags":[
        "shop"
    ],
    "wof:name":"K Shoes",
    "wof:placetype":"venue"
},
  "geometry": {"coordinates":[-2.0770149231,51.8990440369],"type":"Point"}
}