{
  "type": "Feature",
  "properties": {
    "addr:full":"16 Petty Cury Cambridge Cambridgeshire CB2 3NE",
    "addr:housenumber":"16",
    "addr:postcode":"cb2 3ne",
    "addr:street":"Petty Cury",
    "iso:country":"GB",
    "sg:address":"16 Petty Cury",
    "sg:city":"Cambridge",
    "sg:classifiers":[
        {
            "category":"Shopping",
            "subcategory":"Shoes",
            "type":"Retail Goods"
        }
    ],
    "sg:phone":"+44 1223 302982",
    "sg:postcode":"CB2 3NE",
    "sg:province":"Cambridgeshire",
    "sg:tags":[
        "shop"
    ],
    "wof:name":"Ravel Shoes",
    "wof:placetype":"venue"
},
  "geometry": {"coordinates":[0.1198650002,52.20495224],"type":"Point"}
}