{
  "type": "Feature",
  "properties": {
    "addr:full":"59-62 Victoria Road Aberdeen Aberdeen City AB11 9LT",
    "addr:housenumber":"59-62",
    "addr:postcode":"ab11 9lt",
    "addr:street":"Victoria Road",
    "iso:country":"GB",
    "sg:address":"59-62 Victoria Road",
    "sg:city":"Aberdeen",
    "sg:classifiers":[
        {
            "category":"Cinema",
            "subcategory":"Movie Rental",
            "type":"Entertainment"
        }
    ],
    "sg:phone":"+44 1224 899022",
    "sg:postcode":"AB11 9LT",
    "sg:province":"Aberdeen City",
    "sg:tags":[
        "video",
        "library"
    ],
    "wof:name":"Blockbuster Video",
    "wof:placetype":"venue"
},
  "geometry": {"coordinates":[-2.0882470608,57.138168335],"type":"Point"}
}