{
  "type": "Feature",
  "properties": {
    "iso:country":"GB",
    "sg:address":"13 Albert Parade",
    "sg:city":"Eastbourne",
    "sg:classifiers":[
        {
            "category":"Retail",
            "subcategory":"Laundry & Dry Cleaning",
            "type":"Services"
        }
    ],
    "sg:phone":"+44 1323 640645",
    "sg:postcode":"BN21 1SD",
    "sg:province":"East Sussex",
    "sg:tags":[
        "launderette",
        "alteration"
    ],
    "wof:name":"Washerama",
    "wof:placetype":"venue"
},
  "geometry": {"coordinates":[0.25679,50.777649],"type":"Point"}
}