{
  "type": "Feature",
  "properties": {
    "iso:country":"GB",
    "sg:address":"1 Willoughby Gardens, Leicester Forest East",
    "sg:city":"Leicester",
    "sg:classifiers":[
        {
            "category":"Professional",
            "subcategory":"Engineering",
            "type":"Services"
        },
        {
            "category":"Building & Trades",
            "subcategory":"Plumbing",
            "type":"Services"
        }
    ],
    "sg:postcode":"LE3 3GZ",
    "sg:province":"Leicestershire",
    "sg:tags":[
        "consultant",
        "heating",
        "mechanical"
    ],
    "wof:name":"A D C MECHANICAL SERVICES",
    "wof:placetype":"venue"
},
  "geometry": {"coordinates":[-1.212349,52.623577],"type":"Point"}
}