{
  "type": "Feature",
  "properties": {
    "iso:country":"GB",
    "sg:address":"56 Brantwood Drive, Heaton",
    "sg:city":"Bradford",
    "sg:classifiers":[
        {
            "category":"Home & Garden",
            "subcategory":"Household Appliances",
            "type":"Retail Goods"
        }
    ],
    "sg:postcode":"BD9 6QS",
    "sg:province":"West Yorkshire",
    "sg:tags":[
        "electrical"
    ],
    "wof:name":"Alan Holt (Heaton)",
    "wof:placetype":"venue"
},
  "geometry": {"coordinates":[-1.813696,53.818054],"type":"Point"}
}