{
  "type": "Feature",
  "properties": {
    "addr:full":"Ackhurst Road, Common Bank Business Park, Off Southport Road Chorley Lancashire PR7 1HN",
    "addr:postcode":"pr7 1hn",
    "addr:street":"Ackhurst Road Common Bank Business Park Off Southport Road",
    "iso:country":"GB",
    "sg:address":"Ackhurst Road, Common Bank Business Park, Off Southport Road",
    "sg:city":"Chorley",
    "sg:classifiers":[
        {
            "category":"Education",
            "subcategory":"Music School",
            "type":"Public Place"
        }
    ],
    "sg:phone":"+44 1257 279919",
    "sg:postcode":"PR7 1HN",
    "sg:province":"Lancashire",
    "sg:tags":[
        "conservatory"
    ],
    "wof:name":"Chorley Upvc Ltd.",
    "wof:placetype":"venue"
},
  "geometry": {"coordinates":[-2.65396,53.655384],"type":"Point"}
}