{
  "type": "Feature",
  "properties": {
    "iso:country":"GB",
    "sg:address":"271 High St",
    "sg:city":"Berkhamsted",
    "sg:classifiers":[
        {
            "category":"Education",
            "subcategory":"Special Training",
            "type":"Public Place"
        }
    ],
    "sg:phone":"+44 1442 384944",
    "sg:postcode":"HP4 1AA",
    "sg:province":"Bedfordshire",
    "sg:tags":[
        "product",
        "centre"
    ],
    "wof:name":"Murdock Marketing",
    "wof:placetype":"venue"
},
  "geometry": {"coordinates":[-0.5695260167,51.761882782],"type":"Point"}
}