{
  "type": "Feature",
  "properties": {
    "iso:country":"GB",
    "sg:address":"164 George Street, Arndale Centre",
    "sg:city":"Luton",
    "sg:classifiers":[
        {
            "category":"Food & Beverages",
            "subcategory":"Bakery",
            "type":"Retail Goods"
        }
    ],
    "sg:postcode":"LU1 2TL",
    "sg:province":"Bedfordshire",
    "sg:tags":[
        "baker"
    ],
    "wof:name":"Don Miller Hot Bread Kitchens",
    "wof:placetype":"venue"
},
  "geometry": {"coordinates":[-0.4165189862,51.8791618347],"type":"Point"}
}