{
  "type": "Feature",
  "properties": {
    "iso:country":"GB",
    "sg:address":"65 Kimberley Road, Nuthall",
    "sg:city":"Nottingham",
    "sg:classifiers":[
        {
            "category":"Building & Trades",
            "subcategory":"Construction",
            "type":"Services"
        }
    ],
    "sg:postcode":"NG16 1DD",
    "sg:province":"Derbyshire",
    "sg:tags":[
        "decorator",
        "painter"
    ],
    "wof:name":"B Reeve",
    "wof:placetype":"venue"
},
  "geometry": {"coordinates":[-1.240073,52.99437],"type":"Point"}
}