{
  "type": "Feature",
  "properties": {
    "addr:full":"59 Norman Rd Sutton Surrey SM1 2TB",
    "addr:housenumber":"59",
    "addr:postcode":"sm1 2tb",
    "addr:street":"Norman Rd",
    "iso:country":"GB",
    "sg:address":"59 Norman Rd",
    "sg:city":"Sutton",
    "sg:classifiers":[
        {
            "category":"Retail",
            "subcategory":"Repair Shop",
            "type":"Services"
        }
    ],
    "sg:phone":"+44 20 8642 3108",
    "sg:postcode":"SM1 2TB",
    "sg:province":"Surrey",
    "sg:tags":[
        "maintenance"
    ],
    "wof:name":"Jones Bros Tooting",
    "wof:placetype":"venue"
},
  "geometry": {"coordinates":[-0.204701,51.364368],"type":"Point"}
}