{
  "type": "Feature",
  "properties": {
    "addr:full":"230 Western Avenue Macclesfield Cheshire SK11 8AW",
    "addr:housenumber":"230",
    "addr:postcode":"sk11 8aw",
    "addr:street":"Western Avenue",
    "iso:country":"GB",
    "sg:address":"230 Western Avenue",
    "sg:city":"Macclesfield",
    "sg:classifiers":[
        {
            "category":"Professional",
            "subcategory":"Engineering",
            "type":"Services"
        },
        {
            "category":"Real Estate",
            "subcategory":"Architect",
            "type":"Services"
        }
    ],
    "sg:phone":"+44 1625 431984",
    "sg:postcode":"SK11 8AW",
    "sg:province":"Cheshire",
    "sg:tags":[
        "design",
        "engineer"
    ],
    "wof:name":"B.R Hawkins",
    "wof:placetype":"venue"
},
  "geometry": {"coordinates":[-2.130405,53.24707],"type":"Point"}
}