{
  "type": "Feature",
  "properties": {
    "iso:country":"GB",
    "sg:address":"Bridge Road, High Kelling",
    "sg:city":"Holt",
    "sg:classifiers":[
        {
            "category":"Arena",
            "subcategory":"Sports Club",
            "type":"Entertainment"
        }
    ],
    "sg:phone":"+44 1263 712191",
    "sg:postcode":"NR25 6QT",
    "sg:province":"Norfolk",
    "wof:name":"Holt Rugby Football Club Ltd.",
    "wof:placetype":"venue"
},
  "geometry": {"coordinates":[1.0899460316,52.9030570984],"type":"Point"}
}