{
  "type": "Feature",
  "properties": {
    "iso:country":"GB",
    "sg:address":"16 Amesbury Close",
    "sg:city":"Worcester Park",
    "sg:classifiers":[
        {
            "category":"Building & Trades",
            "subcategory":"Construction",
            "type":"Services"
        }
    ],
    "sg:postcode":"KT4 8PW",
    "sg:province":"Surrey",
    "sg:tags":[
        "builder"
    ],
    "wof:name":"Prism Builders",
    "wof:placetype":"venue"
},
  "geometry": {"coordinates":[-0.228171,51.38221],"type":"Point"}
}