{
  "type": "Feature",
  "properties": {
    "iso:country":"GB",
    "sg:address":"220 London Rd, Hazel Grove",
    "sg:city":"Stockport",
    "sg:classifiers":[
        {
            "category":"Retail",
            "subcategory":"Funeral Services",
            "type":"Services"
        },
        {
            "category":"Building & Trades",
            "subcategory":"Construction",
            "type":"Services"
        }
    ],
    "sg:phone":"+44 161 483 2372",
    "sg:postcode":"SK7 4DA",
    "sg:province":"Cheshire",
    "sg:tags":[
        "mnfr",
        "monumental",
        "mason"
    ],
    "wof:name":"Robertson Memorials",
    "wof:placetype":"venue"
},
  "geometry": {"coordinates":[-2.119321,53.379108],"type":"Point"}
}