{
  "type": "Feature",
  "properties": {
    "addr:full":"Riversfield, 6b Castle Road Ellon Aberdeenshire AB41 9EY",
    "addr:housenumber":"6b",
    "addr:postcode":"ab41 9ey",
    "addr:street":"Riversfield;Castle Road",
    "iso:country":"GB",
    "sg:address":"Riversfield, 6b Castle Road",
    "sg:city":"Ellon",
    "sg:classifiers":[
        {
            "category":"Communications",
            "type":"Services"
        }
    ],
    "sg:postcode":"AB41 9EY",
    "sg:province":"Aberdeenshire",
    "sg:tags":[
        "audio-visual"
    ],
    "wof:name":"Cinecosse",
    "wof:placetype":"venue"
},
  "geometry": {"coordinates":[-2.072814,57.364136],"type":"Point"}
}