{
  "type": "Feature",
  "properties": {
    "addr:full":"50 Middle Way Chinnor Buckinghamshire OX39 4TP",
    "addr:housenumber":"50",
    "addr:postcode":"ox39 4tp",
    "addr:street":"Middle Way",
    "iso:country":"GB",
    "sg:address":"50 Middle Way",
    "sg:city":"Chinnor",
    "sg:classifiers":[
        {
            "category":"Professional",
            "subcategory":"Printing & Photocopies",
            "type":"Services"
        }
    ],
    "sg:postcode":"OX39 4TP",
    "sg:province":"Buckinghamshire",
    "sg:tags":[
        "printer"
    ],
    "wof:name":"ALAN JOHN PRINTING SERVICE",
    "wof:placetype":"venue"
},
  "geometry": {"coordinates":[-0.9169579744,51.7009086609],"type":"Point"}
}