{
  "type": "Feature",
  "properties": {
    "iso:country":"GB",
    "sg:address":"Huddersfield Road, Newhey",
    "sg:city":"Rochdale",
    "sg:classifiers":[
        {
            "category":"Organizations",
            "subcategory":"Membership Organization",
            "type":"Services"
        }
    ],
    "sg:phone":"+44 1706 845114",
    "sg:postcode":"OL16 3RU",
    "sg:province":"Lancashire",
    "sg:tags":[
        "club"
    ],
    "wof:name":"Newhey Lodge",
    "wof:placetype":"venue"
},
  "geometry": {"coordinates":[-2.0867679119,53.6042251587],"type":"Point"}
}