{
  "type": "Feature",
  "properties": {
    "addr:full":"Windmill Farm, Otley Road, Beckwithshaw Harrogate North Yorkshire HG3 1QL",
    "addr:postcode":"hg3 1ql",
    "addr:street":"Otley Road Beckwithshaw",
    "iso:country":"GB",
    "sg:address":"Windmill Farm, Otley Road, Beckwithshaw",
    "sg:city":"Harrogate",
    "sg:classifiers":[
        {
            "category":"Shopping",
            "subcategory":"Bicycles & Sporting Goods",
            "type":"Retail Goods"
        },
        {
            "category":"Shopping",
            "subcategory":"Pets & Pet Supplies",
            "type":"Retail Goods"
        }
    ],
    "sg:phone":"+44 1423 566774",
    "sg:postcode":"HG3 1QL",
    "sg:province":"North Yorkshire",
    "sg:tags":[
        "riding",
        "saddlery",
        "equestrian",
        "wear"
    ],
    "wof:name":"Beaver Horse Shop",
    "wof:placetype":"venue"
},
  "geometry": {"coordinates":[-1.585950017,53.9764213562],"type":"Point"}
}