{
  "type": "Feature",
  "properties": {
    "addr:full":"28 High Street Haverfordwest Pembrokeshire SA61 2DA",
    "addr:housenumber":"28",
    "addr:postcode":"sa61 2da",
    "addr:street":"High Street",
    "iso:country":"GB",
    "sg:address":"28 High Street",
    "sg:city":"Haverfordwest",
    "sg:classifiers":[
        {
            "category":"Personal",
            "subcategory":"Beauty Salon",
            "type":"Services"
        }
    ],
    "sg:phone":"+44 1437 760454",
    "sg:postcode":"SA61 2DA",
    "sg:province":"Pembrokeshire",
    "sg:tags":[
        "unisex",
        "hairdresser"
    ],
    "wof:name":"Andrew Price",
    "wof:placetype":"venue"
},
  "geometry": {"coordinates":[-4.969892,51.801701],"type":"Point"}
}