{
  "type": "Feature",
  "properties": {
    "addr:full":"Cae-goronwy Farm, Bontddu Dolgellau Gwynedd LL40 2UR",
    "addr:postcode":"ll40 2ur",
    "addr:street":"Bontddu",
    "iso:country":"GB",
    "sg:address":"Cae-goronwy Farm, Bontddu",
    "sg:city":"Dolgellau",
    "sg:classifiers":[
        {
            "category":"Real Estate",
            "subcategory":"Real Estate Services",
            "type":"Services"
        },
        {
            "category":"Building & Trades",
            "subcategory":"Equipment Rental",
            "type":"Services"
        },
        {
            "category":"Building & Trades",
            "subcategory":"Construction",
            "type":"Services"
        }
    ],
    "sg:phone":"+44 1341 430243",
    "sg:postcode":"LL40 2UR",
    "sg:province":"Gwynedd",
    "sg:tags":[
        "plant",
        "leasing",
        "hire",
        "machinery"
    ],
    "wof:name":"J Owen & Sons",
    "wof:placetype":"venue"
},
  "geometry": {"coordinates":[-3.884276,52.74485],"type":"Point"}
}