{
  "type": "Feature",
  "properties": {
    "iso:country":"GB",
    "sg:address":"179 Coast Rd",
    "sg:city":"Newcastle Upon Tyne",
    "sg:classifiers":[
        {
            "category":"Home & Garden",
            "subcategory":"Household Appliances",
            "type":"Retail Goods"
        }
    ],
    "sg:phone":"+44 191 266 4770",
    "sg:postcode":"NE7 7RR",
    "sg:province":"Tyne and Wear",
    "sg:tags":[
        "electrical"
    ],
    "wof:name":"Kwik Fix",
    "wof:placetype":"venue"
},
  "geometry": {"coordinates":[-1.5674420595,54.9947738647],"type":"Point"}
}