{
  "type": "Feature",
  "properties": {
    "addr:full":"68 High Street, Selsey Chichester West Sussex PO20 0QJ",
    "addr:housenumber":"68",
    "addr:postcode":"po20 0qj",
    "addr:street":"High Street",
    "iso:country":"GB",
    "sg:address":"68 High Street, Selsey",
    "sg:city":"Chichester",
    "sg:classifiers":[
        {
            "category":"Real Estate",
            "subcategory":"Real Estate Agent",
            "type":"Services"
        }
    ],
    "sg:phone":"+44 1243 603901",
    "sg:postcode":"PO20 0QJ",
    "sg:province":"West Sussex",
    "wof:name":"Selsey Properties",
    "wof:placetype":"venue"
},
  "geometry": {"coordinates":[-0.7902020216,50.7347068787],"type":"Point"}
}