{
  "type": "Feature",
  "properties": {
    "iso:country":"GB",
    "sg:address":"7 Church Lane, Husbands Bosworth",
    "sg:city":"Lutterworth",
    "sg:classifiers":[
        {
            "category":"Farming",
            "subcategory":"Fish & Marine Products",
            "type":"Manufacturing & Wholesale Goods"
        },
        {
            "category":"Building & Trades",
            "subcategory":"Construction",
            "type":"Services"
        }
    ],
    "sg:phone":"+44 1858 880671",
    "sg:postcode":"LE17 6LS",
    "sg:province":"Leicestershire",
    "sg:tags":[
        "double",
        "window",
        "glazing",
        "repairer",
        "replacement"
    ],
    "wof:name":"Begleys Windows & Conservatories",
    "wof:placetype":"venue"
},
  "geometry": {"coordinates":[-1.053634,52.453991],"type":"Point"}
}