{
  "type": "Feature",
  "properties": {
    "iso:country":"GB",
    "sg:address":"Castle Farm, Moreton Corbett",
    "sg:city":"Shrewsbury",
    "sg:classifiers":[
        {
            "category":"Farming",
            "subcategory":"Farm",
            "type":"Manufacturing & Wholesale Goods"
        }
    ],
    "sg:phone":"+44 1939 250245",
    "sg:postcode":"SY4 4DW",
    "sg:province":"Shropshire",
    "sg:tags":[
        "mixed",
        "crop"
    ],
    "wof:name":"J H & M S Pinches",
    "wof:placetype":"venue"
},
  "geometry": {"coordinates":[-2.6545500755,52.805141449],"type":"Point"}
}