{
  "type": "Feature",
  "properties": {
    "addr:full":"27 High Street, Chapel-en-le-frith High Peak Cheshire SK23 0HD",
    "addr:housenumber":"27",
    "addr:postcode":"sk23 0hd",
    "addr:street":"High Street",
    "iso:country":"GB",
    "sg:address":"27 High Street, Chapel-en-le-frith",
    "sg:city":"High Peak",
    "sg:classifiers":[
        {
            "category":"Professional",
            "subcategory":"Art Services",
            "type":"Services"
        }
    ],
    "sg:phone":"+44 1298 812306",
    "sg:postcode":"SK23 0HD",
    "sg:province":"Cheshire",
    "sg:tags":[
        "photographer"
    ],
    "wof:name":"Glenwood Studios",
    "wof:placetype":"venue"
},
  "geometry": {"coordinates":[-1.918496,53.322491],"type":"Point"}
}