{
  "type": "Feature",
  "properties": {
    "iso:country":"GB",
    "sg:address":"Red Scar Farm, Underbarrow",
    "sg:city":"Kendal",
    "sg:classifiers":[
        {
            "category":"Farming",
            "subcategory":"Livestock Farm",
            "type":"Manufacturing & Wholesale Goods"
        },
        {
            "category":"Farming",
            "subcategory":"Farm",
            "type":"Manufacturing & Wholesale Goods"
        }
    ],
    "sg:phone":"+44 15395 68717",
    "sg:postcode":"LA8 8HP",
    "sg:province":"Cumbria",
    "sg:tags":[
        "mixed",
        "crop",
        "others"
    ],
    "wof:name":"T Ej S & S A",
    "wof:placetype":"venue"
},
  "geometry": {"coordinates":[-2.821377039,54.3226623535],"type":"Point"}
}