{
  "type": "Feature",
  "properties": {
    "addr:full":"1 Church Rd Erith Kent DA8 1PG",
    "addr:housenumber":"1",
    "addr:postcode":"da8 1pg",
    "addr:street":"Church Rd",
    "iso:country":"GB",
    "sg:address":"1 Church Rd",
    "sg:city":"Erith",
    "sg:classifiers":[
        {
            "category":"Professional",
            "subcategory":"Engineering",
            "type":"Services"
        }
    ],
    "sg:phone":"+44 1322 447714",
    "sg:postcode":"DA8 1PG",
    "sg:province":"Kent",
    "sg:tags":[
        "engineer"
    ],
    "wof:name":"Mechanical & Ferrous Ltd",
    "wof:placetype":"venue"
},
  "geometry": {"coordinates":[0.167965,51.485085],"type":"Point"}
}