{
  "type": "Feature",
  "properties": {
    "iso:country":"GB",
    "sg:address":"2 Temple Street",
    "sg:city":"Aylesbury",
    "sg:classifiers":[
        {
            "category":"Real Estate",
            "subcategory":"Real Estate Agent",
            "type":"Services"
        }
    ],
    "sg:phone":"+44 1296 395111",
    "sg:postcode":"HP20 2RH",
    "sg:province":"Buckinghamshire",
    "wof:name":"Connell Residential",
    "wof:placetype":"venue"
},
  "geometry": {"coordinates":[-0.813724,51.8162],"type":"Point"}
}