{
  "type": "Feature",
  "properties": {
    "addr:full":"3d Merchants Place Reading Berkshire RG1 1DT",
    "addr:housenumber":"3d",
    "addr:postcode":"rg1 1dt",
    "addr:street":"Merchants Place",
    "iso:country":"GB",
    "sg:address":"3d Merchants Place",
    "sg:city":"Reading",
    "sg:classifiers":[
        {
            "category":"Sports & Exercise",
            "subcategory":"Sports Center",
            "type":"Entertainment"
        }
    ],
    "sg:phone":"+44 118 956 0014",
    "sg:postcode":"RG1 1DT",
    "sg:province":"Berkshire",
    "sg:tags":[
        "shop",
        "good"
    ],
    "wof:name":"Kik Sports Martial Arts & Boxing Equipment",
    "wof:placetype":"venue"
},
  "geometry": {"coordinates":[-0.9731600285,51.4572677612],"type":"Point"}
}