{
  "type": "Feature",
  "properties": {
    "iso:country":"GB",
    "sg:address":"369 Coventry Rd, Small Heath",
    "sg:city":"Birmingham",
    "sg:classifiers":[
        {
            "category":"Recreation",
            "subcategory":"Amusement Park",
            "type":"Entertainment"
        }
    ],
    "sg:phone":"+44 121 766 6043",
    "sg:postcode":"B10 0SW",
    "sg:province":"West Midlands",
    "sg:tags":[
        "arcade"
    ],
    "wof:name":"Lucky Strike Amusements",
    "wof:placetype":"venue"
},
  "geometry": {"coordinates":[-1.8639309406,52.4717216492],"type":"Point"}
}