{
  "type": "Feature",
  "properties": {
    "iso:country":"GB",
    "sg:address":"Sparsholt Road",
    "sg:city":"London",
    "sg:classifiers":[
        {
            "category":"Bus Charters",
            "type":"Transportation"
        },
        {
            "category":"Organizations",
            "subcategory":"Non-profit Organization",
            "type":"Services"
        }
    ],
    "sg:phone":"+44 20 7263 1067",
    "sg:postcode":"N19 4EL",
    "sg:province":"Greater London",
    "sg:tags":[
        "hire",
        "coach",
        "voluntary",
        "organisation",
        "charity"
    ],
    "wof:name":"Hanley Crouch Community Association Ltd",
    "wof:placetype":"venue"
},
  "geometry": {"coordinates":[-0.1173740029,51.5705337524],"type":"Point"}
}