{
  "type": "Feature",
  "properties": {
    "addr:full":"Laidlawstiel Cotts, Laidlawstiel Galashiels Scottish Borders TD1 1TJ",
    "addr:postcode":"td1 1tj",
    "iso:country":"GB",
    "sg:address":"Laidlawstiel Cotts, Laidlawstiel",
    "sg:city":"Galashiels",
    "sg:classifiers":[
        {
            "category":"Organizations",
            "subcategory":"Non-profit Organization",
            "type":"Services"
        }
    ],
    "sg:phone":"+44 1896 850267",
    "sg:postcode":"TD1 1TJ",
    "sg:province":"Scottish Borders",
    "sg:tags":[
        "organisation",
        "voluntary",
        "charity"
    ],
    "wof:name":"The National Childbirth Trust",
    "wof:placetype":"venue"
},
  "geometry": {"coordinates":[-2.8029789925,55.6121559143],"type":"Point"}
}