{
  "type": "Feature",
  "properties": {
    "addr:full":"Office Suite, 1 Unit, 1 Staverton Technology Park, Staverton Cheltenham Gloucestershire GL51 6TJ",
    "addr:housenumber":"suite 1 unit 1 staverton",
    "addr:postcode":"gl51 6tj",
    "addr:street":"Technology Park",
    "iso:country":"GB",
    "sg:address":"Office Suite, 1 Unit, 1 Staverton Technology Park, Staverton",
    "sg:city":"Cheltenham",
    "sg:classifiers":[
        {
            "category":"Government",
            "subcategory":"Post Office",
            "type":"Public Place"
        }
    ],
    "sg:phone":"+44 1452 857766",
    "sg:postcode":"GL51 6TJ",
    "sg:province":"Gloucestershire",
    "sg:tags":[
        "messenger",
        "courier"
    ],
    "wof:name":"T.N.T Sameday",
    "wof:placetype":"venue"
},
  "geometry": {"coordinates":[-2.158370018,51.9068489075],"type":"Point"}
}