{
  "type": "Feature",
  "properties": {
    "addr:full":"124-150 Hackney Road London Greater London E2 7QL",
    "addr:housenumber":"124-150",
    "addr:postcode":"e2 7ql",
    "addr:street":"Hackney Road",
    "iso:country":"GB",
    "sg:address":"124-150 Hackney Road",
    "sg:city":"London",
    "sg:classifiers":[
        {
            "category":"Real Estate",
            "subcategory":"Real Estate Agent",
            "type":"Services"
        }
    ],
    "sg:postcode":"E2 7QL",
    "sg:province":"Greater London",
    "wof:name":"Gransim Properties (No.3) Limited",
    "wof:placetype":"venue"
},
  "geometry": {"coordinates":[-0.074568,51.529648],"type":"Point"}
}