{
  "type": "Feature",
  "properties": {
    "addr:full":"36 Glebe Way Hornchurch Essex RM11 3RR",
    "addr:housenumber":"36",
    "addr:postcode":"rm11 3rr",
    "addr:street":"Glebe Way",
    "iso:country":"GB",
    "sg:address":"36 Glebe Way",
    "sg:city":"Hornchurch",
    "sg:classifiers":[
        {
            "category":"Shopping",
            "subcategory":"Pets & Pet Supplies",
            "type":"Retail Goods"
        }
    ],
    "sg:phone":"+44 1708 475895",
    "sg:postcode":"RM11 3RR",
    "sg:province":"Essex",
    "sg:tags":[
        "food"
    ],
    "wof:name":"Oscar Mobile Pet Foods",
    "wof:placetype":"venue"
},
  "geometry": {"coordinates":[0.2236479968,51.5651626587],"type":"Point"}
}