{
  "type": "Feature",
  "properties": {
    "iso:country":"GB",
    "sg:address":"2-6 High Road Leyton",
    "sg:city":"London",
    "sg:classifiers":[
        {
            "category":"Shopping",
            "subcategory":"Computers & Home Electronics",
            "type":"Retail Goods"
        }
    ],
    "sg:phone":"+44 20 8534 6087",
    "sg:postcode":"E15 2BP",
    "sg:province":"Greater London",
    "sg:tags":[
        "tape",
        "video"
    ],
    "wof:name":"Discount Video (Leyton) Ltd.",
    "wof:placetype":"venue"
},
  "geometry": {"coordinates":[0.0226520002,51.5928039551],"type":"Point"}
}