{
  "type": "Feature",
  "properties": {
    "addr:full":"West Hythe Road Hythe Kent CT21 4NT",
    "addr:postcode":"ct21 4nt",
    "addr:street":"West Hythe Road",
    "iso:country":"GB",
    "sg:address":"West Hythe Road",
    "sg:city":"Hythe",
    "sg:classifiers":[
        {
            "category":"Retail",
            "subcategory":"Auto Repair",
            "type":"Services"
        }
    ],
    "sg:phone":"+44 1303 261922",
    "sg:postcode":"CT21 4NT",
    "sg:province":"Kent",
    "sg:tags":[
        "modification",
        "garage"
    ],
    "wof:name":"J A C Motor Enterprises",
    "wof:placetype":"venue"
},
  "geometry": {"coordinates":[1.0256249905,51.0615348816],"type":"Point"}
}