{
  "type": "Feature",
  "properties": {
    "addr:full":"95 Moore Park Road London Greater London SW6 2DA",
    "addr:housenumber":"95",
    "addr:postcode":"sw6 2da",
    "addr:street":"Moore Park Road",
    "iso:country":"GB",
    "sg:address":"95 Moore Park Road",
    "sg:city":"London",
    "sg:classifiers":[
        {
            "category":"Manufacturing",
            "subcategory":"Apparel",
            "type":"Manufacturing & Wholesale Goods"
        }
    ],
    "sg:phone":"+44 20 7731 5008",
    "sg:postcode":"SW6 2DA",
    "sg:province":"Greater London",
    "sg:tags":[
        "shirt",
        "maker"
    ],
    "wof:name":"Stephan Haroutunian Shirts Ltd.",
    "wof:placetype":"venue"
},
  "geometry": {"coordinates":[-0.193314,51.478745],"type":"Point"}
}