{
  "type": "Feature",
  "properties": {
    "addr:full":"3 The Adelaide, Lower Higham Rochester Kent ME3 7LU",
    "addr:housenumber":"3",
    "addr:postcode":"me3 7lu",
    "addr:street":"The Adelaide Lower",
    "iso:country":"GB",
    "sg:address":"3 The Adelaide, Lower Higham",
    "sg:city":"Rochester",
    "sg:classifiers":[
        {
            "category":"Professional",
            "subcategory":"Computer Services",
            "type":"Services"
        }
    ],
    "sg:phone":"+44 1474 824555",
    "sg:postcode":"ME3 7LU",
    "sg:province":"Kent",
    "sg:tags":[
        "consultant"
    ],
    "wof:name":"Skills Centre Ltd (The)",
    "wof:placetype":"venue"
},
  "geometry": {"coordinates":[0.4636600018,51.4272537231],"type":"Point"}
}