{
  "type": "Feature",
  "properties": {
    "iso:country":"GB",
    "sg:address":"6 Main Street",
    "sg:city":"Largs",
    "sg:classifiers":[
        {
            "category":"Shopping",
            "subcategory":"Gifts & Souvenirs",
            "type":"Retail Goods"
        }
    ],
    "sg:postcode":"KA30 8AB",
    "sg:province":"North Ayrshire",
    "sg:tags":[
        "poster",
        "card"
    ],
    "wof:name":"Greetings From Largs",
    "wof:placetype":"venue"
},
  "geometry": {"coordinates":[-4.8693108559,55.7943572998],"type":"Point"}
}