{
  "type": "Feature",
  "properties": {
    "iso:country":"GB",
    "sg:address":"4 Norfolk Road",
    "sg:city":"Littlehampton",
    "sg:classifiers":[
        {
            "category":"Shopping",
            "subcategory":"News",
            "type":"Retail Goods"
        }
    ],
    "sg:phone":"+44 1903 716457",
    "sg:postcode":"BN17 5PL",
    "sg:province":"West Sussex",
    "sg:tags":[
        "newsagent"
    ],
    "wof:name":"Websters Newsagents",
    "wof:placetype":"venue"
},
  "geometry": {"coordinates":[-0.5322350264,50.8040847778],"type":"Point"}
}