{
  "type": "Feature",
  "properties": {
    "iso:country":"GB",
    "sg:address":"35 Broad Street",
    "sg:city":"Ross-on-wye",
    "sg:classifiers":[
        {
            "category":"Personal",
            "subcategory":"Beauty Salon",
            "type":"Services"
        }
    ],
    "sg:phone":"+44 1989 562697",
    "sg:postcode":"HR9 7DY",
    "sg:province":"Gloucestershire",
    "sg:tags":[
        "unisex",
        "hairdresser"
    ],
    "wof:name":"Rene",
    "wof:placetype":"venue"
},
  "geometry": {"coordinates":[-2.58205,51.91573],"type":"Point"}
}