{
  "type": "Feature",
  "properties": {
    "addr:full":"Curborough Road Lichfield Staffordshire WS13 7NR",
    "addr:postcode":"ws13 7nr",
    "addr:street":"Curborough Road",
    "iso:country":"GB",
    "sg:address":"Curborough Road",
    "sg:city":"Lichfield",
    "sg:classifiers":[
        {
            "category":"Bars & Pubs",
            "type":"Food & Drink"
        }
    ],
    "sg:phone":"+44 1543 262018",
    "sg:postcode":"WS13 7NR",
    "sg:province":"Staffordshire",
    "sg:tags":[
        "pubs",
        "inn"
    ],
    "wof:name":"The Anglesey Arms",
    "wof:placetype":"venue"
},
  "geometry": {"coordinates":[-1.829349041,52.6995201111],"type":"Point"}
}