{
  "type": "Feature",
  "properties": {
    "addr:full":"99 Cumberland Road Middlesbrough North Yorkshire TS5 6PP",
    "addr:housenumber":"99",
    "addr:postcode":"ts5 6pp",
    "addr:street":"Cumberland Road",
    "iso:country":"GB",
    "sg:address":"99 Cumberland Road",
    "sg:city":"Middlesbrough",
    "sg:classifiers":[
        {
            "category":"Home & Garden",
            "subcategory":"Household Appliances",
            "type":"Retail Goods"
        }
    ],
    "sg:phone":"+44 1642 818066",
    "sg:postcode":"TS5 6PP",
    "sg:province":"North Yorkshire",
    "sg:tags":[
        "electrical"
    ],
    "wof:name":"Area Hoover Service",
    "wof:placetype":"venue"
},
  "geometry": {"coordinates":[-1.2335239649,54.5603713989],"type":"Point"}
}