{
  "type": "Feature",
  "properties": {
    "iso:country":"GB",
    "sg:address":"378 Barlow Moor Road, Chorton",
    "sg:city":"Manchester",
    "sg:classifiers":[
        {
            "category":"Retail",
            "subcategory":"Repair Shop",
            "type":"Services"
        }
    ],
    "sg:phone":"+44 161 881 0027",
    "sg:postcode":"M21 2AZ",
    "sg:province":"Cheshire",
    "sg:tags":[
        "radio",
        "television",
        "video"
    ],
    "wof:name":"Videotech",
    "wof:placetype":"venue"
},
  "geometry": {"coordinates":[-2.27179,53.43325],"type":"Point"}
}