{
  "type": "Feature",
  "properties": {
    "iso:country":"GB",
    "sg:address":"20 Yarm Road",
    "sg:city":"Stockton-on-tees",
    "sg:classifiers":[
        {
            "category":"Insurance",
            "subcategory":"Insurance Agent",
            "type":"Services"
        }
    ],
    "sg:phone":"+44 1642 607498",
    "sg:postcode":"TS18 3NA",
    "sg:province":"Durham",
    "sg:tags":[
        "broker"
    ],
    "wof:name":"Alan H Lavender & Co. Ltd.",
    "wof:placetype":"venue"
},
  "geometry": {"coordinates":[-1.322485,54.560078],"type":"Point"}
}