{
  "type": "Feature",
  "properties": {
    "addr:full":"Church Lane, Chearsley Aylesbury Buckinghamshire HP18 0DH",
    "addr:postcode":"hp18 0dh",
    "addr:street":"Church Lane",
    "iso:country":"GB",
    "sg:address":"Church Lane, Chearsley",
    "sg:city":"Aylesbury",
    "sg:classifiers":[
        {
            "category":"Food & Beverages",
            "subcategory":"Farmers Market",
            "type":"Retail Goods"
        }
    ],
    "sg:phone":"+44 1844 208303",
    "sg:postcode":"HP18 0DH",
    "sg:province":"Buckinghamshire",
    "sg:tags":[
        "farm",
        "shop",
        "pyo"
    ],
    "wof:name":"M B Heybrook",
    "wof:placetype":"venue"
},
  "geometry": {"coordinates":[-0.9614189863,51.7903747559],"type":"Point"}
}