{
  "type": "Feature",
  "properties": {
    "addr:full":"289 Mare St Hackney Greater London E8 1EJ",
    "addr:housenumber":"289",
    "addr:postcode":"e8 1ej",
    "addr:street":"Mare St",
    "iso:country":"GB",
    "sg:address":"289 Mare St",
    "sg:city":"Hackney",
    "sg:classifiers":[
        {
            "category":"Professional",
            "type":"Services"
        }
    ],
    "sg:phone":"+44 20 8985 3590",
    "sg:postcode":"E8 1EJ",
    "sg:province":"Greater London",
    "sg:tags":[
        "caterer"
    ],
    "wof:name":"Belle's Kitchen",
    "wof:placetype":"venue"
},
  "geometry": {"coordinates":[-0.0553929992,51.545463562],"type":"Point"}
}