{
  "type": "Feature",
  "properties": {
    "addr:full":"87 Newgate Street Bishop Auckland Durham DL14 7EW",
    "addr:housenumber":"87",
    "addr:postcode":"dl14 7ew",
    "addr:street":"Newgate Street",
    "iso:country":"GB",
    "sg:address":"87 Newgate Street",
    "sg:city":"Bishop Auckland",
    "sg:classifiers":[
        {
            "category":"Shopping",
            "subcategory":"Thrift Store",
            "type":"Retail Goods"
        }
    ],
    "sg:phone":"+44 1388 451327",
    "sg:postcode":"DL14 7EW",
    "sg:province":"Durham",
    "sg:tags":[
        "shop",
        "charity"
    ],
    "wof:name":"Help the Aged",
    "wof:placetype":"venue"
},
  "geometry": {"coordinates":[-1.6749149561,54.6625556946],"type":"Point"}
}