{
  "type": "Feature",
  "properties": {
    "iso:country":"GB",
    "sg:address":"Britannia Mills, Gelderd Road, Birstall",
    "sg:city":"Batley",
    "sg:classifiers":[
        {
            "category":"Home & Garden",
            "subcategory":"Hardware",
            "type":"Retail Goods"
        }
    ],
    "sg:postcode":"WF17 9QD",
    "sg:province":"West Yorkshire",
    "sg:tags":[
        "compressor",
        "air"
    ],
    "wof:name":"Woodside Pneumatics Ltd.",
    "wof:placetype":"venue"
},
  "geometry": {"coordinates":[-1.6640059948,53.7350387573],"type":"Point"}
}