{
  "type": "Feature",
  "properties": {
    "iso:country":"GB",
    "sg:address":"320 Uxbridge Road",
    "sg:city":"London",
    "sg:classifiers":[
        {
            "category":"Real Estate",
            "subcategory":"Real Estate Agent",
            "type":"Services"
        }
    ],
    "sg:postcode":"W3 9QP",
    "sg:province":"Greater London",
    "wof:name":"Chatsworth Garden Properties Limited",
    "wof:placetype":"venue"
},
  "geometry": {"coordinates":[-0.277588,51.50845],"type":"Point"}
}