{
  "type": "Feature",
  "properties": {
    "iso:country":"GB",
    "sg:address":"23 Rutland Street, Swinton",
    "sg:city":"Manchester",
    "sg:classifiers":[
        {
            "category":"Freight",
            "type":"Transportation"
        }
    ],
    "sg:phone":"+44 161 728 5711",
    "sg:postcode":"M27 6AU",
    "sg:province":"Greater Manchester",
    "sg:tags":[
        "haulage",
        "road"
    ],
    "wof:name":"M H S Haulage Freight Team",
    "wof:placetype":"venue"
},
  "geometry": {"coordinates":[-2.343214035,53.5150299072],"type":"Point"}
}