{
  "type": "Feature",
  "properties": {
    "iso:country":"GB",
    "sg:address":"Mundella Centre, Green St",
    "sg:city":"Nottingham",
    "sg:classifiers":[
        {
            "category":"Health Services",
            "subcategory":"Health Practitioner",
            "type":"Services"
        }
    ],
    "sg:phone":"+44 115 986 8968",
    "sg:postcode":"NG2 2LA",
    "sg:province":"Nottinghamshire",
    "sg:tags":[
        "psychologist"
    ],
    "wof:name":"Nottingham Educational Psychology Service",
    "wof:placetype":"venue"
},
  "geometry": {"coordinates":[-1.1408200264,52.9367294312],"type":"Point"}
}