{
  "type": "Feature",
  "properties": {
    "iso:country":"GB",
    "sg:address":"139 Gravelly Hill North, Erdington",
    "sg:city":"Birmingham",
    "sg:classifiers":[
        {
            "category":"Autos & Motor Vehicles",
            "subcategory":"Fuel & Gas Station",
            "type":"Retail Goods"
        }
    ],
    "sg:phone":"+44 121 373 1973",
    "sg:postcode":"B23 6BJ",
    "sg:province":"West Midlands",
    "sg:tags":[
        "hr",
        "petrol"
    ],
    "wof:name":"Six Ways Filling Station",
    "wof:placetype":"venue"
},
  "geometry": {"coordinates":[-1.845172,52.521416],"type":"Point"}
}