{
  "type": "Feature",
  "properties": {
    "addr:full":"119 Northenden Road Sale Cheshire M33 3HF",
    "addr:housenumber":"119",
    "addr:postcode":"m33 3hf",
    "addr:street":"Northenden Road",
    "iso:country":"GB",
    "sg:address":"119 Northenden Road",
    "sg:city":"Sale",
    "sg:classifiers":[
        {
            "category":"Food & Beverages",
            "subcategory":"Candy",
            "type":"Retail Goods"
        }
    ],
    "sg:phone":"+44 161 973 1364",
    "sg:postcode":"M33 3HF",
    "sg:province":"Cheshire",
    "sg:tags":[
        "confectioner"
    ],
    "wof:name":"G M Field",
    "wof:placetype":"venue"
},
  "geometry": {"coordinates":[-2.304866,53.420319],"type":"Point"}
}