{
  "type": "Feature",
  "properties": {
    "addr:full":"21 Church Road, Great Bookham Leatherhead Surrey KT23 3PG",
    "addr:housenumber":"21",
    "addr:postcode":"kt23 3pg",
    "addr:street":"Church Road",
    "iso:country":"GB",
    "sg:address":"21 Church Road, Great Bookham",
    "sg:city":"Leatherhead",
    "sg:classifiers":[
        {
            "category":"Food & Beverages",
            "subcategory":"Meat & Fish",
            "type":"Retail Goods"
        }
    ],
    "sg:phone":"+44 1372 457880",
    "sg:postcode":"KT23 3PG",
    "sg:province":"Surrey",
    "sg:tags":[
        "butcher"
    ],
    "wof:name":"Paul Newman & Robert Daniels",
    "wof:placetype":"venue"
},
  "geometry": {"coordinates":[-0.375232,51.279613],"type":"Point"}
}