{
  "type": "Feature",
  "properties": {
    "addr:full":"High Meadow, Tilford Road Farnham Hampshire GU10 2LN",
    "addr:postcode":"gu10 2ln",
    "addr:street":"High Meadow Tilford Road",
    "iso:country":"GB",
    "sg:address":"High Meadow, Tilford Road",
    "sg:city":"Farnham",
    "sg:classifiers":[
        {
            "category":"Communications",
            "type":"Services"
        }
    ],
    "sg:postcode":"GU10 2LN",
    "sg:province":"Hampshire",
    "sg:tags":[
        "telecommunication"
    ],
    "wof:name":"Optical Data Solutions Ltd.",
    "wof:placetype":"venue"
},
  "geometry": {"coordinates":[-0.747517,51.187305],"type":"Point"}
}