{
  "type": "Feature",
  "properties": {
    "addr:full":"Halcyon Court, St Margarets Way Huntingdon Cambridgeshire PE29 6DG",
    "addr:postcode":"pe29 6dg",
    "addr:street":"Halcyon Court;Margarets Way",
    "iso:country":"GB",
    "sg:address":"Halcyon Court, St Margarets Way",
    "sg:city":"Huntingdon",
    "sg:classifiers":[
        {
            "category":"Professional",
            "subcategory":"Art Services",
            "type":"Services"
        }
    ],
    "sg:phone":"+44 1480 413117",
    "sg:postcode":"PE29 6DG",
    "sg:province":"Cambridgeshire",
    "sg:tags":[
        "photographer"
    ],
    "wof:name":"Photosphere",
    "wof:placetype":"venue"
},
  "geometry": {"coordinates":[-0.1929689944,52.3407859802],"type":"Point"}
}