{
  "type": "Feature",
  "properties": {
    "addr:full":"50 Elmcroft Crescent, North Harrow Harrow Greater London HA2 6HN",
    "addr:housenumber":"50",
    "addr:postcode":"ha2 6hn",
    "addr:street":"Elmcroft Crescent North",
    "iso:country":"GB",
    "sg:address":"50 Elmcroft Crescent, North Harrow",
    "sg:city":"Harrow",
    "sg:classifiers":[
        {
            "category":"Building & Trades",
            "subcategory":"Landscaping Services",
            "type":"Services"
        }
    ],
    "sg:phone":"+44 20 8427 7244",
    "sg:postcode":"HA2 6HN",
    "sg:province":"Greater London",
    "sg:tags":[
        "gardening"
    ],
    "wof:name":"Garden Scene",
    "wof:placetype":"venue"
},
  "geometry": {"coordinates":[-0.36478,51.594227],"type":"Point"}
}