{
  "type": "Feature",
  "properties": {
    "addr:full":"73 Sandringham Road Doncaster South Yorkshire DN2 5JA",
    "addr:housenumber":"73",
    "addr:postcode":"dn2 5ja",
    "addr:street":"Sandringham Road",
    "iso:country":"GB",
    "sg:address":"73 Sandringham Road",
    "sg:city":"Doncaster",
    "sg:classifiers":[
        {
            "category":"Fast Food",
            "type":"Food & Drink"
        }
    ],
    "sg:phone":"+44 1302 361362",
    "sg:postcode":"DN2 5JA",
    "sg:province":"South Yorkshire",
    "sg:tags":[
        "away",
        "take"
    ],
    "wof:name":"Dragon City",
    "wof:placetype":"venue"
},
  "geometry": {"coordinates":[-1.105616,53.526573],"type":"Point"}
}