{
  "type": "Feature",
  "properties": {
    "iso:country":"GB",
    "sg:address":"149 Styal Road, Heald Green",
    "sg:city":"Cheadle",
    "sg:classifiers":[
        {
            "category":"Health Services",
            "subcategory":"Nursing And Care Facility",
            "type":"Services"
        },
        {
            "category":"Social Services",
            "subcategory":"Retirement Home",
            "type":"Services"
        }
    ],
    "sg:phone":"+44 161 437 1960",
    "sg:postcode":"SK8 3TG",
    "sg:province":"Cheshire",
    "sg:tags":[
        "residential"
    ],
    "wof:name":"Pymgate Rest Home",
    "wof:placetype":"venue"
},
  "geometry": {"coordinates":[-2.238238,53.37936],"type":"Point"}
}