{
  "type": "Feature",
  "properties": {
    "iso:country":"GB",
    "sg:address":"84 Brookwood Road",
    "sg:city":"London",
    "sg:classifiers":[
        {
            "category":"Shopping",
            "subcategory":"Antiques",
            "type":"Retail Goods"
        }
    ],
    "sg:phone":"+44 20 8875 1778",
    "sg:postcode":"SW18 5BY",
    "sg:province":"Greater London",
    "wof:name":"All Our Yesterdays",
    "wof:placetype":"venue"
},
  "geometry": {"coordinates":[-0.201728,51.443565],"type":"Point"}
}