{
  "type": "Feature",
  "properties": {
    "addr:full":"Lenton Lane, Clifton Bridge Nottingham Nottinghamshire NG7 2NR",
    "addr:postcode":"ng7 2nr",
    "addr:street":"Lenton Lane;Bridge",
    "iso:country":"GB",
    "sg:address":"Lenton Lane, Clifton Bridge",
    "sg:city":"Nottingham",
    "sg:classifiers":[
        {
            "category":"Manufacturing",
            "subcategory":"Building Materials",
            "type":"Manufacturing & Wholesale Goods"
        }
    ],
    "sg:phone":"+44 115 986 1951",
    "sg:postcode":"NG7 2NR",
    "sg:province":"Nottinghamshire",
    "sg:tags":[
        "merchant",
        "builder"
    ],
    "wof:name":"Jackson Building Centres (Nottingham) Ltd.",
    "wof:placetype":"venue"
},
  "geometry": {"coordinates":[-1.1740139723,52.9476509094],"type":"Point"}
}