{
  "type": "Feature",
  "properties": {
    "iso:country":"GB",
    "sg:address":"Walkern Hall Lodge, Walkern Hall",
    "sg:city":"Stevenage",
    "sg:classifiers":[
        {
            "category":"Farming",
            "subcategory":"Livestock Farm",
            "type":"Manufacturing & Wholesale Goods"
        }
    ],
    "sg:phone":"+44 1438 869271",
    "sg:postcode":"SG2 7HZ",
    "sg:province":"Hertfordshire",
    "sg:tags":[
        "others"
    ],
    "wof:name":"d E Boinville G C",
    "wof:placetype":"venue"
},
  "geometry": {"coordinates":[-0.128069,51.917492],"type":"Point"}
}