{
  "type": "Feature",
  "properties": {
    "addr:full":"58 Belsize La Hampstead Greater London NW3 5AR",
    "addr:housenumber":"58",
    "addr:postcode":"nw3 5ar",
    "addr:street":"Belsize La Hampstead",
    "iso:country":"GB",
    "sg:address":"58 Belsize La",
    "sg:city":"Hampstead",
    "sg:classifiers":[
        {
            "category":"Restaurant",
            "type":"Food & Drink"
        }
    ],
    "sg:phone":"+44 20 7794 0717",
    "sg:postcode":"NW3 5AR",
    "sg:province":"Greater London",
    "sg:tags":[
        "indian"
    ],
    "wof:name":"Belsize Tandoori",
    "wof:placetype":"venue"
},
  "geometry": {"coordinates":[-0.171601,51.549374],"type":"Point"}
}