{
  "type": "Feature",
  "properties": {
    "addr:full":"1a Gladstone Road, Northampton Northampton Northamptonshire NN5 7EG",
    "addr:housenumber":"1a",
    "addr:postcode":"nn5 7eg",
    "addr:street":"Gladstone Road",
    "iso:country":"GB",
    "sg:address":"1a Gladstone Road, Northampton",
    "sg:city":"Northampton",
    "sg:classifiers":[
        {
            "category":"Professional",
            "subcategory":"Business Services",
            "type":"Services"
        }
    ],
    "sg:postcode":"NN5 7EG",
    "sg:province":"Northamptonshire",
    "sg:tags":[
        "bookmaker"
    ],
    "wof:name":"Pioneer Bookmakers Ltd",
    "wof:placetype":"venue"
},
  "geometry": {"coordinates":[-0.910143,52.24382],"type":"Point"}
}