{
  "type": "Feature",
  "properties": {
    "addr:full":"Bective Campus, Whiston Rd Northampton Northamptonshire NN2 7RR",
    "addr:postcode":"nn2 7rr",
    "addr:street":"Whiston Rd",
    "iso:country":"GB",
    "sg:address":"Bective Campus, Whiston Rd",
    "sg:city":"Northampton",
    "sg:classifiers":[
        {
            "category":"Education",
            "subcategory":"School",
            "type":"Public Place"
        }
    ],
    "sg:phone":"+44 1604 715246",
    "sg:postcode":"NN2 7RR",
    "sg:province":"Northamptonshire",
    "sg:tags":[
        "local",
        "authority"
    ],
    "wof:name":"Northampton Middle School",
    "wof:placetype":"venue"
},
  "geometry": {"coordinates":[-0.89026,52.265659],"type":"Point"}
}