{
  "type": "Feature",
  "properties": {
    "iso:country":"GB",
    "sg:address":"36 Sherwood Way, High Crompton",
    "sg:city":"Oldham",
    "sg:classifiers":[
        {
            "category":"Personal",
            "subcategory":"Beauty Salon",
            "type":"Services"
        }
    ],
    "sg:phone":"+44 1706 290857",
    "sg:postcode":"OL2 7NB",
    "sg:province":"Lancashire",
    "wof:name":"Top To Toe Qualified Mobile Beauty Therapist",
    "wof:placetype":"venue"
},
  "geometry": {"coordinates":[-2.116753,53.583893],"type":"Point"}
}