{
  "type": "Feature",
  "properties": {
    "addr:full":"Lavenham Road, Acton Sudbury Essex CO10 0BH",
    "addr:postcode":"co10 0bh",
    "addr:street":"Lavenham Road",
    "iso:country":"GB",
    "sg:address":"Lavenham Road, Acton",
    "sg:city":"Sudbury",
    "sg:classifiers":[
        {
            "category":"Home & Garden",
            "subcategory":"Building Materials",
            "type":"Retail Goods"
        }
    ],
    "sg:phone":"+44 1787 377010",
    "sg:postcode":"CO10 0BH",
    "sg:province":"Essex",
    "sg:tags":[
        "ready",
        "mixed",
        "concrete"
    ],
    "wof:name":"A R C Central",
    "wof:placetype":"venue"
},
  "geometry": {"coordinates":[0.7939050198,52.0903167725],"type":"Point"}
}