{
  "type": "Feature",
  "properties": {
    "addr:full":"7 Portland Street Southport Lancashire PR8 1LJ",
    "addr:housenumber":"7",
    "addr:postcode":"pr8 1lj",
    "addr:street":"Portland Street",
    "iso:country":"GB",
    "sg:address":"7 Portland Street",
    "sg:city":"Southport",
    "sg:classifiers":[
        {
            "category":"Travel",
            "subcategory":"Hotels & Motels",
            "type":"Entertainment"
        }
    ],
    "sg:postcode":"PR8 1LJ",
    "sg:province":"Lancashire",
    "wof:name":"Oakwood Private Hotel",
    "wof:placetype":"venue"
},
  "geometry": {"coordinates":[-3.0083510876,53.6447982788],"type":"Point"}
}