{
  "type": "Feature",
  "properties": {
    "iso:country":"GB",
    "sg:address":"Picktree Lane",
    "sg:city":"Chester-le-street",
    "sg:classifiers":[
        {
            "category":"Health Services",
            "subcategory":"Doctor",
            "type":"Services"
        },
        {
            "category":"Health Services",
            "subcategory":"Clinic",
            "type":"Services"
        }
    ],
    "sg:phone":"+44 191 388 3236",
    "sg:postcode":"DH3 3SL",
    "sg:province":"Durham",
    "sg:tags":[
        "nh",
        "practitioners"
    ],
    "wof:name":"Bridge End Surgery",
    "wof:placetype":"venue"
},
  "geometry": {"coordinates":[-1.570307,54.860832],"type":"Point"}
}