{
  "type": "Feature",
  "properties": {
    "iso:country":"GB",
    "sg:address":"3a Oxford House, Oxford Road",
    "sg:city":"Llandudno",
    "sg:classifiers":[
        {
            "category":"Education",
            "subcategory":"Music School",
            "type":"Public Place"
        }
    ],
    "sg:postcode":"LL30 1DH",
    "sg:province":"Conwy",
    "wof:name":"The Yamaha Music School",
    "wof:placetype":"venue"
},
  "geometry": {"coordinates":[-3.818764,53.322433],"type":"Point"}
}