{
  "type": "Feature",
  "properties": {
    "iso:country":"GB",
    "sg:address":"7 Arcade Road",
    "sg:city":"Littlehampton",
    "sg:classifiers":[
        {
            "category":"Health Services",
            "subcategory":"Dentist",
            "type":"Services"
        }
    ],
    "sg:phone":"+44 1903 716135",
    "sg:postcode":"BN17 5AP",
    "sg:province":"West Sussex",
    "wof:name":"Stephen Pittham",
    "wof:placetype":"venue"
},
  "geometry": {"coordinates":[-0.540453,50.808804],"type":"Point"}
}