{
  "type": "Feature",
  "properties": {
    "iso:country":"GB",
    "sg:address":"London Road",
    "sg:city":"Newbury",
    "sg:classifiers":[
        {
            "category":"Travel",
            "subcategory":"Hotels & Motels",
            "type":"Entertainment"
        }
    ],
    "sg:phone":"+44 1635 528838",
    "sg:postcode":"RG14 2BY",
    "sg:province":"Berkshire",
    "wof:name":"Millwaters Hotel",
    "wof:placetype":"venue"
},
  "geometry": {"coordinates":[-1.298059,51.40432],"type":"Point"}
}