{
  "type": "Feature",
  "properties": {
    "addr:full":"166 Pinner Road Harrow Greater London HA1 4JJ",
    "addr:housenumber":"166",
    "addr:postcode":"ha1 4jj",
    "addr:street":"Pinner Road",
    "iso:country":"GB",
    "sg:address":"166 Pinner Road",
    "sg:city":"Harrow",
    "sg:classifiers":[
        {
            "category":"Autos & Motor Vehicles",
            "subcategory":"Automobile Sales",
            "type":"Retail Goods"
        }
    ],
    "sg:postcode":"HA1 4JJ",
    "sg:province":"Greater London",
    "sg:tags":[
        "car"
    ],
    "wof:name":"Alec Jackson Autos Ltd.",
    "wof:placetype":"venue"
},
  "geometry": {"coordinates":[-0.3510070145,51.5819702148],"type":"Point"}
}