{
  "type": "Feature",
  "properties": {
    "addr:full":"26 Green Oak Drive, Wales Sheffield South Yorkshire S26 5NA",
    "addr:housenumber":"26",
    "addr:postcode":"s26 5na",
    "addr:street":"Green Oak Drive;Yorkshire",
    "iso:country":"GB",
    "sg:address":"26 Green Oak Drive, Wales",
    "sg:city":"Sheffield",
    "sg:classifiers":[
        {
            "category":"Building & Trades",
            "subcategory":"Plumbing",
            "type":"Services"
        }
    ],
    "sg:phone":"+44 1909 770174",
    "sg:postcode":"S26 5NA",
    "sg:province":"South Yorkshire",
    "sg:tags":[
        "central",
        "heating"
    ],
    "wof:name":"Fretwell & Lindley",
    "wof:placetype":"venue"
},
  "geometry": {"coordinates":[-1.293889,53.340347],"type":"Point"}
}