{
  "type": "Feature",
  "properties": {
    "addr:full":"Glyn Farm, Brithidir Llanfyllin Shropshire SY22 5EZ",
    "addr:postcode":"sy22 5ez",
    "addr:street":"Llanfyllin Shropshire",
    "iso:country":"GB",
    "sg:address":"Glyn Farm, Brithidir",
    "sg:city":"Llanfyllin",
    "sg:classifiers":[
        {
            "category":"Farming",
            "subcategory":"Livestock Farm",
            "type":"Manufacturing & Wholesale Goods"
        }
    ],
    "sg:postcode":"SY22 5EZ",
    "sg:province":"Shropshire",
    "sg:tags":[
        "others"
    ],
    "wof:name":"Bryan B Gately",
    "wof:placetype":"venue"
},
  "geometry": {"coordinates":[-3.269958,52.764301],"type":"Point"}
}