{
  "type": "Feature",
  "properties": {
    "addr:full":"2 Neeld Pde, Wembley Hill Rd Wembley Greater London HA9 6QU",
    "addr:housenumber":"2;pde",
    "addr:postcode":"ha9 6qu",
    "addr:street":"Neeld;Wembley Hill Rd",
    "iso:country":"GB",
    "sg:address":"2 Neeld Pde, Wembley Hill Rd",
    "sg:city":"Wembley",
    "sg:classifiers":[
        {
            "category":"Real Estate",
            "subcategory":"Real Estate Agent",
            "type":"Services"
        }
    ],
    "sg:phone":"+44 20 8795 3319",
    "sg:postcode":"HA9 6QU",
    "sg:province":"Greater London",
    "wof:name":"A & R Estate Agents & Lettings",
    "wof:placetype":"venue"
},
  "geometry": {"coordinates":[-0.28367,51.551632],"type":"Point"}
}