{
  "type": "Feature",
  "properties": {
    "iso:country":"GB",
    "sg:address":"Ralph Road",
    "sg:city":"Birmingham",
    "sg:classifiers":[
        {
            "category":"Government",
            "subcategory":"City Hall",
            "type":"Public Place"
        },
        {
            "category":"Retail",
            "subcategory":"Event Space",
            "type":"Services"
        }
    ],
    "sg:phone":"+44 121 328 3043",
    "sg:postcode":"B8 1NA",
    "sg:province":"West Midlands",
    "sg:tags":[
        "function",
        "hire",
        "room"
    ],
    "wof:name":"Norton Hall Womens & Childrens Centre",
    "wof:placetype":"venue"
},
  "geometry": {"coordinates":[-1.856523037,52.4887008667],"type":"Point"}
}