{
  "type": "Feature",
  "properties": {
    "iso:country":"GB",
    "sg:address":"Stardust Centre, 82 George Street",
    "sg:city":"Corby",
    "sg:classifiers":[
        {
            "category":"Organizations",
            "subcategory":"Membership Organization",
            "type":"Services"
        },
        {
            "category":"Organizations",
            "subcategory":"Political Organization",
            "type":"Services"
        }
    ],
    "sg:phone":"+44 1536 202741",
    "sg:postcode":"NN17 1QE",
    "sg:province":"Northamptonshire",
    "sg:tags":[
        "club",
        "promoter",
        "pool"
    ],
    "wof:name":"Hamblins Leisure Services Ltd.",
    "wof:placetype":"venue"
},
  "geometry": {"coordinates":[-0.7026000023,52.4859771729],"type":"Point"}
}