{
  "type": "Feature",
  "properties": {
    "addr:full":"Celtic Road, Moss Side Industrial Estate Callington Cornwall PL17 7SD",
    "addr:postcode":"pl17 7sd",
    "addr:street":"Celtic Road;Industrial Estate",
    "iso:country":"GB",
    "sg:address":"Celtic Road, Moss Side Industrial Estate",
    "sg:city":"Callington",
    "sg:classifiers":[
        {
            "category":"Utilities",
            "subcategory":"Natural Gas",
            "type":"Services"
        }
    ],
    "sg:postcode":"PL17 7SD",
    "sg:province":"Cornwall",
    "sg:tags":[
        "welding"
    ],
    "wof:name":"M & A Battie Engineering",
    "wof:placetype":"venue"
},
  "geometry": {"coordinates":[-4.302115,50.505257],"type":"Point"}
}