{
  "type": "Feature",
  "properties": {
    "addr:full":"2nd Floor, Lloyds Tsb Bank Chambers, Market Square Dover Kent CT16 1ND",
    "addr:housenumber":"2nd floor",
    "addr:postcode":"ct16 1nd",
    "addr:street":"Market Square Dover",
    "iso:country":"GB",
    "sg:address":"2nd Floor, Lloyds Tsb Bank Chambers, Market Square",
    "sg:city":"Dover",
    "sg:classifiers":[
        {
            "category":"Professional",
            "subcategory":"Employment Agencies",
            "type":"Services"
        }
    ],
    "sg:phone":"+44 1304 241289",
    "sg:postcode":"CT16 1ND",
    "sg:province":"Kent",
    "sg:tags":[
        "consultant"
    ],
    "wof:name":"Focus Employment Services",
    "wof:placetype":"venue"
},
  "geometry": {"coordinates":[1.328761,51.126846],"type":"Point"}
}