{
  "type": "Feature",
  "properties": {
    "addr:full":"36 Second Avenue Newhaven East Sussex BN9 9HN",
    "addr:housenumber":"36",
    "addr:postcode":"bn9 9hn",
    "addr:street":"Second Avenue",
    "iso:country":"GB",
    "sg:address":"36 Second Avenue",
    "sg:city":"Newhaven",
    "sg:classifiers":[
        {
            "category":"Place Of Worship",
            "type":"Public Place"
        }
    ],
    "sg:phone":"+44 1273 515251",
    "sg:postcode":"BN9 9HN",
    "sg:province":"East Sussex",
    "wof:name":"St Michael's Anglican & Methodist Church",
    "wof:placetype":"venue"
},
  "geometry": {"coordinates":[0.0450790003,50.7907447815],"type":"Point"}
}