{
  "type": "Feature",
  "properties": {
    "addr:full":"125 Llanelian Road Colwyn Bay Conwy LL29 8UW",
    "addr:housenumber":"125",
    "addr:postcode":"ll29 8uw",
    "addr:street":"Llanelian Road",
    "iso:country":"GB",
    "sg:address":"125 Llanelian Road",
    "sg:city":"Colwyn Bay",
    "sg:classifiers":[
        {
            "category":"Government",
            "subcategory":"Office",
            "type":"Public Place"
        }
    ],
    "sg:phone":"+44 1492 517819",
    "sg:postcode":"LL29 8UW",
    "sg:province":"Conwy",
    "sg:tags":[
        "development",
        "agency"
    ],
    "wof:name":"Cambria Homes Ltd.",
    "wof:placetype":"venue"
},
  "geometry": {"coordinates":[-3.6969709396,53.2800521851],"type":"Point"}
}