{
  "type": "Feature",
  "properties": {
    "addr:full":"752 Wilmslow Road Manchester Greater Manchester M20 0DW",
    "addr:housenumber":"752",
    "addr:postcode":"m20 0dw",
    "addr:street":"Wilmslow Road",
    "iso:country":"GB",
    "sg:address":"752 Wilmslow Road",
    "sg:city":"Manchester",
    "sg:classifiers":[
        {
            "category":"Food & Beverages",
            "subcategory":"Bakery",
            "type":"Retail Goods"
        }
    ],
    "sg:phone":"+44 161 434 2737",
    "sg:postcode":"M20 0DW",
    "sg:province":"Greater Manchester",
    "sg:tags":[
        "baker"
    ],
    "wof:name":"Spinks",
    "wof:placetype":"venue"
},
  "geometry": {"coordinates":[-2.23861,53.420261],"type":"Point"}
}