{
  "type": "Feature",
  "properties": {
    "addr:full":"1 Alberta Road Erith Kent DA8 3NA",
    "addr:housenumber":"1",
    "addr:postcode":"da8 3na",
    "addr:street":"Alberta Road",
    "iso:country":"GB",
    "sg:address":"1 Alberta Road",
    "sg:city":"Erith",
    "sg:classifiers":[
        {
            "category":"Building & Trades",
            "subcategory":"Construction",
            "type":"Services"
        }
    ],
    "sg:postcode":"DA8 3NA",
    "sg:province":"Kent",
    "sg:tags":[
        "builder"
    ],
    "wof:name":"Willeach Decorators",
    "wof:placetype":"venue"
},
  "geometry": {"coordinates":[0.159207,51.470074],"type":"Point"}
}