{
  "type": "Feature",
  "properties": {
    "addr:full":"The T A Centre, Clare Street Northampton Northamptonshire NN1 3JQ",
    "addr:postcode":"nn1 3jq",
    "addr:street":"Clare Street",
    "iso:country":"GB",
    "sg:address":"The T A Centre, Clare Street",
    "sg:city":"Northampton",
    "sg:classifiers":[
        {
            "category":"Organizations",
            "subcategory":"Non-profit Organization",
            "type":"Services"
        }
    ],
    "sg:phone":"+44 1604 603899",
    "sg:postcode":"NN1 3JQ",
    "sg:province":"Northamptonshire",
    "sg:tags":[
        "organisation",
        "voluntary",
        "charity"
    ],
    "wof:name":"Ssafa Forces Help",
    "wof:placetype":"venue"
},
  "geometry": {"coordinates":[-0.895284,52.23394],"type":"Point"}
}