{
  "type": "Feature",
  "properties": {
    "iso:country":"GB",
    "sg:address":"Gorseinon Rd",
    "sg:city":"Swansea",
    "sg:classifiers":[
        {
            "category":"Building & Trades",
            "subcategory":"Construction",
            "type":"Services"
        }
    ],
    "sg:phone":"+44 1792 893273",
    "sg:postcode":"SA4 1GE",
    "sg:province":"Carmarthenshire",
    "sg:tags":[
        "joinery"
    ],
    "wof:name":"Wallace & Hinds Ltd",
    "wof:placetype":"venue"
},
  "geometry": {"coordinates":[-4.032269001,51.6676712036],"type":"Point"}
}