{
  "type": "Feature",
  "properties": {
    "iso:country":"GB",
    "sg:address":"Judge Avenue, Auchinleck",
    "sg:city":"Cumnock",
    "sg:classifiers":[
        {
            "category":"Travel",
            "subcategory":"Hostel",
            "type":"Entertainment"
        },
        {
            "category":"Government",
            "subcategory":"Office",
            "type":"Public Place"
        }
    ],
    "sg:phone":"+44 1290 423382",
    "sg:postcode":"KA18 2DW",
    "sg:province":"East Ayrshire",
    "sg:tags":[
        "local"
    ],
    "wof:name":"Carrick View Hostel",
    "wof:placetype":"venue"
},
  "geometry": {"coordinates":[-4.295274,55.474026],"type":"Point"}
}