{
  "type": "Feature",
  "properties": {
    "addr:full":"Whitton Hall Farm, Westbury Shrewsbury Shropshire SY5 9RD",
    "addr:postcode":"sy5 9rd",
    "iso:country":"GB",
    "sg:address":"Whitton Hall Farm, Westbury",
    "sg:city":"Shrewsbury",
    "sg:classifiers":[
        {
            "category":"Farming",
            "subcategory":"Farm",
            "type":"Manufacturing & Wholesale Goods"
        }
    ],
    "sg:phone":"+44 17438843270",
    "sg:postcode":"SY5 9RD",
    "sg:province":"Shropshire",
    "sg:tags":[
        "mixed",
        "crop"
    ],
    "wof:name":"C W Halliday",
    "wof:placetype":"venue"
},
  "geometry": {"coordinates":[-2.952741,52.678089],"type":"Point"}
}