{
  "type": "Feature",
  "properties": {
    "addr:full":"215 Watling Street West Towcester Buckinghamshire NN12 6BX",
    "addr:housenumber":"215",
    "addr:postcode":"nn12 6bx",
    "addr:street":"Watling Street West",
    "iso:country":"GB",
    "sg:address":"215 Watling Street West",
    "sg:city":"Towcester",
    "sg:classifiers":[
        {
            "category":"Professional",
            "subcategory":"Art Services",
            "type":"Services"
        }
    ],
    "sg:phone":"+44 1327 352957",
    "sg:postcode":"NN12 6BX",
    "sg:province":"Buckinghamshire",
    "sg:tags":[
        "picture",
        "restoration",
        "cleaning"
    ],
    "wof:name":"Clark Gallery",
    "wof:placetype":"venue"
},
  "geometry": {"coordinates":[-0.906179,52.086071],"type":"Point"}
}