{
  "type": "Feature",
  "properties": {
    "addr:full":"Berechiah, Low Hawsker Whitby North Yorkshire YO22 4LE",
    "addr:postcode":"yo22 4le",
    "addr:street":"Hawsker",
    "iso:country":"GB",
    "sg:address":"Berechiah, Low Hawsker",
    "sg:city":"Whitby",
    "sg:classifiers":[
        {
            "category":"Home & Garden",
            "subcategory":"Garden Supply",
            "type":"Retail Goods"
        },
        {
            "category":"Farming",
            "subcategory":"Farm",
            "type":"Manufacturing & Wholesale Goods"
        }
    ],
    "sg:phone":"+44 1947 880254",
    "sg:postcode":"YO22 4LE",
    "sg:province":"North Yorkshire",
    "sg:tags":[
        "mixed",
        "bulb",
        "grower"
    ],
    "wof:name":"John P Tindale",
    "wof:placetype":"venue"
},
  "geometry": {"coordinates":[-0.575269,54.455894],"type":"Point"}
}