{
  "type": "Feature",
  "properties": {
    "iso:country":"GB",
    "sg:address":"12 Brecon Close",
    "sg:city":"Luton",
    "sg:classifiers":[
        {
            "category":"Home & Garden",
            "subcategory":"Garden Supply",
            "type":"Retail Goods"
        }
    ],
    "sg:phone":"+44 1582 419102",
    "sg:postcode":"LU1 5HS",
    "sg:province":"Bedfordshire",
    "sg:tags":[
        "pool",
        "swimming"
    ],
    "wof:name":"D Witton",
    "wof:placetype":"venue"
},
  "geometry": {"coordinates":[-0.4220150113,51.8742256165],"type":"Point"}
}