{
  "type": "Feature",
  "properties": {
    "iso:country":"GB",
    "sg:address":"14 Golders Manor Drive, Golders Green",
    "sg:city":"London",
    "sg:classifiers":[
        {
            "category":"Building & Trades",
            "subcategory":"Construction",
            "type":"Services"
        }
    ],
    "sg:postcode":"NW11 9HT",
    "sg:province":"Greater London",
    "sg:tags":[
        "builder"
    ],
    "wof:name":"Moa Builders Ltd",
    "wof:placetype":"venue"
},
  "geometry": {"coordinates":[-0.2108719945,51.5796470642],"type":"Point"}
}