{
  "type": "Feature",
  "properties": {
    "addr:full":"598 Hitchin Road Luton Bedfordshire LU2 7UG",
    "addr:housenumber":"598",
    "addr:postcode":"lu2 7ug",
    "addr:street":"Hitchin Road",
    "iso:country":"GB",
    "sg:address":"598 Hitchin Road",
    "sg:city":"Luton",
    "sg:classifiers":[
        {
            "category":"Food & Beverages",
            "subcategory":"Groceries & Convenience Stores",
            "type":"Retail Goods"
        }
    ],
    "sg:phone":"+44 1582 736471",
    "sg:postcode":"LU2 7UG",
    "sg:province":"Bedfordshire",
    "wof:name":"S & K Stores",
    "wof:placetype":"venue"
},
  "geometry": {"coordinates":[-0.3987909853,51.90076828],"type":"Point"}
}