{
  "type": "Feature",
  "properties": {
    "addr:full":"9a Station Avenue North Houghton Le Spring Durham DH4 6HS",
    "addr:housenumber":"9a",
    "addr:postcode":"dh4 6hs",
    "addr:street":"Station Avenue North;Spring",
    "iso:country":"GB",
    "sg:address":"9a Station Avenue North",
    "sg:city":"Houghton Le Spring",
    "sg:classifiers":[
        {
            "category":"Manufacturing",
            "subcategory":"Petroleum Products",
            "type":"Manufacturing & Wholesale Goods"
        }
    ],
    "sg:phone":"+44 191 385 7696",
    "sg:postcode":"DH4 6HS",
    "sg:province":"Durham",
    "sg:tags":[
        "double",
        "glazing"
    ],
    "wof:name":"Crown uPVC Windows",
    "wof:placetype":"venue"
},
  "geometry": {"coordinates":[-1.5051939487,54.8459014893],"type":"Point"}
}