{
  "type": "Feature",
  "properties": {
    "addr:full":"Mansbridge Road, West End Southampton Hampshire SO18 3HW",
    "addr:postcode":"so18 3hw",
    "addr:street":"Mansbridge Road",
    "iso:country":"GB",
    "sg:address":"Mansbridge Road, West End",
    "sg:city":"Southampton",
    "sg:classifiers":[
        {
            "category":"Shopping",
            "subcategory":"Crafts & Fabrics",
            "type":"Retail Goods"
        }
    ],
    "sg:phone":"+44 23 8047 0555",
    "sg:postcode":"SO18 3HW",
    "sg:province":"Hampshire",
    "sg:tags":[
        "material",
        "art"
    ],
    "wof:name":"Hobbycraft",
    "wof:placetype":"venue"
},
  "geometry": {"coordinates":[-1.357604,50.937794],"type":"Point"}
}