{
  "type": "Feature",
  "properties": {
    "addr:full":"2 Duckworth Gro Bradford West Yorkshire BD9 5HQ",
    "addr:housenumber":"2",
    "addr:postcode":"bd9 5hq",
    "addr:street":"Duckworth Gro Bradford West",
    "iso:country":"GB",
    "sg:address":"2 Duckworth Gro",
    "sg:city":"Bradford",
    "sg:classifiers":[
        {
            "category":"Food & Beverages",
            "subcategory":"Bakery",
            "type":"Retail Goods"
        }
    ],
    "sg:phone":"+44 1274 482313",
    "sg:postcode":"BD9 5HQ",
    "sg:province":"West Yorkshire",
    "sg:tags":[
        "pizza"
    ],
    "wof:name":"Pizza Hut",
    "wof:placetype":"venue"
},
  "geometry": {"coordinates":[-1.7906030416,53.8059120178],"type":"Point"}
}