{
  "type": "Feature",
  "properties": {
    "iso:country":"GB",
    "sg:address":"135 The Moor",
    "sg:city":"Sheffield",
    "sg:classifiers":[
        {
            "category":"Sports & Exercise",
            "subcategory":"Sports Center",
            "type":"Entertainment"
        }
    ],
    "sg:phone":"+44 114 272 1257",
    "sg:postcode":"S1 4PH",
    "sg:province":"South Yorkshire",
    "sg:tags":[
        "shop",
        "good"
    ],
    "wof:name":"Bodyactive (Sheffield)",
    "wof:placetype":"venue"
},
  "geometry": {"coordinates":[-1.474393,53.375141],"type":"Point"}
}