{
  "type": "Feature",
  "properties": {
    "addr:full":"7 Thurbans Rd Farnham Surrey GU9 8TD",
    "addr:housenumber":"7",
    "addr:postcode":"gu9 8td",
    "addr:street":"Thurbans Rd",
    "iso:country":"GB",
    "sg:address":"7 Thurbans Rd",
    "sg:city":"Farnham",
    "sg:classifiers":[
        {
            "category":"Home & Garden",
            "subcategory":"Building Materials",
            "type":"Retail Goods"
        }
    ],
    "sg:postcode":"GU9 8TD",
    "sg:province":"Surrey",
    "sg:tags":[
        "fencing"
    ],
    "wof:name":"Paine,T,",
    "wof:placetype":"venue"
},
  "geometry": {"coordinates":[-0.8110430241,51.19921875],"type":"Point"}
}