{
  "type": "Feature",
  "properties": {
    "addr:full":"6 Fieldhead Gardens Bourne End Berkshire SL8 5RN",
    "addr:housenumber":"6",
    "addr:postcode":"sl8 5rn",
    "addr:street":"Fieldhead Gardens Bourne End",
    "iso:country":"GB",
    "sg:address":"6 Fieldhead Gardens",
    "sg:city":"Bourne End",
    "sg:classifiers":[
        {
            "category":"Education",
            "subcategory":"Special Training",
            "type":"Public Place"
        }
    ],
    "sg:phone":"+44 1628 533085",
    "sg:postcode":"SL8 5RN",
    "sg:province":"Berkshire",
    "sg:tags":[
        "product",
        "centre"
    ],
    "wof:name":"Abbotsbrook Ltd.",
    "wof:placetype":"venue"
},
  "geometry": {"coordinates":[-0.711508,51.575989],"type":"Point"}
}