{
  "type": "Feature",
  "properties": {
    "addr:full":"Willow House, The Highfields Wolverhampton Shropshire WV6 8DW",
    "addr:postcode":"wv6 8dw",
    "addr:street":"The",
    "iso:country":"GB",
    "sg:address":"Willow House, The Highfields",
    "sg:city":"Wolverhampton",
    "sg:classifiers":[
        {
            "category":"Banks & Credit Unions",
            "subcategory":"Financial Services",
            "type":"Services"
        }
    ],
    "sg:phone":"+44 1902 765005",
    "sg:postcode":"WV6 8DW",
    "sg:province":"Shropshire",
    "sg:tags":[
        "adviser"
    ],
    "wof:name":"Berkley Vittoria Independent Financial Services Ltd.",
    "wof:placetype":"venue"
},
  "geometry": {"coordinates":[-2.191136,52.588623],"type":"Point"}
}