{
  "type": "Feature",
  "properties": {
    "iso:country":"GB",
    "sg:address":"Rakehead Landfill Site, Rakehead Lane",
    "sg:city":"Bacup",
    "sg:classifiers":[
        {
            "category":"Utilities",
            "subcategory":"Refuse",
            "type":"Services"
        }
    ],
    "sg:phone":"+44 1706 875695",
    "sg:postcode":"OL13 0PB",
    "sg:province":"Lancashire",
    "sg:tags":[
        "disposal",
        "waste",
        "retail"
    ],
    "wof:name":"Lancashire Waste Services Ltd",
    "wof:placetype":"venue"
},
  "geometry": {"coordinates":[-2.2011039257,53.7027168274],"type":"Point"}
}