{
  "type": "Feature",
  "properties": {
    "addr:full":"85 Northumberland Av Thornton Cleveleys Lancashire FY5 2JZ",
    "addr:housenumber":"85",
    "addr:postcode":"fy5 2jz",
    "addr:street":"Northumberland Av",
    "iso:country":"GB",
    "sg:address":"85 Northumberland Av",
    "sg:city":"Thornton Cleveleys",
    "sg:classifiers":[
        {
            "category":"Building & Trades",
            "subcategory":"Construction",
            "type":"Services"
        }
    ],
    "sg:phone":"+44 1253 852402",
    "sg:postcode":"FY5 2JZ",
    "sg:province":"Lancashire",
    "sg:tags":[
        "roofing"
    ],
    "wof:name":"Cleveleys Asphalt Co",
    "wof:placetype":"venue"
},
  "geometry": {"coordinates":[-3.0285129547,53.8884277344],"type":"Point"}
}