{
  "type": "Feature",
  "properties": {
    "iso:country":"GB",
    "sg:address":"2 Park Ave, Smithies",
    "sg:city":"Barnsley",
    "sg:classifiers":[
        {
            "category":"Arts & Performance",
            "subcategory":"Music",
            "type":"Entertainment"
        },
        {
            "category":"Bars & Pubs",
            "subcategory":"Nightclub",
            "type":"Food & Drink"
        }
    ],
    "sg:postcode":"S71 3TU",
    "sg:province":"South Yorkshire",
    "sg:tags":[
        "mobile",
        "karaoke",
        "disco"
    ],
    "wof:name":"Williams,Austin,",
    "wof:placetype":"venue"
},
  "geometry": {"coordinates":[-1.4762,53.57724],"type":"Point"}
}