{
  "type": "Feature",
  "properties": {
    "addr:full":"Park House, Brimham Rocks Road Harrogate North Yorkshire HG3 3HE",
    "addr:postcode":"hg3 3he",
    "addr:street":"Brimham Rocks Road",
    "iso:country":"GB",
    "sg:address":"Park House, Brimham Rocks Road",
    "sg:city":"Harrogate",
    "sg:classifiers":[
        {
            "category":"Farming",
            "subcategory":"Farm",
            "type":"Manufacturing & Wholesale Goods"
        }
    ],
    "sg:postcode":"HG3 3HE",
    "sg:province":"North Yorkshire",
    "sg:tags":[
        "mixed",
        "crop"
    ],
    "wof:name":"William P Gratton",
    "wof:placetype":"venue"
},
  "geometry": {"coordinates":[-1.622,54.046803],"type":"Point"}
}