{
  "type": "Feature",
  "properties": {
    "iso:country":"GB",
    "sg:address":"10 Load St",
    "sg:city":"Bewdley",
    "sg:classifiers":[
        {
            "category":"Professional",
            "subcategory":"Printing & Photocopies",
            "type":"Services"
        }
    ],
    "sg:postcode":"DY12 2AF",
    "sg:province":"Shropshire",
    "sg:tags":[
        "process",
        "screen",
        "printer"
    ],
    "wof:name":"Boost Midlands",
    "wof:placetype":"venue"
},
  "geometry": {"coordinates":[-2.3150949478,52.3756866455],"type":"Point"}
}