{
  "type": "Feature",
  "properties": {
    "addr:full":"55 Highfield Avenue Brighouse West Yorkshire HD6 4EB",
    "addr:housenumber":"55",
    "addr:postcode":"hd6 4eb",
    "addr:street":"Highfield Avenue Brighouse West",
    "iso:country":"GB",
    "sg:address":"55 Highfield Avenue",
    "sg:city":"Brighouse",
    "sg:classifiers":[
        {
            "category":"Personal",
            "subcategory":"Beauty Salon",
            "type":"Services"
        }
    ],
    "sg:phone":"+44 1484 713143",
    "sg:postcode":"HD6 4EB",
    "sg:province":"West Yorkshire",
    "sg:tags":[
        "ladies",
        "lady",
        "hairdresser"
    ],
    "wof:name":"J Briggs",
    "wof:placetype":"venue"
},
  "geometry": {"coordinates":[-1.7768429518,53.7252731323],"type":"Point"}
}