{
  "type": "Feature",
  "properties": {
    "iso:country":"GB",
    "sg:address":"Tremough Barton Farm, Tremough",
    "sg:city":"Penryn",
    "sg:classifiers":[
        {
            "category":"Farming",
            "subcategory":"Livestock Farm",
            "type":"Manufacturing & Wholesale Goods"
        }
    ],
    "sg:postcode":"TR10 9EZ",
    "sg:province":"Cornwall",
    "sg:tags":[
        "others"
    ],
    "wof:name":"K E & R C Hubbard",
    "wof:placetype":"venue"
},
  "geometry": {"coordinates":[-5.128729,50.170593],"type":"Point"}
}