{
  "type": "Feature",
  "properties": {
    "addr:full":"Castle Street, Portchester Fareham Hampshire PO16 9QQ",
    "addr:postcode":"po16 9qq",
    "addr:street":"Castle Street",
    "iso:country":"GB",
    "sg:address":"Castle Street, Portchester",
    "sg:city":"Fareham",
    "sg:classifiers":[
        {
            "category":"Bars & Pubs",
            "type":"Food & Drink"
        }
    ],
    "sg:phone":"+44 23 9237 6188",
    "sg:postcode":"PO16 9QQ",
    "sg:province":"Hampshire",
    "sg:tags":[
        "pubs",
        "inn"
    ],
    "wof:name":"The White Hart",
    "wof:placetype":"venue"
},
  "geometry": {"coordinates":[-1.130738,50.846088],"type":"Point"}
}