{
  "type": "Feature",
  "properties": {
    "addr:full":"Cedar Lodge Retford Nottinghamshire DN22 0PR",
    "addr:postcode":"dn22 0pr",
    "iso:country":"GB",
    "sg:address":"Cedar Lodge",
    "sg:city":"Retford",
    "sg:classifiers":[
        {
            "category":"Organizations",
            "subcategory":"Non-profit Organization",
            "type":"Services"
        }
    ],
    "sg:phone":"+44 1777 706441",
    "sg:postcode":"DN22 0PR",
    "sg:province":"Nottinghamshire",
    "sg:tags":[
        "organisation",
        "voluntary",
        "charity"
    ],
    "wof:name":"Jamia Al-Karam",
    "wof:placetype":"venue"
},
  "geometry": {"coordinates":[-0.945728,53.325184],"type":"Point"}
}