{
  "type": "Feature",
  "properties": {
    "addr:full":"Unit 3, Campbell Rd Stoke On Trent Staffordshire ST4 4DX",
    "addr:housenumber":"unit 3",
    "addr:postcode":"st4 4dx",
    "addr:street":"Campbell Rd",
    "iso:country":"GB",
    "sg:address":"Unit 3, Campbell Rd",
    "sg:city":"Stoke On Trent",
    "sg:classifiers":[
        {
            "category":"Building & Trades",
            "subcategory":"Construction",
            "type":"Services"
        }
    ],
    "sg:phone":"+44 1782 749009",
    "sg:postcode":"ST4 4DX",
    "sg:province":"Staffordshire",
    "sg:tags":[
        "builder"
    ],
    "wof:name":"Losthead Ltd",
    "wof:placetype":"venue"
},
  "geometry": {"coordinates":[-2.183909,52.999794],"type":"Point"}
}