{
  "type": "Feature",
  "properties": {
    "addr:full":"Grant Works Leeds West Yorkshire LS15 8AF",
    "addr:postcode":"ls15 8af",
    "addr:street":"West",
    "iso:country":"GB",
    "sg:address":"Grant Works",
    "sg:city":"Leeds",
    "sg:classifiers":[
        {
            "category":"Autos & Motor Vehicles",
            "subcategory":"Auto Supplies",
            "type":"Retail Goods"
        }
    ],
    "sg:phone":"+44 1604 770053",
    "sg:postcode":"LS15 8AF",
    "sg:province":"West Yorkshire",
    "sg:tags":[
        "component"
    ],
    "wof:name":"Hamtune Spares Ltd.",
    "wof:placetype":"venue"
},
  "geometry": {"coordinates":[-1.448844,53.802238],"type":"Point"}
}