{
  "type": "Feature",
  "properties": {
    "addr:full":"136 Wythenshawe Road, Northern Moor Manchester Cheshire M23 0PD",
    "addr:housenumber":"136",
    "addr:postcode":"m23 0pd",
    "addr:street":"Wythenshawe Road",
    "iso:country":"GB",
    "sg:address":"136 Wythenshawe Road, Northern Moor",
    "sg:city":"Manchester",
    "sg:classifiers":[
        {
            "category":"Social Services",
            "subcategory":"Retirement Home",
            "type":"Services"
        }
    ],
    "sg:phone":"+44 161 998 6199",
    "sg:postcode":"M23 0PD",
    "sg:province":"Cheshire",
    "sg:tags":[
        "residential",
        "care"
    ],
    "wof:name":"Coppice Residential Home",
    "wof:placetype":"venue"
},
  "geometry": {"coordinates":[-2.275724,53.407364],"type":"Point"}
}