{
  "type": "Feature",
  "properties": {
    "iso:country":"GB",
    "sg:address":"109 The St, Rustington",
    "sg:city":"Littlehampton",
    "sg:classifiers":[
        {
            "category":"Health Services",
            "subcategory":"Optometrist",
            "type":"Services"
        }
    ],
    "sg:phone":"+44 1903 785048",
    "sg:postcode":"BN16 3DP",
    "sg:province":"West Sussex",
    "sg:tags":[
        "optician"
    ],
    "wof:name":"Clifford Brown Opticians",
    "wof:placetype":"venue"
},
  "geometry": {"coordinates":[-0.507077,50.810318],"type":"Point"}
}