{
  "type": "Feature",
  "properties": {
    "iso:country":"GB",
    "sg:address":"Mosterton Road, Misterton",
    "sg:city":"Crewkerne",
    "sg:classifiers":[
        {
            "category":"Autos & Motor Vehicles",
            "subcategory":"Motorcycle Sales",
            "type":"Retail Goods"
        }
    ],
    "sg:phone":"+44 1460 72318",
    "sg:postcode":"TA18 8NT",
    "sg:province":"Dorset",
    "sg:tags":[
        "scooter",
        "cycle"
    ],
    "wof:name":"Taylors Motorcycles",
    "wof:placetype":"venue"
},
  "geometry": {"coordinates":[-2.7738559246,50.8702125549],"type":"Point"}
}