{
  "type": "Feature",
  "properties": {
    "addr:full":"22 Milborough Road, Ystalyfera Swansea Carmarthenshire SA9 2AB",
    "addr:housenumber":"22",
    "addr:postcode":"sa9 2ab",
    "addr:street":"Milborough Road",
    "iso:country":"GB",
    "sg:address":"22 Milborough Road, Ystalyfera",
    "sg:city":"Swansea",
    "sg:classifiers":[
        {
            "category":"Health Services",
            "subcategory":"Nursing And Care Facility",
            "type":"Services"
        },
        {
            "category":"Social Services",
            "subcategory":"Retirement Home",
            "type":"Services"
        }
    ],
    "sg:phone":"+44 1792 882498",
    "sg:postcode":"SA9 2AB",
    "sg:province":"Carmarthenshire",
    "sg:tags":[
        "residential"
    ],
    "wof:name":"Hollies Residential Home",
    "wof:placetype":"venue"
},
  "geometry": {"coordinates":[-3.784284,51.766434],"type":"Point"}
}