{
  "type": "Feature",
  "properties": {
    "addr:full":"80 St. Helens St, Elsecar Barnsley South Yorkshire S74 8BH",
    "addr:housenumber":"80",
    "addr:postcode":"s74 8bh",
    "addr:street":"St.;St;Yorkshire",
    "iso:country":"GB",
    "sg:address":"80 St. Helens St, Elsecar",
    "sg:city":"Barnsley",
    "sg:classifiers":[
        {
            "category":"Manufacturing",
            "subcategory":"Textiles",
            "type":"Manufacturing & Wholesale Goods"
        }
    ],
    "sg:phone":"+44 1226 741558",
    "sg:postcode":"S74 8BH",
    "sg:province":"South Yorkshire",
    "sg:tags":[
        "made-up"
    ],
    "wof:name":"Alterations & Curtain Services",
    "wof:placetype":"venue"
},
  "geometry": {"coordinates":[-1.426022,53.501175],"type":"Point"}
}