{
  "type": "Feature",
  "properties": {
    "addr:full":"233 Glasgow Road, Blantyre Glasgow South Lanarkshire G72 0YS",
    "addr:housenumber":"233",
    "addr:postcode":"g72 0ys",
    "addr:street":"Glasgow Road",
    "iso:country":"GB",
    "sg:address":"233 Glasgow Road, Blantyre",
    "sg:city":"Glasgow",
    "sg:classifiers":[
        {
            "category":"Retail",
            "subcategory":"Funeral Services",
            "type":"Services"
        }
    ],
    "sg:phone":"+44 1698 828335",
    "sg:postcode":"G72 0YS",
    "sg:province":"South Lanarkshire",
    "sg:tags":[
        "director"
    ],
    "wof:name":"CO-OPERATIVE FUNERAL SERVICES LTD",
    "wof:placetype":"venue"
},
  "geometry": {"coordinates":[-4.0922789574,55.7938308716],"type":"Point"}
}