{
  "type": "Feature",
  "properties": {
    "addr:full":"Care Of Redfearn Barnsley South Yorkshire S71 2QG",
    "addr:postcode":"s71 2qg",
    "addr:street":"Yorkshire",
    "iso:country":"GB",
    "sg:address":"Care Of Redfearn",
    "sg:city":"Barnsley",
    "sg:classifiers":[
        {
            "category":"Manufacturing",
            "subcategory":"Wood Products",
            "type":"Manufacturing & Wholesale Goods"
        }
    ],
    "sg:postcode":"S71 2QG",
    "sg:province":"South Yorkshire",
    "sg:tags":[
        "packaging",
        "crate",
        "pallets"
    ],
    "wof:name":"Wheatley Pallet Services",
    "wof:placetype":"venue"
},
  "geometry": {"coordinates":[-1.45403,53.566292],"type":"Point"}
}