{
  "type": "Feature",
  "properties": {
    "addr:full":"49 Thistle St Edinburgh City of Edinburgh EH2 1DY",
    "addr:housenumber":"49",
    "addr:postcode":"eh2 1dy",
    "addr:street":"Thistle St Edinburgh",
    "iso:country":"GB",
    "sg:address":"49 Thistle St",
    "sg:city":"Edinburgh",
    "sg:classifiers":[
        {
            "category":"Shopping",
            "subcategory":"Antiques",
            "type":"Retail Goods"
        }
    ],
    "sg:postcode":"EH2 1DY",
    "sg:province":"City of Edinburgh",
    "wof:name":"Young,Aldric,",
    "wof:placetype":"venue"
},
  "geometry": {"coordinates":[-3.199379,55.954102],"type":"Point"}
}