{
  "type": "Feature",
  "properties": {
    "addr:full":"Redcliffe Quay Bristol City of Bristol BS1 6HU",
    "addr:postcode":"bs1 6hu",
    "addr:street":"Quay",
    "iso:country":"GB",
    "sg:address":"Redcliffe Quay",
    "sg:city":"Bristol",
    "sg:classifiers":[
        {
            "category":"Manufacturing",
            "subcategory":"Tools & Machinery",
            "type":"Manufacturing & Wholesale Goods"
        }
    ],
    "sg:phone":"+44 117 929 6500",
    "sg:postcode":"BS1 6HU",
    "sg:province":"City of Bristol",
    "sg:tags":[
        "society",
        "friendly"
    ],
    "wof:name":"Hsbc Life (U K) Ltd.",
    "wof:placetype":"venue"
},
  "geometry": {"coordinates":[-2.5914289951,51.453666687],"type":"Point"}
}