{
  "type": "Feature",
  "properties": {
    "addr:full":"Unit 4, Titan Way Britannia Enterprise P Lichfield Staffordshire WS14 9TT",
    "addr:housenumber":"unit 4;p",
    "addr:postcode":"ws14 9tt",
    "addr:street":"Titan Way;Lichfield Staffordshire",
    "iso:country":"GB",
    "sg:address":"Unit 4, Titan Way Britannia Enterprise P",
    "sg:city":"Lichfield",
    "sg:classifiers":[
        {
            "category":"Manufacturing",
            "subcategory":"Textiles",
            "type":"Manufacturing & Wholesale Goods"
        }
    ],
    "sg:phone":"+44 1543 419993",
    "sg:postcode":"WS14 9TT",
    "sg:province":"Staffordshire",
    "sg:tags":[
        "made-up"
    ],
    "wof:name":"Lichfield Interiors Ltd.",
    "wof:placetype":"venue"
},
  "geometry": {"coordinates":[-1.796789,52.683739],"type":"Point"}
}