{
  "type": "Feature",
  "properties": {
    "iso:country":"GB",
    "sg:address":"Sweet Briars, East Dean Road, Lockerley",
    "sg:city":"Romsey",
    "sg:classifiers":[
        {
            "category":"Shopping",
            "subcategory":"Pharmacy",
            "type":"Retail Goods"
        }
    ],
    "sg:phone":"+44 1794 340604",
    "sg:postcode":"SO51 0JQ",
    "sg:province":"Hampshire",
    "sg:tags":[
        "medicine",
        "therapy"
    ],
    "wof:name":"Jeanette Silver",
    "wof:placetype":"venue"
},
  "geometry": {"coordinates":[-1.5710940361,51.0347290039],"type":"Point"}
}