{
  "type": "Feature",
  "properties": {
    "addr:full":"40 York Road Tadcaster North Yorkshire LS24 8AF",
    "addr:housenumber":"40",
    "addr:postcode":"ls24 8af",
    "addr:street":"York Road",
    "iso:country":"GB",
    "sg:address":"40 York Road",
    "sg:city":"Tadcaster",
    "sg:classifiers":[
        {
            "category":"Fast Food",
            "type":"Food & Drink"
        }
    ],
    "sg:phone":"+44 1937 834535",
    "sg:postcode":"LS24 8AF",
    "sg:province":"North Yorkshire",
    "sg:tags":[
        "shop",
        "fish",
        "take",
        "chip",
        "away"
    ],
    "wof:name":"York Road Takeaway",
    "wof:placetype":"venue"
},
  "geometry": {"coordinates":[-1.256232,53.887417],"type":"Point"}
}