{
  "type": "Feature",
  "properties": {
    "addr:full":"115 Brick La Whitechapel Greater London E1 6RL",
    "addr:housenumber":"115",
    "addr:postcode":"e1 6rl",
    "addr:street":"Brick La Whitechapel",
    "iso:country":"GB",
    "sg:address":"115 Brick La",
    "sg:city":"Whitechapel",
    "sg:classifiers":[
        {
            "category":"Shopping",
            "subcategory":"Used Merchandise",
            "type":"Retail Goods"
        }
    ],
    "sg:phone":"+44 20 7375 2339",
    "sg:postcode":"E1 6RL",
    "sg:province":"Greater London",
    "sg:tags":[
        "furniture"
    ],
    "wof:name":"Brick Lane Furniture Removers",
    "wof:placetype":"venue"
},
  "geometry": {"coordinates":[-0.0716399997,51.5200653076],"type":"Point"}
}