{
  "type": "Feature",
  "properties": {
    "iso:country":"GB",
    "sg:address":"The Forest Leicester La, Desford",
    "sg:city":"Leicester",
    "sg:classifiers":[
        {
            "category":"Autos & Motor Vehicles",
            "subcategory":"Automobile Sales",
            "type":"Retail Goods"
        }
    ],
    "sg:postcode":"LE9 9JJ",
    "sg:province":"Leicestershire",
    "sg:tags":[
        "commercial"
    ],
    "wof:name":"Watts,John Joseph,",
    "wof:placetype":"venue"
},
  "geometry": {"coordinates":[-1.296534,52.625858],"type":"Point"}
}