{
  "type": "Feature",
  "properties": {
    "addr:full":"Bridgegate Retford Nottinghamshire DN22 7UX",
    "addr:postcode":"dn22 7ux",
    "addr:street":"Bridgegate",
    "iso:country":"GB",
    "sg:address":"Bridgegate",
    "sg:city":"Retford",
    "sg:classifiers":[
        {
            "category":"Health Services",
            "subcategory":"Doctor",
            "type":"Services"
        },
        {
            "category":"Health Services",
            "subcategory":"Clinic",
            "type":"Services"
        }
    ],
    "sg:phone":"+44 1777 702381",
    "sg:postcode":"DN22 7UX",
    "sg:province":"Nottinghamshire",
    "sg:tags":[
        "nh",
        "practitioners"
    ],
    "wof:name":"Bridgegate Surgery",
    "wof:placetype":"venue"
},
  "geometry": {"coordinates":[-0.9476140141,53.3248138428],"type":"Point"}
}