{
  "type": "Feature",
  "properties": {
    "addr:full":"22 Prenton Dell Rd Birkenhead Merseyside L43 3AW",
    "addr:housenumber":"22",
    "addr:postcode":"l43 3aw",
    "addr:street":"Prenton Dell Rd",
    "iso:country":"GB",
    "sg:address":"22 Prenton Dell Rd",
    "sg:city":"Birkenhead",
    "sg:classifiers":[
        {
            "category":"Professional",
            "subcategory":"Testing Lab",
            "type":"Services"
        }
    ],
    "sg:phone":"+44 151 608 4114",
    "sg:postcode":"L43 3AW",
    "sg:province":"Merseyside",
    "sg:tags":[
        "laboratory"
    ],
    "wof:name":"Gloria Artec UK",
    "wof:placetype":"venue"
},
  "geometry": {"coordinates":[-3.0616641045,53.3696212769],"type":"Point"}
}