{
  "type": "Feature",
  "properties": {
    "iso:country":"GB",
    "sg:address":"81 Crofton Road",
    "sg:city":"Orpington",
    "sg:classifiers":[
        {
            "category":"Health Services",
            "subcategory":"Dentist",
            "type":"Services"
        }
    ],
    "sg:phone":"+44 1689 823786",
    "sg:postcode":"BR6 8HU",
    "sg:province":"Kent",
    "wof:name":"David D Kennedy",
    "wof:placetype":"venue"
},
  "geometry": {"coordinates":[0.082479,51.372612],"type":"Point"}
}