{
  "type": "Feature",
  "properties": {
    "iso:country":"GB",
    "sg:address":"3a North Hill Road",
    "sg:city":"Ipswich",
    "sg:classifiers":[
        {
            "category":"Building & Trades",
            "subcategory":"Construction",
            "type":"Services"
        }
    ],
    "sg:phone":"+44 1473 212796",
    "sg:postcode":"IP4 2PW",
    "sg:province":"Suffolk",
    "sg:tags":[
        "builder"
    ],
    "wof:name":"W J M & Co. Builders (Ipswich) Ltd.",
    "wof:placetype":"venue"
},
  "geometry": {"coordinates":[1.169017,52.059708],"type":"Point"}
}