{
  "type": "Feature",
  "properties": {
    "addr:full":"40, Somerville Point, 305 Rotherhithe Street London Greater London SE16 5EQ",
    "addr:housenumber":"40;305",
    "addr:postcode":"se16 5eq",
    "addr:street":"Somerville Point;Rotherhithe Street",
    "iso:country":"GB",
    "sg:address":"40, Somerville Point, 305 Rotherhithe Street",
    "sg:city":"London",
    "sg:classifiers":[
        {
            "category":"Professional",
            "subcategory":"Computer Services",
            "type":"Services"
        }
    ],
    "sg:postcode":"SE16 5EQ",
    "sg:province":"Greater London",
    "sg:tags":[
        "system",
        "software"
    ],
    "wof:name":"Electrise Ltd",
    "wof:placetype":"venue"
},
  "geometry": {"coordinates":[-0.03321,51.501961],"type":"Point"}
}