{
  "type": "Feature",
  "properties": {
    "addr:full":"25 London Road, Headington Oxford Oxfordshire OX3 7RE",
    "addr:housenumber":"25",
    "addr:postcode":"ox3 7re",
    "addr:street":"London Road",
    "iso:country":"GB",
    "sg:address":"25 London Road, Headington",
    "sg:city":"Oxford",
    "sg:classifiers":[
        {
            "category":"Travel",
            "subcategory":"Hotels & Motels",
            "type":"Entertainment"
        }
    ],
    "sg:phone":"+44 1865 769944",
    "sg:postcode":"OX3 7RE",
    "sg:province":"Oxfordshire",
    "sg:tags":[
        "house",
        "guest"
    ],
    "wof:name":"The Dial House",
    "wof:placetype":"venue"
},
  "geometry": {"coordinates":[-1.2158700228,51.7587585449],"type":"Point"}
}