{
  "type": "Feature",
  "properties": {
    "iso:country":"GB",
    "sg:address":"The Old School House, Woburn Lane, Aspley Guise",
    "sg:city":"Milton Keynes",
    "sg:classifiers":[
        {
            "category":"Professional",
            "subcategory":"Engineering",
            "type":"Services"
        }
    ],
    "sg:phone":"+44 1908 583888",
    "sg:postcode":"MK17 8JJ",
    "sg:province":"Bedfordshire",
    "sg:tags":[
        "precision",
        "engineer"
    ],
    "wof:name":"D C Hall Ltd.",
    "wof:placetype":"venue"
},
  "geometry": {"coordinates":[-0.6278799772,52.0133209229],"type":"Point"}
}