{
  "type": "Feature",
  "properties": {
    "iso:country":"GB",
    "sg:address":"Commerce Way",
    "sg:city":"Colchester",
    "sg:classifiers":[
        {
            "category":"Professional",
            "subcategory":"Business Services",
            "type":"Services"
        },
        {
            "category":"Wholesale",
            "subcategory":"Books, Periodicals, & Newspapers",
            "type":"Manufacturing & Wholesale Goods"
        }
    ],
    "sg:phone":"+44 1206 796351",
    "sg:postcode":"CO2 8HP",
    "sg:province":"Essex",
    "sg:tags":[
        "publishers'",
        "publishing"
    ],
    "wof:name":"Portland Press Ltd",
    "wof:placetype":"venue"
},
  "geometry": {"coordinates":[0.93282,51.874641],"type":"Point"}
}