{
  "type": "Feature",
  "properties": {
    "iso:country":"GB",
    "sg:address":"1a Victoria Place, Cobden Street",
    "sg:city":"Peterborough",
    "sg:classifiers":[
        {
            "category":"Professional",
            "type":"Services"
        }
    ],
    "sg:phone":"+44 1733 314464",
    "sg:postcode":"PE1 2HF",
    "sg:province":"Cambridgeshire",
    "sg:tags":[
        "linen",
        "hire"
    ],
    "wof:name":"Anglia Laundry & Linen Hire Services",
    "wof:placetype":"venue"
},
  "geometry": {"coordinates":[-0.2489819974,52.5814208984],"type":"Point"}
}