{
  "type": "Feature",
  "properties": {
    "addr:full":"Allport Rd, Bromborough Wirral Cheshire CH62 6AE",
    "addr:postcode":"ch62 6ae",
    "addr:street":"Allport Rd",
    "iso:country":"GB",
    "sg:address":"Allport Rd, Bromborough",
    "sg:city":"Wirral",
    "sg:classifiers":[
        {
            "category":"Education",
            "subcategory":"Preschool",
            "type":"Public Place"
        },
        {
            "category":"Education",
            "subcategory":"School",
            "type":"Public Place"
        }
    ],
    "sg:phone":"+44 151 334 4345",
    "sg:postcode":"CH62 6AE",
    "sg:province":"Cheshire",
    "sg:tags":[
        "local",
        "pre-school",
        "playgroups",
        "authority"
    ],
    "wof:name":"Christ The King Catholic Aided Primary School",
    "wof:placetype":"venue"
},
  "geometry": {"coordinates":[-2.972834,53.325165],"type":"Point"}
}