{
  "type": "Feature",
  "properties": {
    "addr:full":", South Chard Chard Devon TA20 4QH",
    "addr:postcode":"ta20 4qh",
    "addr:street":"South",
    "iso:country":"GB",
    "sg:address":", South Chard",
    "sg:city":"Chard",
    "sg:classifiers":[
        {
            "category":"Bars & Pubs",
            "type":"Food & Drink"
        }
    ],
    "sg:phone":"+44 1460 220285",
    "sg:postcode":"TA20 4QH",
    "sg:province":"Devon",
    "sg:tags":[
        "pubs",
        "inn"
    ],
    "wof:name":"The Golden Fleece Inn",
    "wof:placetype":"venue"
},
  "geometry": {"coordinates":[-2.9391899109,50.8467292786],"type":"Point"}
}