{
  "type": "Feature",
  "properties": {
    "addr:full":"18 Market Street Brighton East Sussex BN1 1HH",
    "addr:housenumber":"18",
    "addr:postcode":"bn1 1hh",
    "addr:street":"Market Street",
    "iso:country":"GB",
    "sg:address":"18 Market Street",
    "sg:city":"Brighton",
    "sg:classifiers":[
        {
            "category":"Shopping",
            "subcategory":"Department Store",
            "type":"Retail Goods"
        }
    ],
    "sg:phone":"+44 1273 690300",
    "sg:postcode":"BN1 1HH",
    "sg:province":"East Sussex",
    "wof:name":"Special Occasions",
    "wof:placetype":"venue"
},
  "geometry": {"coordinates":[-0.1400559992,50.821346283],"type":"Point"}
}