{
  "type": "Feature",
  "properties": {
    "addr:full":"21 Canterbury Rd Sittingbourne Kent ME10 4SG",
    "addr:housenumber":"21",
    "addr:postcode":"me10 4sg",
    "addr:street":"Canterbury Rd",
    "iso:country":"GB",
    "sg:address":"21 Canterbury Rd",
    "sg:city":"Sittingbourne",
    "sg:classifiers":[
        {
            "category":"Shopping",
            "subcategory":"Department Store",
            "type":"Retail Goods"
        }
    ],
    "sg:postcode":"ME10 4SG",
    "sg:province":"Kent",
    "wof:name":"Graham,Linda,",
    "wof:placetype":"venue"
},
  "geometry": {"coordinates":[0.7493849993,51.3378562927],"type":"Point"}
}