{
  "type": "Feature",
  "properties": {
    "iso:country":"GB",
    "sg:address":"62 Robertson Road",
    "sg:city":"Bristol",
    "sg:classifiers":[
        {
            "category":"Utilities",
            "subcategory":"Sewage",
            "type":"Services"
        }
    ],
    "sg:postcode":"BS5 6JT",
    "sg:province":"City of Bristol",
    "sg:tags":[
        "acoustic",
        "consultant"
    ],
    "wof:name":"Soundwave Acoustics",
    "wof:placetype":"venue"
},
  "geometry": {"coordinates":[-2.5601799488,51.4692192078],"type":"Point"}
}