{
  "type": "Feature",
  "properties": {
    "addr:full":"70 Mill Hill Road Cowes Isle of Wight PO31 7EQ",
    "addr:housenumber":"70",
    "addr:postcode":"po31 7eq",
    "addr:street":"Mill Hill Road",
    "iso:country":"GB",
    "sg:address":"70 Mill Hill Road",
    "sg:city":"Cowes",
    "sg:classifiers":[
        {
            "category":"Shopping",
            "subcategory":"Pets & Pet Supplies",
            "type":"Retail Goods"
        }
    ],
    "sg:phone":"+44 1983 291607",
    "sg:postcode":"PO31 7EQ",
    "sg:province":"Isle of Wight",
    "sg:tags":[
        "food"
    ],
    "wof:name":"Oscar",
    "wof:placetype":"venue"
},
  "geometry": {"coordinates":[-1.3002450466,50.7571144104],"type":"Point"}
}