{
  "type": "Feature",
  "properties": {
    "addr:full":"101 Tachbrook Street London Greater London SW1V 2QA",
    "addr:housenumber":"101",
    "addr:postcode":"sw1v 2qa",
    "addr:street":"Tachbrook Street",
    "iso:country":"GB",
    "sg:address":"101 Tachbrook Street",
    "sg:city":"London",
    "sg:classifiers":[
        {
            "category":"Food & Beverages",
            "subcategory":"Bakery",
            "type":"Retail Goods"
        }
    ],
    "sg:postcode":"SW1V 2QA",
    "sg:province":"Greater London",
    "sg:tags":[
        "baker"
    ],
    "wof:name":"Tachbrook Bakery & Patisserie",
    "wof:placetype":"venue"
},
  "geometry": {"coordinates":[-0.134122,51.48922],"type":"Point"}
}