{
  "type": "Feature",
  "properties": {
    "addr:full":"37 Rivermead Road, Denton Manchester Greater Manchester M34 7PQ",
    "addr:housenumber":"37",
    "addr:postcode":"m34 7pq",
    "addr:street":"Rivermead Road",
    "iso:country":"GB",
    "sg:address":"37 Rivermead Road, Denton",
    "sg:city":"Manchester",
    "sg:classifiers":[
        {
            "category":"Building & Trades",
            "subcategory":"Construction",
            "type":"Services"
        }
    ],
    "sg:phone":"+44 161 336 2534",
    "sg:postcode":"M34 7PQ",
    "sg:province":"Greater Manchester",
    "sg:tags":[
        "builder"
    ],
    "wof:name":"Gary Mycock",
    "wof:placetype":"venue"
},
  "geometry": {"coordinates":[-2.0984508991,53.4382362366],"type":"Point"}
}