{
  "type": "Feature",
  "properties": {
    "addr:full":"117 Lozells Road Birmingham West Midlands B19 2TR",
    "addr:housenumber":"117",
    "addr:postcode":"b19 2tr",
    "addr:street":"Lozells Road",
    "iso:country":"GB",
    "sg:address":"117 Lozells Road",
    "sg:city":"Birmingham",
    "sg:classifiers":[
        {
            "category":"Shopping",
            "subcategory":"Pharmacy",
            "type":"Retail Goods"
        }
    ],
    "sg:phone":"+44 121 554 0472",
    "sg:postcode":"B19 2TR",
    "sg:province":"West Midlands",
    "sg:tags":[
        "pharmacist",
        "chemist"
    ],
    "wof:name":"Rana Dispensing Chemist",
    "wof:placetype":"venue"
},
  "geometry": {"coordinates":[-1.9068369865,52.5029945374],"type":"Point"}
}