{
  "type": "Feature",
  "properties": {
    "iso:country":"GB",
    "sg:address":"58 Lark Rise, Woodfield",
    "sg:city":"Northampton",
    "sg:classifiers":[
        {
            "category":"Shopping",
            "subcategory":"Photographic Equipment",
            "type":"Retail Goods"
        }
    ],
    "sg:phone":"+44 1604 413447",
    "sg:postcode":"NN3 8QT",
    "sg:province":"Northamptonshire",
    "wof:name":"John Heywood Photographer",
    "wof:placetype":"venue"
},
  "geometry": {"coordinates":[-0.8220340014,52.2642745972],"type":"Point"}
}