{
  "type": "Feature",
  "properties": {
    "iso:country":"GB",
    "sg:address":"Suite 14 Munro House, Duke Street",
    "sg:city":"Leeds",
    "sg:classifiers":[
        {
            "category":"Organizations",
            "subcategory":"Non-profit Organization",
            "type":"Services"
        }
    ],
    "sg:phone":"+44 113 244 6007",
    "sg:postcode":"LS9 8AG",
    "sg:province":"West Yorkshire",
    "sg:tags":[
        "organisation",
        "voluntary",
        "charity"
    ],
    "wof:name":"The Stop Project",
    "wof:placetype":"venue"
},
  "geometry": {"coordinates":[-1.533911,53.795986],"type":"Point"}
}