{
  "type": "Feature",
  "properties": {
    "addr:full":"C159 New Covent Garden Market London Greater London SW8 5NA",
    "addr:housenumber":"c159;covent garden",
    "addr:postcode":"sw8 5na",
    "addr:street":"New;Market",
    "iso:country":"GB",
    "sg:address":"C159 New Covent Garden Market",
    "sg:city":"London",
    "sg:classifiers":[
        {
            "category":"Wholesale",
            "subcategory":"Fruits & Vegetables",
            "type":"Manufacturing & Wholesale Goods"
        }
    ],
    "sg:phone":"+44 20 7622 9900",
    "sg:postcode":"SW8 5NA",
    "sg:province":"Greater London",
    "wof:name":"Side Salad",
    "wof:placetype":"venue"
},
  "geometry": {"coordinates":[-0.1228,51.511589],"type":"Point"}
}