{
  "type": "Feature",
  "properties": {
    "addr:full":"Bank House, King Street Clitheroe Lancashire BB7 2EL",
    "addr:postcode":"bb7 2el",
    "addr:street":"King Street",
    "iso:country":"GB",
    "sg:address":"Bank House, King Street",
    "sg:city":"Clitheroe",
    "sg:classifiers":[
        {
            "category":"Organizations",
            "subcategory":"Community Association",
            "type":"Services"
        }
    ],
    "sg:postcode":"BB7 2EL",
    "sg:province":"Lancashire",
    "sg:tags":[
        "relation",
        "public"
    ],
    "wof:name":"Awpr",
    "wof:placetype":"venue"
},
  "geometry": {"coordinates":[-2.393254,53.873329],"type":"Point"}
}