{
  "type": "Feature",
  "properties": {
    "addr:full":"397 Gathurst Road, Shevington Wigan Lancashire WN6 8JB",
    "addr:housenumber":"397",
    "addr:postcode":"wn6 8jb",
    "addr:street":"Gathurst Road",
    "iso:country":"GB",
    "sg:address":"397 Gathurst Road, Shevington",
    "sg:city":"Wigan",
    "sg:classifiers":[
        {
            "category":"Sports & Exercise",
            "subcategory":"Stables",
            "type":"Entertainment"
        }
    ],
    "sg:postcode":"WN6 8JB",
    "sg:province":"Lancashire",
    "sg:tags":[
        "education",
        "equestrian"
    ],
    "wof:name":"Deandane Riding Stables",
    "wof:placetype":"venue"
},
  "geometry": {"coordinates":[-2.696142,53.560452],"type":"Point"}
}