{
  "type": "Feature",
  "properties": {
    "addr:full":"Unit 24, Wholesale Fruit Centre, Bessemer Road Cardiff Cardiff CF11 8BB",
    "addr:housenumber":"unit 24 wholesale;centre",
    "addr:postcode":"cf11 8bb",
    "addr:street":"Bessemer Road",
    "iso:country":"GB",
    "sg:address":"Unit 24, Wholesale Fruit Centre, Bessemer Road",
    "sg:city":"Cardiff",
    "sg:classifiers":[
        {
            "category":"Wholesale",
            "subcategory":"Fruits & Vegetables",
            "type":"Manufacturing & Wholesale Goods"
        }
    ],
    "sg:postcode":"CF11 8BB",
    "sg:province":"Cardiff",
    "wof:name":"Peter Broughton Ltd.",
    "wof:placetype":"venue"
},
  "geometry": {"coordinates":[-3.1983,51.465832],"type":"Point"}
}