{
  "type": "Feature",
  "properties": {
    "addr:full":"12 Clarence Avenue Bristol City of Bristol BS16 5SX",
    "addr:housenumber":"12",
    "addr:postcode":"bs16 5sx",
    "addr:street":"Clarence Avenue",
    "iso:country":"GB",
    "sg:address":"12 Clarence Avenue",
    "sg:city":"Bristol",
    "sg:classifiers":[
        {
            "category":"Autos & Motor Vehicles",
            "subcategory":"Auto Supplies",
            "type":"Retail Goods"
        }
    ],
    "sg:phone":"+44 117 970 1674",
    "sg:postcode":"BS16 5SX",
    "sg:province":"City of Bristol",
    "sg:tags":[
        "windscreen"
    ],
    "wof:name":"Windscreen Repair Service",
    "wof:placetype":"venue"
},
  "geometry": {"coordinates":[-2.503516,51.483082],"type":"Point"}
}