{
  "type": "Feature",
  "properties": {
    "addr:full":"Heath Av Stoke On Trent Cheshire ST7 3RY",
    "addr:postcode":"st7 3ry",
    "addr:street":"Heath Av Stoke On Trent",
    "iso:country":"GB",
    "sg:address":"Heath Av",
    "sg:city":"Stoke On Trent",
    "sg:classifiers":[
        {
            "category":"Education",
            "subcategory":"School",
            "type":"Public Place"
        }
    ],
    "sg:phone":"+44 1270 872914",
    "sg:postcode":"ST7 3RY",
    "sg:province":"Cheshire",
    "sg:tags":[
        "local",
        "authority"
    ],
    "wof:name":"Rode Heath County Primary School",
    "wof:placetype":"venue"
},
  "geometry": {"coordinates":[-2.29313,53.115604],"type":"Point"}
}