{
  "type": "Feature",
  "properties": {
    "addr:full":"42a High Street Battle East Sussex TN33 0EE",
    "addr:housenumber":"42a",
    "addr:postcode":"tn33 0ee",
    "addr:street":"High Street Battle",
    "iso:country":"GB",
    "sg:address":"42a High Street",
    "sg:city":"Battle",
    "sg:classifiers":[
        {
            "category":"Organizations",
            "subcategory":"Non-profit Organization",
            "type":"Services"
        }
    ],
    "sg:phone":"+44 1424 773933",
    "sg:postcode":"TN33 0EE",
    "sg:province":"East Sussex",
    "sg:tags":[
        "organisation",
        "voluntary",
        "charity"
    ],
    "wof:name":"St. Michaels Hospice (Trading) Ltd.",
    "wof:placetype":"venue"
},
  "geometry": {"coordinates":[0.48554,50.915791],"type":"Point"}
}