{
  "type": "Feature",
  "properties": {
    "addr:full":"41 Robert Franklin Way, South Cerney Cirencester Gloucestershire GL7 5UD",
    "addr:housenumber":"41",
    "addr:postcode":"gl7 5ud",
    "addr:street":"Robert Franklin Way",
    "iso:country":"GB",
    "sg:address":"41 Robert Franklin Way, South Cerney",
    "sg:city":"Cirencester",
    "sg:classifiers":[
        {
            "category":"Health Services",
            "subcategory":"Podiatrist",
            "type":"Services"
        }
    ],
    "sg:postcode":"GL7 5UD",
    "sg:province":"Gloucestershire",
    "sg:tags":[
        "podiatrists",
        "chiropodist"
    ],
    "wof:name":"Oakey D.C M.Ch.S S.R.Ch",
    "wof:placetype":"venue"
},
  "geometry": {"coordinates":[-1.9535410404,51.718547821],"type":"Point"}
}