{
  "type": "Feature",
  "properties": {
    "addr:full":"Charles Ct, 1-3 Church Rd Manchester Cheshire M41 9EH",
    "addr:housenumber":"1-3",
    "addr:postcode":"m41 9eh",
    "addr:street":"Charles Ct;Church Rd",
    "iso:country":"GB",
    "sg:address":"Charles Ct, 1-3 Church Rd",
    "sg:city":"Manchester",
    "sg:classifiers":[
        {
            "category":"Transit Center",
            "subcategory":"Passenger",
            "type":"Transportation"
        },
        {
            "category":"Professional",
            "subcategory":"Business Services",
            "type":"Services"
        }
    ],
    "sg:phone":"+44 161 748 7054",
    "sg:postcode":"M41 9EH",
    "sg:province":"Cheshire",
    "sg:tags":[
        "accomodation",
        "centre",
        "commerce"
    ],
    "wof:name":"Charles Court Business Centre",
    "wof:placetype":"venue"
},
  "geometry": {"coordinates":[-2.24881,53.479622],"type":"Point"}
}