{
  "type": "Feature",
  "properties": {
    "iso:country":"GB",
    "sg:address":"94 High St",
    "sg:city":"Ramsgate",
    "sg:classifiers":[
        {
            "category":"Shopping",
            "subcategory":"Antiques",
            "type":"Retail Goods"
        }
    ],
    "sg:phone":"+44 1843 593276",
    "sg:postcode":"CT11 9RX",
    "sg:province":"Kent",
    "wof:name":"The Antique Shop",
    "wof:placetype":"venue"
},
  "geometry": {"coordinates":[1.416491,51.335403],"type":"Point"}
}