{
  "type": "Feature",
  "properties": {
    "iso:country":"GB",
    "sg:address":"Unit 21, Millers Bridge, Seymour Street",
    "sg:city":"Bootle",
    "sg:classifiers":[
        {
            "category":"Professional",
            "subcategory":"Printing & Photocopies",
            "type":"Services"
        }
    ],
    "sg:phone":"+44 151 944 1587",
    "sg:postcode":"L20 1EE",
    "sg:province":"Merseyside",
    "sg:tags":[
        "printer"
    ],
    "wof:name":"Bennett Press",
    "wof:placetype":"venue"
},
  "geometry": {"coordinates":[-2.9991140366,53.4436988831],"type":"Point"}
}