{
  "type": "Feature",
  "properties": {
    "addr:full":"74-75 Commercial Road Hereford Herefordshire HR1 2BP",
    "addr:housenumber":"74-75",
    "addr:postcode":"hr1 2bp",
    "addr:street":"Commercial Road",
    "iso:country":"GB",
    "sg:address":"74-75 Commercial Road",
    "sg:city":"Hereford",
    "sg:classifiers":[
        {
            "category":"Professional",
            "subcategory":"Accounting & Tax Preparation",
            "type":"Services"
        }
    ],
    "sg:postcode":"HR1 2BP",
    "sg:province":"Herefordshire",
    "sg:tags":[
        "accountant"
    ],
    "wof:name":"Young & Co.",
    "wof:placetype":"venue"
},
  "geometry": {"coordinates":[-2.712015,52.05769],"type":"Point"}
}