{
  "type": "Feature",
  "properties": {
    "iso:country":"GB",
    "sg:address":"Barclays House, 35 Borough Road",
    "sg:city":"Burton-on-trent",
    "sg:classifiers":[
        {
            "category":"Manufacturing",
            "subcategory":"Tools & Machinery",
            "type":"Manufacturing & Wholesale Goods"
        },
        {
            "category":"Manufacturing",
            "subcategory":"Motor Vehicles & Parts",
            "type":"Manufacturing & Wholesale Goods"
        }
    ],
    "sg:phone":"+44 1283 533338",
    "sg:postcode":"DE14 2DA",
    "sg:province":"Derbyshire",
    "sg:tags":[
        "bearing",
        "stockist"
    ],
    "wof:name":"Hawkins Industrial Services Ltd.",
    "wof:placetype":"venue"
},
  "geometry": {"coordinates":[-1.643969,52.80711],"type":"Point"}
}