{
  "type": "Feature",
  "properties": {
    "addr:full":"Barnfield Road Spennymoor Durham DL16 6ND",
    "addr:postcode":"dl16 6nd",
    "addr:street":"Barnfield Road",
    "iso:country":"GB",
    "sg:address":"Barnfield Road",
    "sg:city":"Spennymoor",
    "sg:classifiers":[
        {
            "category":"Professional",
            "subcategory":"Employment Agencies",
            "type":"Services"
        }
    ],
    "sg:phone":"+44 1388 644446",
    "sg:postcode":"DL16 6ND",
    "sg:province":"Durham",
    "sg:tags":[
        "consultant"
    ],
    "wof:name":"Employment Service Jobcentre",
    "wof:placetype":"venue"
},
  "geometry": {"coordinates":[-1.592262,54.702335],"type":"Point"}
}