{
  "type": "Feature",
  "properties": {
    "addr:full":"18 Shopping Centre Rotherham South Yorkshire S62 6NG",
    "addr:postcode":"s62 6ng",
    "addr:street":"Centre Rotherham South",
    "iso:country":"GB",
    "sg:address":"18 Shopping Centre",
    "sg:city":"Rotherham",
    "sg:classifiers":[
        {
            "category":"Shopping",
            "type":"Retail Goods"
        }
    ],
    "sg:postcode":"S62 6NG",
    "sg:province":"South Yorkshire",
    "sg:tags":[
        "part",
        "accessory"
    ],
    "wof:name":"Motorists Diy Centre",
    "wof:placetype":"venue"
},
  "geometry": {"coordinates":[-1.34358,53.45961],"type":"Point"}
}