{
  "type": "Feature",
  "properties": {
    "iso:country":"GB",
    "sg:address":"2-8 Marine Avenue",
    "sg:city":"Whitley Bay",
    "sg:classifiers":[
        {
            "category":"Restaurant",
            "type":"Food & Drink"
        }
    ],
    "sg:phone":"+44 191 253 0091",
    "sg:postcode":"NE26 1LY",
    "sg:province":"Northumberland",
    "wof:name":"Marcos",
    "wof:placetype":"venue"
},
  "geometry": {"coordinates":[-1.4486379623,55.047870636],"type":"Point"}
}