{
  "type": "Feature",
  "properties": {
    "addr:full":"12 Holyrood Street Chard Devon TA20 2AH",
    "addr:housenumber":"12",
    "addr:postcode":"ta20 2ah",
    "addr:street":"Holyrood Street",
    "iso:country":"GB",
    "sg:address":"12 Holyrood Street",
    "sg:city":"Chard",
    "sg:classifiers":[
        {
            "category":"Shopping",
            "subcategory":"Clothing, Apparel, & Fashions",
            "type":"Retail Goods"
        },
        {
            "category":"Shopping",
            "subcategory":"Hobbies, Toys, & Games",
            "type":"Retail Goods"
        }
    ],
    "sg:phone":"+44 1460 239090",
    "sg:postcode":"TA20 2AH",
    "sg:province":"Devon",
    "sg:tags":[
        "computer",
        "wear",
        "leisure"
    ],
    "wof:name":"Games Wizard",
    "wof:placetype":"venue"
},
  "geometry": {"coordinates":[-2.9659609795,50.8721466064],"type":"Point"}
}