{
  "type": "Feature",
  "properties": {
    "addr:full":"138 Dynevor Road, Skewen Neath Neath Port Talbot SA10 6TE",
    "addr:housenumber":"138",
    "addr:postcode":"sa10 6te",
    "addr:street":"Dynevor Road",
    "iso:country":"GB",
    "sg:address":"138 Dynevor Road, Skewen",
    "sg:city":"Neath",
    "sg:classifiers":[
        {
            "category":"Shopping",
            "subcategory":"Pets & Pet Supplies",
            "type":"Retail Goods"
        }
    ],
    "sg:phone":"+44 1792 812199",
    "sg:postcode":"SA10 6TE",
    "sg:province":"Neath Port Talbot",
    "wof:name":"Fish & Things",
    "wof:placetype":"venue"
},
  "geometry": {"coordinates":[-3.8465540409,51.6620903015],"type":"Point"}
}