{
  "type": "Feature",
  "properties": {
    "iso:country":"GB",
    "sg:address":"Fawley",
    "sg:city":"Henley-on-thames",
    "sg:classifiers":[
        {
            "category":"Bars & Pubs",
            "type":"Food & Drink"
        }
    ],
    "sg:phone":"+44 1491 638360",
    "sg:postcode":"RG9 6JE",
    "sg:province":"Berkshire",
    "sg:tags":[
        "pubs",
        "inn"
    ],
    "wof:name":"The Walnut Tree",
    "wof:placetype":"venue"
},
  "geometry": {"coordinates":[-0.9244,51.571323],"type":"Point"}
}