{
  "type": "Feature",
  "properties": {
    "addr:full":"Abacus House, 367 Blandford Road Beckenham Kent BR3 4NW",
    "addr:housenumber":"367",
    "addr:postcode":"br3 4nw",
    "addr:street":"Blandford Road",
    "iso:country":"GB",
    "sg:address":"Abacus House, 367 Blandford Road",
    "sg:city":"Beckenham",
    "sg:classifiers":[
        {
            "category":"Professional",
            "subcategory":"Computer Services",
            "type":"Services"
        }
    ],
    "sg:phone":"+44 20 8650 2211",
    "sg:postcode":"BR3 4NW",
    "sg:province":"Kent",
    "sg:tags":[
        "system",
        "software"
    ],
    "wof:name":"Demitcom Ltd.",
    "wof:placetype":"venue"
},
  "geometry": {"coordinates":[-0.054641,51.403603],"type":"Point"}
}