{
  "type": "Feature",
  "properties": {
    "addr:full":"155 Moorwell Road Scunthorpe Lincolnshire DN17 2SX",
    "addr:housenumber":"155",
    "addr:postcode":"dn17 2sx",
    "addr:street":"Moorwell Road",
    "iso:country":"GB",
    "sg:address":"155 Moorwell Road",
    "sg:city":"Scunthorpe",
    "sg:classifiers":[
        {
            "category":"Building & Trades",
            "subcategory":"Construction",
            "type":"Services"
        }
    ],
    "sg:phone":"+44 1724 848573",
    "sg:postcode":"DN17 2SX",
    "sg:province":"Lincolnshire",
    "sg:tags":[
        "joiner",
        "carpenter"
    ],
    "wof:name":"Crown Building & Maintenance Services Ltd.",
    "wof:placetype":"venue"
},
  "geometry": {"coordinates":[-0.672948,53.551052],"type":"Point"}
}