{
  "type": "Feature",
  "properties": {
    "addr:full":"15 Cliff Road Newquay Cornwall TR7 2NE",
    "addr:housenumber":"15",
    "addr:postcode":"tr7 2ne",
    "addr:street":"Cliff Road",
    "iso:country":"GB",
    "sg:address":"15 Cliff Road",
    "sg:city":"Newquay",
    "sg:classifiers":[
        {
            "category":"Professional",
            "subcategory":"Art Services",
            "type":"Services"
        }
    ],
    "sg:phone":"+44 1637 878896",
    "sg:postcode":"TR7 2NE",
    "sg:province":"Cornwall",
    "sg:tags":[
        "photographer"
    ],
    "wof:name":"Atlantic Studios",
    "wof:placetype":"venue"
},
  "geometry": {"coordinates":[-5.075913,50.415749],"type":"Point"}
}