{
  "type": "Feature",
  "properties": {
    "addr:full":"8 Haverfield Road, Blackley Manchester Greater Manchester M9 6NY",
    "addr:housenumber":"8",
    "addr:postcode":"m9 6ny",
    "addr:street":"Haverfield Road",
    "iso:country":"GB",
    "sg:address":"8 Haverfield Road, Blackley",
    "sg:city":"Manchester",
    "sg:classifiers":[
        {
            "category":"Home & Garden",
            "subcategory":"Home Furnishings",
            "type":"Retail Goods"
        }
    ],
    "sg:phone":"+44 1766 771740",
    "sg:postcode":"M9 6NY",
    "sg:province":"Greater Manchester",
    "sg:tags":[
        "awning",
        "canopy",
        "blinds"
    ],
    "wof:name":"Solar Blinds",
    "wof:placetype":"venue"
},
  "geometry": {"coordinates":[-2.2107999325,53.5253601074],"type":"Point"}
}