{
  "type": "Feature",
  "properties": {
    "iso:country":"GB",
    "sg:address":"31 Carlton Cres",
    "sg:city":"Southampton",
    "sg:classifiers":[
        {
            "category":"Banks & Credit Unions",
            "subcategory":"Financial Services",
            "type":"Services"
        }
    ],
    "sg:postcode":"SO15 2EW",
    "sg:province":"Hampshire",
    "sg:tags":[
        "consultant"
    ],
    "wof:name":"Wynsave Investments Ltd",
    "wof:placetype":"venue"
},
  "geometry": {"coordinates":[-1.4040689468,50.9132385254],"type":"Point"}
}