{
  "type": "Feature",
  "properties": {
    "iso:country":"GB",
    "sg:address":"Acle New Rd",
    "sg:city":"Great Yarmouth",
    "sg:classifiers":[
        {
            "category":"Shopping",
            "subcategory":"Florist",
            "type":"Retail Goods"
        }
    ],
    "sg:postcode":"NR30 1SF",
    "sg:province":"Norfolk",
    "wof:name":"Davies,Steve,Wholesale Flowers",
    "wof:placetype":"venue"
},
  "geometry": {"coordinates":[1.713898,52.619358],"type":"Point"}
}