{
  "type": "Feature",
  "properties": {
    "addr:full":"Sandy Lane Prestatyn Denbighshire LL19 8ST",
    "addr:postcode":"ll19 8st",
    "addr:street":"Sandy Lane",
    "iso:country":"GB",
    "sg:address":"Sandy Lane",
    "sg:city":"Prestatyn",
    "sg:classifiers":[
        {
            "category":"Building & Trades",
            "subcategory":"Construction",
            "type":"Services"
        }
    ],
    "sg:phone":"+44 1745 853528",
    "sg:postcode":"LL19 8ST",
    "sg:province":"Denbighshire",
    "sg:tags":[
        "builder"
    ],
    "wof:name":"Glyn B Jones",
    "wof:placetype":"venue"
},
  "geometry": {"coordinates":[-3.410956,53.33606],"type":"Point"}
}