{
  "type": "Feature",
  "properties": {
    "addr:full":"Bacup Road Todmorden Lancashire OL14 7PN",
    "addr:postcode":"ol14 7pn",
    "addr:street":"Bacup Road",
    "iso:country":"GB",
    "sg:address":"Bacup Road",
    "sg:city":"Todmorden",
    "sg:classifiers":[
        {
            "category":"Bars & Pubs",
            "type":"Food & Drink"
        }
    ],
    "sg:phone":"+44 1706 812180",
    "sg:postcode":"OL14 7PN",
    "sg:province":"Lancashire",
    "sg:tags":[
        "pubs",
        "inn"
    ],
    "wof:name":"The Masons Arms",
    "wof:placetype":"venue"
},
  "geometry": {"coordinates":[-2.160465,53.711761],"type":"Point"}
}