{
  "type": "Feature",
  "properties": {
    "iso:country":"GB",
    "sg:address":"40 Marchmont Road",
    "sg:city":"Wallington",
    "sg:classifiers":[
        {
            "category":"Professional",
            "subcategory":"Art Services",
            "type":"Services"
        }
    ],
    "sg:phone":"+44 20 8647 4788",
    "sg:postcode":"SM6 9NU",
    "sg:province":"Surrey",
    "sg:tags":[
        "photographer"
    ],
    "wof:name":"De Ruffo David",
    "wof:placetype":"venue"
},
  "geometry": {"coordinates":[-0.145925,51.350697],"type":"Point"}
}