{
  "type": "Feature",
  "properties": {
    "addr:full":"Askern Road Garage, Askern Road Bentley Doncaster South Yorkshire DN5 0EP",
    "addr:postcode":"dn5 0ep",
    "addr:street":"Askern;Askern Road",
    "iso:country":"GB",
    "sg:address":"Askern Road Garage, Askern Road Bentley",
    "sg:city":"Doncaster",
    "sg:classifiers":[
        {
            "category":"Home & Garden",
            "subcategory":"Building Materials",
            "type":"Retail Goods"
        }
    ],
    "sg:phone":"+44 1302 873811",
    "sg:postcode":"DN5 0EP",
    "sg:province":"South Yorkshire",
    "sg:tags":[
        "garage",
        "door"
    ],
    "wof:name":"Yorkshire Garage Doors Ltd.",
    "wof:placetype":"venue"
},
  "geometry": {"coordinates":[-1.1497189999,53.5567550659],"type":"Point"}
}