{
  "type": "Feature",
  "properties": {
    "addr:full":"Ref Library, Chamberlain Square Birmingham West Midlands B3 3HQ",
    "addr:postcode":"b3 3hq",
    "addr:street":"Chamberlain Square",
    "iso:country":"GB",
    "sg:address":"Ref Library, Chamberlain Square",
    "sg:city":"Birmingham",
    "sg:classifiers":[
        {
            "category":"Government",
            "subcategory":"Office",
            "type":"Public Place"
        }
    ],
    "sg:phone":"+44 121 303 4373",
    "sg:postcode":"B3 3HQ",
    "sg:province":"West Midlands",
    "sg:tags":[
        "local"
    ],
    "wof:name":"Birmingham Public Libraries",
    "wof:placetype":"venue"
},
  "geometry": {"coordinates":[-1.9038809538,52.4800834656],"type":"Point"}
}