{
  "type": "Feature",
  "properties": {
    "iso:country":"GB",
    "sg:address":"16 Quail Road",
    "sg:city":"Ayr",
    "sg:classifiers":[
        {
            "category":"Home & Garden",
            "subcategory":"Household Appliances",
            "type":"Retail Goods"
        }
    ],
    "sg:phone":"+44 1292 280085",
    "sg:postcode":"KA8 8LT",
    "sg:province":"South Ayrshire",
    "sg:tags":[
        "electrical"
    ],
    "wof:name":"William John Walker",
    "wof:placetype":"venue"
},
  "geometry": {"coordinates":[-4.6230401993,55.4774894714],"type":"Point"}
}