{
  "type": "Feature",
  "properties": {
    "iso:country":"GB",
    "sg:address":"4 Drumkinnon Road",
    "sg:city":"Alexandria",
    "sg:classifiers":[
        {
            "category":"Retail",
            "subcategory":"Driving School",
            "type":"Services"
        }
    ],
    "sg:postcode":"G83 8SX",
    "sg:province":"Argyll and Bute",
    "wof:name":"Gillian Driving School",
    "wof:placetype":"venue"
},
  "geometry": {"coordinates":[-4.5893721581,56.0017547607],"type":"Point"}
}