{
  "type": "Feature",
  "properties": {
    "iso:country":"GB",
    "sg:address":"13 Wallasey Rd",
    "sg:city":"Wallasey",
    "sg:classifiers":[
        {
            "category":"Communications",
            "type":"Services"
        }
    ],
    "sg:phone":"+44 151 637 1213",
    "sg:postcode":"CH45 4NL",
    "sg:province":"Merseyside",
    "sg:tags":[
        "telecommunication"
    ],
    "wof:name":"Connection Point",
    "wof:placetype":"venue"
},
  "geometry": {"coordinates":[-3.045792,53.420025],"type":"Point"}
}