{
  "type": "Feature",
  "properties": {
    "addr:full":"21 King Street Wigton Cumbria CA7 9EH",
    "addr:housenumber":"21",
    "addr:postcode":"ca7 9eh",
    "addr:street":"King Street",
    "iso:country":"GB",
    "sg:address":"21 King Street",
    "sg:city":"Wigton",
    "sg:classifiers":[
        {
            "category":"Food & Beverages",
            "subcategory":"Supermarket",
            "type":"Retail Goods"
        }
    ],
    "sg:phone":"+44 16973 42381",
    "sg:postcode":"CA7 9EH",
    "sg:province":"Cumbria",
    "wof:name":"Co-Op Supermarket",
    "wof:placetype":"venue"
},
  "geometry": {"coordinates":[-3.1606519222,54.8254089355],"type":"Point"}
}