{
  "type": "Feature",
  "properties": {
    "addr:full":"New Braeside Surgery, Needhams Row Ebbw Vale Blaenau Gwent NP3 5PL",
    "addr:postcode":"np3 5pl",
    "addr:street":"Needhams Row",
    "iso:country":"GB",
    "sg:address":"New Braeside Surgery, Needhams Row",
    "sg:city":"Ebbw Vale",
    "sg:classifiers":[
        {
            "category":"Health Services",
            "subcategory":"Doctor",
            "type":"Services"
        }
    ],
    "sg:phone":"+44 1495 302257",
    "sg:postcode":"NP3 5PL",
    "sg:province":"Blaenau Gwent",
    "sg:tags":[
        "practitioners"
    ],
    "wof:name":"Malik, N A",
    "wof:placetype":"venue"
},
  "geometry": {"coordinates":[-3.2146799564,51.7970199585],"type":"Point"}
}