{
  "type": "Feature",
  "properties": {
    "iso:country":"GB",
    "sg:address":"South Brent Primary School, Totnes Rd",
    "sg:city":"South Brent",
    "sg:classifiers":[
        {
            "category":"Community Center",
            "subcategory":"Youth",
            "type":"Public Place"
        }
    ],
    "sg:phone":"+44 1364 72008",
    "sg:postcode":"TQ10 9JN",
    "sg:province":"Devon",
    "sg:tags":[
        "organisation",
        "centre"
    ],
    "wof:name":"Avon Valley Playclub The",
    "wof:placetype":"venue"
},
  "geometry": {"coordinates":[-3.833324,50.423351],"type":"Point"}
}