{
  "type": "Feature",
  "properties": {
    "addr:full":"London House, Station Road, Llanrug Caernarfon Gwynedd LL55 4AG",
    "addr:postcode":"ll55 4ag",
    "addr:street":"Station Road",
    "iso:country":"GB",
    "sg:address":"London House, Station Road, Llanrug",
    "sg:city":"Caernarfon",
    "sg:classifiers":[
        {
            "category":"Food & Beverages",
            "subcategory":"Meat & Fish",
            "type":"Retail Goods"
        }
    ],
    "sg:phone":"+44 1286 673574",
    "sg:postcode":"LL55 4AG",
    "sg:province":"Gwynedd",
    "sg:tags":[
        "butcher"
    ],
    "wof:name":"Wavell Roberts Butchers",
    "wof:placetype":"venue"
},
  "geometry": {"coordinates":[-4.1930837631,53.1479797363],"type":"Point"}
}