{
  "type": "Feature",
  "properties": {
    "iso:country":"GB",
    "sg:address":"202 Castle Market",
    "sg:city":"Sheffield",
    "sg:classifiers":[
        {
            "category":"Home & Garden",
            "subcategory":"Household Appliances",
            "type":"Retail Goods"
        }
    ],
    "sg:postcode":"S1 2AF",
    "sg:province":"South Yorkshire",
    "sg:tags":[
        "electrical"
    ],
    "wof:name":"Queengrange Ltd.",
    "wof:placetype":"venue"
},
  "geometry": {"coordinates":[-1.465499,53.383091],"type":"Point"}
}