{
  "type": "Feature",
  "properties": {
    "addr:full":"443 Church Road Birmingham West Midlands B33 8PA",
    "addr:housenumber":"443",
    "addr:postcode":"b33 8pa",
    "addr:street":"Church Road",
    "iso:country":"GB",
    "sg:address":"443 Church Road",
    "sg:city":"Birmingham",
    "sg:classifiers":[
        {
            "category":"Government",
            "subcategory":"Post Office",
            "type":"Public Place"
        }
    ],
    "sg:phone":"+44 121 783 2984",
    "sg:postcode":"B33 8PA",
    "sg:province":"West Midlands",
    "wof:name":"Old Yardley Post Office",
    "wof:placetype":"venue"
},
  "geometry": {"coordinates":[-1.8027629852,52.4750747681],"type":"Point"}
}