{
  "type": "Feature",
  "properties": {
    "iso:country":"GB",
    "sg:address":"High House, Greenbank",
    "sg:city":"Whitehaven",
    "sg:classifiers":[
        {
            "category":"Retail",
            "subcategory":"Auto Repair",
            "type":"Services"
        }
    ],
    "sg:phone":"+44 1946 63482",
    "sg:postcode":"CA28 9RB",
    "sg:province":"Cumbria",
    "sg:tags":[
        "modification",
        "garage"
    ],
    "wof:name":"Terry Ferguson",
    "wof:placetype":"venue"
},
  "geometry": {"coordinates":[-3.5840439796,54.5285301208],"type":"Point"}
}