{
  "type": "Feature",
  "properties": {
    "addr:full":"15-17 Lincolns Inn Fields London Greater London WC2A 3ED",
    "addr:housenumber":"15-17",
    "addr:postcode":"wc2a 3ed",
    "addr:street":"Lincolns;Fields",
    "iso:country":"GB",
    "sg:address":"15-17 Lincolns Inn Fields",
    "sg:city":"London",
    "sg:classifiers":[
        {
            "category":"Organizations",
            "subcategory":"Non-profit Organization",
            "type":"Services"
        }
    ],
    "sg:phone":"+44 20 7396 7414",
    "sg:postcode":"WC2A 3ED",
    "sg:province":"Greater London",
    "sg:tags":[
        "organisation",
        "voluntary",
        "charity"
    ],
    "wof:name":"Pilotlight",
    "wof:placetype":"venue"
},
  "geometry": {"coordinates":[-0.1171239987,51.5170249939],"type":"Point"}
}