{
  "type": "Feature",
  "properties": {
    "addr:full":"246 Narborough Road Leicester Leicestershire LE3 2AP",
    "addr:housenumber":"246",
    "addr:postcode":"le3 2ap",
    "addr:street":"Narborough Road",
    "iso:country":"GB",
    "sg:address":"246 Narborough Road",
    "sg:city":"Leicester",
    "sg:classifiers":[
        {
            "category":"Communications",
            "type":"Services"
        }
    ],
    "sg:postcode":"LE3 2AP",
    "sg:province":"Leicestershire",
    "sg:tags":[
        "telecommunication"
    ],
    "wof:name":"G T S (u K) Ltd",
    "wof:placetype":"venue"
},
  "geometry": {"coordinates":[-1.154868,52.622475],"type":"Point"}
}