{
  "type": "Feature",
  "properties": {
    "iso:country":"GB",
    "sg:address":"40 Gay St",
    "sg:city":"Bath",
    "sg:classifiers":[
        {
            "category":"Museum",
            "subcategory":"Art Museum",
            "type":"Entertainment"
        }
    ],
    "sg:phone":"+44 1225 443000",
    "sg:postcode":"BA1 2NT",
    "sg:province":"Bath and North East Somerset",
    "sg:tags":[
        "gallery"
    ],
    "wof:name":"The Jane Austen Centre",
    "wof:placetype":"venue"
},
  "geometry": {"coordinates":[-2.363043,51.384037],"type":"Point"}
}