{
  "type": "Feature",
  "properties": {
    "addr:full":"35a Seaforth Vale North Liverpool Merseyside L21 3TR",
    "addr:housenumber":"35a",
    "addr:postcode":"l21 3tr",
    "addr:street":"Seaforth Vale North",
    "iso:country":"GB",
    "sg:address":"35a Seaforth Vale North",
    "sg:city":"Liverpool",
    "sg:classifiers":[
        {
            "category":"Military Area",
            "subcategory":"Army Base",
            "type":"Public Place"
        },
        {
            "category":"Manufacturing",
            "subcategory":"Textiles",
            "type":"Manufacturing & Wholesale Goods"
        }
    ],
    "sg:phone":"+44 151 920 2280",
    "sg:postcode":"L21 3TR",
    "sg:province":"Merseyside",
    "sg:tags":[
        "made-up",
        "-",
        "bag",
        "various",
        "supplier",
        "type"
    ],
    "sg:website":"http://www.bulkbags.org",
    "wof:name":"Liverpool Bulk Bags",
    "wof:placetype":"venue"
},
  "geometry": {"coordinates":[-3.0062189102,53.4645004272],"type":"Point"}
}