{
  "type": "Feature",
  "properties": {
    "iso:country":"GB",
    "sg:address":"Cysgod-y-coed, Rhewl",
    "sg:city":"Llangollen",
    "sg:classifiers":[
        {
            "category":"Manufacturing",
            "subcategory":"Lumber",
            "type":"Manufacturing & Wholesale Goods"
        }
    ],
    "sg:phone":"+44 1978 860582",
    "sg:postcode":"LL20 7YT",
    "sg:province":"Denbighshire",
    "sg:tags":[
        "merchant",
        "merchants",
        "importer",
        "agent",
        "timber"
    ],
    "wof:name":"M & D Claybrook",
    "wof:placetype":"venue"
},
  "geometry": {"coordinates":[-3.225665,52.993679],"type":"Point"}
}