{
  "type": "Feature",
  "properties": {
    "iso:country":"GB",
    "sg:address":"14 Freemans Lane, Burbage",
    "sg:city":"Hinckley",
    "sg:classifiers":[
        {
            "category":"Professional",
            "subcategory":"Engineering",
            "type":"Services"
        }
    ],
    "sg:phone":"+44 1455 251024",
    "sg:postcode":"LE10 2HZ",
    "sg:province":"Leicestershire",
    "sg:tags":[
        "consultant",
        "structural"
    ],
    "wof:name":"P K Naldrett & Partners",
    "wof:placetype":"venue"
},
  "geometry": {"coordinates":[-1.350898,52.526348],"type":"Point"}
}