{
  "type": "Feature",
  "properties": {
    "iso:country":"GB",
    "sg:address":"1 Millbank Terrace, Whitton",
    "sg:city":"Stockton-on-tees",
    "sg:classifiers":[
        {
            "category":"Building & Trades",
            "subcategory":"Construction",
            "type":"Services"
        }
    ],
    "sg:phone":"+44 1740 630454",
    "sg:postcode":"TS21 1LH",
    "sg:province":"Durham",
    "sg:tags":[
        "guttering"
    ],
    "wof:name":"County Roofing",
    "wof:placetype":"venue"
},
  "geometry": {"coordinates":[-1.4125000238,54.5980300903],"type":"Point"}
}