{
  "type": "Feature",
  "properties": {
    "iso:country":"GB",
    "sg:address":"132 Tettenhall Road",
    "sg:city":"Wolverhampton",
    "sg:classifiers":[
        {
            "category":"Health Services",
            "subcategory":"Health Practitioner",
            "type":"Services"
        }
    ],
    "sg:postcode":"WV6 0BL",
    "sg:province":"Shropshire",
    "sg:tags":[
        "physiotherapist"
    ],
    "wof:name":"Anthony Peach",
    "wof:placetype":"venue"
},
  "geometry": {"coordinates":[-2.154662,52.593838],"type":"Point"}
}