{
  "type": "Feature",
  "properties": {
    "iso:country":"GB",
    "sg:address":"19 Reynolds Drive",
    "sg:city":"Bolton",
    "sg:classifiers":[
        {
            "category":"Shopping",
            "subcategory":"Stationery & Office Supplies",
            "type":"Retail Goods"
        },
        {
            "category":"Shopping",
            "subcategory":"News",
            "type":"Retail Goods"
        }
    ],
    "sg:phone":"+44 1204 62041",
    "sg:postcode":"BL5 1HW",
    "sg:province":"Lancashire",
    "sg:tags":[
        "commercial",
        "newsagent"
    ],
    "wof:name":"Speedy Office Supplies",
    "wof:placetype":"venue"
},
  "geometry": {"coordinates":[-2.469958,53.542858],"type":"Point"}
}