{
  "type": "Feature",
  "properties": {
    "addr:full":"47a Commercial Road, Skelmanthorpe Huddersfield South Yorkshire HD8 9DA",
    "addr:housenumber":"47a",
    "addr:postcode":"hd8 9da",
    "addr:street":"Commercial Road",
    "iso:country":"GB",
    "sg:address":"47a Commercial Road, Skelmanthorpe",
    "sg:city":"Huddersfield",
    "sg:classifiers":[
        {
            "category":"Recreation",
            "subcategory":"Dog Park",
            "type":"Entertainment"
        }
    ],
    "sg:phone":"+44 1484 865520",
    "sg:postcode":"HD8 9DA",
    "sg:province":"South Yorkshire",
    "wof:name":"Ark Pet Supplies",
    "wof:placetype":"venue"
},
  "geometry": {"coordinates":[-1.649448,53.59161],"type":"Point"}
}