{
  "type": "Feature",
  "properties": {
    "iso:country":"GB",
    "sg:address":"21 West Street",
    "sg:city":"Axminster",
    "sg:classifiers":[
        {
            "category":"Shopping",
            "subcategory":"Department Store",
            "type":"Retail Goods"
        }
    ],
    "sg:phone":"+44 1297 35615",
    "sg:postcode":"EX13 5NU",
    "sg:province":"Devon",
    "wof:name":"Tony Pratt",
    "wof:placetype":"venue"
},
  "geometry": {"coordinates":[-3.001804,50.780464],"type":"Point"}
}