{
  "type": "Feature",
  "properties": {
    "addr:full":"8 Littlemill Place, Rankinstine Ayr East Ayrshire KA6 7HB",
    "addr:housenumber":"8",
    "addr:postcode":"ka6 7hb",
    "addr:street":"Littlemill Place Rankinstine;East",
    "iso:country":"GB",
    "sg:address":"8 Littlemill Place, Rankinstine",
    "sg:city":"Ayr",
    "sg:classifiers":[
        {
            "category":"Shopping",
            "subcategory":"Pharmacy",
            "type":"Retail Goods"
        }
    ],
    "sg:phone":"+44 1292 590102",
    "sg:postcode":"KA6 7HB",
    "sg:province":"East Ayrshire",
    "sg:tags":[
        "medicine",
        "therapy"
    ],
    "wof:name":"Dr Elizabeth Y Earnshaw",
    "wof:placetype":"venue"
},
  "geometry": {"coordinates":[-4.4476499557,55.400478363],"type":"Point"}
}