{
  "type": "Feature",
  "properties": {
    "addr:full":"250 Coleman St Wolverhampton Shropshire WV6 0RH",
    "addr:housenumber":"250",
    "addr:postcode":"wv6 0rh",
    "addr:street":"Coleman St",
    "iso:country":"GB",
    "sg:address":"250 Coleman St",
    "sg:city":"Wolverhampton",
    "sg:classifiers":[
        {
            "category":"Shopping",
            "type":"Retail Goods"
        }
    ],
    "sg:phone":"+44 1902 741880",
    "sg:postcode":"WV6 0RH",
    "sg:province":"Shropshire",
    "sg:tags":[
        "equipment",
        "clothing",
        "safety"
    ],
    "wof:name":"Coleman Industrial Suppliers Ltd",
    "wof:placetype":"venue"
},
  "geometry": {"coordinates":[-2.152487,52.596622],"type":"Point"}
}