{
  "type": "Feature",
  "properties": {
    "iso:country":"GB",
    "sg:address":"5-7 Clifton Road",
    "sg:city":"Rugby",
    "sg:classifiers":[
        {
            "category":"Food & Beverages",
            "subcategory":"Liquor & Beverages",
            "type":"Retail Goods"
        }
    ],
    "sg:phone":"+44 1788 544186",
    "sg:postcode":"CV21 3PY",
    "sg:province":"Warwickshire",
    "sg:tags":[
        "beer",
        "spirit",
        "wines"
    ],
    "wof:name":"Thresher",
    "wof:placetype":"venue"
},
  "geometry": {"coordinates":[-1.25752,52.372223],"type":"Point"}
}