{
  "type": "Feature",
  "properties": {
    "addr:full":"Bothwell Clo Canning Town Greater London E16 1QS",
    "addr:postcode":"e16 1qs",
    "iso:country":"GB",
    "sg:address":"Bothwell Clo",
    "sg:city":"Canning Town",
    "sg:classifiers":[
        {
            "category":"Community Center",
            "type":"Public Place"
        }
    ],
    "sg:phone":"+44 20 7474 2101",
    "sg:postcode":"E16 1QS",
    "sg:province":"Greater London",
    "sg:tags":[
        "centre"
    ],
    "wof:name":"Trinity Centre",
    "wof:placetype":"venue"
},
  "geometry": {"coordinates":[0.0156750008,51.5165786743],"type":"Point"}
}