{
  "type": "Feature",
  "properties": {
    "iso:country":"GB",
    "sg:address":"226 Linden Rd",
    "sg:city":"Gloucester",
    "sg:classifiers":[
        {
            "category":"Manufacturing",
            "subcategory":"Building Materials",
            "type":"Manufacturing & Wholesale Goods"
        }
    ],
    "sg:phone":"+44 1452 418701",
    "sg:postcode":"GL1 5JE",
    "sg:province":"Gloucestershire",
    "sg:tags":[
        "merchant",
        "builder"
    ],
    "wof:name":"Colliers Yard",
    "wof:placetype":"venue"
},
  "geometry": {"coordinates":[-2.244688,51.848564],"type":"Point"}
}