{
  "type": "Feature",
  "properties": {
    "addr:full":"8 Tollgate Buildings, Hadlow Rd Tonbridge Kent TN10 3TF",
    "addr:housenumber":"8",
    "addr:postcode":"tn10 3tf",
    "addr:street":"Tollgate Buildings Hadlow Rd",
    "iso:country":"GB",
    "sg:address":"8 Tollgate Buildings, Hadlow Rd",
    "sg:city":"Tonbridge",
    "sg:classifiers":[
        {
            "category":"Professional",
            "subcategory":"Secretarial Services",
            "type":"Services"
        }
    ],
    "sg:phone":"+44 1732 363898",
    "sg:postcode":"TN10 3TF",
    "sg:province":"Kent",
    "wof:name":"Polly's Ltd",
    "wof:placetype":"venue"
},
  "geometry": {"coordinates":[0.2730399966,51.2080001831],"type":"Point"}
}