{
  "type": "Feature",
  "properties": {
    "addr:full":"88 Winstanley Rd Saffron Walden Essex CB11 3EX",
    "addr:housenumber":"88",
    "addr:postcode":"cb11 3ex",
    "addr:street":"Winstanley Rd",
    "iso:country":"GB",
    "sg:address":"88 Winstanley Rd",
    "sg:city":"Saffron Walden",
    "sg:classifiers":[
        {
            "category":"Arts & Performance",
            "subcategory":"Music",
            "type":"Entertainment"
        }
    ],
    "sg:phone":"+44 1799 500750",
    "sg:postcode":"CB11 3EX",
    "sg:province":"Essex",
    "sg:tags":[
        "mobile",
        "disco"
    ],
    "wof:name":"Roadshow Discotheques",
    "wof:placetype":"venue"
},
  "geometry": {"coordinates":[0.246317,52.013374],"type":"Point"}
}