{
  "type": "Feature",
  "properties": {
    "addr:full":"66 Ethel Street, Bearwood Rowley Regis West Midlands B67 5AJ",
    "addr:housenumber":"66",
    "addr:postcode":"b67 5aj",
    "addr:street":"Ethel Street",
    "iso:country":"GB",
    "sg:address":"66 Ethel Street, Bearwood",
    "sg:city":"Rowley Regis",
    "sg:classifiers":[
        {
            "category":"Building & Trades",
            "subcategory":"Pest Control",
            "type":"Services"
        }
    ],
    "sg:phone":"+44 121 544 7696",
    "sg:postcode":"B67 5AJ",
    "sg:province":"West Midlands",
    "sg:tags":[
        "vermin"
    ],
    "wof:name":"Baird Charles J S Pigeon and Rabbit Control",
    "wof:placetype":"venue"
},
  "geometry": {"coordinates":[-1.973549962,52.4784202576],"type":"Point"}
}