{
  "type": "Feature",
  "properties": {
    "iso:country":"GB",
    "sg:address":"Lea Close, Middleton Road, Sadberge",
    "sg:city":"Darlington",
    "sg:classifiers":[
        {
            "category":"Building & Trades",
            "subcategory":"Landscaping Services",
            "type":"Services"
        },
        {
            "category":"Professional",
            "subcategory":"Employment Agencies",
            "type":"Services"
        }
    ],
    "sg:phone":"+44 1325 332539",
    "sg:postcode":"DL2 1RN",
    "sg:province":"Durham",
    "sg:tags":[
        "consultant",
        "landscape",
        "contractor"
    ],
    "wof:name":"Ian Mitchell",
    "wof:placetype":"venue"
},
  "geometry": {"coordinates":[-1.4700360298,54.546661377],"type":"Point"}
}