{
  "type": "Feature",
  "properties": {
    "iso:country":"GB",
    "sg:address":"16 Coronation Road",
    "sg:city":"East Grinstead",
    "sg:classifiers":[
        {
            "category":"Shopping",
            "subcategory":"Department Store",
            "type":"Retail Goods"
        }
    ],
    "sg:postcode":"RH19 4AL",
    "sg:province":"East Sussex",
    "wof:name":"Herbal Power Ltd.",
    "wof:placetype":"venue"
},
  "geometry": {"coordinates":[-0.010625,51.115692],"type":"Point"}
}