{
  "type": "Feature",
  "properties": {
    "addr:full":"Unit E1 Brookfield Business Centre Cambridge Cambridgeshire CB4 4PS",
    "addr:housenumber":"e1",
    "addr:postcode":"cb4 4ps",
    "addr:street":"Brookfield Business Centre",
    "iso:country":"GB",
    "sg:address":"Unit E1 Brookfield Business Centre",
    "sg:city":"Cambridge",
    "sg:classifiers":[
        {
            "category":"Home & Garden",
            "subcategory":"Hardware",
            "type":"Retail Goods"
        }
    ],
    "sg:phone":"+44 1954 252160",
    "sg:postcode":"CB4 4PS",
    "sg:province":"Cambridgeshire",
    "sg:tags":[
        "compressor",
        "air"
    ],
    "wof:name":"Cash Flo Ltd",
    "wof:placetype":"venue"
},
  "geometry": {"coordinates":[0.1396400034,52.3005981445],"type":"Point"}
}