{
  "type": "Feature",
  "properties": {
    "addr:full":"Wallace Binder Ground, Park Drive Maldon Essex CM9 5XX",
    "addr:postcode":"cm9 5xx",
    "addr:street":"Wallace;Ground Park Drive",
    "iso:country":"GB",
    "sg:address":"Wallace Binder Ground, Park Drive",
    "sg:city":"Maldon",
    "sg:classifiers":[
        {
            "category":"Banks & Credit Unions",
            "subcategory":"Financial Services",
            "type":"Services"
        },
        {
            "category":"Arena",
            "subcategory":"Sports Club",
            "type":"Entertainment"
        }
    ],
    "sg:phone":"+44 1638 713449",
    "sg:postcode":"CM9 5XX",
    "sg:province":"Essex",
    "sg:tags":[
        "cashing",
        "operation",
        "cheque"
    ],
    "wof:name":"Maldon Town Football & Social Club",
    "wof:placetype":"venue"
},
  "geometry": {"coordinates":[0.675249,51.731377],"type":"Point"}
}