{
  "type": "Feature",
  "properties": {
    "iso:country":"GB",
    "sg:address":"Rear Of, 258 Manchester Road",
    "sg:city":"Wigan",
    "sg:classifiers":[
        {
            "category":"Home & Garden",
            "subcategory":"Building Materials",
            "type":"Retail Goods"
        }
    ],
    "sg:phone":"+44 1942 519360",
    "sg:postcode":"WN2 2ED",
    "sg:province":"Lancashire",
    "sg:tags":[
        "ironwork",
        "diy",
        "wrought"
    ],
    "wof:name":"The Wrought Iron Gate Co.",
    "wof:placetype":"venue"
},
  "geometry": {"coordinates":[-2.6001200676,53.5414505005],"type":"Point"}
}