{
  "type": "Feature",
  "properties": {
    "addr:full":"8-10 High Street, Storrington Pulborough West Sussex RH20 4DU",
    "addr:housenumber":"8-10",
    "addr:postcode":"rh20 4du",
    "addr:street":"High Street",
    "iso:country":"GB",
    "sg:address":"8-10 High Street, Storrington",
    "sg:city":"Pulborough",
    "sg:classifiers":[
        {
            "category":"Real Estate",
            "subcategory":"Real Estate Operator",
            "type":"Services"
        }
    ],
    "sg:phone":"+44 1903 745511",
    "sg:postcode":"RH20 4DU",
    "sg:province":"West Sussex",
    "sg:tags":[
        "letting",
        "agent"
    ],
    "wof:name":"Link Property Management",
    "wof:placetype":"venue"
},
  "geometry": {"coordinates":[-0.453549,50.917648],"type":"Point"}
}