{
  "type": "Feature",
  "properties": {
    "iso:country":"GB",
    "sg:address":"Unit 7 Wilson Business Centre, Wilson Road, Huyton",
    "sg:city":"Liverpool",
    "sg:classifiers":[
        {
            "category":"Home & Garden",
            "subcategory":"Furniture",
            "type":"Retail Goods"
        }
    ],
    "sg:postcode":"L36 6AF",
    "sg:province":"Merseyside",
    "wof:name":"C M S Home Furnishings",
    "wof:placetype":"venue"
},
  "geometry": {"coordinates":[-2.82762,53.40723],"type":"Point"}
}