{
  "type": "Feature",
  "properties": {
    "iso:country":"GB",
    "sg:address":"141 Upper Richmond Rd",
    "sg:city":"Putney",
    "sg:classifiers":[
        {
            "category":"Restaurant",
            "type":"Food & Drink"
        }
    ],
    "sg:phone":"+44 20 8789 4304",
    "sg:postcode":"SW15 2TX",
    "sg:province":"Greater London",
    "wof:name":"Bangkok Symphonie Restaurant",
    "wof:placetype":"venue"
},
  "geometry": {"coordinates":[-0.2154310048,51.4603233337],"type":"Point"}
}