{
  "type": "Feature",
  "properties": {
    "iso:country":"GB",
    "sg:address":"74 Andlers Ash Road",
    "sg:city":"Liss",
    "sg:classifiers":[
        {
            "category":"Building & Trades",
            "subcategory":"Construction",
            "type":"Services"
        }
    ],
    "sg:phone":"+44 1730 893482",
    "sg:postcode":"GU33 7LR",
    "sg:province":"Hampshire",
    "sg:tags":[
        "builder"
    ],
    "wof:name":"B A T Hutchence",
    "wof:placetype":"venue"
},
  "geometry": {"coordinates":[-0.8953790069,51.0389518738],"type":"Point"}
}