{
  "type": "Feature",
  "properties": {
    "addr:full":"Williamson House, Williamson Street Stockport Cheshire SK5 6AA",
    "addr:postcode":"sk5 6aa",
    "addr:street":"Williamson Street",
    "iso:country":"GB",
    "sg:address":"Williamson House, Williamson Street",
    "sg:city":"Stockport",
    "sg:classifiers":[
        {
            "category":"Professional",
            "subcategory":"Printing & Photocopies",
            "type":"Services"
        }
    ],
    "sg:phone":"+44 161 442 4211",
    "sg:postcode":"SK5 6AA",
    "sg:province":"Cheshire",
    "sg:tags":[
        "printer"
    ],
    "wof:name":"J R C Graphics Ltd.",
    "wof:placetype":"venue"
},
  "geometry": {"coordinates":[-2.159318924,53.4374732971],"type":"Point"}
}