{
  "type": "Feature",
  "properties": {
    "iso:country":"GB",
    "sg:address":"Dover Road, Tilmanstone",
    "sg:city":"Deal",
    "sg:classifiers":[
        {
            "category":"Bars & Pubs",
            "type":"Food & Drink"
        }
    ],
    "sg:phone":"+44 1304 617582",
    "sg:postcode":"CT14 0HX",
    "sg:province":"Kent",
    "sg:tags":[
        "pubs",
        "inn"
    ],
    "wof:name":"The Plough & Harrow Inn",
    "wof:placetype":"venue"
},
  "geometry": {"coordinates":[1.298251,51.211246],"type":"Point"}
}