{
  "type": "Feature",
  "properties": {
    "iso:country":"GB",
    "sg:address":"Collingwood Centre, Collingwood Drive, Greatbarr",
    "sg:city":"Birmingham",
    "sg:classifiers":[
        {
            "category":"Education",
            "subcategory":"Library",
            "type":"Public Place"
        },
        {
            "category":"Government",
            "subcategory":"Office",
            "type":"Public Place"
        }
    ],
    "sg:phone":"+44 121 366 6503",
    "sg:postcode":"B43 7NE",
    "sg:province":"West Midlands",
    "sg:tags":[
        "book",
        "local"
    ],
    "wof:name":"Pheasey Branch Library",
    "wof:placetype":"venue"
},
  "geometry": {"coordinates":[-1.90409,52.55637],"type":"Point"}
}