{
  "type": "Feature",
  "properties": {
    "iso:country":"GB",
    "sg:address":"Great Western Designer Outlet Villa, Kemble Drive, Church Ward Park",
    "sg:city":"Swindon",
    "sg:classifiers":[
        {
            "category":"Food & Beverages",
            "subcategory":"Meat & Fish",
            "type":"Retail Goods"
        }
    ],
    "sg:phone":"+44 1793 512931",
    "sg:postcode":"SN2 2TA",
    "sg:province":"Wiltshire",
    "sg:tags":[
        "chip"
    ],
    "wof:name":"Harry Ramsdens",
    "wof:placetype":"venue"
},
  "geometry": {"coordinates":[-1.803029,51.568802],"type":"Point"}
}