{
  "type": "Feature",
  "properties": {
    "iso:country":"GB",
    "sg:address":"5 Swan Lane",
    "sg:city":"Norwich",
    "sg:classifiers":[
        {
            "category":"Deli",
            "type":"Food & Drink"
        }
    ],
    "sg:phone":"+44 1603 764341",
    "sg:postcode":"NR2 1HZ",
    "sg:province":"Norfolk",
    "sg:tags":[
        "delicatessen"
    ],
    "wof:name":"Logans Good Food Shop",
    "wof:placetype":"venue"
},
  "geometry": {"coordinates":[1.295961,52.630287],"type":"Point"}
}