{
  "type": "Feature",
  "properties": {
    "iso:country":"GB",
    "sg:address":"5 Hermatidge Road",
    "sg:city":"Bath",
    "sg:classifiers":[
        {
            "category":"Professional",
            "subcategory":"Management & Consulting",
            "type":"Services"
        }
    ],
    "sg:phone":"+44 1225 482227",
    "sg:postcode":"BA1 5SN",
    "sg:province":"Bath and North East Somerset",
    "sg:tags":[
        "consultant",
        "business"
    ],
    "wof:name":"Scott McGregor",
    "wof:placetype":"venue"
},
  "geometry": {"coordinates":[-2.368934,51.394325],"type":"Point"}
}