{
  "type": "Feature",
  "properties": {
    "iso:country":"GB",
    "sg:address":"Leigh Barton Farm, Roadwater",
    "sg:city":"Watchet",
    "sg:classifiers":[
        {
            "category":"Farming",
            "subcategory":"Farm",
            "type":"Manufacturing & Wholesale Goods"
        }
    ],
    "sg:postcode":"TA23 0QN",
    "sg:province":"Somerset",
    "sg:tags":[
        "mixed",
        "crop"
    ],
    "wof:name":"Brendon Hill Stoves",
    "wof:placetype":"venue"
},
  "geometry": {"coordinates":[-3.3302440643,51.1806259155],"type":"Point"}
}