{
  "type": "Feature",
  "properties": {
    "addr:full":"7 Nepean Street London Greater London SW15 5DW",
    "addr:housenumber":"7",
    "addr:postcode":"sw15 5dw",
    "addr:street":"Nepean Street",
    "iso:country":"GB",
    "sg:address":"7 Nepean Street",
    "sg:city":"London",
    "sg:classifiers":[
        {
            "category":"Professional",
            "subcategory":"Art Services",
            "type":"Services"
        }
    ],
    "sg:phone":"+44 20 8780 5352",
    "sg:postcode":"SW15 5DW",
    "sg:province":"Greater London",
    "sg:tags":[
        "photographer"
    ],
    "wof:name":"Julian Calder",
    "wof:placetype":"venue"
},
  "geometry": {"coordinates":[-0.2401520014,51.4514732361],"type":"Point"}
}