{
  "type": "Feature",
  "properties": {
    "iso:country":"GB",
    "sg:address":"77 Town Lane, Benington",
    "sg:city":"Stevenage",
    "sg:classifiers":[
        {
            "category":"Utilities",
            "type":"Services"
        }
    ],
    "sg:phone":"+44 1438 869998",
    "sg:postcode":"SG2 7BT",
    "sg:province":"Hertfordshire",
    "sg:tags":[
        "internet"
    ],
    "wof:name":"Q X 1",
    "wof:placetype":"venue"
},
  "geometry": {"coordinates":[-0.1043749973,51.8944282532],"type":"Point"}
}