{
  "type": "Feature",
  "properties": {
    "iso:country":"GB",
    "sg:address":"7 Falkland Road",
    "sg:city":"Sheffield",
    "sg:classifiers":[
        {
            "category":"Building & Trades",
            "subcategory":"Construction",
            "type":"Services"
        }
    ],
    "sg:phone":"+44 114 266 2427",
    "sg:postcode":"S11 7PL",
    "sg:province":"Derbyshire",
    "sg:tags":[
        "builder"
    ],
    "wof:name":"Robin Andrew Windle",
    "wof:placetype":"venue"
},
  "geometry": {"coordinates":[-1.514267,53.360184],"type":"Point"}
}