{
  "type": "Feature",
  "properties": {
    "iso:country":"GB",
    "sg:address":"Unit 4 Block 6 Lomond Industrial Estate",
    "sg:city":"Alexandria",
    "sg:classifiers":[
        {
            "category":"Manufacturing",
            "subcategory":"Lumber",
            "type":"Manufacturing & Wholesale Goods"
        }
    ],
    "sg:phone":"+44 1389 751154",
    "sg:postcode":"G83 0TL",
    "sg:province":"Argyll and Bute",
    "sg:tags":[
        "importer",
        "merchants",
        "agent",
        "timber"
    ],
    "wof:name":"Stewart Lumber Ltd.",
    "wof:placetype":"venue"
},
  "geometry": {"coordinates":[-4.582669,55.988441],"type":"Point"}
}