{
  "type": "Feature",
  "properties": {
    "addr:full":"57 Albion Road Edinburgh City of Edinburgh EH7 5QY",
    "addr:housenumber":"57",
    "addr:postcode":"eh7 5qy",
    "addr:street":"Albion Road",
    "iso:country":"GB",
    "sg:address":"57 Albion Road",
    "sg:city":"Edinburgh",
    "sg:classifiers":[
        {
            "category":"Organizations",
            "subcategory":"Non-profit Organization",
            "type":"Services"
        }
    ],
    "sg:phone":"+44 131 558 9912",
    "sg:postcode":"EH7 5QY",
    "sg:province":"City of Edinburgh",
    "sg:tags":[
        "organisation",
        "voluntary",
        "charity"
    ],
    "wof:name":"Fabb Scotland Ltd.",
    "wof:placetype":"venue"
},
  "geometry": {"coordinates":[-3.166962,55.961388],"type":"Point"}
}