{
  "type": "Feature",
  "properties": {
    "addr:full":"High View House, 165-167 Station Road Edgware Greater London HA8 7JU",
    "addr:housenumber":"165-167",
    "addr:postcode":"ha8 7ju",
    "addr:street":"Station Road",
    "iso:country":"GB",
    "sg:address":"High View House, 165-167 Station Road",
    "sg:city":"Edgware",
    "sg:classifiers":[
        {
            "category":"Shopping",
            "subcategory":"Antiques",
            "type":"Retail Goods"
        }
    ],
    "sg:phone":"+44 20 8952 9188",
    "sg:postcode":"HA8 7JU",
    "sg:province":"Greater London",
    "sg:tags":[
        "valuer"
    ],
    "wof:name":"Quastel Associates Ltd.",
    "wof:placetype":"venue"
},
  "geometry": {"coordinates":[-0.276113987,51.6138954163],"type":"Point"}
}