{
  "type": "Feature",
  "properties": {
    "addr:full":"Little Camoquhill, Balfron Glasgow Argyll and Bute G63 0QP",
    "addr:postcode":"g63 0qp",
    "iso:country":"GB",
    "sg:address":"Little Camoquhill, Balfron",
    "sg:city":"Glasgow",
    "sg:classifiers":[
        {
            "category":"Home & Garden",
            "subcategory":"Hardware",
            "type":"Retail Goods"
        },
        {
            "category":"Wholesale",
            "subcategory":"Vending Machines",
            "type":"Manufacturing & Wholesale Goods"
        }
    ],
    "sg:phone":"+44 1360 440764",
    "sg:postcode":"G63 0QP",
    "sg:province":"Argyll and Bute",
    "sg:tags":[
        "generator"
    ],
    "wof:name":"L C H Generators Ltd.",
    "wof:placetype":"venue"
},
  "geometry": {"coordinates":[-4.3369731903,56.0710144043],"type":"Point"}
}