{
  "type": "Feature",
  "properties": {
    "addr:full":"27 Haston Close Hereford Herefordshire HR4 0RX",
    "addr:housenumber":"27",
    "addr:postcode":"hr4 0rx",
    "addr:street":"Haston Close",
    "iso:country":"GB",
    "sg:address":"27 Haston Close",
    "sg:city":"Hereford",
    "sg:classifiers":[
        {
            "category":"Manufacturing",
            "subcategory":"Tools & Machinery",
            "type":"Manufacturing & Wholesale Goods"
        },
        {
            "category":"Insurance",
            "subcategory":"Insurance Agent",
            "type":"Services"
        }
    ],
    "sg:phone":"+44 1432 264300",
    "sg:postcode":"HR4 0RX",
    "sg:province":"Herefordshire",
    "sg:tags":[
        "society",
        "broker",
        "friendly"
    ],
    "wof:name":"Herefordshire Insurance Services Ltd",
    "wof:placetype":"venue"
},
  "geometry": {"coordinates":[-2.7460560799,52.066532135],"type":"Point"}
}