{
  "type": "Feature",
  "properties": {
    "iso:country":"GB",
    "sg:address":"80 Radbourne Street",
    "sg:city":"Derby",
    "sg:classifiers":[
        {
            "category":"Shopping",
            "subcategory":"Musical Instruments",
            "type":"Retail Goods"
        }
    ],
    "sg:phone":"+44 1332 346927",
    "sg:postcode":"DE22 3BU",
    "sg:province":"Derbyshire",
    "sg:tags":[
        "piano",
        "tuning",
        "maintenance"
    ],
    "wof:name":"A P STORER",
    "wof:placetype":"venue"
},
  "geometry": {"coordinates":[-1.502149,52.925777],"type":"Point"}
}