{
  "type": "Feature",
  "properties": {
    "addr:full":"42 Havelock Street Spalding Lincolnshire PE11 2YL",
    "addr:housenumber":"42",
    "addr:postcode":"pe11 2yl",
    "addr:street":"Havelock Street",
    "iso:country":"GB",
    "sg:address":"42 Havelock Street",
    "sg:city":"Spalding",
    "sg:classifiers":[
        {
            "category":"Building & Trades",
            "subcategory":"Construction",
            "type":"Services"
        }
    ],
    "sg:phone":"+44 1775 768433",
    "sg:postcode":"PE11 2YL",
    "sg:province":"Lincolnshire",
    "sg:tags":[
        "tiling",
        "contractor"
    ],
    "wof:name":"A J Bennett",
    "wof:placetype":"venue"
},
  "geometry": {"coordinates":[-0.158439,52.784302],"type":"Point"}
}