{
  "type": "Feature",
  "properties": {
    "iso:country":"GB",
    "sg:address":"Albright Wilson Industrial Estate, Ferry Lane",
    "sg:city":"Rainham",
    "sg:classifiers":[
        {
            "category":"Utilities",
            "subcategory":"Natural Gas",
            "type":"Services"
        }
    ],
    "sg:phone":"+44 1708 550202",
    "sg:postcode":"RM13 9BU",
    "sg:province":"Essex",
    "sg:tags":[
        "injector",
        "diesel"
    ],
    "wof:name":"Bess Island Diesels",
    "wof:placetype":"venue"
},
  "geometry": {"coordinates":[0.190426,51.517914],"type":"Point"}
}