{
  "type": "Feature",
  "properties": {
    "iso:country":"GB",
    "sg:address":"Westbank Farm, Capstone Road",
    "sg:city":"Gillingham",
    "sg:classifiers":[
        {
            "category":"Farming",
            "subcategory":"Farm",
            "type":"Manufacturing & Wholesale Goods"
        }
    ],
    "sg:postcode":"ME7 3JF",
    "sg:province":"Kent",
    "sg:tags":[
        "egg",
        "producer"
    ],
    "wof:name":"Peter Harding",
    "wof:placetype":"venue"
},
  "geometry": {"coordinates":[0.5495430231,51.3864593506],"type":"Point"}
}