{
  "type": "Feature",
  "properties": {
    "iso:country":"GB",
    "sg:address":"21 Vestry Mews",
    "sg:city":"London",
    "sg:classifiers":[
        {
            "category":"Professional",
            "subcategory":"Management & Consulting",
            "type":"Services"
        }
    ],
    "sg:postcode":"SE5 8NS",
    "sg:province":"Greater London",
    "sg:tags":[
        "consultant",
        "business"
    ],
    "wof:name":"Regus Ventures Ltd",
    "wof:placetype":"venue"
},
  "geometry": {"coordinates":[-0.08506,51.473171],"type":"Point"}
}