{
  "type": "Feature",
  "properties": {
    "addr:full":"Unit C12, Aven Industrial Park, Tickhill Road, Maltby Rotherham South Yorkshire S66 7QR",
    "addr:housenumber":"c12",
    "addr:postcode":"s66 7qr",
    "addr:street":"Aven Industrial Park Tickhill Road",
    "iso:country":"GB",
    "sg:address":"Unit C12, Aven Industrial Park, Tickhill Road, Maltby",
    "sg:city":"Rotherham",
    "sg:classifiers":[
        {
            "category":"Social Services",
            "subcategory":"Job Training",
            "type":"Services"
        },
        {
            "category":"Education",
            "subcategory":"Special Training",
            "type":"Public Place"
        }
    ],
    "sg:phone":"+44 1709 817150",
    "sg:postcode":"S66 7QR",
    "sg:province":"South Yorkshire",
    "sg:tags":[
        "product",
        "centre"
    ],
    "wof:name":"Scott White Training",
    "wof:placetype":"venue"
},
  "geometry": {"coordinates":[-1.16536,53.423504],"type":"Point"}
}