{
  "type": "Feature",
  "properties": {
    "iso:country":"GB",
    "sg:address":"Unit 4, 80-81 Walsworth Rd",
    "sg:city":"Hitchin",
    "sg:classifiers":[
        {
            "category":"Retail",
            "subcategory":"Auto Repair",
            "type":"Services"
        }
    ],
    "sg:phone":"+44 1462 440995",
    "sg:postcode":"SG4 9SX",
    "sg:province":"Hertfordshire",
    "sg:tags":[
        "car",
        "upholsterer"
    ],
    "wof:name":"A1 Autotrimmers",
    "wof:placetype":"venue"
},
  "geometry": {"coordinates":[-0.2663080096,51.9523239136],"type":"Point"}
}