{
  "type": "Feature",
  "properties": {
    "addr:full":"Dalbeattie Road Castle Douglas Dumfries and Galloway DG7 1HZ",
    "addr:postcode":"dg7 1hz",
    "addr:street":"Dalbeattie Road",
    "iso:country":"GB",
    "sg:address":"Dalbeattie Road",
    "sg:city":"Castle Douglas",
    "sg:classifiers":[
        {
            "category":"Professional",
            "subcategory":"Engineering",
            "type":"Services"
        }
    ],
    "sg:phone":"+44 1556 502338",
    "sg:postcode":"DG7 1HZ",
    "sg:province":"Dumfries and Galloway",
    "wof:name":"James Gordon Engineers Ltd.",
    "wof:placetype":"venue"
},
  "geometry": {"coordinates":[-3.928704,54.94162],"type":"Point"}
}