{
  "type": "Feature",
  "properties": {
    "iso:country":"GB",
    "sg:address":"264 Cowley Road",
    "sg:city":"Oxford",
    "sg:classifiers":[
        {
            "category":"Food & Beverages",
            "subcategory":"Meat & Fish",
            "type":"Retail Goods"
        }
    ],
    "sg:postcode":"OX4 1UH",
    "sg:province":"Oxfordshire",
    "sg:tags":[
        "butcher"
    ],
    "wof:name":"A Hussein",
    "wof:placetype":"venue"
},
  "geometry": {"coordinates":[-1.2321310043,51.7458877563],"type":"Point"}
}