{
  "type": "Feature",
  "properties": {
    "iso:country":"GB",
    "sg:address":"22 Fisher St",
    "sg:city":"Lewes",
    "sg:classifiers":[
        {
            "category":"Fast Food",
            "type":"Food & Drink"
        }
    ],
    "sg:phone":"+44 1273 474221",
    "sg:postcode":"BN7 2DG",
    "sg:province":"East Sussex",
    "sg:tags":[
        "away",
        "take"
    ],
    "wof:name":"New Beefeater The",
    "wof:placetype":"venue"
},
  "geometry": {"coordinates":[0.0097749997,50.8739585876],"type":"Point"}
}