{
  "type": "Feature",
  "properties": {
    "iso:country":"GB",
    "sg:address":"Longtown Street",
    "sg:city":"Dundee",
    "sg:classifiers":[
        {
            "category":"Professional",
            "subcategory":"Business Services",
            "type":"Services"
        },
        {
            "category":"Manufacturing",
            "subcategory":"Building Materials",
            "type":"Manufacturing & Wholesale Goods"
        }
    ],
    "sg:phone":"+44 1382 504088",
    "sg:postcode":"DD4 8LF",
    "sg:province":"Dundee City",
    "sg:tags":[
        "tile",
        "merchant",
        "builder",
        "stockist"
    ],
    "wof:name":"REMBRAND BUILDERS MERCHANTS LTD",
    "wof:placetype":"venue"
},
  "geometry": {"coordinates":[-2.9238989353,56.4813117981],"type":"Point"}
}