{
  "type": "Feature",
  "properties": {
    "iso:country":"GB",
    "sg:address":"Sedge Gate Nursery, Sedge Green",
    "sg:city":"Waltham Abbey",
    "sg:classifiers":[
        {
            "category":"Shopping",
            "subcategory":"Florist",
            "type":"Retail Goods"
        }
    ],
    "sg:phone":"+44 1462 484884",
    "sg:postcode":"EN9 2PA",
    "sg:province":"Essex",
    "wof:name":"1st For Foliage",
    "wof:placetype":"venue"
},
  "geometry": {"coordinates":[0.012415,51.745541],"type":"Point"}
}