{
  "type": "Feature",
  "properties": {
    "addr:full":"450 Blandford Rd Poole Dorset BH16 5BN",
    "addr:housenumber":"450",
    "addr:postcode":"bh16 5bn",
    "addr:street":"Blandford Rd",
    "iso:country":"GB",
    "sg:address":"450 Blandford Rd",
    "sg:city":"Poole",
    "sg:classifiers":[
        {
            "category":"Freight",
            "type":"Transportation"
        }
    ],
    "sg:phone":"+44 1202 684848",
    "sg:postcode":"BH16 5BN",
    "sg:province":"Dorset",
    "sg:tags":[
        "haulage",
        "road"
    ],
    "wof:name":"Sterling European Ltd",
    "wof:placetype":"venue"
},
  "geometry": {"coordinates":[-2.018985,50.728771],"type":"Point"}
}