{
  "type": "Feature",
  "properties": {
    "addr:full":"Church Road, Cheadle Hulme Cheadle Cheshire SK8 7JL",
    "addr:postcode":"sk8 7jl",
    "addr:street":"Church Road",
    "iso:country":"GB",
    "sg:address":"Church Road, Cheadle Hulme",
    "sg:city":"Cheadle",
    "sg:classifiers":[
        {
            "category":"Place Of Worship",
            "type":"Public Place"
        }
    ],
    "sg:phone":"+44 161 485 3455",
    "sg:postcode":"SK8 7JL",
    "sg:province":"Cheshire",
    "wof:name":"All Saints Church",
    "wof:placetype":"venue"
},
  "geometry": {"coordinates":[-2.184754,53.367115],"type":"Point"}
}