{
  "type": "Feature",
  "properties": {
    "addr:full":"Unit 23-24, Brockholes Industrial Park, Rockmill Road Huddersfield South Yorkshire HD9 7BN",
    "addr:housenumber":"unit 23-24",
    "addr:postcode":"hd9 7bn",
    "addr:street":"Brockholes Industrial Park Rockmill Road",
    "iso:country":"GB",
    "sg:address":"Unit 23-24, Brockholes Industrial Park, Rockmill Road",
    "sg:city":"Huddersfield",
    "sg:classifiers":[
        {
            "category":"Professional",
            "subcategory":"Business Services",
            "type":"Services"
        }
    ],
    "sg:postcode":"HD9 7BN",
    "sg:province":"South Yorkshire",
    "sg:tags":[
        "assessment",
        "quality"
    ],
    "wof:name":"J L J Productions",
    "wof:placetype":"venue"
},
  "geometry": {"coordinates":[-1.7727,53.593891],"type":"Point"}
}