{
  "type": "Feature",
  "properties": {
    "iso:country":"GB",
    "sg:address":"55 Hutland Rd",
    "sg:city":"Ipswich",
    "sg:classifiers":[
        {
            "category":"Professional",
            "subcategory":"Computer Services",
            "type":"Services"
        }
    ],
    "sg:phone":"+44 1473 274831",
    "sg:postcode":"IP4 4HQ",
    "sg:province":"Suffolk",
    "sg:tags":[
        "system",
        "software"
    ],
    "wof:name":"VS QS Computers",
    "wof:placetype":"venue"
},
  "geometry": {"coordinates":[1.178443,52.063251],"type":"Point"}
}