{
  "type": "Feature",
  "properties": {
    "addr:full":"72 Lowbank Road Wigan Lancashire WN4 9RZ",
    "addr:housenumber":"72",
    "addr:postcode":"wn4 9rz",
    "addr:street":"Lowbank Road",
    "iso:country":"GB",
    "sg:address":"72 Lowbank Road",
    "sg:city":"Wigan",
    "sg:classifiers":[
        {
            "category":"Building & Trades",
            "subcategory":"Construction",
            "type":"Services"
        }
    ],
    "sg:phone":"+44 1942 270183",
    "sg:postcode":"WN4 9RZ",
    "sg:province":"Lancashire",
    "sg:tags":[
        "builder"
    ],
    "wof:name":"Butcher & Bolton",
    "wof:placetype":"venue"
},
  "geometry": {"coordinates":[-2.650363,53.493179],"type":"Point"}
}