{
  "type": "Feature",
  "properties": {
    "addr:full":"Unit 3d Pennygillam Way, Pennygillam Industrial Estate Launceston Cornwall PL15 7ED",
    "addr:housenumber":"unit",
    "addr:postcode":"pl15 7ed",
    "addr:street":"Pennygillam Way Pennygillam Industrial Estate",
    "iso:country":"GB",
    "sg:address":"Unit 3d Pennygillam Way, Pennygillam Industrial Estate",
    "sg:city":"Launceston",
    "sg:classifiers":[
        {
            "category":"Autos & Motor Vehicles",
            "subcategory":"Auto Supplies",
            "type":"Retail Goods"
        }
    ],
    "sg:phone":"+44 1566 774341",
    "sg:postcode":"PL15 7ED",
    "sg:province":"Cornwall",
    "sg:tags":[
        "car",
        "component"
    ],
    "wof:name":"Albert J Parsons & Sons Ltd.",
    "wof:placetype":"venue"
},
  "geometry": {"coordinates":[-4.3703489304,50.6277160645],"type":"Point"}
}