{
  "type": "Feature",
  "properties": {
    "iso:country":"GB",
    "sg:address":"1 First Avenue",
    "sg:city":"Bradford",
    "sg:classifiers":[
        {
            "category":"Health Services",
            "subcategory":"Nursing And Care Facility",
            "type":"Services"
        },
        {
            "category":"Social Services",
            "subcategory":"Retirement Home",
            "type":"Services"
        }
    ],
    "sg:phone":"+44 1274 626064",
    "sg:postcode":"BD3 7JG",
    "sg:province":"West Yorkshire",
    "sg:tags":[
        "residential"
    ],
    "wof:name":"KATHLEEN & KEVIN CASEY",
    "wof:placetype":"venue"
},
  "geometry": {"coordinates":[-1.7223869562,53.8022041321],"type":"Point"}
}