{
  "type": "Feature",
  "properties": {
    "iso:country":"GB",
    "sg:address":"15 Downing Street",
    "sg:city":"Farnham",
    "sg:classifiers":[
        {
            "category":"Banks & Credit Unions",
            "subcategory":"Financial Services",
            "type":"Services"
        }
    ],
    "sg:phone":"+44 1252 726711",
    "sg:postcode":"GU9 7PB",
    "sg:province":"Surrey",
    "sg:tags":[
        "consultant"
    ],
    "wof:name":"Agency Financial Services",
    "wof:placetype":"venue"
},
  "geometry": {"coordinates":[-0.79946,51.213612],"type":"Point"}
}