{
  "type": "Feature",
  "properties": {
    "iso:country":"GB",
    "sg:address":"19 George St",
    "sg:city":"Hove",
    "sg:classifiers":[
        {
            "category":"Shopping",
            "subcategory":"Books",
            "type":"Retail Goods"
        },
        {
            "category":"Shopping",
            "subcategory":"News",
            "type":"Retail Goods"
        }
    ],
    "sg:postcode":"BN3 3XA",
    "sg:province":"East Sussex",
    "sg:tags":[
        "bookseller",
        "newsagent"
    ],
    "wof:name":"Oliver,John,",
    "wof:placetype":"venue"
},
  "geometry": {"coordinates":[-0.173493,50.829132],"type":"Point"}
}