{
  "type": "Feature",
  "properties": {
    "iso:country":"GB",
    "sg:address":"51 Sheepcote Road",
    "sg:city":"Harrow",
    "sg:classifiers":[
        {
            "category":"Organizations",
            "subcategory":"Non-profit Organization",
            "type":"Services"
        }
    ],
    "sg:phone":"+44 20 8863 8051",
    "sg:postcode":"HA1 2JL",
    "sg:province":"Greater London",
    "sg:tags":[
        "organisation",
        "voluntary",
        "charity"
    ],
    "wof:name":"Ywca",
    "wof:placetype":"venue"
},
  "geometry": {"coordinates":[-0.3285990059,51.5805778503],"type":"Point"}
}