{
  "type": "Feature",
  "properties": {
    "addr:full":"35 Low Hall Industrial Estate, Low Hall Road Leeds West Yorkshire LS18 4EG",
    "addr:housenumber":"35",
    "addr:postcode":"ls18 4eg",
    "addr:street":"Low Hall Industrial Estate;Hall Road",
    "iso:country":"GB",
    "sg:address":"35 Low Hall Industrial Estate, Low Hall Road",
    "sg:city":"Leeds",
    "sg:classifiers":[
        {
            "category":"Shopping",
            "subcategory":"Clothing, Apparel, & Fashions",
            "type":"Retail Goods"
        }
    ],
    "sg:phone":"+44 113 258 1358",
    "sg:postcode":"LS18 4EG",
    "sg:province":"West Yorkshire",
    "sg:tags":[
        "clothing",
        "fabric"
    ],
    "wof:name":"Bundisfield Developments Ltd.",
    "wof:placetype":"venue"
},
  "geometry": {"coordinates":[-1.546587,53.794495],"type":"Point"}
}