{
  "type": "Feature",
  "properties": {
    "iso:country":"GB",
    "sg:address":"284 High Street, Langley",
    "sg:city":"Slough",
    "sg:classifiers":[
        {
            "category":"Food & Beverages",
            "subcategory":"Fruits & Vegetables",
            "type":"Retail Goods"
        }
    ],
    "sg:phone":"+44 1753 541445",
    "sg:postcode":"SL3 8HF",
    "sg:province":"Berkshire",
    "sg:tags":[
        "greengrocer"
    ],
    "wof:name":"Rite Price",
    "wof:placetype":"venue"
},
  "geometry": {"coordinates":[-0.542741,51.504005],"type":"Point"}
}