{
  "type": "Feature",
  "properties": {
    "addr:full":"Rooms 104 First Floor, Building 521 London Heathrow Airport Hounslow Greater London TW6 3TX",
    "addr:housenumber":"104 first floor building 521;heathrow",
    "addr:postcode":"tw6 3tx",
    "addr:street":"Airport",
    "iso:country":"GB",
    "sg:address":"Rooms 104 First Floor, Building 521 London Heathrow Airport",
    "sg:city":"Hounslow",
    "sg:classifiers":[
        {
            "category":"Airline",
            "type":"Transportation"
        }
    ],
    "sg:phone":"+44 1293 579992",
    "sg:postcode":"TW6 3TX",
    "sg:province":"Greater London",
    "wof:name":"China Eastern Airlines",
    "wof:placetype":"venue"
},
  "geometry": {"coordinates":[-0.45527,51.460171],"type":"Point"}
}