{
  "type": "Feature",
  "properties": {
    "iso:country":"GB",
    "sg:address":"Church Street",
    "sg:city":"Carlisle",
    "sg:classifiers":[
        {
            "category":"Bus Charters",
            "type":"Transportation"
        }
    ],
    "sg:phone":"+44 1228 549488",
    "sg:postcode":"CA2 5TJ",
    "sg:province":"Cumbria",
    "sg:tags":[
        "hire",
        "coach"
    ],
    "wof:name":"Borderbus",
    "wof:placetype":"venue"
},
  "geometry": {"coordinates":[-2.9480700493,54.8940048218],"type":"Point"}
}