{
  "type": "Feature",
  "properties": {
    "addr:full":"Hooton Road, Kilnhurst Sheffield South Yorkshire S64 5TA",
    "addr:postcode":"s64 5ta",
    "addr:street":"Hooton Road",
    "iso:country":"GB",
    "sg:address":"Hooton Road, Kilnhurst",
    "sg:city":"Sheffield",
    "sg:classifiers":[
        {
            "category":"Education",
            "subcategory":"School",
            "type":"Public Place"
        },
        {
            "category":"Government",
            "subcategory":"Office",
            "type":"Public Place"
        }
    ],
    "sg:phone":"+44 1709 570590",
    "sg:postcode":"S64 5TA",
    "sg:province":"South Yorkshire",
    "sg:tags":[
        "local",
        "authority"
    ],
    "wof:name":"Kilnhurst Junior & Infant School",
    "wof:placetype":"venue"
},
  "geometry": {"coordinates":[-1.3090289831,53.4720420837],"type":"Point"}
}