{
  "type": "Feature",
  "properties": {
    "addr:full":"639 Uttoxeter Road, Meir Stoke-on-trent Staffordshire ST3 5PZ",
    "addr:housenumber":"639",
    "addr:postcode":"staffordshire st3 5pz",
    "addr:street":"Uttoxeter Road",
    "iso:country":"GB",
    "sg:address":"639 Uttoxeter Road, Meir",
    "sg:city":"Stoke-on-trent",
    "sg:classifiers":[
        {
            "category":"Arts & Performance",
            "subcategory":"Music",
            "type":"Entertainment"
        }
    ],
    "sg:postcode":"ST3 5PZ",
    "sg:province":"Staffordshire",
    "sg:tags":[
        "mobile",
        "disco"
    ],
    "wof:name":"Celebration",
    "wof:placetype":"venue"
},
  "geometry": {"coordinates":[-2.110408,52.980026],"type":"Point"}
}