{
  "type": "Feature",
  "properties": {
    "iso:country":"GB",
    "sg:address":"Guilford Road, Eccles",
    "sg:city":"Manchester",
    "sg:classifiers":[
        {
            "category":"Education",
            "subcategory":"School",
            "type":"Public Place"
        },
        {
            "category":"Government",
            "subcategory":"Office",
            "type":"Public Place"
        }
    ],
    "sg:phone":"+44 161 789 4678",
    "sg:postcode":"M30 7JF",
    "sg:province":"Greater Manchester",
    "sg:tags":[
        "local",
        "authority"
    ],
    "wof:name":"St Patrick's R C High School",
    "wof:placetype":"venue"
},
  "geometry": {"coordinates":[-2.366824,53.482105],"type":"Point"}
}