{
  "type": "Feature",
  "properties": {
    "addr:full":"Forest Mills, Alfreton Road Nottingham Nottinghamshire NG7 3QA",
    "addr:postcode":"ng7 3qa",
    "addr:street":"Forest;Alfreton Road",
    "iso:country":"GB",
    "sg:address":"Forest Mills, Alfreton Road",
    "sg:city":"Nottingham",
    "sg:classifiers":[
        {
            "category":"Professional",
            "subcategory":"Printing & Photocopies",
            "type":"Services"
        }
    ],
    "sg:phone":"+44 115 978 9919",
    "sg:postcode":"NG7 3QA",
    "sg:province":"Nottinghamshire",
    "sg:tags":[
        "printer"
    ],
    "wof:name":"Regeena Printing Ltd.",
    "wof:placetype":"venue"
},
  "geometry": {"coordinates":[-1.166960001,52.9578590393],"type":"Point"}
}