{
  "type": "Feature",
  "properties": {
    "addr:full":"19 Downs View Road Hassocks East Sussex BN6 8HJ",
    "addr:housenumber":"19",
    "addr:postcode":"bn6 8hj",
    "addr:street":"Downs View Road",
    "iso:country":"GB",
    "sg:address":"19 Downs View Road",
    "sg:city":"Hassocks",
    "sg:classifiers":[
        {
            "category":"Building & Trades",
            "subcategory":"Construction",
            "type":"Services"
        }
    ],
    "sg:postcode":"BN6 8HJ",
    "sg:province":"East Sussex",
    "sg:tags":[
        "builder"
    ],
    "wof:name":"Property Doctor",
    "wof:placetype":"venue"
},
  "geometry": {"coordinates":[-0.142226994,50.9228248596],"type":"Point"}
}