{
  "type": "Feature",
  "properties": {
    "addr:full":"Waterside Mill, Lower Bank Street, Waterside Macclesfield Cheshire SK11 7HL",
    "addr:postcode":"sk11 7hl",
    "addr:street":"Waterside Mill Lower Bank Street",
    "iso:country":"GB",
    "sg:address":"Waterside Mill, Lower Bank Street, Waterside",
    "sg:city":"Macclesfield",
    "sg:classifiers":[
        {
            "category":"Shopping",
            "subcategory":"Clothing, Apparel, & Fashions",
            "type":"Retail Goods"
        }
    ],
    "sg:phone":"+44 1625 615056",
    "sg:postcode":"SK11 7HL",
    "sg:province":"Cheshire",
    "sg:tags":[
        "tie",
        "neckwear"
    ],
    "wof:name":"Spurcroft Ltd.",
    "wof:placetype":"venue"
},
  "geometry": {"coordinates":[-2.125756,53.255669],"type":"Point"}
}