{
  "type": "Feature",
  "properties": {
    "iso:country":"GB",
    "sg:address":"86 Pennyland Drive",
    "sg:city":"Thurso",
    "sg:classifiers":[
        {
            "category":"Taxi",
            "type":"Transportation"
        }
    ],
    "sg:phone":"+44 1847 890088",
    "sg:postcode":"KW14 7PW",
    "sg:province":"Highland",
    "sg:tags":[
        "mini",
        "cab"
    ],
    "wof:name":"J J Taxis",
    "wof:placetype":"venue"
},
  "geometry": {"coordinates":[-3.540868,58.594002],"type":"Point"}
}