{
  "type": "Feature",
  "properties": {
    "addr:full":"46b Grasmere Road Blackpool Lancashire FY1 5HT",
    "addr:housenumber":"46b",
    "addr:postcode":"fy1 5ht",
    "addr:street":"Grasmere Road",
    "iso:country":"GB",
    "sg:address":"46b Grasmere Road",
    "sg:city":"Blackpool",
    "sg:classifiers":[
        {
            "category":"Shopping",
            "subcategory":"Department Store",
            "type":"Retail Goods"
        }
    ],
    "sg:phone":"+44 1253 22483",
    "sg:postcode":"FY1 5HT",
    "sg:province":"Lancashire",
    "wof:name":"H Ramsden",
    "wof:placetype":"venue"
},
  "geometry": {"coordinates":[-3.0439341068,53.808506012],"type":"Point"}
}