{
  "type": "Feature",
  "properties": {
    "addr:full":"Circle Road, Whiteley Village Walton-on-thames Surrey KT12 4DT",
    "addr:postcode":"kt12 4dt",
    "addr:street":"Circle Road;Village",
    "iso:country":"GB",
    "sg:address":"Circle Road, Whiteley Village",
    "sg:city":"Walton-on-thames",
    "sg:classifiers":[
        {
            "category":"Government",
            "subcategory":"Post Office",
            "type":"Public Place"
        }
    ],
    "sg:phone":"+44 1932 821467",
    "sg:postcode":"KT12 4DT",
    "sg:province":"Surrey",
    "wof:name":"Whiteley Village Post Office",
    "wof:placetype":"venue"
},
  "geometry": {"coordinates":[-0.4302020073,51.3515319824],"type":"Point"}
}