{
  "type": "Feature",
  "properties": {
    "addr:full":"Unit 2 12 Harper Rd, Stoke Coventry West Midlands CV1 2QA",
    "addr:housenumber":"unit;12",
    "addr:postcode":"cv1 2qa",
    "addr:street":"Harper Rd",
    "iso:country":"GB",
    "sg:address":"Unit 2 12 Harper Rd, Stoke",
    "sg:city":"Coventry",
    "sg:classifiers":[
        {
            "category":"Retail",
            "subcategory":"Auto Rental",
            "type":"Services"
        }
    ],
    "sg:postcode":"CV1 2QA",
    "sg:province":"West Midlands",
    "sg:tags":[
        "car"
    ],
    "wof:name":"Henry,Dennis,",
    "wof:placetype":"venue"
},
  "geometry": {"coordinates":[-1.5077680349,52.4069862366],"type":"Point"}
}