{
  "type": "Feature",
  "properties": {
    "iso:country":"GB",
    "sg:address":"21a Walm Lane",
    "sg:city":"Cricklewood",
    "sg:classifiers":[
        {
            "category":"Shopping",
            "subcategory":"Thrift Store",
            "type":"Retail Goods"
        }
    ],
    "sg:phone":"+44 20 8459 3420",
    "sg:postcode":"NW2 5SH",
    "sg:province":"Greater London",
    "sg:tags":[
        "shop",
        "charity"
    ],
    "wof:name":"Thrift Shop",
    "wof:placetype":"venue"
},
  "geometry": {"coordinates":[-0.224334,51.547699],"type":"Point"}
}