{
  "type": "Feature",
  "properties": {
    "addr:full":"55 Dawes Street Elephant And Castle Greater London SE17 1EL",
    "addr:housenumber":"55",
    "addr:postcode":"and;se17 1el",
    "addr:street":"Dawes Street",
    "iso:country":"GB",
    "sg:address":"55 Dawes Street",
    "sg:city":"Elephant And Castle",
    "sg:classifiers":[
        {
            "category":"Professional",
            "subcategory":"Management & Consulting",
            "type":"Services"
        }
    ],
    "sg:phone":"+44 20 7708 3951",
    "sg:postcode":"SE17 1EL",
    "sg:province":"Greater London",
    "sg:tags":[
        "consultant",
        "image"
    ],
    "wof:name":"101 Direct",
    "wof:placetype":"venue"
},
  "geometry": {"coordinates":[-0.0889040008,51.4898223877],"type":"Point"}
}