{
  "type": "Feature",
  "properties": {
    "addr:full":"10 High Street, Cleator Moor Whitehaven Cumbria CA28 7PZ",
    "addr:housenumber":"10",
    "addr:postcode":"ca28 7pz",
    "addr:street":"High Street",
    "iso:country":"GB",
    "sg:address":"10 High Street, Cleator Moor",
    "sg:city":"Whitehaven",
    "sg:classifiers":[
        {
            "category":"Food & Beverages",
            "subcategory":"Liquor & Beverages",
            "type":"Retail Goods"
        }
    ],
    "sg:phone":"+44 1946 812310",
    "sg:postcode":"CA28 7PZ",
    "sg:province":"Cumbria",
    "sg:tags":[
        "beer",
        "wine",
        "spirit",
        "wines"
    ],
    "wof:name":"Pauls Wines",
    "wof:placetype":"venue"
},
  "geometry": {"coordinates":[-3.583927,54.550873],"type":"Point"}
}