{
  "type": "Feature",
  "properties": {
    "iso:country":"GB",
    "sg:address":"28-30 Nelson Road, Westward House",
    "sg:city":"Bideford",
    "sg:classifiers":[
        {
            "category":"Personal",
            "subcategory":"Beauty Salon",
            "type":"Services"
        }
    ],
    "sg:phone":"+44 1237 473686",
    "sg:postcode":"EX39 1LQ",
    "sg:province":"Devon",
    "sg:tags":[
        "lady",
        "hairdresser"
    ],
    "wof:name":"Lucifers",
    "wof:placetype":"venue"
},
  "geometry": {"coordinates":[-4.237304,51.039894],"type":"Point"}
}