{
  "type": "Feature",
  "properties": {
    "addr:full":"15 Killyon Road London Greater London SW8 2XS",
    "addr:housenumber":"15",
    "addr:postcode":"sw8 2xs",
    "addr:street":"Killyon Road",
    "iso:country":"GB",
    "sg:address":"15 Killyon Road",
    "sg:city":"London",
    "sg:classifiers":[
        {
            "category":"Education",
            "subcategory":"Special Training",
            "type":"Public Place"
        }
    ],
    "sg:phone":"+44 20 7720 4499",
    "sg:postcode":"SW8 2XS",
    "sg:province":"Greater London",
    "sg:tags":[
        "product",
        "centre"
    ],
    "wof:name":"Pellin Institute",
    "wof:placetype":"venue"
},
  "geometry": {"coordinates":[-0.1366630048,51.4690132141],"type":"Point"}
}