{
  "type": "Feature",
  "properties": {
    "addr:full":"2 Crystal Ho, New Bedford Rd Luton Bedfordshire LU1 1HS",
    "addr:housenumber":"2",
    "addr:postcode":"lu1 1hs",
    "addr:street":"Crystal Ho New Bedford Rd",
    "iso:country":"GB",
    "sg:address":"2 Crystal Ho, New Bedford Rd",
    "sg:city":"Luton",
    "sg:classifiers":[
        {
            "category":"Wholesale",
            "subcategory":"Scrap",
            "type":"Manufacturing & Wholesale Goods"
        }
    ],
    "sg:postcode":"LU1 1HS",
    "sg:province":"Bedfordshire",
    "sg:tags":[
        "waste",
        "metal"
    ],
    "wof:name":"Cap-It-All Ltd",
    "wof:placetype":"venue"
},
  "geometry": {"coordinates":[-0.418939,51.882172],"type":"Point"}
}