{
  "type": "Feature",
  "properties": {
    "addr:full":"116a Terregles Av Glasgow Glasgow City G41 4LJ",
    "addr:housenumber":"116a",
    "addr:postcode":"g41 4lj",
    "addr:street":"Terregles Av",
    "iso:country":"GB",
    "sg:address":"116a Terregles Av",
    "sg:city":"Glasgow",
    "sg:classifiers":[
        {
            "category":"Professional",
            "subcategory":"Employment Agencies",
            "type":"Services"
        }
    ],
    "sg:phone":"+44 141 422 1962",
    "sg:postcode":"G41 4LJ",
    "sg:province":"Glasgow City",
    "sg:tags":[
        "consultant"
    ],
    "wof:name":"Spottiswood & Associates",
    "wof:placetype":"venue"
},
  "geometry": {"coordinates":[-4.2860450745,55.8381004333],"type":"Point"}
}