{
  "type": "Feature",
  "properties": {
    "iso:country":"GB",
    "sg:address":"1 Yearling Chase, Swinton",
    "sg:city":"Mexborough",
    "sg:classifiers":[
        {
            "category":"Banks & Credit Unions",
            "subcategory":"Bank",
            "type":"Services"
        },
        {
            "category":"Banks & Credit Unions",
            "subcategory":"Financial Services",
            "type":"Services"
        }
    ],
    "sg:postcode":"S64 8XA",
    "sg:province":"South Yorkshire",
    "sg:tags":[
        "consultant",
        "broker",
        "mortgage"
    ],
    "wof:name":"Roebuck Financial Services",
    "wof:placetype":"venue"
},
  "geometry": {"coordinates":[-1.325978,53.489101],"type":"Point"}
}