{
  "type": "Feature",
  "properties": {
    "addr:full":"88 Bailey Street, Blaenau Gwent Ebbw Vale Blaenau Gwent NP23 4AN",
    "addr:housenumber":"88",
    "addr:postcode":"np23 4an",
    "addr:street":"Bailey Street",
    "iso:country":"GB",
    "sg:address":"88 Bailey Street, Blaenau Gwent",
    "sg:city":"Ebbw Vale",
    "sg:classifiers":[
        {
            "category":"Home & Garden",
            "subcategory":"Kitchen Supply",
            "type":"Retail Goods"
        }
    ],
    "sg:phone":"+44 1495 310573",
    "sg:postcode":"NP23 4AN",
    "sg:province":"Blaenau Gwent",
    "sg:tags":[
        "glassware",
        "china"
    ],
    "wof:name":"Messrs Evans",
    "wof:placetype":"venue"
},
  "geometry": {"coordinates":[-3.174476,51.798214],"type":"Point"}
}