{
  "type": "Feature",
  "properties": {
    "addr:full":"315 Southend Lane Catford Greater London SE6 3ND",
    "addr:housenumber":"315",
    "addr:postcode":"se6 3nd",
    "addr:street":"Southend Lane",
    "iso:country":"GB",
    "sg:address":"315 Southend Lane",
    "sg:city":"Catford",
    "sg:classifiers":[
        {
            "category":"Autos & Motor Vehicles",
            "subcategory":"Automobile Sales",
            "type":"Retail Goods"
        }
    ],
    "sg:phone":"+44 20 8697 1399",
    "sg:postcode":"SE6 3ND",
    "sg:province":"Greater London",
    "sg:tags":[
        "commercial"
    ],
    "wof:name":"Knights Motor Co",
    "wof:placetype":"venue"
},
  "geometry": {"coordinates":[-0.029306,51.427055],"type":"Point"}
}