{
  "type": "Feature",
  "properties": {
    "addr:full":"Sittyton Straloch, Newmachar Aberdeen Aberdeen City AB21 0RP",
    "addr:postcode":"ab21 0rp",
    "iso:country":"GB",
    "sg:address":"Sittyton Straloch, Newmachar",
    "sg:city":"Aberdeen",
    "sg:classifiers":[
        {
            "category":"Organizations",
            "subcategory":"Non-profit Organization",
            "type":"Services"
        },
        {
            "category":"Farming",
            "subcategory":"Farm",
            "type":"Manufacturing & Wholesale Goods"
        },
        {
            "category":"Organizations",
            "subcategory":"Membership Organization",
            "type":"Services"
        }
    ],
    "sg:phone":"+44 1651 882226",
    "sg:postcode":"AB21 0RP",
    "sg:province":"Aberdeen City",
    "sg:tags":[
        "club",
        "organisation",
        "crop",
        "charitable",
        "mixed",
        "charity"
    ],
    "wof:name":"BRITISH BAVARIAN WARMBLOOD ASSOCIATION",
    "wof:placetype":"venue"
},
  "geometry": {"coordinates":[-2.1900589466,57.2652511597],"type":"Point"}
}