{
  "type": "Feature",
  "properties": {
    "addr:full":"185 Liverpool Road South Liverpool Lancashire L31 8AA",
    "addr:housenumber":"185",
    "addr:postcode":"l31 8aa",
    "addr:street":"Liverpool Road South",
    "iso:country":"GB",
    "sg:address":"185 Liverpool Road South",
    "sg:city":"Liverpool",
    "sg:classifiers":[
        {
            "category":"Health Services",
            "subcategory":"Dentist",
            "type":"Services"
        }
    ],
    "sg:phone":"+44 151 526 1866",
    "sg:postcode":"L31 8AA",
    "sg:province":"Lancashire",
    "wof:name":"Oak Dental",
    "wof:placetype":"venue"
},
  "geometry": {"coordinates":[-2.950037,53.510593],"type":"Point"}
}