{
  "type": "Feature",
  "properties": {
    "iso:country":"GB",
    "sg:address":"21 Lodge Street, Ramsbottom",
    "sg:city":"Bury",
    "sg:classifiers":[
        {
            "category":"Autos & Motor Vehicles",
            "subcategory":"Auto Supplies",
            "type":"Retail Goods"
        }
    ],
    "sg:postcode":"BL0 9AW",
    "sg:province":"Lancashire",
    "sg:tags":[
        "part",
        "motorcycle",
        "accessory"
    ],
    "wof:name":"K N R Motorcycles",
    "wof:placetype":"venue"
},
  "geometry": {"coordinates":[-2.318304,53.646141],"type":"Point"}
}