{
  "type": "Feature",
  "properties": {
    "addr:full":"221 Chatsworth Rd Chesterfield Derbyshire S40 2BA",
    "addr:housenumber":"221",
    "addr:postcode":"s40 2ba",
    "addr:street":"Chatsworth Rd",
    "iso:country":"GB",
    "sg:address":"221 Chatsworth Rd",
    "sg:city":"Chesterfield",
    "sg:classifiers":[
        {
            "category":"Shopping",
            "subcategory":"Antiques",
            "type":"Retail Goods"
        }
    ],
    "sg:postcode":"S40 2BA",
    "sg:province":"Derbyshire",
    "wof:name":"Swift,J,",
    "wof:placetype":"venue"
},
  "geometry": {"coordinates":[-1.4468300343,53.2339439392],"type":"Point"}
}