{
  "type": "Feature",
  "properties": {
    "iso:country":"GB",
    "sg:address":"173 North Rd",
    "sg:city":"Darlington",
    "sg:classifiers":[
        {
            "category":"Food & Beverages",
            "subcategory":"Groceries & Convenience Stores",
            "type":"Retail Goods"
        }
    ],
    "sg:postcode":"DL1 2PT",
    "sg:province":"Durham",
    "wof:name":"Robson,Karen,",
    "wof:placetype":"venue"
},
  "geometry": {"coordinates":[-1.55012,54.540825],"type":"Point"}
}