{
  "type": "Feature",
  "properties": {
    "addr:full":"243 Upper Street London Greater London N1 1RU",
    "addr:housenumber":"243",
    "addr:postcode":"n1 1ru",
    "addr:street":"Upper Street",
    "iso:country":"GB",
    "sg:address":"243 Upper Street",
    "sg:city":"London",
    "sg:classifiers":[
        {
            "category":"Health Services",
            "subcategory":"Dentist",
            "type":"Services"
        }
    ],
    "sg:postcode":"N1 1RU",
    "sg:province":"Greater London",
    "wof:name":"M J C Swords",
    "wof:placetype":"venue"
},
  "geometry": {"coordinates":[-0.103501,51.545174],"type":"Point"}
}