{
  "type": "Feature",
  "properties": {
    "addr:full":"4 Richmond Road, Leytonstone London Greater London E11 4BA",
    "addr:housenumber":"4",
    "addr:postcode":"e11 4ba",
    "addr:street":"Richmond Road",
    "iso:country":"GB",
    "sg:address":"4 Richmond Road, Leytonstone",
    "sg:city":"London",
    "sg:classifiers":[
        {
            "category":"Home & Garden",
            "subcategory":"Household Appliances",
            "type":"Retail Goods"
        },
        {
            "category":"Building & Trades",
            "subcategory":"Electrical",
            "type":"Services"
        }
    ],
    "sg:phone":"+44 20 8539 6666",
    "sg:postcode":"E11 4BA",
    "sg:province":"Greater London",
    "sg:tags":[
        "contractor",
        "refrigeration",
        "air conditioning"
    ],
    "wof:name":"Artic Services",
    "wof:placetype":"venue"
},
  "geometry": {"coordinates":[0.001866,51.566109],"type":"Point"}
}