{
  "type": "Feature",
  "properties": {
    "addr:full":"Victoria House, Skeltons Lane, Leyton London Greater London E10 5BZ",
    "addr:postcode":"e10 5bz",
    "addr:street":"Skeltons Lane",
    "iso:country":"GB",
    "sg:address":"Victoria House, Skeltons Lane, Leyton",
    "sg:city":"London",
    "sg:classifiers":[
        {
            "category":"Building & Trades",
            "subcategory":"Cleaning & Sanitation",
            "type":"Services"
        }
    ],
    "sg:phone":"+44 20 8556 0141",
    "sg:postcode":"E10 5BZ",
    "sg:province":"Greater London",
    "sg:tags":[
        "contracting",
        "commercial"
    ],
    "wof:name":"Victoria Medical & General Cleaning Services Ltd.",
    "wof:placetype":"venue"
},
  "geometry": {"coordinates":[-0.007173,51.558685],"type":"Point"}
}