{
  "type": "Feature",
  "properties": {
    "addr:full":"24 Parker Rd Plymouth Devon PL2 3EB",
    "addr:housenumber":"24",
    "addr:postcode":"pl2 3eb",
    "addr:street":"Parker Rd",
    "iso:country":"GB",
    "sg:address":"24 Parker Rd",
    "sg:city":"Plymouth",
    "sg:classifiers":[
        {
            "category":"Building & Trades",
            "subcategory":"Plumbing",
            "type":"Services"
        }
    ],
    "sg:postcode":"PL2 3EB",
    "sg:province":"Devon",
    "sg:tags":[
        "central",
        "heating"
    ],
    "wof:name":"Technical Heating Services",
    "wof:placetype":"venue"
},
  "geometry": {"coordinates":[-4.1546239853,50.3907165527],"type":"Point"}
}