{
  "type": "Feature",
  "properties": {
    "addr:full":"18 Wych Elm Harlow Essex CM20 1QR",
    "addr:housenumber":"18",
    "addr:postcode":"cm20 1qr",
    "addr:street":"Wych Elm",
    "iso:country":"GB",
    "sg:address":"18 Wych Elm",
    "sg:city":"Harlow",
    "sg:classifiers":[
        {
            "category":"Autos & Motor Vehicles",
            "subcategory":"Motorcycle Sales",
            "type":"Retail Goods"
        }
    ],
    "sg:phone":"+44 1279 425262",
    "sg:postcode":"CM20 1QR",
    "sg:province":"Essex",
    "sg:tags":[
        "scooter",
        "cycle"
    ],
    "wof:name":"Harlow Motorcycle Centre Ltd",
    "wof:placetype":"venue"
},
  "geometry": {"coordinates":[0.090113,51.771999],"type":"Point"}
}