{
  "type": "Feature",
  "properties": {
    "addr:full":"1 Mainwaring Dr Chester Cheshire CH4 0AX",
    "addr:housenumber":"1",
    "addr:postcode":"ch4 0ax",
    "addr:street":"Mainwaring Dr",
    "iso:country":"GB",
    "sg:address":"1 Mainwaring Dr",
    "sg:city":"Chester",
    "sg:classifiers":[
        {
            "category":"Bars & Pubs",
            "type":"Food & Drink"
        }
    ],
    "sg:phone":"+44 1244 680063",
    "sg:postcode":"CH4 0AX",
    "sg:province":"Cheshire",
    "sg:tags":[
        "pubs",
        "inn"
    ],
    "wof:name":"Saltney Ferry The",
    "wof:placetype":"venue"
},
  "geometry": {"coordinates":[-2.94276,53.176147],"type":"Point"}
}