{
  "type": "Feature",
  "properties": {
    "iso:country":"GB",
    "sg:address":"260 Picton Road, Wavertree",
    "sg:city":"Liverpool",
    "sg:classifiers":[
        {
            "category":"Communications",
            "subcategory":"Newspaper",
            "type":"Services"
        }
    ],
    "sg:phone":"+44 151 236 9700",
    "sg:postcode":"L15 4LP",
    "sg:province":"Merseyside",
    "sg:tags":[
        "magazine"
    ],
    "wof:name":"Gateacre Press Ltd.",
    "wof:placetype":"venue"
},
  "geometry": {"coordinates":[-2.924187,53.399418],"type":"Point"}
}