{
  "type": "Feature",
  "properties": {
    "addr:full":"24 Kaffir Road Huddersfield West Yorkshire HD2 2AN",
    "addr:housenumber":"24",
    "addr:postcode":"hd2 2an",
    "addr:street":"Kaffir Road",
    "iso:country":"GB",
    "sg:address":"24 Kaffir Road",
    "sg:city":"Huddersfield",
    "sg:classifiers":[
        {
            "category":"Wholesale",
            "subcategory":"Computers",
            "type":"Manufacturing & Wholesale Goods"
        },
        {
            "category":"Professional",
            "subcategory":"Computer Services",
            "type":"Services"
        }
    ],
    "sg:postcode":"HD2 2AN",
    "sg:province":"West Yorkshire",
    "sg:tags":[
        "supplier",
        "consumables",
        "system",
        "software"
    ],
    "wof:name":"Petrel Systems",
    "wof:placetype":"venue"
},
  "geometry": {"coordinates":[-1.8061699867,53.6568984985],"type":"Point"}
}