{
  "type": "Feature",
  "properties": {
    "iso:country":"GB",
    "sg:address":"The University, Western Bank",
    "sg:city":"Sheffield",
    "sg:classifiers":[
        {
            "category":"Farming",
            "subcategory":"Nursery",
            "type":"Manufacturing & Wholesale Goods"
        },
        {
            "category":"Education",
            "subcategory":"Preschool",
            "type":"Public Place"
        },
        {
            "category":"Government",
            "subcategory":"Office",
            "type":"Public Place"
        }
    ],
    "sg:phone":"+44 114 272 0884",
    "sg:postcode":"S10 2TN",
    "sg:province":"South Yorkshire",
    "sg:tags":[
        "local",
        "school",
        "creche"
    ],
    "wof:name":"Mushroom Lane Nursery School",
    "wof:placetype":"venue"
},
  "geometry": {"coordinates":[-1.464544,53.38311],"type":"Point"}
}