{
  "type": "Feature",
  "properties": {
    "addr:full":"Unit 4 1 Cross La Hornsey Greater London N8 7SA",
    "addr:housenumber":"unit;1",
    "addr:postcode":"n8 7sa",
    "addr:street":"Cross La Hornsey",
    "iso:country":"GB",
    "sg:address":"Unit 4 1 Cross La",
    "sg:city":"Hornsey",
    "sg:classifiers":[
        {
            "category":"Manufacturing",
            "subcategory":"Food",
            "type":"Manufacturing & Wholesale Goods"
        }
    ],
    "sg:phone":"+44 20 8341 7451",
    "sg:postcode":"N8 7SA",
    "sg:province":"Greater London",
    "sg:tags":[
        "processing"
    ],
    "wof:name":"Apollo",
    "wof:placetype":"venue"
},
  "geometry": {"coordinates":[-0.1159690022,51.5878334045],"type":"Point"}
}