{
  "type": "Feature",
  "properties": {
    "addr:full":"4 Church Street Rushden Bedfordshire NN10 9YT",
    "addr:housenumber":"4",
    "addr:postcode":"nn10 9yt",
    "addr:street":"Church Street",
    "iso:country":"GB",
    "sg:address":"4 Church Street",
    "sg:city":"Rushden",
    "sg:classifiers":[
        {
            "category":"Home & Garden",
            "subcategory":"Household Appliances",
            "type":"Retail Goods"
        }
    ],
    "sg:postcode":"NN10 9YT",
    "sg:province":"Bedfordshire",
    "sg:tags":[
        "electrical",
        "domestic"
    ],
    "wof:name":"T C Wheatcroft",
    "wof:placetype":"venue"
},
  "geometry": {"coordinates":[-0.5975800157,52.289226532],"type":"Point"}
}