{
  "type": "Feature",
  "properties": {
    "addr:full":"Chapel House Grounds Chipping Norton Gloucestershire OX7 5SZ",
    "addr:postcode":"ox7 5sz",
    "addr:street":"Chipping Norton",
    "iso:country":"GB",
    "sg:address":"Chapel House Grounds",
    "sg:city":"Chipping Norton",
    "sg:classifiers":[
        {
            "category":"Recreation",
            "subcategory":"Dog Park",
            "type":"Entertainment"
        },
        {
            "category":"Retail",
            "subcategory":"Animal Services",
            "type":"Services"
        }
    ],
    "sg:phone":"+44 1608 642821",
    "sg:postcode":"OX7 5SZ",
    "sg:province":"Gloucestershire",
    "sg:tags":[
        "grooming",
        "clipping"
    ],
    "wof:name":"Paws With Inn",
    "wof:placetype":"venue"
},
  "geometry": {"coordinates":[-1.545912981,51.9404067993],"type":"Point"}
}