{
  "type": "Feature",
  "properties": {
    "addr:full":"344/354 London Rd Croydon Surrey CR0 2SP",
    "addr:housenumber":"344 / 354",
    "addr:postcode":"cr0 2sp",
    "addr:street":"London Rd",
    "iso:country":"GB",
    "sg:address":"344/354 London Rd",
    "sg:city":"Croydon",
    "sg:classifiers":[
        {
            "category":"Autos & Motor Vehicles",
            "subcategory":"Automobile Sales",
            "type":"Retail Goods"
        }
    ],
    "sg:postcode":"CR0 2SP",
    "sg:province":"Surrey",
    "sg:tags":[
        "car"
    ],
    "wof:name":"Simpsons Croydon Ltd",
    "wof:placetype":"venue"
},
  "geometry": {"coordinates":[-0.1089470014,51.3844032288],"type":"Point"}
}