{
  "type": "Feature",
  "properties": {
    "addr:full":"5 Quebec Wharf, 14 Thomas Road London Greater London E14 7AF",
    "addr:housenumber":"5;14",
    "addr:postcode":"e14 7af",
    "addr:street":"Quebec Wharf;Thomas Road",
    "iso:country":"GB",
    "sg:address":"5 Quebec Wharf, 14 Thomas Road",
    "sg:city":"London",
    "sg:classifiers":[
        {
            "category":"Professional",
            "subcategory":"Business Services",
            "type":"Services"
        }
    ],
    "sg:phone":"+44 20 7538 1583",
    "sg:postcode":"E14 7AF",
    "sg:province":"Greater London",
    "sg:tags":[
        "publishers'"
    ],
    "wof:name":"London International Publishing Co. Ltd.",
    "wof:placetype":"venue"
},
  "geometry": {"coordinates":[-0.0271700006,51.5145187378],"type":"Point"}
}