{
  "type": "Feature",
  "properties": {
    "addr:full":"2 Abbey Grn Chester Cheshire CH1 2JH",
    "addr:housenumber":"2",
    "addr:postcode":"ch1 2jh",
    "addr:street":"Abbey Grn",
    "iso:country":"GB",
    "sg:address":"2 Abbey Grn",
    "sg:city":"Chester",
    "sg:classifiers":[
        {
            "category":"Restaurant",
            "type":"Food & Drink"
        }
    ],
    "sg:postcode":"CH1 2JH",
    "sg:province":"Cheshire",
    "sg:tags":[
        "thai"
    ],
    "wof:name":"Jomtien's Thai Restaurant",
    "wof:placetype":"venue"
},
  "geometry": {"coordinates":[-2.893064,53.193577],"type":"Point"}
}