{
  "type": "Feature",
  "properties": {
    "iso:country":"GB",
    "sg:address":"The Mills Studio, 54 Bromells Road",
    "sg:city":"London",
    "sg:classifiers":[
        {
            "category":"Professional",
            "subcategory":"Art Services",
            "type":"Services"
        }
    ],
    "sg:postcode":"SW4 0BB",
    "sg:province":"Greater London",
    "sg:tags":[
        "picture",
        "restoration",
        "cleaning"
    ],
    "wof:name":"Jonathan Taylor",
    "wof:placetype":"venue"
},
  "geometry": {"coordinates":[-0.137952,51.462803],"type":"Point"}
}