{
  "type": "Feature",
  "properties": {
    "addr:full":"Hunt Lane Doncaster South Yorkshire DN5 9SE",
    "addr:postcode":"dn5 9se",
    "addr:street":"Hunt Lane",
    "iso:country":"GB",
    "sg:address":"Hunt Lane",
    "sg:city":"Doncaster",
    "sg:classifiers":[
        {
            "category":"Professional",
            "type":"Services"
        }
    ],
    "sg:phone":"+44 1302 788138",
    "sg:postcode":"DN5 9SE",
    "sg:province":"South Yorkshire",
    "sg:tags":[
        "writer"
    ],
    "wof:name":"Brandon Marketing",
    "wof:placetype":"venue"
},
  "geometry": {"coordinates":[-1.1442040205,53.5307540894],"type":"Point"}
}