{
  "type": "Feature",
  "properties": {
    "addr:full":"Bleak Hall Farm, Bleak Lane Ormskirk Lancashire L40 4BP",
    "addr:postcode":"l40 4bp",
    "addr:street":"Bleak Lane",
    "iso:country":"GB",
    "sg:address":"Bleak Hall Farm, Bleak Lane",
    "sg:city":"Ormskirk",
    "sg:classifiers":[
        {
            "category":"Home & Garden",
            "subcategory":"Home Furnishings",
            "type":"Retail Goods"
        }
    ],
    "sg:postcode":"L40 4BP",
    "sg:province":"Lancashire",
    "sg:tags":[
        "furnishers",
        "planner",
        "bedroom"
    ],
    "wof:name":"Steven Draper",
    "wof:placetype":"venue"
},
  "geometry": {"coordinates":[-2.8123700619,53.6007385254],"type":"Point"}
}