{
  "type": "Feature",
  "properties": {
    "addr:full":"Dorset Avenue Chelmsford Essex CM2 9UB",
    "addr:postcode":"cm2 9ub",
    "addr:street":"Dorset Avenue",
    "iso:country":"GB",
    "sg:address":"Dorset Avenue",
    "sg:city":"Chelmsford",
    "sg:classifiers":[
        {
            "category":"Education",
            "subcategory":"Dance Studio",
            "type":"Public Place"
        }
    ],
    "sg:phone":"+44 1245 476335",
    "sg:postcode":"CM2 9UB",
    "sg:province":"Essex",
    "sg:tags":[
        "school",
        "dancing"
    ],
    "wof:name":"Essex Dance Theatre",
    "wof:placetype":"venue"
},
  "geometry": {"coordinates":[0.4910849929,51.716594696],"type":"Point"}
}