{
  "type": "Feature",
  "properties": {
    "iso:country":"GB",
    "sg:address":"6-7 Forde Park",
    "sg:city":"Newton Abbot",
    "sg:classifiers":[
        {
            "category":"Health Services",
            "subcategory":"Nursing And Care Facility",
            "type":"Services"
        }
    ],
    "sg:phone":"+44 1626 354037",
    "sg:postcode":"TQ12 1DE",
    "sg:province":"Devon",
    "sg:tags":[
        "home"
    ],
    "wof:name":"Forde Park Nursing Home",
    "wof:placetype":"venue"
},
  "geometry": {"coordinates":[-3.598256,50.524242],"type":"Point"}
}