{
  "type": "Feature",
  "properties": {
    "iso:country":"GB",
    "sg:address":"Craven House, Emwell Street",
    "sg:city":"Warminster",
    "sg:classifiers":[
        {
            "category":"Shopping",
            "subcategory":"Clothing, Apparel, & Fashions",
            "type":"Retail Goods"
        }
    ],
    "sg:postcode":"BA12 8JA",
    "sg:province":"Somerset",
    "sg:tags":[
        "shop"
    ],
    "wof:name":"Josephines",
    "wof:placetype":"venue"
},
  "geometry": {"coordinates":[-2.187357,51.204708],"type":"Point"}
}