{
  "type": "Feature",
  "properties": {
    "iso:country":"GB",
    "sg:address":"97 Manor Way",
    "sg:city":"Ruislip",
    "sg:classifiers":[
        {
            "category":"Fast Food",
            "type":"Food & Drink"
        }
    ],
    "sg:postcode":"HA4 8HW",
    "sg:province":"Greater London",
    "sg:tags":[
        "away",
        "take"
    ],
    "wof:name":"Golden Pond (Ruislip) Ltd",
    "wof:placetype":"venue"
},
  "geometry": {"coordinates":[-0.415324986,51.5745697021],"type":"Point"}
}