{
  "type": "Feature",
  "properties": {
    "addr:full":"Longshaw St Warrington Cheshire WA5 5JA",
    "addr:postcode":"wa5 5ja",
    "addr:street":"St",
    "iso:country":"GB",
    "sg:address":"Longshaw St",
    "sg:city":"Warrington",
    "sg:classifiers":[
        {
            "category":"Organizations",
            "subcategory":"Membership Organization",
            "type":"Services"
        }
    ],
    "sg:phone":"+44 1925 632076",
    "sg:postcode":"WA5 5JA",
    "sg:province":"Cheshire",
    "sg:tags":[
        "club"
    ],
    "wof:name":"Warrington Transport Club",
    "wof:placetype":"venue"
},
  "geometry": {"coordinates":[-2.6063289642,53.4122047424],"type":"Point"}
}