{
  "type": "Feature",
  "properties": {
    "iso:country":"GB",
    "sg:address":"323/327 Railton Road, Herne Hill",
    "sg:city":"London",
    "sg:classifiers":[
        {
            "category":"Wholesale",
            "subcategory":"Groceries",
            "type":"Manufacturing & Wholesale Goods"
        }
    ],
    "sg:postcode":"SE24 0JN",
    "sg:province":"Greater London",
    "sg:tags":[
        "food",
        "supplier",
        "drink"
    ],
    "wof:name":"Quick Food Products Ltd.",
    "wof:placetype":"venue"
},
  "geometry": {"coordinates":[-0.1014309973,51.4524345398],"type":"Point"}
}