{
  "type": "Feature",
  "properties": {
    "iso:country":"GB",
    "sg:address":"Cambridge Road",
    "sg:city":"Grimsby",
    "sg:classifiers":[
        {
            "category":"Education",
            "subcategory":"School",
            "type":"Public Place"
        },
        {
            "category":"Government",
            "subcategory":"Office",
            "type":"Public Place"
        }
    ],
    "sg:phone":"+44 1472 507891",
    "sg:postcode":"DN34 5TD",
    "sg:province":"Lincolnshire",
    "sg:tags":[
        "local",
        "authority"
    ],
    "wof:name":"NORTH EAST LINCOLNSHIRE COUNCIL",
    "wof:placetype":"venue"
},
  "geometry": {"coordinates":[-0.113174,53.557274],"type":"Point"}
}