{
  "type": "Feature",
  "properties": {
    "addr:full":"C S Resources Team, 11 Willowdale Pl Aberdeen Aberdeen City AB24 5AQ",
    "addr:housenumber":"11",
    "addr:postcode":"ab24 5aq",
    "addr:street":"C;Willowdale Pl",
    "iso:country":"GB",
    "sg:address":"C S Resources Team, 11 Willowdale Pl",
    "sg:city":"Aberdeen",
    "sg:classifiers":[
        {
            "category":"Government",
            "subcategory":"Office",
            "type":"Public Place"
        }
    ],
    "sg:phone":"+44 1224 624317",
    "sg:postcode":"AB24 5AQ",
    "sg:province":"Aberdeen City",
    "sg:tags":[
        "local"
    ],
    "wof:name":"Aberdeen City Council",
    "wof:placetype":"venue"
},
  "geometry": {"coordinates":[-2.09548,57.153809],"type":"Point"}
}