{
  "type": "Feature",
  "properties": {
    "iso:country":"GB",
    "sg:address":"6 East Street",
    "sg:city":"Sudbury",
    "sg:classifiers":[
        {
            "category":"Shopping",
            "subcategory":"Music",
            "type":"Retail Goods"
        }
    ],
    "sg:postcode":"CO10 2TP",
    "sg:province":"Essex",
    "sg:tags":[
        "record",
        "tape",
        "cd"
    ],
    "wof:name":"Respins",
    "wof:placetype":"venue"
},
  "geometry": {"coordinates":[0.732716,52.040001],"type":"Point"}
}