{
  "type": "Feature",
  "properties": {
    "iso:country":"GB",
    "sg:address":"109 Fleet Street",
    "sg:city":"London",
    "sg:classifiers":[
        {
            "category":"Cafe",
            "type":"Food & Drink"
        }
    ],
    "sg:phone":"+44 20 7583 7778",
    "sg:postcode":"EC4A 2AF",
    "sg:province":"Greater London",
    "sg:tags":[
        "tea",
        "room"
    ],
    "wof:name":"Treats Sandwich Bar",
    "wof:placetype":"venue"
},
  "geometry": {"coordinates":[-0.1051039994,51.5142631531],"type":"Point"}
}