{
  "type": "Feature",
  "properties": {
    "iso:country":"GB",
    "sg:address":"7 Honiton Gro, Radcliffe",
    "sg:city":"Manchester",
    "sg:classifiers":[
        {
            "category":"Retail",
            "subcategory":"Driving School",
            "type":"Services"
        }
    ],
    "sg:phone":"+44 161 723 0092",
    "sg:postcode":"M26 3QF",
    "sg:province":"Greater Manchester",
    "wof:name":"Driving Auditions",
    "wof:placetype":"venue"
},
  "geometry": {"coordinates":[-2.3505549431,53.5679359436],"type":"Point"}
}