{
  "type": "Feature",
  "properties": {
    "iso:country":"GB",
    "sg:address":"The Runneymede Centre, Chertsey Road",
    "sg:city":"Addlestone",
    "sg:classifiers":[
        {
            "category":"Government",
            "subcategory":"Office",
            "type":"Public Place"
        }
    ],
    "sg:phone":"+44 1932 794020",
    "sg:postcode":"KT15 2EP",
    "sg:province":"Surrey",
    "sg:tags":[
        "education",
        "agency",
        "authority"
    ],
    "wof:name":"Surrey English Language Support Service",
    "wof:placetype":"venue"
},
  "geometry": {"coordinates":[-0.493514,51.371666],"type":"Point"}
}