{
  "type": "Feature",
  "properties": {
    "addr:full":"Brandy Carr Road, Kirkhamgate Wakefield West Yorkshire WF2 0RS",
    "addr:postcode":"wf2 0rs",
    "addr:street":"Carr Road Kirkhamgate",
    "iso:country":"GB",
    "sg:address":"Brandy Carr Road, Kirkhamgate",
    "sg:city":"Wakefield",
    "sg:classifiers":[
        {
            "category":"Education",
            "subcategory":"School",
            "type":"Public Place"
        },
        {
            "category":"Government",
            "subcategory":"Office",
            "type":"Public Place"
        }
    ],
    "sg:phone":"+44 1924 303735",
    "sg:postcode":"WF2 0RS",
    "sg:province":"West Yorkshire",
    "sg:tags":[
        "local",
        "authority"
    ],
    "wof:name":"Kirkhamgate Junior & Infants School",
    "wof:placetype":"venue"
},
  "geometry": {"coordinates":[-1.5357249975,53.7072525024],"type":"Point"}
}