{
  "type": "Feature",
  "properties": {
    "iso:country":"GB",
    "sg:address":"Elgin Works",
    "sg:city":"Dunfermline",
    "sg:classifiers":[
        {
            "category":"Building & Trades",
            "subcategory":"Construction",
            "type":"Services"
        }
    ],
    "sg:phone":"+44 1383 723196",
    "sg:postcode":"KY12 7SD",
    "sg:province":"Fife",
    "sg:tags":[
        "joinery"
    ],
    "wof:name":"John Y Russell",
    "wof:placetype":"venue"
},
  "geometry": {"coordinates":[-3.457674,56.064205],"type":"Point"}
}