{
  "type": "Feature",
  "properties": {
    "addr:full":"13 The Parade Luton Bedfordshire LU3 3DZ",
    "addr:housenumber":"13",
    "addr:postcode":"lu3 3dz",
    "addr:street":"The Parade",
    "iso:country":"GB",
    "sg:address":"13 The Parade",
    "sg:city":"Luton",
    "sg:classifiers":[
        {
            "category":"Food & Beverages",
            "subcategory":"Bakery",
            "type":"Retail Goods"
        }
    ],
    "sg:phone":"+44 1582 597701",
    "sg:postcode":"LU3 3DZ",
    "sg:province":"Bedfordshire",
    "sg:tags":[
        "baker"
    ],
    "wof:name":"The Bakers Oven",
    "wof:placetype":"venue"
},
  "geometry": {"coordinates":[-0.4530200064,51.9185714722],"type":"Point"}
}