{
  "type": "Feature",
  "properties": {
    "addr:full":"Mary Humphrey Hall, South Farm Road Worthing West Sussex BN14 7PN",
    "addr:postcode":"bn14 7pn",
    "addr:street":"South Farm Road",
    "iso:country":"GB",
    "sg:address":"Mary Humphrey Hall, South Farm Road",
    "sg:city":"Worthing",
    "sg:classifiers":[
        {
            "category":"Education",
            "subcategory":"Preschool",
            "type":"Public Place"
        }
    ],
    "sg:phone":"+44 1903 213054",
    "sg:postcode":"BN14 7PN",
    "sg:province":"West Sussex",
    "sg:tags":[
        "pre-school",
        "playgroups"
    ],
    "wof:name":"Offington Park Pre-School",
    "wof:placetype":"venue"
},
  "geometry": {"coordinates":[-0.3919200003,50.8284187317],"type":"Point"}
}