{
  "type": "Feature",
  "properties": {
    "addr:full":"Greenhill Court, Greenhill Lane Bingley West Yorkshire BD16 4AY",
    "addr:postcode":"bd16 4ay",
    "addr:street":"Greenhill Court Greenhill Lane",
    "iso:country":"GB",
    "sg:address":"Greenhill Court, Greenhill Lane",
    "sg:city":"Bingley",
    "sg:classifiers":[
        {
            "category":"Building & Trades",
            "subcategory":"Landscaping Services",
            "type":"Services"
        }
    ],
    "sg:phone":"+44 1274 510007",
    "sg:postcode":"BD16 4AY",
    "sg:province":"West Yorkshire",
    "sg:tags":[
        "horticultural"
    ],
    "wof:name":"Plantups Ltd.",
    "wof:placetype":"venue"
},
  "geometry": {"coordinates":[-1.836779,53.863373],"type":"Point"}
}