{
  "type": "Feature",
  "properties": {
    "addr:full":"Unit 1c, Cork Lane Leicester Leicestershire LE2 9JR",
    "addr:housenumber":"unit 1c",
    "addr:postcode":"le2 9jr",
    "addr:street":"Cork Lane",
    "iso:country":"GB",
    "sg:address":"Unit 1c, Cork Lane",
    "sg:city":"Leicester",
    "sg:classifiers":[
        {
            "category":"Manufacturing",
            "subcategory":"Petroleum Products",
            "type":"Manufacturing & Wholesale Goods"
        }
    ],
    "sg:postcode":"LE2 9JR",
    "sg:province":"Leicestershire",
    "sg:tags":[
        "double",
        "glazing"
    ],
    "wof:name":"Uniplan (1975) Ltd.",
    "wof:placetype":"venue"
},
  "geometry": {"coordinates":[-1.1671710014,52.5863304138],"type":"Point"}
}