{
  "type": "Feature",
  "properties": {
    "addr:full":"15 Trinity Street, Hanley Stoke-on-trent Staffordshire ST1 5PH",
    "addr:housenumber":"15",
    "addr:postcode":"staffordshire st1 5ph",
    "addr:street":"Trinity Street",
    "iso:country":"GB",
    "sg:address":"15 Trinity Street, Hanley",
    "sg:city":"Stoke-on-trent",
    "sg:classifiers":[
        {
            "category":"Banks & Credit Unions",
            "subcategory":"Investment Brokerage",
            "type":"Services"
        }
    ],
    "sg:phone":"+44 1782 252500",
    "sg:postcode":"ST1 5PH",
    "sg:province":"Staffordshire",
    "sg:tags":[
        "stockbroker"
    ],
    "wof:name":"P H Pope & Son",
    "wof:placetype":"venue"
},
  "geometry": {"coordinates":[-2.186759,53.025139],"type":"Point"}
}