{
  "type": "Feature",
  "properties": {
    "addr:full":"19-20 Hill Street Indoor Market, Hill Street Centre Middlesbrough North Yorkshire TS1 1SU",
    "addr:housenumber":"19-20",
    "addr:postcode":"ts1 1su",
    "addr:street":"Hill Street;Market Hill Street",
    "iso:country":"GB",
    "sg:address":"19-20 Hill Street Indoor Market, Hill Street Centre",
    "sg:city":"Middlesbrough",
    "sg:classifiers":[
        {
            "category":"Shopping",
            "subcategory":"Clothing, Apparel, & Fashions",
            "type":"Retail Goods"
        }
    ],
    "sg:postcode":"TS1 1SU",
    "sg:province":"North Yorkshire",
    "sg:tags":[
        "clothing"
    ],
    "wof:name":"Denrah Trading Co Ltd",
    "wof:placetype":"venue"
},
  "geometry": {"coordinates":[-1.2388590574,54.5767211914],"type":"Point"}
}