{
  "type": "Feature",
  "properties": {
    "addr:full":"3 Tower Pl King's Lynn Norfolk PE30 5DF",
    "addr:housenumber":"3",
    "addr:postcode":"pe30 5df",
    "addr:street":"Tower Pl",
    "iso:country":"GB",
    "sg:address":"3 Tower Pl",
    "sg:city":"King's Lynn",
    "sg:classifiers":[
        {
            "category":"Professional",
            "subcategory":"Computer Services",
            "type":"Services"
        }
    ],
    "sg:phone":"+44 1553 692415",
    "sg:postcode":"PE30 5DF",
    "sg:province":"Norfolk",
    "sg:tags":[
        "system",
        "software"
    ],
    "wof:name":"A.V.G. Systems",
    "wof:placetype":"venue"
},
  "geometry": {"coordinates":[0.39814,52.75169],"type":"Point"}
}