{
  "type": "Feature",
  "properties": {
    "iso:country":"GB",
    "sg:address":"122 Manor Road, Maltby",
    "sg:city":"Rotherham",
    "sg:classifiers":[
        {
            "category":"Shopping",
            "subcategory":"Bicycles & Sporting Goods",
            "type":"Retail Goods"
        }
    ],
    "sg:phone":"+44 1709 813089",
    "sg:postcode":"S66 7EW",
    "sg:province":"South Yorkshire",
    "sg:tags":[
        "shop",
        "cycle",
        "accessory"
    ],
    "wof:name":"Universal Cycle Centre",
    "wof:placetype":"venue"
},
  "geometry": {"coordinates":[-1.201284,53.428913],"type":"Point"}
}