{
  "type": "Feature",
  "properties": {
    "addr:full":"Unit B Durban Rd Bognor Regis West Sussex PO22 9QT",
    "addr:postcode":"po22 9qt",
    "addr:street":"Durban Rd",
    "iso:country":"GB",
    "sg:address":"Unit B Durban Rd",
    "sg:city":"Bognor Regis",
    "sg:classifiers":[
        {
            "category":"Home & Garden",
            "subcategory":"Hardware",
            "type":"Retail Goods"
        }
    ],
    "sg:phone":"+44 1243 870835",
    "sg:postcode":"PO22 9QT",
    "sg:province":"West Sussex",
    "sg:tags":[
        "device",
        "fixing",
        "fastener"
    ],
    "wof:name":"Design Assemblies Co Ltd",
    "wof:placetype":"venue"
},
  "geometry": {"coordinates":[-0.674373,50.799721],"type":"Point"}
}