{
  "type": "Feature",
  "properties": {
    "addr:full":"10 Duke Street Tavistock Devon PL19 0BB",
    "addr:housenumber":"10",
    "addr:postcode":"pl19 0bb",
    "addr:street":"Duke Street",
    "iso:country":"GB",
    "sg:address":"10 Duke Street",
    "sg:city":"Tavistock",
    "sg:classifiers":[
        {
            "category":"Food & Beverages",
            "subcategory":"Bakery",
            "type":"Retail Goods"
        }
    ],
    "sg:phone":"+44 1822 612886",
    "sg:postcode":"PL19 0BB",
    "sg:province":"Devon",
    "sg:tags":[
        "baker"
    ],
    "wof:name":"W T Warren & Son (Hayle) Ltd.",
    "wof:placetype":"venue"
},
  "geometry": {"coordinates":[-4.1437239647,50.5506057739],"type":"Point"}
}