{
  "type": "Feature",
  "properties": {
    "addr:full":"39 Stoney Bank Drive, Kiveton Park Sheffield Sheffield South Yorkshire S26 6SJ",
    "addr:housenumber":"39",
    "addr:postcode":"s26 6sj",
    "addr:street":"Stoney Bank Drive Kiveton Park",
    "iso:country":"GB",
    "sg:address":"39 Stoney Bank Drive, Kiveton Park Sheffield",
    "sg:city":"Sheffield",
    "sg:classifiers":[
        {
            "category":"Building & Trades",
            "subcategory":"Construction",
            "type":"Services"
        }
    ],
    "sg:phone":"+44 1909 772372",
    "sg:postcode":"S26 6SJ",
    "sg:province":"South Yorkshire",
    "sg:tags":[
        "ventilation",
        "contractor"
    ],
    "wof:name":"Dower Tekron",
    "wof:placetype":"venue"
},
  "geometry": {"coordinates":[-1.2600719929,53.3408889771],"type":"Point"}
}