{
  "type": "Feature",
  "properties": {
    "addr:full":"Jansa, Maldon Rd, Tiptree Colchester Essex CO5 0QA",
    "addr:postcode":"co5 0qa",
    "addr:street":"Jansa Maldon Rd",
    "iso:country":"GB",
    "sg:address":"Jansa, Maldon Rd, Tiptree",
    "sg:city":"Colchester",
    "sg:classifiers":[
        {
            "category":"Building & Trades",
            "subcategory":"Construction",
            "type":"Services"
        }
    ],
    "sg:phone":"+44 1621 893134",
    "sg:postcode":"CO5 0QA",
    "sg:province":"Essex",
    "sg:tags":[
        "builder"
    ],
    "wof:name":"J Martin",
    "wof:placetype":"venue"
},
  "geometry": {"coordinates":[0.7453340292,51.8164634705],"type":"Point"}
}