{
  "type": "Feature",
  "properties": {
    "addr:full":"2 Badgers Well Cottages, Launceston Rd, Bridestowe Okehampton Devon EX20 4NT",
    "addr:housenumber":"2",
    "addr:postcode":"ex20 4nt",
    "addr:street":"Badgers Well Cottages Launceston Rd",
    "iso:country":"GB",
    "sg:address":"2 Badgers Well Cottages, Launceston Rd, Bridestowe",
    "sg:city":"Okehampton",
    "sg:classifiers":[
        {
            "category":"Building & Trades",
            "subcategory":"Construction",
            "type":"Services"
        }
    ],
    "sg:phone":"+44 1837 861433",
    "sg:postcode":"EX20 4NT",
    "sg:province":"Devon",
    "sg:tags":[
        "decorator",
        "painter"
    ],
    "wof:name":"P.J Martin",
    "wof:placetype":"venue"
},
  "geometry": {"coordinates":[-4.1067137718,50.6866531372],"type":"Point"}
}