{
  "type": "Feature",
  "properties": {
    "addr:full":"79 Borough Road Middlesbrough North Yorkshire TS1 3AA",
    "addr:housenumber":"79",
    "addr:postcode":"ts1 3aa",
    "addr:street":"Borough Road",
    "iso:country":"GB",
    "sg:address":"79 Borough Road",
    "sg:city":"Middlesbrough",
    "sg:classifiers":[
        {
            "category":"Harbor",
            "type":"Transportation"
        }
    ],
    "sg:phone":"+44 1642 243129",
    "sg:postcode":"TS1 3AA",
    "sg:province":"North Yorkshire",
    "sg:tags":[
        "dock",
        "ports",
        "harbour"
    ],
    "wof:name":"River Tees Port Health Authority",
    "wof:placetype":"venue"
},
  "geometry": {"coordinates":[-1.2362990379,54.5728111267],"type":"Point"}
}