{
  "type": "Feature",
  "properties": {
    "addr:full":"1042 Scotswood Rd Newcastle-upon-tyne Tyne and Wear NE4 8NT",
    "addr:housenumber":"1042",
    "addr:postcode":"ne4 8nt",
    "addr:street":"Scotswood Rd",
    "iso:country":"GB",
    "sg:address":"1042 Scotswood Rd",
    "sg:city":"Newcastle-upon-tyne",
    "sg:classifiers":[
        {
            "category":"Retail",
            "subcategory":"Auto Repair",
            "type":"Services"
        }
    ],
    "sg:postcode":"NE4 8NT",
    "sg:province":"Tyne and Wear",
    "sg:tags":[
        "modification",
        "garage"
    ],
    "wof:name":"Bentinck Auto Co",
    "wof:placetype":"venue"
},
  "geometry": {"coordinates":[-1.663416028,54.9652404785],"type":"Point"}
}