{
  "type": "Feature",
  "properties": {
    "addr:full":"Burghcliffe Court Scarborough North Yorkshire YO11 2AQ",
    "addr:postcode":"yo11 2aq",
    "addr:street":"Court",
    "iso:country":"GB",
    "sg:address":"Burghcliffe Court",
    "sg:city":"Scarborough",
    "sg:classifiers":[
        {
            "category":"Shopping",
            "subcategory":"News",
            "type":"Retail Goods"
        }
    ],
    "sg:phone":"+44 1723 375907",
    "sg:postcode":"YO11 2AQ",
    "sg:province":"North Yorkshire",
    "sg:tags":[
        "newsagent"
    ],
    "wof:name":"Burghcliffe Court Management Co. Ltd.",
    "wof:placetype":"venue"
},
  "geometry": {"coordinates":[-0.39854,54.274849],"type":"Point"}
}