{
  "type": "Feature",
  "properties": {
    "iso:country":"GB",
    "sg:address":"Unit 16 Oakwood Industrial Park, Gatwick Road",
    "sg:city":"Crawley",
    "sg:classifiers":[
        {
            "category":"Retail",
            "subcategory":"Auto Rental",
            "type":"Services"
        }
    ],
    "sg:phone":"+44 1293 550555",
    "sg:postcode":"RH10 9AZ",
    "sg:province":"Surrey",
    "sg:tags":[
        "car"
    ],
    "wof:name":"Southern Self Drive Ltd.",
    "wof:placetype":"venue"
},
  "geometry": {"coordinates":[-0.184753,51.118458],"type":"Point"}
}