{
  "type": "Feature",
  "properties": {
    "addr:full":"76 Priorswood Road Taunton Somerset TA2 7QQ",
    "addr:housenumber":"76",
    "addr:postcode":"ta2 7qq",
    "addr:street":"Priorswood Road",
    "iso:country":"GB",
    "sg:address":"76 Priorswood Road",
    "sg:city":"Taunton",
    "sg:classifiers":[
        {
            "category":"Professional",
            "subcategory":"Art Services",
            "type":"Services"
        },
        {
            "category":"Building & Trades",
            "subcategory":"Construction",
            "type":"Services"
        }
    ],
    "sg:phone":"+44 1823 276230",
    "sg:postcode":"TA2 7QQ",
    "sg:province":"Somerset",
    "sg:tags":[
        "decorator",
        "painter"
    ],
    "wof:name":"D & A Decorators",
    "wof:placetype":"venue"
},
  "geometry": {"coordinates":[-3.095626,51.026608],"type":"Point"}
}