{
  "type": "Feature",
  "properties": {
    "iso:country":"GB",
    "sg:address":"199 Rose La",
    "sg:city":"Liverpool",
    "sg:classifiers":[
        {
            "category":"Fast Food",
            "type":"Food & Drink"
        }
    ],
    "sg:phone":"+44 151 724 5000",
    "sg:postcode":"L18 5EA",
    "sg:province":"Merseyside",
    "sg:tags":[
        "away",
        "take"
    ],
    "wof:name":"Rose Lane Chef",
    "wof:placetype":"venue"
},
  "geometry": {"coordinates":[-2.912995,53.380669],"type":"Point"}
}