{
  "type": "Feature",
  "properties": {
    "addr:full":"Unit 2g Leroy Ho, 436 Essex Rd Islington Greater London N1 3QP",
    "addr:housenumber":"2g;436",
    "addr:postcode":"n1 3qp",
    "addr:street":"Leroy Ho;Essex Rd",
    "iso:country":"GB",
    "sg:address":"Unit 2g Leroy Ho, 436 Essex Rd",
    "sg:city":"Islington",
    "sg:classifiers":[
        {
            "category":"Professional",
            "subcategory":"Lawyer & Legal Services",
            "type":"Services"
        }
    ],
    "sg:phone":"+44 20 7704 2040",
    "sg:postcode":"N1 3QP",
    "sg:province":"Greater London",
    "sg:tags":[
        "advice",
        "counselling"
    ],
    "wof:name":"GALOP",
    "wof:placetype":"venue"
},
  "geometry": {"coordinates":[-0.0871300027,51.5463294983],"type":"Point"}
}