{
  "type": "Feature",
  "properties": {
    "iso:country":"GB",
    "sg:address":"2-6 Park Rd",
    "sg:city":"Hampton",
    "sg:classifiers":[
        {
            "category":"Home & Garden",
            "subcategory":"Hardware",
            "type":"Retail Goods"
        }
    ],
    "sg:phone":"+44 20 8977 6122",
    "sg:postcode":"TW12 1HD",
    "sg:province":"Greater London",
    "sg:tags":[
        "paint",
        "coating"
    ],
    "wof:name":"Malcolm Bell Stove Enamelling",
    "wof:placetype":"venue"
},
  "geometry": {"coordinates":[-0.3545480072,51.4292640686],"type":"Point"}
}