{
  "type": "Feature",
  "properties": {
    "addr:full":"2 Bloomsbury Street London Greater London WC1B 3ST",
    "addr:housenumber":"2",
    "addr:postcode":"wc1b 3st",
    "addr:street":"Bloomsbury Street",
    "iso:country":"GB",
    "sg:address":"2 Bloomsbury Street",
    "sg:city":"London",
    "sg:classifiers":[
        {
            "category":"Real Estate",
            "subcategory":"Real Estate Agent",
            "type":"Services"
        }
    ],
    "sg:postcode":"WC1B 3ST",
    "sg:province":"Greater London",
    "wof:name":"I L C Properties Ltd",
    "wof:placetype":"venue"
},
  "geometry": {"coordinates":[-0.126882,51.517002],"type":"Point"}
}