{
  "type": "Feature",
  "properties": {
    "addr:full":"8-9 Bell Centre, Nottingham Street Melton Mowbray Leicestershire LE13 1PJ",
    "addr:housenumber":"8-9",
    "addr:postcode":"le13 1pj",
    "addr:street":"Bell Centre Nottingham Street",
    "iso:country":"GB",
    "sg:address":"8-9 Bell Centre, Nottingham Street",
    "sg:city":"Melton Mowbray",
    "sg:classifiers":[
        {
            "category":"Shopping",
            "subcategory":"Thrift Store",
            "type":"Retail Goods"
        }
    ],
    "sg:phone":"+44 1664 565355",
    "sg:postcode":"LE13 1PJ",
    "sg:province":"Leicestershire",
    "sg:tags":[
        "shop",
        "charity"
    ],
    "wof:name":"Salvation Army Charity Store",
    "wof:placetype":"venue"
},
  "geometry": {"coordinates":[-0.8876649737,52.7656517029],"type":"Point"}
}