{
  "type": "Feature",
  "properties": {
    "addr:full":"Conygree Farm, Aldsworth Cheltenham Gloucestershire GL54 3PW",
    "addr:postcode":"gl54 3pw",
    "iso:country":"GB",
    "sg:address":"Conygree Farm, Aldsworth",
    "sg:city":"Cheltenham",
    "sg:classifiers":[
        {
            "category":"Farming",
            "subcategory":"Farm",
            "type":"Manufacturing & Wholesale Goods"
        }
    ],
    "sg:phone":"+44 1451 844342",
    "sg:postcode":"GL54 3PW",
    "sg:province":"Gloucestershire",
    "sg:tags":[
        "mixed",
        "crop"
    ],
    "wof:name":"R M Parker",
    "wof:placetype":"venue"
},
  "geometry": {"coordinates":[-1.7750350237,51.7889976501],"type":"Point"}
}