{
  "type": "Feature",
  "properties": {
    "iso:country":"GB",
    "sg:address":"42 Newall Drive, Beeston",
    "sg:city":"Nottingham",
    "sg:classifiers":[
        {
            "category":"Personal",
            "type":"Services"
        }
    ],
    "sg:phone":"+44 115 946 9500",
    "sg:postcode":"NG9 6NX",
    "sg:province":"Nottinghamshire",
    "sg:tags":[
        "wedding"
    ],
    "wof:name":"R & A Video Filming",
    "wof:placetype":"venue"
},
  "geometry": {"coordinates":[-1.239637,52.908161],"type":"Point"}
}