{
  "type": "Feature",
  "properties": {
    "addr:full":"Railway Road, Brinscall Chorley Lancashire PR6 8RJ",
    "addr:postcode":"pr6 8rj",
    "addr:street":"Railway Road",
    "iso:country":"GB",
    "sg:address":"Railway Road, Brinscall",
    "sg:city":"Chorley",
    "sg:classifiers":[
        {
            "category":"Professional",
            "subcategory":"Testing Lab",
            "type":"Services"
        }
    ],
    "sg:phone":"+44 1254 830465",
    "sg:postcode":"PR6 8RJ",
    "sg:province":"Lancashire",
    "sg:tags":[
        "mot"
    ],
    "wof:name":"Brinscall M O T Centre",
    "wof:placetype":"venue"
},
  "geometry": {"coordinates":[-2.5692241192,53.6882705688],"type":"Point"}
}