{
  "type": "Feature",
  "properties": {
    "iso:country":"GB",
    "sg:address":"48 Swindon Rd",
    "sg:city":"Cheltenham",
    "sg:classifiers":[
        {
            "category":"Retail",
            "subcategory":"Auto Rental",
            "type":"Services"
        }
    ],
    "sg:phone":"+44 1242 514411",
    "sg:postcode":"GL50 4AS",
    "sg:province":"Gloucestershire",
    "sg:tags":[
        "car",
        "vehicle"
    ],
    "sg:website":"http://www.earc.com",
    "wof:name":"Enterprise Rent-A-Car UK Ltd",
    "wof:placetype":"venue"
},
  "geometry": {"coordinates":[-2.079282999,51.9048233032],"type":"Point"}
}