{
  "type": "Feature",
  "properties": {
    "addr:full":"Unit 1, 43-47 Eaton Road, Brynhyfrhyd Swansea Swansea SA5 9JX",
    "addr:housenumber":"unit 1",
    "addr:postcode":"43-47;sa5 9jx",
    "addr:street":"Eaton Road Brynhyfrhyd",
    "iso:country":"GB",
    "sg:address":"Unit 1, 43-47 Eaton Road, Brynhyfrhyd",
    "sg:city":"Swansea",
    "sg:classifiers":[
        {
            "category":"Education",
            "subcategory":"Music School",
            "type":"Public Place"
        }
    ],
    "sg:phone":"+44 1792 411155",
    "sg:postcode":"SA5 9JX",
    "sg:province":"Swansea",
    "sg:tags":[
        "conservatory"
    ],
    "wof:name":"Profile Window Systems",
    "wof:placetype":"venue"
},
  "geometry": {"coordinates":[-3.946146965,51.640838623],"type":"Point"}
}