{
  "type": "Feature",
  "properties": {
    "addr:full":"19-21 East Street Petworth West Sussex GU28 0AB",
    "addr:housenumber":"19-21",
    "addr:postcode":"gu28 0ab",
    "addr:street":"East Street",
    "iso:country":"GB",
    "sg:address":"19-21 East Street",
    "sg:city":"Petworth",
    "sg:classifiers":[
        {
            "category":"Shopping",
            "subcategory":"Antiques",
            "type":"Retail Goods"
        },
        {
            "category":"Shopping",
            "subcategory":"Used Merchandise",
            "type":"Retail Goods"
        }
    ],
    "sg:phone":"+44 1798 343408",
    "sg:postcode":"GU28 0AB",
    "sg:province":"West Sussex",
    "sg:tags":[
        "shop",
        "second-hand"
    ],
    "wof:name":"Elliott's Antiques & Fine Arts",
    "wof:placetype":"venue"
},
  "geometry": {"coordinates":[-0.608529,50.986931],"type":"Point"}
}