{
  "type": "Feature",
  "properties": {
    "iso:country":"GB",
    "sg:address":"Trekemletts Farm, Lezant",
    "sg:city":"Launceston",
    "sg:classifiers":[
        {
            "category":"Building & Trades",
            "subcategory":"Construction",
            "type":"Services"
        }
    ],
    "sg:phone":"+44 1566 775878",
    "sg:postcode":"PL15 9LZ",
    "sg:province":"Cornwall",
    "sg:tags":[
        "builder"
    ],
    "wof:name":"F G V Currah",
    "wof:placetype":"venue"
},
  "geometry": {"coordinates":[-4.335878849,50.6312599182],"type":"Point"}
}