{
  "type": "Feature",
  "properties": {
    "iso:country":"GB",
    "sg:address":"10-12 Huntly Square",
    "sg:city":"Dundee",
    "sg:classifiers":[
        {
            "category":"Fast Food",
            "type":"Food & Drink"
        }
    ],
    "sg:phone":"+44 1382 455361",
    "sg:postcode":"DD4 7SX",
    "sg:province":"Dundee City",
    "sg:tags":[
        "away",
        "meal",
        "outlet",
        "take"
    ],
    "wof:name":"Summer Palace",
    "wof:placetype":"venue"
},
  "geometry": {"coordinates":[-2.919381,56.475628],"type":"Point"}
}