{
  "type": "Feature",
  "properties": {
    "iso:country":"GB",
    "sg:address":"Victoria Street",
    "sg:city":"Newark",
    "sg:classifiers":[
        {
            "category":"Education",
            "subcategory":"School",
            "type":"Public Place"
        }
    ],
    "sg:phone":"+44 1636 680051",
    "sg:postcode":"NG24 4UT",
    "sg:province":"Nottinghamshire",
    "sg:tags":[
        "local",
        "authority"
    ],
    "wof:name":"Christ Church C of E Aided Infant School",
    "wof:placetype":"venue"
},
  "geometry": {"coordinates":[-0.8148040175,53.0726242065],"type":"Point"}
}