{
  "type": "Feature",
  "properties": {
    "addr:full":"50 The Cresent, Davenport Stockport Cheshire SK3 8SN",
    "addr:housenumber":"50",
    "addr:postcode":"sk3 8sn",
    "addr:street":"The Cresent",
    "iso:country":"GB",
    "sg:address":"50 The Cresent, Davenport",
    "sg:city":"Stockport",
    "sg:classifiers":[
        {
            "category":"Social Services",
            "subcategory":"Retirement Home",
            "type":"Services"
        }
    ],
    "sg:postcode":"SK3 8SN",
    "sg:province":"Cheshire",
    "sg:tags":[
        "residential",
        "care"
    ],
    "wof:name":"Wyebrook Rest Home",
    "wof:placetype":"venue"
},
  "geometry": {"coordinates":[-2.161516,53.408409],"type":"Point"}
}