{
  "type": "Feature",
  "properties": {
    "addr:full":"Unit 5, Boundary Road Newbury Berkshire RG14 5RR",
    "addr:housenumber":"unit 5",
    "addr:postcode":"rg14 5rr",
    "addr:street":"Boundary Road",
    "iso:country":"GB",
    "sg:address":"Unit 5, Boundary Road",
    "sg:city":"Newbury",
    "sg:classifiers":[
        {
            "category":"Building & Trades",
            "subcategory":"Equipment Rental",
            "type":"Services"
        }
    ],
    "sg:postcode":"RG14 5RR",
    "sg:province":"Berkshire",
    "sg:tags":[
        "hire",
        "centre"
    ],
    "wof:name":"Newbury Tools Ltd.",
    "wof:placetype":"venue"
},
  "geometry": {"coordinates":[-1.3138519526,51.3987846375],"type":"Point"}
}