{
  "type": "Feature",
  "properties": {
    "iso:country":"GB",
    "sg:address":"5 Haweswater Close, Green Park, Bridgeyate",
    "sg:city":"Bristol",
    "sg:classifiers":[
        {
            "category":"Taxi",
            "type":"Transportation"
        },
        {
            "category":"Military Area",
            "subcategory":"Air Force Base",
            "type":"Public Place"
        }
    ],
    "sg:phone":"+44 117 949 2249",
    "sg:postcode":"BS30 5XS",
    "sg:province":"Gloucestershire",
    "sg:tags":[
        "mini",
        "hire",
        "private",
        "cab"
    ],
    "wof:name":"Kings Chase Taxis",
    "wof:placetype":"venue"
},
  "geometry": {"coordinates":[-2.465819,51.454205],"type":"Point"}
}