{
  "type": "Feature",
  "properties": {
    "addr:full":"Trent Avenue, Willington Derby Derbyshire DE65 6DN",
    "addr:postcode":"de65 6dn",
    "addr:street":"Trent Avenue",
    "iso:country":"GB",
    "sg:address":"Trent Avenue, Willington",
    "sg:city":"Derby",
    "sg:classifiers":[
        {
            "category":"Education",
            "subcategory":"School",
            "type":"Public Place"
        }
    ],
    "sg:phone":"+44 1283 702156",
    "sg:postcode":"DE65 6DN",
    "sg:province":"Derbyshire",
    "sg:tags":[
        "local",
        "authority"
    ],
    "wof:name":"Willington Primary School",
    "wof:placetype":"venue"
},
  "geometry": {"coordinates":[-1.552045,52.852699],"type":"Point"}
}