{
  "type": "Feature",
  "properties": {
    "iso:country":"GB",
    "sg:address":"Ward Two, Penley Hospital",
    "sg:city":"Wrexham",
    "sg:classifiers":[
        {
            "category":"Organizations",
            "subcategory":"Non-profit Organization",
            "type":"Services"
        }
    ],
    "sg:postcode":"LL13 0LH",
    "sg:province":"Wrexham",
    "sg:tags":[
        "organisation",
        "voluntary",
        "charity"
    ],
    "wof:name":"Penley Rainbow Centre",
    "wof:placetype":"venue"
},
  "geometry": {"coordinates":[-2.867954,52.952995],"type":"Point"}
}