{
  "type": "Feature",
  "properties": {
    "addr:full":"247 Dentons Green Lane, Dentons Green St Helens Merseyside WA10 6SA",
    "addr:housenumber":"247",
    "addr:postcode":"wa10 6sa",
    "addr:street":"Dentons Green Lane Dentons Green",
    "iso:country":"GB",
    "sg:address":"247 Dentons Green Lane, Dentons Green",
    "sg:city":"St Helens",
    "sg:classifiers":[
        {
            "category":"Building & Trades",
            "subcategory":"Construction",
            "type":"Services"
        }
    ],
    "sg:phone":"+44 1744 757695",
    "sg:postcode":"WA10 6SA",
    "sg:province":"Merseyside",
    "sg:tags":[
        "decorator",
        "painter"
    ],
    "wof:name":"Gardecor",
    "wof:placetype":"venue"
},
  "geometry": {"coordinates":[-2.7573540211,53.4613723755],"type":"Point"}
}