{
  "type": "Feature",
  "properties": {
    "addr:full":"40 Station Road, Coleshill Birmingham Warwickshire B46 1JJ",
    "addr:housenumber":"40",
    "addr:postcode":"b46 1jj",
    "addr:street":"Station Road",
    "iso:country":"GB",
    "sg:address":"40 Station Road, Coleshill",
    "sg:city":"Birmingham",
    "sg:classifiers":[
        {
            "category":"Freight",
            "type":"Transportation"
        }
    ],
    "sg:phone":"+44 1675 466515",
    "sg:postcode":"B46 1JJ",
    "sg:province":"Warwickshire",
    "sg:tags":[
        "airfreight"
    ],
    "wof:name":"Airfreight Worldwide Ltd.",
    "wof:placetype":"venue"
},
  "geometry": {"coordinates":[-1.707464,52.509323],"type":"Point"}
}