{
  "type": "Feature",
  "properties": {
    "iso:country":"GB",
    "sg:address":"19 Brechin Place",
    "sg:city":"South Kensington",
    "sg:classifiers":[
        {
            "category":"Arts & Performance",
            "subcategory":"Art Gallery",
            "type":"Entertainment"
        }
    ],
    "sg:phone":"+44 20 7373 5499",
    "sg:postcode":"SW7 4QB",
    "sg:province":"Greater London",
    "wof:name":"Family Copies",
    "wof:placetype":"venue"
},
  "geometry": {"coordinates":[-0.181256,51.491241],"type":"Point"}
}