{
  "type": "Feature",
  "properties": {
    "addr:full":"95 Bidborough Ridge, Bidborough Tunbridge Wells East Sussex TN3 0XB",
    "addr:housenumber":"95",
    "addr:postcode":"tn3 0xb",
    "addr:street":"Bidborough Ridge",
    "iso:country":"GB",
    "sg:address":"95 Bidborough Ridge, Bidborough",
    "sg:city":"Tunbridge Wells",
    "sg:classifiers":[
        {
            "category":"Bars & Pubs",
            "type":"Food & Drink"
        }
    ],
    "sg:phone":"+44 1892 529870",
    "sg:postcode":"TN3 0XB",
    "sg:province":"East Sussex",
    "sg:tags":[
        "pubs",
        "inn"
    ],
    "wof:name":"Hare & Hounds",
    "wof:placetype":"venue"
},
  "geometry": {"coordinates":[0.2370609939,51.1694602966],"type":"Point"}
}