{
  "type": "Feature",
  "properties": {
    "addr:full":"128 Stirling Street Alva Clackmannanshire FK12 5EH",
    "addr:housenumber":"128",
    "addr:postcode":"fk12 5eh",
    "addr:street":"Stirling Street",
    "iso:country":"GB",
    "sg:address":"128 Stirling Street",
    "sg:city":"Alva",
    "sg:classifiers":[
        {
            "category":"Wholesale",
            "subcategory":"Meat",
            "type":"Manufacturing & Wholesale Goods"
        },
        {
            "category":"Food & Beverages",
            "subcategory":"Meat & Fish",
            "type":"Retail Goods"
        }
    ],
    "sg:phone":"+44 1259 769776",
    "sg:postcode":"FK12 5EH",
    "sg:province":"Clackmannanshire",
    "sg:tags":[
        "product",
        "butcher"
    ],
    "wof:name":"Macfarlane Meat Products Ltd",
    "wof:placetype":"venue"
},
  "geometry": {"coordinates":[-3.8023929596,56.1531143188],"type":"Point"}
}