{
  "type": "Feature",
  "properties": {
    "addr:full":"41 Vallis Way Frome Somerset BA11 3BA",
    "addr:housenumber":"41",
    "addr:postcode":"ba11 3ba",
    "addr:street":"Vallis Way",
    "iso:country":"GB",
    "sg:address":"41 Vallis Way",
    "sg:city":"Frome",
    "sg:classifiers":[
        {
            "category":"Manufacturing",
            "subcategory":"Signs",
            "type":"Manufacturing & Wholesale Goods"
        }
    ],
    "sg:phone":"+44 1373 451353",
    "sg:postcode":"BA11 3BA",
    "sg:province":"Somerset",
    "sg:tags":[
        "nameplate"
    ],
    "wof:name":"Compugraphic Design",
    "wof:placetype":"venue"
},
  "geometry": {"coordinates":[-2.328297,51.231167],"type":"Point"}
}