{
  "type": "Feature",
  "properties": {
    "addr:full":"2 Rotherhill Close Rotherham South Yorkshire S65 2DH",
    "addr:housenumber":"2",
    "addr:postcode":"s65 2dh",
    "addr:street":"Rotherhill Close",
    "iso:country":"GB",
    "sg:address":"2 Rotherhill Close",
    "sg:city":"Rotherham",
    "sg:classifiers":[
        {
            "category":"Home & Garden",
            "subcategory":"Home Furnishings",
            "type":"Retail Goods"
        },
        {
            "category":"Military Area",
            "subcategory":"Air Force Base",
            "type":"Public Place"
        }
    ],
    "sg:phone":"+44 1709 361975",
    "sg:postcode":"S65 2DH",
    "sg:province":"South Yorkshire",
    "sg:tags":[
        "blind",
        "curtain",
        "balloon",
        "novelty",
        "fitting"
    ],
    "wof:name":"Original Creations By Marion",
    "wof:placetype":"venue"
},
  "geometry": {"coordinates":[-1.336866,53.435287],"type":"Point"}
}