{
  "type": "Feature",
  "properties": {
    "iso:country":"GB",
    "sg:address":"37-38 Railway App, Shepherds Bush Market",
    "sg:city":"London",
    "sg:classifiers":[
        {
            "category":"Shopping",
            "subcategory":"Baby Store",
            "type":"Retail Goods"
        }
    ],
    "sg:phone":"+44 20 8743 4280",
    "sg:postcode":"W12 8DG",
    "sg:province":"Greater London",
    "sg:tags":[
        "babywear",
        "childrens"
    ],
    "wof:name":"G J Design",
    "wof:placetype":"venue"
},
  "geometry": {"coordinates":[-0.221426,51.503571],"type":"Point"}
}