{
  "type": "Feature",
  "properties": {
    "iso:country":"GB",
    "sg:address":"55 Broadstone Hall Road South",
    "sg:city":"Stockport",
    "sg:classifiers":[
        {
            "category":"Building & Trades",
            "subcategory":"Construction",
            "type":"Services"
        }
    ],
    "sg:postcode":"SK5 7DQ",
    "sg:province":"Cheshire",
    "sg:tags":[
        "tiling",
        "contractor"
    ],
    "wof:name":"Arden & Lester",
    "wof:placetype":"venue"
},
  "geometry": {"coordinates":[-2.1578149796,53.4296798706],"type":"Point"}
}