{
  "type": "Feature",
  "properties": {
    "addr:full":"Hall View, Hardstoft, Pilsley Chesterfield Derbyshire S45 8AH",
    "addr:postcode":"s45 8ah",
    "iso:country":"GB",
    "sg:address":"Hall View, Hardstoft, Pilsley",
    "sg:city":"Chesterfield",
    "sg:classifiers":[
        {
            "category":"Home & Garden",
            "subcategory":"Garden Supply",
            "type":"Retail Goods"
        }
    ],
    "sg:phone":"+44 1246 854268",
    "sg:postcode":"S45 8AH",
    "sg:province":"Derbyshire",
    "sg:tags":[
        "nursery",
        "centre"
    ],
    "wof:name":"The Herb Garden",
    "wof:placetype":"venue"
},
  "geometry": {"coordinates":[-1.3653190136,53.1553268433],"type":"Point"}
}