{
  "type": "Feature",
  "properties": {
    "addr:full":"46-48 Coatham Road Redcar North Yorkshire TS10 1RS",
    "addr:housenumber":"46-48",
    "addr:postcode":"ts10 1rs",
    "addr:street":"Coatham Road",
    "iso:country":"GB",
    "sg:address":"46-48 Coatham Road",
    "sg:city":"Redcar",
    "sg:classifiers":[
        {
            "category":"Professional",
            "subcategory":"Accounting & Tax Preparation",
            "type":"Services"
        }
    ],
    "sg:phone":"+44 1642 490228",
    "sg:postcode":"TS10 1RS",
    "sg:province":"North Yorkshire",
    "sg:tags":[
        "accountant"
    ],
    "wof:name":"Hiser Proudler & Co",
    "wof:placetype":"venue"
},
  "geometry": {"coordinates":[-1.0727039576,54.6177635193],"type":"Point"}
}