{
  "type": "Feature",
  "properties": {
    "iso:country":"GB",
    "sg:address":"Bridge Road, Stoke Bruerne",
    "sg:city":"Towcester",
    "sg:classifiers":[
        {
            "category":"Bars & Pubs",
            "type":"Food & Drink"
        }
    ],
    "sg:phone":"+44 1604 864988",
    "sg:postcode":"NN12 7SD",
    "sg:province":"Buckinghamshire",
    "sg:tags":[
        "pubs",
        "inn"
    ],
    "wof:name":"The Navigation Inn",
    "wof:placetype":"venue"
},
  "geometry": {"coordinates":[-0.9275,52.144119],"type":"Point"}
}