{
  "type": "Feature",
  "properties": {
    "addr:full":"29 High Street Fraserburgh Aberdeenshire AB43 9AP",
    "addr:housenumber":"29",
    "addr:postcode":"ab43 9ap",
    "addr:street":"High Street",
    "iso:country":"GB",
    "sg:address":"29 High Street",
    "sg:city":"Fraserburgh",
    "sg:classifiers":[
        {
            "category":"Shopping",
            "subcategory":"Shoes",
            "type":"Retail Goods"
        }
    ],
    "sg:phone":"+44 1346 518429",
    "sg:postcode":"AB43 9AP",
    "sg:province":"Aberdeenshire",
    "sg:tags":[
        "shop",
        "retailer",
        "footwear"
    ],
    "wof:name":"Andrew Begg Shoes",
    "wof:placetype":"venue"
},
  "geometry": {"coordinates":[-2.0068020821,57.6936645508],"type":"Point"}
}