{
  "type": "Feature",
  "properties": {
    "addr:full":"2 Queen Victoria Terrace London Greater London E1 9HA",
    "addr:housenumber":"2",
    "addr:postcode":"e1 9ha",
    "addr:street":"Queen",
    "iso:country":"GB",
    "sg:address":"2 Queen Victoria Terrace",
    "sg:city":"London",
    "sg:classifiers":[
        {
            "category":"Shopping",
            "subcategory":"Clothing, Apparel, & Fashions",
            "type":"Retail Goods"
        }
    ],
    "sg:postcode":"E1 9HA",
    "sg:province":"Greater London",
    "sg:tags":[
        "ladieswear"
    ],
    "wof:name":"Piklik",
    "wof:placetype":"venue"
},
  "geometry": {"coordinates":[-0.0897609964,51.5133590698],"type":"Point"}
}