{
  "type": "Feature",
  "properties": {
    "iso:country":"GB",
    "sg:address":"Off Harrowden La, Cardington",
    "sg:city":"Bedford",
    "sg:classifiers":[
        {
            "category":"Wholesale",
            "subcategory":"Books, Periodicals, & Newspapers",
            "type":"Manufacturing & Wholesale Goods"
        }
    ],
    "sg:phone":"+44 1234 211191",
    "sg:postcode":"MK44 3ST",
    "sg:province":"Bedfordshire",
    "sg:tags":[
        "publishing"
    ],
    "wof:name":"Department of Transport",
    "wof:placetype":"venue"
},
  "geometry": {"coordinates":[-0.415984,52.119404],"type":"Point"}
}