{
  "type": "Feature",
  "properties": {
    "addr:full":"Station Road, Nassington Peterborough Cambridgeshire PE8 6QB",
    "addr:postcode":"pe8 6qb",
    "addr:street":"Station Road",
    "iso:country":"GB",
    "sg:address":"Station Road, Nassington",
    "sg:city":"Peterborough",
    "sg:classifiers":[
        {
            "category":"Travel",
            "subcategory":"Hotels & Motels",
            "type":"Entertainment"
        }
    ],
    "sg:postcode":"PE8 6QB",
    "sg:province":"Cambridgeshire",
    "wof:name":"Queens Head Hotel",
    "wof:placetype":"venue"
},
  "geometry": {"coordinates":[-0.511962,52.565777],"type":"Point"}
}