{
  "type": "Feature",
  "properties": {
    "addr:full":"18 Princes Road Ashford Greater London TW15 2LT",
    "addr:housenumber":"18",
    "addr:postcode":"tw15 2lt",
    "addr:street":"Princes Road",
    "iso:country":"GB",
    "sg:address":"18 Princes Road",
    "sg:city":"Ashford",
    "sg:classifiers":[
        {
            "category":"Shopping",
            "subcategory":"Party Supplies",
            "type":"Retail Goods"
        }
    ],
    "sg:phone":"+44 1784 241817",
    "sg:postcode":"TW15 2LT",
    "sg:province":"Greater London",
    "sg:tags":[
        "marquees",
        "floor",
        "tent"
    ],
    "wof:name":"Marquee Mark",
    "wof:placetype":"venue"
},
  "geometry": {"coordinates":[-0.464306,51.431656],"type":"Point"}
}