{
  "type": "Feature",
  "properties": {
    "addr:full":"39 Friars Road Coventry West Midlands CV1 2LJ",
    "addr:housenumber":"39",
    "addr:postcode":"cv1 2lj",
    "addr:street":"Friars Road",
    "iso:country":"GB",
    "sg:address":"39 Friars Road",
    "sg:city":"Coventry",
    "sg:classifiers":[
        {
            "category":"Travel",
            "subcategory":"Hotels & Motels",
            "type":"Entertainment"
        }
    ],
    "sg:phone":"+44 24 7622 7822",
    "sg:postcode":"CV1 2LJ",
    "sg:province":"West Midlands",
    "sg:tags":[
        "house",
        "guest"
    ],
    "wof:name":"The Crest Guest House",
    "wof:placetype":"venue"
},
  "geometry": {"coordinates":[-1.51148,52.403492],"type":"Point"}
}