{
  "type": "Feature",
  "properties": {
    "addr:full":"4 Lancaster Rd Salford Greater Manchester M6 8AN",
    "addr:housenumber":"4",
    "addr:postcode":"m6 8an",
    "addr:street":"Lancaster Rd",
    "iso:country":"GB",
    "sg:address":"4 Lancaster Rd",
    "sg:city":"Salford",
    "sg:classifiers":[
        {
            "category":"Building & Trades",
            "subcategory":"Construction",
            "type":"Services"
        }
    ],
    "sg:phone":"+44 161 787 7899",
    "sg:postcode":"M6 8AN",
    "sg:province":"Greater Manchester",
    "sg:tags":[
        "builder"
    ],
    "wof:name":"T.W Higgin",
    "wof:placetype":"venue"
},
  "geometry": {"coordinates":[-2.319949,53.489693],"type":"Point"}
}