{
  "type": "Feature",
  "properties": {
    "addr:full":"19 Blackbrook Rd Taunton Somerset TA1 2UR",
    "addr:housenumber":"19",
    "addr:postcode":"ta1 2ur",
    "addr:street":"Blackbrook Rd",
    "iso:country":"GB",
    "sg:address":"19 Blackbrook Rd",
    "sg:city":"Taunton",
    "sg:classifiers":[
        {
            "category":"Professional",
            "subcategory":"Engineering",
            "type":"Services"
        }
    ],
    "sg:phone":"+44 1823 335547",
    "sg:postcode":"TA1 2UR",
    "sg:province":"Somerset",
    "sg:tags":[
        "contractor",
        "electrical",
        "engineer"
    ],
    "wof:name":"Gordon J Smith",
    "wof:placetype":"venue"
},
  "geometry": {"coordinates":[-3.0699899197,51.0233802795],"type":"Point"}
}