{
  "type": "Feature",
  "properties": {
    "iso:country":"GB",
    "sg:address":"49 Westgate End",
    "sg:city":"Wakefield",
    "sg:classifiers":[
        {
            "category":"Home & Garden",
            "subcategory":"Home Furnishings",
            "type":"Retail Goods"
        },
        {
            "category":"Manufacturing",
            "subcategory":"Textiles",
            "type":"Manufacturing & Wholesale Goods"
        }
    ],
    "sg:phone":"+44 1924 369990",
    "sg:postcode":"WF2 9RL",
    "sg:province":"West Yorkshire",
    "sg:tags":[
        "beds",
        "made-up",
        "bedding",
        "blanket",
        "bed"
    ],
    "wof:name":"Trade Price Beds",
    "wof:placetype":"venue"
},
  "geometry": {"coordinates":[-1.510187,53.679848],"type":"Point"}
}