{
  "type": "Feature",
  "properties": {
    "addr:full":"172 Park Hill Rd Birmingham West Midlands B17 9HD",
    "addr:housenumber":"172",
    "addr:postcode":"b17 9hd",
    "addr:street":"Park Hill Rd",
    "iso:country":"GB",
    "sg:address":"172 Park Hill Rd",
    "sg:city":"Birmingham",
    "sg:classifiers":[
        {
            "category":"Shopping",
            "subcategory":"Clothing, Apparel, & Fashions",
            "type":"Retail Goods"
        }
    ],
    "sg:phone":"+44 121 428 3927",
    "sg:postcode":"B17 9HD",
    "sg:province":"West Midlands",
    "sg:tags":[
        "shop"
    ],
    "wof:name":"Studio Isabella",
    "wof:placetype":"venue"
},
  "geometry": {"coordinates":[-1.946048975,52.4631195068],"type":"Point"}
}