{
  "type": "Feature",
  "properties": {
    "addr:full":"64 High Street, Rusthall Tunbridge Wells Kent TN4 8SD",
    "addr:housenumber":"64",
    "addr:postcode":"tn4 8sd",
    "addr:street":"High Street;Wells",
    "iso:country":"GB",
    "sg:address":"64 High Street, Rusthall",
    "sg:city":"Tunbridge Wells",
    "sg:classifiers":[
        {
            "category":"Banks & Credit Unions",
            "subcategory":"Financial Services",
            "type":"Services"
        }
    ],
    "sg:phone":"+44 1892 517111",
    "sg:postcode":"TN4 8SD",
    "sg:province":"Kent",
    "sg:tags":[
        "consultant"
    ],
    "wof:name":"Weald Financial Services",
    "wof:placetype":"venue"
},
  "geometry": {"coordinates":[0.26117,51.127869],"type":"Point"}
}