{
  "type": "Feature",
  "properties": {
    "addr:full":"Dunelm, Barling Road Southend-on-sea Essex SS3 0LX",
    "addr:postcode":"ss3 0lx",
    "addr:street":"Barling Road",
    "iso:country":"GB",
    "sg:address":"Dunelm, Barling Road",
    "sg:city":"Southend-on-sea",
    "sg:classifiers":[
        {
            "category":"Professional",
            "subcategory":"Management & Consulting",
            "type":"Services"
        }
    ],
    "sg:phone":"+44 1702 217777",
    "sg:postcode":"SS3 0LX",
    "sg:province":"Essex",
    "sg:tags":[
        "consultant",
        "business"
    ],
    "wof:name":"Gordex Ltd.",
    "wof:placetype":"venue"
},
  "geometry": {"coordinates":[0.75837,51.554592],"type":"Point"}
}