{
  "type": "Feature",
  "properties": {
    "iso:country":"GB",
    "sg:address":"48 Sincil Street",
    "sg:city":"Lincoln",
    "sg:classifiers":[
        {
            "category":"Shopping",
            "subcategory":"News",
            "type":"Retail Goods"
        }
    ],
    "sg:phone":"+44 1522 521983",
    "sg:postcode":"LN5 7ET",
    "sg:province":"Lincolnshire",
    "sg:tags":[
        "newsagent"
    ],
    "sg:website":"http://www.martinmccoll.co.uk",
    "wof:name":"Martin The Newsagent Ltd",
    "wof:placetype":"venue"
},
  "geometry": {"coordinates":[-0.540152,53.222157],"type":"Point"}
}