{
  "type": "Feature",
  "properties": {
    "iso:country":"GB",
    "sg:address":"247 Godiva Road",
    "sg:city":"Leominster",
    "sg:classifiers":[
        {
            "category":"Home & Garden",
            "subcategory":"Household Appliances",
            "type":"Retail Goods"
        },
        {
            "category":"Professional",
            "subcategory":"Art Services",
            "type":"Services"
        }
    ],
    "sg:phone":"+44 1568 611041",
    "sg:postcode":"HR6 8TB",
    "sg:province":"Herefordshire",
    "sg:tags":[
        "consultant",
        "equipment",
        "design",
        "air conditioning"
    ],
    "wof:name":"Reflectaire Ltd.",
    "wof:placetype":"venue"
},
  "geometry": {"coordinates":[-2.7657699585,52.2252464294],"type":"Point"}
}