{
  "type": "Feature",
  "properties": {
    "addr:full":"2e Lanark Road Edinburgh City of Edinburgh EH14 1TQ",
    "addr:postcode":"eh14 1tq",
    "addr:street":"2E Lanark Road",
    "iso:country":"GB",
    "sg:address":"2e Lanark Road",
    "sg:city":"Edinburgh",
    "sg:classifiers":[
        {
            "category":"Retail",
            "subcategory":"Auto Repair",
            "type":"Services"
        }
    ],
    "sg:phone":"+44 131 443 8537",
    "sg:postcode":"EH14 1TQ",
    "sg:province":"City of Edinburgh",
    "sg:tags":[
        "body",
        "car",
        "repairer"
    ],
    "wof:name":"Browns Body Services",
    "wof:placetype":"venue"
},
  "geometry": {"coordinates":[-3.248426,55.923336],"type":"Point"}
}