{
  "type": "Feature",
  "properties": {
    "iso:country":"GB",
    "sg:address":"9 South Parade",
    "sg:city":"Doncaster",
    "sg:classifiers":[
        {
            "category":"Building & Trades",
            "subcategory":"Construction",
            "type":"Services"
        }
    ],
    "sg:postcode":"DN1 2DY",
    "sg:province":"South Yorkshire",
    "sg:tags":[
        "builder"
    ],
    "wof:name":"Suresimple Limited",
    "wof:placetype":"venue"
},
  "geometry": {"coordinates":[-1.125818,53.521008],"type":"Point"}
}