{
  "type": "Feature",
  "properties": {
    "addr:full":"62 Grassholme, Wilnecote Tamworth Staffordshire B77 4BZ",
    "addr:housenumber":"62",
    "addr:postcode":"b77 4bz",
    "addr:street":"Grassholme Wilnecote",
    "iso:country":"GB",
    "sg:address":"62 Grassholme, Wilnecote",
    "sg:city":"Tamworth",
    "sg:classifiers":[
        {
            "category":"Shopping",
            "subcategory":"Computers & Home Electronics",
            "type":"Retail Goods"
        },
        {
            "category":"Building & Trades",
            "subcategory":"Electrical",
            "type":"Services"
        }
    ],
    "sg:phone":"+44 1827 331381",
    "sg:postcode":"B77 4BZ",
    "sg:province":"Staffordshire",
    "sg:tags":[
        "electrician",
        "contractor"
    ],
    "wof:name":"Dearne Electrical",
    "wof:placetype":"venue"
},
  "geometry": {"coordinates":[-1.6560219526,52.6146392822],"type":"Point"}
}