{
  "type": "Feature",
  "properties": {
    "addr:full":"58 High Street Fareham Hampshire PO16 7BG",
    "addr:housenumber":"58",
    "addr:postcode":"po16 7bg",
    "addr:street":"High Street",
    "iso:country":"GB",
    "sg:address":"58 High Street",
    "sg:city":"Fareham",
    "sg:classifiers":[
        {
            "category":"Shopping",
            "subcategory":"Antiques",
            "type":"Retail Goods"
        }
    ],
    "sg:phone":"+44 1329 234964",
    "sg:postcode":"PO16 7BG",
    "sg:province":"Hampshire",
    "wof:name":"The Elizabethan Antique Shop",
    "wof:placetype":"venue"
},
  "geometry": {"coordinates":[-1.1735830307,50.8534736633],"type":"Point"}
}