{
  "type": "Feature",
  "properties": {
    "iso:country":"GB",
    "sg:address":"The Old Laundry, Hawkwood Lane",
    "sg:city":"Chislehurst",
    "sg:classifiers":[
        {
            "category":"Professional",
            "subcategory":"Engineering",
            "type":"Services"
        }
    ],
    "sg:phone":"+44 20 8295 0033",
    "sg:postcode":"BR7 5PW",
    "sg:province":"Kent",
    "sg:tags":[
        "engineer",
        "structural"
    ],
    "wof:name":"K S P Building Design Consultants",
    "wof:placetype":"venue"
},
  "geometry": {"coordinates":[0.0663900003,51.4192848206],"type":"Point"}
}