{
  "type": "Feature",
  "properties": {
    "iso:country":"GB",
    "sg:address":"5 Green Street Lane",
    "sg:city":"Ayr",
    "sg:classifiers":[
        {
            "category":"Building & Trades",
            "subcategory":"Construction",
            "type":"Services"
        }
    ],
    "sg:phone":"+44 1292 265448",
    "sg:postcode":"KA8 8BL",
    "sg:province":"South Ayrshire",
    "sg:tags":[
        "builder"
    ],
    "wof:name":"R H Neil & Son",
    "wof:placetype":"venue"
},
  "geometry": {"coordinates":[-4.631913,55.469177],"type":"Point"}
}