{
  "type": "Feature",
  "properties": {
    "iso:country":"GB",
    "sg:address":"The Hay Pollock Centre,, Josselin Rd,",
    "sg:city":"Basildon",
    "sg:classifiers":[
        {
            "category":"Professional",
            "subcategory":"Management & Consulting",
            "type":"Services"
        },
        {
            "category":"Home & Garden",
            "subcategory":"Kitchen Supply",
            "type":"Retail Goods"
        }
    ],
    "sg:postcode":"SS13 1PU",
    "sg:province":"Essex",
    "sg:tags":[
        "equipment",
        "marketing",
        "brewer",
        "consultant"
    ],
    "wof:name":"Raycom Marketing Services Ltd",
    "wof:placetype":"venue"
},
  "geometry": {"coordinates":[0.517260015,51.5852890015],"type":"Point"}
}