{
  "type": "Feature",
  "properties": {
    "iso:country":"GB",
    "sg:address":"41 Mardley Hill",
    "sg:city":"Welwyn",
    "sg:classifiers":[
        {
            "category":"Professional",
            "type":"Services"
        }
    ],
    "sg:phone":"+44 1438 712322",
    "sg:postcode":"AL6 0TT",
    "sg:province":"Hertfordshire",
    "sg:tags":[
        "caterer"
    ],
    "wof:name":"Dolphins Catering & Entertainments",
    "wof:placetype":"venue"
},
  "geometry": {"coordinates":[-0.1855340004,51.847366333],"type":"Point"}
}