{
  "type": "Feature",
  "properties": {
    "addr:full":"Unit 5 Eldon Way Biggleswade Bedfordshire SG18 8NH",
    "addr:housenumber":"unit 5",
    "addr:postcode":"sg18 8nh",
    "addr:street":"Eldon Way",
    "iso:country":"GB",
    "sg:address":"Unit 5 Eldon Way",
    "sg:city":"Biggleswade",
    "sg:postcode":"SG18 8NH",
    "sg:province":"Bedfordshire",
    "wof:name":"Acrylic House Ltd (The)",
    "wof:placetype":"venue"
},
  "geometry": {"coordinates":[-0.2631790042,52.0781860352],"type":"Point"}
}