{
  "type": "Feature",
  "properties": {
    "iso:country":"GB",
    "sg:address":"4 Gremista Industrial Estate Gremista",
    "sg:city":"Shetland",
    "sg:classifiers":[
        {
            "category":"Retail",
            "subcategory":"Auto Repair",
            "type":"Services"
        }
    ],
    "sg:phone":"+44 1595 695202",
    "sg:postcode":"ZE1 0PX",
    "sg:province":"Shetland Islands",
    "sg:tags":[
        "modification",
        "garage"
    ],
    "wof:name":"Jim's Garage (Shetland) Ltd.",
    "wof:placetype":"venue"
},
  "geometry": {"coordinates":[-1.170289,60.144829],"type":"Point"}
}