{
  "type": "Feature",
  "properties": {
    "addr:full":"72 Water Lane Wilmslow Cheshire SK9 5BB",
    "addr:housenumber":"72",
    "addr:postcode":"sk9 5bb",
    "addr:street":"Water Lane",
    "iso:country":"GB",
    "sg:address":"72 Water Lane",
    "sg:city":"Wilmslow",
    "sg:classifiers":[
        {
            "category":"Personal",
            "subcategory":"Beauty Salon",
            "type":"Services"
        }
    ],
    "sg:phone":"+44 1625 525415",
    "sg:postcode":"SK9 5BB",
    "sg:province":"Cheshire",
    "sg:tags":[
        "unisex",
        "hairdresser"
    ],
    "wof:name":"Headstart",
    "wof:placetype":"venue"
},
  "geometry": {"coordinates":[-2.236413,53.32658],"type":"Point"}
}