{
  "type": "Feature",
  "properties": {
    "addr:full":"187 Bath Road Cheltenham Gloucestershire GL53 7LY",
    "addr:housenumber":"187",
    "addr:postcode":"gl53 7ly",
    "addr:street":"Bath Road",
    "iso:country":"GB",
    "sg:address":"187 Bath Road",
    "sg:city":"Cheltenham",
    "sg:classifiers":[
        {
            "category":"Personal",
            "subcategory":"Beauty Salon",
            "type":"Services"
        },
        {
            "category":"Personal",
            "subcategory":"Barber",
            "type":"Services"
        }
    ],
    "sg:phone":"+44 1242 524746",
    "sg:postcode":"GL53 7LY",
    "sg:province":"Gloucestershire",
    "sg:tags":[
        "unisex",
        "lady",
        "hairdresser"
    ],
    "wof:name":"Beauty Box",
    "wof:placetype":"venue"
},
  "geometry": {"coordinates":[-2.0799059868,51.8887252808],"type":"Point"}
}