{
  "type": "Feature",
  "properties": {
    "addr:full":"Wellington Rd Ely Cambridgeshire CB6 3NP",
    "addr:postcode":"cb6 3np",
    "addr:street":"Wellington Rd",
    "iso:country":"GB",
    "sg:address":"Wellington Rd",
    "sg:city":"Ely",
    "sg:classifiers":[
        {
            "category":"Structure",
            "subcategory":"Warehouse",
            "type":"Public Place"
        }
    ],
    "sg:phone":"+44 1353 669411",
    "sg:postcode":"CB6 3NP",
    "sg:province":"Cambridgeshire",
    "wof:name":"Lockwoods Distribution Ltd",
    "wof:placetype":"venue"
},
  "geometry": {"coordinates":[0.3056200147,52.4578514099],"type":"Point"}
}