{
  "type": "Feature",
  "properties": {
    "iso:country":"GB",
    "sg:address":"134 North St",
    "sg:city":"Brighton",
    "sg:classifiers":[
        {
            "category":"Community Center",
            "type":"Public Place"
        }
    ],
    "sg:phone":"+44 1273 327568",
    "sg:postcode":"BN1 1RG",
    "sg:province":"East Sussex",
    "sg:tags":[
        "centre",
        "entertainment"
    ],
    "wof:name":"Hot Shots & Jumping Jacks",
    "wof:placetype":"venue"
},
  "geometry": {"coordinates":[-0.1422770023,50.8235282898],"type":"Point"}
}