{
  "type": "Feature",
  "properties": {
    "addr:full":"428 Green Street London Greater London E13 9JJ",
    "addr:housenumber":"428",
    "addr:postcode":"e13 9jj",
    "addr:street":"Green Street",
    "iso:country":"GB",
    "sg:address":"428 Green Street",
    "sg:city":"London",
    "sg:classifiers":[
        {
            "category":"Health Services",
            "subcategory":"Optometrist",
            "type":"Services"
        }
    ],
    "sg:postcode":"E13 9JJ",
    "sg:province":"Greater London",
    "sg:tags":[
        "optician"
    ],
    "wof:name":"Niel Gordon Opticians",
    "wof:placetype":"venue"
},
  "geometry": {"coordinates":[0.035774,51.534054],"type":"Point"}
}