{
  "type": "Feature",
  "properties": {
    "iso:country":"GB",
    "sg:address":"23 Green La",
    "sg:city":"Walton On Thames",
    "sg:classifiers":[
        {
            "category":"Autos & Motor Vehicles",
            "subcategory":"Motorcycle Sales",
            "type":"Retail Goods"
        }
    ],
    "sg:phone":"+44 1932 229217",
    "sg:postcode":"KT12 5HD",
    "sg:province":"Surrey",
    "sg:tags":[
        "chauffeur",
        "driven",
        "car"
    ],
    "wof:name":"Hunter Car Service",
    "wof:placetype":"venue"
},
  "geometry": {"coordinates":[-0.406603,51.366825],"type":"Point"}
}