{
  "type": "Feature",
  "properties": {
    "addr:full":"76 Overbury Avenue Beckenham Kent BR3 6PY",
    "addr:housenumber":"76",
    "addr:postcode":"br3 6py",
    "addr:street":"Overbury Avenue",
    "iso:country":"GB",
    "sg:address":"76 Overbury Avenue",
    "sg:city":"Beckenham",
    "sg:classifiers":[
        {
            "category":"Communications",
            "type":"Services"
        }
    ],
    "sg:postcode":"BR3 6PY",
    "sg:province":"Kent",
    "sg:tags":[
        "data",
        "network"
    ],
    "wof:name":"Comflex Data Services Ltd",
    "wof:placetype":"venue"
},
  "geometry": {"coordinates":[-0.0140850004,51.4031448364],"type":"Point"}
}