{
  "type": "Feature",
  "properties": {
    "iso:country":"GB",
    "sg:address":"6 Port Close, Bearsted",
    "sg:city":"Maidstone",
    "sg:classifiers":[
        {
            "category":"Wholesale",
            "subcategory":"Office Equipment",
            "type":"Manufacturing & Wholesale Goods"
        }
    ],
    "sg:postcode":"ME14 4PX",
    "sg:province":"Kent",
    "sg:tags":[
        "partition",
        "cubicle"
    ],
    "wof:name":"Intercon Partitions & Ceilings",
    "wof:placetype":"venue"
},
  "geometry": {"coordinates":[0.5655909777,51.2773704529],"type":"Point"}
}