{
  "type": "Feature",
  "properties": {
    "iso:country":"GB",
    "sg:address":"1 Steam Mill La",
    "sg:city":"Great Yarmouth",
    "sg:classifiers":[
        {
            "category":"Communications",
            "subcategory":"Film & Video Production",
            "type":"Services"
        }
    ],
    "sg:phone":"+44 1493 650996",
    "sg:postcode":"NR31 0HP",
    "sg:province":"Norfolk",
    "sg:tags":[
        "waterjet",
        "cutting"
    ],
    "wof:name":"Circle Hire & Technical Services Ltd",
    "wof:placetype":"venue"
},
  "geometry": {"coordinates":[1.7205970287,52.6068763733],"type":"Point"}
}