{
  "type": "Feature",
  "properties": {
    "addr:full":"20 Main Street, Stewarton Kilmarnock East Ayrshire KA3 5AE",
    "addr:housenumber":"20",
    "addr:postcode":"ka3 5ae",
    "addr:street":"Main Street",
    "iso:country":"GB",
    "sg:address":"20 Main Street, Stewarton",
    "sg:city":"Kilmarnock",
    "sg:classifiers":[
        {
            "category":"Health Services",
            "subcategory":"Optometrist",
            "type":"Services"
        },
        {
            "category":"Social Services",
            "subcategory":"Child Care",
            "type":"Services"
        },
        {
            "category":"Communications",
            "type":"Services"
        }
    ],
    "sg:phone":"+44 1560 485151",
    "sg:postcode":"KA3 5AE",
    "sg:province":"East Ayrshire",
    "sg:tags":[
        "tv",
        "procurement",
        "video",
        "optician",
        "radio"
    ],
    "wof:name":"Provision Ltd.",
    "wof:placetype":"venue"
},
  "geometry": {"coordinates":[-4.5149049759,55.6807632446],"type":"Point"}
}