{
  "type": "Feature",
  "properties": {
    "addr:full":"23 Twigg St Stoke On Trent Staffordshire ST2 0JE",
    "addr:housenumber":"23",
    "addr:postcode":"st2 0je",
    "addr:street":"Twigg St",
    "iso:country":"GB",
    "sg:address":"23 Twigg St",
    "sg:city":"Stoke On Trent",
    "sg:classifiers":[
        {
            "category":"Food & Beverages",
            "subcategory":"Meat & Fish",
            "type":"Retail Goods"
        }
    ],
    "sg:phone":"+44 1782 272858",
    "sg:postcode":"ST2 0JE",
    "sg:province":"Staffordshire",
    "sg:tags":[
        "chip"
    ],
    "wof:name":"New Fry",
    "wof:placetype":"venue"
},
  "geometry": {"coordinates":[-2.1399250031,53.0196075439],"type":"Point"}
}