{
  "type": "Feature",
  "properties": {
    "iso:country":"GB",
    "sg:address":"42 Bengal Road",
    "sg:city":"Bournemouth",
    "sg:classifiers":[
        {
            "category":"Shopping",
            "subcategory":"Pharmacy",
            "type":"Retail Goods"
        }
    ],
    "sg:postcode":"BH9 2NF",
    "sg:province":"Dorset",
    "sg:tags":[
        "medicine",
        "therapy"
    ],
    "wof:name":"L J Dengate",
    "wof:placetype":"venue"
},
  "geometry": {"coordinates":[-1.884936,50.746078],"type":"Point"}
}