{
  "type": "Feature",
  "properties": {
    "addr:full":"77a Station Rd Chesterfield Derbyshire S42 5JJ",
    "addr:housenumber":"77a",
    "addr:postcode":"s42 5jj",
    "addr:street":"Station Rd",
    "iso:country":"GB",
    "sg:address":"77a Station Rd",
    "sg:city":"Chesterfield",
    "sg:classifiers":[
        {
            "category":"Professional",
            "subcategory":"Management & Consulting",
            "type":"Services"
        }
    ],
    "sg:phone":"+44 1246 855601",
    "sg:postcode":"S42 5JJ",
    "sg:province":"Derbyshire",
    "sg:tags":[
        "conservation"
    ],
    "wof:name":"Chesterfield Canal Society The",
    "wof:placetype":"venue"
},
  "geometry": {"coordinates":[-1.396491,53.179314],"type":"Point"}
}