{
  "type": "Feature",
  "properties": {
    "iso:country":"GB",
    "sg:address":"26 Romney Rd",
    "sg:city":"Ipswich",
    "sg:classifiers":[
        {
            "category":"Building & Trades",
            "subcategory":"Construction",
            "type":"Services"
        }
    ],
    "sg:postcode":"IP3 0JU",
    "sg:province":"Suffolk",
    "sg:tags":[
        "door",
        "replacement"
    ],
    "wof:name":"Dorwin's",
    "wof:placetype":"venue"
},
  "geometry": {"coordinates":[1.177889,52.033962],"type":"Point"}
}