{
  "type": "Feature",
  "properties": {
    "addr:full":"Channel View Farm, Marcross Llantwit Major The Vale of Glamorgan CF61 1ZG",
    "addr:postcode":"cf61 1zg",
    "addr:street":"Channel View;Vale",
    "iso:country":"GB",
    "sg:address":"Channel View Farm, Marcross",
    "sg:city":"Llantwit Major",
    "sg:classifiers":[
        {
            "category":"Farming",
            "subcategory":"Livestock Farm",
            "type":"Manufacturing & Wholesale Goods"
        },
        {
            "category":"Farming",
            "subcategory":"Farm",
            "type":"Manufacturing & Wholesale Goods"
        }
    ],
    "sg:phone":"+44 1656 890607",
    "sg:postcode":"CF61 1ZG",
    "sg:province":"The Vale of Glamorgan",
    "sg:tags":[
        "mixed",
        "crop",
        "others"
    ],
    "wof:name":"W J Liscombe & Son",
    "wof:placetype":"venue"
},
  "geometry": {"coordinates":[-3.488492012,51.4101600647],"type":"Point"}
}