{
  "type": "Feature",
  "properties": {
    "iso:country":"GB",
    "sg:address":"Potterston Farm, Dalrymple",
    "sg:city":"Ayr",
    "sg:classifiers":[
        {
            "category":"Farming",
            "subcategory":"Livestock Farm",
            "type":"Manufacturing & Wholesale Goods"
        },
        {
            "category":"Farming",
            "subcategory":"Farm",
            "type":"Manufacturing & Wholesale Goods"
        }
    ],
    "sg:postcode":"KA6 6AN",
    "sg:province":"East Ayrshire",
    "sg:tags":[
        "mixed",
        "crop",
        "others"
    ],
    "wof:name":"J & R KERR",
    "wof:placetype":"venue"
},
  "geometry": {"coordinates":[-4.589121,55.398247],"type":"Point"}
}