{
  "type": "Feature",
  "properties": {
    "addr:full":"57a Jameson Road Birmingham West Midlands B6 7SJ",
    "addr:housenumber":"57a",
    "addr:postcode":"b6 7sj",
    "addr:street":"Jameson Road",
    "iso:country":"GB",
    "sg:address":"57a Jameson Road",
    "sg:city":"Birmingham",
    "sg:classifiers":[
        {
            "category":"Professional",
            "subcategory":"Engineering",
            "type":"Services"
        }
    ],
    "sg:phone":"+44 121 328 0539",
    "sg:postcode":"B6 7SJ",
    "sg:province":"West Midlands",
    "wof:name":"P J S Engineering Ltd.",
    "wof:placetype":"venue"
},
  "geometry": {"coordinates":[-1.8640090227,52.5065307617],"type":"Point"}
}