{
  "type": "Feature",
  "properties": {
    "iso:country":"GB",
    "sg:address":"144 West Regent St",
    "sg:city":"Glasgow",
    "sg:classifiers":[
        {
            "category":"Museum",
            "subcategory":"Art Museum",
            "type":"Entertainment"
        }
    ],
    "sg:phone":"+44 141 204 0708",
    "sg:postcode":"G2 2RQ",
    "sg:province":"Glasgow City",
    "sg:tags":[
        "gallery"
    ],
    "wof:name":"R Duncan Miller Fine Art",
    "wof:placetype":"venue"
},
  "geometry": {"coordinates":[-4.2602257729,55.8636779785],"type":"Point"}
}