{
  "type": "Feature",
  "properties": {
    "addr:full":"109 Annesley Road, Hucknall Nottingham Nottinghamshire NG15 7DR",
    "addr:housenumber":"109",
    "addr:postcode":"ng15 7dr",
    "addr:street":"Annesley Road",
    "iso:country":"GB",
    "sg:address":"109 Annesley Road, Hucknall",
    "sg:city":"Nottingham",
    "sg:classifiers":[
        {
            "category":"Home & Garden",
            "subcategory":"Home Furnishings",
            "type":"Retail Goods"
        }
    ],
    "sg:postcode":"NG15 7DR",
    "sg:province":"Nottinghamshire",
    "sg:tags":[
        "awning",
        "canopy",
        "blinds"
    ],
    "wof:name":"V B C S",
    "wof:placetype":"venue"
},
  "geometry": {"coordinates":[-1.210244,53.040878],"type":"Point"}
}