{
  "type": "Feature",
  "properties": {
    "iso:country":"GB",
    "sg:address":"95 Everest Road, Hagfold, Atherton",
    "sg:city":"Manchester",
    "sg:classifiers":[
        {
            "category":"Professional",
            "subcategory":"Management & Consulting",
            "type":"Services"
        }
    ],
    "sg:postcode":"M46 9NT",
    "sg:province":"Greater Manchester",
    "sg:tags":[
        "consultant",
        "business"
    ],
    "wof:name":"Quantum Connections Ltd.",
    "wof:placetype":"venue"
},
  "geometry": {"coordinates":[-2.494989,53.53624],"type":"Point"}
}