{
  "type": "Feature",
  "properties": {
    "addr:full":"St Lukes Hall, Havana Street, Alpha Gro London Greater London E14 8NA",
    "addr:postcode":"e14 8na",
    "addr:street":"Havana Street",
    "iso:country":"GB",
    "sg:address":"St Lukes Hall, Havana Street, Alpha Gro",
    "sg:city":"London",
    "sg:classifiers":[
        {
            "category":"Education",
            "subcategory":"Special Training",
            "type":"Public Place"
        }
    ],
    "sg:postcode":"E14 8NA",
    "sg:province":"Greater London",
    "sg:tags":[
        "martial art",
        "instruction"
    ],
    "wof:name":"Docklands Kyokushinkai Karate Club",
    "wof:placetype":"venue"
},
  "geometry": {"coordinates":[-0.0240800008,51.4996414185],"type":"Point"}
}