{
  "type": "Feature",
  "properties": {
    "addr:full":"Padmores Yard, St Johns Mews Woking Surrey GU21 7ZE",
    "addr:postcode":"gu21 7ze",
    "addr:street":"Yard St Johns Mews",
    "iso:country":"GB",
    "sg:address":"Padmores Yard, St Johns Mews",
    "sg:city":"Woking",
    "sg:classifiers":[
        {
            "category":"Retail",
            "subcategory":"Auto Repair",
            "type":"Services"
        }
    ],
    "sg:phone":"+44 1483 724565",
    "sg:postcode":"GU21 7ZE",
    "sg:province":"Surrey",
    "sg:tags":[
        "modification",
        "garage"
    ],
    "wof:name":"John Leane Automobiles",
    "wof:placetype":"venue"
},
  "geometry": {"coordinates":[-0.55855,51.322075],"type":"Point"}
}