{
  "type": "Feature",
  "properties": {
    "iso:country":"GB",
    "sg:address":"Nether Winchendon House, Nether Winchendon",
    "sg:city":"Aylesbury",
    "sg:classifiers":[
        {
            "category":"Farming",
            "subcategory":"Farm",
            "type":"Manufacturing & Wholesale Goods"
        }
    ],
    "sg:phone":"+44 1844 290101",
    "sg:postcode":"HP18 0DY",
    "sg:province":"Buckinghamshire",
    "sg:tags":[
        "mixed",
        "crop"
    ],
    "wof:name":"R V Spencer-Bernard",
    "wof:placetype":"venue"
},
  "geometry": {"coordinates":[-0.9649500251,51.7985687256],"type":"Point"}
}