{
  "type": "Feature",
  "properties": {
    "addr:full":"400a Station Road Westcliff-on-sea Essex SS0 8ET",
    "addr:housenumber":"400a",
    "addr:postcode":"ss0 8et",
    "addr:street":"Station Road",
    "iso:country":"GB",
    "sg:address":"400a Station Road",
    "sg:city":"Westcliff-on-sea",
    "sg:classifiers":[
        {
            "category":"Professional",
            "subcategory":"Engineering",
            "type":"Services"
        }
    ],
    "sg:phone":"+44 1702 433131",
    "sg:postcode":"SS0 8ET",
    "sg:province":"Essex",
    "sg:tags":[
        "contractor",
        "electrical",
        "engineer"
    ],
    "wof:name":"Total Electrical Ltd.",
    "wof:placetype":"venue"
},
  "geometry": {"coordinates":[0.684354,51.538471],"type":"Point"}
}