{
  "type": "Feature",
  "properties": {
    "addr:full":"45 Woodvale Way Golders Green Greater London NW11 8SQ",
    "addr:housenumber":"45",
    "addr:postcode":"nw11 8sq",
    "addr:street":"Woodvale Way",
    "iso:country":"GB",
    "sg:address":"45 Woodvale Way",
    "sg:city":"Golders Green",
    "sg:classifiers":[
        {
            "category":"Communications",
            "subcategory":"News Services",
            "type":"Services"
        }
    ],
    "sg:phone":"+44 20 8452 4027",
    "sg:postcode":"NW11 8SQ",
    "sg:province":"Greater London",
    "sg:tags":[
        "photo",
        "agency"
    ],
    "wof:name":"Take 2 Media Services",
    "wof:placetype":"venue"
},
  "geometry": {"coordinates":[-0.213644,51.563122],"type":"Point"}
}