{
  "type": "Feature",
  "properties": {
    "addr:full":"25 Auchinairn Road, Bishopbriggs Glasgow East Dunbartonshire G64 1RT",
    "addr:housenumber":"25",
    "addr:postcode":"g64 1rt",
    "addr:street":"Auchinairn Road",
    "iso:country":"GB",
    "sg:address":"25 Auchinairn Road, Bishopbriggs",
    "sg:city":"Glasgow",
    "sg:classifiers":[
        {
            "category":"Government",
            "subcategory":"Fire Station",
            "type":"Public Place"
        },
        {
            "category":"Home & Garden",
            "subcategory":"Hardware",
            "type":"Retail Goods"
        }
    ],
    "sg:postcode":"G64 1RT",
    "sg:province":"East Dunbartonshire",
    "sg:tags":[
        "w'sale",
        "lighting",
        "retailer"
    ],
    "wof:name":"Illuminate",
    "wof:placetype":"venue"
},
  "geometry": {"coordinates":[-4.226534,55.896713],"type":"Point"}
}