{
  "type": "Feature",
  "properties": {
    "addr:full":"129 Bloomsied Road Lytham St Annes Lancashire FY1 6JN",
    "addr:housenumber":"129",
    "addr:postcode":"fy1 6jn",
    "addr:street":"Bloomsied Road",
    "iso:country":"GB",
    "sg:address":"129 Bloomsied Road",
    "sg:city":"Lytham St Annes",
    "sg:classifiers":[
        {
            "category":"Shopping",
            "type":"Retail Goods"
        }
    ],
    "sg:phone":"+44 1253 343761",
    "sg:postcode":"FY1 6JN",
    "sg:province":"Lancashire",
    "sg:tags":[
        "part",
        "accessory"
    ],
    "wof:name":"Pit Stop",
    "wof:placetype":"venue"
},
  "geometry": {"coordinates":[-3.0417499542,53.8042297363],"type":"Point"}
}