{
  "type": "Feature",
  "properties": {
    "iso:country":"GB",
    "sg:address":"C/o Gew Bowyer, 80 Portswood Road",
    "sg:city":"Southampton",
    "sg:classifiers":[
        {
            "category":"Professional",
            "type":"Services"
        }
    ],
    "sg:phone":"+44 23 8036 3156",
    "sg:postcode":"SO17 2FW",
    "sg:province":"Hampshire",
    "sg:tags":[
        "writer"
    ],
    "wof:name":"Metascript Ltd.",
    "wof:placetype":"venue"
},
  "geometry": {"coordinates":[-1.39528,50.922539],"type":"Point"}
}