{
  "type": "Feature",
  "properties": {
    "addr:full":"41 Bridge Street Peterborough Cambridgeshire PE1 1HA",
    "addr:housenumber":"41",
    "addr:postcode":"pe1 1ha",
    "addr:street":"Bridge Street",
    "iso:country":"GB",
    "sg:address":"41 Bridge Street",
    "sg:city":"Peterborough",
    "sg:classifiers":[
        {
            "category":"Shopping",
            "subcategory":"Shoes",
            "type":"Retail Goods"
        }
    ],
    "sg:phone":"+44 1733 891640",
    "sg:postcode":"PE1 1HA",
    "sg:province":"Cambridgeshire",
    "sg:tags":[
        "shop"
    ],
    "wof:name":"Cobblers",
    "wof:placetype":"venue"
},
  "geometry": {"coordinates":[-0.241978,52.570976],"type":"Point"}
}