{
  "type": "Feature",
  "properties": {
    "iso:country":"GB",
    "sg:address":"Calmore Drive, Caldmore",
    "sg:city":"Southampton",
    "sg:classifiers":[
        {
            "category":"Bars & Pubs",
            "type":"Food & Drink"
        }
    ],
    "sg:phone":"+44 23 8087 4941",
    "sg:postcode":"SO40 2SH",
    "sg:province":"Hampshire",
    "sg:tags":[
        "pubs",
        "inn"
    ],
    "wof:name":"The Saxon Inn",
    "wof:placetype":"venue"
},
  "geometry": {"coordinates":[-1.5096939802,50.9319839478],"type":"Point"}
}