{
  "type": "Feature",
  "properties": {
    "addr:full":"8 Guardian Road Industrial Estate Norwich Norfolk NR5 8PF",
    "addr:housenumber":"8",
    "addr:postcode":"nr5 8pf",
    "addr:street":"Guardian Road Industrial Estate Norwich Norfolk",
    "iso:country":"GB",
    "sg:address":"8 Guardian Road Industrial Estate",
    "sg:city":"Norwich",
    "sg:classifiers":[
        {
            "category":"Manufacturing",
            "subcategory":"Metals",
            "type":"Manufacturing & Wholesale Goods"
        }
    ],
    "sg:phone":"+44 1603 761010",
    "sg:postcode":"NR5 8PF",
    "sg:province":"Norfolk",
    "sg:tags":[
        "steel",
        "stockholder"
    ],
    "wof:name":"E S T S  Ltd.",
    "wof:placetype":"venue"
},
  "geometry": {"coordinates":[1.259325,52.635139],"type":"Point"}
}