{
  "type": "Feature",
  "properties": {
    "iso:country":"GB",
    "sg:address":"112 The Broadway",
    "sg:city":"Southend-on-sea",
    "sg:classifiers":[
        {
            "category":"Real Estate",
            "subcategory":"Architect",
            "type":"Services"
        }
    ],
    "sg:phone":"+44 1268 562266",
    "sg:postcode":"SS1 3HH",
    "sg:province":"Essex",
    "wof:name":"Ayshford & Sansome",
    "wof:placetype":"venue"
},
  "geometry": {"coordinates":[0.760603,51.535027],"type":"Point"}
}