{
  "type": "Feature",
  "properties": {
    "addr:full":"455 George Street Aberdeen Aberdeen City AB25 3BY",
    "addr:housenumber":"455",
    "addr:postcode":"ab25 3by",
    "addr:street":"George Street",
    "iso:country":"GB",
    "sg:address":"455 George Street",
    "sg:city":"Aberdeen",
    "sg:classifiers":[
        {
            "category":"Autos & Motor Vehicles",
            "subcategory":"Auto Supplies",
            "type":"Retail Goods"
        }
    ],
    "sg:phone":"+44 1224 646264",
    "sg:postcode":"AB25 3BY",
    "sg:province":"Aberdeen City",
    "sg:tags":[
        "component"
    ],
    "wof:name":"Partco Autoparts",
    "wof:placetype":"venue"
},
  "geometry": {"coordinates":[-2.1064360142,57.1541633606],"type":"Point"}
}