{
  "type": "Feature",
  "properties": {
    "addr:full":"19-25 Sunbridge Road Bradford West Yorkshire BD1 2AY",
    "addr:housenumber":"19-25",
    "addr:postcode":"bd1 2ay",
    "addr:street":"Sunbridge Road",
    "iso:country":"GB",
    "sg:address":"19-25 Sunbridge Road",
    "sg:city":"Bradford",
    "sg:classifiers":[
        {
            "category":"Organizations",
            "subcategory":"Non-profit Organization",
            "type":"Services"
        }
    ],
    "sg:postcode":"BD1 2AY",
    "sg:province":"West Yorkshire",
    "sg:tags":[
        "organisation",
        "voluntary",
        "charity"
    ],
    "wof:name":"Council for Voluntary Service",
    "wof:placetype":"venue"
},
  "geometry": {"coordinates":[-1.7546110153,53.7934646606],"type":"Point"}
}