{
  "type": "Feature",
  "properties": {
    "iso:country":"GB",
    "sg:address":"The Square, Blanchland",
    "sg:city":"Consett",
    "sg:classifiers":[
        {
            "category":"Cafe",
            "type":"Food & Drink"
        }
    ],
    "sg:phone":"+44 1434 675044",
    "sg:postcode":"DH8 9SR",
    "sg:province":"Durham",
    "sg:tags":[
        "tea",
        "room"
    ],
    "wof:name":"The White Monk Tea Rooms",
    "wof:placetype":"venue"
},
  "geometry": {"coordinates":[-2.054683,54.848042],"type":"Point"}
}