{
  "type": "Feature",
  "properties": {
    "iso:country":"GB",
    "sg:address":"Moat Farm",
    "sg:city":"Worcester",
    "sg:classifiers":[
        {
            "category":"Farming",
            "subcategory":"Livestock Farm",
            "type":"Manufacturing & Wholesale Goods"
        }
    ],
    "sg:phone":"+44 1905 830436",
    "sg:postcode":"WR2 4UA",
    "sg:province":"Worcestershire",
    "sg:tags":[
        "others"
    ],
    "wof:name":"R L Hall",
    "wof:placetype":"venue"
},
  "geometry": {"coordinates":[-2.247489,52.163521],"type":"Point"}
}