{
  "type": "Feature",
  "properties": {
    "iso:country":"GB",
    "sg:address":"Unit 1 Trinity Court, 16 John Dalton Street",
    "sg:city":"Manchester",
    "sg:classifiers":[
        {
            "category":"Shopping",
            "subcategory":"Gifts & Souvenirs",
            "type":"Retail Goods"
        }
    ],
    "sg:phone":"+44 161 833 9383",
    "sg:postcode":"M2 6HY",
    "sg:province":"Greater Manchester",
    "sg:tags":[
        "shop"
    ],
    "wof:name":"Environment Specialist Gift Shop",
    "wof:placetype":"venue"
},
  "geometry": {"coordinates":[-2.246606,53.48048],"type":"Point"}
}