{
  "type": "Feature",
  "properties": {
    "addr:full":"192-193 Queens Road Hastings East Sussex TN34 1RG",
    "addr:housenumber":"192-193",
    "addr:postcode":"tn34 1rg",
    "addr:street":"Queens Road",
    "iso:country":"GB",
    "sg:address":"192-193 Queens Road",
    "sg:city":"Hastings",
    "sg:classifiers":[
        {
            "category":"Professional",
            "subcategory":"Lawyer & Legal Services",
            "type":"Services"
        }
    ],
    "sg:postcode":"TN34 1RG",
    "sg:province":"East Sussex",
    "sg:tags":[
        "solicitor"
    ],
    "wof:name":"Funnell & Perring Solicitors",
    "wof:placetype":"venue"
},
  "geometry": {"coordinates":[0.582807,50.858501],"type":"Point"}
}