{
  "type": "Feature",
  "properties": {
    "iso:country":"GB",
    "sg:address":"Harbrook Farm, New Rd, Clifton",
    "sg:city":"Shefford",
    "sg:classifiers":[
        {
            "category":"Real Estate",
            "subcategory":"Developer",
            "type":"Services"
        }
    ],
    "sg:postcode":"SG17 5JH",
    "sg:province":"Bedfordshire",
    "sg:tags":[
        "property"
    ],
    "wof:name":"Harbrook Land & Property Ltd",
    "wof:placetype":"venue"
},
  "geometry": {"coordinates":[-0.334879,52.04134],"type":"Point"}
}