{
  "type": "Feature",
  "properties": {
    "iso:country":"GB",
    "sg:address":"69 Union Street, Harthill",
    "sg:city":"Sheffield",
    "sg:classifiers":[
        {
            "category":"Professional",
            "subcategory":"Secretarial Services",
            "type":"Services"
        }
    ],
    "sg:postcode":"S26 7YG",
    "sg:province":"South Yorkshire",
    "wof:name":"Tanimara Printing & Office Services",
    "wof:placetype":"venue"
},
  "geometry": {"coordinates":[-1.259974,53.321255],"type":"Point"}
}