{
  "type": "Feature",
  "properties": {
    "iso:country":"GB",
    "sg:address":"32 Parade (the)",
    "sg:city":"Bourne End",
    "sg:classifiers":[
        {
            "category":"Home & Garden",
            "subcategory":"Carpets & Floor Coverings",
            "type":"Retail Goods"
        }
    ],
    "sg:postcode":"SL8 5SY",
    "sg:province":"Berkshire",
    "sg:tags":[
        "carpets",
        "rug",
        "matting"
    ],
    "wof:name":"Larocque Ltd.",
    "wof:placetype":"venue"
},
  "geometry": {"coordinates":[-0.711187005,51.5784301758],"type":"Point"}
}