{
  "type": "Feature",
  "properties": {
    "iso:country":"GB",
    "sg:address":"Antron Farm, Antron Lane, Mabe",
    "sg:city":"Penryn",
    "sg:classifiers":[
        {
            "category":"Farming",
            "subcategory":"Livestock Farm",
            "type":"Manufacturing & Wholesale Goods"
        }
    ],
    "sg:postcode":"TR10 9JD",
    "sg:province":"Cornwall",
    "sg:tags":[
        "others"
    ],
    "wof:name":"David M Coleman",
    "wof:placetype":"venue"
},
  "geometry": {"coordinates":[-5.135714,50.164253],"type":"Point"}
}