{
  "type": "Feature",
  "properties": {
    "addr:full":"80 Braddon Rd Loughborough Leicestershire LE11 5YZ",
    "addr:housenumber":"80",
    "addr:postcode":"le11 5yz",
    "addr:street":"Braddon Rd",
    "iso:country":"GB",
    "sg:address":"80 Braddon Rd",
    "sg:city":"Loughborough",
    "sg:classifiers":[
        {
            "category":"Retail",
            "subcategory":"Driving School",
            "type":"Services"
        }
    ],
    "sg:phone":"+44 1509 842080",
    "sg:postcode":"LE11 5YZ",
    "sg:province":"Leicestershire",
    "wof:name":"T J Simmons",
    "wof:placetype":"venue"
},
  "geometry": {"coordinates":[-1.2372939587,52.7827606201],"type":"Point"}
}