{
  "type": "Feature",
  "properties": {
    "addr:full":"Church La, The Historic Dockyard Chatham Kent ME4 4TE",
    "addr:postcode":"me4 4te",
    "addr:street":"La The Historic Dockyard",
    "iso:country":"GB",
    "sg:address":"Church La, The Historic Dockyard",
    "sg:city":"Chatham",
    "sg:classifiers":[
        {
            "category":"Recreation",
            "subcategory":"Sailing Club",
            "type":"Entertainment"
        }
    ],
    "sg:phone":"+44 1634 402518",
    "sg:postcode":"ME4 4TE",
    "sg:province":"Kent",
    "wof:name":"Medway Sea School The",
    "wof:placetype":"venue"
},
  "geometry": {"coordinates":[0.52745,51.393017],"type":"Point"}
}