{
  "type": "Feature",
  "properties": {
    "iso:country":"GB",
    "sg:address":"Lansdown Road",
    "sg:city":"Bath",
    "sg:classifiers":[
        {
            "category":"Education",
            "subcategory":"School",
            "type":"Public Place"
        }
    ],
    "sg:phone":"+44 1225 313877",
    "sg:postcode":"BA1 5SZ",
    "sg:province":"Bath and North East Somerset",
    "sg:tags":[
        "independent",
        "preparatory"
    ],
    "wof:name":"The Royal School",
    "wof:placetype":"venue"
},
  "geometry": {"coordinates":[-2.362179,51.388901],"type":"Point"}
}