{
  "type": "Feature",
  "properties": {
    "iso:country":"GB",
    "sg:address":"79 Victoria Street",
    "sg:city":"Windsor",
    "sg:classifiers":[
        {
            "category":"Real Estate",
            "subcategory":"Real Estate Operator",
            "type":"Services"
        }
    ],
    "sg:phone":"+44 1753 775588",
    "sg:postcode":"SL4 1EH",
    "sg:province":"Berkshire",
    "sg:tags":[
        "letting",
        "agent"
    ],
    "wof:name":"Murrey Management",
    "wof:placetype":"venue"
},
  "geometry": {"coordinates":[-0.6115310192,51.4798965454],"type":"Point"}
}