{
  "type": "Feature",
  "properties": {
    "iso:country":"GB",
    "sg:address":"Unit 11 Goodwick Industrial Estate, Main Street",
    "sg:city":"Goodwick",
    "sg:classifiers":[
        {
            "category":"Building & Trades",
            "subcategory":"Construction",
            "type":"Services"
        }
    ],
    "sg:phone":"+44 1348 874518",
    "sg:postcode":"SA64 0BD",
    "sg:province":"Pembrokeshire",
    "sg:tags":[
        "equipment"
    ],
    "wof:name":"Fishguard Tool Hire",
    "wof:placetype":"venue"
},
  "geometry": {"coordinates":[-4.997849,52.000923],"type":"Point"}
}