{
  "type": "Feature",
  "properties": {
    "iso:country":"GB",
    "sg:address":"Heddington",
    "sg:city":"Calne",
    "sg:classifiers":[
        {
            "category":"Sports & Exercise",
            "subcategory":"Stables",
            "type":"Entertainment"
        }
    ],
    "sg:phone":"+44 1380 850333",
    "sg:postcode":"SN11 0PP",
    "sg:province":"Wiltshire",
    "sg:tags":[
        "equestrian",
        "centre",
        "livery",
        "schools",
        "riding",
        "education"
    ],
    "wof:name":"Hampsley Hollow Riding Centre",
    "wof:placetype":"venue"
},
  "geometry": {"coordinates":[-1.9952,51.39724],"type":"Point"}
}