{
  "type": "Feature",
  "properties": {
    "addr:full":"75 Kettering Road Northampton Northamptonshire NN1 4AW",
    "addr:housenumber":"75",
    "addr:postcode":"nn1 4aw",
    "addr:street":"Kettering Road",
    "iso:country":"GB",
    "sg:address":"75 Kettering Road",
    "sg:city":"Northampton",
    "sg:classifiers":[
        {
            "category":"Shopping",
            "subcategory":"Musical Instruments",
            "type":"Retail Goods"
        },
        {
            "category":"Shopping",
            "subcategory":"Music",
            "type":"Retail Goods"
        }
    ],
    "sg:phone":"+44 1604 628419",
    "sg:postcode":"NN1 4AW",
    "sg:province":"Northamptonshire",
    "sg:tags":[
        "shop"
    ],
    "wof:name":"Music Market",
    "wof:placetype":"venue"
},
  "geometry": {"coordinates":[-0.8862,52.242031],"type":"Point"}
}