{
  "type": "Feature",
  "properties": {
    "addr:full":"152a Main Road, Biggin Hill Westerham Kent TN16 3BA",
    "addr:housenumber":"152a",
    "addr:postcode":"tn16 3ba",
    "addr:street":"Main Road",
    "iso:country":"GB",
    "sg:address":"152a Main Road, Biggin Hill",
    "sg:city":"Westerham",
    "sg:classifiers":[
        {
            "category":"Travel",
            "subcategory":"Travel Agent",
            "type":"Entertainment"
        }
    ],
    "sg:phone":"+44 1959 571977",
    "sg:postcode":"TN16 3BA",
    "sg:province":"Kent",
    "wof:name":"Travel Experience",
    "wof:placetype":"venue"
},
  "geometry": {"coordinates":[0.0360249989,51.3102149963],"type":"Point"}
}