{
  "type": "Feature",
  "properties": {
    "addr:full":"5 Ashley Way Woking Surrey GU24 9NJ",
    "addr:housenumber":"5",
    "addr:postcode":"gu24 9nj",
    "addr:street":"Ashley Way",
    "iso:country":"GB",
    "sg:address":"5 Ashley Way",
    "sg:city":"Woking",
    "sg:classifiers":[
        {
            "category":"Professional",
            "subcategory":"Engineering",
            "type":"Services"
        }
    ],
    "sg:phone":"+44 1483 487932",
    "sg:postcode":"GU24 9NJ",
    "sg:province":"Surrey",
    "wof:name":"Bryen Associates",
    "wof:placetype":"venue"
},
  "geometry": {"coordinates":[-0.6564819813,51.3394241333],"type":"Point"}
}