{
  "type": "Feature",
  "properties": {
    "iso:country":"GB",
    "sg:address":"Scotsburn Road",
    "sg:city":"Tain",
    "sg:classifiers":[
        {
            "category":"Education",
            "subcategory":"School",
            "type":"Public Place"
        },
        {
            "category":"Government",
            "subcategory":"Office",
            "type":"Public Place"
        }
    ],
    "sg:phone":"+44 1862 892121",
    "sg:postcode":"IV19 1PS",
    "sg:province":"Highland",
    "sg:tags":[
        "local",
        "authority"
    ],
    "wof:name":"Tain Royal Academy",
    "wof:placetype":"venue"
},
  "geometry": {"coordinates":[-4.06149,57.806126],"type":"Point"}
}