{
  "type": "Feature",
  "properties": {
    "iso:country":"GB",
    "sg:address":"19 Dunster Close, Hazelgrove",
    "sg:city":"Stockport",
    "sg:classifiers":[
        {
            "category":"Professional",
            "type":"Services"
        }
    ],
    "sg:phone":"+44 161 483 0769",
    "sg:postcode":"SK7 5PX",
    "sg:province":"Cheshire",
    "sg:tags":[
        "entertainer"
    ],
    "wof:name":"Jolly Jack",
    "wof:placetype":"venue"
},
  "geometry": {"coordinates":[-2.130101,53.374313],"type":"Point"}
}