{
  "type": "Feature",
  "properties": {
    "iso:country":"GB",
    "sg:address":"6 The Avenue",
    "sg:city":"Totland Bay",
    "sg:classifiers":[
        {
            "category":"Social Services",
            "subcategory":"Retirement Home",
            "type":"Services"
        },
        {
            "category":"Organizations",
            "subcategory":"Community Association",
            "type":"Services"
        }
    ],
    "sg:phone":"+44 1983 755348",
    "sg:postcode":"PO39 0DH",
    "sg:province":"Isle of Wight",
    "sg:tags":[
        "society",
        "housing",
        "sheltered",
        "accommodation"
    ],
    "wof:name":"Abbeyfield West Wight Society",
    "wof:placetype":"venue"
},
  "geometry": {"coordinates":[-1.530681,50.684326],"type":"Point"}
}