{
  "type": "Feature",
  "properties": {
    "addr:full":"Unit 3, Bankend Road Dumbarton Argyll and Bute G82 2RB",
    "addr:housenumber":"unit 3",
    "addr:postcode":"g82 2rb",
    "addr:street":"Bankend Road",
    "iso:country":"GB",
    "sg:address":"Unit 3, Bankend Road",
    "sg:city":"Dumbarton",
    "sg:classifiers":[
        {
            "category":"Professional",
            "subcategory":"Detective & Security Services",
            "type":"Services"
        }
    ],
    "sg:postcode":"G82 2RB",
    "sg:province":"Argyll and Bute",
    "sg:tags":[
        "equipment"
    ],
    "wof:name":"B C S Supplies",
    "wof:placetype":"venue"
},
  "geometry": {"coordinates":[-4.565829,55.946838],"type":"Point"}
}