{
  "type": "Feature",
  "properties": {
    "iso:country":"GB",
    "sg:address":"189 Anns Hill Rd",
    "sg:city":"Gosport",
    "sg:classifiers":[
        {
            "category":"Shopping",
            "subcategory":"News",
            "type":"Retail Goods"
        }
    ],
    "sg:phone":"+44 23 9258 2056",
    "sg:postcode":"PO12 3RF",
    "sg:province":"Hampshire",
    "sg:tags":[
        "newsagent"
    ],
    "wof:name":"Fishers",
    "wof:placetype":"venue"
},
  "geometry": {"coordinates":[-1.1489540339,50.7936058044],"type":"Point"}
}