{
  "type": "Feature",
  "properties": {
    "iso:country":"GB",
    "sg:address":"Clinchyard Farm, Hurlford",
    "sg:city":"Kilmarnock",
    "sg:classifiers":[
        {
            "category":"Building & Trades",
            "subcategory":"Cleaning & Sanitation",
            "type":"Services"
        }
    ],
    "sg:phone":"+44 1563 820275",
    "sg:postcode":"KA1 5JF",
    "sg:province":"East Ayrshire",
    "sg:tags":[
        "door",
        "manufacturer"
    ],
    "wof:name":"H S Anderson",
    "wof:placetype":"venue"
},
  "geometry": {"coordinates":[-4.4569540024,55.6008491516],"type":"Point"}
}