{
  "type": "Feature",
  "properties": {
    "addr:full":"7 Brassey Parade, Brassey Avenue Eastbourne East Sussex BN22 9NG",
    "addr:housenumber":"7",
    "addr:postcode":"bn22 9ng",
    "addr:street":"Brassey Parade Brassey Avenue",
    "iso:country":"GB",
    "sg:address":"7 Brassey Parade, Brassey Avenue",
    "sg:city":"Eastbourne",
    "sg:classifiers":[
        {
            "category":"Personal",
            "subcategory":"Beauty Salon",
            "type":"Services"
        }
    ],
    "sg:phone":"+44 1323 507831",
    "sg:postcode":"BN22 9NG",
    "sg:province":"East Sussex",
    "sg:tags":[
        "unisex",
        "hairdresser"
    ],
    "wof:name":"Bandeau Hair Studio",
    "wof:placetype":"venue"
},
  "geometry": {"coordinates":[0.2784950137,50.7966918945],"type":"Point"}
}