{
  "type": "Feature",
  "properties": {
    "addr:full":"181 High Holborn London Greater London WC1V 7RL",
    "addr:housenumber":"181",
    "addr:postcode":"wc1v 7rl",
    "addr:street":"High Holborn",
    "iso:country":"GB",
    "sg:address":"181 High Holborn",
    "sg:city":"London",
    "sg:classifiers":[
        {
            "category":"Government",
            "subcategory":"Post Office",
            "type":"Public Place"
        }
    ],
    "sg:phone":"+44 20 7831 7808",
    "sg:postcode":"WC1V 7RL",
    "sg:province":"Greater London",
    "wof:name":"High Holborn Post Office",
    "wof:placetype":"venue"
},
  "geometry": {"coordinates":[-0.2339929938,51.547252655],"type":"Point"}
}