{
  "type": "Feature",
  "properties": {
    "addr:full":"Bottle House, Maple Av Bishops Stortford Essex CM23 2RP",
    "addr:postcode":"cm23 2rp",
    "addr:street":"Maple Av Bishops Stortford",
    "iso:country":"GB",
    "sg:address":"Bottle House, Maple Av",
    "sg:city":"Bishops Stortford",
    "sg:classifiers":[
        {
            "category":"Building & Trades",
            "subcategory":"Construction",
            "type":"Services"
        }
    ],
    "sg:postcode":"CM23 2RP",
    "sg:province":"Essex",
    "sg:tags":[
        "platform",
        "work",
        "scaffolding"
    ],
    "wof:name":"Connect Scaffolding",
    "wof:placetype":"venue"
},
  "geometry": {"coordinates":[0.1459390074,51.8736457825],"type":"Point"}
}