{
  "type": "Feature",
  "properties": {
    "iso:country":"GB",
    "sg:address":"Maypole Road, Tiptree",
    "sg:city":"Colchester",
    "sg:classifiers":[
        {
            "category":"Autos & Motor Vehicles",
            "subcategory":"Fuel & Gas Station",
            "type":"Retail Goods"
        }
    ],
    "sg:phone":"+44 1621 814320",
    "sg:postcode":"CO5 0EH",
    "sg:province":"Essex",
    "sg:tags":[
        "petrol",
        "filling"
    ],
    "wof:name":"Shell U K Ltd.",
    "wof:placetype":"venue"
},
  "geometry": {"coordinates":[0.745334,51.816463],"type":"Point"}
}