{
  "type": "Feature",
  "properties": {
    "addr:full":"128 High Street Beckenham Kent BR3 1EB",
    "addr:housenumber":"128",
    "addr:postcode":"br3 1eb",
    "addr:street":"High Street",
    "iso:country":"GB",
    "sg:address":"128 High Street",
    "sg:city":"Beckenham",
    "sg:classifiers":[
        {
            "category":"Retail",
            "subcategory":"Laundry & Dry Cleaning",
            "type":"Services"
        }
    ],
    "sg:postcode":"BR3 1EB",
    "sg:province":"Kent",
    "sg:tags":[
        "alteration"
    ],
    "wof:name":"Carnation Cleaners",
    "wof:placetype":"venue"
},
  "geometry": {"coordinates":[-0.026463,51.407768],"type":"Point"}
}