{
  "type": "Feature",
  "properties": {
    "addr:full":"2 Albert Road Tonbridge Kent TN9 2SR",
    "addr:housenumber":"2",
    "addr:postcode":"tn9 2sr",
    "addr:street":"Albert Road",
    "iso:country":"GB",
    "sg:address":"2 Albert Road",
    "sg:city":"Tonbridge",
    "sg:classifiers":[
        {
            "category":"Communications",
            "type":"Services"
        }
    ],
    "sg:postcode":"TN9 2SR",
    "sg:province":"Kent",
    "sg:tags":[
        "audio-visual"
    ],
    "wof:name":"Advantage Video Productions",
    "wof:placetype":"venue"
},
  "geometry": {"coordinates":[0.269049,51.191044],"type":"Point"}
}