{
  "type": "Feature",
  "properties": {
    "iso:country":"GB",
    "sg:address":"10 Oakbank Road, East Calder",
    "sg:city":"Livingston",
    "sg:classifiers":[
        {
            "category":"Home & Garden",
            "subcategory":"Home Furnishings",
            "type":"Retail Goods"
        }
    ],
    "sg:postcode":"EH53 0BX",
    "sg:province":"City of Edinburgh",
    "sg:tags":[
        "awning",
        "canopy",
        "blinds"
    ],
    "wof:name":"Calypso Blinds (Scotland)",
    "wof:placetype":"venue"
},
  "geometry": {"coordinates":[-3.4653398991,55.8902282715],"type":"Point"}
}