{
  "type": "Feature",
  "properties": {
    "iso:country":"GB",
    "sg:address":"15 St Stephens Street",
    "sg:city":"Norwich",
    "sg:classifiers":[
        {
            "category":"Travel",
            "subcategory":"Travel Agent",
            "type":"Entertainment"
        }
    ],
    "sg:phone":"+44 1603 241200",
    "sg:postcode":"NR1 3QW",
    "sg:province":"Norfolk",
    "wof:name":"Thomas Cook",
    "wof:placetype":"venue"
},
  "geometry": {"coordinates":[1.292946,52.62537],"type":"Point"}
}