{
  "type": "Feature",
  "properties": {
    "addr:full":"36-38 Abington Square Northampton Northamptonshire NN1 4AA",
    "addr:housenumber":"36-38",
    "addr:postcode":"nn1 4aa",
    "addr:street":"Abington Square",
    "iso:country":"GB",
    "sg:address":"36-38 Abington Square",
    "sg:city":"Northampton",
    "sg:classifiers":[
        {
            "category":"Banks & Credit Unions",
            "subcategory":"Financial Services",
            "type":"Services"
        }
    ],
    "sg:phone":"+44 1604 674111",
    "sg:postcode":"NN1 4AA",
    "sg:province":"Northamptonshire",
    "sg:tags":[
        "consultant"
    ],
    "wof:name":"Lincoln",
    "wof:placetype":"venue"
},
  "geometry": {"coordinates":[-0.887732,52.240044],"type":"Point"}
}