{
  "type": "Feature",
  "properties": {
    "addr:full":"19-20 Upper High Street Cradley Heath West Midlands B64 5HX",
    "addr:housenumber":"19-20",
    "addr:postcode":"b64 5hx",
    "addr:street":"Upper High Street",
    "iso:country":"GB",
    "sg:address":"19-20 Upper High Street",
    "sg:city":"Cradley Heath",
    "sg:classifiers":[
        {
            "category":"Shopping",
            "subcategory":"Shoes",
            "type":"Retail Goods"
        }
    ],
    "sg:postcode":"B64 5HX",
    "sg:province":"West Midlands",
    "sg:tags":[
        "shop"
    ],
    "wof:name":"Perrins & Alan Pamela",
    "wof:placetype":"venue"
},
  "geometry": {"coordinates":[-2.078799963,52.473690033],"type":"Point"}
}