{
  "type": "Feature",
  "properties": {
    "iso:country":"GB",
    "sg:address":"Unit 3",
    "sg:city":"Lochgilphead",
    "sg:classifiers":[
        {
            "category":"Building & Trades",
            "subcategory":"Construction",
            "type":"Services"
        }
    ],
    "sg:postcode":"PA31 8NE",
    "sg:province":"Argyll and Bute",
    "sg:tags":[
        "flooring"
    ],
    "wof:name":"Touchwood Flooring",
    "wof:placetype":"venue"
},
  "geometry": {"coordinates":[-5.485689,56.060951],"type":"Point"}
}