{
  "type": "Feature",
  "properties": {
    "addr:full":"Villa Farm Kirkby Stephen Cumbria CA17 4DP",
    "addr:postcode":"ca17 4dp",
    "iso:country":"GB",
    "sg:address":"Villa Farm",
    "sg:city":"Kirkby Stephen",
    "sg:classifiers":[
        {
            "category":"Farming",
            "subcategory":"Farm",
            "type":"Manufacturing & Wholesale Goods"
        }
    ],
    "sg:phone":"+44 17683 41562",
    "sg:postcode":"CA17 4DP",
    "sg:province":"Cumbria",
    "sg:tags":[
        "mixed",
        "crop"
    ],
    "wof:name":"T Procter",
    "wof:placetype":"venue"
},
  "geometry": {"coordinates":[-2.348623,54.472717],"type":"Point"}
}