{
  "type": "Feature",
  "properties": {
    "addr:full":"Mote Park Maidstone Kent ME15 7RN",
    "addr:postcode":"me15 7rn",
    "addr:street":"Park",
    "iso:country":"GB",
    "sg:address":"Mote Park",
    "sg:city":"Maidstone",
    "sg:classifiers":[
        {
            "category":"Community Center",
            "type":"Public Place"
        }
    ],
    "sg:phone":"+44 1622 761111",
    "sg:postcode":"ME15 7RN",
    "sg:province":"Kent",
    "sg:tags":[
        "recreation",
        "leisure",
        "centre"
    ],
    "wof:name":"Maidstone Leisure Centre",
    "wof:placetype":"venue"
},
  "geometry": {"coordinates":[0.52639,51.270504],"type":"Point"}
}