{
  "type": "Feature",
  "properties": {
    "iso:country":"GB",
    "sg:address":"78 Lewisham Park",
    "sg:city":"Lewisham",
    "sg:classifiers":[
        {
            "category":"Health Services",
            "subcategory":"Clinic",
            "type":"Services"
        }
    ],
    "sg:phone":"+44 20 8690 1086",
    "sg:postcode":"SE13 6QJ",
    "sg:province":"Greater London",
    "sg:tags":[
        "nh"
    ],
    "wof:name":"Lewisham Child & Family Therapy Centre",
    "wof:placetype":"venue"
},
  "geometry": {"coordinates":[-0.015658,51.454651],"type":"Point"}
}