{
  "type": "Feature",
  "properties": {
    "addr:full":"5 Grand Hotel Buildings, Compton Street Eastbourne East Sussex BN21 4EJ",
    "addr:housenumber":"5",
    "addr:postcode":"bn21 4ej",
    "addr:street":"Compton Street",
    "iso:country":"GB",
    "sg:address":"5 Grand Hotel Buildings, Compton Street",
    "sg:city":"Eastbourne",
    "sg:classifiers":[
        {
            "category":"Shopping",
            "subcategory":"Antiques",
            "type":"Retail Goods"
        }
    ],
    "sg:postcode":"BN21 4EJ",
    "sg:province":"East Sussex",
    "wof:name":"Grand Antiques",
    "wof:placetype":"venue"
},
  "geometry": {"coordinates":[0.2853499949,50.766910553],"type":"Point"}
}