{
  "type": "Feature",
  "properties": {
    "addr:full":"26 Eaton Rise London Greater London W5 2ER",
    "addr:housenumber":"26",
    "addr:postcode":"w5 2er",
    "addr:street":"Eaton Rise",
    "iso:country":"GB",
    "sg:address":"26 Eaton Rise",
    "sg:city":"London",
    "sg:classifiers":[
        {
            "category":"Professional",
            "subcategory":"Business Services",
            "type":"Services"
        }
    ],
    "sg:postcode":"W5 2ER",
    "sg:province":"Greater London",
    "sg:tags":[
        "import",
        "export",
        "agent"
    ],
    "wof:name":"Psychotherapists and Counsellors for Soc",
    "wof:placetype":"venue"
},
  "geometry": {"coordinates":[-0.306518,51.518322],"type":"Point"}
}