{
  "type": "Feature",
  "properties": {
    "addr:full":"22 Epsom Lane North Tadworth Surrey KT20 5EH",
    "addr:housenumber":"22",
    "addr:postcode":"kt20 5eh",
    "addr:street":"Epsom Lane North Tadworth",
    "iso:country":"GB",
    "sg:address":"22 Epsom Lane North",
    "sg:city":"Tadworth",
    "sg:classifiers":[
        {
            "category":"Professional",
            "subcategory":"Art Services",
            "type":"Services"
        },
        {
            "category":"Real Estate",
            "subcategory":"Architect",
            "type":"Services"
        }
    ],
    "sg:phone":"+44 1737 361872",
    "sg:postcode":"KT20 5EH",
    "sg:province":"Surrey",
    "sg:tags":[
        "consultant",
        "design"
    ],
    "wof:name":"Will How Design Associates",
    "wof:placetype":"venue"
},
  "geometry": {"coordinates":[-0.2326509953,51.2931594849],"type":"Point"}
}