{
  "type": "Feature",
  "properties": {
    "iso:country":"GB",
    "sg:address":"Conway Road, Mochdre",
    "sg:city":"Colwyn Bay",
    "sg:classifiers":[
        {
            "category":"Education",
            "subcategory":"Music School",
            "type":"Public Place"
        }
    ],
    "sg:phone":"+44 1492 544811",
    "sg:postcode":"LL28 5HN",
    "sg:province":"Conwy",
    "sg:tags":[
        "conservatory"
    ],
    "wof:name":"R D Johnson & Sons",
    "wof:placetype":"venue"
},
  "geometry": {"coordinates":[-3.7515940666,53.2988967896],"type":"Point"}
}