{
  "type": "Feature",
  "properties": {
    "iso:country":"GB",
    "sg:address":"116 Rawlinson St",
    "sg:city":"Barrow In Furness",
    "sg:classifiers":[
        {
            "category":"Utilities",
            "subcategory":"Fuel Oil & Lpg",
            "type":"Services"
        }
    ],
    "sg:phone":"+44 1229 837769",
    "sg:postcode":"LA14 2DG",
    "sg:province":"Cumbria",
    "sg:tags":[
        "equipment",
        "diesel"
    ],
    "wof:name":"Diesel Repair Specialist",
    "wof:placetype":"venue"
},
  "geometry": {"coordinates":[-3.2206459045,54.1119003296],"type":"Point"}
}