{
  "type": "Feature",
  "properties": {
    "iso:country":"GB",
    "sg:address":"13-14 Lodge Road",
    "sg:city":"Oldbury",
    "sg:classifiers":[
        {
            "category":"Autos & Motor Vehicles",
            "subcategory":"Automobile Sales",
            "type":"Retail Goods"
        }
    ],
    "sg:postcode":"B67 7LU",
    "sg:province":"West Midlands",
    "sg:tags":[
        "car"
    ],
    "wof:name":"Lodge Road Motors",
    "wof:placetype":"venue"
},
  "geometry": {"coordinates":[-2.012082,52.50106],"type":"Point"}
}