{
  "type": "Feature",
  "properties": {
    "addr:full":"Mitchell Ho, 333 Bath St Glasgow Glasgow City G2 4ER",
    "addr:housenumber":"333",
    "addr:postcode":"g2 4er",
    "addr:street":"Bath St",
    "iso:country":"GB",
    "sg:address":"Mitchell Ho, 333 Bath St",
    "sg:city":"Glasgow",
    "sg:classifiers":[
        {
            "category":"Manufacturing",
            "subcategory":"Tools & Machinery",
            "type":"Manufacturing & Wholesale Goods"
        }
    ],
    "sg:phone":"+44 141 248 3331",
    "sg:postcode":"G2 4ER",
    "sg:province":"Glasgow City",
    "sg:tags":[
        "society",
        "friendly"
    ],
    "wof:name":"Cunningham Christie",
    "wof:placetype":"venue"
},
  "geometry": {"coordinates":[-4.2695198059,55.8653488159],"type":"Point"}
}