{
  "type": "Feature",
  "properties": {
    "addr:full":"99 High St West Wallsend Tyne and Wear NE28 8JD",
    "addr:housenumber":"99",
    "addr:postcode":"ne28 8jd",
    "addr:street":"High St",
    "iso:country":"GB",
    "sg:address":"99 High St West",
    "sg:city":"Wallsend",
    "sg:classifiers":[
        {
            "category":"Restaurant",
            "type":"Food & Drink"
        }
    ],
    "sg:postcode":"NE28 8JD",
    "sg:province":"Tyne and Wear",
    "wof:name":"Alexanders Fish Restaurant",
    "wof:placetype":"venue"
},
  "geometry": {"coordinates":[-1.5374319553,54.9905281067],"type":"Point"}
}