{
  "type": "Feature",
  "properties": {
    "addr:full":"37 West End Road Morecambe Lancashire LA4 4DJ",
    "addr:housenumber":"37",
    "addr:postcode":"la4 4dj",
    "addr:street":"West End Road",
    "iso:country":"GB",
    "sg:address":"37 West End Road",
    "sg:city":"Morecambe",
    "sg:classifiers":[
        {
            "category":"Travel",
            "subcategory":"Hotels & Motels",
            "type":"Entertainment"
        }
    ],
    "sg:phone":"+44 1524 411826",
    "sg:postcode":"LA4 4DJ",
    "sg:province":"Lancashire",
    "wof:name":"William Keegan",
    "wof:placetype":"venue"
},
  "geometry": {"coordinates":[-2.8769669533,54.0670776367],"type":"Point"}
}