{
  "type": "Feature",
  "properties": {
    "addr:full":"Unit 1f 25 Frogmore, Wandsworth Wandsworth Greater London SW18 1JA",
    "addr:housenumber":"unit 1f 25",
    "addr:postcode":"sw18 1ja",
    "addr:street":"Frogmore Wandsworth",
    "iso:country":"GB",
    "sg:address":"Unit 1f 25 Frogmore, Wandsworth",
    "sg:city":"Wandsworth",
    "sg:classifiers":[
        {
            "category":"Building & Trades",
            "subcategory":"Construction",
            "type":"Services"
        }
    ],
    "sg:phone":"+44 20 8877 1100",
    "sg:postcode":"SW18 1JA",
    "sg:province":"Greater London",
    "sg:tags":[
        "roofing"
    ],
    "wof:name":"Laird Cross (UK) Ltd",
    "wof:placetype":"venue"
},
  "geometry": {"coordinates":[-0.196925,51.459278],"type":"Point"}
}