{
  "type": "Feature",
  "properties": {
    "iso:country":"GB",
    "sg:address":"36-38 Westbourne Gro, Chepstow Road",
    "sg:city":"London",
    "sg:classifiers":[
        {
            "category":"Banks & Credit Unions",
            "subcategory":"Financial Services",
            "type":"Services"
        }
    ],
    "sg:phone":"+44 20 7229 4572",
    "sg:postcode":"W2 5RU",
    "sg:province":"Greater London",
    "sg:tags":[
        "adviser"
    ],
    "wof:name":"P F D Financial Services Ltd.",
    "wof:placetype":"venue"
},
  "geometry": {"coordinates":[-0.191483,51.518196],"type":"Point"}
}