{
  "type": "Feature",
  "properties": {
    "iso:country":"GB",
    "sg:address":"22 St Thomas Street",
    "sg:city":"Bristol",
    "sg:classifiers":[
        {
            "category":"Wholesale",
            "subcategory":"Construction Materials",
            "type":"Manufacturing & Wholesale Goods"
        }
    ],
    "sg:phone":"+44 117 900 1300",
    "sg:postcode":"BS1 6JJ",
    "sg:province":"City of Bristol",
    "sg:tags":[
        "merchant",
        "glass"
    ],
    "wof:name":"Pilkington United Kingdom Ltd.",
    "wof:placetype":"venue"
},
  "geometry": {"coordinates":[-2.5888528824,51.4510650635],"type":"Point"}
}