{
  "type": "Feature",
  "properties": {
    "addr:full":"2 Mikasa St Barrow-in-furness Cumbria LA14 3BT",
    "addr:housenumber":"2",
    "addr:postcode":"la14 3bt",
    "addr:street":"Mikasa St",
    "iso:country":"GB",
    "sg:address":"2 Mikasa St",
    "sg:city":"Barrow-in-furness",
    "sg:classifiers":[
        {
            "category":"Food & Beverages",
            "subcategory":"Meat & Fish",
            "type":"Retail Goods"
        }
    ],
    "sg:postcode":"LA14 3BT",
    "sg:province":"Cumbria",
    "sg:tags":[
        "butcher"
    ],
    "wof:name":"Hart,Stephen,",
    "wof:placetype":"venue"
},
  "geometry": {"coordinates":[-3.249644,54.103817],"type":"Point"}
}