{
  "type": "Feature",
  "properties": {
    "iso:country":"GB",
    "sg:address":"Bradfield Road",
    "sg:city":"Nottingham",
    "sg:classifiers":[
        {
            "category":"Community Center",
            "subcategory":"Youth",
            "type":"Public Place"
        },
        {
            "category":"Government",
            "subcategory":"Office",
            "type":"Public Place"
        }
    ],
    "sg:phone":"+44 115 929 2387",
    "sg:postcode":"NG8 6GN",
    "sg:province":"Nottinghamshire",
    "sg:tags":[
        "organisation",
        "local",
        "centre"
    ],
    "wof:name":"Broxtowe Youth Activity Centre",
    "wof:placetype":"venue"
},
  "geometry": {"coordinates":[-1.217239,52.977428],"type":"Point"}
}