{
  "type": "Feature",
  "properties": {
    "addr:full":"2 Tamworth Road, Long Eaton Nottingham Nottinghamshire NG2 2NG",
    "addr:housenumber":"2",
    "addr:postcode":"ng2 2ng",
    "addr:street":"Tamworth Road",
    "iso:country":"GB",
    "sg:address":"2 Tamworth Road, Long Eaton",
    "sg:city":"Nottingham",
    "sg:classifiers":[
        {
            "category":"Community Center",
            "subcategory":"Social",
            "type":"Public Place"
        }
    ],
    "sg:phone":"+44 115 946 9936",
    "sg:postcode":"NG2 2NG",
    "sg:province":"Nottinghamshire",
    "sg:tags":[
        "frozen",
        "food",
        "freezer",
        "centre"
    ],
    "wof:name":"Iceland Foods Plc",
    "wof:placetype":"venue"
},
  "geometry": {"coordinates":[-1.1513700485,52.9410705566],"type":"Point"}
}