{
  "type": "Feature",
  "properties": {
    "addr:full":"Browick Road Wymondham Norfolk NR18 0QN",
    "addr:postcode":"nr18 0qn",
    "addr:street":"Browick Road",
    "iso:country":"GB",
    "sg:address":"Browick Road",
    "sg:city":"Wymondham",
    "sg:classifiers":[
        {
            "category":"Building & Trades",
            "subcategory":"Construction",
            "type":"Services"
        }
    ],
    "sg:phone":"+44 1953 606545",
    "sg:postcode":"NR18 0QN",
    "sg:province":"Norfolk",
    "sg:tags":[
        "welder"
    ],
    "wof:name":"Kenneth Darkins",
    "wof:placetype":"venue"
},
  "geometry": {"coordinates":[1.123162,52.570454],"type":"Point"}
}