{
  "type": "Feature",
  "properties": {
    "addr:full":"Gledstone Road, West Marton Skipton Lancashire BD23 3UE",
    "addr:postcode":"bd23 3ue",
    "addr:street":"Gledstone Road West",
    "iso:country":"GB",
    "sg:address":"Gledstone Road, West Marton",
    "sg:city":"Skipton",
    "sg:classifiers":[
        {
            "category":"Shopping",
            "subcategory":"Department Store",
            "type":"Retail Goods"
        },
        {
            "category":"Food & Beverages",
            "subcategory":"Supermarket",
            "type":"Retail Goods"
        }
    ],
    "sg:phone":"+44 1282 842402",
    "sg:postcode":"BD23 3UE",
    "sg:province":"Lancashire",
    "wof:name":"The Village Shop",
    "wof:placetype":"venue"
},
  "geometry": {"coordinates":[-2.162505,53.950356],"type":"Point"}
}