{
  "type": "Feature",
  "properties": {
    "addr:full":"343 Brettell Lane Brierley Hill West Midlands DY5 3JU",
    "addr:housenumber":"343",
    "addr:postcode":"dy5 3ju",
    "addr:street":"Brettell Lane",
    "iso:country":"GB",
    "sg:address":"343 Brettell Lane",
    "sg:city":"Brierley Hill",
    "sg:classifiers":[
        {
            "category":"Autos & Motor Vehicles",
            "subcategory":"Auto Supplies",
            "type":"Retail Goods"
        }
    ],
    "sg:phone":"+44 1384 78467",
    "sg:postcode":"DY5 3JU",
    "sg:province":"West Midlands",
    "sg:tags":[
        "part",
        "motorcycle",
        "accessory"
    ],
    "wof:name":"West Midland Motor Cycle Salvage",
    "wof:placetype":"venue"
},
  "geometry": {"coordinates":[-2.1338911057,52.4753646851],"type":"Point"}
}