{
  "type": "Feature",
  "properties": {
    "addr:full":"Wilsons Park, Monsall Rd Manchester Greater Manchester M40 8WN",
    "addr:postcode":"m40 8wn",
    "addr:street":"Monsall Rd",
    "iso:country":"GB",
    "sg:address":"Wilsons Park, Monsall Rd",
    "sg:city":"Manchester",
    "sg:classifiers":[
        {
            "category":"Professional",
            "subcategory":"Employment Agencies",
            "type":"Services"
        }
    ],
    "sg:phone":"+44 161 202 4214",
    "sg:postcode":"M40 8WN",
    "sg:province":"Greater Manchester",
    "sg:tags":[
        "consultant"
    ],
    "wof:name":"Job Club",
    "wof:placetype":"venue"
},
  "geometry": {"coordinates":[-2.2039198875,53.4997215271],"type":"Point"}
}