{
  "type": "Feature",
  "properties": {
    "addr:full":"Group Medical Centre, Carter Rd Shanklin Isle of Wight PO37 7HR",
    "addr:postcode":"po37 7hr",
    "addr:street":"Carter Rd",
    "iso:country":"GB",
    "sg:address":"Group Medical Centre, Carter Rd",
    "sg:city":"Shanklin",
    "sg:classifiers":[
        {
            "category":"Health Services",
            "subcategory":"Doctor",
            "type":"Services"
        }
    ],
    "sg:phone":"+44 1983 862245",
    "sg:postcode":"PO37 7HR",
    "sg:province":"Isle of Wight",
    "sg:tags":[
        "practitioners"
    ],
    "wof:name":"Stone, B E",
    "wof:placetype":"venue"
},
  "geometry": {"coordinates":[-1.1792390347,50.6269760132],"type":"Point"}
}