{
  "type": "Feature",
  "properties": {
    "iso:country":"GB",
    "sg:address":"Unit 26 Wyndham St, Argyle St",
    "sg:city":"Hull",
    "sg:classifiers":[
        {
            "category":"Professional",
            "subcategory":"Art Services",
            "type":"Services"
        },
        {
            "category":"Professional",
            "subcategory":"Printing & Photocopies",
            "type":"Services"
        }
    ],
    "sg:postcode":"HU3 1JH",
    "sg:province":"East Riding of Yorkshire",
    "sg:tags":[
        "photographer",
        "duplicating",
        "copying"
    ],
    "wof:name":"St. Quinten,Steven,",
    "wof:placetype":"venue"
},
  "geometry": {"coordinates":[-0.360169,53.747879],"type":"Point"}
}