{
  "type": "Feature",
  "properties": {
    "addr:full":"64 Ashburton Road Newton Abbot Devon TQ12 1RH",
    "addr:housenumber":"64",
    "addr:postcode":"tq12 1rh",
    "addr:street":"Ashburton Road",
    "iso:country":"GB",
    "sg:address":"64 Ashburton Road",
    "sg:city":"Newton Abbot",
    "sg:classifiers":[
        {
            "category":"Building & Trades",
            "subcategory":"Construction",
            "type":"Services"
        }
    ],
    "sg:phone":"+44 1626 330226",
    "sg:postcode":"TQ12 1RH",
    "sg:province":"Devon",
    "sg:tags":[
        "builder"
    ],
    "wof:name":"Morris & Sons",
    "wof:placetype":"venue"
},
  "geometry": {"coordinates":[-3.627820015,50.5325622559],"type":"Point"}
}