{
  "type": "Feature",
  "properties": {
    "addr:full":"Town Head Hawes North Yorkshire DL8 3RH",
    "addr:postcode":"dl8 3rh",
    "addr:street":"Town",
    "iso:country":"GB",
    "sg:address":"Town Head",
    "sg:city":"Hawes",
    "sg:classifiers":[
        {
            "category":"Travel",
            "subcategory":"Hotels & Motels",
            "type":"Entertainment"
        }
    ],
    "sg:phone":"+44 1969 667645",
    "sg:postcode":"DL8 3RH",
    "sg:province":"North Yorkshire",
    "sg:tags":[
        "house",
        "guest"
    ],
    "wof:name":"Steppe Haugh Guest House",
    "wof:placetype":"venue"
},
  "geometry": {"coordinates":[-2.1994268894,54.3041763306],"type":"Point"}
}