{
  "type": "Feature",
  "properties": {
    "addr:full":"26 Main Street Wigan Lancashire WN1 1BS",
    "addr:housenumber":"26",
    "addr:postcode":"wn1 1bs",
    "addr:street":"Main Street",
    "iso:country":"GB",
    "sg:address":"26 Main Street",
    "sg:city":"Wigan",
    "sg:classifiers":[
        {
            "category":"Retail",
            "subcategory":"Driving School",
            "type":"Services"
        }
    ],
    "sg:phone":"+44 1942 243024",
    "sg:postcode":"WN1 1BS",
    "sg:province":"Lancashire",
    "wof:name":"The British School of Motoring Ltd.",
    "wof:placetype":"venue"
},
  "geometry": {"coordinates":[-2.7052950859,53.501865387],"type":"Point"}
}