{
  "type": "Feature",
  "properties": {
    "addr:full":"The Print Unit, Nile Road Ilkley North Yorkshire LS29 8HJ",
    "addr:housenumber":"unit",
    "addr:postcode":"ls29 8hj",
    "addr:street":"Nile Road",
    "iso:country":"GB",
    "sg:address":"The Print Unit, Nile Road",
    "sg:city":"Ilkley",
    "sg:classifiers":[
        {
            "category":"Professional",
            "type":"Services"
        }
    ],
    "sg:postcode":"LS29 8HJ",
    "sg:province":"North Yorkshire",
    "sg:tags":[
        "directory",
        "pub"
    ],
    "wof:name":"Moorprint Colour Printers",
    "wof:placetype":"venue"
},
  "geometry": {"coordinates":[-1.821754,53.924461],"type":"Point"}
}