{
  "type": "Feature",
  "properties": {
    "addr:full":"44 Warstock Road, Kings Heath Birmingham West Midlands B11 3ER",
    "addr:housenumber":"44",
    "addr:postcode":"b11 3er",
    "addr:street":"Warstock Road",
    "iso:country":"GB",
    "sg:address":"44 Warstock Road, Kings Heath",
    "sg:city":"Birmingham",
    "sg:classifiers":[
        {
            "category":"Home & Garden",
            "subcategory":"Carpets & Floor Coverings",
            "type":"Retail Goods"
        }
    ],
    "sg:phone":"+44 121 436 6900",
    "sg:postcode":"B11 3ER",
    "sg:province":"West Midlands",
    "sg:tags":[
        "carpets",
        "rug",
        "matting"
    ],
    "wof:name":"Traditional Carpets",
    "wof:placetype":"venue"
},
  "geometry": {"coordinates":[-1.9086040258,52.4785957336],"type":"Point"}
}