{
  "type": "Feature",
  "properties": {
    "iso:country":"GB",
    "sg:address":"276 Huddersfield Road",
    "sg:city":"Halifax",
    "sg:classifiers":[
        {
            "category":"Government",
            "subcategory":"Post Office",
            "type":"Public Place"
        }
    ],
    "sg:postcode":"HX3 0PF",
    "sg:province":"West Yorkshire",
    "wof:name":"Huddersfield Rd Post Office",
    "wof:placetype":"venue"
},
  "geometry": {"coordinates":[-1.8578549623,53.7072296143],"type":"Point"}
}