{
  "type": "Feature",
  "properties": {
    "iso:country":"GB",
    "sg:address":"18a Heathcote Street",
    "sg:city":"Nottingham",
    "sg:classifiers":[
        {
            "category":"Professional",
            "subcategory":"Printing & Photocopies",
            "type":"Services"
        }
    ],
    "sg:phone":"+44 115 941 8123",
    "sg:postcode":"NG1 3AA",
    "sg:province":"Nottinghamshire",
    "sg:tags":[
        "printer"
    ],
    "wof:name":"Gauntleys Preston Ltd.",
    "wof:placetype":"venue"
},
  "geometry": {"coordinates":[-1.143503,52.954216],"type":"Point"}
}