{
  "type": "Feature",
  "properties": {
    "addr:full":"Mills Hill Road, Middleton Manchester Greater Manchester M24 2FT",
    "addr:postcode":"m24 2ft",
    "addr:street":"Mills Hill Road",
    "iso:country":"GB",
    "sg:address":"Mills Hill Road, Middleton",
    "sg:city":"Manchester",
    "sg:classifiers":[
        {
            "category":"Shopping",
            "subcategory":"Stationery & Office Supplies",
            "type":"Retail Goods"
        }
    ],
    "sg:phone":"+44 161 655 3464",
    "sg:postcode":"M24 2FT",
    "sg:province":"Greater Manchester",
    "sg:tags":[
        "box",
        "carton"
    ],
    "wof:name":"K E B Packaging Ltd.",
    "wof:placetype":"venue"
},
  "geometry": {"coordinates":[-2.1913239956,53.5494003296],"type":"Point"}
}