{
  "type": "Feature",
  "properties": {
    "iso:country":"GB",
    "sg:address":"Glenside North",
    "sg:city":"Spalding",
    "sg:classifiers":[
        {
            "category":"Building & Trades",
            "subcategory":"Construction",
            "type":"Services"
        }
    ],
    "sg:phone":"+44 1775 724668",
    "sg:postcode":"PE11 3SD",
    "sg:province":"Lincolnshire",
    "sg:tags":[
        "fork",
        "lift",
        "truck"
    ],
    "wof:name":"E & S Fork Lift Sales",
    "wof:placetype":"venue"
},
  "geometry": {"coordinates":[-0.199524,52.813225],"type":"Point"}
}