{
  "type": "Feature",
  "properties": {
    "addr:full":"Sutton Station, High Street Sutton Surrey SM1 1JA",
    "addr:postcode":"sm1 1ja",
    "addr:street":"High Street",
    "iso:country":"GB",
    "sg:address":"Sutton Station, High Street",
    "sg:city":"Sutton",
    "sg:classifiers":[
        {
            "category":"Professional",
            "subcategory":"Printing & Photocopies",
            "type":"Services"
        }
    ],
    "sg:phone":"+44 20 8661 7544",
    "sg:postcode":"SM1 1JA",
    "sg:province":"Surrey",
    "sg:tags":[
        "engraving"
    ],
    "wof:name":"Dawson Engraving",
    "wof:placetype":"venue"
},
  "geometry": {"coordinates":[-0.1975580007,51.3611907959],"type":"Point"}
}