{
  "type": "Feature",
  "properties": {
    "iso:country":"GB",
    "sg:address":"48 New Road, Skewen",
    "sg:city":"Neath",
    "sg:classifiers":[
        {
            "category":"Shopping",
            "subcategory":"Department Store",
            "type":"Retail Goods"
        }
    ],
    "sg:postcode":"SA10 6EP",
    "sg:province":"Neath Port Talbot",
    "wof:name":"Clarke Discount Stores",
    "wof:placetype":"venue"
},
  "geometry": {"coordinates":[-3.8429,51.661209],"type":"Point"}
}