{
  "type": "Feature",
  "properties": {
    "addr:full":"3 Woodgate, Rothley Leicester Leicestershire LE7 7LL",
    "addr:housenumber":"3;rothley",
    "addr:postcode":"le7 7ll",
    "addr:street":"Woodgate",
    "iso:country":"GB",
    "sg:address":"3 Woodgate, Rothley",
    "sg:city":"Leicester",
    "sg:classifiers":[
        {
            "category":"Professional",
            "subcategory":"Art Services",
            "type":"Services"
        }
    ],
    "sg:phone":"+44 116 237 5648",
    "sg:postcode":"LE7 7LL",
    "sg:province":"Leicestershire",
    "sg:tags":[
        "framing"
    ],
    "wof:name":"Acorn Frames & Crafts",
    "wof:placetype":"venue"
},
  "geometry": {"coordinates":[-1.1376290321,52.7092781067],"type":"Point"}
}