{
  "type": "Feature",
  "properties": {
    "addr:full":"Ty Coch Farm, Greenway Rd Cardiff Caerphilly CF3 1QS",
    "addr:postcode":"cf3 1qs",
    "addr:street":"Greenway Rd",
    "iso:country":"GB",
    "sg:address":"Ty Coch Farm, Greenway Rd",
    "sg:city":"Cardiff",
    "sg:classifiers":[
        {
            "category":"Professional",
            "subcategory":"Credit Reporting & Collection",
            "type":"Services"
        }
    ],
    "sg:phone":"+44 29 2033 1142",
    "sg:postcode":"CF3 1QS",
    "sg:province":"Caerphilly",
    "sg:tags":[
        "collecting",
        "agency"
    ],
    "wof:name":"Jd Associates",
    "wof:placetype":"venue"
},
  "geometry": {"coordinates":[-3.1121299267,51.5189399719],"type":"Point"}
}