{
  "type": "Feature",
  "properties": {
    "iso:country":"GB",
    "sg:address":"Chivenor",
    "sg:city":"Barnstaple",
    "sg:classifiers":[
        {
            "category":"Building & Trades",
            "subcategory":"Construction",
            "type":"Services"
        }
    ],
    "sg:phone":"+44 1271 328438",
    "sg:postcode":"EX31 4AY",
    "sg:province":"Devon",
    "sg:tags":[
        "joiner",
        "carpenter"
    ],
    "wof:name":"1st Call the Woodworks",
    "wof:placetype":"venue"
},
  "geometry": {"coordinates":[-4.13253,51.09317],"type":"Point"}
}