{
  "type": "Feature",
  "properties": {
    "iso:country":"GB",
    "sg:address":"58 Fieldway, Pitsea",
    "sg:city":"Basildon",
    "sg:classifiers":[
        {
            "category":"Manufacturing",
            "subcategory":"Tools & Machinery",
            "type":"Manufacturing & Wholesale Goods"
        }
    ],
    "sg:phone":"+44 1702 258959",
    "sg:postcode":"SS13 3DQ",
    "sg:province":"Essex",
    "sg:tags":[
        "society",
        "friendly"
    ],
    "wof:name":"J S Kennedy Services Ltd.",
    "wof:placetype":"venue"
},
  "geometry": {"coordinates":[0.508448,51.561539],"type":"Point"}
}