{
  "type": "Feature",
  "properties": {
    "iso:country":"GB",
    "sg:address":"228 Park Road",
    "sg:city":"Treorchy",
    "sg:classifiers":[
        {
            "category":"Fast Food",
            "type":"Food & Drink"
        }
    ],
    "sg:phone":"+44 1443 775761",
    "sg:postcode":"CF42 6LD",
    "sg:province":"Rhondda, Cynon, Taff",
    "sg:tags":[
        "away",
        "meal",
        "outlet",
        "take"
    ],
    "wof:name":"Cafe De Coral Ltd",
    "wof:placetype":"venue"
},
  "geometry": {"coordinates":[-3.522021,51.651871],"type":"Point"}
}