{
  "type": "Feature",
  "properties": {
    "addr:full":"13 Walters Way London Greater London SE23 3LH",
    "addr:housenumber":"13",
    "addr:postcode":"se23 3lh",
    "addr:street":"Walters Way",
    "iso:country":"GB",
    "sg:address":"13 Walters Way",
    "sg:city":"London",
    "sg:classifiers":[
        {
            "category":"Personal",
            "type":"Services"
        }
    ],
    "sg:phone":"+44 20 8291 4600",
    "sg:postcode":"SE23 3LH",
    "sg:province":"Greater London",
    "sg:tags":[
        "slimming",
        "product"
    ],
    "wof:name":"Herballife Distributor",
    "wof:placetype":"venue"
},
  "geometry": {"coordinates":[-0.049763,51.449291],"type":"Point"}
}