{
  "type": "Feature",
  "properties": {
    "addr:full":"South St Cockermouth Cumbria CA13 9RT",
    "addr:postcode":"ca13 9rt",
    "addr:street":"South St",
    "iso:country":"GB",
    "sg:address":"South St",
    "sg:city":"Cockermouth",
    "sg:classifiers":[
        {
            "category":"Bars & Pubs",
            "type":"Food & Drink"
        }
    ],
    "sg:phone":"+44 1900 824404",
    "sg:postcode":"CA13 9RT",
    "sg:province":"Cumbria",
    "sg:tags":[
        "pubs",
        "inn"
    ],
    "wof:name":"Rizzo's Bar",
    "wof:placetype":"venue"
},
  "geometry": {"coordinates":[-3.3636789322,54.662273407],"type":"Point"}
}