{
  "type": "Feature",
  "properties": {
    "iso:country":"GB",
    "sg:address":"10 Lowfield Avenue, Greasbrough",
    "sg:city":"Rotherham",
    "sg:classifiers":[
        {
            "category":"Building & Trades",
            "subcategory":"Construction",
            "type":"Services"
        }
    ],
    "sg:phone":"+44 1709 554912",
    "sg:postcode":"S61 4PD",
    "sg:province":"South Yorkshire",
    "sg:tags":[
        "decorator",
        "painter"
    ],
    "wof:name":"M Hinch Decorative Paint Services",
    "wof:placetype":"venue"
},
  "geometry": {"coordinates":[-1.363602,53.45071],"type":"Point"}
}