{
  "type": "Feature",
  "properties": {
    "iso:country":"GB",
    "sg:address":"12 Hall Gro",
    "sg:city":"Welwyn Garden City",
    "sg:classifiers":[
        {
            "category":"Recreation",
            "subcategory":"Fishing",
            "type":"Entertainment"
        }
    ],
    "sg:postcode":"AL7 4PH",
    "sg:province":"Hertfordshire",
    "sg:tags":[
        "angling"
    ],
    "wof:name":"Oakwood Angling",
    "wof:placetype":"venue"
},
  "geometry": {"coordinates":[-0.180328995,51.7892456055],"type":"Point"}
}