{
  "type": "Feature",
  "properties": {
    "addr:full":"12 Hall Gro Welwyn Garden City Hertfordshire AL7 4PH",
    "addr:housenumber":"12",
    "addr:postcode":"al7 4ph",
    "addr:street":"Hall Gro;Garden",
    "iso:country":"GB",
    "sg:address":"12 Hall Gro",
    "sg:city":"Welwyn Garden City",
    "sg:classifiers":[
        {
            "category":"Recreation",
            "subcategory":"Fishing",
            "type":"Entertainment"
        }
    ],
    "sg:postcode":"AL7 4PH",
    "sg:province":"Hertfordshire",
    "sg:tags":[
        "angling"
    ],
    "wof:name":"Oakwood Angling",
    "wof:placetype":"venue"
},
  "geometry": {"coordinates":[-0.180328995,51.7892456055],"type":"Point"}
}