{
  "type": "Feature",
  "properties": {
    "iso:country":"GB",
    "sg:address":"Unit 7, Potter Industrial Estate, Coxmoore Close",
    "sg:city":"Fleet",
    "sg:classifiers":[
        {
            "category":"Building & Trades",
            "subcategory":"Plumbing",
            "type":"Services"
        }
    ],
    "sg:phone":"+44 1252 625141",
    "sg:postcode":"GU52 8EJ",
    "sg:province":"Hampshire",
    "sg:tags":[
        "merchant",
        "plumbers'"
    ],
    "wof:name":"Discount Plumbing & Heating",
    "wof:placetype":"venue"
},
  "geometry": {"coordinates":[-0.8423539996,51.2767486572],"type":"Point"}
}