{
  "type": "Feature",
  "properties": {
    "addr:full":"60-62 St. Georges Place Cheltenham Gloucestershire GL50 3PN",
    "addr:housenumber":"60-62",
    "addr:postcode":"gl50 3pn",
    "addr:street":"St. Georges Place",
    "iso:country":"GB",
    "sg:address":"60-62 St. Georges Place",
    "sg:city":"Cheltenham",
    "sg:classifiers":[
        {
            "category":"Retail",
            "subcategory":"Storage",
            "type":"Services"
        }
    ],
    "sg:phone":"+44 1242 529606",
    "sg:postcode":"GL50 3PN",
    "sg:province":"Gloucestershire",
    "sg:tags":[
        "household",
        "removal"
    ],
    "wof:name":"A 2 B Removals",
    "wof:placetype":"venue"
},
  "geometry": {"coordinates":[-2.0786530972,51.9011230469],"type":"Point"}
}