{
  "type": "Feature",
  "properties": {
    "addr:full":"291 High Street, Harbourne Birmingham West Midlands B17 9QH",
    "addr:housenumber":"291",
    "addr:postcode":"b17 9qh",
    "addr:street":"High Street",
    "iso:country":"GB",
    "sg:address":"291 High Street, Harbourne",
    "sg:city":"Birmingham",
    "sg:classifiers":[
        {
            "category":"Retail",
            "subcategory":"Laundry & Dry Cleaning",
            "type":"Services"
        }
    ],
    "sg:phone":"+44 121 427 9895",
    "sg:postcode":"B17 9QH",
    "sg:province":"West Midlands",
    "sg:tags":[
        "alteration"
    ],
    "wof:name":"Harborne Dry Cleaners",
    "wof:placetype":"venue"
},
  "geometry": {"coordinates":[-1.9552880526,52.4582290649],"type":"Point"}
}