{
  "type": "Feature",
  "properties": {
    "addr:full":"5 Crown Royal Industrial Park, Shawcross Street Stockport Cheshire SK1 3EY",
    "addr:housenumber":"5",
    "addr:postcode":"sk1 3ey",
    "addr:street":"Crown;Shawcross Street",
    "iso:country":"GB",
    "sg:address":"5 Crown Royal Industrial Park, Shawcross Street",
    "sg:city":"Stockport",
    "sg:classifiers":[
        {
            "category":"Communications",
            "type":"Services"
        }
    ],
    "sg:phone":"+44 161 474 7171",
    "sg:postcode":"SK1 3EY",
    "sg:province":"Cheshire",
    "sg:tags":[
        "audio-visual"
    ],
    "wof:name":"Impact Rental (North) Ltd.",
    "wof:placetype":"venue"
},
  "geometry": {"coordinates":[-2.149793,53.403809],"type":"Point"}
}