{
  "type": "Feature",
  "properties": {
    "iso:country":"GB",
    "sg:address":"Peaks Hill",
    "sg:city":"Purley",
    "sg:classifiers":[
        {
            "category":"Education",
            "subcategory":"School",
            "type":"Public Place"
        }
    ],
    "sg:phone":"+44 20 8660 4555",
    "sg:postcode":"CR8 3YP",
    "sg:province":"Surrey",
    "sg:tags":[
        "college"
    ],
    "wof:name":"The John Fisher R C School for Boys",
    "wof:placetype":"venue"
},
  "geometry": {"coordinates":[-0.131219,51.344154],"type":"Point"}
}