{
  "type": "Feature",
  "properties": {
    "iso:country":"GB",
    "sg:address":"Alderminster Farm, Alderminster",
    "sg:city":"Stratford-upon-avon",
    "sg:classifiers":[
        {
            "category":"Retail",
            "subcategory":"Portrait Studio",
            "type":"Services"
        },
        {
            "category":"Professional",
            "subcategory":"Art Services",
            "type":"Services"
        }
    ],
    "sg:phone":"+44 1789 450774",
    "sg:postcode":"CV37 8BP",
    "sg:province":"Warwickshire",
    "sg:tags":[
        "photographer",
        "commercial"
    ],
    "wof:name":"Christopher Wright",
    "wof:placetype":"venue"
},
  "geometry": {"coordinates":[-1.66448,52.135159],"type":"Point"}
}