{
  "type": "Feature",
  "properties": {
    "addr:full":"Unit 40, Phoenix Way, Heston Twickenham Greater London TW5 9NB",
    "addr:housenumber":"unit 40",
    "addr:postcode":"tw5 9nb",
    "addr:street":"Phoenix Way",
    "iso:country":"GB",
    "sg:address":"Unit 40, Phoenix Way, Heston",
    "sg:city":"Twickenham",
    "sg:classifiers":[
        {
            "category":"Manufacturing",
            "subcategory":"Motor Vehicles & Parts",
            "type":"Manufacturing & Wholesale Goods"
        }
    ],
    "sg:phone":"+44 116 275 5750",
    "sg:postcode":"TW5 9NB",
    "sg:province":"Greater London",
    "sg:tags":[
        "bearing"
    ],
    "wof:name":"Tri Star Aerospace Inc",
    "wof:placetype":"venue"
},
  "geometry": {"coordinates":[-0.39662,51.486568],"type":"Point"}
}