{
  "type": "Feature",
  "properties": {
    "iso:country":"GB",
    "sg:address":"Waterloo Street, Ironbridge",
    "sg:city":"Telford",
    "sg:classifiers":[
        {
            "category":"Bars & Pubs",
            "type":"Food & Drink"
        }
    ],
    "sg:phone":"+44 1952 432226",
    "sg:postcode":"TF8 7HG",
    "sg:province":"Shropshire",
    "sg:tags":[
        "pubs",
        "house",
        "inn",
        "public",
        "activity"
    ],
    "wof:name":"Bird in Hand",
    "wof:placetype":"venue"
},
  "geometry": {"coordinates":[-2.478728,52.627979],"type":"Point"}
}