{
  "type": "Feature",
  "properties": {
    "addr:full":"227a Beaconsfield Rd Southall Greater London UB1 1DB",
    "addr:housenumber":"227a",
    "addr:postcode":"ub1 1db",
    "addr:street":"Beaconsfield Rd",
    "iso:country":"GB",
    "sg:address":"227a Beaconsfield Rd",
    "sg:city":"Southall",
    "sg:classifiers":[
        {
            "category":"Shopping",
            "subcategory":"Comic Books",
            "type":"Retail Goods"
        }
    ],
    "sg:phone":"+44 20 8813 9057",
    "sg:postcode":"UB1 1DB",
    "sg:province":"Greater London",
    "sg:tags":[
        "jeweller"
    ],
    "wof:name":"Niraj Jewellers",
    "wof:placetype":"venue"
},
  "geometry": {"coordinates":[-0.388566,51.508316],"type":"Point"}
}