{
  "type": "Feature",
  "properties": {
    "iso:country":"GB",
    "sg:address":"7 Groby Rd",
    "sg:city":"Altrincham",
    "sg:classifiers":[
        {
            "category":"Building & Trades",
            "subcategory":"Construction",
            "type":"Services"
        }
    ],
    "sg:phone":"+44 161 928 0942",
    "sg:postcode":"WA14 1RS",
    "sg:province":"Cheshire",
    "sg:tags":[
        "decorator",
        "painter"
    ],
    "wof:name":"Ron Sowerbutts",
    "wof:placetype":"venue"
},
  "geometry": {"coordinates":[-2.354264,53.387264],"type":"Point"}
}