{
  "type": "Feature",
  "properties": {
    "addr:full":"60 Finchley Av Derby Derbyshire DE22 4EU",
    "addr:housenumber":"60",
    "addr:postcode":"de22 4eu",
    "addr:street":"Finchley Av Derby",
    "iso:country":"GB",
    "sg:address":"60 Finchley Av",
    "sg:city":"Derby",
    "sg:classifiers":[
        {
            "category":"Wholesale",
            "subcategory":"Toys & Hobbies",
            "type":"Manufacturing & Wholesale Goods"
        }
    ],
    "sg:phone":"+44 1332 517612",
    "sg:postcode":"DE22 4EU",
    "sg:province":"Derbyshire",
    "sg:tags":[
        "balloon",
        "novelty"
    ],
    "wof:name":"Air Magic",
    "wof:placetype":"venue"
},
  "geometry": {"coordinates":[-1.526646,52.928982],"type":"Point"}
}