{
  "type": "Feature",
  "properties": {
    "iso:country":"GB",
    "sg:address":"Tre Wen Pen Lon, Newborough",
    "sg:city":"Llanfairpwllgwyngyll",
    "sg:classifiers":[
        {
            "category":"Building & Trades",
            "subcategory":"Construction",
            "type":"Services"
        }
    ],
    "sg:phone":"+44 1248 440373",
    "sg:postcode":"LL61 6RS",
    "sg:province":"Isle of Anglesey",
    "sg:tags":[
        "joinery",
        "joiner",
        "carpenter",
        "carpentry"
    ],
    "wof:name":"T W Owen",
    "wof:placetype":"venue"
},
  "geometry": {"coordinates":[-4.361372,53.166332],"type":"Point"}
}