{
  "type": "Feature",
  "properties": {
    "iso:country":"GB",
    "sg:address":"188 Higher Hillgate",
    "sg:city":"Stockport",
    "sg:classifiers":[
        {
            "category":"Fast Food",
            "type":"Food & Drink"
        }
    ],
    "sg:phone":"+44 161 480 4791",
    "sg:postcode":"SK1 3QY",
    "sg:province":"Cheshire",
    "sg:tags":[
        "away",
        "take"
    ],
    "wof:name":"The Butty Box",
    "wof:placetype":"venue"
},
  "geometry": {"coordinates":[-2.1533029079,53.3996887207],"type":"Point"}
}