{
  "type": "Feature",
  "properties": {
    "iso:country":"GB",
    "sg:address":"10 Carleton Street",
    "sg:city":"Skipton",
    "sg:classifiers":[
        {
            "category":"Bars & Pubs",
            "type":"Food & Drink"
        },
        {
            "category":"Community Center",
            "subcategory":"Social",
            "type":"Public Place"
        }
    ],
    "sg:phone":"+44 1756 793186",
    "sg:postcode":"BD23 2AJ",
    "sg:province":"Lancashire",
    "sg:tags":[
        "pubs",
        "house",
        "inn",
        "activity"
    ],
    "wof:name":"Railway Inn",
    "wof:placetype":"venue"
},
  "geometry": {"coordinates":[-2.020624,53.958401],"type":"Point"}
}