{
  "type": "Feature",
  "properties": {
    "addr:full":"262 Walworth Road London Greater London SE17 2TE",
    "addr:housenumber":"262",
    "addr:postcode":"se17 2te",
    "addr:street":"Walworth Road",
    "iso:country":"GB",
    "sg:address":"262 Walworth Road",
    "sg:city":"London",
    "sg:classifiers":[
        {
            "category":"Banks & Credit Unions",
            "subcategory":"Bank",
            "type":"Services"
        }
    ],
    "sg:phone":"+44 20 8301 7302",
    "sg:postcode":"SE17 2TE",
    "sg:province":"Greater London",
    "wof:name":"Woolwich Ltd.",
    "wof:placetype":"venue"
},
  "geometry": {"coordinates":[-0.09532,51.487122],"type":"Point"}
}