{
  "type": "Feature",
  "properties": {
    "addr:full":"4 Bedford Road East, Rock Ferry Birkenhead Merseyside CH42 1LS",
    "addr:housenumber":"4",
    "addr:postcode":"ch42 1ls",
    "addr:street":"Bedford Road East;Ferry",
    "iso:country":"GB",
    "sg:address":"4 Bedford Road East, Rock Ferry",
    "sg:city":"Birkenhead",
    "sg:classifiers":[
        {
            "category":"Arena",
            "subcategory":"Sports Club",
            "type":"Entertainment"
        }
    ],
    "sg:phone":"+44 151 645 3977",
    "sg:postcode":"CH42 1LS",
    "sg:province":"Merseyside",
    "wof:name":"William Thompson",
    "wof:placetype":"venue"
},
  "geometry": {"coordinates":[-3.004119,53.373692],"type":"Point"}
}