{
  "type": "Feature",
  "properties": {
    "addr:full":"Wigan Road, Standish Wigan Lancashire WN6 0AD",
    "addr:postcode":"wn6 0ad",
    "addr:street":"Wigan Road",
    "iso:country":"GB",
    "sg:address":"Wigan Road, Standish",
    "sg:city":"Wigan",
    "sg:classifiers":[
        {
            "category":"Autos & Motor Vehicles",
            "subcategory":"Fuel & Gas Station",
            "type":"Retail Goods"
        }
    ],
    "sg:phone":"+44 1257 427929",
    "sg:postcode":"WN6 0AD",
    "sg:province":"Lancashire",
    "sg:tags":[
        "petrol",
        "filling"
    ],
    "wof:name":"Boars Head Service Station",
    "wof:placetype":"venue"
},
  "geometry": {"coordinates":[-2.659021,53.583691],"type":"Point"}
}