{
  "type": "Feature",
  "properties": {
    "addr:full":"2 Manor Park Parade London Greater London SE13 5PB",
    "addr:housenumber":"2",
    "addr:postcode":"se13 5pb",
    "addr:street":"Manor Park Parade",
    "iso:country":"GB",
    "sg:address":"2 Manor Park Parade",
    "sg:city":"London",
    "sg:classifiers":[
        {
            "category":"Personal",
            "subcategory":"Barber",
            "type":"Services"
        }
    ],
    "sg:phone":"+44 20 8852 5996",
    "sg:postcode":"SE13 5PB",
    "sg:province":"Greater London",
    "sg:tags":[
        "men's",
        "hairdresser"
    ],
    "wof:name":"Dino's",
    "wof:placetype":"venue"
},
  "geometry": {"coordinates":[-0.002282,51.458736],"type":"Point"}
}