{
  "type": "Feature",
  "properties": {
    "iso:country":"GB",
    "sg:address":"Denbigh Avenue",
    "sg:city":"Wallsend",
    "sg:classifiers":[
        {
            "category":"Bars & Pubs",
            "type":"Food & Drink"
        }
    ],
    "sg:phone":"+44 191 295 1267",
    "sg:postcode":"NE28 0PP",
    "sg:province":"Tyne and Wear",
    "sg:tags":[
        "pubs",
        "inn"
    ],
    "wof:name":"Maurentania",
    "wof:placetype":"venue"
},
  "geometry": {"coordinates":[-1.497939,55.003056],"type":"Point"}
}