{
  "type": "Feature",
  "properties": {
    "iso:country":"GB",
    "sg:address":"Lowther Bridge Offices, Aire St",
    "sg:city":"Goole",
    "sg:classifiers":[
        {
            "category":"Freight",
            "type":"Transportation"
        }
    ],
    "sg:phone":"+44 1405 766659",
    "sg:postcode":"DN14 5QW",
    "sg:province":"East Riding of Yorkshire",
    "sg:tags":[
        "haulage",
        "road"
    ],
    "wof:name":"S.A.F Logistics Ltd",
    "wof:placetype":"venue"
},
  "geometry": {"coordinates":[-0.874499,53.704514],"type":"Point"}
}