{
  "type": "Feature",
  "properties": {
    "addr:full":"S J Dark Business Centre, 57 Torquay Rd Paignton Devon TQ3 3DT",
    "addr:housenumber":"57",
    "addr:postcode":"tq3 3dt",
    "addr:street":"Torquay Rd",
    "iso:country":"GB",
    "sg:address":"S J Dark Business Centre, 57 Torquay Rd",
    "sg:city":"Paignton",
    "sg:classifiers":[
        {
            "category":"Government",
            "subcategory":"Office",
            "type":"Public Place"
        }
    ],
    "sg:phone":"+44 1803 663340",
    "sg:postcode":"TQ3 3DT",
    "sg:province":"Devon",
    "sg:tags":[
        "project",
        "gov",
        "community"
    ],
    "wof:name":"Young At Heart Project",
    "wof:placetype":"venue"
},
  "geometry": {"coordinates":[-3.567614,50.438568],"type":"Point"}
}