{
  "type": "Feature",
  "properties": {
    "iso:country":"GB",
    "sg:address":"228 Briscoe La",
    "sg:city":"Manchester",
    "sg:classifiers":[
        {
            "category":"Utilities",
            "type":"Services"
        }
    ],
    "sg:phone":"+44 161 230 1300",
    "sg:postcode":"M40 2XG",
    "sg:province":"Greater Manchester",
    "sg:tags":[
        "internet"
    ],
    "wof:name":"Spindlemedia",
    "wof:placetype":"venue"
},
  "geometry": {"coordinates":[-2.189958,53.494923],"type":"Point"}
}