{
  "type": "Feature",
  "properties": {
    "iso:country":"GB",
    "sg:address":"The Grove",
    "sg:city":"Chipping Campden",
    "sg:classifiers":[
        {
            "category":"Retail",
            "subcategory":"Auto Repair",
            "type":"Services"
        }
    ],
    "sg:postcode":"GL55 6NW",
    "sg:province":"Gloucestershire",
    "sg:tags":[
        "modification",
        "garage"
    ],
    "wof:name":"Hollis,John,Ebrington Garage",
    "wof:placetype":"venue"
},
  "geometry": {"coordinates":[-1.782310009,52.0458984375],"type":"Point"}
}