{
  "type": "Feature",
  "properties": {
    "addr:full":"34 Woolbrook Road Sidmouth Devon EX10 9UZ",
    "addr:housenumber":"34",
    "addr:postcode":"ex10 9uz",
    "addr:street":"Woolbrook Road",
    "iso:country":"GB",
    "sg:address":"34 Woolbrook Road",
    "sg:city":"Sidmouth",
    "sg:classifiers":[
        {
            "category":"Shopping",
            "subcategory":"News",
            "type":"Retail Goods"
        }
    ],
    "sg:phone":"+44 1395 514224",
    "sg:postcode":"EX10 9UZ",
    "sg:province":"Devon",
    "sg:tags":[
        "newsagent"
    ],
    "wof:name":"Woolbrook News",
    "wof:placetype":"venue"
},
  "geometry": {"coordinates":[-3.2410149574,50.6942558289],"type":"Point"}
}