{
  "type": "Feature",
  "properties": {
    "iso:country":"GB",
    "sg:address":"Blaenant Industrial Estate, Blaenavon Road, Brynmawr",
    "sg:city":"Ebbw Vale",
    "sg:classifiers":[
        {
            "category":"Manufacturing",
            "subcategory":"Rubber & Plastics",
            "type":"Manufacturing & Wholesale Goods"
        }
    ],
    "sg:phone":"+44 1495 310583",
    "sg:postcode":"NP23 4BX",
    "sg:province":"Blaenau Gwent",
    "sg:tags":[
        "product"
    ],
    "wof:name":"Performance Masterbatches Ltd.",
    "wof:placetype":"venue"
},
  "geometry": {"coordinates":[-3.169904,51.796413],"type":"Point"}
}