{
  "type": "Feature",
  "properties": {
    "iso:country":"GB",
    "sg:address":"Caldwell House, Lyttleton Street",
    "sg:city":"West Bromwich",
    "sg:classifiers":[
        {
            "category":"Shopping",
            "subcategory":"Department Store",
            "type":"Retail Goods"
        }
    ],
    "sg:postcode":"B70 7SF",
    "sg:province":"West Midlands",
    "wof:name":"Caldwell Stores",
    "wof:placetype":"venue"
},
  "geometry": {"coordinates":[-1.99886,52.513557],"type":"Point"}
}