{
  "type": "Feature",
  "properties": {
    "addr:full":"Mendips Rd Fareham Hampshire PO14 1QD",
    "addr:postcode":"po14 1qd",
    "addr:street":"Mendips Rd",
    "iso:country":"GB",
    "sg:address":"Mendips Rd",
    "sg:city":"Fareham",
    "sg:classifiers":[
        {
            "category":"Place Of Worship",
            "type":"Public Place"
        }
    ],
    "sg:phone":"+44 1329 239319",
    "sg:postcode":"PO14 1QD",
    "sg:province":"Hampshire",
    "wof:name":"Our Saviour Lutheran Church",
    "wof:placetype":"venue"
},
  "geometry": {"coordinates":[-1.204984,50.84745],"type":"Point"}
}