{
  "type": "Feature",
  "properties": {
    "addr:full":"19 Chetwode Ave, Monkston Milton Keynes Buckinghamshire MK10 9EH",
    "addr:housenumber":"19",
    "addr:postcode":"mk10 9eh",
    "addr:street":"Chetwode Ave",
    "iso:country":"GB",
    "sg:address":"19 Chetwode Ave, Monkston",
    "sg:city":"Milton Keynes",
    "sg:classifiers":[
        {
            "category":"Professional",
            "subcategory":"Management & Consulting",
            "type":"Services"
        }
    ],
    "sg:phone":"+44 1908 232499",
    "sg:postcode":"MK10 9EH",
    "sg:province":"Buckinghamshire",
    "sg:tags":[
        "marketing",
        "consultant"
    ],
    "wof:name":"Pixie Cards Ltd",
    "wof:placetype":"venue"
},
  "geometry": {"coordinates":[-0.696157,52.036011],"type":"Point"}
}