{
  "type": "Feature",
  "properties": {
    "addr:full":"Ridings House, Depot Lane, Seamer Road Scarborough North Yorkshire YO12 4EB",
    "addr:postcode":"yo12 4eb",
    "addr:street":"Depot Lane Seamer Road",
    "iso:country":"GB",
    "sg:address":"Ridings House, Depot Lane, Seamer Road",
    "sg:city":"Scarborough",
    "sg:classifiers":[
        {
            "category":"Shopping",
            "subcategory":"Clothing, Apparel, & Fashions",
            "type":"Retail Goods"
        }
    ],
    "sg:phone":"+44 1723 501669",
    "sg:postcode":"YO12 4EB",
    "sg:province":"North Yorkshire",
    "sg:tags":[
        "leather",
        "garment"
    ],
    "wof:name":"Icon Designs",
    "wof:placetype":"venue"
},
  "geometry": {"coordinates":[-0.4151189923,54.2728157043],"type":"Point"}
}