{
  "type": "Feature",
  "properties": {
    "addr:full":"27 Cliffe Road, Walkley Sheffield South Yorkshire S6 5DR",
    "addr:housenumber":"27",
    "addr:postcode":"s6 5dr",
    "addr:street":"Cliffe Road",
    "iso:country":"GB",
    "sg:address":"27 Cliffe Road, Walkley",
    "sg:city":"Sheffield",
    "sg:classifiers":[
        {
            "category":"Building & Trades",
            "subcategory":"Construction",
            "type":"Services"
        }
    ],
    "sg:postcode":"S6 5DR",
    "sg:province":"South Yorkshire",
    "sg:tags":[
        "dry",
        "lining",
        "plasterers",
        "screeders"
    ],
    "wof:name":"Alan Cowen",
    "wof:placetype":"venue"
},
  "geometry": {"coordinates":[-1.513874,53.392689],"type":"Point"}
}