{
  "type": "Feature",
  "properties": {
    "iso:country":"GB",
    "sg:address":"3 - 4 Little Portland Street",
    "sg:city":"London",
    "sg:classifiers":[
        {
            "category":"Manufacturing",
            "subcategory":"Apparel",
            "type":"Manufacturing & Wholesale Goods"
        }
    ],
    "sg:phone":"+44 20 7580 8981",
    "sg:postcode":"W1W 7JB",
    "sg:province":"Greater London",
    "sg:tags":[
        "garment",
        "designer"
    ],
    "wof:name":"Miss Sam Plc",
    "wof:placetype":"venue"
},
  "geometry": {"coordinates":[-0.140603,51.517422],"type":"Point"}
}