{
  "type": "Feature",
  "properties": {
    "addr:full":"60 Dunchurch Road Rugby Warwickshire CV22 6AD",
    "addr:housenumber":"60",
    "addr:postcode":"cv22 6ad",
    "addr:street":"Dunchurch Road",
    "iso:country":"GB",
    "sg:address":"60 Dunchurch Road",
    "sg:city":"Rugby",
    "sg:classifiers":[
        {
            "category":"Retail",
            "subcategory":"Repair Shop",
            "type":"Services"
        }
    ],
    "sg:phone":"+44 1788 551211",
    "sg:postcode":"CV22 6AD",
    "sg:province":"Warwickshire",
    "sg:tags":[
        "plant",
        "machinery"
    ],
    "wof:name":"Cossar Jetter Services",
    "wof:placetype":"venue"
},
  "geometry": {"coordinates":[-1.2647490501,52.3689117432],"type":"Point"}
}