{
  "type": "Feature",
  "properties": {
    "addr:full":"Market Place Sutton-in-ashfield Nottinghamshire NG17 1AQ",
    "addr:postcode":"ng17 1aq",
    "addr:street":"Market Place",
    "iso:country":"GB",
    "sg:address":"Market Place",
    "sg:city":"Sutton-in-ashfield",
    "sg:classifiers":[
        {
            "category":"Bars & Pubs",
            "type":"Food & Drink"
        },
        {
            "category":"Community Center",
            "subcategory":"Social",
            "type":"Public Place"
        }
    ],
    "sg:phone":"+44 1623 559501",
    "sg:postcode":"NG17 1AQ",
    "sg:province":"Nottinghamshire",
    "sg:tags":[
        "pubs",
        "house",
        "inn",
        "activity"
    ],
    "wof:name":"The Denmans Head",
    "wof:placetype":"venue"
},
  "geometry": {"coordinates":[-1.2642339468,53.1251296997],"type":"Point"}
}