{
  "type": "Feature",
  "properties": {
    "addr:full":"67-70 Charlotte Road London Greater London EC2A 3PE",
    "addr:housenumber":"67-70",
    "addr:postcode":"ec2a 3pe",
    "addr:street":"Charlotte Road",
    "iso:country":"GB",
    "sg:address":"67-70 Charlotte Road",
    "sg:city":"London",
    "sg:classifiers":[
        {
            "category":"Government",
            "subcategory":"Post Office",
            "type":"Public Place"
        }
    ],
    "sg:phone":"+44 20 7129 4200",
    "sg:postcode":"EC2A 3PE",
    "sg:province":"Greater London",
    "sg:tags":[
        "messenger",
        "courier"
    ],
    "wof:name":"Arrow Express Ltd.",
    "wof:placetype":"venue"
},
  "geometry": {"coordinates":[-0.081022,51.526382],"type":"Point"}
}