{
  "type": "Feature",
  "properties": {
    "addr:full":"44 Market Street Chorley Lancashire PR7 2SE",
    "addr:housenumber":"44",
    "addr:postcode":"pr7 2se",
    "addr:street":"Market Street",
    "iso:country":"GB",
    "sg:address":"44 Market Street",
    "sg:city":"Chorley",
    "sg:classifiers":[
        {
            "category":"Banks & Credit Unions",
            "subcategory":"Financial Services",
            "type":"Services"
        }
    ],
    "sg:phone":"+44 1257 262151",
    "sg:postcode":"PR7 2SE",
    "sg:province":"Lancashire",
    "sg:tags":[
        "building",
        "society"
    ],
    "wof:name":"Cheshire Building Society",
    "wof:placetype":"venue"
},
  "geometry": {"coordinates":[-2.6321089268,53.6520385742],"type":"Point"}
}