{
  "type": "Feature",
  "properties": {
    "iso:country":"GB",
    "sg:address":"45 Overstone Road, Moulton",
    "sg:city":"Northampton",
    "sg:classifiers":[
        {
            "category":"Building & Trades",
            "subcategory":"Landscaping Services",
            "type":"Services"
        }
    ],
    "sg:phone":"+44 1604 644394",
    "sg:postcode":"NN3 7UU",
    "sg:province":"Northamptonshire",
    "sg:tags":[
        "pond",
        "aquarium"
    ],
    "wof:name":"Nicky's Fish",
    "wof:placetype":"venue"
},
  "geometry": {"coordinates":[-0.8421949744,52.2890434265],"type":"Point"}
}