{
  "type": "Feature",
  "properties": {
    "addr:full":"6 George Street Hastings East Sussex TN34 3EG",
    "addr:housenumber":"6",
    "addr:postcode":"tn34 3eg",
    "addr:street":"George Street",
    "iso:country":"GB",
    "sg:address":"6 George Street",
    "sg:city":"Hastings",
    "sg:classifiers":[
        {
            "category":"Shopping",
            "subcategory":"Hobbies, Toys, & Games",
            "type":"Retail Goods"
        }
    ],
    "sg:phone":"+44 1424 426311",
    "sg:postcode":"TN34 3EG",
    "sg:province":"East Sussex",
    "sg:tags":[
        "collectors'",
        "item"
    ],
    "wof:name":"Mr Merchandise",
    "wof:placetype":"venue"
},
  "geometry": {"coordinates":[0.589198,50.856087],"type":"Point"}
}