{
  "type": "Feature",
  "properties": {
    "addr:full":"6 South Queen Street, Morley Leeds West Yorkshire LS27 9EW",
    "addr:housenumber":"6",
    "addr:postcode":"ls27 9ew",
    "addr:street":"South Queen Street",
    "iso:country":"GB",
    "sg:address":"6 South Queen Street, Morley",
    "sg:city":"Leeds",
    "sg:classifiers":[
        {
            "category":"Travel",
            "subcategory":"Travel Agent",
            "type":"Entertainment"
        }
    ],
    "sg:phone":"+44 113 253 4720",
    "sg:postcode":"LS27 9EW",
    "sg:province":"West Yorkshire",
    "sg:tags":[
        "agency",
        "activity"
    ],
    "wof:name":"Wallace Arnold Travel Shop",
    "wof:placetype":"venue"
},
  "geometry": {"coordinates":[-1.59942,53.742748],"type":"Point"}
}