{
  "type": "Feature",
  "properties": {
    "addr:full":"The Linen Hall, 162 Regent Street London Greater London W1B 5TG",
    "addr:housenumber":"162",
    "addr:postcode":"w1b 5tg",
    "addr:street":"Regent Street",
    "iso:country":"GB",
    "sg:address":"The Linen Hall, 162 Regent Street",
    "sg:city":"London",
    "sg:classifiers":[
        {
            "category":"Professional",
            "subcategory":"Employment Agencies",
            "type":"Services"
        }
    ],
    "sg:phone":"+44 20 7297 2059",
    "sg:postcode":"W1B 5TG",
    "sg:province":"Greater London",
    "sg:tags":[
        "consultant"
    ],
    "wof:name":"Harpur Accountancy Recruitment Ltd.",
    "wof:placetype":"venue"
},
  "geometry": {"coordinates":[-0.139375,51.511906],"type":"Point"}
}