{
  "type": "Feature",
  "properties": {
    "addr:full":"Momenta House, Monument Hill Weybridge Surrey KT13 8RT",
    "addr:postcode":"kt13 8rt",
    "addr:street":"Monument Hill Weybridge",
    "iso:country":"GB",
    "sg:address":"Momenta House, Monument Hill",
    "sg:city":"Weybridge",
    "sg:classifiers":[
        {
            "category":"Professional",
            "subcategory":"Management & Consulting",
            "type":"Services"
        }
    ],
    "sg:phone":"+44 1932 835500",
    "sg:postcode":"KT13 8RT",
    "sg:province":"Surrey",
    "sg:tags":[
        "marketing",
        "consultant"
    ],
    "wof:name":"Officesmart Ltd.",
    "wof:placetype":"venue"
},
  "geometry": {"coordinates":[-0.4553540051,51.3736114502],"type":"Point"}
}