{
  "type": "Feature",
  "properties": {
    "iso:country":"GB",
    "sg:address":"Lypiatt Street",
    "sg:city":"Cheltenham",
    "sg:classifiers":[
        {
            "category":"Utilities",
            "subcategory":"Mobile Phone",
            "type":"Services"
        }
    ],
    "sg:phone":"+44 1242 514940",
    "sg:postcode":"GL50 2UB",
    "sg:province":"Gloucestershire",
    "sg:tags":[
        "battery",
        "supplier"
    ],
    "wof:name":"Groves Batteries",
    "wof:placetype":"venue"
},
  "geometry": {"coordinates":[-2.0882050991,51.8914031982],"type":"Point"}
}