{
  "type": "Feature",
  "properties": {
    "addr:full":"234-236 Edleston Road Crewe Cheshire CW2 7EH",
    "addr:housenumber":"234-236",
    "addr:postcode":"cw2 7eh",
    "addr:street":"Edleston Road",
    "iso:country":"GB",
    "sg:address":"234-236 Edleston Road",
    "sg:city":"Crewe",
    "sg:classifiers":[
        {
            "category":"Shopping",
            "subcategory":"Clothing, Apparel, & Fashions",
            "type":"Retail Goods"
        }
    ],
    "sg:phone":"+44 1270 256364",
    "sg:postcode":"CW2 7EH",
    "sg:province":"Cheshire",
    "sg:tags":[
        "menswear"
    ],
    "wof:name":"Eric Barnes Menswear",
    "wof:placetype":"venue"
},
  "geometry": {"coordinates":[-2.4420199394,53.0952453613],"type":"Point"}
}