{
  "type": "Feature",
  "properties": {
    "addr:full":"9 Cleveland Street Chorley Lancashire PR7 1BH",
    "addr:housenumber":"9",
    "addr:postcode":"pr7 1bh",
    "addr:street":"Cleveland Street",
    "iso:country":"GB",
    "sg:address":"9 Cleveland Street",
    "sg:city":"Chorley",
    "sg:classifiers":[
        {
            "category":"Shopping",
            "subcategory":"Clothing, Apparel, & Fashions",
            "type":"Retail Goods"
        }
    ],
    "sg:phone":"+44 1257 274492",
    "sg:postcode":"PR7 1BH",
    "sg:province":"Lancashire",
    "sg:tags":[
        "ladieswear"
    ],
    "wof:name":"Dorothy Perkins",
    "wof:placetype":"venue"
},
  "geometry": {"coordinates":[-2.631264925,53.6539421082],"type":"Point"}
}