{
  "type": "Feature",
  "properties": {
    "addr:full":"63 Hesketh Lane, Tarleton Preston Lancashire PR4 6AQ",
    "addr:housenumber":"63",
    "addr:postcode":"pr4 6aq",
    "addr:street":"Hesketh Lane",
    "iso:country":"GB",
    "sg:address":"63 Hesketh Lane, Tarleton",
    "sg:city":"Preston",
    "sg:classifiers":[
        {
            "category":"Utilities",
            "subcategory":"Refuse",
            "type":"Services"
        }
    ],
    "sg:phone":"+44 1772 812394",
    "sg:postcode":"PR4 6AQ",
    "sg:province":"Lancashire",
    "sg:tags":[
        "skip",
        "hire"
    ],
    "wof:name":"R W Morris (Haulage) Ltd.",
    "wof:placetype":"venue"
},
  "geometry": {"coordinates":[-2.832061,53.685375],"type":"Point"}
}