{
  "type": "Feature",
  "properties": {
    "addr:full":"33 Powley Rd Sheffield South Yorkshire S6 1DD",
    "addr:housenumber":"33",
    "addr:postcode":"s6 1dd",
    "addr:street":"Powley Rd",
    "iso:country":"GB",
    "sg:address":"33 Powley Rd",
    "sg:city":"Sheffield",
    "sg:classifiers":[
        {
            "category":"Bus Charters",
            "type":"Transportation"
        }
    ],
    "sg:phone":"+44 114 234 8435",
    "sg:postcode":"S6 1DD",
    "sg:province":"South Yorkshire",
    "sg:tags":[
        "mini",
        "hire",
        "leasing"
    ],
    "wof:name":"Aero VIP Travel",
    "wof:placetype":"venue"
},
  "geometry": {"coordinates":[-1.4965529442,53.4275588989],"type":"Point"}
}