{
  "type": "Feature",
  "properties": {
    "addr:full":"Wood Lane, Cuddington Northwich Cheshire CW8 2TL",
    "addr:postcode":"cw8 2tl",
    "addr:street":"Wood Lane",
    "iso:country":"GB",
    "sg:address":"Wood Lane, Cuddington",
    "sg:city":"Northwich",
    "sg:classifiers":[
        {
            "category":"Building & Trades",
            "subcategory":"Cleaning & Sanitation",
            "type":"Services"
        }
    ],
    "sg:postcode":"CW8 2TL",
    "sg:province":"Cheshire",
    "sg:tags":[
        "sweep",
        "chimney"
    ],
    "wof:name":"Leslie Fry",
    "wof:placetype":"venue"
},
  "geometry": {"coordinates":[-2.602213,53.238754],"type":"Point"}
}