{
  "type": "Feature",
  "properties": {
    "iso:country":"GB",
    "sg:address":"Unit 7 Catford Mews, 32 Winslade Way Catford",
    "sg:city":"London",
    "sg:classifiers":[
        {
            "category":"Personal",
            "type":"Services"
        }
    ],
    "sg:postcode":"SE6 4JU",
    "sg:province":"Greater London",
    "sg:tags":[
        "wedding"
    ],
    "wof:name":"Madeleine's",
    "wof:placetype":"venue"
},
  "geometry": {"coordinates":[-0.02068,51.446159],"type":"Point"}
}