{
  "type": "Feature",
  "properties": {
    "addr:full":"61 South Clerk Street Edinburgh City of Edinburgh EH8 9PP",
    "addr:housenumber":"61",
    "addr:postcode":"eh8 9pp",
    "addr:street":"South Clerk Street",
    "iso:country":"GB",
    "sg:address":"61 South Clerk Street",
    "sg:city":"Edinburgh",
    "sg:classifiers":[
        {
            "category":"Shopping",
            "subcategory":"Musical Instruments",
            "type":"Retail Goods"
        },
        {
            "category":"Shopping",
            "subcategory":"Computers & Home Electronics",
            "type":"Retail Goods"
        }
    ],
    "sg:phone":"+44 131 667 3844",
    "sg:postcode":"EH8 9PP",
    "sg:province":"City of Edinburgh",
    "sg:tags":[
        "music",
        "television",
        "sheet",
        "sale"
    ],
    "wof:name":"Drum Central Ltd",
    "wof:placetype":"venue"
},
  "geometry": {"coordinates":[-3.1796860695,55.9396743774],"type":"Point"}
}