{
  "type": "Feature",
  "properties": {
    "addr:full":"44 Preston St Brighton East Sussex BN1 2HP",
    "addr:housenumber":"44",
    "addr:postcode":"bn1 2hp",
    "addr:street":"Preston St",
    "iso:country":"GB",
    "sg:address":"44 Preston St",
    "sg:city":"Brighton",
    "sg:classifiers":[
        {
            "category":"Cafe",
            "type":"Food & Drink"
        }
    ],
    "sg:phone":"+44 1273 723846",
    "sg:postcode":"BN1 2HP",
    "sg:province":"East Sussex",
    "sg:tags":[
        "tea",
        "room"
    ],
    "wof:name":"Capone's",
    "wof:placetype":"venue"
},
  "geometry": {"coordinates":[-0.150892,50.824093],"type":"Point"}
}