{
  "type": "Feature",
  "properties": {
    "iso:country":"GB",
    "sg:address":"Futhercroft Surgery, Minsterley Road, Pontesbury",
    "sg:city":"Shrewsbury",
    "sg:classifiers":[
        {
            "category":"Retail",
            "subcategory":"Veterinary Services",
            "type":"Services"
        }
    ],
    "sg:phone":"+44 1743 790289",
    "sg:postcode":"SY5 0QJ",
    "sg:province":"Shropshire",
    "sg:tags":[
        "surgeon"
    ],
    "wof:name":"Abbey Veternary Surgery",
    "wof:placetype":"venue"
},
  "geometry": {"coordinates":[-2.925398,52.638226],"type":"Point"}
}