{
  "type": "Feature",
  "properties": {
    "addr:full":"9 Birmingham Rd Birmingham Warwickshire B46 1SP",
    "addr:housenumber":"9",
    "addr:postcode":"b46 1sp",
    "addr:street":"Birmingham Rd",
    "iso:country":"GB",
    "sg:address":"9 Birmingham Rd",
    "sg:city":"Birmingham",
    "sg:classifiers":[
        {
            "category":"Shopping",
            "subcategory":"Pharmacy",
            "type":"Retail Goods"
        }
    ],
    "sg:phone":"+44 121 747 2155",
    "sg:postcode":"B46 1SP",
    "sg:province":"Warwickshire",
    "sg:tags":[
        "pharmacist",
        "chemist"
    ],
    "wof:name":"Lloyds Chemist",
    "wof:placetype":"venue"
},
  "geometry": {"coordinates":[-1.741786,52.517933],"type":"Point"}
}