{
  "type": "Feature",
  "properties": {
    "addr:full":"First Floor, 18 Childwall Abbey Road, Childwall Liverpool Merseyside L16 0JN",
    "addr:housenumber":"18",
    "addr:postcode":"l16 0jn",
    "addr:street":"Abbey Road",
    "iso:country":"GB",
    "sg:address":"First Floor, 18 Childwall Abbey Road, Childwall",
    "sg:city":"Liverpool",
    "sg:classifiers":[
        {
            "category":"Professional",
            "subcategory":"Accounting & Tax Preparation",
            "type":"Services"
        }
    ],
    "sg:phone":"+44 151 737 1992",
    "sg:postcode":"L16 0JN",
    "sg:province":"Merseyside",
    "sg:tags":[
        "accountant"
    ],
    "wof:name":"Sutre Accountancy Services",
    "wof:placetype":"venue"
},
  "geometry": {"coordinates":[-2.8913600445,53.3943481445],"type":"Point"}
}