{
  "type": "Feature",
  "properties": {
    "iso:country":"GB",
    "sg:address":"Hafandeg, Penygraig, Rhosllanerchrugog",
    "sg:city":"Wrexham",
    "sg:classifiers":[
        {
            "category":"Organizations",
            "subcategory":"Non-profit Organization",
            "type":"Services"
        }
    ],
    "sg:phone":"+44 1978 840063",
    "sg:postcode":"LL14 1LR",
    "sg:province":"Wrexham",
    "sg:tags":[
        "organisation",
        "voluntary",
        "charity"
    ],
    "wof:name":"Leukaemia Research Fund",
    "wof:placetype":"venue"
},
  "geometry": {"coordinates":[-3.05422,53.007999],"type":"Point"}
}