{
  "type": "Feature",
  "properties": {
    "addr:full":"P O Box 35 Wilmslow Cheshire SK9 2LW",
    "addr:housenumber":"box 35",
    "addr:postcode":"sk9 2lw",
    "addr:street":"P O",
    "iso:country":"GB",
    "sg:address":"P O Box 35",
    "sg:city":"Wilmslow",
    "sg:classifiers":[
        {
            "category":"Professional",
            "subcategory":"Business Services",
            "type":"Services"
        }
    ],
    "sg:phone":"+44 1625 535595",
    "sg:postcode":"SK9 2LW",
    "sg:province":"Cheshire",
    "sg:tags":[
        "hospitality",
        "corporate"
    ],
    "wof:name":"Corporate Initiatives Ltd",
    "wof:placetype":"venue"
},
  "geometry": {"coordinates":[-2.2278969288,53.3267974854],"type":"Point"}
}