{
  "type": "Feature",
  "properties": {
    "addr:full":"Poldurn, Penhale Road, Penwithick St Austell Cornwall PL26 8UP",
    "addr:postcode":"pl26 8up",
    "addr:street":"Penhale Road",
    "iso:country":"GB",
    "sg:address":"Poldurn, Penhale Road, Penwithick",
    "sg:city":"St Austell",
    "sg:classifiers":[
        {
            "category":"Professional",
            "subcategory":"Computer Services",
            "type":"Services"
        }
    ],
    "sg:postcode":"PL26 8UP",
    "sg:province":"Cornwall",
    "sg:tags":[
        "system",
        "software"
    ],
    "wof:name":"Poldurn Systems",
    "wof:placetype":"venue"
},
  "geometry": {"coordinates":[-4.7799038887,50.3705749512],"type":"Point"}
}