{
  "type": "Feature",
  "properties": {
    "iso:country":"GB",
    "sg:address":"6 Commercial Street",
    "sg:city":"Cinderford",
    "sg:classifiers":[
        {
            "category":"Fast Food",
            "type":"Food & Drink"
        },
        {
            "category":"Food & Beverages",
            "subcategory":"Meat & Fish",
            "type":"Retail Goods"
        },
        {
            "category":"Food & Beverages",
            "subcategory":"Groceries & Convenience Stores",
            "type":"Retail Goods"
        }
    ],
    "sg:phone":"+44 1594 822234",
    "sg:postcode":"GL14 2RR",
    "sg:province":"Gloucestershire",
    "sg:tags":[
        "shop",
        "away",
        "take",
        "chip"
    ],
    "wof:name":"Vi's Fish & Chips",
    "wof:placetype":"venue"
},
  "geometry": {"coordinates":[-2.49981,51.823257],"type":"Point"}
}