{
  "type": "Feature",
  "properties": {
    "iso:country":"GB",
    "sg:address":"Norton Bury Farm, Nortonbury",
    "sg:city":"Letchworth",
    "sg:classifiers":[
        {
            "category":"Organizations",
            "subcategory":"Membership Organization",
            "type":"Services"
        }
    ],
    "sg:postcode":"SG6 1AN",
    "sg:province":"Hertfordshire",
    "sg:tags":[
        "club"
    ],
    "wof:name":"Norton Bury Scout & Guide Activity Centre",
    "wof:placetype":"venue"
},
  "geometry": {"coordinates":[-0.2042589933,51.9987716675],"type":"Point"}
}