{
  "type": "Feature",
  "properties": {
    "iso:country":"GB",
    "sg:address":"22 Esplanade, Broughty Ferry",
    "sg:city":"Dundee",
    "sg:classifiers":[
        {
            "category":"Travel",
            "subcategory":"Hotels & Motels",
            "type":"Entertainment"
        }
    ],
    "sg:phone":"+44 1382 775537",
    "sg:postcode":"DD5 2EN",
    "sg:province":"Angus",
    "wof:name":"Beach House Hotel",
    "wof:placetype":"venue"
},
  "geometry": {"coordinates":[-2.862649,56.468719],"type":"Point"}
}