{
  "type": "Feature",
  "properties": {
    "addr:full":"Jenny Field Dr Harrogate North Yorkshire HG3 2XQ",
    "addr:postcode":"hg3 2xq",
    "addr:street":"Jenny Field Dr",
    "iso:country":"GB",
    "sg:address":"Jenny Field Dr",
    "sg:city":"Harrogate",
    "sg:classifiers":[
        {
            "category":"Shopping",
            "subcategory":"Pharmacy",
            "type":"Retail Goods"
        }
    ],
    "sg:phone":"+44 1423 508050",
    "sg:postcode":"HG3 2XQ",
    "sg:province":"North Yorkshire",
    "sg:tags":[
        "pharmacist",
        "chemist"
    ],
    "wof:name":"K R Rutter Ltd",
    "wof:placetype":"venue"
},
  "geometry": {"coordinates":[-1.5708990097,54.0034408569],"type":"Point"}
}