{
  "type": "Feature",
  "properties": {
    "addr:full":"Unit 4b The Precinct, Candleby Lane, Cotgrave Nottingham Nottinghamshire NG12 3JG",
    "addr:housenumber":"unit 4b",
    "addr:postcode":"ng12 3jg",
    "addr:street":"The Precinct Candleby Lane",
    "iso:country":"GB",
    "sg:address":"Unit 4b The Precinct, Candleby Lane, Cotgrave",
    "sg:city":"Nottingham",
    "sg:classifiers":[
        {
            "category":"Shopping",
            "subcategory":"Pharmacy",
            "type":"Retail Goods"
        }
    ],
    "sg:phone":"+44 115 989 2436",
    "sg:postcode":"NG12 3JG",
    "sg:province":"Nottinghamshire",
    "sg:tags":[
        "pharmacist",
        "chemist"
    ],
    "wof:name":"Gordon Davis (Chemists) Ltd.",
    "wof:placetype":"venue"
},
  "geometry": {"coordinates":[-1.0474770069,52.9091262817],"type":"Point"}
}