{
  "type": "Feature",
  "properties": {
    "iso:country":"GB",
    "sg:address":"20 Queens Street",
    "sg:city":"Skipton",
    "sg:classifiers":[
        {
            "category":"Building & Trades",
            "subcategory":"Cleaning & Sanitation",
            "type":"Services"
        }
    ],
    "sg:phone":"+44 1756 790739",
    "sg:postcode":"BD23 1HE",
    "sg:province":"Lancashire",
    "sg:tags":[
        "sweep",
        "chimney"
    ],
    "wof:name":"CHIMNEY SWEEP",
    "wof:placetype":"venue"
},
  "geometry": {"coordinates":[-2.006949,53.962471],"type":"Point"}
}