{
  "type": "Feature",
  "properties": {
    "addr:full":"The Buttermarket, 22-23 North Street Chichester West Sussex PO19 1LQ",
    "addr:housenumber":"22-23",
    "addr:postcode":"po19 1lq",
    "addr:street":"North Street",
    "iso:country":"GB",
    "sg:address":"The Buttermarket, 22-23 North Street",
    "sg:city":"Chichester",
    "sg:classifiers":[
        {
            "category":"Farming",
            "subcategory":"Fish & Marine Products",
            "type":"Manufacturing & Wholesale Goods"
        }
    ],
    "sg:phone":"+44 1243 776538",
    "sg:postcode":"PO19 1LQ",
    "sg:province":"West Sussex",
    "sg:tags":[
        "fishmonger"
    ],
    "wof:name":"Old City Fishshop",
    "wof:placetype":"venue"
},
  "geometry": {"coordinates":[-0.7754290104,50.8361663818],"type":"Point"}
}