{
  "type": "Feature",
  "properties": {
    "addr:full":"The Square, Portscatho Truro Cornwall TR2 5HW",
    "addr:postcode":"tr2 5hw",
    "addr:street":"The Square Portscatho",
    "iso:country":"GB",
    "sg:address":"The Square, Portscatho",
    "sg:city":"Truro",
    "sg:classifiers":[
        {
            "category":"Bars & Pubs",
            "type":"Food & Drink"
        }
    ],
    "sg:postcode":"TR2 5HW",
    "sg:province":"Cornwall",
    "sg:tags":[
        "pubs",
        "inn"
    ],
    "wof:name":"Plume of Feathers",
    "wof:placetype":"venue"
},
  "geometry": {"coordinates":[-4.9754137993,50.1791992188],"type":"Point"}
}