{
  "type": "Feature",
  "properties": {
    "addr:full":"16 Craylands Lane Swanscombe Kent DA10 0LP",
    "addr:housenumber":"16",
    "addr:postcode":"da10 0lp",
    "addr:street":"Craylands Lane",
    "iso:country":"GB",
    "sg:address":"16 Craylands Lane",
    "sg:city":"Swanscombe",
    "sg:classifiers":[
        {
            "category":"Bars & Pubs",
            "type":"Food & Drink"
        }
    ],
    "sg:phone":"+44 1322 384814",
    "sg:postcode":"DA10 0LP",
    "sg:province":"Kent",
    "sg:tags":[
        "pubs",
        "inn"
    ],
    "wof:name":"The Rising Sun",
    "wof:placetype":"venue"
},
  "geometry": {"coordinates":[0.3015,51.446796],"type":"Point"}
}