{
  "type": "Feature",
  "properties": {
    "iso:country":"GB",
    "sg:address":"Unit B-c, Oakcroft Business Centre, Oakcroft Road",
    "sg:city":"Chessington",
    "sg:classifiers":[
        {
            "category":"Professional",
            "subcategory":"Computer Services",
            "type":"Services"
        }
    ],
    "sg:phone":"+44 20 8391 4080",
    "sg:postcode":"KT9 1RH",
    "sg:province":"Surrey",
    "sg:tags":[
        "system",
        "software"
    ],
    "wof:name":"Cardinal Computers Ltd.",
    "wof:placetype":"venue"
},
  "geometry": {"coordinates":[-0.30864501,51.3618736267],"type":"Point"}
}