{
  "type": "Feature",
  "properties": {
    "iso:country":"GB",
    "sg:address":"370 Wilsthorpe Rd, Long Eaton",
    "sg:city":"Nottingham",
    "sg:classifiers":[
        {
            "category":"Health Services",
            "subcategory":"Nursing And Care Facility",
            "type":"Services"
        }
    ],
    "sg:phone":"+44 115 946 2150",
    "sg:postcode":"NG10 4AA",
    "sg:province":"Derbyshire",
    "sg:tags":[
        "home"
    ],
    "wof:name":"Bupa Nursing Homes Ltd",
    "wof:placetype":"venue"
},
  "geometry": {"coordinates":[-1.2934399843,52.8996810913],"type":"Point"}
}