{
  "type": "Feature",
  "properties": {
    "addr:full":"127 Trowell Rd Nottingham Nottinghamshire NG8 2EN",
    "addr:housenumber":"127",
    "addr:postcode":"ng8 2en",
    "addr:street":"Trowell Rd",
    "iso:country":"GB",
    "sg:address":"127 Trowell Rd",
    "sg:city":"Nottingham",
    "sg:classifiers":[
        {
            "category":"Autos & Motor Vehicles",
            "subcategory":"Automobile Sales",
            "type":"Retail Goods"
        }
    ],
    "sg:phone":"+44 115 928 0713",
    "sg:postcode":"NG8 2EN",
    "sg:province":"Nottinghamshire",
    "sg:tags":[
        "car"
    ],
    "wof:name":"Wollaton Car Centre",
    "wof:placetype":"venue"
},
  "geometry": {"coordinates":[-1.2317080498,52.9552001953],"type":"Point"}
}