{
  "type": "Feature",
  "properties": {
    "iso:country":"GB",
    "sg:address":"Albion Ho, Albion St",
    "sg:city":"Willenhall",
    "sg:classifiers":[
        {
            "category":"Professional",
            "subcategory":"Employment Agencies",
            "type":"Services"
        }
    ],
    "sg:phone":"+44 1902 601622",
    "sg:postcode":"WV13 1NJ",
    "sg:province":"West Midlands",
    "sg:tags":[
        "consultant"
    ],
    "wof:name":"Employment Mart",
    "wof:placetype":"venue"
},
  "geometry": {"coordinates":[-2.0448141098,52.5867958069],"type":"Point"}
}