{
  "type": "Feature",
  "properties": {
    "iso:country":"GB",
    "sg:address":"The Common",
    "sg:city":"Marlborough",
    "sg:classifiers":[
        {
            "category":"Sports & Exercise",
            "subcategory":"Golf",
            "type":"Entertainment"
        }
    ],
    "sg:phone":"+44 1672 512147",
    "sg:postcode":"SN8 1DU",
    "sg:province":"Berkshire",
    "sg:tags":[
        "club",
        "course"
    ],
    "wof:name":"Marlborough Golf Club",
    "wof:placetype":"venue"
},
  "geometry": {"coordinates":[-1.730899,51.425201],"type":"Point"}
}