{
  "type": "Feature",
  "properties": {
    "addr:full":"Unit 5-6 Maritime St, Copse Rd Fleetwood Lancashire FY7 7PB",
    "addr:housenumber":"unit 5-6",
    "addr:postcode":"fy7 7pb",
    "addr:street":"Maritime St Copse Rd",
    "iso:country":"GB",
    "sg:address":"Unit 5-6 Maritime St, Copse Rd",
    "sg:city":"Fleetwood",
    "sg:classifiers":[
        {
            "category":"Food & Beverages",
            "subcategory":"Specialty",
            "type":"Retail Goods"
        }
    ],
    "sg:phone":"+44 1253 479111",
    "sg:postcode":"FY7 7PB",
    "sg:province":"Lancashire",
    "sg:tags":[
        "product",
        "health"
    ],
    "wof:name":"Natural Options",
    "wof:placetype":"venue"
},
  "geometry": {"coordinates":[-3.025534,53.911243],"type":"Point"}
}