{
  "type": "Feature",
  "properties": {
    "addr:full":"58 High Street Shanklin Isle of Wight PO37 6JN",
    "addr:housenumber":"58",
    "addr:postcode":"po37 6jn",
    "addr:street":"High Street",
    "iso:country":"GB",
    "sg:address":"58 High Street",
    "sg:city":"Shanklin",
    "sg:classifiers":[
        {
            "category":"Home & Garden",
            "subcategory":"Kitchen Supply",
            "type":"Retail Goods"
        }
    ],
    "sg:phone":"+44 1983 862322",
    "sg:postcode":"PO37 6JN",
    "sg:province":"Isle of Wight",
    "sg:tags":[
        "glassware",
        "china"
    ],
    "wof:name":"Bradleys",
    "wof:placetype":"venue"
},
  "geometry": {"coordinates":[-1.1794259548,50.6279220581],"type":"Point"}
}