{
  "type": "Feature",
  "properties": {
    "iso:country":"GB",
    "sg:address":"484 Manchester Road",
    "sg:city":"Stockport",
    "sg:classifiers":[
        {
            "category":"Food & Beverages",
            "subcategory":"Fruits & Vegetables",
            "type":"Retail Goods"
        }
    ],
    "sg:phone":"+44 161 432 7957",
    "sg:postcode":"SK4 5DL",
    "sg:province":"Cheshire",
    "sg:tags":[
        "greengrocer"
    ],
    "wof:name":"Cottrells",
    "wof:placetype":"venue"
},
  "geometry": {"coordinates":[-2.178813,53.430012],"type":"Point"}
}