{
  "type": "Feature",
  "properties": {
    "iso:country":"GB",
    "sg:address":"Unit 60a, Gorse Industrial Estate",
    "sg:city":"Thetford",
    "sg:classifiers":[
        {
            "category":"Manufacturing",
            "subcategory":"Metals",
            "type":"Manufacturing & Wholesale Goods"
        }
    ],
    "sg:phone":"+44 1842 890555",
    "sg:postcode":"IP24 2PH",
    "sg:province":"Norfolk",
    "wof:name":"Breckland Polishing",
    "wof:placetype":"venue"
},
  "geometry": {"coordinates":[0.716477,52.383865],"type":"Point"}
}