{
  "type": "Feature",
  "properties": {
    "iso:country":"GB",
    "sg:address":"32 Warner Drive, Springwood Industrial Estate",
    "sg:city":"Braintree",
    "sg:classifiers":[
        {
            "category":"Manufacturing",
            "subcategory":"Motor Vehicles & Parts",
            "type":"Manufacturing & Wholesale Goods"
        }
    ],
    "sg:postcode":"CM7 2YW",
    "sg:province":"Essex",
    "sg:tags":[
        "bearing"
    ],
    "wof:name":"Transmission Bearings (U K) Ltd.",
    "wof:placetype":"venue"
},
  "geometry": {"coordinates":[0.5340870023,51.8837585449],"type":"Point"}
}