{
  "type": "Feature",
  "properties": {
    "addr:full":"6 The Pavement Taunton Devon TA3 6LX",
    "addr:housenumber":"6",
    "addr:postcode":"ta3 6lx",
    "addr:street":"The Pavement",
    "iso:country":"GB",
    "sg:address":"6 The Pavement",
    "sg:city":"Taunton",
    "sg:classifiers":[
        {
            "category":"Retail",
            "subcategory":"Auto Repair",
            "type":"Services"
        }
    ],
    "sg:postcode":"TA3 6LX",
    "sg:province":"Devon",
    "sg:tags":[
        "modification",
        "garage"
    ],
    "wof:name":"Burt,John,",
    "wof:placetype":"venue"
},
  "geometry": {"coordinates":[-2.9727039337,51.0214538574],"type":"Point"}
}