{
  "type": "Feature",
  "properties": {
    "addr:full":"64 Cross St Sale Cheshire M33 7AN",
    "addr:housenumber":"64",
    "addr:postcode":"m33 7an",
    "addr:street":"Cross St",
    "iso:country":"GB",
    "sg:address":"64 Cross St",
    "sg:city":"Sale",
    "sg:classifiers":[
        {
            "category":"Professional",
            "subcategory":"Employment Agencies",
            "type":"Services"
        }
    ],
    "sg:phone":"+44 161 973 7444",
    "sg:postcode":"M33 7AN",
    "sg:province":"Cheshire",
    "sg:tags":[
        "consultant"
    ],
    "wof:name":"LMR Ltd",
    "wof:placetype":"venue"
},
  "geometry": {"coordinates":[-2.3226718903,53.4277153015],"type":"Point"}
}