{
  "type": "Feature",
  "properties": {
    "addr:full":"15 Bredy Close Poole Dorset BH17 9JP",
    "addr:housenumber":"15",
    "addr:postcode":"bh17 9jp",
    "addr:street":"Bredy Close",
    "iso:country":"GB",
    "sg:address":"15 Bredy Close",
    "sg:city":"Poole",
    "sg:classifiers":[
        {
            "category":"Shopping",
            "subcategory":"Catalog Store",
            "type":"Retail Goods"
        }
    ],
    "sg:postcode":"BH17 9JP",
    "sg:province":"Dorset",
    "sg:tags":[
        "mail",
        "order"
    ],
    "wof:name":"Tradewinds Mail-Order",
    "wof:placetype":"venue"
},
  "geometry": {"coordinates":[-1.9749369621,50.7488059998],"type":"Point"}
}