{
  "type": "Feature",
  "properties": {
    "addr:full":"Wick Road Bristol Somerset BS39 5XD",
    "addr:postcode":"bs39 5xd",
    "addr:street":"Wick Road",
    "iso:country":"GB",
    "sg:address":"Wick Road",
    "sg:city":"Bristol",
    "sg:classifiers":[
        {
            "category":"Food & Beverages",
            "subcategory":"Bakery",
            "type":"Retail Goods"
        }
    ],
    "sg:phone":"+44 1275 332557",
    "sg:postcode":"BS39 5XD",
    "sg:province":"Somerset",
    "sg:tags":[
        "confectionery"
    ],
    "wof:name":"E J Montgomery & Sons",
    "wof:placetype":"venue"
},
  "geometry": {"coordinates":[-2.5968239307,51.3334846497],"type":"Point"}
}