{
  "type": "Feature",
  "properties": {
    "iso:country":"GB",
    "sg:address":"Hayfield Garage, Earby Road",
    "sg:city":"Barnoldswick",
    "sg:classifiers":[
        {
            "category":"Retail",
            "subcategory":"Auto Repair",
            "type":"Services"
        }
    ],
    "sg:phone":"+44 1282 813292",
    "sg:postcode":"BB18 6SR",
    "sg:province":"Lancashire",
    "sg:tags":[
        "modification",
        "garage"
    ],
    "wof:name":"Paul Woodall",
    "wof:placetype":"venue"
},
  "geometry": {"coordinates":[-2.146199,53.914486],"type":"Point"}
}