{
  "type": "Feature",
  "properties": {
    "addr:full":"Olinda Heathside Lane Hindhead Hampshire GU26 6QA",
    "addr:postcode":"gu26 6qa",
    "addr:street":"Heathside Lane",
    "iso:country":"GB",
    "sg:address":"Olinda Heathside Lane",
    "sg:city":"Hindhead",
    "sg:classifiers":[
        {
            "category":"Social Services",
            "subcategory":"Job Training",
            "type":"Services"
        }
    ],
    "sg:phone":"+44 1428 605866",
    "sg:postcode":"GU26 6QA",
    "sg:province":"Hampshire",
    "sg:tags":[
        "translator",
        "interpreter"
    ],
    "wof:name":"Dwyrain Associates",
    "wof:placetype":"venue"
},
  "geometry": {"coordinates":[-0.753168,51.12188],"type":"Point"}
}