{
  "type": "Feature",
  "properties": {
    "addr:full":"Spalding Common Spalding Lincolnshire PE11 3AS",
    "addr:postcode":"pe11 3as",
    "addr:street":"Spalding Common",
    "iso:country":"GB",
    "sg:address":"Spalding Common",
    "sg:city":"Spalding",
    "sg:classifiers":[
        {
            "category":"Education",
            "subcategory":"School",
            "type":"Public Place"
        },
        {
            "category":"Government",
            "subcategory":"Office",
            "type":"Public Place"
        }
    ],
    "sg:phone":"+44 1775 722155",
    "sg:postcode":"PE11 3AS",
    "sg:province":"Lincolnshire",
    "sg:tags":[
        "local",
        "authority"
    ],
    "wof:name":"Goodfellows Church of England Primary School",
    "wof:placetype":"venue"
},
  "geometry": {"coordinates":[-0.173240006,52.7668800354],"type":"Point"}
}