{
  "type": "Feature",
  "properties": {
    "iso:country":"GB",
    "sg:address":"Helpline",
    "sg:city":"Bristol",
    "sg:classifiers":[
        {
            "category":"Professional",
            "subcategory":"Lawyer & Legal Services",
            "type":"Services"
        }
    ],
    "sg:phone":"+44 117 965 6285",
    "sg:postcode":"BS16 3EA",
    "sg:province":"City of Bristol",
    "sg:tags":[
        "advice",
        "counselling"
    ],
    "wof:name":"M E Association",
    "wof:placetype":"venue"
},
  "geometry": {"coordinates":[-2.591429,51.453667],"type":"Point"}
}