{
  "type": "Feature",
  "properties": {
    "addr:full":"77 Market St Ashby-de-la-zouch Derbyshire LE65 1AH",
    "addr:housenumber":"77",
    "addr:postcode":"le65 1ah",
    "addr:street":"Market St",
    "iso:country":"GB",
    "sg:address":"77 Market St",
    "sg:city":"Ashby-de-la-zouch",
    "sg:classifiers":[
        {
            "category":"Building & Trades",
            "subcategory":"Landscaping Services",
            "type":"Services"
        }
    ],
    "sg:postcode":"LE65 1AH",
    "sg:province":"Derbyshire",
    "sg:tags":[
        "landscape",
        "contractor"
    ],
    "wof:name":"Choice Design",
    "wof:placetype":"venue"
},
  "geometry": {"coordinates":[-1.4733439684,52.7466506958],"type":"Point"}
}