{
  "type": "Feature",
  "properties": {
    "iso:country":"GB",
    "sg:address":"The Barn, Rainbow Nursery",
    "sg:city":"Clacton-on-sea",
    "sg:classifiers":[
        {
            "category":"Manufacturing",
            "subcategory":"Wood Products",
            "type":"Manufacturing & Wholesale Goods"
        }
    ],
    "sg:postcode":"CO16 9AG",
    "sg:province":"Essex",
    "sg:tags":[
        "maker",
        "cabinet"
    ],
    "wof:name":"Andrew Smith",
    "wof:placetype":"venue"
},
  "geometry": {"coordinates":[1.1083099842,51.8641586304],"type":"Point"}
}