{
  "type": "Feature",
  "properties": {
    "addr:full":"37-39 High St Lincoln Lincolnshire LN4 4NP",
    "addr:housenumber":"37-39",
    "addr:postcode":"ln4 4np",
    "addr:street":"High St",
    "iso:country":"GB",
    "sg:address":"37-39 High St",
    "sg:city":"Lincoln",
    "sg:classifiers":[
        {
            "category":"Professional",
            "subcategory":"Printing & Photocopies",
            "type":"Services"
        }
    ],
    "sg:phone":"+44 1526 342386",
    "sg:postcode":"LN4 4NP",
    "sg:province":"Lincolnshire",
    "sg:tags":[
        "engraving"
    ],
    "wof:name":"Tattershall Engraving",
    "wof:placetype":"venue"
},
  "geometry": {"coordinates":[-0.277949,53.078766],"type":"Point"}
}