{
  "type": "Feature",
  "properties": {
    "iso:country":"GB",
    "sg:address":"2a Market Street, Atherton",
    "sg:city":"Manchester",
    "sg:classifiers":[
        {
            "category":"Taxi",
            "type":"Transportation"
        },
        {
            "category":"Military Area",
            "subcategory":"Air Force Base",
            "type":"Public Place"
        }
    ],
    "sg:phone":"+44 1942 893388",
    "sg:postcode":"M46 0DN",
    "sg:province":"Greater Manchester",
    "sg:tags":[
        "hire",
        "private"
    ],
    "wof:name":"Atherton Cab Co",
    "wof:placetype":"venue"
},
  "geometry": {"coordinates":[-2.490553,53.523567],"type":"Point"}
}