{
  "type": "Feature",
  "properties": {
    "iso:country":"GB",
    "sg:address":"39 Salisbury Drive, Water Orton",
    "sg:city":"Birmingham",
    "sg:classifiers":[
        {
            "category":"Retail",
            "subcategory":"Driving School",
            "type":"Services"
        }
    ],
    "sg:postcode":"B46 1QH",
    "sg:province":"Warwickshire",
    "wof:name":"Spencer School of Motoring",
    "wof:placetype":"venue"
},
  "geometry": {"coordinates":[-1.734218,52.518219],"type":"Point"}
}