{
  "type": "Feature",
  "properties": {
    "addr:full":"6 Mardol Shrewsbury Shropshire SY1 1PY",
    "addr:housenumber":"6",
    "addr:postcode":"sy1 1py",
    "addr:street":"Mardol",
    "iso:country":"GB",
    "sg:address":"6 Mardol",
    "sg:city":"Shrewsbury",
    "sg:classifiers":[
        {
            "category":"Shopping",
            "subcategory":"Music",
            "type":"Retail Goods"
        }
    ],
    "sg:phone":"+44 1743 343247",
    "sg:postcode":"SY1 1PY",
    "sg:province":"Shropshire",
    "sg:tags":[
        "record",
        "tape",
        "cd"
    ],
    "wof:name":"MVC",
    "wof:placetype":"venue"
},
  "geometry": {"coordinates":[-2.755648,52.708305],"type":"Point"}
}