{
  "type": "Feature",
  "properties": {
    "iso:country":"GB",
    "sg:address":"62 Cornwall Street",
    "sg:city":"Plymouth",
    "sg:classifiers":[
        {
            "category":"Communications",
            "type":"Services"
        }
    ],
    "sg:phone":"+44 1752 251155",
    "sg:postcode":"PL1 1LR",
    "sg:province":"Devon",
    "sg:tags":[
        "tv",
        "video",
        "radio"
    ],
    "wof:name":"Sony Centre",
    "wof:placetype":"venue"
},
  "geometry": {"coordinates":[-4.1435289383,50.3724555969],"type":"Point"}
}