{
  "type": "Feature",
  "properties": {
    "addr:full":"35 Boston Avenue Southend-on-sea Essex SS2 6JH",
    "addr:housenumber":"35",
    "addr:postcode":"ss2 6jh",
    "addr:street":"Boston Avenue",
    "iso:country":"GB",
    "sg:address":"35 Boston Avenue",
    "sg:city":"Southend-on-sea",
    "sg:classifiers":[
        {
            "category":"Building & Trades",
            "subcategory":"Construction",
            "type":"Services"
        }
    ],
    "sg:phone":"+44 1702 335504",
    "sg:postcode":"SS2 6JH",
    "sg:province":"Essex",
    "sg:tags":[
        "roofing"
    ],
    "wof:name":"Maplin Tulers",
    "wof:placetype":"venue"
},
  "geometry": {"coordinates":[0.70647,51.541962],"type":"Point"}
}