{
  "type": "Feature",
  "properties": {
    "iso:country":"GB",
    "sg:address":"Birmingham Regional Office, P O Box 34 15 Colmore Row",
    "sg:city":"Birmingham",
    "sg:classifiers":[
        {
            "category":"Banks & Credit Unions",
            "subcategory":"Bank",
            "type":"Services"
        }
    ],
    "sg:phone":"+44 121 236 4000",
    "sg:postcode":"B3 2BY",
    "sg:province":"West Midlands",
    "wof:name":"Barclays Bank Plc",
    "wof:placetype":"venue"
},
  "geometry": {"coordinates":[-1.90057,52.482578],"type":"Point"}
}