{
  "type": "Feature",
  "properties": {
    "iso:country":"GB",
    "sg:address":"Vincent Street",
    "sg:city":"Swansea",
    "sg:classifiers":[
        {
            "category":"Education",
            "subcategory":"School",
            "type":"Public Place"
        }
    ],
    "sg:phone":"+44 1792 655763",
    "sg:postcode":"SA1 3TY",
    "sg:province":"Neath Port Talbot",
    "sg:tags":[
        "local",
        "authority"
    ],
    "wof:name":"St Helens Primary School",
    "wof:placetype":"venue"
},
  "geometry": {"coordinates":[-3.954334,51.615326],"type":"Point"}
}