{
  "type": "Feature",
  "properties": {
    "iso:country":"GB",
    "sg:address":"227 Birchfield Road East",
    "sg:city":"Northampton",
    "sg:classifiers":[
        {
            "category":"Shopping",
            "subcategory":"Florist",
            "type":"Retail Goods"
        }
    ],
    "sg:phone":"+44 1604 718312",
    "sg:postcode":"NN3 2BZ",
    "sg:province":"Northamptonshire",
    "wof:name":"The Flower House",
    "wof:placetype":"venue"
},
  "geometry": {"coordinates":[-0.865786,52.252323],"type":"Point"}
}