{
  "type": "Feature",
  "properties": {
    "iso:country":"GB",
    "sg:address":"16 Portland Square",
    "sg:city":"Workington",
    "sg:classifiers":[
        {
            "category":"Social Services",
            "subcategory":"Retirement Home",
            "type":"Services"
        }
    ],
    "sg:phone":"+44 1900 601726",
    "sg:postcode":"CA14 4BJ",
    "sg:province":"Cumbria",
    "sg:tags":[
        "care"
    ],
    "wof:name":"The Care Agency",
    "wof:placetype":"venue"
},
  "geometry": {"coordinates":[-3.5406150818,54.6423072815],"type":"Point"}
}