{
  "type": "Feature",
  "properties": {
    "iso:country":"GB",
    "sg:address":"City Business Centre, Suite 25, St Olans Ct, Lower Rd, Rotherh",
    "sg:city":"London",
    "sg:classifiers":[
        {
            "category":"Professional",
            "type":"Services"
        }
    ],
    "sg:phone":"+44 20 7394 8880",
    "sg:postcode":"SE16 2XB",
    "sg:province":"Greater London",
    "sg:tags":[
        "repair",
        "tech",
        "maintenance"
    ],
    "wof:name":"Heights Business Systems Ltd",
    "wof:placetype":"venue"
},
  "geometry": {"coordinates":[-0.051319,51.495556],"type":"Point"}
}