{
  "type": "Feature",
  "properties": {
    "addr:full":"Chalk Hall Farm, Hilborough Thetford Norfolk IP26 5BY",
    "addr:housenumber":"hilborough",
    "addr:postcode":"ip26 5by",
    "iso:country":"GB",
    "sg:address":"Chalk Hall Farm, Hilborough",
    "sg:city":"Thetford",
    "sg:classifiers":[
        {
            "category":"Farming",
            "subcategory":"Farm",
            "type":"Manufacturing & Wholesale Goods"
        }
    ],
    "sg:phone":"+44 1842 878270",
    "sg:postcode":"IP26 5BY",
    "sg:province":"Norfolk",
    "sg:tags":[
        "egg",
        "producer"
    ],
    "wof:name":"H & S Rolph",
    "wof:placetype":"venue"
},
  "geometry": {"coordinates":[0.689388,52.57016],"type":"Point"}
}