{
  "type": "Feature",
  "properties": {
    "addr:full":"Unit 6 Bullsbridge Industrial Estate, Hayes Road Southall Greater London UB2 5NB",
    "addr:housenumber":"unit 6;estate",
    "addr:postcode":"ub2 5nb",
    "addr:street":"Bullsbridge Industrial;Hayes Road",
    "iso:country":"GB",
    "sg:address":"Unit 6 Bullsbridge Industrial Estate, Hayes Road",
    "sg:city":"Southall",
    "sg:classifiers":[
        {
            "category":"Sports & Exercise",
            "subcategory":"Tennis Court",
            "type":"Entertainment"
        }
    ],
    "sg:phone":"+44 20 8561 4525",
    "sg:postcode":"UB2 5NB",
    "sg:province":"Greater London",
    "sg:tags":[
        "breakdown",
        "recovery"
    ],
    "wof:name":"Fleet Assistance Plc",
    "wof:placetype":"venue"
},
  "geometry": {"coordinates":[-0.403361,51.498447],"type":"Point"}
}