{
  "type": "Feature",
  "properties": {
    "addr:full":"138 Plungington Road Preston Lancashire PR1 7UD",
    "addr:housenumber":"138",
    "addr:postcode":"pr1 7ud",
    "addr:street":"Plungington Road",
    "iso:country":"GB",
    "sg:address":"138 Plungington Road",
    "sg:city":"Preston",
    "sg:classifiers":[
        {
            "category":"Food & Beverages",
            "subcategory":"Meat & Fish",
            "type":"Retail Goods"
        }
    ],
    "sg:phone":"+44 1772 258470",
    "sg:postcode":"PR1 7UD",
    "sg:province":"Lancashire",
    "sg:tags":[
        "butcher"
    ],
    "wof:name":"J Bamber & Sons Butchers",
    "wof:placetype":"venue"
},
  "geometry": {"coordinates":[-2.713022,53.772446],"type":"Point"}
}