{
  "type": "Feature",
  "properties": {
    "addr:full":"210 Topsham Road Exeter Devon EX2 6AA",
    "addr:housenumber":"210",
    "addr:postcode":"ex2 6aa",
    "addr:street":"Topsham Road",
    "iso:country":"GB",
    "sg:address":"210 Topsham Road",
    "sg:city":"Exeter",
    "sg:classifiers":[
        {
            "category":"Shopping",
            "subcategory":"Stationery & Office Supplies",
            "type":"Retail Goods"
        }
    ],
    "sg:phone":"+44 1392 258551",
    "sg:postcode":"EX2 6AA",
    "sg:province":"Devon",
    "sg:tags":[
        "equipment"
    ],
    "wof:name":"Imperial Office Equipment",
    "wof:placetype":"venue"
},
  "geometry": {"coordinates":[-3.513197,50.710781],"type":"Point"}
}