{
  "type": "Feature",
  "properties": {
    "addr:full":"Y Glyn, Anglesey Llanbedrgoch Isle of Anglesey LL76 8SX",
    "addr:postcode":"ll76 8sx",
    "addr:street":"Llanbedrgoch",
    "iso:country":"GB",
    "sg:address":"Y Glyn, Anglesey",
    "sg:city":"Llanbedrgoch",
    "sg:classifiers":[
        {
            "category":"Farming",
            "subcategory":"Farm",
            "type":"Manufacturing & Wholesale Goods"
        }
    ],
    "sg:phone":"+44 1248 852387",
    "sg:postcode":"LL76 8SX",
    "sg:province":"Isle of Anglesey",
    "sg:tags":[
        "mixed",
        "crop"
    ],
    "wof:name":"Tebbutt Farms Ltd.",
    "wof:placetype":"venue"
},
  "geometry": {"coordinates":[-4.2370128632,53.300491333],"type":"Point"}
}