{
  "type": "Feature",
  "properties": {
    "addr:full":"86 Victoria St Grimsby Lincolnshire DN31 1BG",
    "addr:housenumber":"86",
    "addr:postcode":"dn31 1bg",
    "addr:street":"Victoria St",
    "iso:country":"GB",
    "sg:address":"86 Victoria St",
    "sg:city":"Grimsby",
    "sg:classifiers":[
        {
            "category":"Personal",
            "subcategory":"Beauty Salon",
            "type":"Services"
        }
    ],
    "sg:phone":"+44 1472 343332",
    "sg:postcode":"DN31 1BG",
    "sg:province":"Lincolnshire",
    "sg:tags":[
        "unisex",
        "hairdresser"
    ],
    "wof:name":"Concept Hair Design",
    "wof:placetype":"venue"
},
  "geometry": {"coordinates":[-0.0811590031,53.5704231262],"type":"Point"}
}