{
  "type": "Feature",
  "properties": {
    "addr:full":"5 Russell Gardens Wickford Essex SS11 8QU",
    "addr:housenumber":"5",
    "addr:postcode":"ss11 8qu",
    "addr:street":"Russell Gardens",
    "iso:country":"GB",
    "sg:address":"5 Russell Gardens",
    "sg:city":"Wickford",
    "sg:classifiers":[
        {
            "category":"Retail",
            "subcategory":"Auto Repair",
            "type":"Services"
        }
    ],
    "sg:phone":"+44 1268 734830",
    "sg:postcode":"SS11 8QU",
    "sg:province":"Essex",
    "sg:tags":[
        "modification",
        "garage"
    ],
    "wof:name":"D B Motors",
    "wof:placetype":"venue"
},
  "geometry": {"coordinates":[0.532511,51.608891],"type":"Point"}
}