{
  "type": "Feature",
  "properties": {
    "iso:country":"GB",
    "sg:address":"P O Box 25",
    "sg:city":"Wilmslow",
    "sg:classifiers":[
        {
            "category":"Building & Trades",
            "subcategory":"Equipment Rental",
            "type":"Services"
        }
    ],
    "sg:phone":"+44 1625 522445",
    "sg:postcode":"SK9 2FU",
    "sg:province":"Cheshire",
    "sg:tags":[
        "hire",
        "catering"
    ],
    "wof:name":"Roland Moss Ltd.",
    "wof:placetype":"venue"
},
  "geometry": {"coordinates":[-2.227897,53.326797],"type":"Point"}
}