{
  "type": "Feature",
  "properties": {
    "addr:full":"67 Jubilee Dr, Thornbury Bristol Gloucestershire BS35 2YH",
    "addr:housenumber":"67",
    "addr:postcode":"bs35 2yh",
    "addr:street":"Jubilee Dr",
    "iso:country":"GB",
    "sg:address":"67 Jubilee Dr, Thornbury",
    "sg:city":"Bristol",
    "sg:classifiers":[
        {
            "category":"Professional",
            "subcategory":"Business Services",
            "type":"Services"
        }
    ],
    "sg:postcode":"BS35 2YH",
    "sg:province":"Gloucestershire",
    "sg:tags":[
        "hospitality",
        "corporate"
    ],
    "wof:name":"Dembury,David,",
    "wof:placetype":"venue"
},
  "geometry": {"coordinates":[-2.5086619854,51.6074256897],"type":"Point"}
}