{
  "type": "Feature",
  "properties": {
    "addr:full":"74 Prestbury Road Cheltenham Gloucestershire GL52 2DJ",
    "addr:housenumber":"74",
    "addr:postcode":"gl52 2dj",
    "addr:street":"Prestbury Road",
    "iso:country":"GB",
    "sg:address":"74 Prestbury Road",
    "sg:city":"Cheltenham",
    "sg:classifiers":[
        {
            "category":"Retail",
            "subcategory":"Funeral Services",
            "type":"Services"
        },
        {
            "category":"Building & Trades",
            "subcategory":"Construction",
            "type":"Services"
        }
    ],
    "sg:phone":"+44 1242 525383",
    "sg:postcode":"GL52 2DJ",
    "sg:province":"Gloucestershire",
    "sg:tags":[
        "director",
        "monumental",
        "mason"
    ],
    "wof:name":"Selim Smith & Co",
    "wof:placetype":"venue"
},
  "geometry": {"coordinates":[-2.0635650158,51.9063720703],"type":"Point"}
}