{
  "type": "Feature",
  "properties": {
    "iso:country":"GB",
    "sg:address":"452 Oakleigh Road North",
    "sg:city":"London",
    "sg:classifiers":[
        {
            "category":"Organizations",
            "subcategory":"Community Association",
            "type":"Services"
        }
    ],
    "sg:postcode":"N20 0RZ",
    "sg:province":"Greater London",
    "sg:tags":[
        "relation",
        "public"
    ],
    "wof:name":"B G Smithard Associates",
    "wof:placetype":"venue"
},
  "geometry": {"coordinates":[-0.1525450051,51.6227378845],"type":"Point"}
}