{
  "type": "Feature",
  "properties": {
    "iso:country":"GB",
    "sg:address":"Terrace Road, Binfield",
    "sg:city":"Bracknell",
    "sg:classifiers":[
        {
            "category":"Autos & Motor Vehicles",
            "subcategory":"Auto Supplies",
            "type":"Retail Goods"
        }
    ],
    "sg:phone":"+44 1344 450586",
    "sg:postcode":"RG12 5DS",
    "sg:province":"Berkshire",
    "sg:tags":[
        "tyre"
    ],
    "wof:name":"Total Tyre & Exhaust Co",
    "wof:placetype":"venue"
},
  "geometry": {"coordinates":[-0.78916,51.431519],"type":"Point"}
}