{
  "type": "Feature",
  "properties": {
    "addr:full":"Second Floor, Bentalls Shopping Centre Kingston-upon-thames Greater London KT1 1TP",
    "addr:housenumber":"second",
    "addr:postcode":"kt1 1tp",
    "addr:street":"Kingston-Upon-Thames",
    "iso:country":"GB",
    "sg:address":"Second Floor, Bentalls Shopping Centre",
    "sg:city":"Kingston-upon-thames",
    "sg:classifiers":[
        {
            "category":"Shopping",
            "subcategory":"Hobbies, Toys, & Games",
            "type":"Retail Goods"
        }
    ],
    "sg:phone":"+44 20 8974 8900",
    "sg:postcode":"KT1 1TP",
    "sg:province":"Greater London",
    "sg:tags":[
        "shop",
        "toy"
    ],
    "wof:name":"Fun Learning Ltd.",
    "wof:placetype":"venue"
},
  "geometry": {"coordinates":[-0.3050000072,51.4116592407],"type":"Point"}
}