{
  "type": "Feature",
  "properties": {
    "iso:country":"GB",
    "sg:address":"113 Bargates",
    "sg:city":"Christchurch",
    "sg:classifiers":[
        {
            "category":"Food & Beverages",
            "subcategory":"Meat & Fish",
            "type":"Retail Goods"
        }
    ],
    "sg:phone":"+44 1202 473283",
    "sg:postcode":"BH23 1QH",
    "sg:province":"Dorset",
    "sg:tags":[
        "chip"
    ],
    "wof:name":"J C's Fish & Chips",
    "wof:placetype":"venue"
},
  "geometry": {"coordinates":[-1.781893,50.738644],"type":"Point"}
}