{
  "type": "Feature",
  "properties": {
    "iso:country":"GB",
    "sg:address":"3 Fox Cotts, Stanningfield",
    "sg:city":"Bury St Edmunds",
    "sg:classifiers":[
        {
            "category":"Building & Trades",
            "subcategory":"Cleaning & Sanitation",
            "type":"Services"
        },
        {
            "category":"Building & Trades",
            "subcategory":"Construction",
            "type":"Services"
        }
    ],
    "sg:postcode":"IP29 4RU",
    "sg:province":"Suffolk",
    "sg:tags":[
        "dry",
        "control",
        "damp",
        "rot",
        "builder"
    ],
    "wof:name":"Rickards,Michael,",
    "wof:placetype":"venue"
},
  "geometry": {"coordinates":[0.75115,52.179111],"type":"Point"}
}