{
  "type": "Feature",
  "properties": {
    "addr:full":"11 Mead Industrial Park, Riverway Harlow Essex CM20 2SE",
    "addr:housenumber":"11",
    "addr:postcode":"cm20 2se",
    "addr:street":"Mead Industrial Park Riverway",
    "iso:country":"GB",
    "sg:address":"11 Mead Industrial Park, Riverway",
    "sg:city":"Harlow",
    "sg:classifiers":[
        {
            "category":"Building & Trades",
            "subcategory":"Electrical",
            "type":"Services"
        }
    ],
    "sg:phone":"+44 1279 411131",
    "sg:postcode":"CM20 2SE",
    "sg:province":"Essex",
    "sg:tags":[
        "lighting"
    ],
    "wof:name":"Futimis House",
    "wof:placetype":"venue"
},
  "geometry": {"coordinates":[0.097506,51.773151],"type":"Point"}
}