{
  "type": "Feature",
  "properties": {
    "addr:full":"Frances Street Sunderland Tyne and Wear SR3 1EN",
    "addr:postcode":"sr3 1en",
    "addr:street":"Frances Street",
    "iso:country":"GB",
    "sg:address":"Frances Street",
    "sg:city":"Sunderland",
    "sg:classifiers":[
        {
            "category":"Food & Beverages",
            "subcategory":"Meat & Fish",
            "type":"Retail Goods"
        }
    ],
    "sg:phone":"+44 191 521 0069",
    "sg:postcode":"SR3 1EN",
    "sg:province":"Tyne and Wear",
    "sg:tags":[
        "butcher"
    ],
    "wof:name":"J G Haswell",
    "wof:placetype":"venue"
},
  "geometry": {"coordinates":[-1.40412,54.872429],"type":"Point"}
}