{
  "type": "Feature",
  "properties": {
    "addr:full":"Woodlands, Highleigh Road Chichester West Sussex PO20 7NR",
    "addr:postcode":"po20 7nr",
    "addr:street":"Highleigh Road",
    "iso:country":"GB",
    "sg:address":"Woodlands, Highleigh Road",
    "sg:city":"Chichester",
    "sg:classifiers":[
        {
            "category":"Health Services",
            "subcategory":"Clinic",
            "type":"Services"
        }
    ],
    "sg:postcode":"PO20 7NR",
    "sg:province":"West Sussex",
    "sg:tags":[
        "aromatherapy"
    ],
    "wof:name":"K T Taphouse",
    "wof:placetype":"venue"
},
  "geometry": {"coordinates":[-0.803218,50.77924],"type":"Point"}
}