{
  "type": "Feature",
  "properties": {
    "iso:country":"GB",
    "sg:address":"The Point, Mount Stuart Sq",
    "sg:city":"Cardiff",
    "sg:classifiers":[
        {
            "category":"Arts & Performance",
            "subcategory":"Theater",
            "type":"Entertainment"
        }
    ],
    "sg:phone":"+44 29 2030 0331",
    "sg:postcode":"CF10 5BB",
    "sg:province":"Cardiff",
    "sg:tags":[
        "hall",
        "theatre",
        "concert"
    ],
    "wof:name":"Hijinx",
    "wof:placetype":"venue"
},
  "geometry": {"coordinates":[-3.168709,51.465813],"type":"Point"}
}