{
  "type": "Feature",
  "properties": {
    "iso:country":"GB",
    "sg:address":"North Road",
    "sg:city":"Carnforth",
    "sg:classifiers":[
        {
            "category":"Autos & Motor Vehicles",
            "subcategory":"Motorcycle Sales",
            "type":"Retail Goods"
        }
    ],
    "sg:postcode":"LA5 9LJ",
    "sg:province":"Cumbria",
    "wof:name":"Steve Tonkin Restorations",
    "wof:placetype":"venue"
},
  "geometry": {"coordinates":[-2.7596809864,54.1307678223],"type":"Point"}
}