{
  "type": "Feature",
  "properties": {
    "addr:full":"44 The Squirrels Pinner Greater London HA5 3BD",
    "addr:housenumber":"44",
    "addr:postcode":"ha5 3bd",
    "addr:street":"The Squirrels",
    "iso:country":"GB",
    "sg:address":"44 The Squirrels",
    "sg:city":"Pinner",
    "sg:classifiers":[
        {
            "category":"Professional",
            "subcategory":"Secretarial Services",
            "type":"Services"
        }
    ],
    "sg:phone":"+44 20 8429 3884",
    "sg:postcode":"HA5 3BD",
    "sg:province":"Greater London",
    "wof:name":"Pinner Typing Services",
    "wof:placetype":"venue"
},
  "geometry": {"coordinates":[-0.3716079891,51.5934829712],"type":"Point"}
}