{
  "type": "Feature",
  "properties": {
    "addr:full":"The Forge, The Green, Denton Green Cuddesdon Oxford Oxfordshire OX44 9JE",
    "addr:postcode":"ox44 9je",
    "addr:street":"The Green",
    "iso:country":"GB",
    "sg:address":"The Forge, The Green, Denton Green Cuddesdon",
    "sg:city":"Oxford",
    "sg:classifiers":[
        {
            "category":"Professional",
            "subcategory":"Engineering",
            "type":"Services"
        }
    ],
    "sg:postcode":"OX44 9JE",
    "sg:province":"Oxfordshire",
    "sg:tags":[
        "consulting",
        "engineer"
    ],
    "wof:name":"Hamlet Partnership",
    "wof:placetype":"venue"
},
  "geometry": {"coordinates":[-1.133565,51.724281],"type":"Point"}
}