{
  "type": "Feature",
  "properties": {
    "iso:country":"GB",
    "sg:address":"Market Place, Abridge",
    "sg:city":"Romford",
    "sg:classifiers":[
        {
            "category":"Banks & Credit Unions",
            "subcategory":"Bank",
            "type":"Services"
        }
    ],
    "sg:phone":"+44 1992 814671",
    "sg:postcode":"RM4 1UA",
    "sg:province":"Essex",
    "sg:tags":[
        "broker",
        "mortgage"
    ],
    "wof:name":"Clive Jefferson Associates",
    "wof:placetype":"venue"
},
  "geometry": {"coordinates":[0.118166998,51.6512489319],"type":"Point"}
}