{
  "type": "Feature",
  "properties": {
    "addr:full":"Marston Road Stafford Staffordshire ST16 3BX",
    "addr:postcode":"st16 3bx",
    "addr:street":"Marston Road",
    "iso:country":"GB",
    "sg:address":"Marston Road",
    "sg:city":"Stafford",
    "sg:classifiers":[
        {
            "category":"Bars & Pubs",
            "type":"Food & Drink"
        }
    ],
    "sg:phone":"+44 1785 601851",
    "sg:postcode":"ST16 3BX",
    "sg:province":"Staffordshire",
    "sg:tags":[
        "pubs",
        "inn"
    ],
    "wof:name":"The Albion",
    "wof:placetype":"venue"
},
  "geometry": {"coordinates":[-2.119832,52.817554],"type":"Point"}
}