{
  "type": "Feature",
  "properties": {
    "addr:full":"3 Canterbury Road, Urmston Manchester Cheshire M41 7BH",
    "addr:housenumber":"3",
    "addr:postcode":"m41 7bh",
    "addr:street":"Canterbury Road",
    "iso:country":"GB",
    "sg:address":"3 Canterbury Road, Urmston",
    "sg:city":"Manchester",
    "sg:classifiers":[
        {
            "category":"Professional",
            "subcategory":"Art Services",
            "type":"Services"
        },
        {
            "category":"Building & Trades",
            "subcategory":"Construction",
            "type":"Services"
        }
    ],
    "sg:phone":"+44 161 747 9293",
    "sg:postcode":"M41 7BH",
    "sg:province":"Cheshire",
    "sg:tags":[
        "decorator",
        "painter"
    ],
    "wof:name":"A S Marland",
    "wof:placetype":"venue"
},
  "geometry": {"coordinates":[-2.3632819653,53.4547309875],"type":"Point"}
}