{
  "type": "Feature",
  "properties": {
    "addr:full":"181 St Johns Lane Bristol City of Bristol BS3 5AG",
    "addr:housenumber":"181",
    "addr:postcode":"bs3 5ag",
    "addr:street":"St Johns Lane",
    "iso:country":"GB",
    "sg:address":"181 St Johns Lane",
    "sg:city":"Bristol",
    "sg:classifiers":[
        {
            "category":"Personal",
            "subcategory":"Beauty Salon",
            "type":"Services"
        }
    ],
    "sg:phone":"+44 117 977 6158",
    "sg:postcode":"BS3 5AG",
    "sg:province":"City of Bristol",
    "sg:tags":[
        "lady",
        "hairdresser"
    ],
    "wof:name":"New Image",
    "wof:placetype":"venue"
},
  "geometry": {"coordinates":[-2.5836119652,51.43775177],"type":"Point"}
}