{
  "type": "Feature",
  "properties": {
    "addr:full":"284 Fox Hollies Rd Birmingham West Midlands B27 7PT",
    "addr:housenumber":"284",
    "addr:postcode":"b27 7pt",
    "addr:street":"Fox Hollies Rd",
    "iso:country":"GB",
    "sg:address":"284 Fox Hollies Rd",
    "sg:city":"Birmingham",
    "sg:classifiers":[
        {
            "category":"Home & Garden",
            "subcategory":"Hardware",
            "type":"Retail Goods"
        }
    ],
    "sg:phone":"+44 121 706 3370",
    "sg:postcode":"B27 7PT",
    "sg:province":"West Midlands",
    "sg:tags":[
        "equipment",
        "heating"
    ],
    "wof:name":"Heat Technik Ltd",
    "wof:placetype":"venue"
},
  "geometry": {"coordinates":[-1.833302021,52.4426345825],"type":"Point"}
}