{
  "type": "Feature",
  "properties": {
    "addr:full":"22 May Day Green Barnsley South Yorkshire S70 1SH",
    "addr:housenumber":"22",
    "addr:postcode":"s70 1sh",
    "addr:street":"May Day;Yorkshire",
    "iso:country":"GB",
    "sg:address":"22 May Day Green",
    "sg:city":"Barnsley",
    "sg:classifiers":[
        {
            "category":"Professional",
            "subcategory":"Lawyer & Legal Services",
            "type":"Services"
        }
    ],
    "sg:phone":"+44 1226 280532",
    "sg:postcode":"S70 1SH",
    "sg:province":"South Yorkshire",
    "sg:tags":[
        "advice",
        "counselling"
    ],
    "wof:name":"The Barn",
    "wof:placetype":"venue"
},
  "geometry": {"coordinates":[-1.4795670509,53.5529441833],"type":"Point"}
}