{
  "type": "Feature",
  "properties": {
    "addr:full":"The Design Centre, Cotebrook Tarporley Cheshire CW6 9DY",
    "addr:postcode":"cw6 9dy",
    "addr:street":"Tarporley",
    "iso:country":"GB",
    "sg:address":"The Design Centre, Cotebrook",
    "sg:city":"Tarporley",
    "sg:classifiers":[
        {
            "category":"Professional",
            "type":"Services"
        }
    ],
    "sg:postcode":"CW6 9DY",
    "sg:province":"Cheshire",
    "sg:tags":[
        "interior",
        "furnishers",
        "designer"
    ],
    "wof:name":"Christopher James",
    "wof:placetype":"venue"
},
  "geometry": {"coordinates":[-2.6687550545,53.1593551636],"type":"Point"}
}