{
  "type": "Feature",
  "properties": {
    "addr:full":"41 Broom Road Rotherham South Yorkshire S60 2SW",
    "addr:housenumber":"41",
    "addr:postcode":"s60 2sw",
    "addr:street":"Broom Road",
    "iso:country":"GB",
    "sg:address":"41 Broom Road",
    "sg:city":"Rotherham",
    "sg:classifiers":[
        {
            "category":"Health Services",
            "subcategory":"Dentist",
            "type":"Services"
        }
    ],
    "sg:phone":"+44 1709 372244",
    "sg:postcode":"S60 2SW",
    "sg:province":"South Yorkshire",
    "wof:name":"Darling & Evans",
    "wof:placetype":"venue"
},
  "geometry": {"coordinates":[-1.3417030573,53.4243850708],"type":"Point"}
}