{
  "type": "Feature",
  "properties": {
    "addr:full":"221 Hucknall Lane, Bulwell Nottingham Nottinghamshire NG6 8AG",
    "addr:housenumber":"221",
    "addr:postcode":"ng6 8ag",
    "addr:street":"Hucknall Lane",
    "iso:country":"GB",
    "sg:address":"221 Hucknall Lane, Bulwell",
    "sg:city":"Nottingham",
    "sg:classifiers":[
        {
            "category":"Food & Beverages",
            "subcategory":"Liquor & Beverages",
            "type":"Retail Goods"
        }
    ],
    "sg:phone":"+44 115 927 2626",
    "sg:postcode":"NG6 8AG",
    "sg:province":"Nottinghamshire",
    "sg:tags":[
        "beer",
        "wine",
        "spirit",
        "wines"
    ],
    "wof:name":"Booze Buster",
    "wof:placetype":"venue"
},
  "geometry": {"coordinates":[-1.1903150082,53.0121879578],"type":"Point"}
}