{
  "type": "Feature",
  "properties": {
    "addr:full":"26 North Street Crewe Cheshire CW1 4NL",
    "addr:housenumber":"26",
    "addr:postcode":"cw1 4nl",
    "addr:street":"North Street",
    "iso:country":"GB",
    "sg:address":"26 North Street",
    "sg:city":"Crewe",
    "sg:classifiers":[
        {
            "category":"Bars & Pubs",
            "type":"Food & Drink"
        }
    ],
    "sg:phone":"+44 1270 584265",
    "sg:postcode":"CW1 4NL",
    "sg:province":"Cheshire",
    "sg:tags":[
        "pubs",
        "house",
        "inn",
        "public",
        "activity"
    ],
    "wof:name":"Horse Shoe Hotel",
    "wof:placetype":"venue"
},
  "geometry": {"coordinates":[-2.441445,53.111866],"type":"Point"}
}