{
  "type": "Feature",
  "properties": {
    "iso:country":"GB",
    "sg:address":"Airedale House, 77 Albion Street",
    "sg:city":"Leeds",
    "sg:classifiers":[
        {
            "category":"Professional",
            "subcategory":"Management & Consulting",
            "type":"Services"
        }
    ],
    "sg:phone":"+44 113 242 4432",
    "sg:postcode":"LS1 5AW",
    "sg:province":"West Yorkshire",
    "sg:tags":[
        "consultant",
        "training"
    ],
    "wof:name":"Prism Consulting",
    "wof:placetype":"venue"
},
  "geometry": {"coordinates":[-1.5451960564,53.7984275818],"type":"Point"}
}