{
  "type": "Feature",
  "properties": {
    "addr:full":"Piggotts Hill La Harpenden Hertfordshire AL5 1AB",
    "addr:postcode":"al5 1ab",
    "addr:street":"Piggotts Hill La Harpenden",
    "iso:country":"GB",
    "sg:address":"Piggotts Hill La",
    "sg:city":"Harpenden",
    "sg:classifiers":[
        {
            "category":"Sports & Exercise",
            "subcategory":"Golf",
            "type":"Entertainment"
        }
    ],
    "sg:phone":"+44 1582 760112",
    "sg:postcode":"AL5 1AB",
    "sg:province":"Hertfordshire",
    "sg:tags":[
        "club",
        "course"
    ],
    "wof:name":"Aldwickbury Park Golf Club Ltd",
    "wof:placetype":"venue"
},
  "geometry": {"coordinates":[-0.337699,51.810642],"type":"Point"}
}