{
  "type": "Feature",
  "properties": {
    "addr:full":"11 High Street Chard Devon TA20 1QF",
    "addr:housenumber":"11",
    "addr:postcode":"ta20 1qf",
    "addr:street":"High Street",
    "iso:country":"GB",
    "sg:address":"11 High Street",
    "sg:city":"Chard",
    "sg:classifiers":[
        {
            "category":"Professional",
            "subcategory":"Art Services",
            "type":"Services"
        }
    ],
    "sg:phone":"+44 1460 66808",
    "sg:postcode":"TA20 1QF",
    "sg:province":"Devon",
    "sg:tags":[
        "graphic",
        "designer"
    ],
    "wof:name":"New Century Printing Ltd.",
    "wof:placetype":"venue"
},
  "geometry": {"coordinates":[-2.966907,50.872475],"type":"Point"}
}