{
  "type": "Feature",
  "properties": {
    "addr:full":"4 Genesis Bussiness Center Horsham West Sussex RH13 5QH",
    "addr:housenumber":"4",
    "addr:postcode":"rh13 5qh",
    "addr:street":"Genesis Bussiness Center",
    "iso:country":"GB",
    "sg:address":"4 Genesis Bussiness Center",
    "sg:city":"Horsham",
    "sg:classifiers":[
        {
            "category":"Building & Trades",
            "subcategory":"Construction",
            "type":"Services"
        }
    ],
    "sg:phone":"+44 1403 253606",
    "sg:postcode":"RH13 5QH",
    "sg:province":"West Sussex",
    "sg:tags":[
        "builder",
        "decorator",
        "painter"
    ],
    "wof:name":"Horsham Home Improvements",
    "wof:placetype":"venue"
},
  "geometry": {"coordinates":[-0.3074,51.070831],"type":"Point"}
}