{
  "type": "Feature",
  "properties": {
    "addr:full":"25 Finlay St Fulham Greater London SW6 6HE",
    "addr:housenumber":"25",
    "addr:postcode":"sw6 6he",
    "addr:street":"Finlay St",
    "iso:country":"GB",
    "sg:address":"25 Finlay St",
    "sg:city":"Fulham",
    "sg:classifiers":[
        {
            "category":"Professional",
            "subcategory":"Management & Consulting",
            "type":"Services"
        }
    ],
    "sg:phone":"+44 20 7384 2703",
    "sg:postcode":"SW6 6HE",
    "sg:province":"Greater London",
    "sg:tags":[
        "marketing",
        "consultant"
    ],
    "wof:name":"The Sean O'Connor Consultancy",
    "wof:placetype":"venue"
},
  "geometry": {"coordinates":[-0.2169750035,51.4760398865],"type":"Point"}
}