{
  "type": "Feature",
  "properties": {
    "iso:country":"GB",
    "sg:address":"Place Of Bonhill",
    "sg:city":"Alexandria",
    "sg:classifiers":[
        {
            "category":"Education",
            "subcategory":"School",
            "type":"Public Place"
        }
    ],
    "sg:phone":"+44 1389 757231",
    "sg:postcode":"G83 0TR",
    "sg:province":"Argyll and Bute",
    "sg:tags":[
        "local",
        "authority"
    ],
    "wof:name":"Vale Of Leven Academy School",
    "wof:placetype":"venue"
},
  "geometry": {"coordinates":[-4.583064,55.977905],"type":"Point"}
}