{
  "type": "Feature",
  "properties": {
    "iso:country":"GB",
    "sg:address":"7 The Westbury Centre, Westbury Road, Clayton",
    "sg:city":"Newcastle",
    "sg:classifiers":[
        {
            "category":"Shopping",
            "subcategory":"Pharmacy",
            "type":"Retail Goods"
        }
    ],
    "sg:phone":"+44 1782 712160",
    "sg:postcode":"ST5 4LY",
    "sg:province":"Staffordshire",
    "sg:tags":[
        "pharmacist",
        "chemist"
    ],
    "wof:name":"Lloyds Chemist",
    "wof:placetype":"venue"
},
  "geometry": {"coordinates":[-2.2226219177,52.9883880615],"type":"Point"}
}