{
  "type": "Feature",
  "properties": {
    "addr:full":"Moreside, 13 Hamlet Rd Romford Essex RM5 2DS",
    "addr:housenumber":"13",
    "addr:postcode":"rm5 2ds",
    "addr:street":"Moreside;Hamlet Rd",
    "iso:country":"GB",
    "sg:address":"Moreside, 13 Hamlet Rd",
    "sg:city":"Romford",
    "sg:classifiers":[
        {
            "category":"Education",
            "subcategory":"Special Training",
            "type":"Public Place"
        }
    ],
    "sg:phone":"+44 1708 751883",
    "sg:postcode":"RM5 2DS",
    "sg:province":"Essex",
    "sg:tags":[
        "martial art",
        "instruction"
    ],
    "wof:name":"Collier Row Karate Club",
    "wof:placetype":"venue"
},
  "geometry": {"coordinates":[0.1504700035,51.5997390747],"type":"Point"}
}