{
  "type": "Feature",
  "properties": {
    "iso:country":"GB",
    "sg:address":"29 Stonycroft",
    "sg:city":"Washington",
    "sg:classifiers":[
        {
            "category":"Personal",
            "subcategory":"Tanning Parlor",
            "type":"Services"
        }
    ],
    "sg:postcode":"NE37 1UL",
    "sg:province":"Tyne and Wear",
    "sg:tags":[
        "sunbeds"
    ],
    "wof:name":"Reed,Alan,",
    "wof:placetype":"venue"
},
  "geometry": {"coordinates":[-1.5297499895,54.9071502686],"type":"Point"}
}