{
  "type": "Feature",
  "properties": {
    "iso:country":"GB",
    "sg:address":"85 Hillside Road",
    "sg:city":"Northwood",
    "sg:classifiers":[
        {
            "category":"Professional",
            "subcategory":"Computer Services",
            "type":"Services"
        }
    ],
    "sg:phone":"+44 1923 825979",
    "sg:postcode":"HA6 1PZ",
    "sg:province":"Greater London",
    "sg:tags":[
        "consultant"
    ],
    "wof:name":"Faircare Ltd.",
    "wof:placetype":"venue"
},
  "geometry": {"coordinates":[-0.4036830068,51.6072769165],"type":"Point"}
}