{
  "type": "Feature",
  "properties": {
    "addr:full":"Knowle Bank Road, Shraley Brook Stoke-on-trent Cheshire ST7 8DS",
    "addr:postcode":"st7 8ds",
    "addr:street":"Bank Road Shraley Brook",
    "iso:country":"GB",
    "sg:address":"Knowle Bank Road, Shraley Brook",
    "sg:city":"Stoke-on-trent",
    "sg:classifiers":[
        {
            "category":"Utilities",
            "subcategory":"Fuel Oil & Lpg",
            "type":"Services"
        }
    ],
    "sg:postcode":"ST7 8DS",
    "sg:province":"Cheshire",
    "sg:tags":[
        "coal",
        "smokeless"
    ],
    "wof:name":"Holland & Smith",
    "wof:placetype":"venue"
},
  "geometry": {"coordinates":[-2.32821,53.04591],"type":"Point"}
}