{
  "type": "Feature",
  "properties": {
    "addr:full":"21 Nile Street North Shields Tyne and Wear NE29 0BB",
    "addr:housenumber":"21",
    "addr:postcode":"ne29 0bb",
    "addr:street":"Nile Street",
    "iso:country":"GB",
    "sg:address":"21 Nile Street",
    "sg:city":"North Shields",
    "sg:classifiers":[
        {
            "category":"Personal",
            "subcategory":"Barber",
            "type":"Services"
        }
    ],
    "sg:phone":"+44 191 258 1867",
    "sg:postcode":"NE29 0BB",
    "sg:province":"Tyne and Wear",
    "sg:tags":[
        "men's",
        "hairdresser"
    ],
    "wof:name":"Solos",
    "wof:placetype":"venue"
},
  "geometry": {"coordinates":[-1.4492759705,55.0098686218],"type":"Point"}
}