{
  "type": "Feature",
  "properties": {
    "iso:country":"GB",
    "sg:address":"90 Wickham Road",
    "sg:city":"Beckenham",
    "sg:classifiers":[
        {
            "category":"Shopping",
            "subcategory":"Pharmacy",
            "type":"Retail Goods"
        }
    ],
    "sg:postcode":"BR3 6QH",
    "sg:province":"Kent",
    "sg:tags":[
        "pharmacist",
        "chemist"
    ],
    "wof:name":"Langley Pharmacy",
    "wof:placetype":"venue"
},
  "geometry": {"coordinates":[-0.0182920005,51.399887085],"type":"Point"}
}