{
  "type": "Feature",
  "properties": {
    "iso:country":"GB",
    "sg:address":"4 Charlotte Pl",
    "sg:city":"West End",
    "sg:classifiers":[
        {
            "category":"Shopping",
            "subcategory":"Gifts & Souvenirs",
            "type":"Retail Goods"
        }
    ],
    "sg:phone":"+44 20 7436 9253",
    "sg:postcode":"W1P 1AQ",
    "sg:province":"Hampshire",
    "sg:tags":[
        "shop"
    ],
    "wof:name":"Preposterous Presents Gift Shop",
    "wof:placetype":"venue"
},
  "geometry": {"coordinates":[-0.13899,51.50758],"type":"Point"}
}