{
  "type": "Feature",
  "properties": {
    "addr:full":"Rhydyffynnon, Derwydd Road Ammanford Carmarthenshire SA18 3LJ",
    "addr:postcode":"sa18 3lj",
    "addr:street":"Derwydd Road",
    "iso:country":"GB",
    "sg:address":"Rhydyffynnon, Derwydd Road",
    "sg:city":"Ammanford",
    "sg:classifiers":[
        {
            "category":"Farming",
            "subcategory":"Farm",
            "type":"Manufacturing & Wholesale Goods"
        }
    ],
    "sg:postcode":"SA18 3LJ",
    "sg:province":"Carmarthenshire",
    "sg:tags":[
        "mixed",
        "crop"
    ],
    "wof:name":"John R Williams",
    "wof:placetype":"venue"
},
  "geometry": {"coordinates":[-3.9889450073,51.7923965454],"type":"Point"}
}