{
  "type": "Feature",
  "properties": {
    "iso:country":"GB",
    "sg:address":"15 Ashurst Close",
    "sg:city":"Liverpool",
    "sg:classifiers":[
        {
            "category":"Home & Garden",
            "subcategory":"Household Appliances",
            "type":"Retail Goods"
        }
    ],
    "sg:phone":"+44 151 428 4688",
    "sg:postcode":"L25 3QL",
    "sg:province":"Merseyside",
    "sg:tags":[
        "electrical"
    ],
    "wof:name":"Terrys Appliance Repairs",
    "wof:placetype":"venue"
},
  "geometry": {"coordinates":[-2.862752,53.385563],"type":"Point"}
}