{
  "type": "Feature",
  "properties": {
    "iso:country":"GB",
    "sg:address":"23 Westgate",
    "sg:city":"Huddersfield",
    "sg:classifiers":[
        {
            "category":"Professional",
            "type":"Services"
        }
    ],
    "sg:phone":"+44 1484 516166",
    "sg:postcode":"HD5 8XF",
    "sg:province":"West Yorkshire",
    "sg:tags":[
        "interior",
        "furnishers",
        "designer"
    ],
    "wof:name":"Janina Interiors",
    "wof:placetype":"venue"
},
  "geometry": {"coordinates":[-1.747138,53.631252],"type":"Point"}
}