{
  "type": "Feature",
  "properties": {
    "addr:full":"West Hele, Buckland Brewer Bideford Devon EX39 5LZ",
    "addr:postcode":"ex39 5lz",
    "addr:street":"West;Buckland",
    "iso:country":"GB",
    "sg:address":"West Hele, Buckland Brewer",
    "sg:city":"Bideford",
    "sg:classifiers":[
        {
            "category":"Real Estate",
            "subcategory":"Surveying",
            "type":"Services"
        },
        {
            "category":"Real Estate",
            "subcategory":"Architect",
            "type":"Services"
        }
    ],
    "sg:phone":"+44 1237 451044",
    "sg:postcode":"EX39 5LZ",
    "sg:province":"Devon",
    "sg:tags":[
        "surveyor",
        "valuer"
    ],
    "wof:name":"Robert H Hicks",
    "wof:placetype":"venue"
},
  "geometry": {"coordinates":[-4.2514038086,50.9642944336],"type":"Point"}
}