{
  "type": "Feature",
  "properties": {
    "addr:full":"Mill Lane Teignmouth Devon TQ14 9BQ",
    "addr:postcode":"tq14 9bq",
    "addr:street":"Mill Lane",
    "iso:country":"GB",
    "sg:address":"Mill Lane",
    "sg:city":"Teignmouth",
    "sg:classifiers":[
        {
            "category":"Health Services",
            "subcategory":"Hospital",
            "type":"Services"
        },
        {
            "category":"Social Services",
            "subcategory":"Adult Care",
            "type":"Services"
        },
        {
            "category":"Health Services",
            "subcategory":"Clinic",
            "type":"Services"
        }
    ],
    "sg:phone":"+44 1626 772161",
    "sg:postcode":"TQ14 9BQ",
    "sg:province":"Devon",
    "sg:tags":[
        "nh",
        "day",
        "centre"
    ],
    "wof:name":"Teignmouth Hospital",
    "wof:placetype":"venue"
},
  "geometry": {"coordinates":[-3.514549,50.552101],"type":"Point"}
}