{
  "type": "Feature",
  "properties": {
    "iso:country":"GB",
    "sg:address":"Summers Lane",
    "sg:city":"London",
    "sg:classifiers":[
        {
            "category":"Professional",
            "type":"Services"
        },
        {
            "category":"Community Center",
            "subcategory":"Social",
            "type":"Public Place"
        }
    ],
    "sg:phone":"+44 20 8446 2217",
    "sg:postcode":"N12 0PD",
    "sg:province":"Greater London",
    "sg:tags":[
        "house",
        "caterer",
        "activity"
    ],
    "wof:name":"HARTS CATERING SERVICES",
    "wof:placetype":"venue"
},
  "geometry": {"coordinates":[-0.1623139977,51.6111488342],"type":"Point"}
}