{
  "type": "Feature",
  "properties": {
    "addr:full":"Frinsbury House, Cox Street, Detling Maidstone Kent ME14 3HE",
    "addr:postcode":"me14 3he",
    "addr:street":"Cox Street",
    "iso:country":"GB",
    "sg:address":"Frinsbury House, Cox Street, Detling",
    "sg:city":"Maidstone",
    "sg:classifiers":[
        {
            "category":"Manufacturing",
            "subcategory":"Motor Vehicles & Parts",
            "type":"Manufacturing & Wholesale Goods"
        },
        {
            "category":"Autos & Motor Vehicles",
            "subcategory":"Motorcycle Sales",
            "type":"Retail Goods"
        }
    ],
    "sg:phone":"+44 1622 730939",
    "sg:postcode":"ME14 3HE",
    "sg:province":"Kent",
    "sg:tags":[
        "equipment",
        "electronic"
    ],
    "wof:name":"Boyer Bransden Electronics Ltd",
    "wof:placetype":"venue"
},
  "geometry": {"coordinates":[0.6053259969,51.3266029358],"type":"Point"}
}