{
  "type": "Feature",
  "properties": {
    "iso:country":"GB",
    "sg:address":"2 Signal Squadron, Ta Centre, Mid Craigie Road",
    "sg:city":"Dundee",
    "sg:classifiers":[
        {
            "category":"Military Area",
            "subcategory":"Coast Guard Base",
            "type":"Public Place"
        },
        {
            "category":"Government",
            "subcategory":"Office",
            "type":"Public Place"
        }
    ],
    "sg:phone":"+44 1382 457049",
    "sg:postcode":"DD4 7RH",
    "sg:province":"Dundee City",
    "sg:tags":[
        "force",
        "armed",
        "reserve"
    ],
    "sg:website":"http://www.tanet.mod.uk",
    "wof:name":"Territorial Auxiliary & Volunteer Reserve Association",
    "wof:placetype":"venue"
},
  "geometry": {"coordinates":[-2.93557,56.475498],"type":"Point"}
}