{
  "type": "Feature",
  "properties": {
    "addr:full":"Market Hall, Friargate Grimsby Lincolnshire DN31 1EE",
    "addr:postcode":"dn31 1ee",
    "addr:street":"Friargate",
    "iso:country":"GB",
    "sg:address":"Market Hall, Friargate",
    "sg:city":"Grimsby",
    "sg:classifiers":[
        {
            "category":"Sports & Exercise",
            "subcategory":"Sports Center",
            "type":"Entertainment"
        }
    ],
    "sg:postcode":"DN31 1EE",
    "sg:province":"Lincolnshire",
    "sg:tags":[
        "shop",
        "good"
    ],
    "wof:name":"Hargrave,A & J H,",
    "wof:placetype":"venue"
},
  "geometry": {"coordinates":[-0.087994,53.564465],"type":"Point"}
}