{
  "type": "Feature",
  "properties": {
    "addr:full":"Wagon Yard, Lower Church Lane Farnham Surrey GU9 7PS",
    "addr:postcode":"gu9 7ps",
    "addr:street":"Wagon;Lower Church Lane",
    "iso:country":"GB",
    "sg:address":"Wagon Yard, Lower Church Lane",
    "sg:city":"Farnham",
    "sg:classifiers":[
        {
            "category":"Manufacturing",
            "subcategory":"Jewelry",
            "type":"Manufacturing & Wholesale Goods"
        }
    ],
    "sg:phone":"+44 1252 721185",
    "sg:postcode":"GU9 7PS",
    "sg:province":"Surrey",
    "sg:tags":[
        "designer",
        "design",
        "jewellery"
    ],
    "wof:name":"Ruta Brown",
    "wof:placetype":"venue"
},
  "geometry": {"coordinates":[-0.799719,51.212975],"type":"Point"}
}