{
  "type": "Feature",
  "properties": {
    "addr:full":"11 East Laith Gate Doncaster South Yorkshire DN1 1JG",
    "addr:housenumber":"11",
    "addr:postcode":"dn1 1jg",
    "addr:street":"East Laith Gate",
    "iso:country":"GB",
    "sg:address":"11 East Laith Gate",
    "sg:city":"Doncaster",
    "sg:classifiers":[
        {
            "category":"Shopping",
            "subcategory":"Thrift Store",
            "type":"Retail Goods"
        }
    ],
    "sg:phone":"+44 1302 322107",
    "sg:postcode":"DN1 1JG",
    "sg:province":"South Yorkshire",
    "sg:tags":[
        "shop",
        "charity"
    ],
    "wof:name":"Shelter Shop",
    "wof:placetype":"venue"
},
  "geometry": {"coordinates":[-1.130275,53.524414],"type":"Point"}
}