{
  "type": "Feature",
  "properties": {
    "iso:country":"GB",
    "sg:address":"Sutton Lodge, Davids La",
    "sg:city":"Ringwood",
    "sg:classifiers":[
        {
            "category":"Autos & Motor Vehicles",
            "subcategory":"Automobile Sales",
            "type":"Retail Goods"
        }
    ],
    "sg:postcode":"BH24 2AW",
    "sg:province":"Dorset",
    "sg:tags":[
        "car"
    ],
    "wof:name":"Howard Autos",
    "wof:placetype":"venue"
},
  "geometry": {"coordinates":[-1.7929890156,50.8463287354],"type":"Point"}
}