{
  "type": "Feature",
  "properties": {
    "addr:full":"Westren Close Leominster Herefordshire HR6 0QD",
    "addr:postcode":"hr6 0qd",
    "addr:street":"Westren Close",
    "iso:country":"GB",
    "sg:address":"Westren Close",
    "sg:city":"Leominster",
    "sg:classifiers":[
        {
            "category":"Organizations",
            "subcategory":"Non-profit Organization",
            "type":"Services"
        }
    ],
    "sg:postcode":"HR6 0QD",
    "sg:province":"Herefordshire",
    "sg:tags":[
        "organisation",
        "voluntary",
        "charity"
    ],
    "wof:name":"Day One Christian Ministries",
    "wof:placetype":"venue"
},
  "geometry": {"coordinates":[-2.730519,52.220261],"type":"Point"}
}