{
  "type": "Feature",
  "properties": {
    "addr:full":"193 Uxbridge Road Rickmansworth Hertfordshire WD3 8DP",
    "addr:housenumber":"193",
    "addr:postcode":"wd3 8dp",
    "addr:street":"Uxbridge Road",
    "iso:country":"GB",
    "sg:address":"193 Uxbridge Road",
    "sg:city":"Rickmansworth",
    "sg:classifiers":[
        {
            "category":"Professional",
            "subcategory":"Accounting & Tax Preparation",
            "type":"Services"
        }
    ],
    "sg:postcode":"WD3 8DP",
    "sg:province":"Hertfordshire",
    "sg:tags":[
        "accountant"
    ],
    "wof:name":"Glencairn Uk Ltd",
    "wof:placetype":"venue"
},
  "geometry": {"coordinates":[-0.5008260012,51.6304512024],"type":"Point"}
}