{
  "type": "Feature",
  "properties": {
    "addr:full":"87 Carlton Pl Glasgow Glasgow City G5 9TD",
    "addr:housenumber":"87",
    "addr:postcode":"g5 9td",
    "addr:street":"Carlton Pl",
    "iso:country":"GB",
    "sg:address":"87 Carlton Pl",
    "sg:city":"Glasgow",
    "sg:classifiers":[
        {
            "category":"Professional",
            "subcategory":"Lawyer & Legal Services",
            "type":"Services"
        }
    ],
    "sg:phone":"+44 141 420 6300",
    "sg:postcode":"G5 9TD",
    "sg:province":"Glasgow City",
    "sg:tags":[
        "solicitor"
    ],
    "wof:name":"Pearson Swinburne & Co",
    "wof:placetype":"venue"
},
  "geometry": {"coordinates":[-4.2579631805,55.8545570374],"type":"Point"}
}