{
  "type": "Feature",
  "properties": {
    "addr:full":"2 Evesham Close, The Cotswolds Boldon Colliery Tyne and Wear NE35 9LL",
    "addr:housenumber":"2",
    "addr:postcode":"ne35 9ll",
    "addr:street":"Evesham Close",
    "iso:country":"GB",
    "sg:address":"2 Evesham Close, The Cotswolds",
    "sg:city":"Boldon Colliery",
    "sg:classifiers":[
        {
            "category":"Real Estate",
            "subcategory":"Real Estate Services",
            "type":"Services"
        }
    ],
    "sg:phone":"+44 191 537 1616",
    "sg:postcode":"NE35 9LL",
    "sg:province":"Tyne and Wear",
    "sg:tags":[
        "building",
        "raw",
        "material"
    ],
    "wof:name":"Sharelogic Ltd.",
    "wof:placetype":"venue"
},
  "geometry": {"coordinates":[-1.4622340202,54.9504508972],"type":"Point"}
}