{
  "type": "Feature",
  "properties": {
    "addr:full":"Unit 6 Avon Meads, St Philips Causeway Bristol City of Bristol BS2 0SP",
    "addr:housenumber":"unit 6",
    "addr:postcode":"bs2 0sp",
    "addr:street":"Avon Meads St Philips Causeway",
    "iso:country":"GB",
    "sg:address":"Unit 6 Avon Meads, St Philips Causeway",
    "sg:city":"Bristol",
    "sg:classifiers":[
        {
            "category":"Home & Garden",
            "subcategory":"Household Appliances",
            "type":"Retail Goods"
        }
    ],
    "sg:phone":"+44 845 600 7002",
    "sg:postcode":"BS2 0SP",
    "sg:province":"City of Bristol",
    "sg:tags":[
        "electrical",
        "domestic"
    ],
    "wof:name":"Comet Group Plc",
    "wof:placetype":"venue"
},
  "geometry": {"coordinates":[-2.55999,51.446579],"type":"Point"}
}