{
  "type": "Feature",
  "properties": {
    "addr:full":"Lowther Gardens Lytham St Annes Lancashire FY8 5QQ",
    "addr:postcode":"fy8 5qq",
    "addr:street":"Lowther Gardens;St",
    "iso:country":"GB",
    "sg:address":"Lowther Gardens",
    "sg:city":"Lytham St Annes",
    "sg:classifiers":[
        {
            "category":"Cafe",
            "type":"Food & Drink"
        }
    ],
    "sg:phone":"+44 1253 735523",
    "sg:postcode":"FY8 5QQ",
    "sg:province":"Lancashire",
    "sg:tags":[
        "tea",
        "room"
    ],
    "wof:name":"Lowther Pavilion Cafe",
    "wof:placetype":"venue"
},
  "geometry": {"coordinates":[-2.970189,53.736145],"type":"Point"}
}