{
  "type": "Feature",
  "properties": {
    "addr:full":"Unit 8-9, Enterprise Court, Huncoat Indstl Est Accrington Lancashire BB5 6TS",
    "addr:housenumber":"unit 8-9",
    "addr:postcode":"bb5 6ts",
    "addr:street":"Enterprise Court;Indstl Est",
    "iso:country":"GB",
    "sg:address":"Unit 8-9, Enterprise Court, Huncoat Indstl Est",
    "sg:city":"Accrington",
    "sg:classifiers":[
        {
            "category":"Manufacturing",
            "subcategory":"Metals",
            "type":"Manufacturing & Wholesale Goods"
        }
    ],
    "sg:phone":"+44 1254 233186",
    "sg:postcode":"BB5 6TS",
    "sg:province":"Lancashire",
    "sg:tags":[
        "steel",
        "fabricator",
        "erectors"
    ],
    "wof:name":"Mayor & Schofield Fabrications Ltd",
    "wof:placetype":"venue"
},
  "geometry": {"coordinates":[-2.3555738926,53.76720047],"type":"Point"}
}