{
  "type": "Feature",
  "properties": {
    "iso:country":"GB",
    "sg:address":"11 Church Street, Ruddington",
    "sg:city":"Nottingham",
    "sg:classifiers":[
        {
            "category":"Travel",
            "subcategory":"Travel Agent",
            "type":"Entertainment"
        }
    ],
    "sg:phone":"+44 115 984 6846",
    "sg:postcode":"NG11 6HA",
    "sg:province":"Nottinghamshire",
    "sg:tags":[
        "agency",
        "activity"
    ],
    "wof:name":"Ruddington Travel",
    "wof:placetype":"venue"
},
  "geometry": {"coordinates":[-1.1352159977,52.8611679077],"type":"Point"}
}