{
  "type": "Feature",
  "properties": {
    "addr:full":"Ryefield Farm, Funtington Road Chichester West Sussex PO18 9AP",
    "addr:postcode":"po18 9ap",
    "addr:street":"Funtington Road",
    "iso:country":"GB",
    "sg:address":"Ryefield Farm, Funtington Road",
    "sg:city":"Chichester",
    "sg:classifiers":[
        {
            "category":"Communications",
            "type":"Services"
        }
    ],
    "sg:phone":"+44 1243 575749",
    "sg:postcode":"PO18 9AP",
    "sg:province":"West Sussex",
    "sg:tags":[
        "tv",
        "video",
        "radio"
    ],
    "wof:name":"Osborne Refrigeration",
    "wof:placetype":"venue"
},
  "geometry": {"coordinates":[-0.8663979769,50.8720397949],"type":"Point"}
}