{
  "type": "Feature",
  "properties": {
    "addr:full":"2 Parkway Centre Middlesbrough North Yorkshire TS8 0TJ",
    "addr:housenumber":"2",
    "addr:postcode":"ts8 0tj",
    "addr:street":"Parkway Centre",
    "iso:country":"GB",
    "sg:address":"2 Parkway Centre",
    "sg:city":"Middlesbrough",
    "sg:classifiers":[
        {
            "category":"Shopping",
            "subcategory":"Clothing, Apparel, & Fashions",
            "type":"Retail Goods"
        }
    ],
    "sg:phone":"+44 1642 596513",
    "sg:postcode":"TS8 0TJ",
    "sg:province":"North Yorkshire",
    "sg:tags":[
        "shop"
    ],
    "wof:name":"Thrifty",
    "wof:placetype":"venue"
},
  "geometry": {"coordinates":[-1.214304,54.523476],"type":"Point"}
}