{
  "type": "Feature",
  "properties": {
    "addr:full":"Unit 4, East St Prescot Merseyside L34 5RR",
    "addr:housenumber":"unit 4",
    "addr:postcode":"l34 5rr",
    "addr:street":"East St",
    "iso:country":"GB",
    "sg:address":"Unit 4, East St",
    "sg:city":"Prescot",
    "sg:classifiers":[
        {
            "category":"Autos & Motor Vehicles",
            "subcategory":"Auto Supplies",
            "type":"Retail Goods"
        }
    ],
    "sg:phone":"+44 151 523 7077",
    "sg:postcode":"L34 5RR",
    "sg:province":"Merseyside",
    "sg:tags":[
        "windscreen"
    ],
    "wof:name":"Silver Shield Windscreens",
    "wof:placetype":"venue"
},
  "geometry": {"coordinates":[-2.7986059189,53.4284667969],"type":"Point"}
}