{
  "type": "Feature",
  "properties": {
    "addr:full":"1 Church Street, Wye Ashford Kent TN25 5BN",
    "addr:housenumber":"1",
    "addr:postcode":"tn25 5bn",
    "addr:street":"Church Street",
    "iso:country":"GB",
    "sg:address":"1 Church Street, Wye",
    "sg:city":"Ashford",
    "sg:classifiers":[
        {
            "category":"Shopping",
            "subcategory":"Gifts & Souvenirs",
            "type":"Retail Goods"
        }
    ],
    "sg:postcode":"TN25 5BN",
    "sg:province":"Kent",
    "sg:tags":[
        "shop"
    ],
    "wof:name":"The Gift Horse",
    "wof:placetype":"venue"
},
  "geometry": {"coordinates":[0.9368,51.182499],"type":"Point"}
}