{
  "type": "Feature",
  "properties": {
    "iso:country":"GB",
    "sg:address":"55 Beulah Road, Walthamstow",
    "sg:city":"London",
    "sg:classifiers":[
        {
            "category":"Professional",
            "subcategory":"Accounting & Tax Preparation",
            "type":"Services"
        }
    ],
    "sg:phone":"+44 20 8520 5395",
    "sg:postcode":"E17 9LG",
    "sg:province":"Greater London",
    "sg:tags":[
        "accountant"
    ],
    "wof:name":"McKinzey Peter Co.",
    "wof:placetype":"venue"
},
  "geometry": {"coordinates":[-0.009762,51.580933],"type":"Point"}
}