{
  "type": "Feature",
  "properties": {
    "addr:full":"P O Box 32169 London Greater London N4 4XA",
    "addr:housenumber":"box 32169",
    "addr:postcode":"n4 4xa",
    "iso:country":"GB",
    "sg:address":"P O Box 32169",
    "sg:city":"London",
    "sg:classifiers":[
        {
            "category":"Professional",
            "subcategory":"Employment Agencies",
            "type":"Services"
        }
    ],
    "sg:phone":"+44 20 8348 0310",
    "sg:postcode":"N4 4XA",
    "sg:province":"Greater London",
    "sg:tags":[
        "consultant"
    ],
    "wof:name":"Blue Chip Corporation Ltd.",
    "wof:placetype":"venue"
},
  "geometry": {"coordinates":[-0.1114500016,51.5736999512],"type":"Point"}
}