{
  "type": "Feature",
  "properties": {
    "iso:country":"GB",
    "sg:address":"39 Curzon Avenue",
    "sg:city":"Horsham",
    "sg:classifiers":[
        {
            "category":"Arena",
            "subcategory":"Sports Club",
            "type":"Entertainment"
        }
    ],
    "sg:phone":"+44 1403 253782",
    "sg:postcode":"RH12 2LA",
    "sg:province":"West Sussex",
    "wof:name":"Karate Dokuja Karate Do Wado Kai",
    "wof:placetype":"venue"
},
  "geometry": {"coordinates":[-0.33823,51.066322],"type":"Point"}
}