{
  "type": "Feature",
  "properties": {
    "addr:full":"167a Wigan Road Leigh Lancashire WN7 5DF",
    "addr:housenumber":"167a",
    "addr:postcode":"wn7 5df",
    "addr:street":"Wigan Road Leigh",
    "iso:country":"GB",
    "sg:address":"167a Wigan Road",
    "sg:city":"Leigh",
    "sg:classifiers":[
        {
            "category":"Personal",
            "subcategory":"Beauty Salon",
            "type":"Services"
        }
    ],
    "sg:phone":"+44 1942 261860",
    "sg:postcode":"WN7 5DF",
    "sg:province":"Lancashire",
    "sg:tags":[
        "unisex",
        "hairdresser"
    ],
    "wof:name":"Sharons",
    "wof:placetype":"venue"
},
  "geometry": {"coordinates":[-2.5339460373,53.502494812],"type":"Point"}
}