{
  "type": "Feature",
  "properties": {
    "addr:full":"Beechcroft, Stone Lane Welshpool Shropshire SY21 7NZ",
    "addr:postcode":"sy21 7nz",
    "addr:street":"Stone Lane",
    "iso:country":"GB",
    "sg:address":"Beechcroft, Stone Lane",
    "sg:city":"Welshpool",
    "sg:classifiers":[
        {
            "category":"Building & Trades",
            "subcategory":"Equipment Rental",
            "type":"Services"
        }
    ],
    "sg:phone":"+44 1938 552434",
    "sg:postcode":"SY21 7NZ",
    "sg:province":"Shropshire",
    "sg:tags":[
        "plant",
        "machinery"
    ],
    "wof:name":"Rodney Graham Gotto",
    "wof:placetype":"venue"
},
  "geometry": {"coordinates":[-3.1452031136,52.661190033],"type":"Point"}
}