{
  "type": "Feature",
  "properties": {
    "iso:country":"GB",
    "sg:address":"Evesham Road, Greet",
    "sg:city":"Cheltenham",
    "sg:classifiers":[
        {
            "category":"Bars & Pubs",
            "type":"Food & Drink"
        },
        {
            "category":"Community Center",
            "subcategory":"Social",
            "type":"Public Place"
        }
    ],
    "sg:phone":"+44 1242 602430",
    "sg:postcode":"GL54 5BH",
    "sg:province":"Gloucestershire",
    "sg:tags":[
        "pubs",
        "house",
        "inn",
        "activity"
    ],
    "wof:name":"Harvest Home",
    "wof:placetype":"venue"
},
  "geometry": {"coordinates":[-1.9663410187,51.9690933228],"type":"Point"}
}