{
  "type": "Feature",
  "properties": {
    "iso:country":"GB",
    "sg:address":"2 Charlecombe Court, Stoke Lane, Westbury-on-trym",
    "sg:city":"Bristol",
    "sg:classifiers":[
        {
            "category":"Shopping",
            "subcategory":"Crafts & Fabrics",
            "type":"Retail Goods"
        }
    ],
    "sg:postcode":"BS9 3RL",
    "sg:province":"City of Bristol",
    "sg:tags":[
        "shop"
    ],
    "wof:name":"Patchwork House",
    "wof:placetype":"venue"
},
  "geometry": {"coordinates":[-2.6252090931,51.4889640808],"type":"Point"}
}