{
  "type": "Feature",
  "properties": {
    "addr:full":"Unit 4 Carlton Lane Castleford West Yorkshire WF10 1BA",
    "addr:housenumber":"unit 4",
    "addr:postcode":"wf10 1ba",
    "addr:street":"Carlton Lane",
    "iso:country":"GB",
    "sg:address":"Unit 4 Carlton Lane",
    "sg:city":"Castleford",
    "sg:classifiers":[
        {
            "category":"Food & Beverages",
            "subcategory":"Bakery",
            "type":"Retail Goods"
        }
    ],
    "sg:phone":"+44 1977 603843",
    "sg:postcode":"WF10 1BA",
    "sg:province":"West Yorkshire",
    "sg:tags":[
        "baker"
    ],
    "wof:name":"Watson's Bakeries",
    "wof:placetype":"venue"
},
  "geometry": {"coordinates":[-1.3504290581,53.7265014648],"type":"Point"}
}