{
  "type": "Feature",
  "properties": {
    "addr:full":"Harrisons Farm, Old School La Chorley Lancashire PR7 4DX",
    "addr:postcode":"pr7 4dx",
    "addr:street":"Old;La Chorley",
    "iso:country":"GB",
    "sg:address":"Harrisons Farm, Old School La",
    "sg:city":"Chorley",
    "sg:classifiers":[
        {
            "category":"Farming",
            "subcategory":"Livestock Farm",
            "type":"Manufacturing & Wholesale Goods"
        }
    ],
    "sg:phone":"+44 1257 480367",
    "sg:postcode":"PR7 4DX",
    "sg:province":"Lancashire",
    "sg:tags":[
        "others"
    ],
    "wof:name":"J L Gill",
    "wof:placetype":"venue"
},
  "geometry": {"coordinates":[-2.604931,53.608929],"type":"Point"}
}