{
  "type": "Feature",
  "properties": {
    "iso:country":"GB",
    "sg:address":"51-53 Bridge Street",
    "sg:city":"Downham Market",
    "sg:classifiers":[
        {
            "category":"Restaurant",
            "type":"Food & Drink"
        }
    ],
    "sg:phone":"+44 1366 388147",
    "sg:postcode":"PE38 9DW",
    "sg:province":"Cambridgeshire",
    "sg:tags":[
        "thai",
        "-"
    ],
    "wof:name":"Dang Thai Restaurant",
    "wof:placetype":"venue"
},
  "geometry": {"coordinates":[0.374516,52.602638],"type":"Point"}
}