{
  "type": "Feature",
  "properties": {
    "addr:full":"Parkside, Sellman Street, Gnosall Stafford Staffordshire ST20 0EP",
    "addr:postcode":"st20 0ep",
    "addr:street":"Sellman Street",
    "iso:country":"GB",
    "sg:address":"Parkside, Sellman Street, Gnosall",
    "sg:city":"Stafford",
    "sg:classifiers":[
        {
            "category":"Professional",
            "subcategory":"Management & Consulting",
            "type":"Services"
        }
    ],
    "sg:phone":"+44 1785 823263",
    "sg:postcode":"ST20 0EP",
    "sg:province":"Staffordshire",
    "sg:tags":[
        "consultant",
        "business"
    ],
    "wof:name":"Gordon V Herbert",
    "wof:placetype":"venue"
},
  "geometry": {"coordinates":[-2.256487,52.78233],"type":"Point"}
}