{
  "type": "Feature",
  "properties": {
    "addr:full":"Clarke Road Northampton Northamptonshire NN1 4PW",
    "addr:postcode":"nn1 4pw",
    "addr:street":"Clarke Road",
    "iso:country":"GB",
    "sg:address":"Clarke Road",
    "sg:city":"Northampton",
    "sg:classifiers":[
        {
            "category":"Autos & Motor Vehicles",
            "subcategory":"Automobile Sales",
            "type":"Retail Goods"
        }
    ],
    "sg:phone":"+44 1604 631611",
    "sg:postcode":"NN1 4PW",
    "sg:province":"Northamptonshire",
    "sg:tags":[
        "car"
    ],
    "wof:name":"Campbell Motors",
    "wof:placetype":"venue"
},
  "geometry": {"coordinates":[-0.872706,52.247673],"type":"Point"}
}