{
  "type": "Feature",
  "properties": {
    "iso:country":"GB",
    "sg:address":"16 Market Street, Birstall",
    "sg:city":"Batley",
    "sg:classifiers":[
        {
            "category":"Personal",
            "subcategory":"Beauty Salon",
            "type":"Services"
        }
    ],
    "sg:postcode":"WF17 9EN",
    "sg:province":"West Yorkshire",
    "sg:tags":[
        "unisex",
        "hairdresser"
    ],
    "wof:name":"Dawn Meakin",
    "wof:placetype":"venue"
},
  "geometry": {"coordinates":[-1.6609419584,53.7311325073],"type":"Point"}
}