{
  "type": "Feature",
  "properties": {
    "iso:country":"GB",
    "sg:address":"23 South Street",
    "sg:city":"Farnham",
    "sg:classifiers":[
        {
            "category":"Restaurant",
            "type":"Food & Drink"
        }
    ],
    "sg:postcode":"GU9 7QU",
    "sg:province":"Surrey",
    "sg:tags":[
        "greek"
    ],
    "wof:name":"The New Grecian Taverna",
    "wof:placetype":"venue"
},
  "geometry": {"coordinates":[-0.795929,51.214119],"type":"Point"}
}