{
  "type": "Feature",
  "properties": {
    "iso:country":"GB",
    "sg:address":"199 New Cross Rd",
    "sg:city":"New Cross",
    "sg:classifiers":[
        {
            "category":"Personal",
            "type":"Services"
        }
    ],
    "sg:phone":"+44 20 7639 6657",
    "sg:postcode":"SE14 5ET",
    "sg:province":"Greater London",
    "sg:tags":[
        "delivery"
    ],
    "wof:name":"Royal Mail",
    "wof:placetype":"venue"
},
  "geometry": {"coordinates":[-0.04591,51.47456],"type":"Point"}
}