{
  "type": "Feature",
  "properties": {
    "iso:country":"GB",
    "sg:address":"Mains Road",
    "sg:city":"Beith",
    "sg:classifiers":[
        {
            "category":"Landmark",
            "subcategory":"Tourist Attraction",
            "type":"Public Place"
        }
    ],
    "sg:phone":"+44 1505 503898",
    "sg:postcode":"KA15 2AF",
    "sg:province":"North Ayrshire",
    "sg:tags":[
        "interest"
    ],
    "wof:name":"Meadowside Pervillion",
    "wof:placetype":"venue"
},
  "geometry": {"coordinates":[-4.6361560822,55.7523651123],"type":"Point"}
}