{
  "type": "Feature",
  "properties": {
    "addr:full":"Carrs House, Fore Street, Tamerton Foliot Plymouth Devon PL5 4NA",
    "addr:postcode":"pl5 4na",
    "addr:street":"Fore Street",
    "iso:country":"GB",
    "sg:address":"Carrs House, Fore Street, Tamerton Foliot",
    "sg:city":"Plymouth",
    "sg:classifiers":[
        {
            "category":"Fast Food",
            "type":"Food & Drink"
        }
    ],
    "sg:phone":"+44 1752 709067",
    "sg:postcode":"PL5 4NA",
    "sg:province":"Devon",
    "sg:tags":[
        "away",
        "meal",
        "outlet",
        "take"
    ],
    "wof:name":"May Fong",
    "wof:placetype":"venue"
},
  "geometry": {"coordinates":[-4.1562690735,50.4286575317],"type":"Point"}
}