{
  "type": "Feature",
  "properties": {
    "iso:country":"GB",
    "sg:address":"22a Nicolson St",
    "sg:city":"Edinburgh",
    "sg:classifiers":[
        {
            "category":"Restaurant",
            "type":"Food & Drink"
        }
    ],
    "sg:postcode":"EH8 9DH",
    "sg:province":"City of Edinburgh",
    "wof:name":"Librizzis",
    "wof:placetype":"venue"
},
  "geometry": {"coordinates":[-3.1855,55.946781],"type":"Point"}
}