{
  "type": "Feature",
  "properties": {
    "addr:full":"Ford Forge, Heatherslaw Cornhill-on-tweed Northumberland TD12 4QA",
    "addr:postcode":"td12 4qa",
    "addr:street":"Northumberland",
    "iso:country":"GB",
    "sg:address":"Ford Forge, Heatherslaw",
    "sg:city":"Cornhill-on-tweed",
    "sg:classifiers":[
        {
            "category":"Landmark",
            "subcategory":"Tourist Attraction",
            "type":"Public Place"
        }
    ],
    "sg:phone":"+44 1890 820244",
    "sg:postcode":"TD12 4QA",
    "sg:province":"Northumberland",
    "sg:tags":[
        "interest"
    ],
    "wof:name":"The Heatherslaw Light Railway Co. Ltd.",
    "wof:placetype":"venue"
},
  "geometry": {"coordinates":[-2.220848,55.648235],"type":"Point"}
}