{
  "type": "Feature",
  "properties": {
    "iso:country":"GB",
    "sg:address":"Leppings Lane, Wadsley Bridge",
    "sg:city":"Sheffield",
    "sg:classifiers":[
        {
            "category":"Travel",
            "subcategory":"Travel Agent",
            "type":"Entertainment"
        }
    ],
    "sg:phone":"+44 114 234 5247",
    "sg:postcode":"S6 1LR",
    "sg:province":"South Yorkshire",
    "wof:name":"Law Bros (Tours) Ltd.",
    "wof:placetype":"venue"
},
  "geometry": {"coordinates":[-1.5009930134,53.4148826599],"type":"Point"}
}