{
  "type": "Feature",
  "properties": {
    "iso:country":"GB",
    "sg:address":"43 Grants Avenue",
    "sg:city":"Bournemouth",
    "sg:classifiers":[
        {
            "category":"Professional",
            "subcategory":"Art Services",
            "type":"Services"
        },
        {
            "category":"Building & Trades",
            "subcategory":"Construction",
            "type":"Services"
        }
    ],
    "sg:postcode":"BH1 4NS",
    "sg:province":"Dorset",
    "sg:tags":[
        "decorator",
        "painter"
    ],
    "wof:name":"Richard James Redwood",
    "wof:placetype":"venue"
},
  "geometry": {"coordinates":[-1.844959,50.733677],"type":"Point"}
}