{
  "type": "Feature",
  "properties": {
    "addr:full":"98 Laghall Court, Kingholm Quay Dumfries Dumfries and Galloway DG1 4SX",
    "addr:housenumber":"98",
    "addr:postcode":"dg1 4sx",
    "addr:street":"Laghall Court;Quay",
    "iso:country":"GB",
    "sg:address":"98 Laghall Court, Kingholm Quay",
    "sg:city":"Dumfries",
    "sg:classifiers":[
        {
            "category":"Freight",
            "type":"Transportation"
        }
    ],
    "sg:phone":"+44 1387 264445",
    "sg:postcode":"DG1 4SX",
    "sg:province":"Dumfries and Galloway",
    "sg:tags":[
        "haulage",
        "transport",
        "road"
    ],
    "wof:name":"George M Brown",
    "wof:placetype":"venue"
},
  "geometry": {"coordinates":[-3.601616,55.045727],"type":"Point"}
}