{
  "type": "Feature",
  "properties": {
    "addr:full":"17 Junction Place Haslemere Hampshire GU27 1LE",
    "addr:housenumber":"17",
    "addr:postcode":"gu27 1le",
    "addr:street":"Junction Place",
    "iso:country":"GB",
    "sg:address":"17 Junction Place",
    "sg:city":"Haslemere",
    "sg:classifiers":[
        {
            "category":"Fast Food",
            "type":"Food & Drink"
        }
    ],
    "sg:phone":"+44 1428 644666",
    "sg:postcode":"GU27 1LE",
    "sg:province":"Hampshire",
    "sg:tags":[
        "away",
        "meal",
        "outlet",
        "take"
    ],
    "wof:name":"The Tasty",
    "wof:placetype":"venue"
},
  "geometry": {"coordinates":[-0.7335050106,51.0878067017],"type":"Point"}
}