{
  "type": "Feature",
  "properties": {
    "iso:country":"GB",
    "sg:address":"35 Newgate Rd",
    "sg:city":"Sale",
    "sg:classifiers":[
        {
            "category":"Social Services",
            "subcategory":"Job Training",
            "type":"Services"
        }
    ],
    "sg:phone":"+44 161 973 4355",
    "sg:postcode":"M33 4UG",
    "sg:province":"Cheshire",
    "sg:tags":[
        "translator",
        "interpreter"
    ],
    "wof:name":"German Translations",
    "wof:placetype":"venue"
},
  "geometry": {"coordinates":[-2.35984,53.409679],"type":"Point"}
}