{
  "type": "Feature",
  "properties": {
    "iso:country":"GB",
    "sg:address":"Care Of Sordale",
    "sg:city":"Halkirk",
    "sg:classifiers":[
        {
            "category":"Farming",
            "subcategory":"Livestock Farm",
            "type":"Manufacturing & Wholesale Goods"
        }
    ],
    "sg:phone":"+44 1847 831228",
    "sg:postcode":"KW12 6XB",
    "sg:province":"Highland",
    "sg:tags":[
        "others"
    ],
    "wof:name":"Allen J Scott",
    "wof:placetype":"venue"
},
  "geometry": {"coordinates":[-3.495523,58.514343],"type":"Point"}
}