{
  "type": "Feature",
  "properties": {
    "addr:full":"C/o House Of Fraser, George Street Altrincham Cheshire WA14 1RH",
    "addr:housenumber":"/ o",
    "addr:postcode":"wa14 1rh",
    "addr:street":"C;George Street",
    "iso:country":"GB",
    "sg:address":"C/o House Of Fraser, George Street",
    "sg:city":"Altrincham",
    "sg:classifiers":[
        {
            "category":"Shopping",
            "subcategory":"Clothing, Apparel, & Fashions",
            "type":"Retail Goods"
        }
    ],
    "sg:phone":"+44 161 928 6662",
    "sg:postcode":"WA14 1RH",
    "sg:province":"Cheshire",
    "sg:tags":[
        "ladieswear"
    ],
    "wof:name":"Country Casuals",
    "wof:placetype":"venue"
},
  "geometry": {"coordinates":[-2.349209,53.386726],"type":"Point"}
}