{
  "type": "Feature",
  "properties": {
    "addr:full":"58 Hillreach London Greater London SE18 4AL",
    "addr:housenumber":"58",
    "addr:postcode":"se18 4al",
    "addr:street":"Hillreach",
    "iso:country":"GB",
    "sg:address":"58 Hillreach",
    "sg:city":"London",
    "sg:classifiers":[
        {
            "category":"Shopping",
            "subcategory":"Department Store",
            "type":"Retail Goods"
        }
    ],
    "sg:phone":"+44 20 8854 1836",
    "sg:postcode":"SE18 4AL",
    "sg:province":"Greater London",
    "wof:name":"Hillreach General Store",
    "wof:placetype":"venue"
},
  "geometry": {"coordinates":[0.0502969995,51.4856071472],"type":"Point"}
}