{
  "type": "Feature",
  "properties": {
    "addr:full":"1-3 William Street Sunderland Tyne and Wear SR1 1UL",
    "addr:housenumber":"1-3",
    "addr:postcode":"sr1 1ul",
    "addr:street":"William Street",
    "iso:country":"GB",
    "sg:address":"1-3 William Street",
    "sg:city":"Sunderland",
    "sg:classifiers":[
        {
            "category":"Professional",
            "subcategory":"Printing & Photocopies",
            "type":"Services"
        }
    ],
    "sg:phone":"+44 191 567 4727",
    "sg:postcode":"SR1 1UL",
    "sg:province":"Tyne and Wear",
    "sg:tags":[
        "printer"
    ],
    "wof:name":"Robert Attey & Sons Ltd.",
    "wof:placetype":"venue"
},
  "geometry": {"coordinates":[-1.378536,54.908108],"type":"Point"}
}