{
  "type": "Feature",
  "properties": {
    "iso:country":"GB",
    "sg:address":"Southam Rd",
    "sg:city":"Banbury",
    "sg:classifiers":[
        {
            "category":"Autos & Motor Vehicles",
            "subcategory":"Automobile Sales",
            "type":"Retail Goods"
        }
    ],
    "sg:phone":"+44 1295 268491",
    "sg:postcode":"OX16 7RR",
    "sg:province":"Oxfordshire",
    "sg:tags":[
        "car"
    ],
    "wof:name":"Reg Vardy",
    "wof:placetype":"venue"
},
  "geometry": {"coordinates":[-1.3368400335,52.0745773315],"type":"Point"}
}