{
  "type": "Feature",
  "properties": {
    "addr:full":"1 Rick Meadow, Yeolmbridge Launceston Cornwall PL15 8TX",
    "addr:housenumber":"1",
    "addr:postcode":"pl15 8tx",
    "addr:street":"Rick Meadow Yeolmbridge Launceston",
    "iso:country":"GB",
    "sg:address":"1 Rick Meadow, Yeolmbridge",
    "sg:city":"Launceston",
    "sg:classifiers":[
        {
            "category":"Professional",
            "subcategory":"Engineering",
            "type":"Services"
        }
    ],
    "sg:postcode":"PL15 8TX",
    "sg:province":"Cornwall",
    "sg:tags":[
        "contractor",
        "electrical",
        "engineer"
    ],
    "wof:name":"Vivien Heard",
    "wof:placetype":"venue"
},
  "geometry": {"coordinates":[-4.3811488152,50.6627807617],"type":"Point"}
}