{
  "type": "Feature",
  "properties": {
    "addr:full":"The Surgery, Sandy La Stafford Shropshire ST19 9ES",
    "addr:postcode":"st19 9es",
    "addr:street":"Sandy",
    "iso:country":"GB",
    "sg:address":"The Surgery, Sandy La",
    "sg:city":"Stafford",
    "sg:classifiers":[
        {
            "category":"Health Services",
            "subcategory":"Doctor",
            "type":"Services"
        }
    ],
    "sg:phone":"+44 1902 850206",
    "sg:postcode":"ST19 9ES",
    "sg:province":"Shropshire",
    "sg:tags":[
        "practitioners"
    ],
    "wof:name":"Taylor, R C H",
    "wof:placetype":"venue"
},
  "geometry": {"coordinates":[-2.1719200611,52.6758918762],"type":"Point"}
}