{
  "type": "Feature",
  "properties": {
    "addr:full":"Fincham Rd, Stow Bardolph King's Lynn Lincolnshire PE34 3HX",
    "addr:postcode":"pe34 3hx",
    "addr:street":"Fincham Rd",
    "iso:country":"GB",
    "sg:address":"Fincham Rd, Stow Bardolph",
    "sg:city":"King's Lynn",
    "sg:classifiers":[
        {
            "category":"Building & Trades",
            "subcategory":"Construction",
            "type":"Services"
        }
    ],
    "sg:phone":"+44 1366 384031",
    "sg:postcode":"PE34 3HX",
    "sg:province":"Lincolnshire",
    "sg:tags":[
        "joiner",
        "carpenter"
    ],
    "wof:name":"Peter Goodrum",
    "wof:placetype":"venue"
},
  "geometry": {"coordinates":[0.40727,52.62582],"type":"Point"}
}