{
  "type": "Feature",
  "properties": {
    "addr:full":"90 High St Barnet Hertfordshire EN5 5SN",
    "addr:housenumber":"90",
    "addr:postcode":"en5 5sn",
    "addr:street":"High St",
    "iso:country":"GB",
    "sg:address":"90 High St",
    "sg:city":"Barnet",
    "sg:classifiers":[
        {
            "category":"Manufacturing",
            "subcategory":"Textiles",
            "type":"Manufacturing & Wholesale Goods"
        }
    ],
    "sg:phone":"+44 20 8449 5877",
    "sg:postcode":"EN5 5SN",
    "sg:province":"Hertfordshire",
    "sg:tags":[
        "made-up"
    ],
    "wof:name":"The Linen Box",
    "wof:placetype":"venue"
},
  "geometry": {"coordinates":[-0.2009959966,51.6535377502],"type":"Point"}
}