{
  "type": "Feature",
  "properties": {
    "iso:country":"GB",
    "sg:address":"Falsgrave Cres",
    "sg:city":"York",
    "sg:classifiers":[
        {
            "category":"Community Center",
            "subcategory":"Youth",
            "type":"Public Place"
        }
    ],
    "sg:phone":"+44 1904 630526",
    "sg:postcode":"YO3 7AZ",
    "sg:province":"East Riding of Yorkshire",
    "sg:tags":[
        "organisation",
        "centre"
    ],
    "wof:name":"Young Peoples Fellowship Youth Club",
    "wof:placetype":"venue"
},
  "geometry": {"coordinates":[-1.086959,53.971802],"type":"Point"}
}