{
  "type": "Feature",
  "properties": {
    "addr:full":"Bodelva Par Cornwall PL24 2SG",
    "addr:postcode":"pl24 2sg",
    "iso:country":"GB",
    "sg:address":"Bodelva",
    "sg:city":"Par",
    "sg:classifiers":[
        {
            "category":"Landmark",
            "subcategory":"Tourist Attraction",
            "type":"Public Place"
        }
    ],
    "sg:phone":"+44 1726 811911",
    "sg:postcode":"PL24 2SG",
    "sg:province":"Cornwall",
    "sg:tags":[
        "interest"
    ],
    "wof:name":"Eden Project Ltd.",
    "wof:placetype":"venue"
},
  "geometry": {"coordinates":[-4.738104,50.360546],"type":"Point"}
}