{
  "type": "Feature",
  "properties": {
    "addr:full":"18 Stirling Avenue Aylesbury Buckinghamshire HP20 1BE",
    "addr:housenumber":"18",
    "addr:postcode":"hp20 1be",
    "addr:street":"Stirling Avenue",
    "iso:country":"GB",
    "sg:address":"18 Stirling Avenue",
    "sg:city":"Aylesbury",
    "sg:classifiers":[
        {
            "category":"Retail",
            "subcategory":"Driving School",
            "type":"Services"
        }
    ],
    "sg:postcode":"HP20 1BE",
    "sg:province":"Buckinghamshire",
    "wof:name":"Drive on School of Motoring",
    "wof:placetype":"venue"
},
  "geometry": {"coordinates":[-0.8067470193,51.8211326599],"type":"Point"}
}