{
  "type": "Feature",
  "properties": {
    "iso:country":"GB",
    "sg:address":"7 Warsash Close",
    "sg:city":"Havant",
    "sg:classifiers":[
        {
            "category":"Professional",
            "subcategory":"Computer Services",
            "type":"Services"
        }
    ],
    "sg:phone":"+44 23 9248 6886",
    "sg:postcode":"PO9 4LE",
    "sg:province":"Hampshire",
    "sg:tags":[
        "system",
        "software"
    ],
    "wof:name":"Computer Cafe",
    "wof:placetype":"venue"
},
  "geometry": {"coordinates":[-0.991257,50.873665],"type":"Point"}
}