{
  "type": "Feature",
  "properties": {
    "addr:full":"Harberton Totnes Devon TQ9 7SP",
    "addr:postcode":"tq9 7sp",
    "iso:country":"GB",
    "sg:address":"Harberton",
    "sg:city":"Totnes",
    "sg:classifiers":[
        {
            "category":"Farming",
            "subcategory":"Livestock Farm",
            "type":"Manufacturing & Wholesale Goods"
        }
    ],
    "sg:phone":"+44 1803 862418",
    "sg:postcode":"TQ9 7SP",
    "sg:province":"Devon",
    "sg:tags":[
        "others"
    ],
    "wof:name":"R Rose",
    "wof:placetype":"venue"
},
  "geometry": {"coordinates":[-3.7173240185,50.4118461609],"type":"Point"}
}