{
  "type": "Feature",
  "properties": {
    "iso:country":"GB",
    "sg:address":"28 Dunsmore Road",
    "sg:city":"Walton-on-thames",
    "sg:classifiers":[
        {
            "category":"Social Services",
            "subcategory":"Adult Care",
            "type":"Services"
        }
    ],
    "sg:postcode":"KT12 2LJ",
    "sg:province":"Surrey",
    "sg:tags":[
        "domestic",
        "cleaning"
    ],
    "wof:name":"Victorian Maids",
    "wof:placetype":"venue"
},
  "geometry": {"coordinates":[-0.4120360017,51.3966255188],"type":"Point"}
}