{
  "type": "Feature",
  "properties": {
    "addr:full":"33 Brouster Hill, East Kilbride Glasgow South Lanarkshire G74 1AG",
    "addr:housenumber":"33",
    "addr:postcode":"g74 1ag",
    "addr:street":"Brouster Hill",
    "iso:country":"GB",
    "sg:address":"33 Brouster Hill, East Kilbride",
    "sg:city":"Glasgow",
    "sg:classifiers":[
        {
            "category":"Health Services",
            "subcategory":"Podiatrist",
            "type":"Services"
        }
    ],
    "sg:postcode":"G74 1AG",
    "sg:province":"South Lanarkshire",
    "sg:tags":[
        "podiatrists",
        "chiropodist"
    ],
    "wof:name":"Anne M McLean",
    "wof:placetype":"venue"
},
  "geometry": {"coordinates":[-4.1777791977,55.7629547119],"type":"Point"}
}