{
  "type": "Feature",
  "properties": {
    "addr:full":"241 North St Glasgow Glasgow City G3 7DL",
    "addr:housenumber":"241",
    "addr:postcode":"g3 7dl",
    "addr:street":"North St",
    "iso:country":"GB",
    "sg:address":"241 North St",
    "sg:city":"Glasgow",
    "sg:classifiers":[
        {
            "category":"Bars & Pubs",
            "type":"Food & Drink"
        }
    ],
    "sg:phone":"+44 141 226 4419",
    "sg:postcode":"G3 7DL",
    "sg:province":"Glasgow City",
    "sg:tags":[
        "pubs",
        "inn"
    ],
    "wof:name":"Ritz Bar The",
    "wof:placetype":"venue"
},
  "geometry": {"coordinates":[-4.2719039917,55.8660697937],"type":"Point"}
}