{
  "type": "Feature",
  "properties": {
    "addr:full":"Po Box 1 Huncote Leicester Leicestershire LE9 3AX",
    "addr:housenumber":"po;1",
    "addr:postcode":"le9 3ax",
    "addr:street":"Box",
    "iso:country":"GB",
    "sg:address":"Po Box 1 Huncote",
    "sg:city":"Leicester",
    "sg:classifiers":[
        {
            "category":"Communications",
            "subcategory":"Film & Video Production",
            "type":"Services"
        }
    ],
    "sg:postcode":"LE9 3AX",
    "sg:province":"Leicestershire",
    "sg:tags":[
        "tv"
    ],
    "wof:name":"Ashwells Tv Rentals",
    "wof:placetype":"venue"
},
  "geometry": {"coordinates":[-1.246739,52.557522],"type":"Point"}
}