{
  "type": "Feature",
  "properties": {
    "addr:full":"Park Road Ruthin Denbighshire LL15 1NQ",
    "addr:postcode":"ll15 1nq",
    "addr:street":"Park Road",
    "iso:country":"GB",
    "sg:address":"Park Road",
    "sg:city":"Ruthin",
    "sg:classifiers":[
        {
            "category":"Professional",
            "subcategory":"Business Services",
            "type":"Services"
        },
        {
            "category":"Shopping",
            "type":"Retail Goods"
        }
    ],
    "sg:phone":"+44 1824 704900",
    "sg:postcode":"LL15 1NQ",
    "sg:province":"Denbighshire",
    "sg:tags":[
        "merchant",
        "agricultural"
    ],
    "sg:website":"http://www.wynnstay.co.uk",
    "wof:name":"Wynnstay Group Plc",
    "wof:placetype":"venue"
},
  "geometry": {"coordinates":[-3.31597,53.113392],"type":"Point"}
}