{
  "type": "Feature",
  "properties": {
    "addr:full":"361 Annan Road Dumfries Dumfries and Galloway DG1 3JR",
    "addr:housenumber":"361",
    "addr:postcode":"dg1 3jr",
    "addr:street":"Annan Road",
    "iso:country":"GB",
    "sg:address":"361 Annan Road",
    "sg:city":"Dumfries",
    "sg:classifiers":[
        {
            "category":"Autos & Motor Vehicles",
            "subcategory":"Automobile Sales",
            "type":"Retail Goods"
        }
    ],
    "sg:postcode":"DG1 3JR",
    "sg:province":"Dumfries and Galloway",
    "sg:tags":[
        "car"
    ],
    "wof:name":"Solway Cars",
    "wof:placetype":"venue"
},
  "geometry": {"coordinates":[-3.572742,55.069122],"type":"Point"}
}