{
  "type": "Feature",
  "properties": {
    "addr:full":"14 East Sheen Avenue London Greater London SW14 8AS",
    "addr:housenumber":"14",
    "addr:postcode":"sw14 8as",
    "addr:street":"East Sheen Avenue",
    "iso:country":"GB",
    "sg:address":"14 East Sheen Avenue",
    "sg:city":"London",
    "sg:classifiers":[
        {
            "category":"Organizations",
            "subcategory":"Non-profit Organization",
            "type":"Services"
        }
    ],
    "sg:phone":"+44 20 8392 1839",
    "sg:postcode":"SW14 8AS",
    "sg:province":"Greater London",
    "sg:tags":[
        "organisation",
        "voluntary",
        "charity"
    ],
    "wof:name":"The Suzy Lamplugh Trust",
    "wof:placetype":"venue"
},
  "geometry": {"coordinates":[-0.2621389925,51.464225769],"type":"Point"}
}