{
  "type": "Feature",
  "properties": {
    "iso:country":"GB",
    "sg:address":"The Weathervanes, The Street, Troston",
    "sg:city":"Bury St Edmunds",
    "sg:classifiers":[
        {
            "category":"Professional",
            "subcategory":"Management & Consulting",
            "type":"Services"
        },
        {
            "category":"Building & Trades",
            "subcategory":"Plumbing",
            "type":"Services"
        }
    ],
    "sg:phone":"+44 1359 269360",
    "sg:postcode":"IP31 1EW",
    "sg:province":"Suffolk",
    "sg:tags":[
        "consultant",
        "energy",
        "conservation",
        "heating"
    ],
    "wof:name":"Conservation Engineering Ltd.",
    "wof:placetype":"venue"
},
  "geometry": {"coordinates":[0.783419,52.314877],"type":"Point"}
}