{
  "type": "Feature",
  "properties": {
    "addr:full":"1 North End, Bassingbourn Royston Bedfordshire SG8 5NX",
    "addr:housenumber":"1;bassingbourn",
    "addr:postcode":"sg8 5nx",
    "addr:street":"North End",
    "iso:country":"GB",
    "sg:address":"1 North End, Bassingbourn",
    "sg:city":"Royston",
    "sg:classifiers":[
        {
            "category":"Professional",
            "subcategory":"Management & Consulting",
            "type":"Services"
        }
    ],
    "sg:phone":"+44 1763 242746",
    "sg:postcode":"SG8 5NX",
    "sg:province":"Bedfordshire",
    "sg:tags":[
        "consultant",
        "business"
    ],
    "wof:name":"Stephen Brooker Consulting Ltd.",
    "wof:placetype":"venue"
},
  "geometry": {"coordinates":[-0.0597050004,52.0775985718],"type":"Point"}
}