{
  "type": "Feature",
  "properties": {
    "iso:country":"GB",
    "sg:address":"Unit 3, Manor Building, Holywell Road",
    "sg:city":"Flint",
    "sg:classifiers":[
        {
            "category":"Home & Garden",
            "subcategory":"Furniture",
            "type":"Retail Goods"
        }
    ],
    "sg:phone":"+44 1352 763773",
    "sg:postcode":"CH6 5RR",
    "sg:province":"Flintshire",
    "wof:name":"North Wales Classic Upholstery Ltd.",
    "wof:placetype":"venue"
},
  "geometry": {"coordinates":[-3.1554789543,53.2596855164],"type":"Point"}
}