{
  "type": "Feature",
  "properties": {
    "addr:full":"Unit 1, 20 Rothbury Road, Hackney London Greater London E9 5HA",
    "addr:housenumber":"unit;20",
    "addr:postcode":"e9 5ha",
    "addr:street":"Rothbury Road",
    "iso:country":"GB",
    "sg:address":"Unit 1, 20 Rothbury Road, Hackney",
    "sg:city":"London",
    "sg:classifiers":[
        {
            "category":"Professional",
            "subcategory":"Printing & Photocopies",
            "type":"Services"
        }
    ],
    "sg:phone":"+44 20 8985 1280",
    "sg:postcode":"E9 5HA",
    "sg:province":"Greater London",
    "sg:tags":[
        "plate",
        "lithographic",
        "maker"
    ],
    "wof:name":"Sceptic Ltd.",
    "wof:placetype":"venue"
},
  "geometry": {"coordinates":[-0.0263529997,51.5419540405],"type":"Point"}
}