{
  "type": "Feature",
  "properties": {
    "addr:full":"22 Tower Road Bournemouth Dorset BH1 4LB",
    "addr:housenumber":"22",
    "addr:postcode":"bh1 4lb",
    "addr:street":"Tower Road",
    "iso:country":"GB",
    "sg:address":"22 Tower Road",
    "sg:city":"Bournemouth",
    "sg:classifiers":[
        {
            "category":"Health Services",
            "subcategory":"Hospital",
            "type":"Services"
        }
    ],
    "sg:phone":"+44 1202 300024",
    "sg:postcode":"BH1 4LB",
    "sg:province":"Dorset",
    "wof:name":"Springbourne House",
    "wof:placetype":"venue"
},
  "geometry": {"coordinates":[-1.842457056,50.7299995422],"type":"Point"}
}