{
  "type": "Feature",
  "properties": {
    "iso:country":"GB",
    "sg:address":"Bhompston Farm, Bhompston",
    "sg:city":"Dorchester",
    "sg:classifiers":[
        {
            "category":"Farming",
            "subcategory":"Livestock Farm",
            "type":"Manufacturing & Wholesale Goods"
        }
    ],
    "sg:postcode":"DT2 8QN",
    "sg:province":"Dorset",
    "sg:tags":[
        "others"
    ],
    "wof:name":"Anthony Wakely & Son",
    "wof:placetype":"venue"
},
  "geometry": {"coordinates":[-2.3881,50.714699],"type":"Point"}
}