{
  "type": "Feature",
  "properties": {
    "addr:full":"Unit 7, Guniess Road Trading Estate, Guniess Road Manchester Cheshire M17 1SB",
    "addr:housenumber":"unit 7",
    "addr:postcode":"m17 1sb",
    "addr:street":"Guniess Road Trading Estate Guniess Road",
    "iso:country":"GB",
    "sg:address":"Unit 7, Guniess Road Trading Estate, Guniess Road",
    "sg:city":"Manchester",
    "sg:classifiers":[
        {
            "category":"Freight",
            "type":"Transportation"
        }
    ],
    "sg:phone":"+44 161 876 5959",
    "sg:postcode":"M17 1SB",
    "sg:province":"Cheshire",
    "sg:tags":[
        "forwarders"
    ],
    "wof:name":"Freight Base",
    "wof:placetype":"venue"
},
  "geometry": {"coordinates":[-2.333178997,53.476360321],"type":"Point"}
}