{
  "type": "Feature",
  "properties": {
    "addr:full":"3d St Francis Way Shefford Bedfordshire SG17 5DZ",
    "addr:housenumber":"3d",
    "addr:postcode":"sg17 5dz",
    "addr:street":"St Francis Way",
    "iso:country":"GB",
    "sg:address":"3d St Francis Way",
    "sg:city":"Shefford",
    "sg:classifiers":[
        {
            "category":"Shopping",
            "subcategory":"Mobile Phones",
            "type":"Retail Goods"
        }
    ],
    "sg:postcode":"SG17 5DZ",
    "sg:province":"Bedfordshire",
    "wof:name":"Lakerise Services Ltd",
    "wof:placetype":"venue"
},
  "geometry": {"coordinates":[-0.3349109888,52.0370292664],"type":"Point"}
}