{
  "type": "Feature",
  "properties": {
    "iso:country":"GB",
    "sg:address":"Liley Lane, Garage Site",
    "sg:city":"Wakefield",
    "sg:classifiers":[
        {
            "category":"Retail",
            "subcategory":"Auto Repair",
            "type":"Services"
        }
    ],
    "sg:phone":"+44 1924 848568",
    "sg:postcode":"WF4 4EN",
    "sg:province":"West Yorkshire",
    "sg:tags":[
        "body",
        "car"
    ],
    "wof:name":"Taylor Brothers (Body Repairs) Ltd.",
    "wof:placetype":"venue"
},
  "geometry": {"coordinates":[-1.6677340269,53.6384963989],"type":"Point"}
}