{
  "type": "Feature",
  "properties": {
    "addr:full":"Wardens Flat, Delight Court, Dipton Stanley Durham DH9 9XJ",
    "addr:postcode":"dh9 9xj",
    "addr:street":"Stanley",
    "iso:country":"GB",
    "sg:address":"Wardens Flat, Delight Court, Dipton",
    "sg:city":"Stanley",
    "sg:classifiers":[
        {
            "category":"Social Services",
            "subcategory":"Adult Care",
            "type":"Services"
        },
        {
            "category":"Government",
            "subcategory":"Office",
            "type":"Public Place"
        }
    ],
    "sg:phone":"+44 1207 570988",
    "sg:postcode":"DH9 9XJ",
    "sg:province":"Durham",
    "sg:tags":[
        "local",
        "housing",
        "central",
        "sheltered"
    ],
    "wof:name":"Delight Court",
    "wof:placetype":"venue"
},
  "geometry": {"coordinates":[-1.6903380156,54.872379303],"type":"Point"}
}