{
  "type": "Feature",
  "properties": {
    "iso:country":"GB",
    "sg:address":"20 North Bridge Street",
    "sg:city":"Bathgate",
    "sg:classifiers":[
        {
            "category":"Home & Garden",
            "subcategory":"Hardware",
            "type":"Retail Goods"
        }
    ],
    "sg:phone":"+44 1506 653922",
    "sg:postcode":"EH48 4PS",
    "sg:province":"West Lothian",
    "sg:tags":[
        "part",
        "accessory"
    ],
    "wof:name":"Jim Allan Motorcycles Ltd.",
    "wof:placetype":"venue"
},
  "geometry": {"coordinates":[-3.6443378925,55.9022293091],"type":"Point"}
}