{
  "type": "Feature",
  "properties": {
    "iso:country":"GB",
    "sg:address":"Unit 6",
    "sg:city":"Redruth",
    "sg:classifiers":[
        {
            "category":"Shopping",
            "subcategory":"Clothing, Apparel, & Fashions",
            "type":"Retail Goods"
        }
    ],
    "sg:phone":"+44 1209 218868",
    "sg:postcode":"TR15 3SF",
    "sg:province":"Cornwall",
    "sg:tags":[
        "t-shirt"
    ],
    "wof:name":"Screentech Design",
    "wof:placetype":"venue"
},
  "geometry": {"coordinates":[-5.255129,50.232479],"type":"Point"}
}