{
  "type": "Feature",
  "properties": {
    "iso:country":"GB",
    "sg:address":"17 Old Lane, Bramhope",
    "sg:city":"Leeds",
    "sg:classifiers":[
        {
            "category":"Building & Trades",
            "subcategory":"Plumbing",
            "type":"Services"
        }
    ],
    "sg:phone":"+44 113 284 2001",
    "sg:postcode":"LS16 9AY",
    "sg:province":"West Yorkshire",
    "sg:tags":[
        "plumber",
        "heating"
    ],
    "wof:name":"B H P Services Ltd.",
    "wof:placetype":"venue"
},
  "geometry": {"coordinates":[-1.626278,53.885216],"type":"Point"}
}