{
  "type": "Feature",
  "properties": {
    "iso:country":"GB",
    "sg:address":"35 Dimond Street",
    "sg:city":"Pembroke Dock",
    "sg:classifiers":[
        {
            "category":"Banks & Credit Unions",
            "subcategory":"Bank",
            "type":"Services"
        }
    ],
    "sg:phone":"+44 1646 682063",
    "sg:postcode":"SA72 6BX",
    "sg:province":"Pembrokeshire",
    "sg:tags":[
        "financial",
        "institution"
    ],
    "sg:website":"http://www.lloydstsb.com",
    "wof:name":"Lloyds Tsb Bank Plc",
    "wof:placetype":"venue"
},
  "geometry": {"coordinates":[-4.9407281876,51.6938400269],"type":"Point"}
}