{
  "type": "Feature",
  "properties": {
    "addr:full":"1 Hesketh Road Lytham St Annes Lancashire FY8 3DY",
    "addr:housenumber":"1",
    "addr:postcode":"fy8 3dy",
    "addr:street":"Hesketh Road",
    "iso:country":"GB",
    "sg:address":"1 Hesketh Road",
    "sg:city":"Lytham St Annes",
    "sg:classifiers":[
        {
            "category":"Professional",
            "subcategory":"Engineering",
            "type":"Services"
        },
        {
            "category":"Building & Trades",
            "subcategory":"Electrical",
            "type":"Services"
        }
    ],
    "sg:phone":"+44 1253 729793",
    "sg:postcode":"FY8 3DY",
    "sg:province":"Lancashire",
    "sg:tags":[
        "engineer",
        "electrician",
        "contractor"
    ],
    "wof:name":"Jeff Lee",
    "wof:placetype":"venue"
},
  "geometry": {"coordinates":[-3.0134460926,53.7649726868],"type":"Point"}
}