{
  "type": "Feature",
  "properties": {
    "iso:country":"GB",
    "sg:address":"Maypole Road, Tiptree",
    "sg:city":"Colchester",
    "sg:classifiers":[
        {
            "category":"Communications",
            "subcategory":"Newspaper",
            "type":"Services"
        }
    ],
    "sg:postcode":"CO5 0EJ",
    "sg:province":"Essex",
    "sg:tags":[
        "magazine"
    ],
    "wof:name":"Signet Publishing",
    "wof:placetype":"venue"
},
  "geometry": {"coordinates":[0.745334,51.816463],"type":"Point"}
}