{
  "type": "Feature",
  "properties": {
    "addr:full":"1 Russel Villa, Aberfan Merthyr Tydfil Caerphilly CF48 4TJ",
    "addr:housenumber":"1",
    "addr:postcode":"cf48 4tj",
    "addr:street":"Russel Villa Aberfan",
    "iso:country":"GB",
    "sg:address":"1 Russel Villa, Aberfan",
    "sg:city":"Merthyr Tydfil",
    "sg:classifiers":[
        {
            "category":"Building & Trades",
            "subcategory":"Construction",
            "type":"Services"
        }
    ],
    "sg:phone":"+44 1443 692200",
    "sg:postcode":"CF48 4TJ",
    "sg:province":"Caerphilly",
    "sg:tags":[
        "builder"
    ],
    "wof:name":"B  Humphreys Building Construction Ltd.",
    "wof:placetype":"venue"
},
  "geometry": {"coordinates":[-3.3431301117,51.7008895874],"type":"Point"}
}