{
  "type": "Feature",
  "properties": {
    "iso:country":"GB",
    "sg:address":"360 Lordship Lane",
    "sg:city":"London",
    "sg:classifiers":[
        {
            "category":"Shopping",
            "subcategory":"Baby Store",
            "type":"Retail Goods"
        }
    ],
    "sg:phone":"+44 20 8801 0568",
    "sg:postcode":"N17 7QX",
    "sg:province":"Greater London",
    "sg:tags":[
        "equipment",
        "nursery",
        "accessory"
    ],
    "wof:name":"Simply Outgrown",
    "wof:placetype":"venue"
},
  "geometry": {"coordinates":[-0.092124,51.598042],"type":"Point"}
}