{
  "type": "Feature",
  "properties": {
    "iso:country":"GB",
    "sg:address":"Lingfield Way, Yarm Rd Ind Est",
    "sg:city":"Darlington",
    "sg:classifiers":[
        {
            "category":"Manufacturing",
            "subcategory":"Wood Products",
            "type":"Manufacturing & Wholesale Goods"
        }
    ],
    "sg:phone":"+44 1325 487201",
    "sg:postcode":"DL1 4PZ",
    "sg:province":"Durham",
    "sg:tags":[
        "encapsulation",
        "lamination"
    ],
    "wof:name":"Meyer Laminates",
    "wof:placetype":"venue"
},
  "geometry": {"coordinates":[-1.506374,54.526459],"type":"Point"}
}