{
  "type": "Feature",
  "properties": {
    "addr:full":"Unit 1 Bayford Street Industrial Units, Bayford St Hackney Greater London E8 3SE",
    "addr:housenumber":"unit 1;units",
    "addr:postcode":"e8 3se",
    "addr:street":"Bayford Street;St",
    "iso:country":"GB",
    "sg:address":"Unit 1 Bayford Street Industrial Units, Bayford St",
    "sg:city":"Hackney",
    "sg:classifiers":[
        {
            "category":"Retail",
            "subcategory":"Repair Shop",
            "type":"Services"
        }
    ],
    "sg:phone":"+44 20 8533 0915",
    "sg:postcode":"E8 3SE",
    "sg:province":"Greater London",
    "sg:tags":[
        "upholsterer"
    ],
    "wof:name":"The Factory Shop",
    "wof:placetype":"venue"
},
  "geometry": {"coordinates":[-0.057079,51.53968],"type":"Point"}
}