{
  "type": "Feature",
  "properties": {
    "iso:country":"GB",
    "sg:address":"157 Cunningham Drive",
    "sg:city":"Glasgow",
    "sg:classifiers":[
        {
            "category":"Building & Trades",
            "subcategory":"Plumbing",
            "type":"Services"
        }
    ],
    "sg:phone":"+44 141 633 3336",
    "sg:postcode":"G46 6EW",
    "sg:province":"East Renfrewshire",
    "sg:tags":[
        "heating"
    ],
    "wof:name":"R B H Plumbing & Heating",
    "wof:placetype":"venue"
},
  "geometry": {"coordinates":[-4.281332,55.80331],"type":"Point"}
}