{
  "type": "Feature",
  "properties": {
    "addr:full":"Middle Farm Rorrington, Chirbury Montgomery Shropshire SY15 6BX",
    "addr:postcode":"sy15 6bx",
    "addr:street":"Middle;Rorrington;Montgomery",
    "iso:country":"GB",
    "sg:address":"Middle Farm Rorrington, Chirbury",
    "sg:city":"Montgomery",
    "sg:classifiers":[
        {
            "category":"Home & Garden",
            "subcategory":"Garden Supply",
            "type":"Retail Goods"
        },
        {
            "category":"Farming",
            "subcategory":"Farm",
            "type":"Manufacturing & Wholesale Goods"
        }
    ],
    "sg:phone":"+44 1938 561213",
    "sg:postcode":"SY15 6BX",
    "sg:province":"Shropshire",
    "sg:tags":[
        "mixed",
        "bulb",
        "crop",
        "grower"
    ],
    "wof:name":"Robert W A Davies",
    "wof:placetype":"venue"
},
  "geometry": {"coordinates":[-3.1464788914,52.5635643005],"type":"Point"}
}