{
  "type": "Feature",
  "properties": {
    "iso:country":"GB",
    "sg:address":"Holmes Farm, Cotes Road, Barrow On Soar",
    "sg:city":"Loughborough",
    "sg:classifiers":[
        {
            "category":"Farming",
            "subcategory":"Livestock Farm",
            "type":"Manufacturing & Wholesale Goods"
        }
    ],
    "sg:postcode":"LE12 8JR",
    "sg:province":"Leicestershire",
    "sg:tags":[
        "others"
    ],
    "wof:name":"A & J C Kimber",
    "wof:placetype":"venue"
},
  "geometry": {"coordinates":[-1.16153,52.76857],"type":"Point"}
}