{
  "type": "Feature",
  "properties": {
    "iso:country":"GB",
    "sg:address":"367-369 Croydon Road",
    "sg:city":"Wallington",
    "sg:classifiers":[
        {
            "category":"Shopping",
            "subcategory":"News",
            "type":"Retail Goods"
        }
    ],
    "sg:phone":"+44 20 8647 5310",
    "sg:postcode":"SM6 7NY",
    "sg:province":"Surrey",
    "sg:tags":[
        "newsagent"
    ],
    "wof:name":"Steptoes Newsagents",
    "wof:placetype":"venue"
},
  "geometry": {"coordinates":[-0.1522540003,51.3675613403],"type":"Point"}
}