{
  "type": "Feature",
  "properties": {
    "addr:full":"32 Salters Hill, Upper Norwood Upper Norwood Greater London SE19 1DZ",
    "addr:housenumber":"32",
    "addr:postcode":"se19 1dz",
    "addr:street":"Salters Hill",
    "iso:country":"GB",
    "sg:address":"32 Salters Hill, Upper Norwood",
    "sg:city":"Upper Norwood",
    "sg:classifiers":[
        {
            "category":"Professional",
            "subcategory":"Management & Consulting",
            "type":"Services"
        }
    ],
    "sg:phone":"+44 20 8670 9143",
    "sg:postcode":"SE19 1DZ",
    "sg:province":"Greater London",
    "sg:tags":[
        "consultant",
        "business"
    ],
    "wof:name":"Human Resource & Organisational Development C",
    "wof:placetype":"venue"
},
  "geometry": {"coordinates":[-0.093213,51.423603],"type":"Point"}
}