{
  "type": "Feature",
  "properties": {
    "addr:full":"14 The Pingle Rugeley Staffordshire WS15 2UR",
    "addr:housenumber":"14;pingle",
    "addr:postcode":"ws15 2ur",
    "addr:street":"The",
    "iso:country":"GB",
    "sg:address":"14 The Pingle",
    "sg:city":"Rugeley",
    "sg:classifiers":[
        {
            "category":"Personal",
            "subcategory":"Psychics & Astrologers",
            "type":"Services"
        }
    ],
    "sg:phone":"+44 1889 585480",
    "sg:postcode":"WS15 2UR",
    "sg:province":"Staffordshire",
    "sg:tags":[
        "clairvoyant",
        "palmist"
    ],
    "wof:name":"Jane Riley",
    "wof:placetype":"venue"
},
  "geometry": {"coordinates":[-1.961156,52.752789],"type":"Point"}
}