{
  "type": "Feature",
  "properties": {
    "addr:full":"Connemara, Northwaterbridge Laurencekirk Aberdeenshire AB30 1QP",
    "addr:postcode":"ab30 1qp",
    "iso:country":"GB",
    "sg:address":"Connemara, Northwaterbridge",
    "sg:city":"Laurencekirk",
    "sg:classifiers":[
        {
            "category":"Professional",
            "subcategory":"Art Services",
            "type":"Services"
        },
        {
            "category":"Building & Trades",
            "subcategory":"Construction",
            "type":"Services"
        }
    ],
    "sg:phone":"+44 1674 840613",
    "sg:postcode":"AB30 1QP",
    "sg:province":"Aberdeenshire",
    "sg:tags":[
        "decorator",
        "painter"
    ],
    "wof:name":"Eric Greig",
    "wof:placetype":"venue"
},
  "geometry": {"coordinates":[-2.4693739414,56.8306617737],"type":"Point"}
}