{
  "type": "Feature",
  "properties": {
    "addr:full":"Flat 11, The Counting House Paisley Renfrewshire PA1 2NU",
    "addr:housenumber":"flat 11",
    "addr:postcode":"pa1 2nu",
    "addr:street":"The",
    "iso:country":"GB",
    "sg:address":"Flat 11, The Counting House",
    "sg:city":"Paisley",
    "sg:classifiers":[
        {
            "category":"Retail",
            "subcategory":"Driving School",
            "type":"Services"
        }
    ],
    "sg:phone":"+44 141 889 3226",
    "sg:postcode":"PA1 2NU",
    "sg:province":"Renfrewshire",
    "wof:name":"Graham Ogg School of Motoring",
    "wof:placetype":"venue"
},
  "geometry": {"coordinates":[-4.4580798149,55.8405075073],"type":"Point"}
}