{
  "type": "Feature",
  "properties": {
    "iso:country":"GB",
    "sg:address":"Eldene Centre",
    "sg:city":"Swindon",
    "sg:classifiers":[
        {
            "category":"Food & Beverages",
            "subcategory":"Supermarket",
            "type":"Retail Goods"
        }
    ],
    "sg:phone":"+44 1793 522930",
    "sg:postcode":"SN3 3RZ",
    "sg:province":"Wiltshire",
    "wof:name":"Oxford Swindon & Gloucester Co-Operative Society Ltd",
    "wof:placetype":"venue"
},
  "geometry": {"coordinates":[-1.7364120483,51.5553817749],"type":"Point"}
}