{
  "type": "Feature",
  "properties": {
    "addr:full":"392 Kingsland Rd London Greater London E8 4AA",
    "addr:housenumber":"392",
    "addr:postcode":"e8 4aa",
    "addr:street":"Kingsland Rd",
    "iso:country":"GB",
    "sg:address":"392 Kingsland Rd",
    "sg:city":"London",
    "sg:classifiers":[
        {
            "category":"Food & Beverages",
            "subcategory":"Supermarket",
            "type":"Retail Goods"
        }
    ],
    "sg:postcode":"E8 4AA",
    "sg:province":"Greater London",
    "wof:name":"Morgans Food Sava Centre",
    "wof:placetype":"venue"
},
  "geometry": {"coordinates":[-0.0760560036,51.5412902832],"type":"Point"}
}