{
  "type": "Feature",
  "properties": {
    "addr:full":"Llangarthginning Farm, Llanboidy Road Carmarthen Carmarthenshire SA33 5QZ",
    "addr:postcode":"sa33 5qz",
    "addr:street":"Llanboidy Road",
    "iso:country":"GB",
    "sg:address":"Llangarthginning Farm, Llanboidy Road",
    "sg:city":"Carmarthen",
    "sg:classifiers":[
        {
            "category":"Farming",
            "subcategory":"Livestock Farm",
            "type":"Manufacturing & Wholesale Goods"
        }
    ],
    "sg:phone":"+44 1994 230658",
    "sg:postcode":"SA33 5QZ",
    "sg:province":"Carmarthenshire",
    "sg:tags":[
        "others"
    ],
    "wof:name":"B M & A K Jackson",
    "wof:placetype":"venue"
},
  "geometry": {"coordinates":[-4.51909,51.865101],"type":"Point"}
}