{
  "type": "Feature",
  "properties": {
    "addr:full":"26 Elgin Road Lossiemouth Moray IV31 6HE",
    "addr:housenumber":"26",
    "addr:postcode":"iv31 6he",
    "addr:street":"Elgin Road",
    "iso:country":"GB",
    "sg:address":"26 Elgin Road",
    "sg:city":"Lossiemouth",
    "sg:classifiers":[
        {
            "category":"Professional",
            "subcategory":"Accounting & Tax Preparation",
            "type":"Services"
        }
    ],
    "sg:phone":"+44 1343 812785",
    "sg:postcode":"IV31 6HE",
    "sg:province":"Moray",
    "sg:tags":[
        "accountant",
        "bookkeeping",
        "primarily",
        "activity"
    ],
    "wof:name":"Raymond Alexander Sinclair",
    "wof:placetype":"venue"
},
  "geometry": {"coordinates":[-3.2897179127,57.7132377625],"type":"Point"}
}