{
  "type": "Feature",
  "properties": {
    "iso:country":"GB",
    "sg:address":"6 Barretts Gro",
    "sg:city":"London",
    "sg:classifiers":[
        {
            "category":"Health Services",
            "subcategory":"Doctor",
            "type":"Services"
        }
    ],
    "sg:phone":"+44 20 7254 1661",
    "sg:postcode":"N16 8AR",
    "sg:province":"Greater London",
    "sg:tags":[
        "practitioners"
    ],
    "wof:name":"R L Gangola",
    "wof:placetype":"venue"
},
  "geometry": {"coordinates":[-0.078704,51.552139],"type":"Point"}
}