{
  "type": "Feature",
  "properties": {
    "addr:full":"121 St Leonards Road Leicester Leicestershire LE2 3BZ",
    "addr:housenumber":"121",
    "addr:postcode":"le2 3bz",
    "addr:street":"St Leonards Road",
    "iso:country":"GB",
    "sg:address":"121 St Leonards Road",
    "sg:city":"Leicester",
    "sg:classifiers":[
        {
            "category":"Manufacturing",
            "subcategory":"Wood Products",
            "type":"Manufacturing & Wholesale Goods"
        }
    ],
    "sg:phone":"+44 116 270 3560",
    "sg:postcode":"LE2 3BZ",
    "sg:province":"Leicestershire",
    "sg:tags":[
        "packaging",
        "crate",
        "pallets"
    ],
    "wof:name":"A J Packaging & Polythene Ltd.",
    "wof:placetype":"venue"
},
  "geometry": {"coordinates":[-1.1189140081,52.6160545349],"type":"Point"}
}