{
  "type": "Feature",
  "properties": {
    "addr:full":"The Hollies, Stone House Hospital, Cotton La Dartford Kent DA2 6AU",
    "addr:postcode":"da2 6au",
    "addr:street":"Cotton La Dartford",
    "iso:country":"GB",
    "sg:address":"The Hollies, Stone House Hospital, Cotton La",
    "sg:city":"Dartford",
    "sg:classifiers":[
        {
            "category":"Health Services",
            "subcategory":"Clinic",
            "type":"Services"
        }
    ],
    "sg:phone":"+44 1322 622099",
    "sg:postcode":"DA2 6AU",
    "sg:province":"Kent",
    "sg:tags":[
        "abuse",
        "drug"
    ],
    "wof:name":"Drug & Alcohol Counselling Services",
    "wof:placetype":"venue"
},
  "geometry": {"coordinates":[0.2453500032,51.4447288513],"type":"Point"}
}