{
  "type": "Feature",
  "properties": {
    "iso:country":"GB",
    "sg:address":"City Walls Medical Centre, St. Martins Way",
    "sg:city":"Chester",
    "sg:classifiers":[
        {
            "category":"Shopping",
            "subcategory":"Pharmacy",
            "type":"Retail Goods"
        }
    ],
    "sg:phone":"+44 1244 347229",
    "sg:postcode":"CH1 2NR",
    "sg:province":"Cheshire",
    "sg:tags":[
        "pharmacist",
        "chemist"
    ],
    "wof:name":"Moss Chemists",
    "wof:placetype":"venue"
},
  "geometry": {"coordinates":[-2.897589,53.189945],"type":"Point"}
}