{
  "type": "Feature",
  "properties": {
    "addr:full":"13 Holmeside Sunderland Tyne and Wear SR1 3JF",
    "addr:housenumber":"13",
    "addr:postcode":"sr1 3jf",
    "addr:street":"Holmeside Sunderland",
    "iso:country":"GB",
    "sg:address":"13 Holmeside",
    "sg:city":"Sunderland",
    "sg:classifiers":[
        {
            "category":"Deli",
            "type":"Food & Drink"
        }
    ],
    "sg:phone":"+44 191 510 2951",
    "sg:postcode":"SR1 3JF",
    "sg:province":"Tyne and Wear",
    "sg:tags":[
        "delicatessen"
    ],
    "wof:name":"B J's",
    "wof:placetype":"venue"
},
  "geometry": {"coordinates":[-1.385647,54.904343],"type":"Point"}
}