{
  "type": "Feature",
  "properties": {
    "addr:full":"3 Victoria Road Rushden Bedfordshire NN10 0AH",
    "addr:housenumber":"3",
    "addr:postcode":"nn10 0ah",
    "addr:street":"Victoria Road",
    "iso:country":"GB",
    "sg:address":"3 Victoria Road",
    "sg:city":"Rushden",
    "sg:classifiers":[
        {
            "category":"Professional",
            "subcategory":"Employment Agencies",
            "type":"Services"
        }
    ],
    "sg:phone":"+44 1933 413413",
    "sg:postcode":"NN10 0AH",
    "sg:province":"Bedfordshire",
    "sg:tags":[
        "consultant"
    ],
    "wof:name":"Recruitment Direct Services Ltd.",
    "wof:placetype":"venue"
},
  "geometry": {"coordinates":[-0.5986899734,52.2929573059],"type":"Point"}
}