{
  "type": "Feature",
  "properties": {
    "addr:full":"11 Princes Street London Greater London W1B 2LJ",
    "addr:housenumber":"11",
    "addr:postcode":"w1b 2lj",
    "addr:street":"Princes Street",
    "iso:country":"GB",
    "sg:address":"11 Princes Street",
    "sg:city":"London",
    "sg:classifiers":[
        {
            "category":"Real Estate",
            "subcategory":"Architect",
            "type":"Services"
        }
    ],
    "sg:phone":"+44 20 7629 0203",
    "sg:postcode":"W1B 2LJ",
    "sg:province":"Greater London",
    "wof:name":"Grant Littler Studios",
    "wof:placetype":"venue"
},
  "geometry": {"coordinates":[-0.1436280012,51.5143241882],"type":"Point"}
}