{
  "type": "Feature",
  "properties": {
    "addr:full":"Gilmore Works, Bavelaw Road Balerno City of Edinburgh EH14 7AE",
    "addr:postcode":"eh14 7ae",
    "addr:street":"Bavelaw Road",
    "iso:country":"GB",
    "sg:address":"Gilmore Works, Bavelaw Road",
    "sg:city":"Balerno",
    "sg:classifiers":[
        {
            "category":"Building & Trades",
            "subcategory":"Construction",
            "type":"Services"
        }
    ],
    "sg:postcode":"EH14 7AE",
    "sg:province":"City of Edinburgh",
    "sg:tags":[
        "dry",
        "lining",
        "plasterers",
        "screeders"
    ],
    "wof:name":"David Fisher & Sons (Edinburgh) Ltd.",
    "wof:placetype":"venue"
},
  "geometry": {"coordinates":[-3.343444109,55.8885040283],"type":"Point"}
}