{
  "type": "Feature",
  "properties": {
    "addr:full":"17 Elmfield Rd Southall Greater London UB2 5AJ",
    "addr:housenumber":"17",
    "addr:postcode":"ub2 5aj",
    "addr:street":"Elmfield Rd",
    "iso:country":"GB",
    "sg:address":"17 Elmfield Rd",
    "sg:city":"Southall",
    "sg:classifiers":[
        {
            "category":"Place Of Worship",
            "type":"Public Place"
        }
    ],
    "sg:phone":"+44 20 8813 8429",
    "sg:postcode":"UB2 5AJ",
    "sg:province":"Greater London",
    "wof:name":"Hindu Temple Trust The",
    "wof:placetype":"venue"
},
  "geometry": {"coordinates":[-0.3831009865,51.5016098022],"type":"Point"}
}