{
  "type": "Feature",
  "properties": {
    "addr:full":"Eddington Road, St Helens Ryde Isle of Wight PO33 1YA",
    "addr:postcode":"po33 1ya",
    "addr:street":"Eddington Road",
    "iso:country":"GB",
    "sg:address":"Eddington Road, St Helens",
    "sg:city":"Ryde",
    "sg:classifiers":[
        {
            "category":"Recreation",
            "subcategory":"Campground",
            "type":"Entertainment"
        }
    ],
    "sg:phone":"+44 1983 872401",
    "sg:postcode":"PO33 1YA",
    "sg:province":"Isle of Wight",
    "sg:tags":[
        "holiday",
        "camp",
        "park",
        "centre"
    ],
    "wof:name":"Nodes Point Holiday Park",
    "wof:placetype":"venue"
},
  "geometry": {"coordinates":[-1.1025300026,50.7045402527],"type":"Point"}
}