{
  "type": "Feature",
  "properties": {
    "iso:country":"GB",
    "sg:address":"South Deeside Road",
    "sg:city":"Aberdeen",
    "sg:classifiers":[
        {
            "category":"Retail",
            "subcategory":"Event Space",
            "type":"Services"
        }
    ],
    "sg:phone":"+44 1224 732124",
    "sg:postcode":"AB12 5GB",
    "sg:province":"Aberdeen City",
    "sg:tags":[
        "function",
        "room"
    ],
    "wof:name":"Maryculter House Hotel Ltd.",
    "wof:placetype":"venue"
},
  "geometry": {"coordinates":[-2.143509,57.126701],"type":"Point"}
}