{
  "type": "Feature",
  "properties": {
    "addr:full":"B T C House, 9 Millington Road Hayes Greater London UB3 4AZ",
    "addr:housenumber":"9",
    "addr:postcode":"ub3 4az",
    "addr:street":"Millington Road",
    "iso:country":"GB",
    "sg:address":"B T C House, 9 Millington Road",
    "sg:city":"Hayes",
    "sg:classifiers":[
        {
            "category":"Shopping",
            "subcategory":"Stationery & Office Supplies",
            "type":"Retail Goods"
        },
        {
            "category":"Professional",
            "subcategory":"Printing & Photocopies",
            "type":"Services"
        }
    ],
    "sg:postcode":"UB3 4AZ",
    "sg:province":"Greater London",
    "sg:tags":[
        "process",
        "item",
        "screen",
        "printer",
        "promotional"
    ],
    "wof:name":"B T C Group",
    "wof:placetype":"venue"
},
  "geometry": {"coordinates":[-0.4283440113,51.5026245117],"type":"Point"}
}