{
  "type": "Feature",
  "properties": {
    "addr:full":"Abbey Walk St Andrews Fife KY16 9LB",
    "addr:postcode":"ky16 9lb",
    "addr:street":"Abbey Walk",
    "iso:country":"GB",
    "sg:address":"Abbey Walk",
    "sg:city":"St Andrews",
    "sg:classifiers":[
        {
            "category":"Community Center",
            "type":"Public Place"
        }
    ],
    "sg:phone":"+44 1334 474140",
    "sg:postcode":"KY16 9LB",
    "sg:province":"Fife",
    "sg:tags":[
        "centre"
    ],
    "wof:name":"Cosmos Community Centre",
    "wof:placetype":"venue"
},
  "geometry": {"coordinates":[-2.7857310772,56.3369216919],"type":"Point"}
}