{
  "type": "Feature",
  "properties": {
    "addr:full":"69 Harborne Ct, Harborne Rd Birmingham West Midlands B15 3BU",
    "addr:housenumber":"69",
    "addr:postcode":"b15 3bu",
    "addr:street":"Harborne Ct Harborne Rd",
    "iso:country":"GB",
    "sg:address":"69 Harborne Ct, Harborne Rd",
    "sg:city":"Birmingham",
    "sg:classifiers":[
        {
            "category":"Organizations",
            "subcategory":"Professional Association",
            "type":"Services"
        }
    ],
    "sg:phone":"+44 121 454 6475",
    "sg:postcode":"B15 3BU",
    "sg:province":"West Midlands",
    "sg:tags":[
        "union",
        "trade"
    ],
    "wof:name":"Royal College of Nursing of the United K",
    "wof:placetype":"venue"
},
  "geometry": {"coordinates":[-1.923368,52.470928],"type":"Point"}
}