{
  "type": "Feature",
  "properties": {
    "iso:country":"GB",
    "sg:address":"46 Botanic Road",
    "sg:city":"Southport",
    "sg:classifiers":[
        {
            "category":"Personal",
            "subcategory":"Barber",
            "type":"Services"
        }
    ],
    "sg:phone":"+44 1704 214270",
    "sg:postcode":"PR9 7NE",
    "sg:province":"Lancashire",
    "sg:tags":[
        "men's",
        "hairdresser"
    ],
    "wof:name":"Brian Gilder Barber Shop",
    "wof:placetype":"venue"
},
  "geometry": {"coordinates":[-2.9641170502,53.6587982178],"type":"Point"}
}