{
  "type": "Feature",
  "properties": {
    "addr:full":"30 Lyon Street Bognor Regis West Sussex PO21 1DA",
    "addr:housenumber":"30",
    "addr:postcode":"po21 1da",
    "addr:street":"Lyon Street",
    "iso:country":"GB",
    "sg:address":"30 Lyon Street",
    "sg:city":"Bognor Regis",
    "sg:classifiers":[
        {
            "category":"Retail",
            "subcategory":"Repair Shop",
            "type":"Services"
        }
    ],
    "sg:phone":"+44 1243 864585",
    "sg:postcode":"PO21 1DA",
    "sg:province":"West Sussex",
    "sg:tags":[
        "machine",
        "appliance",
        "electrical",
        "washing"
    ],
    "wof:name":"P M S Of Bognor",
    "wof:placetype":"venue"
},
  "geometry": {"coordinates":[-0.672042,50.785534],"type":"Point"}
}