{
  "type": "Feature",
  "properties": {
    "addr:full":"13 Beechcroft Chislehurst Kent BR7 5DB",
    "addr:housenumber":"13",
    "addr:postcode":"br7 5db",
    "addr:street":"Beechcroft",
    "iso:country":"GB",
    "sg:address":"13 Beechcroft",
    "sg:city":"Chislehurst",
    "sg:classifiers":[
        {
            "category":"Shopping",
            "subcategory":"Books",
            "type":"Retail Goods"
        }
    ],
    "sg:phone":"+44 20 8295 1781",
    "sg:postcode":"BR7 5DB",
    "sg:province":"Kent",
    "sg:tags":[
        "maps",
        "globe",
        "chart"
    ],
    "wof:name":"Venture Graphics",
    "wof:placetype":"venue"
},
  "geometry": {"coordinates":[0.0592929982,51.4152336121],"type":"Point"}
}