{
  "type": "Feature",
  "properties": {
    "addr:full":"4 Albert Quay Aberdeen Aberdeen City AB11 5QA",
    "addr:housenumber":"4",
    "addr:postcode":"ab11 5qa",
    "addr:street":"Albert Quay",
    "iso:country":"GB",
    "sg:address":"4 Albert Quay",
    "sg:city":"Aberdeen",
    "sg:classifiers":[
        {
            "category":"Professional",
            "type":"Services"
        }
    ],
    "sg:phone":"+44 1224 587001",
    "sg:postcode":"AB11 5QA",
    "sg:province":"Aberdeen City",
    "sg:tags":[
        "marine"
    ],
    "wof:name":"Salvus Bain (Management) Ltd.",
    "wof:placetype":"venue"
},
  "geometry": {"coordinates":[-2.088381052,57.1421508789],"type":"Point"}
}