{
  "type": "Feature",
  "properties": {
    "iso:country":"GB",
    "sg:address":"19 Abbey Road",
    "sg:city":"Malvern",
    "sg:classifiers":[
        {
            "category":"Professional",
            "subcategory":"Printing & Photocopies",
            "type":"Services"
        }
    ],
    "sg:phone":"+44 1684 563738",
    "sg:postcode":"WR14 3ES",
    "sg:province":"Herefordshire",
    "sg:tags":[
        "printer"
    ],
    "wof:name":"Elmbury Developments Ltd.",
    "wof:placetype":"venue"
},
  "geometry": {"coordinates":[-2.3291919231,52.1102142334],"type":"Point"}
}