{
  "type": "Feature",
  "properties": {
    "addr:full":"75 Raddlebarn Road Birmingham West Midlands B29 7DA",
    "addr:housenumber":"75",
    "addr:postcode":"b29 7da",
    "addr:street":"Raddlebarn Road",
    "iso:country":"GB",
    "sg:address":"75 Raddlebarn Road",
    "sg:city":"Birmingham",
    "sg:classifiers":[
        {
            "category":"Food & Beverages",
            "subcategory":"Liquor & Beverages",
            "type":"Retail Goods"
        }
    ],
    "sg:phone":"+44 121 415 4019",
    "sg:postcode":"B29 7DA",
    "sg:province":"West Midlands",
    "sg:tags":[
        "beer",
        "spirit",
        "wines"
    ],
    "wof:name":"Victoria Wine",
    "wof:placetype":"venue"
},
  "geometry": {"coordinates":[-1.926554,52.439499],"type":"Point"}
}