{
  "type": "Feature",
  "properties": {
    "addr:full":"53 High Street Rochester Kent ME1 1LN",
    "addr:housenumber":"53",
    "addr:postcode":"me1 1ln",
    "addr:street":"High Street",
    "iso:country":"GB",
    "sg:address":"53 High Street",
    "sg:city":"Rochester",
    "sg:classifiers":[
        {
            "category":"Shopping",
            "subcategory":"Discount & Variety Stores",
            "type":"Retail Goods"
        }
    ],
    "sg:phone":"+44 1634 827992",
    "sg:postcode":"ME1 1LN",
    "sg:province":"Kent",
    "sg:tags":[
        "shop",
        "model"
    ],
    "wof:name":"Rons Model Rail & Diecast",
    "wof:placetype":"venue"
},
  "geometry": {"coordinates":[0.5036929846,51.3900680542],"type":"Point"}
}