{
  "type": "Feature",
  "properties": {
    "addr:full":"157 Mare Street London Greater London E8 3RH",
    "addr:housenumber":"157",
    "addr:postcode":"e8 3rh",
    "addr:street":"Mare Street",
    "iso:country":"GB",
    "sg:address":"157 Mare Street",
    "sg:city":"London",
    "sg:classifiers":[
        {
            "category":"Health Services",
            "subcategory":"Dentist",
            "type":"Services"
        }
    ],
    "sg:phone":"+44 20 8985 1622",
    "sg:postcode":"E8 3RH",
    "sg:province":"Greater London",
    "wof:name":"The Triangle Dental Practice",
    "wof:placetype":"venue"
},
  "geometry": {"coordinates":[-0.056403,51.539494],"type":"Point"}
}