{
  "type": "Feature",
  "properties": {
    "addr:full":"38 Oxford Street Mountain Ash Rhondda, Cynon, Taff CF45 3HB",
    "addr:housenumber":"38",
    "addr:postcode":"cf45 3hb",
    "addr:street":"Oxford Street;Cynon Taff",
    "iso:country":"GB",
    "sg:address":"38 Oxford Street",
    "sg:city":"Mountain Ash",
    "sg:classifiers":[
        {
            "category":"Shopping",
            "subcategory":"Clothing, Apparel, & Fashions",
            "type":"Retail Goods"
        }
    ],
    "sg:phone":"+44 1443 473846",
    "sg:postcode":"CF45 3HB",
    "sg:province":"Rhondda, Cynon, Taff",
    "sg:tags":[
        "shop"
    ],
    "wof:name":"Boys R Us",
    "wof:placetype":"venue"
},
  "geometry": {"coordinates":[-3.378647089,51.6817398071],"type":"Point"}
}