{
  "type": "Feature",
  "properties": {
    "iso:country":"GB",
    "sg:address":"Fitz Park House, 31 Station Street",
    "sg:city":"Keswick",
    "sg:classifiers":[
        {
            "category":"Health Services",
            "subcategory":"Dentist",
            "type":"Services"
        }
    ],
    "sg:phone":"+44 17687 73020",
    "sg:postcode":"CA12 5HH",
    "sg:province":"Cumbria",
    "wof:name":"PETER D NELSON",
    "wof:placetype":"venue"
},
  "geometry": {"coordinates":[-3.1348850727,54.6011657715],"type":"Point"}
}