{
  "type": "Feature",
  "properties": {
    "addr:full":"34 Bramley Road Tewkesbury Gloucestershire GL20 8AQ",
    "addr:housenumber":"34",
    "addr:postcode":"gl20 8aq",
    "addr:street":"Bramley Road",
    "iso:country":"GB",
    "sg:address":"34 Bramley Road",
    "sg:city":"Tewkesbury",
    "sg:classifiers":[
        {
            "category":"Building & Trades",
            "subcategory":"Construction",
            "type":"Services"
        }
    ],
    "sg:phone":"+44 1684 292639",
    "sg:postcode":"GL20 8AQ",
    "sg:province":"Gloucestershire",
    "sg:tags":[
        "decorator",
        "painter"
    ],
    "wof:name":"Peter Hancox",
    "wof:placetype":"venue"
},
  "geometry": {"coordinates":[-2.1483149529,52.0000801086],"type":"Point"}
}