{
  "type": "Feature",
  "properties": {
    "addr:full":"77 Pevensey Way, Frimley Camberley Hampshire GU16 9UU",
    "addr:housenumber":"77",
    "addr:postcode":"gu16 9uu",
    "addr:street":"Pevensey Way",
    "iso:country":"GB",
    "sg:address":"77 Pevensey Way, Frimley",
    "sg:city":"Camberley",
    "sg:classifiers":[
        {
            "category":"Communications",
            "type":"Services"
        }
    ],
    "sg:postcode":"GU16 9UU",
    "sg:province":"Hampshire",
    "sg:tags":[
        "audio-visual"
    ],
    "wof:name":"Gordon Video Services",
    "wof:placetype":"venue"
},
  "geometry": {"coordinates":[-0.722498,51.309002],"type":"Point"}
}