{
  "type": "Feature",
  "properties": {
    "addr:full":"19 Lavendon Ho, Paveley St, Marleybone London Greater London NW8 8TJ",
    "addr:housenumber":"19",
    "addr:postcode":"nw8 8tj",
    "addr:street":"Lavendon Ho Paveley St Marleybone",
    "iso:country":"GB",
    "sg:address":"19 Lavendon Ho, Paveley St, Marleybone",
    "sg:city":"London",
    "sg:classifiers":[
        {
            "category":"Building & Trades",
            "subcategory":"Cleaning & Sanitation",
            "type":"Services"
        }
    ],
    "sg:postcode":"NW8 8TJ",
    "sg:province":"Greater London",
    "sg:tags":[
        "commercial"
    ],
    "wof:name":"Ofili,Henry,",
    "wof:placetype":"venue"
},
  "geometry": {"coordinates":[-0.1657180041,51.5258178711],"type":"Point"}
}