{
  "type": "Feature",
  "properties": {
    "addr:full":"24 Bothlyn Avenue, Kirkintilloch Glasgow East Dunbartonshire G66 3DX",
    "addr:housenumber":"24",
    "addr:postcode":"g66 3dx",
    "addr:street":"Bothlyn Avenue",
    "iso:country":"GB",
    "sg:address":"24 Bothlyn Avenue, Kirkintilloch",
    "sg:city":"Glasgow",
    "sg:classifiers":[
        {
            "category":"Home & Garden",
            "subcategory":"Building Materials",
            "type":"Retail Goods"
        }
    ],
    "sg:postcode":"G66 3DX",
    "sg:province":"East Dunbartonshire",
    "sg:tags":[
        "fencing"
    ],
    "wof:name":"Aspen Timber Fencing Services",
    "wof:placetype":"venue"
},
  "geometry": {"coordinates":[-4.1436347961,55.9327049255],"type":"Point"}
}