{
  "type": "Feature",
  "properties": {
    "addr:full":"134 Tolmers Road, Cufley Potters Bar Greater London EN6 4JR",
    "addr:housenumber":"134",
    "addr:postcode":"en6 4jr",
    "addr:street":"Tolmers Road Cufley",
    "iso:country":"GB",
    "sg:address":"134 Tolmers Road, Cufley",
    "sg:city":"Potters Bar",
    "sg:classifiers":[
        {
            "category":"Military Area",
            "subcategory":"Air Force Base",
            "type":"Public Place"
        }
    ],
    "sg:phone":"+44 1707 870891",
    "sg:postcode":"EN6 4JR",
    "sg:province":"Greater London",
    "sg:tags":[
        "water",
        "treatment"
    ],
    "wof:name":"Flo-Logix Ltd.",
    "wof:placetype":"venue"
},
  "geometry": {"coordinates":[-0.115468,51.71566],"type":"Point"}
}