{
  "type": "Feature",
  "properties": {
    "addr:full":"559 Fishponds Rd Bristol City of Bristol BS16 3AF",
    "addr:housenumber":"559",
    "addr:postcode":"bs16 3af",
    "addr:street":"Fishponds Rd",
    "iso:country":"GB",
    "sg:address":"559 Fishponds Rd",
    "sg:city":"Bristol",
    "sg:classifiers":[
        {
            "category":"Professional",
            "subcategory":"Computer Services",
            "type":"Services"
        }
    ],
    "sg:phone":"+44 117 958 4433",
    "sg:postcode":"BS16 3AF",
    "sg:province":"City of Bristol",
    "sg:tags":[
        "system",
        "software"
    ],
    "wof:name":"Bristol Office Computer Services (BOCS)",
    "wof:placetype":"venue"
},
  "geometry": {"coordinates":[-2.530364,51.477516],"type":"Point"}
}