{
  "type": "Feature",
  "properties": {
    "addr:full":"111 The Street, Fetcham Leatherhead Surrey KT22 9RD",
    "addr:housenumber":"111",
    "addr:postcode":"kt22 9rd",
    "addr:street":"The Street",
    "iso:country":"GB",
    "sg:address":"111 The Street, Fetcham",
    "sg:city":"Leatherhead",
    "sg:classifiers":[
        {
            "category":"Farming",
            "subcategory":"Livestock Farm",
            "type":"Manufacturing & Wholesale Goods"
        },
        {
            "category":"Shopping",
            "subcategory":"Florist",
            "type":"Retail Goods"
        }
    ],
    "sg:phone":"+44 1372 374385",
    "sg:postcode":"KT22 9RD",
    "sg:province":"Surrey",
    "sg:tags":[
        "breeder"
    ],
    "wof:name":"Flower Craft",
    "wof:placetype":"venue"
},
  "geometry": {"coordinates":[-0.3568409979,51.2967796326],"type":"Point"}
}