{
  "type": "Feature",
  "properties": {
    "iso:country":"GB",
    "sg:address":"Seagate Works, Seagate Road, Long Sutton",
    "sg:city":"Spalding",
    "sg:classifiers":[
        {
            "category":"Manufacturing",
            "subcategory":"Building Materials",
            "type":"Manufacturing & Wholesale Goods"
        }
    ],
    "sg:phone":"+44 1406 362262",
    "sg:postcode":"PE12 9AD",
    "sg:province":"Cambridgeshire",
    "sg:tags":[
        "concrete",
        "product"
    ],
    "wof:name":"C Warrick & Son (Concrete) Ltd.",
    "wof:placetype":"venue"
},
  "geometry": {"coordinates":[0.1225780025,52.7852554321],"type":"Point"}
}