{
  "type": "Feature",
  "properties": {
    "iso:country":"GB",
    "sg:address":"41 Church Road, Bookham",
    "sg:city":"Leatherhead",
    "sg:classifiers":[
        {
            "category":"Restaurant",
            "type":"Food & Drink"
        }
    ],
    "sg:phone":"+44 1372 459136",
    "sg:postcode":"KT23 3PG",
    "sg:province":"Surrey",
    "sg:tags":[
        "indian",
        "-"
    ],
    "wof:name":"Great Bookham Tandoori",
    "wof:placetype":"venue"
},
  "geometry": {"coordinates":[-0.375867,51.28001],"type":"Point"}
}