{
  "type": "Feature",
  "properties": {
    "iso:country":"GB",
    "sg:address":"Cannards Farm",
    "sg:city":"Shepton Mallet",
    "sg:classifiers":[
        {
            "category":"Shopping",
            "subcategory":"Party Supplies",
            "type":"Retail Goods"
        }
    ],
    "sg:postcode":"BA4 4LY",
    "sg:province":"Somerset",
    "sg:tags":[
        "marquees",
        "floor",
        "tent"
    ],
    "wof:name":"Albion Woods Tents",
    "wof:placetype":"venue"
},
  "geometry": {"coordinates":[-2.536038,51.177185],"type":"Point"}
}