{
  "type": "Feature",
  "properties": {
    "iso:country":"GB",
    "sg:address":"1763-1765 London Rd",
    "sg:city":"Leigh On Sea",
    "sg:classifiers":[
        {
            "category":"Autos & Motor Vehicles",
            "subcategory":"Automobile Sales",
            "type":"Retail Goods"
        }
    ],
    "sg:phone":"+44 1702 480325",
    "sg:postcode":"SS9 2ST",
    "sg:province":"Essex",
    "sg:tags":[
        "car"
    ],
    "wof:name":"Orchard Motor Co Ltd",
    "wof:placetype":"venue"
},
  "geometry": {"coordinates":[0.630554,51.548534],"type":"Point"}
}