{
  "type": "Feature",
  "properties": {
    "addr:full":"1a Snow Hill Ct Clerkenwell Greater London EC1A 2EJ",
    "addr:housenumber":"1a",
    "addr:postcode":"ec1a 2ej",
    "addr:street":"Snow Hill Ct",
    "iso:country":"GB",
    "sg:address":"1a Snow Hill Ct",
    "sg:city":"Clerkenwell",
    "sg:classifiers":[
        {
            "category":"Health Services",
            "subcategory":"Doctor",
            "type":"Services"
        }
    ],
    "sg:phone":"+44 20 7236 2832",
    "sg:postcode":"EC1A 2EJ",
    "sg:province":"Greater London",
    "sg:tags":[
        "practitioners"
    ],
    "wof:name":"Harris-Jones, R D L",
    "wof:placetype":"venue"
},
  "geometry": {"coordinates":[-0.1026299968,51.5168190002],"type":"Point"}
}