{
  "type": "Feature",
  "properties": {
    "addr:full":"Area 3, Marzell Ho, 122 North End Rd West Kensington Greater London W14 9PP",
    "addr:housenumber":"122",
    "addr:postcode":"w14 9pp",
    "addr:street":"Marzell;North End Rd",
    "iso:country":"GB",
    "sg:address":"Area 3, Marzell Ho, 122 North End Rd",
    "sg:city":"West Kensington",
    "sg:classifiers":[
        {
            "category":"Social Services",
            "type":"Services"
        }
    ],
    "sg:phone":"+44 20 7385 7971",
    "sg:postcode":"W14 9PP",
    "sg:province":"Greater London",
    "wof:name":"Social Services",
    "wof:placetype":"venue"
},
  "geometry": {"coordinates":[-0.20517,51.488659],"type":"Point"}
}