{
  "type": "Feature",
  "properties": {
    "iso:country":"GB",
    "sg:address":"30 Luther Clo",
    "sg:city":"Edgware",
    "sg:classifiers":[
        {
            "category":"Shopping",
            "subcategory":"Computers & Home Electronics",
            "type":"Retail Goods"
        }
    ],
    "sg:phone":"+44 20 8905 3883",
    "sg:postcode":"HA8 8YY",
    "sg:province":"Greater London",
    "wof:name":"Kitstop U K Ltd",
    "wof:placetype":"venue"
},
  "geometry": {"coordinates":[-0.26545,51.628105],"type":"Point"}
}