{
  "type": "Feature",
  "properties": {
    "addr:full":"Highways Office, Fenn Rd Halstead Essex CO9 2HG",
    "addr:postcode":"co9 2hg",
    "addr:street":"Fenn Rd",
    "iso:country":"GB",
    "sg:address":"Highways Office, Fenn Rd",
    "sg:city":"Halstead",
    "sg:classifiers":[
        {
            "category":"Professional",
            "subcategory":"Engineering",
            "type":"Services"
        }
    ],
    "sg:phone":"+44 1787 474202",
    "sg:postcode":"CO9 2HG",
    "sg:province":"Essex",
    "sg:tags":[
        "consulting",
        "engineer"
    ],
    "wof:name":"Atkins W S Essex Transportation",
    "wof:placetype":"venue"
},
  "geometry": {"coordinates":[0.6358249784,51.9439964294],"type":"Point"}
}