{
  "type": "Feature",
  "properties": {
    "addr:full":"12 Pear Tree Road Ashford Greater London TW15 1PW",
    "addr:housenumber":"12",
    "addr:postcode":"tw15 1pw",
    "addr:street":"Pear Tree Road",
    "iso:country":"GB",
    "sg:address":"12 Pear Tree Road",
    "sg:city":"Ashford",
    "sg:classifiers":[
        {
            "category":"Professional",
            "subcategory":"Business Services",
            "type":"Services"
        }
    ],
    "sg:phone":"+44 1784 243430",
    "sg:postcode":"TW15 1PW",
    "sg:province":"Greater London",
    "sg:tags":[
        "shop",
        "cleaning"
    ],
    "wof:name":"Crystal Cleaning Services",
    "wof:placetype":"venue"
},
  "geometry": {"coordinates":[-0.4409160018,51.4293479919],"type":"Point"}
}