{
  "type": "Feature",
  "properties": {
    "addr:full":"49-51 Windmill Hill Enfield Greater London EN2 7AE",
    "addr:housenumber":"49-51",
    "addr:postcode":"en2 7ae",
    "addr:street":"Windmill Hill",
    "iso:country":"GB",
    "sg:address":"49-51 Windmill Hill",
    "sg:city":"Enfield",
    "sg:classifiers":[
        {
            "category":"Real Estate",
            "subcategory":"Surveying",
            "type":"Services"
        },
        {
            "category":"Real Estate",
            "subcategory":"Real Estate Agent",
            "type":"Services"
        }
    ],
    "sg:phone":"+44 20 8367 4060",
    "sg:postcode":"EN2 7AE",
    "sg:province":"Greater London",
    "sg:tags":[
        "surveyor",
        "valuer"
    ],
    "wof:name":"Ian Gibbs & Robin Davies",
    "wof:placetype":"venue"
},
  "geometry": {"coordinates":[-0.092008,51.653488],"type":"Point"}
}