{
  "type": "Feature",
  "properties": {
    "iso:country":"GB",
    "sg:address":"123 Victoria Road",
    "sg:city":"Middlesbrough",
    "sg:classifiers":[
        {
            "category":"Shopping",
            "type":"Retail Goods"
        }
    ],
    "sg:phone":"+44 1642 242441",
    "sg:postcode":"TS1 3HX",
    "sg:province":"North Yorkshire",
    "sg:tags":[
        "part",
        "accessory"
    ],
    "wof:name":"Al-Makkah",
    "wof:placetype":"venue"
},
  "geometry": {"coordinates":[-1.23048,54.569172],"type":"Point"}
}