{
  "type": "Feature",
  "properties": {
    "addr:full":"13 Victoria St Nottingham Nottinghamshire NG1 2EW",
    "addr:housenumber":"13",
    "addr:postcode":"ng1 2ew",
    "addr:street":"Victoria St",
    "iso:country":"GB",
    "sg:address":"13 Victoria St",
    "sg:city":"Nottingham",
    "sg:classifiers":[
        {
            "category":"Professional",
            "subcategory":"Computer Services",
            "type":"Services"
        }
    ],
    "sg:postcode":"NG1 2EW",
    "sg:province":"Nottinghamshire",
    "sg:tags":[
        "system",
        "software"
    ],
    "wof:name":"J B S Computer Services",
    "wof:placetype":"venue"
},
  "geometry": {"coordinates":[-1.146298,52.953411],"type":"Point"}
}