{
  "type": "Feature",
  "properties": {
    "iso:country":"GB",
    "sg:address":"Mary Jones House, 24 Tower Road",
    "sg:city":"Orpington",
    "sg:classifiers":[
        {
            "category":"Organizations",
            "subcategory":"Community Association",
            "type":"Services"
        }
    ],
    "sg:phone":"+44 1689 830470",
    "sg:postcode":"BR6 0SQ",
    "sg:province":"Kent",
    "sg:tags":[
        "society",
        "housing"
    ],
    "wof:name":"Abbeyfield Orpington Society",
    "wof:placetype":"venue"
},
  "geometry": {"coordinates":[0.0942059979,51.3691215515],"type":"Point"}
}