{
  "type": "Feature",
  "properties": {
    "addr:full":"Main St Wantage Berkshire OX12 8BU",
    "addr:postcode":"ox12 8bu",
    "addr:street":"Main St",
    "iso:country":"GB",
    "sg:address":"Main St",
    "sg:city":"Wantage",
    "sg:classifiers":[
        {
            "category":"Place Of Worship",
            "type":"Public Place"
        }
    ],
    "sg:phone":"+44 1235 763321",
    "sg:postcode":"OX12 8BU",
    "sg:province":"Berkshire",
    "wof:name":"Grove Methodist Church",
    "wof:placetype":"venue"
},
  "geometry": {"coordinates":[-1.4518729448,51.65026474],"type":"Point"}
}