{
  "type": "Feature",
  "properties": {
    "iso:country":"GB",
    "sg:address":"Kestrel Way, Thornhill",
    "sg:city":"Cardiff",
    "sg:classifiers":[
        {
            "category":"Building & Trades",
            "subcategory":"Construction",
            "type":"Services"
        }
    ],
    "sg:phone":"+44 29 2076 3268",
    "sg:postcode":"CF14 9DF",
    "sg:province":"Cardiff",
    "sg:tags":[
        "builder"
    ],
    "wof:name":"Persimmon Homes",
    "wof:placetype":"venue"
},
  "geometry": {"coordinates":[-3.1925389767,51.5380859375],"type":"Point"}
}