{
  "type": "Feature",
  "properties": {
    "iso:country":"GB",
    "sg:address":"25-26 St Helens Road",
    "sg:city":"Swansea",
    "sg:classifiers":[
        {
            "category":"Home & Garden",
            "subcategory":"Household Appliances",
            "type":"Retail Goods"
        }
    ],
    "sg:postcode":"SA1 4AP",
    "sg:province":"Neath Port Talbot",
    "sg:tags":[
        "electrical"
    ],
    "wof:name":"Telefix",
    "wof:placetype":"venue"
},
  "geometry": {"coordinates":[-3.952466,51.618176],"type":"Point"}
}