{
  "type": "Feature",
  "properties": {
    "addr:full":"10 Berkeley Drive Burnley Lancashire BB12 7QG",
    "addr:housenumber":"10",
    "addr:postcode":"bb12 7qg",
    "addr:street":"Berkeley Drive",
    "iso:country":"GB",
    "sg:address":"10 Berkeley Drive",
    "sg:city":"Burnley",
    "sg:classifiers":[
        {
            "category":"Shopping",
            "subcategory":"Computers & Home Electronics",
            "type":"Retail Goods"
        }
    ],
    "sg:postcode":"BB12 7QG",
    "sg:province":"Lancashire",
    "sg:tags":[
        "equipment",
        "radio"
    ],
    "wof:name":"E L T Radiotelephones",
    "wof:placetype":"venue"
},
  "geometry": {"coordinates":[-2.3499119282,53.8102836609],"type":"Point"}
}