{
  "type": "Feature",
  "properties": {
    "addr:full":"St Lukes Community Centre, Princess Drive Liverpool Merseyside L14 8XG",
    "addr:postcode":"l14 8xg",
    "addr:street":"Princess Drive",
    "iso:country":"GB",
    "sg:address":"St Lukes Community Centre, Princess Drive",
    "sg:city":"Liverpool",
    "sg:classifiers":[
        {
            "category":"Professional",
            "subcategory":"Computer Services",
            "type":"Services"
        }
    ],
    "sg:postcode":"L14 8XG",
    "sg:province":"Merseyside",
    "sg:tags":[
        "information"
    ],
    "wof:name":"Princess Drive Information & Advice Centre",
    "wof:placetype":"venue"
},
  "geometry": {"coordinates":[-2.978481,53.409775],"type":"Point"}
}