{
  "type": "Feature",
  "properties": {
    "iso:country":"GB",
    "sg:address":"Albany House, 120-126 Station Road",
    "sg:city":"Redhill",
    "sg:classifiers":[
        {
            "category":"Home & Garden",
            "subcategory":"Home Furnishings",
            "type":"Retail Goods"
        }
    ],
    "sg:phone":"+44 1737 764242",
    "sg:postcode":"RH1 1PY",
    "sg:province":"Surrey",
    "sg:tags":[
        "merchant",
        "diy",
        "decorators'"
    ],
    "wof:name":"C Brewer & Sons Ltd.",
    "wof:placetype":"venue"
},
  "geometry": {"coordinates":[-0.1722600013,51.2402763367],"type":"Point"}
}