{
  "type": "Feature",
  "properties": {
    "iso:country":"GB",
    "sg:address":"112-114 Houndsditch",
    "sg:city":"London",
    "sg:classifiers":[
        {
            "category":"Fast Food",
            "type":"Food & Drink"
        }
    ],
    "sg:phone":"+44 20 7623 5434",
    "sg:postcode":"EC3A 7BD",
    "sg:province":"Greater London",
    "sg:tags":[
        "away",
        "take"
    ],
    "wof:name":"Burger King",
    "wof:placetype":"venue"
},
  "geometry": {"coordinates":[-0.079113,51.515701],"type":"Point"}
}