{
  "type": "Feature",
  "properties": {
    "addr:full":"Bolton Percy York North Yorkshire YO23 7AG",
    "addr:postcode":"yo23 7ag",
    "iso:country":"GB",
    "sg:address":"Bolton Percy",
    "sg:city":"York",
    "sg:classifiers":[
        {
            "category":"Bars & Pubs",
            "type":"Food & Drink"
        }
    ],
    "sg:phone":"+44 1904 744255",
    "sg:postcode":"YO23 7AG",
    "sg:province":"North Yorkshire",
    "sg:tags":[
        "pubs",
        "inn"
    ],
    "wof:name":"The Crown Inn",
    "wof:placetype":"venue"
},
  "geometry": {"coordinates":[-1.19353,53.864559],"type":"Point"}
}