{
  "type": "Feature",
  "properties": {
    "addr:full":"107 Steyne Road Seaford East Sussex BN25 1AS",
    "addr:housenumber":"107",
    "addr:postcode":"bn25 1as",
    "addr:street":"Steyne Road",
    "iso:country":"GB",
    "sg:address":"107 Steyne Road",
    "sg:city":"Seaford",
    "sg:classifiers":[
        {
            "category":"Social Services",
            "subcategory":"Retirement Home",
            "type":"Services"
        }
    ],
    "sg:phone":"+44 1323 490851",
    "sg:postcode":"BN25 1AS",
    "sg:province":"East Sussex",
    "sg:tags":[
        "rest"
    ],
    "wof:name":"Seaford Head Retirement Home",
    "wof:placetype":"venue"
},
  "geometry": {"coordinates":[0.099465,50.770489],"type":"Point"}
}