{
  "type": "Feature",
  "properties": {
    "addr:full":"17 Old Square Walsall West Midlands WS1 1QA",
    "addr:housenumber":"17",
    "addr:postcode":"ws1 1qa",
    "addr:street":"Old Square",
    "iso:country":"GB",
    "sg:address":"17 Old Square",
    "sg:city":"Walsall",
    "sg:classifiers":[
        {
            "category":"Shopping",
            "subcategory":"Department Store",
            "type":"Retail Goods"
        }
    ],
    "sg:phone":"+44 1922 627101",
    "sg:postcode":"WS1 1QA",
    "sg:province":"West Midlands",
    "wof:name":"Debenhams Retail Plc",
    "wof:placetype":"venue"
},
  "geometry": {"coordinates":[-1.9804689884,52.5837516785],"type":"Point"}
}