{
  "type": "Feature",
  "properties": {
    "iso:country":"GB",
    "sg:address":"108 Dura Street",
    "sg:city":"Dundee",
    "sg:classifiers":[
        {
            "category":"Bars & Pubs",
            "type":"Food & Drink"
        },
        {
            "category":"Community Center",
            "subcategory":"Social",
            "type":"Public Place"
        }
    ],
    "sg:phone":"+44 1382 451173",
    "sg:postcode":"DD4 6TE",
    "sg:province":"Dundee City",
    "sg:tags":[
        "pubs",
        "house",
        "inn",
        "activity"
    ],
    "wof:name":"Stobs Well Bar",
    "wof:placetype":"venue"
},
  "geometry": {"coordinates":[-2.9566640854,56.4726829529],"type":"Point"}
}