{
  "type": "Feature",
  "properties": {
    "addr:full":"Unit A, Church Lane, Kelbrook Barnoldswick Lancashire BB18 6UF",
    "addr:housenumber":"unit a",
    "addr:postcode":"bb18 6uf",
    "addr:street":"Church Lane",
    "iso:country":"GB",
    "sg:address":"Unit A, Church Lane, Kelbrook",
    "sg:city":"Barnoldswick",
    "sg:classifiers":[
        {
            "category":"Professional",
            "subcategory":"Engineering",
            "type":"Services"
        }
    ],
    "sg:phone":"+44 1282 817781",
    "sg:postcode":"BB18 6UF",
    "sg:province":"Lancashire",
    "sg:tags":[
        "engineer",
        "mechanical"
    ],
    "wof:name":"K.R.H Engineering",
    "wof:placetype":"venue"
},
  "geometry": {"coordinates":[-2.1511089802,53.8983001709],"type":"Point"}
}