{
  "type": "Feature",
  "properties": {
    "iso:country":"GB",
    "sg:address":"Broad Street, Wrington",
    "sg:city":"Bristol",
    "sg:classifiers":[
        {
            "category":"Government",
            "subcategory":"Post Office",
            "type":"Public Place"
        }
    ],
    "sg:postcode":"BS40 5LA",
    "sg:province":"Somerset",
    "wof:name":"Wrington Sub Post Office",
    "wof:placetype":"venue"
},
  "geometry": {"coordinates":[-2.763928,51.361839],"type":"Point"}
}