{
  "type": "Feature",
  "properties": {
    "iso:country":"GB",
    "sg:address":"Upper St Dennis Farm, Honington",
    "sg:city":"Shipston-on-stour",
    "sg:classifiers":[
        {
            "category":"Home & Garden",
            "subcategory":"Garden Supply",
            "type":"Retail Goods"
        },
        {
            "category":"Farming",
            "subcategory":"Livestock Farm",
            "type":"Manufacturing & Wholesale Goods"
        }
    ],
    "sg:phone":"+44 1608 661426",
    "sg:postcode":"CV36 5EL",
    "sg:province":"Warwickshire",
    "sg:tags":[
        "bulb",
        "grower",
        "others"
    ],
    "wof:name":"James Mahon & Sons",
    "wof:placetype":"venue"
},
  "geometry": {"coordinates":[-1.568624,52.028473],"type":"Point"}
}