{
  "type": "Feature",
  "properties": {
    "addr:full":"Trident Works, Harts Lane Bristol Somerset BS39 5EA",
    "addr:postcode":"bs39 5ea",
    "addr:street":"Harts Lane",
    "iso:country":"GB",
    "sg:address":"Trident Works, Harts Lane",
    "sg:city":"Bristol",
    "sg:classifiers":[
        {
            "category":"Retail",
            "subcategory":"Auto Repair",
            "type":"Services"
        }
    ],
    "sg:postcode":"BS39 5EA",
    "sg:province":"Somerset",
    "sg:tags":[
        "modification",
        "garage"
    ],
    "wof:name":"Paul Gunstone",
    "wof:placetype":"venue"
},
  "geometry": {"coordinates":[-2.5858099461,51.3085212708],"type":"Point"}
}