{
  "type": "Feature",
  "properties": {
    "iso:country":"GB",
    "sg:address":"6a Broad Street",
    "sg:city":"Wokingham",
    "sg:classifiers":[
        {
            "category":"Shopping",
            "subcategory":"Gifts & Souvenirs",
            "type":"Retail Goods"
        }
    ],
    "sg:phone":"+44 118 979 3003",
    "sg:postcode":"RG40 1AB",
    "sg:province":"Berkshire",
    "sg:tags":[
        "poster",
        "card"
    ],
    "wof:name":"Midas Cards",
    "wof:placetype":"venue"
},
  "geometry": {"coordinates":[-0.835622,51.411148],"type":"Point"}
}