{
  "type": "Feature",
  "properties": {
    "addr:full":"9 Lansdowne Square Hove East Sussex BN3 1HE",
    "addr:housenumber":"9",
    "addr:postcode":"bn3 1he",
    "addr:street":"Lansdowne Square Hove",
    "iso:country":"GB",
    "sg:address":"9 Lansdowne Square",
    "sg:city":"Hove",
    "sg:classifiers":[
        {
            "category":"Communications",
            "type":"Services"
        }
    ],
    "sg:phone":"+44 1273 204041",
    "sg:postcode":"BN3 1HE",
    "sg:province":"East Sussex",
    "sg:tags":[
        "telecommunication"
    ],
    "wof:name":"Tor Communications Ltd.",
    "wof:placetype":"venue"
},
  "geometry": {"coordinates":[-0.1611700058,50.824760437],"type":"Point"}
}