{
  "type": "Feature",
  "properties": {
    "addr:full":"The Towers, 28 Bond St Wakefield West Yorkshire WF1 2QP",
    "addr:housenumber":"28",
    "addr:postcode":"wf1 2qp",
    "addr:street":"Bond St",
    "iso:country":"GB",
    "sg:address":"The Towers, 28 Bond St",
    "sg:city":"Wakefield",
    "sg:classifiers":[
        {
            "category":"Health Services",
            "subcategory":"Dentist",
            "type":"Services"
        }
    ],
    "sg:phone":"+44 1924 372064",
    "sg:postcode":"WF1 2QP",
    "sg:province":"West Yorkshire",
    "wof:name":"Jack Roberts",
    "wof:placetype":"venue"
},
  "geometry": {"coordinates":[-1.5029900074,53.6861000061],"type":"Point"}
}