{
  "type": "Feature",
  "properties": {
    "iso:country":"GB",
    "sg:address":"New Coundon",
    "sg:city":"Bishop Auckland",
    "sg:classifiers":[
        {
            "category":"Travel",
            "subcategory":"Hotels & Motels",
            "type":"Entertainment"
        }
    ],
    "sg:phone":"+44 1388 661727",
    "sg:postcode":"DL14 8QB",
    "sg:province":"Durham",
    "wof:name":"Park Head Hotel",
    "wof:placetype":"venue"
},
  "geometry": {"coordinates":[-1.64742,54.66608],"type":"Point"}
}