{
  "type": "Feature",
  "properties": {
    "addr:full":"50-52 Seamer Road Scarborough North Yorkshire YO12 4EA",
    "addr:housenumber":"50-52",
    "addr:postcode":"yo12 4ea",
    "addr:street":"Seamer Road",
    "iso:country":"GB",
    "sg:address":"50-52 Seamer Road",
    "sg:city":"Scarborough",
    "sg:classifiers":[
        {
            "category":"Social Services",
            "type":"Services"
        }
    ],
    "sg:phone":"+44 1723 506030",
    "sg:postcode":"YO12 4EA",
    "sg:province":"North Yorkshire",
    "sg:tags":[
        "disability"
    ],
    "wof:name":"Quality Life Mobililty",
    "wof:placetype":"venue"
},
  "geometry": {"coordinates":[-0.4154460132,54.2721862793],"type":"Point"}
}