{
  "type": "Feature",
  "properties": {
    "iso:country":"GB",
    "sg:address":"382-386 Two Mile Hill Road, Kingswood",
    "sg:city":"Bristol",
    "sg:classifiers":[
        {
            "category":"Professional",
            "subcategory":"Employment Agencies",
            "type":"Services"
        }
    ],
    "sg:phone":"+44 117 991 3200",
    "sg:postcode":"BS15 1AA",
    "sg:province":"City of Bristol",
    "sg:tags":[
        "consultant"
    ],
    "wof:name":"Department of Education & Employment",
    "wof:placetype":"venue"
},
  "geometry": {"coordinates":[-2.514919,51.463234],"type":"Point"}
}