{
  "type": "Feature",
  "properties": {
    "addr:full":"320 High Street Rochester Kent ME1 1BT",
    "addr:housenumber":"320",
    "addr:postcode":"me1 1bt",
    "addr:street":"High Street",
    "iso:country":"GB",
    "sg:address":"320 High Street",
    "sg:city":"Rochester",
    "sg:classifiers":[
        {
            "category":"Professional",
            "subcategory":"Printing & Photocopies",
            "type":"Services"
        }
    ],
    "sg:phone":"+44 1634 404783",
    "sg:postcode":"ME1 1BT",
    "sg:province":"Kent",
    "sg:tags":[
        "printer"
    ],
    "wof:name":"Envostat Services",
    "wof:placetype":"venue"
},
  "geometry": {"coordinates":[0.5124130249,51.3836326599],"type":"Point"}
}