{
  "type": "Feature",
  "properties": {
    "addr:full":"207 Front Lane, Cranham Upminster Essex RM14 1LD",
    "addr:housenumber":"207",
    "addr:postcode":"rm14 1ld",
    "addr:street":"Front Lane",
    "iso:country":"GB",
    "sg:address":"207 Front Lane, Cranham",
    "sg:city":"Upminster",
    "sg:classifiers":[
        {
            "category":"Retail",
            "subcategory":"Repair Shop",
            "type":"Services"
        }
    ],
    "sg:phone":"+44 1708 509310",
    "sg:postcode":"RM14 1LD",
    "sg:province":"Essex",
    "sg:tags":[
        "upholsterer"
    ],
    "wof:name":"Darren Colvin",
    "wof:placetype":"venue"
},
  "geometry": {"coordinates":[0.26803,51.567753],"type":"Point"}
}