{
  "type": "Feature",
  "properties": {
    "addr:full":"Wymondham Library, Beckets Chapel, 2 Church Street Wymondham Norfolk NR18 0PH",
    "addr:housenumber":"2",
    "addr:postcode":"nr18 0ph",
    "addr:street":"Church Street",
    "iso:country":"GB",
    "sg:address":"Wymondham Library, Beckets Chapel, 2 Church Street",
    "sg:city":"Wymondham",
    "sg:classifiers":[
        {
            "category":"Education",
            "subcategory":"Library",
            "type":"Public Place"
        },
        {
            "category":"Government",
            "subcategory":"Office",
            "type":"Public Place"
        }
    ],
    "sg:phone":"+44 1953 603319",
    "sg:postcode":"NR18 0PH",
    "sg:province":"Norfolk",
    "sg:tags":[
        "book",
        "local"
    ],
    "wof:name":"Norfolk County Council",
    "wof:placetype":"venue"
},
  "geometry": {"coordinates":[1.1160639524,52.5702285767],"type":"Point"}
}