{
  "type": "Feature",
  "properties": {
    "iso:country":"GB",
    "sg:address":"Radio Ho, West Canal Wharf",
    "sg:city":"Cardiff",
    "sg:classifiers":[
        {
            "category":"Communications",
            "type":"Services"
        }
    ],
    "sg:phone":"+44 29 2023 7878",
    "sg:postcode":"CF1 5XL",
    "sg:province":"Cardiff",
    "sg:tags":[
        "broadcasting"
    ],
    "wof:name":"Touch Radio",
    "wof:placetype":"venue"
},
  "geometry": {"coordinates":[-3.18067,51.481258],"type":"Point"}
}