{
  "type": "Feature",
  "properties": {
    "addr:full":"1a Phillimore Gardens London Greater London W8 7QG",
    "addr:housenumber":"1a",
    "addr:postcode":"w8 7qg",
    "addr:street":"Phillimore Gardens",
    "iso:country":"GB",
    "sg:address":"1a Phillimore Gardens",
    "sg:city":"London",
    "sg:classifiers":[
        {
            "category":"Restaurant",
            "type":"Food & Drink"
        }
    ],
    "sg:phone":"+44 20 7938 5338",
    "sg:postcode":"W8 7QG",
    "sg:province":"Greater London",
    "wof:name":"Sticky Fingers Restaurant Ltd.",
    "wof:placetype":"venue"
},
  "geometry": {"coordinates":[-0.1988849938,51.5013313293],"type":"Point"}
}