{
  "type": "Feature",
  "properties": {
    "iso:country":"GB",
    "sg:address":"Bank Chambers, 178 Lord Street",
    "sg:city":"Fleetwood",
    "sg:classifiers":[
        {
            "category":"Professional",
            "subcategory":"Advertising",
            "type":"Services"
        }
    ],
    "sg:phone":"+44 1253 778610",
    "sg:postcode":"FY7 6SR",
    "sg:province":"Lancashire",
    "wof:name":"Premier Design Publications",
    "wof:placetype":"venue"
},
  "geometry": {"coordinates":[-3.014669,53.92128],"type":"Point"}
}