{
  "type": "Feature",
  "properties": {
    "addr:full":"180 Northdown Road Margate Kent CT9 2QN",
    "addr:housenumber":"180",
    "addr:postcode":"ct9 2qn",
    "addr:street":"Northdown Road",
    "iso:country":"GB",
    "sg:address":"180 Northdown Road",
    "sg:city":"Margate",
    "sg:classifiers":[
        {
            "category":"Health Services",
            "subcategory":"Optometrist",
            "type":"Services"
        }
    ],
    "sg:phone":"+44 1843 221168",
    "sg:postcode":"CT9 2QN",
    "sg:province":"Kent",
    "sg:tags":[
        "optician"
    ],
    "wof:name":"Alison H Mortley",
    "wof:placetype":"venue"
},
  "geometry": {"coordinates":[1.3954279423,51.3880691528],"type":"Point"}
}