{
  "type": "Feature",
  "properties": {
    "iso:country":"GB",
    "sg:address":"46 Aspley Hill, Woburn Sands",
    "sg:city":"Milton Keynes",
    "sg:classifiers":[
        {
            "category":"Museum",
            "subcategory":"Art Museum",
            "type":"Entertainment"
        }
    ],
    "sg:phone":"+44 1908 585337",
    "sg:postcode":"MK17 8NJ",
    "sg:province":"Bedfordshire",
    "sg:tags":[
        "gallery"
    ],
    "wof:name":"Hornington Ltd",
    "wof:placetype":"venue"
},
  "geometry": {"coordinates":[-0.643899,52.010719],"type":"Point"}
}