{
  "type": "Feature",
  "properties": {
    "addr:full":"15 Chitty Street London Greater London W1T 4AX",
    "addr:housenumber":"15",
    "addr:postcode":"w1t 4ax",
    "addr:street":"Chitty Street",
    "iso:country":"GB",
    "sg:address":"15 Chitty Street",
    "sg:city":"London",
    "sg:classifiers":[
        {
            "category":"Professional",
            "subcategory":"Advertising",
            "type":"Services"
        }
    ],
    "sg:phone":"+44 20 7580 0186",
    "sg:postcode":"W1T 4AX",
    "sg:province":"Greater London",
    "sg:tags":[
        "medium"
    ],
    "wof:name":"Equinox Communications Ltd.",
    "wof:placetype":"venue"
},
  "geometry": {"coordinates":[-0.136447,51.521191],"type":"Point"}
}