{
  "type": "Feature",
  "properties": {
    "iso:country":"GB",
    "sg:address":"1 Charlotte Street",
    "sg:city":"Ayr",
    "sg:classifiers":[
        {
            "category":"Banks & Credit Unions",
            "subcategory":"Bank",
            "type":"Services"
        },
        {
            "category":"Banks & Credit Unions",
            "subcategory":"Financial Services",
            "type":"Services"
        }
    ],
    "sg:phone":"+44 1292 266925",
    "sg:postcode":"KA7 1DZ",
    "sg:province":"South Ayrshire",
    "sg:tags":[
        "consultant",
        "institution"
    ],
    "wof:name":"DALBEATTIE FINANCE CO LTD",
    "wof:placetype":"venue"
},
  "geometry": {"coordinates":[-4.635169,55.462662],"type":"Point"}
}