{
  "type": "Feature",
  "properties": {
    "addr:full":"6 Glebe Rd, Crondall Farnham Hampshire GU10 5PJ",
    "addr:housenumber":"6",
    "addr:postcode":"gu10 5pj",
    "addr:street":"Glebe Rd",
    "iso:country":"GB",
    "sg:address":"6 Glebe Rd, Crondall",
    "sg:city":"Farnham",
    "sg:classifiers":[
        {
            "category":"Travel",
            "subcategory":"Travel Agent",
            "type":"Entertainment"
        }
    ],
    "sg:phone":"+44 1252 852516",
    "sg:postcode":"GU10 5PJ",
    "sg:province":"Hampshire",
    "wof:name":"Flight Solutions",
    "wof:placetype":"venue"
},
  "geometry": {"coordinates":[-0.860435009,51.2326049805],"type":"Point"}
}