{
  "type": "Feature",
  "properties": {
    "iso:country":"GB",
    "sg:address":"4th Floor Centre Heights, 137 Finchley Road",
    "sg:city":"London",
    "sg:classifiers":[
        {
            "category":"Organizations",
            "subcategory":"Membership Organization",
            "type":"Services"
        }
    ],
    "sg:postcode":"NW3 6JG",
    "sg:province":"Greater London",
    "sg:tags":[
        "club"
    ],
    "wof:name":"Fifty Three Stanhope Gardens Ltd",
    "wof:placetype":"venue"
},
  "geometry": {"coordinates":[-0.17559,51.543869],"type":"Point"}
}