{
  "type": "Feature",
  "properties": {
    "addr:full":"124 High St Hampton Greater London TW12 1NS",
    "addr:housenumber":"124",
    "addr:postcode":"tw12 1ns",
    "addr:street":"High St",
    "iso:country":"GB",
    "sg:address":"124 High St",
    "sg:city":"Hampton",
    "sg:classifiers":[
        {
            "category":"Professional",
            "subcategory":"Computer Services",
            "type":"Services"
        }
    ],
    "sg:phone":"+44 20 8943 3388",
    "sg:postcode":"TW12 1NS",
    "sg:province":"Greater London",
    "sg:tags":[
        "system",
        "software"
    ],
    "wof:name":"Four Star Capital UK",
    "wof:placetype":"venue"
},
  "geometry": {"coordinates":[-0.3539330065,51.4292945862],"type":"Point"}
}