{
  "type": "Feature",
  "properties": {
    "addr:full":"Moons Farm, Gay Street Lane, North Heath Pulborough West Sussex RH20 2HN",
    "addr:postcode":"rh20 2hn",
    "addr:street":"Street Lane",
    "iso:country":"GB",
    "sg:address":"Moons Farm, Gay Street Lane, North Heath",
    "sg:city":"Pulborough",
    "sg:classifiers":[
        {
            "category":"Building & Trades",
            "subcategory":"Pest Control",
            "type":"Services"
        },
        {
            "category":"Social Services",
            "subcategory":"Adult Care",
            "type":"Services"
        }
    ],
    "sg:phone":"+44 1798 872046",
    "sg:postcode":"RH20 2HN",
    "sg:province":"West Sussex",
    "sg:tags":[
        "prevention",
        "treatment",
        "woodworm"
    ],
    "wof:name":"Astons Timber Treatment & Rising Damp Control",
    "wof:placetype":"venue"
},
  "geometry": {"coordinates":[-0.5118790269,50.9570770264],"type":"Point"}
}