{
  "type": "Feature",
  "properties": {
    "addr:full":"19 Clare Road Greenford Greater London UB6 0DE",
    "addr:housenumber":"19",
    "addr:postcode":"ub6 0de",
    "addr:street":"Clare Road",
    "iso:country":"GB",
    "sg:address":"19 Clare Road",
    "sg:city":"Greenford",
    "sg:classifiers":[
        {
            "category":"Building & Trades",
            "subcategory":"Landscaping Services",
            "type":"Services"
        }
    ],
    "sg:phone":"+44 20 8869 1147",
    "sg:postcode":"UB6 0DE",
    "sg:province":"Greater London",
    "sg:tags":[
        "gardening"
    ],
    "wof:name":"Clare Gardening Services",
    "wof:placetype":"venue"
},
  "geometry": {"coordinates":[-0.3451,51.550076],"type":"Point"}
}