{
  "type": "Feature",
  "properties": {
    "iso:country":"GB",
    "sg:address":"3 Horninglow Road",
    "sg:city":"Burton On Trent",
    "sg:classifiers":[
        {
            "category":"Communications",
            "type":"Services"
        }
    ],
    "sg:postcode":"DE14 2PR",
    "sg:province":"Derbyshire",
    "sg:tags":[
        "tv",
        "video",
        "radio"
    ],
    "wof:name":"Dean Poxon",
    "wof:placetype":"venue"
},
  "geometry": {"coordinates":[-1.636161,52.813435],"type":"Point"}
}