{
  "type": "Feature",
  "properties": {
    "addr:full":"Shepley Industrial Estate South, Audenshaw Manchester Greater Manchester M34 5DW",
    "addr:postcode":"m34 5dw",
    "addr:street":"Estate South Audenshaw",
    "iso:country":"GB",
    "sg:address":"Shepley Industrial Estate South, Audenshaw",
    "sg:city":"Manchester",
    "sg:classifiers":[
        {
            "category":"Real Estate",
            "subcategory":"Real Estate Services",
            "type":"Services"
        },
        {
            "category":"Real Estate",
            "subcategory":"Real Estate Agent",
            "type":"Services"
        }
    ],
    "sg:phone":"+44 161 336 4316",
    "sg:postcode":"M34 5DW",
    "sg:province":"Greater Manchester",
    "sg:tags":[
        "management"
    ],
    "wof:name":"Ravenseft Industrial Estates Ltd",
    "wof:placetype":"venue"
},
  "geometry": {"coordinates":[-2.129179,53.471275],"type":"Point"}
}