{
  "type": "Feature",
  "properties": {
    "addr:full":"34 Bargate Lincoln Lincolnshire LN5 8DH",
    "addr:housenumber":"34",
    "addr:postcode":"ln5 8dh",
    "addr:street":"Bargate Lincoln",
    "iso:country":"GB",
    "sg:address":"34 Bargate",
    "sg:city":"Lincoln",
    "sg:classifiers":[
        {
            "category":"Retail",
            "subcategory":"Auto Repair",
            "type":"Services"
        }
    ],
    "sg:phone":"+44 1522 541586",
    "sg:postcode":"LN5 8DH",
    "sg:province":"Lincolnshire",
    "sg:tags":[
        "body",
        "car",
        "repairer"
    ],
    "wof:name":"J A M Body Repairs",
    "wof:placetype":"venue"
},
  "geometry": {"coordinates":[-0.543845,53.216503],"type":"Point"}
}