{
  "type": "Feature",
  "properties": {
    "addr:full":"15 Manor Close, Langtoft Peterborough Cambridgeshire PE6 9NB",
    "addr:housenumber":"15",
    "addr:postcode":"pe6 9nb",
    "addr:street":"Manor Close",
    "iso:country":"GB",
    "sg:address":"15 Manor Close, Langtoft",
    "sg:city":"Peterborough",
    "sg:classifiers":[
        {
            "category":"Professional",
            "subcategory":"Engineering",
            "type":"Services"
        }
    ],
    "sg:phone":"+44 1778 341474",
    "sg:postcode":"PE6 9NB",
    "sg:province":"Cambridgeshire",
    "sg:tags":[
        "contractor",
        "electrical",
        "engineer"
    ],
    "wof:name":"R Rippon Electrical Installations",
    "wof:placetype":"venue"
},
  "geometry": {"coordinates":[-0.3449290097,52.6973876953],"type":"Point"}
}