{
  "type": "Feature",
  "properties": {
    "addr:full":"23/24 Wivenhoe Business Centre, Brook Street, Wivenhoe Colchester Essex CO7 9DP",
    "addr:housenumber":"23 / 24",
    "addr:postcode":"co7 9dp",
    "addr:street":"Wivenhoe Business Centre Brook Street",
    "iso:country":"GB",
    "sg:address":"23/24 Wivenhoe Business Centre, Brook Street, Wivenhoe",
    "sg:city":"Colchester",
    "sg:classifiers":[
        {
            "category":"Home & Garden",
            "subcategory":"Building Materials",
            "type":"Retail Goods"
        },
        {
            "category":"Building & Trades",
            "subcategory":"Construction",
            "type":"Services"
        }
    ],
    "sg:phone":"+44 1206 822017",
    "sg:postcode":"CO7 9DP",
    "sg:province":"Essex",
    "sg:tags":[
        "ironwork",
        "builder",
        "diy",
        "wrought"
    ],
    "wof:name":"Hart Metal Craft",
    "wof:placetype":"venue"
},
  "geometry": {"coordinates":[0.95947,51.856838],"type":"Point"}
}