{
  "type": "Feature",
  "properties": {
    "iso:country":"GB",
    "sg:address":"Charity Farm, Skipwith",
    "sg:city":"Selby",
    "sg:classifiers":[
        {
            "category":"Wholesale",
            "subcategory":"Toys & Hobbies",
            "type":"Manufacturing & Wholesale Goods"
        }
    ],
    "sg:postcode":"YO8 5SL",
    "sg:province":"East Riding of Yorkshire",
    "sg:tags":[
        "balloon",
        "novelty"
    ],
    "wof:name":"Balloon Rides Ltd.",
    "wof:placetype":"venue"
},
  "geometry": {"coordinates":[-0.991483,53.838184],"type":"Point"}
}