{
  "type": "Feature",
  "properties": {
    "iso:country":"GB",
    "sg:address":"Unit 4 Fernfield Industrial Estate, Whaddon Road, Mursley",
    "sg:city":"Milton Keynes",
    "sg:classifiers":[
        {
            "category":"Retail",
            "subcategory":"Auto Repair",
            "type":"Services"
        }
    ],
    "sg:phone":"+44 1908 502638",
    "sg:postcode":"MK17 0PS",
    "sg:province":"Bedfordshire",
    "sg:tags":[
        "body",
        "car"
    ],
    "wof:name":"Autotech",
    "wof:placetype":"venue"
},
  "geometry": {"coordinates":[-0.8137500286,51.9436035156],"type":"Point"}
}