{
  "type": "Feature",
  "properties": {
    "iso:country":"GB",
    "sg:address":"20 Clonmore St",
    "sg:city":"Wandsworth",
    "sg:classifiers":[
        {
            "category":"Professional",
            "subcategory":"Accounting & Tax Preparation",
            "type":"Services"
        }
    ],
    "sg:phone":"+44 20 8871 0649",
    "sg:postcode":"SW18 5EX",
    "sg:province":"Greater London",
    "sg:tags":[
        "payroll"
    ],
    "wof:name":"Rocket Business Services",
    "wof:placetype":"venue"
},
  "geometry": {"coordinates":[-0.2039799988,51.4442710876],"type":"Point"}
}