{
  "type": "Feature",
  "properties": {
    "addr:full":"Swadforth House, Gracious Street Knaresborough North Yorkshire HG5 8DT",
    "addr:postcode":"hg5 8dt",
    "addr:street":"Gracious Street",
    "iso:country":"GB",
    "sg:address":"Swadforth House, Gracious Street",
    "sg:city":"Knaresborough",
    "sg:classifiers":[
        {
            "category":"Shopping",
            "subcategory":"Antiques",
            "type":"Retail Goods"
        }
    ],
    "sg:postcode":"HG5 8DT",
    "sg:province":"North Yorkshire",
    "wof:name":"John Thompson Antiques",
    "wof:placetype":"venue"
},
  "geometry": {"coordinates":[-1.4650889635,54.0071411133],"type":"Point"}
}