{
  "type": "Feature",
  "properties": {
    "addr:full":"40-41 High St Preston Lancashire PR3 1EA",
    "addr:housenumber":"40-41",
    "addr:postcode":"pr3 1ea",
    "addr:street":"High St",
    "iso:country":"GB",
    "sg:address":"40-41 High St",
    "sg:city":"Preston",
    "sg:classifiers":[
        {
            "category":"Shopping",
            "subcategory":"Florist",
            "type":"Retail Goods"
        }
    ],
    "sg:phone":"+44 1995 603758",
    "sg:postcode":"PR3 1EA",
    "sg:province":"Lancashire",
    "wof:name":"Bloomers",
    "wof:placetype":"venue"
},
  "geometry": {"coordinates":[-2.7736771107,53.9023323059],"type":"Point"}
}