{
  "type": "Feature",
  "properties": {
    "addr:full":"64 Bosman Drive Windlesham Surrey GU20 6JW",
    "addr:housenumber":"64",
    "addr:postcode":"gu20 6jw",
    "addr:street":"Bosman Drive",
    "iso:country":"GB",
    "sg:address":"64 Bosman Drive",
    "sg:city":"Windlesham",
    "sg:classifiers":[
        {
            "category":"Professional",
            "subcategory":"Art Services",
            "type":"Services"
        }
    ],
    "sg:phone":"+44 1276 475864",
    "sg:postcode":"GU20 6JW",
    "sg:province":"Surrey",
    "sg:tags":[
        "photographer"
    ],
    "wof:name":"James Daniel Fairman",
    "wof:placetype":"venue"
},
  "geometry": {"coordinates":[-0.668406,51.377045],"type":"Point"}
}