{
  "type": "Feature",
  "properties": {
    "addr:full":"Woodlands, Woodlands Lane, Storrington Pulborough West Sussex RH20 3HG",
    "addr:postcode":"rh20 3hg",
    "addr:street":"Woodlands Lane",
    "iso:country":"GB",
    "sg:address":"Woodlands, Woodlands Lane, Storrington",
    "sg:city":"Pulborough",
    "sg:classifiers":[
        {
            "category":"Professional",
            "subcategory":"Printing & Photocopies",
            "type":"Services"
        }
    ],
    "sg:phone":"+44 1903 745445",
    "sg:postcode":"RH20 3HG",
    "sg:province":"West Sussex",
    "sg:tags":[
        "printer"
    ],
    "wof:name":"Print Marketing Services",
    "wof:placetype":"venue"
},
  "geometry": {"coordinates":[-0.4183860123,50.9264221191],"type":"Point"}
}