{
  "type": "Feature",
  "properties": {
    "addr:full":"2 Graham Rd Chiswick Greater London W4 5DR",
    "addr:housenumber":"2",
    "addr:postcode":"w4 5dr",
    "addr:street":"Graham Rd",
    "iso:country":"GB",
    "sg:address":"2 Graham Rd",
    "sg:city":"Chiswick",
    "sg:classifiers":[
        {
            "category":"Professional",
            "subcategory":"Accounting & Tax Preparation",
            "type":"Services"
        }
    ],
    "sg:phone":"+44 20 8987 9490",
    "sg:postcode":"W4 5DR",
    "sg:province":"Greater London",
    "sg:tags":[
        "accountant"
    ],
    "wof:name":"Martina Eyre",
    "wof:placetype":"venue"
},
  "geometry": {"coordinates":[-0.262961,51.501354],"type":"Point"}
}