{
  "type": "Feature",
  "properties": {
    "addr:full":"Westwood Farm, Cotleigh Honiton Devon EX14 9HX",
    "addr:housenumber":"cotleigh",
    "addr:postcode":"ex14 9hx",
    "iso:country":"GB",
    "sg:address":"Westwood Farm, Cotleigh",
    "sg:city":"Honiton",
    "sg:classifiers":[
        {
            "category":"Farming",
            "subcategory":"Farm",
            "type":"Manufacturing & Wholesale Goods"
        }
    ],
    "sg:phone":"+44 1404 861219",
    "sg:postcode":"EX14 9HX",
    "sg:province":"Devon",
    "sg:tags":[
        "mixed",
        "crop"
    ],
    "wof:name":"D H Coombe",
    "wof:placetype":"venue"
},
  "geometry": {"coordinates":[-3.1323189735,50.8133201599],"type":"Point"}
}