{
  "type": "Feature",
  "properties": {
    "iso:country":"GB",
    "sg:address":"North Street, Cromford",
    "sg:city":"Matlock",
    "sg:classifiers":[
        {
            "category":"Bars & Pubs",
            "type":"Food & Drink"
        },
        {
            "category":"Community Center",
            "subcategory":"Social",
            "type":"Public Place"
        }
    ],
    "sg:phone":"+44 1629 822102",
    "sg:postcode":"DE4 3RG",
    "sg:province":"Derbyshire",
    "sg:tags":[
        "pubs",
        "house",
        "inn",
        "activity"
    ],
    "wof:name":"Bell Inn",
    "wof:placetype":"venue"
},
  "geometry": {"coordinates":[-1.548274,53.135616],"type":"Point"}
}