{
  "type": "Feature",
  "properties": {
    "addr:full":"108 Rectory Road, Pitsea Basildon Essex SS13 2AH",
    "addr:housenumber":"108",
    "addr:postcode":"ss13 2ah",
    "addr:street":"Rectory Road",
    "iso:country":"GB",
    "sg:address":"108 Rectory Road, Pitsea",
    "sg:city":"Basildon",
    "sg:classifiers":[
        {
            "category":"Personal",
            "subcategory":"Beauty Salon",
            "type":"Services"
        }
    ],
    "sg:phone":"+44 1268 553666",
    "sg:postcode":"SS13 2AH",
    "sg:province":"Essex",
    "sg:tags":[
        "unisex",
        "hairdresser"
    ],
    "wof:name":"Obsession",
    "wof:placetype":"venue"
},
  "geometry": {"coordinates":[0.5097169876,51.5715675354],"type":"Point"}
}