{
  "type": "Feature",
  "properties": {
    "iso:country":"GB",
    "sg:address":"Suite 1 Ferguson House, 11 Blackfriars Road",
    "sg:city":"Salford",
    "sg:classifiers":[
        {
            "category":"Manufacturing",
            "subcategory":"Textiles",
            "type":"Manufacturing & Wholesale Goods"
        }
    ],
    "sg:postcode":"M3 7AQ",
    "sg:province":"Greater Manchester",
    "wof:name":"Konsan (U K) Ltd.",
    "wof:placetype":"venue"
},
  "geometry": {"coordinates":[-2.252066,53.485924],"type":"Point"}
}