{
  "type": "Feature",
  "properties": {
    "addr:full":"Deans Farm Buildings, Deans Farm, Phillips Lane Salisbury Wiltshire SP1 3YR",
    "addr:postcode":"sp1 3yr",
    "addr:street":"Deans;Phillips Lane",
    "iso:country":"GB",
    "sg:address":"Deans Farm Buildings, Deans Farm, Phillips Lane",
    "sg:city":"Salisbury",
    "sg:classifiers":[
        {
            "category":"Shopping",
            "subcategory":"Party Supplies",
            "type":"Retail Goods"
        }
    ],
    "sg:phone":"+44 1722 336600",
    "sg:postcode":"SP1 3YR",
    "sg:province":"Wiltshire",
    "sg:tags":[
        "inflatables",
        "bouncy",
        "castle"
    ],
    "wof:name":"Billy's Bouncers",
    "wof:placetype":"venue"
},
  "geometry": {"coordinates":[-1.81012,51.0947],"type":"Point"}
}