{
  "type": "Feature",
  "properties": {
    "iso:country":"GB",
    "sg:address":"5 High Street",
    "sg:city":"Budleigh Salterton",
    "sg:classifiers":[
        {
            "category":"Food & Beverages",
            "subcategory":"Meat & Fish",
            "type":"Retail Goods"
        }
    ],
    "sg:postcode":"EX9 6LD",
    "sg:province":"Devon",
    "sg:tags":[
        "chip"
    ],
    "wof:name":"Salterton Fish & Chip Shop",
    "wof:placetype":"venue"
},
  "geometry": {"coordinates":[-3.325717,50.629131],"type":"Point"}
}