{
  "type": "Feature",
  "properties": {
    "iso:country":"GB",
    "sg:address":"345 Lee High Road",
    "sg:city":"London",
    "sg:classifiers":[
        {
            "category":"Home & Garden",
            "subcategory":"Hardware",
            "type":"Retail Goods"
        }
    ],
    "sg:phone":"+44 20 8355 8020",
    "sg:postcode":"SE12 8RU",
    "sg:province":"Greater London",
    "sg:tags":[
        "part",
        "accessory"
    ],
    "wof:name":"Hooter Scooter Ltd.",
    "wof:placetype":"venue"
},
  "geometry": {"coordinates":[0.008982,51.457371],"type":"Point"}
}