{
  "type": "Feature",
  "properties": {
    "addr:full":"16 Heath Rd South, Weston Runcorn Cheshire WA7 4QQ",
    "addr:housenumber":"16",
    "addr:postcode":"wa7 4qq",
    "addr:street":"Heath Rd",
    "iso:country":"GB",
    "sg:address":"16 Heath Rd South, Weston",
    "sg:city":"Runcorn",
    "sg:classifiers":[
        {
            "category":"Communications",
            "type":"Services"
        }
    ],
    "sg:postcode":"WA7 4QQ",
    "sg:province":"Cheshire",
    "sg:tags":[
        "tv",
        "video",
        "radio"
    ],
    "wof:name":"Weston Aerial & Satellite Services",
    "wof:placetype":"venue"
},
  "geometry": {"coordinates":[-2.7379789352,53.3255691528],"type":"Point"}
}