{
  "type": "Feature",
  "properties": {
    "iso:country":"GB",
    "sg:address":"18 Romsey Place",
    "sg:city":"Mansfield",
    "sg:classifiers":[
        {
            "category":"Organizations",
            "subcategory":"Non-profit Organization",
            "type":"Services"
        }
    ],
    "sg:postcode":"NG19 6UD",
    "sg:province":"Derbyshire",
    "sg:tags":[
        "organisation",
        "voluntary",
        "charity"
    ],
    "wof:name":"Nottingham Branch Ms Society Social Committee",
    "wof:placetype":"venue"
},
  "geometry": {"coordinates":[-1.231481,53.143723],"type":"Point"}
}