{
  "type": "Feature",
  "properties": {
    "addr:full":"348 Grt Horton Road Bradford West Yorkshire BD7 1QJ",
    "addr:housenumber":"348",
    "addr:postcode":"bd7 1qj",
    "addr:street":"Grt Horton Road",
    "iso:country":"GB",
    "sg:address":"348 Grt Horton Road",
    "sg:city":"Bradford",
    "sg:classifiers":[
        {
            "category":"Shopping",
            "subcategory":"News",
            "type":"Retail Goods"
        }
    ],
    "sg:phone":"+44 1274 574793",
    "sg:postcode":"BD7 1QJ",
    "sg:province":"West Yorkshire",
    "sg:tags":[
        "newsagent"
    ],
    "wof:name":"Ali's Newsagents",
    "wof:placetype":"venue"
},
  "geometry": {"coordinates":[-1.7742220163,53.7870635986],"type":"Point"}
}