{
  "type": "Feature",
  "properties": {
    "addr:full":"11 Rushcroft Road, Brixton London Greater London SW2 1JH",
    "addr:housenumber":"11",
    "addr:postcode":"sw2 1jh",
    "addr:street":"Rushcroft Road",
    "iso:country":"GB",
    "sg:address":"11 Rushcroft Road, Brixton",
    "sg:city":"London",
    "sg:classifiers":[
        {
            "category":"Personal",
            "subcategory":"Beauty Salon",
            "type":"Services"
        }
    ],
    "sg:phone":"+44 20 7326 0191",
    "sg:postcode":"SW2 1JH",
    "sg:province":"Greater London",
    "sg:tags":[
        "unisex",
        "hairdresser"
    ],
    "wof:name":"Knobi",
    "wof:placetype":"venue"
},
  "geometry": {"coordinates":[-0.1126890033,51.4612808228],"type":"Point"}
}