{
  "type": "Feature",
  "properties": {
    "addr:full":"Beacon Hill Indust Est, Botany Way Purfleet Essex RM19 1SR",
    "addr:postcode":"rm19 1sr",
    "addr:street":"Botany Way",
    "iso:country":"GB",
    "sg:address":"Beacon Hill Indust Est, Botany Way",
    "sg:city":"Purfleet",
    "sg:classifiers":[
        {
            "category":"Building & Trades",
            "subcategory":"Construction",
            "type":"Services"
        }
    ],
    "sg:phone":"+44 1708 861969",
    "sg:postcode":"RM19 1SR",
    "sg:province":"Essex",
    "sg:tags":[
        "block"
    ],
    "wof:name":"A R C Conbloc",
    "wof:placetype":"venue"
},
  "geometry": {"coordinates":[0.2414930016,51.4803390503],"type":"Point"}
}