{
  "type": "Feature",
  "properties": {
    "iso:country":"GB",
    "sg:address":"The Persona House, 1 Wellington Road",
    "sg:city":"Horsham",
    "sg:classifiers":[
        {
            "category":"Professional",
            "subcategory":"Engineering",
            "type":"Services"
        }
    ],
    "sg:phone":"+44 1403 217799",
    "sg:postcode":"RH12 1DD",
    "sg:province":"West Sussex",
    "sg:tags":[
        "consulting",
        "engineer"
    ],
    "wof:name":"Persona Associates Ltd.",
    "wof:placetype":"venue"
},
  "geometry": {"coordinates":[-0.3242169917,51.063205719],"type":"Point"}
}