{
  "type": "Feature",
  "properties": {
    "iso:country":"GB",
    "sg:address":"3 Hall Green Rd",
    "sg:city":"Coventry",
    "sg:classifiers":[
        {
            "category":"Retail",
            "subcategory":"Laundry & Dry Cleaning",
            "type":"Services"
        }
    ],
    "sg:phone":"+44 24 7668 9828",
    "sg:postcode":"CV6 7BX",
    "sg:province":"Warwickshire",
    "sg:tags":[
        "launderette"
    ],
    "wof:name":"Bell Green Washeteria",
    "wof:placetype":"venue"
},
  "geometry": {"coordinates":[-1.484559,52.430759],"type":"Point"}
}