{
  "type": "Feature",
  "properties": {
    "iso:country":"GB",
    "sg:address":"50 High Street, Markyate",
    "sg:city":"St Albans",
    "sg:classifiers":[
        {
            "category":"Building & Trades",
            "subcategory":"Construction",
            "type":"Services"
        }
    ],
    "sg:phone":"+44 1582 840236",
    "sg:postcode":"AL3 8HZ",
    "sg:province":"Hertfordshire",
    "sg:tags":[
        "builder"
    ],
    "wof:name":"W G  Hillier Ltd.",
    "wof:placetype":"venue"
},
  "geometry": {"coordinates":[-0.4612959921,51.8364562988],"type":"Point"}
}