{
  "type": "Feature",
  "properties": {
    "iso:country":"GB",
    "sg:address":"Whitehouse Farm, Thirsk Road",
    "sg:city":"York",
    "sg:classifiers":[
        {
            "category":"Farming",
            "subcategory":"Livestock Farm",
            "type":"Manufacturing & Wholesale Goods"
        }
    ],
    "sg:phone":"+44 1347 821325",
    "sg:postcode":"YO61 3NF",
    "sg:province":"North Yorkshire",
    "sg:tags":[
        "others"
    ],
    "wof:name":"P A Caygill",
    "wof:placetype":"venue"
},
  "geometry": {"coordinates":[-1.22204,54.13155],"type":"Point"}
}