{
  "type": "Feature",
  "properties": {
    "iso:country":"GB",
    "sg:address":"763b Finchley Rd",
    "sg:city":"London",
    "sg:classifiers":[
        {
            "category":"Retail",
            "subcategory":"Auto Repair",
            "type":"Services"
        }
    ],
    "sg:postcode":"NW11 8DL",
    "sg:province":"Greater London",
    "sg:tags":[
        "modification",
        "garage"
    ],
    "wof:name":"Automatic Transmission Engineering",
    "wof:placetype":"venue"
},
  "geometry": {"coordinates":[-0.1966170073,51.5647087097],"type":"Point"}
}