{
  "type": "Feature",
  "properties": {
    "iso:country":"GB",
    "sg:address":"18 Reginald Square",
    "sg:city":"London",
    "sg:classifiers":[
        {
            "category":"Building & Trades",
            "subcategory":"Plumbing",
            "type":"Services"
        },
        {
            "category":"Building & Trades",
            "subcategory":"Construction",
            "type":"Services"
        }
    ],
    "sg:phone":"+44 20 8694 2064",
    "sg:postcode":"SE8 4RU",
    "sg:province":"Greater London",
    "sg:tags":[
        "plumber",
        "heating",
        "contractor"
    ],
    "wof:name":"Steven Jeffrey Domestic Plumbing & Heating",
    "wof:placetype":"venue"
},
  "geometry": {"coordinates":[-0.025478,51.476067],"type":"Point"}
}