{
  "type": "Feature",
  "properties": {
    "iso:country":"GB",
    "sg:address":"Unit 4 Nevis Business Pk, Balgownie Rd, Bridge Of Don",
    "sg:city":"Aberdeen",
    "sg:classifiers":[
        {
            "category":"Building & Trades",
            "subcategory":"Construction",
            "type":"Services"
        }
    ],
    "sg:postcode":"AB22 8NT",
    "sg:province":"Aberdeen City",
    "sg:tags":[
        "fork",
        "lift",
        "truck"
    ],
    "wof:name":"B E L Lift Trucks (Scotland) Ltd",
    "wof:placetype":"venue"
},
  "geometry": {"coordinates":[-2.100368,57.182037],"type":"Point"}
}