{
  "type": "Feature",
  "properties": {
    "iso:country":"GB",
    "sg:address":"Vine Road, Johnston",
    "sg:city":"Haverfordwest",
    "sg:classifiers":[
        {
            "category":"Wholesale",
            "subcategory":"Scrap",
            "type":"Manufacturing & Wholesale Goods"
        }
    ],
    "sg:phone":"+44 1437 890339",
    "sg:postcode":"SA62 3NY",
    "sg:province":"Pembrokeshire",
    "sg:tags":[
        "breaker",
        "dismantlers"
    ],
    "wof:name":"Halfway Motor Spares",
    "wof:placetype":"venue"
},
  "geometry": {"coordinates":[-4.993949,51.762764],"type":"Point"}
}