{
  "type": "Feature",
  "properties": {
    "iso:country":"GB",
    "sg:address":"321-322 Glenrothes House, North Street",
    "sg:city":"Glenrothes",
    "sg:classifiers":[
        {
            "category":"Government",
            "subcategory":"Police Station",
            "type":"Public Place"
        }
    ],
    "sg:phone":"+44 1592 612004",
    "sg:postcode":"KY7 5LY",
    "sg:province":"Fife",
    "sg:tags":[
        "officer",
        "sheriff"
    ],
    "wof:name":"Alex M Adamson",
    "wof:placetype":"venue"
},
  "geometry": {"coordinates":[-3.173744,56.197208],"type":"Point"}
}