{
  "type": "Feature",
  "properties": {
    "iso:country":"GB",
    "sg:address":"63 Micklehome Drive",
    "sg:city":"Burton-on-trent",
    "sg:classifiers":[
        {
            "category":"Real Estate",
            "subcategory":"Architect",
            "type":"Services"
        }
    ],
    "sg:phone":"+44 1283 792962",
    "sg:postcode":"DE13 7AU",
    "sg:province":"Derbyshire",
    "wof:name":"David Evans",
    "wof:placetype":"venue"
},
  "geometry": {"coordinates":[-1.74073,52.733692],"type":"Point"}
}