{
  "type": "Feature",
  "properties": {
    "iso:country":"GB",
    "sg:address":"10 Vernon Place, Northern Court",
    "sg:city":"Nottingham",
    "sg:classifiers":[
        {
            "category":"Professional",
            "subcategory":"Engineering",
            "type":"Services"
        }
    ],
    "sg:phone":"+44 115 976 1866",
    "sg:postcode":"NG6 0DE",
    "sg:province":"Nottinghamshire",
    "wof:name":"Castwell Services",
    "wof:placetype":"venue"
},
  "geometry": {"coordinates":[-1.178655,52.98299],"type":"Point"}
}