{
  "type": "Feature",
  "properties": {
    "addr:full":"18 Shottskirk Road Shotts North Lanarkshire ML7 4AB",
    "addr:housenumber":"18",
    "addr:postcode":"ml7 4ab",
    "addr:street":"Shottskirk Road",
    "iso:country":"GB",
    "sg:address":"18 Shottskirk Road",
    "sg:city":"Shotts",
    "sg:classifiers":[
        {
            "category":"Shopping",
            "subcategory":"Thrift Store",
            "type":"Retail Goods"
        }
    ],
    "sg:phone":"+44 1501 822931",
    "sg:postcode":"ML7 4AB",
    "sg:province":"North Lanarkshire",
    "sg:tags":[
        "shop",
        "charity"
    ],
    "wof:name":"Barnardo's",
    "wof:placetype":"venue"
},
  "geometry": {"coordinates":[-3.8075470924,55.8205490112],"type":"Point"}
}