{
  "type": "Feature",
  "properties": {
    "addr:full":"122 High Street, Eckington Sheffield Derbyshire S21 4DR",
    "addr:housenumber":"122",
    "addr:postcode":"s21 4dr",
    "addr:street":"High Street",
    "iso:country":"GB",
    "sg:address":"122 High Street, Eckington",
    "sg:city":"Sheffield",
    "sg:classifiers":[
        {
            "category":"Autos & Motor Vehicles",
            "subcategory":"Auto Supplies",
            "type":"Retail Goods"
        },
        {
            "category":"Shopping",
            "type":"Retail Goods"
        }
    ],
    "sg:phone":"+44 1246 433240",
    "sg:postcode":"S21 4DR",
    "sg:province":"Derbyshire",
    "sg:tags":[
        "car",
        "part",
        "accessory"
    ],
    "wof:name":"ECKINGTON MOTOR SPARES",
    "wof:placetype":"venue"
},
  "geometry": {"coordinates":[-1.3635460138,53.3081283569],"type":"Point"}
}