{
  "type": "Feature",
  "properties": {
    "addr:full":"166 Fore Street London Greater London N18 2JB",
    "addr:housenumber":"166",
    "addr:postcode":"n18 2jb",
    "addr:street":"Fore Street",
    "iso:country":"GB",
    "sg:address":"166 Fore Street",
    "sg:city":"London",
    "sg:classifiers":[
        {
            "category":"Taxi",
            "type":"Transportation"
        }
    ],
    "sg:postcode":"N18 2JB",
    "sg:province":"Greater London",
    "sg:tags":[
        "mini",
        "cab"
    ],
    "wof:name":"Fore Cars",
    "wof:placetype":"venue"
},
  "geometry": {"coordinates":[-0.0645039976,51.6134338379],"type":"Point"}
}