{
  "type": "Feature",
  "properties": {
    "addr:full":"Mercer Ho, Swan Rd Harrogate North Yorkshire HG1 2SA",
    "addr:postcode":"hg1 2sa",
    "addr:street":"Swan Rd",
    "iso:country":"GB",
    "sg:address":"Mercer Ho, Swan Rd",
    "sg:city":"Harrogate",
    "sg:classifiers":[
        {
            "category":"Building & Trades",
            "subcategory":"Landscaping Services",
            "type":"Services"
        }
    ],
    "sg:postcode":"HG1 2SA",
    "sg:province":"North Yorkshire",
    "sg:tags":[
        "horticultural",
        "consultant"
    ],
    "wof:name":"Sykes International Ltd",
    "wof:placetype":"venue"
},
  "geometry": {"coordinates":[-1.544524,53.99469],"type":"Point"}
}