{
  "type": "Feature",
  "properties": {
    "addr:full":"Clyde Street Aberdeen Aberdeen City AB11 5QG",
    "addr:postcode":"ab11 5qg",
    "addr:street":"Clyde Street",
    "iso:country":"GB",
    "sg:address":"Clyde Street",
    "sg:city":"Aberdeen",
    "sg:classifiers":[
        {
            "category":"Food & Beverages",
            "subcategory":"Meat & Fish",
            "type":"Retail Goods"
        }
    ],
    "sg:phone":"+44 1224 591607",
    "sg:postcode":"AB11 5QG",
    "sg:province":"Aberdeen City",
    "sg:tags":[
        "merchant"
    ],
    "wof:name":"Coupers Seafoods",
    "wof:placetype":"venue"
},
  "geometry": {"coordinates":[-2.0889840126,57.141456604],"type":"Point"}
}