{
  "type": "Feature",
  "properties": {
    "addr:full":"2 Buxton Road, Hazel Grove Stockport Cheshire SK7 6AD",
    "addr:housenumber":"2",
    "addr:postcode":"sk7 6ad",
    "addr:street":"Buxton Road",
    "iso:country":"GB",
    "sg:address":"2 Buxton Road, Hazel Grove",
    "sg:city":"Stockport",
    "sg:classifiers":[
        {
            "category":"Bars & Pubs",
            "type":"Food & Drink"
        }
    ],
    "sg:phone":"+44 161 483 2168",
    "sg:postcode":"SK7 6AD",
    "sg:province":"Cheshire",
    "sg:tags":[
        "pubs",
        "inn"
    ],
    "wof:name":"The Rising Sun",
    "wof:placetype":"venue"
},
  "geometry": {"coordinates":[-2.113018,53.375172],"type":"Point"}
}