{
  "type": "Feature",
  "properties": {
    "addr:full":"55 Havant Road Portsmouth Hampshire PO2 7HH",
    "addr:housenumber":"55",
    "addr:postcode":"hampshire po2 7hh",
    "addr:street":"Havant Road",
    "iso:country":"GB",
    "sg:address":"55 Havant Road",
    "sg:city":"Portsmouth",
    "sg:classifiers":[
        {
            "category":"Retail",
            "subcategory":"Auto Repair",
            "type":"Services"
        }
    ],
    "sg:phone":"+44 23 9236 6477",
    "sg:postcode":"PO2 7HH",
    "sg:province":"Hampshire",
    "sg:tags":[
        "modification",
        "garage"
    ],
    "wof:name":"H E L Motors",
    "wof:placetype":"venue"
},
  "geometry": {"coordinates":[-1.078719,50.813473],"type":"Point"}
}