{
  "type": "Feature",
  "properties": {
    "addr:full":"1 Fisher Street Carlisle Cumbria CA3 8RR",
    "addr:housenumber":"1",
    "addr:postcode":"ca3 8rr",
    "addr:street":"Fisher Street",
    "iso:country":"GB",
    "sg:address":"1 Fisher Street",
    "sg:city":"Carlisle",
    "sg:classifiers":[
        {
            "category":"Government",
            "subcategory":"Office",
            "type":"Public Place"
        },
        {
            "category":"Organizations",
            "subcategory":"Non-profit Organization",
            "type":"Services"
        }
    ],
    "sg:phone":"+44 1228 595656",
    "sg:postcode":"CA3 8RR",
    "sg:province":"Cumbria",
    "sg:tags":[
        "organisation",
        "central",
        "voluntary",
        "charity"
    ],
    "wof:name":"Mencap",
    "wof:placetype":"venue"
},
  "geometry": {"coordinates":[-2.9385530949,54.8964767456],"type":"Point"}
}