{
  "type": "Feature",
  "properties": {
    "addr:full":"Avon Mill Lane Bristol City of Bristol BS31 2UG",
    "addr:postcode":"bs31 2ug",
    "addr:street":"Avon Mill Lane",
    "iso:country":"GB",
    "sg:address":"Avon Mill Lane",
    "sg:city":"Bristol",
    "sg:classifiers":[
        {
            "category":"Restaurant",
            "type":"Food & Drink"
        }
    ],
    "sg:phone":"+44 117 986 7280",
    "sg:postcode":"BS31 2UG",
    "sg:province":"City of Bristol",
    "wof:name":"Brassmill The",
    "wof:placetype":"venue"
},
  "geometry": {"coordinates":[-2.492980957,51.4171447754],"type":"Point"}
}