{
  "type": "Feature",
  "properties": {
    "addr:full":"The Street Fleet Hampshire GU51 5SG",
    "addr:postcode":"gu51 5sg",
    "addr:street":"The Street",
    "iso:country":"GB",
    "sg:address":"The Street",
    "sg:city":"Fleet",
    "sg:classifiers":[
        {
            "category":"Shopping",
            "subcategory":"Department Store",
            "type":"Retail Goods"
        }
    ],
    "sg:phone":"+44 1252 615832",
    "sg:postcode":"GU51 5SG",
    "sg:province":"Hampshire",
    "wof:name":"Crookham Village Stores",
    "wof:placetype":"venue"
},
  "geometry": {"coordinates":[-0.8556249738,51.2651748657],"type":"Point"}
}