{
  "type": "Feature",
  "properties": {
    "iso:country":"GB",
    "sg:address":"Haywards Heath Road, Balcombe",
    "sg:city":"Haywards Heath",
    "sg:classifiers":[
        {
            "category":"Professional",
            "type":"Services"
        },
        {
            "category":"Professional",
            "subcategory":"Art Services",
            "type":"Services"
        }
    ],
    "sg:postcode":"RH17 6PE",
    "sg:province":"East Sussex",
    "sg:tags":[
        "interior",
        "furnishers",
        "designer"
    ],
    "wof:name":"English Interiors",
    "wof:placetype":"venue"
},
  "geometry": {"coordinates":[-0.127648,51.057617],"type":"Point"}
}