{
  "type": "Feature",
  "properties": {
    "addr:full":"497 London Road Westcliff-on-sea Essex SS0 9LG",
    "addr:housenumber":"497",
    "addr:postcode":"ss0 9lg",
    "addr:street":"London Road",
    "iso:country":"GB",
    "sg:address":"497 London Road",
    "sg:city":"Westcliff-on-sea",
    "sg:classifiers":[
        {
            "category":"Retail",
            "subcategory":"Auto Repair",
            "type":"Services"
        }
    ],
    "sg:phone":"+44 1702 348055",
    "sg:postcode":"SS0 9LG",
    "sg:province":"Essex",
    "sg:tags":[
        "modification",
        "garage"
    ],
    "wof:name":"Crescent Autos",
    "wof:placetype":"venue"
},
  "geometry": {"coordinates":[0.690135,51.54454],"type":"Point"}
}