{
  "type": "Feature",
  "properties": {
    "iso:country":"GB",
    "sg:address":"40 Main St",
    "sg:city":"Nottingham",
    "sg:classifiers":[
        {
            "category":"Shopping",
            "subcategory":"Florist",
            "type":"Retail Goods"
        }
    ],
    "sg:phone":"+44 115 938 3169",
    "sg:postcode":"NG16 2LY",
    "sg:province":"Derbyshire",
    "wof:name":"Barbara's",
    "wof:placetype":"venue"
},
  "geometry": {"coordinates":[-1.282544,52.993317],"type":"Point"}
}