{
  "type": "Feature",
  "properties": {
    "iso:country":"GB",
    "sg:address":"Pendower House, Northumberland Road",
    "sg:city":"Southsea",
    "sg:classifiers":[
        {
            "category":"Professional",
            "subcategory":"Management & Consulting",
            "type":"Services"
        }
    ],
    "sg:postcode":"PO5 1DS",
    "sg:province":"Hampshire",
    "sg:tags":[
        "consultant",
        "business"
    ],
    "wof:name":"Business Conversion Ltd",
    "wof:placetype":"venue"
},
  "geometry": {"coordinates":[-1.078366,50.795933],"type":"Point"}
}