{
  "type": "Feature",
  "properties": {
    "iso:country":"GB",
    "sg:address":"81 Townhill Road",
    "sg:city":"Dunfermline",
    "sg:classifiers":[
        {
            "category":"Food & Beverages",
            "subcategory":"Supermarket",
            "type":"Retail Goods"
        },
        {
            "category":"Food & Beverages",
            "subcategory":"Fruits & Vegetables",
            "type":"Retail Goods"
        }
    ],
    "sg:postcode":"KY12 0BN",
    "sg:province":"Fife",
    "sg:tags":[
        "greengrocer"
    ],
    "wof:name":"Townhill Road Stores",
    "wof:placetype":"venue"
},
  "geometry": {"coordinates":[-3.448683,56.079441],"type":"Point"}
}