{
  "type": "Feature",
  "properties": {
    "iso:country":"GB",
    "sg:address":"Heniton Hill Cottage, Ashbrittle",
    "sg:city":"Wellington",
    "sg:classifiers":[
        {
            "category":"Building & Trades",
            "subcategory":"Plumbing",
            "type":"Services"
        }
    ],
    "sg:phone":"+44 1398 361469",
    "sg:postcode":"TA21 0LH",
    "sg:province":"Devon",
    "sg:tags":[
        "heating"
    ],
    "wof:name":"John Davey Boiler Specialist",
    "wof:placetype":"venue"
},
  "geometry": {"coordinates":[-3.355814,50.984344],"type":"Point"}
}