{
  "type": "Feature",
  "properties": {
    "addr:full":"Burway Trading Estate, Bromfield Rd Ludlow Herefordshire SY8 1EN",
    "addr:postcode":"sy8 1en",
    "addr:street":"Bromfield Rd",
    "iso:country":"GB",
    "sg:address":"Burway Trading Estate, Bromfield Rd",
    "sg:city":"Ludlow",
    "sg:classifiers":[
        {
            "category":"Autos & Motor Vehicles",
            "subcategory":"Automobile Sales",
            "type":"Retail Goods"
        }
    ],
    "sg:phone":"+44 1584 878444",
    "sg:postcode":"SY8 1EN",
    "sg:province":"Herefordshire",
    "sg:tags":[
        "commercial"
    ],
    "wof:name":"Adam V Neath",
    "wof:placetype":"venue"
},
  "geometry": {"coordinates":[-2.7190139294,52.3705940247],"type":"Point"}
}