{
  "type": "Feature",
  "properties": {
    "addr:full":"15 Knightrider Street Maidstone Kent ME15 6LP",
    "addr:housenumber":"15",
    "addr:postcode":"me15 6lp",
    "addr:street":"Knightrider Street",
    "iso:country":"GB",
    "sg:address":"15 Knightrider Street",
    "sg:city":"Maidstone",
    "sg:classifiers":[
        {
            "category":"Autos & Motor Vehicles",
            "subcategory":"Automobile Sales",
            "type":"Retail Goods"
        }
    ],
    "sg:phone":"+44 1622 690757",
    "sg:postcode":"ME15 6LP",
    "sg:province":"Kent",
    "sg:tags":[
        "car"
    ],
    "wof:name":"E & M Cars",
    "wof:placetype":"venue"
},
  "geometry": {"coordinates":[0.5245710015,51.2702980042],"type":"Point"}
}