{
  "type": "Feature",
  "properties": {
    "iso:country":"GB",
    "sg:address":"Isdn Business Unit, 3 Meridian House, Winsford Industrial Estate",
    "sg:city":"Winsford",
    "sg:classifiers":[
        {
            "category":"Communications",
            "type":"Services"
        }
    ],
    "sg:phone":"+44 1606 557559",
    "sg:postcode":"CW7 3QG",
    "sg:province":"Cheshire",
    "sg:tags":[
        "data",
        "network"
    ],
    "wof:name":"Accoda Ltd.",
    "wof:placetype":"venue"
},
  "geometry": {"coordinates":[-2.489659071,53.1973762512],"type":"Point"}
}