{
  "type": "Feature",
  "properties": {
    "iso:country":"GB",
    "sg:address":"Ssi Ho, Fordbrook Business Center, Marlborough Rd",
    "sg:city":"Pewsey",
    "sg:classifiers":[
        {
            "category":"Professional",
            "type":"Services"
        }
    ],
    "sg:phone":"+44 1672 562576",
    "sg:postcode":"SN9 5NU",
    "sg:province":"Wiltshire",
    "sg:tags":[
        "entertainer"
    ],
    "wof:name":"Impact Production",
    "wof:placetype":"venue"
},
  "geometry": {"coordinates":[-1.762319,51.340286],"type":"Point"}
}