{
  "type": "Feature",
  "properties": {
    "iso:country":"GB",
    "sg:address":"37a Outram Street",
    "sg:city":"Sutton-in-ashfield",
    "sg:classifiers":[
        {
            "category":"Professional",
            "subcategory":"Detective & Security Services",
            "type":"Services"
        }
    ],
    "sg:postcode":"NG17 4BA",
    "sg:province":"Nottinghamshire",
    "wof:name":"Davin Hulme Security Dogs",
    "wof:placetype":"venue"
},
  "geometry": {"coordinates":[-1.258835,53.126606],"type":"Point"}
}