{
  "type": "Feature",
  "properties": {
    "iso:country":"GB",
    "sg:address":"29 Forth Street",
    "sg:city":"Edinburgh",
    "sg:classifiers":[
        {
            "category":"Organizations",
            "subcategory":"Non-profit Organization",
            "type":"Services"
        }
    ],
    "sg:phone":"+44 131 556 6598",
    "sg:postcode":"EH1 3LE",
    "sg:province":"City of Edinburgh",
    "sg:tags":[
        "organisation",
        "voluntary",
        "charity"
    ],
    "wof:name":"National Union of Students Scotland",
    "wof:placetype":"venue"
},
  "geometry": {"coordinates":[-3.18623,55.957916],"type":"Point"}
}