{
  "type": "Feature",
  "properties": {
    "iso:country":"GB",
    "sg:address":"30 Wellsway",
    "sg:city":"Bath",
    "sg:classifiers":[
        {
            "category":"Food & Beverages",
            "subcategory":"Bakery",
            "type":"Retail Goods"
        }
    ],
    "sg:phone":"+44 1225 482372",
    "sg:postcode":"BA2 2AA",
    "sg:province":"Somerset",
    "sg:tags":[
        "baker"
    ],
    "wof:name":"Mountstevens Ltd.",
    "wof:placetype":"venue"
},
  "geometry": {"coordinates":[-2.366667,51.372887],"type":"Point"}
}