{
  "type": "Feature",
  "properties": {
    "iso:country":"GB",
    "sg:address":"3 Laurel Bank",
    "sg:city":"Dingwall",
    "sg:classifiers":[
        {
            "category":"Professional",
            "subcategory":"Art Services",
            "type":"Services"
        },
        {
            "category":"Building & Trades",
            "subcategory":"Construction",
            "type":"Services"
        }
    ],
    "sg:phone":"+44 1349 861078",
    "sg:postcode":"IV15 9NE",
    "sg:province":"Highland",
    "sg:tags":[
        "decorator",
        "painter"
    ],
    "wof:name":"Lenny Crossley",
    "wof:placetype":"venue"
},
  "geometry": {"coordinates":[-4.431448,57.59618],"type":"Point"}
}