{
  "type": "Feature",
  "properties": {
    "iso:country":"GB",
    "sg:address":"1a West Way",
    "sg:city":"Orpington",
    "sg:classifiers":[
        {
            "category":"Health Services",
            "subcategory":"Dentist",
            "type":"Services"
        }
    ],
    "sg:phone":"+44 1689 831814",
    "sg:postcode":"BR5 1LN",
    "sg:province":"Kent",
    "wof:name":"Adams House Dental Surgery",
    "wof:placetype":"venue"
},
  "geometry": {"coordinates":[0.0736320019,51.3886985779],"type":"Point"}
}