{
  "type": "Feature",
  "properties": {
    "iso:country":"GB",
    "sg:address":"3 Gillygate",
    "sg:city":"York",
    "sg:classifiers":[
        {
            "category":"Shopping",
            "subcategory":"Party Supplies",
            "type":"Retail Goods"
        }
    ],
    "sg:phone":"+44 1904 630317",
    "sg:postcode":"YO3 7EA",
    "sg:province":"East Riding of Yorkshire",
    "sg:tags":[
        "novelty"
    ],
    "wof:name":"Kaos Fab",
    "wof:placetype":"venue"
},
  "geometry": {"coordinates":[-1.085488,53.963165],"type":"Point"}
}