{
  "type": "Feature",
  "properties": {
    "addr:full":"11 Lobelia Clo Newcastle Upon Tyne Tyne and Wear NE5 1UT",
    "addr:housenumber":"11",
    "addr:postcode":"ne5 1ut",
    "addr:street":"Lobelia Clo",
    "iso:country":"GB",
    "sg:address":"11 Lobelia Clo",
    "sg:city":"Newcastle Upon Tyne",
    "sg:classifiers":[
        {
            "category":"Building & Trades",
            "subcategory":"Construction",
            "type":"Services"
        }
    ],
    "sg:phone":"+44 191 264 4209",
    "sg:postcode":"NE5 1UT",
    "sg:province":"Tyne and Wear",
    "sg:tags":[
        "decorator",
        "painter"
    ],
    "wof:name":"W E Wallis",
    "wof:placetype":"venue"
},
  "geometry": {"coordinates":[-1.7205079794,55.0015907288],"type":"Point"}
}