{
  "type": "Feature",
  "properties": {
    "iso:country":"GB",
    "sg:address":"8 Grand Parade, Upper Richmond Road West",
    "sg:city":"London",
    "sg:classifiers":[
        {
            "category":"Professional",
            "subcategory":"Art Services",
            "type":"Services"
        }
    ],
    "sg:phone":"+44 20 8876 1740",
    "sg:postcode":"SW14 7PR",
    "sg:province":"Greater London",
    "sg:tags":[
        "photographer"
    ],
    "wof:name":"Pictorials",
    "wof:placetype":"venue"
},
  "geometry": {"coordinates":[-0.2711299956,51.4640617371],"type":"Point"}
}