{
  "type": "Feature",
  "properties": {
    "iso:country":"GB",
    "sg:address":"North Forty Foot Bank, Boston West",
    "sg:city":"Boston",
    "sg:classifiers":[
        {
            "category":"Farming",
            "subcategory":"Farm",
            "type":"Manufacturing & Wholesale Goods"
        }
    ],
    "sg:phone":"+44 1205 362141",
    "sg:postcode":"PE21 8JS",
    "sg:province":"Lincolnshire",
    "sg:tags":[
        "mixed",
        "crop"
    ],
    "wof:name":"Pocklington Estates Ltd.",
    "wof:placetype":"venue"
},
  "geometry": {"coordinates":[-0.048669,52.982056],"type":"Point"}
}