{
  "type": "Feature",
  "properties": {
    "iso:country":"GB",
    "sg:address":"Bucknall Road",
    "sg:city":"Stoke-on-trent",
    "sg:classifiers":[
        {
            "category":"Bars & Pubs",
            "type":"Food & Drink"
        }
    ],
    "sg:phone":"+44 1782 213123",
    "sg:postcode":"ST1 6AJ",
    "sg:province":"Staffordshire",
    "sg:tags":[
        "pubs",
        "inn"
    ],
    "wof:name":"New Finney Gardens",
    "wof:placetype":"venue"
},
  "geometry": {"coordinates":[-2.160099,53.024994],"type":"Point"}
}