{
  "type": "Feature",
  "properties": {
    "iso:country":"GB",
    "sg:address":"11-13 Nutter Rd",
    "sg:city":"Thornton Cleveleys",
    "sg:classifiers":[
        {
            "category":"Social Services",
            "subcategory":"Retirement Home",
            "type":"Services"
        }
    ],
    "sg:phone":"+44 1253 855132",
    "sg:postcode":"FY5 1BG",
    "sg:province":"Lancashire",
    "sg:tags":[
        "rest"
    ],
    "wof:name":"Dewsbury House",
    "wof:placetype":"venue"
},
  "geometry": {"coordinates":[-3.042152,53.877754],"type":"Point"}
}