{
  "type": "Feature",
  "properties": {
    "iso:country":"GB",
    "sg:address":"11 St Marys Street",
    "sg:city":"Wallingford",
    "sg:classifiers":[
        {
            "category":"Banks & Credit Unions",
            "subcategory":"Financial Services",
            "type":"Services"
        }
    ],
    "sg:postcode":"OX10 0EL",
    "sg:province":"Oxfordshire",
    "sg:tags":[
        "consultant"
    ],
    "wof:name":"Group Plc Radnor",
    "wof:placetype":"venue"
},
  "geometry": {"coordinates":[-1.124358,51.600037],"type":"Point"}
}