{
  "type": "Feature",
  "properties": {
    "iso:country":"GB",
    "sg:address":"12a The Centre, Church Road, Tiptree",
    "sg:city":"Colchester",
    "sg:classifiers":[
        {
            "category":"Professional",
            "subcategory":"Management & Consulting",
            "type":"Services"
        }
    ],
    "sg:postcode":"CO5 0HF",
    "sg:province":"Essex",
    "sg:tags":[
        "consultant",
        "business",
        "marketing"
    ],
    "wof:name":"Chris Proffitt Associates",
    "wof:placetype":"venue"
},
  "geometry": {"coordinates":[0.7504050136,51.810760498],"type":"Point"}
}