{
  "type": "Feature",
  "properties": {
    "addr:full":"91 Hamilton Place Aberdeen Aberdeen City AB15 5BU",
    "addr:housenumber":"91",
    "addr:postcode":"ab15 5bu",
    "addr:street":"Hamilton Place",
    "iso:country":"GB",
    "sg:address":"91 Hamilton Place",
    "sg:city":"Aberdeen",
    "sg:classifiers":[
        {
            "category":"Recreation",
            "type":"Entertainment"
        }
    ],
    "sg:postcode":"AB15 5BU",
    "sg:province":"Aberdeen City",
    "sg:tags":[
        "corporate",
        "leisure"
    ],
    "wof:name":"Purple Promotions Ltd.",
    "wof:placetype":"venue"
},
  "geometry": {"coordinates":[-2.1305150986,57.1465377808],"type":"Point"}
}