{
  "type": "Feature",
  "properties": {
    "iso:country":"GB",
    "sg:address":"The Grange, Cotham Lane",
    "sg:city":"Newark",
    "sg:classifiers":[
        {
            "category":"Home & Garden",
            "subcategory":"Carpets & Floor Coverings",
            "type":"Retail Goods"
        }
    ],
    "sg:phone":"+44 1636 700336",
    "sg:postcode":"NG24 3RJ",
    "sg:province":"Nottinghamshire",
    "sg:tags":[
        "case",
        "crate",
        "pallets"
    ],
    "wof:name":"Premier Supplies Ltd.",
    "wof:placetype":"venue"
},
  "geometry": {"coordinates":[-0.7987589836,53.0338897705],"type":"Point"}
}