{
  "type": "Feature",
  "properties": {
    "addr:full":"North Rd Durham Durham DH1 4UE",
    "addr:postcode":"dh1 4ue",
    "addr:street":"North Rd",
    "iso:country":"GB",
    "sg:address":"North Rd",
    "sg:city":"Durham",
    "sg:classifiers":[
        {
            "category":"Health Services",
            "subcategory":"Dentist",
            "type":"Services"
        }
    ],
    "sg:phone":"+44 191 386 6300",
    "sg:postcode":"DH1 4UE",
    "sg:province":"Durham",
    "wof:name":"B Asslack",
    "wof:placetype":"venue"
},
  "geometry": {"coordinates":[-1.583869,54.778557],"type":"Point"}
}