{
  "type": "Feature",
  "properties": {
    "addr:full":"18 St Marys Gro Richmond Greater London TW9 1UY",
    "addr:housenumber":"18",
    "addr:postcode":"tw9 1uy",
    "addr:street":"St",
    "iso:country":"GB",
    "sg:address":"18 St Marys Gro",
    "sg:city":"Richmond",
    "sg:classifiers":[
        {
            "category":"Home & Garden",
            "subcategory":"Home Furnishings",
            "type":"Retail Goods"
        }
    ],
    "sg:phone":"+44 20 8940 4850",
    "sg:postcode":"TW9 1UY",
    "sg:province":"Greater London",
    "sg:tags":[
        "wall",
        "wallpaper",
        "covering"
    ],
    "wof:name":"Hamilton Weston Wallpapers Ltd.",
    "wof:placetype":"venue"
},
  "geometry": {"coordinates":[-0.2913559973,51.4629440308],"type":"Point"}
}