{
  "type": "Feature",
  "properties": {
    "iso:country":"GB",
    "sg:address":"79 Commercial Street",
    "sg:city":"Newport",
    "sg:classifiers":[
        {
            "category":"Fast Food",
            "type":"Food & Drink"
        },
        {
            "category":"Food & Beverages",
            "subcategory":"Groceries & Convenience Stores",
            "type":"Retail Goods"
        }
    ],
    "sg:phone":"+44 1633 259518",
    "sg:postcode":"NP20 1LR",
    "sg:province":"Newport",
    "sg:tags":[
        "shop",
        "fish",
        "take",
        "chip",
        "away"
    ],
    "wof:name":"Golden Kitchen",
    "wof:placetype":"venue"
},
  "geometry": {"coordinates":[-2.992973,51.583721],"type":"Point"}
}