{
  "type": "Feature",
  "properties": {
    "addr:full":"10 Mitre Place South Shields Tyne and Wear NE33 5TB",
    "addr:housenumber":"10",
    "addr:postcode":"ne33 5tb",
    "addr:street":"Mitre Place",
    "iso:country":"GB",
    "sg:address":"10 Mitre Place",
    "sg:city":"South Shields",
    "sg:classifiers":[
        {
            "category":"Retail",
            "subcategory":"Auto Repair",
            "type":"Services"
        }
    ],
    "sg:phone":"+44 191 455 1622",
    "sg:postcode":"NE33 5TB",
    "sg:province":"Tyne and Wear",
    "sg:tags":[
        "electrician"
    ],
    "wof:name":"Rippon Auto Electrics",
    "wof:placetype":"venue"
},
  "geometry": {"coordinates":[-1.445333,54.981804],"type":"Point"}
}