{
  "type": "Feature",
  "properties": {
    "iso:country":"GB",
    "sg:address":"3 Benbridge Indust Est, Holloway Rd",
    "sg:city":"Maldon",
    "sg:classifiers":[
        {
            "category":"Sports & Exercise",
            "subcategory":"Race Track",
            "type":"Entertainment"
        }
    ],
    "sg:phone":"+44 1621 851981",
    "sg:postcode":"CM9 4ER",
    "sg:province":"Essex",
    "sg:tags":[
        "motor"
    ],
    "wof:name":"Blue-Sprint Motor Sports Ltd",
    "wof:placetype":"venue"
},
  "geometry": {"coordinates":[0.675249,51.731377],"type":"Point"}
}