{
  "type": "Feature",
  "properties": {
    "addr:full":"Keighley Business Centre, Unit S1 Knowle Mill South Street Keighley West Yorkshire BD21 1AG",
    "addr:housenumber":"unit s1",
    "addr:postcode":"bd21 1ag",
    "addr:street":"Keighley;Knowle Mill South Street",
    "iso:country":"GB",
    "sg:address":"Keighley Business Centre, Unit S1 Knowle Mill South Street",
    "sg:city":"Keighley",
    "sg:classifiers":[
        {
            "category":"Shopping",
            "subcategory":"Clothing, Apparel, & Fashions",
            "type":"Retail Goods"
        }
    ],
    "sg:phone":"+44 1535 667625",
    "sg:postcode":"BD21 1AG",
    "sg:province":"West Yorkshire",
    "sg:tags":[
        "clothing",
        "fabric"
    ],
    "wof:name":"Work in Style Ltd.",
    "wof:placetype":"venue"
},
  "geometry": {"coordinates":[-1.909674,53.866364],"type":"Point"}
}