{
  "type": "Feature",
  "properties": {
    "iso:country":"GB",
    "sg:address":"173 Broadway Lane",
    "sg:city":"Bournemouth",
    "sg:classifiers":[
        {
            "category":"Building & Trades",
            "subcategory":"Construction",
            "type":"Services"
        }
    ],
    "sg:phone":"+44 1202 532964",
    "sg:postcode":"BH8 0AD",
    "sg:province":"Dorset",
    "sg:tags":[
        "decorator",
        "painter"
    ],
    "wof:name":"Averil Decor",
    "wof:placetype":"venue"
},
  "geometry": {"coordinates":[-1.850758,50.76128],"type":"Point"}
}