{
  "type": "Feature",
  "properties": {
    "iso:country":"GB",
    "sg:address":"27-30 Devonshire Square",
    "sg:city":"Loughborough",
    "sg:classifiers":[
        {
            "category":"Food & Beverages",
            "subcategory":"Supermarket",
            "type":"Retail Goods"
        }
    ],
    "sg:phone":"+44 1509 215483",
    "sg:postcode":"LE11 3DW",
    "sg:province":"Leicestershire",
    "wof:name":"Tesco Stores Ltd.",
    "wof:placetype":"venue"
},
  "geometry": {"coordinates":[-1.20734,52.769718],"type":"Point"}
}