{
  "type": "Feature",
  "properties": {
    "addr:full":"24 Hastings Road Bexhill-on-sea East Sussex TN40 2HH",
    "addr:housenumber":"24",
    "addr:postcode":"tn40 2hh",
    "addr:street":"Hastings Road",
    "iso:country":"GB",
    "sg:address":"24 Hastings Road",
    "sg:city":"Bexhill-on-sea",
    "sg:classifiers":[
        {
            "category":"Health Services",
            "subcategory":"Nursing And Care Facility",
            "type":"Services"
        }
    ],
    "sg:phone":"+44 1424 213532",
    "sg:postcode":"TN40 2HH",
    "sg:province":"East Sussex",
    "sg:tags":[
        "home"
    ],
    "wof:name":"Ancaster Court",
    "wof:placetype":"venue"
},
  "geometry": {"coordinates":[0.484656,50.847721],"type":"Point"}
}