{
  "type": "Feature",
  "properties": {
    "addr:full":"72 Costa Street, South Bank Middlesbrough North Yorkshire TS6 6EU",
    "addr:housenumber":"72",
    "addr:postcode":"ts6 6eu",
    "addr:street":"Costa Street",
    "iso:country":"GB",
    "sg:address":"72 Costa Street, South Bank",
    "sg:city":"Middlesbrough",
    "sg:classifiers":[
        {
            "category":"Organizations",
            "subcategory":"Non-profit Organization",
            "type":"Services"
        }
    ],
    "sg:phone":"+44 1642 465118",
    "sg:postcode":"TS6 6EU",
    "sg:province":"North Yorkshire",
    "sg:tags":[
        "charitable",
        "organisation",
        "voluntary",
        "charity"
    ],
    "wof:name":"G A S P",
    "wof:placetype":"venue"
},
  "geometry": {"coordinates":[-1.18165,54.57782],"type":"Point"}
}