{
  "type": "Feature",
  "properties": {
    "iso:country":"GB",
    "sg:address":"53 New Road, Hethersett",
    "sg:city":"Norwich",
    "sg:classifiers":[
        {
            "category":"Retail",
            "subcategory":"Repair Shop",
            "type":"Services"
        },
        {
            "category":"Shopping",
            "subcategory":"Antiques",
            "type":"Retail Goods"
        }
    ],
    "sg:phone":"+44 1603 812008",
    "sg:postcode":"NR9 3HJ",
    "sg:province":"Norfolk",
    "sg:tags":[
        "restoration"
    ],
    "wof:name":"Alma Antique Restorers",
    "wof:placetype":"venue"
},
  "geometry": {"coordinates":[1.16613,52.596413],"type":"Point"}
}