{
  "type": "Feature",
  "properties": {
    "iso:country":"GB",
    "sg:address":"Suite 3, Dudley House",
    "sg:city":"Bracknell",
    "sg:classifiers":[
        {
            "category":"Professional",
            "subcategory":"Lawyer & Legal Services",
            "type":"Services"
        }
    ],
    "sg:phone":"+44 1344 456565",
    "sg:postcode":"RG12 1LL",
    "sg:province":"Berkshire",
    "sg:tags":[
        "solicitor"
    ],
    "wof:name":"L S I Sales Ltd.",
    "wof:placetype":"venue"
},
  "geometry": {"coordinates":[-0.75205,51.416981],"type":"Point"}
}