{
  "type": "Feature",
  "properties": {
    "addr:full":"First Floor Aylesbury Buckinghamshire HP20 2LQ",
    "addr:postcode":"hp20 2lq",
    "iso:country":"GB",
    "sg:address":"First Floor",
    "sg:city":"Aylesbury",
    "sg:classifiers":[
        {
            "category":"Professional",
            "subcategory":"Computer Services",
            "type":"Services"
        }
    ],
    "sg:phone":"+44 1296 398469",
    "sg:postcode":"HP20 2LQ",
    "sg:province":"Buckinghamshire",
    "sg:tags":[
        "system",
        "software"
    ],
    "wof:name":"Haydon Training Services Ltd.",
    "wof:placetype":"venue"
},
  "geometry": {"coordinates":[-0.811864,51.818779],"type":"Point"}
}