{
  "type": "Feature",
  "properties": {
    "iso:country":"GB",
    "sg:address":"Sunny Croft South Street, Normanton On Trent",
    "sg:city":"Newark",
    "sg:classifiers":[
        {
            "category":"Recreation",
            "type":"Entertainment"
        }
    ],
    "sg:phone":"+44 1636 821828",
    "sg:postcode":"NG23 6RQ",
    "sg:province":"Lincolnshire",
    "sg:tags":[
        "snooker",
        "billiards",
        "pool"
    ],
    "wof:name":"A C Gibson",
    "wof:placetype":"venue"
},
  "geometry": {"coordinates":[-0.816628,53.208183],"type":"Point"}
}