{
  "type": "Feature",
  "properties": {
    "iso:country":"GB",
    "sg:address":"P O Box 1160",
    "sg:city":"Bristol",
    "sg:classifiers":[
        {
            "category":"Manufacturing",
            "subcategory":"Wood Products",
            "type":"Manufacturing & Wholesale Goods"
        }
    ],
    "sg:phone":"+44 117 956 9089",
    "sg:postcode":"BS39 4JL",
    "sg:province":"Somerset",
    "sg:tags":[
        "packaging",
        "crate",
        "pallets"
    ],
    "wof:name":"Kingswood Packaging",
    "wof:placetype":"venue"
},
  "geometry": {"coordinates":[-2.5537490845,51.3702392578],"type":"Point"}
}