{
  "type": "Feature",
  "properties": {
    "iso:country":"GB",
    "sg:address":"The Coach House, Hafod Y Llan, Nant Gwynant",
    "sg:city":"Caernarfon",
    "sg:classifiers":[
        {
            "category":"Government",
            "subcategory":"Office",
            "type":"Public Place"
        },
        {
            "category":"Education",
            "subcategory":"University",
            "type":"Public Place"
        },
        {
            "category":"Recreation",
            "type":"Entertainment"
        }
    ],
    "sg:phone":"+44 1766 890369",
    "sg:postcode":"LL55 1BH",
    "sg:province":"Gwynedd",
    "sg:tags":[
        "outdoor",
        "agency",
        "authority",
        "pursuit"
    ],
    "wof:name":"Herts Snowdonia Centre",
    "wof:placetype":"venue"
},
  "geometry": {"coordinates":[-4.2718091011,53.1425933838],"type":"Point"}
}