{
  "type": "Feature",
  "properties": {
    "addr:full":"Unit 3 The Standard Works, The Wells Rd Nottingham Nottinghamshire NG3 3AR",
    "addr:housenumber":"unit 3",
    "addr:postcode":"ng3 3ar",
    "addr:street":"The;The Wells Rd",
    "iso:country":"GB",
    "sg:address":"Unit 3 The Standard Works, The Wells Rd",
    "sg:city":"Nottingham",
    "sg:classifiers":[
        {
            "category":"Manufacturing",
            "subcategory":"Textiles",
            "type":"Manufacturing & Wholesale Goods"
        }
    ],
    "sg:phone":"+44 115 955 8565",
    "sg:postcode":"NG3 3AR",
    "sg:province":"Nottinghamshire",
    "sg:tags":[
        "merchant",
        "agent"
    ],
    "wof:name":"Baydex Fabrics Ltd",
    "wof:placetype":"venue"
},
  "geometry": {"coordinates":[-1.12909,52.965618],"type":"Point"}
}