{
  "type": "Feature",
  "properties": {
    "addr:full":"26 Blackfriars St Manchester Greater Manchester M3 2EG",
    "addr:housenumber":"26",
    "addr:postcode":"m3 2eg",
    "addr:street":"Blackfriars St",
    "iso:country":"GB",
    "sg:address":"26 Blackfriars St",
    "sg:city":"Manchester",
    "sg:classifiers":[
        {
            "category":"Health Services",
            "subcategory":"Dentist",
            "type":"Services"
        }
    ],
    "sg:phone":"+44 161 832 4939",
    "sg:postcode":"M3 2EG",
    "sg:province":"Greater Manchester",
    "sg:tags":[
        "technician",
        "dental"
    ],
    "wof:name":"Deansgate Dental Laboratory",
    "wof:placetype":"venue"
},
  "geometry": {"coordinates":[-2.247549057,53.4836807251],"type":"Point"}
}