{
  "type": "Feature",
  "properties": {
    "addr:full":"Darnells Farm, Linton Ross-on-wye Gloucestershire HR9 7SQ",
    "addr:postcode":"hr9 7sq",
    "iso:country":"GB",
    "sg:address":"Darnells Farm, Linton",
    "sg:city":"Ross-on-wye",
    "sg:classifiers":[
        {
            "category":"Farming",
            "subcategory":"Crops",
            "type":"Manufacturing & Wholesale Goods"
        },
        {
            "category":"Farming",
            "subcategory":"Livestock Farm",
            "type":"Manufacturing & Wholesale Goods"
        }
    ],
    "sg:phone":"+44 1989 720316",
    "sg:postcode":"HR9 7SQ",
    "sg:province":"Gloucestershire",
    "sg:tags":[
        "arable",
        "others"
    ],
    "wof:name":"C E & E J Chapman & Son",
    "wof:placetype":"venue"
},
  "geometry": {"coordinates":[-2.581733,51.916481],"type":"Point"}
}