{
  "type": "Feature",
  "properties": {
    "addr:full":"128 Bessborough Road Harrow Greater London HA1 3DQ",
    "addr:housenumber":"128",
    "addr:postcode":"ha1 3dq",
    "addr:street":"Bessborough Road",
    "iso:country":"GB",
    "sg:address":"128 Bessborough Road",
    "sg:city":"Harrow",
    "sg:classifiers":[
        {
            "category":"Autos & Motor Vehicles",
            "subcategory":"Auto Supplies",
            "type":"Retail Goods"
        },
        {
            "category":"Autos & Motor Vehicles",
            "subcategory":"Recreational Vehicle Sales",
            "type":"Retail Goods"
        }
    ],
    "sg:phone":"+44 20 8423 4073",
    "sg:postcode":"HA1 3DQ",
    "sg:province":"Greater London",
    "sg:tags":[
        "machine",
        "supplier",
        "system",
        "dictation"
    ],
    "wof:name":"Dictation Machine Services",
    "wof:placetype":"venue"
},
  "geometry": {"coordinates":[-0.3438900113,51.5741729736],"type":"Point"}
}