{
  "type": "Feature",
  "properties": {
    "iso:country":"GB",
    "sg:address":"Enterprise House, 1 Apex View",
    "sg:city":"Leeds",
    "sg:classifiers":[
        {
            "category":"Professional",
            "subcategory":"Computer Services",
            "type":"Services"
        }
    ],
    "sg:phone":"+44 113 259 5100",
    "sg:postcode":"LS11 9BH",
    "sg:province":"West Yorkshire",
    "sg:tags":[
        "system",
        "software"
    ],
    "wof:name":"Armature Ltd.",
    "wof:placetype":"venue"
},
  "geometry": {"coordinates":[-1.546075,53.787945],"type":"Point"}
}