{
  "type": "Feature",
  "properties": {
    "addr:full":"25 Rails Lane Hayling Island Hampshire PO11 9LG",
    "addr:housenumber":"25",
    "addr:postcode":"po11 9lg",
    "addr:street":"Rails Lane",
    "iso:country":"GB",
    "sg:address":"25 Rails Lane",
    "sg:city":"Hayling Island",
    "sg:classifiers":[
        {
            "category":"Government",
            "subcategory":"Post Office",
            "type":"Public Place"
        }
    ],
    "sg:phone":"+44 23 9246 2900",
    "sg:postcode":"PO11 9LG",
    "sg:province":"Hampshire",
    "wof:name":"B W Simpson Sub Post Office",
    "wof:placetype":"venue"
},
  "geometry": {"coordinates":[-0.965337,50.782585],"type":"Point"}
}