{
  "type": "Feature",
  "properties": {
    "iso:country":"GB",
    "sg:address":"Queen Ann House, 11 Charlotte Street",
    "sg:city":"Bath",
    "sg:classifiers":[
        {
            "category":"Professional",
            "subcategory":"Employment Agencies",
            "type":"Services"
        }
    ],
    "sg:phone":"+44 1225 460048",
    "sg:postcode":"BA1 2NE",
    "sg:province":"Bath and North East Somerset",
    "sg:tags":[
        "consultant"
    ],
    "wof:name":"Reed Employment",
    "wof:placetype":"venue"
},
  "geometry": {"coordinates":[-2.36602211,51.3835067749],"type":"Point"}
}