{
  "type": "Feature",
  "properties": {
    "addr:full":"York House, Fletching Street Mayfield East Sussex TN20 6TE",
    "addr:postcode":"tn20 6te",
    "addr:street":"Fletching Street",
    "iso:country":"GB",
    "sg:address":"York House, Fletching Street",
    "sg:city":"Mayfield",
    "sg:classifiers":[
        {
            "category":"Professional",
            "subcategory":"Art Services",
            "type":"Services"
        }
    ],
    "sg:postcode":"TN20 6TE",
    "sg:province":"East Sussex",
    "sg:tags":[
        "consultant",
        "design"
    ],
    "wof:name":"James Pursey Design",
    "wof:placetype":"venue"
},
  "geometry": {"coordinates":[0.2683410048,51.0214653015],"type":"Point"}
}