{
  "type": "Feature",
  "properties": {
    "iso:country":"GB",
    "sg:address":"Womaston House, Walton",
    "sg:city":"Presteigne",
    "sg:classifiers":[
        {
            "category":"Organizations",
            "subcategory":"Non-profit Organization",
            "type":"Services"
        }
    ],
    "sg:phone":"+44 1544 230308",
    "sg:postcode":"LD8 2PT",
    "sg:province":"Herefordshire",
    "sg:tags":[
        "charitable",
        "organisation",
        "voluntary",
        "charity"
    ],
    "wof:name":"Macintyre Care",
    "wof:placetype":"venue"
},
  "geometry": {"coordinates":[-3.052599,52.26371],"type":"Point"}
}