{
  "type": "Feature",
  "properties": {
    "iso:country":"GB",
    "sg:address":"60 Wishart Gardens",
    "sg:city":"Bournemouth",
    "sg:classifiers":[
        {
            "category":"Building & Trades",
            "subcategory":"Construction",
            "type":"Services"
        }
    ],
    "sg:phone":"+44 1202 547200",
    "sg:postcode":"BH9 3QZ",
    "sg:province":"Dorset",
    "sg:tags":[
        "builder"
    ],
    "wof:name":"Bourne Construction & Maintenance Ltd.",
    "wof:placetype":"venue"
},
  "geometry": {"coordinates":[-1.862497,50.764244],"type":"Point"}
}