{
  "type": "Feature",
  "properties": {
    "addr:full":"72 Woodlands Av Littlehampton West Sussex BN16 3EY",
    "addr:housenumber":"72",
    "addr:postcode":"bn16 3ey",
    "addr:street":"Woodlands Av Littlehampton",
    "iso:country":"GB",
    "sg:address":"72 Woodlands Av",
    "sg:city":"Littlehampton",
    "sg:classifiers":[
        {
            "category":"Retail",
            "subcategory":"Veterinary Services",
            "type":"Services"
        }
    ],
    "sg:phone":"+44 1903 785762",
    "sg:postcode":"BN16 3EY",
    "sg:province":"West Sussex",
    "sg:tags":[
        "surgeon"
    ],
    "wof:name":"Woodlands",
    "wof:placetype":"venue"
},
  "geometry": {"coordinates":[-0.5080029964,50.8117103577],"type":"Point"}
}