{
  "type": "Feature",
  "properties": {
    "iso:country":"GB",
    "sg:address":"Station Road, St Clears",
    "sg:city":"Carmarthen",
    "sg:classifiers":[
        {
            "category":"Autos & Motor Vehicles",
            "subcategory":"Fuel & Gas Station",
            "type":"Retail Goods"
        }
    ],
    "sg:phone":"+44 1994 230355",
    "sg:postcode":"SA33 4BP",
    "sg:province":"Carmarthenshire",
    "sg:tags":[
        "petrol",
        "filling"
    ],
    "wof:name":"O J Williams Energy Ltd.",
    "wof:placetype":"venue"
},
  "geometry": {"coordinates":[-4.4924111366,51.8257598877],"type":"Point"}
}