{
  "type": "Feature",
  "properties": {
    "iso:country":"GB",
    "sg:address":"377 Hoylake Road, Moreton",
    "sg:city":"Wirral",
    "sg:classifiers":[
        {
            "category":"Professional",
            "subcategory":"Accounting & Tax Preparation",
            "type":"Services"
        }
    ],
    "sg:phone":"+44 151 677 7729",
    "sg:postcode":"CH46 0RW",
    "sg:province":"Merseyside",
    "sg:tags":[
        "accountant",
        "activity"
    ],
    "sg:website":"http://www.hailwood.co.uk",
    "wof:name":"Hailwood & Co",
    "wof:placetype":"venue"
},
  "geometry": {"coordinates":[-3.118663,53.398483],"type":"Point"}
}