{
  "type": "Feature",
  "properties": {
    "iso:country":"GB",
    "sg:address":", Little London",
    "sg:city":"Heathfield",
    "sg:classifiers":[
        {
            "category":"Autos & Motor Vehicles",
            "subcategory":"Fuel & Gas Station",
            "type":"Retail Goods"
        }
    ],
    "sg:phone":"+44 1435 864398",
    "sg:postcode":"TN21 0AY",
    "sg:province":"East Sussex",
    "sg:tags":[
        "petrol",
        "filling"
    ],
    "wof:name":"Little London Garage",
    "wof:placetype":"venue"
},
  "geometry": {"coordinates":[0.2343910038,50.9570159912],"type":"Point"}
}