{
  "type": "Feature",
  "properties": {
    "addr:full":"15 Woodland Rd Sheffield Derbyshire S8 8PD",
    "addr:housenumber":"15",
    "addr:postcode":"s8 8pd",
    "addr:street":"Woodland Rd",
    "iso:country":"GB",
    "sg:address":"15 Woodland Rd",
    "sg:city":"Sheffield",
    "sg:classifiers":[
        {
            "category":"Professional",
            "type":"Services"
        }
    ],
    "sg:phone":"+44 114 258 1288",
    "sg:postcode":"S8 8PD",
    "sg:province":"Derbyshire",
    "sg:tags":[
        "shopfitters"
    ],
    "wof:name":"Woodland Construction",
    "wof:placetype":"venue"
},
  "geometry": {"coordinates":[-1.463719964,53.3454666138],"type":"Point"}
}