{
  "type": "Feature",
  "properties": {
    "addr:full":"1-2 Bedeburn Foot, Newbiggin Hall Estate Newcastle-upon-tyne Tyne and Wear NE5 4JX",
    "addr:housenumber":"1-2",
    "addr:postcode":"ne5 4jx",
    "addr:street":"Bedeburn Foot Newbiggin Hall Estate",
    "iso:country":"GB",
    "sg:address":"1-2 Bedeburn Foot, Newbiggin Hall Estate",
    "sg:city":"Newcastle-upon-tyne",
    "sg:classifiers":[
        {
            "category":"Food & Beverages",
            "subcategory":"Supermarket",
            "type":"Retail Goods"
        }
    ],
    "sg:phone":"+44 191 286 3447",
    "sg:postcode":"NE5 4JX",
    "sg:province":"Tyne and Wear",
    "wof:name":"Bedeburn Stores",
    "wof:placetype":"venue"
},
  "geometry": {"coordinates":[-1.6929700375,55.0086517334],"type":"Point"}
}