{
  "type": "Feature",
  "properties": {
    "addr:full":"10 Chaplin Road Wembley Greater London HA0 4TX",
    "addr:housenumber":"10",
    "addr:postcode":"ha0 4tx",
    "addr:street":"Chaplin Road",
    "iso:country":"GB",
    "sg:address":"10 Chaplin Road",
    "sg:city":"Wembley",
    "sg:classifiers":[
        {
            "category":"Communications",
            "type":"Services"
        }
    ],
    "sg:postcode":"HA0 4TX",
    "sg:province":"Greater London",
    "sg:tags":[
        "tv",
        "video",
        "radio"
    ],
    "wof:name":"A G S Systems of Wembley",
    "wof:placetype":"venue"
},
  "geometry": {"coordinates":[-0.2994270027,51.5505943298],"type":"Point"}
}