{
  "type": "Feature",
  "properties": {
    "addr:full":"5 Station Road, Sutton-on-sea Mablethorpe Lincolnshire LN12 2HJ",
    "addr:housenumber":"5",
    "addr:postcode":"ln12 2hj",
    "addr:street":"Station Road Sutton-On-Sea Mablethorpe",
    "iso:country":"GB",
    "sg:address":"5 Station Road, Sutton-on-sea",
    "sg:city":"Mablethorpe",
    "sg:classifiers":[
        {
            "category":"Travel",
            "subcategory":"Hotels & Motels",
            "type":"Entertainment"
        }
    ],
    "sg:postcode":"LN12 2HJ",
    "sg:province":"Lincolnshire",
    "sg:tags":[
        "house",
        "guest"
    ],
    "wof:name":"Norvic Self Catering",
    "wof:placetype":"venue"
},
  "geometry": {"coordinates":[0.280035,53.311661],"type":"Point"}
}