{
  "type": "Feature",
  "properties": {
    "addr:full":"91 Bolton Street Chorley Lancashire PR7 3AG",
    "addr:housenumber":"91",
    "addr:postcode":"pr7 3ag",
    "addr:street":"Bolton Street",
    "iso:country":"GB",
    "sg:address":"91 Bolton Street",
    "sg:city":"Chorley",
    "sg:classifiers":[
        {
            "category":"Government",
            "subcategory":"Post Office",
            "type":"Public Place"
        }
    ],
    "sg:phone":"+44 1257 264425",
    "sg:postcode":"PR7 3AG",
    "sg:province":"Lancashire",
    "wof:name":"Bolton Road Post Office",
    "wof:placetype":"venue"
},
  "geometry": {"coordinates":[-2.628385067,53.6480178833],"type":"Point"}
}