{
  "type": "Feature",
  "properties": {
    "addr:full":"75 Dumfries St Treorchy Rhondda, Cynon, Taff CF42 6TS",
    "addr:housenumber":"75",
    "addr:postcode":"cf42 6ts",
    "addr:street":"Dumfries St;Cynon Taff",
    "iso:country":"GB",
    "sg:address":"75 Dumfries St",
    "sg:city":"Treorchy",
    "sg:classifiers":[
        {
            "category":"Banks & Credit Unions",
            "subcategory":"Financial Services",
            "type":"Services"
        }
    ],
    "sg:phone":"+44 1443 776018",
    "sg:postcode":"CF42 6TS",
    "sg:province":"Rhondda, Cynon, Taff",
    "sg:tags":[
        "consultant"
    ],
    "wof:name":"Mr M P Harris",
    "wof:placetype":"venue"
},
  "geometry": {"coordinates":[-3.507702,51.661591],"type":"Point"}
}