{
  "type": "Feature",
  "properties": {
    "iso:country":"GB",
    "sg:address":"221 Narborough Road",
    "sg:city":"Leicester",
    "sg:classifiers":[
        {
            "category":"Fast Food",
            "type":"Food & Drink"
        }
    ],
    "sg:phone":"+44 116 282 7331",
    "sg:postcode":"LE3 2QR",
    "sg:province":"Leicestershire",
    "sg:tags":[
        "away",
        "take"
    ],
    "wof:name":"Pizza Place",
    "wof:placetype":"venue"
},
  "geometry": {"coordinates":[-1.1547889709,52.6229438782],"type":"Point"}
}