{
  "type": "Feature",
  "properties": {
    "iso:country":"GB",
    "sg:address":"44 Whitehall Park",
    "sg:city":"London",
    "sg:classifiers":[
        {
            "category":"Professional",
            "subcategory":"Management & Consulting",
            "type":"Services"
        },
        {
            "category":"Social Services",
            "subcategory":"Job Training",
            "type":"Services"
        }
    ],
    "sg:phone":"+44 20 7272 0100",
    "sg:postcode":"N19 3TN",
    "sg:province":"Greater London",
    "sg:tags":[
        "consultant",
        "provider"
    ],
    "wof:name":"Oliver Purnell",
    "wof:placetype":"venue"
},
  "geometry": {"coordinates":[-0.1351899952,51.5703697205],"type":"Point"}
}