{
  "type": "Feature",
  "properties": {
    "addr:full":"Unit 1a Gatwick Road Crawley Surrey RH10 9RN",
    "addr:housenumber":"unit 1a",
    "addr:postcode":"rh10 9rn",
    "addr:street":"Gatwick Road",
    "iso:country":"GB",
    "sg:address":"Unit 1a Gatwick Road",
    "sg:city":"Crawley",
    "sg:classifiers":[
        {
            "category":"Professional",
            "type":"Services"
        }
    ],
    "sg:phone":"+44 1293 522384",
    "sg:postcode":"RH10 9RN",
    "sg:province":"Surrey",
    "sg:tags":[
        "aircraft",
        "maintenance",
        "caterer"
    ],
    "wof:name":"Albert Abela & Co",
    "wof:placetype":"venue"
},
  "geometry": {"coordinates":[-0.164524,51.138241],"type":"Point"}
}