{
  "type": "Feature",
  "properties": {
    "addr:full":"66 Bence Lane, Darton Barnsley South Yorkshire S75 5PE",
    "addr:housenumber":"66",
    "addr:postcode":"s75 5pe",
    "addr:street":"Bence Lane;Yorkshire",
    "iso:country":"GB",
    "sg:address":"66 Bence Lane, Darton",
    "sg:city":"Barnsley",
    "sg:classifiers":[
        {
            "category":"Social Services",
            "subcategory":"Retirement Home",
            "type":"Services"
        }
    ],
    "sg:phone":"+44 1226 382688",
    "sg:postcode":"S75 5PE",
    "sg:province":"South Yorkshire",
    "sg:tags":[
        "residential",
        "care"
    ],
    "wof:name":"The Maples",
    "wof:placetype":"venue"
},
  "geometry": {"coordinates":[-1.5359410048,53.5796279907],"type":"Point"}
}