{
  "type": "Feature",
  "properties": {
    "addr:full":"The Vicarage, Greetham Street Southsea Hampshire PO5 4LH",
    "addr:postcode":"po5 4lh",
    "addr:street":"Greetham Street",
    "iso:country":"GB",
    "sg:address":"The Vicarage, Greetham Street",
    "sg:city":"Southsea",
    "sg:classifiers":[
        {
            "category":"Place Of Worship",
            "type":"Public Place"
        }
    ],
    "sg:phone":"+44 23 9282 6073",
    "sg:postcode":"PO5 4LH",
    "sg:province":"Hampshire",
    "wof:name":"Portsmouth Diocesan Board of Finance (The",
    "wof:placetype":"venue"
},
  "geometry": {"coordinates":[-1.088164,50.784664],"type":"Point"}
}