{
  "type": "Feature",
  "properties": {
    "addr:full":"3 Glendoune Street Girvan South Ayrshire KA26 0AA",
    "addr:housenumber":"3",
    "addr:postcode":"ka26 0aa",
    "addr:street":"Glendoune Street",
    "iso:country":"GB",
    "sg:address":"3 Glendoune Street",
    "sg:city":"Girvan",
    "sg:classifiers":[
        {
            "category":"Personal",
            "subcategory":"Beauty Salon",
            "type":"Services"
        }
    ],
    "sg:phone":"+44 1465 712292",
    "sg:postcode":"KA26 0AA",
    "sg:province":"South Ayrshire",
    "sg:tags":[
        "unisex",
        "hairdresser"
    ],
    "wof:name":"Monty's Hairdressers",
    "wof:placetype":"venue"
},
  "geometry": {"coordinates":[-4.855826,55.236546],"type":"Point"}
}