{
  "type": "Feature",
  "properties": {
    "addr:full":"304-308 Station Road Harrow Greater London HA1 2DX",
    "addr:housenumber":"304-308",
    "addr:postcode":"ha1 2dx",
    "addr:street":"Station Road",
    "iso:country":"GB",
    "sg:address":"304-308 Station Road",
    "sg:city":"Harrow",
    "sg:classifiers":[
        {
            "category":"Shopping",
            "subcategory":"Clothing, Apparel, & Fashions",
            "type":"Retail Goods"
        }
    ],
    "sg:postcode":"HA1 2DX",
    "sg:province":"Greater London",
    "sg:tags":[
        "shop"
    ],
    "wof:name":"Q S Plc",
    "wof:placetype":"venue"
},
  "geometry": {"coordinates":[-0.3330410123,51.5814933777],"type":"Point"}
}