{
  "type": "Feature",
  "properties": {
    "iso:country":"GB",
    "sg:address":"65 Adswood Lane West",
    "sg:city":"Stockport",
    "sg:classifiers":[
        {
            "category":"Fast Food",
            "type":"Food & Drink"
        }
    ],
    "sg:phone":"+44 161 480 2445",
    "sg:postcode":"SK3 8HZ",
    "sg:province":"Cheshire",
    "sg:tags":[
        "away",
        "take"
    ],
    "wof:name":"Noble House Takeaway",
    "wof:placetype":"venue"
},
  "geometry": {"coordinates":[-2.159689,53.396206],"type":"Point"}
}