{
  "type": "Feature",
  "properties": {
    "addr:full":"Old Walsall Road Birmingham West Midlands B42 1DT",
    "addr:postcode":"b42 1dt",
    "addr:street":"Old Walsall Road",
    "iso:country":"GB",
    "sg:address":"Old Walsall Road",
    "sg:city":"Birmingham",
    "sg:classifiers":[
        {
            "category":"Autos & Motor Vehicles",
            "subcategory":"Fuel & Gas Station",
            "type":"Retail Goods"
        }
    ],
    "sg:phone":"+44 121 358 8900",
    "sg:postcode":"B42 1DT",
    "sg:province":"West Midlands",
    "sg:tags":[
        "petrol",
        "filling"
    ],
    "wof:name":"Shell (U K)",
    "wof:placetype":"venue"
},
  "geometry": {"coordinates":[-1.929531,52.542938],"type":"Point"}
}