{
  "type": "Feature",
  "properties": {
    "addr:full":"20 Market Street Wymondham Norfolk NR18 0BB",
    "addr:housenumber":"20",
    "addr:postcode":"nr18 0bb",
    "addr:street":"Market Street",
    "iso:country":"GB",
    "sg:address":"20 Market Street",
    "sg:city":"Wymondham",
    "sg:classifiers":[
        {
            "category":"Shopping",
            "subcategory":"Hobbies, Toys, & Games",
            "type":"Retail Goods"
        }
    ],
    "sg:postcode":"NR18 0BB",
    "sg:province":"Norfolk",
    "sg:tags":[
        "computer"
    ],
    "wof:name":"Gameplay Computers",
    "wof:placetype":"venue"
},
  "geometry": {"coordinates":[1.1116600037,52.5703582764],"type":"Point"}
}