{
  "type": "Feature",
  "properties": {
    "addr:full":"68 Saddler Street Durham Durham DH1 3NP",
    "addr:housenumber":"68",
    "addr:postcode":"dh1 3np",
    "addr:street":"Saddler Street",
    "iso:country":"GB",
    "sg:address":"68 Saddler Street",
    "sg:city":"Durham",
    "sg:classifiers":[
        {
            "category":"Professional",
            "subcategory":"Lawyer & Legal Services",
            "type":"Services"
        }
    ],
    "sg:phone":"+44 191 386 1161",
    "sg:postcode":"DH1 3NP",
    "sg:province":"Durham",
    "sg:tags":[
        "solicitor"
    ],
    "wof:name":"John Bayles & Co",
    "wof:placetype":"venue"
},
  "geometry": {"coordinates":[-1.5751589537,54.7763061523],"type":"Point"}
}