{
  "type": "Feature",
  "properties": {
    "addr:full":"Merrydale Huddersfield West Yorkshire HD7 5UZ",
    "addr:postcode":"hd7 5uz",
    "addr:street":"West",
    "iso:country":"GB",
    "sg:address":"Merrydale",
    "sg:city":"Huddersfield",
    "sg:classifiers":[
        {
            "category":"Building & Trades",
            "subcategory":"Construction",
            "type":"Services"
        }
    ],
    "sg:phone":"+44 1484 846757",
    "sg:postcode":"HD7 5UZ",
    "sg:province":"West Yorkshire",
    "sg:tags":[
        "builder"
    ],
    "wof:name":"Stephen Slator",
    "wof:placetype":"venue"
},
  "geometry": {"coordinates":[-1.8791890144,53.6215286255],"type":"Point"}
}