{
  "type": "Feature",
  "properties": {
    "iso:country":"GB",
    "sg:address":"8 West Pallant",
    "sg:city":"Chichester",
    "sg:classifiers":[
        {
            "category":"Professional",
            "subcategory":"Business Services",
            "type":"Services"
        }
    ],
    "sg:phone":"+44 1243 536929",
    "sg:postcode":"PO19 1TD",
    "sg:province":"West Sussex",
    "sg:tags":[
        "transfer",
        "agent"
    ],
    "wof:name":"Pinkertons (Estate Agents) Ltd.",
    "wof:placetype":"venue"
},
  "geometry": {"coordinates":[-0.7781900167,50.8352394104],"type":"Point"}
}