{
  "type": "Feature",
  "properties": {
    "addr:full":"Valkyrie, Donington Road, Kirton End Boston Lincolnshire PE20 1NX",
    "addr:postcode":"pe20 1nx",
    "addr:street":"Donington Road",
    "iso:country":"GB",
    "sg:address":"Valkyrie, Donington Road, Kirton End",
    "sg:city":"Boston",
    "sg:classifiers":[
        {
            "category":"Professional",
            "subcategory":"Art Services",
            "type":"Services"
        },
        {
            "category":"Building & Trades",
            "subcategory":"Construction",
            "type":"Services"
        }
    ],
    "sg:phone":"+44 1205 722646",
    "sg:postcode":"PE20 1NX",
    "sg:province":"Lincolnshire",
    "sg:tags":[
        "decorator",
        "painter"
    ],
    "wof:name":"C HINCHLIFFE",
    "wof:placetype":"venue"
},
  "geometry": {"coordinates":[-0.0571379997,52.9280471802],"type":"Point"}
}