{
  "type": "Feature",
  "properties": {
    "addr:full":"22 New Road, Mytholnroyd Halifax West Yorkshire HX7 5DZ",
    "addr:housenumber":"22",
    "addr:postcode":"hx7 5dz",
    "addr:street":"New Road",
    "iso:country":"GB",
    "sg:address":"22 New Road, Mytholnroyd",
    "sg:city":"Halifax",
    "sg:classifiers":[
        {
            "category":"Health Services",
            "subcategory":"Podiatrist",
            "type":"Services"
        }
    ],
    "sg:phone":"+44 1422 885455",
    "sg:postcode":"HX7 5DZ",
    "sg:province":"West Yorkshire",
    "sg:tags":[
        "podiatrists",
        "chiropodist"
    ],
    "wof:name":"N A Clegg",
    "wof:placetype":"venue"
},
  "geometry": {"coordinates":[-1.9827489853,53.729511261],"type":"Point"}
}