{
  "type": "Feature",
  "properties": {
    "addr:full":"Arch 3 Great Norbury Street Hyde Cheshire SK14 1BW",
    "addr:postcode":"sk14 1bw",
    "addr:street":"Arch;Great Norbury Street",
    "iso:country":"GB",
    "sg:address":"Arch 3 Great Norbury Street",
    "sg:city":"Hyde",
    "sg:classifiers":[
        {
            "category":"Retail",
            "subcategory":"Auto Repair",
            "type":"Services"
        }
    ],
    "sg:phone":"+44 161 368 5558",
    "sg:postcode":"SK14 1BW",
    "sg:province":"Cheshire",
    "sg:tags":[
        "modification",
        "garage"
    ],
    "wof:name":"A & N Motoring Centre",
    "wof:placetype":"venue"
},
  "geometry": {"coordinates":[-2.074819,53.446045],"type":"Point"}
}