{
  "type": "Feature",
  "properties": {
    "addr:full":"43-45 Fisher Street Stranraer Dumfries and Galloway DG9 7LH",
    "addr:housenumber":"43-45",
    "addr:postcode":"dg9 7lh",
    "addr:street":"Fisher Street",
    "iso:country":"GB",
    "sg:address":"43-45 Fisher Street",
    "sg:city":"Stranraer",
    "sg:classifiers":[
        {
            "category":"Building & Trades",
            "subcategory":"Plumbing",
            "type":"Services"
        }
    ],
    "sg:phone":"+44 1776 702357",
    "sg:postcode":"DG9 7LH",
    "sg:province":"Dumfries and Galloway",
    "sg:tags":[
        "plumber",
        "heating"
    ],
    "wof:name":"David Train",
    "wof:placetype":"venue"
},
  "geometry": {"coordinates":[-5.0294790268,54.9056015015],"type":"Point"}
}