{
  "type": "Feature",
  "properties": {
    "addr:full":"First Floor Suite, 30-32 West Street Fareham Hampshire PO16 0JW",
    "addr:housenumber":"suite 30-32",
    "addr:postcode":"po16 0jw",
    "addr:street":"West Street",
    "iso:country":"GB",
    "sg:address":"First Floor Suite, 30-32 West Street",
    "sg:city":"Fareham",
    "sg:classifiers":[
        {
            "category":"Personal",
            "subcategory":"Beauty Salon",
            "type":"Services"
        }
    ],
    "sg:phone":"+44 1329 220050",
    "sg:postcode":"PO16 0JW",
    "sg:province":"Hampshire",
    "wof:name":"Beauty Secrets Salon Ltd",
    "wof:placetype":"venue"
},
  "geometry": {"coordinates":[-1.176587,50.852222],"type":"Point"}
}