{
  "type": "Feature",
  "properties": {
    "addr:full":"118-130 Ridgeway, Plympton Plymouth Devon PL7 2HN",
    "addr:housenumber":"118-130",
    "addr:postcode":"pl7 2hn",
    "addr:street":"Ridgeway",
    "iso:country":"GB",
    "sg:address":"118-130 Ridgeway, Plympton",
    "sg:city":"Plymouth",
    "sg:classifiers":[
        {
            "category":"Autos & Motor Vehicles",
            "subcategory":"Automobile Sales",
            "type":"Retail Goods"
        }
    ],
    "sg:phone":"+44 1752 343777",
    "sg:postcode":"PL7 2HN",
    "sg:province":"Devon",
    "sg:tags":[
        "car",
        "used",
        "commercial"
    ],
    "sg:website":"http://www.specialistvehicles.net",
    "wof:name":"Specialist Vehicles Of Plymouth Ltd",
    "wof:placetype":"venue"
},
  "geometry": {"coordinates":[-4.049238,50.387192],"type":"Point"}
}