{
  "type": "Feature",
  "properties": {
    "addr:full":"258 Wharfdale Rd Birmingham West Midlands B11 2EG",
    "addr:housenumber":"258",
    "addr:postcode":"b11 2eg",
    "addr:street":"Wharfdale Rd",
    "iso:country":"GB",
    "sg:address":"258 Wharfdale Rd",
    "sg:city":"Birmingham",
    "sg:classifiers":[
        {
            "category":"Building & Trades",
            "subcategory":"Construction",
            "type":"Services"
        }
    ],
    "sg:postcode":"B11 2EG",
    "sg:province":"West Midlands",
    "sg:tags":[
        "glazier"
    ],
    "wof:name":"Markey,Nicholas,",
    "wof:placetype":"venue"
},
  "geometry": {"coordinates":[-1.828087,52.456631],"type":"Point"}
}