{
  "type": "Feature",
  "properties": {
    "addr:full":"136 Provision Market, High Street Newport Newport NP20 1DD",
    "addr:housenumber":"136",
    "addr:postcode":"np20 1dd",
    "addr:street":"Provision Market High Street",
    "iso:country":"GB",
    "sg:address":"136 Provision Market, High Street",
    "sg:city":"Newport",
    "sg:classifiers":[
        {
            "category":"Shopping",
            "subcategory":"Comic Books",
            "type":"Retail Goods"
        }
    ],
    "sg:postcode":"NP20 1DD",
    "sg:province":"Newport",
    "sg:tags":[
        "magazine"
    ],
    "wof:name":"Negative Zone Comics",
    "wof:placetype":"venue"
},
  "geometry": {"coordinates":[-2.9962799549,51.5889205933],"type":"Point"}
}