{
  "type": "Feature",
  "properties": {
    "addr:full":"63 Poulton Road Fleetwood Lancashire FY7 6TF",
    "addr:housenumber":"63",
    "addr:postcode":"fy7 6tf",
    "addr:street":"Poulton Road",
    "iso:country":"GB",
    "sg:address":"63 Poulton Road",
    "sg:city":"Fleetwood",
    "sg:classifiers":[
        {
            "category":"Travel",
            "subcategory":"Travel Agent",
            "type":"Entertainment"
        }
    ],
    "sg:phone":"+44 1253 772893",
    "sg:postcode":"FY7 6TF",
    "sg:province":"Lancashire",
    "sg:tags":[
        "agency",
        "activity"
    ],
    "wof:name":"HOLIDAYMAKERS",
    "wof:placetype":"venue"
},
  "geometry": {"coordinates":[-3.019438982,53.9210548401],"type":"Point"}
}