{
  "type": "Feature",
  "properties": {
    "addr:full":"South Park Sevenoaks Kent TN13 1EH",
    "addr:postcode":"tn13 1eh",
    "addr:street":"South Park",
    "iso:country":"GB",
    "sg:address":"South Park",
    "sg:city":"Sevenoaks",
    "sg:classifiers":[
        {
            "category":"Education",
            "subcategory":"School",
            "type":"Public Place"
        }
    ],
    "sg:postcode":"TN13 1EH",
    "sg:province":"Kent",
    "sg:tags":[
        "local",
        "authority"
    ],
    "wof:name":"St Thomas R C Primary School",
    "wof:placetype":"venue"
},
  "geometry": {"coordinates":[0.1877550036,51.2713813782],"type":"Point"}
}