{
  "type": "Feature",
  "properties": {
    "iso:country":"GB",
    "sg:address":"22 Sycamore Clo, Snaith",
    "sg:city":"Goole",
    "sg:classifiers":[
        {
            "category":"Education",
            "subcategory":"Dance Studio",
            "type":"Public Place"
        }
    ],
    "sg:postcode":"DN14 9QU",
    "sg:province":"East Riding of Yorkshire",
    "sg:tags":[
        "school",
        "dancing"
    ],
    "wof:name":"Macdonald School of Theatre Dance",
    "wof:placetype":"venue"
},
  "geometry": {"coordinates":[-1.025951,53.688908],"type":"Point"}
}