{
  "type": "Feature",
  "properties": {
    "addr:full":"The Studio, Briarfield, Middleton On Sea Bognor Regis West Sussex PO22 6NL",
    "addr:postcode":"po22 6nl",
    "iso:country":"GB",
    "sg:address":"The Studio, Briarfield, Middleton On Sea",
    "sg:city":"Bognor Regis",
    "sg:classifiers":[
        {
            "category":"Professional",
            "subcategory":"Engineering",
            "type":"Services"
        }
    ],
    "sg:phone":"+44 1243 587588",
    "sg:postcode":"PO22 6NL",
    "sg:province":"West Sussex",
    "sg:tags":[
        "consulting",
        "engineer"
    ],
    "wof:name":"Chittenden Associates",
    "wof:placetype":"venue"
},
  "geometry": {"coordinates":[-0.637369,50.794628],"type":"Point"}
}