{
  "type": "Feature",
  "properties": {
    "addr:full":"5 Trinity Street Coventry West Midlands CV1 1FJ",
    "addr:housenumber":"5",
    "addr:postcode":"cv1 1fj",
    "addr:street":"Trinity Street",
    "iso:country":"GB",
    "sg:address":"5 Trinity Street",
    "sg:city":"Coventry",
    "sg:classifiers":[
        {
            "category":"Professional",
            "subcategory":"Employment Agencies",
            "type":"Services"
        }
    ],
    "sg:phone":"+44 24 7655 3643",
    "sg:postcode":"CV1 1FJ",
    "sg:province":"West Midlands",
    "sg:tags":[
        "consultant"
    ],
    "wof:name":"Kinetic Plc",
    "wof:placetype":"venue"
},
  "geometry": {"coordinates":[-1.509069,52.41032],"type":"Point"}
}