{
  "type": "Feature",
  "properties": {
    "addr:full":"7 Christchurch Street East Frome Somerset BA11 1QB",
    "addr:housenumber":"7",
    "addr:postcode":"ba11 1qb",
    "addr:street":"Christchurch Street East",
    "iso:country":"GB",
    "sg:address":"7 Christchurch Street East",
    "sg:city":"Frome",
    "sg:classifiers":[
        {
            "category":"Home & Garden",
            "subcategory":"Household Appliances",
            "type":"Retail Goods"
        }
    ],
    "sg:phone":"+44 1373 472824",
    "sg:postcode":"BA11 1QB",
    "sg:province":"Somerset",
    "sg:tags":[
        "electrical",
        "domestic"
    ],
    "wof:name":"Bill Savage Electrical Cookers Galore",
    "wof:placetype":"venue"
},
  "geometry": {"coordinates":[-2.3218529224,51.2287635803],"type":"Point"}
}