{
  "type": "Feature",
  "properties": {
    "iso:country":"GB",
    "sg:address":"5 Outer Circle Road",
    "sg:city":"Lincoln",
    "sg:classifiers":[
        {
            "category":"Retail",
            "subcategory":"Auto Rental",
            "type":"Services"
        }
    ],
    "sg:phone":"+44 1522 523111",
    "sg:postcode":"LN2 4HZ",
    "sg:province":"Lincolnshire",
    "sg:tags":[
        "car"
    ],
    "wof:name":"Enterprise Rent A Car",
    "wof:placetype":"venue"
},
  "geometry": {"coordinates":[-0.511122,53.242859],"type":"Point"}
}