{
  "type": "Feature",
  "properties": {
    "addr:full":"26 Mill Street Shrewsbury Shropshire SY4 5ED",
    "addr:housenumber":"26",
    "addr:postcode":"sy4 5ed",
    "addr:street":"Mill Street",
    "iso:country":"GB",
    "sg:address":"26 Mill Street",
    "sg:city":"Shrewsbury",
    "sg:classifiers":[
        {
            "category":"Building & Trades",
            "subcategory":"Construction",
            "type":"Services"
        }
    ],
    "sg:postcode":"SY4 5ED",
    "sg:province":"Shropshire",
    "sg:tags":[
        "builder"
    ],
    "wof:name":"Pj Building Contractors",
    "wof:placetype":"venue"
},
  "geometry": {"coordinates":[-2.725985,52.854095],"type":"Point"}
}