{
  "type": "Feature",
  "properties": {
    "iso:country":"GB",
    "sg:address":"1 Cluntergate, Horbury",
    "sg:city":"Wakefield",
    "sg:classifiers":[
        {
            "category":"Shopping",
            "subcategory":"Stationery & Office Supplies",
            "type":"Retail Goods"
        },
        {
            "category":"Professional",
            "subcategory":"Printing & Photocopies",
            "type":"Services"
        }
    ],
    "sg:phone":"+44 1924 274979",
    "sg:postcode":"WF4 5AF",
    "sg:province":"West Yorkshire",
    "sg:tags":[
        "printer",
        "commercial"
    ],
    "wof:name":"George Alderson & Co",
    "wof:placetype":"venue"
},
  "geometry": {"coordinates":[-1.548139,53.65789],"type":"Point"}
}