{
  "type": "Feature",
  "properties": {
    "iso:country":"GB",
    "sg:address":"100 Orchard Street",
    "sg:city":"Galston",
    "sg:classifiers":[
        {
            "category":"Building & Trades",
            "subcategory":"Landscaping Services",
            "type":"Services"
        }
    ],
    "sg:phone":"+44 1563 822311",
    "sg:postcode":"KA4 8EL",
    "sg:province":"East Ayrshire",
    "sg:tags":[
        "forestry",
        "tree"
    ],
    "wof:name":"G M Tree Surgeons",
    "wof:placetype":"venue"
},
  "geometry": {"coordinates":[-4.38674,55.597965],"type":"Point"}
}