{
  "type": "Feature",
  "properties": {
    "iso:country":"GB",
    "sg:address":"113 Shields Road",
    "sg:city":"Newcastle-upon-tyne",
    "sg:classifiers":[
        {
            "category":"Food & Beverages",
            "subcategory":"Bakery",
            "type":"Retail Goods"
        }
    ],
    "sg:phone":"+44 191 224 1217",
    "sg:postcode":"NE6 1DN",
    "sg:province":"Tyne and Wear",
    "sg:tags":[
        "baker"
    ],
    "wof:name":"Milligans",
    "wof:placetype":"venue"
},
  "geometry": {"coordinates":[-1.581548,54.977207],"type":"Point"}
}