{
  "type": "Feature",
  "properties": {
    "addr:full":"24-26 Le Strange Terrace Hunstanton Norfolk PE36 5AJ",
    "addr:housenumber":"24-26",
    "addr:postcode":"pe36 5aj",
    "addr:street":"Le Strange Terrace",
    "iso:country":"GB",
    "sg:address":"24-26 Le Strange Terrace",
    "sg:city":"Hunstanton",
    "sg:classifiers":[
        {
            "category":"Restaurant",
            "type":"Food & Drink"
        }
    ],
    "sg:phone":"+44 1485 532218",
    "sg:postcode":"PE36 5AJ",
    "sg:province":"Norfolk",
    "wof:name":"Catina Restaurant",
    "wof:placetype":"venue"
},
  "geometry": {"coordinates":[0.487235,52.938545],"type":"Point"}
}