{
  "type": "Feature",
  "properties": {
    "addr:full":"9 Oak Glade York North Yorkshire YO31 9JN",
    "addr:housenumber":"9",
    "addr:postcode":"yo31 9jn",
    "addr:street":"Oak Glade",
    "iso:country":"GB",
    "sg:address":"9 Oak Glade",
    "sg:city":"York",
    "sg:classifiers":[
        {
            "category":"Building & Trades",
            "subcategory":"Construction",
            "type":"Services"
        }
    ],
    "sg:phone":"+44 1904 652066",
    "sg:postcode":"YO31 9JN",
    "sg:province":"North Yorkshire",
    "sg:tags":[
        "builder"
    ],
    "wof:name":"Richards Builders & Property Maintenance",
    "wof:placetype":"venue"
},
  "geometry": {"coordinates":[-1.060008,53.987606],"type":"Point"}
}