{
  "type": "Feature",
  "properties": {
    "iso:country":"GB",
    "sg:address":"324 Cann Hall Road",
    "sg:city":"London",
    "sg:classifiers":[
        {
            "category":"Cinema",
            "subcategory":"Movie Rental",
            "type":"Entertainment"
        }
    ],
    "sg:phone":"+44 20 8522 1245",
    "sg:postcode":"E11 3NW",
    "sg:province":"Greater London",
    "sg:tags":[
        "video",
        "library"
    ],
    "wof:name":"Cann Hall Superstore",
    "wof:placetype":"venue"
},
  "geometry": {"coordinates":[0.01747,51.557758],"type":"Point"}
}