{
  "type": "Feature",
  "properties": {
    "iso:country":"GB",
    "sg:address":"312 Woodside Way, Springvale Indust Est",
    "sg:city":"Cwmbran",
    "sg:classifiers":[
        {
            "category":"Government",
            "subcategory":"Post Office",
            "type":"Public Place"
        }
    ],
    "sg:postcode":"NP44 5BR",
    "sg:province":"Monmouthshire",
    "sg:tags":[
        "messenger",
        "courier"
    ],
    "wof:name":"Johns,Robert,",
    "wof:placetype":"venue"
},
  "geometry": {"coordinates":[-3.0367639065,51.656703949],"type":"Point"}
}