{
  "type": "Feature",
  "properties": {
    "addr:full":"4 Sandown Drive, Halebarns Altrincham Cheshire WA15 0BA",
    "addr:housenumber":"4",
    "addr:postcode":"wa15 0ba",
    "addr:street":"Sandown Drive",
    "iso:country":"GB",
    "sg:address":"4 Sandown Drive, Halebarns",
    "sg:city":"Altrincham",
    "sg:classifiers":[
        {
            "category":"Health Services",
            "subcategory":"Health Practitioner",
            "type":"Services"
        }
    ],
    "sg:phone":"+44 161 980 6756",
    "sg:postcode":"WA15 0BA",
    "sg:province":"Cheshire",
    "sg:tags":[
        "acupuncture"
    ],
    "wof:name":"Kuen P Chan",
    "wof:placetype":"venue"
},
  "geometry": {"coordinates":[-2.308817,53.359715],"type":"Point"}
}