{
  "type": "Feature",
  "properties": {
    "iso:country":"GB",
    "sg:address":"474a Chiswick High Road",
    "sg:city":"London",
    "sg:classifiers":[
        {
            "category":"Retail",
            "subcategory":"Repair Shop",
            "type":"Services"
        }
    ],
    "sg:phone":"+44 20 8994 4567",
    "sg:postcode":"W4 5TT",
    "sg:province":"Greater London",
    "sg:tags":[
        "clocks",
        "watch"
    ],
    "wof:name":"Which Watch",
    "wof:placetype":"venue"
},
  "geometry": {"coordinates":[-0.273029,51.492611],"type":"Point"}
}