{
  "type": "Feature",
  "properties": {
    "iso:country":"GB",
    "sg:address":"2 Neighbourhood Centre, Cogges Hill Rd",
    "sg:city":"Witney",
    "sg:classifiers":[
        {
            "category":"Government",
            "subcategory":"Post Office",
            "type":"Public Place"
        }
    ],
    "sg:phone":"+44 1993 776557",
    "sg:postcode":"OX8 6XY",
    "sg:province":"Oxfordshire",
    "wof:name":"Newlands Post Office",
    "wof:placetype":"venue"
},
  "geometry": {"coordinates":[-1.4961700439,51.7826309204],"type":"Point"}
}