{
  "type": "Feature",
  "properties": {
    "addr:full":"Nettleham Road Lincoln Lincolnshire LN2 4DJ",
    "addr:postcode":"ln2 4dj",
    "addr:street":"Nettleham Road",
    "iso:country":"GB",
    "sg:address":"Nettleham Road",
    "sg:city":"Lincoln",
    "sg:classifiers":[
        {
            "category":"Autos & Motor Vehicles",
            "subcategory":"Fuel & Gas Station",
            "type":"Retail Goods"
        }
    ],
    "sg:phone":"+44 1522 533054",
    "sg:postcode":"LN2 4DJ",
    "sg:province":"Lincolnshire",
    "sg:tags":[
        "hr",
        "petrol"
    ],
    "wof:name":"Nettleham Road Service Station",
    "wof:placetype":"venue"
},
  "geometry": {"coordinates":[-0.5183230042,53.2508087158],"type":"Point"}
}