{
  "type": "Feature",
  "properties": {
    "addr:full":"Roundstone Surgery, Polebarn Rd Trowbridge Wiltshire BA14 7EG",
    "addr:postcode":"ba14 7eg",
    "addr:street":"Polebarn Rd",
    "iso:country":"GB",
    "sg:address":"Roundstone Surgery, Polebarn Rd",
    "sg:city":"Trowbridge",
    "sg:classifiers":[
        {
            "category":"Health Services",
            "subcategory":"Doctor",
            "type":"Services"
        }
    ],
    "sg:phone":"+44 1225 752752",
    "sg:postcode":"BA14 7EG",
    "sg:province":"Wiltshire",
    "sg:tags":[
        "practitioners"
    ],
    "wof:name":"Flack, J",
    "wof:placetype":"venue"
},
  "geometry": {"coordinates":[-2.2083740234,51.3153419495],"type":"Point"}
}