{
  "type": "Feature",
  "properties": {
    "addr:full":"Po Box 6 Bilston West Midlands WV14 0JF",
    "addr:housenumber":"po;6",
    "addr:postcode":"wv14 0jf",
    "addr:street":"Box",
    "iso:country":"GB",
    "sg:address":"Po Box 6",
    "sg:city":"Bilston",
    "sg:classifiers":[
        {
            "category":"Wholesale",
            "subcategory":"Vending Machines",
            "type":"Manufacturing & Wholesale Goods"
        }
    ],
    "sg:phone":"+44 1256 340600",
    "sg:postcode":"WV14 0JF",
    "sg:province":"West Midlands",
    "sg:tags":[
        "sale"
    ],
    "wof:name":"Vendcare Services Ltd.",
    "wof:placetype":"venue"
},
  "geometry": {"coordinates":[-2.0811491013,52.5626106262],"type":"Point"}
}