{
  "type": "Feature",
  "properties": {
    "iso:country":"GB",
    "sg:address":"61b Portico Lane",
    "sg:city":"Prescot",
    "sg:classifiers":[
        {
            "category":"Shopping",
            "subcategory":"News",
            "type":"Retail Goods"
        }
    ],
    "sg:postcode":"L35 7JW",
    "sg:province":"Cheshire",
    "sg:tags":[
        "newsagent"
    ],
    "wof:name":"Cunningham & Stephenson",
    "wof:placetype":"venue"
},
  "geometry": {"coordinates":[-2.782075,53.428772],"type":"Point"}
}