{
  "type": "Feature",
  "properties": {
    "iso:country":"GB",
    "sg:address":"Woodlands Grange, Woodlands La, Almondsbury",
    "sg:city":"Bristol",
    "sg:classifiers":[
        {
            "category":"Professional",
            "subcategory":"Engineering",
            "type":"Services"
        }
    ],
    "sg:postcode":"BS32 4JY",
    "sg:province":"Gloucestershire",
    "wof:name":"Woodlands Grange Management Services Ltd",
    "wof:placetype":"venue"
},
  "geometry": {"coordinates":[-2.564619,51.556526],"type":"Point"}
}