{
  "type": "Feature",
  "properties": {
    "addr:full":"22 Winchelsey Rise South Croydon Surrey CR2 7BN",
    "addr:housenumber":"22",
    "addr:postcode":"cr2 7bn",
    "addr:street":"Winchelsey Rise",
    "iso:country":"GB",
    "sg:address":"22 Winchelsey Rise",
    "sg:city":"South Croydon",
    "sg:classifiers":[
        {
            "category":"Professional",
            "subcategory":"Accounting & Tax Preparation",
            "type":"Services"
        }
    ],
    "sg:postcode":"CR2 7BN",
    "sg:province":"Surrey",
    "sg:tags":[
        "accountant"
    ],
    "wof:name":"John D Browne",
    "wof:placetype":"venue"
},
  "geometry": {"coordinates":[-0.0831009969,51.356426239],"type":"Point"}
}