{
  "type": "Feature",
  "properties": {
    "addr:full":"Water Lane Richmond Greater London TW9 1TH",
    "addr:postcode":"tw9 1th",
    "addr:street":"Water Lane",
    "iso:country":"GB",
    "sg:address":"Water Lane",
    "sg:city":"Richmond",
    "sg:classifiers":[
        {
            "category":"Bars & Pubs",
            "type":"Food & Drink"
        }
    ],
    "sg:phone":"+44 20 8940 6844",
    "sg:postcode":"TW9 1TH",
    "sg:province":"Greater London",
    "sg:tags":[
        "pubs",
        "inn"
    ],
    "wof:name":"White Cross Hotel",
    "wof:placetype":"venue"
},
  "geometry": {"coordinates":[-0.307352,51.459156],"type":"Point"}
}