{
  "type": "Feature",
  "properties": {
    "addr:full":"Unit 10 Queens Square, Sandwell Centre West Bromwich West Midlands B70 7NG",
    "addr:housenumber":"unit 10",
    "addr:postcode":"b70 7ng",
    "addr:street":"Queens Square Sandwell;West",
    "iso:country":"GB",
    "sg:address":"Unit 10 Queens Square, Sandwell Centre",
    "sg:city":"West Bromwich",
    "sg:classifiers":[
        {
            "category":"Shopping",
            "subcategory":"Pawn Shop",
            "type":"Retail Goods"
        }
    ],
    "sg:postcode":"B70 7NG",
    "sg:province":"West Midlands",
    "sg:tags":[
        "pawnbroker"
    ],
    "wof:name":"T H Baker & Co",
    "wof:placetype":"venue"
},
  "geometry": {"coordinates":[-1.9900230169,52.5194740295],"type":"Point"}
}