{
  "type": "Feature",
  "properties": {
    "iso:country":"GB",
    "sg:address":"4 Calluna Dr, Bletchley",
    "sg:city":"Milton Keynes",
    "sg:classifiers":[
        {
            "category":"Professional",
            "subcategory":"Management & Consulting",
            "type":"Services"
        }
    ],
    "sg:postcode":"MK3 6NZ",
    "sg:province":"Buckinghamshire",
    "sg:tags":[
        "consultant",
        "business"
    ],
    "wof:name":"Vectra Consultants Ltd",
    "wof:placetype":"venue"
},
  "geometry": {"coordinates":[-0.747194,52.007927],"type":"Point"}
}