{
  "type": "Feature",
  "properties": {
    "addr:full":"Central Library, 2 Westgate Oxford Oxfordshire OX1 1DJ",
    "addr:housenumber":"2",
    "addr:postcode":"ox1 1dj",
    "addr:street":"Westgate",
    "iso:country":"GB",
    "sg:address":"Central Library, 2 Westgate",
    "sg:city":"Oxford",
    "sg:classifiers":[
        {
            "category":"Sports & Exercise",
            "subcategory":"Bowling",
            "type":"Entertainment"
        }
    ],
    "sg:phone":"+44 1865 815432",
    "sg:postcode":"OX1 1DJ",
    "sg:province":"Oxfordshire",
    "sg:tags":[
        "photography"
    ],
    "wof:name":"Oxfordshire Photographic Archive",
    "wof:placetype":"venue"
},
  "geometry": {"coordinates":[-1.2594890594,51.7562065125],"type":"Point"}
}