{
  "type": "Feature",
  "properties": {
    "iso:country":"GB",
    "sg:address":"20 Redwood Av",
    "sg:city":"Reading",
    "sg:classifiers":[
        {
            "category":"Professional",
            "subcategory":"Management & Consulting",
            "type":"Services"
        }
    ],
    "sg:phone":"+44 118 969 7461",
    "sg:postcode":"RG5 4DR",
    "sg:province":"Berkshire",
    "sg:tags":[
        "consultant",
        "specialist"
    ],
    "wof:name":"Celtic Touch (Mobile)",
    "wof:placetype":"venue"
},
  "geometry": {"coordinates":[-0.887412,51.446022],"type":"Point"}
}