{
  "type": "Feature",
  "properties": {
    "iso:country":"GB",
    "sg:address":"1 White Stubbs Cottages, Carneles Green",
    "sg:city":"Broxbourne",
    "sg:classifiers":[
        {
            "category":"Building & Trades",
            "subcategory":"Construction",
            "type":"Services"
        }
    ],
    "sg:phone":"+44 1992 465053",
    "sg:postcode":"EN10 7QB",
    "sg:province":"Essex",
    "sg:tags":[
        "joiner",
        "carpenter"
    ],
    "wof:name":"Michael H Dear",
    "wof:placetype":"venue"
},
  "geometry": {"coordinates":[-0.02046,51.743214],"type":"Point"}
}