{
  "type": "Feature",
  "properties": {
    "iso:country":"GB",
    "sg:address":"39 Winsford Avenue, Allesey",
    "sg:city":"Coventry",
    "sg:classifiers":[
        {
            "category":"Food & Beverages",
            "subcategory":"Meat & Fish",
            "type":"Retail Goods"
        }
    ],
    "sg:postcode":"CV5 9JG",
    "sg:province":"West Midlands",
    "sg:tags":[
        "butcher"
    ],
    "wof:name":"Alan Taylor Butchers",
    "wof:placetype":"venue"
},
  "geometry": {"coordinates":[-1.554535,52.413246],"type":"Point"}
}