{
  "type": "Feature",
  "properties": {
    "iso:country":"GB",
    "sg:address":"Unit 21 Heathbrook, Llanishen",
    "sg:city":"Cardiff",
    "sg:classifiers":[
        {
            "category":"Retail",
            "subcategory":"Repair Shop",
            "type":"Services"
        }
    ],
    "sg:postcode":"CF14 5FA",
    "sg:province":"Cardiff",
    "sg:tags":[
        "maintenance"
    ],
    "wof:name":"Cymraeg Property Services",
    "wof:placetype":"venue"
},
  "geometry": {"coordinates":[-3.182751,51.521664],"type":"Point"}
}