{
  "type": "Feature",
  "properties": {
    "addr:full":"Edward St Carlisle Cumbria CA1 2JB",
    "addr:postcode":"ca1 2jb",
    "addr:street":"Edward St",
    "iso:country":"GB",
    "sg:address":"Edward St",
    "sg:city":"Carlisle",
    "sg:classifiers":[
        {
            "category":"Place Of Worship",
            "type":"Public Place"
        }
    ],
    "sg:phone":"+44 1228 526474",
    "sg:postcode":"CA1 2JB",
    "sg:province":"Cumbria",
    "wof:name":"Elim Free Church",
    "wof:placetype":"venue"
},
  "geometry": {"coordinates":[-2.925483942,54.8901100159],"type":"Point"}
}