{
  "type": "Feature",
  "properties": {
    "addr:full":"77 Beaufort Mansions, Beaufort Street London Greater London SW3 5AF",
    "addr:housenumber":"77",
    "addr:postcode":"sw3 5af",
    "addr:street":"Beaufort Street",
    "iso:country":"GB",
    "sg:address":"77 Beaufort Mansions, Beaufort Street",
    "sg:city":"London",
    "sg:classifiers":[
        {
            "category":"Professional",
            "subcategory":"Accounting & Tax Preparation",
            "type":"Services"
        }
    ],
    "sg:postcode":"SW3 5AF",
    "sg:province":"Greater London",
    "sg:tags":[
        "accountant"
    ],
    "wof:name":"Wild Front Ear Ltd",
    "wof:placetype":"venue"
},
  "geometry": {"coordinates":[-0.1749199927,51.4833106995],"type":"Point"}
}