{
  "type": "Feature",
  "properties": {
    "addr:full":"8 Nursery Ave Kilmarnock East Ayrshire KA1 3DT",
    "addr:housenumber":"8",
    "addr:postcode":"ka1 3dt",
    "addr:street":"Nursery Ave",
    "iso:country":"GB",
    "sg:address":"8 Nursery Ave",
    "sg:city":"Kilmarnock",
    "sg:classifiers":[
        {
            "category":"Social Services",
            "subcategory":"Retirement Home",
            "type":"Services"
        }
    ],
    "sg:phone":"+44 1563 532437",
    "sg:postcode":"KA1 3DT",
    "sg:province":"East Ayrshire",
    "sg:tags":[
        "care"
    ],
    "wof:name":"Mclellan Michael",
    "wof:placetype":"venue"
},
  "geometry": {"coordinates":[-4.4859828949,55.6070251465],"type":"Point"}
}