{
  "type": "Feature",
  "properties": {
    "iso:country":"GB",
    "sg:address":"132 High Street, Worle",
    "sg:city":"Weston Super Mare",
    "sg:classifiers":[
        {
            "category":"Shopping",
            "subcategory":"Department Store",
            "type":"Retail Goods"
        }
    ],
    "sg:phone":"+44 1934 513701",
    "sg:postcode":"BS22 6HE",
    "sg:province":"Somerset",
    "wof:name":"Murari L Takyar",
    "wof:placetype":"venue"
},
  "geometry": {"coordinates":[-2.928759,51.359772],"type":"Point"}
}