{
  "type": "Feature",
  "properties": {
    "addr:full":"40 Nightingale Way, Leegomery Telford Shropshire TF1 6DT",
    "addr:housenumber":"40",
    "addr:postcode":"tf1 6dt",
    "addr:street":"Nightingale Way",
    "iso:country":"GB",
    "sg:address":"40 Nightingale Way, Leegomery",
    "sg:city":"Telford",
    "sg:classifiers":[
        {
            "category":"Building & Trades",
            "subcategory":"Construction",
            "type":"Services"
        },
        {
            "category":"Home & Garden",
            "subcategory":"Carpets & Floor Coverings",
            "type":"Retail Goods"
        }
    ],
    "sg:postcode":"TF1 6DT",
    "sg:province":"Shropshire",
    "sg:tags":[
        "textile",
        "flooring",
        "floorcoverings"
    ],
    "wof:name":"Jones,Ian,",
    "wof:placetype":"venue"
},
  "geometry": {"coordinates":[-2.504298,52.711514],"type":"Point"}
}