{
  "type": "Feature",
  "properties": {
    "iso:country":"GB",
    "sg:address":"Bishop Browns House, Durham Street",
    "sg:city":"Cardiff",
    "sg:classifiers":[
        {
            "category":"Organizations",
            "subcategory":"Non-profit Organization",
            "type":"Services"
        }
    ],
    "sg:phone":"+44 29 2066 7007",
    "sg:postcode":"CF11 6PB",
    "sg:province":"Cardiff",
    "sg:tags":[
        "organisation",
        "voluntary",
        "charity"
    ],
    "wof:name":"St. David's Children Society",
    "wof:placetype":"venue"
},
  "geometry": {"coordinates":[-3.187602,51.470684],"type":"Point"}
}