{
  "type": "Feature",
  "properties": {
    "addr:full":"Golf Road, Formby Liverpool Lancashire L37 1LQ",
    "addr:postcode":"l37 1lq",
    "addr:street":"Golf Road",
    "iso:country":"GB",
    "sg:address":"Golf Road, Formby",
    "sg:city":"Liverpool",
    "sg:classifiers":[
        {
            "category":"Sports & Exercise",
            "subcategory":"Golf",
            "type":"Entertainment"
        }
    ],
    "sg:postcode":"L37 1LQ",
    "sg:province":"Lancashire",
    "sg:tags":[
        "club",
        "course"
    ],
    "wof:name":"Formby Golf Club Ltd.",
    "wof:placetype":"venue"
},
  "geometry": {"coordinates":[-3.07233,53.566547],"type":"Point"}
}