{
  "type": "Feature",
  "properties": {
    "addr:full":"Flowery Leys Lane Alfreton Derbyshire DE55 7HA",
    "addr:postcode":"de55 7ha",
    "addr:street":"Flowery Leys Lane",
    "iso:country":"GB",
    "sg:address":"Flowery Leys Lane",
    "sg:city":"Alfreton",
    "sg:classifiers":[
        {
            "category":"Education",
            "subcategory":"School",
            "type":"Public Place"
        }
    ],
    "sg:phone":"+44 1773 832895",
    "sg:postcode":"DE55 7HA",
    "sg:province":"Derbyshire",
    "sg:tags":[
        "local",
        "authority"
    ],
    "wof:name":"Leys Junior School",
    "wof:placetype":"venue"
},
  "geometry": {"coordinates":[-1.372985,53.094646],"type":"Point"}
}