{
  "type": "Feature",
  "properties": {
    "iso:country":"GB",
    "sg:address":"4 Bridge Street",
    "sg:city":"Appleby-in-westmorland",
    "sg:classifiers":[
        {
            "category":"Shopping",
            "subcategory":"Stationery & Office Supplies",
            "type":"Retail Goods"
        }
    ],
    "sg:postcode":"CA16 6QH",
    "sg:province":"Cumbria",
    "wof:name":"Whiteheads of Appleby",
    "wof:placetype":"venue"
},
  "geometry": {"coordinates":[-2.4907341003,54.5781097412],"type":"Point"}
}