{
  "type": "Feature",
  "properties": {
    "iso:country":"GB",
    "sg:address":"Finsbury Health Centre, 11 Pine St",
    "sg:city":"Clerkenwell",
    "sg:classifiers":[
        {
            "category":"Health Services",
            "subcategory":"Doctor",
            "type":"Services"
        }
    ],
    "sg:phone":"+44 20 7837 9837",
    "sg:postcode":"EC1R 0JH",
    "sg:province":"Greater London",
    "sg:tags":[
        "practitioners"
    ],
    "wof:name":"Mills, S M",
    "wof:placetype":"venue"
},
  "geometry": {"coordinates":[-0.10987,51.52507],"type":"Point"}
}