{
  "type": "Feature",
  "properties": {
    "iso:country":"GB",
    "sg:address":"39 High Street",
    "sg:city":"Kington",
    "sg:classifiers":[
        {
            "category":"Food & Beverages",
            "subcategory":"Meat & Fish",
            "type":"Retail Goods"
        }
    ],
    "sg:phone":"+44 1544 230470",
    "sg:postcode":"HR5 3BJ",
    "sg:province":"Herefordshire",
    "sg:tags":[
        "butcher"
    ],
    "wof:name":"Glyn Slade Jones",
    "wof:placetype":"venue"
},
  "geometry": {"coordinates":[-3.030278,52.20332],"type":"Point"}
}