{
  "type": "Feature",
  "properties": {
    "iso:country":"GB",
    "sg:address":"41 Jeffries Hill Bottom",
    "sg:city":"Bristol",
    "sg:classifiers":[
        {
            "category":"Building & Trades",
            "subcategory":"Cleaning & Sanitation",
            "type":"Services"
        }
    ],
    "sg:postcode":"BS15 3BE",
    "sg:province":"City of Bristol",
    "sg:tags":[
        "commercial"
    ],
    "wof:name":"P J Howell",
    "wof:placetype":"venue"
},
  "geometry": {"coordinates":[-2.5255510807,51.4493980408],"type":"Point"}
}