{
  "type": "Feature",
  "properties": {
    "iso:country":"GB",
    "sg:address":"3 West Marden",
    "sg:city":"Chichester",
    "sg:classifiers":[
        {
            "category":"Professional",
            "subcategory":"Engineering",
            "type":"Services"
        }
    ],
    "sg:postcode":"PO18 9ES",
    "sg:province":"West Sussex",
    "sg:tags":[
        "contractor",
        "electrical",
        "engineer"
    ],
    "wof:name":"Ky Edwards",
    "wof:placetype":"venue"
},
  "geometry": {"coordinates":[-0.90539,50.916302],"type":"Point"}
}