{
  "type": "Feature",
  "properties": {
    "iso:country":"GB",
    "sg:address":"48 Cassillis Road",
    "sg:city":"Maybole",
    "sg:classifiers":[
        {
            "category":"Manufacturing",
            "subcategory":"Textiles",
            "type":"Manufacturing & Wholesale Goods"
        }
    ],
    "sg:postcode":"KA19 7HF",
    "sg:province":"East Ayrshire",
    "sg:tags":[
        "knitwear"
    ],
    "wof:name":"A Y Agencies",
    "wof:placetype":"venue"
},
  "geometry": {"coordinates":[-4.679853,55.355499],"type":"Point"}
}