{
  "type": "Feature",
  "properties": {
    "addr:full":"48 Cassillis Road Maybole East Ayrshire KA19 7HF",
    "addr:housenumber":"48",
    "addr:postcode":"ka19 7hf",
    "addr:street":"Cassillis Road",
    "iso:country":"GB",
    "sg:address":"48 Cassillis Road",
    "sg:city":"Maybole",
    "sg:classifiers":[
        {
            "category":"Manufacturing",
            "subcategory":"Textiles",
            "type":"Manufacturing & Wholesale Goods"
        }
    ],
    "sg:postcode":"KA19 7HF",
    "sg:province":"East Ayrshire",
    "sg:tags":[
        "knitwear"
    ],
    "wof:name":"A Y Agencies",
    "wof:placetype":"venue"
},
  "geometry": {"coordinates":[-4.679853,55.355499],"type":"Point"}
}