{
  "type": "Feature",
  "properties": {
    "addr:full":"19a Coombe Rd New Malden Surrey KT3 4PX",
    "addr:housenumber":"19a",
    "addr:postcode":"kt3 4px",
    "addr:street":"Coombe Rd",
    "iso:country":"GB",
    "sg:address":"19a Coombe Rd",
    "sg:city":"New Malden",
    "sg:classifiers":[
        {
            "category":"Shopping",
            "subcategory":"Catalog Store",
            "type":"Retail Goods"
        }
    ],
    "sg:postcode":"KT3 4PX",
    "sg:province":"Surrey",
    "sg:tags":[
        "mail",
        "order"
    ],
    "wof:name":"U C Results",
    "wof:placetype":"venue"
},
  "geometry": {"coordinates":[-0.2568509877,51.4044494629],"type":"Point"}
}