{
  "type": "Feature",
  "properties": {
    "addr:full":"10 Albany Close Fleet Hampshire GU51 3PY",
    "addr:housenumber":"10",
    "addr:postcode":"gu51 3py",
    "addr:street":"Albany Close",
    "iso:country":"GB",
    "sg:address":"10 Albany Close",
    "sg:city":"Fleet",
    "sg:classifiers":[
        {
            "category":"Military Area",
            "subcategory":"Air Force Base",
            "type":"Public Place"
        }
    ],
    "sg:phone":"+44 1252 815888",
    "sg:postcode":"GU51 3PY",
    "sg:province":"Hampshire",
    "sg:tags":[
        "taxi",
        "hire",
        "private"
    ],
    "wof:name":"Acorn Cabs",
    "wof:placetype":"venue"
},
  "geometry": {"coordinates":[-0.827025,51.278557],"type":"Point"}
}