{
  "type": "Feature",
  "properties": {
    "iso:country":"GB",
    "sg:address":"8 Northburgh Street",
    "sg:city":"London",
    "sg:classifiers":[
        {
            "category":"Professional",
            "subcategory":"Art Services",
            "type":"Services"
        }
    ],
    "sg:phone":"+44 20 8253 5444",
    "sg:postcode":"EC1V 0AY",
    "sg:province":"Greater London",
    "sg:tags":[
        "graphic",
        "designer"
    ],
    "wof:name":"Gableglade Ltd.",
    "wof:placetype":"venue"
},
  "geometry": {"coordinates":[-0.1000740007,51.5240783691],"type":"Point"}
}