{
  "type": "Feature",
  "properties": {
    "iso:country":"GB",
    "sg:address":"Quoit Farm, Stanton Drew",
    "sg:city":"Bristol",
    "sg:classifiers":[
        {
            "category":"Farming",
            "subcategory":"Livestock Farm",
            "type":"Manufacturing & Wholesale Goods"
        }
    ],
    "sg:phone":"+44 1275 332594",
    "sg:postcode":"BS39 4ES",
    "sg:province":"Somerset",
    "sg:tags":[
        "others"
    ],
    "wof:name":"David Tibbs",
    "wof:placetype":"venue"
},
  "geometry": {"coordinates":[-2.580069,51.366444],"type":"Point"}
}