{
  "type": "Feature",
  "properties": {
    "addr:full":"108 Infirmary Road Sheffield South Yorkshire S6 3DG",
    "addr:housenumber":"108",
    "addr:postcode":"s6 3dg",
    "addr:street":"Infirmary Road",
    "iso:country":"GB",
    "sg:address":"108 Infirmary Road",
    "sg:city":"Sheffield",
    "sg:classifiers":[
        {
            "category":"Shopping",
            "subcategory":"Shoes",
            "type":"Retail Goods"
        }
    ],
    "sg:phone":"+44 114 273 7903",
    "sg:postcode":"S6 3DG",
    "sg:province":"South Yorkshire",
    "sg:tags":[
        "shop",
        "retailer",
        "footwear"
    ],
    "wof:name":"Wynsors World Of Shoes",
    "wof:placetype":"venue"
},
  "geometry": {"coordinates":[-1.4824960232,53.3910865784],"type":"Point"}
}