{
  "type": "Feature",
  "properties": {
    "iso:country":"GB",
    "sg:address":"Cornerways, Bulkington Road, Shilton",
    "sg:city":"Coventry",
    "sg:classifiers":[
        {
            "category":"Building & Trades",
            "subcategory":"Construction",
            "type":"Services"
        }
    ],
    "sg:phone":"+44 24 7661 2633",
    "sg:postcode":"CV7 9JS",
    "sg:province":"Warwickshire",
    "sg:tags":[
        "builder"
    ],
    "wof:name":"F J Cafferty",
    "wof:placetype":"venue"
},
  "geometry": {"coordinates":[-1.405547,52.456535],"type":"Point"}
}