{
  "type": "Feature",
  "properties": {
    "addr:full":"3 Whitton Road Stockton-on-tees Durham TS19 7EE",
    "addr:housenumber":"3",
    "addr:postcode":"ts19 7ee",
    "addr:street":"Whitton Road",
    "iso:country":"GB",
    "sg:address":"3 Whitton Road",
    "sg:city":"Stockton-on-tees",
    "sg:classifiers":[
        {
            "category":"Professional",
            "subcategory":"Accounting & Tax Preparation",
            "type":"Services"
        }
    ],
    "sg:phone":"+44 1642 587711",
    "sg:postcode":"TS19 7EE",
    "sg:province":"Durham",
    "sg:tags":[
        "accountant"
    ],
    "wof:name":"Paul Jarvis & Co",
    "wof:placetype":"venue"
},
  "geometry": {"coordinates":[-1.349650979,54.5627212524],"type":"Point"}
}