{
  "type": "Feature",
  "properties": {
    "iso:country":"GB",
    "sg:address":"21 Crackenedge La",
    "sg:city":"Dewsbury",
    "sg:classifiers":[
        {
            "category":"Manufacturing",
            "subcategory":"Tools & Machinery",
            "type":"Manufacturing & Wholesale Goods"
        }
    ],
    "sg:postcode":"WF13 1PU",
    "sg:province":"West Yorkshire",
    "sg:tags":[
        "society",
        "friendly"
    ],
    "wof:name":"Refuge Assurance Plc",
    "wof:placetype":"venue"
},
  "geometry": {"coordinates":[-1.6277229786,53.6925582886],"type":"Point"}
}