{
  "type": "Feature",
  "properties": {
    "addr:full":"Balconie Street, Evanton Dingwall Highland IV16 9UN",
    "addr:postcode":"iv16 9un",
    "addr:street":"Balconie Street",
    "iso:country":"GB",
    "sg:address":"Balconie Street, Evanton",
    "sg:city":"Dingwall",
    "sg:classifiers":[
        {
            "category":"Recreation",
            "subcategory":"Campground",
            "type":"Entertainment"
        }
    ],
    "sg:phone":"+44 1349 830917",
    "sg:postcode":"IV16 9UN",
    "sg:province":"Highland",
    "sg:tags":[
        "caravan",
        "park",
        "site",
        "camping"
    ],
    "wof:name":"K & H Petley",
    "wof:placetype":"venue"
},
  "geometry": {"coordinates":[-4.3363437653,57.663646698],"type":"Point"}
}