{
  "type": "Feature",
  "properties": {
    "iso:country":"GB",
    "sg:address":"Treetops, Pilgrims Way",
    "sg:city":"Tonbridge",
    "sg:classifiers":[
        {
            "category":"Building & Trades",
            "subcategory":"Plumbing",
            "type":"Services"
        }
    ],
    "sg:phone":"+44 1959 564269",
    "sg:postcode":"TN11 9BH",
    "sg:province":"Kent",
    "sg:tags":[
        "heating"
    ],
    "wof:name":"Kesterel  Mechanical  S Ervices Ltd",
    "wof:placetype":"venue"
},
  "geometry": {"coordinates":[0.25912,51.207989],"type":"Point"}
}