{
  "type": "Feature",
  "properties": {
    "iso:country":"GB",
    "sg:address":"Langlands Mill",
    "sg:city":"Melrose",
    "sg:classifiers":[
        {
            "category":"Retail",
            "subcategory":"Auto Repair",
            "type":"Services"
        }
    ],
    "sg:phone":"+44 1835 823002",
    "sg:postcode":"TD6 0RY",
    "sg:province":"Scottish Borders",
    "sg:tags":[
        "modification",
        "garage"
    ],
    "wof:name":"Halltune Garage",
    "wof:placetype":"venue"
},
  "geometry": {"coordinates":[-2.737578,55.598831],"type":"Point"}
}