{
  "type": "Feature",
  "properties": {
    "addr:full":"Branley Middle Road, Tiptoe Lymington Hampshire SO41 6FX",
    "addr:postcode":"so41 6fx",
    "addr:street":"Middle Road Tiptoe",
    "iso:country":"GB",
    "sg:address":"Branley Middle Road, Tiptoe",
    "sg:city":"Lymington",
    "sg:classifiers":[
        {
            "category":"Building & Trades",
            "subcategory":"Landscaping Services",
            "type":"Services"
        }
    ],
    "sg:phone":"+44 1590 682787",
    "sg:postcode":"SO41 6FX",
    "sg:province":"Hampshire",
    "sg:tags":[
        "gardening"
    ],
    "wof:name":"J F Street",
    "wof:placetype":"venue"
},
  "geometry": {"coordinates":[-1.638167,50.779064],"type":"Point"}
}