{
  "type": "Feature",
  "properties": {
    "addr:full":"Broadwaters Drive Kidderminster Staffordshire DY10 2RY",
    "addr:postcode":"dy10 2ry",
    "addr:street":"Broadwaters Drive",
    "iso:country":"GB",
    "sg:address":"Broadwaters Drive",
    "sg:city":"Kidderminster",
    "sg:classifiers":[
        {
            "category":"Government",
            "subcategory":"City Hall",
            "type":"Public Place"
        },
        {
            "category":"Retail",
            "subcategory":"Event Space",
            "type":"Services"
        }
    ],
    "sg:phone":"+44 1562 751265",
    "sg:postcode":"DY10 2RY",
    "sg:province":"Staffordshire",
    "sg:tags":[
        "function",
        "hire",
        "room"
    ],
    "wof:name":"St Oswald's Church Centre",
    "wof:placetype":"venue"
},
  "geometry": {"coordinates":[-2.2347140312,52.399433136],"type":"Point"}
}