{
  "type": "Feature",
  "properties": {
    "addr:full":"Longton House, Burnley Road, Clayton-le-moors Accrington Lancashire BB5 5TW",
    "addr:postcode":"bb5 5tw",
    "addr:street":"Burnley Road Clayton-Le-Moors Accrington",
    "iso:country":"GB",
    "sg:address":"Longton House, Burnley Road, Clayton-le-moors",
    "sg:city":"Accrington",
    "sg:classifiers":[
        {
            "category":"Government",
            "subcategory":"Post Office",
            "type":"Public Place"
        }
    ],
    "sg:phone":"+44 1254 395801",
    "sg:postcode":"BB5 5TW",
    "sg:province":"Lancashire",
    "sg:tags":[
        "messenger",
        "courier"
    ],
    "wof:name":"Accolade Logistics Ltd.",
    "wof:placetype":"venue"
},
  "geometry": {"coordinates":[-2.3538870811,53.7906112671],"type":"Point"}
}