{
  "type": "Feature",
  "properties": {
    "addr:full":"84c High Street Northallerton North Yorkshire DL7 8PP",
    "addr:housenumber":"84c",
    "addr:postcode":"dl7 8pp",
    "addr:street":"High Street",
    "iso:country":"GB",
    "sg:address":"84c High Street",
    "sg:city":"Northallerton",
    "sg:classifiers":[
        {
            "category":"Shopping",
            "subcategory":"Computers & Home Electronics",
            "type":"Retail Goods"
        }
    ],
    "sg:phone":"+44 1609 779681",
    "sg:postcode":"DL7 8PP",
    "sg:province":"North Yorkshire",
    "sg:tags":[
        "electrical"
    ],
    "wof:name":"City Electrical Factors Ltd.",
    "wof:placetype":"venue"
},
  "geometry": {"coordinates":[-1.434201,54.340054],"type":"Point"}
}