{
  "type": "Feature",
  "properties": {
    "iso:country":"GB",
    "sg:address":"56a Sunnybank Road, Greetland",
    "sg:city":"Halifax",
    "sg:classifiers":[
        {
            "category":"Building & Trades",
            "subcategory":"Plumbing",
            "type":"Services"
        }
    ],
    "sg:phone":"+44 1422 371569",
    "sg:postcode":"HX4 8JP",
    "sg:province":"West Yorkshire",
    "sg:tags":[
        "central",
        "heating"
    ],
    "wof:name":"David Beaumont",
    "wof:placetype":"venue"
},
  "geometry": {"coordinates":[-1.8722779751,53.6871528625],"type":"Point"}
}