{
  "type": "Feature",
  "properties": {
    "addr:full":"Unit 3 Whitehall Estate, Flex Meadow, The Pinnacles Harlow Essex CM19 5TJ",
    "addr:housenumber":"unit 3",
    "addr:postcode":"cm19 5tj",
    "addr:street":"Whitehall;Flex Meadow The Pinnacles",
    "iso:country":"GB",
    "sg:address":"Unit 3 Whitehall Estate, Flex Meadow, The Pinnacles",
    "sg:city":"Harlow",
    "sg:classifiers":[
        {
            "category":"Shopping",
            "subcategory":"Stationery & Office Supplies",
            "type":"Retail Goods"
        }
    ],
    "sg:phone":"+44 1279 439544",
    "sg:postcode":"CM19 5TJ",
    "sg:province":"Essex",
    "sg:tags":[
        "printers'"
    ],
    "wof:name":"Stehlin Hostag Inc (Uk)",
    "wof:placetype":"venue"
},
  "geometry": {"coordinates":[0.0678080022,51.7630500793],"type":"Point"}
}