{
  "type": "Feature",
  "properties": {
    "addr:full":"Saltersford Macclesfield Cheshire SK10 5XL",
    "addr:postcode":"sk10 5xl",
    "addr:street":"Saltersford",
    "iso:country":"GB",
    "sg:address":"Saltersford",
    "sg:city":"Macclesfield",
    "sg:classifiers":[
        {
            "category":"Place Of Worship",
            "type":"Public Place"
        }
    ],
    "sg:phone":"+44 1625 572013",
    "sg:postcode":"SK10 5XL",
    "sg:province":"Cheshire",
    "wof:name":"St John The Baptist C Of E Church",
    "wof:placetype":"venue"
},
  "geometry": {"coordinates":[-2.092239,53.29847],"type":"Point"}
}