{
  "type": "Feature",
  "properties": {
    "iso:country":"GB",
    "sg:address":"Belmont St",
    "sg:city":"Bognor Regis",
    "sg:classifiers":[
        {
            "category":"Shopping",
            "subcategory":"Bicycles & Sporting Goods",
            "type":"Retail Goods"
        }
    ],
    "sg:phone":"+44 1243 866311",
    "sg:postcode":"PO21 2LH",
    "sg:province":"West Sussex",
    "sg:tags":[
        "cycle",
        "accessory"
    ],
    "wof:name":"Marramba Cat",
    "wof:placetype":"venue"
},
  "geometry": {"coordinates":[-0.6696190238,50.7836761475],"type":"Point"}
}