{
  "type": "Feature",
  "properties": {
    "iso:country":"GB",
    "sg:address":"4 Unity Terrace, Harelaw, Dipton",
    "sg:city":"Stanley",
    "sg:classifiers":[
        {
            "category":"Building & Trades",
            "subcategory":"Plumbing",
            "type":"Services"
        }
    ],
    "sg:postcode":"DH9 9BA",
    "sg:province":"Durham",
    "sg:tags":[
        "heating"
    ],
    "wof:name":"A 1 Plumbing & Electrical",
    "wof:placetype":"venue"
},
  "geometry": {"coordinates":[-1.751619,54.874584],"type":"Point"}
}