{
  "type": "Feature",
  "properties": {
    "iso:country":"GB",
    "sg:address":"2 Augusta Street",
    "sg:city":"Grimsby",
    "sg:classifiers":[
        {
            "category":"Retail",
            "subcategory":"Veterinary Services",
            "type":"Services"
        }
    ],
    "sg:phone":"+44 1472 347054",
    "sg:postcode":"DN34 4TA",
    "sg:province":"Lincolnshire",
    "sg:tags":[
        "surgeon",
        "activity"
    ],
    "wof:name":"Abbey Veterinary Centre",
    "wof:placetype":"venue"
},
  "geometry": {"coordinates":[-0.092688,53.559715],"type":"Point"}
}