{
  "type": "Feature",
  "properties": {
    "iso:country":"GB",
    "sg:address":"Stretton Road, Clay Cross",
    "sg:city":"Chesterfield",
    "sg:classifiers":[
        {
            "category":"Organizations",
            "subcategory":"Religious Organization",
            "type":"Services"
        }
    ],
    "sg:phone":"+44 1246 862621",
    "sg:postcode":"S45 9AQ",
    "sg:province":"Derbyshire",
    "sg:tags":[
        "organisation"
    ],
    "wof:name":"St. Clares Convent",
    "wof:placetype":"venue"
},
  "geometry": {"coordinates":[-1.4135309458,53.1542549133],"type":"Point"}
}