{
  "type": "Feature",
  "properties": {
    "addr:full":"Kingsway House, Cat Street Hartfield East Sussex TN7 4DS",
    "addr:postcode":"tn7 4ds",
    "addr:street":"Cat Street",
    "iso:country":"GB",
    "sg:address":"Kingsway House, Cat Street",
    "sg:city":"Hartfield",
    "sg:classifiers":[
        {
            "category":"Autos & Motor Vehicles",
            "subcategory":"Automobile Sales",
            "type":"Retail Goods"
        }
    ],
    "sg:postcode":"TN7 4DS",
    "sg:province":"East Sussex",
    "sg:tags":[
        "car"
    ],
    "wof:name":"Village Cars",
    "wof:placetype":"venue"
},
  "geometry": {"coordinates":[0.0790510029,51.0880050659],"type":"Point"}
}