{
  "type": "Feature",
  "properties": {
    "iso:country":"GB",
    "sg:address":"Cotmanhay Road",
    "sg:city":"Ilkeston",
    "sg:classifiers":[
        {
            "category":"Bars & Pubs",
            "type":"Food & Drink"
        }
    ],
    "sg:phone":"+44 115 944 2249",
    "sg:postcode":"DE7 8HU",
    "sg:province":"Derbyshire",
    "sg:tags":[
        "pubs",
        "inn"
    ],
    "wof:name":"Great Northern Inn",
    "wof:placetype":"venue"
},
  "geometry": {"coordinates":[-1.3074740171,52.9897918701],"type":"Point"}
}