{
  "type": "Feature",
  "properties": {
    "iso:country":"GB",
    "sg:address":"5 Queens Corner",
    "sg:city":"Colchester",
    "sg:classifiers":[
        {
            "category":"Shopping",
            "subcategory":"Pets & Pet Supplies",
            "type":"Retail Goods"
        }
    ],
    "sg:phone":"+44 1206 386878",
    "sg:postcode":"CO5 8RG",
    "sg:province":"Essex",
    "sg:tags":[
        "food"
    ],
    "wof:name":"Pet Food & Things",
    "wof:placetype":"venue"
},
  "geometry": {"coordinates":[0.9199410081,51.7807540894],"type":"Point"}
}