{
  "type": "Feature",
  "properties": {
    "iso:country":"GB",
    "sg:address":"300 Brook Street, Broughty Ferry",
    "sg:city":"Dundee",
    "sg:classifiers":[
        {
            "category":"Shopping",
            "subcategory":"Pets & Pet Supplies",
            "type":"Retail Goods"
        }
    ],
    "sg:phone":"+44 1382 775406",
    "sg:postcode":"DD5 2AN",
    "sg:province":"Angus",
    "wof:name":"John Sinclair",
    "wof:placetype":"venue"
},
  "geometry": {"coordinates":[-2.871931,56.466736],"type":"Point"}
}