{
  "type": "Feature",
  "properties": {
    "addr:full":"750 Newport Road, Rumney Cardiff Caerphilly CF3 4FF",
    "addr:housenumber":"750",
    "addr:postcode":"cf3 4ff",
    "addr:street":"Newport Road",
    "iso:country":"GB",
    "sg:address":"750 Newport Road, Rumney",
    "sg:city":"Cardiff",
    "sg:classifiers":[
        {
            "category":"Building & Trades",
            "subcategory":"Construction",
            "type":"Services"
        }
    ],
    "sg:phone":"+44 29 2079 6833",
    "sg:postcode":"CF3 4FF",
    "sg:province":"Caerphilly",
    "sg:tags":[
        "builder"
    ],
    "wof:name":"N Wiley",
    "wof:placetype":"venue"
},
  "geometry": {"coordinates":[-3.1338059902,51.5069847107],"type":"Point"}
}