{
  "type": "Feature",
  "properties": {
    "iso:country":"GB",
    "sg:address":"1 West Blackhall Street",
    "sg:city":"Greenock",
    "sg:classifiers":[
        {
            "category":"Shopping",
            "subcategory":"Clothing, Apparel, & Fashions",
            "type":"Retail Goods"
        }
    ],
    "sg:phone":"+44 1475 888182",
    "sg:postcode":"PA15 1UA",
    "sg:province":"Inverclyde",
    "sg:tags":[
        "shop"
    ],
    "wof:name":"Domani Clothing",
    "wof:placetype":"venue"
},
  "geometry": {"coordinates":[-4.760716,55.949406],"type":"Point"}
}