{
  "type": "Feature",
  "properties": {
    "iso:country":"GB",
    "sg:address":"21-23 Edgwarebury Lane",
    "sg:city":"Edgware",
    "sg:classifiers":[
        {
            "category":"Food & Beverages",
            "subcategory":"Meat & Fish",
            "type":"Retail Goods"
        }
    ],
    "sg:phone":"+44 20 8958 5945",
    "sg:postcode":"HA8 8LH",
    "sg:province":"Greater London",
    "sg:tags":[
        "butcher"
    ],
    "wof:name":"Louis Mann & Son Ltd.",
    "wof:placetype":"venue"
},
  "geometry": {"coordinates":[-0.27808,51.616058],"type":"Point"}
}