{
  "type": "Feature",
  "properties": {
    "addr:full":"60 Prestbury Rd Cheltenham Gloucestershire GL52 2DA",
    "addr:housenumber":"60",
    "addr:postcode":"gl52 2da",
    "addr:street":"Prestbury Rd",
    "iso:country":"GB",
    "sg:address":"60 Prestbury Rd",
    "sg:city":"Cheltenham",
    "sg:classifiers":[
        {
            "category":"Real Estate",
            "subcategory":"Surveying",
            "type":"Services"
        }
    ],
    "sg:phone":"+44 1242 529111",
    "sg:postcode":"GL52 2DA",
    "sg:province":"Gloucestershire",
    "sg:tags":[
        "surveyor",
        "quantity"
    ],
    "wof:name":"J Baddeley",
    "wof:placetype":"venue"
},
  "geometry": {"coordinates":[-2.0645639896,51.90599823],"type":"Point"}
}