{
  "type": "Feature",
  "properties": {
    "iso:country":"GB",
    "sg:address":"Fielden Square",
    "sg:city":"Todmorden",
    "sg:classifiers":[
        {
            "category":"Bars & Pubs",
            "type":"Food & Drink"
        }
    ],
    "sg:phone":"+44 1706 813532",
    "sg:postcode":"OL14 6LZ",
    "sg:province":"Lancashire",
    "sg:tags":[
        "pubs",
        "inn"
    ],
    "wof:name":"GOLDEN LION HOTEL",
    "wof:placetype":"venue"
},
  "geometry": {"coordinates":[-2.0988259315,53.7121086121],"type":"Point"}
}