{
  "type": "Feature",
  "properties": {
    "iso:country":"GB",
    "sg:address":"19 Market Pl",
    "sg:city":"Holt",
    "sg:classifiers":[
        {
            "category":"Real Estate",
            "subcategory":"Architect",
            "type":"Services"
        }
    ],
    "sg:postcode":"NR25 6BE",
    "sg:province":"Norfolk",
    "wof:name":"Faulkner,Anthony,Architect",
    "wof:placetype":"venue"
},
  "geometry": {"coordinates":[1.0892549753,52.9061927795],"type":"Point"}
}