{
  "type": "Feature",
  "properties": {
    "addr:full":"83 Dragon Road Harrogate North Yorkshire HG1 5DB",
    "addr:housenumber":"83",
    "addr:postcode":"hg1 5db",
    "addr:street":"Dragon Road",
    "iso:country":"GB",
    "sg:address":"83 Dragon Road",
    "sg:city":"Harrogate",
    "sg:classifiers":[
        {
            "category":"Building & Trades",
            "subcategory":"Plumbing",
            "type":"Services"
        }
    ],
    "sg:phone":"+44 1423 565219",
    "sg:postcode":"HG1 5DB",
    "sg:province":"North Yorkshire",
    "sg:tags":[
        "heating"
    ],
    "wof:name":"L Bonner",
    "wof:placetype":"venue"
},
  "geometry": {"coordinates":[-1.533612,53.998962],"type":"Point"}
}