{
  "type": "Feature",
  "properties": {
    "addr:full":"Ground Floor Interpower House Aldershot Hampshire GU11 1JG",
    "addr:housenumber":"ground floor interpower house aldershot",
    "addr:postcode":"gu11 1jg",
    "iso:country":"GB",
    "sg:address":"Ground Floor Interpower House",
    "sg:city":"Aldershot",
    "sg:classifiers":[
        {
            "category":"Organizations",
            "subcategory":"Membership Organization",
            "type":"Services"
        }
    ],
    "sg:postcode":"GU11 1JG",
    "sg:province":"Hampshire",
    "sg:tags":[
        "club"
    ],
    "wof:name":"Seventh Avondale Residents Association Ltd.",
    "wof:placetype":"venue"
},
  "geometry": {"coordinates":[-0.7593460083,51.2496032715],"type":"Point"}
}