{
  "type": "Feature",
  "properties": {
    "addr:full":"58 Selsea Avenue Herne Bay Kent CT6 8SD",
    "addr:housenumber":"58",
    "addr:postcode":"ct6 8sd",
    "addr:street":"Selsea Avenue",
    "iso:country":"GB",
    "sg:address":"58 Selsea Avenue",
    "sg:city":"Herne Bay",
    "sg:classifiers":[
        {
            "category":"Health Services",
            "subcategory":"Nursing And Care Facility",
            "type":"Services"
        },
        {
            "category":"Social Services",
            "subcategory":"Retirement Home",
            "type":"Services"
        }
    ],
    "sg:phone":"+44 1227 361917",
    "sg:postcode":"CT6 8SD",
    "sg:province":"Kent",
    "sg:tags":[
        "residential"
    ],
    "wof:name":"Wimbledon Hotel",
    "wof:placetype":"venue"
},
  "geometry": {"coordinates":[1.111629,51.369854],"type":"Point"}
}