{
  "type": "Feature",
  "properties": {
    "iso:country":"GB",
    "sg:address":"Unit 1 New England Trading Est, Gascoigne Rd",
    "sg:city":"Barking",
    "sg:classifiers":[
        {
            "category":"Freight",
            "type":"Transportation"
        }
    ],
    "sg:phone":"+44 20 8594 7171",
    "sg:postcode":"IG11 7LN",
    "sg:province":"Essex",
    "sg:tags":[
        "forwarders"
    ],
    "wof:name":"Nedlloyd Road Cargo Ltd",
    "wof:placetype":"venue"
},
  "geometry": {"coordinates":[0.080730997,51.5296821594],"type":"Point"}
}