{
  "type": "Feature",
  "properties": {
    "addr:full":"Weekend Training Centre, Croxton Road Thetford Norfolk IP24 1LH",
    "addr:postcode":"ip24 1lh",
    "addr:street":"Croxton Road",
    "iso:country":"GB",
    "sg:address":"Weekend Training Centre, Croxton Road",
    "sg:city":"Thetford",
    "sg:classifiers":[
        {
            "category":"Community Center",
            "subcategory":"Youth",
            "type":"Public Place"
        }
    ],
    "sg:phone":"+44 1842 764776",
    "sg:postcode":"IP24 1LH",
    "sg:province":"Norfolk",
    "sg:tags":[
        "organisation",
        "centre"
    ],
    "wof:name":"Army Cadet Force",
    "wof:placetype":"venue"
},
  "geometry": {"coordinates":[0.75535,52.442871],"type":"Point"}
}