{
  "type": "Feature",
  "properties": {
    "addr:full":"New Vernon House, Off Villa Street, Beeston Nottingham Nottinghamshire NG9 2NS",
    "addr:postcode":"ng9 2ns",
    "addr:street":"Off Villa Street",
    "iso:country":"GB",
    "sg:address":"New Vernon House, Off Villa Street, Beeston",
    "sg:city":"Nottingham",
    "sg:classifiers":[
        {
            "category":"Real Estate",
            "subcategory":"Surveying",
            "type":"Services"
        }
    ],
    "sg:phone":"+44 115 922 2469",
    "sg:postcode":"NG9 2NS",
    "sg:province":"Nottinghamshire",
    "sg:tags":[
        "surveyor",
        "land"
    ],
    "wof:name":"Survey Three Ltd.",
    "wof:placetype":"venue"
},
  "geometry": {"coordinates":[-1.2154289484,52.9283905029],"type":"Point"}
}