{
  "type": "Feature",
  "properties": {
    "addr:full":"Raglan Health Centre, Chepstow Rd Raglan Monmouthshire NP5 2EN",
    "addr:postcode":"np5 2en",
    "addr:street":"Chepstow Rd",
    "iso:country":"GB",
    "sg:address":"Raglan Health Centre, Chepstow Rd",
    "sg:city":"Raglan",
    "sg:classifiers":[
        {
            "category":"Health Services",
            "subcategory":"Doctor",
            "type":"Services"
        }
    ],
    "sg:phone":"+44 1291 690222",
    "sg:postcode":"NP5 2EN",
    "sg:province":"Monmouthshire",
    "sg:tags":[
        "practitioners"
    ],
    "wof:name":"Downing, J A",
    "wof:placetype":"venue"
},
  "geometry": {"coordinates":[-2.852930069,51.7646484375],"type":"Point"}
}