{
  "type": "Feature",
  "properties": {
    "iso:country":"GB",
    "sg:address":"Spring Group Plc Third Floor, 80 Bishopsgate",
    "sg:city":"London",
    "sg:classifiers":[
        {
            "category":"Professional",
            "subcategory":"Employment Agencies",
            "type":"Services"
        }
    ],
    "sg:postcode":"EC2N 4AU",
    "sg:province":"Greater London",
    "sg:tags":[
        "consultant"
    ],
    "wof:name":"Elizabeth Hunt Recruitment Consultants Ltd.",
    "wof:placetype":"venue"
},
  "geometry": {"coordinates":[-0.0822800025,51.5154304504],"type":"Point"}
}