{
  "type": "Feature",
  "properties": {
    "addr:full":"Rosedale, Allet Truro Cornwall TR4 9DJ",
    "addr:postcode":"tr4 9dj",
    "iso:country":"GB",
    "sg:address":"Rosedale, Allet",
    "sg:city":"Truro",
    "sg:classifiers":[
        {
            "category":"Organizations",
            "subcategory":"Non-profit Organization",
            "type":"Services"
        }
    ],
    "sg:postcode":"TR4 9DJ",
    "sg:province":"Cornwall",
    "sg:tags":[
        "organisation",
        "animal",
        "welfare"
    ],
    "wof:name":"Cats Protection",
    "wof:placetype":"venue"
},
  "geometry": {"coordinates":[-5.102007,50.297386],"type":"Point"}
}