{
  "type": "Feature",
  "properties": {
    "addr:full":"30-32 Marine Road Abergele Conwy LL22 7PR",
    "addr:housenumber":"30-32",
    "addr:postcode":"ll22 7pr",
    "addr:street":"Marine Road",
    "iso:country":"GB",
    "sg:address":"30-32 Marine Road",
    "sg:city":"Abergele",
    "sg:classifiers":[
        {
            "category":"Retail",
            "subcategory":"Laundry & Dry Cleaning",
            "type":"Services"
        }
    ],
    "sg:phone":"+44 1745 826888",
    "sg:postcode":"LL22 7PR",
    "sg:province":"Conwy",
    "sg:tags":[
        "launderette"
    ],
    "wof:name":"The Launderette",
    "wof:placetype":"venue"
},
  "geometry": {"coordinates":[-3.5805430412,53.2941970825],"type":"Point"}
}