{
  "type": "Feature",
  "properties": {
    "addr:full":"Kiln Close Farm, Glasson Wigton Cumbria CA7 5DT",
    "addr:postcode":"ca7 5dt",
    "addr:street":"Kiln Close",
    "iso:country":"GB",
    "sg:address":"Kiln Close Farm, Glasson",
    "sg:city":"Wigton",
    "sg:classifiers":[
        {
            "category":"Farming",
            "subcategory":"Farm",
            "type":"Manufacturing & Wholesale Goods"
        }
    ],
    "sg:phone":"+44 16973 51514",
    "sg:postcode":"CA7 5DT",
    "sg:province":"Cumbria",
    "sg:tags":[
        "mixed",
        "crop"
    ],
    "wof:name":"Robert & Ian Grainger",
    "wof:placetype":"venue"
},
  "geometry": {"coordinates":[-3.167899,54.933735],"type":"Point"}
}