{
  "type": "Feature",
  "properties": {
    "addr:full":"Site 39 Kingston Bdwy, Kingston Industrial Estate Carlisle Cumbria CA3 0HA",
    "addr:housenumber":"39;estate",
    "addr:postcode":"ca3 0ha",
    "addr:street":"Kingston Bdwy;Industrial",
    "iso:country":"GB",
    "sg:address":"Site 39 Kingston Bdwy, Kingston Industrial Estate",
    "sg:city":"Carlisle",
    "sg:classifiers":[
        {
            "category":"Home & Garden",
            "subcategory":"Kitchen Supply",
            "type":"Retail Goods"
        }
    ],
    "sg:phone":"+44 1228 534996",
    "sg:postcode":"CA3 0HA",
    "sg:province":"Cumbria",
    "sg:tags":[
        "equipment",
        "catering"
    ],
    "wof:name":"Border Food Machinery",
    "wof:placetype":"venue"
},
  "geometry": {"coordinates":[-2.9361689091,54.8965148926],"type":"Point"}
}