{
  "type": "Feature",
  "properties": {
    "addr:full":"Gordon Ho Fullerton Rd Wandsworth Greater London SW18 1BX",
    "addr:postcode":"sw18 1bx",
    "addr:street":"Fullerton Rd",
    "iso:country":"GB",
    "sg:address":"Gordon Ho Fullerton Rd",
    "sg:city":"Wandsworth",
    "sg:classifiers":[
        {
            "category":"Building & Trades",
            "subcategory":"Plumbing",
            "type":"Services"
        }
    ],
    "sg:phone":"+44 20 8874 6662",
    "sg:postcode":"SW18 1BX",
    "sg:province":"Greater London",
    "sg:tags":[
        "central",
        "heating"
    ],
    "wof:name":"L H S Engineering",
    "wof:placetype":"venue"
},
  "geometry": {"coordinates":[-0.187629,51.458843],"type":"Point"}
}