{
  "type": "Feature",
  "properties": {
    "addr:full":"Lower City Rd Oldbury West Midlands B69 2HF",
    "addr:postcode":"b69 2hf",
    "addr:street":"Lower City Rd",
    "iso:country":"GB",
    "sg:address":"Lower City Rd",
    "sg:city":"Oldbury",
    "sg:classifiers":[
        {
            "category":"Autos & Motor Vehicles",
            "subcategory":"Auto Supplies",
            "type":"Retail Goods"
        }
    ],
    "sg:phone":"+44 121 544 4100",
    "sg:postcode":"B69 2HF",
    "sg:province":"West Midlands",
    "sg:tags":[
        "gearbox"
    ],
    "wof:name":"A J Commercial Spares",
    "wof:placetype":"venue"
},
  "geometry": {"coordinates":[-2.03725,52.509373],"type":"Point"}
}