{
  "type": "Feature",
  "properties": {
    "iso:country":"GB",
    "sg:address":"19 Bank Street",
    "sg:city":"Irvine",
    "sg:classifiers":[
        {
            "category":"Cinema",
            "subcategory":"Movie Rental",
            "type":"Entertainment"
        }
    ],
    "sg:phone":"+44 1294 275443",
    "sg:postcode":"KA12 0AJ",
    "sg:province":"North Ayrshire",
    "sg:tags":[
        "video",
        "library"
    ],
    "wof:name":"Video Drive in",
    "wof:placetype":"venue"
},
  "geometry": {"coordinates":[-4.664949,55.6157],"type":"Point"}
}