{
  "type": "Feature",
  "properties": {
    "addr:full":"Deugh Studio, Carsphairn Castle Douglas Dumfries and Galloway DG7 3TJ",
    "addr:postcode":"dg7 3tj",
    "addr:street":"Castle",
    "iso:country":"GB",
    "sg:address":"Deugh Studio, Carsphairn",
    "sg:city":"Castle Douglas",
    "sg:classifiers":[
        {
            "category":"Professional",
            "type":"Services"
        }
    ],
    "sg:phone":"+44 1644 460654",
    "sg:postcode":"DG7 3TJ",
    "sg:province":"Dumfries and Galloway",
    "sg:tags":[
        "entertainer"
    ],
    "wof:name":"Funny Faces Face Painting",
    "wof:placetype":"venue"
},
  "geometry": {"coordinates":[-4.259524,55.211975],"type":"Point"}
}