{
  "type": "Feature",
  "properties": {
    "iso:country":"GB",
    "sg:address":"High St",
    "sg:city":"Goole",
    "sg:classifiers":[
        {
            "category":"Bars & Pubs",
            "type":"Food & Drink"
        }
    ],
    "sg:phone":"+44 1757 638357",
    "sg:postcode":"DN14 7HT",
    "sg:province":"East Riding of Yorkshire",
    "sg:tags":[
        "pubs",
        "inn"
    ],
    "wof:name":"Kings Head The",
    "wof:placetype":"venue"
},
  "geometry": {"coordinates":[-0.957848,53.74984],"type":"Point"}
}