{
  "type": "Feature",
  "properties": {
    "addr:full":"57 St Petersgate Stockport Cheshire SK1 1DH",
    "addr:housenumber":"57",
    "addr:postcode":"sk1 1dh",
    "addr:street":"St Petersgate",
    "iso:country":"GB",
    "sg:address":"57 St Petersgate",
    "sg:city":"Stockport",
    "sg:classifiers":[
        {
            "category":"Professional",
            "subcategory":"Employment Agencies",
            "type":"Services"
        }
    ],
    "sg:phone":"+44 161 480 4959",
    "sg:postcode":"SK1 1DH",
    "sg:province":"Cheshire",
    "sg:tags":[
        "consultant"
    ],
    "wof:name":"Hays Specialist Recruitment Ltd.",
    "wof:placetype":"venue"
},
  "geometry": {"coordinates":[-2.159422,53.40905],"type":"Point"}
}