{
  "type": "Feature",
  "properties": {
    "iso:country":"GB",
    "sg:address":"Rysell, Lincoln Road, Skellingthorpe",
    "sg:city":"Lincoln",
    "sg:classifiers":[
        {
            "category":"Freight",
            "type":"Transportation"
        }
    ],
    "sg:phone":"+44 1522 682519",
    "sg:postcode":"LN6 5SA",
    "sg:province":"Lincolnshire",
    "sg:tags":[
        "haulage",
        "road"
    ],
    "wof:name":"S Lyon & Son (Haulage) Ltd.",
    "wof:placetype":"venue"
},
  "geometry": {"coordinates":[-0.616529,53.236427],"type":"Point"}
}