{
  "type": "Feature",
  "properties": {
    "addr:full":"Unit C-d-e, Little Money Road Norwich Norfolk NR14 6JD",
    "addr:postcode":"nr14 6jd",
    "addr:street":"Money Road Norwich",
    "iso:country":"GB",
    "sg:address":"Unit C-d-e, Little Money Road",
    "sg:city":"Norwich",
    "sg:classifiers":[
        {
            "category":"Manufacturing",
            "subcategory":"Metals",
            "type":"Manufacturing & Wholesale Goods"
        }
    ],
    "sg:phone":"+44 1508 528307",
    "sg:postcode":"NR14 6JD",
    "sg:province":"Norfolk",
    "wof:name":"Norfolk Zinc Plating Co.",
    "wof:placetype":"venue"
},
  "geometry": {"coordinates":[1.491,52.527954],"type":"Point"}
}