{
  "type": "Feature",
  "properties": {
    "addr:full":"6 Nightingale Cres Bracknell Berkshire RG12 9PU",
    "addr:housenumber":"6",
    "addr:postcode":"rg12 9pu",
    "addr:street":"Nightingale Cres",
    "iso:country":"GB",
    "sg:address":"6 Nightingale Cres",
    "sg:city":"Bracknell",
    "sg:classifiers":[
        {
            "category":"Professional",
            "subcategory":"Computer Services",
            "type":"Services"
        }
    ],
    "sg:phone":"+44 1344 483222",
    "sg:postcode":"RG12 9PU",
    "sg:province":"Berkshire",
    "sg:tags":[
        "system",
        "software"
    ],
    "wof:name":"P C'S & Cables Ltd",
    "wof:placetype":"venue"
},
  "geometry": {"coordinates":[-0.7434610128,51.403301239],"type":"Point"}
}