{
  "type": "Feature",
  "properties": {
    "addr:full":"10 Sturdee Place Hastings East Sussex TN34 3AJ",
    "addr:housenumber":"10",
    "addr:postcode":"tn34 3aj",
    "addr:street":"Sturdee Place Hastings",
    "iso:country":"GB",
    "sg:address":"10 Sturdee Place",
    "sg:city":"Hastings",
    "sg:classifiers":[
        {
            "category":"Real Estate",
            "subcategory":"Real Estate Agent",
            "type":"Services"
        }
    ],
    "sg:phone":"+44 1424 440189",
    "sg:postcode":"TN34 3AJ",
    "sg:province":"East Sussex",
    "wof:name":"Bradleys",
    "wof:placetype":"venue"
},
  "geometry": {"coordinates":[0.586828,50.85532],"type":"Point"}
}