{
  "type": "Feature",
  "properties": {
    "addr:full":"31 Church View, Agbrigg Road Wakefield West Yorkshire WF1 5AL",
    "addr:housenumber":"31",
    "addr:postcode":"wf1 5al",
    "addr:street":"Church View Agbrigg Road",
    "iso:country":"GB",
    "sg:address":"31 Church View, Agbrigg Road",
    "sg:city":"Wakefield",
    "sg:classifiers":[
        {
            "category":"Wholesale",
            "subcategory":"Meat",
            "type":"Manufacturing & Wholesale Goods"
        },
        {
            "category":"Farming",
            "subcategory":"Farm",
            "type":"Manufacturing & Wholesale Goods"
        }
    ],
    "sg:phone":"+44 1924 250689",
    "sg:postcode":"WF1 5AL",
    "sg:province":"West Yorkshire",
    "sg:tags":[
        "wholesaler",
        "egg",
        "producer"
    ],
    "wof:name":"Churchview Farm Eggs",
    "wof:placetype":"venue"
},
  "geometry": {"coordinates":[-1.4761990309,53.6683540344],"type":"Point"}
}