{
  "type": "Feature",
  "properties": {
    "addr:full":"126 Halifax Road Sheffield South Yorkshire S6 1LH",
    "addr:housenumber":"126",
    "addr:postcode":"s6 1lh",
    "addr:street":"Halifax Road",
    "iso:country":"GB",
    "sg:address":"126 Halifax Road",
    "sg:city":"Sheffield",
    "sg:classifiers":[
        {
            "category":"Fast Food",
            "type":"Food & Drink"
        }
    ],
    "sg:phone":"+44 114 233 3397",
    "sg:postcode":"S6 1LH",
    "sg:province":"South Yorkshire",
    "sg:tags":[
        "away",
        "take"
    ],
    "wof:name":"Rasheeds Indian Takeaway",
    "wof:placetype":"venue"
},
  "geometry": {"coordinates":[-1.4925160408,53.4210166931],"type":"Point"}
}