{
  "type": "Feature",
  "properties": {
    "addr:full":"20 Maybrook Drive Saltash Cornwall PL12 4PX",
    "addr:housenumber":"20",
    "addr:postcode":"pl12 4px",
    "addr:street":"Maybrook Drive",
    "iso:country":"GB",
    "sg:address":"20 Maybrook Drive",
    "sg:city":"Saltash",
    "sg:classifiers":[
        {
            "category":"Manufacturing",
            "subcategory":"Tools & Machinery",
            "type":"Manufacturing & Wholesale Goods"
        }
    ],
    "sg:phone":"+44 1752 844385",
    "sg:postcode":"PL12 4PX",
    "sg:province":"Cornwall",
    "sg:tags":[
        "society",
        "friendly"
    ],
    "wof:name":"Robinson & Co",
    "wof:placetype":"venue"
},
  "geometry": {"coordinates":[-4.2288541794,50.4083709717],"type":"Point"}
}