{
  "type": "Feature",
  "properties": {
    "iso:country":"GB",
    "sg:address":"102-104 Hereford House, Coleshill",
    "sg:city":"Birmingham",
    "sg:classifiers":[
        {
            "category":"Wholesale",
            "subcategory":"Non-durable Goods",
            "type":"Manufacturing & Wholesale Goods"
        }
    ],
    "sg:phone":"+44 1675 464161",
    "sg:postcode":"B46 3BL",
    "sg:province":"Warwickshire",
    "sg:tags":[
        "carry",
        "cash"
    ],
    "wof:name":"Edna (U K) Frozen Food Ltd.",
    "wof:placetype":"venue"
},
  "geometry": {"coordinates":[-1.7068,52.498611],"type":"Point"}
}