{
  "type": "Feature",
  "properties": {
    "addr:full":"24a Fulmer Drive Gerrards Cross Buckinghamshire SL9 7HJ",
    "addr:housenumber":"24a",
    "addr:postcode":"sl9 7hj",
    "addr:street":"Fulmer Drive",
    "iso:country":"GB",
    "sg:address":"24a Fulmer Drive",
    "sg:city":"Gerrards Cross",
    "sg:classifiers":[
        {
            "category":"Communications",
            "subcategory":"Film & Video Production",
            "type":"Services"
        }
    ],
    "sg:phone":"+44 1753 891181",
    "sg:postcode":"SL9 7HJ",
    "sg:province":"Buckinghamshire",
    "sg:tags":[
        "pr",
        "telemarketing"
    ],
    "wof:name":"Telemarketing Solutions",
    "wof:placetype":"venue"
},
  "geometry": {"coordinates":[-0.555202,51.56937],"type":"Point"}
}