{
  "type": "Feature",
  "properties": {
    "iso:country":"GB",
    "sg:address":"Bank House, 22 Henry Street",
    "sg:city":"Glossop",
    "sg:classifiers":[
        {
            "category":"Restaurant",
            "type":"Food & Drink"
        }
    ],
    "sg:phone":"+44 1457 862975",
    "sg:postcode":"SK13 8BW",
    "sg:province":"Derbyshire",
    "wof:name":"Ristorante Napoli",
    "wof:placetype":"venue"
},
  "geometry": {"coordinates":[-1.94895,53.443996],"type":"Point"}
}