{
  "type": "Feature",
  "properties": {
    "addr:full":"A S R House, Arden Gro Harpenden Hertfordshire AL5 4SJ",
    "addr:postcode":"al5 4sj",
    "addr:street":"A;Arden Gro Harpenden",
    "iso:country":"GB",
    "sg:address":"A S R House, Arden Gro",
    "sg:city":"Harpenden",
    "sg:classifiers":[
        {
            "category":"Professional",
            "subcategory":"Computer Services",
            "type":"Services"
        }
    ],
    "sg:phone":"+44 1582 714800",
    "sg:postcode":"AL5 4SJ",
    "sg:province":"Hertfordshire",
    "sg:tags":[
        "system",
        "software"
    ],
    "wof:name":"A S R Computers Ltd.",
    "wof:placetype":"venue"
},
  "geometry": {"coordinates":[-0.3531790078,51.8145256042],"type":"Point"}
}