{
  "type": "Feature",
  "properties": {
    "iso:country":"GB",
    "sg:address":"Charlesworth Street",
    "sg:city":"Stockport",
    "sg:classifiers":[
        {
            "category":"Autos & Motor Vehicles",
            "subcategory":"Motorcycle Sales",
            "type":"Retail Goods"
        }
    ],
    "sg:phone":"+44 161 480 0778",
    "sg:postcode":"SK1 3UE",
    "sg:province":"Cheshire",
    "wof:name":"College Motor Cycles",
    "wof:placetype":"venue"
},
  "geometry": {"coordinates":[-2.157379,53.401958],"type":"Point"}
}