{
  "type": "Feature",
  "properties": {
    "iso:country":"GB",
    "sg:address":"11a Avenue Road, High Kelling",
    "sg:city":"Holt",
    "sg:classifiers":[
        {
            "category":"Retail",
            "subcategory":"Funeral Services",
            "type":"Services"
        }
    ],
    "sg:postcode":"NR25 6RD",
    "sg:province":"Norfolk",
    "wof:name":"Lloyd Durham Funeral Services",
    "wof:placetype":"venue"
},
  "geometry": {"coordinates":[1.128714,52.916584],"type":"Point"}
}