{
  "type": "Feature",
  "properties": {
    "addr:full":"41 Lyndhurst Road Worthing West Sussex BN11 2DB",
    "addr:housenumber":"41",
    "addr:postcode":"bn11 2db",
    "addr:street":"Lyndhurst Road",
    "iso:country":"GB",
    "sg:address":"41 Lyndhurst Road",
    "sg:city":"Worthing",
    "sg:classifiers":[
        {
            "category":"Bars & Pubs",
            "type":"Food & Drink"
        }
    ],
    "sg:phone":"+44 1903 234854",
    "sg:postcode":"BN11 2DB",
    "sg:province":"West Sussex",
    "sg:tags":[
        "pubs",
        "inn"
    ],
    "wof:name":"Michael Dominick",
    "wof:placetype":"venue"
},
  "geometry": {"coordinates":[-0.366159,50.815159],"type":"Point"}
}