{
  "type": "Feature",
  "properties": {
    "addr:full":"Cowdray Avenue Colchester Essex CO1 1YH",
    "addr:postcode":"co1 1yh",
    "addr:street":"Cowdray Avenue",
    "iso:country":"GB",
    "sg:address":"Cowdray Avenue",
    "sg:city":"Colchester",
    "sg:classifiers":[
        {
            "category":"Community Center",
            "type":"Public Place"
        }
    ],
    "sg:phone":"+44 1206 282000",
    "sg:postcode":"CO1 1YH",
    "sg:province":"Essex",
    "sg:tags":[
        "recreation",
        "leisure",
        "centre"
    ],
    "wof:name":"Colchester Leisure World",
    "wof:placetype":"venue"
},
  "geometry": {"coordinates":[0.90863,51.89785],"type":"Point"}
}