{
  "type": "Feature",
  "properties": {
    "iso:country":"GB",
    "sg:address":"4 Birches Lane, Lostock Green",
    "sg:city":"Northwich",
    "sg:classifiers":[
        {
            "category":"Bakery",
            "type":"Food & Drink"
        },
        {
            "category":"Home & Garden",
            "subcategory":"Kitchen Supply",
            "type":"Retail Goods"
        }
    ],
    "sg:postcode":"CW9 7SL",
    "sg:province":"Cheshire",
    "sg:tags":[
        "cake",
        "equipment",
        "maker"
    ],
    "wof:name":"Brookdale Country Kitchen",
    "wof:placetype":"venue"
},
  "geometry": {"coordinates":[-2.463947,53.262516],"type":"Point"}
}