{
  "type": "Feature",
  "properties": {
    "addr:full":"47 Ferry Road Edinburgh City of Edinburgh EH6 4AF",
    "addr:housenumber":"47",
    "addr:postcode":"eh6 4af",
    "addr:street":"Ferry Road",
    "iso:country":"GB",
    "sg:address":"47 Ferry Road",
    "sg:city":"Edinburgh",
    "sg:classifiers":[
        {
            "category":"Fast Food",
            "type":"Food & Drink"
        }
    ],
    "sg:phone":"+44 131 554 5346",
    "sg:postcode":"EH6 4AF",
    "sg:province":"City of Edinburgh",
    "sg:tags":[
        "away",
        "meal",
        "outlet",
        "take"
    ],
    "wof:name":"Ferry's Curry Connection",
    "wof:placetype":"venue"
},
  "geometry": {"coordinates":[-3.1805660725,55.97498703],"type":"Point"}
}