{
  "type": "Feature",
  "properties": {
    "addr:full":"24 Elizabeth Rd Manchester Cheshire M31 4PU",
    "addr:housenumber":"24",
    "addr:postcode":"m31 4pu",
    "addr:street":"Elizabeth Rd",
    "iso:country":"GB",
    "sg:address":"24 Elizabeth Rd",
    "sg:city":"Manchester",
    "sg:classifiers":[
        {
            "category":"Building & Trades",
            "subcategory":"Construction",
            "type":"Services"
        }
    ],
    "sg:phone":"+44 161 775 8294",
    "sg:postcode":"M31 4PU",
    "sg:province":"Cheshire",
    "sg:tags":[
        "decorator",
        "painter"
    ],
    "wof:name":"Anthony Shawcross",
    "wof:placetype":"venue"
},
  "geometry": {"coordinates":[-2.4298949242,53.4207992554],"type":"Point"}
}