{
  "type": "Feature",
  "properties": {
    "addr:full":"Glossoms Farm, Scalford Back Road, Thorpe Arnold Melton Mowbray Leicestershire LE14 4SB",
    "addr:housenumber":"scalford",
    "addr:postcode":"le14 4sb",
    "addr:street":"Back Road",
    "iso:country":"GB",
    "sg:address":"Glossoms Farm, Scalford Back Road, Thorpe Arnold",
    "sg:city":"Melton Mowbray",
    "sg:classifiers":[
        {
            "category":"Home & Garden",
            "subcategory":"Garden Supply",
            "type":"Retail Goods"
        },
        {
            "category":"Farming",
            "subcategory":"Livestock Farm",
            "type":"Manufacturing & Wholesale Goods"
        }
    ],
    "sg:postcode":"LE14 4SB",
    "sg:province":"Leicestershire",
    "sg:tags":[
        "bulb",
        "grower",
        "others"
    ],
    "wof:name":"J D & J M Craig",
    "wof:placetype":"venue"
},
  "geometry": {"coordinates":[-0.870559,52.809254],"type":"Point"}
}