{
  "type": "Feature",
  "properties": {
    "iso:country":"GB",
    "sg:address":"126 Colindale Avenue, Colindale",
    "sg:city":"London",
    "sg:classifiers":[
        {
            "category":"Real Estate",
            "subcategory":"Developer",
            "type":"Services"
        },
        {
            "category":"Building & Trades",
            "subcategory":"Construction",
            "type":"Services"
        }
    ],
    "sg:phone":"+44 20 8205 5055",
    "sg:postcode":"NW9 5HW",
    "sg:province":"Greater London",
    "sg:tags":[
        "builder",
        "property"
    ],
    "wof:name":"London Building Co. Plc",
    "wof:placetype":"venue"
},
  "geometry": {"coordinates":[-0.252361,51.593861],"type":"Point"}
}