{
  "type": "Feature",
  "properties": {
    "iso:country":"GB",
    "sg:address":"Unit 3, The Maltings High St, Sileby",
    "sg:city":"Loughborough",
    "sg:classifiers":[
        {
            "category":"Education",
            "subcategory":"Music School",
            "type":"Public Place"
        }
    ],
    "sg:phone":"+44 116 267 2808",
    "sg:postcode":"LE12 7RX",
    "sg:province":"Leicestershire",
    "sg:tags":[
        "conservatory"
    ],
    "wof:name":"Premier Frames",
    "wof:placetype":"venue"
},
  "geometry": {"coordinates":[-1.10662,52.732651],"type":"Point"}
}