{
  "type": "Feature",
  "properties": {
    "addr:full":"Broad St Coventry Warwickshire CV6 5AZ",
    "addr:postcode":"cv6 5az",
    "addr:street":"Broad St",
    "iso:country":"GB",
    "sg:address":"Broad St",
    "sg:city":"Coventry",
    "sg:classifiers":[
        {
            "category":"Place Of Worship",
            "type":"Public Place"
        }
    ],
    "sg:phone":"+44 247689000",
    "sg:postcode":"CV6 5AZ",
    "sg:province":"Warwickshire",
    "wof:name":"Foleshill Baptist Church",
    "wof:placetype":"venue"
},
  "geometry": {"coordinates":[-1.493219,52.426708],"type":"Point"}
}