{
  "type": "Feature",
  "properties": {
    "iso:country":"GB",
    "sg:address":"52 Parkwood Road",
    "sg:city":"Bournemouth",
    "sg:classifiers":[
        {
            "category":"Social Services",
            "subcategory":"Retirement Home",
            "type":"Services"
        },
        {
            "category":"Real Estate",
            "subcategory":"Real Estate Agent",
            "type":"Services"
        }
    ],
    "sg:postcode":"BH5 2BL",
    "sg:province":"Dorset",
    "sg:tags":[
        "rest"
    ],
    "wof:name":"Treeborough Rest Home",
    "wof:placetype":"venue"
},
  "geometry": {"coordinates":[-1.8250620365,50.7264404297],"type":"Point"}
}