{
  "type": "Feature",
  "properties": {
    "addr:full":"26 South Street Lancing West Sussex BN15 8AG",
    "addr:housenumber":"26",
    "addr:postcode":"bn15 8ag",
    "addr:street":"South Street",
    "iso:country":"GB",
    "sg:address":"26 South Street",
    "sg:city":"Lancing",
    "sg:classifiers":[
        {
            "category":"Retail",
            "subcategory":"Funeral Services",
            "type":"Services"
        },
        {
            "category":"Manufacturing",
            "subcategory":"Building Materials",
            "type":"Manufacturing & Wholesale Goods"
        }
    ],
    "sg:phone":"+44 1903 764426",
    "sg:postcode":"BN15 8AG",
    "sg:province":"West Sussex",
    "sg:tags":[
        "stonemason"
    ],
    "wof:name":"H D Tribe",
    "wof:placetype":"venue"
},
  "geometry": {"coordinates":[-0.3232429922,50.8261375427],"type":"Point"}
}