{
  "type": "Feature",
  "properties": {
    "addr:full":", Sudbury Ashbourne Derbyshire DE6 5HT",
    "addr:postcode":"de6 5ht",
    "iso:country":"GB",
    "sg:address":", Sudbury",
    "sg:city":"Ashbourne",
    "sg:classifiers":[
        {
            "category":"Landmark",
            "subcategory":"Tourist Attraction",
            "type":"Public Place"
        }
    ],
    "sg:phone":"+44 1283 585337",
    "sg:postcode":"DE6 5HT",
    "sg:province":"Derbyshire",
    "sg:tags":[
        "interest"
    ],
    "wof:name":"Sudbury Hall",
    "wof:placetype":"venue"
},
  "geometry": {"coordinates":[-1.7664619684,52.8982124329],"type":"Point"}
}