{
  "type": "Feature",
  "properties": {
    "iso:country":"GB",
    "sg:address":"Europoint Centre, 5-11 Lavington St",
    "sg:city":"London",
    "sg:classifiers":[
        {
            "category":"Manufacturing",
            "subcategory":"Wood Products",
            "type":"Manufacturing & Wholesale Goods"
        }
    ],
    "sg:phone":"+44 20 7922 1111",
    "sg:postcode":"SE1 0NZ",
    "sg:province":"Greater London",
    "sg:tags":[
        "pulp",
        "agent"
    ],
    "wof:name":"Price & Pierce Woodpulp Ltd",
    "wof:placetype":"venue"
},
  "geometry": {"coordinates":[-0.1001200005,51.5051689148],"type":"Point"}
}