{
  "type": "Feature",
  "properties": {
    "addr:full":"38 High Street Blairgowrie Perth and Kinross PH10 6DA",
    "addr:housenumber":"38",
    "addr:postcode":"ph10 6da",
    "addr:street":"High Street",
    "iso:country":"GB",
    "sg:address":"38 High Street",
    "sg:city":"Blairgowrie",
    "sg:classifiers":[
        {
            "category":"Personal",
            "subcategory":"Beauty Salon",
            "type":"Services"
        }
    ],
    "sg:phone":"+44 1250 873263",
    "sg:postcode":"PH10 6DA",
    "sg:province":"Perth and Kinross",
    "sg:tags":[
        "unisex",
        "hairdresser"
    ],
    "wof:name":"Hair Studios",
    "wof:placetype":"venue"
},
  "geometry": {"coordinates":[-3.3396799564,56.5922164917],"type":"Point"}
}