{
  "type": "Feature",
  "properties": {
    "addr:full":"21 Queen Elizabeth 11 Square, South Woodham Ferrer Chelmsford Essex CM3 5TD",
    "addr:housenumber":"21;11",
    "addr:postcode":"cm3 5td",
    "addr:street":"Queen Elizabeth;Square South",
    "iso:country":"GB",
    "sg:address":"21 Queen Elizabeth 11 Square, South Woodham Ferrer",
    "sg:city":"Chelmsford",
    "sg:classifiers":[
        {
            "category":"Health Services",
            "subcategory":"Optometrist",
            "type":"Services"
        }
    ],
    "sg:phone":"+44 1245 322114",
    "sg:postcode":"CM3 5TD",
    "sg:province":"Essex",
    "sg:tags":[
        "optician"
    ],
    "wof:name":"M J Revell Opticians",
    "wof:placetype":"venue"
},
  "geometry": {"coordinates":[0.6072769761,51.6531524658],"type":"Point"}
}