{
  "type": "Feature",
  "properties": {
    "addr:full":"Surrex Farm, Colchester Road, Coggeshall Colchester Essex CO6 1RR",
    "addr:postcode":"co6 1rr",
    "addr:street":"Colchester Road",
    "iso:country":"GB",
    "sg:address":"Surrex Farm, Colchester Road, Coggeshall",
    "sg:city":"Colchester",
    "sg:classifiers":[
        {
            "category":"Transit Center",
            "subcategory":"Freight",
            "type":"Transportation"
        }
    ],
    "sg:phone":"+44 1376 561490",
    "sg:postcode":"CO6 1RR",
    "sg:province":"Essex",
    "sg:tags":[
        "piano",
        "accessory"
    ],
    "wof:name":"Colin Cooper",
    "wof:placetype":"venue"
},
  "geometry": {"coordinates":[0.6910380125,51.8712997437],"type":"Point"}
}