{
  "type": "Feature",
  "properties": {
    "addr:full":"23c North Street Emsworth Hampshire PO10 7BY",
    "addr:housenumber":"23c",
    "addr:postcode":"po10 7by",
    "addr:street":"North Street",
    "iso:country":"GB",
    "sg:address":"23c North Street",
    "sg:city":"Emsworth",
    "sg:classifiers":[
        {
            "category":"Personal",
            "subcategory":"Beauty Salon",
            "type":"Services"
        }
    ],
    "sg:phone":"+44 1243 431667",
    "sg:postcode":"PO10 7BY",
    "sg:province":"Hampshire",
    "sg:tags":[
        "unisex",
        "hairdresser"
    ],
    "wof:name":"Cabello's Salon",
    "wof:placetype":"venue"
},
  "geometry": {"coordinates":[-0.937002,50.848873],"type":"Point"}
}