{
  "type": "Feature",
  "properties": {
    "addr:full":"Meadow Cottage, Steels Lane, Oxshott Leatherhead Surrey KT22 0QQ",
    "addr:postcode":"kt22 0qq",
    "addr:street":"Steels Lane",
    "iso:country":"GB",
    "sg:address":"Meadow Cottage, Steels Lane, Oxshott",
    "sg:city":"Leatherhead",
    "sg:classifiers":[
        {
            "category":"Arts & Performance",
            "subcategory":"Theater",
            "type":"Entertainment"
        }
    ],
    "sg:phone":"+44 1372 843761",
    "sg:postcode":"KT22 0QQ",
    "sg:province":"Surrey",
    "sg:tags":[
        "theatrical",
        "agency"
    ],
    "wof:name":"St. James's Management",
    "wof:placetype":"venue"
},
  "geometry": {"coordinates":[-0.3567959964,51.3322677612],"type":"Point"}
}