{
  "type": "Feature",
  "properties": {
    "addr:full":"Noades Leaze Farm, Bath Road, Wick Bristol Gloucestershire BS30 5RR",
    "addr:postcode":"bs30 5rr",
    "addr:street":"Bath Road",
    "iso:country":"GB",
    "sg:address":"Noades Leaze Farm, Bath Road, Wick",
    "sg:city":"Bristol",
    "sg:classifiers":[
        {
            "category":"Farming",
            "subcategory":"Livestock Farm",
            "type":"Manufacturing & Wholesale Goods"
        }
    ],
    "sg:postcode":"BS30 5RR",
    "sg:province":"Gloucestershire",
    "sg:tags":[
        "others"
    ],
    "wof:name":"Arthur G Bishop",
    "wof:placetype":"venue"
},
  "geometry": {"coordinates":[-2.430641,51.453663],"type":"Point"}
}