{
  "type": "Feature",
  "properties": {
    "addr:full":"Finches, Lower Cousley Wood Wadhurst East Sussex TN5 6HE",
    "addr:postcode":"tn5 6he",
    "addr:street":"Lower Cousley Wood",
    "iso:country":"GB",
    "sg:address":"Finches, Lower Cousley Wood",
    "sg:city":"Wadhurst",
    "sg:classifiers":[
        {
            "category":"Professional",
            "subcategory":"Computer Services",
            "type":"Services"
        }
    ],
    "sg:phone":"+44 1892 783722",
    "sg:postcode":"TN5 6HE",
    "sg:province":"East Sussex",
    "sg:tags":[
        "system",
        "software"
    ],
    "wof:name":"Board Level Ltd.",
    "wof:placetype":"venue"
},
  "geometry": {"coordinates":[0.339718014,51.0620079041],"type":"Point"}
}