{
  "type": "Feature",
  "properties": {
    "addr:full":"83 Rookery Way, Whitchurch Bristol City of Bristol BS14 0DZ",
    "addr:housenumber":"83",
    "addr:postcode":"bs14 0dz",
    "addr:street":"Rookery Way",
    "iso:country":"GB",
    "sg:address":"83 Rookery Way, Whitchurch",
    "sg:city":"Bristol",
    "sg:classifiers":[
        {
            "category":"Communications",
            "type":"Services"
        }
    ],
    "sg:postcode":"BS14 0DZ",
    "sg:province":"City of Bristol",
    "sg:tags":[
        "data",
        "network"
    ],
    "wof:name":"Netcon Data Systems Ltd",
    "wof:placetype":"venue"
},
  "geometry": {"coordinates":[-2.5782830715,51.4056243896],"type":"Point"}
}