{
  "type": "Feature",
  "properties": {
    "iso:country":"GB",
    "sg:address":"7 Cleveland Row",
    "sg:city":"London",
    "sg:classifiers":[
        {
            "category":"Professional",
            "subcategory":"Engineering",
            "type":"Services"
        }
    ],
    "sg:phone":"+44 20 7930 2424",
    "sg:postcode":"SW1A 1DB",
    "sg:province":"Greater London",
    "sg:tags":[
        "engineer"
    ],
    "wof:name":"G K N Holdings Plc",
    "wof:placetype":"venue"
},
  "geometry": {"coordinates":[-0.138966,51.504696],"type":"Point"}
}