{
  "type": "Feature",
  "properties": {
    "addr:full":"Gladstone Road Northampton Northamptonshire NN5 7EJ",
    "addr:postcode":"nn5 7ej",
    "addr:street":"Gladstone Road",
    "iso:country":"GB",
    "sg:address":"Gladstone Road",
    "sg:city":"Northampton",
    "sg:classifiers":[
        {
            "category":"Social Services",
            "subcategory":"Adult Care",
            "type":"Services"
        }
    ],
    "sg:phone":"+44 1604 752611",
    "sg:postcode":"NN5 7EJ",
    "sg:province":"Northamptonshire",
    "sg:tags":[
        "day",
        "centre"
    ],
    "wof:name":"Gladstone Day Centre",
    "wof:placetype":"venue"
},
  "geometry": {"coordinates":[-0.912429,52.250271],"type":"Point"}
}