{
  "type": "Feature",
  "properties": {
    "iso:country":"GB",
    "sg:address":"39 Clarence Road",
    "sg:city":"Chatham",
    "sg:classifiers":[
        {
            "category":"Building & Trades",
            "subcategory":"Construction",
            "type":"Services"
        },
        {
            "category":"Manufacturing",
            "subcategory":"Paper Products",
            "type":"Manufacturing & Wholesale Goods"
        }
    ],
    "sg:postcode":"ME4 5EH",
    "sg:province":"Kent",
    "sg:tags":[
        "cardboard",
        "decorator",
        "painter"
    ],
    "wof:name":"A J Bubb Decorators",
    "wof:placetype":"venue"
},
  "geometry": {"coordinates":[0.538154006,51.3715019226],"type":"Point"}
}