{
  "type": "Feature",
  "properties": {
    "addr:full":"17 High Street Bracknell Berkshire RG12 1DB",
    "addr:housenumber":"17",
    "addr:postcode":"rg12 1db",
    "addr:street":"High Street",
    "iso:country":"GB",
    "sg:address":"17 High Street",
    "sg:city":"Bracknell",
    "sg:classifiers":[
        {
            "category":"Insurance",
            "subcategory":"Insurance Agent",
            "type":"Services"
        }
    ],
    "sg:postcode":"RG12 1DB",
    "sg:province":"Berkshire",
    "sg:tags":[
        "broker"
    ],
    "wof:name":"Aspey Insurance Brokers Ltd.",
    "wof:placetype":"venue"
},
  "geometry": {"coordinates":[-0.751599,51.416882],"type":"Point"}
}