{
  "type": "Feature",
  "properties": {
    "iso:country":"GB",
    "sg:address":"17 High Street",
    "sg:city":"Bracknell",
    "sg:classifiers":[
        {
            "category":"Insurance",
            "subcategory":"Insurance Agent",
            "type":"Services"
        }
    ],
    "sg:postcode":"RG12 1DB",
    "sg:province":"Berkshire",
    "sg:tags":[
        "broker"
    ],
    "wof:name":"Aspey Insurance Brokers Ltd.",
    "wof:placetype":"venue"
},
  "geometry": {"coordinates":[-0.751599,51.416882],"type":"Point"}
}