{
  "type": "Feature",
  "properties": {
    "addr:full":"The Garage, Main Street, Wold Newton Driffield East Riding of Yorkshire YO25 3YG",
    "addr:postcode":"yo25 3yg",
    "addr:street":"Main Street;Newton",
    "iso:country":"GB",
    "sg:address":"The Garage, Main Street, Wold Newton",
    "sg:city":"Driffield",
    "sg:classifiers":[
        {
            "category":"Food & Beverages",
            "subcategory":"Groceries & Convenience Stores",
            "type":"Retail Goods"
        }
    ],
    "sg:phone":"+44 1262 470686",
    "sg:postcode":"YO25 3YG",
    "sg:province":"East Riding of Yorkshire",
    "sg:tags":[
        "wax"
    ],
    "wof:name":"Bee Health Manufacturing",
    "wof:placetype":"venue"
},
  "geometry": {"coordinates":[-0.398465,54.141808],"type":"Point"}
}