{
  "type": "Feature",
  "properties": {
    "addr:full":"300 Shirley Road Southampton Hampshire SO15 3HL",
    "addr:housenumber":"300",
    "addr:postcode":"so15 3hl",
    "addr:street":"Shirley Road",
    "iso:country":"GB",
    "sg:address":"300 Shirley Road",
    "sg:city":"Southampton",
    "sg:classifiers":[
        {
            "category":"Retail",
            "subcategory":"Driving School",
            "type":"Services"
        }
    ],
    "sg:postcode":"SO15 3HL",
    "sg:province":"Hampshire",
    "wof:name":"A D T",
    "wof:placetype":"venue"
},
  "geometry": {"coordinates":[-1.426699,50.916847],"type":"Point"}
}