{
  "type": "Feature",
  "properties": {
    "addr:full":"Skipton Bridge Thirsk North Yorkshire YO7 4SB",
    "addr:postcode":"yo7 4sb",
    "iso:country":"GB",
    "sg:address":"Skipton Bridge",
    "sg:city":"Thirsk",
    "sg:classifiers":[
        {
            "category":"Farming",
            "subcategory":"Farm",
            "type":"Manufacturing & Wholesale Goods"
        }
    ],
    "sg:postcode":"YO7 4SB",
    "sg:province":"North Yorkshire",
    "sg:tags":[
        "mixed",
        "crop"
    ],
    "wof:name":"R & B K Wise",
    "wof:placetype":"venue"
},
  "geometry": {"coordinates":[-1.3422529697,54.2326889038],"type":"Point"}
}