{
  "type": "Feature",
  "properties": {
    "addr:full":"50 Bibshall Crescent Dunstable Bedfordshire LU6 3NE",
    "addr:housenumber":"50",
    "addr:postcode":"lu6 3ne",
    "addr:street":"Bibshall Crescent",
    "iso:country":"GB",
    "sg:address":"50 Bibshall Crescent",
    "sg:city":"Dunstable",
    "sg:classifiers":[
        {
            "category":"Manufacturing",
            "subcategory":"Petroleum Products",
            "type":"Manufacturing & Wholesale Goods"
        }
    ],
    "sg:phone":"+44 1582 602529",
    "sg:postcode":"LU6 3NE",
    "sg:province":"Bedfordshire",
    "sg:tags":[
        "double",
        "glazing"
    ],
    "wof:name":"Window Doctor",
    "wof:placetype":"venue"
},
  "geometry": {"coordinates":[-0.5146329999,51.8761634827],"type":"Point"}
}