{
  "type": "Feature",
  "properties": {
    "addr:full":"4/5 Prospect Mills, Thornton Rd,, Thornton, Bradford West Yorkshire BD13 3LN",
    "addr:housenumber":"4 / 5",
    "addr:postcode":"bd13 3ln",
    "addr:street":"Prospect Mills Thornton Rd",
    "iso:country":"GB",
    "sg:address":"4/5 Prospect Mills, Thornton Rd,, Thornton,",
    "sg:city":"Bradford",
    "sg:classifiers":[
        {
            "category":"Home & Garden",
            "subcategory":"Home Furnishings",
            "type":"Retail Goods"
        }
    ],
    "sg:phone":"+44 1274 881818",
    "sg:postcode":"BD13 3LN",
    "sg:province":"West Yorkshire",
    "sg:tags":[
        "homefurnishings"
    ],
    "wof:name":"Evergreen Design Furniture Ltd",
    "wof:placetype":"venue"
},
  "geometry": {"coordinates":[-1.8494340181,53.7902336121],"type":"Point"}
}