{
  "type": "Feature",
  "properties": {
    "addr:full":"185 Park Road London Greater London N8 8JJ",
    "addr:housenumber":"185",
    "addr:postcode":"n8 8jj",
    "addr:street":"Park Road",
    "iso:country":"GB",
    "sg:address":"185 Park Road",
    "sg:city":"London",
    "sg:classifiers":[
        {
            "category":"Arena",
            "subcategory":"Sports Club",
            "type":"Entertainment"
        }
    ],
    "sg:postcode":"N8 8JJ",
    "sg:province":"Greater London",
    "sg:tags":[
        "ground"
    ],
    "wof:name":"North Middlesex Sports Club",
    "wof:placetype":"venue"
},
  "geometry": {"coordinates":[-0.1330340058,51.5856513977],"type":"Point"}
}