{
  "type": "Feature",
  "properties": {
    "addr:full":"169 High Street Redcar North Yorkshire TS10 3AN",
    "addr:housenumber":"169",
    "addr:postcode":"ts10 3an",
    "addr:street":"High Street",
    "iso:country":"GB",
    "sg:address":"169 High Street",
    "sg:city":"Redcar",
    "sg:classifiers":[
        {
            "category":"Banks & Credit Unions",
            "subcategory":"Financial Services",
            "type":"Services"
        }
    ],
    "sg:postcode":"TS10 3AN",
    "sg:province":"North Yorkshire",
    "sg:tags":[
        "claim",
        "assessor"
    ],
    "wof:name":"Bryan Sampson",
    "wof:placetype":"venue"
},
  "geometry": {"coordinates":[-1.058581,54.617348],"type":"Point"}
}