{
  "type": "Feature",
  "properties": {
    "addr:full":"Tennyson Way Kidderminster Staffordshire DY10 3YT",
    "addr:postcode":"dy10 3yt",
    "addr:street":"Tennyson Way",
    "iso:country":"GB",
    "sg:address":"Tennyson Way",
    "sg:city":"Kidderminster",
    "sg:classifiers":[
        {
            "category":"Bars & Pubs",
            "type":"Food & Drink"
        }
    ],
    "sg:phone":"+44 1562 824734",
    "sg:postcode":"DY10 3YT",
    "sg:province":"Staffordshire",
    "sg:tags":[
        "pubs",
        "inn"
    ],
    "wof:name":"Cavalier The",
    "wof:placetype":"venue"
},
  "geometry": {"coordinates":[-2.2222619057,52.3890266418],"type":"Point"}
}