{
  "type": "Feature",
  "properties": {
    "iso:country":"GB",
    "sg:address":"5 Speculation Place",
    "sg:city":"Washington",
    "sg:classifiers":[
        {
            "category":"Food & Beverages",
            "subcategory":"Liquor & Beverages",
            "type":"Retail Goods"
        }
    ],
    "sg:phone":"+44 191 416 3755",
    "sg:postcode":"NE37 2AL",
    "sg:province":"Tyne and Wear",
    "sg:tags":[
        "beer",
        "spirit",
        "wines"
    ],
    "wof:name":"Booze Buster",
    "wof:placetype":"venue"
},
  "geometry": {"coordinates":[-1.519009,54.912563],"type":"Point"}
}