{
  "type": "Feature",
  "properties": {
    "addr:full":"Box Office, Prospect Rd Shanklin Isle of Wight PO37 6AJ",
    "addr:postcode":"po37 6aj",
    "addr:street":"Prospect Rd",
    "iso:country":"GB",
    "sg:address":"Box Office, Prospect Rd",
    "sg:city":"Shanklin",
    "sg:classifiers":[
        {
            "category":"Arts & Performance",
            "subcategory":"Theater",
            "type":"Entertainment"
        }
    ],
    "sg:phone":"+44 1983 868000",
    "sg:postcode":"PO37 6AJ",
    "sg:province":"Isle of Wight",
    "sg:tags":[
        "hall",
        "theatre",
        "concert"
    ],
    "wof:name":"Shanklin Theatre",
    "wof:placetype":"venue"
},
  "geometry": {"coordinates":[-1.179239,50.626976],"type":"Point"}
}