{
  "type": "Feature",
  "properties": {
    "addr:full":"213a Garratt Lane London Greater London SW18 4DS",
    "addr:housenumber":"213a",
    "addr:postcode":"sw18 4ds",
    "addr:street":"Garratt Lane",
    "iso:country":"GB",
    "sg:address":"213a Garratt Lane",
    "sg:city":"London",
    "sg:classifiers":[
        {
            "category":"Social Services",
            "subcategory":"Adult Care",
            "type":"Services"
        }
    ],
    "sg:postcode":"SW18 4DS",
    "sg:province":"Greater London",
    "sg:tags":[
        "domestic",
        "cleaning"
    ],
    "wof:name":"Homeclene Services Ltd.",
    "wof:placetype":"venue"
},
  "geometry": {"coordinates":[-0.189533,51.44976],"type":"Point"}
}