{
  "type": "Feature",
  "properties": {
    "addr:full":"31 Dalkeith Road Sutton Coldfield West Midlands B73 6BW",
    "addr:housenumber":"31",
    "addr:postcode":"b73 6bw",
    "addr:street":"Dalkeith Road",
    "iso:country":"GB",
    "sg:address":"31 Dalkeith Road",
    "sg:city":"Sutton Coldfield",
    "sg:classifiers":[
        {
            "category":"Professional",
            "subcategory":"Engineering",
            "type":"Services"
        },
        {
            "category":"Shopping",
            "subcategory":"Computers & Home Electronics",
            "type":"Retail Goods"
        }
    ],
    "sg:phone":"+44 1509 260893",
    "sg:postcode":"B73 6BW",
    "sg:province":"West Midlands",
    "sg:tags":[
        "automation",
        "electronic",
        "system",
        "engineer"
    ],
    "wof:name":"Mandator Control Systems Ltd.",
    "wof:placetype":"venue"
},
  "geometry": {"coordinates":[-1.854565,52.550682],"type":"Point"}
}