{
  "type": "Feature",
  "properties": {
    "iso:country":"GB",
    "sg:address":"Unit 1, Richard Street",
    "sg:city":"Wigan",
    "sg:classifiers":[
        {
            "category":"Bus Charters",
            "type":"Transportation"
        }
    ],
    "sg:phone":"+44 1942 492252",
    "sg:postcode":"WN3 4JN",
    "sg:province":"Lancashire",
    "sg:tags":[
        "coach"
    ],
    "wof:name":"Wigan Ring & Ride",
    "wof:placetype":"venue"
},
  "geometry": {"coordinates":[-2.6220290661,53.5396156311],"type":"Point"}
}