{
  "type": "Feature",
  "properties": {
    "addr:full":"9 The Mall Cwmbran Monmouthshire NP44 1PX",
    "addr:housenumber":"9",
    "addr:postcode":"np44 1px",
    "addr:street":"The Mall",
    "iso:country":"GB",
    "sg:address":"9 The Mall",
    "sg:city":"Cwmbran",
    "sg:classifiers":[
        {
            "category":"Shopping",
            "subcategory":"Clothing, Apparel, & Fashions",
            "type":"Retail Goods"
        }
    ],
    "sg:phone":"+44 1633 870236",
    "sg:postcode":"NP44 1PX",
    "sg:province":"Monmouthshire",
    "sg:tags":[
        "shop"
    ],
    "wof:name":"Top Shop",
    "wof:placetype":"venue"
},
  "geometry": {"coordinates":[-3.019933939,51.6534156799],"type":"Point"}
}