{
  "type": "Feature",
  "properties": {
    "addr:full":"9 Elizabeth Mews Hampstead Greater London NW3 4TL",
    "addr:housenumber":"9",
    "addr:postcode":"nw3 4tl",
    "addr:street":"Elizabeth Mews",
    "iso:country":"GB",
    "sg:address":"9 Elizabeth Mews",
    "sg:city":"Hampstead",
    "sg:classifiers":[
        {
            "category":"Building & Trades",
            "subcategory":"Construction",
            "type":"Services"
        }
    ],
    "sg:phone":"+44 20 7485 4845",
    "sg:postcode":"NW3 4TL",
    "sg:province":"Greater London",
    "sg:tags":[
        "builder"
    ],
    "wof:name":"V.W Croucher & Son",
    "wof:placetype":"venue"
},
  "geometry": {"coordinates":[-0.1615419984,51.5465583801],"type":"Point"}
}