{
  "type": "Feature",
  "properties": {
    "addr:full":"Unit 24 Billing Arbours House, Heather Lane Northampton Northamptonshire NN3 8EY",
    "addr:housenumber":"unit 24 billing arbours house",
    "addr:postcode":"nn3 8ey",
    "addr:street":"Heather Lane",
    "iso:country":"GB",
    "sg:address":"Unit 24 Billing Arbours House, Heather Lane",
    "sg:city":"Northampton",
    "sg:classifiers":[
        {
            "category":"Wholesale",
            "subcategory":"Medical Equipment & Supplies",
            "type":"Manufacturing & Wholesale Goods"
        }
    ],
    "sg:postcode":"NN3 8EY",
    "sg:province":"Northamptonshire",
    "sg:tags":[
        "hospital"
    ],
    "wof:name":"Technical Surgical Products",
    "wof:placetype":"venue"
},
  "geometry": {"coordinates":[-0.842361,52.267048],"type":"Point"}
}