{
  "type": "Feature",
  "properties": {
    "addr:full":"19 Widdenton View, Lane End High Wycombe Buckinghamshire HP14 3EB",
    "addr:housenumber":"19",
    "addr:postcode":"hp14 3eb",
    "addr:street":"Widdenton View;End",
    "iso:country":"GB",
    "sg:address":"19 Widdenton View, Lane End",
    "sg:city":"High Wycombe",
    "sg:classifiers":[
        {
            "category":"Autos & Motor Vehicles",
            "subcategory":"Motorcycle Sales",
            "type":"Retail Goods"
        }
    ],
    "sg:postcode":"HP14 3EB",
    "sg:province":"Buckinghamshire",
    "sg:tags":[
        "chauffeur",
        "driven",
        "car"
    ],
    "wof:name":"All Seasons",
    "wof:placetype":"venue"
},
  "geometry": {"coordinates":[-0.829744,51.622486],"type":"Point"}
}