{
  "type": "Feature",
  "properties": {
    "addr:full":"7 St Johns Way, Knowle Solihull Warwickshire B93 0LE",
    "addr:housenumber":"7",
    "addr:postcode":"b93 0le",
    "addr:street":"St Johns Way",
    "iso:country":"GB",
    "sg:address":"7 St Johns Way, Knowle",
    "sg:city":"Solihull",
    "sg:classifiers":[
        {
            "category":"Shopping",
            "subcategory":"Bicycles & Sporting Goods",
            "type":"Retail Goods"
        }
    ],
    "sg:phone":"+44 1564 777900",
    "sg:postcode":"B93 0LE",
    "sg:province":"Warwickshire",
    "sg:tags":[
        "dance",
        "balletwear"
    ],
    "wof:name":"Suave Dancer",
    "wof:placetype":"venue"
},
  "geometry": {"coordinates":[-1.7346160412,52.3884429932],"type":"Point"}
}