{
  "type": "Feature",
  "properties": {
    "iso:country":"GB",
    "sg:address":"Bethesda St",
    "sg:city":"Burnley",
    "sg:classifiers":[
        {
            "category":"Place Of Worship",
            "type":"Public Place"
        }
    ],
    "sg:phone":"+44 1254 889159",
    "sg:postcode":"BB11 1PR",
    "sg:province":"Lancashire",
    "wof:name":"Burnley United Reform Church",
    "wof:placetype":"venue"
},
  "geometry": {"coordinates":[-2.2455360889,53.7900390625],"type":"Point"}
}