{
  "type": "Feature",
  "properties": {
    "addr:full":"42 Severn St Worcester Worcestershire WR1 2ND",
    "addr:housenumber":"42",
    "addr:postcode":"wr1 2nd",
    "addr:street":"Severn St",
    "iso:country":"GB",
    "sg:address":"42 Severn St",
    "sg:city":"Worcester",
    "sg:classifiers":[
        {
            "category":"Bars & Pubs",
            "type":"Food & Drink"
        }
    ],
    "sg:postcode":"WR1 2ND",
    "sg:province":"Worcestershire",
    "sg:tags":[
        "pubs",
        "inn"
    ],
    "wof:name":"Walker,Bernard,",
    "wof:placetype":"venue"
},
  "geometry": {"coordinates":[-2.2216711044,52.1866035461],"type":"Point"}
}