{
  "type": "Feature",
  "properties": {
    "addr:full":"89 Redcliff St Bristol City of Bristol BS1 6LU",
    "addr:housenumber":"89",
    "addr:postcode":"bs1 6lu",
    "addr:street":"Redcliff St",
    "iso:country":"GB",
    "sg:address":"89 Redcliff St",
    "sg:city":"Bristol",
    "sg:classifiers":[
        {
            "category":"Professional",
            "subcategory":"Management & Consulting",
            "type":"Services"
        }
    ],
    "sg:phone":"+44 117 934 9800",
    "sg:postcode":"BS1 6LU",
    "sg:province":"City of Bristol",
    "sg:tags":[
        "marketing",
        "consultant"
    ],
    "wof:name":"Aspect Marketing Services Ltd",
    "wof:placetype":"venue"
},
  "geometry": {"coordinates":[-2.5927920341,51.449508667],"type":"Point"}
}