{
  "type": "Feature",
  "properties": {
    "addr:full":"3 The Chestnuts, Burnham Road Southminster Essex CM0 7HD",
    "addr:housenumber":"3",
    "addr:postcode":"cm0 7hd",
    "addr:street":"The Chestnuts Burnham Road",
    "iso:country":"GB",
    "sg:address":"3 The Chestnuts, Burnham Road",
    "sg:city":"Southminster",
    "sg:classifiers":[
        {
            "category":"Manufacturing",
            "subcategory":"Petroleum Products",
            "type":"Manufacturing & Wholesale Goods"
        }
    ],
    "sg:phone":"+44 1245 474722",
    "sg:postcode":"CM0 7HD",
    "sg:province":"Essex",
    "sg:tags":[
        "double",
        "glazing"
    ],
    "wof:name":"Associated Services",
    "wof:placetype":"venue"
},
  "geometry": {"coordinates":[0.8291900158,51.6624183655],"type":"Point"}
}