{
  "type": "Feature",
  "properties": {
    "iso:country":"GB",
    "sg:address":"19 Belmont Avenue",
    "sg:city":"Bournemouth",
    "sg:classifiers":[
        {
            "category":"Travel",
            "subcategory":"Travel Agent",
            "type":"Entertainment"
        }
    ],
    "sg:postcode":"BH8 0AN",
    "sg:province":"Dorset",
    "wof:name":"Travel Jet",
    "wof:placetype":"venue"
},
  "geometry": {"coordinates":[-1.85229,50.754078],"type":"Point"}
}