{
  "type": "Feature",
  "properties": {
    "addr:full":"19 Belmont Avenue Bournemouth Dorset BH8 0AN",
    "addr:housenumber":"19",
    "addr:postcode":"bh8 0an",
    "addr:street":"Belmont Avenue",
    "iso:country":"GB",
    "sg:address":"19 Belmont Avenue",
    "sg:city":"Bournemouth",
    "sg:classifiers":[
        {
            "category":"Travel",
            "subcategory":"Travel Agent",
            "type":"Entertainment"
        }
    ],
    "sg:postcode":"BH8 0AN",
    "sg:province":"Dorset",
    "wof:name":"Travel Jet",
    "wof:placetype":"venue"
},
  "geometry": {"coordinates":[-1.85229,50.754078],"type":"Point"}
}