{
  "type": "Feature",
  "properties": {
    "addr:full":"Keynsham Surgery 4 Station Road, Keynsham Bristol City of Bristol BS31 2BN",
    "addr:housenumber":"4",
    "addr:postcode":"bs31 2bn",
    "addr:street":"Station Road",
    "iso:country":"GB",
    "sg:address":"Keynsham Surgery 4 Station Road, Keynsham",
    "sg:city":"Bristol",
    "sg:classifiers":[
        {
            "category":"Health Services",
            "subcategory":"Doctor",
            "type":"Services"
        }
    ],
    "sg:phone":"+44 117 986 2343",
    "sg:postcode":"BS31 2BN",
    "sg:province":"City of Bristol",
    "sg:tags":[
        "practitioners"
    ],
    "wof:name":"Keynsham Surgery",
    "wof:placetype":"venue"
},
  "geometry": {"coordinates":[-2.5160269737,51.4249954224],"type":"Point"}
}