{
  "type": "Feature",
  "properties": {
    "addr:full":"44-46 George Street Altrincham Cheshire WA14 1RH",
    "addr:housenumber":"44-46",
    "addr:postcode":"wa14 1rh",
    "addr:street":"George Street",
    "iso:country":"GB",
    "sg:address":"44-46 George Street",
    "sg:city":"Altrincham",
    "sg:classifiers":[
        {
            "category":"Travel",
            "subcategory":"Travel Agent",
            "type":"Entertainment"
        }
    ],
    "sg:phone":"+44 161 941 4061",
    "sg:postcode":"WA14 1RH",
    "sg:province":"Cheshire",
    "wof:name":"Going Places Leisure Travel",
    "wof:placetype":"venue"
},
  "geometry": {"coordinates":[-2.350018,53.387314],"type":"Point"}
}