{
  "type": "Feature",
  "properties": {
    "iso:country":"GB",
    "sg:address":"Unit 38",
    "sg:city":"Loanhead",
    "sg:classifiers":[
        {
            "category":"Manufacturing",
            "subcategory":"Petroleum Products",
            "type":"Manufacturing & Wholesale Goods"
        }
    ],
    "sg:phone":"+44 131 228 8004",
    "sg:postcode":"EH20 9LZ",
    "sg:province":"Midlothian",
    "sg:tags":[
        "double",
        "glazing"
    ],
    "wof:name":"Lochinvar Windows Ltd.",
    "wof:placetype":"venue"
},
  "geometry": {"coordinates":[-3.154689,55.880932],"type":"Point"}
}