{
  "type": "Feature",
  "properties": {
    "addr:full":"294 Sandbanks Road, Lilliput Poole Dorset BH14 8HX",
    "addr:housenumber":"294",
    "addr:postcode":"bh14 8hx",
    "addr:street":"Sandbanks Road",
    "iso:country":"GB",
    "sg:address":"294 Sandbanks Road, Lilliput",
    "sg:city":"Poole",
    "sg:classifiers":[
        {
            "category":"Personal",
            "subcategory":"Beauty Salon",
            "type":"Services"
        }
    ],
    "sg:phone":"+44 1202 708058",
    "sg:postcode":"BH14 8HX",
    "sg:province":"Dorset",
    "sg:tags":[
        "lady",
        "hairdresser"
    ],
    "wof:name":"Jane Naden International Hair Stylists",
    "wof:placetype":"venue"
},
  "geometry": {"coordinates":[-1.9450889826,50.7074546814],"type":"Point"}
}