{
  "type": "Feature",
  "properties": {
    "iso:country":"GB",
    "sg:address":"9 Shardeloes Road",
    "sg:city":"London",
    "sg:classifiers":[
        {
            "category":"Retail",
            "subcategory":"Veterinary Services",
            "type":"Services"
        }
    ],
    "sg:phone":"+44 20 8692 3030",
    "sg:postcode":"SE14 6NZ",
    "sg:province":"Greater London",
    "sg:tags":[
        "surgeon"
    ],
    "wof:name":"John Hankinson Veterinary Surgery",
    "wof:placetype":"venue"
},
  "geometry": {"coordinates":[-0.033727,51.47261],"type":"Point"}
}