{
  "type": "Feature",
  "properties": {
    "addr:full":"81 Cussons Clo, Cheshunt Waltham Cross Essex EN8 9PJ",
    "addr:housenumber":"81",
    "addr:postcode":"en8 9pj",
    "addr:street":"Cussons Clo Cheshunt Waltham Cross",
    "iso:country":"GB",
    "sg:address":"81 Cussons Clo, Cheshunt",
    "sg:city":"Waltham Cross",
    "sg:classifiers":[
        {
            "category":"Building & Trades",
            "subcategory":"Construction",
            "type":"Services"
        }
    ],
    "sg:postcode":"EN8 9PJ",
    "sg:province":"Essex",
    "sg:tags":[
        "decorator",
        "painter"
    ],
    "wof:name":"Chase,Michael,",
    "wof:placetype":"venue"
},
  "geometry": {"coordinates":[-0.033814,51.69051],"type":"Point"}
}