{
  "type": "Feature",
  "properties": {
    "addr:full":"Units 1-2 Kendal Court, Cambridge Road Cambridge Cambridgeshire CB4 9YS",
    "addr:housenumber":"units 1-2",
    "addr:postcode":"cb4 9ys",
    "addr:street":"Kendal Court Cambridge Road",
    "iso:country":"GB",
    "sg:address":"Units 1-2 Kendal Court, Cambridge Road",
    "sg:city":"Cambridge",
    "sg:classifiers":[
        {
            "category":"Professional",
            "subcategory":"Printing & Photocopies",
            "type":"Services"
        }
    ],
    "sg:phone":"+44 1223 236786",
    "sg:postcode":"CB4 9YS",
    "sg:province":"Cambridgeshire",
    "sg:tags":[
        "printer"
    ],
    "wof:name":"Camtrust",
    "wof:placetype":"venue"
},
  "geometry": {"coordinates":[0.1109199971,52.2416992188],"type":"Point"}
}