{
  "type": "Feature",
  "properties": {
    "addr:full":"Park Ho, 158-160 Arthur Rd Wimbledon Greater London SW19 8AQ",
    "addr:housenumber":"158-160",
    "addr:postcode":"sw19 8aq",
    "addr:street":"Park;Arthur Rd",
    "iso:country":"GB",
    "sg:address":"Park Ho, 158-160 Arthur Rd",
    "sg:city":"Wimbledon",
    "sg:classifiers":[
        {
            "category":"Real Estate",
            "subcategory":"Surveying",
            "type":"Services"
        }
    ],
    "sg:phone":"+44 20 8946 7950",
    "sg:postcode":"SW19 8AQ",
    "sg:province":"Greater London",
    "sg:tags":[
        "surveyor",
        "valuer"
    ],
    "wof:name":"Frank Coffey Associates",
    "wof:placetype":"venue"
},
  "geometry": {"coordinates":[-0.2070239931,51.4209976196],"type":"Point"}
}