{
  "type": "Feature",
  "properties": {
    "addr:full":"9 Sherlock Mews London Greater London W1U 6DW",
    "addr:housenumber":"9",
    "addr:postcode":"w1u 6dw",
    "addr:street":"Sherlock Mews",
    "iso:country":"GB",
    "sg:address":"9 Sherlock Mews",
    "sg:city":"London",
    "sg:classifiers":[
        {
            "category":"Professional",
            "subcategory":"Management & Consulting",
            "type":"Services"
        }
    ],
    "sg:postcode":"W1U 6DW",
    "sg:province":"Greater London",
    "sg:tags":[
        "consultant",
        "business"
    ],
    "wof:name":"Synapse Training Associates Ltd",
    "wof:placetype":"venue"
},
  "geometry": {"coordinates":[-0.15638,51.520817],"type":"Point"}
}