{
  "type": "Feature",
  "properties": {
    "iso:country":"GB",
    "sg:address":"7 Chaucer Rise",
    "sg:city":"Dukinfield",
    "sg:classifiers":[
        {
            "category":"Professional",
            "subcategory":"Business Services",
            "type":"Services"
        }
    ],
    "sg:phone":"+44 161 303 2873",
    "sg:postcode":"SK16 5EB",
    "sg:province":"Greater Manchester",
    "sg:tags":[
        "import",
        "export",
        "agent"
    ],
    "wof:name":"Rosevada Ltd",
    "wof:placetype":"venue"
},
  "geometry": {"coordinates":[-2.0541980267,53.4701690674],"type":"Point"}
}