{
  "type": "Feature",
  "properties": {
    "iso:country":"GB",
    "sg:address":"63 Oak Hill Crescent",
    "sg:city":"Woodford Green",
    "sg:classifiers":[
        {
            "category":"Professional",
            "subcategory":"Engineering",
            "type":"Services"
        }
    ],
    "sg:postcode":"IG8 9PR",
    "sg:province":"Essex",
    "sg:tags":[
        "contractor",
        "electrical",
        "engineer"
    ],
    "wof:name":"Uk-European Electrical Ltd",
    "wof:placetype":"venue"
},
  "geometry": {"coordinates":[0.004569,51.603695],"type":"Point"}
}