{
  "type": "Feature",
  "properties": {
    "addr:full":"5 Heights Of Alma, Stanley Crook Durham DL15 9QW",
    "addr:housenumber":"5",
    "addr:postcode":"dl15 9qw",
    "addr:street":"Heights Of;Stanley",
    "iso:country":"GB",
    "sg:address":"5 Heights Of Alma, Stanley",
    "sg:city":"Crook",
    "sg:classifiers":[
        {
            "category":"Home & Garden",
            "subcategory":"Furniture",
            "type":"Retail Goods"
        }
    ],
    "sg:phone":"+44 1388 768990",
    "sg:postcode":"DL15 9QW",
    "sg:province":"Durham",
    "wof:name":"Staples Woodcraft",
    "wof:placetype":"venue"
},
  "geometry": {"coordinates":[-1.7487939596,54.7143630981],"type":"Point"}
}