{
  "type": "Feature",
  "properties": {
    "addr:full":"42 Waterleat Close Paignton Devon TQ3 3UN",
    "addr:housenumber":"42",
    "addr:postcode":"tq3 3un",
    "addr:street":"Waterleat Close",
    "iso:country":"GB",
    "sg:address":"42 Waterleat Close",
    "sg:city":"Paignton",
    "sg:classifiers":[
        {
            "category":"Shopping",
            "subcategory":"Computers & Home Electronics",
            "type":"Retail Goods"
        }
    ],
    "sg:phone":"+44 1803 553883",
    "sg:postcode":"TQ3 3UN",
    "sg:province":"Devon",
    "sg:tags":[
        "aerial",
        "television",
        "radio"
    ],
    "wof:name":"A B C Aerials (Torbay)",
    "wof:placetype":"venue"
},
  "geometry": {"coordinates":[-3.5828258991,50.4330024719],"type":"Point"}
}