{
  "type": "Feature",
  "properties": {
    "iso:country":"GB",
    "sg:address":"20 Dingle Road, Upholland",
    "sg:city":"Skelmersdale",
    "sg:classifiers":[
        {
            "category":"Health Services",
            "subcategory":"Doctor",
            "type":"Services"
        }
    ],
    "sg:phone":"+44 1695 624042",
    "sg:postcode":"WN8 0EN",
    "sg:province":"Lancashire",
    "sg:tags":[
        "practitioners"
    ],
    "wof:name":"The Matthew Ryder Clinic",
    "wof:placetype":"venue"
},
  "geometry": {"coordinates":[-2.7265748978,53.5426254272],"type":"Point"}
}