{
  "type": "Feature",
  "properties": {
    "addr:full":"Shrogswood Road, Wickersley Rotherham South Yorkshire S60 4BY",
    "addr:postcode":"s60 4by",
    "addr:street":"Shrogswood Road",
    "iso:country":"GB",
    "sg:address":"Shrogswood Road, Wickersley",
    "sg:city":"Rotherham",
    "sg:classifiers":[
        {
            "category":"Sports & Exercise",
            "subcategory":"Golf",
            "type":"Entertainment"
        }
    ],
    "sg:phone":"+44 1709 541046",
    "sg:postcode":"S60 4BY",
    "sg:province":"South Yorkshire",
    "sg:tags":[
        "club",
        "course"
    ],
    "wof:name":"Sitwell Park Golf Club Ltd.",
    "wof:placetype":"venue"
},
  "geometry": {"coordinates":[-1.3134740591,53.4171257019],"type":"Point"}
}