{
  "type": "Feature",
  "properties": {
    "addr:full":"Unit 9 Frederick Road Kidderminster Staffordshire DY11 7RA",
    "addr:housenumber":"unit 9",
    "addr:postcode":"dy11 7ra",
    "addr:street":"Frederick Road",
    "iso:country":"GB",
    "sg:address":"Unit 9 Frederick Road",
    "sg:city":"Kidderminster",
    "sg:classifiers":[
        {
            "category":"Shopping",
            "subcategory":"Musical Instruments",
            "type":"Retail Goods"
        },
        {
            "category":"Manufacturing",
            "subcategory":"Musical Instruments",
            "type":"Manufacturing & Wholesale Goods"
        }
    ],
    "sg:phone":"+44 1562 827666",
    "sg:postcode":"DY11 7RA",
    "sg:province":"Staffordshire",
    "sg:tags":[
        "music",
        "sheet",
        "agent",
        "manufacturer"
    ],
    "wof:name":"Music Shipping Co.",
    "wof:placetype":"venue"
},
  "geometry": {"coordinates":[-2.240093,52.364841],"type":"Point"}
}