{
  "type": "Feature",
  "properties": {
    "iso:country":"GB",
    "sg:address":"Bogma Hall Farm, Coxhoe",
    "sg:city":"Durham",
    "sg:classifiers":[
        {
            "category":"Farming",
            "subcategory":"Livestock Farm",
            "type":"Manufacturing & Wholesale Goods"
        }
    ],
    "sg:phone":"+44 191 377 0281",
    "sg:postcode":"DH6 4EN",
    "sg:province":"Durham",
    "sg:tags":[
        "others"
    ],
    "wof:name":"John D Seymour",
    "wof:placetype":"venue"
},
  "geometry": {"coordinates":[-1.5024340153,54.7149009705],"type":"Point"}
}