{
  "type": "Feature",
  "properties": {
    "addr:full":"Haverfield, Fletchwood Lane, Totton Southampton Hampshire SO40 7DZ",
    "addr:postcode":"so40 7dz",
    "addr:street":"Fletchwood Lane",
    "iso:country":"GB",
    "sg:address":"Haverfield, Fletchwood Lane, Totton",
    "sg:city":"Southampton",
    "sg:classifiers":[
        {
            "category":"Professional",
            "subcategory":"Accounting & Tax Preparation",
            "type":"Services"
        }
    ],
    "sg:postcode":"SO40 7DZ",
    "sg:province":"Hampshire",
    "sg:tags":[
        "accountant"
    ],
    "wof:name":"Jones Forbes & Co. Ltd.",
    "wof:placetype":"venue"
},
  "geometry": {"coordinates":[-1.5323870182,50.8972091675],"type":"Point"}
}