{
  "type": "Feature",
  "properties": {
    "addr:full":"Hubbards Close Hornchurch Essex RM11 3DH",
    "addr:postcode":"rm11 3dh",
    "addr:street":"Hubbards Close",
    "iso:country":"GB",
    "sg:address":"Hubbards Close",
    "sg:city":"Hornchurch",
    "sg:classifiers":[
        {
            "category":"Wholesale",
            "subcategory":"Non-durable Goods",
            "type":"Manufacturing & Wholesale Goods"
        },
        {
            "category":"Utilities",
            "subcategory":"Refuse",
            "type":"Services"
        }
    ],
    "sg:phone":"+44 1708 456910",
    "sg:postcode":"RM11 3DH",
    "sg:province":"Essex",
    "sg:tags":[
        "disposal",
        "waste",
        "animal",
        "by-product"
    ],
    "wof:name":"Fortune Farm",
    "wof:placetype":"venue"
},
  "geometry": {"coordinates":[0.2424100041,51.5769195557],"type":"Point"}
}