{
  "type": "Feature",
  "properties": {
    "iso:country":"GB",
    "sg:address":"Edon Ho, 1 Pen-y-lan Rd",
    "sg:city":"Cardiff",
    "sg:classifiers":[
        {
            "category":"Insurance",
            "subcategory":"Insurance Agent",
            "type":"Services"
        }
    ],
    "sg:phone":"+44 29 2045 3000",
    "sg:postcode":"CF2 3PG",
    "sg:province":"Cardiff",
    "sg:tags":[
        "broker"
    ],
    "wof:name":"Time To Insure Ltd",
    "wof:placetype":"venue"
},
  "geometry": {"coordinates":[-3.18067,51.481258],"type":"Point"}
}