{
  "type": "Feature",
  "properties": {
    "iso:country":"GB",
    "sg:address":"Dunearn Dr",
    "sg:city":"Kirkcaldy",
    "sg:classifiers":[
        {
            "category":"Bars & Pubs",
            "type":"Food & Drink"
        }
    ],
    "sg:phone":"+44 1592 201946",
    "sg:postcode":"KY2 6AH",
    "sg:province":"Fife",
    "sg:tags":[
        "pubs",
        "inn"
    ],
    "wof:name":"Dunearn Roadhouse",
    "wof:placetype":"venue"
},
  "geometry": {"coordinates":[-3.184464,56.124729],"type":"Point"}
}