{
  "type": "Feature",
  "properties": {
    "iso:country":"GB",
    "sg:address":"Culworth Road, Chipping Warden",
    "sg:city":"Banbury",
    "sg:classifiers":[
        {
            "category":"Bars & Pubs",
            "type":"Food & Drink"
        }
    ],
    "sg:phone":"+44 1295 660230",
    "sg:postcode":"OX17 1LB",
    "sg:province":"Northamptonshire",
    "sg:tags":[
        "pubs",
        "inn"
    ],
    "wof:name":"The Griffin",
    "wof:placetype":"venue"
},
  "geometry": {"coordinates":[-1.271519,52.135799],"type":"Point"}
}