{
  "type": "Feature",
  "properties": {
    "addr:full":"3 Ashgrove, Messingham Scunthorpe Lincolnshire DN17 3QY",
    "addr:housenumber":"3",
    "addr:postcode":"dn17 3qy",
    "addr:street":"Ashgrove",
    "iso:country":"GB",
    "sg:address":"3 Ashgrove, Messingham",
    "sg:city":"Scunthorpe",
    "sg:classifiers":[
        {
            "category":"Building & Trades",
            "subcategory":"Construction",
            "type":"Services"
        }
    ],
    "sg:phone":"+44 1724 764175",
    "sg:postcode":"DN17 3QY",
    "sg:province":"Lincolnshire",
    "sg:tags":[
        "joiner",
        "carpenter"
    ],
    "wof:name":"K Wood",
    "wof:placetype":"venue"
},
  "geometry": {"coordinates":[-0.6888689995,53.5283699036],"type":"Point"}
}