{
  "type": "Feature",
  "properties": {
    "addr:full":"Cherrywood Lodge, Polperro Road Looe Cornwall PL13 2JE",
    "addr:postcode":"pl13 2je",
    "addr:street":"Polperro Road",
    "iso:country":"GB",
    "sg:address":"Cherrywood Lodge, Polperro Road",
    "sg:city":"Looe",
    "sg:classifiers":[
        {
            "category":"Shopping",
            "subcategory":"Music",
            "type":"Retail Goods"
        }
    ],
    "sg:phone":"+44 1503 265515",
    "sg:postcode":"PL13 2JE",
    "sg:province":"Cornwall",
    "sg:tags":[
        "record",
        "tape",
        "cd"
    ],
    "wof:name":"Energy Mail Order",
    "wof:placetype":"venue"
},
  "geometry": {"coordinates":[-4.462355,50.356121],"type":"Point"}
}