{
  "type": "Feature",
  "properties": {
    "iso:country":"GB",
    "sg:address":"45 The Moor",
    "sg:city":"Bedford",
    "sg:classifiers":[
        {
            "category":"Personal",
            "subcategory":"Beauty Salon",
            "type":"Services"
        }
    ],
    "sg:phone":"+44 1234 721242",
    "sg:postcode":"MK43 7JR",
    "sg:province":"Bedfordshire",
    "sg:tags":[
        "unisex",
        "hairdresser"
    ],
    "wof:name":"Pigtails",
    "wof:placetype":"venue"
},
  "geometry": {"coordinates":[-0.60632,52.191105],"type":"Point"}
}