{
  "type": "Feature",
  "properties": {
    "addr:full":"115 Queenstown Road London Greater London SW8 3RH",
    "addr:housenumber":"115",
    "addr:postcode":"sw8 3rh",
    "addr:street":"Queenstown Road",
    "iso:country":"GB",
    "sg:address":"115 Queenstown Road",
    "sg:city":"London",
    "sg:classifiers":[
        {
            "category":"Shopping",
            "subcategory":"Used Merchandise",
            "type":"Retail Goods"
        },
        {
            "category":"Retail",
            "subcategory":"Storage",
            "type":"Services"
        },
        {
            "category":"Home & Garden",
            "subcategory":"Furniture",
            "type":"Retail Goods"
        }
    ],
    "sg:phone":"+44 20 7720 9206",
    "sg:postcode":"SW8 3RH",
    "sg:province":"Greater London",
    "sg:tags":[
        "household",
        "outlet",
        "removal"
    ],
    "wof:name":"Furnituretc Ltd",
    "wof:placetype":"venue"
},
  "geometry": {"coordinates":[-0.149961,51.469734],"type":"Point"}
}