{
  "type": "Feature",
  "properties": {
    "addr:full":"88 South Street, Stanground Peterborough Cambridgeshire PE2 8EZ",
    "addr:housenumber":"88",
    "addr:postcode":"pe2 8ez",
    "addr:street":"South Street",
    "iso:country":"GB",
    "sg:address":"88 South Street, Stanground",
    "sg:city":"Peterborough",
    "sg:classifiers":[
        {
            "category":"Autos & Motor Vehicles",
            "subcategory":"Automobile Sales",
            "type":"Retail Goods"
        }
    ],
    "sg:phone":"+44 1733 555011",
    "sg:postcode":"PE2 8EZ",
    "sg:province":"Cambridgeshire",
    "sg:tags":[
        "car"
    ],
    "wof:name":"Regency Cars",
    "wof:placetype":"venue"
},
  "geometry": {"coordinates":[-0.227483,52.556992],"type":"Point"}
}