{
  "type": "Feature",
  "properties": {
    "addr:full":"Queens Avenue London Greater London N10 3PE",
    "addr:postcode":"n10 3pe",
    "addr:street":"Queens Avenue",
    "iso:country":"GB",
    "sg:address":"Queens Avenue",
    "sg:city":"London",
    "sg:classifiers":[
        {
            "category":"Education",
            "subcategory":"Library",
            "type":"Public Place"
        }
    ],
    "sg:phone":"+44 20 8883 6734",
    "sg:postcode":"N10 3PE",
    "sg:province":"Greater London",
    "sg:tags":[
        "book"
    ],
    "wof:name":"Muswell Hill Library",
    "wof:placetype":"venue"
},
  "geometry": {"coordinates":[-0.1449600011,51.5918807983],"type":"Point"}
}