{
  "type": "Feature",
  "properties": {
    "addr:full":"Gretton Farm, Gretton Cheltenham Gloucestershire GL54 5ES",
    "addr:housenumber":"gretton",
    "addr:postcode":"gl54 5es",
    "iso:country":"GB",
    "sg:address":"Gretton Farm, Gretton",
    "sg:city":"Cheltenham",
    "sg:classifiers":[
        {
            "category":"Building & Trades",
            "subcategory":"Construction",
            "type":"Services"
        }
    ],
    "sg:phone":"+44 1242 602474",
    "sg:postcode":"GL54 5ES",
    "sg:province":"Gloucestershire",
    "sg:tags":[
        "demolition",
        "contractor"
    ],
    "wof:name":"Deconstruct Demolition Services",
    "wof:placetype":"venue"
},
  "geometry": {"coordinates":[-1.987416,51.971378],"type":"Point"}
}