{
  "type": "Feature",
  "properties": {
    "addr:full":"3 Maine Road Manchester Greater Manchester M14 4DN",
    "addr:housenumber":"3",
    "addr:postcode":"m14 4dn",
    "addr:street":"Maine Road",
    "iso:country":"GB",
    "sg:address":"3 Maine Road",
    "sg:city":"Manchester",
    "sg:classifiers":[
        {
            "category":"Professional",
            "subcategory":"Business Services",
            "type":"Services"
        }
    ],
    "sg:postcode":"M14 4DN",
    "sg:province":"Greater Manchester",
    "sg:tags":[
        "distribution"
    ],
    "wof:name":"N & B Transport",
    "wof:placetype":"venue"
},
  "geometry": {"coordinates":[-2.2352399826,53.4570884705],"type":"Point"}
}