{
  "type": "Feature",
  "properties": {
    "addr:full":"20 Bridge Street Kirkwall Orkney Islands KW15 1HR",
    "addr:housenumber":"20",
    "addr:postcode":"kw15 1hr",
    "addr:street":"Bridge Street",
    "iso:country":"GB",
    "sg:address":"20 Bridge Street",
    "sg:city":"Kirkwall",
    "sg:classifiers":[
        {
            "category":"Professional",
            "subcategory":"Art Services",
            "type":"Services"
        }
    ],
    "sg:phone":"+44 1856 873574",
    "sg:postcode":"KW15 1HR",
    "sg:province":"Orkney Islands",
    "sg:tags":[
        "photographer"
    ],
    "wof:name":"Orkney Photographic",
    "wof:placetype":"venue"
},
  "geometry": {"coordinates":[-2.95779,58.984203],"type":"Point"}
}