{
  "type": "Feature",
  "properties": {
    "addr:full":"429 Dudley Road Birmingham West Midlands B18 4HD",
    "addr:housenumber":"429",
    "addr:postcode":"b18 4hd",
    "addr:street":"Dudley Road",
    "iso:country":"GB",
    "sg:address":"429 Dudley Road",
    "sg:city":"Birmingham",
    "sg:classifiers":[
        {
            "category":"Cinema",
            "subcategory":"Movie Rental",
            "type":"Entertainment"
        }
    ],
    "sg:phone":"+44 121 558 4967",
    "sg:postcode":"B18 4HD",
    "sg:province":"West Midlands",
    "sg:tags":[
        "video",
        "library"
    ],
    "wof:name":"Video Oasis",
    "wof:placetype":"venue"
},
  "geometry": {"coordinates":[-1.9466370344,52.4874725342],"type":"Point"}
}