{
  "type": "Feature",
  "properties": {
    "iso:country":"GB",
    "sg:address":"Haseldine Road, London Colney",
    "sg:city":"St Albans",
    "sg:classifiers":[
        {
            "category":"Social Services",
            "subcategory":"Adult Care",
            "type":"Services"
        },
        {
            "category":"Social Services",
            "subcategory":"Retirement Home",
            "type":"Services"
        }
    ],
    "sg:phone":"+44 1727 825809",
    "sg:postcode":"AL2 1RS",
    "sg:province":"Hertfordshire",
    "sg:tags":[
        "housing",
        "sheltered",
        "accommodation"
    ],
    "wof:name":"Cyril Dumpleton House",
    "wof:placetype":"venue"
},
  "geometry": {"coordinates":[-0.296517998,51.7234954834],"type":"Point"}
}