{
  "type": "Feature",
  "properties": {
    "iso:country":"GB",
    "sg:address":"54 Vicar Street",
    "sg:city":"Falkirk",
    "sg:classifiers":[
        {
            "category":"Education",
            "subcategory":"Library",
            "type":"Public Place"
        }
    ],
    "sg:phone":"+44 1324 633569",
    "sg:postcode":"FK1 1JB",
    "sg:province":"Falkirk",
    "sg:tags":[
        "reproduction",
        "furniture"
    ],
    "wof:name":"Fairweathers",
    "wof:placetype":"venue"
},
  "geometry": {"coordinates":[-3.7844090462,56.0016059875],"type":"Point"}
}