{
  "type": "Feature",
  "properties": {
    "iso:country":"GB",
    "sg:address":"Suite 1 B Y C, House Lock Lane, Birdham",
    "sg:city":"Chichester",
    "sg:classifiers":[
        {
            "category":"Retail",
            "subcategory":"Storage",
            "type":"Services"
        }
    ],
    "sg:postcode":"PO20 7BB",
    "sg:province":"West Sussex",
    "sg:tags":[
        "household",
        "removal"
    ],
    "wof:name":"Archibald Removals Ltd.",
    "wof:placetype":"venue"
},
  "geometry": {"coordinates":[-0.829297,50.803181],"type":"Point"}
}