{
  "type": "Feature",
  "properties": {
    "iso:country":"GB",
    "sg:address":"2 Park Flats, New Park Rd",
    "sg:city":"Cranleigh",
    "sg:classifiers":[
        {
            "category":"Shopping",
            "subcategory":"Photographic Equipment",
            "type":"Retail Goods"
        }
    ],
    "sg:phone":"+44 1483 274328",
    "sg:postcode":"GU6 7HL",
    "sg:province":"Surrey",
    "wof:name":"Mark Alexander Scott Photography",
    "wof:placetype":"venue"
},
  "geometry": {"coordinates":[-0.482999,51.141541],"type":"Point"}
}