{
  "type": "Feature",
  "properties": {
    "iso:country":"GB",
    "sg:address":"286 Romford Road",
    "sg:city":"London",
    "sg:classifiers":[
        {
            "category":"Home & Garden",
            "subcategory":"Garden Supply",
            "type":"Retail Goods"
        }
    ],
    "sg:postcode":"E7 9HD",
    "sg:province":"Greater London",
    "sg:tags":[
        "nursery",
        "centre"
    ],
    "wof:name":"Forest Gate Construction Co. Ltd.",
    "wof:placetype":"venue"
},
  "geometry": {"coordinates":[0.0232170001,51.5463905334],"type":"Point"}
}