{
  "type": "Feature",
  "properties": {
    "addr:full":"23 Howley Grange Rd Halesowen West Midlands B62 0HN",
    "addr:housenumber":"23",
    "addr:postcode":"b62 0hn",
    "addr:street":"Howley Grange Rd",
    "iso:country":"GB",
    "sg:address":"23 Howley Grange Rd",
    "sg:city":"Halesowen",
    "sg:classifiers":[
        {
            "category":"Health Services",
            "subcategory":"Doctor",
            "type":"Services"
        }
    ],
    "sg:phone":"+44 121 422 2345",
    "sg:postcode":"B62 0HN",
    "sg:province":"West Midlands",
    "sg:tags":[
        "practitioners"
    ],
    "wof:name":"Lewis, R A",
    "wof:placetype":"venue"
},
  "geometry": {"coordinates":[-2.01762,52.458157],"type":"Point"}
}