{
  "type": "Feature",
  "properties": {
    "addr:full":"Desborough Road High Wycombe Buckinghamshire HP11 2PR",
    "addr:postcode":"hp11 2pr",
    "addr:street":"Desborough Road",
    "iso:country":"GB",
    "sg:address":"Desborough Road",
    "sg:city":"High Wycombe",
    "sg:classifiers":[
        {
            "category":"Bars & Pubs",
            "type":"Food & Drink"
        }
    ],
    "sg:phone":"+44 1494 527982",
    "sg:postcode":"HP11 2PR",
    "sg:province":"Buckinghamshire",
    "sg:tags":[
        "pubs",
        "inn"
    ],
    "wof:name":"Rose & Crown",
    "wof:placetype":"venue"
},
  "geometry": {"coordinates":[-0.7642740011,51.6324234009],"type":"Point"}
}