{
  "type": "Feature",
  "properties": {
    "addr:full":"55 Mansfield Road Basingstoke Hampshire RG22 6DY",
    "addr:housenumber":"55",
    "addr:postcode":"rg22 6dy",
    "addr:street":"Mansfield Road",
    "iso:country":"GB",
    "sg:address":"55 Mansfield Road",
    "sg:city":"Basingstoke",
    "sg:classifiers":[
        {
            "category":"Personal",
            "type":"Services"
        }
    ],
    "sg:postcode":"RG22 6DY",
    "sg:province":"Hampshire",
    "sg:tags":[
        "dressmaker"
    ],
    "wof:name":"Mrs Bolis's Dressmaking Services",
    "wof:placetype":"venue"
},
  "geometry": {"coordinates":[-1.1108230352,51.2529640198],"type":"Point"}
}