{
  "type": "Feature",
  "properties": {
    "addr:full":"Unit 2 Ashcourt, Westover Industrial Estate Ivybridge Devon PL21 9GE",
    "addr:housenumber":"unit 2",
    "addr:postcode":"pl21 9ge",
    "addr:street":"Ashcourt Westover Industrial Estate",
    "iso:country":"GB",
    "sg:address":"Unit 2 Ashcourt, Westover Industrial Estate",
    "sg:city":"Ivybridge",
    "sg:classifiers":[
        {
            "category":"Home & Garden",
            "subcategory":"Household Appliances",
            "type":"Retail Goods"
        }
    ],
    "sg:postcode":"PL21 9GE",
    "sg:province":"Devon",
    "sg:tags":[
        "electrical"
    ],
    "wof:name":"Willcocks Appliance Services",
    "wof:placetype":"venue"
},
  "geometry": {"coordinates":[-3.9273629189,50.3855667114],"type":"Point"}
}