{
  "type": "Feature",
  "properties": {
    "addr:full":"Weald House, 88 Main Road, Sundridge Sevenoaks Kent TN14 6ER",
    "addr:housenumber":"88",
    "addr:postcode":"tn14 6er",
    "addr:street":"Main Road",
    "iso:country":"GB",
    "sg:address":"Weald House, 88 Main Road, Sundridge",
    "sg:city":"Sevenoaks",
    "sg:classifiers":[
        {
            "category":"Banks & Credit Unions",
            "subcategory":"Financial Services",
            "type":"Services"
        }
    ],
    "sg:phone":"+44 1959 568800",
    "sg:postcode":"TN14 6ER",
    "sg:province":"Kent",
    "sg:tags":[
        "consultant"
    ],
    "wof:name":"Close Brothers Military Services Ltd.",
    "wof:placetype":"venue"
},
  "geometry": {"coordinates":[0.1317590028,51.2789764404],"type":"Point"}
}