{
  "type": "Feature",
  "properties": {
    "iso:country":"GB",
    "sg:address":"1e & 1f Lee Grn",
    "sg:city":"Mirfield",
    "sg:classifiers":[
        {
            "category":"Personal",
            "subcategory":"Beauty Salon",
            "type":"Services"
        }
    ],
    "sg:phone":"+44 1924 490237",
    "sg:postcode":"WF14 0AB",
    "sg:province":"West Yorkshire",
    "sg:tags":[
        "unisex",
        "hairdresser"
    ],
    "wof:name":"Hairlines Beauty Workshop",
    "wof:placetype":"venue"
},
  "geometry": {"coordinates":[-1.69559,53.685329],"type":"Point"}
}