{
  "type": "Feature",
  "properties": {
    "iso:country":"GB",
    "sg:address":"Venture House, Cross St Arnold",
    "sg:city":"Nottingham",
    "sg:classifiers":[
        {
            "category":"Professional",
            "subcategory":"Accounting & Tax Preparation",
            "type":"Services"
        }
    ],
    "sg:phone":"+44 115 926 3018",
    "sg:postcode":"NG5 7PJ",
    "sg:province":"Nottinghamshire",
    "sg:tags":[
        "accountant"
    ],
    "wof:name":"Julian Jackson",
    "wof:placetype":"venue"
},
  "geometry": {"coordinates":[-1.1313929558,53.0065078735],"type":"Point"}
}