{
  "type": "Feature",
  "properties": {
    "addr:full":"St Georges Way Leicester Leicestershire LE1 1SH",
    "addr:postcode":"le1 1sh",
    "addr:street":"St Georges Way",
    "iso:country":"GB",
    "sg:address":"St Georges Way",
    "sg:city":"Leicester",
    "sg:classifiers":[
        {
            "category":"Autos & Motor Vehicles",
            "subcategory":"Automobile Sales",
            "type":"Retail Goods"
        }
    ],
    "sg:phone":"+44 116 251 9665",
    "sg:postcode":"LE1 1SH",
    "sg:province":"Leicestershire",
    "sg:tags":[
        "car"
    ],
    "wof:name":"St.Georges Motor Co.",
    "wof:placetype":"venue"
},
  "geometry": {"coordinates":[-1.123229,52.634892],"type":"Point"}
}