{
  "type": "Feature",
  "properties": {
    "iso:country":"GB",
    "sg:address":"113 Townhead, Kirkintilloch",
    "sg:city":"Glasgow",
    "sg:classifiers":[
        {
            "category":"Building & Trades",
            "subcategory":"Construction",
            "type":"Services"
        }
    ],
    "sg:phone":"+44 141 776 8050",
    "sg:postcode":"G66 1NX",
    "sg:province":"East Dunbartonshire",
    "sg:tags":[
        "joiner",
        "carpenter"
    ],
    "wof:name":"The Door Shop",
    "wof:placetype":"venue"
},
  "geometry": {"coordinates":[-4.179119,55.947262],"type":"Point"}
}