{
  "type": "Feature",
  "properties": {
    "iso:country":"GB",
    "sg:address":"Unit 17 Tremarl Industrial Estate",
    "sg:city":"Llandudno Junction",
    "sg:classifiers":[
        {
            "category":"Professional",
            "subcategory":"Engineering",
            "type":"Services"
        }
    ],
    "sg:phone":"+44 1492 573100",
    "sg:postcode":"LL31 9NF",
    "sg:province":"Conwy",
    "sg:tags":[
        "contractor",
        "electrical",
        "engineer"
    ],
    "wof:name":"R L Martindale",
    "wof:placetype":"venue"
},
  "geometry": {"coordinates":[-3.7934288979,53.2809562683],"type":"Point"}
}