{
  "type": "Feature",
  "properties": {
    "addr:full":"131b Hathaway Road Grays Essex RM17 5LS",
    "addr:housenumber":"131b",
    "addr:postcode":"rm17 5ls",
    "addr:street":"Hathaway Road",
    "iso:country":"GB",
    "sg:address":"131b Hathaway Road",
    "sg:city":"Grays",
    "sg:classifiers":[
        {
            "category":"Manufacturing",
            "subcategory":"Petroleum Products",
            "type":"Manufacturing & Wholesale Goods"
        }
    ],
    "sg:phone":"+44 1375 384374",
    "sg:postcode":"RM17 5LS",
    "sg:province":"Essex",
    "sg:tags":[
        "double",
        "glazing"
    ],
    "wof:name":"Daybreak Window",
    "wof:placetype":"venue"
},
  "geometry": {"coordinates":[0.324521,51.486256],"type":"Point"}
}