{
  "type": "Feature",
  "properties": {
    "addr:full":"Tivoli Walk, Mumbles Road Swansea Swansea SA3 4DN",
    "addr:postcode":"sa3 4dn",
    "addr:street":"Tivoli Walk Mumbles Road",
    "iso:country":"GB",
    "sg:address":"Tivoli Walk, Mumbles Road",
    "sg:city":"Swansea",
    "sg:classifiers":[
        {
            "category":"Cafe",
            "type":"Food & Drink"
        }
    ],
    "sg:postcode":"SA3 4DN",
    "sg:province":"Swansea",
    "sg:tags":[
        "tea",
        "room"
    ],
    "wof:name":"Trams Diner",
    "wof:placetype":"venue"
},
  "geometry": {"coordinates":[-3.9913370609,51.572467804],"type":"Point"}
}