{
  "type": "Feature",
  "properties": {
    "iso:country":"GB",
    "sg:address":"82-84 Station Road, Shirebrook",
    "sg:city":"Mansfield",
    "sg:classifiers":[
        {
            "category":"Shopping",
            "subcategory":"News",
            "type":"Retail Goods"
        }
    ],
    "sg:phone":"+44 1623 742595",
    "sg:postcode":"NG20 8SZ",
    "sg:province":"Derbyshire",
    "sg:tags":[
        "newsagent"
    ],
    "wof:name":"Jaspers News",
    "wof:placetype":"venue"
},
  "geometry": {"coordinates":[-1.206779,53.203991],"type":"Point"}
}