{
  "type": "Feature",
  "properties": {
    "addr:full":"101 Grahams Road Falkirk Falkirk FK2 7DD",
    "addr:housenumber":"101",
    "addr:postcode":"fk2 7dd",
    "addr:street":"Grahams Road",
    "iso:country":"GB",
    "sg:address":"101 Grahams Road",
    "sg:city":"Falkirk",
    "sg:classifiers":[
        {
            "category":"Personal",
            "subcategory":"Beauty Salon",
            "type":"Services"
        }
    ],
    "sg:postcode":"FK2 7DD",
    "sg:province":"Falkirk",
    "sg:tags":[
        "unisex",
        "hairdresser"
    ],
    "wof:name":"S G Hi'tek Hair",
    "wof:placetype":"venue"
},
  "geometry": {"coordinates":[-3.7841489315,56.0074806213],"type":"Point"}
}