{
  "type": "Feature",
  "properties": {
    "iso:country":"GB",
    "sg:address":"8 Princes Parade",
    "sg:city":"Liverpool",
    "sg:classifiers":[
        {
            "category":"Professional",
            "subcategory":"Accounting & Tax Preparation",
            "type":"Services"
        }
    ],
    "sg:phone":"+44 151 227 4242",
    "sg:postcode":"L3 1QJ",
    "sg:province":"Merseyside",
    "sg:tags":[
        "accountant",
        "activity"
    ],
    "sg:website":"http://www.pwc.com",
    "wof:name":"Pricewaterhousecoopers Llp",
    "wof:placetype":"venue"
},
  "geometry": {"coordinates":[-2.962299,53.393925],"type":"Point"}
}