{
  "type": "Feature",
  "properties": {
    "addr:full":"Burwardsley Chester Cheshire CH3 9PF",
    "addr:postcode":"ch3 9pf",
    "addr:street":"Chester",
    "iso:country":"GB",
    "sg:address":"Burwardsley",
    "sg:city":"Chester",
    "sg:classifiers":[
        {
            "category":"Travel",
            "subcategory":"Hotels & Motels",
            "type":"Entertainment"
        }
    ],
    "sg:phone":"+44 1829 770434",
    "sg:postcode":"CH3 9PF",
    "sg:province":"Cheshire",
    "wof:name":"The Pheasant Inn Ltd.",
    "wof:placetype":"venue"
},
  "geometry": {"coordinates":[-2.7173600197,53.1048088074],"type":"Point"}
}