{
  "type": "Feature",
  "properties": {
    "iso:country":"GB",
    "sg:address":"Peter House, Oxford Street",
    "sg:city":"Manchester",
    "sg:classifiers":[
        {
            "category":"Real Estate",
            "subcategory":"Architect",
            "type":"Services"
        }
    ],
    "sg:phone":"+44 1625 431792",
    "sg:postcode":"M1 5AB",
    "sg:province":"Greater Manchester",
    "wof:name":"Rod Hackney & Associates Ltd.",
    "wof:placetype":"venue"
},
  "geometry": {"coordinates":[-2.2408840656,53.4743499756],"type":"Point"}
}