{
  "type": "Feature",
  "properties": {
    "iso:country":"GB",
    "sg:address":"Caker Stream Rd",
    "sg:city":"Alton",
    "sg:classifiers":[
        {
            "category":"Manufacturing",
            "subcategory":"Electronics",
            "type":"Manufacturing & Wholesale Goods"
        }
    ],
    "sg:phone":"+44 1420 542239",
    "sg:postcode":"GU34 2QF",
    "sg:province":"Hampshire",
    "sg:tags":[
        "control",
        "component",
        "-",
        "electronic"
    ],
    "wof:name":"Kaizen Systems Ltd",
    "wof:placetype":"venue"
},
  "geometry": {"coordinates":[-0.9623270035,51.1517944336],"type":"Point"}
}