{
  "type": "Feature",
  "properties": {
    "addr:full":"8 Fairview Terrace Merthyr Tydfil Merthyr Tydfil CF47 0RL",
    "addr:housenumber":"8",
    "addr:postcode":"cf47 0rl",
    "addr:street":"Fairview Terrace",
    "iso:country":"GB",
    "sg:address":"8 Fairview Terrace",
    "sg:city":"Merthyr Tydfil",
    "sg:classifiers":[
        {
            "category":"Building & Trades",
            "subcategory":"Construction",
            "type":"Services"
        }
    ],
    "sg:postcode":"CF47 0RL",
    "sg:province":"Merthyr Tydfil",
    "sg:tags":[
        "joiner",
        "carpenter"
    ],
    "wof:name":"John Wakeham",
    "wof:placetype":"venue"
},
  "geometry": {"coordinates":[-3.372795105,51.741481781],"type":"Point"}
}