{
  "type": "Feature",
  "properties": {
    "addr:full":"64 North Road, Chester Le Street Durham Durham DH3 4AJ",
    "addr:housenumber":"64",
    "addr:postcode":"dh3 4aj",
    "addr:street":"North Road;Le Street",
    "iso:country":"GB",
    "sg:address":"64 North Road, Chester Le Street",
    "sg:city":"Durham",
    "sg:classifiers":[
        {
            "category":"Freight",
            "type":"Transportation"
        }
    ],
    "sg:postcode":"DH3 4AJ",
    "sg:province":"Durham",
    "sg:tags":[
        "haulage",
        "road"
    ],
    "wof:name":"Herdman Haulage Ltd.",
    "wof:placetype":"venue"
},
  "geometry": {"coordinates":[-1.5754799843,54.8721694946],"type":"Point"}
}