{
  "type": "Feature",
  "properties": {
    "addr:full":"Byron House Nottingham Nottinghamshire NG1 4GH",
    "addr:postcode":"ng1 4gh",
    "iso:country":"GB",
    "sg:address":"Byron House",
    "sg:city":"Nottingham",
    "sg:classifiers":[
        {
            "category":"Professional",
            "subcategory":"Employment Agencies",
            "type":"Services"
        },
        {
            "category":"Education",
            "subcategory":"University",
            "type":"Public Place"
        }
    ],
    "sg:phone":"+44 115 848 6200",
    "sg:postcode":"NG1 4GH",
    "sg:province":"Nottinghamshire",
    "sg:tags":[
        "consultant",
        "school",
        "medical"
    ],
    "wof:name":"The Nottingham Trent University Union of Students",
    "wof:placetype":"venue"
},
  "geometry": {"coordinates":[-1.143924,52.949226],"type":"Point"}
}