{
  "type": "Feature",
  "properties": {
    "iso:country":"GB",
    "sg:address":"1 Pinewood Gdns",
    "sg:city":"Ferndown",
    "sg:classifiers":[
        {
            "category":"Real Estate",
            "subcategory":"Architect",
            "type":"Services"
        }
    ],
    "sg:postcode":"BH22 9TT",
    "sg:province":"Dorset",
    "sg:tags":[
        "architectural"
    ],
    "wof:name":"Perks,Alan,Associates",
    "wof:placetype":"venue"
},
  "geometry": {"coordinates":[-1.89504,50.808743],"type":"Point"}
}