{
  "type": "Feature",
  "properties": {
    "addr:full":"Unit 44 Downs Road, Willenhall Wednesbury West Midlands WV13 2PX",
    "addr:housenumber":"unit 44",
    "addr:postcode":"wv13 2px",
    "addr:street":"Downs Road",
    "iso:country":"GB",
    "sg:address":"Unit 44 Downs Road, Willenhall",
    "sg:city":"Wednesbury",
    "sg:classifiers":[
        {
            "category":"Utilities",
            "subcategory":"Natural Gas",
            "type":"Services"
        }
    ],
    "sg:phone":"+44 121 526 5311",
    "sg:postcode":"WV13 2PX",
    "sg:province":"West Midlands",
    "sg:tags":[
        "supplier",
        "industrial"
    ],
    "wof:name":"Daniel Pipework Services",
    "wof:placetype":"venue"
},
  "geometry": {"coordinates":[-2.042804,52.579632],"type":"Point"}
}