{
  "type": "Feature",
  "properties": {
    "iso:country":"GB",
    "sg:address":"25-32 Marshall Street",
    "sg:city":"London",
    "sg:classifiers":[
        {
            "category":"Communications",
            "subcategory":"Film & Video Production",
            "type":"Services"
        }
    ],
    "sg:phone":"+44 20 7306 5600",
    "sg:postcode":"W1F 7ES",
    "sg:province":"Greater London",
    "sg:tags":[
        "recording",
        "studio"
    ],
    "wof:name":"Grand Central Sound Studios Ltd.",
    "wof:placetype":"venue"
},
  "geometry": {"coordinates":[-0.13842,51.513851],"type":"Point"}
}