{
  "type": "Feature",
  "properties": {
    "iso:country":"GB",
    "sg:address":"26 Homledale Road",
    "sg:city":"Exeter",
    "sg:classifiers":[
        {
            "category":"Building & Trades",
            "subcategory":"Plumbing",
            "type":"Services"
        }
    ],
    "sg:phone":"+44 1392 209827",
    "sg:postcode":"EX1 3DW",
    "sg:province":"Devon",
    "sg:tags":[
        "heating"
    ],
    "wof:name":"A W Fisher Plumbing",
    "wof:placetype":"venue"
},
  "geometry": {"coordinates":[-3.461769,50.747173],"type":"Point"}
}