{
  "type": "Feature",
  "properties": {
    "addr:full":"544 Blackpool Road, Ashton Preston Lancashire PR2 1HY",
    "addr:housenumber":"544",
    "addr:postcode":"pr2 1hy",
    "addr:street":"Blackpool Road",
    "iso:country":"GB",
    "sg:address":"544 Blackpool Road, Ashton",
    "sg:city":"Preston",
    "sg:classifiers":[
        {
            "category":"Health Services",
            "subcategory":"Health Practitioner",
            "type":"Services"
        }
    ],
    "sg:phone":"+44 1772 728798",
    "sg:postcode":"PR2 1HY",
    "sg:province":"Lancashire",
    "sg:tags":[
        "hypnotherapists"
    ],
    "wof:name":"J S & J M Gibson",
    "wof:placetype":"venue"
},
  "geometry": {"coordinates":[-2.7382059097,53.7691078186],"type":"Point"}
}