{
  "type": "Feature",
  "properties": {
    "iso:country":"GB",
    "sg:address":"105 High Street",
    "sg:city":"Stourbridge",
    "sg:classifiers":[
        {
            "category":"Cafe",
            "type":"Food & Drink"
        }
    ],
    "sg:phone":"+44 1384 441552",
    "sg:postcode":"DY8 1EE",
    "sg:province":"Staffordshire",
    "sg:tags":[
        "tea",
        "room"
    ],
    "wof:name":"The Well Trust",
    "wof:placetype":"venue"
},
  "geometry": {"coordinates":[-2.145678,52.456699],"type":"Point"}
}