{
  "type": "Feature",
  "properties": {
    "addr:full":"23 Redden Court Road, Harold Wood Romford Essex RM3 0UR",
    "addr:housenumber":"23",
    "addr:postcode":"rm3 0ur",
    "addr:street":"Redden Court Road",
    "iso:country":"GB",
    "sg:address":"23 Redden Court Road, Harold Wood",
    "sg:city":"Romford",
    "sg:classifiers":[
        {
            "category":"Professional",
            "subcategory":"Accounting & Tax Preparation",
            "type":"Services"
        }
    ],
    "sg:phone":"+44 1708 377999",
    "sg:postcode":"RM3 0UR",
    "sg:province":"Essex",
    "sg:tags":[
        "accountant"
    ],
    "wof:name":"C M Greene",
    "wof:placetype":"venue"
},
  "geometry": {"coordinates":[0.2279909998,51.5867843628],"type":"Point"}
}