{
  "type": "Feature",
  "properties": {
    "addr:full":"Gorse Covert Centre, Thorpe Acre Melton Mowbray Leicestershire LE11 1AJ",
    "addr:postcode":"le11 1aj",
    "addr:street":"Thorpe Acre",
    "iso:country":"GB",
    "sg:address":"Gorse Covert Centre, Thorpe Acre",
    "sg:city":"Melton Mowbray",
    "sg:classifiers":[
        {
            "category":"Food & Beverages",
            "subcategory":"Supermarket",
            "type":"Retail Goods"
        }
    ],
    "sg:phone":"+44 1509 843618",
    "sg:postcode":"LE11 1AJ",
    "sg:province":"Leicestershire",
    "wof:name":"Safeway Stores Ltd.",
    "wof:placetype":"venue"
},
  "geometry": {"coordinates":[-1.20103,52.773869],"type":"Point"}
}