{
  "type": "Feature",
  "properties": {
    "iso:country":"GB",
    "sg:address":"Cranfield Road",
    "sg:city":"Camborne",
    "sg:classifiers":[
        {
            "category":"Education",
            "subcategory":"School",
            "type":"Public Place"
        }
    ],
    "sg:phone":"+44 1209 713436",
    "sg:postcode":"TR14 7PN",
    "sg:province":"Cornwall",
    "sg:tags":[
        "local",
        "authority"
    ],
    "wof:name":"St Meriadoc C of E Junior School",
    "wof:placetype":"venue"
},
  "geometry": {"coordinates":[-5.309534,50.213085],"type":"Point"}
}