{
  "type": "Feature",
  "properties": {
    "addr:full":"442 Kingstanding Road Birmingham West Midlands B44 9SA",
    "addr:housenumber":"442",
    "addr:postcode":"b44 9sa",
    "addr:street":"Kingstanding Road",
    "iso:country":"GB",
    "sg:address":"442 Kingstanding Road",
    "sg:city":"Birmingham",
    "sg:classifiers":[
        {
            "category":"Professional",
            "subcategory":"Business Services",
            "type":"Services"
        },
        {
            "category":"Casinos & Gambling",
            "type":"Entertainment"
        }
    ],
    "sg:phone":"+44 870 518 1715",
    "sg:postcode":"B44 9SA",
    "sg:province":"West Midlands",
    "sg:tags":[
        "turf",
        "accountant",
        "bookmaker"
    ],
    "wof:name":"William Hill plc",
    "wof:placetype":"venue"
},
  "geometry": {"coordinates":[-1.8857710361,52.5424385071],"type":"Point"}
}