{
  "type": "Feature",
  "properties": {
    "iso:country":"GB",
    "sg:address":"1 Bernard Street",
    "sg:city":"Edinburgh",
    "sg:classifiers":[
        {
            "category":"Fast Food",
            "type":"Food & Drink"
        }
    ],
    "sg:phone":"+44 131 554 3628",
    "sg:postcode":"EH6 6PW",
    "sg:province":"City of Edinburgh",
    "sg:tags":[
        "away",
        "meal",
        "outlet",
        "take"
    ],
    "wof:name":"SAUCEBOAT",
    "wof:placetype":"venue"
},
  "geometry": {"coordinates":[-3.166963,55.975189],"type":"Point"}
}