{
  "type": "Feature",
  "properties": {
    "iso:country":"GB",
    "sg:address":"44-44 Bedwlwyn Road, Duffryn Industrial Estate, Ystrad Mynach",
    "sg:city":"Hengoed",
    "sg:classifiers":[
        {
            "category":"Personal",
            "type":"Services"
        }
    ],
    "sg:phone":"+44 1443 812212",
    "sg:postcode":"CF82 7YY",
    "sg:province":"Caerphilly",
    "sg:tags":[
        "delivery"
    ],
    "wof:name":"Royal Mail Letters",
    "wof:placetype":"venue"
},
  "geometry": {"coordinates":[-3.2346489429,51.6425933838],"type":"Point"}
}