{
  "type": "Feature",
  "properties": {
    "addr:full":"43 Booths Lane, Great Barr Birmingham West Midlands B42 2RG",
    "addr:housenumber":"43",
    "addr:postcode":"b42 2rg",
    "addr:street":"Booths Lane",
    "iso:country":"GB",
    "sg:address":"43 Booths Lane, Great Barr",
    "sg:city":"Birmingham",
    "sg:classifiers":[
        {
            "category":"Home & Garden",
            "subcategory":"Household Appliances",
            "type":"Retail Goods"
        },
        {
            "category":"Retail",
            "subcategory":"Repair Shop",
            "type":"Services"
        }
    ],
    "sg:phone":"+44 121 366 6988",
    "sg:postcode":"B42 2RG",
    "sg:province":"West Midlands",
    "sg:tags":[
        "electrical"
    ],
    "wof:name":"Birmingham Electrical Co Bull Ring",
    "wof:placetype":"venue"
},
  "geometry": {"coordinates":[-1.917452,52.546646],"type":"Point"}
}