{
  "type": "Feature",
  "properties": {
    "iso:country":"GB",
    "sg:address":"Field Mills Red Doles Lane, Leeds Road",
    "sg:city":"Huddersfield",
    "sg:classifiers":[
        {
            "category":"Manufacturing",
            "subcategory":"Metals",
            "type":"Manufacturing & Wholesale Goods"
        }
    ],
    "sg:postcode":"HD2 1YG",
    "sg:province":"West Yorkshire",
    "sg:tags":[
        "anodisers",
        "mnfrs"
    ],
    "wof:name":"Heywood Metal Finishers Ltd.",
    "wof:placetype":"venue"
},
  "geometry": {"coordinates":[-1.76782,53.660721],"type":"Point"}
}