{
  "type": "Feature",
  "properties": {
    "iso:country":"GB",
    "sg:address":"1 Hyndley Close",
    "sg:city":"Stoke-on-trent",
    "sg:classifiers":[
        {
            "category":"Building & Trades",
            "subcategory":"Construction",
            "type":"Services"
        }
    ],
    "sg:phone":"+44 1782 261757",
    "sg:postcode":"ST2 9JD",
    "sg:province":"Staffordshire",
    "sg:tags":[
        "decorator",
        "painter"
    ],
    "wof:name":"R Godwin",
    "wof:placetype":"venue"
},
  "geometry": {"coordinates":[-2.145909071,53.0213394165],"type":"Point"}
}