{
  "type": "Feature",
  "properties": {
    "addr:full":"198 Boston Rd Hanwell Greater London W7 2AD",
    "addr:housenumber":"198",
    "addr:postcode":"w7 2ad",
    "addr:street":"Boston Rd",
    "iso:country":"GB",
    "sg:address":"198 Boston Rd",
    "sg:city":"Hanwell",
    "sg:classifiers":[
        {
            "category":"Professional",
            "subcategory":"Accounting & Tax Preparation",
            "type":"Services"
        }
    ],
    "sg:phone":"+44 20 8579 6499",
    "sg:postcode":"W7 2AD",
    "sg:province":"Greater London",
    "sg:tags":[
        "accountant"
    ],
    "wof:name":"Murugesu & Associates",
    "wof:placetype":"venue"
},
  "geometry": {"coordinates":[-0.3294480145,51.5007591248],"type":"Point"}
}