{
  "type": "Feature",
  "properties": {
    "addr:full":"65 Burntscarth Grn, Locharbriggs Dumfries Dumfries and Galloway DG1 1UL",
    "addr:housenumber":"65",
    "addr:postcode":"dg1 1ul",
    "addr:street":"Burntscarth Grn Locharbriggs",
    "iso:country":"GB",
    "sg:address":"65 Burntscarth Grn, Locharbriggs",
    "sg:city":"Dumfries",
    "sg:classifiers":[
        {
            "category":"Taxi",
            "type":"Transportation"
        },
        {
            "category":"Military Area",
            "subcategory":"Air Force Base",
            "type":"Public Place"
        }
    ],
    "sg:phone":"+44 1387 710007",
    "sg:postcode":"DG1 1UL",
    "sg:province":"Dumfries and Galloway",
    "sg:tags":[
        "hire",
        "private"
    ],
    "wof:name":"A To B Taxis",
    "wof:placetype":"venue"
},
  "geometry": {"coordinates":[-3.5837199688,55.1069297791],"type":"Point"}
}