{
  "type": "Feature",
  "properties": {
    "addr:full":"7th Floor, Berkeley Square London W1J 6DA",
    "addr:housenumber":"7th floor",
    "addr:postcode":"w1j 6da",
    "addr:street":"Berkeley Square",
    "iso:country":"GB",
    "sg:address":"7th Floor, Berkeley Square",
    "sg:city":"London",
    "sg:classifiers":[
        {
            "category":"Professional",
            "subcategory":"Computer Services",
            "type":"Services"
        }
    ],
    "sg:postcode":"W1J 6DA",
    "sg:website":"http://www.arcelormittal.com",
    "wof:name":"ArcelorMittal",
    "wof:placetype":"venue"
},
  "geometry": {"coordinates":[-0.146588,51.5096437],"type":"Point"}
}