{
  "type": "Feature",
  "properties": {
    "addr:full":"Shardeloes, Missenden Road Amersham Buckinghamshire HP7 0RL",
    "addr:postcode":"hp7 0rl",
    "addr:street":"Missenden Road",
    "iso:country":"GB",
    "sg:address":"Shardeloes, Missenden Road",
    "sg:city":"Amersham",
    "sg:classifiers":[
        {
            "category":"Arena",
            "subcategory":"Sports Club",
            "type":"Entertainment"
        }
    ],
    "sg:phone":"+44 1494 433020",
    "sg:postcode":"HP7 0RL",
    "sg:province":"Buckinghamshire",
    "wof:name":"Amersham Cricket Club",
    "wof:placetype":"venue"
},
  "geometry": {"coordinates":[-0.624468,51.66827],"type":"Point"}
}