{
  "type": "Feature",
  "properties": {
    "iso:country":"GB",
    "sg:address":"South Trefula, St Day",
    "sg:city":"Redruth",
    "sg:classifiers":[
        {
            "category":"Home & Garden",
            "subcategory":"Home Furnishings",
            "type":"Retail Goods"
        }
    ],
    "sg:phone":"+44 1209 213129",
    "sg:postcode":"TR16 5ER",
    "sg:province":"Cornwall",
    "sg:tags":[
        "furnishers",
        "planner",
        "kitchen"
    ],
    "wof:name":"Complete Kitchen Choice",
    "wof:placetype":"venue"
},
  "geometry": {"coordinates":[-5.199494,50.238186],"type":"Point"}
}