{
  "type": "Feature",
  "properties": {
    "addr:full":"36 Coach Road, Alresford Colchester Essex CO7 8EB",
    "addr:housenumber":"36",
    "addr:postcode":"co7 8eb",
    "addr:street":"Coach Road",
    "iso:country":"GB",
    "sg:address":"36 Coach Road, Alresford",
    "sg:city":"Colchester",
    "sg:classifiers":[
        {
            "category":"Professional",
            "subcategory":"Business Services",
            "type":"Services"
        }
    ],
    "sg:phone":"+44 1206 822168",
    "sg:postcode":"CO7 8EB",
    "sg:province":"Essex",
    "sg:tags":[
        "agent",
        "manufacturers'"
    ],
    "wof:name":"Ernie Osborne Motor Trade",
    "wof:placetype":"venue"
},
  "geometry": {"coordinates":[1.0032910109,51.8551635742],"type":"Point"}
}