{
  "type": "Feature",
  "properties": {
    "addr:full":"34/40 High St, Wanstead London Greater London E11 2RJ",
    "addr:housenumber":"34 / 40",
    "addr:postcode":"e11 2rj",
    "addr:street":"High St",
    "iso:country":"GB",
    "sg:address":"34/40 High St, Wanstead",
    "sg:city":"London",
    "sg:classifiers":[
        {
            "category":"Real Estate",
            "subcategory":"Developer",
            "type":"Services"
        }
    ],
    "sg:postcode":"E11 2RJ",
    "sg:province":"Greater London",
    "sg:tags":[
        "property"
    ],
    "wof:name":"Kingswater (Lincoln) Ltd",
    "wof:placetype":"venue"
},
  "geometry": {"coordinates":[0.0273000002,51.5760993958],"type":"Point"}
}