{
  "type": "Feature",
  "properties": {
    "iso:country":"GB",
    "sg:address":"Unit 4-5 Fairview Industrial Estate",
    "sg:city":"Ashford",
    "sg:classifiers":[
        {
            "category":"Home & Garden",
            "subcategory":"Building Materials",
            "type":"Retail Goods"
        }
    ],
    "sg:phone":"+44 1233 733821",
    "sg:postcode":"TN26 2NR",
    "sg:province":"Kent",
    "sg:tags":[
        "ventilator",
        "ventilation",
        "system"
    ],
    "wof:name":"Fume Cupboard Design",
    "wof:placetype":"venue"
},
  "geometry": {"coordinates":[0.8734499812,51.0631713867],"type":"Point"}
}