{
  "type": "Feature",
  "properties": {
    "iso:country":"GB",
    "sg:address":"49 Market Place",
    "sg:city":"Thirsk",
    "sg:classifiers":[
        {
            "category":"Shopping",
            "subcategory":"Bicycles & Sporting Goods",
            "type":"Retail Goods"
        }
    ],
    "sg:phone":"+44 1845 522048",
    "sg:postcode":"YO7 1HA",
    "sg:province":"North Yorkshire",
    "sg:tags":[
        "riding",
        "saddlery",
        "wear"
    ],
    "wof:name":"W W & Sons Scott",
    "wof:placetype":"venue"
},
  "geometry": {"coordinates":[-1.3431110382,54.2328453064],"type":"Point"}
}