{
  "type": "Feature",
  "properties": {
    "iso:country":"GB",
    "sg:address":"Waterbarn Mill, Stacksteads",
    "sg:city":"Bacup",
    "sg:classifiers":[
        {
            "category":"Manufacturing",
            "subcategory":"Rubber & Plastics",
            "type":"Manufacturing & Wholesale Goods"
        }
    ],
    "sg:phone":"+44 1706 874135",
    "sg:postcode":"OL13 0NH",
    "sg:province":"Lancashire",
    "sg:tags":[
        "supplier",
        "stockist"
    ],
    "wof:name":"H R Plastics Ltd.",
    "wof:placetype":"venue"
},
  "geometry": {"coordinates":[-2.231204,53.69183],"type":"Point"}
}