{
  "type": "Feature",
  "properties": {
    "iso:country":"GB",
    "sg:address":"68 Herbertson Crescent",
    "sg:city":"Irvine",
    "sg:classifiers":[
        {
            "category":"Taxi",
            "type":"Transportation"
        }
    ],
    "sg:postcode":"KA12 0QN",
    "sg:province":"North Ayrshire",
    "sg:tags":[
        "mini",
        "cab"
    ],
    "wof:name":"Ace Cabs",
    "wof:placetype":"venue"
},
  "geometry": {"coordinates":[-4.657411,55.621895],"type":"Point"}
}