{
  "type": "Feature",
  "properties": {
    "iso:country":"GB",
    "sg:address":"3 Southernhay West",
    "sg:city":"Exeter",
    "sg:classifiers":[
        {
            "category":"Building & Trades",
            "subcategory":"Construction",
            "type":"Services"
        }
    ],
    "sg:phone":"+44 1392 823833",
    "sg:postcode":"EX1 1JG",
    "sg:province":"Devon",
    "sg:tags":[
        "builder"
    ],
    "wof:name":"White,L A,& Son Ltd",
    "wof:placetype":"venue"
},
  "geometry": {"coordinates":[-3.527716,50.721706],"type":"Point"}
}