{
  "type": "Feature",
  "properties": {
    "iso:country":"GB",
    "sg:address":"21 Hainton Avenue",
    "sg:city":"Grimsby",
    "sg:classifiers":[
        {
            "category":"Insurance",
            "subcategory":"Insurance Agent",
            "type":"Services"
        }
    ],
    "sg:postcode":"DN32 9BB",
    "sg:province":"Lincolnshire",
    "wof:name":"Swinton",
    "wof:placetype":"venue"
},
  "geometry": {"coordinates":[-0.074802,53.566242],"type":"Point"}
}