{
  "type": "Feature",
  "properties": {
    "iso:country":"GB",
    "sg:address":"New Road",
    "sg:city":"Dagenham",
    "sg:classifiers":[
        {
            "category":"Autos & Motor Vehicles",
            "subcategory":"Automobile Sales",
            "type":"Retail Goods"
        },
        {
            "category":"Autos & Motor Vehicles",
            "subcategory":"Recreational Vehicle Sales",
            "type":"Retail Goods"
        }
    ],
    "sg:phone":"+44 20 8526 3066",
    "sg:postcode":"RM9 6EX",
    "sg:province":"Essex",
    "sg:tags":[
        "car",
        "used",
        "new"
    ],
    "sg:website":"http://www.dagenhammotors.co.uk",
    "wof:name":"Dagenham Motors Group Ltd.",
    "wof:placetype":"venue"
},
  "geometry": {"coordinates":[0.1482319981,51.5316390991],"type":"Point"}
}