{
  "type": "Feature",
  "properties": {
    "addr:full":"92 Powis Street, Woolwich London Greater London SE18 6JB",
    "addr:housenumber":"92",
    "addr:postcode":"se18 6jb",
    "addr:street":"Powis Street",
    "iso:country":"GB",
    "sg:address":"92 Powis Street, Woolwich",
    "sg:city":"London",
    "sg:classifiers":[
        {
            "category":"Shopping",
            "subcategory":"Gifts & Souvenirs",
            "type":"Retail Goods"
        }
    ],
    "sg:phone":"+44 20 8316 7239",
    "sg:postcode":"SE18 6JB",
    "sg:province":"Greater London",
    "sg:tags":[
        "poster",
        "card"
    ],
    "wof:name":"Clinton Cards Plc",
    "wof:placetype":"venue"
},
  "geometry": {"coordinates":[0.061705,51.492859],"type":"Point"}
}