{
  "type": "Feature",
  "properties": {
    "addr:full":"Unit 26a, Sunbeam Street Wolverhampton West Midlands WV2 4PF",
    "addr:housenumber":"unit 26a",
    "addr:postcode":"wv2 4pf",
    "addr:street":"Sunbeam Street",
    "iso:country":"GB",
    "sg:address":"Unit 26a, Sunbeam Street",
    "sg:city":"Wolverhampton",
    "sg:classifiers":[
        {
            "category":"Building & Trades",
            "subcategory":"Construction",
            "type":"Services"
        }
    ],
    "sg:postcode":"WV2 4PF",
    "sg:province":"West Midlands",
    "sg:tags":[
        "valve"
    ],
    "wof:name":"B & G Valves & Engineering Services",
    "wof:placetype":"venue"
},
  "geometry": {"coordinates":[-2.1314089298,52.5726509094],"type":"Point"}
}