{
  "type": "Feature",
  "properties": {
    "iso:country":"GB",
    "sg:address":"Clark Brownscombe, 8 The Drive",
    "sg:city":"Hove",
    "sg:classifiers":[
        {
            "category":"Professional",
            "subcategory":"Computer Services",
            "type":"Services"
        }
    ],
    "sg:postcode":"BN3 3JT",
    "sg:province":"East Sussex",
    "sg:tags":[
        "system",
        "software"
    ],
    "wof:name":"Brownhurst Ltd",
    "wof:placetype":"venue"
},
  "geometry": {"coordinates":[-0.1824489981,50.8389434814],"type":"Point"}
}