{
  "type": "Feature",
  "properties": {
    "iso:country":"GB",
    "sg:address":"Prebendal Farm, Grove Road, Slip End",
    "sg:city":"Luton",
    "sg:classifiers":[
        {
            "category":"Shopping",
            "subcategory":"Pets & Pet Supplies",
            "type":"Retail Goods"
        }
    ],
    "sg:phone":"+44 1582 725381",
    "sg:postcode":"LU1 4DF",
    "sg:province":"Bedfordshire",
    "sg:tags":[
        "shop"
    ],
    "wof:name":"Browns Pet Supplies",
    "wof:placetype":"venue"
},
  "geometry": {"coordinates":[-0.434341,51.854115],"type":"Point"}
}