{
  "type": "Feature",
  "properties": {
    "iso:country":"GB",
    "sg:address":"1 Finkle Street",
    "sg:city":"Selby",
    "sg:classifiers":[
        {
            "category":"Real Estate",
            "subcategory":"Real Estate Agent",
            "type":"Services"
        }
    ],
    "sg:phone":"+44 1757 213733",
    "sg:postcode":"YO8 4DT",
    "sg:province":"East Riding of Yorkshire",
    "wof:name":"Reeds Rains",
    "wof:placetype":"venue"
},
  "geometry": {"coordinates":[-1.0694090128,53.7841758728],"type":"Point"}
}