{
  "type": "Feature",
  "properties": {
    "addr:full":"73 Causeyside Street Paisley Renfrewshire PA1 1YT",
    "addr:housenumber":"73",
    "addr:postcode":"pa1 1yt",
    "addr:street":"Causeyside Street",
    "iso:country":"GB",
    "sg:address":"73 Causeyside Street",
    "sg:city":"Paisley",
    "sg:classifiers":[
        {
            "category":"Personal",
            "subcategory":"Beauty Salon",
            "type":"Services"
        }
    ],
    "sg:phone":"+44 141 889 2683",
    "sg:postcode":"PA1 1YT",
    "sg:province":"Renfrewshire",
    "sg:tags":[
        "ladies",
        "lady",
        "hairdresser"
    ],
    "wof:name":"Hairline",
    "wof:placetype":"venue"
},
  "geometry": {"coordinates":[-4.424154,55.84082],"type":"Point"}
}