{
  "type": "Feature",
  "properties": {
    "addr:full":"5 Shoplands Welwyn Garden City Hertfordshire AL8 7RH",
    "addr:housenumber":"5",
    "addr:postcode":"al8 7rh",
    "addr:street":"Shoplands Welwyn",
    "iso:country":"GB",
    "sg:address":"5 Shoplands",
    "sg:city":"Welwyn Garden City",
    "sg:classifiers":[
        {
            "category":"Food & Beverages",
            "subcategory":"Fruits & Vegetables",
            "type":"Retail Goods"
        }
    ],
    "sg:postcode":"AL8 7RH",
    "sg:province":"Hertfordshire",
    "sg:tags":[
        "greengrocer"
    ],
    "wof:name":"Tony Bond Greengrocer",
    "wof:placetype":"venue"
},
  "geometry": {"coordinates":[-0.202926,51.815525],"type":"Point"}
}