{
  "type": "Feature",
  "properties": {
    "addr:full":"32 Charnwood Road, Shepshed Loughborough Leicestershire LE12 9QF",
    "addr:housenumber":"32",
    "addr:postcode":"le12 9qf",
    "addr:street":"Charnwood Road",
    "iso:country":"GB",
    "sg:address":"32 Charnwood Road, Shepshed",
    "sg:city":"Loughborough",
    "sg:classifiers":[
        {
            "category":"Building & Trades",
            "subcategory":"Construction",
            "type":"Services"
        }
    ],
    "sg:phone":"+44 1509 600540",
    "sg:postcode":"LE12 9QF",
    "sg:province":"Leicestershire",
    "sg:tags":[
        "joinery"
    ],
    "wof:name":"Woodteam Ltd.",
    "wof:placetype":"venue"
},
  "geometry": {"coordinates":[-1.2913719416,52.7706222534],"type":"Point"}
}