{
  "type": "Feature",
  "properties": {
    "addr:full":"16 Teesdale, East Kilbride Glasgow South Lanarkshire G74 4NN",
    "addr:housenumber":"16;east",
    "addr:postcode":"g74 4nn",
    "addr:street":"Teesdale",
    "iso:country":"GB",
    "sg:address":"16 Teesdale, East Kilbride",
    "sg:city":"Glasgow",
    "sg:classifiers":[
        {
            "category":"Professional",
            "subcategory":"Art Services",
            "type":"Services"
        }
    ],
    "sg:postcode":"G74 4NN",
    "sg:province":"South Lanarkshire",
    "sg:tags":[
        "photographer"
    ],
    "wof:name":"Millar Photography",
    "wof:placetype":"venue"
},
  "geometry": {"coordinates":[-4.194077,55.769165],"type":"Point"}
}