{
  "type": "Feature",
  "properties": {
    "addr:full":"Ascham St Kentish Town Greater London NW5 2PD",
    "addr:postcode":"nw5 2pd",
    "addr:street":"Ascham St",
    "iso:country":"GB",
    "sg:address":"Ascham St",
    "sg:city":"Kentish Town",
    "sg:classifiers":[
        {
            "category":"Health Services",
            "subcategory":"Nursing And Care Facility",
            "type":"Services"
        }
    ],
    "sg:phone":"+44 20 7419 7474",
    "sg:postcode":"NW5 2PD",
    "sg:province":"Greater London",
    "sg:tags":[
        "home"
    ],
    "wof:name":"Ash Court Nursing Home",
    "wof:placetype":"venue"
},
  "geometry": {"coordinates":[-0.139339,51.5555648804],"type":"Point"}
}