{
  "type": "Feature",
  "properties": {
    "addr:full":"Sunnyview, Crown Hill, Llantwit Fardre Pontypridd Rhondda, Cynon, Taff CF38 2NA",
    "addr:postcode":"cf38 2na",
    "addr:street":"Llantwit Fardre",
    "iso:country":"GB",
    "sg:address":"Sunnyview, Crown Hill, Llantwit Fardre",
    "sg:city":"Pontypridd",
    "sg:classifiers":[
        {
            "category":"Professional",
            "subcategory":"Art Services",
            "type":"Services"
        },
        {
            "category":"Building & Trades",
            "subcategory":"Construction",
            "type":"Services"
        }
    ],
    "sg:phone":"+44 1443 208592",
    "sg:postcode":"CF38 2NA",
    "sg:province":"Rhondda, Cynon, Taff",
    "sg:tags":[
        "decorator",
        "painter"
    ],
    "wof:name":"G & L R Decorators",
    "wof:placetype":"venue"
},
  "geometry": {"coordinates":[-3.3345069885,51.557800293],"type":"Point"}
}