{
  "type": "Feature",
  "properties": {
    "iso:country":"GB",
    "sg:address":"Old London Rd",
    "sg:city":"Hastings",
    "sg:classifiers":[
        {
            "category":"Place Of Worship",
            "type":"Public Place"
        }
    ],
    "sg:phone":"+44 1424 424520",
    "sg:postcode":"TN35 5LU",
    "sg:province":"East Sussex",
    "wof:name":"Halton Baptist Church",
    "wof:placetype":"venue"
},
  "geometry": {"coordinates":[0.6072030067,50.8746147156],"type":"Point"}
}