{
  "type": "Feature",
  "properties": {
    "addr:full":"Security Buildings Storforth Lane Chesterfield Derbyshire S40 2TU",
    "addr:postcode":"s40 2tu",
    "addr:street":"Storforth Lane",
    "iso:country":"GB",
    "sg:address":"Security Buildings Storforth Lane",
    "sg:city":"Chesterfield",
    "sg:classifiers":[
        {
            "category":"Professional",
            "subcategory":"Engineering",
            "type":"Services"
        },
        {
            "category":"Professional",
            "subcategory":"Detective & Security Services",
            "type":"Services"
        }
    ],
    "sg:phone":"+44 1246 556400",
    "sg:postcode":"S40 2TU",
    "sg:province":"Derbyshire",
    "sg:tags":[
        "burglar",
        "alarm",
        "system",
        "contractor",
        "electrical",
        "engineer"
    ],
    "wof:name":"B Safe Security Systems Ltd.",
    "wof:placetype":"venue"
},
  "geometry": {"coordinates":[-1.42335,53.220402],"type":"Point"}
}