{
  "type": "Feature",
  "properties": {
    "addr:full":"2a Gareth Grove Bromley Kent BR1 5EQ",
    "addr:housenumber":"2a",
    "addr:postcode":"br1 5eq",
    "addr:street":"Gareth Grove",
    "iso:country":"GB",
    "sg:address":"2a Gareth Grove",
    "sg:city":"Bromley",
    "sg:classifiers":[
        {
            "category":"Food & Beverages",
            "subcategory":"Specialty",
            "type":"Retail Goods"
        }
    ],
    "sg:phone":"+44 20 8516 5384",
    "sg:postcode":"BR1 5EQ",
    "sg:province":"Kent",
    "sg:tags":[
        "dietetic",
        "homogenised"
    ],
    "wof:name":"Herbalife International",
    "wof:placetype":"venue"
},
  "geometry": {"coordinates":[0.018101,51.429249],"type":"Point"}
}