{
  "type": "Feature",
  "properties": {
    "iso:country":"GB",
    "sg:address":"8 Airedale Drive",
    "sg:city":"Bridlington",
    "sg:classifiers":[
        {
            "category":"Autos & Motor Vehicles",
            "subcategory":"Auto Supplies",
            "type":"Retail Goods"
        }
    ],
    "sg:phone":"+44 1262 604858",
    "sg:postcode":"YO16 5GL",
    "sg:province":"East Riding of Yorkshire",
    "sg:tags":[
        "towbars"
    ],
    "wof:name":"Wold Towbar Supplies Ltd.",
    "wof:placetype":"venue"
},
  "geometry": {"coordinates":[-0.23709,54.104671],"type":"Point"}
}