{
  "type": "Feature",
  "properties": {
    "iso:country":"GB",
    "sg:address":"Bailiffs Court, Kildwick",
    "sg:city":"Keighley",
    "sg:classifiers":[
        {
            "category":"Professional",
            "type":"Services"
        }
    ],
    "sg:phone":"+44 1535 631800",
    "sg:postcode":"BD20 9AD",
    "sg:province":"North Yorkshire",
    "sg:tags":[
        "interior",
        "furnishers",
        "designer"
    ],
    "wof:name":"Optima Interiors",
    "wof:placetype":"venue"
},
  "geometry": {"coordinates":[-1.984548,53.908337],"type":"Point"}
}