{
  "type": "Feature",
  "properties": {
    "addr:full":"64 Bexleigh Avenue St Leonards-on-sea East Sussex TN38 8BB",
    "addr:housenumber":"64",
    "addr:postcode":"tn38 8bb",
    "addr:street":"Bexleigh Avenue St",
    "iso:country":"GB",
    "sg:address":"64 Bexleigh Avenue",
    "sg:city":"St Leonards-on-sea",
    "sg:classifiers":[
        {
            "category":"Building & Trades",
            "subcategory":"Cleaning & Sanitation",
            "type":"Services"
        }
    ],
    "sg:phone":"+44 1424 436865",
    "sg:postcode":"TN38 8BB",
    "sg:province":"East Sussex",
    "sg:tags":[
        "commercial"
    ],
    "wof:name":"Complete Cleaning Services",
    "wof:placetype":"venue"
},
  "geometry": {"coordinates":[0.5094050169,50.8465499878],"type":"Point"}
}