{
  "type": "Feature",
  "properties": {
    "addr:full":"52-64 Heath Road Twickenham Greater London TW1 4BX",
    "addr:housenumber":"52-64",
    "addr:postcode":"tw1 4bx",
    "addr:street":"Heath Road",
    "iso:country":"GB",
    "sg:address":"52-64 Heath Road",
    "sg:city":"Twickenham",
    "sg:classifiers":[
        {
            "category":"Professional",
            "subcategory":"Advertising",
            "type":"Services"
        }
    ],
    "sg:phone":"+44 20 8891 4388",
    "sg:postcode":"TW1 4BX",
    "sg:province":"Greater London",
    "sg:tags":[
        "agency"
    ],
    "wof:name":"Roper Stammers Ltd.",
    "wof:placetype":"venue"
},
  "geometry": {"coordinates":[-0.332321,51.445358],"type":"Point"}
}