{
  "type": "Feature",
  "properties": {
    "iso:country":"GB",
    "sg:address":"Unit9, Rougham Industrial Estate, Rougham",
    "sg:city":"Bury St Edmunds",
    "sg:classifiers":[
        {
            "category":"Professional",
            "subcategory":"Printing & Photocopies",
            "type":"Services"
        }
    ],
    "sg:phone":"+44 1359 271259",
    "sg:postcode":"IP30 9ND",
    "sg:province":"Suffolk",
    "sg:tags":[
        "print",
        "finisher"
    ],
    "wof:name":"Folding Services Ltd",
    "wof:placetype":"venue"
},
  "geometry": {"coordinates":[0.798714,52.222191],"type":"Point"}
}