{
  "type": "Feature",
  "properties": {
    "addr:full":"Kingsbury Green London Greater London NW9 8XR",
    "addr:postcode":"nw9 8xr",
    "iso:country":"GB",
    "sg:address":"Kingsbury Green",
    "sg:city":"London",
    "sg:classifiers":[
        {
            "category":"Place Of Worship",
            "type":"Public Place"
        }
    ],
    "sg:phone":"+44 20 8204 8089",
    "sg:postcode":"NW9 8XR",
    "sg:province":"Greater London",
    "wof:name":"Kingsbury Synagogue",
    "wof:placetype":"venue"
},
  "geometry": {"coordinates":[-0.26373,51.582581],"type":"Point"}
}