{
  "type": "Feature",
  "properties": {
    "addr:full":"Geest House, Hadleigh Rd Ipswich Suffolk IP2 0DH",
    "addr:postcode":"ip2 0dh",
    "addr:street":"Hadleigh Rd",
    "iso:country":"GB",
    "sg:address":"Geest House, Hadleigh Rd",
    "sg:city":"Ipswich",
    "sg:classifiers":[
        {
            "category":"Freight",
            "type":"Transportation"
        }
    ],
    "sg:phone":"+44 1473 230100",
    "sg:postcode":"IP2 0DH",
    "sg:province":"Suffolk",
    "sg:tags":[
        "overseas",
        "shipping",
        "removal"
    ],
    "wof:name":"Geest North Sea Line Bv",
    "wof:placetype":"venue"
},
  "geometry": {"coordinates":[1.1247860193,52.0581092834],"type":"Point"}
}