{
  "type": "Feature",
  "properties": {
    "iso:country":"GB",
    "sg:address":"Mawgan Porth",
    "sg:city":"Newquay",
    "sg:classifiers":[
        {
            "category":"Bars & Pubs",
            "type":"Food & Drink"
        }
    ],
    "sg:postcode":"TR8 4AL",
    "sg:province":"Cornwall",
    "sg:tags":[
        "pubs",
        "inn"
    ],
    "wof:name":"Edward Simpson",
    "wof:placetype":"venue"
},
  "geometry": {"coordinates":[-5.03102,50.461948],"type":"Point"}
}