{
  "type": "Feature",
  "properties": {
    "addr:full":"2 The Courtyards, Wyncolls Road, Severalls Industrial Park Colchester Essex CO4 9PE",
    "addr:housenumber":"2",
    "addr:postcode":"co4 9pe",
    "addr:street":"The;Wyncolls Road Severalls Industrial Park",
    "iso:country":"GB",
    "sg:address":"2 The Courtyards, Wyncolls Road, Severalls Industrial Park",
    "sg:city":"Colchester",
    "sg:classifiers":[
        {
            "category":"Shopping",
            "subcategory":"Computers & Home Electronics",
            "type":"Retail Goods"
        }
    ],
    "sg:phone":"+44 1206 224920",
    "sg:postcode":"CO4 9PE",
    "sg:province":"Essex",
    "wof:name":"Trust Technology Products Uk Ltd.",
    "wof:placetype":"venue"
},
  "geometry": {"coordinates":[0.9254000187,51.9162216187],"type":"Point"}
}