{
  "type": "Feature",
  "properties": {
    "addr:full":"52-54 New Canal Salisbury Wiltshire SP1 2AQ",
    "addr:housenumber":"52-54",
    "addr:postcode":"sp1 2aq",
    "addr:street":"New Canal",
    "iso:country":"GB",
    "sg:address":"52-54 New Canal",
    "sg:city":"Salisbury",
    "sg:classifiers":[
        {
            "category":"Sports & Exercise",
            "subcategory":"Sports Center",
            "type":"Entertainment"
        }
    ],
    "sg:phone":"+44 1722 339907",
    "sg:postcode":"SP1 2AQ",
    "sg:province":"Wiltshire",
    "sg:tags":[
        "shop",
        "good"
    ],
    "wof:name":"Hargreaves (Sports) Ltd.",
    "wof:placetype":"venue"
},
  "geometry": {"coordinates":[-1.7963949442,51.0684165955],"type":"Point"}
}