{
  "type": "Feature",
  "properties": {
    "addr:full":"The Grn, Shenington Banbury Oxfordshire OX15 6NE",
    "addr:postcode":"ox15 6ne",
    "iso:country":"GB",
    "sg:address":"The Grn, Shenington",
    "sg:city":"Banbury",
    "sg:classifiers":[
        {
            "category":"Farming",
            "subcategory":"Farm",
            "type":"Manufacturing & Wholesale Goods"
        }
    ],
    "sg:phone":"+44 1295 680553",
    "sg:postcode":"OX15 6NE",
    "sg:province":"Oxfordshire",
    "sg:tags":[
        "mixed",
        "crop"
    ],
    "wof:name":"P P Gibbs",
    "wof:placetype":"venue"
},
  "geometry": {"coordinates":[-1.458724,52.082436],"type":"Point"}
}