{
  "type": "Feature",
  "properties": {
    "iso:country":"GB",
    "sg:address":"6 The Paddocks",
    "sg:city":"Rugby",
    "sg:classifiers":[
        {
            "category":"Food & Beverages",
            "subcategory":"Fruits & Vegetables",
            "type":"Retail Goods"
        }
    ],
    "sg:postcode":"CV23 9NW",
    "sg:province":"Northamptonshire",
    "sg:tags":[
        "greengrocer"
    ],
    "wof:name":"J G Simmonds",
    "wof:placetype":"venue"
},
  "geometry": {"coordinates":[-1.400497,52.348816],"type":"Point"}
}