{
  "type": "Feature",
  "properties": {
    "addr:full":"Little Powgavie, Inchture Perth Perth and Kinross PH14 9QP",
    "addr:postcode":"ph14 9qp",
    "addr:street":"Inchture",
    "iso:country":"GB",
    "sg:address":"Little Powgavie, Inchture",
    "sg:city":"Perth",
    "sg:classifiers":[
        {
            "category":"Real Estate",
            "subcategory":"Architect",
            "type":"Services"
        }
    ],
    "sg:postcode":"PH14 9QP",
    "sg:province":"Perth and Kinross",
    "wof:name":"Andrew D Brown",
    "wof:placetype":"venue"
},
  "geometry": {"coordinates":[-3.168468,56.446461],"type":"Point"}
}