{
  "type": "Feature",
  "properties": {
    "addr:full":"Constituency Of Ross, Skye And Inverness West, 1a Montague Row Inverness Highland IV3 5DX",
    "addr:housenumber":"1a",
    "addr:postcode":"iv3 5dx",
    "addr:street":"West;Montague Row",
    "iso:country":"GB",
    "sg:address":"Constituency Of Ross, Skye And Inverness West, 1a Montague Row",
    "sg:city":"Inverness",
    "sg:classifiers":[
        {
            "category":"Government",
            "subcategory":"Office",
            "type":"Public Place"
        }
    ],
    "sg:phone":"+44 1463 714377",
    "sg:postcode":"IV3 5DX",
    "sg:province":"Highland",
    "sg:tags":[
        "mp",
        "meps"
    ],
    "wof:name":"Charles Kennedy MP, Rt Hon (LDem)",
    "wof:placetype":"venue"
},
  "geometry": {"coordinates":[-4.2356119156,57.4790153503],"type":"Point"}
}