{
  "type": "Feature",
  "properties": {
    "iso:country":"GB",
    "sg:address":"City Service Centre, Terminus Road Industrial Estate",
    "sg:city":"Chichester",
    "sg:classifiers":[
        {
            "category":"Autos & Motor Vehicles",
            "subcategory":"Automobile Sales",
            "type":"Retail Goods"
        },
        {
            "category":"Retail",
            "subcategory":"Auto Repair",
            "type":"Services"
        }
    ],
    "sg:phone":"+44 1243 774321",
    "sg:postcode":"PO19 8TX",
    "sg:province":"West Sussex",
    "sg:tags":[
        "modification",
        "garage",
        "car"
    ],
    "wof:name":"City Service Centre",
    "wof:placetype":"venue"
},
  "geometry": {"coordinates":[-0.775429,50.836166],"type":"Point"}
}