{
  "type": "Feature",
  "properties": {
    "iso:country":"GB",
    "sg:address":"27a Banastre Rd",
    "sg:city":"Southport",
    "sg:classifiers":[
        {
            "category":"Professional",
            "type":"Services"
        }
    ],
    "sg:postcode":"PR8 5AW",
    "sg:province":"Lancashire",
    "sg:tags":[
        "interior",
        "furnishers",
        "designer"
    ],
    "wof:name":"Studio 3 (Contracts) Ltd",
    "wof:placetype":"venue"
},
  "geometry": {"coordinates":[-3.007818,53.637924],"type":"Point"}
}