{
  "type": "Feature",
  "properties": {
    "addr:full":"Mill Pond Farm, Ramsey Harwich Essex CO12 5LJ",
    "addr:postcode":"co12 5lj",
    "addr:street":"Pond",
    "iso:country":"GB",
    "sg:address":"Mill Pond Farm, Ramsey",
    "sg:city":"Harwich",
    "sg:classifiers":[
        {
            "category":"Farming",
            "subcategory":"Farm",
            "type":"Manufacturing & Wholesale Goods"
        }
    ],
    "sg:phone":"+44 1255 886096",
    "sg:postcode":"CO12 5LJ",
    "sg:province":"Essex",
    "sg:tags":[
        "mixed",
        "crop"
    ],
    "wof:name":"J Phelan",
    "wof:placetype":"venue"
},
  "geometry": {"coordinates":[1.217402,51.929771],"type":"Point"}
}