{
  "type": "Feature",
  "properties": {
    "iso:country":"GB",
    "sg:address":"Low Farm, Pinchinthorpe",
    "sg:city":"Guisborough",
    "sg:classifiers":[
        {
            "category":"Farming",
            "subcategory":"Livestock Farm",
            "type":"Manufacturing & Wholesale Goods"
        }
    ],
    "sg:phone":"+44 1287 632508",
    "sg:postcode":"TS14 8HQ",
    "sg:province":"North Yorkshire",
    "sg:tags":[
        "others"
    ],
    "wof:name":"C & R Thompson",
    "wof:placetype":"venue"
},
  "geometry": {"coordinates":[-1.072504,54.526161],"type":"Point"}
}