{
  "type": "Feature",
  "properties": {
    "addr:full":"228 Kimberworth Road Rotherham South Yorkshire S61 1HH",
    "addr:housenumber":"228",
    "addr:postcode":"s61 1hh",
    "addr:street":"Kimberworth Road",
    "iso:country":"GB",
    "sg:address":"228 Kimberworth Road",
    "sg:city":"Rotherham",
    "sg:classifiers":[
        {
            "category":"Home & Garden",
            "subcategory":"Home Furnishings",
            "type":"Retail Goods"
        }
    ],
    "sg:postcode":"S61 1HH",
    "sg:province":"South Yorkshire",
    "sg:tags":[
        "furnishers",
        "planner",
        "bedroom"
    ],
    "wof:name":"Kimberworth Discount Centre",
    "wof:placetype":"venue"
},
  "geometry": {"coordinates":[-1.3830339909,53.4324073792],"type":"Point"}
}