{
  "type": "Feature",
  "properties": {
    "addr:full":"10c Corporation St Chesterfield Derbyshire S41 7TP",
    "addr:housenumber":"10c",
    "addr:postcode":"s41 7tp",
    "addr:street":"Corporation St",
    "iso:country":"GB",
    "sg:address":"10c Corporation St",
    "sg:city":"Chesterfield",
    "sg:classifiers":[
        {
            "category":"Shopping",
            "subcategory":"Clothing, Apparel, & Fashions",
            "type":"Retail Goods"
        }
    ],
    "sg:postcode":"S41 7TP",
    "sg:province":"Derbyshire",
    "sg:tags":[
        "shop",
        "dress",
        "fancy"
    ],
    "wof:name":"Bingham,Anne,",
    "wof:placetype":"venue"
},
  "geometry": {"coordinates":[-1.423151,53.236851],"type":"Point"}
}