{
  "type": "Feature",
  "properties": {
    "addr:full":"26 Queen St Barnstaple Devon EX32 8HQ",
    "addr:housenumber":"26",
    "addr:postcode":"ex32 8hq",
    "addr:street":"Queen St",
    "iso:country":"GB",
    "sg:address":"26 Queen St",
    "sg:city":"Barnstaple",
    "sg:classifiers":[
        {
            "category":"Professional",
            "subcategory":"Business Services",
            "type":"Services"
        }
    ],
    "sg:phone":"+44 1271 323323",
    "sg:postcode":"EX32 8HQ",
    "sg:province":"Devon",
    "sg:tags":[
        "bookmaker"
    ],
    "wof:name":"Vickers",
    "wof:placetype":"venue"
},
  "geometry": {"coordinates":[-4.0564379692,51.079208374],"type":"Point"}
}