{
  "type": "Feature",
  "properties": {
    "addr:full":"Russell Farm, Cobblers Hill, Wendover Aylesbury Buckinghamshire HP22 6QD",
    "addr:postcode":"hp22 6qd",
    "addr:street":"Hill Wendover",
    "iso:country":"GB",
    "sg:address":"Russell Farm, Cobblers Hill, Wendover",
    "sg:city":"Aylesbury",
    "sg:classifiers":[
        {
            "category":"Retail",
            "subcategory":"Animal Services",
            "type":"Services"
        },
        {
            "category":"Personal",
            "subcategory":"Adult",
            "type":"Services"
        }
    ],
    "sg:postcode":"HP22 6QD",
    "sg:province":"Buckinghamshire",
    "sg:tags":[
        "trainer",
        "horse",
        "equestrian"
    ],
    "wof:name":"Wendover Dene Racing",
    "wof:placetype":"venue"
},
  "geometry": {"coordinates":[-0.7424640059,51.7640914917],"type":"Point"}
}