{
  "type": "Feature",
  "properties": {
    "iso:country":"GB",
    "sg:address":"Oriel Drive, Aintree",
    "sg:city":"Liverpool",
    "sg:classifiers":[
        {
            "category":"Community Center",
            "subcategory":"Youth",
            "type":"Public Place"
        }
    ],
    "sg:phone":"+44 151 526 1177",
    "sg:postcode":"L10 6NJ",
    "sg:province":"Merseyside",
    "sg:tags":[
        "organisation",
        "centre"
    ],
    "wof:name":"Aintree Youth Centre",
    "wof:placetype":"venue"
},
  "geometry": {"coordinates":[-2.936607,53.485054],"type":"Point"}
}