{
  "type": "Feature",
  "properties": {
    "addr:full":"21 Blithfield Avenue Loughborough Leicestershire LE11 4SY",
    "addr:housenumber":"21",
    "addr:postcode":"le11 4sy",
    "addr:street":"Blithfield Avenue",
    "iso:country":"GB",
    "sg:address":"21 Blithfield Avenue",
    "sg:city":"Loughborough",
    "sg:classifiers":[
        {
            "category":"Building & Trades",
            "subcategory":"Cleaning & Sanitation",
            "type":"Services"
        }
    ],
    "sg:postcode":"LE11 4SY",
    "sg:province":"Leicestershire",
    "sg:tags":[
        "commercial"
    ],
    "wof:name":"Simpson Cleaning Services",
    "wof:placetype":"venue"
},
  "geometry": {"coordinates":[-1.2447220087,52.767578125],"type":"Point"}
}