{
  "type": "Feature",
  "properties": {
    "addr:full":"24a Tudor Street London Greater London EC4Y 0AY",
    "addr:housenumber":"24a",
    "addr:postcode":"ec4y 0ay",
    "addr:street":"Tudor Street",
    "iso:country":"GB",
    "sg:address":"24a Tudor Street",
    "sg:city":"London",
    "sg:classifiers":[
        {
            "category":"Professional",
            "type":"Services"
        }
    ],
    "sg:postcode":"EC4Y 0AY",
    "sg:province":"Greater London",
    "sg:tags":[
        "caterer"
    ],
    "wof:name":"Paxtel Ltd.",
    "wof:placetype":"venue"
},
  "geometry": {"coordinates":[-0.1065590009,51.5127563477],"type":"Point"}
}