{
  "type": "Feature",
  "properties": {
    "iso:country":"GB",
    "sg:address":"Greenheath Business Centre, Three Colts Lane",
    "sg:city":"London",
    "sg:classifiers":[
        {
            "category":"Building & Trades",
            "subcategory":"Construction",
            "type":"Services"
        }
    ],
    "sg:phone":"+44 20 7790 2300",
    "sg:postcode":"E2 6JL",
    "sg:province":"Greater London",
    "sg:tags":[
        "worker",
        "metal"
    ],
    "wof:name":"Rytech Fabrications",
    "wof:placetype":"venue"
},
  "geometry": {"coordinates":[-0.058909,51.5242],"type":"Point"}
}