{
  "type": "Feature",
  "properties": {
    "iso:country":"GB",
    "sg:address":"73 Mansfield Est",
    "sg:city":"Tain",
    "sg:classifiers":[
        {
            "category":"Military Area",
            "subcategory":"Air Force Base",
            "type":"Public Place"
        }
    ],
    "sg:phone":"+44 1862 894285",
    "sg:postcode":"IV19 1JL",
    "sg:province":"Highland",
    "sg:tags":[
        "taxi",
        "hire",
        "private"
    ],
    "wof:name":"Billies Taxis",
    "wof:placetype":"venue"
},
  "geometry": {"coordinates":[-4.0610089302,57.8047790527],"type":"Point"}
}