{
  "type": "Feature",
  "properties": {
    "iso:country":"GB",
    "sg:address":"27 Heartsease Lane",
    "sg:city":"Norwich",
    "sg:classifiers":[
        {
            "category":"Building & Trades",
            "subcategory":"Construction",
            "type":"Services"
        }
    ],
    "sg:phone":"+44 1603 433571",
    "sg:postcode":"NR7 9NP",
    "sg:province":"Norfolk",
    "sg:tags":[
        "builder"
    ],
    "wof:name":"Stanley H Leathers",
    "wof:placetype":"venue"
},
  "geometry": {"coordinates":[1.328017,52.638577],"type":"Point"}
}