{
  "type": "Feature",
  "properties": {
    "addr:full":"115 Kilburn Square, Kilburn London Greater London NW6 6PS",
    "addr:housenumber":"115",
    "addr:postcode":"nw6 6ps",
    "addr:street":"Kilburn Square",
    "iso:country":"GB",
    "sg:address":"115 Kilburn Square, Kilburn",
    "sg:city":"London",
    "sg:classifiers":[
        {
            "category":"Health Services",
            "subcategory":"Clinic",
            "type":"Services"
        }
    ],
    "sg:phone":"+44 20 7625 5115",
    "sg:postcode":"NW6 6PS",
    "sg:province":"Greater London",
    "sg:tags":[
        "nh"
    ],
    "wof:name":"Square Circle Solutions Ltd.",
    "wof:placetype":"venue"
},
  "geometry": {"coordinates":[-0.196589,51.53751],"type":"Point"}
}