{
  "type": "Feature",
  "properties": {
    "addr:full":"Albert Buildings, 49 Queen Victoria Street London Greater London EC4N 4SA",
    "addr:housenumber":"49",
    "addr:postcode":"ec4n 4sa",
    "addr:street":"Albert;Queen Victoria Street",
    "iso:country":"GB",
    "sg:address":"Albert Buildings, 49 Queen Victoria Street",
    "sg:city":"London",
    "sg:classifiers":[
        {
            "category":"Shopping",
            "subcategory":"Stationery & Office Supplies",
            "type":"Retail Goods"
        }
    ],
    "sg:phone":"+44 20 7236 4000",
    "sg:postcode":"EC4N 4SA",
    "sg:province":"Greater London",
    "sg:tags":[
        "item",
        "promotional"
    ],
    "wof:name":"Dukes of London",
    "wof:placetype":"venue"
},
  "geometry": {"coordinates":[-0.0927800015,51.5123786926],"type":"Point"}
}