{
  "type": "Feature",
  "properties": {
    "addr:full":"Hinksford Garden Centre, Hinksford Lane Kingswinford Staffordshire DY6 0BH",
    "addr:postcode":"dy6 0bh",
    "addr:street":"Hinksford Lane",
    "iso:country":"GB",
    "sg:address":"Hinksford Garden Centre, Hinksford Lane",
    "sg:city":"Kingswinford",
    "sg:classifiers":[
        {
            "category":"Home & Garden",
            "subcategory":"Garden Supply",
            "type":"Retail Goods"
        }
    ],
    "sg:phone":"+44 1384 401789",
    "sg:postcode":"DY6 0BH",
    "sg:province":"Staffordshire",
    "sg:tags":[
        "nursery",
        "centre"
    ],
    "wof:name":"Tafs",
    "wof:placetype":"venue"
},
  "geometry": {"coordinates":[-2.1973590851,52.5088348389],"type":"Point"}
}