{
  "type": "Feature",
  "properties": {
    "addr:full":"2 Willow Shopping Centre, Downend Road, Downend Bristol City of Bristol BS16 5UJ",
    "addr:housenumber":"2",
    "addr:postcode":"bs16 5uj",
    "addr:street":"Willow Shopping;Downend Road",
    "iso:country":"GB",
    "sg:address":"2 Willow Shopping Centre, Downend Road, Downend",
    "sg:city":"Bristol",
    "sg:classifiers":[
        {
            "category":"Travel",
            "subcategory":"Travel Agent",
            "type":"Entertainment"
        }
    ],
    "sg:phone":"+44 117 970 2700",
    "sg:postcode":"BS16 5UJ",
    "sg:province":"City of Bristol",
    "wof:name":"Bakers Dolphin Travel",
    "wof:placetype":"venue"
},
  "geometry": {"coordinates":[-2.5914289951,51.453666687],"type":"Point"}
}