{
  "type": "Feature",
  "properties": {
    "addr:full":"30 High St Thornton Heath Surrey CR7 8LE",
    "addr:housenumber":"30",
    "addr:postcode":"cr7 8le",
    "addr:street":"High St",
    "iso:country":"GB",
    "sg:address":"30 High St",
    "sg:city":"Thornton Heath",
    "sg:classifiers":[
        {
            "category":"Professional",
            "subcategory":"Accounting & Tax Preparation",
            "type":"Services"
        }
    ],
    "sg:phone":"+44 20 8684 3253",
    "sg:postcode":"CR7 8LE",
    "sg:province":"Surrey",
    "sg:tags":[
        "accountant"
    ],
    "wof:name":"D Scrafton & Co",
    "wof:placetype":"venue"
},
  "geometry": {"coordinates":[-0.094062,51.398438],"type":"Point"}
}