{
  "type": "Feature",
  "properties": {
    "addr:full":"Bank Street, Park Village Wolverhampton Staffordshire WV10 9DU",
    "addr:postcode":"wv10 9du",
    "addr:street":"Bank Street",
    "iso:country":"GB",
    "sg:address":"Bank Street, Park Village",
    "sg:city":"Wolverhampton",
    "sg:classifiers":[
        {
            "category":"Building & Trades",
            "subcategory":"Construction",
            "type":"Services"
        }
    ],
    "sg:phone":"+44 1902 736630",
    "sg:postcode":"WV10 9DU",
    "sg:province":"Staffordshire",
    "sg:tags":[
        "roofing"
    ],
    "wof:name":"W & S Long Ltd.",
    "wof:placetype":"venue"
},
  "geometry": {"coordinates":[-2.1122689247,52.598903656],"type":"Point"}
}