{
  "type": "Feature",
  "properties": {
    "addr:full":"1 Chamberlain Road Aylesbury Buckinghamshire HP19 8RB",
    "addr:housenumber":"1",
    "addr:postcode":"hp19 8rb",
    "addr:street":"Chamberlain Road",
    "iso:country":"GB",
    "sg:address":"1 Chamberlain Road",
    "sg:city":"Aylesbury",
    "sg:classifiers":[
        {
            "category":"Home & Garden",
            "subcategory":"Hardware",
            "type":"Retail Goods"
        },
        {
            "category":"Shopping",
            "subcategory":"Pets & Pet Supplies",
            "type":"Retail Goods"
        }
    ],
    "sg:phone":"+44 1296 429333",
    "sg:postcode":"HP19 8RB",
    "sg:province":"Buckinghamshire",
    "sg:tags":[
        "product",
        "wire",
        "electrical"
    ],
    "wof:name":"Shaws Pet Products Ltd.",
    "wof:placetype":"venue"
},
  "geometry": {"coordinates":[-0.832699,51.822933],"type":"Point"}
}