{
  "type": "Feature",
  "properties": {
    "iso:country":"GB",
    "sg:address":"The Old Sorting Office, The Highway, Hawarden",
    "sg:city":"Deeside",
    "sg:classifiers":[
        {
            "category":"Professional",
            "subcategory":"Lawyer & Legal Services",
            "type":"Services"
        }
    ],
    "sg:phone":"+44 1244 535536",
    "sg:postcode":"CH5 3DG",
    "sg:province":"Flintshire",
    "wof:name":"First Legal",
    "wof:placetype":"venue"
},
  "geometry": {"coordinates":[-3.026109,53.184776],"type":"Point"}
}