{
  "type": "Feature",
  "properties": {
    "iso:country":"GB",
    "sg:address":"1 Hallam Clo, Bessacarr",
    "sg:city":"Doncaster",
    "sg:classifiers":[
        {
            "category":"Manufacturing",
            "subcategory":"Petroleum Products",
            "type":"Manufacturing & Wholesale Goods"
        }
    ],
    "sg:postcode":"DN4 7RT",
    "sg:province":"South Yorkshire",
    "sg:tags":[
        "double",
        "glazing"
    ],
    "wof:name":"Corsair",
    "wof:placetype":"venue"
},
  "geometry": {"coordinates":[-1.093045,53.502758],"type":"Point"}
}