{
  "type": "Feature",
  "properties": {
    "addr:full":"148 Gloucester Avenue Chelmsford Essex CM2 9LG",
    "addr:housenumber":"148",
    "addr:postcode":"cm2 9lg",
    "addr:street":"Gloucester Avenue",
    "iso:country":"GB",
    "sg:address":"148 Gloucester Avenue",
    "sg:city":"Chelmsford",
    "sg:classifiers":[
        {
            "category":"Shopping",
            "subcategory":"News",
            "type":"Retail Goods"
        }
    ],
    "sg:phone":"+44 1245 492837",
    "sg:postcode":"CM2 9LG",
    "sg:province":"Essex",
    "sg:tags":[
        "newsagent"
    ],
    "wof:name":"Martin the Newsagent",
    "wof:placetype":"venue"
},
  "geometry": {"coordinates":[0.4738669991,51.7159538269],"type":"Point"}
}