{
  "type": "Feature",
  "properties": {
    "addr:full":"44 Carlton Road Worksop Nottinghamshire S80 1PH",
    "addr:housenumber":"44",
    "addr:postcode":"s80 1ph",
    "addr:street":"Carlton Road",
    "iso:country":"GB",
    "sg:address":"44 Carlton Road",
    "sg:city":"Worksop",
    "sg:classifiers":[
        {
            "category":"Autos & Motor Vehicles",
            "subcategory":"Auto Supplies",
            "type":"Retail Goods"
        }
    ],
    "sg:phone":"+44 1909 501818",
    "sg:postcode":"S80 1PH",
    "sg:province":"Nottinghamshire",
    "sg:tags":[
        "tyre"
    ],
    "wof:name":"Ats",
    "wof:placetype":"venue"
},
  "geometry": {"coordinates":[-1.1218620539,53.308807373],"type":"Point"}
}