{
  "type": "Feature",
  "properties": {
    "addr:full":"Unit 1 Berwick-upon-tweed Northumberland TD15 1UN",
    "addr:housenumber":"unit 1",
    "addr:postcode":"td15 1un",
    "addr:street":"Northumberland",
    "iso:country":"GB",
    "sg:address":"Unit 1",
    "sg:city":"Berwick-upon-tweed",
    "sg:classifiers":[
        {
            "category":"Manufacturing",
            "subcategory":"Wood Products",
            "type":"Manufacturing & Wholesale Goods"
        },
        {
            "category":"Manufacturing",
            "subcategory":"Paper Products",
            "type":"Manufacturing & Wholesale Goods"
        }
    ],
    "sg:phone":"+44 1289 304700",
    "sg:postcode":"TD15 1UN",
    "sg:province":"Northumberland",
    "sg:tags":[
        "packaging",
        "material",
        "crate",
        "pallets",
        "manufacturer"
    ],
    "wof:name":"Tweed Packaging",
    "wof:placetype":"venue"
},
  "geometry": {"coordinates":[-2.055219,55.768349],"type":"Point"}
}