{
  "type": "Feature",
  "properties": {
    "iso:country":"GB",
    "sg:address":"23 Fox Street",
    "sg:city":"Carnoustie",
    "sg:classifiers":[
        {
            "category":"Building & Trades",
            "subcategory":"Construction",
            "type":"Services"
        }
    ],
    "sg:phone":"+44 1241 854554",
    "sg:postcode":"DD7 6AJ",
    "sg:province":"Angus",
    "sg:tags":[
        "joiner",
        "carpenter"
    ],
    "wof:name":"David B Christie Joiners",
    "wof:placetype":"venue"
},
  "geometry": {"coordinates":[-2.708475,56.500469],"type":"Point"}
}