{
  "type": "Feature",
  "properties": {
    "addr:full":"42 Oaklyn Gardens Shanklin Isle of Wight PO37 7DG",
    "addr:housenumber":"42",
    "addr:postcode":"po37 7dg",
    "addr:street":"Oaklyn Gardens",
    "iso:country":"GB",
    "sg:address":"42 Oaklyn Gardens",
    "sg:city":"Shanklin",
    "sg:classifiers":[
        {
            "category":"Building & Trades",
            "subcategory":"Construction",
            "type":"Services"
        }
    ],
    "sg:phone":"+44 1983 866738",
    "sg:postcode":"PO37 7DG",
    "sg:province":"Isle of Wight",
    "sg:tags":[
        "roofing"
    ],
    "wof:name":"Vectabuild",
    "wof:placetype":"venue"
},
  "geometry": {"coordinates":[-1.174449,50.638626],"type":"Point"}
}