{
  "type": "Feature",
  "properties": {
    "addr:full":"19 Grace Hill Folkestone Kent CT20 1HA",
    "addr:housenumber":"19",
    "addr:postcode":"ct20 1ha",
    "addr:street":"Grace Hill",
    "iso:country":"GB",
    "sg:address":"19 Grace Hill",
    "sg:city":"Folkestone",
    "sg:classifiers":[
        {
            "category":"Professional",
            "subcategory":"Printing & Photocopies",
            "type":"Services"
        }
    ],
    "sg:phone":"+44 1303 850708",
    "sg:postcode":"CT20 1HA",
    "sg:province":"Kent",
    "sg:tags":[
        "duplicating",
        "copying"
    ],
    "wof:name":"Copy Link",
    "wof:placetype":"venue"
},
  "geometry": {"coordinates":[1.1804790497,51.0815620422],"type":"Point"}
}