{
  "type": "Feature",
  "properties": {
    "iso:country":"GB",
    "sg:address":"2 Croft Close, Mill Hill",
    "sg:city":"London",
    "sg:classifiers":[
        {
            "category":"Retail",
            "subcategory":"Animal Services",
            "type":"Services"
        }
    ],
    "sg:phone":"+44 20 8201 1606",
    "sg:postcode":"NW7 4QL",
    "sg:province":"Greater London",
    "sg:tags":[
        "pet"
    ],
    "wof:name":"Pals4pets Ltd.",
    "wof:placetype":"venue"
},
  "geometry": {"coordinates":[-0.25236,51.623871],"type":"Point"}
}