{
  "type": "Feature",
  "properties": {
    "addr:full":"14 Viking Clo Great Yarmouth Norfolk NR31 6ES",
    "addr:housenumber":"14",
    "addr:postcode":"nr31 6es",
    "addr:street":"Viking Clo Great Yarmouth",
    "iso:country":"GB",
    "sg:address":"14 Viking Clo",
    "sg:city":"Great Yarmouth",
    "sg:classifiers":[
        {
            "category":"Retail",
            "subcategory":"Driving School",
            "type":"Services"
        }
    ],
    "sg:phone":"+44 1493 602214",
    "sg:postcode":"NR31 6ES",
    "sg:province":"Norfolk",
    "wof:name":"C A Ecclestone",
    "wof:placetype":"venue"
},
  "geometry": {"coordinates":[1.7260349989,52.5649223328],"type":"Point"}
}