{
  "type": "Feature",
  "properties": {
    "iso:country":"GB",
    "sg:address":"Rutland Mills, Tootal Street",
    "sg:city":"Wakefield",
    "sg:classifiers":[
        {
            "category":"Shopping",
            "subcategory":"Clothing, Apparel, & Fashions",
            "type":"Retail Goods"
        }
    ],
    "sg:phone":"+44 1924 384477",
    "sg:postcode":"WF1 5JN",
    "sg:province":"West Yorkshire",
    "sg:tags":[
        "clothing",
        "fabric"
    ],
    "wof:name":"Raven Apparel Ltd.",
    "wof:placetype":"venue"
},
  "geometry": {"coordinates":[-1.49043,53.675442],"type":"Point"}
}