{
  "type": "Feature",
  "properties": {
    "addr:full":"Roxanne Lucille Schmacher, Bembridge Cranleigh Surrey GU6 7BQ",
    "addr:postcode":"gu6 7bq",
    "addr:street":"Roxanne",
    "iso:country":"GB",
    "sg:address":"Roxanne Lucille Schmacher, Bembridge",
    "sg:city":"Cranleigh",
    "sg:classifiers":[
        {
            "category":"Airline",
            "type":"Transportation"
        }
    ],
    "sg:postcode":"GU6 7BQ",
    "sg:province":"Surrey",
    "sg:tags":[
        "aircraft",
        "charter"
    ],
    "wof:name":"Canada 3000 Airlines Ltd.",
    "wof:placetype":"venue"
},
  "geometry": {"coordinates":[-0.482999,51.141541],"type":"Point"}
}