{
  "type": "Feature",
  "properties": {
    "addr:full":"9 Mill Hill Road, Eaton Ford St Neots Bedfordshire PE19 7AG",
    "addr:housenumber":"9",
    "addr:postcode":"pe19 7ag",
    "addr:street":"Mill Hill Road;Ford",
    "iso:country":"GB",
    "sg:address":"9 Mill Hill Road, Eaton Ford",
    "sg:city":"St Neots",
    "sg:classifiers":[
        {
            "category":"Building & Trades",
            "subcategory":"Landscaping Services",
            "type":"Services"
        }
    ],
    "sg:postcode":"PE19 7AG",
    "sg:province":"Bedfordshire",
    "sg:tags":[
        "gardening"
    ],
    "wof:name":"Neat & Tidy Landscape Gardeners",
    "wof:placetype":"venue"
},
  "geometry": {"coordinates":[-0.2793439925,52.2268486023],"type":"Point"}
}