{
  "type": "Feature",
  "properties": {
    "iso:country":"GB",
    "sg:address":"18 Southmead Close",
    "sg:city":"Mayfield",
    "sg:classifiers":[
        {
            "category":"Building & Trades",
            "subcategory":"Construction",
            "type":"Services"
        }
    ],
    "sg:phone":"+44 1435 873467",
    "sg:postcode":"TN20 6UJ",
    "sg:province":"East Sussex",
    "sg:tags":[
        "glazier",
        "decorator",
        "painter"
    ],
    "wof:name":"Trevor D Streeter",
    "wof:placetype":"venue"
},
  "geometry": {"coordinates":[0.2737169862,51.0220031738],"type":"Point"}
}