{
  "type": "Feature",
  "properties": {
    "addr:full":"3 Etherley Close Stockton-on-tees Durham TS19 8HY",
    "addr:housenumber":"3",
    "addr:postcode":"ts19 8hy",
    "addr:street":"Etherley Close",
    "iso:country":"GB",
    "sg:address":"3 Etherley Close",
    "sg:city":"Stockton-on-tees",
    "sg:classifiers":[
        {
            "category":"Food & Beverages",
            "subcategory":"Liquor & Beverages",
            "type":"Retail Goods"
        }
    ],
    "sg:phone":"+44 1642 672854",
    "sg:postcode":"TS19 8HY",
    "sg:province":"Durham",
    "sg:tags":[
        "beer",
        "spirit",
        "wines"
    ],
    "wof:name":"G E & M Jones & Son",
    "wof:placetype":"venue"
},
  "geometry": {"coordinates":[-1.3533869982,54.5884628296],"type":"Point"}
}