{
  "type": "Feature",
  "properties": {
    "iso:country":"GB",
    "sg:address":"104 Trongate",
    "sg:city":"Glasgow",
    "sg:classifiers":[
        {
            "category":"Shopping",
            "subcategory":"Baby Store",
            "type":"Retail Goods"
        }
    ],
    "sg:phone":"+44 141 552 1178",
    "sg:postcode":"G1 5EP",
    "sg:province":"Glasgow City",
    "sg:tags":[
        "babywear",
        "childrens"
    ],
    "wof:name":"Tot Spot Ltd.",
    "wof:placetype":"venue"
},
  "geometry": {"coordinates":[-4.2461118698,55.8571472168],"type":"Point"}
}