{
  "type": "Feature",
  "properties": {
    "iso:country":"GB",
    "sg:address":"190-191 St Andrews Rd",
    "sg:city":"Northampton",
    "sg:classifiers":[
        {
            "category":"Autos & Motor Vehicles",
            "subcategory":"Automobile Sales",
            "type":"Retail Goods"
        }
    ],
    "sg:phone":"+44 1604 721398",
    "sg:postcode":"NN2 6DA",
    "sg:province":"Northamptonshire",
    "sg:tags":[
        "car",
        "used"
    ],
    "wof:name":"Autoselect Car Sales",
    "wof:placetype":"venue"
},
  "geometry": {"coordinates":[-0.904043,52.247303],"type":"Point"}
}