{
  "type": "Feature",
  "properties": {
    "iso:country":"GB",
    "sg:address":"32-40 Station Road",
    "sg:city":"London",
    "sg:classifiers":[
        {
            "category":"Manufacturing",
            "subcategory":"Building Materials",
            "type":"Manufacturing & Wholesale Goods"
        }
    ],
    "sg:phone":"+44 20 8349 9987",
    "sg:postcode":"N3 2SA",
    "sg:province":"Greater London",
    "sg:tags":[
        "merchant",
        "builder"
    ],
    "wof:name":"Halarias Builders Merchants",
    "wof:placetype":"venue"
},
  "geometry": {"coordinates":[-0.1919659972,51.5998420715],"type":"Point"}
}