{
  "type": "Feature",
  "properties": {
    "addr:full":"42 East Church St Buckie Moray AB56 1AB",
    "addr:housenumber":"42",
    "addr:postcode":"ab56 1ab",
    "addr:street":"East Church St",
    "iso:country":"GB",
    "sg:address":"42 East Church St",
    "sg:city":"Buckie",
    "sg:classifiers":[
        {
            "category":"Shopping",
            "subcategory":"Department Store",
            "type":"Retail Goods"
        }
    ],
    "sg:postcode":"AB56 1AB",
    "sg:province":"Moray",
    "wof:name":"Musicmatters",
    "wof:placetype":"venue"
},
  "geometry": {"coordinates":[-2.961228,57.677227],"type":"Point"}
}