{
  "type": "Feature",
  "properties": {
    "iso:country":"GB",
    "sg:address":"Ouseburn Building, Albion Row",
    "sg:city":"Newcastle-upon-tyne",
    "sg:classifiers":[
        {
            "category":"Education",
            "subcategory":"School",
            "type":"Public Place"
        }
    ],
    "sg:postcode":"NE6 1LL",
    "sg:province":"Tyne and Wear",
    "sg:tags":[
        "local",
        "authority"
    ],
    "wof:name":"Total Learning Challenge Project",
    "wof:placetype":"venue"
},
  "geometry": {"coordinates":[-1.5859400034,54.9721412659],"type":"Point"}
}