{
  "type": "Feature",
  "properties": {
    "addr:full":"Atlas Centre, Union Road West Bromwich West Midlands B70 9DR",
    "addr:postcode":"b70 9dr",
    "addr:street":"Union Road",
    "iso:country":"GB",
    "sg:address":"Atlas Centre, Union Road",
    "sg:city":"West Bromwich",
    "sg:classifiers":[
        {
            "category":"Manufacturing",
            "subcategory":"Metals",
            "type":"Manufacturing & Wholesale Goods"
        }
    ],
    "sg:phone":"+44 121 500 4100",
    "sg:postcode":"B70 9DR",
    "sg:province":"West Midlands",
    "sg:tags":[
        "steel",
        "stockholder"
    ],
    "wof:name":"William King Ltd.",
    "wof:placetype":"venue"
},
  "geometry": {"coordinates":[-1.9902240038,52.5186233521],"type":"Point"}
}