{
  "type": "Feature",
  "properties": {
    "addr:full":"1 Church Street Wetherby North Yorkshire LS22 6LP",
    "addr:housenumber":"1",
    "addr:postcode":"ls22 6lp",
    "addr:street":"Church Street",
    "iso:country":"GB",
    "sg:address":"1 Church Street",
    "sg:city":"Wetherby",
    "sg:classifiers":[
        {
            "category":"Shopping",
            "subcategory":"Antiques",
            "type":"Retail Goods"
        }
    ],
    "sg:postcode":"LS22 6LP",
    "sg:province":"North Yorkshire",
    "wof:name":"Barbara's",
    "wof:placetype":"venue"
},
  "geometry": {"coordinates":[-1.386524,53.929611],"type":"Point"}
}