{
  "type": "Feature",
  "properties": {
    "addr:full":"12 Grays Inn Square, Grays Inn London Greater London WC1R 5JP",
    "addr:housenumber":"12",
    "addr:postcode":"wc1r 5jp",
    "addr:street":"Grays Inn Square",
    "iso:country":"GB",
    "sg:address":"12 Grays Inn Square, Grays Inn",
    "sg:city":"London",
    "sg:classifiers":[
        {
            "category":"Professional",
            "subcategory":"Lawyer & Legal Services",
            "type":"Services"
        }
    ],
    "sg:phone":"+44 20 7404 4866",
    "sg:postcode":"WC1R 5JP",
    "sg:province":"Greater London",
    "sg:tags":[
        "barrister"
    ],
    "wof:name":"Niamh McCarthy",
    "wof:placetype":"venue"
},
  "geometry": {"coordinates":[-0.11263,51.519421],"type":"Point"}
}