{
  "type": "Feature",
  "properties": {
    "addr:full":"Strawberry Lane Industrial Estate, Strawberry Lane Willenhall West Midlands WV13 3RS",
    "addr:housenumber":"estate",
    "addr:postcode":"wv13 3rs",
    "addr:street":"Strawberry Lane Industrial;Strawberry Lane",
    "iso:country":"GB",
    "sg:address":"Strawberry Lane Industrial Estate, Strawberry Lane",
    "sg:city":"Willenhall",
    "sg:classifiers":[
        {
            "category":"Home & Garden",
            "subcategory":"Hardware",
            "type":"Retail Goods"
        },
        {
            "category":"Shopping",
            "subcategory":"Computers & Home Electronics",
            "type":"Retail Goods"
        }
    ],
    "sg:phone":"+44 1902 368000",
    "sg:postcode":"WV13 3RS",
    "sg:province":"West Midlands",
    "sg:tags":[
        "mnfr"
    ],
    "wof:name":"Laidlaw Architectural Hardware",
    "wof:placetype":"venue"
},
  "geometry": {"coordinates":[-2.085889,52.589176],"type":"Point"}
}