{
  "type": "Feature",
  "properties": {
    "iso:country":"GB",
    "sg:address":"Reprographic House, Canal Road, Armley",
    "sg:city":"Leeds",
    "sg:classifiers":[
        {
            "category":"Shopping",
            "subcategory":"Stationery & Office Supplies",
            "type":"Retail Goods"
        }
    ],
    "sg:phone":"+44 113 263 0601",
    "sg:postcode":"LS12 2ND",
    "sg:province":"West Yorkshire",
    "sg:tags":[
        "drawing"
    ],
    "wof:name":"Central Drawing Office Services Yorks Ltd",
    "wof:placetype":"venue"
},
  "geometry": {"coordinates":[-1.58348,53.800369],"type":"Point"}
}