{
  "type": "Feature",
  "properties": {
    "addr:full":"29 Melrose Gardens Hammersmith Greater London W6 7RN",
    "addr:housenumber":"29",
    "addr:postcode":"w6 7rn",
    "addr:street":"Melrose Gardens",
    "iso:country":"GB",
    "sg:address":"29 Melrose Gardens",
    "sg:city":"Hammersmith",
    "sg:classifiers":[
        {
            "category":"Museum",
            "subcategory":"Art Museum",
            "type":"Entertainment"
        }
    ],
    "sg:phone":"+44 20 7603 3817",
    "sg:postcode":"W6 7RN",
    "sg:province":"Greater London",
    "sg:tags":[
        "gallery"
    ],
    "wof:name":"Feathers Gallery",
    "wof:placetype":"venue"
},
  "geometry": {"coordinates":[-0.223713,51.499886],"type":"Point"}
}