{
  "type": "Feature",
  "properties": {
    "addr:full":"St Marys St Haverfordwest Pembrokeshire SA61 2DR",
    "addr:postcode":"sa61 2dr",
    "addr:street":"St;St",
    "iso:country":"GB",
    "sg:address":"St Marys St",
    "sg:city":"Haverfordwest",
    "sg:classifiers":[
        {
            "category":"Professional",
            "subcategory":"Accounting & Tax Preparation",
            "type":"Services"
        }
    ],
    "sg:phone":"+44 1437 764785",
    "sg:postcode":"SA61 2DR",
    "sg:province":"Pembrokeshire",
    "sg:tags":[
        "accountant"
    ],
    "wof:name":"Simon Llewellin & Co",
    "wof:placetype":"venue"
},
  "geometry": {"coordinates":[-4.971631,51.80135],"type":"Point"}
}