{
  "type": "Feature",
  "properties": {
    "addr:full":"Devonshire Cres Leeds West Yorkshire LS8 1BZ",
    "addr:postcode":"ls8 1bz",
    "addr:street":"Devonshire Cres",
    "iso:country":"GB",
    "sg:address":"Devonshire Cres",
    "sg:city":"Leeds",
    "sg:classifiers":[
        {
            "category":"Retail",
            "subcategory":"Auto Repair",
            "type":"Services"
        }
    ],
    "sg:postcode":"LS8 1BZ",
    "sg:province":"West Yorkshire",
    "sg:tags":[
        "modification",
        "garage"
    ],
    "wof:name":"Rennison,Stephen,",
    "wof:placetype":"venue"
},
  "geometry": {"coordinates":[-1.514613986,53.8411560059],"type":"Point"}
}