{
  "type": "Feature",
  "properties": {
    "iso:country":"GB",
    "sg:address":"44 Queen Street, Cubbington",
    "sg:city":"Leamington Spa",
    "sg:classifiers":[
        {
            "category":"Food & Beverages",
            "subcategory":"Supermarket",
            "type":"Retail Goods"
        }
    ],
    "sg:postcode":"CV32 7NA",
    "sg:province":"Warwickshire",
    "wof:name":"Spar",
    "wof:placetype":"venue"
},
  "geometry": {"coordinates":[-1.5010819435,52.3106651306],"type":"Point"}
}