{
  "type": "Feature",
  "properties": {
    "iso:country":"GB",
    "sg:address":"Unit 26 The Market, The Piazza",
    "sg:city":"London",
    "sg:classifiers":[
        {
            "category":"Home & Garden",
            "subcategory":"Kitchen Supply",
            "type":"Retail Goods"
        }
    ],
    "sg:phone":"+44 20 7379 8374",
    "sg:postcode":"WC2E 8AH",
    "sg:province":"Greater London",
    "sg:tags":[
        "glassware",
        "china"
    ],
    "wof:name":"Reject China Shop",
    "wof:placetype":"venue"
},
  "geometry": {"coordinates":[-0.182653,51.585697],"type":"Point"}
}