{
  "type": "Feature",
  "properties": {
    "addr:full":"Beverley Road, North Newbald York East Riding of Yorkshire YO43 4SQ",
    "addr:postcode":"yo43 4sq",
    "addr:street":"Beverley Road North",
    "iso:country":"GB",
    "sg:address":"Beverley Road, North Newbald",
    "sg:city":"York",
    "sg:classifiers":[
        {
            "category":"Education",
            "subcategory":"School",
            "type":"Public Place"
        },
        {
            "category":"Government",
            "subcategory":"Office",
            "type":"Public Place"
        }
    ],
    "sg:phone":"+44 1430 827612",
    "sg:postcode":"YO43 4SQ",
    "sg:province":"East Riding of Yorkshire",
    "sg:tags":[
        "local",
        "authority"
    ],
    "wof:name":"Newbald County Primary School",
    "wof:placetype":"venue"
},
  "geometry": {"coordinates":[-0.6063349843,53.8227043152],"type":"Point"}
}