{
  "type": "Feature",
  "properties": {
    "iso:country":"GB",
    "sg:address":"29 Mill Lane",
    "sg:city":"Sandy",
    "sg:classifiers":[
        {
            "category":"Professional",
            "subcategory":"Management & Consulting",
            "type":"Services"
        }
    ],
    "sg:phone":"+44 1767 699488",
    "sg:postcode":"SG19 1NL",
    "sg:province":"Bedfordshire",
    "sg:tags":[
        "consultant",
        "safety"
    ],
    "wof:name":"Stirling Consultants",
    "wof:placetype":"venue"
},
  "geometry": {"coordinates":[-0.292904,52.125183],"type":"Point"}
}