{
  "type": "Feature",
  "properties": {
    "iso:country":"GB",
    "sg:address":"455 West Green Road",
    "sg:city":"London",
    "sg:classifiers":[
        {
            "category":"Personal",
            "type":"Services"
        }
    ],
    "sg:postcode":"N15 3PW",
    "sg:province":"Greater London",
    "sg:tags":[
        "tailor"
    ],
    "wof:name":"Express Trousers Makers",
    "wof:placetype":"venue"
},
  "geometry": {"coordinates":[-0.098739,51.587448],"type":"Point"}
}