{
  "type": "Feature",
  "properties": {
    "iso:country":"GB",
    "sg:address":"Court Hill Mount",
    "sg:city":"Irvine",
    "sg:classifiers":[
        {
            "category":"Shopping Center",
            "type":"Public Place"
        }
    ],
    "sg:postcode":"KA11 4JZ",
    "sg:province":"East Ayrshire",
    "sg:tags":[
        "clutch",
        "brake",
        "centre"
    ],
    "wof:name":"Robert Wiper Motors",
    "wof:placetype":"venue"
},
  "geometry": {"coordinates":[-4.6354298592,55.6080093384],"type":"Point"}
}