{
  "type": "Feature",
  "properties": {
    "addr:full":"237 Euston Rd Camden Greater London NW1 2BU",
    "addr:housenumber":"237",
    "addr:postcode":"nw1 2bu",
    "addr:street":"Euston Rd",
    "iso:country":"GB",
    "sg:address":"237 Euston Rd",
    "sg:city":"Camden",
    "sg:classifiers":[
        {
            "category":"Professional",
            "subcategory":"Employment Agencies",
            "type":"Services"
        }
    ],
    "sg:phone":"+44 20 7387 0024",
    "sg:postcode":"NW1 2BU",
    "sg:province":"Greater London",
    "sg:tags":[
        "consultant"
    ],
    "wof:name":"Adecco Alfred Marks",
    "wof:placetype":"venue"
},
  "geometry": {"coordinates":[-0.136055,51.525326],"type":"Point"}
}