{
  "type": "Feature",
  "properties": {
    "addr:full":"24 Arthurs Ct, Greyhill View, Portskewett Newport East Riding of Yorkshire NP6 4SD",
    "addr:housenumber":"24",
    "addr:postcode":"np6 4sd",
    "addr:street":"Arthurs Ct Greyhill View",
    "iso:country":"GB",
    "sg:address":"24 Arthurs Ct, Greyhill View, Portskewett",
    "sg:city":"Newport",
    "sg:classifiers":[
        {
            "category":"Shopping",
            "subcategory":"Crafts & Fabrics",
            "type":"Retail Goods"
        }
    ],
    "sg:phone":"+44 1291 425552",
    "sg:postcode":"NP6 4SD",
    "sg:province":"East Riding of Yorkshire",
    "sg:tags":[
        "machine",
        "sewing",
        "knitting"
    ],
    "wof:name":"Bob Challingsworth Sewing Machine Services",
    "wof:placetype":"venue"
},
  "geometry": {"coordinates":[-2.71924,51.591282],"type":"Point"}
}