{
  "type": "Feature",
  "properties": {
    "addr:full":"28 York Road Northampton Northamptonshire NN1 5QH",
    "addr:housenumber":"28",
    "addr:postcode":"nn1 5qh",
    "addr:street":"York Road",
    "iso:country":"GB",
    "sg:address":"28 York Road",
    "sg:city":"Northampton",
    "sg:classifiers":[
        {
            "category":"Fast Food",
            "type":"Food & Drink"
        }
    ],
    "sg:phone":"+44 1604 604878",
    "sg:postcode":"NN1 5QH",
    "sg:province":"Northamptonshire",
    "sg:tags":[
        "away",
        "take"
    ],
    "wof:name":"Flames Grill",
    "wof:placetype":"venue"
},
  "geometry": {"coordinates":[-0.889021,52.239716],"type":"Point"}
}