{
  "type": "Feature",
  "properties": {
    "addr:full":"1233 Warwick Road, Acocks Green Birmingham West Midlands B27 6PX",
    "addr:housenumber":"1233",
    "addr:postcode":"b27 6px",
    "addr:street":"Warwick Road",
    "iso:country":"GB",
    "sg:address":"1233 Warwick Road, Acocks Green",
    "sg:city":"Birmingham",
    "sg:classifiers":[
        {
            "category":"Professional",
            "subcategory":"Management & Consulting",
            "type":"Services"
        },
        {
            "category":"Home & Garden",
            "subcategory":"Hardware",
            "type":"Retail Goods"
        }
    ],
    "sg:phone":"+44 121 707 6866",
    "sg:postcode":"B27 6PX",
    "sg:province":"West Midlands",
    "sg:tags":[
        "marketing",
        "consultant"
    ],
    "wof:name":"SPAN MARKETING LTD",
    "wof:placetype":"venue"
},
  "geometry": {"coordinates":[-1.8154759407,52.4446487427],"type":"Point"}
}