{
  "type": "Feature",
  "properties": {
    "iso:country":"GB",
    "sg:address":"3 Selbourne Street",
    "sg:city":"Walsall",
    "sg:classifiers":[
        {
            "category":"Building & Trades",
            "subcategory":"Construction",
            "type":"Services"
        }
    ],
    "sg:phone":"+44 1922 648804",
    "sg:postcode":"WS1 2JN",
    "sg:province":"West Midlands",
    "sg:tags":[
        "decorator",
        "painter"
    ],
    "wof:name":"Marshall & Reynolds",
    "wof:placetype":"venue"
},
  "geometry": {"coordinates":[-1.9714839458,52.5826797485],"type":"Point"}
}