{
  "type": "Feature",
  "properties": {
    "addr:full":"68 Upton Court Road Slough Berkshire SL3 7LZ",
    "addr:housenumber":"68",
    "addr:postcode":"sl3 7lz",
    "addr:street":"Upton Court Road",
    "iso:country":"GB",
    "sg:address":"68 Upton Court Road",
    "sg:city":"Slough",
    "sg:classifiers":[
        {
            "category":"Retail",
            "subcategory":"Driving School",
            "type":"Services"
        }
    ],
    "sg:phone":"+44 1753 538900",
    "sg:postcode":"SL3 7LZ",
    "sg:province":"Berkshire",
    "wof:name":"Sindher Driving School",
    "wof:placetype":"venue"
},
  "geometry": {"coordinates":[-0.5747929811,51.5006065369],"type":"Point"}
}