{
  "type": "Feature",
  "properties": {
    "addr:full":"48 Coombe Lane, Raynes Park London Greater London SW20 0LA",
    "addr:housenumber":"48",
    "addr:postcode":"sw20 0la",
    "addr:street":"Coombe Lane",
    "iso:country":"GB",
    "sg:address":"48 Coombe Lane, Raynes Park",
    "sg:city":"London",
    "sg:classifiers":[
        {
            "category":"Restaurant",
            "type":"Food & Drink"
        }
    ],
    "sg:phone":"+44 20 8296 0205",
    "sg:postcode":"SW20 0LA",
    "sg:province":"Greater London",
    "wof:name":"Cafe Marquee",
    "wof:placetype":"venue"
},
  "geometry": {"coordinates":[-0.230185,51.409561],"type":"Point"}
}