{
  "type": "Feature",
  "properties": {
    "iso:country":"GB",
    "sg:address":"582 Hertford Road",
    "sg:city":"Enfield",
    "sg:classifiers":[
        {
            "category":"Insurance",
            "subcategory":"Insurance Agent",
            "type":"Services"
        }
    ],
    "sg:phone":"+44 20 8443 2143",
    "sg:postcode":"EN3 5SU",
    "sg:province":"Greater London",
    "sg:tags":[
        "broker"
    ],
    "wof:name":"Tangent Insurance Brokers Ltd.",
    "wof:placetype":"venue"
},
  "geometry": {"coordinates":[-0.041511,51.669037],"type":"Point"}
}