{
  "type": "Feature",
  "properties": {
    "iso:country":"GB",
    "sg:address":"1 Pinfold Street",
    "sg:city":"Birmingham",
    "sg:classifiers":[
        {
            "category":"Government",
            "subcategory":"Post Office",
            "type":"Public Place"
        }
    ],
    "sg:phone":"+44 845 722 3344",
    "sg:postcode":"B2 4AA",
    "sg:province":"West Midlands",
    "wof:name":"Post Office Ltd",
    "wof:placetype":"venue"
},
  "geometry": {"coordinates":[-1.901968,52.478962],"type":"Point"}
}