{
  "type": "Feature",
  "properties": {
    "addr:full":"179 Silverdale Road Tunbridge Wells Kent TN4 9HT",
    "addr:housenumber":"179",
    "addr:postcode":"tn4 9ht",
    "addr:street":"Silverdale Road",
    "iso:country":"GB",
    "sg:address":"179 Silverdale Road",
    "sg:city":"Tunbridge Wells",
    "sg:classifiers":[
        {
            "category":"Shopping",
            "subcategory":"News",
            "type":"Retail Goods"
        }
    ],
    "sg:phone":"+44 1892 524327",
    "sg:postcode":"TN4 9HT",
    "sg:province":"Kent",
    "sg:tags":[
        "newsagent"
    ],
    "wof:name":"Silverdale News",
    "wof:placetype":"venue"
},
  "geometry": {"coordinates":[0.2741949856,51.1470298767],"type":"Point"}
}