{
  "type": "Feature",
  "properties": {
    "addr:full":"282 Manchester Rd Bolton Lancashire BL3 2QS",
    "addr:housenumber":"282",
    "addr:postcode":"bl3 2qs",
    "addr:street":"Manchester Rd",
    "iso:country":"GB",
    "sg:address":"282 Manchester Rd",
    "sg:city":"Bolton",
    "sg:classifiers":[
        {
            "category":"Military Area",
            "subcategory":"Air Force Base",
            "type":"Public Place"
        }
    ],
    "sg:phone":"+44 1204 399800",
    "sg:postcode":"BL3 2QS",
    "sg:province":"Lancashire",
    "sg:tags":[
        "taxi",
        "hire",
        "private"
    ],
    "wof:name":"Zodiac Cars",
    "wof:placetype":"venue"
},
  "geometry": {"coordinates":[-2.418077,53.568333],"type":"Point"}
}