{
  "type": "Feature",
  "properties": {
    "addr:full":"258 Fulham Road London Greater London SW10 9EL",
    "addr:housenumber":"258",
    "addr:postcode":"sw10 9el",
    "addr:street":"Fulham Road",
    "iso:country":"GB",
    "sg:address":"258 Fulham Road",
    "sg:city":"London",
    "sg:classifiers":[
        {
            "category":"Shopping",
            "subcategory":"Computers & Home Electronics",
            "type":"Retail Goods"
        }
    ],
    "sg:phone":"+44 20 7352 8496",
    "sg:postcode":"SW10 9EL",
    "sg:province":"Greater London",
    "sg:tags":[
        "hi-fi",
        "centre"
    ],
    "wof:name":"Richer Sounds Plc",
    "wof:placetype":"venue"
},
  "geometry": {"coordinates":[-0.1835969985,51.4845657349],"type":"Point"}
}