{
  "type": "Feature",
  "properties": {
    "addr:full":"16 Woodland Rd Cwmbran Monmouthshire NP44 2DZ",
    "addr:housenumber":"16",
    "addr:postcode":"np44 2dz",
    "addr:street":"Woodland Rd",
    "iso:country":"GB",
    "sg:address":"16 Woodland Rd",
    "sg:city":"Cwmbran",
    "sg:classifiers":[
        {
            "category":"Health Services",
            "subcategory":"Nursing And Care Facility",
            "type":"Services"
        }
    ],
    "sg:phone":"+44 1633 873299",
    "sg:postcode":"NP44 2DZ",
    "sg:province":"Monmouthshire",
    "sg:tags":[
        "home"
    ],
    "wof:name":"Woodlands 2 Nursing Home",
    "wof:placetype":"venue"
},
  "geometry": {"coordinates":[-3.011983,51.658585],"type":"Point"}
}