{
  "type": "Feature",
  "properties": {
    "addr:full":"West Acre Bradley Green, Spon Lane, Grendon Atherstone Leicestershire CV9 3DN",
    "addr:postcode":"cv9 3dn",
    "addr:street":"Bradley Green Spon Lane",
    "iso:country":"GB",
    "sg:address":"West Acre Bradley Green, Spon Lane, Grendon",
    "sg:city":"Atherstone",
    "sg:classifiers":[
        {
            "category":"Building & Trades",
            "subcategory":"Construction",
            "type":"Services"
        }
    ],
    "sg:phone":"+44 1827 713068",
    "sg:postcode":"CV9 3DN",
    "sg:province":"Leicestershire",
    "sg:tags":[
        "joiner",
        "carpenter"
    ],
    "wof:name":"N G Pallett Carpenter & Joiner",
    "wof:placetype":"venue"
},
  "geometry": {"coordinates":[-1.58092,52.598652],"type":"Point"}
}