{
  "type": "Feature",
  "properties": {
    "addr:full":"171 Cherry Hinton Road, Cambridge Cambridge Cambridgeshire CB1 7BX",
    "addr:housenumber":"171",
    "addr:postcode":"cb1 7bx",
    "addr:street":"Cherry Hinton Road",
    "iso:country":"GB",
    "sg:address":"171 Cherry Hinton Road, Cambridge",
    "sg:city":"Cambridge",
    "sg:classifiers":[
        {
            "category":"Organizations",
            "subcategory":"Membership Organization",
            "type":"Services"
        }
    ],
    "sg:postcode":"CB1 7BX",
    "sg:province":"Cambridgeshire",
    "sg:tags":[
        "club"
    ],
    "wof:name":"Turnstone Management Services Ltd",
    "wof:placetype":"venue"
},
  "geometry": {"coordinates":[0.1447079927,52.188129425],"type":"Point"}
}