{
  "type": "Feature",
  "properties": {
    "iso:country":"GB",
    "sg:address":"44 Bath Hill, Keynsham",
    "sg:city":"Bristol",
    "sg:classifiers":[
        {
            "category":"Banks & Credit Unions",
            "subcategory":"Financial Services",
            "type":"Services"
        }
    ],
    "sg:postcode":"BS31 1HG",
    "sg:province":"City of Bristol",
    "sg:tags":[
        "adviser"
    ],
    "wof:name":"David Wall",
    "wof:placetype":"venue"
},
  "geometry": {"coordinates":[-2.4967989922,51.4144134521],"type":"Point"}
}