{
  "type": "Feature",
  "properties": {
    "addr:full":"Newtown La Cradley Heath West Midlands B64 5EA",
    "addr:postcode":"b64 5ea",
    "iso:country":"GB",
    "sg:address":"Newtown La",
    "sg:city":"Cradley Heath",
    "sg:classifiers":[
        {
            "category":"Manufacturing",
            "subcategory":"Building Materials",
            "type":"Manufacturing & Wholesale Goods"
        }
    ],
    "sg:phone":"+44 1384 569113",
    "sg:postcode":"B64 5EA",
    "sg:province":"West Midlands",
    "sg:tags":[
        "merchant",
        "builder"
    ],
    "wof:name":"Hollibuild Builders Merchants Ltd",
    "wof:placetype":"venue"
},
  "geometry": {"coordinates":[-2.079734087,52.4736251831],"type":"Point"}
}