{
  "type": "Feature",
  "properties": {
    "addr:full":"14 Falkirk Close Hornchurch Essex RM11 3QJ",
    "addr:housenumber":"14",
    "addr:postcode":"rm11 3qj",
    "addr:street":"Falkirk Close",
    "iso:country":"GB",
    "sg:address":"14 Falkirk Close",
    "sg:city":"Hornchurch",
    "sg:classifiers":[
        {
            "category":"Professional",
            "type":"Services"
        }
    ],
    "sg:phone":"+44 1708 476446",
    "sg:postcode":"RM11 3QJ",
    "sg:province":"Essex",
    "sg:tags":[
        "reflexologists"
    ],
    "wof:name":"Baxter Lisa",
    "wof:placetype":"venue"
},
  "geometry": {"coordinates":[0.238219,51.56105],"type":"Point"}
}