{
  "type": "Feature",
  "properties": {
    "addr:full":"2 Preston Road Yeovil Somerset BA21 3AA",
    "addr:housenumber":"2",
    "addr:postcode":"ba21 3aa",
    "addr:street":"Preston Road",
    "iso:country":"GB",
    "sg:address":"2 Preston Road",
    "sg:city":"Yeovil",
    "sg:classifiers":[
        {
            "category":"Bars & Pubs",
            "type":"Food & Drink"
        }
    ],
    "sg:postcode":"BA21 3AA",
    "sg:province":"Somerset",
    "sg:tags":[
        "pubs",
        "inn"
    ],
    "wof:name":"Somerset Inn",
    "wof:placetype":"venue"
},
  "geometry": {"coordinates":[-2.638698,50.946167],"type":"Point"}
}