{
  "type": "Feature",
  "properties": {
    "addr:full":"77 Brecon Rd Aberdare Neath Port Talbot CF44 9NL",
    "addr:housenumber":"77",
    "addr:postcode":"cf44 9nl",
    "addr:street":"Brecon Rd",
    "iso:country":"GB",
    "sg:address":"77 Brecon Rd",
    "sg:city":"Aberdare",
    "sg:classifiers":[
        {
            "category":"Personal",
            "subcategory":"Beauty Salon",
            "type":"Services"
        }
    ],
    "sg:phone":"+44 1685 813311",
    "sg:postcode":"CF44 9NL",
    "sg:province":"Neath Port Talbot",
    "sg:tags":[
        "unisex",
        "hairdresser"
    ],
    "wof:name":"Scissors Hairdressers",
    "wof:placetype":"venue"
},
  "geometry": {"coordinates":[-3.513321,51.739285],"type":"Point"}
}