{
  "type": "Feature",
  "properties": {
    "addr:full":"Office 39 Centurian House, Centurian Way Preston Lancashire PR5 2GR",
    "addr:housenumber":"39 centurian house",
    "addr:postcode":"pr5 2gr",
    "addr:street":"Centurian Way",
    "iso:country":"GB",
    "sg:address":"Office 39 Centurian House, Centurian Way",
    "sg:city":"Preston",
    "sg:classifiers":[
        {
            "category":"Communications",
            "type":"Services"
        }
    ],
    "sg:phone":"+44 1772 458300",
    "sg:postcode":"PR5 2GR",
    "sg:province":"Lancashire",
    "sg:tags":[
        "audio-visual"
    ],
    "wof:name":"Video Solutions",
    "wof:placetype":"venue"
},
  "geometry": {"coordinates":[-2.63084,53.745762],"type":"Point"}
}