{
  "type": "Feature",
  "properties": {
    "iso:country":"GB",
    "sg:address":"109 Nutcroft Gro, Fetcham",
    "sg:city":"Leatherhead",
    "sg:classifiers":[
        {
            "category":"Real Estate",
            "subcategory":"Developer",
            "type":"Services"
        }
    ],
    "sg:phone":"+44 1372 372334",
    "sg:postcode":"KT22 9LD",
    "sg:province":"Surrey",
    "sg:tags":[
        "calligrapher"
    ],
    "wof:name":"Marie Lynskey",
    "wof:placetype":"venue"
},
  "geometry": {"coordinates":[-0.3514649868,51.2958335876],"type":"Point"}
}