{
  "type": "Feature",
  "properties": {
    "iso:country":"GB",
    "sg:address":"95 Fenchurch Street",
    "sg:city":"London",
    "sg:classifiers":[
        {
            "category":"Deli",
            "type":"Food & Drink"
        }
    ],
    "sg:phone":"+44 20 7702 9003",
    "sg:postcode":"EC3M 5JB",
    "sg:province":"Greater London",
    "sg:tags":[
        "delivery",
        "sandwich"
    ],
    "wof:name":"Remy's",
    "wof:placetype":"venue"
},
  "geometry": {"coordinates":[-0.0780259967,51.5132064819],"type":"Point"}
}