{
  "type": "Feature",
  "properties": {
    "addr:full":"Unit 15 Friendship Mill, Whalley Road, Read Burnley Lancashire BB12 7PN",
    "addr:housenumber":"unit 15",
    "addr:postcode":"bb12 7pn",
    "addr:street":"Friendship Mill Whalley Road",
    "iso:country":"GB",
    "sg:address":"Unit 15 Friendship Mill, Whalley Road, Read",
    "sg:city":"Burnley",
    "sg:classifiers":[
        {
            "category":"Manufacturing",
            "subcategory":"Metals",
            "type":"Manufacturing & Wholesale Goods"
        }
    ],
    "sg:phone":"+44 1282 773156",
    "sg:postcode":"BB12 7PN",
    "sg:province":"Lancashire",
    "sg:tags":[
        "work",
        "sheet"
    ],
    "wof:name":"John Oldcorne",
    "wof:placetype":"venue"
},
  "geometry": {"coordinates":[-2.3510639668,53.8066482544],"type":"Point"}
}