{
  "type": "Feature",
  "properties": {
    "iso:country":"GB",
    "sg:address":"Auchinraith Avenue",
    "sg:city":"Hamilton",
    "sg:classifiers":[
        {
            "category":"Education",
            "subcategory":"School",
            "type":"Public Place"
        },
        {
            "category":"Government",
            "subcategory":"Office",
            "type":"Public Place"
        }
    ],
    "sg:phone":"+44 1698 423200",
    "sg:postcode":"ML3 0JQ",
    "sg:province":"South Lanarkshire",
    "sg:tags":[
        "local",
        "authority"
    ],
    "wof:name":"Beckford Primary School",
    "wof:placetype":"venue"
},
  "geometry": {"coordinates":[-4.060474,55.785416],"type":"Point"}
}