{
  "type": "Feature",
  "properties": {
    "addr:full":"22 Wallgate Wigan Lancashire WN1 1JU",
    "addr:housenumber":"22",
    "addr:postcode":"wn1 1ju",
    "addr:street":"Wallgate Wigan",
    "iso:country":"GB",
    "sg:address":"22 Wallgate",
    "sg:city":"Wigan",
    "sg:classifiers":[
        {
            "category":"Education",
            "subcategory":"Special Training",
            "type":"Public Place"
        }
    ],
    "sg:postcode":"WN1 1JU",
    "sg:province":"Lancashire",
    "sg:tags":[
        "product",
        "centre"
    ],
    "wof:name":"Future Business College",
    "wof:placetype":"venue"
},
  "geometry": {"coordinates":[-2.63226,53.545547],"type":"Point"}
}