{
  "type": "Feature",
  "properties": {
    "addr:full":"24 White Hart Lane, Tottenham London Greater London N17 8DP",
    "addr:housenumber":"24",
    "addr:postcode":"n17 8dp",
    "addr:street":"White Hart Lane",
    "iso:country":"GB",
    "sg:address":"24 White Hart Lane, Tottenham",
    "sg:city":"London",
    "sg:classifiers":[
        {
            "category":"Personal",
            "subcategory":"Tattoo Parlor",
            "type":"Services"
        }
    ],
    "sg:phone":"+44 20 8880 3785",
    "sg:postcode":"N17 8DP",
    "sg:province":"Greater London",
    "sg:tags":[
        "tattooing",
        "piercing",
        "artist"
    ],
    "wof:name":"White Hart Tattoo Studios",
    "wof:placetype":"venue"
},
  "geometry": {"coordinates":[-0.0699,51.6054],"type":"Point"}
}