{
  "type": "Feature",
  "properties": {
    "addr:full":"5 Netherhampton Cottages, Netherhampton Road, Netherhampton Salisbury Wiltshire SP2 8PX",
    "addr:housenumber":"5",
    "addr:postcode":"sp2 8px",
    "addr:street":"Netherhampton;Netherhampton Road",
    "iso:country":"GB",
    "sg:address":"5 Netherhampton Cottages, Netherhampton Road, Netherhampton",
    "sg:city":"Salisbury",
    "sg:classifiers":[
        {
            "category":"Recreation",
            "subcategory":"Gun Range",
            "type":"Entertainment"
        }
    ],
    "sg:phone":"+44 1722 741123",
    "sg:postcode":"SP2 8PX",
    "sg:province":"Wiltshire",
    "sg:tags":[
        "operator",
        "tour"
    ],
    "wof:name":"Discover Adventure Ltd.",
    "wof:placetype":"venue"
},
  "geometry": {"coordinates":[-1.8490840197,51.0673484802],"type":"Point"}
}