{
  "type": "Feature",
  "properties": {
    "iso:country":"GB",
    "sg:address":"The Studio Cartland Road, Kings Heath",
    "sg:city":"Birmingham",
    "sg:classifiers":[
        {
            "category":"Home & Garden",
            "subcategory":"Building Materials",
            "type":"Retail Goods"
        }
    ],
    "sg:phone":"+44 121 444 0101",
    "sg:postcode":"B14 7NS",
    "sg:province":"West Midlands",
    "sg:tags":[
        "furnishers",
        "bathroom",
        "planner"
    ],
    "wof:name":"Designer Bathrooms by Michael",
    "wof:placetype":"venue"
},
  "geometry": {"coordinates":[-1.9086040258,52.4785957336],"type":"Point"}
}