{
  "type": "Feature",
  "properties": {
    "addr:full":"Unit 18, Railway Rd Skelmersdale Lancashire WN8 8TL",
    "addr:housenumber":"unit 18",
    "addr:postcode":"wn8 8tl",
    "addr:street":"Railway Rd",
    "iso:country":"GB",
    "sg:address":"Unit 18, Railway Rd",
    "sg:city":"Skelmersdale",
    "sg:classifiers":[
        {
            "category":"Train Station",
            "subcategory":"Rail",
            "type":"Transportation"
        }
    ],
    "sg:phone":"+44 1695 733588",
    "sg:postcode":"WN8 8TL",
    "sg:province":"Lancashire",
    "sg:tags":[
        "caravan"
    ],
    "wof:name":"Hitch Hog",
    "wof:placetype":"venue"
},
  "geometry": {"coordinates":[-2.787447,53.546825],"type":"Point"}
}