{
  "type": "Feature",
  "properties": {
    "iso:country":"GB",
    "sg:address":"248 Wragby Road",
    "sg:city":"Lincoln",
    "sg:classifiers":[
        {
            "category":"Government",
            "subcategory":"Post Office",
            "type":"Public Place"
        }
    ],
    "sg:postcode":"LN2 4PX",
    "sg:province":"Lincolnshire",
    "wof:name":"St.Giles Post Office",
    "wof:placetype":"venue"
},
  "geometry": {"coordinates":[-0.515014,53.240955],"type":"Point"}
}