{
  "type": "Feature",
  "properties": {
    "iso:country":"GB",
    "sg:address":"3 Claremount Terrace",
    "sg:city":"Glasgow",
    "sg:classifiers":[
        {
            "category":"Real Estate",
            "subcategory":"Surveying",
            "type":"Services"
        }
    ],
    "sg:postcode":"G3 7XR",
    "sg:province":"Glasgow City",
    "sg:tags":[
        "surveyor",
        "quantity"
    ],
    "wof:name":"Thomas J Ross",
    "wof:placetype":"venue"
},
  "geometry": {"coordinates":[-4.277613,55.867619],"type":"Point"}
}