{
  "type": "Feature",
  "properties": {
    "iso:country":"GB",
    "sg:address":"Chapel Lane",
    "sg:city":"Louth",
    "sg:classifiers":[
        {
            "category":"Manufacturing",
            "subcategory":"Glass & Minerals",
            "type":"Manufacturing & Wholesale Goods"
        }
    ],
    "sg:postcode":"LN11 8HQ",
    "sg:province":"Lincolnshire",
    "sg:tags":[
        "mnfrs",
        "fibre"
    ],
    "wof:name":"Trevor Carpenter",
    "wof:placetype":"venue"
},
  "geometry": {"coordinates":[0.0555289984,53.3379440308],"type":"Point"}
}