{
  "type": "Feature",
  "properties": {
    "addr:full":"40 Ostley Views London Greater London W5 2HH",
    "addr:housenumber":"40",
    "addr:postcode":"w5 2hh",
    "addr:street":"Ostley Views",
    "iso:country":"GB",
    "sg:address":"40 Ostley Views",
    "sg:city":"London",
    "sg:classifiers":[
        {
            "category":"Professional",
            "subcategory":"Business Services",
            "type":"Services"
        }
    ],
    "sg:phone":"+44 20 7223 7802",
    "sg:postcode":"W5 2HH",
    "sg:province":"Greater London",
    "sg:tags":[
        "import",
        "export",
        "agent"
    ],
    "wof:name":"Park Lloyd International Ltd.",
    "wof:placetype":"venue"
},
  "geometry": {"coordinates":[-0.3062300086,51.5174217224],"type":"Point"}
}