{
  "type": "Feature",
  "properties": {
    "iso:country":"GB",
    "sg:address":"146 New St, Telford Centre, Town Centre",
    "sg:city":"Telford",
    "sg:classifiers":[
        {
            "category":"Shopping",
            "subcategory":"Catalog Store",
            "type":"Retail Goods"
        }
    ],
    "sg:phone":"+44 1952 201836",
    "sg:postcode":"TF3 4BP",
    "sg:province":"Shropshire",
    "sg:tags":[
        "catalogue",
        "showroom"
    ],
    "wof:name":"Index The Catalogue Shop",
    "wof:placetype":"venue"
},
  "geometry": {"coordinates":[-2.444159,52.673939],"type":"Point"}
}