{
  "type": "Feature",
  "properties": {
    "iso:country":"GB",
    "sg:address":"Burkitts Lane",
    "sg:city":"Sudbury",
    "sg:classifiers":[
        {
            "category":"Retail",
            "subcategory":"Auto Repair",
            "type":"Services"
        }
    ],
    "sg:postcode":"CO10 1HB",
    "sg:province":"Essex",
    "sg:tags":[
        "modification",
        "garage"
    ],
    "wof:name":"S Roberts",
    "wof:placetype":"venue"
},
  "geometry": {"coordinates":[0.729136,52.039047],"type":"Point"}
}