{
  "type": "Feature",
  "properties": {
    "iso:country":"GB",
    "sg:address":"81 Kenneth Road",
    "sg:city":"Basildon",
    "sg:classifiers":[
        {
            "category":"Building & Trades",
            "subcategory":"Landscaping Services",
            "type":"Services"
        }
    ],
    "sg:postcode":"SS13 2BW",
    "sg:province":"Essex",
    "sg:tags":[
        "landscape",
        "contractor"
    ],
    "wof:name":"Ronald Brown Landscapes",
    "wof:placetype":"venue"
},
  "geometry": {"coordinates":[0.514123,51.574093],"type":"Point"}
}