{
  "type": "Feature",
  "properties": {
    "addr:full":"35 High Street Loughborough Leicestershire LE11 2PZ",
    "addr:housenumber":"35",
    "addr:postcode":"le11 2pz",
    "addr:street":"High Street",
    "iso:country":"GB",
    "sg:address":"35 High Street",
    "sg:city":"Loughborough",
    "sg:classifiers":[
        {
            "category":"Health Services",
            "subcategory":"Optometrist",
            "type":"Services"
        }
    ],
    "sg:phone":"+44 1509 260023",
    "sg:postcode":"LE11 2PZ",
    "sg:province":"Leicestershire",
    "sg:tags":[
        "optician"
    ],
    "wof:name":"Jeremy Haynes",
    "wof:placetype":"venue"
},
  "geometry": {"coordinates":[-1.205619,52.771626],"type":"Point"}
}