{
  "type": "Feature",
  "properties": {
    "addr:full":"104a Main St Leicester Leicestershire LE9 2AP",
    "addr:housenumber":"104a",
    "addr:postcode":"le9 2ap",
    "addr:street":"Main St",
    "iso:country":"GB",
    "sg:address":"104a Main St",
    "sg:city":"Leicester",
    "sg:classifiers":[
        {
            "category":"Personal",
            "subcategory":"Beauty Salon",
            "type":"Services"
        }
    ],
    "sg:phone":"+44 116 239 5987",
    "sg:postcode":"LE9 2AP",
    "sg:province":"Leicestershire",
    "sg:tags":[
        "lady",
        "hairdresser"
    ],
    "wof:name":"Alison Mobile",
    "wof:placetype":"venue"
},
  "geometry": {"coordinates":[-1.228779,52.637825],"type":"Point"}
}