{
  "type": "Feature",
  "properties": {
    "addr:full":"Canon House, Canon Street Kettering Northamptonshire NN16 8RE",
    "addr:postcode":"nn16 8re",
    "addr:street":"Canon Street",
    "iso:country":"GB",
    "sg:address":"Canon House, Canon Street",
    "sg:city":"Kettering",
    "sg:classifiers":[
        {
            "category":"Shopping",
            "subcategory":"Mobile Phones",
            "type":"Retail Goods"
        },
        {
            "category":"Communications",
            "type":"Services"
        }
    ],
    "sg:phone":"+44 1536 310875",
    "sg:postcode":"NN16 8RE",
    "sg:province":"Northamptonshire",
    "sg:tags":[
        "telecommunication"
    ],
    "wof:name":"Jade Communications",
    "wof:placetype":"venue"
},
  "geometry": {"coordinates":[-0.7232080102,52.4028015137],"type":"Point"}
}