{
  "type": "Feature",
  "properties": {
    "iso:country":"GB",
    "sg:address":"120 West Park Drive",
    "sg:city":"Porthcawl",
    "sg:classifiers":[
        {
            "category":"Real Estate",
            "subcategory":"Architect",
            "type":"Services"
        }
    ],
    "sg:phone":"+44 1656 784445",
    "sg:postcode":"CF36 3RN",
    "sg:province":"Bridgend",
    "wof:name":"Arthur P Millis",
    "wof:placetype":"venue"
},
  "geometry": {"coordinates":[-3.7088739872,51.4921112061],"type":"Point"}
}