{
  "type": "Feature",
  "properties": {
    "addr:full":"9 Edith Street Consett Durham DH8 5DN",
    "addr:housenumber":"9",
    "addr:postcode":"dh8 5dn",
    "addr:street":"Edith Street",
    "iso:country":"GB",
    "sg:address":"9 Edith Street",
    "sg:city":"Consett",
    "sg:classifiers":[
        {
            "category":"Personal",
            "type":"Services"
        }
    ],
    "sg:phone":"+44 1207 581424",
    "sg:postcode":"DH8 5DN",
    "sg:province":"Durham",
    "sg:tags":[
        "dressmaker"
    ],
    "wof:name":"Stitches",
    "wof:placetype":"venue"
},
  "geometry": {"coordinates":[-1.8354389668,54.8528556824],"type":"Point"}
}