{
  "type": "Feature",
  "properties": {
    "iso:country":"GB",
    "sg:address":"41 Portland Street",
    "sg:city":"Edinburgh",
    "sg:classifiers":[
        {
            "category":"Government",
            "subcategory":"Office",
            "type":"Public Place"
        }
    ],
    "sg:phone":"+44 131 554 3784",
    "sg:postcode":"EH6 4BB",
    "sg:province":"City of Edinburgh",
    "sg:tags":[
        "central"
    ],
    "wof:name":"Cauvin House Orphange",
    "wof:placetype":"venue"
},
  "geometry": {"coordinates":[-3.1825399399,55.9772720337],"type":"Point"}
}