{
  "type": "Feature",
  "properties": {
    "addr:full":"52 Alexander Drive, Timperley Altrincham Cheshire WA15 6NH",
    "addr:housenumber":"52",
    "addr:postcode":"wa15 6nh",
    "addr:street":"Alexander Drive",
    "iso:country":"GB",
    "sg:address":"52 Alexander Drive, Timperley",
    "sg:city":"Altrincham",
    "sg:classifiers":[
        {
            "category":"Professional",
            "subcategory":"Detective & Security Services",
            "type":"Services"
        }
    ],
    "sg:phone":"+44 161 980 8191",
    "sg:postcode":"WA15 6NH",
    "sg:province":"Cheshire",
    "sg:tags":[
        "alarm",
        "burglar",
        "system"
    ],
    "wof:name":"S Milne",
    "wof:placetype":"venue"
},
  "geometry": {"coordinates":[-2.3291409016,53.3966636658],"type":"Point"}
}