{
  "type": "Feature",
  "properties": {
    "addr:full":"Southcote Road Bournemouth Dorset BH1 3SH",
    "addr:postcode":"bh1 3sh",
    "addr:street":"Southcote Road",
    "iso:country":"GB",
    "sg:address":"Southcote Road",
    "sg:city":"Bournemouth",
    "sg:classifiers":[
        {
            "category":"Retail",
            "subcategory":"Auto Repair",
            "type":"Services"
        }
    ],
    "sg:phone":"+44 1202 552222",
    "sg:postcode":"BH1 3SH",
    "sg:province":"Dorset",
    "sg:tags":[
        "modification",
        "garage"
    ],
    "wof:name":"J Shergold Motor Repairs",
    "wof:placetype":"venue"
},
  "geometry": {"coordinates":[-1.8516039848,50.726978302],"type":"Point"}
}