{
  "type": "Feature",
  "properties": {
    "addr:full":"9 Priory Road Durham Durham DH1 5JG",
    "addr:housenumber":"9",
    "addr:postcode":"dh1 5jg",
    "addr:street":"Priory Road",
    "iso:country":"GB",
    "sg:address":"9 Priory Road",
    "sg:city":"Durham",
    "sg:classifiers":[
        {
            "category":"Food & Beverages",
            "subcategory":"Fruits & Vegetables",
            "type":"Retail Goods"
        }
    ],
    "sg:phone":"+44 191 386 5324",
    "sg:postcode":"DH1 5JG",
    "sg:province":"Durham",
    "sg:tags":[
        "greengrocer"
    ],
    "wof:name":"V Cummins",
    "wof:placetype":"venue"
},
  "geometry": {"coordinates":[-1.583401,54.794998],"type":"Point"}
}