{
  "type": "Feature",
  "properties": {
    "iso:country":"GB",
    "sg:address":"71 High Street, Langford",
    "sg:city":"Biggleswade",
    "sg:classifiers":[
        {
            "category":"Food & Beverages",
            "subcategory":"Farmers Market",
            "type":"Retail Goods"
        }
    ],
    "sg:phone":"+44 1462 700269",
    "sg:postcode":"SG18 9RY",
    "sg:province":"Bedfordshire",
    "sg:tags":[
        "gardener"
    ],
    "wof:name":"F C Huckle & Son",
    "wof:placetype":"venue"
},
  "geometry": {"coordinates":[-0.2905830145,52.0741004944],"type":"Point"}
}