{
  "type": "Feature",
  "properties": {
    "addr:full":"Primrose Farm, 77 Skelmersdale Road Skelmersdale Lancashire WN8 8BU",
    "addr:housenumber":"77",
    "addr:postcode":"wn8 8bu",
    "addr:street":"Skelmersdale Road",
    "iso:country":"GB",
    "sg:address":"Primrose Farm, 77 Skelmersdale Road",
    "sg:city":"Skelmersdale",
    "sg:classifiers":[
        {
            "category":"Farming",
            "subcategory":"Livestock Farm",
            "type":"Manufacturing & Wholesale Goods"
        }
    ],
    "sg:phone":"+44 1695 722788",
    "sg:postcode":"WN8 8BU",
    "sg:province":"Lancashire",
    "sg:tags":[
        "others"
    ],
    "wof:name":"L Birchall",
    "wof:placetype":"venue"
},
  "geometry": {"coordinates":[-2.775784,53.549404],"type":"Point"}
}