{
  "type": "Feature",
  "properties": {
    "addr:full":"24 Ashley Drive, Bramhall Stockport Cheshire SK7 1EW",
    "addr:housenumber":"24",
    "addr:postcode":"sk7 1ew",
    "addr:street":"Ashley Drive",
    "iso:country":"GB",
    "sg:address":"24 Ashley Drive, Bramhall",
    "sg:city":"Stockport",
    "sg:classifiers":[
        {
            "category":"Social Services",
            "subcategory":"Job Training",
            "type":"Services"
        }
    ],
    "sg:phone":"+44 161 439 6555",
    "sg:postcode":"SK7 1EW",
    "sg:province":"Cheshire",
    "sg:tags":[
        "translator",
        "interpreter"
    ],
    "wof:name":"A Fine Line",
    "wof:placetype":"venue"
},
  "geometry": {"coordinates":[-2.1735920906,53.3580970764],"type":"Point"}
}