{
  "type": "Feature",
  "properties": {
    "addr:full":"Low Farm, 5 Main Rd, Marsh Lane Sheffield Derbyshire S21 5RH",
    "addr:housenumber":"5",
    "addr:postcode":"s21 5rh",
    "addr:street":"Main Rd Marsh Lane",
    "iso:country":"GB",
    "sg:address":"Low Farm, 5 Main Rd, Marsh Lane",
    "sg:city":"Sheffield",
    "sg:classifiers":[
        {
            "category":"Autos & Motor Vehicles",
            "subcategory":"Auto Supplies",
            "type":"Retail Goods"
        }
    ],
    "sg:phone":"+44 1246 435328",
    "sg:postcode":"S21 5RH",
    "sg:province":"Derbyshire",
    "sg:tags":[
        "windscreen"
    ],
    "wof:name":"All Repairs At Home Or Work",
    "wof:placetype":"venue"
},
  "geometry": {"coordinates":[-1.3925089836,53.3078155518],"type":"Point"}
}