{
  "type": "Feature",
  "properties": {
    "addr:full":"Springfield, Larkins Lane, Headington Oxford Oxfordshire OX3 9DW",
    "addr:postcode":"ox3 9dw",
    "addr:street":"Larkins Lane",
    "iso:country":"GB",
    "sg:address":"Springfield, Larkins Lane, Headington",
    "sg:city":"Oxford",
    "sg:classifiers":[
        {
            "category":"Health Services",
            "subcategory":"Podiatrist",
            "type":"Services"
        },
        {
            "category":"Health Services",
            "subcategory":"Chiropractor",
            "type":"Services"
        }
    ],
    "sg:phone":"+44 1865 742894",
    "sg:postcode":"OX3 9DW",
    "sg:province":"Oxfordshire",
    "sg:tags":[
        "podiatrists",
        "chiropodist"
    ],
    "wof:name":"ANTHONY ELLIOT-SMITH",
    "wof:placetype":"venue"
},
  "geometry": {"coordinates":[-1.2105799913,51.7653503418],"type":"Point"}
}