{
  "type": "Feature",
  "properties": {
    "addr:full":"37 Quakers Hall Lane Sevenoaks Kent TN13 3TX",
    "addr:housenumber":"37",
    "addr:postcode":"tn13 3tx",
    "addr:street":"Quakers Hall Lane",
    "iso:country":"GB",
    "sg:address":"37 Quakers Hall Lane",
    "sg:city":"Sevenoaks",
    "sg:classifiers":[
        {
            "category":"Retail",
            "subcategory":"Funeral Services",
            "type":"Services"
        }
    ],
    "sg:phone":"+44 1732 454457",
    "sg:postcode":"TN13 3TX",
    "sg:province":"Kent",
    "wof:name":"W Hodges",
    "wof:placetype":"venue"
},
  "geometry": {"coordinates":[0.1961760074,51.2828788757],"type":"Point"}
}