{
  "type": "Feature",
  "properties": {
    "addr:full":"28 Marlborough Road Richmond Greater London TW10 6JR",
    "addr:housenumber":"28",
    "addr:postcode":"tw10 6jr",
    "addr:street":"Marlborough Road",
    "iso:country":"GB",
    "sg:address":"28 Marlborough Road",
    "sg:city":"Richmond",
    "sg:classifiers":[
        {
            "category":"Professional",
            "subcategory":"Lawyer & Legal Services",
            "type":"Services"
        }
    ],
    "sg:postcode":"TW10 6JR",
    "sg:province":"Greater London",
    "sg:tags":[
        "solicitor"
    ],
    "wof:name":"The Centre for Law Reform Ltd",
    "wof:placetype":"venue"
},
  "geometry": {"coordinates":[-0.294811,51.454422],"type":"Point"}
}