{
  "type": "Feature",
  "properties": {
    "iso:country":"GB",
    "sg:address":"Circle House, 85 Cecil Street",
    "sg:city":"Birmingham",
    "sg:classifiers":[
        {
            "category":"Manufacturing",
            "subcategory":"Tools & Machinery",
            "type":"Manufacturing & Wholesale Goods"
        }
    ],
    "sg:phone":"+44 121 359 6499",
    "sg:postcode":"B19 3SU",
    "sg:province":"West Midlands",
    "sg:tags":[
        "society",
        "friendly"
    ],
    "wof:name":"Barnes & Co",
    "wof:placetype":"venue"
},
  "geometry": {"coordinates":[-1.8960189819,52.4893035889],"type":"Point"}
}