{
  "type": "Feature",
  "properties": {
    "addr:full":"10e Sun St Sandy Bedfordshire SG19 2LR",
    "addr:housenumber":"10e",
    "addr:postcode":"sg19 2lr",
    "addr:street":"Sun St",
    "iso:country":"GB",
    "sg:address":"10e Sun St",
    "sg:city":"Sandy",
    "sg:classifiers":[
        {
            "category":"Professional",
            "subcategory":"Art Services",
            "type":"Services"
        }
    ],
    "sg:phone":"+44 1767 262623",
    "sg:postcode":"SG19 2LR",
    "sg:province":"Bedfordshire",
    "sg:tags":[
        "model",
        "maker"
    ],
    "wof:name":"Trapp One",
    "wof:placetype":"venue"
},
  "geometry": {"coordinates":[-0.215049997,52.1273574829],"type":"Point"}
}