{
  "type": "Feature",
  "properties": {
    "addr:full":"Saxelby Rd Melton Mowbray Leicestershire LE14 3TU",
    "addr:postcode":"le14 3tu",
    "addr:street":"Saxelby Rd",
    "iso:country":"GB",
    "sg:address":"Saxelby Rd",
    "sg:city":"Melton Mowbray",
    "sg:classifiers":[
        {
            "category":"Sports & Exercise",
            "subcategory":"Stables",
            "type":"Entertainment"
        }
    ],
    "sg:phone":"+44 1664 813663",
    "sg:postcode":"LE14 3TU",
    "sg:province":"Leicestershire",
    "sg:tags":[
        "education",
        "equestrian"
    ],
    "wof:name":"Saxleby Stables",
    "wof:placetype":"venue"
},
  "geometry": {"coordinates":[-0.958498,52.767597],"type":"Point"}
}