{
  "type": "Feature",
  "properties": {
    "iso:country":"GB",
    "sg:address":"Kyrle House, Ashbrittle",
    "sg:city":"Wellington",
    "sg:classifiers":[
        {
            "category":"Manufacturing",
            "subcategory":"Wood Products",
            "type":"Manufacturing & Wholesale Goods"
        },
        {
            "category":"Building & Trades",
            "subcategory":"Electrical",
            "type":"Services"
        }
    ],
    "sg:phone":"+44 1823 672224",
    "sg:postcode":"TA21 0LJ",
    "sg:province":"Devon",
    "sg:tags":[
        "equipment",
        "lighting",
        "manufacturer"
    ],
    "wof:name":"Art in Lighting",
    "wof:placetype":"venue"
},
  "geometry": {"coordinates":[-3.2999489307,50.9844894409],"type":"Point"}
}