{
  "type": "Feature",
  "properties": {
    "addr:full":"23 Mapleton Close Bromley Kent BR2 9DU",
    "addr:housenumber":"23",
    "addr:postcode":"br2 9du",
    "addr:street":"Mapleton Close",
    "iso:country":"GB",
    "sg:address":"23 Mapleton Close",
    "sg:city":"Bromley",
    "sg:classifiers":[
        {
            "category":"Professional",
            "subcategory":"Computer Services",
            "type":"Services"
        }
    ],
    "sg:postcode":"BR2 9DU",
    "sg:province":"Kent",
    "sg:tags":[
        "system",
        "software"
    ],
    "wof:name":"Rumlink Ltd.",
    "wof:placetype":"venue"
},
  "geometry": {"coordinates":[0.0115379998,51.3894119263],"type":"Point"}
}