{
  "type": "Feature",
  "properties": {
    "addr:full":"The Rhyddings, Bradford Road, Burley-in-wharfedaleroad Ilkley North Yorkshire LS29 7QP",
    "addr:postcode":"ls29 7qp",
    "addr:street":"Bradford Road Burley-In-Wharfedaleroad",
    "iso:country":"GB",
    "sg:address":"The Rhyddings, Bradford Road, Burley-in-wharfedaleroad",
    "sg:city":"Ilkley",
    "sg:classifiers":[
        {
            "category":"Transit Center",
            "subcategory":"Passenger",
            "type":"Transportation"
        },
        {
            "category":"Retail",
            "subcategory":"Pet Boarding",
            "type":"Services"
        }
    ],
    "sg:phone":"+44 1943 872802",
    "sg:postcode":"LS29 7QP",
    "sg:province":"North Yorkshire",
    "sg:tags":[
        "kennel",
        "catteries"
    ],
    "wof:name":"The Rhyddings",
    "wof:placetype":"venue"
},
  "geometry": {"coordinates":[-1.821754,53.924461],"type":"Point"}
}