{
  "type": "Feature",
  "properties": {
    "addr:full":"Unit 2-3 Mayfield Farm, East Hardwick Pontefract North Yorkshire WF8 3EQ",
    "addr:housenumber":"unit 2-3;farm",
    "addr:postcode":"wf8 3eq",
    "addr:street":"Mayfield",
    "iso:country":"GB",
    "sg:address":"Unit 2-3 Mayfield Farm, East Hardwick",
    "sg:city":"Pontefract",
    "sg:classifiers":[
        {
            "category":"Professional",
            "subcategory":"Accounting & Tax Preparation",
            "type":"Services"
        }
    ],
    "sg:phone":"+44 1977 617322",
    "sg:postcode":"WF8 3EQ",
    "sg:province":"North Yorkshire",
    "sg:tags":[
        "accountant"
    ],
    "wof:name":"Ackworth Book-keeping Services",
    "wof:placetype":"venue"
},
  "geometry": {"coordinates":[-1.302604,53.660912],"type":"Point"}
}