{
  "type": "Feature",
  "properties": {
    "addr:full":"Hilltop Farm, Hall Road, Brockdish Diss Norfolk IP21 4JT",
    "addr:postcode":"ip21 4jt",
    "addr:street":"Hall Road",
    "iso:country":"GB",
    "sg:address":"Hilltop Farm, Hall Road, Brockdish",
    "sg:city":"Diss",
    "sg:classifiers":[
        {
            "category":"Wholesale",
            "subcategory":"Scrap",
            "type":"Manufacturing & Wholesale Goods"
        }
    ],
    "sg:postcode":"IP21 4JT",
    "sg:province":"Norfolk",
    "sg:tags":[
        "waste",
        "metal"
    ],
    "wof:name":"David Piper",
    "wof:placetype":"venue"
},
  "geometry": {"coordinates":[1.2411,52.368824],"type":"Point"}
}