{
  "type": "Feature",
  "properties": {
    "addr:full":"Edmundson House, Tatton Street Knutsford Cheshire WA16 6AY",
    "addr:postcode":"wa16 6ay",
    "addr:street":"Tatton Street",
    "iso:country":"GB",
    "sg:address":"Edmundson House, Tatton Street",
    "sg:city":"Knutsford",
    "sg:classifiers":[
        {
            "category":"Professional",
            "subcategory":"Business Services",
            "type":"Services"
        }
    ],
    "sg:postcode":"WA16 6AY",
    "sg:province":"Cheshire",
    "sg:tags":[
        "import",
        "export",
        "agent"
    ],
    "wof:name":"Edmundson Export Ltd.",
    "wof:placetype":"venue"
},
  "geometry": {"coordinates":[-2.3751440048,53.306804657],"type":"Point"}
}