{
  "type": "Feature",
  "properties": {
    "iso:country":"GB",
    "sg:address":"68 Gilwilly Road, Gilwilly Ndstl Estate",
    "sg:city":"Penrith",
    "sg:classifiers":[
        {
            "category":"Manufacturing",
            "subcategory":"Petroleum Products",
            "type":"Manufacturing & Wholesale Goods"
        }
    ],
    "sg:postcode":"CA11 9BL",
    "sg:province":"Cumbria",
    "sg:tags":[
        "double",
        "glazing"
    ],
    "wof:name":"Julie Gregson",
    "wof:placetype":"venue"
},
  "geometry": {"coordinates":[-2.7619490623,54.6670417786],"type":"Point"}
}