{
  "type": "Feature",
  "properties": {
    "iso:country":"GB",
    "sg:address":"Castle Ground, North Rd",
    "sg:city":"Cardiff",
    "sg:classifiers":[
        {
            "category":"Organizations",
            "subcategory":"Membership Organization",
            "type":"Services"
        }
    ],
    "sg:phone":"+44 29 2023 1216",
    "sg:postcode":"CF1 3ER",
    "sg:province":"Cardiff",
    "sg:tags":[
        "club"
    ],
    "wof:name":"Cardiff Lawn Tennis Club",
    "wof:placetype":"venue"
},
  "geometry": {"coordinates":[-3.18067,51.481258],"type":"Point"}
}