{
  "type": "Feature",
  "properties": {
    "addr:full":"4 Whiteness Green Broadstairs Kent CT10 3JS",
    "addr:housenumber":"4",
    "addr:postcode":"ct10 3js",
    "addr:street":"Whiteness Green",
    "iso:country":"GB",
    "sg:address":"4 Whiteness Green",
    "sg:city":"Broadstairs",
    "sg:classifiers":[
        {
            "category":"Shopping",
            "subcategory":"Bicycles & Sporting Goods",
            "type":"Retail Goods"
        }
    ],
    "sg:phone":"+44 1843 860308",
    "sg:postcode":"CT10 3JS",
    "sg:province":"Kent",
    "sg:tags":[
        "dance",
        "balletwear"
    ],
    "wof:name":"Jazz Hot Dancewear",
    "wof:placetype":"venue"
},
  "geometry": {"coordinates":[1.4313570261,51.3810310364],"type":"Point"}
}