{
  "type": "Feature",
  "properties": {
    "addr:full":"Westview, Pincents La, Tilehurst Reading Berkshire RG7 3NW",
    "addr:postcode":"rg7 3nw",
    "addr:street":"La Tilehurst",
    "iso:country":"GB",
    "sg:address":"Westview, Pincents La, Tilehurst",
    "sg:city":"Reading",
    "sg:classifiers":[
        {
            "category":"Building & Trades",
            "subcategory":"Construction",
            "type":"Services"
        }
    ],
    "sg:postcode":"RG7 3NW",
    "sg:province":"Berkshire",
    "sg:tags":[
        "builder"
    ],
    "wof:name":"Westview Loft Conversions",
    "wof:placetype":"venue"
},
  "geometry": {"coordinates":[-1.0586999655,51.4001502991],"type":"Point"}
}