{
  "type": "Feature",
  "properties": {
    "iso:country":"GB",
    "sg:address":"28-30 Hall Street",
    "sg:city":"Southport",
    "sg:classifiers":[
        {
            "category":"Professional",
            "subcategory":"Detective & Security Services",
            "type":"Services"
        },
        {
            "category":"Building & Trades",
            "subcategory":"Electrical",
            "type":"Services"
        }
    ],
    "sg:phone":"+44 800 389 1825",
    "sg:postcode":"PR9 0SE",
    "sg:province":"Lancashire",
    "sg:tags":[
        "burglar",
        "alarm",
        "electrician",
        "system",
        "contractor"
    ],
    "wof:name":"European Environmental Controls Ltd",
    "wof:placetype":"venue"
},
  "geometry": {"coordinates":[-2.9930551052,53.6462516785],"type":"Point"}
}