{
  "type": "Feature",
  "properties": {
    "iso:country":"GB",
    "sg:address":"Cusworth Hall, Cusworth",
    "sg:city":"Doncaster",
    "sg:classifiers":[
        {
            "category":"Cafe",
            "type":"Food & Drink"
        }
    ],
    "sg:phone":"+44 1302 390959",
    "sg:postcode":"DN5 7TU",
    "sg:province":"South Yorkshire",
    "sg:tags":[
        "tea",
        "snack",
        "bar",
        "room"
    ],
    "wof:name":"Cusworth Hall Tea Rooms",
    "wof:placetype":"venue"
},
  "geometry": {"coordinates":[-1.176652,53.530937],"type":"Point"}
}