{
  "type": "Feature",
  "properties": {
    "iso:country":"GB",
    "sg:address":"Unit A4",
    "sg:city":"Liverpool",
    "sg:classifiers":[
        {
            "category":"Building & Trades",
            "subcategory":"Construction",
            "type":"Services"
        }
    ],
    "sg:phone":"+44 151 357 7832",
    "sg:postcode":"L20 6PF",
    "sg:province":"Merseyside",
    "sg:tags":[
        "glass",
        "replacement"
    ],
    "wof:name":"Expo Security Ltd.",
    "wof:placetype":"venue"
},
  "geometry": {"coordinates":[-2.9946401119,53.4663505554],"type":"Point"}
}