{
  "type": "Feature",
  "properties": {
    "iso:country":"GB",
    "sg:address":"210 Dallow Road",
    "sg:city":"Luton",
    "sg:classifiers":[
        {
            "category":"Building & Trades",
            "subcategory":"Landscaping Services",
            "type":"Services"
        }
    ],
    "sg:postcode":"LU1 1NQ",
    "sg:province":"Bedfordshire",
    "sg:tags":[
        "design",
        "garden"
    ],
    "wof:name":"Concept Gardens",
    "wof:placetype":"venue"
},
  "geometry": {"coordinates":[-0.434822,51.8825],"type":"Point"}
}