{
  "type": "Feature",
  "properties": {
    "iso:country":"GB",
    "sg:address":"11 Chess Way",
    "sg:city":"Rickmansworth",
    "sg:classifiers":[
        {
            "category":"Farming",
            "subcategory":"Livestock Farm",
            "type":"Manufacturing & Wholesale Goods"
        }
    ],
    "sg:phone":"+44 1923 286000",
    "sg:postcode":"WD3 5TA",
    "sg:province":"Hertfordshire",
    "sg:tags":[
        "others"
    ],
    "wof:name":"Volaise Enterprises Ltd",
    "wof:placetype":"venue"
},
  "geometry": {"coordinates":[-0.495964,51.660637],"type":"Point"}
}