{
  "type": "Feature",
  "properties": {
    "addr:full":"Wigton Road Carlisle Cumbria CA5 6LG",
    "addr:postcode":"ca5 6lg",
    "addr:street":"Wigton Road",
    "iso:country":"GB",
    "sg:address":"Wigton Road",
    "sg:city":"Carlisle",
    "sg:classifiers":[
        {
            "category":"Autos & Motor Vehicles",
            "subcategory":"Fuel & Gas Station",
            "type":"Retail Goods"
        }
    ],
    "sg:postcode":"CA5 6LG",
    "sg:province":"Cumbria",
    "sg:tags":[
        "petrol",
        "filling"
    ],
    "wof:name":"Cardewlees Service Station",
    "wof:placetype":"venue"
},
  "geometry": {"coordinates":[-2.962029,54.887718],"type":"Point"}
}