{
  "type": "Feature",
  "properties": {
    "iso:country":"GB",
    "sg:address":"3 Leigham Hall Parade, Streatham High Road",
    "sg:city":"London",
    "sg:classifiers":[
        {
            "category":"Shopping",
            "subcategory":"Baby Store",
            "type":"Retail Goods"
        }
    ],
    "sg:postcode":"SW16 1DR",
    "sg:province":"Greater London",
    "sg:tags":[
        "babywear",
        "childrens"
    ],
    "wof:name":"Baby Boomer",
    "wof:placetype":"venue"
},
  "geometry": {"coordinates":[-0.1281089932,51.4357414246],"type":"Point"}
}