{
  "type": "Feature",
  "properties": {
    "iso:country":"GB",
    "sg:address":"8 Goldings Hill",
    "sg:city":"Loughton",
    "sg:classifiers":[
        {
            "category":"Building & Trades",
            "subcategory":"Construction",
            "type":"Services"
        }
    ],
    "sg:phone":"+44 20 8502 4752",
    "sg:postcode":"IG10 1LL",
    "sg:province":"Essex",
    "sg:tags":[
        "tiling",
        "contractor"
    ],
    "wof:name":"Supreme Planners",
    "wof:placetype":"venue"
},
  "geometry": {"coordinates":[0.0668239966,51.6578102112],"type":"Point"}
}