{
  "type": "Feature",
  "properties": {
    "addr:full":"26 Gloucester Street Stroud Gloucestershire GL5 1QG",
    "addr:housenumber":"26",
    "addr:postcode":"gl5 1qg",
    "addr:street":"Gloucester Street",
    "iso:country":"GB",
    "sg:address":"26 Gloucester Street",
    "sg:city":"Stroud",
    "sg:classifiers":[
        {
            "category":"Cafe",
            "type":"Food & Drink"
        }
    ],
    "sg:phone":"+44 1453 756745",
    "sg:postcode":"GL5 1QG",
    "sg:province":"Gloucestershire",
    "sg:tags":[
        "tea",
        "room"
    ],
    "wof:name":"The Door",
    "wof:placetype":"venue"
},
  "geometry": {"coordinates":[-2.2172970772,51.7467765808],"type":"Point"}
}