{
  "type": "Feature",
  "properties": {
    "addr:full":"39 Chipstead Valley Road Coulsdon Surrey CR5 2RB",
    "addr:housenumber":"39",
    "addr:postcode":"cr5 2rb",
    "addr:street":"Chipstead Valley Road",
    "iso:country":"GB",
    "sg:address":"39 Chipstead Valley Road",
    "sg:city":"Coulsdon",
    "sg:classifiers":[
        {
            "category":"Fast Food",
            "type":"Food & Drink"
        }
    ],
    "sg:phone":"+44 20 8763 9995",
    "sg:postcode":"CR5 2RB",
    "sg:province":"Surrey",
    "sg:tags":[
        "delivery"
    ],
    "wof:name":"Happy Swan Express Chinese Takeaway",
    "wof:placetype":"venue"
},
  "geometry": {"coordinates":[-0.139831,51.320263],"type":"Point"}
}