{
  "type": "Feature",
  "properties": {
    "addr:full":"Dental Surgery, 396 Anlaby Road Hull East Riding of Yorkshire HU3 6PB",
    "addr:housenumber":"396",
    "addr:postcode":"hu3 6pb",
    "addr:street":"Anlaby Road",
    "iso:country":"GB",
    "sg:address":"Dental Surgery, 396 Anlaby Road",
    "sg:city":"Hull",
    "sg:classifiers":[
        {
            "category":"Health Services",
            "subcategory":"Dentist",
            "type":"Services"
        }
    ],
    "sg:phone":"+44 1482 506004",
    "sg:postcode":"HU3 6PB",
    "sg:province":"East Riding of Yorkshire",
    "wof:name":"Christopher Ayer & Associates",
    "wof:placetype":"venue"
},
  "geometry": {"coordinates":[-0.37547,53.74387],"type":"Point"}
}