{
  "type": "Feature",
  "properties": {
    "addr:full":"A1 Kingsway Business Park, Oldfield Rd Hampton Greater London TW12 2HD",
    "addr:postcode":"tw12 2hd",
    "addr:street":"Business Park Oldfield Rd",
    "iso:country":"GB",
    "sg:address":"A1 Kingsway Business Park, Oldfield Rd",
    "sg:city":"Hampton",
    "sg:classifiers":[
        {
            "category":"Professional",
            "subcategory":"Detective & Security Services",
            "type":"Services"
        }
    ],
    "sg:phone":"+44 20 8941 1099",
    "sg:postcode":"TW12 2HD",
    "sg:province":"Greater London",
    "wof:name":"Pegasus Security Group Ltd",
    "wof:placetype":"venue"
},
  "geometry": {"coordinates":[-0.373679,51.417568],"type":"Point"}
}