{
  "type": "Feature",
  "properties": {
    "iso:country":"GB",
    "sg:address":", Avon Dassett",
    "sg:city":"Leamington Spa",
    "sg:classifiers":[
        {
            "category":"Manufacturing",
            "subcategory":"Glass & Minerals",
            "type":"Manufacturing & Wholesale Goods"
        }
    ],
    "sg:phone":"+44 1295 770067",
    "sg:postcode":"CV33 0AA",
    "sg:province":"Warwickshire",
    "sg:tags":[
        "chalk",
        "stone",
        "slate"
    ],
    "wof:name":"Avonhill Quarry",
    "wof:placetype":"venue"
},
  "geometry": {"coordinates":[-1.393616,52.165775],"type":"Point"}
}