{
  "type": "Feature",
  "properties": {
    "addr:full":"41 Woodhall Street, Chapelhall Airdrie North Lanarkshire ML6 8RR",
    "addr:housenumber":"41",
    "addr:postcode":"ml6 8rr",
    "addr:street":"Woodhall Street",
    "iso:country":"GB",
    "sg:address":"41 Woodhall Street, Chapelhall",
    "sg:city":"Airdrie",
    "sg:classifiers":[
        {
            "category":"Food & Beverages",
            "subcategory":"Supermarket",
            "type":"Retail Goods"
        }
    ],
    "sg:phone":"+44 1236 770290",
    "sg:postcode":"ML6 8RR",
    "sg:province":"North Lanarkshire",
    "wof:name":"Kwik Save Stores",
    "wof:placetype":"venue"
},
  "geometry": {"coordinates":[-3.9524929523,55.8403053284],"type":"Point"}
}