{
  "type": "Feature",
  "properties": {
    "addr:full":"370 Aigburth Rd Liverpool Merseyside L17 6AE",
    "addr:housenumber":"370",
    "addr:postcode":"l17 6ae",
    "addr:street":"Aigburth Rd",
    "iso:country":"GB",
    "sg:address":"370 Aigburth Rd",
    "sg:city":"Liverpool",
    "sg:classifiers":[
        {
            "category":"Professional",
            "type":"Services"
        }
    ],
    "sg:phone":"+44 151 427 0016",
    "sg:postcode":"L17 6AE",
    "sg:province":"Merseyside",
    "sg:tags":[
        "interior",
        "furnishers",
        "designer"
    ],
    "wof:name":"Applied Fine Arts Inc",
    "wof:placetype":"venue"
},
  "geometry": {"coordinates":[-2.9257769585,53.36743927],"type":"Point"}
}