{
  "type": "Feature",
  "properties": {
    "iso:country":"GB",
    "sg:address":"Cumberland Hotel, Marble Arch",
    "sg:city":"London",
    "sg:classifiers":[
        {
            "category":"Professional",
            "subcategory":"Employment Agencies",
            "type":"Services"
        }
    ],
    "sg:postcode":"W1H 7DX",
    "sg:province":"Greater London",
    "sg:tags":[
        "consultant"
    ],
    "wof:name":"First Choice Languages Ltd",
    "wof:placetype":"venue"
},
  "geometry": {"coordinates":[-0.159139,51.513794],"type":"Point"}
}