{
  "type": "Feature",
  "properties": {
    "iso:country":"GB",
    "sg:address":"Care Of Kwik Save",
    "sg:city":"Llandovery",
    "sg:classifiers":[
        {
            "category":"Food & Beverages",
            "subcategory":"Meat & Fish",
            "type":"Retail Goods"
        }
    ],
    "sg:postcode":"SA20 0DD",
    "sg:province":"Carmarthenshire",
    "sg:tags":[
        "butcher"
    ],
    "wof:name":"P Figoni & H Jones",
    "wof:placetype":"venue"
},
  "geometry": {"coordinates":[-3.800155,51.994087],"type":"Point"}
}