{
  "type": "Feature",
  "properties": {
    "addr:full":"50 High Street, Dawley Telford Shropshire TF4 2EX",
    "addr:housenumber":"50",
    "addr:postcode":"tf4 2ex",
    "addr:street":"High Street",
    "iso:country":"GB",
    "sg:address":"50 High Street, Dawley",
    "sg:city":"Telford",
    "sg:classifiers":[
        {
            "category":"Fast Food",
            "type":"Food & Drink"
        }
    ],
    "sg:phone":"+44 1952 505480",
    "sg:postcode":"TF4 2EX",
    "sg:province":"Shropshire",
    "sg:tags":[
        "away",
        "take"
    ],
    "wof:name":"Lotus Chinese Restaurant",
    "wof:placetype":"venue"
},
  "geometry": {"coordinates":[-2.467194,52.66378],"type":"Point"}
}