{
  "type": "Feature",
  "properties": {
    "iso:country":"GB",
    "sg:address":"45 Bdwy",
    "sg:city":"Gillingham",
    "sg:classifiers":[
        {
            "category":"Building & Trades",
            "subcategory":"Cleaning & Sanitation",
            "type":"Services"
        }
    ],
    "sg:postcode":"ME8 6BA",
    "sg:province":"Kent",
    "sg:tags":[
        "computer",
        "telephone"
    ],
    "wof:name":"Broadway Computer Cleaning Service",
    "wof:placetype":"venue"
},
  "geometry": {"coordinates":[0.572066,51.373806],"type":"Point"}
}