{
  "type": "Feature",
  "properties": {
    "iso:country":"GB",
    "sg:address":"186 Fleet Street",
    "sg:city":"London",
    "sg:classifiers":[
        {
            "category":"Professional",
            "subcategory":"Printing & Photocopies",
            "type":"Services"
        }
    ],
    "sg:phone":"+44 20 7405 5686",
    "sg:postcode":"EC4A 2HR",
    "sg:province":"Greater London",
    "sg:tags":[
        "printer"
    ],
    "wof:name":"Kall-Kwik Printing",
    "wof:placetype":"venue"
},
  "geometry": {"coordinates":[-0.110034,51.514065],"type":"Point"}
}