{
  "type": "Feature",
  "properties": {
    "addr:full":"Colmworth Business Park St Neots Bedfordshire PE19 8YH",
    "addr:housenumber":"colmworth",
    "addr:postcode":"pe19 8yh",
    "addr:street":"Business Park",
    "iso:country":"GB",
    "sg:address":"Colmworth Business Park",
    "sg:city":"St Neots",
    "sg:classifiers":[
        {
            "category":"Professional",
            "subcategory":"Printing & Photocopies",
            "type":"Services"
        }
    ],
    "sg:phone":"+44 1480 215155",
    "sg:postcode":"PE19 8YH",
    "sg:province":"Bedfordshire",
    "sg:tags":[
        "computer",
        "tag",
        "label"
    ],
    "wof:name":"Lattice Labels Ltd.",
    "wof:placetype":"venue"
},
  "geometry": {"coordinates":[-0.288914,52.209412],"type":"Point"}
}