{
  "type": "Feature",
  "properties": {
    "addr:full":"9 Guy Place East Leamington Spa Warwickshire CV32 4RG",
    "addr:housenumber":"9",
    "addr:postcode":"cv32 4rg",
    "addr:street":"Guy Place East",
    "iso:country":"GB",
    "sg:address":"9 Guy Place East",
    "sg:city":"Leamington Spa",
    "sg:classifiers":[
        {
            "category":"Shopping",
            "subcategory":"Bicycles & Sporting Goods",
            "type":"Retail Goods"
        }
    ],
    "sg:phone":"+44 1926 450193",
    "sg:postcode":"CV32 4RG",
    "sg:province":"Warwickshire",
    "sg:tags":[
        "equipment",
        "leisure"
    ],
    "wof:name":"Scubaaction Diving Centre",
    "wof:placetype":"venue"
},
  "geometry": {"coordinates":[-1.533171,52.293457],"type":"Point"}
}