{
  "type": "Feature",
  "properties": {
    "addr:full":"P O Box 57 Sevenoaks Kent TN14 6TG",
    "addr:housenumber":"box 57",
    "addr:postcode":"tn14 6tg",
    "addr:street":"P O",
    "iso:country":"GB",
    "sg:address":"P O Box 57",
    "sg:city":"Sevenoaks",
    "sg:classifiers":[
        {
            "category":"Shopping",
            "subcategory":"Stationery & Office Supplies",
            "type":"Retail Goods"
        }
    ],
    "sg:postcode":"TN14 6TG",
    "sg:province":"Kent",
    "sg:tags":[
        "envelope"
    ],
    "wof:name":"Camson Envelopes",
    "wof:placetype":"venue"
},
  "geometry": {"coordinates":[0.1302,51.24662],"type":"Point"}
}