{
  "type": "Feature",
  "properties": {
    "addr:full":"Cross Street, Oadby Leicester Leicestershire LE2 4DD",
    "addr:postcode":"le2 4dd",
    "addr:street":"Cross Street",
    "iso:country":"GB",
    "sg:address":"Cross Street, Oadby",
    "sg:city":"Leicester",
    "sg:classifiers":[
        {
            "category":"Manufacturing",
            "subcategory":"Tools & Machinery",
            "type":"Manufacturing & Wholesale Goods"
        }
    ],
    "sg:phone":"+44 116 271 7715",
    "sg:postcode":"LE2 4DD",
    "sg:province":"Leicestershire",
    "sg:tags":[
        "design",
        "maker",
        "manufacturer"
    ],
    "wof:name":"C G P Engineering Ltd",
    "wof:placetype":"venue"
},
  "geometry": {"coordinates":[-1.083019,52.604],"type":"Point"}
}