{
  "type": "Feature",
  "properties": {
    "addr:full":"County Buildings, Wellington Sq Ayr South Ayrshire KA7 1DR",
    "addr:postcode":"ka7 1dr",
    "addr:street":"Wellington Sq",
    "iso:country":"GB",
    "sg:address":"County Buildings, Wellington Sq",
    "sg:city":"Ayr",
    "sg:classifiers":[
        {
            "category":"Professional",
            "subcategory":"Employment Agencies",
            "type":"Services"
        }
    ],
    "sg:phone":"+44 1292 612236",
    "sg:postcode":"KA7 1DR",
    "sg:province":"South Ayrshire",
    "sg:tags":[
        "career",
        "guidance"
    ],
    "wof:name":"Ayrshire Careers Partnership",
    "wof:placetype":"venue"
},
  "geometry": {"coordinates":[-4.63863,55.46151],"type":"Point"}
}