{
  "type": "Feature",
  "properties": {
    "addr:full":"Aldersyde, Grange Road Hartlepool Durham TS26 0DS",
    "addr:postcode":"ts26 0ds",
    "addr:street":"Grange Road",
    "iso:country":"GB",
    "sg:address":"Aldersyde, Grange Road",
    "sg:city":"Hartlepool",
    "sg:classifiers":[
        {
            "category":"Farming",
            "subcategory":"Nursery",
            "type":"Manufacturing & Wholesale Goods"
        }
    ],
    "sg:postcode":"TS26 0DS",
    "sg:province":"Durham",
    "sg:tags":[
        "creche"
    ],
    "wof:name":"Aldersyde Day Nursery",
    "wof:placetype":"venue"
},
  "geometry": {"coordinates":[-1.2366499901,54.6855583191],"type":"Point"}
}