{
  "type": "Feature",
  "properties": {
    "iso:country":"GB",
    "sg:address":"The Firs, Seaview Road, Cranmore",
    "sg:city":"Yarmouth",
    "sg:classifiers":[
        {
            "category":"Building & Trades",
            "subcategory":"Construction",
            "type":"Services"
        }
    ],
    "sg:phone":"+44 1983 760289",
    "sg:postcode":"PO41 0XU",
    "sg:province":"Isle of Wight",
    "sg:tags":[
        "builder"
    ],
    "wof:name":"Brian A Smith",
    "wof:placetype":"venue"
},
  "geometry": {"coordinates":[-1.4966590405,50.7050094604],"type":"Point"}
}