{
  "type": "Feature",
  "properties": {
    "addr:full":"385 Washway Road Sale Cheshire M33 4FJ",
    "addr:housenumber":"385",
    "addr:postcode":"m33 4fj",
    "addr:street":"Washway Road",
    "iso:country":"GB",
    "sg:address":"385 Washway Road",
    "sg:city":"Sale",
    "sg:classifiers":[
        {
            "category":"Shopping",
            "subcategory":"News",
            "type":"Retail Goods"
        }
    ],
    "sg:phone":"+44 161 973 5106",
    "sg:postcode":"M33 4FJ",
    "sg:province":"Cheshire",
    "sg:tags":[
        "newsagent"
    ],
    "wof:name":"Phills",
    "wof:placetype":"venue"
},
  "geometry": {"coordinates":[-2.344552,53.408344],"type":"Point"}
}