{
  "type": "Feature",
  "properties": {
    "addr:full":"78 Dunvegan Rd Eltham Greater London SE9 1SB",
    "addr:housenumber":"78",
    "addr:postcode":"se9 1sb",
    "addr:street":"Dunvegan Rd",
    "iso:country":"GB",
    "sg:address":"78 Dunvegan Rd",
    "sg:city":"Eltham",
    "sg:classifiers":[
        {
            "category":"Health Services",
            "subcategory":"Dentist",
            "type":"Services"
        }
    ],
    "sg:phone":"+44 20 8850 8886",
    "sg:postcode":"SE9 1SB",
    "sg:province":"Greater London",
    "wof:name":"M.A Minns",
    "wof:placetype":"venue"
},
  "geometry": {"coordinates":[0.0551959984,51.456401825],"type":"Point"}
}