{
  "type": "Feature",
  "properties": {
    "addr:full":"27 High Street Ferndale Rhondda, Cynon, Taff CF43 4RH",
    "addr:housenumber":"27",
    "addr:postcode":"cf43 4rh",
    "addr:street":"High Street",
    "iso:country":"GB",
    "sg:address":"27 High Street",
    "sg:city":"Ferndale",
    "sg:classifiers":[
        {
            "category":"Health Services",
            "subcategory":"Doctor",
            "type":"Services"
        },
        {
            "category":"Health Services",
            "subcategory":"Dentist",
            "type":"Services"
        }
    ],
    "sg:phone":"+44 1443 732030",
    "sg:postcode":"CF43 4RH",
    "sg:province":"Rhondda, Cynon, Taff",
    "wof:name":"LEYTON ROBERTS",
    "wof:placetype":"venue"
},
  "geometry": {"coordinates":[-3.448652,51.661827],"type":"Point"}
}