{
  "type": "Feature",
  "properties": {
    "iso:country":"GB",
    "sg:address":"Abernethy Clinic, 44 Main St",
    "sg:city":"Perth",
    "sg:classifiers":[
        {
            "category":"Health Services",
            "subcategory":"Doctor",
            "type":"Services"
        }
    ],
    "sg:phone":"+44 1738 850461",
    "sg:postcode":"PH2 9JH",
    "sg:province":"Perth and Kinross",
    "sg:tags":[
        "practitioners"
    ],
    "wof:name":"Booth, D J W",
    "wof:placetype":"venue"
},
  "geometry": {"coordinates":[-3.40354,56.327637],"type":"Point"}
}