{
  "type": "Feature",
  "properties": {
    "addr:full":"Unit 3 Penllwyngwent Industrial Estate, Saville Road Bridgend Bridgend CF32 7AX",
    "addr:housenumber":"unit 3",
    "addr:postcode":"cf32 7ax",
    "addr:street":"Penllwyngwent Industrial Estate Saville Road",
    "iso:country":"GB",
    "sg:address":"Unit 3 Penllwyngwent Industrial Estate, Saville Road",
    "sg:city":"Bridgend",
    "sg:classifiers":[
        {
            "category":"Retail",
            "subcategory":"Portrait Studio",
            "type":"Services"
        }
    ],
    "sg:postcode":"CF32 7AX",
    "sg:province":"Bridgend",
    "sg:tags":[
        "photographic"
    ],
    "wof:name":"Pete Davies",
    "wof:placetype":"venue"
},
  "geometry": {"coordinates":[-3.5415899754,51.6084213257],"type":"Point"}
}