{
  "type": "Feature",
  "properties": {
    "iso:country":"GB",
    "sg:address":"Normanston Drive",
    "sg:city":"Lowestoft",
    "sg:classifiers":[
        {
            "category":"Community Center",
            "type":"Public Place"
        }
    ],
    "sg:phone":"+44 1502 565340",
    "sg:postcode":"NR32 2PZ",
    "sg:province":"Suffolk",
    "sg:tags":[
        "nursery",
        "centre"
    ],
    "wof:name":"Normanston Park",
    "wof:placetype":"venue"
},
  "geometry": {"coordinates":[1.7346,52.483135],"type":"Point"}
}