{
  "type": "Feature",
  "properties": {
    "iso:country":"GB",
    "sg:address":"108 Sunderland Road",
    "sg:city":"South Shields",
    "sg:classifiers":[
        {
            "category":"Building & Trades",
            "subcategory":"Construction",
            "type":"Services"
        }
    ],
    "sg:phone":"+44 191 455 6293",
    "sg:postcode":"NE34 6LX",
    "sg:province":"Tyne and Wear",
    "sg:tags":[
        "dry",
        "plastering",
        "plasterers",
        "lining",
        "related",
        "screeders"
    ],
    "wof:name":"Harry Swan",
    "wof:placetype":"venue"
},
  "geometry": {"coordinates":[-1.415718,54.980186],"type":"Point"}
}