{
  "type": "Feature",
  "properties": {
    "addr:full":"Sumners Farm, Epping Green Epping Essex CM16 6PX",
    "addr:postcode":"cm16 6px",
    "addr:street":"Epping Green",
    "iso:country":"GB",
    "sg:address":"Sumners Farm, Epping Green",
    "sg:city":"Epping",
    "sg:classifiers":[
        {
            "category":"Professional",
            "subcategory":"Secretarial Services",
            "type":"Services"
        },
        {
            "category":"Building & Trades",
            "subcategory":"Construction",
            "type":"Services"
        }
    ],
    "sg:phone":"+44 1992 573489",
    "sg:postcode":"CM16 6PX",
    "sg:province":"Essex",
    "sg:tags":[
        "pipework",
        "stenographic",
        "contractor"
    ],
    "wof:name":"Utilities Support Services Ltd.",
    "wof:placetype":"venue"
},
  "geometry": {"coordinates":[0.07914,51.7266311646],"type":"Point"}
}