{
  "type": "Feature",
  "properties": {
    "addr:full":"1 Wellgatehead Lanark South Lanarkshire ML11 9AA",
    "addr:housenumber":"1",
    "addr:postcode":"ml11 9aa",
    "addr:street":"Wellgatehead Lanark",
    "iso:country":"GB",
    "sg:address":"1 Wellgatehead",
    "sg:city":"Lanark",
    "sg:classifiers":[
        {
            "category":"Bars & Pubs",
            "type":"Food & Drink"
        }
    ],
    "sg:phone":"+44 1555 661056",
    "sg:postcode":"ML11 9AA",
    "sg:province":"South Lanarkshire",
    "sg:tags":[
        "pubs",
        "inn"
    ],
    "wof:name":"The Corral Inn",
    "wof:placetype":"venue"
},
  "geometry": {"coordinates":[-3.7775790691,55.6723976135],"type":"Point"}
}