{
  "type": "Feature",
  "properties": {
    "addr:full":"12a High Street East, Hadfield Glossop Derbyshire SK13 8DA",
    "addr:housenumber":"12a",
    "addr:postcode":"sk13 8da",
    "addr:street":"High Street East",
    "iso:country":"GB",
    "sg:address":"12a High Street East, Hadfield",
    "sg:city":"Glossop",
    "sg:classifiers":[
        {
            "category":"Professional",
            "subcategory":"Detective & Security Services",
            "type":"Services"
        }
    ],
    "sg:phone":"+44 1457 850720",
    "sg:postcode":"SK13 8DA",
    "sg:province":"Derbyshire",
    "sg:tags":[
        "alarm",
        "burglar",
        "system"
    ],
    "wof:name":"Page Alarms",
    "wof:placetype":"venue"
},
  "geometry": {"coordinates":[-1.948258996,53.4432106018],"type":"Point"}
}