{
  "type": "Feature",
  "properties": {
    "iso:country":"GB",
    "sg:address":"4 Farmers Fold",
    "sg:city":"Wolverhampton",
    "sg:classifiers":[
        {
            "category":"Food & Beverages",
            "subcategory":"Supermarket",
            "type":"Retail Goods"
        }
    ],
    "sg:postcode":"WV1 3NU",
    "sg:province":"West Midlands",
    "wof:name":"Spice Box (The)",
    "wof:placetype":"venue"
},
  "geometry": {"coordinates":[-2.129034,52.584435],"type":"Point"}
}