{
  "type": "Feature",
  "properties": {
    "iso:country":"GB",
    "sg:address":"304 Green Lanes",
    "sg:city":"London",
    "sg:classifiers":[
        {
            "category":"Organizations",
            "subcategory":"Non-profit Organization",
            "type":"Services"
        }
    ],
    "sg:phone":"+44 20 8886 3340",
    "sg:postcode":"N13 5TW",
    "sg:province":"Greater London",
    "sg:tags":[
        "organisation",
        "voluntary",
        "charity"
    ],
    "wof:name":"Scope",
    "wof:placetype":"venue"
},
  "geometry": {"coordinates":[-0.107485,51.618717],"type":"Point"}
}