{
  "type": "Feature",
  "properties": {
    "iso:country":"GB",
    "sg:address":"Unit 8 The Quad, Mercury Court",
    "sg:city":"Chester",
    "sg:classifiers":[
        {
            "category":"Home & Garden",
            "subcategory":"Hardware",
            "type":"Retail Goods"
        }
    ],
    "sg:phone":"+44 1244 390444",
    "sg:postcode":"CH1 4QP",
    "sg:province":"Cheshire",
    "sg:tags":[
        "equipment",
        "central",
        "heating"
    ],
    "wof:name":"Heating Controls & Spares",
    "wof:placetype":"venue"
},
  "geometry": {"coordinates":[-2.894369,53.188129],"type":"Point"}
}