{
  "type": "Feature",
  "properties": {
    "addr:full":"329 Bearwood Rd, Bearwood Smethwick Smethwick West Midlands B66 4DP",
    "addr:housenumber":"329",
    "addr:postcode":"b66 4dp",
    "addr:street":"Bearwood Rd",
    "iso:country":"GB",
    "sg:address":"329 Bearwood Rd, Bearwood Smethwick",
    "sg:city":"Smethwick",
    "sg:classifiers":[
        {
            "category":"Manufacturing",
            "subcategory":"Petroleum Products",
            "type":"Manufacturing & Wholesale Goods"
        }
    ],
    "sg:phone":"+44 121 420 2253",
    "sg:postcode":"B66 4DP",
    "sg:province":"West Midlands",
    "sg:tags":[
        "double",
        "glazing"
    ],
    "wof:name":"Secure Windows",
    "wof:placetype":"venue"
},
  "geometry": {"coordinates":[-1.969347,52.480965],"type":"Point"}
}