{
  "type": "Feature",
  "properties": {
    "addr:full":"212 Brixton Hill, Brixton London Greater London SW2 1HE",
    "addr:housenumber":"212",
    "addr:postcode":"sw2 1he",
    "addr:street":"Brixton Hill",
    "iso:country":"GB",
    "sg:address":"212 Brixton Hill, Brixton",
    "sg:city":"London",
    "sg:classifiers":[
        {
            "category":"Retail",
            "subcategory":"Veterinary Services",
            "type":"Services"
        }
    ],
    "sg:phone":"+44 20 8671 5566",
    "sg:postcode":"SW2 1HE",
    "sg:province":"Greater London",
    "sg:tags":[
        "surgeon"
    ],
    "wof:name":"Goddards Veterinary Clinic",
    "wof:placetype":"venue"
},
  "geometry": {"coordinates":[-0.1237500012,51.4490089417],"type":"Point"}
}