{
  "type": "Feature",
  "properties": {
    "iso:country":"GB",
    "sg:address":"Tyn Yr Wtra, Llanwyddelan",
    "sg:city":"Newtown",
    "sg:classifiers":[
        {
            "category":"Farming",
            "subcategory":"Livestock Farm",
            "type":"Manufacturing & Wholesale Goods"
        }
    ],
    "sg:postcode":"SY16 3BT",
    "sg:province":"Powys",
    "sg:tags":[
        "others"
    ],
    "wof:name":"T S & G Jerman",
    "wof:placetype":"venue"
},
  "geometry": {"coordinates":[-3.364276,52.602245],"type":"Point"}
}