{
  "type": "Feature",
  "properties": {
    "iso:country":"GB",
    "sg:address":"35 Drury Lane",
    "sg:city":"Solihull",
    "sg:classifiers":[
        {
            "category":"Shopping",
            "subcategory":"Gifts & Souvenirs",
            "type":"Retail Goods"
        }
    ],
    "sg:phone":"+44 121 705 8318",
    "sg:postcode":"B91 3BP",
    "sg:province":"West Midlands",
    "sg:tags":[
        "shop",
        "poster",
        "card"
    ],
    "wof:name":"Strand Cards Ltd.",
    "wof:placetype":"venue"
},
  "geometry": {"coordinates":[-1.775555,52.414043],"type":"Point"}
}