{
  "type": "Feature",
  "properties": {
    "iso:country":"GB",
    "sg:address":"Sheddingdean Neighbourhood Centre, Maple Dr",
    "sg:city":"Burgess Hill",
    "sg:classifiers":[
        {
            "category":"Education",
            "subcategory":"Preschool",
            "type":"Public Place"
        }
    ],
    "sg:phone":"+44 1444 230506",
    "sg:postcode":"RH15 8UA",
    "sg:province":"East Sussex",
    "sg:tags":[
        "pre-school",
        "playgroups"
    ],
    "wof:name":"Windmill Opportunity Playgroup",
    "wof:placetype":"venue"
},
  "geometry": {"coordinates":[-0.1391739994,50.955329895],"type":"Point"}
}