{
  "type": "Feature",
  "properties": {
    "addr:full":"22 Kerry Close, Shaw Swindon Wiltshire SN5 5SQ",
    "addr:housenumber":"22",
    "addr:postcode":"sn5 5sq",
    "addr:street":"Kerry Close",
    "iso:country":"GB",
    "sg:address":"22 Kerry Close, Shaw",
    "sg:city":"Swindon",
    "sg:classifiers":[
        {
            "category":"Retail",
            "subcategory":"Repair Shop",
            "type":"Services"
        }
    ],
    "sg:postcode":"SN5 5SQ",
    "sg:province":"Wiltshire",
    "sg:tags":[
        "maintenance"
    ],
    "wof:name":"Odd Job Man",
    "wof:placetype":"venue"
},
  "geometry": {"coordinates":[-1.838755,51.564041],"type":"Point"}
}