{
  "type": "Feature",
  "properties": {
    "iso:country":"GB",
    "sg:address":"6 Wood End Road",
    "sg:city":"Harrow",
    "sg:classifiers":[
        {
            "category":"Real Estate",
            "subcategory":"Architect",
            "type":"Services"
        }
    ],
    "sg:postcode":"HA1 3PW",
    "sg:province":"Greater London",
    "wof:name":"M J Ford Associates Ltd",
    "wof:placetype":"venue"
},
  "geometry": {"coordinates":[-0.338131,51.560558],"type":"Point"}
}