{
  "type": "Feature",
  "properties": {
    "addr:full":"464 Brixton Road London Greater London SW9 8EA",
    "addr:housenumber":"464",
    "addr:postcode":"sw9 8ea",
    "addr:street":"Brixton Road",
    "iso:country":"GB",
    "sg:address":"464 Brixton Road",
    "sg:city":"London",
    "sg:classifiers":[
        {
            "category":"Shopping",
            "subcategory":"Beauty & Cosmetics",
            "type":"Retail Goods"
        }
    ],
    "sg:phone":"+44 20 7738 4464",
    "sg:postcode":"SW9 8EA",
    "sg:province":"Greater London",
    "sg:tags":[
        "product"
    ],
    "wof:name":"The Body Shop",
    "wof:placetype":"venue"
},
  "geometry": {"coordinates":[-0.1150059998,51.462978363],"type":"Point"}
}