{
  "type": "Feature",
  "properties": {
    "iso:country":"GB",
    "sg:address":"Manor Trading Est, 4-6 Armstrong Rd",
    "sg:city":"Benfleet",
    "sg:classifiers":[
        {
            "category":"Manufacturing",
            "subcategory":"Aerospace",
            "type":"Manufacturing & Wholesale Goods"
        }
    ],
    "sg:phone":"+44 1268 792681",
    "sg:postcode":"SS7 4PW",
    "sg:province":"Essex",
    "sg:tags":[
        "aircraft",
        "furnishing",
        "fitting"
    ],
    "wof:name":"Methodical Engineers Ltd",
    "wof:placetype":"venue"
},
  "geometry": {"coordinates":[0.56264,51.543316],"type":"Point"}
}