{
  "type": "Feature",
  "properties": {
    "addr:full":"409 Southchurch Road Southend-on-sea Essex SS1 1PH",
    "addr:housenumber":"409",
    "addr:postcode":"ss1 1ph",
    "addr:street":"Southchurch Road",
    "iso:country":"GB",
    "sg:address":"409 Southchurch Road",
    "sg:city":"Southend-on-sea",
    "sg:classifiers":[
        {
            "category":"Shopping",
            "subcategory":"Stationery & Office Supplies",
            "type":"Retail Goods"
        }
    ],
    "sg:postcode":"SS1 1PH",
    "sg:province":"Essex",
    "sg:tags":[
        "printers'"
    ],
    "wof:name":"Stirling Graphics Ltd.",
    "wof:placetype":"venue"
},
  "geometry": {"coordinates":[0.7117140293,51.5404281616],"type":"Point"}
}