{
  "type": "Feature",
  "properties": {
    "addr:full":"17 Towngate Ossett West Yorkshire WF5 9BL",
    "addr:housenumber":"17;ossett",
    "addr:postcode":"wf5 9bl",
    "addr:street":"Towngate",
    "iso:country":"GB",
    "sg:address":"17 Towngate",
    "sg:city":"Ossett",
    "sg:classifiers":[
        {
            "category":"Shopping",
            "subcategory":"Stationery & Office Supplies",
            "type":"Retail Goods"
        }
    ],
    "sg:phone":"+44 1924 273144",
    "sg:postcode":"WF5 9BL",
    "sg:province":"West Yorkshire",
    "wof:name":"Portfolio Stationery & Office Supplies",
    "wof:placetype":"venue"
},
  "geometry": {"coordinates":[-1.5770889521,53.6799201965],"type":"Point"}
}