{
  "type": "Feature",
  "properties": {
    "addr:full":"25 Ledcameroch Crescent, Bearsden Glasgow East Dunbartonshire G61 4AR",
    "addr:housenumber":"25",
    "addr:postcode":"g61 4ar",
    "addr:street":"Ledcameroch Crescent",
    "iso:country":"GB",
    "sg:address":"25 Ledcameroch Crescent, Bearsden",
    "sg:city":"Glasgow",
    "sg:classifiers":[
        {
            "category":"Real Estate",
            "subcategory":"Real Estate Operator",
            "type":"Services"
        }
    ],
    "sg:phone":"+44 141 942 1202",
    "sg:postcode":"G61 4AR",
    "sg:province":"East Dunbartonshire",
    "sg:tags":[
        "letting",
        "agent"
    ],
    "wof:name":"Directline Property Services",
    "wof:placetype":"venue"
},
  "geometry": {"coordinates":[-4.338832,55.916992],"type":"Point"}
}