{
  "type": "Feature",
  "properties": {
    "addr:full":"3 Manor Walk, 130 High St Solihull West Midlands B91 3SX",
    "addr:housenumber":"3;130",
    "addr:postcode":"b91 3sx",
    "addr:street":"Manor Walk;High St",
    "iso:country":"GB",
    "sg:address":"3 Manor Walk, 130 High St",
    "sg:city":"Solihull",
    "sg:classifiers":[
        {
            "category":"Shopping",
            "subcategory":"Pets & Pet Supplies",
            "type":"Retail Goods"
        }
    ],
    "sg:phone":"+44 121 705 2791",
    "sg:postcode":"B91 3SX",
    "sg:province":"West Midlands",
    "wof:name":"Pets World",
    "wof:placetype":"venue"
},
  "geometry": {"coordinates":[-1.777848959,52.4150657654],"type":"Point"}
}