{
  "type": "Feature",
  "properties": {
    "addr:full":"7 London Rd, Tun Wells Tunbridge Wells Kent TN1 1DG",
    "addr:housenumber":"7",
    "addr:postcode":"tn1 1dg",
    "addr:street":"London Rd",
    "iso:country":"GB",
    "sg:address":"7 London Rd, Tun Wells",
    "sg:city":"Tunbridge Wells",
    "sg:classifiers":[
        {
            "category":"Manufacturing",
            "subcategory":"Wood Products",
            "type":"Manufacturing & Wholesale Goods"
        },
        {
            "category":"Professional",
            "subcategory":"Art Services",
            "type":"Services"
        }
    ],
    "sg:phone":"+44 1892 619550",
    "sg:postcode":"TN1 1DG",
    "sg:province":"Kent",
    "sg:tags":[
        "interior",
        "designer",
        "maker",
        "cabinet"
    ],
    "wof:name":"Clive Christian Of Tunbridge Wells",
    "wof:placetype":"venue"
},
  "geometry": {"coordinates":[0.2598100007,51.1273193359],"type":"Point"}
}