{
  "type": "Feature",
  "properties": {
    "addr:full":"57-61 Byron Rd Harrow Greater London HA3 7SZ",
    "addr:housenumber":"57-61",
    "addr:postcode":"ha3 7sz",
    "addr:street":"Byron Rd",
    "iso:country":"GB",
    "sg:address":"57-61 Byron Rd",
    "sg:city":"Harrow",
    "sg:classifiers":[
        {
            "category":"Retail",
            "subcategory":"Auto Repair",
            "type":"Services"
        }
    ],
    "sg:phone":"+44 20 8863 9146",
    "sg:postcode":"HA3 7SZ",
    "sg:province":"Greater London",
    "sg:tags":[
        "modification",
        "garage"
    ],
    "wof:name":"P D Motors",
    "wof:placetype":"venue"
},
  "geometry": {"coordinates":[-0.3298290074,51.5934066772],"type":"Point"}
}