{
  "type": "Feature",
  "properties": {
    "iso:country":"GB",
    "sg:address":"81a Coppice Rd",
    "sg:city":"Stockport",
    "sg:classifiers":[
        {
            "category":"Professional",
            "subcategory":"Engineering",
            "type":"Services"
        }
    ],
    "sg:phone":"+44 1625 850921",
    "sg:postcode":"SK12 1SL",
    "sg:province":"Cheshire",
    "sg:tags":[
        "electronic",
        "engineer"
    ],
    "wof:name":"John E Birks & Associates Ltd",
    "wof:placetype":"venue"
},
  "geometry": {"coordinates":[-2.1014139652,53.3462104797],"type":"Point"}
}