{
  "type": "Feature",
  "properties": {
    "iso:country":"GB",
    "sg:address":"338 Rossendale Road",
    "sg:city":"Burnley",
    "sg:classifiers":[
        {
            "category":"Bars & Pubs",
            "type":"Food & Drink"
        }
    ],
    "sg:phone":"+44 1282 422745",
    "sg:postcode":"BB11 5JF",
    "sg:province":"Lancashire",
    "sg:tags":[
        "pubs",
        "inn"
    ],
    "wof:name":"The Running Pump",
    "wof:placetype":"venue"
},
  "geometry": {"coordinates":[-2.266509,53.77655],"type":"Point"}
}