{
  "type": "Feature",
  "properties": {
    "addr:full":"Merryfield, 21 Park Road Walsall West Midlands WS5 3JU",
    "addr:housenumber":"21",
    "addr:postcode":"ws5 3ju",
    "addr:street":"Merryfield;Park Road",
    "iso:country":"GB",
    "sg:address":"Merryfield, 21 Park Road",
    "sg:city":"Walsall",
    "sg:classifiers":[
        {
            "category":"Organizations",
            "subcategory":"Membership Organization",
            "type":"Services"
        }
    ],
    "sg:postcode":"WS5 3JU",
    "sg:province":"West Midlands",
    "sg:tags":[
        "club"
    ],
    "wof:name":"Centreway Management Services Ltd.",
    "wof:placetype":"venue"
},
  "geometry": {"coordinates":[-1.9439300299,52.5655403137],"type":"Point"}
}