{
  "type": "Feature",
  "properties": {
    "addr:full":"26 Stow Hill Newport Newport NP20 1JD",
    "addr:housenumber":"26",
    "addr:postcode":"np20 1jd",
    "addr:street":"Stow Hill",
    "iso:country":"GB",
    "sg:address":"26 Stow Hill",
    "sg:city":"Newport",
    "sg:classifiers":[
        {
            "category":"Professional",
            "subcategory":"Employment Agencies",
            "type":"Services"
        }
    ],
    "sg:phone":"+44 1633 215155",
    "sg:postcode":"NP20 1JD",
    "sg:province":"Newport",
    "sg:tags":[
        "consultant",
        "recruitment"
    ],
    "wof:name":"Travail Employment Group Ltd",
    "wof:placetype":"venue"
},
  "geometry": {"coordinates":[-2.997153,51.587273],"type":"Point"}
}