{
  "type": "Feature",
  "properties": {
    "addr:full":"233a Clarkston Rd Glasgow East Renfrewshire G44 3DS",
    "addr:housenumber":"233a",
    "addr:postcode":"g44 3ds",
    "addr:street":"Clarkston Rd",
    "iso:country":"GB",
    "sg:address":"233a Clarkston Rd",
    "sg:city":"Glasgow",
    "sg:classifiers":[
        {
            "category":"Professional",
            "subcategory":"Accounting & Tax Preparation",
            "type":"Services"
        }
    ],
    "sg:phone":"+44 141 637 1333",
    "sg:postcode":"G44 3DS",
    "sg:province":"East Renfrewshire",
    "sg:tags":[
        "accountant"
    ],
    "wof:name":"Martin Robertson Associates",
    "wof:placetype":"venue"
},
  "geometry": {"coordinates":[-4.2671518326,55.8136825562],"type":"Point"}
}