{
  "type": "Feature",
  "properties": {
    "iso:country":"GB",
    "sg:address":"Hartest",
    "sg:city":"Bury St Edmunds",
    "sg:classifiers":[
        {
            "category":"Professional",
            "subcategory":"Engineering",
            "type":"Services"
        }
    ],
    "sg:phone":"+44 1284 830726",
    "sg:postcode":"IP29 4EH",
    "sg:province":"Suffolk",
    "sg:tags":[
        "contractor",
        "electrical",
        "engineer"
    ],
    "wof:name":"Heatlec Installations Ltd.",
    "wof:placetype":"venue"
},
  "geometry": {"coordinates":[0.67607,52.143181],"type":"Point"}
}