{
  "type": "Feature",
  "properties": {
    "addr:full":"31 Mkt St Barnsley South Yorkshire S70 1SN",
    "addr:housenumber":"31",
    "addr:postcode":"s70 1sn",
    "addr:street":"Mkt St;Yorkshire",
    "iso:country":"GB",
    "sg:address":"31 Mkt St",
    "sg:city":"Barnsley",
    "sg:classifiers":[
        {
            "category":"Shopping",
            "subcategory":"Clothing, Apparel, & Fashions",
            "type":"Retail Goods"
        }
    ],
    "sg:postcode":"S70 1SN",
    "sg:province":"South Yorkshire",
    "sg:tags":[
        "shop"
    ],
    "wof:name":"Chain Store Seconds",
    "wof:placetype":"venue"
},
  "geometry": {"coordinates":[-1.480831027,53.5511322021],"type":"Point"}
}