{
  "type": "Feature",
  "properties": {
    "iso:country":"GB",
    "sg:address":"12 Bond Street",
    "sg:city":"Wakefield",
    "sg:classifiers":[
        {
            "category":"Retail",
            "subcategory":"Repair Shop",
            "type":"Services"
        }
    ],
    "sg:phone":"+44 1924 290011",
    "sg:postcode":"WF1 2QP",
    "sg:province":"West Yorkshire",
    "sg:tags":[
        "clocks",
        "watch"
    ],
    "wof:name":"The Watch Hospital Ltd.",
    "wof:placetype":"venue"
},
  "geometry": {"coordinates":[-1.5029809475,53.6855049133],"type":"Point"}
}