{
  "type": "Feature",
  "properties": {
    "iso:country":"GB",
    "sg:address":"7 Christchurch Rd",
    "sg:city":"New Milton",
    "sg:classifiers":[
        {
            "category":"Food & Beverages",
            "subcategory":"Fruits & Vegetables",
            "type":"Retail Goods"
        }
    ],
    "sg:postcode":"BH25 6QA",
    "sg:province":"Hampshire",
    "sg:tags":[
        "greengrocer"
    ],
    "wof:name":"Bailey,Michael,",
    "wof:placetype":"venue"
},
  "geometry": {"coordinates":[-1.670462966,50.7455062866],"type":"Point"}
}