{
  "type": "Feature",
  "properties": {
    "addr:full":"Hill Farm, Lower Somersham Ipswich Suffolk IP8 4PU",
    "addr:postcode":"ip8 4pu",
    "addr:street":"Hill;Lower",
    "iso:country":"GB",
    "sg:address":"Hill Farm, Lower Somersham",
    "sg:city":"Ipswich",
    "sg:classifiers":[
        {
            "category":"Farming",
            "subcategory":"Livestock Farm",
            "type":"Manufacturing & Wholesale Goods"
        }
    ],
    "sg:phone":"+44 1473 658662",
    "sg:postcode":"IP8 4PU",
    "sg:province":"Suffolk",
    "sg:tags":[
        "others"
    ],
    "wof:name":"S M G Whittaker",
    "wof:placetype":"venue"
},
  "geometry": {"coordinates":[1.1081550121,52.0797996521],"type":"Point"}
}