{
  "type": "Feature",
  "properties": {
    "iso:country":"GB",
    "sg:address":"64 The Gravel",
    "sg:city":"Preston",
    "sg:classifiers":[
        {
            "category":"Shopping",
            "subcategory":"Clothing, Apparel, & Fashions",
            "type":"Retail Goods"
        }
    ],
    "sg:phone":"+44 1772 813600",
    "sg:postcode":"PR4 6JX",
    "sg:province":"Lancashire",
    "sg:tags":[
        "dresswear"
    ],
    "wof:name":"Yes Sir",
    "wof:placetype":"venue"
},
  "geometry": {"coordinates":[-2.8846600056,53.6620063782],"type":"Point"}
}