{
  "type": "Feature",
  "properties": {
    "addr:full":"The Gatehouse, Legrams Mill Lane Bradford West Yorkshire BD7 2BA",
    "addr:postcode":"bd7 2ba",
    "addr:street":"Legrams Mill Lane",
    "iso:country":"GB",
    "sg:address":"The Gatehouse, Legrams Mill Lane",
    "sg:city":"Bradford",
    "sg:classifiers":[
        {
            "category":"Cafe",
            "type":"Food & Drink"
        }
    ],
    "sg:postcode":"BD7 2BA",
    "sg:province":"West Yorkshire",
    "sg:tags":[
        "tea",
        "room"
    ],
    "wof:name":"Maks",
    "wof:placetype":"venue"
},
  "geometry": {"coordinates":[-1.787109,53.790459],"type":"Point"}
}