{
  "type": "Feature",
  "properties": {
    "addr:full":"Kirkby Lane Farm, Park Lane, Selston Nottingham Derbyshire NG16 6JG",
    "addr:postcode":"ng16 6jg",
    "addr:street":"Kirkby Lane;Park Lane",
    "iso:country":"GB",
    "sg:address":"Kirkby Lane Farm, Park Lane, Selston",
    "sg:city":"Nottingham",
    "sg:classifiers":[
        {
            "category":"Farming",
            "subcategory":"Livestock Farm",
            "type":"Manufacturing & Wholesale Goods"
        }
    ],
    "sg:postcode":"NG16 6JG",
    "sg:province":"Derbyshire",
    "sg:tags":[
        "others"
    ],
    "wof:name":"P M Briggs",
    "wof:placetype":"venue"
},
  "geometry": {"coordinates":[-1.296042,53.094151],"type":"Point"}
}