{
  "type": "Feature",
  "properties": {
    "addr:full":"79 Marine Road West Morecambe Lancashire LA4 4ER",
    "addr:housenumber":"79",
    "addr:postcode":"la4 4er",
    "addr:street":"Marine Road West Morecambe",
    "iso:country":"GB",
    "sg:address":"79 Marine Road West",
    "sg:city":"Morecambe",
    "sg:classifiers":[
        {
            "category":"Shopping",
            "subcategory":"Florist",
            "type":"Retail Goods"
        }
    ],
    "sg:postcode":"LA4 4ER",
    "sg:province":"Lancashire",
    "wof:name":"Taylor,Terrence,",
    "wof:placetype":"venue"
},
  "geometry": {"coordinates":[-2.879249,54.067173],"type":"Point"}
}