{
  "type": "Feature",
  "properties": {
    "iso:country":"GB",
    "sg:address":"12 High Street, Walcott",
    "sg:city":"Lincoln",
    "sg:classifiers":[
        {
            "category":"Military Area",
            "subcategory":"Army Base",
            "type":"Public Place"
        },
        {
            "category":"Professional",
            "subcategory":"Business Services",
            "type":"Services"
        }
    ],
    "sg:phone":"+44 1526 860520",
    "sg:postcode":"LN4 3SN",
    "sg:province":"Lincolnshire",
    "sg:tags":[
        "transportation",
        "livestock",
        "transport"
    ],
    "wof:name":"Blades Livestock Transport",
    "wof:placetype":"venue"
},
  "geometry": {"coordinates":[-0.3265070021,53.1247406006],"type":"Point"}
}