{
  "type": "Feature",
  "properties": {
    "addr:full":"211 London Road East, Batheaston Bath Bath and North East Somerset BA1 7NB",
    "addr:housenumber":"211",
    "addr:postcode":"ba1 7nb",
    "addr:street":"London Road East",
    "iso:country":"GB",
    "sg:address":"211 London Road East, Batheaston",
    "sg:city":"Bath",
    "sg:classifiers":[
        {
            "category":"Health Services",
            "subcategory":"Doctor",
            "type":"Services"
        },
        {
            "category":"Health Services",
            "subcategory":"Dentist",
            "type":"Services"
        }
    ],
    "sg:phone":"+44 1225 859394",
    "sg:postcode":"BA1 7NB",
    "sg:province":"Bath and North East Somerset",
    "wof:name":"BARTHEASTON DENTAL PRACTICE",
    "wof:placetype":"venue"
},
  "geometry": {"coordinates":[-2.317865,51.405628],"type":"Point"}
}