{
  "type": "Feature",
  "properties": {
    "addr:full":"Burrel Road St Ives Cambridgeshire PE27 3LE",
    "addr:postcode":"pe27 3le",
    "addr:street":"Burrel Road",
    "iso:country":"GB",
    "sg:address":"Burrel Road",
    "sg:city":"St Ives",
    "sg:classifiers":[
        {
            "category":"Shopping",
            "subcategory":"Stationery & Office Supplies",
            "type":"Retail Goods"
        },
        {
            "category":"Professional",
            "subcategory":"Art Services",
            "type":"Services"
        }
    ],
    "sg:phone":"+44 1480 465233",
    "sg:postcode":"PE27 3LE",
    "sg:province":"Cambridgeshire",
    "sg:tags":[
        "graphic",
        "designer",
        "printers'"
    ],
    "wof:name":"C L Enterprises Ltd.",
    "wof:placetype":"venue"
},
  "geometry": {"coordinates":[-0.0645439997,52.33826828],"type":"Point"}
}