{
  "type": "Feature",
  "properties": {
    "iso:country":"GB",
    "sg:address":"191 High St",
    "sg:city":"Gillingham",
    "sg:classifiers":[
        {
            "category":"Communications",
            "subcategory":"Film & Video Production",
            "type":"Services"
        }
    ],
    "sg:postcode":"ME7 1AQ",
    "sg:province":"Kent",
    "sg:tags":[
        "tv"
    ],
    "wof:name":"Tantony,D,",
    "wof:placetype":"venue"
},
  "geometry": {"coordinates":[0.5492849946,51.3865585327],"type":"Point"}
}