{
  "type": "Feature",
  "properties": {
    "iso:country":"GB",
    "sg:address":"Unit 12 Brunswick Street",
    "sg:city":"Darwen",
    "sg:classifiers":[
        {
            "category":"Retail",
            "subcategory":"Auto Repair",
            "type":"Services"
        }
    ],
    "sg:postcode":"BB3 2AJ",
    "sg:province":"Lancashire",
    "sg:tags":[
        "modification",
        "garage"
    ],
    "wof:name":"John Simmonds",
    "wof:placetype":"venue"
},
  "geometry": {"coordinates":[-2.462149,53.693169],"type":"Point"}
}