{
  "type": "Feature",
  "properties": {
    "addr:full":"11a Haven Road Poole Dorset BH13 7LE",
    "addr:housenumber":"11a",
    "addr:postcode":"bh13 7le",
    "addr:street":"Haven Road",
    "iso:country":"GB",
    "sg:address":"11a Haven Road",
    "sg:city":"Poole",
    "sg:classifiers":[
        {
            "category":"Banks & Credit Unions",
            "subcategory":"Investment Brokerage",
            "type":"Services"
        },
        {
            "category":"Banks & Credit Unions",
            "subcategory":"Financial Services",
            "type":"Services"
        }
    ],
    "sg:phone":"+44 1202 706868",
    "sg:postcode":"BH13 7LE",
    "sg:province":"Dorset",
    "sg:tags":[
        "consultant"
    ],
    "wof:name":"J ROTHCHILD & ASSOCIATES",
    "wof:placetype":"venue"
},
  "geometry": {"coordinates":[-1.9207500219,50.7052497864],"type":"Point"}
}