{
  "type": "Feature",
  "properties": {
    "iso:country":"GB",
    "sg:address":"Dutton Road, Aldermans Green Industri",
    "sg:city":"Coventry",
    "sg:classifiers":[
        {
            "category":"Professional",
            "subcategory":"Engineering",
            "type":"Services"
        }
    ],
    "sg:postcode":"CV2 2LE",
    "sg:province":"Warwickshire",
    "wof:name":"Tebunus Ltd.",
    "wof:placetype":"venue"
},
  "geometry": {"coordinates":[-1.461921,52.443558],"type":"Point"}
}