{
  "type": "Feature",
  "properties": {
    "addr:full":"171 North Hyde Road Hayes Greater London UB3 4NS",
    "addr:housenumber":"171",
    "addr:postcode":"ub3 4ns",
    "addr:street":"North Hyde Road",
    "iso:country":"GB",
    "sg:address":"171 North Hyde Road",
    "sg:city":"Hayes",
    "sg:classifiers":[
        {
            "category":"Personal",
            "subcategory":"Beauty Salon",
            "type":"Services"
        }
    ],
    "sg:postcode":"UB3 4NS",
    "sg:province":"Greater London",
    "sg:tags":[
        "unisex",
        "hairdresser"
    ],
    "wof:name":"Sheena's",
    "wof:placetype":"venue"
},
  "geometry": {"coordinates":[-0.41309,51.497906],"type":"Point"}
}