{
  "type": "Feature",
  "properties": {
    "iso:country":"GB",
    "sg:address":"50 Birk Avenue, Kendrick",
    "sg:city":"Barnsley",
    "sg:classifiers":[
        {
            "category":"Building & Trades",
            "subcategory":"Construction",
            "type":"Services"
        }
    ],
    "sg:phone":"+44 1226 219130",
    "sg:postcode":"S70 3AG",
    "sg:province":"South Yorkshire",
    "sg:tags":[
        "roofing"
    ],
    "wof:name":"Kemps Roofing",
    "wof:placetype":"venue"
},
  "geometry": {"coordinates":[-1.453164,53.541531],"type":"Point"}
}