{
  "type": "Feature",
  "properties": {
    "addr:full":"Unit 2a Parnall Road Industrial, Estate Parnall Ro Bristol City of Bristol BS16 3JQ",
    "addr:housenumber":"unit 2a",
    "addr:postcode":"bs16 3jq",
    "addr:street":"Parnall Road Industrial Estate;Ro",
    "iso:country":"GB",
    "sg:address":"Unit 2a Parnall Road Industrial, Estate Parnall Ro",
    "sg:city":"Bristol",
    "sg:classifiers":[
        {
            "category":"Manufacturing",
            "subcategory":"Paper Products",
            "type":"Manufacturing & Wholesale Goods"
        }
    ],
    "sg:phone":"+44 117 965 5259",
    "sg:postcode":"BS16 3JQ",
    "sg:province":"City of Bristol",
    "sg:tags":[
        "cardboard"
    ],
    "wof:name":"J M L Packaging Services Ltd.",
    "wof:placetype":"venue"
},
  "geometry": {"coordinates":[-2.533299,51.476349],"type":"Point"}
}