{
  "type": "Feature",
  "properties": {
    "addr:full":"37 Lower York St Wakefield West Yorkshire WF3 1RN",
    "addr:housenumber":"37",
    "addr:postcode":"wf3 1rn",
    "addr:street":"Lower York St",
    "iso:country":"GB",
    "sg:address":"37 Lower York St",
    "sg:city":"Wakefield",
    "sg:classifiers":[
        {
            "category":"Food & Beverages",
            "subcategory":"Liquor & Beverages",
            "type":"Retail Goods"
        }
    ],
    "sg:phone":"+44 1924 373183",
    "sg:postcode":"WF3 1RN",
    "sg:province":"West Yorkshire",
    "sg:tags":[
        "beer",
        "spirit",
        "wines"
    ],
    "wof:name":"Novakovic & Budimir",
    "wof:placetype":"venue"
},
  "geometry": {"coordinates":[-1.4984610081,53.6867027283],"type":"Point"}
}