{
  "type": "Feature",
  "properties": {
    "iso:country":"GB",
    "sg:address":"Wilsthorpe Road, Long Eaton",
    "sg:city":"Nottingham",
    "sg:classifiers":[
        {
            "category":"Restaurant",
            "type":"Food & Drink"
        }
    ],
    "sg:phone":"+44 115 946 2613",
    "sg:postcode":"NG10 3AW",
    "sg:province":"Derbyshire",
    "wof:name":"Milestone Restaurants",
    "wof:placetype":"venue"
},
  "geometry": {"coordinates":[-1.291834,52.895229],"type":"Point"}
}