{
  "type": "Feature",
  "properties": {
    "addr:full":"Woodfalls Ind Est, Gravelly Ways, Laddingford Maidstone Kent ME18 6DA",
    "addr:postcode":"me18 6da",
    "iso:country":"GB",
    "sg:address":"Woodfalls Ind Est, Gravelly Ways, Laddingford",
    "sg:city":"Maidstone",
    "sg:classifiers":[
        {
            "category":"Communications",
            "subcategory":"Film & Video Production",
            "type":"Services"
        }
    ],
    "sg:phone":"+44 1622 871116",
    "sg:postcode":"ME18 6DA",
    "sg:province":"Kent",
    "sg:tags":[
        "equipment",
        "cctv",
        "mnfr"
    ],
    "wof:name":"Event Security Systems Ltd",
    "wof:placetype":"venue"
},
  "geometry": {"coordinates":[0.4181280136,51.2064170837],"type":"Point"}
}