{
  "type": "Feature",
  "properties": {
    "addr:full":"West Allington Bridport Dorset DT6 5BW",
    "addr:postcode":"dt6 5bw",
    "addr:street":"West",
    "iso:country":"GB",
    "sg:address":"West Allington",
    "sg:city":"Bridport",
    "sg:classifiers":[
        {
            "category":"Autos & Motor Vehicles",
            "subcategory":"Automobile Sales",
            "type":"Retail Goods"
        },
        {
            "category":"Retail",
            "subcategory":"Auto Repair",
            "type":"Services"
        }
    ],
    "sg:phone":"+44 1308 422611",
    "sg:postcode":"DT6 5BW",
    "sg:province":"Dorset",
    "sg:tags":[
        "modification",
        "garage",
        "car"
    ],
    "wof:name":"West Road Garage",
    "wof:placetype":"venue"
},
  "geometry": {"coordinates":[-2.77089,50.73439],"type":"Point"}
}