{
  "type": "Feature",
  "properties": {
    "addr:full":"York House, 9 British Road St Agnes Cornwall TR5 0TX",
    "addr:housenumber":"9",
    "addr:postcode":"tr5 0tx",
    "addr:street":"British Road",
    "iso:country":"GB",
    "sg:address":"York House, 9 British Road",
    "sg:city":"St Agnes",
    "sg:classifiers":[
        {
            "category":"Health Services",
            "subcategory":"Dentist",
            "type":"Services"
        }
    ],
    "sg:phone":"+44 1872 552353",
    "sg:postcode":"TR5 0TX",
    "sg:province":"Cornwall",
    "wof:name":"McMahon & Ashworth",
    "wof:placetype":"venue"
},
  "geometry": {"coordinates":[-5.2019629478,50.3105812073],"type":"Point"}
}