{
  "type": "Feature",
  "properties": {
    "addr:full":"Middleton Avenue, Strutherhill Industrial Estate Larkhall South Lanarkshire ML9 2TL",
    "addr:postcode":"ml9 2tl",
    "addr:street":"Middleton Avenue Strutherhill Industrial Estate",
    "iso:country":"GB",
    "sg:address":"Middleton Avenue, Strutherhill Industrial Estate",
    "sg:city":"Larkhall",
    "sg:classifiers":[
        {
            "category":"Manufacturing",
            "subcategory":"Tools & Machinery",
            "type":"Manufacturing & Wholesale Goods"
        }
    ],
    "sg:phone":"+44 1698 883100",
    "sg:postcode":"ML9 2TL",
    "sg:province":"South Lanarkshire",
    "sg:tags":[
        "design",
        "maker"
    ],
    "wof:name":"Green Brothers (U K) Ltd.",
    "wof:placetype":"venue"
},
  "geometry": {"coordinates":[-3.9592349529,55.7248153687],"type":"Point"}
}