{
  "type": "Feature",
  "properties": {
    "iso:country":"GB",
    "sg:address":"Compass Road, Silfield",
    "sg:city":"Wymondham",
    "sg:classifiers":[
        {
            "category":"Shopping",
            "type":"Retail Goods"
        }
    ],
    "sg:postcode":"NR18 9NN",
    "sg:province":"Norfolk",
    "sg:tags":[
        "part",
        "accessory"
    ],
    "wof:name":"John Drake",
    "wof:placetype":"venue"
},
  "geometry": {"coordinates":[1.127271,52.551933],"type":"Point"}
}