{
  "type": "Feature",
  "properties": {
    "iso:country":"GB",
    "sg:address":"8 Parkway Centre, Coulby Newham",
    "sg:city":"Middlesbrough",
    "sg:classifiers":[
        {
            "category":"Shopping",
            "subcategory":"Pets & Pet Supplies",
            "type":"Retail Goods"
        }
    ],
    "sg:phone":"+44 1642 599506",
    "sg:postcode":"TS8 0TJ",
    "sg:province":"North Yorkshire",
    "wof:name":"Middlesborough Rawhide Chew Co",
    "wof:placetype":"venue"
},
  "geometry": {"coordinates":[-1.222629,54.528839],"type":"Point"}
}