{
  "type": "Feature",
  "properties": {
    "addr:full":"631 Old Kent Road London Greater London SE15 1JU",
    "addr:housenumber":"631",
    "addr:postcode":"se15 1ju",
    "addr:street":"Old Kent Road",
    "iso:country":"GB",
    "sg:address":"631 Old Kent Road",
    "sg:city":"London",
    "sg:classifiers":[
        {
            "category":"Autos & Motor Vehicles",
            "subcategory":"Automobile Sales",
            "type":"Retail Goods"
        }
    ],
    "sg:phone":"+44 20 7732 1750",
    "sg:postcode":"SE15 1JU",
    "sg:province":"Greater London",
    "sg:tags":[
        "commercial"
    ],
    "wof:name":"S M Motors",
    "wof:placetype":"venue"
},
  "geometry": {"coordinates":[-0.0628850013,51.4827423096],"type":"Point"}
}