{
  "type": "Feature",
  "properties": {
    "addr:full":"308 Meltham Road Huddersfield West Yorkshire HD4 7EX",
    "addr:housenumber":"308",
    "addr:postcode":"hd4 7ex",
    "addr:street":"Meltham Road",
    "iso:country":"GB",
    "sg:address":"308 Meltham Road",
    "sg:city":"Huddersfield",
    "sg:classifiers":[
        {
            "category":"Food & Beverages",
            "subcategory":"Meat & Fish",
            "type":"Retail Goods"
        }
    ],
    "sg:postcode":"HD4 7EX",
    "sg:province":"West Yorkshire",
    "sg:tags":[
        "butcher"
    ],
    "wof:name":"Richard Hirst",
    "wof:placetype":"venue"
},
  "geometry": {"coordinates":[-1.8140799999,53.6153411865],"type":"Point"}
}