{
  "type": "Feature",
  "properties": {
    "iso:country":"GB",
    "sg:address":"4 Grovesnor Place",
    "sg:city":"London",
    "sg:classifiers":[
        {
            "category":"Professional",
            "subcategory":"Engineering",
            "type":"Services"
        }
    ],
    "sg:phone":"+44 20 7823 0700",
    "sg:postcode":"SW1X 7PG",
    "sg:province":"Greater London",
    "sg:tags":[
        "consulting",
        "engineer"
    ],
    "wof:name":"Parsons Group International Ltd.",
    "wof:placetype":"venue"
},
  "geometry": {"coordinates":[-0.151187,51.501541],"type":"Point"}
}