{
  "type": "Feature",
  "properties": {
    "iso:country":"GB",
    "sg:address":"294 Brentwood Road",
    "sg:city":"Romford",
    "sg:classifiers":[
        {
            "category":"Manufacturing",
            "subcategory":"Furniture",
            "type":"Manufacturing & Wholesale Goods"
        }
    ],
    "sg:phone":"+44 1708 446203",
    "sg:postcode":"RM2 5TA",
    "sg:province":"Essex",
    "sg:tags":[
        "polishing",
        "french"
    ],
    "wof:name":"D Tyler",
    "wof:placetype":"venue"
},
  "geometry": {"coordinates":[0.205294,51.574986],"type":"Point"}
}