{
  "type": "Feature",
  "properties": {
    "addr:full":"12 Timber Bush Edinburgh City of Edinburgh EH6 6QH",
    "addr:housenumber":"12",
    "addr:postcode":"eh6 6qh",
    "addr:street":"Timber Bush Edinburgh",
    "iso:country":"GB",
    "sg:address":"12 Timber Bush",
    "sg:city":"Edinburgh",
    "sg:classifiers":[
        {
            "category":"Food & Beverages",
            "subcategory":"Meat & Fish",
            "type":"Retail Goods"
        }
    ],
    "sg:phone":"+44 131 554 9340",
    "sg:postcode":"EH6 6QH",
    "sg:province":"City of Edinburgh",
    "sg:tags":[
        "merchant"
    ],
    "wof:name":"Denholm Seafoods Ltd.",
    "wof:placetype":"venue"
},
  "geometry": {"coordinates":[-3.1681830883,55.9765815735],"type":"Point"}
}