{
  "type": "Feature",
  "properties": {
    "addr:full":"21 Cumberland Avenue Emsworth Hampshire PO10 7UH",
    "addr:housenumber":"21",
    "addr:postcode":"po10 7uh",
    "addr:street":"Cumberland Avenue",
    "iso:country":"GB",
    "sg:address":"21 Cumberland Avenue",
    "sg:city":"Emsworth",
    "sg:classifiers":[
        {
            "category":"Building & Trades",
            "subcategory":"Landscaping Services",
            "type":"Services"
        }
    ],
    "sg:phone":"+44 23 9257 1777",
    "sg:postcode":"PO10 7UH",
    "sg:province":"Hampshire",
    "sg:tags":[
        "landscape",
        "contractor"
    ],
    "wof:name":"Professional Lawn Services",
    "wof:placetype":"venue"
},
  "geometry": {"coordinates":[-0.942456007,50.8629150391],"type":"Point"}
}