{
  "type": "Feature",
  "properties": {
    "addr:full":"23 Sidney St, Swinton Mexborough South Yorkshire S64 8LT",
    "addr:housenumber":"23",
    "addr:postcode":"s64 8lt",
    "addr:street":"Sidney St",
    "iso:country":"GB",
    "sg:address":"23 Sidney St, Swinton",
    "sg:city":"Mexborough",
    "sg:classifiers":[
        {
            "category":"Professional",
            "type":"Services"
        }
    ],
    "sg:postcode":"S64 8LT",
    "sg:province":"South Yorkshire",
    "sg:tags":[
        "reflexologists"
    ],
    "wof:name":"Lund,Helen E,",
    "wof:placetype":"venue"
},
  "geometry": {"coordinates":[-1.3094650507,53.4874420166],"type":"Point"}
}