{
  "type": "Feature",
  "properties": {
    "addr:full":"34 The High Street, Old Woking Woking Surrey GU22 9ER",
    "addr:housenumber":"34",
    "addr:postcode":"gu22 9er",
    "addr:street":"The High Street",
    "iso:country":"GB",
    "sg:address":"34 The High Street, Old Woking",
    "sg:city":"Woking",
    "sg:classifiers":[
        {
            "category":"Building & Trades",
            "subcategory":"Construction",
            "type":"Services"
        }
    ],
    "sg:phone":"+44 1483 766106",
    "sg:postcode":"GU22 9ER",
    "sg:province":"Surrey",
    "sg:tags":[
        "builder"
    ],
    "wof:name":"J E Ellesley Builder & Contractor Ltd.",
    "wof:placetype":"venue"
},
  "geometry": {"coordinates":[-0.539729,51.301659],"type":"Point"}
}