{
  "type": "Feature",
  "properties": {
    "addr:full":"Block 8 Unit 2 Stevenston North Ayrshire KA20 3JT",
    "addr:housenumber":"unit 2",
    "addr:postcode":"ka20 3jt",
    "iso:country":"GB",
    "sg:address":"Block 8 Unit 2",
    "sg:city":"Stevenston",
    "sg:classifiers":[
        {
            "category":"Ice Cream",
            "type":"Food & Drink"
        }
    ],
    "sg:postcode":"KA20 3JT",
    "sg:province":"North Ayrshire",
    "sg:tags":[
        "shop",
        "mobile",
        "parlour"
    ],
    "wof:name":"Joes Ices",
    "wof:placetype":"venue"
},
  "geometry": {"coordinates":[-4.7562508583,55.6429252625],"type":"Point"}
}