{
  "type": "Feature",
  "properties": {
    "addr:full":"41 Crescent Road Burgess Hill East Sussex RH15 8EH",
    "addr:housenumber":"41",
    "addr:postcode":"rh15 8eh",
    "addr:street":"Crescent Road",
    "iso:country":"GB",
    "sg:address":"41 Crescent Road",
    "sg:city":"Burgess Hill",
    "sg:classifiers":[
        {
            "category":"Building & Trades",
            "subcategory":"Construction",
            "type":"Services"
        }
    ],
    "sg:phone":"+44 1444 243319",
    "sg:postcode":"RH15 8EH",
    "sg:province":"East Sussex",
    "sg:tags":[
        "heating",
        "contractor"
    ],
    "wof:name":"Keith Parsons & Son",
    "wof:placetype":"venue"
},
  "geometry": {"coordinates":[-0.129438,50.958191],"type":"Point"}
}