{
  "type": "Feature",
  "properties": {
    "iso:country":"GB",
    "sg:address":"Hook Lane",
    "sg:city":"Ipswich",
    "sg:classifiers":[
        {
            "category":"Wholesale",
            "subcategory":"Fruits & Vegetables",
            "type":"Manufacturing & Wholesale Goods"
        }
    ],
    "sg:phone":"+44 1473 823260",
    "sg:postcode":"IP7 5PH",
    "sg:province":"Suffolk",
    "wof:name":"Stackfield Orchard",
    "wof:placetype":"venue"
},
  "geometry": {"coordinates":[0.970607,52.035564],"type":"Point"}
}