{
  "type": "Feature",
  "properties": {
    "addr:full":"71 Camberton Road, Linslade Leighton Buzzard Bedfordshire LU7 2UW",
    "addr:housenumber":"71",
    "addr:postcode":"lu7 2uw",
    "addr:street":"Camberton Road",
    "iso:country":"GB",
    "sg:address":"71 Camberton Road, Linslade",
    "sg:city":"Leighton Buzzard",
    "sg:classifiers":[
        {
            "category":"Shopping",
            "subcategory":"Antiques",
            "type":"Retail Goods"
        }
    ],
    "sg:postcode":"LU7 2UW",
    "sg:province":"Bedfordshire",
    "wof:name":"The Archway Gallery",
    "wof:placetype":"venue"
},
  "geometry": {"coordinates":[-0.6710289717,51.9107704163],"type":"Point"}
}