{
  "type": "Feature",
  "properties": {
    "addr:full":"Eurohub Midlands, Birch Lane, Stonall Walsall Staffordshire WS9 0NF",
    "addr:postcode":"ws9 0nf",
    "addr:street":"Birch Lane",
    "iso:country":"GB",
    "sg:address":"Eurohub Midlands, Birch Lane, Stonall",
    "sg:city":"Walsall",
    "sg:classifiers":[
        {
            "category":"Airline",
            "type":"Transportation"
        }
    ],
    "sg:phone":"+44 1922 745747",
    "sg:postcode":"WS9 0NF",
    "sg:province":"Staffordshire",
    "sg:tags":[
        "aircraft",
        "charter"
    ],
    "wof:name":"Aviation Consultants Ltd.",
    "wof:placetype":"venue"
},
  "geometry": {"coordinates":[-1.8994699717,52.618938446],"type":"Point"}
}