{
  "type": "Feature",
  "properties": {
    "addr:full":"69 Schaw Drive, Bearsden Glasgow East Dunbartonshire G61 3SB",
    "addr:housenumber":"69",
    "addr:postcode":"g61 3sb",
    "addr:street":"Schaw Drive",
    "iso:country":"GB",
    "sg:address":"69 Schaw Drive, Bearsden",
    "sg:city":"Glasgow",
    "sg:classifiers":[
        {
            "category":"Health Services",
            "subcategory":"Nursing And Care Facility",
            "type":"Services"
        }
    ],
    "sg:phone":"+44 141 943 0087",
    "sg:postcode":"G61 3SB",
    "sg:province":"East Dunbartonshire",
    "sg:tags":[
        "home"
    ],
    "wof:name":"Private Nursing Homes of Glasgow Ltd.",
    "wof:placetype":"venue"
},
  "geometry": {"coordinates":[-4.3380541801,55.9265403748],"type":"Point"}
}