{
  "type": "Feature",
  "properties": {
    "addr:full":"Deeside Hospital, Plough Lane Deeside Flintshire CH5 1XX",
    "addr:postcode":"ch5 1xx",
    "addr:street":"Plough Lane",
    "iso:country":"GB",
    "sg:address":"Deeside Hospital, Plough Lane",
    "sg:city":"Deeside",
    "sg:classifiers":[
        {
            "category":"Health Services",
            "subcategory":"Dentist",
            "type":"Services"
        }
    ],
    "sg:phone":"+44 1244 815241",
    "sg:postcode":"CH5 1XX",
    "sg:province":"Flintshire",
    "wof:name":"Shotton Community Dental Clinic",
    "wof:placetype":"venue"
},
  "geometry": {"coordinates":[-3.0296239853,53.208366394],"type":"Point"}
}