{
  "type": "Feature",
  "properties": {
    "iso:country":"GB",
    "sg:address":"Milton House, Market Street",
    "sg:city":"Atherstone",
    "sg:classifiers":[
        {
            "category":"Organizations",
            "subcategory":"Membership Organization",
            "type":"Services"
        }
    ],
    "sg:phone":"+44 1827 714485",
    "sg:postcode":"CV9 1ET",
    "sg:province":"Leicestershire",
    "sg:tags":[
        "club"
    ],
    "wof:name":"Atherstone Ex-Service Men's Club & Institute Ltd.",
    "wof:placetype":"venue"
},
  "geometry": {"coordinates":[-1.5464140177,52.5779342651],"type":"Point"}
}