{
  "type": "Feature",
  "properties": {
    "addr:full":"3-5 St Johns Precinct Workington Cumbria CA14 3BD",
    "addr:housenumber":"3-5",
    "addr:postcode":"ca14 3bd",
    "addr:street":"St Johns Precinct Workington",
    "iso:country":"GB",
    "sg:address":"3-5 St Johns Precinct",
    "sg:city":"Workington",
    "sg:classifiers":[
        {
            "category":"Shopping",
            "subcategory":"Shoes",
            "type":"Retail Goods"
        }
    ],
    "sg:phone":"+44 1900 61135",
    "sg:postcode":"CA14 3BD",
    "sg:province":"Cumbria",
    "sg:tags":[
        "shop"
    ],
    "wof:name":"Barratt Shoes",
    "wof:placetype":"venue"
},
  "geometry": {"coordinates":[-3.544629,54.642288],"type":"Point"}
}