{
  "type": "Feature",
  "properties": {
    "iso:country":"GB",
    "sg:address":"7 Elm Tree Avenue, Westfield, Radstock",
    "sg:city":"Bath",
    "sg:classifiers":[
        {
            "category":"Food & Beverages",
            "subcategory":"Groceries & Convenience Stores",
            "type":"Retail Goods"
        }
    ],
    "sg:phone":"+44 1761 436932",
    "sg:postcode":"BA3 3SX",
    "sg:province":"Somerset",
    "wof:name":"Elm Tree Stores",
    "wof:placetype":"venue"
},
  "geometry": {"coordinates":[-2.4654500484,51.2865524292],"type":"Point"}
}