{
  "type": "Feature",
  "properties": {
    "addr:full":"212 Broomhouse Road Edinburgh City of Edinburgh EH12 9AE",
    "addr:housenumber":"212",
    "addr:postcode":"eh12 9ae",
    "addr:street":"Broomhouse Road",
    "iso:country":"GB",
    "sg:address":"212 Broomhouse Road",
    "sg:city":"Edinburgh",
    "sg:classifiers":[
        {
            "category":"Education",
            "subcategory":"School",
            "type":"Public Place"
        }
    ],
    "sg:phone":"+44 131 334 9262",
    "sg:postcode":"EH12 9AE",
    "sg:province":"City of Edinburgh",
    "sg:tags":[
        "local",
        "authority"
    ],
    "wof:name":"Forrester High School",
    "wof:placetype":"venue"
},
  "geometry": {"coordinates":[-3.287613,55.932686],"type":"Point"}
}