{
  "type": "Feature",
  "properties": {
    "iso:country":"GB",
    "sg:address":"Symonds Farm Ind Est, Great Saxham",
    "sg:city":"Bury St Edmunds",
    "sg:classifiers":[
        {
            "category":"Freight",
            "type":"Transportation"
        }
    ],
    "sg:phone":"+44 1284 811939",
    "sg:postcode":"IP29 5JU",
    "sg:province":"Suffolk",
    "sg:tags":[
        "haulage",
        "road"
    ],
    "wof:name":"Pallex",
    "wof:placetype":"venue"
},
  "geometry": {"coordinates":[0.6181150079,52.2340164185],"type":"Point"}
}