{
  "type": "Feature",
  "properties": {
    "addr:full":"2 Manor Gardens London Greater London N7 6JZ",
    "addr:housenumber":"2",
    "addr:postcode":"n7 6jz",
    "addr:street":"Manor Gardens",
    "iso:country":"GB",
    "sg:address":"2 Manor Gardens",
    "sg:city":"London",
    "sg:classifiers":[
        {
            "category":"Real Estate",
            "subcategory":"Real Estate Operator",
            "type":"Services"
        },
        {
            "category":"Organizations",
            "subcategory":"Non-profit Organization",
            "type":"Services"
        }
    ],
    "sg:postcode":"N7 6JZ",
    "sg:province":"Greater London",
    "sg:tags":[
        "letting",
        "organisation",
        "voluntary",
        "agent",
        "charity"
    ],
    "wof:name":"The National Association for the Care & Resettlement of Offenders",
    "wof:placetype":"venue"
},
  "geometry": {"coordinates":[-0.122507,51.560455],"type":"Point"}
}