{
  "type": "Feature",
  "properties": {
    "iso:country":"GB",
    "sg:address":"2 Brighton Cotts, Main Street, Offenham",
    "sg:city":"Evesham",
    "sg:classifiers":[
        {
            "category":"Building & Trades",
            "subcategory":"Construction",
            "type":"Services"
        }
    ],
    "sg:postcode":"WR11 8RX",
    "sg:province":"Gloucestershire",
    "sg:tags":[
        "decorator",
        "painter"
    ],
    "wof:name":"Morris H Sandalls",
    "wof:placetype":"venue"
},
  "geometry": {"coordinates":[-1.9213459492,52.1116752625],"type":"Point"}
}