{
  "type": "Feature",
  "properties": {
    "addr:full":"High St Tewkesbury Gloucestershire GL20 5JZ",
    "addr:postcode":"gl20 5jz",
    "addr:street":"High St",
    "iso:country":"GB",
    "sg:address":"High St",
    "sg:city":"Tewkesbury",
    "sg:classifiers":[
        {
            "category":"Government",
            "subcategory":"Post Office",
            "type":"Public Place"
        }
    ],
    "sg:phone":"+44 1684 293232",
    "sg:postcode":"GL20 5JZ",
    "sg:province":"Gloucestershire",
    "wof:name":"Tewkesbury M S P O",
    "wof:placetype":"venue"
},
  "geometry": {"coordinates":[-2.153909,51.997746],"type":"Point"}
}