{
  "type": "Feature",
  "properties": {
    "addr:full":"1a Lime Street Bedford Bedfordshire MK40 1LD",
    "addr:housenumber":"1a",
    "addr:postcode":"mk40 1ld",
    "addr:street":"Lime Street",
    "iso:country":"GB",
    "sg:address":"1a Lime Street",
    "sg:city":"Bedford",
    "sg:classifiers":[
        {
            "category":"Professional",
            "subcategory":"Testing Lab",
            "type":"Services"
        }
    ],
    "sg:phone":"+44 1234 363344",
    "sg:postcode":"MK40 1LD",
    "sg:province":"Bedfordshire",
    "sg:tags":[
        "pregnancy"
    ],
    "wof:name":"Life",
    "wof:placetype":"venue"
},
  "geometry": {"coordinates":[-0.467537,52.138],"type":"Point"}
}