{
  "type": "Feature",
  "properties": {
    "iso:country":"GB",
    "sg:address":"1 Wellington Road",
    "sg:city":"Mablethorpe",
    "sg:classifiers":[
        {
            "category":"Shopping",
            "subcategory":"Crafts & Fabrics",
            "type":"Retail Goods"
        }
    ],
    "sg:postcode":"LN12 1HR",
    "sg:province":"Lincolnshire",
    "sg:tags":[
        "shop",
        "needlecraft",
        "wool"
    ],
    "wof:name":"The Fent Shop",
    "wof:placetype":"venue"
},
  "geometry": {"coordinates":[0.2602440119,53.3420982361],"type":"Point"}
}