{
  "type": "Feature",
  "properties": {
    "addr:full":"462 Fulham Rd London Greater London SW6 1DN",
    "addr:housenumber":"462",
    "addr:postcode":"sw6 1dn",
    "addr:street":"Fulham Rd",
    "iso:country":"GB",
    "sg:address":"462 Fulham Rd",
    "sg:city":"London",
    "sg:classifiers":[
        {
            "category":"Professional",
            "subcategory":"Art Services",
            "type":"Services"
        }
    ],
    "sg:postcode":"SW6 1DN",
    "sg:province":"Greater London",
    "sg:tags":[
        "framing"
    ],
    "wof:name":"Coleman,Timothy,",
    "wof:placetype":"venue"
},
  "geometry": {"coordinates":[-0.194518,51.480175],"type":"Point"}
}