{
  "type": "Feature",
  "properties": {
    "iso:country":"GB",
    "sg:address":"Eros Business Pk, Kenny Hill",
    "sg:city":"Bury St Edmunds",
    "sg:classifiers":[
        {
            "category":"Shopping",
            "subcategory":"Used Merchandise",
            "type":"Retail Goods"
        }
    ],
    "sg:postcode":"IP28 8DS",
    "sg:province":"Cambridgeshire",
    "sg:tags":[
        "shop",
        "second-hand",
        "furniture"
    ],
    "wof:name":"Shackleton,L,",
    "wof:placetype":"venue"
},
  "geometry": {"coordinates":[0.45862,52.382172],"type":"Point"}
}