{
  "type": "Feature",
  "properties": {
    "addr:full":"54 Wimpole Road Colchester Essex CO1 2DL",
    "addr:housenumber":"54",
    "addr:postcode":"co1 2dl",
    "addr:street":"Wimpole Road Colchester",
    "iso:country":"GB",
    "sg:address":"54 Wimpole Road",
    "sg:city":"Colchester",
    "sg:classifiers":[
        {
            "category":"Health Services",
            "subcategory":"Dentist",
            "type":"Services"
        }
    ],
    "sg:phone":"+44 1206 796326",
    "sg:postcode":"CO1 2DL",
    "sg:province":"Essex",
    "wof:name":"Wimpole Road Dental Surgeons",
    "wof:placetype":"venue"
},
  "geometry": {"coordinates":[0.9136850238,51.8807868958],"type":"Point"}
}