{
  "type": "Feature",
  "properties": {
    "addr:full":"14 New Road Brighton East Sussex BN1 1UF",
    "addr:housenumber":"14",
    "addr:postcode":"bn1 1uf",
    "addr:street":"New Road",
    "iso:country":"GB",
    "sg:address":"14 New Road",
    "sg:city":"Brighton",
    "sg:classifiers":[
        {
            "category":"Health Services",
            "subcategory":"Doctor",
            "type":"Services"
        }
    ],
    "sg:postcode":"BN1 1UF",
    "sg:province":"East Sussex",
    "sg:tags":[
        "practitioners"
    ],
    "wof:name":"The Foundation For Traditional Medicine Ltd",
    "wof:placetype":"venue"
},
  "geometry": {"coordinates":[-0.139609,50.82338],"type":"Point"}
}