{
  "type": "Feature",
  "properties": {
    "addr:full":"23 Queen Street Oldham Lancashire OL1 1RD",
    "addr:housenumber":"23",
    "addr:postcode":"ol1 1rd",
    "addr:street":"Queen Street",
    "iso:country":"GB",
    "sg:address":"23 Queen Street",
    "sg:city":"Oldham",
    "sg:classifiers":[
        {
            "category":"Professional",
            "subcategory":"Lawyer & Legal Services",
            "type":"Services"
        }
    ],
    "sg:phone":"+44 161 678 7996",
    "sg:postcode":"OL1 1RD",
    "sg:province":"Lancashire",
    "sg:tags":[
        "conveyancing"
    ],
    "wof:name":"Peter Robinson & Co. Ltd.",
    "wof:placetype":"venue"
},
  "geometry": {"coordinates":[-2.109479,53.541534],"type":"Point"}
}