{
  "type": "Feature",
  "properties": {
    "addr:full":"Crown Buildings, The Walnuts Orpington Kent BR6 0TL",
    "addr:postcode":"br6 0tl",
    "addr:street":"Walnuts",
    "iso:country":"GB",
    "sg:address":"Crown Buildings, The Walnuts",
    "sg:city":"Orpington",
    "sg:classifiers":[
        {
            "category":"Professional",
            "subcategory":"Employment Agencies",
            "type":"Services"
        }
    ],
    "sg:phone":"+44 1689 303555",
    "sg:postcode":"BR6 0TL",
    "sg:province":"Kent",
    "sg:tags":[
        "consultant"
    ],
    "wof:name":"Orpington Job Centre",
    "wof:placetype":"venue"
},
  "geometry": {"coordinates":[0.10108,51.37804],"type":"Point"}
}