{
  "type": "Feature",
  "properties": {
    "addr:full":"74 Roundstone Drive, East Preston Littlehampton West Sussex BN16 1ER",
    "addr:housenumber":"74",
    "addr:postcode":"bn16 1er",
    "addr:street":"Roundstone Drive",
    "iso:country":"GB",
    "sg:address":"74 Roundstone Drive, East Preston",
    "sg:city":"Littlehampton",
    "sg:classifiers":[
        {
            "category":"Building & Trades",
            "subcategory":"Construction",
            "type":"Services"
        }
    ],
    "sg:postcode":"BN16 1ER",
    "sg:province":"West Sussex",
    "sg:tags":[
        "roofing"
    ],
    "wof:name":"Arun Asphalt",
    "wof:placetype":"venue"
},
  "geometry": {"coordinates":[-0.478625,50.814877],"type":"Point"}
}