{
  "type": "Feature",
  "properties": {
    "addr:full":"15 Moraine Avenue, Blairdardie Glasgow Glasgow City G15 6HD",
    "addr:housenumber":"15",
    "addr:postcode":"g15 6hd",
    "addr:street":"Moraine Avenue",
    "iso:country":"GB",
    "sg:address":"15 Moraine Avenue, Blairdardie",
    "sg:city":"Glasgow",
    "sg:classifiers":[
        {
            "category":"Taxi",
            "type":"Transportation"
        }
    ],
    "sg:phone":"+44 141 944 1111",
    "sg:postcode":"G15 6HD",
    "sg:province":"Glasgow City",
    "sg:tags":[
        "mini",
        "cab"
    ],
    "wof:name":"Drumchapel & North Glasgow Private Hire Cars",
    "wof:placetype":"venue"
},
  "geometry": {"coordinates":[-4.360492,55.901917],"type":"Point"}
}