{
  "type": "Feature",
  "properties": {
    "addr:full":"103 Chapelton Drive, Polbeth West Calder South Lanarkshire EH55 8SQ",
    "addr:housenumber":"103",
    "addr:postcode":"eh55 8sq",
    "addr:street":"Chapelton Drive Polbeth West",
    "iso:country":"GB",
    "sg:address":"103 Chapelton Drive, Polbeth",
    "sg:city":"West Calder",
    "sg:classifiers":[
        {
            "category":"Personal",
            "subcategory":"Beauty Salon",
            "type":"Services"
        }
    ],
    "sg:postcode":"EH55 8SQ",
    "sg:province":"South Lanarkshire",
    "sg:tags":[
        "unisex",
        "hairdresser"
    ],
    "wof:name":"Hair-Biz",
    "wof:placetype":"venue"
},
  "geometry": {"coordinates":[-3.551254,55.858402],"type":"Point"}
}