{
  "type": "Feature",
  "properties": {
    "iso:country":"GB",
    "sg:address":"151 Eastfield Rd",
    "sg:city":"Louth",
    "sg:classifiers":[
        {
            "category":"Taxi",
            "type":"Transportation"
        },
        {
            "category":"Military Area",
            "subcategory":"Air Force Base",
            "type":"Public Place"
        }
    ],
    "sg:postcode":"LN11 7AS",
    "sg:province":"Lincolnshire",
    "sg:tags":[
        "mini",
        "hire",
        "private",
        "cab"
    ],
    "wof:name":"Butler,Peter,",
    "wof:placetype":"venue"
},
  "geometry": {"coordinates":[0.0153339999,53.3729248047],"type":"Point"}
}