{
  "type": "Feature",
  "properties": {
    "addr:full":"St Cripsin, Duke Street Norwich Norfolk NR3 1PD",
    "addr:postcode":"nr3 1pd",
    "addr:street":"Duke Street",
    "iso:country":"GB",
    "sg:address":"St Cripsin, Duke Street",
    "sg:city":"Norwich",
    "sg:classifiers":[
        {
            "category":"Professional",
            "subcategory":"Lawyer & Legal Services",
            "type":"Services"
        }
    ],
    "sg:phone":"+44 1603 617617",
    "sg:postcode":"NR3 1PD",
    "sg:province":"Norfolk",
    "wof:name":"Countrywide Legal Indemnities Ltd.",
    "wof:placetype":"venue"
},
  "geometry": {"coordinates":[1.2930879593,52.6353111267],"type":"Point"}
}