{
  "type": "Feature",
  "properties": {
    "iso:country":"GB",
    "sg:address":"Allhallows Road, Lower Stoke",
    "sg:city":"Rochester",
    "sg:classifiers":[
        {
            "category":"Education",
            "subcategory":"School",
            "type":"Public Place"
        }
    ],
    "sg:phone":"+44 1634 270268",
    "sg:postcode":"ME3 9SL",
    "sg:province":"Kent",
    "sg:tags":[
        "local",
        "authority"
    ],
    "wof:name":"Stoke County Primary School",
    "wof:placetype":"venue"
},
  "geometry": {"coordinates":[0.6366400123,51.4565162659],"type":"Point"}
}