{
  "type": "Feature",
  "properties": {
    "addr:full":"70 Saxon Leas, Winterslow Salisbury Dorset SP5 1RW",
    "addr:housenumber":"70",
    "addr:postcode":"sp5 1rw",
    "addr:street":"Saxon Leas",
    "iso:country":"GB",
    "sg:address":"70 Saxon Leas, Winterslow",
    "sg:city":"Salisbury",
    "sg:classifiers":[
        {
            "category":"Building & Trades",
            "subcategory":"Landscaping Services",
            "type":"Services"
        }
    ],
    "sg:postcode":"SP5 1RW",
    "sg:province":"Dorset",
    "sg:tags":[
        "landscape",
        "contractor"
    ],
    "wof:name":"Amco",
    "wof:placetype":"venue"
},
  "geometry": {"coordinates":[-1.6518690586,51.0945968628],"type":"Point"}
}