{
  "type": "Feature",
  "properties": {
    "iso:country":"GB",
    "sg:address":"Kew Bridge Railway Depot North, Lionel Rd",
    "sg:city":"Brentford",
    "sg:classifiers":[
        {
            "category":"Bus Charters",
            "type":"Transportation"
        }
    ],
    "sg:phone":"+44 20 8995 1111",
    "sg:postcode":"TW8 0JA",
    "sg:province":"Greater London",
    "sg:tags":[
        "mini",
        "hire",
        "leasing"
    ],
    "wof:name":"Hilton Cars",
    "wof:placetype":"venue"
},
  "geometry": {"coordinates":[-0.287464,51.488625],"type":"Point"}
}