{
  "type": "Feature",
  "properties": {
    "iso:country":"GB",
    "sg:address":"27-29 Forbes Rd",
    "sg:city":"Edinburgh",
    "sg:classifiers":[
        {
            "category":"Home & Garden",
            "subcategory":"Hardware",
            "type":"Retail Goods"
        }
    ],
    "sg:phone":"+44 131 228 6385",
    "sg:postcode":"EH10 4EG",
    "sg:province":"City of Edinburgh",
    "sg:tags":[
        "equipment",
        "bathroom",
        "fitting"
    ],
    "wof:name":"Splash",
    "wof:placetype":"venue"
},
  "geometry": {"coordinates":[-3.207379,55.936981],"type":"Point"}
}