{
  "type": "Feature",
  "properties": {
    "addr:full":"3 The Old Stables, Warborough Road, Letcombe Regis Wantage Berkshire OX12 9LD",
    "addr:housenumber":"3",
    "addr:postcode":"ox12 9ld",
    "addr:street":"The;Warborough Road",
    "iso:country":"GB",
    "sg:address":"3 The Old Stables, Warborough Road, Letcombe Regis",
    "sg:city":"Wantage",
    "sg:classifiers":[
        {
            "category":"Building & Trades",
            "subcategory":"Landscaping Services",
            "type":"Services"
        }
    ],
    "sg:postcode":"OX12 9LD",
    "sg:province":"Berkshire",
    "sg:tags":[
        "designer",
        "architect",
        "landscape"
    ],
    "wof:name":"Eleanor Harvey Garden Design",
    "wof:placetype":"venue"
},
  "geometry": {"coordinates":[-1.450075,51.578224],"type":"Point"}
}