{
  "type": "Feature",
  "properties": {
    "addr:full":"47 Commercial Road Poole Dorset BH14 0HU",
    "addr:housenumber":"47",
    "addr:postcode":"bh14 0hu",
    "addr:street":"Commercial Road",
    "iso:country":"GB",
    "sg:address":"47 Commercial Road",
    "sg:city":"Poole",
    "sg:classifiers":[
        {
            "category":"Shopping",
            "subcategory":"Computers & Home Electronics",
            "type":"Retail Goods"
        },
        {
            "category":"Professional",
            "subcategory":"Computer Services",
            "type":"Services"
        }
    ],
    "sg:phone":"+44 1202 734363",
    "sg:postcode":"BH14 0HU",
    "sg:province":"Dorset",
    "sg:tags":[
        "software",
        "sales",
        "system"
    ],
    "wof:name":"Infospeed Ltd.",
    "wof:placetype":"venue"
},
  "geometry": {"coordinates":[-1.9560699463,50.723651886],"type":"Point"}
}