{
  "type": "Feature",
  "properties": {
    "addr:full":"96 Great George St Glasgow Glasgow City G12 8RY",
    "addr:housenumber":"96",
    "addr:postcode":"g12 8ry",
    "addr:street":"Great George St",
    "iso:country":"GB",
    "sg:address":"96 Great George St",
    "sg:city":"Glasgow",
    "sg:classifiers":[
        {
            "category":"Professional",
            "subcategory":"Lawyer & Legal Services",
            "type":"Services"
        }
    ],
    "sg:phone":"+44 141 334 4548",
    "sg:postcode":"G12 8RY",
    "sg:province":"Glasgow City",
    "sg:tags":[
        "advice",
        "counselling"
    ],
    "wof:name":"Kate Hamilton Stress Counselling Service",
    "wof:placetype":"venue"
},
  "geometry": {"coordinates":[-4.291011,55.875397],"type":"Point"}
}