{
  "type": "Feature",
  "properties": {
    "addr:full":"Factory La Manningtree Essex CO11 1NT",
    "addr:postcode":"co11 1nt",
    "addr:street":"Factory La Manningtree",
    "iso:country":"GB",
    "sg:address":"Factory La",
    "sg:city":"Manningtree",
    "sg:classifiers":[
        {
            "category":"Personal",
            "type":"Services"
        },
        {
            "category":"Freight",
            "type":"Transportation"
        }
    ],
    "sg:phone":"+44 1206 396381",
    "sg:postcode":"CO11 1NT",
    "sg:province":"Essex",
    "sg:tags":[
        "delivery",
        "haulage",
        "road"
    ],
    "wof:name":"Capel Express (Warwick) Ltd",
    "wof:placetype":"venue"
},
  "geometry": {"coordinates":[1.06304,51.945381],"type":"Point"}
}