{
  "type": "Feature",
  "properties": {
    "addr:full":"29 Lavender Hill London Greater London SW11 5QW",
    "addr:housenumber":"29",
    "addr:postcode":"sw11 5qw",
    "addr:street":"Lavender Hill",
    "iso:country":"GB",
    "sg:address":"29 Lavender Hill",
    "sg:city":"London",
    "sg:classifiers":[
        {
            "category":"Shopping",
            "subcategory":"News",
            "type":"Retail Goods"
        }
    ],
    "sg:postcode":"SW11 5QW",
    "sg:province":"Greater London",
    "sg:tags":[
        "newsagent"
    ],
    "wof:name":"Roys",
    "wof:placetype":"venue"
},
  "geometry": {"coordinates":[-0.1520300061,51.4660720825],"type":"Point"}
}