{
  "type": "Feature",
  "properties": {
    "addr:full":"Thames Street Nottingham Nottinghamshire NG6 8HW",
    "addr:postcode":"ng6 8hw",
    "addr:street":"Thames Street",
    "iso:country":"GB",
    "sg:address":"Thames Street",
    "sg:city":"Nottingham",
    "sg:classifiers":[
        {
            "category":"Retail",
            "subcategory":"Auto Repair",
            "type":"Services"
        }
    ],
    "sg:postcode":"NG6 8HW",
    "sg:province":"Nottinghamshire",
    "sg:tags":[
        "modification",
        "garage"
    ],
    "wof:name":"Glen Woodhouse Motors",
    "wof:placetype":"venue"
},
  "geometry": {"coordinates":[-1.201334,53.00264],"type":"Point"}
}