{
  "type": "Feature",
  "properties": {
    "addr:full":"38a High Row Darlington Durham DL3 7QW",
    "addr:housenumber":"38a",
    "addr:postcode":"dl3 7qw",
    "addr:street":"High Row",
    "iso:country":"GB",
    "sg:address":"38a High Row",
    "sg:city":"Darlington",
    "sg:classifiers":[
        {
            "category":"Professional",
            "subcategory":"Art Services",
            "type":"Services"
        }
    ],
    "sg:postcode":"DL3 7QW",
    "sg:province":"Durham",
    "sg:tags":[
        "graphic",
        "designer"
    ],
    "wof:name":"Dashin Blue Design",
    "wof:placetype":"venue"
},
  "geometry": {"coordinates":[-1.555504,54.525681],"type":"Point"}
}