{
  "type": "Feature",
  "properties": {
    "addr:full":"1a Crooked Bridge Road Stafford Staffordshire ST16 3NE",
    "addr:housenumber":"1a",
    "addr:postcode":"st16 3ne",
    "addr:street":"Crooked Bridge Road",
    "iso:country":"GB",
    "sg:address":"1a Crooked Bridge Road",
    "sg:city":"Stafford",
    "sg:classifiers":[
        {
            "category":"Home & Garden",
            "subcategory":"Carpets & Floor Coverings",
            "type":"Retail Goods"
        }
    ],
    "sg:phone":"+44 1785 226443",
    "sg:postcode":"ST16 3NE",
    "sg:province":"Staffordshire",
    "sg:tags":[
        "carpets",
        "rug",
        "matting"
    ],
    "wof:name":"Not Just Curtains",
    "wof:placetype":"venue"
},
  "geometry": {"coordinates":[-2.1186630726,52.8125915527],"type":"Point"}
}