{
  "type": "Feature",
  "properties": {
    "iso:country":"GB",
    "sg:address":"63 Derwent Street",
    "sg:city":"Leicester",
    "sg:classifiers":[
        {
            "category":"Arts & Performance",
            "subcategory":"Music",
            "type":"Entertainment"
        }
    ],
    "sg:postcode":"LE2 0GE",
    "sg:province":"Leicestershire",
    "sg:tags":[
        "mobile",
        "disco"
    ],
    "wof:name":"D I S C O",
    "wof:placetype":"venue"
},
  "geometry": {"coordinates":[-1.1117149591,52.6322898865],"type":"Point"}
}