{
  "type": "Feature",
  "properties": {
    "addr:full":"37 Newnham Way Harrow Greater London HA3 9NU",
    "addr:housenumber":"37",
    "addr:postcode":"ha3 9nu",
    "addr:street":"Newnham Way",
    "iso:country":"GB",
    "sg:address":"37 Newnham Way",
    "sg:city":"Harrow",
    "sg:classifiers":[
        {
            "category":"Food & Beverages",
            "subcategory":"Fruits & Vegetables",
            "type":"Retail Goods"
        }
    ],
    "sg:phone":"+44 20 8907 0624",
    "sg:postcode":"HA3 9NU",
    "sg:province":"Greater London",
    "sg:tags":[
        "greengrocer"
    ],
    "wof:name":"K F V Fruit & Veg (Kenton) Ltd.",
    "wof:placetype":"venue"
},
  "geometry": {"coordinates":[-0.290586,51.587227],"type":"Point"}
}