{
  "type": "Feature",
  "properties": {
    "addr:full":"2 Reeth Close Leicester Leicestershire LE4 0SP",
    "addr:housenumber":"2",
    "addr:postcode":"le4 0sp",
    "addr:street":"Reeth Close",
    "iso:country":"GB",
    "sg:address":"2 Reeth Close",
    "sg:city":"Leicester",
    "sg:classifiers":[
        {
            "category":"Education",
            "subcategory":"Special Training",
            "type":"Public Place"
        }
    ],
    "sg:phone":"+44 116 236 2670",
    "sg:postcode":"LE4 0SP",
    "sg:province":"Leicestershire",
    "sg:tags":[
        "aid",
        "first"
    ],
    "wof:name":"BERNARD FOX",
    "wof:placetype":"venue"
},
  "geometry": {"coordinates":[-1.155177,52.660652],"type":"Point"}
}