{
  "type": "Feature",
  "properties": {
    "iso:country":"GB",
    "sg:address":"74 Merton Avenue",
    "sg:city":"Fareham",
    "sg:classifiers":[
        {
            "category":"Communications",
            "subcategory":"Film & Video Production",
            "type":"Services"
        }
    ],
    "sg:phone":"+44 23 9278 5748",
    "sg:postcode":"PO16 9NH",
    "sg:province":"Hampshire",
    "sg:tags":[
        "tv",
        "studio"
    ],
    "wof:name":"Castle Video Productions",
    "wof:placetype":"venue"
},
  "geometry": {"coordinates":[-1.127648,50.838966],"type":"Point"}
}