{
  "type": "Feature",
  "properties": {
    "iso:country":"GB",
    "sg:address":"13 Alfred Rd",
    "sg:city":"Eastbourne",
    "sg:classifiers":[
        {
            "category":"Taxi",
            "type":"Transportation"
        }
    ],
    "sg:phone":"+44 1323 469225",
    "sg:postcode":"BN23 6TA",
    "sg:province":"East Sussex",
    "sg:tags":[
        "mini",
        "cab"
    ],
    "wof:name":"Maple Leaf Minibus",
    "wof:placetype":"venue"
},
  "geometry": {"coordinates":[0.3196339905,50.7942962646],"type":"Point"}
}