{
  "type": "Feature",
  "properties": {
    "iso:country":"GB",
    "sg:address":"41 Bridge Street, Howden The Wear",
    "sg:city":"Crook",
    "sg:classifiers":[
        {
            "category":"Retail",
            "subcategory":"Funeral Services",
            "type":"Services"
        }
    ],
    "sg:phone":"+44 1388 762582",
    "sg:postcode":"DL15 8EX",
    "sg:province":"Durham",
    "sg:tags":[
        "director",
        "cemetery",
        "crematorium"
    ],
    "wof:name":"Gibson's Funeral Services",
    "wof:placetype":"venue"
},
  "geometry": {"coordinates":[-1.749423,54.694992],"type":"Point"}
}