{
  "type": "Feature",
  "properties": {
    "iso:country":"GB",
    "sg:address":"Rutland Road",
    "sg:city":"Sheffield",
    "sg:classifiers":[
        {
            "category":"Manufacturing",
            "subcategory":"Metals",
            "type":"Manufacturing & Wholesale Goods"
        }
    ],
    "sg:postcode":"S3 8BE",
    "sg:province":"South Yorkshire",
    "sg:tags":[
        "foundry"
    ],
    "wof:name":"Stapak Services",
    "wof:placetype":"venue"
},
  "geometry": {"coordinates":[-1.476749,53.393227],"type":"Point"}
}