{
  "type": "Feature",
  "properties": {
    "iso:country":"GB",
    "sg:address":"32a High St",
    "sg:city":"Emsworth",
    "sg:classifiers":[
        {
            "category":"Real Estate",
            "subcategory":"Surveying",
            "type":"Services"
        }
    ],
    "sg:postcode":"PO10 7AW",
    "sg:province":"Hampshire",
    "sg:tags":[
        "surveyor",
        "valuer"
    ],
    "wof:name":"Groom,Harold J,Chartered Surveyor",
    "wof:placetype":"venue"
},
  "geometry": {"coordinates":[-0.935943,50.846275],"type":"Point"}
}