{
  "type": "Feature",
  "properties": {
    "addr:full":"Carlisle Street, Kilnhurst Rotherham South Yorkshire S62 5UX",
    "addr:postcode":"s62 5ux",
    "addr:street":"Carlisle Street",
    "iso:country":"GB",
    "sg:address":"Carlisle Street, Kilnhurst",
    "sg:city":"Rotherham",
    "sg:classifiers":[
        {
            "category":"Wholesale",
            "subcategory":"Non-durable Goods",
            "type":"Manufacturing & Wholesale Goods"
        }
    ],
    "sg:phone":"+44 1709 583071",
    "sg:postcode":"S62 5UX",
    "sg:province":"South Yorkshire",
    "sg:tags":[
        "carry",
        "cash"
    ],
    "wof:name":"Danish Bacon Co Wholesalers",
    "wof:placetype":"venue"
},
  "geometry": {"coordinates":[-1.32917,53.464088],"type":"Point"}
}