{
  "type": "Feature",
  "properties": {
    "iso:country":"GB",
    "sg:address":"18d Lydgate, Northowram",
    "sg:city":"Halifax",
    "sg:classifiers":[
        {
            "category":"Shopping",
            "subcategory":"News",
            "type":"Retail Goods"
        }
    ],
    "sg:phone":"+44 1422 202102",
    "sg:postcode":"HX3 7EJ",
    "sg:province":"West Yorkshire",
    "sg:tags":[
        "newsagent"
    ],
    "wof:name":"Lydgate News",
    "wof:placetype":"venue"
},
  "geometry": {"coordinates":[-1.822829,53.747169],"type":"Point"}
}