{
  "type": "Feature",
  "properties": {
    "addr:full":"Bressay, Lerwick Shetland Shetland Islands ZE2 9EL",
    "addr:postcode":"ze2 9el",
    "addr:street":"Bressay",
    "iso:country":"GB",
    "sg:address":"Bressay, Lerwick",
    "sg:city":"Shetland",
    "sg:classifiers":[
        {
            "category":"Travel",
            "subcategory":"Hotels & Motels",
            "type":"Entertainment"
        }
    ],
    "sg:postcode":"ZE2 9EL",
    "sg:province":"Shetland Islands",
    "wof:name":"Maryfield House Hotel",
    "wof:placetype":"venue"
},
  "geometry": {"coordinates":[-1.11605,60.15591],"type":"Point"}
}