{
  "type": "Feature",
  "properties": {
    "addr:full":"20 Smithpool Rd Stoke On Trent Staffordshire ST4 4NZ",
    "addr:housenumber":"20",
    "addr:postcode":"st4 4nz",
    "addr:street":"Smithpool Rd",
    "iso:country":"GB",
    "sg:address":"20 Smithpool Rd",
    "sg:city":"Stoke On Trent",
    "sg:classifiers":[
        {
            "category":"Personal",
            "subcategory":"Beauty Salon",
            "type":"Services"
        }
    ],
    "sg:phone":"+44 1782 412687",
    "sg:postcode":"ST4 4NZ",
    "sg:province":"Staffordshire",
    "sg:tags":[
        "lady",
        "hairdresser"
    ],
    "wof:name":"Alicia",
    "wof:placetype":"venue"
},
  "geometry": {"coordinates":[-2.169183,52.998859],"type":"Point"}
}