{
  "type": "Feature",
  "properties": {
    "iso:country":"GB",
    "sg:address":"38-40 High Street",
    "sg:city":"Croydon",
    "sg:classifiers":[
        {
            "category":"Shopping",
            "subcategory":"Clothing, Apparel, & Fashions",
            "type":"Retail Goods"
        }
    ],
    "sg:phone":"+44 20 8680 0740",
    "sg:postcode":"CR0 1YB",
    "sg:province":"Surrey",
    "sg:tags":[
        "shop",
        "clothing"
    ],
    "wof:name":"Redston Ltd.",
    "wof:placetype":"venue"
},
  "geometry": {"coordinates":[-0.100552,51.372574],"type":"Point"}
}