{
  "type": "Feature",
  "properties": {
    "addr:full":"74 High Street, Hanham Bristol City of Bristol BS15 3DS",
    "addr:housenumber":"74",
    "addr:postcode":"bs15 3ds",
    "addr:street":"High Street",
    "iso:country":"GB",
    "sg:address":"74 High Street, Hanham",
    "sg:city":"Bristol",
    "sg:classifiers":[
        {
            "category":"Shopping",
            "subcategory":"Baby Store",
            "type":"Retail Goods"
        }
    ],
    "sg:postcode":"BS15 3DS",
    "sg:province":"City of Bristol",
    "sg:tags":[
        "nursery",
        "accessory"
    ],
    "wof:name":"4 Kids",
    "wof:placetype":"venue"
},
  "geometry": {"coordinates":[-2.516807,51.448757],"type":"Point"}
}