{
  "type": "Feature",
  "properties": {
    "addr:full":"Within Rackhams 76 The Parade Leamington Spa Warwickshire CV32 4DA",
    "addr:housenumber":"76",
    "addr:postcode":"cv32 4da",
    "addr:street":"The Parade",
    "iso:country":"GB",
    "sg:address":"Within Rackhams 76 The Parade",
    "sg:city":"Leamington Spa",
    "sg:classifiers":[
        {
            "category":"Manufacturing",
            "subcategory":"Textiles",
            "type":"Manufacturing & Wholesale Goods"
        }
    ],
    "sg:phone":"+44 1926 421117",
    "sg:postcode":"CV32 4DA",
    "sg:province":"Warwickshire",
    "sg:tags":[
        "linen"
    ],
    "wof:name":"Yves Delorme",
    "wof:placetype":"venue"
},
  "geometry": {"coordinates":[-1.5353239775,52.2891387939],"type":"Point"}
}