{
  "type": "Feature",
  "properties": {
    "iso:country":"GB",
    "sg:address":"Leek Rd, Longsdon",
    "sg:city":"Stoke On Trent",
    "sg:classifiers":[
        {
            "category":"Bars & Pubs",
            "type":"Food & Drink"
        }
    ],
    "sg:phone":"+44 1538 385356",
    "sg:postcode":"ST9 9QF",
    "sg:province":"Staffordshire",
    "sg:tags":[
        "pubs",
        "inn"
    ],
    "wof:name":"New Inn",
    "wof:placetype":"venue"
},
  "geometry": {"coordinates":[-2.101622,53.083141],"type":"Point"}
}