{
  "type": "Feature",
  "properties": {
    "addr:full":"High Barns Ely Cambridgeshire CB7 4RB",
    "addr:postcode":"cb7 4rb",
    "iso:country":"GB",
    "sg:address":"High Barns",
    "sg:city":"Ely",
    "sg:classifiers":[
        {
            "category":"Education",
            "subcategory":"School",
            "type":"Public Place"
        }
    ],
    "sg:phone":"+44 1353 662163",
    "sg:postcode":"CB7 4RB",
    "sg:province":"Cambridgeshire",
    "sg:tags":[
        "local",
        "authority"
    ],
    "wof:name":"St Marys C Of E Junior School",
    "wof:placetype":"venue"
},
  "geometry": {"coordinates":[0.27373299,52.4085731506],"type":"Point"}
}