{
  "type": "Feature",
  "properties": {
    "addr:full":"Unit 7, Marcus Rd, Dunkeswell Honiton Devon EX14 0RA",
    "addr:housenumber":"unit 7",
    "addr:postcode":"ex14 0ra",
    "addr:street":"Marcus Rd",
    "iso:country":"GB",
    "sg:address":"Unit 7, Marcus Rd, Dunkeswell",
    "sg:city":"Honiton",
    "sg:classifiers":[
        {
            "category":"Building & Trades",
            "subcategory":"Construction",
            "type":"Services"
        }
    ],
    "sg:phone":"+44 1404 890180",
    "sg:postcode":"EX14 0RA",
    "sg:province":"Devon",
    "sg:tags":[
        "welder",
        "mechanical"
    ],
    "wof:name":"Weldmark Uk",
    "wof:placetype":"venue"
},
  "geometry": {"coordinates":[-3.1968998909,50.79737854],"type":"Point"}
}