{
  "type": "Feature",
  "properties": {
    "addr:full":"74 Kings Road Reading Berkshire RG1 3BJ",
    "addr:housenumber":"74",
    "addr:postcode":"rg1 3bj",
    "addr:street":"Kings Road",
    "iso:country":"GB",
    "sg:address":"74 Kings Road",
    "sg:city":"Reading",
    "sg:classifiers":[
        {
            "category":"Food & Beverages",
            "subcategory":"Candy",
            "type":"Retail Goods"
        }
    ],
    "sg:phone":"+44 118 957 1722",
    "sg:postcode":"RG1 3BJ",
    "sg:province":"Berkshire",
    "sg:tags":[
        "confectioner"
    ],
    "wof:name":"G S THORNE",
    "wof:placetype":"venue"
},
  "geometry": {"coordinates":[-0.9649149776,51.4546508789],"type":"Point"}
}