{
  "type": "Feature",
  "properties": {
    "iso:country":"GB",
    "sg:address":"Unit Ww Pinfold Lane",
    "sg:city":"Bridlington",
    "sg:classifiers":[
        {
            "category":"Manufacturing",
            "subcategory":"Tools & Machinery",
            "type":"Manufacturing & Wholesale Goods"
        }
    ],
    "sg:phone":"+44 1262 606691",
    "sg:postcode":"YO16 6BT",
    "sg:province":"East Riding of Yorkshire",
    "wof:name":"T Braithwaite",
    "wof:placetype":"venue"
},
  "geometry": {"coordinates":[-0.2099709958,54.1154975891],"type":"Point"}
}