{
  "type": "Feature",
  "properties": {
    "addr:full":"Bogside Farm Airdrie North Lanarkshire ML6 7TJ",
    "addr:postcode":"ml6 7tj",
    "iso:country":"GB",
    "sg:address":"Bogside Farm",
    "sg:city":"Airdrie",
    "sg:classifiers":[
        {
            "category":"Farming",
            "subcategory":"Livestock Farm",
            "type":"Manufacturing & Wholesale Goods"
        },
        {
            "category":"Farming",
            "subcategory":"Farm",
            "type":"Manufacturing & Wholesale Goods"
        }
    ],
    "sg:postcode":"ML6 7TJ",
    "sg:province":"North Lanarkshire",
    "sg:tags":[
        "mixed",
        "crop",
        "others"
    ],
    "wof:name":"David & Jane Hopkin",
    "wof:placetype":"venue"
},
  "geometry": {"coordinates":[-3.9807839394,55.8658638],"type":"Point"}
}