{
  "type": "Feature",
  "properties": {
    "addr:full":"2 The Laurels March Cambridgeshire PE15 8PL",
    "addr:housenumber":"2",
    "addr:postcode":"pe15 8pl",
    "addr:street":"The Laurels",
    "iso:country":"GB",
    "sg:address":"2 The Laurels",
    "sg:city":"March",
    "sg:classifiers":[
        {
            "category":"Building & Trades",
            "subcategory":"Pest Control",
            "type":"Services"
        }
    ],
    "sg:phone":"+44 1354 655395",
    "sg:postcode":"PE15 8PL",
    "sg:province":"Cambridgeshire",
    "sg:tags":[
        "vermin"
    ],
    "wof:name":"D & M Pest Control",
    "wof:placetype":"venue"
},
  "geometry": {"coordinates":[0.094679,52.565617],"type":"Point"}
}