{
  "type": "Feature",
  "properties": {
    "addr:full":"Selbrook House, Shaw Swindon Wiltshire SN5 3PP",
    "addr:housenumber":"selbrook",
    "addr:postcode":"sn5 3pp",
    "iso:country":"GB",
    "sg:address":"Selbrook House, Shaw",
    "sg:city":"Swindon",
    "sg:classifiers":[
        {
            "category":"Banks & Credit Unions",
            "subcategory":"Financial Services",
            "type":"Services"
        }
    ],
    "sg:phone":"+44 1793 771142",
    "sg:postcode":"SN5 3PP",
    "sg:province":"Wiltshire",
    "sg:tags":[
        "consultant"
    ],
    "wof:name":"M B Pearson",
    "wof:placetype":"venue"
},
  "geometry": {"coordinates":[-1.829585,51.567478],"type":"Point"}
}