{
  "type": "Feature",
  "properties": {
    "iso:country":"GB",
    "sg:address":"459 Stourport Rd",
    "sg:city":"Kidderminster",
    "sg:classifiers":[
        {
            "category":"Government",
            "subcategory":"City Hall",
            "type":"Public Place"
        }
    ],
    "sg:phone":"+44 1562 60534",
    "sg:postcode":"DY11 7BD",
    "sg:province":"Staffordshire",
    "wof:name":"Holy Innocents Community Hall",
    "wof:placetype":"venue"
},
  "geometry": {"coordinates":[-2.256859,52.379005],"type":"Point"}
}