{
  "type": "Feature",
  "properties": {
    "iso:country":"GB",
    "sg:address":"Sanroyd House, 9 Monk Street",
    "sg:city":"Monmouth",
    "sg:classifiers":[
        {
            "category":"Professional",
            "type":"Services"
        }
    ],
    "sg:postcode":"NP25 3NZ",
    "sg:province":"Gloucestershire",
    "sg:tags":[
        "repair",
        "tech",
        "maintenance"
    ],
    "wof:name":"Agincourt Computer Services",
    "wof:placetype":"venue"
},
  "geometry": {"coordinates":[-2.712494,51.813675],"type":"Point"}
}