{
  "type": "Feature",
  "properties": {
    "addr:full":"Court House, Upperhead Row Huddersfield West Yorkshire HD1 2JS",
    "addr:postcode":"hd1 2js",
    "addr:street":"Upperhead Row",
    "iso:country":"GB",
    "sg:address":"Court House, Upperhead Row",
    "sg:city":"Huddersfield",
    "sg:classifiers":[
        {
            "category":"Government",
            "subcategory":"Office",
            "type":"Public Place"
        }
    ],
    "sg:phone":"+44 1484 453327",
    "sg:postcode":"HD1 2JS",
    "sg:province":"West Yorkshire",
    "sg:tags":[
        "local"
    ],
    "wof:name":"Bail Information",
    "wof:placetype":"venue"
},
  "geometry": {"coordinates":[-1.786104,53.646629],"type":"Point"}
}