{
  "type": "Feature",
  "properties": {
    "iso:country":"GB",
    "sg:address":"4 Castle St",
    "sg:city":"Canterbury",
    "sg:classifiers":[
        {
            "category":"Building & Trades",
            "subcategory":"Construction",
            "type":"Services"
        }
    ],
    "sg:phone":"+44 1622 859841",
    "sg:postcode":"CT1 2QF",
    "sg:province":"Kent",
    "sg:tags":[
        "contractor"
    ],
    "wof:name":"Rawlings,S E,Ltd",
    "wof:placetype":"venue"
},
  "geometry": {"coordinates":[1.078039,51.27729],"type":"Point"}
}