{
  "type": "Feature",
  "properties": {
    "addr:full":"8/10 Dryden St, Covent Gdn London Greater London WC2E 9NA",
    "addr:housenumber":"8 / 10",
    "addr:postcode":"wc2e 9na",
    "addr:street":"Dryden St;Gdn",
    "iso:country":"GB",
    "sg:address":"8/10 Dryden St, Covent Gdn",
    "sg:city":"London",
    "sg:classifiers":[
        {
            "category":"Communications",
            "subcategory":"Newspaper",
            "type":"Services"
        }
    ],
    "sg:phone":"+44 20 7240 4493",
    "sg:postcode":"WC2E 9NA",
    "sg:province":"Greater London",
    "sg:tags":[
        "magazine"
    ],
    "wof:name":"Hayward Medical Communications Ltd",
    "wof:placetype":"venue"
},
  "geometry": {"coordinates":[-0.122922,51.514721],"type":"Point"}
}