{
  "type": "Feature",
  "properties": {
    "iso:country":"GB",
    "sg:address":"Thorpe Hall Farm, Middleton Lane, Thorpe",
    "sg:city":"Wakefield",
    "sg:classifiers":[
        {
            "category":"Food & Beverages",
            "subcategory":"Farmers Market",
            "type":"Retail Goods"
        }
    ],
    "sg:postcode":"WF3 3BU",
    "sg:province":"West Yorkshire",
    "sg:tags":[
        "gardener"
    ],
    "wof:name":"R P Crowther",
    "wof:placetype":"venue"
},
  "geometry": {"coordinates":[-1.5132440329,53.7392997742],"type":"Point"}
}