{
  "type": "Feature",
  "properties": {
    "addr:full":"1 Droitwich Road, Feckenham Redditch Warwickshire B96 6JE",
    "addr:housenumber":"1",
    "addr:postcode":"b96 6je",
    "addr:street":"Droitwich Road",
    "iso:country":"GB",
    "sg:address":"1 Droitwich Road, Feckenham",
    "sg:city":"Redditch",
    "sg:classifiers":[
        {
            "category":"Bars & Pubs",
            "type":"Food & Drink"
        }
    ],
    "sg:phone":"+44 1527 893495",
    "sg:postcode":"B96 6JE",
    "sg:province":"Warwickshire",
    "sg:tags":[
        "pubs",
        "inn"
    ],
    "wof:name":"The Lygon Arms",
    "wof:placetype":"venue"
},
  "geometry": {"coordinates":[-1.9904719591,52.250038147],"type":"Point"}
}