{
  "type": "Feature",
  "properties": {
    "iso:country":"GB",
    "sg:address":"North Street",
    "sg:city":"Midhurst",
    "sg:classifiers":[
        {
            "category":"Manufacturing",
            "subcategory":"Tools & Machinery",
            "type":"Manufacturing & Wholesale Goods"
        }
    ],
    "sg:phone":"+44 1730 816576",
    "sg:postcode":"GU29 9DJ",
    "sg:province":"West Sussex",
    "sg:tags":[
        "society",
        "friendly"
    ],
    "wof:name":"David Cole Insurance",
    "wof:placetype":"venue"
},
  "geometry": {"coordinates":[-0.738613,50.987309],"type":"Point"}
}