{
  "type": "Feature",
  "properties": {
    "addr:full":"51 High Street Reigate Surrey RH2 9RT",
    "addr:housenumber":"51",
    "addr:postcode":"rh2 9rt",
    "addr:street":"High Street",
    "iso:country":"GB",
    "sg:address":"51 High Street",
    "sg:city":"Reigate",
    "sg:classifiers":[
        {
            "category":"Recreation",
            "subcategory":"Gun Range",
            "type":"Entertainment"
        }
    ],
    "sg:phone":"+44 1737 222250",
    "sg:postcode":"RH2 9RT",
    "sg:province":"Surrey",
    "sg:tags":[
        "operator",
        "tour"
    ],
    "wof:name":"The Travel Designs Co. Ltd.",
    "wof:placetype":"venue"
},
  "geometry": {"coordinates":[-0.209879,51.23801],"type":"Point"}
}