{
  "type": "Feature",
  "properties": {
    "addr:full":"19 Church Road Bexleyheath Kent DA7 4DD",
    "addr:housenumber":"19",
    "addr:postcode":"da7 4dd",
    "addr:street":"Church Road",
    "iso:country":"GB",
    "sg:address":"19 Church Road",
    "sg:city":"Bexleyheath",
    "sg:classifiers":[
        {
            "category":"Professional",
            "subcategory":"Engineering",
            "type":"Services"
        }
    ],
    "sg:phone":"+44 181 693 9427",
    "sg:postcode":"DA7 4DD",
    "sg:province":"Kent",
    "sg:tags":[
        "contractor",
        "electrical",
        "engineer"
    ],
    "wof:name":"E H Brown (Peckham) Ltd.",
    "wof:placetype":"venue"
},
  "geometry": {"coordinates":[0.138285,51.458408],"type":"Point"}
}