{
  "type": "Feature",
  "properties": {
    "iso:country":"GB",
    "sg:address":"Orme Street, Burslem",
    "sg:city":"Stoke-on-trent",
    "sg:classifiers":[
        {
            "category":"Home & Garden",
            "subcategory":"Kitchen Supply",
            "type":"Retail Goods"
        }
    ],
    "sg:phone":"+44 1782 821000",
    "sg:postcode":"ST6 3RB",
    "sg:province":"Staffordshire",
    "sg:tags":[
        "equipment",
        "catering"
    ],
    "wof:name":"Steelite International Plc",
    "wof:placetype":"venue"
},
  "geometry": {"coordinates":[-2.209272,53.043213],"type":"Point"}
}