{
  "type": "Feature",
  "properties": {
    "iso:country":"GB",
    "sg:address":"10 Forest Centre",
    "sg:city":"Bordon",
    "sg:classifiers":[
        {
            "category":"Communications",
            "type":"Services"
        }
    ],
    "sg:phone":"+44 1420 475000",
    "sg:postcode":"GU35 0TN",
    "sg:province":"Hampshire",
    "sg:tags":[
        "tv",
        "video",
        "radio"
    ],
    "wof:name":"Bordon Sound & Vision",
    "wof:placetype":"venue"
},
  "geometry": {"coordinates":[-0.859682,51.111034],"type":"Point"}
}