{
  "type": "Feature",
  "properties": {
    "iso:country":"GB",
    "sg:address":"Oregon, Hook Lane",
    "sg:city":"Chichester",
    "sg:classifiers":[
        {
            "category":"Building & Trades",
            "subcategory":"Construction",
            "type":"Services"
        }
    ],
    "sg:phone":"+44 1243 543070",
    "sg:postcode":"PO20 3TF",
    "sg:province":"West Sussex",
    "sg:tags":[
        "builder"
    ],
    "wof:name":"Burwin Construction Ltd.",
    "wof:placetype":"venue"
},
  "geometry": {"coordinates":[-0.67609,50.835499],"type":"Point"}
}