{
  "type": "Feature",
  "properties": {
    "addr:full":"5 High Street Stone Staffordshire ST15 8AJ",
    "addr:housenumber":"5",
    "addr:postcode":"st15 8aj",
    "addr:street":"High Street",
    "iso:country":"GB",
    "sg:address":"5 High Street",
    "sg:city":"Stone",
    "sg:classifiers":[
        {
            "category":"Manufacturing",
            "subcategory":"Tools & Machinery",
            "type":"Manufacturing & Wholesale Goods"
        }
    ],
    "sg:phone":"+44 1785 815181",
    "sg:postcode":"ST15 8AJ",
    "sg:province":"Staffordshire",
    "sg:tags":[
        "society",
        "friendly"
    ],
    "wof:name":"Geoffrey Jones & Andrew Barrow",
    "wof:placetype":"venue"
},
  "geometry": {"coordinates":[-2.1452898979,52.9015846252],"type":"Point"}
}