{
  "type": "Feature",
  "properties": {
    "addr:full":"Cheese Yard, West Horrington Wells Somerset BA5 3ED",
    "addr:postcode":"ba5 3ed",
    "addr:street":"West",
    "iso:country":"GB",
    "sg:address":"Cheese Yard, West Horrington",
    "sg:city":"Wells",
    "sg:classifiers":[
        {
            "category":"Health Services",
            "subcategory":"Health Practitioner",
            "type":"Services"
        }
    ],
    "sg:phone":"+44 1749 675568",
    "sg:postcode":"BA5 3ED",
    "sg:province":"Somerset",
    "sg:tags":[
        "physiotherapist"
    ],
    "wof:name":"Wells Physiotherapy Practice & Sports Injury Clinic",
    "wof:placetype":"venue"
},
  "geometry": {"coordinates":[-2.611834,51.224686],"type":"Point"}
}