{
  "type": "Feature",
  "properties": {
    "addr:full":"Shenley Fields Drive Birmingham West Midlands B31 1XH",
    "addr:housenumber":"shenley",
    "addr:postcode":"b31 1xh",
    "addr:street":"Fields Drive",
    "iso:country":"GB",
    "sg:address":"Shenley Fields Drive",
    "sg:city":"Birmingham",
    "sg:classifiers":[
        {
            "category":"Organizations",
            "subcategory":"Community Association",
            "type":"Services"
        }
    ],
    "sg:phone":"+44 121 411 2541",
    "sg:postcode":"B31 1XH",
    "sg:province":"West Midlands",
    "sg:tags":[
        "associations",
        "housing",
        "co-operatives",
        "society",
        "trust",
        "societies"
    ],
    "wof:name":"HOUSING 21",
    "wof:placetype":"venue"
},
  "geometry": {"coordinates":[-1.9781520367,52.4346656799],"type":"Point"}
}