{
  "type": "Feature",
  "properties": {
    "iso:country":"GB",
    "sg:address":"359 Kingston Rd, Wimbledon Chase",
    "sg:city":"London",
    "sg:classifiers":[
        {
            "category":"Personal",
            "subcategory":"Beauty Salon",
            "type":"Services"
        }
    ],
    "sg:postcode":"SW20 8JX",
    "sg:province":"Greater London",
    "sg:tags":[
        "unisex",
        "hairdresser"
    ],
    "wof:name":"Claringbold,Tina,",
    "wof:placetype":"venue"
},
  "geometry": {"coordinates":[-0.2131640017,51.4096336365],"type":"Point"}
}