{
  "type": "Feature",
  "properties": {
    "addr:full":"Gordon Av March Cambridgeshire PE15 8AL",
    "addr:postcode":"pe15 8al",
    "addr:street":"Gordon Av March",
    "iso:country":"GB",
    "sg:address":"Gordon Av",
    "sg:city":"March",
    "sg:classifiers":[
        {
            "category":"Education",
            "subcategory":"Library",
            "type":"Public Place"
        }
    ],
    "sg:phone":"+44 1354 653349",
    "sg:postcode":"PE15 8AL",
    "sg:province":"Cambridgeshire",
    "sg:tags":[
        "book"
    ],
    "wof:name":"March Library",
    "wof:placetype":"venue"
},
  "geometry": {"coordinates":[0.08591,52.552608],"type":"Point"}
}