{
  "type": "Feature",
  "properties": {
    "addr:full":"Maidstone Rd Leicester Leicestershire LE2 0UA",
    "addr:postcode":"le2 0ua",
    "addr:street":"Maidstone Rd",
    "iso:country":"GB",
    "sg:address":"Maidstone Rd",
    "sg:city":"Leicester",
    "sg:classifiers":[
        {
            "category":"Social Services",
            "type":"Services"
        }
    ],
    "sg:phone":"+44 116 262 2644",
    "sg:postcode":"LE2 0UA",
    "sg:province":"Leicestershire",
    "wof:name":"Maidstone Centre",
    "wof:placetype":"venue"
},
  "geometry": {"coordinates":[-1.117532,52.635372],"type":"Point"}
}