{
  "type": "Feature",
  "properties": {
    "iso:country":"GB",
    "sg:address":"Lowfields Road",
    "sg:city":"Leeds",
    "sg:classifiers":[
        {
            "category":"Professional",
            "subcategory":"Engineering",
            "type":"Services"
        }
    ],
    "sg:phone":"+44 113 243 5155",
    "sg:postcode":"LS12 6BS",
    "sg:province":"West Yorkshire",
    "sg:tags":[
        "contractor",
        "electrical",
        "engineer"
    ],
    "wof:name":"Scatco Europa Ltd.",
    "wof:placetype":"venue"
},
  "geometry": {"coordinates":[-1.5761640072,53.7827148438],"type":"Point"}
}