{
  "type": "Feature",
  "properties": {
    "iso:country":"GB",
    "sg:address":"4 Meadow Rise, Lacey Green",
    "sg:city":"Princes Risborough",
    "sg:classifiers":[
        {
            "category":"Banks & Credit Unions",
            "subcategory":"Financial Services",
            "type":"Services"
        }
    ],
    "sg:phone":"+44 1844 273377",
    "sg:postcode":"HP27 0QY",
    "sg:province":"Buckinghamshire",
    "sg:tags":[
        "adviser"
    ],
    "wof:name":"Assured Future",
    "wof:placetype":"venue"
},
  "geometry": {"coordinates":[-0.832952,51.721622],"type":"Point"}
}