{
  "type": "Feature",
  "properties": {
    "iso:country":"GB",
    "sg:address":"15 High Street",
    "sg:city":"Abergavenny",
    "sg:classifiers":[
        {
            "category":"Real Estate",
            "subcategory":"Real Estate Agent",
            "type":"Services"
        }
    ],
    "sg:phone":"+44 1873 852821",
    "sg:postcode":"NP7 5RY",
    "sg:province":"Herefordshire",
    "wof:name":"Digby Turner & Co.",
    "wof:placetype":"venue"
},
  "geometry": {"coordinates":[-3.019295,51.822586],"type":"Point"}
}