{
  "type": "Feature",
  "properties": {
    "iso:country":"GB",
    "sg:address":"Ilkley Hall, Ilkley Hall Park",
    "sg:city":"Ilkley",
    "sg:classifiers":[
        {
            "category":"Insurance",
            "subcategory":"Insurance Agent",
            "type":"Services"
        }
    ],
    "sg:phone":"+44 1943 603777",
    "sg:postcode":"LS29 9LD",
    "sg:province":"North Yorkshire",
    "sg:tags":[
        "broker"
    ],
    "wof:name":"Hudson Foster & Co",
    "wof:placetype":"venue"
},
  "geometry": {"coordinates":[-1.819929,53.921692],"type":"Point"}
}