{
  "type": "Feature",
  "properties": {
    "iso:country":"GB",
    "sg:address":"50 St Mildreds Rd",
    "sg:city":"Ramsgate",
    "sg:classifiers":[
        {
            "category":"Social Services",
            "subcategory":"Retirement Home",
            "type":"Services"
        }
    ],
    "sg:phone":"+44 1843 592045",
    "sg:postcode":"CT11 0EF",
    "sg:province":"Kent",
    "sg:tags":[
        "residential",
        "care"
    ],
    "wof:name":"Southdene",
    "wof:placetype":"venue"
},
  "geometry": {"coordinates":[1.402961,51.330696],"type":"Point"}
}