{
  "type": "Feature",
  "properties": {
    "iso:country":"GB",
    "sg:address":"Rugby Ho, Rugby Rd",
    "sg:city":"Twickenham",
    "sg:classifiers":[
        {
            "category":"Professional",
            "subcategory":"Business Services",
            "type":"Services"
        }
    ],
    "sg:phone":"+44 20 8607 9944",
    "sg:postcode":"TW1 1DQ",
    "sg:province":"Greater London",
    "sg:tags":[
        "hospitality",
        "corporate"
    ],
    "wof:name":"Mall Corporate Events Ltd The",
    "wof:placetype":"venue"
},
  "geometry": {"coordinates":[-0.328229,51.446636],"type":"Point"}
}