{
  "type": "Feature",
  "properties": {
    "addr:full":"St Michaels Mount Marazion Cornwall TR17 0HT",
    "addr:housenumber":"marazion",
    "addr:postcode":"tr17 0ht",
    "addr:street":"Mount",
    "iso:country":"GB",
    "sg:address":"St Michaels Mount",
    "sg:city":"Marazion",
    "sg:classifiers":[
        {
            "category":"Restaurant",
            "type":"Food & Drink"
        }
    ],
    "sg:phone":"+44 1736 710748",
    "sg:postcode":"TR17 0HT",
    "sg:province":"Cornwall",
    "wof:name":"The National Trust",
    "wof:placetype":"venue"
},
  "geometry": {"coordinates":[-5.4774799347,50.1161384583],"type":"Point"}
}