{
  "type": "Feature",
  "properties": {
    "iso:country":"GB",
    "sg:address":"1 Charing Cross",
    "sg:city":"Norwich",
    "sg:classifiers":[
        {
            "category":"Real Estate",
            "subcategory":"Real Estate Agent",
            "type":"Services"
        }
    ],
    "sg:phone":"+44 1603 629158",
    "sg:postcode":"NR2 4AX",
    "sg:province":"Norfolk",
    "wof:name":"G A Key",
    "wof:placetype":"venue"
},
  "geometry": {"coordinates":[1.2929190397,52.630821228],"type":"Point"}
}