{
  "type": "Feature",
  "properties": {
    "addr:full":"12 Cheapside, High Road London Greater London N22 6HH",
    "addr:housenumber":"12",
    "addr:postcode":"n22 6hh",
    "addr:street":"Cheapside High Road",
    "iso:country":"GB",
    "sg:address":"12 Cheapside, High Road",
    "sg:city":"London",
    "sg:classifiers":[
        {
            "category":"Shopping",
            "subcategory":"Jewelry",
            "type":"Retail Goods"
        },
        {
            "category":"Shopping",
            "subcategory":"Comic Books",
            "type":"Retail Goods"
        }
    ],
    "sg:phone":"+44 20 8889 9484",
    "sg:postcode":"N22 6HH",
    "sg:province":"Greater London",
    "sg:tags":[
        "jeweller",
        "sale",
        "jewellery"
    ],
    "wof:name":"Discount Jewellers",
    "wof:placetype":"venue"
},
  "geometry": {"coordinates":[-0.10386,51.591061],"type":"Point"}
}