{
  "type": "Feature",
  "properties": {
    "addr:full":"1 Scrattons Terr, Ripple Rd Barking Essex IG11 0TY",
    "addr:housenumber":"1",
    "addr:postcode":"ig11 0ty",
    "addr:street":"Scrattons Terr Ripple Rd",
    "iso:country":"GB",
    "sg:address":"1 Scrattons Terr, Ripple Rd",
    "sg:city":"Barking",
    "sg:classifiers":[
        {
            "category":"Bus Charters",
            "type":"Transportation"
        }
    ],
    "sg:postcode":"IG11 0TY",
    "sg:province":"Essex",
    "sg:tags":[
        "mini",
        "hire",
        "leasing"
    ],
    "wof:name":"Farrugia,Tony,",
    "wof:placetype":"venue"
},
  "geometry": {"coordinates":[0.129111,51.531384],"type":"Point"}
}