{
  "type": "Feature",
  "properties": {
    "iso:country":"GB",
    "sg:address":"36 St James Road, Long Sutton",
    "sg:city":"Spalding",
    "sg:classifiers":[
        {
            "category":"Utilities",
            "subcategory":"Fuel Oil & Lpg",
            "type":"Services"
        }
    ],
    "sg:phone":"+44 1406 363170",
    "sg:postcode":"PE12 9AZ",
    "sg:province":"Cambridgeshire",
    "wof:name":"Alan J Wilkinson Ltd.",
    "wof:placetype":"venue"
},
  "geometry": {"coordinates":[0.1075249985,52.7684173584],"type":"Point"}
}