{
  "type": "Feature",
  "properties": {
    "iso:country":"GB",
    "sg:address":"19 West Wilts Craft Centre, Storridge Road",
    "sg:city":"Westbury",
    "sg:classifiers":[
        {
            "category":"Home & Garden",
            "subcategory":"Home Furnishings",
            "type":"Retail Goods"
        }
    ],
    "sg:postcode":"BA13 4HU",
    "sg:province":"Wiltshire",
    "sg:tags":[
        "awning",
        "canopy",
        "blinds"
    ],
    "wof:name":"Harmony Blinds",
    "wof:placetype":"venue"
},
  "geometry": {"coordinates":[-2.1851289272,51.2574768066],"type":"Point"}
}