{
  "type": "Feature",
  "properties": {
    "addr:full":"Physiotherapy Department, St Catherines Hospital, Church Rd Birkenhead Merseyside L42 0LQ",
    "addr:postcode":"l42 0lq",
    "addr:street":"Church Rd",
    "iso:country":"GB",
    "sg:address":"Physiotherapy Department, St Catherines Hospital, Church Rd",
    "sg:city":"Birkenhead",
    "sg:classifiers":[
        {
            "category":"Health Services",
            "subcategory":"Hospital",
            "type":"Services"
        }
    ],
    "sg:phone":"+44 151 604 7260",
    "sg:postcode":"L42 0LQ",
    "sg:province":"Merseyside",
    "wof:name":"Wirral & West Cheshire Community NHS Trust",
    "wof:placetype":"venue"
},
  "geometry": {"coordinates":[-3.02549,53.392559],"type":"Point"}
}