{
  "type": "Feature",
  "properties": {
    "addr:full":"73 Rowan Clo, Stoke Hill Guildford Surrey GU1 1PW",
    "addr:housenumber":"73",
    "addr:postcode":"gu1 1pw",
    "addr:street":"Rowan;Stoke Hill",
    "iso:country":"GB",
    "sg:address":"73 Rowan Clo, Stoke Hill",
    "sg:city":"Guildford",
    "sg:classifiers":[
        {
            "category":"Retail",
            "subcategory":"Repair Shop",
            "type":"Services"
        }
    ],
    "sg:postcode":"GU1 1PW",
    "sg:province":"Surrey",
    "sg:tags":[
        "maintenance"
    ],
    "wof:name":"Pettinato,Antonio,",
    "wof:placetype":"venue"
},
  "geometry": {"coordinates":[-0.581904,51.256962],"type":"Point"}
}