{
  "type": "Feature",
  "properties": {
    "iso:country":"GB",
    "sg:address":"4 Dudley Street",
    "sg:city":"Grimsby",
    "sg:classifiers":[
        {
            "category":"Health Services",
            "subcategory":"Clinic",
            "type":"Services"
        }
    ],
    "sg:phone":"+44 1472 251351",
    "sg:postcode":"DN31 2AB",
    "sg:province":"Lincolnshire",
    "sg:tags":[
        "abuse",
        "drug"
    ],
    "wof:name":"Impact (D A S) Ltd.",
    "wof:placetype":"venue"
},
  "geometry": {"coordinates":[-0.092693,53.562855],"type":"Point"}
}