{
  "type": "Feature",
  "properties": {
    "addr:full":"191 Cowbridge Road East Cardiff Cardiff CF1 9AJ",
    "addr:housenumber":"191",
    "addr:postcode":"cf1 9aj",
    "addr:street":"Cowbridge Road East",
    "iso:country":"GB",
    "sg:address":"191 Cowbridge Road East",
    "sg:city":"Cardiff",
    "sg:classifiers":[
        {
            "category":"Travel",
            "subcategory":"Travel Agent",
            "type":"Entertainment"
        }
    ],
    "sg:phone":"+44 29 2039 8662",
    "sg:postcode":"CF1 9AJ",
    "sg:province":"Cardiff",
    "wof:name":"Lunn Poly Ltd.",
    "wof:placetype":"venue"
},
  "geometry": {"coordinates":[-3.198077,51.481358],"type":"Point"}
}