{
  "type": "Feature",
  "properties": {
    "addr:full":"6 Sandbach Road South, Alsager Stoke-on-trent Cheshire ST7 2LU",
    "addr:housenumber":"6",
    "addr:postcode":"st7 2lu",
    "addr:street":"Sandbach Road South",
    "iso:country":"GB",
    "sg:address":"6 Sandbach Road South, Alsager",
    "sg:city":"Stoke-on-trent",
    "sg:classifiers":[
        {
            "category":"Shopping",
            "subcategory":"Clothing, Apparel, & Fashions",
            "type":"Retail Goods"
        }
    ],
    "sg:postcode":"ST7 2LU",
    "sg:province":"Cheshire",
    "sg:tags":[
        "shop",
        "dress",
        "fancy"
    ],
    "wof:name":"Fancy That",
    "wof:placetype":"venue"
},
  "geometry": {"coordinates":[-2.3001470566,53.0932312012],"type":"Point"}
}