{
  "type": "Feature",
  "properties": {
    "iso:country":"GB",
    "sg:address":"33 Market Place",
    "sg:city":"Brackley",
    "sg:classifiers":[
        {
            "category":"Fast Food",
            "type":"Food & Drink"
        }
    ],
    "sg:phone":"+44 1280 706959",
    "sg:postcode":"NN13 7AB",
    "sg:province":"Buckinghamshire",
    "sg:tags":[
        "away",
        "take"
    ],
    "wof:name":"Poran",
    "wof:placetype":"venue"
},
  "geometry": {"coordinates":[-1.148706,52.027149],"type":"Point"}
}