{
  "type": "Feature",
  "properties": {
    "iso:country":"GB",
    "sg:address":"7 Collets Drive",
    "sg:city":"Cheltenham",
    "sg:classifiers":[
        {
            "category":"Autos & Motor Vehicles",
            "subcategory":"Auto Supplies",
            "type":"Retail Goods"
        }
    ],
    "sg:phone":"+44 1242 227222",
    "sg:postcode":"GL51 8JQ",
    "sg:province":"Gloucestershire",
    "sg:tags":[
        "tyre"
    ],
    "wof:name":"J T Realisation Ltd.",
    "wof:placetype":"venue"
},
  "geometry": {"coordinates":[-2.0896940231,51.9060440063],"type":"Point"}
}