{
  "type": "Feature",
  "properties": {
    "iso:country":"GB",
    "sg:address":"6 The Bank, Countesthorpe",
    "sg:city":"Leicester",
    "sg:classifiers":[
        {
            "category":"Fast Food",
            "type":"Food & Drink"
        }
    ],
    "sg:phone":"+44 116 277 1185",
    "sg:postcode":"LE8 5RL",
    "sg:province":"Leicestershire",
    "sg:tags":[
        "away",
        "meal",
        "outlet",
        "take"
    ],
    "wof:name":"Wings Takeaway",
    "wof:placetype":"venue"
},
  "geometry": {"coordinates":[-1.094375,52.524609],"type":"Point"}
}