{
  "type": "Feature",
  "properties": {
    "addr:full":"Criddon Hall Farm, Criddon Bridgnorth Shropshire WV16 6UJ",
    "addr:postcode":"wv16 6uj",
    "addr:street":"Criddon Bridgnorth",
    "iso:country":"GB",
    "sg:address":"Criddon Hall Farm, Criddon",
    "sg:city":"Bridgnorth",
    "sg:classifiers":[
        {
            "category":"Farming",
            "subcategory":"Farm",
            "type":"Manufacturing & Wholesale Goods"
        }
    ],
    "sg:phone":"+44 1746 789291",
    "sg:postcode":"WV16 6UJ",
    "sg:province":"Shropshire",
    "sg:tags":[
        "mixed",
        "crop"
    ],
    "wof:name":"B E H & A P Gill",
    "wof:placetype":"venue"
},
  "geometry": {"coordinates":[-2.420479,52.536819],"type":"Point"}
}