{
  "type": "Feature",
  "properties": {
    "iso:country":"GB",
    "sg:address":"Royal Court, Kings Road",
    "sg:city":"Reading",
    "sg:classifiers":[
        {
            "category":"Restaurant",
            "type":"Food & Drink"
        }
    ],
    "sg:phone":"+44 118 959 6169",
    "sg:postcode":"RG1 4AE",
    "sg:province":"Berkshire",
    "sg:tags":[
        "thai",
        "-"
    ],
    "wof:name":"Bens Bar & Thai Restaurant",
    "wof:placetype":"venue"
},
  "geometry": {"coordinates":[-0.9592040181,51.4539756775],"type":"Point"}
}