{
  "type": "Feature",
  "properties": {
    "iso:country":"GB",
    "sg:address":"74 London Road",
    "sg:city":"Harleston",
    "sg:classifiers":[
        {
            "category":"Bars & Pubs",
            "type":"Food & Drink"
        }
    ],
    "sg:phone":"+44 1379 852345",
    "sg:postcode":"IP20 9BZ",
    "sg:province":"Norfolk",
    "sg:tags":[
        "pubs",
        "inn"
    ],
    "wof:name":"Cherry Tree",
    "wof:placetype":"venue"
},
  "geometry": {"coordinates":[1.295239,52.397663],"type":"Point"}
}