{
  "type": "Feature",
  "properties": {
    "iso:country":"GB",
    "sg:address":"Unit 17 Cobham Business Centre, Cobham Rd",
    "sg:city":"Birmingham",
    "sg:classifiers":[
        {
            "category":"Building & Trades",
            "subcategory":"Construction",
            "type":"Services"
        }
    ],
    "sg:phone":"+44 121 766 8362",
    "sg:postcode":"B9 4UP",
    "sg:province":"West Midlands",
    "sg:tags":[
        "builder"
    ],
    "wof:name":"Buckland Builders",
    "wof:placetype":"venue"
},
  "geometry": {"coordinates":[-1.85544,52.48],"type":"Point"}
}