{
  "type": "Feature",
  "properties": {
    "iso:country":"GB",
    "sg:address":"37 Richmond Avenue",
    "sg:city":"Oldham",
    "sg:classifiers":[
        {
            "category":"Organizations",
            "subcategory":"Non-profit Organization",
            "type":"Services"
        }
    ],
    "sg:phone":"+44 161 626 6350",
    "sg:postcode":"OL2 5RH",
    "sg:province":"Lancashire",
    "sg:tags":[
        "organisation",
        "voluntary",
        "charity"
    ],
    "wof:name":"The Salvation Army",
    "wof:placetype":"venue"
},
  "geometry": {"coordinates":[-2.1271328926,53.5681533813],"type":"Point"}
}