{
  "type": "Feature",
  "properties": {
    "iso:country":"GB",
    "sg:address":"2 Enfield",
    "sg:city":"Leeds",
    "sg:classifiers":[
        {
            "category":"Shopping",
            "subcategory":"Computers & Home Electronics",
            "type":"Retail Goods"
        }
    ],
    "sg:phone":"+44 113 250 5445",
    "sg:postcode":"LS19 7RY",
    "sg:province":"West Yorkshire",
    "sg:tags":[
        "aerial",
        "television",
        "radio"
    ],
    "wof:name":"D Goodyear Aerials",
    "wof:placetype":"venue"
},
  "geometry": {"coordinates":[-1.686831,53.862972],"type":"Point"}
}