{
  "type": "Feature",
  "properties": {
    "addr:full":"4 Union Street, London Bridge London Greater London SE1 1SZ",
    "addr:housenumber":"4",
    "addr:postcode":"se1 1sz",
    "addr:street":"Union Street",
    "iso:country":"GB",
    "sg:address":"4 Union Street, London Bridge",
    "sg:city":"London",
    "sg:classifiers":[
        {
            "category":"Professional",
            "subcategory":"Employment Agencies",
            "type":"Services"
        }
    ],
    "sg:phone":"+44 20 8740 1999",
    "sg:postcode":"SE1 1SZ",
    "sg:province":"Greater London",
    "sg:tags":[
        "consultant"
    ],
    "wof:name":"Angel",
    "wof:placetype":"venue"
},
  "geometry": {"coordinates":[-0.092034,51.503468],"type":"Point"}
}