{
  "type": "Feature",
  "properties": {
    "iso:country":"GB",
    "sg:address":"29b North Street",
    "sg:city":"Bishops Stortford",
    "sg:classifiers":[
        {
            "category":"Real Estate",
            "subcategory":"Real Estate Operator",
            "type":"Services"
        }
    ],
    "sg:phone":"+44 1279 866866",
    "sg:postcode":"CM23 2LD",
    "sg:province":"Essex",
    "sg:tags":[
        "letting",
        "agent"
    ],
    "wof:name":"AVENUE PROPERTY MANAGEMENT",
    "wof:placetype":"venue"
},
  "geometry": {"coordinates":[0.158083,51.872616],"type":"Point"}
}