{
  "type": "Feature",
  "properties": {
    "addr:full":"174 Collier Row Rd, Collier Row Romford Essex RM5 2BD",
    "addr:housenumber":"174",
    "addr:postcode":"rm5 2bd",
    "addr:street":"Collier Row Rd",
    "iso:country":"GB",
    "sg:address":"174 Collier Row Rd, Collier Row",
    "sg:city":"Romford",
    "sg:classifiers":[
        {
            "category":"Home & Garden",
            "subcategory":"Home Furnishings",
            "type":"Retail Goods"
        }
    ],
    "sg:postcode":"RM5 2BD",
    "sg:province":"Essex",
    "sg:tags":[
        "blind",
        "curtain",
        "fitting"
    ],
    "wof:name":"Curtain Creations",
    "wof:placetype":"venue"
},
  "geometry": {"coordinates":[0.153478,51.59782],"type":"Point"}
}