{
  "type": "Feature",
  "properties": {
    "iso:country":"GB",
    "sg:address":"6 Anjou Blvd, Robin Park",
    "sg:city":"Wigan",
    "sg:classifiers":[
        {
            "category":"Restaurant",
            "type":"Food & Drink"
        }
    ],
    "sg:phone":"+44 1942 211811",
    "sg:postcode":"WN5 0UJ",
    "sg:province":"Lancashire",
    "sg:tags":[
        "american"
    ],
    "wof:name":"O K Diners Ltd.",
    "wof:placetype":"venue"
},
  "geometry": {"coordinates":[-2.659214,53.546284],"type":"Point"}
}