{
  "type": "Feature",
  "properties": {
    "addr:full":"Ashlar House, 115 Walsall Road, Aldridge Walsall Staffordshire WS9 0AX",
    "addr:housenumber":"115",
    "addr:postcode":"ws9 0ax",
    "addr:street":"Walsall Road",
    "iso:country":"GB",
    "sg:address":"Ashlar House, 115 Walsall Road, Aldridge",
    "sg:city":"Walsall",
    "sg:classifiers":[
        {
            "category":"Banks & Credit Unions",
            "subcategory":"Financial Services",
            "type":"Services"
        },
        {
            "category":"Communications",
            "type":"Services"
        }
    ],
    "sg:phone":"+44 1922 743560",
    "sg:postcode":"WS9 0AX",
    "sg:province":"Staffordshire",
    "sg:tags":[
        "consultant",
        "telecommunication"
    ],
    "wof:name":"Technology Finance (Uk) Ltd.",
    "wof:placetype":"venue"
},
  "geometry": {"coordinates":[-1.926839,52.598316],"type":"Point"}
}