{
  "type": "Feature",
  "properties": {
    "iso:country":"GB",
    "sg:address":"Unit 1g, Peckleton Lane Business Park, Peckleton",
    "sg:city":"Leicester",
    "sg:classifiers":[
        {
            "category":"Manufacturing",
            "subcategory":"Apparel",
            "type":"Manufacturing & Wholesale Goods"
        }
    ],
    "sg:postcode":"LE9 7RF",
    "sg:province":"Leicestershire",
    "sg:tags":[
        "mnfr",
        "lingerie",
        "hosiery"
    ],
    "wof:name":"In Style Hosiery",
    "wof:placetype":"venue"
},
  "geometry": {"coordinates":[-1.281237,52.609066],"type":"Point"}
}