{
  "type": "Feature",
  "properties": {
    "addr:full":"25 Delrene Road Solihull West Midlands B90 2HJ",
    "addr:housenumber":"25",
    "addr:postcode":"b90 2hj",
    "addr:street":"Delrene Road",
    "iso:country":"GB",
    "sg:address":"25 Delrene Road",
    "sg:city":"Solihull",
    "sg:classifiers":[
        {
            "category":"Home & Garden",
            "subcategory":"Carpets & Floor Coverings",
            "type":"Retail Goods"
        }
    ],
    "sg:postcode":"B90 2HJ",
    "sg:province":"West Midlands",
    "sg:tags":[
        "carpets",
        "rug",
        "matting"
    ],
    "wof:name":"K Hill Carpets",
    "wof:placetype":"venue"
},
  "geometry": {"coordinates":[-1.8387520313,52.4113006592],"type":"Point"}
}