{
  "type": "Feature",
  "properties": {
    "addr:full":"Town Hall, 5 Clove Crescent London Greater London E14 2BG",
    "addr:housenumber":"5",
    "addr:postcode":"e14 2bg",
    "addr:street":"Clove Crescent",
    "iso:country":"GB",
    "sg:address":"Town Hall, 5 Clove Crescent",
    "sg:city":"London",
    "sg:classifiers":[
        {
            "category":"Government",
            "subcategory":"Office",
            "type":"Public Place"
        }
    ],
    "sg:postcode":"E14 2BG",
    "sg:province":"Greater London",
    "sg:tags":[
        "local"
    ],
    "wof:name":"Tower Hamlets",
    "wof:placetype":"venue"
},
  "geometry": {"coordinates":[-0.00558,51.509659],"type":"Point"}
}