{
  "type": "Feature",
  "properties": {
    "iso:country":"GB",
    "sg:address":"Church La",
    "sg:city":"Kidlington",
    "sg:classifiers":[
        {
            "category":"Place Of Worship",
            "type":"Public Place"
        }
    ],
    "sg:phone":"+44 1865 375749",
    "sg:postcode":"OX5 1PY",
    "sg:province":"Buckinghamshire",
    "wof:name":"St Bartholomew C of E Church",
    "wof:placetype":"venue"
},
  "geometry": {"coordinates":[-1.309575,51.804394],"type":"Point"}
}