{
  "type": "Feature",
  "properties": {
    "addr:full":"125a Clepington Road Dundee Dundee City DD3 7PA",
    "addr:housenumber":"125a",
    "addr:postcode":"dd3 7pa",
    "addr:street":"Clepington Road",
    "iso:country":"GB",
    "sg:address":"125a Clepington Road",
    "sg:city":"Dundee",
    "sg:classifiers":[
        {
            "category":"Personal",
            "subcategory":"Barber",
            "type":"Services"
        }
    ],
    "sg:postcode":"DD3 7PA",
    "sg:province":"Dundee City",
    "sg:tags":[
        "men's",
        "hairdresser"
    ],
    "wof:name":"Mike the Barbers",
    "wof:placetype":"venue"
},
  "geometry": {"coordinates":[-2.964022,56.477795],"type":"Point"}
}