{
  "type": "Feature",
  "properties": {
    "addr:full":"Tycam, Brynteg Llanybydder Carmarthenshire SA40 9UX",
    "addr:postcode":"sa40 9ux",
    "iso:country":"GB",
    "sg:address":"Tycam, Brynteg",
    "sg:city":"Llanybydder",
    "sg:classifiers":[
        {
            "category":"Farming",
            "subcategory":"Livestock Farm",
            "type":"Manufacturing & Wholesale Goods"
        }
    ],
    "sg:phone":"+44 1570 480467",
    "sg:postcode":"SA40 9UX",
    "sg:province":"Carmarthenshire",
    "sg:tags":[
        "others"
    ],
    "wof:name":"J S Howells",
    "wof:placetype":"venue"
},
  "geometry": {"coordinates":[-4.1583609581,52.0739364624],"type":"Point"}
}