{
  "type": "Feature",
  "properties": {
    "addr:full":"Hardwick Hall, Sedgefield Stockton-on-tees Durham TS21 1EH",
    "addr:postcode":"ts21 1eh",
    "iso:country":"GB",
    "sg:address":"Hardwick Hall, Sedgefield",
    "sg:city":"Stockton-on-tees",
    "sg:classifiers":[
        {
            "category":"Travel",
            "subcategory":"Hotels & Motels",
            "type":"Entertainment"
        }
    ],
    "sg:phone":"+44 1740 620253",
    "sg:postcode":"TS21 1EH",
    "sg:province":"Durham",
    "wof:name":"Hardwick Hall Hotel",
    "wof:placetype":"venue"
},
  "geometry": {"coordinates":[-1.39474,54.589409],"type":"Point"}
}