{
  "type": "Feature",
  "properties": {
    "iso:country":"GB",
    "sg:address":"5 Lowergate, Paddock",
    "sg:city":"Huddersfield",
    "sg:classifiers":[
        {
            "category":"Personal",
            "subcategory":"Beauty Salon",
            "type":"Services"
        }
    ],
    "sg:postcode":"HD3 4ET",
    "sg:province":"West Yorkshire",
    "sg:tags":[
        "lady",
        "hairdresser"
    ],
    "wof:name":"Mayfayre Salon",
    "wof:placetype":"venue"
},
  "geometry": {"coordinates":[-1.82201,53.642586],"type":"Point"}
}