{
  "type": "Feature",
  "properties": {
    "iso:country":"GB",
    "sg:address":"31-33 Cardiff Road",
    "sg:city":"Caerphilly",
    "sg:classifiers":[
        {
            "category":"Professional",
            "subcategory":"Lawyer & Legal Services",
            "type":"Services"
        }
    ],
    "sg:phone":"+44 29 2086 8811",
    "sg:postcode":"CF83 1FN",
    "sg:province":"Caerphilly",
    "sg:tags":[
        "solicitor"
    ],
    "wof:name":"Newman Jenkins Partnership",
    "wof:placetype":"venue"
},
  "geometry": {"coordinates":[-3.220492,51.574165],"type":"Point"}
}