{
  "type": "Feature",
  "properties": {
    "addr:full":"Argyle Housed, 22b Calabria Road London Greater London N5 1JA",
    "addr:housenumber":"22b",
    "addr:postcode":"n5 1ja",
    "addr:street":"Calabria Road",
    "iso:country":"GB",
    "sg:address":"Argyle Housed, 22b Calabria Road",
    "sg:city":"London",
    "sg:classifiers":[
        {
            "category":"Communications",
            "type":"Services"
        }
    ],
    "sg:postcode":"N5 1JA",
    "sg:province":"Greater London",
    "sg:tags":[
        "telecommunication"
    ],
    "wof:name":"Regus Communications Ltd",
    "wof:placetype":"venue"
},
  "geometry": {"coordinates":[-0.1001399979,51.547580719],"type":"Point"}
}