{
  "type": "Feature",
  "properties": {
    "iso:country":"GB",
    "sg:address":"Unit 10, Alexander Stephen Ho, 91 Holmfauld Rd",
    "sg:city":"Glasgow",
    "sg:classifiers":[
        {
            "category":"Building & Trades",
            "subcategory":"Construction",
            "type":"Services"
        }
    ],
    "sg:postcode":"G51 4RY",
    "sg:province":"Glasgow City",
    "sg:tags":[
        "pipework",
        "contractor"
    ],
    "wof:name":"Montage Resource Ltd",
    "wof:placetype":"venue"
},
  "geometry": {"coordinates":[-4.33175,55.86647],"type":"Point"}
}