{
  "type": "Feature",
  "properties": {
    "addr:full":"Mersey Street Manchester Greater Manchester M11 1EP",
    "addr:postcode":"m11 1ep",
    "addr:street":"Mersey Street",
    "iso:country":"GB",
    "sg:address":"Mersey Street",
    "sg:city":"Manchester",
    "sg:classifiers":[
        {
            "category":"Place Of Worship",
            "type":"Public Place"
        }
    ],
    "sg:phone":"+44 161 370 3622",
    "sg:postcode":"M11 1EP",
    "sg:province":"Greater Manchester",
    "wof:name":"United baptist Tabernacle",
    "wof:placetype":"venue"
},
  "geometry": {"coordinates":[-2.161434,53.473099],"type":"Point"}
}