{
  "type": "Feature",
  "properties": {
    "iso:country":"GB",
    "sg:address":"1 Peckham Park Road",
    "sg:city":"London",
    "sg:classifiers":[
        {
            "category":"Shopping",
            "subcategory":"Computers & Home Electronics",
            "type":"Retail Goods"
        }
    ],
    "sg:phone":"+44 20 7639 7225",
    "sg:postcode":"SE15 6TR",
    "sg:province":"Greater London",
    "sg:tags":[
        "telephone"
    ],
    "wof:name":"We Yone Enterprises",
    "wof:placetype":"venue"
},
  "geometry": {"coordinates":[-0.064924,51.483303],"type":"Point"}
}