{
  "type": "Feature",
  "properties": {
    "iso:country":"GB",
    "sg:address":"5 Stanley Drive, Bishopbriggs",
    "sg:city":"Glasgow",
    "sg:classifiers":[
        {
            "category":"Building & Trades",
            "subcategory":"Construction",
            "type":"Services"
        }
    ],
    "sg:phone":"+44 141 772 2205",
    "sg:postcode":"G64 2LA",
    "sg:province":"East Dunbartonshire",
    "sg:tags":[
        "joiner",
        "carpenter"
    ],
    "wof:name":"A J Allport",
    "wof:placetype":"venue"
},
  "geometry": {"coordinates":[-4.216277,55.912113],"type":"Point"}
}