{
  "type": "Feature",
  "properties": {
    "iso:country":"GB",
    "sg:address":"Constable Works",
    "sg:city":"Dundee",
    "sg:classifiers":[
        {
            "category":"Manufacturing",
            "subcategory":"Textiles",
            "type":"Manufacturing & Wholesale Goods"
        }
    ],
    "sg:phone":"+44 1382 735800",
    "sg:postcode":"DD5 3RU",
    "sg:province":"Angus",
    "sg:tags":[
        "made-up"
    ],
    "wof:name":"Malcolm Ogilvie & Co. Ltd.",
    "wof:placetype":"venue"
},
  "geometry": {"coordinates":[-2.813689,56.537655],"type":"Point"}
}