{
  "type": "Feature",
  "properties": {
    "iso:country":"GB",
    "sg:address":"10 Linkfield Corner",
    "sg:city":"Redhill",
    "sg:classifiers":[
        {
            "category":"Fast Food",
            "type":"Food & Drink"
        },
        {
            "category":"Restaurant",
            "type":"Food & Drink"
        }
    ],
    "sg:phone":"+44 1737 762590",
    "sg:postcode":"RH1 1BB",
    "sg:province":"Surrey",
    "sg:tags":[
        "away",
        "-",
        "take",
        "chinese"
    ],
    "wof:name":"Tim M Chu",
    "wof:placetype":"venue"
},
  "geometry": {"coordinates":[-0.169082,51.245773],"type":"Point"}
}