{
  "type": "Feature",
  "properties": {
    "addr:full":"Market St Barnsley South Yorkshire S70 1SL",
    "addr:postcode":"s70 1sl",
    "addr:street":"Market St;Yorkshire",
    "iso:country":"GB",
    "sg:address":"Market St",
    "sg:city":"Barnsley",
    "sg:classifiers":[
        {
            "category":"Shopping",
            "subcategory":"Baby Store",
            "type":"Retail Goods"
        }
    ],
    "sg:phone":"+44 1226 731435",
    "sg:postcode":"S70 1SL",
    "sg:province":"South Yorkshire",
    "sg:tags":[
        "babywear",
        "childrens"
    ],
    "wof:name":"Kidz Shop The",
    "wof:placetype":"venue"
},
  "geometry": {"coordinates":[-1.4808700085,53.5515213013],"type":"Point"}
}