{
  "type": "Feature",
  "properties": {
    "iso:country":"GB",
    "sg:address":"37 Aberdeen Road, Cotham",
    "sg:city":"Bristol",
    "sg:classifiers":[
        {
            "category":"Building & Trades",
            "subcategory":"Construction",
            "type":"Services"
        }
    ],
    "sg:phone":"+44 117 974 3444",
    "sg:postcode":"BS6 6HY",
    "sg:province":"City of Bristol",
    "sg:tags":[
        "contractor",
        "paving",
        "driveway"
    ],
    "wof:name":"Rws Contracts Ltd.",
    "wof:placetype":"venue"
},
  "geometry": {"coordinates":[-2.605001,51.463913],"type":"Point"}
}