{
  "type": "Feature",
  "properties": {
    "addr:full":"84 Salisbury Rd Southampton Hampshire SO40 3JA",
    "addr:housenumber":"84",
    "addr:postcode":"so40 3ja",
    "addr:street":"Salisbury Rd",
    "iso:country":"GB",
    "sg:address":"84 Salisbury Rd",
    "sg:city":"Southampton",
    "sg:classifiers":[
        {
            "category":"Retail",
            "subcategory":"Veterinary Services",
            "type":"Services"
        }
    ],
    "sg:postcode":"SO40 3JA",
    "sg:province":"Hampshire",
    "sg:tags":[
        "surgeon"
    ],
    "wof:name":"Smart,N,",
    "wof:placetype":"venue"
},
  "geometry": {"coordinates":[-1.49406,50.922073],"type":"Point"}
}