{
  "type": "Feature",
  "properties": {
    "iso:country":"GB",
    "sg:address":"92 Carrington Lane, Ashton-on-mersey",
    "sg:city":"Sale",
    "sg:classifiers":[
        {
            "category":"Organizations",
            "subcategory":"Membership Organization",
            "type":"Services"
        }
    ],
    "sg:postcode":"M33 5NG",
    "sg:province":"Cheshire",
    "sg:tags":[
        "club"
    ],
    "wof:name":"Southgate Court Management (Sale) Ltd",
    "wof:placetype":"venue"
},
  "geometry": {"coordinates":[-2.346756,53.429638],"type":"Point"}
}