{
  "type": "Feature",
  "properties": {
    "iso:country":"GB",
    "sg:address":"41 Robertson Street",
    "sg:city":"Hastings",
    "sg:classifiers":[
        {
            "category":"Personal",
            "subcategory":"Beauty Salon",
            "type":"Services"
        }
    ],
    "sg:phone":"+44 1424 717910",
    "sg:postcode":"TN34 1HL",
    "sg:province":"East Sussex",
    "sg:tags":[
        "unisex",
        "hairdresser"
    ],
    "wof:name":"Mister B",
    "wof:placetype":"venue"
},
  "geometry": {"coordinates":[0.5771520138,50.855140686],"type":"Point"}
}