{
  "type": "Feature",
  "properties": {
    "addr:full":"Unit C, Copetts Centre, Colney Hatch Lane London Greater London N12 0AJ",
    "addr:housenumber":"unit c copetts centre",
    "addr:postcode":"n12 0aj",
    "addr:street":"Hatch Lane",
    "iso:country":"GB",
    "sg:address":"Unit C, Copetts Centre, Colney Hatch Lane",
    "sg:city":"London",
    "sg:classifiers":[
        {
            "category":"Food & Beverages",
            "subcategory":"Bakery",
            "type":"Retail Goods"
        },
        {
            "category":"Home & Garden",
            "subcategory":"Kitchen Supply",
            "type":"Retail Goods"
        }
    ],
    "sg:phone":"+44 20 8368 6119",
    "sg:postcode":"N12 0AJ",
    "sg:province":"Greater London",
    "sg:tags":[
        "confectioner",
        "baker",
        "confectionery"
    ],
    "wof:name":"Beckers Bakeries Ltd.",
    "wof:placetype":"venue"
},
  "geometry": {"coordinates":[-0.1565800011,51.6064910889],"type":"Point"}
}