{
  "type": "Feature",
  "properties": {
    "iso:country":"GB",
    "sg:address":"51 Kilmarnock Road, Shawlands",
    "sg:city":"Glasgow",
    "sg:classifiers":[
        {
            "category":"Health Services",
            "subcategory":"Optometrist",
            "type":"Services"
        }
    ],
    "sg:postcode":"G41 3YN",
    "sg:province":"Glasgow City",
    "sg:tags":[
        "optician"
    ],
    "wof:name":"Remocker Shapiro Ltd.",
    "wof:placetype":"venue"
},
  "geometry": {"coordinates":[-4.282795,55.828907],"type":"Point"}
}