{
  "type": "Feature",
  "properties": {
    "addr:full":"73 Station Road Billingham Durham TS23 1AE",
    "addr:housenumber":"73",
    "addr:postcode":"ts23 1ae",
    "addr:street":"Station Road",
    "iso:country":"GB",
    "sg:address":"73 Station Road",
    "sg:city":"Billingham",
    "sg:classifiers":[
        {
            "category":"Shopping",
            "subcategory":"Florist",
            "type":"Retail Goods"
        }
    ],
    "sg:phone":"+44 1642 533015",
    "sg:postcode":"TS23 1AE",
    "sg:province":"Durham",
    "wof:name":"W Bell",
    "wof:placetype":"venue"
},
  "geometry": {"coordinates":[-1.2951600552,54.597454071],"type":"Point"}
}