{
  "type": "Feature",
  "properties": {
    "addr:full":"68 Campfield Road St Albans Hertfordshire AL1 5HZ",
    "addr:housenumber":"68",
    "addr:postcode":"al1 5hz",
    "addr:street":"Campfield Road",
    "iso:country":"GB",
    "sg:address":"68 Campfield Road",
    "sg:city":"St Albans",
    "sg:classifiers":[
        {
            "category":"Health Services",
            "subcategory":"Medical Lab",
            "type":"Services"
        },
        {
            "category":"Shopping",
            "subcategory":"Pharmacy",
            "type":"Retail Goods"
        }
    ],
    "sg:phone":"+44 1727 861441",
    "sg:postcode":"AL1 5HZ",
    "sg:province":"Hertfordshire",
    "sg:tags":[
        "medicine",
        "alternative",
        "therapy",
        "treatment"
    ],
    "wof:name":"Complementary Therapies At Perspectives Clinic",
    "wof:placetype":"venue"
},
  "geometry": {"coordinates":[-0.314604,51.750313],"type":"Point"}
}