{
  "type": "Feature",
  "properties": {
    "addr:full":"43 Panton Street Cambridge Cambridgeshire CB2 1HL",
    "addr:housenumber":"43",
    "addr:postcode":"cb2 1hl",
    "addr:street":"Panton Street",
    "iso:country":"GB",
    "sg:address":"43 Panton Street",
    "sg:city":"Cambridge",
    "sg:classifiers":[
        {
            "category":"Bars & Pubs",
            "type":"Food & Drink"
        }
    ],
    "sg:phone":"+44 1223 505028",
    "sg:postcode":"CB2 1HL",
    "sg:province":"Cambridgeshire",
    "sg:tags":[
        "pubs",
        "inn"
    ],
    "wof:name":"Panton Arms",
    "wof:placetype":"venue"
},
  "geometry": {"coordinates":[0.124945,52.196392],"type":"Point"}
}