{
  "type": "Feature",
  "properties": {
    "iso:country":"GB",
    "sg:address":"30 Cottage Rd",
    "sg:city":"Leeds",
    "sg:classifiers":[
        {
            "category":"Building & Trades",
            "subcategory":"Construction",
            "type":"Services"
        }
    ],
    "sg:phone":"+44 113 278 3895",
    "sg:postcode":"LS6 4DD",
    "sg:province":"West Yorkshire",
    "sg:tags":[
        "builder"
    ],
    "wof:name":"Cottage Corner Services",
    "wof:placetype":"venue"
},
  "geometry": {"coordinates":[-1.581067,53.827049],"type":"Point"}
}