{
  "type": "Feature",
  "properties": {
    "iso:country":"GB",
    "sg:address":"Tyrral Park",
    "sg:city":"Peterborough",
    "sg:classifiers":[
        {
            "category":"Professional",
            "subcategory":"Testing Lab",
            "type":"Services"
        }
    ],
    "sg:phone":"+44 1733 896666",
    "sg:postcode":"PE1 5PT",
    "sg:province":"Cambridgeshire",
    "sg:tags":[
        "mot"
    ],
    "wof:name":"Appleyard Peterborough",
    "wof:placetype":"venue"
},
  "geometry": {"coordinates":[-0.217006,52.573879],"type":"Point"}
}