{
  "type": "Feature",
  "properties": {
    "iso:country":"GB",
    "sg:address":"5 St Pauls Square",
    "sg:city":"Burton-on-trent",
    "sg:classifiers":[
        {
            "category":"Farming",
            "subcategory":"Nursery",
            "type":"Manufacturing & Wholesale Goods"
        }
    ],
    "sg:phone":"+44 1283 537308",
    "sg:postcode":"DE14 2EF",
    "sg:province":"Derbyshire",
    "sg:tags":[
        "creche"
    ],
    "wof:name":"Collingwood Nursery",
    "wof:placetype":"venue"
},
  "geometry": {"coordinates":[-1.64745,52.808517],"type":"Point"}
}