{
  "type": "Feature",
  "properties": {
    "addr:full":"Rear Of 160 Marsden Rd Blackpool Lancashire FY4 3DU",
    "addr:postcode":"fy4 3du",
    "addr:street":"Marsden Rd",
    "iso:country":"GB",
    "sg:address":"Rear Of 160 Marsden Rd",
    "sg:city":"Blackpool",
    "sg:classifiers":[
        {
            "category":"Shopping",
            "type":"Retail Goods"
        }
    ],
    "sg:phone":"+44 1253 760858",
    "sg:postcode":"FY4 3DU",
    "sg:province":"Lancashire",
    "sg:tags":[
        "part",
        "accessory"
    ],
    "wof:name":"South Shore Spares",
    "wof:placetype":"venue"
},
  "geometry": {"coordinates":[-3.03402,53.797192],"type":"Point"}
}