{
  "type": "Feature",
  "properties": {
    "addr:full":"347 Washway Road Sale Cheshire M33 4FH",
    "addr:housenumber":"347",
    "addr:postcode":"m33 4fh",
    "addr:street":"Washway Road",
    "iso:country":"GB",
    "sg:address":"347 Washway Road",
    "sg:city":"Sale",
    "sg:classifiers":[
        {
            "category":"Shopping",
            "subcategory":"Computers & Home Electronics",
            "type":"Retail Goods"
        }
    ],
    "sg:phone":"+44 161 998 2759",
    "sg:postcode":"M33 4FH",
    "sg:province":"Cheshire",
    "sg:tags":[
        "aerial",
        "television",
        "radio"
    ],
    "wof:name":"Rooms Bros of Sale",
    "wof:placetype":"venue"
},
  "geometry": {"coordinates":[-2.341876,53.410728],"type":"Point"}
}