{
  "type": "Feature",
  "properties": {
    "addr:full":"46-48 Broadway, Stoneleigh Epsom Surrey KT17 2HS",
    "addr:housenumber":"46-48",
    "addr:postcode":"kt17 2hs",
    "addr:street":"Broadway",
    "iso:country":"GB",
    "sg:address":"46-48 Broadway, Stoneleigh",
    "sg:city":"Epsom",
    "sg:classifiers":[
        {
            "category":"Home & Garden",
            "subcategory":"Household Appliances",
            "type":"Retail Goods"
        }
    ],
    "sg:phone":"+44 20 8393 3252",
    "sg:postcode":"KT17 2HS",
    "sg:province":"Surrey",
    "sg:tags":[
        "domestic",
        "centre"
    ],
    "wof:name":"G H Bradbury & Son (T V) Ltd.",
    "wof:placetype":"venue"
},
  "geometry": {"coordinates":[-0.2476640046,51.3632240295],"type":"Point"}
}