{
  "type": "Feature",
  "properties": {
    "addr:full":"Earl Place, 15 Appold St Moorgate Greater London EC2A 2AA",
    "addr:housenumber":"15",
    "addr:postcode":"ec2a 2aa",
    "addr:street":"Earl;Appold St Moorgate",
    "iso:country":"GB",
    "sg:address":"Earl Place, 15 Appold St",
    "sg:city":"Moorgate",
    "sg:classifiers":[
        {
            "category":"Banks & Credit Unions",
            "subcategory":"Financial Services",
            "type":"Services"
        }
    ],
    "sg:phone":"+44 20 7247 4884",
    "sg:postcode":"EC2A 2AA",
    "sg:province":"Greater London",
    "sg:tags":[
        "consultant"
    ],
    "wof:name":"London Global Securities",
    "wof:placetype":"venue"
},
  "geometry": {"coordinates":[-0.08228,51.519798],"type":"Point"}
}