{
  "type": "Feature",
  "properties": {
    "addr:full":"22 Station Square Orpington Kent BR5 1NA",
    "addr:housenumber":"22",
    "addr:postcode":"br5 1na",
    "addr:street":"Station Square Orpington",
    "iso:country":"GB",
    "sg:address":"22 Station Square",
    "sg:city":"Orpington",
    "sg:classifiers":[
        {
            "category":"Shopping",
            "subcategory":"Gifts & Souvenirs",
            "type":"Retail Goods"
        }
    ],
    "sg:postcode":"BR5 1NA",
    "sg:province":"Kent",
    "sg:tags":[
        "shop"
    ],
    "wof:name":"The Beehive",
    "wof:placetype":"venue"
},
  "geometry": {"coordinates":[0.074386999,51.3891563416],"type":"Point"}
}