{
  "type": "Feature",
  "properties": {
    "addr:full":"117 Nether Street, North Finchley London Greater London N12 8AB",
    "addr:housenumber":"117",
    "addr:postcode":"n12 8ab",
    "addr:street":"Nether Street",
    "iso:country":"GB",
    "sg:address":"117 Nether Street, North Finchley",
    "sg:city":"London",
    "sg:classifiers":[
        {
            "category":"Autos & Motor Vehicles",
            "subcategory":"Automobile Sales",
            "type":"Retail Goods"
        }
    ],
    "sg:phone":"+44 20 8445 1264",
    "sg:postcode":"N12 8AB",
    "sg:province":"Greater London",
    "sg:tags":[
        "car"
    ],
    "wof:name":"Alfa Bravo Ltd",
    "wof:placetype":"venue"
},
  "geometry": {"coordinates":[-0.184439,51.613964],"type":"Point"}
}