{
  "type": "Feature",
  "properties": {
    "addr:full":"26 Little Headley Close Bristol City of Bristol BS13 7PJ",
    "addr:housenumber":"26",
    "addr:postcode":"bs13 7pj",
    "addr:street":"Little Headley Close",
    "iso:country":"GB",
    "sg:address":"26 Little Headley Close",
    "sg:city":"Bristol",
    "sg:classifiers":[
        {
            "category":"Professional",
            "subcategory":"Engineering",
            "type":"Services"
        }
    ],
    "sg:phone":"+44 117 964 6868",
    "sg:postcode":"BS13 7PJ",
    "sg:province":"City of Bristol",
    "sg:tags":[
        "contractor",
        "electrical",
        "engineer"
    ],
    "wof:name":"Michael Berriman",
    "wof:placetype":"venue"
},
  "geometry": {"coordinates":[-2.604696,51.418419],"type":"Point"}
}