{
  "type": "Feature",
  "properties": {
    "addr:full":"14 Broughton Clo Plymouth Devon PL3 5QT",
    "addr:housenumber":"14",
    "addr:postcode":"pl3 5qt",
    "addr:street":"Broughton Clo",
    "iso:country":"GB",
    "sg:address":"14 Broughton Clo",
    "sg:city":"Plymouth",
    "sg:classifiers":[
        {
            "category":"Professional",
            "subcategory":"Management & Consulting",
            "type":"Services"
        },
        {
            "category":"Professional",
            "subcategory":"Engineering",
            "type":"Services"
        }
    ],
    "sg:postcode":"PL3 5QT",
    "sg:province":"Devon",
    "sg:tags":[
        "civil",
        "consultant",
        "business",
        "engineer"
    ],
    "wof:name":"Bird,Kenneth L V,",
    "wof:placetype":"venue"
},
  "geometry": {"coordinates":[-4.1321291924,50.3964233398],"type":"Point"}
}