{
  "type": "Feature",
  "properties": {
    "addr:full":"4 Bank Road East Linton East Lothian EH40 3AH",
    "addr:housenumber":"4",
    "addr:postcode":"eh40 3ah",
    "addr:street":"Bank Road",
    "iso:country":"GB",
    "sg:address":"4 Bank Road",
    "sg:city":"East Linton",
    "sg:classifiers":[
        {
            "category":"Banks & Credit Unions",
            "subcategory":"Bank",
            "type":"Services"
        }
    ],
    "sg:phone":"+44 1620 860224",
    "sg:postcode":"EH40 3AH",
    "sg:province":"East Lothian",
    "sg:tags":[
        "financial",
        "institution"
    ],
    "wof:name":"The Royal Bank of Scotland Plc",
    "wof:placetype":"venue"
},
  "geometry": {"coordinates":[-2.6570749283,55.986289978],"type":"Point"}
}