{
  "type": "Feature",
  "properties": {
    "addr:full":"49 Ilfracombe Gardens Whitley Bay Northumberland NE26 3LZ",
    "addr:housenumber":"49",
    "addr:postcode":"ne26 3lz",
    "addr:street":"Ilfracombe Gardens",
    "iso:country":"GB",
    "sg:address":"49 Ilfracombe Gardens",
    "sg:city":"Whitley Bay",
    "sg:classifiers":[
        {
            "category":"Shopping",
            "subcategory":"Bicycles & Sporting Goods",
            "type":"Retail Goods"
        },
        {
            "category":"Wholesale",
            "subcategory":"Sporting Goods",
            "type":"Manufacturing & Wholesale Goods"
        }
    ],
    "sg:phone":"+44 191 251 4388",
    "sg:postcode":"NE26 3LZ",
    "sg:province":"Northumberland",
    "sg:tags":[
        "supplier",
        "equipment",
        "camping"
    ],
    "wof:name":"Outdoor World Ltd.",
    "wof:placetype":"venue"
},
  "geometry": {"coordinates":[-1.45524,55.048351],"type":"Point"}
}