{
  "type": "Feature",
  "properties": {
    "iso:country":"GB",
    "sg:address":"Boverton Castle, Boverton",
    "sg:city":"Llantwit Major",
    "sg:classifiers":[
        {
            "category":"Travel",
            "subcategory":"Hotels & Motels",
            "type":"Entertainment"
        },
        {
            "category":"Community Center",
            "subcategory":"Social",
            "type":"Public Place"
        }
    ],
    "sg:phone":"+44 1446 792428",
    "sg:postcode":"CF61 1UH",
    "sg:province":"The Vale of Glamorgan",
    "sg:tags":[
        "house",
        "activity"
    ],
    "wof:name":"Boverton Castle Hotel",
    "wof:placetype":"venue"
},
  "geometry": {"coordinates":[-3.46319,51.404861],"type":"Point"}
}