{
  "type": "Feature",
  "properties": {
    "iso:country":"GB",
    "sg:address":"18 Hedworth Lane",
    "sg:city":"Boldon Colliery",
    "sg:classifiers":[
        {
            "category":"Food & Beverages",
            "subcategory":"Meat & Fish",
            "type":"Retail Goods"
        }
    ],
    "sg:phone":"+44 191 420 0069",
    "sg:postcode":"NE35 9HS",
    "sg:province":"Tyne and Wear",
    "sg:tags":[
        "butcher"
    ],
    "wof:name":"BILLY IDLE",
    "wof:placetype":"venue"
},
  "geometry": {"coordinates":[-1.464998,54.953808],"type":"Point"}
}