{
  "type": "Feature",
  "properties": {
    "addr:full":"141 Kidbrooke Park Rd Blackheath Greater London SE3 0DZ",
    "addr:housenumber":"141",
    "addr:postcode":"se3 0dz",
    "addr:street":"Kidbrooke Park Rd",
    "iso:country":"GB",
    "sg:address":"141 Kidbrooke Park Rd",
    "sg:city":"Blackheath",
    "sg:classifiers":[
        {
            "category":"Place Of Worship",
            "type":"Public Place"
        }
    ],
    "sg:phone":"+44 20 8856 4536",
    "sg:postcode":"SE3 0DZ",
    "sg:province":"Greater London",
    "wof:name":"St John Fisher R C Church",
    "wof:placetype":"venue"
},
  "geometry": {"coordinates":[0.0268660001,51.4668388367],"type":"Point"}
}