{
  "type": "Feature",
  "properties": {
    "addr:full":"White House 44 Hunstanton Road, Dersingham King's Lynn Norfolk PE31 6HQ",
    "addr:housenumber":"44",
    "addr:postcode":"pe31 6hq",
    "addr:street":"Hunstanton Road;Lynn",
    "iso:country":"GB",
    "sg:address":"White House 44 Hunstanton Road, Dersingham",
    "sg:city":"King's Lynn",
    "sg:classifiers":[
        {
            "category":"Professional",
            "subcategory":"Management & Consulting",
            "type":"Services"
        }
    ],
    "sg:phone":"+44 1485 544880",
    "sg:postcode":"PE31 6HQ",
    "sg:province":"Norfolk",
    "sg:tags":[
        "fire",
        "consultant",
        "protection"
    ],
    "wof:name":"Downham Health Safety & Security Ltd.",
    "wof:placetype":"venue"
},
  "geometry": {"coordinates":[0.5026599765,52.8481216431],"type":"Point"}
}