{
  "type": "Feature",
  "properties": {
    "addr:full":"Unit 1 Abbots Quay, Monks Ferry Birkenhead Merseyside CH41 5LH",
    "addr:housenumber":"unit 1",
    "addr:postcode":"ch41 5lh",
    "addr:street":"Abbots Quay Monks Ferry",
    "iso:country":"GB",
    "sg:address":"Unit 1 Abbots Quay, Monks Ferry",
    "sg:city":"Birkenhead",
    "sg:classifiers":[
        {
            "category":"Professional",
            "subcategory":"Accounting & Tax Preparation",
            "type":"Services"
        }
    ],
    "sg:phone":"+44 151 649 3900",
    "sg:postcode":"CH41 5LH",
    "sg:province":"Merseyside",
    "sg:tags":[
        "accountant"
    ],
    "wof:name":"The Priory Partnership",
    "wof:placetype":"venue"
},
  "geometry": {"coordinates":[-3.0085499287,53.3904914856],"type":"Point"}
}