{
  "type": "Feature",
  "properties": {
    "iso:country":"GB",
    "sg:address":"Main Street, Ollerton",
    "sg:city":"Newark",
    "sg:classifiers":[
        {
            "category":"Travel",
            "subcategory":"Hotels & Motels",
            "type":"Entertainment"
        }
    ],
    "sg:phone":"+44 1623 822573",
    "sg:postcode":"NG22 9AD",
    "sg:province":"Nottinghamshire",
    "wof:name":"Hop Pole Hotel",
    "wof:placetype":"venue"
},
  "geometry": {"coordinates":[-0.968734026,53.2128753662],"type":"Point"}
}