{
  "type": "Feature",
  "properties": {
    "addr:full":"55 Buckingham Gardens West Molesey Greater London KT8 1TJ",
    "addr:housenumber":"55",
    "addr:postcode":"kt8 1tj",
    "addr:street":"Buckingham Gardens",
    "iso:country":"GB",
    "sg:address":"55 Buckingham Gardens",
    "sg:city":"West Molesey",
    "sg:classifiers":[
        {
            "category":"Home & Garden",
            "subcategory":"Home Furnishings",
            "type":"Retail Goods"
        }
    ],
    "sg:postcode":"KT8 1TJ",
    "sg:province":"Greater London",
    "sg:tags":[
        "furnishers",
        "planner",
        "kitchen"
    ],
    "wof:name":"Nicholas Peak",
    "wof:placetype":"venue"
},
  "geometry": {"coordinates":[-0.3674690127,51.4091491699],"type":"Point"}
}