{
  "type": "Feature",
  "properties": {
    "addr:full":"81 Byres Road Glasgow Glasgow City G11 5HN",
    "addr:housenumber":"81",
    "addr:postcode":"g11 5hn",
    "addr:street":"Byres Road",
    "iso:country":"GB",
    "sg:address":"81 Byres Road",
    "sg:city":"Glasgow",
    "sg:classifiers":[
        {
            "category":"Autos & Motor Vehicles",
            "subcategory":"Auto Supplies",
            "type":"Retail Goods"
        },
        {
            "category":"Shopping",
            "type":"Retail Goods"
        }
    ],
    "sg:phone":"+44 141 334 5626",
    "sg:postcode":"G11 5HN",
    "sg:province":"Glasgow City",
    "sg:tags":[
        "car",
        "part",
        "accessory"
    ],
    "wof:name":"Graham's Auto Centre",
    "wof:placetype":"venue"
},
  "geometry": {"coordinates":[-4.2979741096,55.8720054626],"type":"Point"}
}