{
  "type": "Feature",
  "properties": {
    "iso:country":"GB",
    "sg:address":"Ikea Tower, 255 North Circular Rd, Brent Park",
    "sg:city":"London",
    "sg:classifiers":[
        {
            "category":"Health Services",
            "subcategory":"Clinic",
            "type":"Services"
        }
    ],
    "sg:phone":"+44 20 8237 2000",
    "sg:postcode":"NW10 0JQ",
    "sg:province":"Greater London",
    "sg:tags":[
        "nh"
    ],
    "wof:name":"North West London Mental Health N H S Tr",
    "wof:placetype":"venue"
},
  "geometry": {"coordinates":[-0.2585200071,51.5524597168],"type":"Point"}
}