{
  "type": "Feature",
  "properties": {
    "addr:full":"59 Lee Green Mirfield West Yorkshire WF14 0AE",
    "addr:housenumber":"59",
    "addr:postcode":"wf14 0ae",
    "addr:street":"Lee;West",
    "iso:country":"GB",
    "sg:address":"59 Lee Green",
    "sg:city":"Mirfield",
    "sg:classifiers":[
        {
            "category":"Bars & Pubs",
            "type":"Food & Drink"
        }
    ],
    "sg:phone":"+44 1924 490431",
    "sg:postcode":"WF14 0AE",
    "sg:province":"West Yorkshire",
    "sg:tags":[
        "pubs",
        "inn"
    ],
    "wof:name":"Shoulder of Mutton",
    "wof:placetype":"venue"
},
  "geometry": {"coordinates":[-1.689909,53.684158],"type":"Point"}
}