{
  "type": "Feature",
  "properties": {
    "addr:full":"13-14a Norman Way Industrial Estate, Ate Norman Way Cambridge Cambridgeshire CB4 5QE",
    "addr:housenumber":"13-14a;estate",
    "addr:postcode":"cb4 5qe",
    "addr:street":"Norman Way Industrial;Norman Way",
    "iso:country":"GB",
    "sg:address":"13-14a Norman Way Industrial Estate, Ate Norman Way",
    "sg:city":"Cambridge",
    "sg:classifiers":[
        {
            "category":"Shopping",
            "subcategory":"Computers & Home Electronics",
            "type":"Retail Goods"
        }
    ],
    "sg:phone":"+44 1954 231616",
    "sg:postcode":"CB4 5QE",
    "sg:province":"Cambridgeshire",
    "sg:tags":[
        "electrical"
    ],
    "wof:name":"Beam Group Ltd.",
    "wof:placetype":"venue"
},
  "geometry": {"coordinates":[0.02027,52.304962],"type":"Point"}
}