{
  "type": "Feature",
  "properties": {
    "iso:country":"GB",
    "sg:address":"Exchange House, 458 Midsummer Blvd, Central Milton Keynes",
    "sg:city":"Milton Keynes",
    "sg:classifiers":[
        {
            "category":"Personal",
            "subcategory":"Beauty Salon",
            "type":"Services"
        }
    ],
    "sg:phone":"+44 1908 230133",
    "sg:postcode":"MK9 2EA",
    "sg:province":"Buckinghamshire",
    "sg:tags":[
        "unisex",
        "hairdresser"
    ],
    "wof:name":"Hair Exchange",
    "wof:placetype":"venue"
},
  "geometry": {"coordinates":[-0.762182,52.039192],"type":"Point"}
}