{
  "type": "Feature",
  "properties": {
    "addr:full":"Black Lodge, Hargrave Wellingborough Northamptonshire NN9 6BS",
    "addr:postcode":"nn9 6bs",
    "iso:country":"GB",
    "sg:address":"Black Lodge, Hargrave",
    "sg:city":"Wellingborough",
    "sg:classifiers":[
        {
            "category":"Farming",
            "subcategory":"Livestock Farm",
            "type":"Manufacturing & Wholesale Goods"
        }
    ],
    "sg:phone":"+44 1933 622821",
    "sg:postcode":"NN9 6BS",
    "sg:province":"Northamptonshire",
    "sg:tags":[
        "others"
    ],
    "wof:name":"R H Merrick",
    "wof:placetype":"venue"
},
  "geometry": {"coordinates":[-0.4800589979,52.324016571],"type":"Point"}
}