{
  "type": "Feature",
  "properties": {
    "addr:full":"1 Shardlow Gardens Doncaster South Yorkshire DN4 6UB",
    "addr:housenumber":"1",
    "addr:postcode":"dn4 6ub",
    "addr:street":"Shardlow Gardens",
    "iso:country":"GB",
    "sg:address":"1 Shardlow Gardens",
    "sg:city":"Doncaster",
    "sg:classifiers":[
        {
            "category":"Professional",
            "subcategory":"Accounting & Tax Preparation",
            "type":"Services"
        }
    ],
    "sg:postcode":"DN4 6UB",
    "sg:province":"South Yorkshire",
    "sg:tags":[
        "accountant"
    ],
    "wof:name":"Blenkinsop & Co",
    "wof:placetype":"venue"
},
  "geometry": {"coordinates":[-1.073225975,53.5019035339],"type":"Point"}
}