{
  "type": "Feature",
  "properties": {
    "addr:full":"120a High Street Brentford Greater London TW8 8AT",
    "addr:housenumber":"120a",
    "addr:postcode":"tw8 8at",
    "addr:street":"High Street",
    "iso:country":"GB",
    "sg:address":"120a High Street",
    "sg:city":"Brentford",
    "sg:classifiers":[
        {
            "category":"Professional",
            "subcategory":"Art Services",
            "type":"Services"
        }
    ],
    "sg:phone":"+44 20 8758 1115",
    "sg:postcode":"TW8 8AT",
    "sg:province":"Greater London",
    "sg:tags":[
        "photographer"
    ],
    "wof:name":"The Awkward Bros",
    "wof:placetype":"venue"
},
  "geometry": {"coordinates":[-0.308611989,51.4829177856],"type":"Point"}
}