{
  "type": "Feature",
  "properties": {
    "iso:country":"GB",
    "sg:address":"Barnehurst Close",
    "sg:city":"Erith",
    "sg:classifiers":[
        {
            "category":"Education",
            "subcategory":"School",
            "type":"Public Place"
        },
        {
            "category":"Government",
            "subcategory":"Office",
            "type":"Public Place"
        }
    ],
    "sg:phone":"+44 1322 334214",
    "sg:postcode":"DA8 3NL",
    "sg:province":"Kent",
    "sg:tags":[
        "college",
        "local"
    ],
    "wof:name":"Barnehurst Junior School",
    "wof:placetype":"venue"
},
  "geometry": {"coordinates":[0.162255,51.469868],"type":"Point"}
}