{
  "type": "Feature",
  "properties": {
    "addr:full":"55 Pendre Cardigan Ceredigion SA43 1JR",
    "addr:housenumber":"55",
    "addr:postcode":"sa43 1jr",
    "addr:street":"Pendre",
    "iso:country":"GB",
    "sg:address":"55 Pendre",
    "sg:city":"Cardigan",
    "sg:classifiers":[
        {
            "category":"Food & Beverages",
            "subcategory":"Specialty",
            "type":"Retail Goods"
        }
    ],
    "sg:phone":"+44 1239 612187",
    "sg:postcode":"SA43 1JR",
    "sg:province":"Ceredigion",
    "sg:tags":[
        "product",
        "health"
    ],
    "wof:name":"T & H Andrews",
    "wof:placetype":"venue"
},
  "geometry": {"coordinates":[-4.6604418755,52.0840263367],"type":"Point"}
}