{
  "type": "Feature",
  "properties": {
    "addr:full":"828 Manchester Rd Rochdale Lancashire OL11 3AW",
    "addr:housenumber":"828",
    "addr:postcode":"ol11 3aw",
    "addr:street":"Manchester Rd",
    "iso:country":"GB",
    "sg:address":"828 Manchester Rd",
    "sg:city":"Rochdale",
    "sg:classifiers":[
        {
            "category":"Building & Trades",
            "subcategory":"Construction",
            "type":"Services"
        }
    ],
    "sg:phone":"+44 1706 354138",
    "sg:postcode":"OL11 3AW",
    "sg:province":"Lancashire",
    "sg:tags":[
        "roofing"
    ],
    "wof:name":"I B S Roofing",
    "wof:placetype":"venue"
},
  "geometry": {"coordinates":[-2.179008007,53.5919532776],"type":"Point"}
}