{
  "type": "Feature",
  "properties": {
    "iso:country":"GB",
    "sg:address":"24-26 Meltham Road",
    "sg:city":"Huddersfield",
    "sg:classifiers":[
        {
            "category":"Autos & Motor Vehicles",
            "subcategory":"Auto Supplies",
            "type":"Retail Goods"
        }
    ],
    "sg:phone":"+44 1484 543111",
    "sg:postcode":"HD1 3TJ",
    "sg:province":"West Yorkshire",
    "sg:tags":[
        "component"
    ],
    "wof:name":"Mandell & Bottomley Specialised Motor Services Ltd.",
    "wof:placetype":"venue"
},
  "geometry": {"coordinates":[-1.795905,53.632835],"type":"Point"}
}