{
  "type": "Feature",
  "properties": {
    "addr:full":"8 Quarry Street Guildford Surrey GU1 3UY",
    "addr:housenumber":"8",
    "addr:postcode":"gu1 3uy",
    "addr:street":"Quarry Street",
    "iso:country":"GB",
    "sg:address":"8 Quarry Street",
    "sg:city":"Guildford",
    "sg:classifiers":[
        {
            "category":"Real Estate",
            "subcategory":"Surveying",
            "type":"Services"
        }
    ],
    "sg:phone":"+44 1483 796800",
    "sg:postcode":"GU1 3UY",
    "sg:province":"Surrey",
    "sg:tags":[
        "surveyor",
        "valuer"
    ],
    "wof:name":"Savills (L&P) Ltd.",
    "wof:placetype":"venue"
},
  "geometry": {"coordinates":[-0.5740209818,51.2339630127],"type":"Point"}
}