{
  "type": "Feature",
  "properties": {
    "iso:country":"GB",
    "sg:address":"101 Harley St",
    "sg:city":"West End",
    "sg:classifiers":[
        {
            "category":"Sports & Exercise",
            "subcategory":"Gym",
            "type":"Entertainment"
        }
    ],
    "sg:phone":"+44 20 7493 0994",
    "sg:postcode":"W1N 1DF",
    "sg:province":"Hampshire",
    "sg:tags":[
        "fitness",
        "health",
        "centre"
    ],
    "wof:name":"Personnel Fitness (London) Ltd",
    "wof:placetype":"venue"
},
  "geometry": {"coordinates":[-0.148047,51.520981],"type":"Point"}
}