{
  "type": "Feature",
  "properties": {
    "iso:country":"GB",
    "sg:address":"84 City Road",
    "sg:city":"London",
    "sg:classifiers":[
        {
            "category":"Fast Food",
            "type":"Food & Drink"
        }
    ],
    "sg:postcode":"EC1Y 2DP",
    "sg:province":"Greater London",
    "sg:tags":[
        "away",
        "take"
    ],
    "wof:name":"Oscar's Sandwich Bar",
    "wof:placetype":"venue"
},
  "geometry": {"coordinates":[-0.0877119973,51.5252342224],"type":"Point"}
}