{
  "type": "Feature",
  "properties": {
    "addr:full":"14 Barnby Gate Newark Nottinghamshire NG24 1PZ",
    "addr:housenumber":"14",
    "addr:postcode":"ng24 1pz",
    "addr:street":"Barnby Gate",
    "iso:country":"GB",
    "sg:address":"14 Barnby Gate",
    "sg:city":"Newark",
    "sg:classifiers":[
        {
            "category":"Professional",
            "subcategory":"Art Services",
            "type":"Services"
        }
    ],
    "sg:phone":"+44 1636 610426",
    "sg:postcode":"NG24 1PZ",
    "sg:province":"Nottinghamshire",
    "sg:tags":[
        "picture",
        "framing"
    ],
    "wof:name":"SPEEDFRAME",
    "wof:placetype":"venue"
},
  "geometry": {"coordinates":[-0.806121,53.075397],"type":"Point"}
}