{
  "type": "Feature",
  "properties": {
    "addr:full":"5 Bennerley Court, Bulwell Nottingham Nottinghamshire NG6 8UT",
    "addr:housenumber":"5",
    "addr:postcode":"ng6 8ut",
    "addr:street":"Bennerley Court",
    "iso:country":"GB",
    "sg:address":"5 Bennerley Court, Bulwell",
    "sg:city":"Nottingham",
    "sg:classifiers":[
        {
            "category":"Manufacturing",
            "subcategory":"Tools & Machinery",
            "type":"Manufacturing & Wholesale Goods"
        }
    ],
    "sg:phone":"+44 115 975 7571",
    "sg:postcode":"NG6 8UT",
    "sg:province":"Nottinghamshire",
    "sg:tags":[
        "bearing",
        "stockist"
    ],
    "wof:name":"Airport Bearing Co. Ltd.",
    "wof:placetype":"venue"
},
  "geometry": {"coordinates":[-1.1981639862,53.0011940002],"type":"Point"}
}