{
  "type": "Feature",
  "properties": {
    "addr:full":"5a Woodside Avenue London Greater London SE25 5DW",
    "addr:housenumber":"5a",
    "addr:postcode":"se25 5dw",
    "addr:street":"Woodside Avenue",
    "iso:country":"GB",
    "sg:address":"5a Woodside Avenue",
    "sg:city":"London",
    "sg:classifiers":[
        {
            "category":"Building & Trades",
            "subcategory":"Construction",
            "type":"Services"
        }
    ],
    "sg:phone":"+44 20 8654 2191",
    "sg:postcode":"SE25 5DW",
    "sg:province":"Greater London",
    "sg:tags":[
        "roofing"
    ],
    "wof:name":"South London Asphalt Co. Ltd.",
    "wof:placetype":"venue"
},
  "geometry": {"coordinates":[-0.066046,51.391323],"type":"Point"}
}