{
  "type": "Feature",
  "properties": {
    "addr:full":"31 Bury New Road Manchester Greater Manchester M8 8EQ",
    "addr:housenumber":"31",
    "addr:postcode":"m8 8eq",
    "addr:street":"Bury New Road",
    "iso:country":"GB",
    "sg:address":"31 Bury New Road",
    "sg:city":"Manchester",
    "sg:classifiers":[
        {
            "category":"Shopping",
            "subcategory":"Department Store",
            "type":"Retail Goods"
        },
        {
            "category":"Shopping",
            "subcategory":"Clothing, Apparel, & Fashions",
            "type":"Retail Goods"
        }
    ],
    "sg:postcode":"M8 8EQ",
    "sg:province":"Greater Manchester",
    "sg:tags":[
        "clothing"
    ],
    "wof:name":"Fashion Arena Ltd.",
    "wof:placetype":"venue"
},
  "geometry": {"coordinates":[-2.2499389648,53.4933319092],"type":"Point"}
}