{
  "type": "Feature",
  "properties": {
    "addr:full":"Circus Street Brighton East Sussex BN2 9QF",
    "addr:postcode":"bn2 9qf",
    "addr:street":"Circus Street",
    "iso:country":"GB",
    "sg:address":"Circus Street",
    "sg:city":"Brighton",
    "sg:classifiers":[
        {
            "category":"Wholesale",
            "subcategory":"Fruits & Vegetables",
            "type":"Manufacturing & Wholesale Goods"
        }
    ],
    "sg:phone":"+44 1273 705516",
    "sg:postcode":"BN2 9QF",
    "sg:province":"East Sussex",
    "wof:name":"J G Hale Ltd.",
    "wof:placetype":"venue"
},
  "geometry": {"coordinates":[-0.134968996,50.8250083923],"type":"Point"}
}