{
  "type": "Feature",
  "properties": {
    "addr:full":"Rockery House, Queenwood Road Stockbridge Hampshire SO20 8BP",
    "addr:postcode":"so20 8bp",
    "addr:street":"Queenwood Road",
    "iso:country":"GB",
    "sg:address":"Rockery House, Queenwood Road",
    "sg:city":"Stockbridge",
    "sg:classifiers":[
        {
            "category":"Shopping",
            "subcategory":"Antiques",
            "type":"Retail Goods"
        }
    ],
    "sg:postcode":"SO20 8BP",
    "sg:province":"Hampshire",
    "wof:name":"Professional Antiques",
    "wof:placetype":"venue"
},
  "geometry": {"coordinates":[-1.5632389784,51.0939865112],"type":"Point"}
}