{
  "type": "Feature",
  "properties": {
    "iso:country":"GB",
    "sg:address":"61 High Street",
    "sg:city":"Alness",
    "sg:classifiers":[
        {
            "category":"Fast Food",
            "type":"Food & Drink"
        }
    ],
    "sg:phone":"+44 1349 883717",
    "sg:postcode":"IV17 0SH",
    "sg:province":"Highland",
    "sg:tags":[
        "away",
        "take"
    ],
    "wof:name":"New World Chinese Take Away",
    "wof:placetype":"venue"
},
  "geometry": {"coordinates":[-4.2532639503,57.6958999634],"type":"Point"}
}