{
  "type": "Feature",
  "properties": {
    "iso:country":"GB",
    "sg:address":"12 Kelso Place",
    "sg:city":"Dundee",
    "sg:classifiers":[
        {
            "category":"Wholesale",
            "subcategory":"Music Publishers",
            "type":"Manufacturing & Wholesale Goods"
        }
    ],
    "sg:postcode":"DD2 1SL",
    "sg:province":"Dundee City",
    "wof:name":"Masterclass Music Ltd.",
    "wof:placetype":"venue"
},
  "geometry": {"coordinates":[-3.0106561184,56.4610862732],"type":"Point"}
}