{
  "type": "Feature",
  "properties": {
    "addr:full":"24 Trinity Square Llandudno Conwy LL30 2RH",
    "addr:housenumber":"24",
    "addr:postcode":"ll30 2rh",
    "addr:street":"Trinity Square",
    "iso:country":"GB",
    "sg:address":"24 Trinity Square",
    "sg:city":"Llandudno",
    "sg:classifiers":[
        {
            "category":"Professional",
            "subcategory":"Lawyer & Legal Services",
            "type":"Services"
        }
    ],
    "sg:phone":"+44 1492 871474",
    "sg:postcode":"LL30 2RH",
    "sg:province":"Conwy",
    "sg:tags":[
        "practitioner",
        "insolvency"
    ],
    "wof:name":"Parkin S Booth & Co",
    "wof:placetype":"venue"
},
  "geometry": {"coordinates":[-3.827712,53.323093],"type":"Point"}
}