{
  "type": "Feature",
  "properties": {
    "iso:country":"GB",
    "sg:address":"3 Rookery Place, Fenstanton",
    "sg:city":"Huntingdon",
    "sg:classifiers":[
        {
            "category":"Personal",
            "subcategory":"Beauty Salon",
            "type":"Services"
        }
    ],
    "sg:postcode":"PE28 9LZ",
    "sg:province":"Bedfordshire",
    "sg:tags":[
        "unisex",
        "hairdresser"
    ],
    "wof:name":"Elegant",
    "wof:placetype":"venue"
},
  "geometry": {"coordinates":[-0.0654570013,52.2976341248],"type":"Point"}
}