{
  "type": "Feature",
  "properties": {
    "addr:full":"20 Rock Avenue Gillingham Kent ME7 5PT",
    "addr:housenumber":"20",
    "addr:postcode":"me7 5pt",
    "addr:street":"Rock Avenue",
    "iso:country":"GB",
    "sg:address":"20 Rock Avenue",
    "sg:city":"Gillingham",
    "sg:classifiers":[
        {
            "category":"Professional",
            "subcategory":"Accounting & Tax Preparation",
            "type":"Services"
        }
    ],
    "sg:postcode":"ME7 5PT",
    "sg:province":"Kent",
    "sg:tags":[
        "accountant"
    ],
    "wof:name":"Giles Williams & Co.",
    "wof:placetype":"venue"
},
  "geometry": {"coordinates":[0.5467460155,51.380115509],"type":"Point"}
}