{
  "type": "Feature",
  "properties": {
    "addr:full":"12 Briercliffe Road Burnley Lancashire BB10 1XB",
    "addr:housenumber":"12",
    "addr:postcode":"bb10 1xb",
    "addr:street":"Briercliffe Road",
    "iso:country":"GB",
    "sg:address":"12 Briercliffe Road",
    "sg:city":"Burnley",
    "sg:classifiers":[
        {
            "category":"Home & Garden",
            "subcategory":"Home Furnishings",
            "type":"Retail Goods"
        }
    ],
    "sg:phone":"+44 1282 839844",
    "sg:postcode":"BB10 1XB",
    "sg:province":"Lancashire",
    "sg:tags":[
        "blind",
        "curtain",
        "fitting"
    ],
    "wof:name":"Cushi Numbers",
    "wof:placetype":"venue"
},
  "geometry": {"coordinates":[-2.2328059673,53.8028335571],"type":"Point"}
}