{
  "type": "Feature",
  "properties": {
    "addr:full":"78-80 Long Street Thirsk North Yorkshire YO7 1AU",
    "addr:housenumber":"78-80",
    "addr:postcode":"yo7 1au",
    "addr:street":"Long Street",
    "iso:country":"GB",
    "sg:address":"78-80 Long Street",
    "sg:city":"Thirsk",
    "sg:classifiers":[
        {
            "category":"Retail",
            "subcategory":"Auto Repair",
            "type":"Services"
        }
    ],
    "sg:phone":"+44 1845 524000",
    "sg:postcode":"YO7 1AU",
    "sg:province":"North Yorkshire",
    "sg:tags":[
        "modification",
        "garage"
    ],
    "wof:name":"Alan Evans Ltd.",
    "wof:placetype":"venue"
},
  "geometry": {"coordinates":[-1.33966,54.236065],"type":"Point"}
}