{
  "type": "Feature",
  "properties": {
    "addr:full":"Unit 4 Guardian Business Park, Dallow Road Luton Bedfordshire LU1 1NA",
    "addr:housenumber":"unit 4",
    "addr:postcode":"lu1 1na",
    "addr:street":"Guardian Business Park Dallow Road",
    "iso:country":"GB",
    "sg:address":"Unit 4 Guardian Business Park, Dallow Road",
    "sg:city":"Luton",
    "sg:classifiers":[
        {
            "category":"Manufacturing",
            "subcategory":"Petroleum Products",
            "type":"Manufacturing & Wholesale Goods"
        }
    ],
    "sg:postcode":"LU1 1NA",
    "sg:province":"Bedfordshire",
    "sg:tags":[
        "double",
        "glazing"
    ],
    "wof:name":"Pennine Windows Ltd.",
    "wof:placetype":"venue"
},
  "geometry": {"coordinates":[-0.4156149924,51.8813362122],"type":"Point"}
}