{
  "type": "Feature",
  "properties": {
    "addr:full":"17 Mill Road Worthing West Sussex BN11 4LD",
    "addr:housenumber":"17",
    "addr:postcode":"bn11 4ld",
    "addr:street":"Mill Road",
    "iso:country":"GB",
    "sg:address":"17 Mill Road",
    "sg:city":"Worthing",
    "sg:classifiers":[
        {
            "category":"Health Services",
            "subcategory":"Dentist",
            "type":"Services"
        }
    ],
    "sg:phone":"+44 1903 200111",
    "sg:postcode":"BN11 4LD",
    "sg:province":"West Sussex",
    "sg:tags":[
        "technician",
        "dental"
    ],
    "wof:name":"Millhouse Dental Laboratory",
    "wof:placetype":"venue"
},
  "geometry": {"coordinates":[-0.3896909952,50.8140411377],"type":"Point"}
}