{
  "type": "Feature",
  "properties": {
    "iso:country":"GB",
    "sg:address":"4 Castilian Terr",
    "sg:city":"Northampton",
    "sg:classifiers":[
        {
            "category":"Professional",
            "subcategory":"Lawyer & Legal Services",
            "type":"Services"
        }
    ],
    "sg:postcode":"NN1 1LE",
    "sg:province":"Northamptonshire",
    "sg:tags":[
        "solicitor"
    ],
    "wof:name":"Woodford Robinson",
    "wof:placetype":"venue"
},
  "geometry": {"coordinates":[-0.8917980194,52.2372245789],"type":"Point"}
}