{
  "type": "Feature",
  "properties": {
    "addr:full":"The Market Hall, College Grn Tywyn Gwynedd LL36 9BY",
    "addr:postcode":"ll36 9by",
    "addr:street":"College Grn",
    "iso:country":"GB",
    "sg:address":"The Market Hall, College Grn",
    "sg:city":"Tywyn",
    "sg:classifiers":[
        {
            "category":"Shopping",
            "subcategory":"Stationery & Office Supplies",
            "type":"Retail Goods"
        }
    ],
    "sg:phone":"+44 1654 712020",
    "sg:postcode":"LL36 9BY",
    "sg:province":"Gwynedd",
    "wof:name":"Impact",
    "wof:placetype":"venue"
},
  "geometry": {"coordinates":[-4.0884189606,52.5865859985],"type":"Point"}
}