{
  "type": "Feature",
  "properties": {
    "iso:country":"GB",
    "sg:address":"Dock Gate No 2",
    "sg:city":"Felixstowe",
    "sg:classifiers":[
        {
            "category":"Freight",
            "type":"Transportation"
        }
    ],
    "sg:phone":"+44 1394 675601",
    "sg:postcode":"IP11 8SW",
    "sg:province":"Suffolk",
    "sg:tags":[
        "forwarders"
    ],
    "wof:name":"Stora Enso",
    "wof:placetype":"venue"
},
  "geometry": {"coordinates":[1.342465,51.961369],"type":"Point"}
}