{
  "type": "Feature",
  "properties": {
    "iso:country":"GB",
    "sg:address":"Unit 1 Tundry Way",
    "sg:city":"Blaydon-on-tyne",
    "sg:classifiers":[
        {
            "category":"Shopping",
            "subcategory":"Bicycles & Sporting Goods",
            "type":"Retail Goods"
        }
    ],
    "sg:phone":"+44 191 499 0345",
    "sg:postcode":"NE21 5SJ",
    "sg:province":"Tyne and Wear",
    "sg:tags":[
        "water",
        "cooler"
    ],
    "wof:name":"Aqua Cool",
    "wof:placetype":"venue"
},
  "geometry": {"coordinates":[-1.6947200298,54.9668617249],"type":"Point"}
}