{
  "type": "Feature",
  "properties": {
    "iso:country":"GB",
    "sg:address":"Heathlands Nursery, Ixworth",
    "sg:city":"Bury St Edmunds",
    "sg:classifiers":[
        {
            "category":"Wholesale",
            "subcategory":"Fruits & Vegetables",
            "type":"Manufacturing & Wholesale Goods"
        }
    ],
    "sg:postcode":"IP31 2JP",
    "sg:province":"Suffolk",
    "wof:name":"M H W Turner",
    "wof:placetype":"venue"
},
  "geometry": {"coordinates":[0.8396499753,52.2942047119],"type":"Point"}
}