{
  "type": "Feature",
  "properties": {
    "iso:country":"GB",
    "sg:address":"Ampthill Road, Kempston Hardwick",
    "sg:city":"Bedford",
    "sg:classifiers":[
        {
            "category":"Bars & Pubs",
            "type":"Food & Drink"
        }
    ],
    "sg:phone":"+44 1234 852310",
    "sg:postcode":"MK45 3JF",
    "sg:province":"Bedfordshire",
    "sg:tags":[
        "pubs",
        "inn"
    ],
    "wof:name":"The Chimney Corner",
    "wof:placetype":"venue"
},
  "geometry": {"coordinates":[-0.481479,52.111721],"type":"Point"}
}