{
  "type": "Feature",
  "properties": {
    "addr:full":"13 Hornbeam Way, Cheshunt Waltham Cross Greater London EN7 6EZ",
    "addr:housenumber":"13",
    "addr:postcode":"en7 6ez",
    "addr:street":"Hornbeam Way",
    "iso:country":"GB",
    "sg:address":"13 Hornbeam Way, Cheshunt",
    "sg:city":"Waltham Cross",
    "sg:classifiers":[
        {
            "category":"Autos & Motor Vehicles",
            "subcategory":"Motorcycle Sales",
            "type":"Retail Goods"
        }
    ],
    "sg:phone":"+44 1992 632302",
    "sg:postcode":"EN7 6EZ",
    "sg:province":"Greater London",
    "sg:tags":[
        "chauffeur",
        "driven",
        "car"
    ],
    "wof:name":"Chauffeur Drive Solutions",
    "wof:placetype":"venue"
},
  "geometry": {"coordinates":[-0.0628509969,51.7085952759],"type":"Point"}
}