{
  "type": "Feature",
  "properties": {
    "iso:country":"GB",
    "sg:address":"Southview, Sharpham",
    "sg:city":"Street",
    "sg:classifiers":[
        {
            "category":"Farming",
            "subcategory":"Farm",
            "type":"Manufacturing & Wholesale Goods"
        }
    ],
    "sg:phone":"+44 1458 447833",
    "sg:postcode":"BA16 9SF",
    "sg:province":"Somerset",
    "sg:tags":[
        "mixed",
        "crop"
    ],
    "wof:name":"C D NORTON",
    "wof:placetype":"venue"
},
  "geometry": {"coordinates":[-2.7487199306,51.127872467],"type":"Point"}
}