{
  "type": "Feature",
  "properties": {
    "addr:full":"Perry Farm Exeter Devon EX5 5LN",
    "addr:postcode":"ex5 5ln",
    "iso:country":"GB",
    "sg:address":"Perry Farm",
    "sg:city":"Exeter",
    "sg:classifiers":[
        {
            "category":"Farming",
            "subcategory":"Livestock Farm",
            "type":"Manufacturing & Wholesale Goods"
        }
    ],
    "sg:phone":"+44 1884 855306",
    "sg:postcode":"EX5 5LN",
    "sg:province":"Devon",
    "sg:tags":[
        "others"
    ],
    "wof:name":"J Chanin",
    "wof:placetype":"venue"
},
  "geometry": {"coordinates":[-3.5181899071,50.8397407532],"type":"Point"}
}