{
  "type": "Feature",
  "properties": {
    "iso:country":"GB",
    "sg:address":"26-28 Drysdale Street",
    "sg:city":"Alloa",
    "sg:classifiers":[
        {
            "category":"Government",
            "subcategory":"Office",
            "type":"Public Place"
        }
    ],
    "sg:phone":"+44 1259 226200",
    "sg:postcode":"FK10 1JL",
    "sg:province":"Clackmannanshire",
    "sg:tags":[
        "local"
    ],
    "wof:name":"CLACKMANNANSHIRE DISTRICT COUNCIL",
    "wof:placetype":"venue"
},
  "geometry": {"coordinates":[-3.7908771038,56.1159706116],"type":"Point"}
}