{
  "type": "Feature",
  "properties": {
    "iso:country":"GB",
    "sg:address":"87 Replingham Road",
    "sg:city":"London",
    "sg:classifiers":[
        {
            "category":"Home & Garden",
            "subcategory":"Carpets & Floor Coverings",
            "type":"Retail Goods"
        }
    ],
    "sg:phone":"+44 20 8877 9191",
    "sg:postcode":"SW18 5LU",
    "sg:province":"Greater London",
    "sg:tags":[
        "carpets",
        "rug",
        "matting"
    ],
    "wof:name":"Redwood Interiors Ltd.",
    "wof:placetype":"venue"
},
  "geometry": {"coordinates":[-0.202724,51.445389],"type":"Point"}
}