{
  "type": "Feature",
  "properties": {
    "addr:full":"The Maltings, School Lane Amersham Buckinghamshire HP7 0ET",
    "addr:postcode":"hp7 0et",
    "addr:street":"The;School Lane",
    "iso:country":"GB",
    "sg:address":"The Maltings, School Lane",
    "sg:city":"Amersham",
    "sg:classifiers":[
        {
            "category":"Home & Garden",
            "subcategory":"Home Furnishings",
            "type":"Retail Goods"
        },
        {
            "category":"Wholesale",
            "subcategory":"Home Furnishings",
            "type":"Manufacturing & Wholesale Goods"
        }
    ],
    "sg:phone":"+44 1494 721089",
    "sg:postcode":"HP7 0ET",
    "sg:province":"Buckinghamshire",
    "sg:tags":[
        "blind",
        "manufacture",
        "fitting",
        "curtain"
    ],
    "wof:name":"Les Ouvrieres",
    "wof:placetype":"venue"
},
  "geometry": {"coordinates":[-0.618791,51.668301],"type":"Point"}
}