{
  "type": "Feature",
  "properties": {
    "iso:country":"GB",
    "sg:address":"13 Bridge Street",
    "sg:city":"Newhaven",
    "sg:classifiers":[
        {
            "category":"Retail",
            "subcategory":"Funeral Services",
            "type":"Services"
        }
    ],
    "sg:phone":"+44 1273 611004",
    "sg:postcode":"BN9 9PH",
    "sg:province":"East Sussex",
    "sg:tags":[
        "director"
    ],
    "wof:name":"Bennett Funeral Service",
    "wof:placetype":"venue"
},
  "geometry": {"coordinates":[0.051354,50.79446],"type":"Point"}
}