{
  "type": "Feature",
  "properties": {
    "addr:full":"40 Townhead Irvine North Ayrshire KA12 0BE",
    "addr:housenumber":"40",
    "addr:postcode":"ka12 0be",
    "addr:street":"Townhead",
    "iso:country":"GB",
    "sg:address":"40 Townhead",
    "sg:city":"Irvine",
    "sg:classifiers":[
        {
            "category":"Taxi",
            "type":"Transportation"
        },
        {
            "category":"Military Area",
            "subcategory":"Air Force Base",
            "type":"Public Place"
        }
    ],
    "sg:phone":"+44 1294 271010",
    "sg:postcode":"KA12 0BE",
    "sg:province":"North Ayrshire",
    "sg:tags":[
        "hire",
        "private"
    ],
    "wof:name":"C Cars",
    "wof:placetype":"venue"
},
  "geometry": {"coordinates":[-4.6620531082,55.6138343811],"type":"Point"}
}