{
  "type": "Feature",
  "properties": {
    "addr:full":"151 Dowson Road Hyde Cheshire SK14 5HJ",
    "addr:housenumber":"151",
    "addr:postcode":"sk14 5hj",
    "addr:street":"Dowson Road",
    "iso:country":"GB",
    "sg:address":"151 Dowson Road",
    "sg:city":"Hyde",
    "sg:classifiers":[
        {
            "category":"Building & Trades",
            "subcategory":"Construction",
            "type":"Services"
        }
    ],
    "sg:postcode":"SK14 5HJ",
    "sg:province":"Cheshire",
    "sg:tags":[
        "builder"
    ],
    "wof:name":"Lee Adams",
    "wof:placetype":"venue"
},
  "geometry": {"coordinates":[-2.0757820606,53.4407196045],"type":"Point"}
}