{
  "type": "Feature",
  "properties": {
    "iso:country":"GB",
    "sg:address":"10 Winchelsea Drive",
    "sg:city":"Chelmsford",
    "sg:classifiers":[
        {
            "category":"Health Services",
            "subcategory":"Clinic",
            "type":"Services"
        }
    ],
    "sg:phone":"+44 1245 353629",
    "sg:postcode":"CM2 9TL",
    "sg:province":"Essex",
    "sg:tags":[
        "aromatherapy"
    ],
    "wof:name":"Effleurage",
    "wof:placetype":"venue"
},
  "geometry": {"coordinates":[0.488649,51.719357],"type":"Point"}
}