{
  "type": "Feature",
  "properties": {
    "addr:full":"35a West St Boston Lincolnshire PE21 8QN",
    "addr:housenumber":"35a",
    "addr:postcode":"pe21 8qn",
    "addr:street":"West St",
    "iso:country":"GB",
    "sg:address":"35a West St",
    "sg:city":"Boston",
    "sg:classifiers":[
        {
            "category":"Professional",
            "subcategory":"Lawyer & Legal Services",
            "type":"Services"
        }
    ],
    "sg:phone":"+44 1205 365533",
    "sg:postcode":"PE21 8QN",
    "sg:province":"Lincolnshire",
    "sg:tags":[
        "advice",
        "counselling"
    ],
    "wof:name":"Relate",
    "wof:placetype":"venue"
},
  "geometry": {"coordinates":[-0.0269290004,52.976436615],"type":"Point"}
}