{
  "type": "Feature",
  "properties": {
    "iso:country":"GB",
    "sg:address":"242 Yardley Wood Road",
    "sg:city":"Birmingham",
    "sg:classifiers":[
        {
            "category":"Professional",
            "subcategory":"Lawyer & Legal Services",
            "type":"Services"
        }
    ],
    "sg:phone":"+44 121 449 0002",
    "sg:postcode":"B13 9JN",
    "sg:province":"West Midlands",
    "sg:tags":[
        "solicitor"
    ],
    "wof:name":"Penelope J R Hall Solicitor",
    "wof:placetype":"venue"
},
  "geometry": {"coordinates":[-1.8718080521,52.4406776428],"type":"Point"}
}