{
  "type": "Feature",
  "properties": {
    "addr:full":"Higginhsaw Industrial Estate, Shaw Road Oldham Lancashire OL1 4AJ",
    "addr:postcode":"ol1 4aj",
    "addr:street":"Estate Shaw Road",
    "iso:country":"GB",
    "sg:address":"Higginhsaw Industrial Estate, Shaw Road",
    "sg:city":"Oldham",
    "sg:classifiers":[
        {
            "category":"Building & Trades",
            "subcategory":"Equipment Rental",
            "type":"Services"
        }
    ],
    "sg:phone":"+44 161 626 4942",
    "sg:postcode":"OL1 4AJ",
    "sg:province":"Lancashire",
    "sg:tags":[
        "plant",
        "machinery"
    ],
    "wof:name":"Ge Capital Equipment Services Ltd.",
    "wof:placetype":"venue"
},
  "geometry": {"coordinates":[-2.112329,53.54031],"type":"Point"}
}