{
  "type": "Feature",
  "properties": {
    "addr:full":"177 Maidstone Rd Chatham Kent ME4 6JG",
    "addr:housenumber":"177",
    "addr:postcode":"me4 6jg",
    "addr:street":"Maidstone Rd",
    "iso:country":"GB",
    "sg:address":"177 Maidstone Rd",
    "sg:city":"Chatham",
    "sg:classifiers":[
        {
            "category":"Professional",
            "subcategory":"Engineering",
            "type":"Services"
        }
    ],
    "sg:phone":"+44 1634 830500",
    "sg:postcode":"ME4 6JG",
    "sg:province":"Kent",
    "sg:tags":[
        "engineer",
        "mechanical"
    ],
    "wof:name":"E J S Services Ltd",
    "wof:placetype":"venue"
},
  "geometry": {"coordinates":[0.517133,51.360809],"type":"Point"}
}