{
  "type": "Feature",
  "properties": {
    "addr:full":"Account Enquiry, P O Box 4 Stoke On Trent Staffordshire ST4 2JA",
    "addr:housenumber":"4",
    "addr:postcode":"st4 2ja",
    "addr:street":"P O Box;On",
    "iso:country":"GB",
    "sg:address":"Account Enquiry, P O Box 4",
    "sg:city":"Stoke On Trent",
    "sg:classifiers":[
        {
            "category":"Utilities",
            "subcategory":"Electric",
            "type":"Services"
        }
    ],
    "sg:phone":"+44 1782 744422",
    "sg:postcode":"ST4 2JA",
    "sg:province":"Staffordshire",
    "sg:tags":[
        "electricity"
    ],
    "wof:name":"M E B",
    "wof:placetype":"venue"
},
  "geometry": {"coordinates":[-2.16996,53.005199],"type":"Point"}
}