{
  "type": "Feature",
  "properties": {
    "iso:country":"GB",
    "sg:address":"62 Winthorpe Road",
    "sg:city":"Newark",
    "sg:classifiers":[
        {
            "category":"Building & Trades",
            "subcategory":"Construction",
            "type":"Services"
        }
    ],
    "sg:phone":"+44 1636 673735",
    "sg:postcode":"NG24 2AB",
    "sg:province":"Nottinghamshire",
    "sg:tags":[
        "builder"
    ],
    "wof:name":"Sherwood Builders",
    "wof:placetype":"venue"
},
  "geometry": {"coordinates":[-0.797385,53.088997],"type":"Point"}
}