{
  "type": "Feature",
  "properties": {
    "addr:full":"16 Hare Lane, Claygate Esher Surrey KT10 9BS",
    "addr:housenumber":"16",
    "addr:postcode":"kt10 9bs",
    "addr:street":"Hare Lane",
    "iso:country":"GB",
    "sg:address":"16 Hare Lane, Claygate",
    "sg:city":"Esher",
    "sg:classifiers":[
        {
            "category":"Real Estate",
            "subcategory":"Architect",
            "type":"Services"
        }
    ],
    "sg:phone":"+44 1372 462662",
    "sg:postcode":"KT10 9BS",
    "sg:province":"Surrey",
    "wof:name":"Surveyors  Skeet-Smith",
    "wof:placetype":"venue"
},
  "geometry": {"coordinates":[-0.3509190083,51.3629188538],"type":"Point"}
}