{
  "type": "Feature",
  "properties": {
    "addr:full":"2 Bridge Works, Nazeing New Road Broxbourne Essex EN10 6SG",
    "addr:housenumber":"2",
    "addr:postcode":"en10 6sg",
    "addr:street":"Bridge Works;New Road",
    "iso:country":"GB",
    "sg:address":"2 Bridge Works, Nazeing New Road",
    "sg:city":"Broxbourne",
    "sg:classifiers":[
        {
            "category":"Retail",
            "subcategory":"Auto Repair",
            "type":"Services"
        }
    ],
    "sg:phone":"+44 1992 451622",
    "sg:postcode":"EN10 6SG",
    "sg:province":"Essex",
    "sg:tags":[
        "car",
        "upholsterer"
    ],
    "wof:name":"H R S",
    "wof:placetype":"venue"
},
  "geometry": {"coordinates":[-0.008327,51.743404],"type":"Point"}
}