{
  "type": "Feature",
  "properties": {
    "iso:country":"GB",
    "sg:address":"27-28 Banburgh House, Manor Walks",
    "sg:city":"Cramlington",
    "sg:classifiers":[
        {
            "category":"Professional",
            "subcategory":"Employment Agencies",
            "type":"Services"
        }
    ],
    "sg:postcode":"NE23 6QE",
    "sg:province":"Northumberland",
    "sg:tags":[
        "career",
        "guidance"
    ],
    "wof:name":"Northumberland Guidance Co. Ltd.",
    "wof:placetype":"venue"
},
  "geometry": {"coordinates":[-1.564857,55.078117],"type":"Point"}
}