{
  "type": "Feature",
  "properties": {
    "addr:full":"29 Hillside Road Ashtead Surrey KT21 1RZ",
    "addr:housenumber":"29",
    "addr:postcode":"kt21 1rz",
    "addr:street":"Hillside Road",
    "iso:country":"GB",
    "sg:address":"29 Hillside Road",
    "sg:city":"Ashtead",
    "sg:classifiers":[
        {
            "category":"Building & Trades",
            "subcategory":"Construction",
            "type":"Services"
        }
    ],
    "sg:postcode":"KT21 1RZ",
    "sg:province":"Surrey",
    "sg:tags":[
        "builder"
    ],
    "wof:name":"Whyatt Construction",
    "wof:placetype":"venue"
},
  "geometry": {"coordinates":[-0.2996689975,51.3149337769],"type":"Point"}
}