{
  "type": "Feature",
  "properties": {
    "addr:full":"14 Cressington Place Bourne End Berkshire SL8 5SN",
    "addr:housenumber":"14",
    "addr:postcode":"sl8 5sn",
    "addr:street":"Cressington Place Bourne End",
    "iso:country":"GB",
    "sg:address":"14 Cressington Place",
    "sg:city":"Bourne End",
    "sg:classifiers":[
        {
            "category":"Health Services",
            "subcategory":"Podiatrist",
            "type":"Services"
        }
    ],
    "sg:phone":"+44 1628 523290",
    "sg:postcode":"SL8 5SN",
    "sg:province":"Berkshire",
    "sg:tags":[
        "podiatrists",
        "chiropodist"
    ],
    "wof:name":"Alison Taylor",
    "wof:placetype":"venue"
},
  "geometry": {"coordinates":[-0.7149419785,51.5810928345],"type":"Point"}
}