{
  "type": "Feature",
  "properties": {
    "addr:full":"Cornishway East Taunton Somerset TA1 5LZ",
    "addr:postcode":"ta1 5lz",
    "addr:street":"East",
    "iso:country":"GB",
    "sg:address":"Cornishway East",
    "sg:city":"Taunton",
    "sg:classifiers":[
        {
            "category":"Professional",
            "subcategory":"Engineering",
            "type":"Services"
        }
    ],
    "sg:postcode":"TA1 5LZ",
    "sg:province":"Somerset",
    "wof:name":"Hall,Peter C,",
    "wof:placetype":"venue"
},
  "geometry": {"coordinates":[-3.1311690807,51.011680603],"type":"Point"}
}