{
  "type": "Feature",
  "properties": {
    "addr:full":"Unit 2 Abbey Mill, Station Road Southampton Hampshire SO32 1DH",
    "addr:housenumber":"unit 2",
    "addr:postcode":"so32 1dh",
    "addr:street":"Abbey Mill Station Road",
    "iso:country":"GB",
    "sg:address":"Unit 2 Abbey Mill, Station Road",
    "sg:city":"Southampton",
    "sg:classifiers":[
        {
            "category":"Retail",
            "subcategory":"Auto Repair",
            "type":"Services"
        }
    ],
    "sg:phone":"+44 1489 893227",
    "sg:postcode":"SO32 1DH",
    "sg:province":"Hampshire",
    "sg:tags":[
        "modification",
        "garage"
    ],
    "wof:name":"Field Motors",
    "wof:placetype":"venue"
},
  "geometry": {"coordinates":[-1.217599988,50.9530181885],"type":"Point"}
}