{
  "type": "Feature",
  "properties": {
    "addr:full":"341 Leeds Rd Bradford West Yorkshire BD3 9LU",
    "addr:housenumber":"341",
    "addr:postcode":"bd3 9lu",
    "addr:street":"Leeds Rd",
    "iso:country":"GB",
    "sg:address":"341 Leeds Rd",
    "sg:city":"Bradford",
    "sg:classifiers":[
        {
            "category":"Autos & Motor Vehicles",
            "subcategory":"Fuel & Gas Station",
            "type":"Retail Goods"
        }
    ],
    "sg:postcode":"BD3 9LU",
    "sg:province":"West Yorkshire",
    "sg:tags":[
        "hr",
        "petrol"
    ],
    "wof:name":"Tyke Petroleum (Laisterdyke) Ltd",
    "wof:placetype":"venue"
},
  "geometry": {"coordinates":[-1.7348749638,53.7925720215],"type":"Point"}
}