{
  "type": "Feature",
  "properties": {
    "addr:full":"21 High Grn, Brooke Norwich Norfolk NR15 1HR",
    "addr:housenumber":"21",
    "addr:postcode":"nr15 1hr",
    "addr:street":"High Grn Brooke Norwich",
    "iso:country":"GB",
    "sg:address":"21 High Grn, Brooke",
    "sg:city":"Norwich",
    "sg:classifiers":[
        {
            "category":"Building & Trades",
            "subcategory":"Construction",
            "type":"Services"
        }
    ],
    "sg:postcode":"NR15 1HR",
    "sg:province":"Norfolk",
    "sg:tags":[
        "joiner",
        "carpenter"
    ],
    "wof:name":"A W Joinery & Building Services",
    "wof:placetype":"venue"
},
  "geometry": {"coordinates":[1.367141,52.540642],"type":"Point"}
}