{
  "type": "Feature",
  "properties": {
    "iso:country":"GB",
    "sg:address":"113 Farringdon Road, Marden Estate",
    "sg:city":"North Shields",
    "sg:classifiers":[
        {
            "category":"Building & Trades",
            "subcategory":"Plumbing",
            "type":"Services"
        }
    ],
    "sg:phone":"+44 191 236 4277",
    "sg:postcode":"NE30 3HF",
    "sg:province":"Tyne and Wear",
    "sg:tags":[
        "central",
        "heating"
    ],
    "wof:name":"Herron Heating & Plumbing",
    "wof:placetype":"venue"
},
  "geometry": {"coordinates":[-1.4527169466,55.031375885],"type":"Point"}
}