{
  "type": "Feature",
  "properties": {
    "iso:country":"GB",
    "sg:address":"Halfway Road, Minster On Sea",
    "sg:city":"Sheerness",
    "sg:classifiers":[
        {
            "category":"Restaurant",
            "type":"Food & Drink"
        },
        {
            "category":"Community Center",
            "subcategory":"Social",
            "type":"Public Place"
        }
    ],
    "sg:phone":"+44 1795 662917",
    "sg:postcode":"ME12 3AU",
    "sg:province":"Kent",
    "sg:tags":[
        "house",
        "activity"
    ],
    "wof:name":"P J & J B GANNON",
    "wof:placetype":"venue"
},
  "geometry": {"coordinates":[0.771757,51.430321],"type":"Point"}
}