{
  "type": "Feature",
  "properties": {
    "addr:full":"Lochalsh House, Balmacara Kyle Highland IV40 8DN",
    "addr:postcode":"iv40 8dn",
    "addr:street":"Balmacara",
    "iso:country":"GB",
    "sg:address":"Lochalsh House, Balmacara",
    "sg:city":"Kyle",
    "sg:classifiers":[
        {
            "category":"Landmark",
            "subcategory":"Tourist Attraction",
            "type":"Public Place"
        }
    ],
    "sg:phone":"+44 1599 566325",
    "sg:postcode":"IV40 8DN",
    "sg:province":"Highland",
    "sg:tags":[
        "interest"
    ],
    "wof:name":"The National Trust",
    "wof:placetype":"venue"
},
  "geometry": {"coordinates":[-5.7140522003,57.2809448242],"type":"Point"}
}