{
  "type": "Feature",
  "properties": {
    "addr:full":"Worgan St Lambeth Greater London SE11 5ED",
    "addr:postcode":"se11 5ed",
    "addr:street":"Worgan St",
    "iso:country":"GB",
    "sg:address":"Worgan St",
    "sg:city":"Lambeth",
    "sg:classifiers":[
        {
            "category":"Place Of Worship",
            "type":"Public Place"
        }
    ],
    "sg:phone":"+44 20 7587 1912",
    "sg:postcode":"SE11 5ED",
    "sg:province":"Greater London",
    "wof:name":"Vauxhall Methodist Church",
    "wof:placetype":"venue"
},
  "geometry": {"coordinates":[-0.119354,51.489426],"type":"Point"}
}