{
  "type": "Feature",
  "properties": {
    "addr:full":"11 Kings Road Fleet Hampshire GU51 3AA",
    "addr:housenumber":"11",
    "addr:postcode":"gu51 3aa",
    "addr:street":"Kings Road",
    "iso:country":"GB",
    "sg:address":"11 Kings Road",
    "sg:city":"Fleet",
    "sg:classifiers":[
        {
            "category":"Shopping",
            "subcategory":"Antiques",
            "type":"Retail Goods"
        }
    ],
    "sg:postcode":"GU51 3AA",
    "sg:province":"Hampshire",
    "wof:name":"The Antique Shop",
    "wof:placetype":"venue"
},
  "geometry": {"coordinates":[-0.836265,51.284473],"type":"Point"}
}