{
  "type": "Feature",
  "properties": {
    "addr:full":"160 Haslemere Road Southsea Hampshire PO4 9AS",
    "addr:housenumber":"160",
    "addr:postcode":"po4 9as",
    "addr:street":"Haslemere Road",
    "iso:country":"GB",
    "sg:address":"160 Haslemere Road",
    "sg:city":"Southsea",
    "sg:classifiers":[
        {
            "category":"Building & Trades",
            "subcategory":"Construction",
            "type":"Services"
        }
    ],
    "sg:phone":"+44 23 9273 4739",
    "sg:postcode":"PO4 9AS",
    "sg:province":"Hampshire",
    "sg:tags":[
        "builder"
    ],
    "wof:name":"C T Porter",
    "wof:placetype":"venue"
},
  "geometry": {"coordinates":[-1.0672630072,50.7883377075],"type":"Point"}
}