{
  "type": "Feature",
  "properties": {
    "addr:full":"37 Fern Way Watford Hertfordshire WD25 0HQ",
    "addr:housenumber":"37",
    "addr:postcode":"wd25 0hq",
    "addr:street":"Fern Way",
    "iso:country":"GB",
    "sg:address":"37 Fern Way",
    "sg:city":"Watford",
    "sg:classifiers":[
        {
            "category":"Building & Trades",
            "subcategory":"Construction",
            "type":"Services"
        }
    ],
    "sg:phone":"+44 1923 463651",
    "sg:postcode":"WD25 0HQ",
    "sg:province":"Hertfordshire",
    "sg:tags":[
        "roofing"
    ],
    "wof:name":"Longlife Roofing",
    "wof:placetype":"venue"
},
  "geometry": {"coordinates":[-0.4007259905,51.6869506836],"type":"Point"}
}