{
  "type": "Feature",
  "properties": {
    "iso:country":"GB",
    "sg:address":"The Estury Business Park, Lower Yelland",
    "sg:city":"Barnstaple",
    "sg:classifiers":[
        {
            "category":"Home & Garden",
            "subcategory":"Hardware",
            "type":"Retail Goods"
        }
    ],
    "sg:phone":"+44 1271 861221",
    "sg:postcode":"EX31 3EZ",
    "sg:province":"Devon",
    "wof:name":"Steve Green",
    "wof:placetype":"venue"
},
  "geometry": {"coordinates":[-4.164753,51.067776],"type":"Point"}
}