{
  "type": "Feature",
  "properties": {
    "iso:country":"GB",
    "sg:address":"50 Potash Rd",
    "sg:city":"Billericay",
    "sg:classifiers":[
        {
            "category":"Professional",
            "subcategory":"Computer Services",
            "type":"Services"
        }
    ],
    "sg:phone":"+44 1277 653918",
    "sg:postcode":"CM11 1DL",
    "sg:province":"Essex",
    "sg:tags":[
        "system",
        "software"
    ],
    "wof:name":"Tolaforce Ltd",
    "wof:placetype":"venue"
},
  "geometry": {"coordinates":[0.436955,51.643986],"type":"Point"}
}