{
  "type": "Feature",
  "properties": {
    "addr:full":"Hunters Brook, Epping Road Waltham Abbey Essex EN9 2DH",
    "addr:postcode":"en9 2dh",
    "addr:street":"Hunters Brook Epping Road",
    "iso:country":"GB",
    "sg:address":"Hunters Brook, Epping Road",
    "sg:city":"Waltham Abbey",
    "sg:classifiers":[
        {
            "category":"Building & Trades",
            "subcategory":"Construction",
            "type":"Services"
        }
    ],
    "sg:postcode":"EN9 2DH",
    "sg:province":"Essex",
    "sg:tags":[
        "builder"
    ],
    "wof:name":"D J C Builders",
    "wof:placetype":"venue"
},
  "geometry": {"coordinates":[0.0014900001,51.6864204407],"type":"Point"}
}