{
  "type": "Feature",
  "properties": {
    "addr:full":"Earle Street Yeovil Somerset BA20 1JW",
    "addr:postcode":"ba20 1jw",
    "addr:street":"Earle Street",
    "iso:country":"GB",
    "sg:address":"Earle Street",
    "sg:city":"Yeovil",
    "sg:classifiers":[
        {
            "category":"Home & Garden",
            "subcategory":"Home Furnishings",
            "type":"Retail Goods"
        },
        {
            "category":"Building & Trades",
            "subcategory":"Construction",
            "type":"Services"
        }
    ],
    "sg:phone":"+44 1935 472054",
    "sg:postcode":"BA20 1JW",
    "sg:province":"Somerset",
    "sg:tags":[
        "mantelpiece",
        "fireplace"
    ],
    "wof:name":"By The Fire",
    "wof:placetype":"venue"
},
  "geometry": {"coordinates":[-2.626395,50.942558],"type":"Point"}
}