{
  "type": "Feature",
  "properties": {
    "addr:full":"Lower Ground Floor 4 Royal Cres Cheltenham Gloucestershire GL50 3DA",
    "addr:housenumber":"4",
    "addr:postcode":"gl50 3da",
    "addr:street":"Ground Floor;Royal Cres",
    "iso:country":"GB",
    "sg:address":"Lower Ground Floor 4 Royal Cres",
    "sg:city":"Cheltenham",
    "sg:classifiers":[
        {
            "category":"Real Estate",
            "subcategory":"Architect",
            "type":"Services"
        }
    ],
    "sg:phone":"+44 1242 242943",
    "sg:postcode":"GL50 3DA",
    "sg:province":"Gloucestershire",
    "wof:name":"Stanley Partnership",
    "wof:placetype":"venue"
},
  "geometry": {"coordinates":[-2.078459,51.898048],"type":"Point"}
}