{
  "type": "Feature",
  "properties": {
    "iso:country":"GB",
    "sg:address":"Springfield Mount, Edgebolton, Shawbury",
    "sg:city":"Shrewsbury",
    "sg:classifiers":[
        {
            "category":"Farming",
            "subcategory":"Livestock Farm",
            "type":"Manufacturing & Wholesale Goods"
        }
    ],
    "sg:postcode":"SY4 4EL",
    "sg:province":"Shropshire",
    "sg:tags":[
        "others"
    ],
    "wof:name":"J C Ditty",
    "wof:placetype":"venue"
},
  "geometry": {"coordinates":[-2.656574,52.787674],"type":"Point"}
}