{
  "type": "Feature",
  "properties": {
    "addr:full":"Martlett Road Minehead Somerset TA24 5QD",
    "addr:postcode":"ta24 5qd",
    "addr:street":"Martlett Road",
    "iso:country":"GB",
    "sg:address":"Martlett Road",
    "sg:city":"Minehead",
    "sg:classifiers":[
        {
            "category":"Health Services",
            "subcategory":"Nursing And Care Facility",
            "type":"Services"
        }
    ],
    "sg:postcode":"TA24 5QD",
    "sg:province":"Somerset",
    "sg:tags":[
        "home"
    ],
    "wof:name":"Oaklodge Residential Home",
    "wof:placetype":"venue"
},
  "geometry": {"coordinates":[-3.4799690247,51.205406189],"type":"Point"}
}