{
  "type": "Feature",
  "properties": {
    "iso:country":"GB",
    "sg:address":"2 Ryhope Close",
    "sg:city":"Bedworth",
    "sg:classifiers":[
        {
            "category":"Building & Trades",
            "subcategory":"Construction",
            "type":"Services"
        }
    ],
    "sg:phone":"+44 24 7673 8010",
    "sg:postcode":"CV12 0LU",
    "sg:province":"Warwickshire",
    "sg:tags":[
        "builder"
    ],
    "wof:name":"B.M Building Services",
    "wof:placetype":"venue"
},
  "geometry": {"coordinates":[-1.510073,52.475075],"type":"Point"}
}