{
  "type": "Feature",
  "properties": {
    "addr:full":"4 Sedgemere Avenue Crewe Cheshire CW1 3YU",
    "addr:housenumber":"4",
    "addr:postcode":"cw1 3yu",
    "addr:street":"Sedgemere Avenue",
    "iso:country":"GB",
    "sg:address":"4 Sedgemere Avenue",
    "sg:city":"Crewe",
    "sg:classifiers":[
        {
            "category":"Military Area",
            "subcategory":"Air Force Base",
            "type":"Public Place"
        }
    ],
    "sg:phone":"+44 1270 500121",
    "sg:postcode":"CW1 3YU",
    "sg:province":"Cheshire",
    "sg:tags":[
        "taxi",
        "hire",
        "private"
    ],
    "wof:name":"Mike's Taxi Service",
    "wof:placetype":"venue"
},
  "geometry": {"coordinates":[-2.4616250992,53.1141738892],"type":"Point"}
}