{
  "type": "Feature",
  "properties": {
    "iso:country":"GB",
    "sg:address":"194 High Street, Stoke Newington",
    "sg:city":"London",
    "sg:classifiers":[
        {
            "category":"Restaurant",
            "type":"Food & Drink"
        }
    ],
    "sg:phone":"+44 20 7249 9111",
    "sg:postcode":"N16 7LL",
    "sg:province":"Greater London",
    "sg:tags":[
        "italian"
    ],
    "wof:name":"La Fenice",
    "wof:placetype":"venue"
},
  "geometry": {"coordinates":[0.050839,51.539619],"type":"Point"}
}