{
  "type": "Feature",
  "properties": {
    "addr:full":"Brock Street, North Queensferry Inverkeithing Fife KY11 1JF",
    "addr:postcode":"ky11 1jf",
    "addr:street":"Brock Street North;Inverkeithing",
    "iso:country":"GB",
    "sg:address":"Brock Street, North Queensferry",
    "sg:city":"Inverkeithing",
    "sg:classifiers":[
        {
            "category":"Food & Beverages",
            "subcategory":"Supermarket",
            "type":"Retail Goods"
        },
        {
            "category":"Food & Beverages",
            "subcategory":"Fruits & Vegetables",
            "type":"Retail Goods"
        }
    ],
    "sg:phone":"+44 1383 412055",
    "sg:postcode":"KY11 1JF",
    "sg:province":"Fife",
    "sg:tags":[
        "greengrocer"
    ],
    "wof:name":"Wilmas",
    "wof:placetype":"venue"
},
  "geometry": {"coordinates":[-3.3976790905,56.0311317444],"type":"Point"}
}