{
  "type": "Feature",
  "properties": {
    "addr:full":"Fitzroy House, Abott Street, Dalston London Greater London E8 3DP",
    "addr:postcode":"e8 3dp",
    "addr:street":"Abott Street",
    "iso:country":"GB",
    "sg:address":"Fitzroy House, Abott Street, Dalston",
    "sg:city":"London",
    "sg:classifiers":[
        {
            "category":"Home & Garden",
            "subcategory":"Carpets & Floor Coverings",
            "type":"Retail Goods"
        }
    ],
    "sg:phone":"+44 20 7254 8187",
    "sg:postcode":"E8 3DP",
    "sg:province":"Greater London",
    "sg:tags":[
        "trimming",
        "trimmer"
    ],
    "wof:name":"G J Turner & Co. (Trimmings) Ltd.",
    "wof:placetype":"venue"
},
  "geometry": {"coordinates":[-0.074500002,51.5470809937],"type":"Point"}
}