{
  "type": "Feature",
  "properties": {
    "addr:full":"Works Road, Pontardawe Swansea Neath Port Talbot SA8 4AF",
    "addr:postcode":"sa8 4af",
    "addr:street":"Works Road",
    "iso:country":"GB",
    "sg:address":"Works Road, Pontardawe",
    "sg:city":"Swansea",
    "sg:classifiers":[
        {
            "category":"Building & Trades",
            "subcategory":"Construction",
            "type":"Services"
        }
    ],
    "sg:phone":"+44 1792 864279",
    "sg:postcode":"SA8 4AF",
    "sg:province":"Neath Port Talbot",
    "sg:tags":[
        "builder"
    ],
    "wof:name":"Tawe Builders Ltd.",
    "wof:placetype":"venue"
},
  "geometry": {"coordinates":[-3.8805999756,51.7648506165],"type":"Point"}
}