{
  "type": "Feature",
  "properties": {
    "iso:country":"GB",
    "sg:address":"Unit 2, Synergy House, Manchester Science Park",
    "sg:city":"Manchester",
    "sg:classifiers":[
        {
            "category":"Government",
            "subcategory":"Post Office",
            "type":"Public Place"
        }
    ],
    "sg:phone":"+44 161 232 0202",
    "sg:postcode":"M15 6SY",
    "sg:province":"Cheshire",
    "sg:tags":[
        "organisation",
        "soc",
        "research"
    ],
    "wof:name":"Shandon Clinic Ltd",
    "wof:placetype":"venue"
},
  "geometry": {"coordinates":[-2.236649,53.464806],"type":"Point"}
}