{
  "type": "Feature",
  "properties": {
    "iso:country":"GB",
    "sg:address":"21 High Street, Ringstead",
    "sg:city":"Kettering",
    "sg:classifiers":[
        {
            "category":"Shopping",
            "subcategory":"News",
            "type":"Retail Goods"
        },
        {
            "category":"Food & Beverages",
            "subcategory":"Groceries & Convenience Stores",
            "type":"Retail Goods"
        }
    ],
    "sg:phone":"+44 1933 622134",
    "sg:postcode":"NN14 4DA",
    "sg:province":"Northamptonshire",
    "sg:tags":[
        "newsagent"
    ],
    "wof:name":"RINGSTEAD STORES",
    "wof:placetype":"venue"
},
  "geometry": {"coordinates":[-0.645596,52.382572],"type":"Point"}
}