{
  "type": "Feature",
  "properties": {
    "addr:full":"Clocktower Buildings, 12 Shore Road Southampton Hampshire SO31 9GQ",
    "addr:housenumber":"12",
    "addr:postcode":"so31 9gq",
    "addr:street":"Shore Road",
    "iso:country":"GB",
    "sg:address":"Clocktower Buildings, 12 Shore Road",
    "sg:city":"Southampton",
    "sg:classifiers":[
        {
            "category":"Professional",
            "subcategory":"Printing & Photocopies",
            "type":"Services"
        }
    ],
    "sg:phone":"+44 1489 581277",
    "sg:postcode":"SO31 9GQ",
    "sg:province":"Hampshire",
    "sg:tags":[
        "printer"
    ],
    "wof:name":"Warsash Copy Centre",
    "wof:placetype":"venue"
},
  "geometry": {"coordinates":[-1.3004000187,50.8531799316],"type":"Point"}
}