{
  "type": "Feature",
  "properties": {
    "iso:country":"GB",
    "sg:address":"16 Dews Road",
    "sg:city":"Salisbury",
    "sg:classifiers":[
        {
            "category":"Communications",
            "type":"Services"
        }
    ],
    "sg:phone":"+44 1722 414404",
    "sg:postcode":"SP2 7SN",
    "sg:province":"Wiltshire",
    "sg:tags":[
        "system",
        "music",
        "public",
        "address"
    ],
    "wof:name":"Midas Sound & Lighting",
    "wof:placetype":"venue"
},
  "geometry": {"coordinates":[-1.803462,51.069752],"type":"Point"}
}