{
  "type": "Feature",
  "properties": {
    "addr:full":"Block A Government Buildings, Coley Avenue Reading Berkshire RG1 6DT",
    "addr:postcode":"rg1 6dt",
    "addr:street":"Coley Avenue",
    "iso:country":"GB",
    "sg:address":"Block A Government Buildings, Coley Avenue",
    "sg:city":"Reading",
    "sg:classifiers":[
        {
            "category":"Government",
            "subcategory":"Office",
            "type":"Public Place"
        }
    ],
    "sg:phone":"+44 118 958 1222",
    "sg:postcode":"RG1 6DT",
    "sg:province":"Berkshire",
    "sg:tags":[
        "central"
    ],
    "wof:name":"Ministry of Agriculture",
    "wof:placetype":"venue"
},
  "geometry": {"coordinates":[-0.963009,51.453522],"type":"Point"}
}