{
  "type": "Feature",
  "properties": {
    "addr:full":"5 Ford Street, Lanchester Durham Durham DH7 0SQ",
    "addr:housenumber":"5",
    "addr:postcode":"dh7 0sq",
    "addr:street":"Ford Street",
    "iso:country":"GB",
    "sg:address":"5 Ford Street, Lanchester",
    "sg:city":"Durham",
    "sg:classifiers":[
        {
            "category":"Retail",
            "subcategory":"Driving School",
            "type":"Services"
        }
    ],
    "sg:phone":"+44 1207 283535",
    "sg:postcode":"DH7 0SQ",
    "sg:province":"Durham",
    "wof:name":"Brian Caile",
    "wof:placetype":"venue"
},
  "geometry": {"coordinates":[-1.743688941,54.8191947937],"type":"Point"}
}