{
  "type": "Feature",
  "properties": {
    "addr:full":"Church Rd Romford Essex RM4 1LH",
    "addr:postcode":"rm4 1lh",
    "addr:street":"Church Rd",
    "iso:country":"GB",
    "sg:address":"Church Rd",
    "sg:city":"Romford",
    "sg:classifiers":[
        {
            "category":"Education",
            "subcategory":"Preschool",
            "type":"Public Place"
        }
    ],
    "sg:phone":"+44 1708 371793",
    "sg:postcode":"RM4 1LH",
    "sg:province":"Essex",
    "sg:tags":[
        "pre-school",
        "playgroups"
    ],
    "wof:name":"St Thomas Playgroup",
    "wof:placetype":"venue"
},
  "geometry": {"coordinates":[0.225084,51.656418],"type":"Point"}
}