{
  "type": "Feature",
  "properties": {
    "addr:full":"Lutterworth Drive, Adwick Le Street Doncaster North Yorkshire DN6 7BX",
    "addr:postcode":"dn6 7bx",
    "addr:street":"Lutterworth Drive Adwick Le Street",
    "iso:country":"GB",
    "sg:address":"Lutterworth Drive, Adwick Le Street",
    "sg:city":"Doncaster",
    "sg:classifiers":[
        {
            "category":"Autos & Motor Vehicles",
            "subcategory":"Fuel & Gas Station",
            "type":"Retail Goods"
        }
    ],
    "sg:phone":"+44 1302 722768",
    "sg:postcode":"DN6 7BX",
    "sg:province":"North Yorkshire",
    "sg:tags":[
        "petrol",
        "filling"
    ],
    "wof:name":"Murco Petroleum Ltd.",
    "wof:placetype":"venue"
},
  "geometry": {"coordinates":[-1.1905839443,53.5724639893],"type":"Point"}
}