{
  "type": "Feature",
  "properties": {
    "iso:country":"GB",
    "sg:address":"3 Holborough Road",
    "sg:city":"Snodland",
    "sg:classifiers":[
        {
            "category":"Personal",
            "subcategory":"Beauty Salon",
            "type":"Services"
        },
        {
            "category":"Personal",
            "subcategory":"Barber",
            "type":"Services"
        }
    ],
    "sg:phone":"+44 1634 241498",
    "sg:postcode":"ME6 5NL",
    "sg:province":"Kent",
    "sg:tags":[
        "unisex",
        "hairdresser"
    ],
    "wof:name":"Trios Hair Studio",
    "wof:placetype":"venue"
},
  "geometry": {"coordinates":[0.442478,51.330555],"type":"Point"}
}