{
  "type": "Feature",
  "properties": {
    "iso:country":"GB",
    "sg:address":"108 Bradford Road, Stanningley",
    "sg:city":"Pudsey",
    "sg:classifiers":[
        {
            "category":"Retail",
            "subcategory":"Auto Repair",
            "type":"Services"
        }
    ],
    "sg:postcode":"LS28 6UR",
    "sg:province":"West Yorkshire",
    "sg:tags":[
        "modification",
        "garage"
    ],
    "wof:name":"Stanningley Service Station",
    "wof:placetype":"venue"
},
  "geometry": {"coordinates":[-1.6746690273,53.8057060242],"type":"Point"}
}