{
  "type": "Feature",
  "properties": {
    "addr:full":"14 Gerrard Close, Knowle Bristol City of Bristol BS4 1UH",
    "addr:housenumber":"14",
    "addr:postcode":"bs4 1uh",
    "addr:street":"Gerrard Close",
    "iso:country":"GB",
    "sg:address":"14 Gerrard Close, Knowle",
    "sg:city":"Bristol",
    "sg:classifiers":[
        {
            "category":"Shopping",
            "subcategory":"Computers & Home Electronics",
            "type":"Retail Goods"
        }
    ],
    "sg:phone":"+44 117 964 5260",
    "sg:postcode":"BS4 1UH",
    "sg:province":"City of Bristol",
    "sg:tags":[
        "sound",
        "equipment",
        "system"
    ],
    "wof:name":"Arena Pa & Lighting",
    "wof:placetype":"venue"
},
  "geometry": {"coordinates":[-2.5923740864,51.4199714661],"type":"Point"}
}