{
  "type": "Feature",
  "properties": {
    "addr:full":"Toad Hall, Willow Road Whitstable Kent CT5 3DW",
    "addr:postcode":"ct5 3dw",
    "addr:street":"Willow Road",
    "iso:country":"GB",
    "sg:address":"Toad Hall, Willow Road",
    "sg:city":"Whitstable",
    "sg:classifiers":[
        {
            "category":"Building & Trades",
            "subcategory":"Construction",
            "type":"Services"
        }
    ],
    "sg:phone":"+44 1227 770388",
    "sg:postcode":"CT5 3DW",
    "sg:province":"Kent",
    "sg:tags":[
        "joiner",
        "carpenter"
    ],
    "wof:name":"Toadcraft Ltd.",
    "wof:placetype":"venue"
},
  "geometry": {"coordinates":[1.026406,51.362247],"type":"Point"}
}