{
  "type": "Feature",
  "properties": {
    "addr:full":"119 Bridgnorth Road, Wollaston Stourbridge Staffordshire DY8 3NX",
    "addr:housenumber":"119",
    "addr:postcode":"dy8 3nx",
    "addr:street":"Bridgnorth Road",
    "iso:country":"GB",
    "sg:address":"119 Bridgnorth Road, Wollaston",
    "sg:city":"Stourbridge",
    "sg:classifiers":[
        {
            "category":"Food & Beverages",
            "subcategory":"Meat & Fish",
            "type":"Retail Goods"
        }
    ],
    "sg:phone":"+44 1384 394119",
    "sg:postcode":"DY8 3NX",
    "sg:province":"Staffordshire",
    "sg:tags":[
        "butcher"
    ],
    "wof:name":"Harris Butchers",
    "wof:placetype":"venue"
},
  "geometry": {"coordinates":[-2.164005,52.460167],"type":"Point"}
}