{
  "type": "Feature",
  "properties": {
    "addr:full":"Ringway Ho, Kelvin Rd Newbury Berkshire RG14 2DB",
    "addr:postcode":"rg14 2db",
    "addr:street":"Kelvin Rd",
    "iso:country":"GB",
    "sg:address":"Ringway Ho, Kelvin Rd",
    "sg:city":"Newbury",
    "sg:classifiers":[
        {
            "category":"Banks & Credit Unions",
            "subcategory":"Financial Services",
            "type":"Services"
        }
    ],
    "sg:postcode":"RG14 2DB",
    "sg:province":"Berkshire",
    "sg:tags":[
        "consultant"
    ],
    "wof:name":"Personal Credit Services",
    "wof:placetype":"venue"
},
  "geometry": {"coordinates":[-1.3258719444,51.405872345],"type":"Point"}
}