{
  "type": "Feature",
  "properties": {
    "addr:full":"Speke Hall, The Walk, Speke Liverpool Merseyside L24 1XD",
    "addr:postcode":"l24 1xd",
    "addr:street":"Speke;The Walk",
    "iso:country":"GB",
    "sg:address":"Speke Hall, The Walk, Speke",
    "sg:city":"Liverpool",
    "sg:classifiers":[
        {
            "category":"Banks & Credit Unions",
            "subcategory":"Financial Services",
            "type":"Services"
        },
        {
            "category":"Landmark",
            "subcategory":"Tourist Attraction",
            "type":"Public Place"
        }
    ],
    "sg:phone":"+44 151 427 7231",
    "sg:postcode":"L24 1XD",
    "sg:province":"Merseyside",
    "sg:tags":[
        "consultant",
        "interest"
    ],
    "wof:name":"The National Trust",
    "wof:placetype":"venue"
},
  "geometry": {"coordinates":[-2.8658189774,53.3494949341],"type":"Point"}
}