{
  "type": "Feature",
  "properties": {
    "addr:full":"Labelnet House Hallsford Bridge, Industrial Estate, Stondon Road Ongar Essex CM5 9RB",
    "addr:postcode":"cm5 9rb",
    "addr:street":"Hallsford Bridge;Stondon Road",
    "iso:country":"GB",
    "sg:address":"Labelnet House Hallsford Bridge, Industrial Estate, Stondon Road",
    "sg:city":"Ongar",
    "sg:classifiers":[
        {
            "category":"Professional",
            "subcategory":"Printing & Photocopies",
            "type":"Services"
        },
        {
            "category":"Organizations",
            "subcategory":"Professional Association",
            "type":"Services"
        }
    ],
    "sg:phone":"+44 1277 364964",
    "sg:postcode":"CM5 9RB",
    "sg:province":"Essex",
    "sg:tags":[
        "finishing",
        "label",
        "tag",
        "supply"
    ],
    "wof:name":"Labelnet Ltd",
    "wof:placetype":"venue"
},
  "geometry": {"coordinates":[0.24517,51.706131],"type":"Point"}
}