{
  "type": "Feature",
  "properties": {
    "iso:country":"GB",
    "sg:address":"Oilfield Support Base, Shore Road",
    "sg:city":"Invergordon",
    "sg:classifiers":[
        {
            "category":"Freight",
            "type":"Transportation"
        }
    ],
    "sg:phone":"+44 1349 853341",
    "sg:postcode":"IV18 0EX",
    "sg:province":"Highland",
    "sg:tags":[
        "forwarders"
    ],
    "wof:name":"Port Services (Invergordon) Ltd.",
    "wof:placetype":"venue"
},
  "geometry": {"coordinates":[-4.166444,57.687851],"type":"Point"}
}