{
  "type": "Feature",
  "properties": {
    "addr:full":"New Hall Hey Rd Rossendale Lancashire BB4 6HR",
    "addr:postcode":"bb4 6hr",
    "addr:street":"Hey Rd",
    "iso:country":"GB",
    "sg:address":"New Hall Hey Rd",
    "sg:city":"Rossendale",
    "sg:classifiers":[
        {
            "category":"Manufacturing",
            "subcategory":"Textiles",
            "type":"Manufacturing & Wholesale Goods"
        }
    ],
    "sg:postcode":"BB4 6HR",
    "sg:province":"Lancashire",
    "sg:tags":[
        "dyer"
    ],
    "wof:name":"Point Control",
    "wof:placetype":"venue"
},
  "geometry": {"coordinates":[-2.290951,53.698154],"type":"Point"}
}