{
  "type": "Feature",
  "properties": {
    "iso:country":"GB",
    "sg:address":"Davo Mains, Fordoun",
    "sg:city":"Laurencekirk",
    "sg:classifiers":[
        {
            "category":"Farming",
            "subcategory":"Farm",
            "type":"Manufacturing & Wholesale Goods"
        }
    ],
    "sg:phone":"+44 1561 320436",
    "sg:postcode":"AB30 1JL",
    "sg:province":"Aberdeenshire",
    "sg:tags":[
        "mixed",
        "crop"
    ],
    "wof:name":"N R Gammie",
    "wof:placetype":"venue"
},
  "geometry": {"coordinates":[-2.4693739414,56.8306617737],"type":"Point"}
}