{
  "type": "Feature",
  "properties": {
    "iso:country":"GB",
    "sg:address":"55 Jasmine Gro",
    "sg:city":"Penge",
    "sg:classifiers":[
        {
            "category":"Building & Trades",
            "subcategory":"Construction",
            "type":"Services"
        }
    ],
    "sg:phone":"+44 20 8778 3218",
    "sg:postcode":"SE20 8JY",
    "sg:province":"Greater London",
    "sg:tags":[
        "decorator",
        "painter"
    ],
    "wof:name":"Adson Building Consultants Ltd",
    "wof:placetype":"venue"
},
  "geometry": {"coordinates":[-0.060455,51.411324],"type":"Point"}
}