{
  "type": "Feature",
  "properties": {
    "iso:country":"GB",
    "sg:address":"The Lodge, New Road",
    "sg:city":"Pontefract",
    "sg:classifiers":[
        {
            "category":"Professional",
            "subcategory":"Management & Consulting",
            "type":"Services"
        }
    ],
    "sg:phone":"+44 870 766 0101",
    "sg:postcode":"WF7 6HE",
    "sg:province":"West Yorkshire",
    "sg:tags":[
        "consultant",
        "business"
    ],
    "wof:name":"Scott Tatham & Co",
    "wof:placetype":"venue"
},
  "geometry": {"coordinates":[-1.3818700314,53.6841316223],"type":"Point"}
}