{
  "type": "Feature",
  "properties": {
    "iso:country":"GB",
    "sg:address":"191 West Hendon Broadway",
    "sg:city":"London",
    "sg:classifiers":[
        {
            "category":"Shopping",
            "subcategory":"Clothing, Apparel, & Fashions",
            "type":"Retail Goods"
        }
    ],
    "sg:phone":"+44 20 8203 7230",
    "sg:postcode":"NW9 7DD",
    "sg:province":"Greater London",
    "sg:tags":[
        "ladieswear"
    ],
    "wof:name":"Swagat Creations",
    "wof:placetype":"venue"
},
  "geometry": {"coordinates":[-0.242094,51.579731],"type":"Point"}
}