{
  "type": "Feature",
  "properties": {
    "addr:full":"43 Windmill Hill Enfield Greater London EN2 7AE",
    "addr:housenumber":"43",
    "addr:postcode":"en2 7ae",
    "addr:street":"Windmill Hill",
    "iso:country":"GB",
    "sg:address":"43 Windmill Hill",
    "sg:city":"Enfield",
    "sg:classifiers":[
        {
            "category":"Home & Garden",
            "subcategory":"Furniture",
            "type":"Retail Goods"
        }
    ],
    "sg:phone":"+44 20 8367 1677",
    "sg:postcode":"EN2 7AE",
    "sg:province":"Greater London",
    "wof:name":"Matts & Slatts",
    "wof:placetype":"venue"
},
  "geometry": {"coordinates":[-0.09225,51.65353],"type":"Point"}
}