{
  "type": "Feature",
  "properties": {
    "iso:country":"GB",
    "sg:address":"1 Craven Gardens",
    "sg:city":"Romford",
    "sg:classifiers":[
        {
            "category":"Building & Trades",
            "subcategory":"Construction",
            "type":"Services"
        }
    ],
    "sg:phone":"+44 1708 373649",
    "sg:postcode":"RM3 0DF",
    "sg:province":"Essex",
    "sg:tags":[
        "bricklaying"
    ],
    "wof:name":"Keane Build",
    "wof:placetype":"venue"
},
  "geometry": {"coordinates":[0.25223,51.603191],"type":"Point"}
}