{
  "type": "Feature",
  "properties": {
    "iso:country":"GB",
    "sg:address":"Parcummin, Llanddowror, St Clears",
    "sg:city":"Carmarthen",
    "sg:classifiers":[
        {
            "category":"Farming",
            "subcategory":"Livestock Farm",
            "type":"Manufacturing & Wholesale Goods"
        }
    ],
    "sg:phone":"+44 1994 453257",
    "sg:postcode":"SA33 4JD",
    "sg:province":"Carmarthenshire",
    "sg:tags":[
        "others"
    ],
    "wof:name":"D E & D E Morris",
    "wof:placetype":"venue"
},
  "geometry": {"coordinates":[-4.56245,51.778648],"type":"Point"}
}