{
  "type": "Feature",
  "properties": {
    "addr:full":"The Courtyard, 59 Fox Street Gillingham Kent ME7 1HH",
    "addr:housenumber":"59",
    "addr:postcode":"me7 1hh",
    "addr:street":"Fox Street",
    "iso:country":"GB",
    "sg:address":"The Courtyard, 59 Fox Street",
    "sg:city":"Gillingham",
    "sg:classifiers":[
        {
            "category":"Building & Trades",
            "subcategory":"Construction",
            "type":"Services"
        }
    ],
    "sg:phone":"+44 1634 578828",
    "sg:postcode":"ME7 1HH",
    "sg:province":"Kent",
    "sg:tags":[
        "builder"
    ],
    "wof:name":"N H C Builders & Contractors Ltd.",
    "wof:placetype":"venue"
},
  "geometry": {"coordinates":[0.5495430231,51.3864593506],"type":"Point"}
}