{
  "type": "Feature",
  "properties": {
    "iso:country":"GB",
    "sg:address":"Market Square, Llanrhaeadr Ym Mochnant",
    "sg:city":"Oswestry",
    "sg:classifiers":[
        {
            "category":"Government",
            "subcategory":"Post Office",
            "type":"Public Place"
        }
    ],
    "sg:postcode":"SY10 0JG",
    "sg:province":"Shropshire",
    "wof:name":"Llanrhaeadr Post Office",
    "wof:placetype":"venue"
},
  "geometry": {"coordinates":[-3.302219,52.825294],"type":"Point"}
}