{
  "type": "Feature",
  "properties": {
    "addr:full":"37 Knollwood Park, Horsforth Leeds West Yorkshire LS18 4SH",
    "addr:housenumber":"37",
    "addr:postcode":"ls18 4sh",
    "addr:street":"Knollwood Park",
    "iso:country":"GB",
    "sg:address":"37 Knollwood Park, Horsforth",
    "sg:city":"Leeds",
    "sg:classifiers":[
        {
            "category":"Building & Trades",
            "subcategory":"Construction",
            "type":"Services"
        }
    ],
    "sg:postcode":"LS18 4SH",
    "sg:province":"West Yorkshire",
    "sg:tags":[
        "joiner",
        "carpenter"
    ],
    "wof:name":"C G Jennings",
    "wof:placetype":"venue"
},
  "geometry": {"coordinates":[-1.620346,53.835323],"type":"Point"}
}