{
  "type": "Feature",
  "properties": {
    "iso:country":"GB",
    "sg:address":"14 Hermitage Ct",
    "sg:city":"Potters Bar",
    "sg:classifiers":[
        {
            "category":"Home & Garden",
            "subcategory":"Building Materials",
            "type":"Retail Goods"
        }
    ],
    "sg:postcode":"EN6 5DX",
    "sg:province":"Greater London",
    "sg:tags":[
        "furnishers",
        "bathroom",
        "planner"
    ],
    "wof:name":"Spicer,J W,",
    "wof:placetype":"venue"
},
  "geometry": {"coordinates":[-0.177922,51.691235],"type":"Point"}
}