{
  "type": "Feature",
  "properties": {
    "addr:full":"10 Colston Bassett, Emerson Valley Milton Keynes Buckinghamshire MK4 2BA",
    "addr:housenumber":"10",
    "addr:postcode":"mk4 2ba",
    "addr:street":"Colston",
    "iso:country":"GB",
    "sg:address":"10 Colston Bassett, Emerson Valley",
    "sg:city":"Milton Keynes",
    "sg:classifiers":[
        {
            "category":"Professional",
            "subcategory":"Lawyer & Legal Services",
            "type":"Services"
        }
    ],
    "sg:phone":"+44 1908 501388",
    "sg:postcode":"MK4 2BA",
    "sg:province":"Buckinghamshire",
    "sg:tags":[
        "writing"
    ],
    "wof:name":"Felix Thomas",
    "wof:placetype":"venue"
},
  "geometry": {"coordinates":[-0.7742469907,52.0003013611],"type":"Point"}
}