{
  "type": "Feature",
  "properties": {
    "addr:full":"Unit 1, 9 Sulgrave Road Leicester Leicestershire LE5 0LH",
    "addr:housenumber":"unit;9",
    "addr:postcode":"le5 0lh",
    "addr:street":"Sulgrave Road",
    "iso:country":"GB",
    "sg:address":"Unit 1, 9 Sulgrave Road",
    "sg:city":"Leicester",
    "sg:classifiers":[
        {
            "category":"Wholesale",
            "subcategory":"Construction Materials",
            "type":"Manufacturing & Wholesale Goods"
        }
    ],
    "sg:phone":"+44 116 236 4364",
    "sg:postcode":"LE5 0LH",
    "sg:province":"Leicestershire",
    "sg:tags":[
        "supplier",
        "colour"
    ],
    "wof:name":"Tritex Colours (Europe) Ltd.",
    "wof:placetype":"venue"
},
  "geometry": {"coordinates":[-1.1004920006,52.6424446106],"type":"Point"}
}