{
  "type": "Feature",
  "properties": {
    "addr:full":"83 Columbia Road, Ensbury Park Bournemouth Dorset BH10 4EB",
    "addr:housenumber":"83",
    "addr:postcode":"bh10 4eb",
    "addr:street":"Columbia Road Ensbury Park",
    "iso:country":"GB",
    "sg:address":"83 Columbia Road, Ensbury Park",
    "sg:city":"Bournemouth",
    "sg:classifiers":[
        {
            "category":"Personal",
            "subcategory":"Barber",
            "type":"Services"
        }
    ],
    "sg:phone":"+44 1202 525539",
    "sg:postcode":"BH10 4EB",
    "sg:province":"Dorset",
    "sg:tags":[
        "men's",
        "hairdresser"
    ],
    "wof:name":"Antonio",
    "wof:placetype":"venue"
},
  "geometry": {"coordinates":[-1.890365,50.752129],"type":"Point"}
}