{
  "type": "Feature",
  "properties": {
    "addr:full":"28 St Albans Rd Sheffield South Yorkshire S10 4DP",
    "addr:housenumber":"28",
    "addr:postcode":"s10 4dp",
    "addr:street":"St Albans Rd",
    "iso:country":"GB",
    "sg:address":"28 St Albans Rd",
    "sg:city":"Sheffield",
    "sg:classifiers":[
        {
            "category":"Professional",
            "subcategory":"Management & Consulting",
            "type":"Services"
        }
    ],
    "sg:phone":"+44 114 258 0866",
    "sg:postcode":"S10 4DP",
    "sg:province":"South Yorkshire",
    "sg:tags":[
        "fire",
        "consultant",
        "protection"
    ],
    "wof:name":"Fire Health And Safety Consultants Ltd",
    "wof:placetype":"venue"
},
  "geometry": {"coordinates":[-1.55009,53.371395],"type":"Point"}
}