{
  "type": "Feature",
  "properties": {
    "iso:country":"GB",
    "sg:address":"Unit 1 Bartram Farm, Old Otford Road",
    "sg:city":"Sevenoaks",
    "sg:classifiers":[
        {
            "category":"Professional",
            "subcategory":"Printing & Photocopies",
            "type":"Services"
        }
    ],
    "sg:phone":"+44 1732 740968",
    "sg:postcode":"TN14 5EZ",
    "sg:province":"Kent",
    "sg:tags":[
        "emblem",
        "wholesale",
        "badge"
    ],
    "wof:name":"Casebourne's",
    "wof:placetype":"venue"
},
  "geometry": {"coordinates":[0.189895,51.31015],"type":"Point"}
}