{
  "type": "Feature",
  "properties": {
    "addr:full":"8 Radnor Place Mansfield Derbyshire NG19 7RN",
    "addr:housenumber":"8",
    "addr:postcode":"ng19 7rn",
    "addr:street":"Radnor Place",
    "iso:country":"GB",
    "sg:address":"8 Radnor Place",
    "sg:city":"Mansfield",
    "sg:classifiers":[
        {
            "category":"Autos & Motor Vehicles",
            "subcategory":"Automobile Sales",
            "type":"Retail Goods"
        }
    ],
    "sg:postcode":"NG19 7RN",
    "sg:province":"Derbyshire",
    "sg:tags":[
        "car"
    ],
    "wof:name":"Don Weston Cars",
    "wof:placetype":"venue"
},
  "geometry": {"coordinates":[-1.2334530354,53.1685066223],"type":"Point"}
}