{
  "type": "Feature",
  "properties": {
    "addr:full":"Braemar House, Water Lane Stansted Essex CM24 8BJ",
    "addr:postcode":"cm24 8bj",
    "addr:street":"Water Lane",
    "iso:country":"GB",
    "sg:address":"Braemar House, Water Lane",
    "sg:city":"Stansted",
    "sg:classifiers":[
        {
            "category":"Government",
            "subcategory":"Post Office",
            "type":"Public Place"
        }
    ],
    "sg:phone":"+44 1279 647055",
    "sg:postcode":"CM24 8BJ",
    "sg:province":"Essex",
    "sg:tags":[
        "messenger",
        "courier"
    ],
    "wof:name":"Earlybird Couriers",
    "wof:placetype":"venue"
},
  "geometry": {"coordinates":[0.1965889931,51.9007301331],"type":"Point"}
}