{
  "type": "Feature",
  "properties": {
    "iso:country":"GB",
    "sg:address":"109 London Road",
    "sg:city":"Dover",
    "sg:classifiers":[
        {
            "category":"Social Services",
            "type":"Services"
        }
    ],
    "sg:phone":"+44 1304 868000",
    "sg:postcode":"CT17 0TH",
    "sg:province":"Kent",
    "sg:tags":[
        "benefit",
        "agency"
    ],
    "wof:name":"The Benefits Agency",
    "wof:placetype":"venue"
},
  "geometry": {"coordinates":[1.299726963,51.1347541809],"type":"Point"}
}