{
  "type": "Feature",
  "properties": {
    "iso:country":"GB",
    "sg:address":"George Street",
    "sg:city":"Ryde",
    "sg:classifiers":[
        {
            "category":"Place Of Worship",
            "type":"Public Place"
        }
    ],
    "sg:phone":"+44 1983 812774",
    "sg:postcode":"PO33 2JF",
    "sg:province":"Isle of Wight",
    "wof:name":"Ryde Baptist Church",
    "wof:placetype":"venue"
},
  "geometry": {"coordinates":[-1.1597390175,50.7321357727],"type":"Point"}
}