{
  "type": "Feature",
  "properties": {
    "addr:full":", Overbury Tewkesbury Gloucestershire GL20 7NT",
    "addr:postcode":"gl20 7nt",
    "iso:country":"GB",
    "sg:address":", Overbury",
    "sg:city":"Tewkesbury",
    "sg:classifiers":[
        {
            "category":"Education",
            "subcategory":"School",
            "type":"Public Place"
        }
    ],
    "sg:phone":"+44 1386 725235",
    "sg:postcode":"GL20 7NT",
    "sg:province":"Gloucestershire",
    "sg:tags":[
        "local",
        "authority"
    ],
    "wof:name":"Overbury C Of E First School",
    "wof:placetype":"venue"
},
  "geometry": {"coordinates":[-2.056999,52.039295],"type":"Point"}
}