{
  "type": "Feature",
  "properties": {
    "addr:full":"8-9 Birkenhead Market Birkenhead Merseyside CH41 6EY",
    "addr:housenumber":"8-9",
    "addr:postcode":"ch41 6ey",
    "addr:street":"Birkenhead Market",
    "iso:country":"GB",
    "sg:address":"8-9 Birkenhead Market",
    "sg:city":"Birkenhead",
    "sg:classifiers":[
        {
            "category":"Food & Beverages",
            "subcategory":"Bakery",
            "type":"Retail Goods"
        }
    ],
    "sg:postcode":"CH41 6EY",
    "sg:province":"Merseyside",
    "sg:tags":[
        "baker"
    ],
    "wof:name":"Krusty Kob",
    "wof:placetype":"venue"
},
  "geometry": {"coordinates":[-3.025489,53.392567],"type":"Point"}
}