{
  "type": "Feature",
  "properties": {
    "addr:full":"21 High Street Llandovery Carmarthenshire SA20 0PU",
    "addr:housenumber":"21",
    "addr:postcode":"sa20 0pu",
    "addr:street":"High Street",
    "iso:country":"GB",
    "sg:address":"21 High Street",
    "sg:city":"Llandovery",
    "sg:classifiers":[
        {
            "category":"Fast Food",
            "type":"Food & Drink"
        }
    ],
    "sg:phone":"+44 1550 720012",
    "sg:postcode":"SA20 0PU",
    "sg:province":"Carmarthenshire",
    "sg:tags":[
        "away",
        "take"
    ],
    "wof:name":"Mayflower Chinese Take Away",
    "wof:placetype":"venue"
},
  "geometry": {"coordinates":[-3.794331,51.993969],"type":"Point"}
}