{
  "type": "Feature",
  "properties": {
    "addr:full":"32 High Street, Guilden Morden Royston Bedfordshire SG8 0JR",
    "addr:housenumber":"32",
    "addr:postcode":"sg8 0jr",
    "addr:street":"High Street",
    "iso:country":"GB",
    "sg:address":"32 High Street, Guilden Morden",
    "sg:city":"Royston",
    "sg:classifiers":[
        {
            "category":"Building & Trades",
            "subcategory":"Construction",
            "type":"Services"
        }
    ],
    "sg:phone":"+44 1763 853369",
    "sg:postcode":"SG8 0JR",
    "sg:province":"Bedfordshire",
    "sg:tags":[
        "staircase"
    ],
    "wof:name":"Team-Technology Ltd.",
    "wof:placetype":"venue"
},
  "geometry": {"coordinates":[-0.091317,52.124386],"type":"Point"}
}