{
  "type": "Feature",
  "properties": {
    "addr:full":"130 Verdant Lane Catford Greater London SE6 1LG",
    "addr:housenumber":"130",
    "addr:postcode":"se6 1lg",
    "addr:street":"Verdant Lane",
    "iso:country":"GB",
    "sg:address":"130 Verdant Lane",
    "sg:city":"Catford",
    "sg:classifiers":[
        {
            "category":"Building & Trades",
            "subcategory":"Construction",
            "type":"Services"
        }
    ],
    "sg:phone":"+44 20 8695 1311",
    "sg:postcode":"SE6 1LG",
    "sg:province":"Greater London",
    "sg:tags":[
        "ventilation",
        "contractor"
    ],
    "wof:name":"Sanctuary Property Care Ltd",
    "wof:placetype":"venue"
},
  "geometry": {"coordinates":[0.0042320001,51.4411277771],"type":"Point"}
}