{
  "type": "Feature",
  "properties": {
    "iso:country":"GB",
    "sg:address":"156 Cemetry Rd",
    "sg:city":"Sheffield",
    "sg:classifiers":[
        {
            "category":"Retail",
            "subcategory":"Repair Shop",
            "type":"Services"
        }
    ],
    "sg:phone":"+44 114 273 7772",
    "sg:postcode":"S11 8FR",
    "sg:province":"Derbyshire",
    "sg:tags":[
        "upholsterer"
    ],
    "wof:name":"Smithfield Design Upholstery",
    "wof:placetype":"venue"
},
  "geometry": {"coordinates":[-1.482648,53.370399],"type":"Point"}
}