{
  "type": "Feature",
  "properties": {
    "addr:full":"238 High Street Enfield Greater London EN3 4EZ",
    "addr:housenumber":"238",
    "addr:postcode":"en3 4ez",
    "addr:street":"High Street",
    "iso:country":"GB",
    "sg:address":"238 High Street",
    "sg:city":"Enfield",
    "sg:classifiers":[
        {
            "category":"Taxi",
            "type":"Transportation"
        }
    ],
    "sg:phone":"+44 20 8804 8045",
    "sg:postcode":"EN3 4EZ",
    "sg:province":"Greater London",
    "sg:tags":[
        "mini",
        "hire",
        "cab",
        "private",
        "vehicle"
    ],
    "wof:name":"Ponders End Car Service",
    "wof:placetype":"venue"
},
  "geometry": {"coordinates":[-0.0465020016,51.6499290466],"type":"Point"}
}