{
  "type": "Feature",
  "properties": {
    "addr:full":"2 Brighton Gro, Fenham Newcastle-upon-tyne Tyne and Wear NE4 5NR",
    "addr:housenumber":"2",
    "addr:postcode":"ne4 5nr",
    "addr:street":"Brighton Gro Fenham",
    "iso:country":"GB",
    "sg:address":"2 Brighton Gro, Fenham",
    "sg:city":"Newcastle-upon-tyne",
    "sg:classifiers":[
        {
            "category":"Education",
            "subcategory":"Special Training",
            "type":"Public Place"
        }
    ],
    "sg:phone":"+44 191 226 0394",
    "sg:postcode":"NE4 5NR",
    "sg:province":"Tyne and Wear",
    "sg:tags":[
        "product",
        "centre"
    ],
    "sg:website":"http://www.wwmail.co.uk",
    "wof:name":"The Angelou Centre",
    "wof:placetype":"venue"
},
  "geometry": {"coordinates":[-1.642096,54.9743],"type":"Point"}
}