{
  "type": "Feature",
  "properties": {
    "addr:full":"Pollingfold Farm, Ellens Green Horsham West Sussex RH12 3AS",
    "addr:postcode":"rh12 3as",
    "addr:street":"Ellens Green",
    "iso:country":"GB",
    "sg:address":"Pollingfold Farm, Ellens Green",
    "sg:city":"Horsham",
    "sg:classifiers":[
        {
            "category":"Shopping",
            "subcategory":"Pets & Pet Supplies",
            "type":"Retail Goods"
        }
    ],
    "sg:phone":"+44 1483 232294",
    "sg:postcode":"RH12 3AS",
    "sg:province":"West Sussex",
    "sg:tags":[
        "food"
    ],
    "wof:name":"Frosbury Farm Feeds",
    "wof:placetype":"venue"
},
  "geometry": {"coordinates":[-0.3291069865,51.0651817322],"type":"Point"}
}