{
  "type": "Feature",
  "properties": {
    "iso:country":"GB",
    "sg:address":"3 St Pauls Hill",
    "sg:city":"Winchester",
    "sg:classifiers":[
        {
            "category":"Bars & Pubs",
            "type":"Food & Drink"
        }
    ],
    "sg:phone":"+44 1962 867795",
    "sg:postcode":"SO22 5AE",
    "sg:province":"Hampshire",
    "sg:tags":[
        "pubs",
        "inn"
    ],
    "wof:name":"Railway Inn",
    "wof:placetype":"venue"
},
  "geometry": {"coordinates":[-1.323103,51.06707],"type":"Point"}
}