{
  "type": "Feature",
  "properties": {
    "addr:full":"100 Blossom Way West Drayton Greater London UB7 9HG",
    "addr:housenumber":"100",
    "addr:postcode":"ub7 9hg",
    "addr:street":"Blossom Way",
    "iso:country":"GB",
    "sg:address":"100 Blossom Way",
    "sg:city":"West Drayton",
    "sg:classifiers":[
        {
            "category":"Retail",
            "subcategory":"Auto Repair",
            "type":"Services"
        }
    ],
    "sg:postcode":"UB7 9HG",
    "sg:province":"Greater London",
    "sg:tags":[
        "electrician"
    ],
    "wof:name":"A E L Mobile Auto Electrics",
    "wof:placetype":"venue"
},
  "geometry": {"coordinates":[-0.457267,51.497856],"type":"Point"}
}