{
  "type": "Feature",
  "properties": {
    "iso:country":"GB",
    "sg:address":"Unit 19 Cornhill",
    "sg:city":"Accrington",
    "sg:classifiers":[
        {
            "category":"Shopping",
            "subcategory":"Comic Books",
            "type":"Retail Goods"
        }
    ],
    "sg:phone":"+44 1254 390322",
    "sg:postcode":"BB5 1EX",
    "sg:province":"Lancashire",
    "sg:tags":[
        "jeweller"
    ],
    "wof:name":"H Samuel",
    "wof:placetype":"venue"
},
  "geometry": {"coordinates":[-2.367959,53.75486],"type":"Point"}
}