{
  "type": "Feature",
  "properties": {
    "iso:country":"GB",
    "sg:address":"Robot Works, Matilda Street",
    "sg:city":"Sheffield",
    "sg:classifiers":[
        {
            "category":"Manufacturing",
            "subcategory":"Tools & Machinery",
            "type":"Manufacturing & Wholesale Goods"
        },
        {
            "category":"Home & Garden",
            "subcategory":"Building Materials",
            "type":"Retail Goods"
        }
    ],
    "sg:phone":"+44 114 272 2504",
    "sg:postcode":"S1 4QG",
    "sg:province":"South Yorkshire",
    "sg:tags":[
        "supplier"
    ],
    "wof:name":"WORLDWIDE TOOLS LTD",
    "wof:placetype":"venue"
},
  "geometry": {"coordinates":[-1.464544,53.38311],"type":"Point"}
}