{
  "type": "Feature",
  "properties": {
    "iso:country":"GB",
    "sg:address":"Unit 1 Acre Street, Whitworth",
    "sg:city":"Rochdale",
    "sg:classifiers":[
        {
            "category":"Manufacturing",
            "subcategory":"Paper Products",
            "type":"Manufacturing & Wholesale Goods"
        }
    ],
    "sg:phone":"+44 1706 854262",
    "sg:postcode":"OL12 8XH",
    "sg:province":"Lancashire",
    "sg:tags":[
        "cardboard"
    ],
    "wof:name":"Valley Decorators",
    "wof:placetype":"venue"
},
  "geometry": {"coordinates":[-2.172489,53.661789],"type":"Point"}
}