{
  "type": "Feature",
  "properties": {
    "addr:full":"Kilner House, 197 Freemasons Rd, Canning Town Canning Town Greater London E16 3PD",
    "addr:housenumber":"197",
    "addr:postcode":"e16 3pd",
    "addr:street":"Freemasons Rd",
    "iso:country":"GB",
    "sg:address":"Kilner House, 197 Freemasons Rd, Canning Town",
    "sg:city":"Canning Town",
    "sg:classifiers":[
        {
            "category":"Social Services",
            "type":"Services"
        }
    ],
    "sg:phone":"+44 20 7599 8899",
    "sg:postcode":"E16 3PD",
    "sg:province":"Greater London",
    "sg:tags":[
        "benefit",
        "agency"
    ],
    "wof:name":"Benefits Agency",
    "wof:placetype":"venue"
},
  "geometry": {"coordinates":[0.025189,51.514896],"type":"Point"}
}