{
  "type": "Feature",
  "properties": {
    "iso:country":"GB",
    "sg:address":"1-2 Church Street, Clare",
    "sg:city":"Sudbury",
    "sg:classifiers":[
        {
            "category":"Shopping",
            "subcategory":"Antiques",
            "type":"Retail Goods"
        },
        {
            "category":"Shopping",
            "subcategory":"Used Merchandise",
            "type":"Retail Goods"
        }
    ],
    "sg:phone":"+44 1787 277693",
    "sg:postcode":"CO10 8PD",
    "sg:province":"Essex",
    "sg:tags":[
        "shop",
        "second-hand"
    ],
    "wof:name":"F D Salter Antiques",
    "wof:placetype":"venue"
},
  "geometry": {"coordinates":[0.581336,52.07893],"type":"Point"}
}