{
  "type": "Feature",
  "properties": {
    "iso:country":"GB",
    "sg:address":"Sheaf Brewery, Ecclesall Road",
    "sg:city":"Sheffield",
    "sg:classifiers":[
        {
            "category":"Brewery",
            "type":"Food & Drink"
        }
    ],
    "sg:phone":"+44 114 276 8787",
    "sg:postcode":"S11 8HZ",
    "sg:province":"Derbyshire",
    "sg:tags":[
        "brewer"
    ],
    "wof:name":"S H Ward & Co. Ltd.",
    "wof:placetype":"venue"
},
  "geometry": {"coordinates":[-1.464544,53.38311],"type":"Point"}
}