{
  "type": "Feature",
  "properties": {
    "iso:country":"GB",
    "sg:address":"Ransfield, Ratho",
    "sg:city":"Newbridge",
    "sg:classifiers":[
        {
            "category":"Farming",
            "subcategory":"Farm",
            "type":"Manufacturing & Wholesale Goods"
        }
    ],
    "sg:phone":"+44 131 333 1214",
    "sg:postcode":"EH28 8NS",
    "sg:province":"City of Edinburgh",
    "sg:tags":[
        "mixed",
        "crop"
    ],
    "wof:name":"James Lawrie",
    "wof:placetype":"venue"
},
  "geometry": {"coordinates":[-3.409335,55.940845],"type":"Point"}
}