{
  "type": "Feature",
  "properties": {
    "addr:full":"72 Greenfields Road Reading Berkshire RG2 8SG",
    "addr:housenumber":"72",
    "addr:postcode":"rg2 8sg",
    "addr:street":"Greenfields Road",
    "iso:country":"GB",
    "sg:address":"72 Greenfields Road",
    "sg:city":"Reading",
    "sg:classifiers":[
        {
            "category":"Retail",
            "subcategory":"Driving School",
            "type":"Services"
        }
    ],
    "sg:postcode":"RG2 8SG",
    "sg:province":"Berkshire",
    "wof:name":"Harries School of Motoring",
    "wof:placetype":"venue"
},
  "geometry": {"coordinates":[-0.9671790004,51.4212150574],"type":"Point"}
}