{
  "type": "Feature",
  "properties": {
    "addr:full":"8 Battledown Close Cheltenham Gloucestershire GL52 6RD",
    "addr:housenumber":"8",
    "addr:postcode":"gl52 6rd",
    "addr:street":"Battledown Close",
    "iso:country":"GB",
    "sg:address":"8 Battledown Close",
    "sg:city":"Cheltenham",
    "sg:classifiers":[
        {
            "category":"Education",
            "subcategory":"Music School",
            "type":"Public Place"
        },
        {
            "category":"Personal",
            "type":"Services"
        }
    ],
    "sg:phone":"+44 1242 235655",
    "sg:postcode":"GL52 6RD",
    "sg:province":"Gloucestershire",
    "sg:tags":[
        "slimming",
        "product",
        "teacher"
    ],
    "wof:name":"Healthy Weigh Tricia Matthews",
    "wof:placetype":"venue"
},
  "geometry": {"coordinates":[-2.057254,51.89698],"type":"Point"}
}