{
  "type": "Feature",
  "properties": {
    "addr:full":"Wanstead Leisure Centre Redbridge Lane W, Wanstead London Greater London E11 2JZ",
    "addr:postcode":"e11 2jz",
    "addr:street":"Redbridge Lane W",
    "iso:country":"GB",
    "sg:address":"Wanstead Leisure Centre Redbridge Lane W, Wanstead",
    "sg:city":"London",
    "sg:classifiers":[
        {
            "category":"Organizations",
            "subcategory":"Membership Organization",
            "type":"Services"
        }
    ],
    "sg:postcode":"E11 2JZ",
    "sg:province":"Greater London",
    "sg:tags":[
        "club"
    ],
    "wof:name":"Butler,Rod,",
    "wof:placetype":"venue"
},
  "geometry": {"coordinates":[0.027567,51.576279],"type":"Point"}
}