{
  "type": "Feature",
  "properties": {
    "iso:country":"GB",
    "sg:address":"Unit 26, Motherwell Business Centre",
    "sg:city":"Motherwell",
    "sg:classifiers":[
        {
            "category":"Shopping",
            "subcategory":"Stationery & Office Supplies",
            "type":"Retail Goods"
        }
    ],
    "sg:phone":"+44 1698 254624",
    "sg:postcode":"ML1 1PR",
    "sg:province":"North Lanarkshire",
    "wof:name":"Jaydea Marketing",
    "wof:placetype":"venue"
},
  "geometry": {"coordinates":[-3.986604,55.79126],"type":"Point"}
}