{
  "type": "Feature",
  "properties": {
    "addr:full":"393 Green Lanes London Greater London N4 1EU",
    "addr:housenumber":"393",
    "addr:postcode":"n4 1eu",
    "addr:street":"Green Lanes",
    "iso:country":"GB",
    "sg:address":"393 Green Lanes",
    "sg:city":"London",
    "sg:classifiers":[
        {
            "category":"Professional",
            "subcategory":"Lawyer & Legal Services",
            "type":"Services"
        }
    ],
    "sg:phone":"+44 20 8348 8233",
    "sg:postcode":"N4 1EU",
    "sg:province":"Greater London",
    "sg:tags":[
        "solicitor"
    ],
    "wof:name":"A Nicolaou A & Co",
    "wof:placetype":"venue"
},
  "geometry": {"coordinates":[-0.0990900025,51.5777206421],"type":"Point"}
}