{
  "type": "Feature",
  "properties": {
    "iso:country":"GB",
    "sg:address":"Fairfields Clinic",
    "sg:city":"Basingstoke",
    "sg:classifiers":[
        {
            "category":"Health Services",
            "subcategory":"Health Practitioner",
            "type":"Services"
        }
    ],
    "sg:postcode":"RG21 3HP",
    "sg:province":"Hampshire",
    "sg:tags":[
        "acupuncture"
    ],
    "wof:name":"Ron Piercy",
    "wof:placetype":"venue"
},
  "geometry": {"coordinates":[-1.086359,51.259094],"type":"Point"}
}