{
  "type": "Feature",
  "properties": {
    "addr:full":"393 Banbury Rd Oxford Oxfordshire OX2 7RF",
    "addr:housenumber":"393",
    "addr:postcode":"ox2 7rf",
    "addr:street":"Banbury Rd",
    "iso:country":"GB",
    "sg:address":"393 Banbury Rd",
    "sg:city":"Oxford",
    "sg:classifiers":[
        {
            "category":"Place Of Worship",
            "type":"Public Place"
        }
    ],
    "sg:phone":"+44 1865 515371",
    "sg:postcode":"OX2 7RF",
    "sg:province":"Oxfordshire",
    "wof:name":"Shekinah Bible Church",
    "wof:placetype":"venue"
},
  "geometry": {"coordinates":[-1.270112,51.786297],"type":"Point"}
}