{
  "type": "Feature",
  "properties": {
    "addr:full":"Etchells Street, St Petersgate Stockport Cheshire SK1 1EF",
    "addr:postcode":"sk1 1ef",
    "addr:street":"Etchells Street St Petersgate",
    "iso:country":"GB",
    "sg:address":"Etchells Street, St Petersgate",
    "sg:city":"Stockport",
    "sg:classifiers":[
        {
            "category":"Education",
            "subcategory":"School",
            "type":"Public Place"
        }
    ],
    "sg:phone":"+44 161 480 5029",
    "sg:postcode":"SK1 1EF",
    "sg:province":"Cheshire",
    "sg:tags":[
        "local",
        "authority"
    ],
    "wof:name":"St Joseph's R C Primary School",
    "wof:placetype":"venue"
},
  "geometry": {"coordinates":[-2.1578791142,53.4100341797],"type":"Point"}
}