{
  "type": "Feature",
  "properties": {
    "addr:full":"1 Woolgate Ct, St Benedicts St Norwich Norfolk NR2 4AP",
    "addr:housenumber":"1",
    "addr:postcode":"nr2 4ap",
    "addr:street":"Woolgate Ct St Benedicts St",
    "iso:country":"GB",
    "sg:address":"1 Woolgate Ct, St Benedicts St",
    "sg:city":"Norwich",
    "sg:classifiers":[
        {
            "category":"Social Services",
            "subcategory":"Retirement Home",
            "type":"Services"
        }
    ],
    "sg:phone":"+44 1603 219982",
    "sg:postcode":"NR2 4AP",
    "sg:province":"Norfolk",
    "sg:tags":[
        "care"
    ],
    "wof:name":"Primrose Care Ltd",
    "wof:placetype":"venue"
},
  "geometry": {"coordinates":[1.2918050289,52.6308021545],"type":"Point"}
}