{
  "type": "Feature",
  "properties": {
    "addr:full":"Kitchen, Watergall, Bretton Peterborough Cambridgeshire PE3 8NX",
    "addr:postcode":"pe3 8nx",
    "addr:street":"Bretton",
    "iso:country":"GB",
    "sg:address":"Kitchen, Watergall, Bretton",
    "sg:city":"Peterborough",
    "sg:classifiers":[
        {
            "category":"Education",
            "subcategory":"School",
            "type":"Public Place"
        }
    ],
    "sg:phone":"+44 1733 265230",
    "sg:postcode":"PE3 8NX",
    "sg:province":"Cambridgeshire",
    "sg:tags":[
        "local",
        "authority"
    ],
    "wof:name":"Watergall Junior School",
    "wof:placetype":"venue"
},
  "geometry": {"coordinates":[-0.2888390124,52.6007995605],"type":"Point"}
}