{
  "type": "Feature",
  "properties": {
    "addr:full":"Unit 5, Stephenson Court, Barrington Ind Est Bedlington Northumberland NE22 7DQ",
    "addr:housenumber":"unit 5",
    "addr:postcode":"ne22 7dq",
    "addr:street":"Stephenson Court;Northumberland",
    "iso:country":"GB",
    "sg:address":"Unit 5, Stephenson Court, Barrington Ind Est",
    "sg:city":"Bedlington",
    "sg:classifiers":[
        {
            "category":"Professional",
            "subcategory":"Engineering",
            "type":"Services"
        }
    ],
    "sg:phone":"+44 1670 530411",
    "sg:postcode":"NE22 7DQ",
    "sg:province":"Northumberland",
    "sg:tags":[
        "ge",
        "engineer",
        "mechanical"
    ],
    "wof:name":"Elan Manufacturing",
    "wof:placetype":"venue"
},
  "geometry": {"coordinates":[-1.5824439526,55.1440734863],"type":"Point"}
}