{
  "type": "Feature",
  "properties": {
    "addr:full":"Manor Farm, Wood Enderby Boston Lincolnshire PE22 7PQ",
    "addr:postcode":"pe22 7pq",
    "addr:street":"Manor",
    "iso:country":"GB",
    "sg:address":"Manor Farm, Wood Enderby",
    "sg:city":"Boston",
    "sg:classifiers":[
        {
            "category":"Farming",
            "subcategory":"Farm",
            "type":"Manufacturing & Wholesale Goods"
        }
    ],
    "sg:phone":"+44 1507 568382",
    "sg:postcode":"PE22 7PQ",
    "sg:province":"Lincolnshire",
    "sg:tags":[
        "mixed",
        "crop"
    ],
    "wof:name":"G A Scholey & Son",
    "wof:placetype":"venue"
},
  "geometry": {"coordinates":[-0.095149,53.156761],"type":"Point"}
}