{
  "type": "Feature",
  "properties": {
    "addr:full":"210 Cyncoed Road Cardiff Cardiff CF23 6RS",
    "addr:housenumber":"210",
    "addr:postcode":"cf23 6rs",
    "addr:street":"Cyncoed Road",
    "iso:country":"GB",
    "sg:address":"210 Cyncoed Road",
    "sg:city":"Cardiff",
    "sg:classifiers":[
        {
            "category":"Banks & Credit Unions",
            "subcategory":"Bureau De Change",
            "type":"Services"
        }
    ],
    "sg:phone":"+44 29 2068 9450",
    "sg:postcode":"CF23 6RS",
    "sg:province":"Cardiff",
    "sg:tags":[
        "town",
        "consultant",
        "planning"
    ],
    "wof:name":"Edward Butler",
    "wof:placetype":"venue"
},
  "geometry": {"coordinates":[-3.1637039185,51.5154418945],"type":"Point"}
}