{
  "type": "Feature",
  "properties": {
    "addr:full":"50 George Street Perth Perth and Kinross PH1 5JL",
    "addr:housenumber":"50",
    "addr:postcode":"ph1 5jl",
    "addr:street":"George Street",
    "iso:country":"GB",
    "sg:address":"50 George Street",
    "sg:city":"Perth",
    "sg:classifiers":[
        {
            "category":"Retail",
            "subcategory":"Laundry & Dry Cleaning",
            "type":"Services"
        }
    ],
    "sg:phone":"+44 1738 627207",
    "sg:postcode":"PH1 5JL",
    "sg:province":"Perth and Kinross",
    "sg:tags":[
        "launderette"
    ],
    "wof:name":"The Laundry Shop",
    "wof:placetype":"venue"
},
  "geometry": {"coordinates":[-3.4279069901,56.3977394104],"type":"Point"}
}