{
  "type": "Feature",
  "properties": {
    "iso:country":"GB",
    "sg:address":"244 Acklam Road",
    "sg:city":"London",
    "sg:classifiers":[
        {
            "category":"Community Center",
            "type":"Public Place"
        }
    ],
    "sg:phone":"+44 20 8964 1496",
    "sg:postcode":"W10 5YG",
    "sg:province":"Greater London",
    "sg:tags":[
        "centre"
    ],
    "wof:name":"The Muslim Cultural Heritage Centre (M C H C) Trust",
    "wof:placetype":"venue"
},
  "geometry": {"coordinates":[-0.204439,51.521061],"type":"Point"}
}