{
  "type": "Feature",
  "properties": {
    "iso:country":"GB",
    "sg:address":"2 Hen Aelwyd, Penrhyn Terrace",
    "sg:city":"Bangor",
    "sg:classifiers":[
        {
            "category":"Building & Trades",
            "subcategory":"Construction",
            "type":"Services"
        }
    ],
    "sg:phone":"+44 1248 600633",
    "sg:postcode":"LL57 3NB",
    "sg:province":"Gwynedd",
    "sg:tags":[
        "roofing",
        "contracting"
    ],
    "wof:name":"G B Hughes",
    "wof:placetype":"venue"
},
  "geometry": {"coordinates":[-4.126064,53.229595],"type":"Point"}
}