{
  "type": "Feature",
  "properties": {
    "addr:full":"West Heddon Nurseries, Heddon On The Wall Newcastle-upon-tyne Northumberland NE15 0JS",
    "addr:housenumber":"newcastle-upon-tyne",
    "addr:postcode":"ne15 0js",
    "addr:street":"West;Heddon;Wall",
    "iso:country":"GB",
    "sg:address":"West Heddon Nurseries, Heddon On The Wall",
    "sg:city":"Newcastle-upon-tyne",
    "sg:classifiers":[
        {
            "category":"Home & Garden",
            "subcategory":"Garden Supply",
            "type":"Retail Goods"
        }
    ],
    "sg:phone":"+44 1661 852445",
    "sg:postcode":"NE15 0JS",
    "sg:province":"Northumberland",
    "sg:tags":[
        "nursery",
        "centre"
    ],
    "wof:name":"Halls Of Heddon Ltd",
    "wof:placetype":"venue"
},
  "geometry": {"coordinates":[-1.7947679758,54.997303009],"type":"Point"}
}