{
  "type": "Feature",
  "properties": {
    "addr:full":"Old School, 51 High Street Lochwinnoch Renfrewshire PA12 4AB",
    "addr:housenumber":"51",
    "addr:postcode":"pa12 4ab",
    "addr:street":"High Street",
    "iso:country":"GB",
    "sg:address":"Old School, 51 High Street",
    "sg:city":"Lochwinnoch",
    "sg:classifiers":[
        {
            "category":"Education",
            "subcategory":"Library",
            "type":"Public Place"
        },
        {
            "category":"Government",
            "subcategory":"Office",
            "type":"Public Place"
        }
    ],
    "sg:phone":"+44 1505 842305",
    "sg:postcode":"PA12 4AB",
    "sg:province":"Renfrewshire",
    "sg:tags":[
        "book",
        "local"
    ],
    "wof:name":"Lochwinnoch Community Library",
    "wof:placetype":"venue"
},
  "geometry": {"coordinates":[-4.622879,55.797619],"type":"Point"}
}