{
  "type": "Feature",
  "properties": {
    "addr:full":"5 Sherbrooke Close, Calverton Nottingham Nottinghamshire NG14 6LN",
    "addr:housenumber":"5",
    "addr:postcode":"ng14 6ln",
    "addr:street":"Sherbrooke Close",
    "iso:country":"GB",
    "sg:address":"5 Sherbrooke Close, Calverton",
    "sg:city":"Nottingham",
    "sg:classifiers":[
        {
            "category":"Health Services",
            "subcategory":"Podiatrist",
            "type":"Services"
        }
    ],
    "sg:phone":"+44 115 965 4733",
    "sg:postcode":"NG14 6LN",
    "sg:province":"Nottinghamshire",
    "sg:tags":[
        "podiatrists",
        "chiropodist"
    ],
    "wof:name":"Pauline Cleverley",
    "wof:placetype":"venue"
},
  "geometry": {"coordinates":[-1.087121,53.041286],"type":"Point"}
}