{
  "type": "Feature",
  "properties": {
    "iso:country":"GB",
    "sg:address":"76 Duke St",
    "sg:city":"Edinburgh",
    "sg:classifiers":[
        {
            "category":"Travel",
            "subcategory":"Travel Agent",
            "type":"Entertainment"
        }
    ],
    "sg:phone":"+44 131 555 2555",
    "sg:postcode":"EH6 8HL",
    "sg:province":"City of Edinburgh",
    "wof:name":"Scotmid Travel",
    "wof:placetype":"venue"
},
  "geometry": {"coordinates":[-3.1692810059,55.9696846008],"type":"Point"}
}