{
  "type": "Feature",
  "properties": {
    "iso:country":"GB",
    "sg:address":"6 Hermitage Parade",
    "sg:city":"Ascot",
    "sg:classifiers":[
        {
            "category":"Restaurant",
            "type":"Food & Drink"
        }
    ],
    "sg:phone":"+44 1344 622285",
    "sg:postcode":"SL5 7TE",
    "sg:province":"Berkshire",
    "sg:tags":[
        "italian"
    ],
    "wof:name":"Ciao Ninety",
    "wof:placetype":"venue"
},
  "geometry": {"coordinates":[-0.673794,51.410675],"type":"Point"}
}