{
  "type": "Feature",
  "properties": {
    "addr:full":"30 Crossways Avenue East Grinstead East Sussex RH19 1HZ",
    "addr:housenumber":"30",
    "addr:postcode":"rh19 1hz",
    "addr:street":"Crossways Avenue",
    "iso:country":"GB",
    "sg:address":"30 Crossways Avenue",
    "sg:city":"East Grinstead",
    "sg:classifiers":[
        {
            "category":"Home & Garden",
            "subcategory":"Building Materials",
            "type":"Retail Goods"
        }
    ],
    "sg:postcode":"RH19 1HZ",
    "sg:province":"East Sussex",
    "sg:tags":[
        "garage",
        "door"
    ],
    "wof:name":"A K Doors & Gates",
    "wof:placetype":"venue"
},
  "geometry": {"coordinates":[-0.024141,51.128597],"type":"Point"}
}