{
  "type": "Feature",
  "properties": {
    "addr:full":"Camp Road, Upper Heyford Bicester Oxfordshire OX25 5LU",
    "addr:postcode":"ox25 5lu",
    "addr:street":"Camp Road",
    "iso:country":"GB",
    "sg:address":"Camp Road, Upper Heyford",
    "sg:city":"Bicester",
    "sg:classifiers":[
        {
            "category":"Retail",
            "subcategory":"Auto Repair",
            "type":"Services"
        }
    ],
    "sg:phone":"+44 1869 232805",
    "sg:postcode":"OX25 5LU",
    "sg:province":"Oxfordshire",
    "sg:tags":[
        "modification",
        "garage"
    ],
    "wof:name":"Heyford Garage",
    "wof:placetype":"venue"
},
  "geometry": {"coordinates":[-1.2543489933,51.9281654358],"type":"Point"}
}