{
  "type": "Feature",
  "properties": {
    "iso:country":"GB",
    "sg:address":"77 Vivian Road",
    "sg:city":"Birmingham",
    "sg:classifiers":[
        {
            "category":"Professional",
            "subcategory":"Engineering",
            "type":"Services"
        }
    ],
    "sg:phone":"+44 121 427 3101",
    "sg:postcode":"B17 0DY",
    "sg:province":"West Midlands",
    "sg:tags":[
        "contractor",
        "electrical",
        "engineer"
    ],
    "wof:name":"L H Durrant & Co. Ltd.",
    "wof:placetype":"venue"
},
  "geometry": {"coordinates":[-1.9527909756,52.4574890137],"type":"Point"}
}