{
  "type": "Feature",
  "properties": {
    "iso:country":"GB",
    "sg:address":"28 Medlock Rd, Failsworth",
    "sg:city":"Manchester",
    "sg:classifiers":[
        {
            "category":"Building & Trades",
            "subcategory":"Construction",
            "type":"Services"
        }
    ],
    "sg:phone":"+44 161 682 0954",
    "sg:postcode":"M35 9WN",
    "sg:province":"Lancashire",
    "sg:tags":[
        "builder"
    ],
    "wof:name":"A.S.R Building Contractors",
    "wof:placetype":"venue"
},
  "geometry": {"coordinates":[-2.1370699406,53.5038299561],"type":"Point"}
}