{
  "type": "Feature",
  "properties": {
    "iso:country":"GB",
    "sg:address":"Care Of Quantum Care Ltd, Wratten Road West",
    "sg:city":"Hitchin",
    "sg:classifiers":[
        {
            "category":"Health Services",
            "subcategory":"Nursing And Care Facility",
            "type":"Services"
        },
        {
            "category":"Social Services",
            "subcategory":"Retirement Home",
            "type":"Services"
        }
    ],
    "sg:phone":"+44 1462 450703",
    "sg:postcode":"SG5 2AU",
    "sg:province":"Bedfordshire",
    "sg:tags":[
        "residential"
    ],
    "wof:name":"Minsden",
    "wof:placetype":"venue"
},
  "geometry": {"coordinates":[-0.284408,51.952435],"type":"Point"}
}