{
  "type": "Feature",
  "properties": {
    "addr:full":"6 Mill Lane Billingham Durham TS23 1HF",
    "addr:housenumber":"6",
    "addr:postcode":"ts23 1hf",
    "addr:street":"Mill Lane",
    "iso:country":"GB",
    "sg:address":"6 Mill Lane",
    "sg:city":"Billingham",
    "sg:classifiers":[
        {
            "category":"Fast Food",
            "type":"Food & Drink"
        }
    ],
    "sg:postcode":"TS23 1HF",
    "sg:province":"Durham",
    "sg:tags":[
        "away",
        "take"
    ],
    "wof:name":"Crowns Chop Suey House",
    "wof:placetype":"venue"
},
  "geometry": {"coordinates":[-1.289544,54.593449],"type":"Point"}
}