{
  "type": "Feature",
  "properties": {
    "addr:full":"267 Market Street Hyde Cheshire SK14 1HE",
    "addr:housenumber":"267",
    "addr:postcode":"sk14 1he",
    "addr:street":"Market Street",
    "iso:country":"GB",
    "sg:address":"267 Market Street",
    "sg:city":"Hyde",
    "sg:classifiers":[
        {
            "category":"Building & Trades",
            "subcategory":"Cleaning & Sanitation",
            "type":"Services"
        }
    ],
    "sg:postcode":"SK14 1HE",
    "sg:province":"Cheshire",
    "sg:tags":[
        "dry",
        "control",
        "damp",
        "rot"
    ],
    "wof:name":"Mylestone Damp Course & Timber Decay Co",
    "wof:placetype":"venue"
},
  "geometry": {"coordinates":[-2.0732679367,53.4467544556],"type":"Point"}
}