{
  "type": "Feature",
  "properties": {
    "addr:full":"14 High Street, Bulkington Devizes Wiltshire SN10 1SJ",
    "addr:housenumber":"14",
    "addr:postcode":"sn10 1sj",
    "addr:street":"High Street",
    "iso:country":"GB",
    "sg:address":"14 High Street, Bulkington",
    "sg:city":"Devizes",
    "sg:classifiers":[
        {
            "category":"Government",
            "subcategory":"Post Office",
            "type":"Public Place"
        }
    ],
    "sg:postcode":"SN10 1SJ",
    "sg:province":"Wiltshire",
    "wof:name":"Erlestoke Sub Post Office & Stores",
    "wof:placetype":"venue"
},
  "geometry": {"coordinates":[-1.994264,51.351696],"type":"Point"}
}