{
  "type": "Feature",
  "properties": {
    "addr:full":"Riverside Industrial Estate, Thames Road Barking Essex IG11 0ND",
    "addr:housenumber":"estate",
    "addr:postcode":"ig11 0nd",
    "addr:street":"Thames Road",
    "iso:country":"GB",
    "sg:address":"Riverside Industrial Estate, Thames Road",
    "sg:city":"Barking",
    "sg:classifiers":[
        {
            "category":"Building & Trades",
            "subcategory":"Construction",
            "type":"Services"
        }
    ],
    "sg:phone":"+44 20 8591 5525",
    "sg:postcode":"IG11 0ND",
    "sg:province":"Essex",
    "sg:tags":[
        "glazier"
    ],
    "wof:name":"Highway Glass (Uk)",
    "wof:placetype":"venue"
},
  "geometry": {"coordinates":[0.0811149999,51.539100647],"type":"Point"}
}