{
  "type": "Feature",
  "properties": {
    "addr:full":"55 Fernhurst Road Southsea Hampshire PO4 8AA",
    "addr:housenumber":"55",
    "addr:postcode":"po4 8aa",
    "addr:street":"Fernhurst Road",
    "iso:country":"GB",
    "sg:address":"55 Fernhurst Road",
    "sg:city":"Southsea",
    "sg:classifiers":[
        {
            "category":"Building & Trades",
            "subcategory":"Cleaning & Sanitation",
            "type":"Services"
        }
    ],
    "sg:postcode":"PO4 8AA",
    "sg:province":"Hampshire",
    "sg:tags":[
        "commercial"
    ],
    "wof:name":"M G Cleaning Services",
    "wof:placetype":"venue"
},
  "geometry": {"coordinates":[-1.0685030222,50.7926254272],"type":"Point"}
}