{
  "type": "Feature",
  "properties": {
    "iso:country":"GB",
    "sg:address":"6 Efford Crescent",
    "sg:city":"Plymouth",
    "sg:classifiers":[
        {
            "category":"Personal",
            "subcategory":"Beauty Salon",
            "type":"Services"
        }
    ],
    "sg:postcode":"PL3 6NH",
    "sg:province":"Devon",
    "sg:tags":[
        "unisex",
        "hairdresser"
    ],
    "wof:name":"Adele Thomas",
    "wof:placetype":"venue"
},
  "geometry": {"coordinates":[-4.118432045,50.3916702271],"type":"Point"}
}