{
  "type": "Feature",
  "properties": {
    "addr:full":"149 Kingfisher Drive Guildford Surrey GU4 7EY",
    "addr:housenumber":"149",
    "addr:postcode":"gu4 7ey",
    "addr:street":"Kingfisher Drive",
    "iso:country":"GB",
    "sg:address":"149 Kingfisher Drive",
    "sg:city":"Guildford",
    "sg:classifiers":[
        {
            "category":"Professional",
            "type":"Services"
        }
    ],
    "sg:postcode":"GU4 7EY",
    "sg:province":"Surrey",
    "sg:tags":[
        "entertainer"
    ],
    "wof:name":"The Tony Barrie Organisation",
    "wof:placetype":"venue"
},
  "geometry": {"coordinates":[-0.536766,51.252472],"type":"Point"}
}