{
  "type": "Feature",
  "properties": {
    "iso:country":"GB",
    "sg:address":"31 Sherwood Road",
    "sg:city":"Bromsgrove",
    "sg:classifiers":[
        {
            "category":"Retail",
            "subcategory":"Auto Repair",
            "type":"Services"
        }
    ],
    "sg:phone":"+44 1527 579175",
    "sg:postcode":"B60 3DR",
    "sg:province":"Worcestershire",
    "sg:tags":[
        "modification",
        "garage",
        "related"
    ],
    "wof:name":"S H Auto",
    "wof:placetype":"venue"
},
  "geometry": {"coordinates":[-2.060017,52.318134],"type":"Point"}
}