{
  "type": "Feature",
  "properties": {
    "addr:full":"Main Road, Newport Brough East Riding of Yorkshire HU15 2PR",
    "addr:postcode":"hu15 2pr",
    "addr:street":"Main Road",
    "iso:country":"GB",
    "sg:address":"Main Road, Newport",
    "sg:city":"Brough",
    "sg:classifiers":[
        {
            "category":"Food & Beverages",
            "subcategory":"Supermarket",
            "type":"Retail Goods"
        }
    ],
    "sg:phone":"+44 1430 441552",
    "sg:postcode":"HU15 2PR",
    "sg:province":"East Riding of Yorkshire",
    "sg:tags":[
        "frozen"
    ],
    "wof:name":"Hedon Salads (Holdings) Ltd.",
    "wof:placetype":"venue"
},
  "geometry": {"coordinates":[-0.695354,53.764118],"type":"Point"}
}