{
  "type": "Feature",
  "properties": {
    "addr:full":"The Ferns, Woodcock Road, Flamborough Bridlington East Riding of Yorkshire YO15 1LJ",
    "addr:postcode":"yo15 1lj",
    "addr:street":"Woodcock Road",
    "iso:country":"GB",
    "sg:address":"The Ferns, Woodcock Road, Flamborough",
    "sg:city":"Bridlington",
    "sg:classifiers":[
        {
            "category":"Professional",
            "subcategory":"Engineering",
            "type":"Services"
        },
        {
            "category":"Real Estate",
            "subcategory":"Architect",
            "type":"Services"
        }
    ],
    "sg:phone":"+44 1262 851197",
    "sg:postcode":"YO15 1LJ",
    "sg:province":"East Riding of Yorkshire",
    "sg:tags":[
        "engineer"
    ],
    "wof:name":"Fanfare Engineering Ltd.",
    "wof:placetype":"venue"
},
  "geometry": {"coordinates":[-0.1269129962,54.1135368347],"type":"Point"}
}