{
  "type": "Feature",
  "properties": {
    "addr:full":"St Bernards Drive Bootle Merseyside L30 2QU",
    "addr:postcode":"l30 2qu",
    "addr:street":"St Bernards Drive",
    "iso:country":"GB",
    "sg:address":"St Bernards Drive",
    "sg:city":"Bootle",
    "sg:classifiers":[
        {
            "category":"Social Services",
            "subcategory":"Retirement Home",
            "type":"Services"
        }
    ],
    "sg:phone":"+44 151 924 8648",
    "sg:postcode":"L30 2QU",
    "sg:province":"Merseyside",
    "sg:tags":[
        "rest"
    ],
    "wof:name":"Cullen Grange",
    "wof:placetype":"venue"
},
  "geometry": {"coordinates":[-2.9847331047,53.4871864319],"type":"Point"}
}