{
  "type": "Feature",
  "properties": {
    "addr:full":"Bluebridge Industrial Estate, Fifth Avenue Halstead Essex CO9 2SZ",
    "addr:postcode":"co9 2sz",
    "addr:street":"Estate Fifth Avenue",
    "iso:country":"GB",
    "sg:address":"Bluebridge Industrial Estate, Fifth Avenue",
    "sg:city":"Halstead",
    "sg:classifiers":[
        {
            "category":"Professional",
            "subcategory":"Engineering",
            "type":"Services"
        }
    ],
    "sg:phone":"+44 1787 479393",
    "sg:postcode":"CO9 2SZ",
    "sg:province":"Essex",
    "sg:tags":[
        "engineer"
    ],
    "wof:name":"Headington & Co",
    "wof:placetype":"venue"
},
  "geometry": {"coordinates":[0.654198,51.939163],"type":"Point"}
}