{
  "type": "Feature",
  "properties": {
    "iso:country":"GB",
    "sg:address":"20 New Conduit Street",
    "sg:city":"King's Lynn",
    "sg:classifiers":[
        {
            "category":"Shopping",
            "subcategory":"Department Store",
            "type":"Retail Goods"
        }
    ],
    "sg:phone":"+44 1553 691186",
    "sg:postcode":"PE30 1DL",
    "sg:province":"Norfolk",
    "wof:name":"Weigh & Save (Wholesale)",
    "wof:placetype":"venue"
},
  "geometry": {"coordinates":[0.39662,52.753609],"type":"Point"}
}