{
  "type": "Feature",
  "properties": {
    "iso:country":"GB",
    "sg:address":"Kingsley Summercourt, Newquay",
    "sg:city":"Truro",
    "sg:classifiers":[
        {
            "category":"Building & Trades",
            "subcategory":"Construction",
            "type":"Services"
        }
    ],
    "sg:postcode":"TR8 5AG",
    "sg:province":"Cornwall",
    "sg:tags":[
        "joinery"
    ],
    "wof:name":"Top Notch Joinery (South Western) Ltd.",
    "wof:placetype":"venue"
},
  "geometry": {"coordinates":[-4.9720687866,50.3669052124],"type":"Point"}
}