{
  "type": "Feature",
  "properties": {
    "iso:country":"GB",
    "sg:address":"Sutton Cum Lound",
    "sg:city":"Retford",
    "sg:classifiers":[
        {
            "category":"Landmark",
            "subcategory":"Tourist Attraction",
            "type":"Public Place"
        }
    ],
    "sg:phone":"+44 1777 818099",
    "sg:postcode":"DN22 8SB",
    "sg:province":"Nottinghamshire",
    "sg:tags":[
        "interest"
    ],
    "wof:name":"Wetlands Waterfowl Reserve",
    "wof:placetype":"venue"
},
  "geometry": {"coordinates":[-0.962739,53.366295],"type":"Point"}
}