{
  "type": "Feature",
  "properties": {
    "addr:full":"59 Binley Road Coventry Warwickshire CV3 1HU",
    "addr:housenumber":"59",
    "addr:postcode":"cv3 1hu",
    "addr:street":"Binley Road",
    "iso:country":"GB",
    "sg:address":"59 Binley Road",
    "sg:city":"Coventry",
    "sg:classifiers":[
        {
            "category":"Government",
            "subcategory":"Post Office",
            "type":"Public Place"
        }
    ],
    "sg:phone":"+44 24 7645 8538",
    "sg:postcode":"CV3 1HU",
    "sg:province":"Warwickshire",
    "wof:name":"Stoke Green Sub Post Office",
    "wof:placetype":"venue"
},
  "geometry": {"coordinates":[-1.477784,52.406429],"type":"Point"}
}