{
  "type": "Feature",
  "properties": {
    "iso:country":"GB",
    "sg:address":"59 Charlton Rd, Keynsham",
    "sg:city":"Bristol",
    "sg:classifiers":[
        {
            "category":"Health Services",
            "subcategory":"Nursing And Care Facility",
            "type":"Services"
        }
    ],
    "sg:phone":"+44 117 986 1114",
    "sg:postcode":"BS31 2JQ",
    "sg:province":"City of Bristol",
    "sg:tags":[
        "home"
    ],
    "wof:name":"Hillsborough House Residential Home",
    "wof:placetype":"venue"
},
  "geometry": {"coordinates":[-2.507384,51.412697],"type":"Point"}
}