{
  "type": "Feature",
  "properties": {
    "addr:full":"Unit 22-24 Priory Meadow, Kings Walk Hastings East Sussex TN34 1PH",
    "addr:housenumber":"unit 22-24",
    "addr:postcode":"tn34 1ph",
    "addr:street":"Priory Meadow Kings Walk",
    "iso:country":"GB",
    "sg:address":"Unit 22-24 Priory Meadow, Kings Walk",
    "sg:city":"Hastings",
    "sg:classifiers":[
        {
            "category":"Shopping",
            "subcategory":"Clothing, Apparel, & Fashions",
            "type":"Retail Goods"
        }
    ],
    "sg:phone":"+44 1424 447401",
    "sg:postcode":"TN34 1PH",
    "sg:province":"East Sussex",
    "sg:tags":[
        "menswear"
    ],
    "wof:name":"Burton Menswear",
    "wof:placetype":"venue"
},
  "geometry": {"coordinates":[0.577363,50.861153],"type":"Point"}
}