{
  "type": "Feature",
  "properties": {
    "iso:country":"GB",
    "sg:address":"133 High Street",
    "sg:city":"Gosport",
    "sg:classifiers":[
        {
            "category":"Real Estate",
            "subcategory":"Real Estate Agent",
            "type":"Services"
        }
    ],
    "sg:phone":"+44 23 9258 0246",
    "sg:postcode":"PO12 1DZ",
    "sg:province":"Hampshire",
    "wof:name":"Fairhalls",
    "wof:placetype":"venue"
},
  "geometry": {"coordinates":[-1.124801,50.794758],"type":"Point"}
}