{
  "type": "Feature",
  "properties": {
    "addr:full":"133 High Street Gosport Hampshire PO12 1DZ",
    "addr:housenumber":"133",
    "addr:postcode":"po12 1dz",
    "addr:street":"High Street",
    "iso:country":"GB",
    "sg:address":"133 High Street",
    "sg:city":"Gosport",
    "sg:classifiers":[
        {
            "category":"Real Estate",
            "subcategory":"Real Estate Agent",
            "type":"Services"
        }
    ],
    "sg:phone":"+44 23 9258 0246",
    "sg:postcode":"PO12 1DZ",
    "sg:province":"Hampshire",
    "wof:name":"Fairhalls",
    "wof:placetype":"venue"
},
  "geometry": {"coordinates":[-1.124801,50.794758],"type":"Point"}
}