{
  "type": "Feature",
  "properties": {
    "addr:full":"302 Silbury Boulevard Milton Keynes Buckinghamshire MK9 2AE",
    "addr:housenumber":"302",
    "addr:postcode":"mk9 2ae",
    "addr:street":"Silbury Boulevard",
    "iso:country":"GB",
    "sg:address":"302 Silbury Boulevard",
    "sg:city":"Milton Keynes",
    "sg:classifiers":[
        {
            "category":"Home & Garden",
            "subcategory":"Furniture",
            "type":"Retail Goods"
        }
    ],
    "sg:phone":"+44 1908 241319",
    "sg:postcode":"MK9 2AE",
    "sg:province":"Buckinghamshire",
    "wof:name":"Traesko Pine",
    "wof:placetype":"venue"
},
  "geometry": {"coordinates":[-0.766623,52.03989],"type":"Point"}
}