{
  "type": "Feature",
  "properties": {
    "addr:full":"336 London Road Westcliff-on-sea Essex SS0 7JJ",
    "addr:housenumber":"336",
    "addr:postcode":"ss0 7jj",
    "addr:street":"London Road",
    "iso:country":"GB",
    "sg:address":"336 London Road",
    "sg:city":"Westcliff-on-sea",
    "sg:classifiers":[
        {
            "category":"Health Services",
            "subcategory":"Optometrist",
            "type":"Services"
        }
    ],
    "sg:phone":"+44 1702 346828",
    "sg:postcode":"SS0 7JJ",
    "sg:province":"Essex",
    "sg:tags":[
        "optician"
    ],
    "wof:name":"Harvey Rose & Sons",
    "wof:placetype":"venue"
},
  "geometry": {"coordinates":[0.696779,51.541485],"type":"Point"}
}