{
  "type": "Feature",
  "properties": {
    "iso:country":"GB",
    "sg:address":"56 Berry Street",
    "sg:city":"Liverpool",
    "sg:classifiers":[
        {
            "category":"Personal",
            "subcategory":"Beauty Salon",
            "type":"Services"
        }
    ],
    "sg:phone":"+44 151 709 5396",
    "sg:postcode":"L1 4JQ",
    "sg:province":"Merseyside",
    "sg:tags":[
        "unisex",
        "hairdresser"
    ],
    "wof:name":"Hair Saloon",
    "wof:placetype":"venue"
},
  "geometry": {"coordinates":[-2.976326,53.400604],"type":"Point"}
}