{
  "type": "Feature",
  "properties": {
    "iso:country":"GB",
    "sg:address":"186 Water Street",
    "sg:city":"Accrington",
    "sg:classifiers":[
        {
            "category":"Shopping",
            "subcategory":"Department Store",
            "type":"Retail Goods"
        }
    ],
    "sg:postcode":"BB5 6QU",
    "sg:province":"Lancashire",
    "wof:name":"Fiaz Bros",
    "wof:placetype":"venue"
},
  "geometry": {"coordinates":[-2.3553891182,53.7568664551],"type":"Point"}
}