{
  "type": "Feature",
  "properties": {
    "addr:full":"Churchill Post Office, Front Street Winscombe Somerset BS25 5NB",
    "addr:postcode":"bs25 5nb",
    "addr:street":"Front Street",
    "iso:country":"GB",
    "sg:address":"Churchill Post Office, Front Street",
    "sg:city":"Winscombe",
    "sg:classifiers":[
        {
            "category":"Government",
            "subcategory":"Post Office",
            "type":"Public Place"
        }
    ],
    "sg:phone":"+44 1934 852332",
    "sg:postcode":"BS25 5NB",
    "sg:province":"Somerset",
    "wof:name":"Churchill Post Office & Stores",
    "wof:placetype":"venue"
},
  "geometry": {"coordinates":[-2.8313291073,51.3131713867],"type":"Point"}
}