{
  "type": "Feature",
  "properties": {
    "iso:country":"GB",
    "sg:address":"Mckerrell Road",
    "sg:city":"London",
    "sg:classifiers":[
        {
            "category":"Community Center",
            "type":"Public Place"
        },
        {
            "category":"Government",
            "subcategory":"Office",
            "type":"Public Place"
        }
    ],
    "sg:phone":"+44 20 7732 3516",
    "sg:postcode":"SE15 5HX",
    "sg:province":"Greater London",
    "sg:tags":[
        "recreation",
        "local",
        "leisure",
        "centre"
    ],
    "wof:name":"Peckham Leisure Centre",
    "wof:placetype":"venue"
},
  "geometry": {"coordinates":[-0.066499,51.47271],"type":"Point"}
}