{
  "type": "Feature",
  "properties": {
    "addr:full":"Lysander Road, Cribbs Causeway, Westbury On Trym Bristol City of Bristol BS10 7UB",
    "addr:postcode":"bs10 7ub",
    "addr:street":"Lysander Road Cribbs Causeway",
    "iso:country":"GB",
    "sg:address":"Lysander Road, Cribbs Causeway, Westbury On Trym",
    "sg:city":"Bristol",
    "sg:classifiers":[
        {
            "category":"Personal",
            "type":"Services"
        }
    ],
    "sg:phone":"+44 117 950 0155",
    "sg:postcode":"BS10 7UB",
    "sg:province":"City of Bristol",
    "sg:tags":[
        "delivery"
    ],
    "wof:name":"Business Post Ltd.",
    "wof:placetype":"venue"
},
  "geometry": {"coordinates":[-2.603222,51.526237],"type":"Point"}
}