{
  "type": "Feature",
  "properties": {
    "addr:full":"Haugh Lane Blaydon-on-tyne Tyne and Wear NE21 4SA",
    "addr:postcode":"ne21 4sa",
    "addr:street":"Haugh Lane",
    "iso:country":"GB",
    "sg:address":"Haugh Lane",
    "sg:city":"Blaydon-on-tyne",
    "sg:classifiers":[
        {
            "category":"Professional",
            "subcategory":"Engineering",
            "type":"Services"
        }
    ],
    "sg:phone":"+44 191 414 2015",
    "sg:postcode":"NE21 4SA",
    "sg:province":"Tyne and Wear",
    "sg:tags":[
        "hydraulic",
        "engineer"
    ],
    "wof:name":"Tipping Gears & Engineering Ltd.",
    "wof:placetype":"venue"
},
  "geometry": {"coordinates":[-1.7498799562,54.9780921936],"type":"Point"}
}