{
  "type": "Feature",
  "properties": {
    "addr:full":"16 North Street Ashford Kent TN24 8JR",
    "addr:housenumber":"16",
    "addr:postcode":"tn24 8jr",
    "addr:street":"North Street",
    "iso:country":"GB",
    "sg:address":"16 North Street",
    "sg:city":"Ashford",
    "sg:classifiers":[
        {
            "category":"Professional",
            "subcategory":"Art Services",
            "type":"Services"
        }
    ],
    "sg:phone":"+44 1233 637629",
    "sg:postcode":"TN24 8JR",
    "sg:province":"Kent",
    "sg:tags":[
        "photographer"
    ],
    "wof:name":"Coliseum",
    "wof:placetype":"venue"
},
  "geometry": {"coordinates":[0.8733789921,51.1494941711],"type":"Point"}
}