{
  "type": "Feature",
  "properties": {
    "addr:full":"Dickson House, Dickson St Dunfermline Fife KY12 7SL",
    "addr:postcode":"ky12 7sl",
    "addr:street":"Dickson St",
    "iso:country":"GB",
    "sg:address":"Dickson House, Dickson St",
    "sg:city":"Dunfermline",
    "sg:classifiers":[
        {
            "category":"Organizations",
            "subcategory":"Non-profit Organization",
            "type":"Services"
        }
    ],
    "sg:phone":"+44 1383 620822",
    "sg:postcode":"KY12 7SL",
    "sg:province":"Fife",
    "sg:tags":[
        "organisation",
        "voluntary",
        "charity"
    ],
    "wof:name":"The Asthma Research Trust",
    "wof:placetype":"venue"
},
  "geometry": {"coordinates":[-3.460363,56.062157],"type":"Point"}
}