{
  "type": "Feature",
  "properties": {
    "addr:full":"3 Malthouse Cotts, 31 Byfield Road, Chipping Warden Banbury Northamptonshire OX17 1LE",
    "addr:housenumber":"3;31",
    "addr:postcode":"ox17 1le",
    "addr:street":"Malthouse Cotts;Byfield Road",
    "iso:country":"GB",
    "sg:address":"3 Malthouse Cotts, 31 Byfield Road, Chipping Warden",
    "sg:city":"Banbury",
    "sg:classifiers":[
        {
            "category":"Professional",
            "subcategory":"Computer Services",
            "type":"Services"
        }
    ],
    "sg:phone":"+44 1295 660682",
    "sg:postcode":"OX17 1LE",
    "sg:province":"Northamptonshire",
    "sg:tags":[
        "consultant"
    ],
    "wof:name":"Cing Technologies Ltd.",
    "wof:placetype":"venue"
},
  "geometry": {"coordinates":[-1.275915,52.134903],"type":"Point"}
}