{
  "type": "Feature",
  "properties": {
    "addr:full":"24 Truro Rd St. Austell Cornwall PL25 5JF",
    "addr:housenumber":"24",
    "addr:postcode":"pl25 5jf",
    "addr:street":"Truro Rd",
    "iso:country":"GB",
    "sg:address":"24 Truro Rd",
    "sg:city":"St. Austell",
    "sg:classifiers":[
        {
            "category":"Social Services",
            "subcategory":"Retirement Home",
            "type":"Services"
        }
    ],
    "sg:phone":"+44 1726 72619",
    "sg:postcode":"PL25 5JF",
    "sg:province":"Cornwall",
    "sg:tags":[
        "residential",
        "care"
    ],
    "wof:name":"Belfield Rest Home",
    "wof:placetype":"venue"
},
  "geometry": {"coordinates":[-4.7972950935,50.3387107849],"type":"Point"}
}