{
  "type": "Feature",
  "properties": {
    "iso:country":"GB",
    "sg:address":"1 Augusta Street",
    "sg:city":"Birmingham",
    "sg:classifiers":[
        {
            "category":"Shopping",
            "subcategory":"Jewelry",
            "type":"Retail Goods"
        }
    ],
    "sg:phone":"+44 121 236 6858",
    "sg:postcode":"B18 6JA",
    "sg:province":"West Midlands",
    "sg:tags":[
        "gold",
        "silversmith"
    ],
    "wof:name":"Casting House Ltd.",
    "wof:placetype":"venue"
},
  "geometry": {"coordinates":[-1.911255,52.488228],"type":"Point"}
}