{
  "type": "Feature",
  "properties": {
    "addr:full":"Cheriton, Garfield Avenue, Litchard Bridgend Bridgend CF31 1QB",
    "addr:postcode":"cf31 1qb",
    "addr:street":"Garfield Avenue Litchard",
    "iso:country":"GB",
    "sg:address":"Cheriton, Garfield Avenue, Litchard",
    "sg:city":"Bridgend",
    "sg:classifiers":[
        {
            "category":"Home & Garden",
            "subcategory":"Home Furnishings",
            "type":"Retail Goods"
        },
        {
            "category":"Communications",
            "type":"Services"
        }
    ],
    "sg:phone":"+44 1656 653409",
    "sg:postcode":"CF31 1QB",
    "sg:province":"Bridgend",
    "sg:tags":[
        "planner",
        "tv",
        "furnishers",
        "video",
        "radio",
        "kitchen"
    ],
    "wof:name":"Owen W Rayment",
    "wof:placetype":"venue"
},
  "geometry": {"coordinates":[-3.5782630444,51.5088348389],"type":"Point"}
}