{
  "type": "Feature",
  "properties": {
    "addr:full":"Ranger House, Walnut Tree Close Guildford Surrey GU1 4US",
    "addr:postcode":"gu1 4us",
    "addr:street":"Walnut Tree Close",
    "iso:country":"GB",
    "sg:address":"Ranger House, Walnut Tree Close",
    "sg:city":"Guildford",
    "sg:classifiers":[
        {
            "category":"Mining & Drilling",
            "type":"Manufacturing & Wholesale Goods"
        }
    ],
    "sg:phone":"+44 1483 401401",
    "sg:postcode":"GU1 4US",
    "sg:province":"Surrey",
    "sg:tags":[
        "oil",
        "petroleum"
    ],
    "wof:name":"Ranger Oil (U K ) Ltd.",
    "wof:placetype":"venue"
},
  "geometry": {"coordinates":[-0.579395,51.236385],"type":"Point"}
}