{
  "type": "Feature",
  "properties": {
    "addr:full":"14 Blackburn Road Bathgate West Lothian EH48 2EY",
    "addr:housenumber":"14",
    "addr:postcode":"eh48 2ey",
    "addr:street":"Blackburn Road Bathgate",
    "iso:country":"GB",
    "sg:address":"14 Blackburn Road",
    "sg:city":"Bathgate",
    "sg:classifiers":[
        {
            "category":"Home & Garden",
            "subcategory":"Furniture",
            "type":"Retail Goods"
        }
    ],
    "sg:phone":"+44 1506 634922",
    "sg:postcode":"EH48 2EY",
    "sg:province":"West Lothian",
    "wof:name":"Leith Pine Factory",
    "wof:placetype":"venue"
},
  "geometry": {"coordinates":[-3.622259,55.893085],"type":"Point"}
}