{
  "type": "Feature",
  "properties": {
    "addr:full":"54 Eden Street Kingston-upon-thames Greater London KT1 1EE",
    "addr:housenumber":"54",
    "addr:postcode":"kt1 1ee",
    "addr:street":"Eden Street",
    "iso:country":"GB",
    "sg:address":"54 Eden Street",
    "sg:city":"Kingston-upon-thames",
    "sg:classifiers":[
        {
            "category":"Cafe",
            "type":"Food & Drink"
        }
    ],
    "sg:phone":"+44 20 8546 6795",
    "sg:postcode":"KT1 1EE",
    "sg:province":"Greater London",
    "sg:tags":[
        "tea",
        "room"
    ],
    "wof:name":"Eden Cafe",
    "wof:placetype":"venue"
},
  "geometry": {"coordinates":[-0.3031849861,51.4091148376],"type":"Point"}
}