{
  "type": "Feature",
  "properties": {
    "addr:full":"22 Whittle Place, South Newmoor Industrial Estate Irvine East Ayrshire KA11 4HR",
    "addr:housenumber":"22",
    "addr:postcode":"ka11 4hr",
    "addr:street":"Whittle Place South Newmoor Industrial Estate",
    "iso:country":"GB",
    "sg:address":"22 Whittle Place, South Newmoor Industrial Estate",
    "sg:city":"Irvine",
    "sg:classifiers":[
        {
            "category":"Autos & Motor Vehicles",
            "subcategory":"Auto Supplies",
            "type":"Retail Goods"
        }
    ],
    "sg:phone":"+44 1294 211497",
    "sg:postcode":"KA11 4HR",
    "sg:province":"East Ayrshire",
    "sg:tags":[
        "windscreen"
    ],
    "wof:name":"Autoglass",
    "wof:placetype":"venue"
},
  "geometry": {"coordinates":[-4.6426639557,55.6117553711],"type":"Point"}
}