{
  "type": "Feature",
  "properties": {
    "iso:country":"GB",
    "sg:address":"West Way",
    "sg:city":"Cirencester",
    "sg:classifiers":[
        {
            "category":"Retail",
            "subcategory":"Laundry & Dry Cleaning",
            "type":"Services"
        }
    ],
    "sg:phone":"+44 1285 652315",
    "sg:postcode":"GL7 1JA",
    "sg:province":"Gloucestershire",
    "sg:tags":[
        "launderette"
    ],
    "wof:name":"Panda Laundrette",
    "wof:placetype":"venue"
},
  "geometry": {"coordinates":[-1.966209,51.715736],"type":"Point"}
}