{
  "type": "Feature",
  "properties": {
    "iso:country":"GB",
    "sg:address":"Colcot Road",
    "sg:city":"Barry",
    "sg:classifiers":[
        {
            "category":"Arena",
            "subcategory":"Sports Club",
            "type":"Entertainment"
        },
        {
            "category":"Government",
            "subcategory":"Office",
            "type":"Public Place"
        }
    ],
    "sg:phone":"+44 1446 735182",
    "sg:postcode":"CF62 8UJ",
    "sg:province":"The Vale of Glamorgan",
    "sg:tags":[
        "local"
    ],
    "wof:name":"Barry Sports Centre",
    "wof:placetype":"venue"
},
  "geometry": {"coordinates":[-3.283894,51.417751],"type":"Point"}
}