{
  "type": "Feature",
  "properties": {
    "addr:full":"7 Pydar Mews Truro Cornwall TR1 2UX",
    "addr:housenumber":"7",
    "addr:postcode":"tr1 2ux",
    "addr:street":"Pydar Mews",
    "iso:country":"GB",
    "sg:address":"7 Pydar Mews",
    "sg:city":"Truro",
    "sg:classifiers":[
        {
            "category":"Shopping",
            "subcategory":"Clothing, Apparel, & Fashions",
            "type":"Retail Goods"
        }
    ],
    "sg:phone":"+44 1872 222547",
    "sg:postcode":"TR1 2UX",
    "sg:province":"Cornwall",
    "sg:tags":[
        "shop"
    ],
    "wof:name":"Falcoln Leather Wear",
    "wof:placetype":"venue"
},
  "geometry": {"coordinates":[-5.053194046,50.2642097473],"type":"Point"}
}