{
  "type": "Feature",
  "properties": {
    "addr:full":"5 Market St Darwen Lancashire BB3 1AZ",
    "addr:housenumber":"5",
    "addr:postcode":"bb3 1az",
    "addr:street":"Market St",
    "iso:country":"GB",
    "sg:address":"5 Market St",
    "sg:city":"Darwen",
    "sg:classifiers":[
        {
            "category":"Shopping",
            "subcategory":"Gifts & Souvenirs",
            "type":"Retail Goods"
        }
    ],
    "sg:phone":"+44 1254 761048",
    "sg:postcode":"BB3 1AZ",
    "sg:province":"Lancashire",
    "sg:tags":[
        "poster",
        "card"
    ],
    "wof:name":"Cards",
    "wof:placetype":"venue"
},
  "geometry": {"coordinates":[-2.4683709145,53.6964836121],"type":"Point"}
}