{
  "type": "Feature",
  "properties": {
    "addr:full":"16 Pine Close Loughborough Leicestershire LE11 2NZ",
    "addr:housenumber":"16",
    "addr:postcode":"le11 2nz",
    "addr:street":"Pine Close",
    "iso:country":"GB",
    "sg:address":"16 Pine Close",
    "sg:city":"Loughborough",
    "sg:classifiers":[
        {
            "category":"Taxi",
            "type":"Transportation"
        },
        {
            "category":"Military Area",
            "subcategory":"Air Force Base",
            "type":"Public Place"
        }
    ],
    "sg:phone":"+44 1509 211647",
    "sg:postcode":"LE11 2NZ",
    "sg:province":"Leicestershire",
    "sg:tags":[
        "hire",
        "private"
    ],
    "wof:name":"Colin's Taxis",
    "wof:placetype":"venue"
},
  "geometry": {"coordinates":[-1.2088259459,52.7485656738],"type":"Point"}
}