{
  "type": "Feature",
  "properties": {
    "addr:full":"151 The Street, Boughton Under Blean Faversham Kent ME13 9BH",
    "addr:housenumber":"151",
    "addr:postcode":"me13 9bh",
    "addr:street":"The Street",
    "iso:country":"GB",
    "sg:address":"151 The Street, Boughton Under Blean",
    "sg:city":"Faversham",
    "sg:classifiers":[
        {
            "category":"Banks & Credit Unions",
            "subcategory":"Financial Services",
            "type":"Services"
        }
    ],
    "sg:postcode":"ME13 9BH",
    "sg:province":"Kent",
    "sg:tags":[
        "consultant"
    ],
    "wof:name":"Taylors Financial Planning Ltd.",
    "wof:placetype":"venue"
},
  "geometry": {"coordinates":[0.9513890147,51.2961921692],"type":"Point"}
}