{
  "type": "Feature",
  "properties": {
    "addr:full":"The Concourse Skelmersdale Lancashire WN8 6LN",
    "addr:postcode":"wn8 6ln",
    "iso:country":"GB",
    "sg:address":"The Concourse",
    "sg:city":"Skelmersdale",
    "sg:classifiers":[
        {
            "category":"Professional",
            "subcategory":"Computer Services",
            "type":"Services"
        }
    ],
    "sg:phone":"+44 1695 725665",
    "sg:postcode":"WN8 6LN",
    "sg:province":"Lancashire",
    "sg:tags":[
        "information"
    ],
    "wof:name":"Skelmersdale Youth Information Shop",
    "wof:placetype":"venue"
},
  "geometry": {"coordinates":[-2.7757840157,53.5494041443],"type":"Point"}
}