{
  "type": "Feature",
  "properties": {
    "iso:country":"GB",
    "sg:address":"7 Trinity Avenue",
    "sg:city":"Sale",
    "sg:classifiers":[
        {
            "category":"Utilities",
            "subcategory":"Mobile Phone",
            "type":"Services"
        },
        {
            "category":"Home & Garden",
            "subcategory":"Kitchen Supply",
            "type":"Retail Goods"
        }
    ],
    "sg:phone":"+44 161 973 1547",
    "sg:postcode":"M33 3ED",
    "sg:province":"Cheshire",
    "sg:tags":[
        "equipment",
        "bar",
        "accessory"
    ],
    "wof:name":"B W Repair & Maintenance",
    "wof:placetype":"venue"
},
  "geometry": {"coordinates":[-2.3073310852,53.4203338623],"type":"Point"}
}