{
  "type": "Feature",
  "properties": {
    "addr:full":"Redhill Farm Yard, Redhill Alcester Warwickshire B49 6NQ",
    "addr:postcode":"b49 6nq",
    "iso:country":"GB",
    "sg:address":"Redhill Farm Yard, Redhill",
    "sg:city":"Alcester",
    "sg:classifiers":[
        {
            "category":"Shopping",
            "subcategory":"Stationery & Office Supplies",
            "type":"Retail Goods"
        }
    ],
    "sg:phone":"+44 1789 762255",
    "sg:postcode":"B49 6NQ",
    "sg:province":"Warwickshire",
    "sg:tags":[
        "equipment"
    ],
    "wof:name":"Gordon Smith Office Equipment",
    "wof:placetype":"venue"
},
  "geometry": {"coordinates":[-1.8609919548,52.2217979431],"type":"Point"}
}