{
  "type": "Feature",
  "properties": {
    "addr:full":"21 Laurier Road London Greater London NW5 1SD",
    "addr:housenumber":"21",
    "addr:postcode":"nw5 1sd",
    "addr:street":"Laurier Road",
    "iso:country":"GB",
    "sg:address":"21 Laurier Road",
    "sg:city":"London",
    "sg:classifiers":[
        {
            "category":"Social Services",
            "subcategory":"Job Training",
            "type":"Services"
        }
    ],
    "sg:phone":"+44 20 7267 1800",
    "sg:postcode":"NW5 1SD",
    "sg:province":"Greater London",
    "sg:tags":[
        "translator",
        "interpreter"
    ],
    "wof:name":"Linguists for Business Ltd.",
    "wof:placetype":"venue"
},
  "geometry": {"coordinates":[-0.144709006,51.559387207],"type":"Point"}
}