{
  "type": "Feature",
  "properties": {
    "addr:full":"20c Hanworth Rd Hounslow Greater London TW3 1UA",
    "addr:housenumber":"20c",
    "addr:postcode":"tw3 1ua",
    "addr:street":"Hanworth Rd",
    "iso:country":"GB",
    "sg:address":"20c Hanworth Rd",
    "sg:city":"Hounslow",
    "sg:classifiers":[
        {
            "category":"Autos & Motor Vehicles",
            "subcategory":"Automobile Sales",
            "type":"Retail Goods"
        }
    ],
    "sg:phone":"+44 20 8577 1505",
    "sg:postcode":"TW3 1UA",
    "sg:province":"Greater London",
    "sg:tags":[
        "car",
        "specialist",
        "sales",
        "classic"
    ],
    "wof:name":"Heathrow Sportscars",
    "wof:placetype":"venue"
},
  "geometry": {"coordinates":[-0.357687,51.469341],"type":"Point"}
}