{
  "type": "Feature",
  "properties": {
    "iso:country":"GB",
    "sg:address":"5th Floor, 29-30 Warwick Street",
    "sg:city":"London",
    "sg:classifiers":[
        {
            "category":"Professional",
            "type":"Services"
        }
    ],
    "sg:postcode":"W1B 5NH",
    "sg:province":"Greater London",
    "sg:tags":[
        "directory",
        "pub"
    ],
    "wof:name":"Property Trade Directory Ltd.",
    "wof:placetype":"venue"
},
  "geometry": {"coordinates":[-0.138053,51.510799],"type":"Point"}
}