{
  "type": "Feature",
  "properties": {
    "iso:country":"GB",
    "sg:address":"11 Faircross Parade, Longbridge Road",
    "sg:city":"Barking",
    "sg:classifiers":[
        {
            "category":"Shopping",
            "subcategory":"Pharmacy",
            "type":"Retail Goods"
        }
    ],
    "sg:phone":"+44 20 8594 2686",
    "sg:postcode":"IG11 8UN",
    "sg:province":"Essex",
    "sg:tags":[
        "pharmacist",
        "dispensing",
        "chemist"
    ],
    "wof:name":"Britannia Pharmacy",
    "wof:placetype":"venue"
},
  "geometry": {"coordinates":[0.083659,51.541523],"type":"Point"}
}