{
  "type": "Feature",
  "properties": {
    "iso:country":"GB",
    "sg:address":"248 County Road, Walton",
    "sg:city":"Liverpool",
    "sg:classifiers":[
        {
            "category":"Home & Garden",
            "subcategory":"Home Furnishings",
            "type":"Retail Goods"
        }
    ],
    "sg:postcode":"L4 5PW",
    "sg:province":"Merseyside",
    "sg:tags":[
        "awning",
        "canopy",
        "blinds"
    ],
    "wof:name":"County Blinds",
    "wof:placetype":"venue"
},
  "geometry": {"coordinates":[-2.967816,53.44516],"type":"Point"}
}