{
  "type": "Feature",
  "properties": {
    "addr:full":"St Martins Barn, St Martins Road Littlehampton West Sussex BN17 6BS",
    "addr:postcode":"bn17 6bs",
    "addr:street":"St Martins Road",
    "iso:country":"GB",
    "sg:address":"St Martins Barn, St Martins Road",
    "sg:city":"Littlehampton",
    "sg:classifiers":[
        {
            "category":"Autos & Motor Vehicles",
            "subcategory":"Auto Supplies",
            "type":"Retail Goods"
        }
    ],
    "sg:phone":"+44 1903 717480",
    "sg:postcode":"BN17 6BS",
    "sg:province":"West Sussex",
    "sg:tags":[
        "tyre"
    ],
    "wof:name":"Littlehampton Tyre & Exhaust Service",
    "wof:placetype":"venue"
},
  "geometry": {"coordinates":[-0.538959,50.82103],"type":"Point"}
}