{
  "type": "Feature",
  "properties": {
    "addr:full":"Pullastone, Kingsthorne Hereford Herefordshire HR2 8AQ",
    "addr:postcode":"hr2 8aq",
    "iso:country":"GB",
    "sg:address":"Pullastone, Kingsthorne",
    "sg:city":"Hereford",
    "sg:classifiers":[
        {
            "category":"Professional",
            "subcategory":"Management & Consulting",
            "type":"Services"
        },
        {
            "category":"Professional",
            "subcategory":"Research",
            "type":"Services"
        }
    ],
    "sg:phone":"+44 1432 341341",
    "sg:postcode":"HR2 8AQ",
    "sg:province":"Herefordshire",
    "sg:tags":[
        "consultant",
        "business",
        "market"
    ],
    "wof:name":"Durdle Davies Business Research",
    "wof:placetype":"venue"
},
  "geometry": {"coordinates":[-2.734999,51.985374],"type":"Point"}
}