{
  "type": "Feature",
  "properties": {
    "addr:full":"The Chesnuts, Station Rd Tonbridge Kent TN12 0PZ",
    "addr:postcode":"tn12 0pz",
    "addr:street":"Station Rd",
    "iso:country":"GB",
    "sg:address":"The Chesnuts, Station Rd",
    "sg:city":"Tonbridge",
    "sg:classifiers":[
        {
            "category":"Retail",
            "subcategory":"Repair Shop",
            "type":"Services"
        }
    ],
    "sg:phone":"+44 1580 893011",
    "sg:postcode":"TN12 0PZ",
    "sg:province":"Kent",
    "sg:tags":[
        "maintenance"
    ],
    "wof:name":"Boughton Group The",
    "wof:placetype":"venue"
},
  "geometry": {"coordinates":[0.552241981,51.1640357971],"type":"Point"}
}