{
  "type": "Feature",
  "properties": {
    "addr:full":", Melmerby Penrith Cumbria CA10 1HE",
    "addr:postcode":"ca10 1he",
    "iso:country":"GB",
    "sg:address":", Melmerby",
    "sg:city":"Penrith",
    "sg:classifiers":[
        {
            "category":"Recreation",
            "subcategory":"Campground",
            "type":"Entertainment"
        }
    ],
    "sg:phone":"+44 1768 881311",
    "sg:postcode":"CA10 1HE",
    "sg:province":"Cumbria",
    "sg:tags":[
        "caravan",
        "park"
    ],
    "wof:name":"Melmerby Caravan Park",
    "wof:placetype":"venue"
},
  "geometry": {"coordinates":[-2.600285,54.729557],"type":"Point"}
}