{
  "type": "Feature",
  "properties": {
    "addr:full":"123 Flaxley Road Birmingham West Midlands B33 9HQ",
    "addr:housenumber":"123",
    "addr:postcode":"b33 9hq",
    "addr:street":"Flaxley Road",
    "iso:country":"GB",
    "sg:address":"123 Flaxley Road",
    "sg:city":"Birmingham",
    "sg:classifiers":[
        {
            "category":"Building & Trades",
            "subcategory":"Locksmith",
            "type":"Services"
        },
        {
            "category":"Retail",
            "subcategory":"Storage",
            "type":"Services"
        }
    ],
    "sg:phone":"+44 121 783 0442",
    "sg:postcode":"B33 9HQ",
    "sg:province":"West Midlands",
    "sg:tags":[
        "vault",
        "safe"
    ],
    "wof:name":"C & T Locksmiths",
    "wof:placetype":"venue"
},
  "geometry": {"coordinates":[-1.806888,52.487488],"type":"Point"}
}