{
  "type": "Feature",
  "properties": {
    "addr:full":"12-14 Broadmead Bristol City of Bristol BS1 3HH",
    "addr:housenumber":"12-14",
    "addr:postcode":"bs1 3hh",
    "addr:street":"Broadmead",
    "iso:country":"GB",
    "sg:address":"12-14 Broadmead",
    "sg:city":"Bristol",
    "sg:classifiers":[
        {
            "category":"Banks & Credit Unions",
            "subcategory":"Financial Services",
            "type":"Services"
        }
    ],
    "sg:phone":"+44 117 929 7626",
    "sg:postcode":"BS1 3HH",
    "sg:province":"City of Bristol",
    "sg:tags":[
        "building",
        "society"
    ],
    "wof:name":"Britannia Building Society",
    "wof:placetype":"venue"
},
  "geometry": {"coordinates":[-2.587343,51.458294],"type":"Point"}
}