{
  "type": "Feature",
  "properties": {
    "iso:country":"GB",
    "sg:address":"Unit 3, Adam House",
    "sg:city":"Worcester",
    "sg:classifiers":[
        {
            "category":"Manufacturing",
            "subcategory":"Wood Products",
            "type":"Manufacturing & Wholesale Goods"
        }
    ],
    "sg:phone":"+44 1905 773837",
    "sg:postcode":"WR1 3EX",
    "sg:province":"Worcestershire",
    "sg:tags":[
        "packaging",
        "crate",
        "pallets"
    ],
    "wof:name":"T & S Packaging",
    "wof:placetype":"venue"
},
  "geometry": {"coordinates":[-2.222274,52.191067],"type":"Point"}
}