{
  "type": "Feature",
  "properties": {
    "iso:country":"GB",
    "sg:address":"Pencoyd Granary, Pencoyd",
    "sg:city":"Hereford",
    "sg:classifiers":[
        {
            "category":"Building & Trades",
            "subcategory":"Construction",
            "type":"Services"
        }
    ],
    "sg:postcode":"HR2 8JY",
    "sg:province":"Herefordshire",
    "sg:tags":[
        "heating",
        "contractor"
    ],
    "wof:name":"M G Lewis Plumbing & Heating",
    "wof:placetype":"venue"
},
  "geometry": {"coordinates":[-2.699743,51.931149],"type":"Point"}
}