{
  "type": "Feature",
  "properties": {
    "iso:country":"GB",
    "sg:address":"160c Finchley Rd",
    "sg:city":"Hampstead",
    "sg:classifiers":[
        {
            "category":"Personal",
            "subcategory":"Barber",
            "type":"Services"
        }
    ],
    "sg:phone":"+44 20 7435 5020",
    "sg:postcode":"NW3 5HD",
    "sg:province":"Greater London",
    "sg:tags":[
        "men's",
        "hairdresser"
    ],
    "wof:name":"Michael",
    "wof:placetype":"venue"
},
  "geometry": {"coordinates":[-0.181312,51.549267],"type":"Point"}
}