{
  "type": "Feature",
  "properties": {
    "addr:full":"64 High Street Wells Somerset BA5 2AJ",
    "addr:housenumber":"64",
    "addr:postcode":"ba5 2aj",
    "addr:street":"High Street",
    "iso:country":"GB",
    "sg:address":"64 High Street",
    "sg:city":"Wells",
    "sg:classifiers":[
        {
            "category":"Shopping",
            "subcategory":"Comic Books",
            "type":"Retail Goods"
        }
    ],
    "sg:postcode":"BA5 2AJ",
    "sg:province":"Somerset",
    "sg:tags":[
        "jeweller"
    ],
    "wof:name":"Gallery of Wells & Cheddar",
    "wof:placetype":"venue"
},
  "geometry": {"coordinates":[-2.6481220722,51.2083015442],"type":"Point"}
}