{
  "type": "Feature",
  "properties": {
    "iso:country":"GB",
    "sg:address":"Holders Yard, 52b College Street",
    "sg:city":"Petersfield",
    "sg:classifiers":[
        {
            "category":"Building & Trades",
            "subcategory":"Construction",
            "type":"Services"
        }
    ],
    "sg:phone":"+44 1730 264586",
    "sg:postcode":"GU31 4AF",
    "sg:province":"Hampshire",
    "sg:tags":[
        "joiner",
        "carpenter"
    ],
    "wof:name":"R A Holden",
    "wof:placetype":"venue"
},
  "geometry": {"coordinates":[-0.9339,51.00639],"type":"Point"}
}