{
  "type": "Feature",
  "properties": {
    "addr:full":"Hereford Road Shrewsbury Shropshire SY3 9LB",
    "addr:postcode":"sy3 9lb",
    "addr:street":"Hereford Road",
    "iso:country":"GB",
    "sg:address":"Hereford Road",
    "sg:city":"Shrewsbury",
    "sg:classifiers":[
        {
            "category":"Travel",
            "subcategory":"Hotels & Motels",
            "type":"Entertainment"
        }
    ],
    "sg:phone":"+44 1743 355559",
    "sg:postcode":"SY3 9LB",
    "sg:province":"Shropshire",
    "sg:tags":[
        "house",
        "guest"
    ],
    "wof:name":"Moneybrook House",
    "wof:placetype":"venue"
},
  "geometry": {"coordinates":[-2.755387,52.688923],"type":"Point"}
}