{
  "type": "Feature",
  "properties": {
    "addr:full":"Beaumaris Court, Keele Road Newcastle Staffordshire ST5 2JW",
    "addr:postcode":"st5 2jw",
    "addr:street":"Beaumaris Court Keele Road",
    "iso:country":"GB",
    "sg:address":"Beaumaris Court, Keele Road",
    "sg:city":"Newcastle",
    "sg:classifiers":[
        {
            "category":"Organizations",
            "subcategory":"Community Association",
            "type":"Services"
        }
    ],
    "sg:phone":"+44 1782 633899",
    "sg:postcode":"ST5 2JW",
    "sg:province":"Staffordshire",
    "sg:tags":[
        "society",
        "housing"
    ],
    "wof:name":"Anchor Housing Trust",
    "wof:placetype":"venue"
},
  "geometry": {"coordinates":[-2.2441260815,53.0079879761],"type":"Point"}
}