{
  "type": "Feature",
  "properties": {
    "iso:country":"GB",
    "sg:address":"315 Lincoln Road",
    "sg:city":"Peterborough",
    "sg:classifiers":[
        {
            "category":"Communications",
            "type":"Services"
        }
    ],
    "sg:phone":"+44 1733 557677",
    "sg:postcode":"PE1 2PH",
    "sg:province":"Cambridgeshire",
    "sg:tags":[
        "telecommunication"
    ],
    "wof:name":"Milfield Mobile Communications",
    "wof:placetype":"venue"
},
  "geometry": {"coordinates":[-0.246416,52.587364],"type":"Point"}
}