{
  "type": "Feature",
  "properties": {
    "addr:full":"91 Forefield Lane, Great Crosby Liverpool Merseyside L23 9TQ",
    "addr:housenumber":"91",
    "addr:postcode":"l23 9tq",
    "addr:street":"Forefield Lane",
    "iso:country":"GB",
    "sg:address":"91 Forefield Lane, Great Crosby",
    "sg:city":"Liverpool",
    "sg:classifiers":[
        {
            "category":"Home & Garden",
            "subcategory":"Household Appliances",
            "type":"Retail Goods"
        }
    ],
    "sg:postcode":"L23 9TQ",
    "sg:province":"Merseyside",
    "sg:tags":[
        "gas"
    ],
    "wof:name":"Bellman Heating",
    "wof:placetype":"venue"
},
  "geometry": {"coordinates":[-3.010255,53.490601],"type":"Point"}
}