{
  "type": "Feature",
  "properties": {
    "iso:country":"GB",
    "sg:address":"1 Cambridge Road",
    "sg:city":"Brixham",
    "sg:classifiers":[
        {
            "category":"Government",
            "subcategory":"Post Office",
            "type":"Public Place"
        }
    ],
    "sg:phone":"+44 1803 852808",
    "sg:postcode":"TQ5 8JW",
    "sg:province":"Devon",
    "wof:name":"Cambridge Stores",
    "wof:placetype":"venue"
},
  "geometry": {"coordinates":[-3.528036,50.394321],"type":"Point"}
}