{
  "type": "Feature",
  "properties": {
    "addr:full":"33 Woodside View, Holmesfield Dronfield Derbyshire S18 7WX",
    "addr:housenumber":"33",
    "addr:postcode":"s18 7wx",
    "addr:street":"Woodside",
    "iso:country":"GB",
    "sg:address":"33 Woodside View, Holmesfield",
    "sg:city":"Dronfield",
    "sg:classifiers":[
        {
            "category":"Professional",
            "subcategory":"Printing & Photocopies",
            "type":"Services"
        }
    ],
    "sg:phone":"+44 114 289 0316",
    "sg:postcode":"S18 7WX",
    "sg:province":"Derbyshire",
    "sg:tags":[
        "top",
        "publishing",
        "desk"
    ],
    "wof:name":"Thumbprint Studio",
    "wof:placetype":"venue"
},
  "geometry": {"coordinates":[-1.517449,53.296452],"type":"Point"}
}