{
  "type": "Feature",
  "properties": {
    "iso:country":"GB",
    "sg:address":"24 Fountain Square, Hanley",
    "sg:city":"Stoke-on-trent",
    "sg:classifiers":[
        {
            "category":"Shopping",
            "subcategory":"Tobacco",
            "type":"Retail Goods"
        }
    ],
    "sg:postcode":"ST1 1LD",
    "sg:province":"Staffordshire",
    "sg:tags":[
        "tobacconist"
    ],
    "wof:name":"J M Edwards",
    "wof:placetype":"venue"
},
  "geometry": {"coordinates":[-2.1755,53.025799],"type":"Point"}
}