{
  "type": "Feature",
  "properties": {
    "iso:country":"GB",
    "sg:address":"Montgomerie Street, Tarbolton",
    "sg:city":"Mauchline",
    "sg:classifiers":[
        {
            "category":"Arena",
            "subcategory":"Sports Club",
            "type":"Entertainment"
        }
    ],
    "sg:phone":"+44 1292 541531",
    "sg:postcode":"KA5 5QD",
    "sg:province":"East Ayrshire",
    "wof:name":"Tarbolton Bowling Club",
    "wof:placetype":"venue"
},
  "geometry": {"coordinates":[-4.4860491753,55.5126457214],"type":"Point"}
}