{
  "type": "Feature",
  "properties": {
    "addr:full":"9 Park Way London Greater London NW1 7PG",
    "addr:housenumber":"9",
    "addr:postcode":"nw1 7pg",
    "addr:street":"Park Way",
    "iso:country":"GB",
    "sg:address":"9 Park Way",
    "sg:city":"London",
    "sg:classifiers":[
        {
            "category":"Professional",
            "subcategory":"Management & Consulting",
            "type":"Services"
        }
    ],
    "sg:phone":"+44 20 7482 5920",
    "sg:postcode":"NW1 7PG",
    "sg:province":"Greater London",
    "sg:tags":[
        "marketing",
        "consultant"
    ],
    "wof:name":"Perennis Ltd.",
    "wof:placetype":"venue"
},
  "geometry": {"coordinates":[-0.2054439932,51.5836029053],"type":"Point"}
}