{
  "type": "Feature",
  "properties": {
    "addr:full":"52 High Street, Hampton Hill Hampton Greater London TW12 1PD",
    "addr:housenumber":"52",
    "addr:postcode":"tw12 1pd",
    "addr:street":"High Street",
    "iso:country":"GB",
    "sg:address":"52 High Street, Hampton Hill",
    "sg:city":"Hampton",
    "sg:classifiers":[
        {
            "category":"Deli",
            "type":"Food & Drink"
        }
    ],
    "sg:phone":"+44 20 8977 5493",
    "sg:postcode":"TW12 1PD",
    "sg:province":"Greater London",
    "sg:tags":[
        "delivery",
        "sandwich"
    ],
    "wof:name":"Lunch Box",
    "wof:placetype":"venue"
},
  "geometry": {"coordinates":[-0.356366992,51.4260864258],"type":"Point"}
}