{
  "type": "Feature",
  "properties": {
    "addr:full":"58 Main Street, Wheldrake York North Yorkshire YO19 6AB",
    "addr:housenumber":"58",
    "addr:postcode":"yo19 6ab",
    "addr:street":"Main Street",
    "iso:country":"GB",
    "sg:address":"58 Main Street, Wheldrake",
    "sg:city":"York",
    "sg:classifiers":[
        {
            "category":"Shopping",
            "subcategory":"Department Store",
            "type":"Retail Goods"
        }
    ],
    "sg:phone":"+44 1904 448228",
    "sg:postcode":"YO19 6AB",
    "sg:province":"North Yorkshire",
    "wof:name":"Welldrake Costcutter",
    "wof:placetype":"venue"
},
  "geometry": {"coordinates":[-1.0584779978,53.8330955505],"type":"Point"}
}