{
  "type": "Feature",
  "properties": {
    "iso:country":"GB",
    "sg:address":"5-7 Unitas Road",
    "sg:city":"Bellshill",
    "sg:classifiers":[
        {
            "category":"Food & Beverages",
            "subcategory":"Meat & Fish",
            "type":"Retail Goods"
        }
    ],
    "sg:phone":"+44 1698 843764",
    "sg:postcode":"ML4 1QL",
    "sg:province":"North Lanarkshire",
    "sg:tags":[
        "butcher"
    ],
    "wof:name":"Benjamin Mallagh",
    "wof:placetype":"venue"
},
  "geometry": {"coordinates":[-4.010209,55.818546],"type":"Point"}
}