{
  "type": "Feature",
  "properties": {
    "iso:country":"GB",
    "sg:address":"179 Wensleydale Road, Great Barr",
    "sg:city":"Birmingham",
    "sg:classifiers":[
        {
            "category":"Manufacturing",
            "subcategory":"Petroleum Products",
            "type":"Manufacturing & Wholesale Goods"
        }
    ],
    "sg:postcode":"B42 1PJ",
    "sg:province":"West Midlands",
    "sg:tags":[
        "double",
        "glazing"
    ],
    "wof:name":"Alan Wallace Window & Building Services",
    "wof:placetype":"venue"
},
  "geometry": {"coordinates":[-1.921188,52.532154],"type":"Point"}
}