{
  "type": "Feature",
  "properties": {
    "addr:full":"Station House, Station Road, Bentley Ipswich Suffolk IP9 2DB",
    "addr:postcode":"ip9 2db",
    "addr:street":"Station Road",
    "iso:country":"GB",
    "sg:address":"Station House, Station Road, Bentley",
    "sg:city":"Ipswich",
    "sg:classifiers":[
        {
            "category":"Home & Garden",
            "subcategory":"Building Materials",
            "type":"Retail Goods"
        },
        {
            "category":"Building & Trades",
            "subcategory":"Construction",
            "type":"Services"
        }
    ],
    "sg:phone":"+44 1473 327288",
    "sg:postcode":"IP9 2DB",
    "sg:province":"Suffolk",
    "sg:tags":[
        "insulation",
        "installers"
    ],
    "wof:name":"Ipswich Insulations Ltd.",
    "wof:placetype":"venue"
},
  "geometry": {"coordinates":[1.068967,51.991161],"type":"Point"}
}