{
  "type": "Feature",
  "properties": {
    "iso:country":"GB",
    "sg:address":"12 Burscough Street",
    "sg:city":"Ormskirk",
    "sg:classifiers":[
        {
            "category":"Shopping",
            "subcategory":"Gifts & Souvenirs",
            "type":"Retail Goods"
        }
    ],
    "sg:phone":"+44 1695 572138",
    "sg:postcode":"L39 2ER",
    "sg:province":"Lancashire",
    "sg:tags":[
        "shop",
        "poster",
        "card"
    ],
    "wof:name":"Peter Draper",
    "wof:placetype":"venue"
},
  "geometry": {"coordinates":[-2.885562,53.567791],"type":"Point"}
}