{
  "type": "Feature",
  "properties": {
    "iso:country":"GB",
    "sg:address":"Bayer Ho, Strawberry Hill",
    "sg:city":"Newbury",
    "sg:classifiers":[
        {
            "category":"Shopping",
            "subcategory":"Beauty & Cosmetics",
            "type":"Retail Goods"
        }
    ],
    "sg:postcode":"RG14 1JA",
    "sg:province":"Berkshire",
    "sg:tags":[
        "product"
    ],
    "wof:name":"Creations Aromatiques Ltd",
    "wof:placetype":"venue"
},
  "geometry": {"coordinates":[-1.327904,51.404991],"type":"Point"}
}