{
  "type": "Feature",
  "properties": {
    "addr:full":"106 Forest Road, Sutton Manor St Helens Cheshire WA9 4AH",
    "addr:housenumber":"106",
    "addr:postcode":"wa9 4ah",
    "addr:street":"Forest Road",
    "iso:country":"GB",
    "sg:address":"106 Forest Road, Sutton Manor",
    "sg:city":"St Helens",
    "sg:classifiers":[
        {
            "category":"Personal",
            "subcategory":"Beauty Salon",
            "type":"Services"
        }
    ],
    "sg:postcode":"WA9 4AH",
    "sg:province":"Cheshire",
    "sg:tags":[
        "unisex",
        "hairdresser"
    ],
    "wof:name":"His 'N' Hairs",
    "wof:placetype":"venue"
},
  "geometry": {"coordinates":[-2.732743,53.414253],"type":"Point"}
}