{
  "type": "Feature",
  "properties": {
    "addr:full":"19-21 Drumsheugh Gardens Edinburgh City of Edinburgh EH3 7RW",
    "addr:housenumber":"19-21",
    "addr:postcode":"eh3 7rw",
    "addr:street":"Drumsheugh Gardens",
    "iso:country":"GB",
    "sg:address":"19-21 Drumsheugh Gardens",
    "sg:city":"Edinburgh",
    "sg:classifiers":[
        {
            "category":"Health Services",
            "subcategory":"Nursing And Care Facility",
            "type":"Services"
        }
    ],
    "sg:phone":"+44 131 225 6151",
    "sg:postcode":"EH3 7RW",
    "sg:province":"City of Edinburgh",
    "sg:tags":[
        "home"
    ],
    "wof:name":"Lynedoch Private Nursing Home",
    "wof:placetype":"venue"
},
  "geometry": {"coordinates":[-3.214981,55.952438],"type":"Point"}
}