{
  "type": "Feature",
  "properties": {
    "iso:country":"GB",
    "sg:address":"42 Cholmondeley Road",
    "sg:city":"Salford",
    "sg:classifiers":[
        {
            "category":"Building & Trades",
            "subcategory":"Construction",
            "type":"Services"
        }
    ],
    "sg:phone":"+44 161 737 8140",
    "sg:postcode":"M6 8NH",
    "sg:province":"Greater Manchester",
    "sg:tags":[
        "builder"
    ],
    "wof:name":"J & C Builders",
    "wof:placetype":"venue"
},
  "geometry": {"coordinates":[-2.3168439865,53.4942131042],"type":"Point"}
}