{
  "type": "Feature",
  "properties": {
    "iso:country":"GB",
    "sg:address":"130 Warwards La, Selly Oak",
    "sg:city":"Birmingham",
    "sg:classifiers":[
        {
            "category":"Building & Trades",
            "subcategory":"Cleaning & Sanitation",
            "type":"Services"
        }
    ],
    "sg:postcode":"B29 7RE",
    "sg:province":"West Midlands",
    "sg:tags":[
        "steam"
    ],
    "wof:name":"Glover,Edward,",
    "wof:placetype":"venue"
},
  "geometry": {"coordinates":[-1.924117,52.436867],"type":"Point"}
}