{
  "type": "Feature",
  "properties": {
    "addr:full":"17 Moss Lane Pinner Greater London HA5 3BB",
    "addr:housenumber":"17",
    "addr:postcode":"ha5 3bb",
    "addr:street":"Moss Lane",
    "iso:country":"GB",
    "sg:address":"17 Moss Lane",
    "sg:city":"Pinner",
    "sg:classifiers":[
        {
            "category":"Real Estate",
            "subcategory":"Architect",
            "type":"Services"
        }
    ],
    "sg:postcode":"HA5 3BB",
    "sg:province":"Greater London",
    "wof:name":"Ouroborus Design & Engineering Ltd",
    "wof:placetype":"venue"
},
  "geometry": {"coordinates":[-0.3790940046,51.6024627686],"type":"Point"}
}