{
  "type": "Feature",
  "properties": {
    "iso:country":"GB",
    "sg:address":"1 Derwent Street",
    "sg:city":"Sunderland",
    "sg:classifiers":[
        {
            "category":"Professional",
            "subcategory":"Printing & Photocopies",
            "type":"Services"
        }
    ],
    "sg:postcode":"SR1 3NT",
    "sg:province":"Tyne and Wear",
    "sg:tags":[
        "printer"
    ],
    "wof:name":"P D C Copyprint (Sunderland)",
    "wof:placetype":"venue"
},
  "geometry": {"coordinates":[-1.387031,54.903446],"type":"Point"}
}