{
  "type": "Feature",
  "properties": {
    "iso:country":"GB",
    "sg:address":"4 Balmoral Road",
    "sg:city":"Trowbridge",
    "sg:classifiers":[
        {
            "category":"Banks & Credit Unions",
            "subcategory":"Bank",
            "type":"Services"
        }
    ],
    "sg:postcode":"BA14 0JS",
    "sg:province":"Wiltshire",
    "sg:tags":[
        "stocktaking",
        "inventory"
    ],
    "wof:name":"A1 Stocktaking",
    "wof:placetype":"venue"
},
  "geometry": {"coordinates":[-2.218187,51.304901],"type":"Point"}
}