{
  "type": "Feature",
  "properties": {
    "addr:full":"Atherton Street St Helens Merseyside WA10 2HT",
    "addr:postcode":"wa10 2ht",
    "addr:street":"Atherton Street",
    "iso:country":"GB",
    "sg:address":"Atherton Street",
    "sg:city":"St Helens",
    "sg:classifiers":[
        {
            "category":"Health Services",
            "subcategory":"Clinic",
            "type":"Services"
        }
    ],
    "sg:phone":"+44 1744 611501",
    "sg:postcode":"WA10 2HT",
    "sg:province":"Merseyside",
    "sg:tags":[
        "nh"
    ],
    "wof:name":"Lingholme Health Centre",
    "wof:placetype":"venue"
},
  "geometry": {"coordinates":[-2.7446539402,53.4589385986],"type":"Point"}
}