{
  "type": "Feature",
  "properties": {
    "iso:country":"GB",
    "sg:address":"16 Tranter Crescent",
    "sg:city":"Cannock",
    "sg:classifiers":[
        {
            "category":"Building & Trades",
            "subcategory":"Construction",
            "type":"Services"
        }
    ],
    "sg:postcode":"WS11 2ZE",
    "sg:province":"Staffordshire",
    "sg:tags":[
        "joiner",
        "carpenter"
    ],
    "wof:name":"Underhill Partitioning",
    "wof:placetype":"venue"
},
  "geometry": {"coordinates":[-2.003887,52.697067],"type":"Point"}
}