{
  "type": "Feature",
  "properties": {
    "iso:country":"GB",
    "sg:address":"St Marys Road, Great Bentley",
    "sg:city":"Colchester",
    "sg:classifiers":[
        {
            "category":"Food & Beverages",
            "subcategory":"Farmers Market",
            "type":"Retail Goods"
        }
    ],
    "sg:postcode":"CO7 8NJ",
    "sg:province":"Essex",
    "sg:tags":[
        "farm",
        "shop",
        "pyo"
    ],
    "wof:name":"Carpenters Farm",
    "wof:placetype":"venue"
},
  "geometry": {"coordinates":[1.07332,51.841835],"type":"Point"}
}