{
  "type": "Feature",
  "properties": {
    "iso:country":"GB",
    "sg:address":"Hythe Clinic, 140-144 High St",
    "sg:city":"Hythe",
    "sg:classifiers":[
        {
            "category":"Organizations",
            "subcategory":"Non-profit Organization",
            "type":"Services"
        }
    ],
    "sg:postcode":"CT21 5JU",
    "sg:province":"Kent",
    "sg:tags":[
        "organisation",
        "voluntary",
        "charity"
    ],
    "wof:name":"Mencap Ltd",
    "wof:placetype":"venue"
},
  "geometry": {"coordinates":[1.0804810524,51.0708274841],"type":"Point"}
}