{
  "type": "Feature",
  "properties": {
    "iso:country":"GB",
    "sg:address":"5 Grafton Street",
    "sg:city":"Altrincham",
    "sg:classifiers":[
        {
            "category":"Shopping",
            "subcategory":"Baby Store",
            "type":"Retail Goods"
        }
    ],
    "sg:phone":"+44 161 928 7657",
    "sg:postcode":"WA14 1DU",
    "sg:province":"Cheshire",
    "sg:tags":[
        "babywear",
        "childrens"
    ],
    "wof:name":"Toto's",
    "wof:placetype":"venue"
},
  "geometry": {"coordinates":[-2.3499889374,53.3857688904],"type":"Point"}
}