{
  "type": "Feature",
  "properties": {
    "iso:country":"GB",
    "sg:address":"113 Ainsworth Road",
    "sg:city":"Bury",
    "sg:classifiers":[
        {
            "category":"Retail",
            "subcategory":"Laundry & Dry Cleaning",
            "type":"Services"
        }
    ],
    "sg:postcode":"BL8 2PY",
    "sg:province":"Lancashire",
    "sg:tags":[
        "launderette"
    ],
    "wof:name":"Launderette",
    "wof:placetype":"venue"
},
  "geometry": {"coordinates":[-2.319759,53.592541],"type":"Point"}
}