{
  "type": "Feature",
  "properties": {
    "iso:country":"GB",
    "sg:address":"Two Pools Farm, Wotton Rd",
    "sg:city":"Bristol",
    "sg:classifiers":[
        {
            "category":"Home & Garden",
            "subcategory":"Building Materials",
            "type":"Retail Goods"
        }
    ],
    "sg:postcode":"BS37 9XD",
    "sg:province":"Gloucestershire",
    "sg:tags":[
        "roofing",
        "rafter",
        "beams"
    ],
    "wof:name":"Griffee,David,",
    "wof:placetype":"venue"
},
  "geometry": {"coordinates":[-2.45275,51.558201],"type":"Point"}
}