{
  "type": "Feature",
  "properties": {
    "addr:full":"Bone Lane Newbury Berkshire RG14 5PH",
    "addr:postcode":"rg14 5ph",
    "addr:street":"Bone Lane",
    "iso:country":"GB",
    "sg:address":"Bone Lane",
    "sg:city":"Newbury",
    "sg:classifiers":[
        {
            "category":"Manufacturing",
            "subcategory":"Buildings",
            "type":"Manufacturing & Wholesale Goods"
        },
        {
            "category":"Wholesale",
            "subcategory":"Electrical",
            "type":"Manufacturing & Wholesale Goods"
        }
    ],
    "sg:phone":"+44 1635 31880",
    "sg:postcode":"RG14 5PH",
    "sg:province":"Berkshire",
    "sg:tags":[
        "system",
        "equipment",
        "refrigeration",
        "air conditioning"
    ],
    "wof:name":"Nationwide Refrigeration Supplies Ltd.",
    "wof:placetype":"venue"
},
  "geometry": {"coordinates":[-1.3098189831,51.4016494751],"type":"Point"}
}