{
  "type": "Feature",
  "properties": {
    "addr:full":"Bathwick Hill Bath Somerset BA2 6EN",
    "addr:postcode":"ba2 6en",
    "iso:country":"GB",
    "sg:address":"Bathwick Hill",
    "sg:city":"Bath",
    "sg:classifiers":[
        {
            "category":"Social Services",
            "subcategory":"Retirement Home",
            "type":"Services"
        }
    ],
    "sg:phone":"+44 1225 466574",
    "sg:postcode":"BA2 6EN",
    "sg:province":"Somerset",
    "sg:tags":[
        "residential",
        "care"
    ],
    "wof:name":"Woodside Residential Care Home",
    "wof:placetype":"venue"
},
  "geometry": {"coordinates":[-2.3396759033,51.3783187866],"type":"Point"}
}