{
  "type": "Feature",
  "properties": {
    "iso:country":"GB",
    "sg:address":"33 Queens Road",
    "sg:city":"Farnborough",
    "sg:classifiers":[
        {
            "category":"Shopping",
            "subcategory":"Gifts & Souvenirs",
            "type":"Retail Goods"
        }
    ],
    "sg:postcode":"GU14 6DU",
    "sg:province":"Hampshire",
    "sg:tags":[
        "shop"
    ],
    "wof:name":"Upstairs Downstairs",
    "wof:placetype":"venue"
},
  "geometry": {"coordinates":[-0.757059,51.274883],"type":"Point"}
}