{
  "type": "Feature",
  "properties": {
    "addr:full":"Well Royd House, Roils Head Rd Halifax West Yorkshire HX2 0LH",
    "addr:postcode":"hx2 0lh",
    "addr:street":"Head Rd",
    "iso:country":"GB",
    "sg:address":"Well Royd House, Roils Head Rd",
    "sg:city":"Halifax",
    "sg:classifiers":[
        {
            "category":"Health Services",
            "subcategory":"Nursing And Care Facility",
            "type":"Services"
        }
    ],
    "sg:phone":"+44 1422 350109",
    "sg:postcode":"HX2 0LH",
    "sg:province":"West Yorkshire",
    "sg:tags":[
        "home"
    ],
    "wof:name":"Well Royd House",
    "wof:placetype":"venue"
},
  "geometry": {"coordinates":[-1.9165689945,53.7259101868],"type":"Point"}
}