{
  "type": "Feature",
  "properties": {
    "iso:country":"GB",
    "sg:address":"Kirkland Coach Ho 4a Bridgend",
    "sg:city":"Dalry",
    "sg:classifiers":[
        {
            "category":"Professional",
            "subcategory":"Management & Consulting",
            "type":"Services"
        }
    ],
    "sg:postcode":"KA24 4DA",
    "sg:province":"North Ayrshire",
    "sg:tags":[
        "consultant",
        "training"
    ],
    "wof:name":"Wyatt,Jeremy,",
    "wof:placetype":"venue"
},
  "geometry": {"coordinates":[-4.720990181,55.7065963745],"type":"Point"}
}