{
  "type": "Feature",
  "properties": {
    "iso:country":"GB",
    "sg:address":"88 Kempton Road",
    "sg:city":"London",
    "sg:classifiers":[
        {
            "category":"Food & Beverages",
            "subcategory":"Groceries & Convenience Stores",
            "type":"Retail Goods"
        }
    ],
    "sg:phone":"+44 20 8548 8315",
    "sg:postcode":"E6 2LB",
    "sg:province":"Greater London",
    "wof:name":"Kempton Corner Shop",
    "wof:placetype":"venue"
},
  "geometry": {"coordinates":[0.057136,51.535469],"type":"Point"}
}