{
  "type": "Feature",
  "properties": {
    "addr:full":"114 Lavenham Rd Wandsworth Greater London SW18 5HF",
    "addr:housenumber":"114",
    "addr:postcode":"sw18 5hf",
    "addr:street":"Lavenham Rd",
    "iso:country":"GB",
    "sg:address":"114 Lavenham Rd",
    "sg:city":"Wandsworth",
    "sg:classifiers":[
        {
            "category":"Organizations",
            "subcategory":"Community Association",
            "type":"Services"
        }
    ],
    "sg:phone":"+44 20 8877 1254",
    "sg:postcode":"SW18 5HF",
    "sg:province":"Greater London",
    "sg:tags":[
        "relation",
        "public"
    ],
    "wof:name":"Rea Publicity",
    "wof:placetype":"venue"
},
  "geometry": {"coordinates":[-0.199806,51.442429],"type":"Point"}
}