{
  "type": "Feature",
  "properties": {
    "iso:country":"GB",
    "sg:address":"52 Yoden Way",
    "sg:city":"Peterlee",
    "sg:classifiers":[
        {
            "category":"Farming",
            "subcategory":"Livestock Farm",
            "type":"Manufacturing & Wholesale Goods"
        },
        {
            "category":"Home & Garden",
            "subcategory":"Furniture",
            "type":"Retail Goods"
        }
    ],
    "sg:phone":"+44 191 587 1168",
    "sg:postcode":"SR8 1BS",
    "sg:province":"Durham",
    "sg:tags":[
        "others"
    ],
    "wof:name":"Michael O'Connor (Carpets) Ltd.",
    "wof:placetype":"venue"
},
  "geometry": {"coordinates":[-1.330859,54.75869],"type":"Point"}
}