{
  "type": "Feature",
  "properties": {
    "addr:full":"12 Fairlawn Gro Banstead Surrey SM7 3BN",
    "addr:housenumber":"12",
    "addr:postcode":"sm7 3bn",
    "addr:street":"Fairlawn Gro",
    "iso:country":"GB",
    "sg:address":"12 Fairlawn Gro",
    "sg:city":"Banstead",
    "sg:classifiers":[
        {
            "category":"Government",
            "subcategory":"Post Office",
            "type":"Public Place"
        }
    ],
    "sg:phone":"+44 20 8770 1122",
    "sg:postcode":"SM7 3BN",
    "sg:province":"Surrey",
    "sg:tags":[
        "messenger",
        "courier"
    ],
    "wof:name":"Go Go Couriers",
    "wof:placetype":"venue"
},
  "geometry": {"coordinates":[-0.180529,51.331295],"type":"Point"}
}