{
  "type": "Feature",
  "properties": {
    "addr:full":"Moreton Hall, Symonds Road Bury St Edmunds Suffolk IP32 7EW",
    "addr:postcode":"ip32 7ew",
    "addr:street":"Symonds Road",
    "iso:country":"GB",
    "sg:address":"Moreton Hall, Symonds Road",
    "sg:city":"Bury St Edmunds",
    "sg:classifiers":[
        {
            "category":"Community Center",
            "type":"Public Place"
        }
    ],
    "sg:phone":"+44 1284 763405",
    "sg:postcode":"IP32 7EW",
    "sg:province":"Suffolk",
    "sg:tags":[
        "centre"
    ],
    "wof:name":"Moreton Hall Community Centre",
    "wof:placetype":"venue"
},
  "geometry": {"coordinates":[0.7419599891,52.245059967],"type":"Point"}
}