{
  "type": "Feature",
  "properties": {
    "addr:full":"Pancake Hill, Lower Chedworth Cheltenham Gloucestershire GL54 4AW",
    "addr:postcode":"gl54 4aw",
    "addr:street":"Lower",
    "iso:country":"GB",
    "sg:address":"Pancake Hill, Lower Chedworth",
    "sg:city":"Cheltenham",
    "sg:classifiers":[
        {
            "category":"Building & Trades",
            "subcategory":"Construction",
            "type":"Services"
        }
    ],
    "sg:phone":"+44 1285 720334",
    "sg:postcode":"GL54 4AW",
    "sg:province":"Gloucestershire",
    "sg:tags":[
        "builder"
    ],
    "wof:name":"Amphlett & Co",
    "wof:placetype":"venue"
},
  "geometry": {"coordinates":[-1.9252170324,51.8057937622],"type":"Point"}
}