{
  "type": "Feature",
  "properties": {
    "addr:full":"Unit 13, Park Royal Business Centre, 7-19 Park Royal Road London Greater London NW10 7LQ",
    "addr:housenumber":"unit 13;7-19",
    "addr:postcode":"nw10 7lq",
    "addr:street":"Park;Park Royal Road",
    "iso:country":"GB",
    "sg:address":"Unit 13, Park Royal Business Centre, 7-19 Park Royal Road",
    "sg:city":"London",
    "sg:classifiers":[
        {
            "category":"Communications",
            "type":"Services"
        }
    ],
    "sg:phone":"+44 20 8961 1600",
    "sg:postcode":"NW10 7LQ",
    "sg:province":"Greater London",
    "sg:tags":[
        "tv",
        "video",
        "radio"
    ],
    "wof:name":"Sat Supplier Co",
    "wof:placetype":"venue"
},
  "geometry": {"coordinates":[-0.266864,51.526459],"type":"Point"}
}