{
  "type": "Feature",
  "properties": {
    "iso:country":"GB",
    "sg:address":"Unit 2, Goldthorpe Industrial Estate",
    "sg:city":"Rotherham",
    "sg:classifiers":[
        {
            "category":"Professional",
            "subcategory":"Engineering",
            "type":"Services"
        }
    ],
    "sg:postcode":"S63 9BL",
    "sg:province":"South Yorkshire",
    "wof:name":"Admech Engineering Ltd.",
    "wof:placetype":"venue"
},
  "geometry": {"coordinates":[-1.309283,53.527668],"type":"Point"}
}