{
  "type": "Feature",
  "properties": {
    "iso:country":"GB",
    "sg:address":"3 Commercial Street, Ystrad Mynach",
    "sg:city":"Hengoed",
    "sg:classifiers":[
        {
            "category":"Banks & Credit Unions",
            "subcategory":"Investment Brokerage",
            "type":"Services"
        },
        {
            "category":"Home & Garden",
            "subcategory":"Furniture",
            "type":"Retail Goods"
        }
    ],
    "sg:phone":"+44 1443 812991",
    "sg:postcode":"CF82 7DU",
    "sg:province":"Caerphilly",
    "sg:tags":[
        "furnishers",
        "houshold",
        "contract"
    ],
    "wof:name":"Richard Lewis Furnishers",
    "wof:placetype":"venue"
},
  "geometry": {"coordinates":[-3.236361,51.641052],"type":"Point"}
}