{
  "type": "Feature",
  "properties": {
    "iso:country":"GB",
    "sg:address":"36 Occupation Lane, Illingworth",
    "sg:city":"Halifax",
    "sg:classifiers":[
        {
            "category":"Professional",
            "subcategory":"Engineering",
            "type":"Services"
        }
    ],
    "sg:postcode":"HX2 9RL",
    "sg:province":"West Yorkshire",
    "sg:tags":[
        "contractor",
        "electrical",
        "engineer"
    ],
    "wof:name":"Sargent,S A,Electrical Contractor",
    "wof:placetype":"venue"
},
  "geometry": {"coordinates":[-1.8880339861,53.756893158],"type":"Point"}
}