{
  "type": "Feature",
  "properties": {
    "addr:full":"Orchard Springs, Clapham Exeter Devon EX6 7YG",
    "addr:postcode":"ex6 7yg",
    "addr:street":"Orchard Springs",
    "iso:country":"GB",
    "sg:address":"Orchard Springs, Clapham",
    "sg:city":"Exeter",
    "sg:classifiers":[
        {
            "category":"Transit Center",
            "subcategory":"Passenger",
            "type":"Transportation"
        },
        {
            "category":"Retail",
            "subcategory":"Pet Boarding",
            "type":"Services"
        }
    ],
    "sg:phone":"+44 1392 832595",
    "sg:postcode":"EX6 7YG",
    "sg:province":"Devon",
    "sg:tags":[
        "kennel",
        "catteries"
    ],
    "wof:name":"Animal Paradise",
    "wof:placetype":"venue"
},
  "geometry": {"coordinates":[-3.681549,50.688358],"type":"Point"}
}