{
  "type": "Feature",
  "properties": {
    "addr:full":"9a Roydon Road, Stanstead Abbotts Ware Hertfordshire SG12 8HQ",
    "addr:housenumber":"9a",
    "addr:postcode":"sg12 8hq",
    "addr:street":"Roydon Road",
    "iso:country":"GB",
    "sg:address":"9a Roydon Road, Stanstead Abbotts",
    "sg:city":"Ware",
    "sg:classifiers":[
        {
            "category":"Banks & Credit Unions",
            "subcategory":"Investment Brokerage",
            "type":"Services"
        },
        {
            "category":"Shopping",
            "subcategory":"Gifts & Souvenirs",
            "type":"Retail Goods"
        }
    ],
    "sg:phone":"+44 1363 881088",
    "sg:postcode":"SG12 8HQ",
    "sg:province":"Hertfordshire",
    "sg:tags":[
        "stockbroker",
        "watch",
        "clock"
    ],
    "wof:name":"Hollingsworth & Wilkes Ltd",
    "wof:placetype":"venue"
},
  "geometry": {"coordinates":[0.0092209997,51.7879905701],"type":"Point"}
}