{
  "type": "Feature",
  "properties": {
    "iso:country":"GB",
    "sg:address":"44 Windsor Terr",
    "sg:city":"Sunderland",
    "sg:classifiers":[
        {
            "category":"Home & Garden",
            "subcategory":"Hardware",
            "type":"Retail Goods"
        }
    ],
    "sg:postcode":"SR2 9QF",
    "sg:province":"Tyne and Wear",
    "sg:tags":[
        "retailer",
        "diy"
    ],
    "wof:name":"Grangetown Diy",
    "wof:placetype":"venue"
},
  "geometry": {"coordinates":[-1.414271,54.951805],"type":"Point"}
}