{
  "type": "Feature",
  "properties": {
    "addr:full":"43a Commercial Street London Greater London E1 6BD",
    "addr:housenumber":"43a",
    "addr:postcode":"e1 6bd",
    "addr:street":"Commercial Street",
    "iso:country":"GB",
    "sg:address":"43a Commercial Street",
    "sg:city":"London",
    "sg:classifiers":[
        {
            "category":"Shopping",
            "subcategory":"Clothing, Apparel, & Fashions",
            "type":"Retail Goods"
        }
    ],
    "sg:phone":"+44 20 7377 0492",
    "sg:postcode":"E1 6BD",
    "sg:province":"Greater London",
    "sg:tags":[
        "lingerie"
    ],
    "wof:name":"Lama Ltd.",
    "wof:placetype":"venue"
},
  "geometry": {"coordinates":[-0.0736699998,51.5171661377],"type":"Point"}
}