{
  "type": "Feature",
  "properties": {
    "addr:full":"Torquay Girls Grammar School, Shipley La Torquay Devon TQ2 7DY",
    "addr:postcode":"tq2 7dy",
    "addr:street":"La Torquay",
    "iso:country":"GB",
    "sg:address":"Torquay Girls Grammar School, Shipley La",
    "sg:city":"Torquay",
    "sg:classifiers":[
        {
            "category":"Arena",
            "subcategory":"Sports Club",
            "type":"Entertainment"
        }
    ],
    "sg:phone":"+44 1803 616251",
    "sg:postcode":"TQ2 7DY",
    "sg:province":"Devon",
    "wof:name":"South Devon Sports Assocciation For The Disabled",
    "wof:placetype":"venue"
},
  "geometry": {"coordinates":[-3.543464,50.467194],"type":"Point"}
}