{
  "type": "Feature",
  "properties": {
    "addr:full":"10 Simpson St Middlesbrough North Yorkshire TS5 6HP",
    "addr:housenumber":"10",
    "addr:postcode":"ts5 6hp",
    "addr:street":"Simpson St",
    "iso:country":"GB",
    "sg:address":"10 Simpson St",
    "sg:city":"Middlesbrough",
    "sg:classifiers":[
        {
            "category":"Building & Trades",
            "subcategory":"Construction",
            "type":"Services"
        }
    ],
    "sg:postcode":"TS5 6HP",
    "sg:province":"North Yorkshire",
    "sg:tags":[
        "builder"
    ],
    "wof:name":"Previously Enjoyed Furniture",
    "wof:placetype":"venue"
},
  "geometry": {"coordinates":[-1.1738690138,54.5754394531],"type":"Point"}
}