{
  "type": "Feature",
  "properties": {
    "addr:full":"Thornton Rd Kirkcaldy Fife KY1 3NZ",
    "addr:postcode":"ky1 3nz",
    "addr:street":"Thornton Rd",
    "iso:country":"GB",
    "sg:address":"Thornton Rd",
    "sg:city":"Kirkcaldy",
    "sg:classifiers":[
        {
            "category":"Home & Garden",
            "subcategory":"Garden Supply",
            "type":"Retail Goods"
        }
    ],
    "sg:phone":"+44 1592 652861",
    "sg:postcode":"KY1 3NZ",
    "sg:province":"Fife",
    "sg:tags":[
        "nursery",
        "centre"
    ],
    "wof:name":"Gardenland Garden Centre",
    "wof:placetype":"venue"
},
  "geometry": {"coordinates":[-3.1630289555,56.1095962524],"type":"Point"}
}