{
  "type": "Feature",
  "properties": {
    "addr:full":"2 Pilgrim St Birkenhead Merseyside L41 5EH",
    "addr:housenumber":"2",
    "addr:postcode":"l41 5eh",
    "addr:street":"Pilgrim St",
    "iso:country":"GB",
    "sg:address":"2 Pilgrim St",
    "sg:city":"Birkenhead",
    "sg:classifiers":[
        {
            "category":"Shopping",
            "subcategory":"Discount & Variety Stores",
            "type":"Retail Goods"
        }
    ],
    "sg:phone":"+44 151 647 7494",
    "sg:postcode":"L41 5EH",
    "sg:province":"Merseyside",
    "sg:tags":[
        "cleaning",
        "supply"
    ],
    "wof:name":"Motospec",
    "wof:placetype":"venue"
},
  "geometry": {"coordinates":[-3.0122659206,53.3914985657],"type":"Point"}
}