{
  "type": "Feature",
  "properties": {
    "iso:country":"GB",
    "sg:address":"Unit 1 Howe Moss Drive Kirkhill, Industrial Estate, Dyce",
    "sg:city":"Aberdeen",
    "sg:classifiers":[
        {
            "category":"Professional",
            "subcategory":"Engineering",
            "type":"Services"
        }
    ],
    "sg:phone":"+44 1224 722333",
    "sg:postcode":"AB21 0GL",
    "sg:province":"Aberdeen City",
    "sg:tags":[
        "consulting",
        "engineer"
    ],
    "wof:name":"Furmanite International",
    "wof:placetype":"venue"
},
  "geometry": {"coordinates":[-2.214522,57.207512],"type":"Point"}
}