{
  "type": "Feature",
  "properties": {
    "iso:country":"GB",
    "sg:address":"7 High Street",
    "sg:city":"Northampton",
    "sg:classifiers":[
        {
            "category":"Food & Beverages",
            "subcategory":"Meat & Fish",
            "type":"Retail Goods"
        }
    ],
    "sg:postcode":"NN7 4AQ",
    "sg:province":"Buckinghamshire",
    "sg:tags":[
        "butcher"
    ],
    "wof:name":"R G Elliott",
    "wof:placetype":"venue"
},
  "geometry": {"coordinates":[-0.9902210236,52.2418174744],"type":"Point"}
}