{
  "type": "Feature",
  "properties": {
    "iso:country":"GB",
    "sg:address":"Crag Brow",
    "sg:city":"Windermere",
    "sg:classifiers":[
        {
            "category":"Shopping",
            "subcategory":"Comic Books",
            "type":"Retail Goods"
        }
    ],
    "sg:postcode":"LA23 3BX",
    "sg:province":"Cumbria",
    "sg:tags":[
        "jeweller"
    ],
    "wof:name":"Lakeland Jewellers",
    "wof:placetype":"venue"
},
  "geometry": {"coordinates":[-2.918861,54.36491],"type":"Point"}
}