{
  "type": "Feature",
  "properties": {
    "iso:country":"GB",
    "sg:address":"Flat 2 11 West Pilton Av",
    "sg:city":"Edinburgh",
    "sg:classifiers":[
        {
            "category":"Professional",
            "subcategory":"Detective & Security Services",
            "type":"Services"
        }
    ],
    "sg:phone":"+44 131 332 0877",
    "sg:postcode":"EH4 4BX",
    "sg:province":"City of Edinburgh",
    "wof:name":"W R T Securities",
    "wof:placetype":"venue"
},
  "geometry": {"coordinates":[-3.245249,55.971958],"type":"Point"}
}