{
  "type": "Feature",
  "properties": {
    "addr:full":"45 Marischal St Peterhead Aberdeenshire AB42 6ZQ",
    "addr:housenumber":"45",
    "addr:postcode":"ab42 6zq",
    "addr:street":"Marischal St",
    "iso:country":"GB",
    "sg:address":"45 Marischal St",
    "sg:city":"Peterhead",
    "sg:classifiers":[
        {
            "category":"Banks & Credit Unions",
            "subcategory":"Financial Services",
            "type":"Services"
        }
    ],
    "sg:postcode":"AB42 6ZQ",
    "sg:province":"Aberdeenshire",
    "sg:tags":[
        "building",
        "society"
    ],
    "wof:name":"Nationwide Building Society",
    "wof:placetype":"venue"
},
  "geometry": {"coordinates":[-1.7761390209,57.5049781799],"type":"Point"}
}