{
  "type": "Feature",
  "properties": {
    "iso:country":"GB",
    "sg:address":"28 Marsh Street, Rothwell",
    "sg:city":"Leeds",
    "sg:classifiers":[
        {
            "category":"Real Estate",
            "subcategory":"Real Estate Agent",
            "type":"Services"
        }
    ],
    "sg:phone":"+44 113 282 2136",
    "sg:postcode":"LS26 0BB",
    "sg:province":"West Yorkshire",
    "wof:name":"Reeds Rains",
    "wof:placetype":"venue"
},
  "geometry": {"coordinates":[-1.476932,53.748089],"type":"Point"}
}