{
  "type": "Feature",
  "properties": {
    "addr:full":"8 Tidworth Rd Salisbury Hampshire SP4 0NG",
    "addr:housenumber":"8",
    "addr:postcode":"sp4 0ng",
    "addr:street":"Tidworth Rd",
    "iso:country":"GB",
    "sg:address":"8 Tidworth Rd",
    "sg:city":"Salisbury",
    "sg:classifiers":[
        {
            "category":"Professional",
            "subcategory":"Lawyer & Legal Services",
            "type":"Services"
        }
    ],
    "sg:phone":"+44 1980 610721",
    "sg:postcode":"SP4 0NG",
    "sg:province":"Hampshire",
    "sg:tags":[
        "advice",
        "counselling"
    ],
    "wof:name":"Jean Kerley",
    "wof:placetype":"venue"
},
  "geometry": {"coordinates":[-1.7335729599,51.1323928833],"type":"Point"}
}