{
  "type": "Feature",
  "properties": {
    "addr:full":"47 Mount Wise Newquay Cornwall TR7 2BL",
    "addr:housenumber":"47",
    "addr:postcode":"tr7 2bl",
    "addr:street":"Mount",
    "iso:country":"GB",
    "sg:address":"47 Mount Wise",
    "sg:city":"Newquay",
    "sg:classifiers":[
        {
            "category":"Travel",
            "subcategory":"Hotels & Motels",
            "type":"Entertainment"
        }
    ],
    "sg:phone":"+44 1637 872921",
    "sg:postcode":"TR7 2BL",
    "sg:province":"Cornwall",
    "sg:website":"http://www.blenheimhotel.co.uk",
    "wof:name":"The Blenheim Hotel",
    "wof:placetype":"venue"
},
  "geometry": {"coordinates":[-5.0824689865,50.4117736816],"type":"Point"}
}