{
  "type": "Feature",
  "properties": {
    "iso:country":"GB",
    "sg:address":"Lynwood House, Leighton Road, Northall",
    "sg:city":"Dunstable",
    "sg:classifiers":[
        {
            "category":"Professional",
            "subcategory":"Accounting & Tax Preparation",
            "type":"Services"
        }
    ],
    "sg:postcode":"LU6 2ET",
    "sg:province":"Bedfordshire",
    "sg:tags":[
        "accountant"
    ],
    "wof:name":"Packer & Co",
    "wof:placetype":"venue"
},
  "geometry": {"coordinates":[-0.593667,51.862793],"type":"Point"}
}