{
  "type": "Feature",
  "properties": {
    "iso:country":"GB",
    "sg:address":"377 Lord Street",
    "sg:city":"Southport",
    "sg:classifiers":[
        {
            "category":"Professional",
            "type":"Services"
        },
        {
            "category":"Professional",
            "subcategory":"Advertising",
            "type":"Services"
        },
        {
            "category":"Professional",
            "subcategory":"Management & Consulting",
            "type":"Services"
        }
    ],
    "sg:phone":"+44 1704 544999",
    "sg:postcode":"PR9 0AG",
    "sg:province":"Lancashire",
    "sg:tags":[
        "consultant",
        "related",
        "business",
        "exhibition"
    ],
    "wof:name":"Access Point Ltd",
    "wof:placetype":"venue"
},
  "geometry": {"coordinates":[-3.002922,53.64983],"type":"Point"}
}