{
  "type": "Feature",
  "properties": {
    "addr:full":"Unit 7, Mersey Road Industrial Estate Manchester Lancashire M35 9LU",
    "addr:housenumber":"unit 7",
    "addr:postcode":"m35 9lu",
    "addr:street":"Mersey Road Industrial Estate",
    "iso:country":"GB",
    "sg:address":"Unit 7, Mersey Road Industrial Estate",
    "sg:city":"Manchester",
    "sg:classifiers":[
        {
            "category":"Wholesale",
            "subcategory":"Vending Machines",
            "type":"Manufacturing & Wholesale Goods"
        }
    ],
    "sg:phone":"+44 161 684 7373",
    "sg:postcode":"M35 9LU",
    "sg:province":"Lancashire",
    "wof:name":"Superdrink Ltd.",
    "wof:placetype":"venue"
},
  "geometry": {"coordinates":[-2.143859,53.515079],"type":"Point"}
}