{
  "type": "Feature",
  "properties": {
    "addr:full":"Boltons Private Rest Home Reading Berkshire RG6 1QD",
    "addr:postcode":"rg6 1qd",
    "addr:street":"Boltons Private",
    "iso:country":"GB",
    "sg:address":"Boltons Private Rest Home",
    "sg:city":"Reading",
    "sg:classifiers":[
        {
            "category":"Social Services",
            "subcategory":"Retirement Home",
            "type":"Services"
        }
    ],
    "sg:phone":"+44 118 926 1712",
    "sg:postcode":"RG6 1QD",
    "sg:province":"Berkshire",
    "sg:tags":[
        "residential",
        "care"
    ],
    "wof:name":"Boltons Home for the Elderly",
    "wof:placetype":"venue"
},
  "geometry": {"coordinates":[-0.9424700141,51.4514083862],"type":"Point"}
}