{
  "type": "Feature",
  "properties": {
    "addr:full":"95 Belgrave Road Leicester Leicestershire LE4 6AS",
    "addr:housenumber":"95",
    "addr:postcode":"le4 6as",
    "addr:street":"Belgrave Road",
    "iso:country":"GB",
    "sg:address":"95 Belgrave Road",
    "sg:city":"Leicester",
    "sg:classifiers":[
        {
            "category":"Shopping",
            "subcategory":"Discount & Variety Stores",
            "type":"Retail Goods"
        }
    ],
    "sg:phone":"+44 116 266 7772",
    "sg:postcode":"LE4 6AS",
    "sg:province":"Leicestershire",
    "sg:tags":[
        "centre"
    ],
    "wof:name":"Poundshop",
    "wof:placetype":"venue"
},
  "geometry": {"coordinates":[-1.1222070456,52.6498985291],"type":"Point"}
}