{
  "type": "Feature",
  "properties": {
    "addr:full":"16 Armoury Terrace Ebbw Vale Blaenau Gwent NP23 6BD",
    "addr:housenumber":"16",
    "addr:postcode":"np23 6bd",
    "addr:street":"Armoury Terrace",
    "iso:country":"GB",
    "sg:address":"16 Armoury Terrace",
    "sg:city":"Ebbw Vale",
    "sg:classifiers":[
        {
            "category":"Shopping",
            "type":"Retail Goods"
        }
    ],
    "sg:phone":"+44 1495 301606",
    "sg:postcode":"NP23 6BD",
    "sg:province":"Blaenau Gwent",
    "sg:tags":[
        "part",
        "accessory"
    ],
    "wof:name":"Car Care Discounts",
    "wof:placetype":"venue"
},
  "geometry": {"coordinates":[-3.2079908848,51.7756538391],"type":"Point"}
}