{
  "type": "Feature",
  "properties": {
    "addr:full":"Riviere Sands Holiday Park, Phillack Hayle Cornwall TR27 5AF",
    "addr:postcode":"tr27 5af",
    "addr:street":"Riviere",
    "iso:country":"GB",
    "sg:address":"Riviere Sands Holiday Park, Phillack",
    "sg:city":"Hayle",
    "sg:classifiers":[
        {
            "category":"Personal",
            "subcategory":"Beauty Salon",
            "type":"Services"
        }
    ],
    "sg:phone":"+44 1736 755662",
    "sg:postcode":"TR27 5AF",
    "sg:province":"Cornwall",
    "sg:tags":[
        "unisex",
        "hairdresser"
    ],
    "wof:name":"Helen Bawden Hairdressing",
    "wof:placetype":"venue"
},
  "geometry": {"coordinates":[-5.40896,50.195908],"type":"Point"}
}