{
  "type": "Feature",
  "properties": {
    "addr:full":"Whitecrook Centre, Whitecrook St Clydebank East Dunbartonshire G81 1QF",
    "addr:postcode":"g81 1qf",
    "addr:street":"St",
    "iso:country":"GB",
    "sg:address":"Whitecrook Centre, Whitecrook St",
    "sg:city":"Clydebank",
    "sg:classifiers":[
        {
            "category":"Professional",
            "subcategory":"Management & Consulting",
            "type":"Services"
        }
    ],
    "sg:phone":"+44 141 951 4951",
    "sg:postcode":"G81 1QF",
    "sg:province":"East Dunbartonshire",
    "sg:tags":[
        "consultant",
        "business"
    ],
    "wof:name":"Imera (Information Management) Consultants Ltd",
    "wof:placetype":"venue"
},
  "geometry": {"coordinates":[-4.4008598328,55.8989601135],"type":"Point"}
}