{
  "type": "Feature",
  "properties": {
    "addr:full":"Garage Lane, Setch King's Lynn Norfolk PE33 0BE",
    "addr:postcode":"pe33 0be",
    "addr:street":"Garage Lane;Lynn",
    "iso:country":"GB",
    "sg:address":"Garage Lane, Setch",
    "sg:city":"King's Lynn",
    "sg:classifiers":[
        {
            "category":"Building & Trades",
            "subcategory":"Landscaping Services",
            "type":"Services"
        }
    ],
    "sg:phone":"+44 1553 811717",
    "sg:postcode":"PE33 0BE",
    "sg:province":"Norfolk",
    "sg:tags":[
        "horticultural"
    ],
    "wof:name":"The Norfolk Leisure Co. Ltd.",
    "wof:placetype":"venue"
},
  "geometry": {"coordinates":[0.4153400064,52.6989898682],"type":"Point"}
}