{
  "type": "Feature",
  "properties": {
    "iso:country":"GB",
    "sg:address":"105 Holmes Avenue",
    "sg:city":"Hove",
    "sg:classifiers":[
        {
            "category":"Professional",
            "type":"Services"
        }
    ],
    "sg:postcode":"BN3 7LE",
    "sg:province":"East Sussex",
    "sg:tags":[
        "entertainer"
    ],
    "wof:name":"Mark Worgan",
    "wof:placetype":"venue"
},
  "geometry": {"coordinates":[-0.186291,50.84433],"type":"Point"}
}