{
  "type": "Feature",
  "properties": {
    "iso:country":"GB",
    "sg:address":"Unit C6 Chester Enterprise Centre, Hoole Bridge",
    "sg:city":"Chester",
    "sg:classifiers":[
        {
            "category":"Professional",
            "subcategory":"Management & Consulting",
            "type":"Services"
        }
    ],
    "sg:postcode":"CH2 3NE",
    "sg:province":"Cheshire",
    "sg:tags":[
        "consultant",
        "business"
    ],
    "wof:name":"Halley,Michael,",
    "wof:placetype":"venue"
},
  "geometry": {"coordinates":[-2.8685588837,53.2032203674],"type":"Point"}
}