{
  "type": "Feature",
  "properties": {
    "addr:full":"49 The Green Banbury Oxfordshire OX16 9AB",
    "addr:housenumber":"49",
    "addr:postcode":"ox16 9ab",
    "addr:street":"The Green",
    "iso:country":"GB",
    "sg:address":"49 The Green",
    "sg:city":"Banbury",
    "sg:classifiers":[
        {
            "category":"Real Estate",
            "subcategory":"Architect",
            "type":"Services"
        }
    ],
    "sg:phone":"+44 1295 263666",
    "sg:postcode":"OX16 9AB",
    "sg:province":"Oxfordshire",
    "wof:name":"Fallhill Ltd",
    "wof:placetype":"venue"
},
  "geometry": {"coordinates":[-1.3313800097,52.0550689697],"type":"Point"}
}