{
  "type": "Feature",
  "properties": {
    "addr:full":"1a Edison Road Bedford Bedfordshire MK41 0LF",
    "addr:housenumber":"1a",
    "addr:postcode":"mk41 0lf",
    "addr:street":"Edison Road",
    "iso:country":"GB",
    "sg:address":"1a Edison Road",
    "sg:city":"Bedford",
    "sg:classifiers":[
        {
            "category":"Home & Garden",
            "subcategory":"Hardware",
            "type":"Retail Goods"
        }
    ],
    "sg:phone":"+44 1234 327555",
    "sg:postcode":"MK41 0LF",
    "sg:province":"Bedfordshire",
    "sg:tags":[
        "lawnmowers",
        "machinery"
    ],
    "wof:name":"Mowamania",
    "wof:placetype":"venue"
},
  "geometry": {"coordinates":[-0.4190550148,52.1483726501],"type":"Point"}
}