{
  "type": "Feature",
  "properties": {
    "addr:full":"Unit 7, Sandtoft Industrial Estate Doncaster Lincolnshire DN9 1PN",
    "addr:housenumber":"unit 7;estate",
    "addr:postcode":"dn9 1pn",
    "addr:street":"Sandtoft Industrial",
    "iso:country":"GB",
    "sg:address":"Unit 7, Sandtoft Industrial Estate",
    "sg:city":"Doncaster",
    "sg:classifiers":[
        {
            "category":"Home & Garden",
            "subcategory":"Garden Supply",
            "type":"Retail Goods"
        }
    ],
    "sg:phone":"+44 1427 874804",
    "sg:postcode":"DN9 1PN",
    "sg:province":"Lincolnshire",
    "sg:tags":[
        "sand",
        "gravel"
    ],
    "wof:name":"Mills (Plant & Aggregates) Ltd.",
    "wof:placetype":"venue"
},
  "geometry": {"coordinates":[-0.8483890295,53.561050415],"type":"Point"}
}