{
  "type": "Feature",
  "properties": {
    "addr:full":"9 Anstice Square Telford Shropshire TF7 5BD",
    "addr:housenumber":"9",
    "addr:postcode":"tf7 5bd",
    "addr:street":"Anstice Square",
    "iso:country":"GB",
    "sg:address":"9 Anstice Square",
    "sg:city":"Telford",
    "sg:classifiers":[
        {
            "category":"Shopping",
            "subcategory":"Clothing, Apparel, & Fashions",
            "type":"Retail Goods"
        }
    ],
    "sg:phone":"+44 1952 581711",
    "sg:postcode":"TF7 5BD",
    "sg:province":"Shropshire",
    "sg:tags":[
        "shop"
    ],
    "wof:name":"B M B Fashions",
    "wof:placetype":"venue"
},
  "geometry": {"coordinates":[-2.4547410011,52.6337471008],"type":"Point"}
}