{
  "type": "Feature",
  "properties": {
    "addr:full":"North End Rd Stromness Orkney Islands KW16 3AG",
    "addr:postcode":"kw16 3ag",
    "addr:street":"North End Rd",
    "iso:country":"GB",
    "sg:address":"North End Rd",
    "sg:city":"Stromness",
    "sg:classifiers":[
        {
            "category":"Government",
            "subcategory":"Police Station",
            "type":"Public Place"
        }
    ],
    "sg:phone":"+44 1856 850222",
    "sg:postcode":"KW16 3AG",
    "sg:province":"Orkney Islands",
    "sg:tags":[
        "support"
    ],
    "wof:name":"Stromness Police Station",
    "wof:placetype":"venue"
},
  "geometry": {"coordinates":[-3.2951519489,58.9672622681],"type":"Point"}
}