{
  "type": "Feature",
  "properties": {
    "iso:country":"GB",
    "sg:address":"35 West Bars",
    "sg:city":"Chesterfield",
    "sg:classifiers":[
        {
            "category":"Personal",
            "subcategory":"Beauty Salon",
            "type":"Services"
        }
    ],
    "sg:phone":"+44 1246 278488",
    "sg:postcode":"S40 1AG",
    "sg:province":"Derbyshire",
    "sg:tags":[
        "unisex",
        "hairdresser"
    ],
    "wof:name":"Vanity Hair Styles",
    "wof:placetype":"venue"
},
  "geometry": {"coordinates":[-1.434054,53.235668],"type":"Point"}
}