{
  "type": "Feature",
  "properties": {
    "iso:country":"GB",
    "sg:address":"Windy Goll Farm, Carlops",
    "sg:city":"Penicuik",
    "sg:classifiers":[
        {
            "category":"Sports & Exercise",
            "subcategory":"Stables",
            "type":"Entertainment"
        }
    ],
    "sg:postcode":"EH26 9NL",
    "sg:province":"Midlothian",
    "sg:tags":[
        "education",
        "equestrian"
    ],
    "wof:name":"Pentland Hills Icelandic Trekking Centre",
    "wof:placetype":"venue"
},
  "geometry": {"coordinates":[-3.338737011,55.7916145325],"type":"Point"}
}