{
  "type": "Feature",
  "properties": {
    "iso:country":"GB",
    "sg:address":"Essentec House, Pool Lane, Brocton",
    "sg:city":"Stafford",
    "sg:classifiers":[
        {
            "category":"Shopping",
            "subcategory":"Computers & Home Electronics",
            "type":"Retail Goods"
        }
    ],
    "sg:phone":"+44 1785 666941",
    "sg:postcode":"ST17 0TY",
    "sg:province":"Staffordshire",
    "wof:name":"Essentec Systems Ltd",
    "wof:placetype":"venue"
},
  "geometry": {"coordinates":[-2.0450739861,52.7743415833],"type":"Point"}
}