{
  "type": "Feature",
  "properties": {
    "addr:full":"161 Glasgow Road, East Kilbride Glasgow South Lanarkshire G74 4PA",
    "addr:housenumber":"161",
    "addr:postcode":"g74 4pa",
    "addr:street":"Glasgow Road",
    "iso:country":"GB",
    "sg:address":"161 Glasgow Road, East Kilbride",
    "sg:city":"Glasgow",
    "sg:classifiers":[
        {
            "category":"Professional",
            "subcategory":"Engineering",
            "type":"Services"
        }
    ],
    "sg:phone":"+44 1355 222525",
    "sg:postcode":"G74 4PA",
    "sg:province":"South Lanarkshire",
    "sg:tags":[
        "consulting",
        "engineer"
    ],
    "wof:name":"The Braes Partnership",
    "wof:placetype":"venue"
},
  "geometry": {"coordinates":[-4.164488,55.786987],"type":"Point"}
}