{
  "type": "Feature",
  "properties": {
    "addr:full":"Minster Chambers, 42-44 Castle Street Salisbury Wiltshire SP1 3TX",
    "addr:housenumber":"42-44",
    "addr:postcode":"sp1 3tx",
    "addr:street":"Castle Street",
    "iso:country":"GB",
    "sg:address":"Minster Chambers, 42-44 Castle Street",
    "sg:city":"Salisbury",
    "sg:classifiers":[
        {
            "category":"Building & Trades",
            "subcategory":"Construction",
            "type":"Services"
        }
    ],
    "sg:postcode":"SP1 3TX",
    "sg:province":"Wiltshire",
    "sg:tags":[
        "builder"
    ],
    "wof:name":"Asbury Associates",
    "wof:placetype":"venue"
},
  "geometry": {"coordinates":[-1.7960499525,51.071269989],"type":"Point"}
}