{
  "type": "Feature",
  "properties": {
    "addr:full":"Unit 3 Cavendish Walk Chesterfield Derbyshire S44 6DB",
    "addr:housenumber":"unit 3",
    "addr:postcode":"s44 6db",
    "addr:street":"Cavendish Walk",
    "iso:country":"GB",
    "sg:address":"Unit 3 Cavendish Walk",
    "sg:city":"Chesterfield",
    "sg:classifiers":[
        {
            "category":"Shopping",
            "subcategory":"Florist",
            "type":"Retail Goods"
        }
    ],
    "sg:phone":"+44 1246 826397",
    "sg:postcode":"S44 6DB",
    "sg:province":"Derbyshire",
    "wof:name":"Flowertalk",
    "wof:placetype":"venue"
},
  "geometry": {"coordinates":[-1.2832039595,53.2251205444],"type":"Point"}
}