{
  "type": "Feature",
  "properties": {
    "iso:country":"GB",
    "sg:address":"Hydan Fawr, Cyfronydd",
    "sg:city":"Welshpool",
    "sg:classifiers":[
        {
            "category":"Building & Trades",
            "subcategory":"Construction",
            "type":"Services"
        }
    ],
    "sg:phone":"+44 1938 850298",
    "sg:postcode":"SY21 9EU",
    "sg:province":"Shropshire",
    "sg:tags":[
        "builder"
    ],
    "wof:name":"E G Lewis",
    "wof:placetype":"venue"
},
  "geometry": {"coordinates":[-3.2677268982,52.6615447998],"type":"Point"}
}