{
  "type": "Feature",
  "properties": {
    "addr:full":"George Street Barnsley South Yorkshire S70 1AX",
    "addr:postcode":"s70 1ax",
    "addr:street":"George Street;Yorkshire",
    "iso:country":"GB",
    "sg:address":"George Street",
    "sg:city":"Barnsley",
    "sg:classifiers":[
        {
            "category":"Place Of Worship",
            "type":"Public Place"
        }
    ],
    "sg:phone":"+44 1226 203730",
    "sg:postcode":"S70 1AX",
    "sg:province":"South Yorkshire",
    "sg:website":"http://www.barnsley.catholicweb.com",
    "wof:name":"Holy Rood R C Church",
    "wof:placetype":"venue"
},
  "geometry": {"coordinates":[-1.484239,53.55022],"type":"Point"}
}