{
  "type": "Feature",
  "properties": {
    "iso:country":"GB",
    "sg:address":"2 Lancaster Avenue",
    "sg:city":"London",
    "sg:classifiers":[
        {
            "category":"Social Services",
            "subcategory":"Retirement Home",
            "type":"Services"
        }
    ],
    "sg:phone":"+44 20 8946 0369",
    "sg:postcode":"SW19 5DE",
    "sg:province":"Greater London",
    "sg:tags":[
        "residential",
        "care"
    ],
    "wof:name":"Lee House Wimbledon",
    "wof:placetype":"venue"
},
  "geometry": {"coordinates":[-0.2175980061,51.4271888733],"type":"Point"}
}