{
  "type": "Feature",
  "properties": {
    "addr:full":"A30, Yeovil Rd Crewkerne Dorset TA18 7NS",
    "addr:postcode":"ta18 7ns",
    "addr:street":"Yeovil Rd",
    "iso:country":"GB",
    "sg:address":"A30, Yeovil Rd",
    "sg:city":"Crewkerne",
    "sg:classifiers":[
        {
            "category":"Autos & Motor Vehicles",
            "subcategory":"Fuel & Gas Station",
            "type":"Retail Goods"
        }
    ],
    "sg:phone":"+44 1460 72234",
    "sg:postcode":"TA18 7NS",
    "sg:province":"Dorset",
    "sg:tags":[
        "petrol",
        "filling"
    ],
    "wof:name":"Haselbury Firs",
    "wof:placetype":"venue"
},
  "geometry": {"coordinates":[-2.7742640972,50.8927841187],"type":"Point"}
}