{
  "type": "Feature",
  "properties": {
    "addr:full":"116a High Street Poole Dorset BH15 1DF",
    "addr:housenumber":"116a",
    "addr:postcode":"bh15 1df",
    "addr:street":"High Street",
    "iso:country":"GB",
    "sg:address":"116a High Street",
    "sg:city":"Poole",
    "sg:classifiers":[
        {
            "category":"Retail",
            "subcategory":"Laundry & Dry Cleaning",
            "type":"Services"
        }
    ],
    "sg:phone":"+44 1202 674310",
    "sg:postcode":"BH15 1DF",
    "sg:province":"Dorset",
    "sg:tags":[
        "alteration"
    ],
    "wof:name":"Johnsons",
    "wof:placetype":"venue"
},
  "geometry": {"coordinates":[-1.9838550091,50.7159919739],"type":"Point"}
}