{
  "type": "Feature",
  "properties": {
    "iso:country":"GB",
    "sg:address":"Treetops, Place La",
    "sg:city":"Newton Abbot",
    "sg:classifiers":[
        {
            "category":"Building & Trades",
            "subcategory":"Construction",
            "type":"Services"
        }
    ],
    "sg:phone":"+44 1364 652152",
    "sg:postcode":"TQ13 7EP",
    "sg:province":"Devon",
    "sg:tags":[
        "builder"
    ],
    "wof:name":"D J Cole",
    "wof:placetype":"venue"
},
  "geometry": {"coordinates":[-3.74676,50.525101],"type":"Point"}
}