{
  "type": "Feature",
  "properties": {
    "iso:country":"GB",
    "sg:address":"156 Greenbank Rd",
    "sg:city":"Edinburgh",
    "sg:classifiers":[
        {
            "category":"Building & Trades",
            "subcategory":"Plumbing",
            "type":"Services"
        }
    ],
    "sg:phone":"+44 131 447 9833",
    "sg:postcode":"EH10 5RN",
    "sg:province":"City of Edinburgh",
    "sg:tags":[
        "heating"
    ],
    "wof:name":"Shower Services East",
    "wof:placetype":"venue"
},
  "geometry": {"coordinates":[-3.2194230556,55.9122848511],"type":"Point"}
}