{
  "type": "Feature",
  "properties": {
    "addr:full":"The Griffin Alley, Rear Of 18 High Street Malmesbury Wiltshire SN16 9AU",
    "addr:housenumber":"rear of 18",
    "addr:postcode":"sn16 9au",
    "addr:street":"High Street",
    "iso:country":"GB",
    "sg:address":"The Griffin Alley, Rear Of 18 High Street",
    "sg:city":"Malmesbury",
    "sg:classifiers":[
        {
            "category":"Personal",
            "subcategory":"Barber",
            "type":"Services"
        }
    ],
    "sg:phone":"+44 1666 822057",
    "sg:postcode":"SN16 9AU",
    "sg:province":"Wiltshire",
    "sg:tags":[
        "men's",
        "hairdresser"
    ],
    "wof:name":"Elmers Salon",
    "wof:placetype":"venue"
},
  "geometry": {"coordinates":[-2.097419,51.582245],"type":"Point"}
}