{
  "type": "Feature",
  "properties": {
    "iso:country":"GB",
    "sg:address":"Greenacres, Moss Side",
    "sg:city":"Nairn",
    "sg:classifiers":[
        {
            "category":"Retail",
            "subcategory":"Driving School",
            "type":"Services"
        }
    ],
    "sg:phone":"+44 1667 452516",
    "sg:postcode":"IV12 5NZ",
    "sg:province":"Highland",
    "wof:name":"Nairn School Of Motoring",
    "wof:placetype":"venue"
},
  "geometry": {"coordinates":[-3.911094,57.572136],"type":"Point"}
}