{
  "type": "Feature",
  "properties": {
    "addr:full":"2-4 Laneham St Scunthorpe Lincolnshire DN15 6LJ",
    "addr:housenumber":"2-4",
    "addr:postcode":"dn15 6lj",
    "addr:street":"Laneham St",
    "iso:country":"GB",
    "sg:address":"2-4 Laneham St",
    "sg:city":"Scunthorpe",
    "sg:classifiers":[
        {
            "category":"Professional",
            "subcategory":"Art Services",
            "type":"Services"
        }
    ],
    "sg:phone":"+44 1724 278662",
    "sg:postcode":"DN15 6LJ",
    "sg:province":"Lincolnshire",
    "sg:tags":[
        "picture",
        "restoration"
    ],
    "wof:name":"The Factory Framing Shop",
    "wof:placetype":"venue"
},
  "geometry": {"coordinates":[-0.6520320177,53.5909919739],"type":"Point"}
}