{
  "type": "Feature",
  "properties": {
    "iso:country":"GB",
    "sg:address":"Units 3a & 3b Moss Road, Industrial Estate East",
    "sg:city":"Witham",
    "sg:classifiers":[
        {
            "category":"Freight",
            "type":"Transportation"
        }
    ],
    "sg:phone":"+44 1376 502612",
    "sg:postcode":"CM8 3UQ",
    "sg:province":"Essex",
    "sg:tags":[
        "forwarders"
    ],
    "wof:name":"Inter Forward Freight Services Ltd.",
    "wof:placetype":"venue"
},
  "geometry": {"coordinates":[0.650368,51.804039],"type":"Point"}
}