{
  "type": "Feature",
  "properties": {
    "addr:full":"69 Wentwood View Caldicot Monmouthshire NP26 4QH",
    "addr:housenumber":"69",
    "addr:postcode":"np26 4qh",
    "addr:street":"Wentwood View",
    "iso:country":"GB",
    "sg:address":"69 Wentwood View",
    "sg:city":"Caldicot",
    "sg:classifiers":[
        {
            "category":"Personal",
            "type":"Services"
        },
        {
            "category":"Professional",
            "subcategory":"Lawyer & Legal Services",
            "type":"Services"
        }
    ],
    "sg:phone":"+44 1291 424933",
    "sg:postcode":"NP26 4QH",
    "sg:province":"Monmouthshire",
    "sg:tags":[
        "advice",
        "counselling"
    ],
    "wof:name":"Joyce Dallimore",
    "wof:placetype":"venue"
},
  "geometry": {"coordinates":[-2.754175,51.598595],"type":"Point"}
}