{
  "type": "Feature",
  "properties": {
    "iso:country":"GB",
    "sg:address":"9 Melton Rd",
    "sg:city":"Oakham",
    "sg:classifiers":[
        {
            "category":"Food & Beverages",
            "subcategory":"Fruits & Vegetables",
            "type":"Retail Goods"
        }
    ],
    "sg:postcode":"LE15 6AX",
    "sg:province":"Leicestershire",
    "sg:tags":[
        "greengrocer"
    ],
    "wof:name":"Rutland Produce",
    "wof:placetype":"venue"
},
  "geometry": {"coordinates":[-0.733021,52.670696],"type":"Point"}
}