{
  "type": "Feature",
  "properties": {
    "addr:full":"Tidkinhow Farm, Boosbeck Saltburn-by-the-sea North Yorkshire TS12 3DH",
    "addr:postcode":"ts12 3dh",
    "iso:country":"GB",
    "sg:address":"Tidkinhow Farm, Boosbeck",
    "sg:city":"Saltburn-by-the-sea",
    "sg:classifiers":[
        {
            "category":"Professional",
            "subcategory":"Computer Services",
            "type":"Services"
        }
    ],
    "sg:phone":"+44 1287 637655",
    "sg:postcode":"TS12 3DH",
    "sg:province":"North Yorkshire",
    "sg:tags":[
        "system",
        "software"
    ],
    "wof:name":"Spectro Systems Ltd.",
    "wof:placetype":"venue"
},
  "geometry": {"coordinates":[-0.9833869934,54.5459251404],"type":"Point"}
}