{
  "type": "Feature",
  "properties": {
    "addr:full":"Quakers Place, Standish Wigan Lancashire WN6 0TQ",
    "addr:postcode":"wn6 0tq",
    "addr:street":"Quakers Place",
    "iso:country":"GB",
    "sg:address":"Quakers Place, Standish",
    "sg:city":"Wigan",
    "sg:classifiers":[
        {
            "category":"Restaurant",
            "type":"Food & Drink"
        }
    ],
    "sg:phone":"+44 1257 422400",
    "sg:postcode":"WN6 0TQ",
    "sg:province":"Lancashire",
    "wof:name":"Milano Restaurant",
    "wof:placetype":"venue"
},
  "geometry": {"coordinates":[-2.6634008884,53.5860214233],"type":"Point"}
}