{
  "type": "Feature",
  "properties": {
    "iso:country":"GB",
    "sg:address":"341 Southport Rd",
    "sg:city":"Liverpool",
    "sg:classifiers":[
        {
            "category":"Food & Beverages",
            "subcategory":"Candy",
            "type":"Retail Goods"
        }
    ],
    "sg:phone":"+44 151 531 0445",
    "sg:postcode":"L31 4EE",
    "sg:province":"Lancashire",
    "sg:tags":[
        "merchant",
        "produce"
    ],
    "wof:name":"J B Hurst",
    "wof:placetype":"venue"
},
  "geometry": {"coordinates":[-2.959329,53.535549],"type":"Point"}
}