{
  "type": "Feature",
  "properties": {
    "addr:full":"38 Poulton Rd Wallasey Merseyside CH44 9DQ",
    "addr:housenumber":"38",
    "addr:postcode":"ch44 9dq",
    "addr:street":"Poulton Rd",
    "iso:country":"GB",
    "sg:address":"38 Poulton Rd",
    "sg:city":"Wallasey",
    "sg:classifiers":[
        {
            "category":"Professional",
            "subcategory":"Business Services",
            "type":"Services"
        }
    ],
    "sg:postcode":"CH44 9DQ",
    "sg:province":"Merseyside",
    "sg:tags":[
        "import",
        "export",
        "agent"
    ],
    "wof:name":"Bold,Thomas,",
    "wof:placetype":"venue"
},
  "geometry": {"coordinates":[-3.028161,53.412235],"type":"Point"}
}