{
  "type": "Feature",
  "properties": {
    "addr:full":"Station House, 2-6 Station Approach Harpenden Hertfordshire AL5 4SS",
    "addr:housenumber":"2-6",
    "addr:postcode":"al5 4ss",
    "addr:street":"Station Approach",
    "iso:country":"GB",
    "sg:address":"Station House, 2-6 Station Approach",
    "sg:city":"Harpenden",
    "sg:classifiers":[
        {
            "category":"Food & Beverages",
            "subcategory":"Liquor & Beverages",
            "type":"Retail Goods"
        }
    ],
    "sg:phone":"+44 1582 768809",
    "sg:postcode":"AL5 4SS",
    "sg:province":"Hertfordshire",
    "sg:tags":[
        "drink",
        "soft"
    ],
    "wof:name":"Brooklyn Brewed Soda Co. Ltd.",
    "wof:placetype":"venue"
},
  "geometry": {"coordinates":[-0.352106005,51.815864563],"type":"Point"}
}