{
  "type": "Feature",
  "properties": {
    "addr:full":"756 Anniesland Road Glasgow Glasgow City G14 0YU",
    "addr:housenumber":"756",
    "addr:postcode":"g14 0yu",
    "addr:street":"Anniesland Road",
    "iso:country":"GB",
    "sg:address":"756 Anniesland Road",
    "sg:city":"Glasgow",
    "sg:classifiers":[
        {
            "category":"Shopping",
            "subcategory":"News",
            "type":"Retail Goods"
        }
    ],
    "sg:phone":"+44 141 954 5660",
    "sg:postcode":"G14 0YU",
    "sg:province":"Glasgow City",
    "sg:tags":[
        "newsagent"
    ],
    "wof:name":"Knightswood Newsagent",
    "wof:placetype":"venue"
},
  "geometry": {"coordinates":[-4.359655,55.885765],"type":"Point"}
}