{
  "type": "Feature",
  "properties": {
    "iso:country":"GB",
    "sg:address":"Hilda Rd",
    "sg:city":"Canning Town",
    "sg:classifiers":[
        {
            "category":"Community Center",
            "subcategory":"Youth",
            "type":"Public Place"
        }
    ],
    "sg:phone":"+44 20 7476 6835",
    "sg:postcode":"E16 4NW",
    "sg:province":"Greater London",
    "sg:tags":[
        "organisation",
        "centre"
    ],
    "wof:name":"Eastlea Youth Centre",
    "wof:placetype":"venue"
},
  "geometry": {"coordinates":[0.009595,51.522629],"type":"Point"}
}