{
  "type": "Feature",
  "properties": {
    "addr:full":"4 Blackburn Road, Rishton Blackburn Lancashire BB1 4BS",
    "addr:housenumber":"4",
    "addr:postcode":"bb1 4bs",
    "addr:street":"Blackburn Road",
    "iso:country":"GB",
    "sg:address":"4 Blackburn Road, Rishton",
    "sg:city":"Blackburn",
    "sg:classifiers":[
        {
            "category":"Social Services",
            "type":"Services"
        }
    ],
    "sg:phone":"+44 1254 887124",
    "sg:postcode":"BB1 4BS",
    "sg:province":"Lancashire",
    "wof:name":"District Purchasing Team",
    "wof:placetype":"venue"
},
  "geometry": {"coordinates":[-2.4176440239,53.7680168152],"type":"Point"}
}