{
  "type": "Feature",
  "properties": {
    "addr:full":"147b High St Sevenoaks Kent TN13 1XJ",
    "addr:housenumber":"147b",
    "addr:postcode":"tn13 1xj",
    "addr:street":"High St",
    "iso:country":"GB",
    "sg:address":"147b High St",
    "sg:city":"Sevenoaks",
    "sg:classifiers":[
        {
            "category":"Professional",
            "subcategory":"Business Services",
            "type":"Services"
        }
    ],
    "sg:phone":"+44 1732 457509",
    "sg:postcode":"TN13 1XJ",
    "sg:province":"Kent",
    "sg:tags":[
        "tile",
        "stockist"
    ],
    "wof:name":"Swan Bath & Tile Centre",
    "wof:placetype":"venue"
},
  "geometry": {"coordinates":[0.192524,51.273071],"type":"Point"}
}