{
  "type": "Feature",
  "properties": {
    "iso:country":"GB",
    "sg:address":"141 Greenlee Garth",
    "sg:city":"Newton Aycliffe",
    "sg:classifiers":[
        {
            "category":"Communications",
            "type":"Services"
        }
    ],
    "sg:phone":"+44 1325 301470",
    "sg:postcode":"DL5 7EX",
    "sg:province":"Durham",
    "sg:tags":[
        "tv",
        "video",
        "radio"
    ],
    "wof:name":"Elliotts Satellites",
    "wof:placetype":"venue"
},
  "geometry": {"coordinates":[-1.5954910517,54.6250076294],"type":"Point"}
}