{
  "type": "Feature",
  "properties": {
    "iso:country":"GB",
    "sg:address":"Poppyfields, Haine Road",
    "sg:city":"Ramsgate",
    "sg:classifiers":[
        {
            "category":"Building & Trades",
            "subcategory":"Construction",
            "type":"Services"
        }
    ],
    "sg:phone":"+44 1843 590731",
    "sg:postcode":"CT12 5ET",
    "sg:province":"Kent",
    "sg:tags":[
        "builder"
    ],
    "wof:name":"Bedford Brickwork",
    "wof:placetype":"venue"
},
  "geometry": {"coordinates":[1.38515,51.34763],"type":"Point"}
}