{
  "type": "Feature",
  "properties": {
    "iso:country":"GB",
    "sg:address":"Wilstrop Hall Farm, Wilstrop, Grn Hammerton",
    "sg:city":"York",
    "sg:classifiers":[
        {
            "category":"Farming",
            "subcategory":"Livestock Farm",
            "type":"Manufacturing & Wholesale Goods"
        }
    ],
    "sg:phone":"+44 1423 330215",
    "sg:postcode":"YO26 8HA",
    "sg:province":"North Yorkshire",
    "sg:tags":[
        "others"
    ],
    "wof:name":"Blacker,Robin & Gillian,",
    "wof:placetype":"venue"
},
  "geometry": {"coordinates":[-1.3057579994,54.0061454773],"type":"Point"}
}