{
  "type": "Feature",
  "properties": {
    "iso:country":"GB",
    "sg:address":"38-40 Queen Street",
    "sg:city":"Penzance",
    "sg:classifiers":[
        {
            "category":"Professional",
            "subcategory":"Management & Consulting",
            "type":"Services"
        }
    ],
    "sg:postcode":"TR18 4BH",
    "sg:province":"Cornwall",
    "sg:tags":[
        "consultant",
        "business"
    ],
    "wof:name":"Museum Street Buildings Ltd.",
    "wof:placetype":"venue"
},
  "geometry": {"coordinates":[-5.535929,50.116982],"type":"Point"}
}