{
  "type": "Feature",
  "properties": {
    "addr:full":"38-40 Queen Street Penzance Cornwall TR18 4BH",
    "addr:housenumber":"38-40",
    "addr:postcode":"tr18 4bh",
    "addr:street":"Queen Street",
    "iso:country":"GB",
    "sg:address":"38-40 Queen Street",
    "sg:city":"Penzance",
    "sg:classifiers":[
        {
            "category":"Professional",
            "subcategory":"Management & Consulting",
            "type":"Services"
        }
    ],
    "sg:postcode":"TR18 4BH",
    "sg:province":"Cornwall",
    "sg:tags":[
        "consultant",
        "business"
    ],
    "wof:name":"Museum Street Buildings Ltd.",
    "wof:placetype":"venue"
},
  "geometry": {"coordinates":[-5.535929,50.116982],"type":"Point"}
}