{
  "type": "Feature",
  "properties": {
    "iso:country":"GB",
    "sg:address":"School Of The Environment, De Montfort University",
    "sg:city":"Leicester",
    "sg:classifiers":[
        {
            "category":"Health Services",
            "subcategory":"Doctor",
            "type":"Services"
        },
        {
            "category":"Health Services",
            "subcategory":"Clinic",
            "type":"Services"
        }
    ],
    "sg:phone":"+44 116 257 7416",
    "sg:postcode":"LE1 9BH",
    "sg:province":"Leicestershire",
    "sg:tags":[
        "nh",
        "practitioners"
    ],
    "wof:name":"Cad Centre",
    "wof:placetype":"venue"
},
  "geometry": {"coordinates":[-1.140365,52.637886],"type":"Point"}
}