{
  "type": "Feature",
  "properties": {
    "addr:full":"1 Lincoln Inn Fields London Greater London WC2A 3AA",
    "addr:housenumber":"1",
    "addr:postcode":"wc2a 3aa",
    "addr:street":"Inn Fields",
    "iso:country":"GB",
    "sg:address":"1 Lincoln Inn Fields",
    "sg:city":"London",
    "sg:classifiers":[
        {
            "category":"Real Estate",
            "subcategory":"Real Estate Agent",
            "type":"Services"
        }
    ],
    "sg:postcode":"WC2A 3AA",
    "sg:province":"Greater London",
    "wof:name":"Prince Estates Ltd.",
    "wof:placetype":"venue"
},
  "geometry": {"coordinates":[-0.1184919998,51.5166473389],"type":"Point"}
}