{
  "type": "Feature",
  "properties": {
    "addr:full":"Bordars Rd Hanwell Greater London W7 1AG",
    "addr:postcode":"w7 1ag",
    "addr:street":"Bordars Rd",
    "iso:country":"GB",
    "sg:address":"Bordars Rd",
    "sg:city":"Hanwell",
    "sg:classifiers":[
        {
            "category":"Place Of Worship",
            "type":"Public Place"
        }
    ],
    "sg:phone":"+44 20 8578 2796",
    "sg:postcode":"W7 1AG",
    "sg:province":"Greater London",
    "wof:name":"St Christopher C of E Church",
    "wof:placetype":"venue"
},
  "geometry": {"coordinates":[-0.332369,51.523441],"type":"Point"}
}