{
  "type": "Feature",
  "properties": {
    "iso:country":"GB",
    "sg:address":"1 Hilary Drive",
    "sg:city":"Crowthorne",
    "sg:classifiers":[
        {
            "category":"Autos & Motor Vehicles",
            "subcategory":"Recreational Vehicle Sales",
            "type":"Retail Goods"
        }
    ],
    "sg:phone":"+44 1344 774187",
    "sg:postcode":"RG45 6QF",
    "sg:province":"Berkshire",
    "sg:tags":[
        "caravan"
    ],
    "wof:name":"Damp & Damaged",
    "wof:placetype":"venue"
},
  "geometry": {"coordinates":[-0.7976970077,51.3769836426],"type":"Point"}
}