{
  "type": "Feature",
  "properties": {
    "iso:country":"GB",
    "sg:address":"74 Welcroft Rd",
    "sg:city":"Welwyn Garden City",
    "sg:classifiers":[
        {
            "category":"Building & Trades",
            "subcategory":"Plumbing",
            "type":"Services"
        }
    ],
    "sg:postcode":"AL7 3JY",
    "sg:province":"Hertfordshire",
    "sg:tags":[
        "central",
        "heating"
    ],
    "wof:name":"Fuller Heating",
    "wof:placetype":"venue"
},
  "geometry": {"coordinates":[-0.184061,51.792709],"type":"Point"}
}