{
  "type": "Feature",
  "properties": {
    "addr:full":"3 Esme House The Surgery, Ludovick Walk Putney Greater London SW15 5LJ",
    "addr:housenumber":"3",
    "addr:postcode":"sw15 5lj",
    "addr:street":"Esme House;Ludovick Walk",
    "iso:country":"GB",
    "sg:address":"3 Esme House The Surgery, Ludovick Walk",
    "sg:city":"Putney",
    "sg:classifiers":[
        {
            "category":"Health Services",
            "subcategory":"Doctor",
            "type":"Services"
        }
    ],
    "sg:phone":"+44 20 8878 0952",
    "sg:postcode":"SW15 5LJ",
    "sg:province":"Greater London",
    "sg:tags":[
        "practitioners"
    ],
    "wof:name":"Weeks, R",
    "wof:placetype":"venue"
},
  "geometry": {"coordinates":[-0.215624,51.463654],"type":"Point"}
}