{
  "type": "Feature",
  "properties": {
    "addr:full":"Bank Chambers, 9 Kensington Bishop Auckland Durham DL14 6HX",
    "addr:housenumber":"9",
    "addr:postcode":"dl14 6hx",
    "addr:street":"Kensington Bishop",
    "iso:country":"GB",
    "sg:address":"Bank Chambers, 9 Kensington",
    "sg:city":"Bishop Auckland",
    "sg:classifiers":[
        {
            "category":"Banks & Credit Unions",
            "subcategory":"Financial Services",
            "type":"Services"
        }
    ],
    "sg:phone":"+44 1388 458919",
    "sg:postcode":"DL14 6HX",
    "sg:province":"Durham",
    "sg:tags":[
        "adviser",
        "independent"
    ],
    "wof:name":"Pace Financial Services Ltd",
    "wof:placetype":"venue"
},
  "geometry": {"coordinates":[-1.680494,54.650101],"type":"Point"}
}