{
  "type": "Feature",
  "properties": {
    "addr:full":"33 Bennerley Rd Battersea Greater London SW11 6DR",
    "addr:housenumber":"33",
    "addr:postcode":"sw11 6dr",
    "addr:street":"Bennerley Rd",
    "iso:country":"GB",
    "sg:address":"33 Bennerley Rd",
    "sg:city":"Battersea",
    "sg:classifiers":[
        {
            "category":"Recreation",
            "subcategory":"Gun Range",
            "type":"Entertainment"
        }
    ],
    "sg:phone":"+44 20 7228 2331",
    "sg:postcode":"SW11 6DR",
    "sg:province":"Greater London",
    "sg:tags":[
        "operator",
        "tour"
    ],
    "wof:name":"Snow Zone",
    "wof:placetype":"venue"
},
  "geometry": {"coordinates":[-0.1683129966,51.4576911926],"type":"Point"}
}