{
  "type": "Feature",
  "properties": {
    "iso:country":"GB",
    "sg:address":"69 High Street, Gorleston",
    "sg:city":"Great Yarmouth",
    "sg:classifiers":[
        {
            "category":"Shopping",
            "subcategory":"Florist",
            "type":"Retail Goods"
        }
    ],
    "sg:phone":"+44 1493 662093",
    "sg:postcode":"NR31 6RQ",
    "sg:province":"Norfolk",
    "wof:name":"W J White",
    "wof:placetype":"venue"
},
  "geometry": {"coordinates":[1.728934,52.581017],"type":"Point"}
}