{
  "type": "Feature",
  "properties": {
    "addr:full":"7a Commerce Way Letchworth Hertfordshire SG6 3DN",
    "addr:housenumber":"7a",
    "addr:postcode":"sg6 3dn",
    "addr:street":"Commerce Way",
    "iso:country":"GB",
    "sg:address":"7a Commerce Way",
    "sg:city":"Letchworth",
    "sg:classifiers":[
        {
            "category":"Real Estate",
            "subcategory":"Real Estate Agent",
            "type":"Services"
        }
    ],
    "sg:phone":"+44 1462 480281",
    "sg:postcode":"SG6 3DN",
    "sg:province":"Hertfordshire",
    "wof:name":"Letchworth Shopping Centre",
    "wof:placetype":"venue"
},
  "geometry": {"coordinates":[-0.2222429961,51.9725494385],"type":"Point"}
}