{
  "type": "Feature",
  "properties": {
    "addr:full":"17 Pightle Close, Elmswell Bury St Edmunds Suffolk IP30 9EJ",
    "addr:housenumber":"17",
    "addr:postcode":"ip30 9ej",
    "addr:street":"Pightle Close",
    "iso:country":"GB",
    "sg:address":"17 Pightle Close, Elmswell",
    "sg:city":"Bury St Edmunds",
    "sg:classifiers":[
        {
            "category":"Professional",
            "subcategory":"Accounting & Tax Preparation",
            "type":"Services"
        }
    ],
    "sg:phone":"+44 1359 242284",
    "sg:postcode":"IP30 9EJ",
    "sg:province":"Suffolk",
    "sg:tags":[
        "accountant"
    ],
    "wof:name":"Tax Assist Direct",
    "wof:placetype":"venue"
},
  "geometry": {"coordinates":[0.9078050256,52.2352714539],"type":"Point"}
}