{
  "type": "Feature",
  "properties": {
    "addr:full":"Falcon Road, Ponders End Enfield Greater London EN3 4LS",
    "addr:postcode":"en3 4ls",
    "addr:street":"Falcon Road",
    "iso:country":"GB",
    "sg:address":"Falcon Road, Ponders End",
    "sg:city":"Enfield",
    "sg:classifiers":[
        {
            "category":"Professional",
            "subcategory":"Engineering",
            "type":"Services"
        },
        {
            "category":"Building & Trades",
            "subcategory":"Construction",
            "type":"Services"
        }
    ],
    "sg:phone":"+44 20 8443 2433",
    "sg:postcode":"EN3 4LS",
    "sg:province":"Greater London",
    "sg:tags":[
        "civil",
        "engineer",
        "contractor"
    ],
    "wof:name":"Wedge Contracts Ltd.",
    "wof:placetype":"venue"
},
  "geometry": {"coordinates":[-0.041579,51.642635],"type":"Point"}
}