{
  "type": "Feature",
  "properties": {
    "addr:full":"54 Springfield Road, Rowde Devizes Wiltshire SN10 2PB",
    "addr:housenumber":"54",
    "addr:postcode":"sn10 2pb",
    "addr:street":"Springfield Road",
    "iso:country":"GB",
    "sg:address":"54 Springfield Road, Rowde",
    "sg:city":"Devizes",
    "sg:classifiers":[
        {
            "category":"Professional",
            "subcategory":"Art Services",
            "type":"Services"
        },
        {
            "category":"Building & Trades",
            "subcategory":"Construction",
            "type":"Services"
        }
    ],
    "sg:phone":"+44 1380 723037",
    "sg:postcode":"SN10 2PB",
    "sg:province":"Wiltshire",
    "sg:tags":[
        "decorator",
        "painter"
    ],
    "wof:name":"Robert Hayter",
    "wof:placetype":"venue"
},
  "geometry": {"coordinates":[-2.0291678905,51.361240387],"type":"Point"}
}