{
  "type": "Feature",
  "properties": {
    "iso:country":"GB",
    "sg:address":"Sandwickhill School, East St",
    "sg:city":"Isle Of Lewis",
    "sg:classifiers":[
        {
            "category":"Government",
            "subcategory":"Office",
            "type":"Public Place"
        }
    ],
    "sg:phone":"+44 1851 703300",
    "sg:postcode":"HS2 0AG",
    "sg:province":"Eilean Siar",
    "sg:tags":[
        "local"
    ],
    "wof:name":"Comhairle Nan Eilean Siar",
    "wof:placetype":"venue"
},
  "geometry": {"coordinates":[-6.301189,58.290138],"type":"Point"}
}