{
  "type": "Feature",
  "properties": {
    "iso:country":"GB",
    "sg:address":"Vicarage Fields Surgery, Vicarage Field",
    "sg:city":"Hailsham",
    "sg:classifiers":[
        {
            "category":"Health Services",
            "subcategory":"Doctor",
            "type":"Services"
        }
    ],
    "sg:phone":"+44 1323 441155",
    "sg:postcode":"BN27 1BE",
    "sg:province":"East Sussex",
    "sg:tags":[
        "practitioners"
    ],
    "wof:name":"Tourle, C",
    "wof:placetype":"venue"
},
  "geometry": {"coordinates":[0.259073,50.863613],"type":"Point"}
}