{
  "type": "Feature",
  "properties": {
    "addr:full":"117a Aughton Street Ormskirk Lancashire L39 3BN",
    "addr:housenumber":"117a",
    "addr:postcode":"l39 3bn",
    "addr:street":"Aughton Street",
    "iso:country":"GB",
    "sg:address":"117a Aughton Street",
    "sg:city":"Ormskirk",
    "sg:classifiers":[
        {
            "category":"Shopping",
            "subcategory":"Hobbies, Toys, & Games",
            "type":"Retail Goods"
        }
    ],
    "sg:postcode":"L39 3BN",
    "sg:province":"Lancashire",
    "sg:tags":[
        "collectors'",
        "item"
    ],
    "wof:name":"Collectors Corner",
    "wof:placetype":"venue"
},
  "geometry": {"coordinates":[-2.89005,53.564621],"type":"Point"}
}