{
  "type": "Feature",
  "properties": {
    "iso:country":"GB",
    "sg:address":"13 Steep Hill",
    "sg:city":"Lincoln",
    "sg:classifiers":[
        {
            "category":"Shopping",
            "subcategory":"Books",
            "type":"Retail Goods"
        }
    ],
    "sg:phone":"+44 1522 543217",
    "sg:postcode":"LN2 1LT",
    "sg:province":"Lincolnshire",
    "sg:tags":[
        "bookseller",
        "retailer"
    ],
    "wof:name":"Readers Rest",
    "wof:placetype":"venue"
},
  "geometry": {"coordinates":[-0.538628,53.232971],"type":"Point"}
}