{
  "type": "Feature",
  "properties": {
    "addr:full":"4 Graingerville North, Westgate Rd Newcastle Upon Tyne Tyne and Wear NE4 6UJ",
    "addr:housenumber":"4",
    "addr:postcode":"ne4 6uj",
    "addr:street":"Graingerville North Westgate Rd",
    "iso:country":"GB",
    "sg:address":"4 Graingerville North, Westgate Rd",
    "sg:city":"Newcastle Upon Tyne",
    "sg:classifiers":[
        {
            "category":"Health Services",
            "subcategory":"Clinic",
            "type":"Services"
        }
    ],
    "sg:phone":"+44 191 219 5239",
    "sg:postcode":"NE4 6UJ",
    "sg:province":"Tyne and Wear",
    "sg:tags":[
        "planning",
        "family",
        "centre"
    ],
    "wof:name":"Graingerville Family Planning Clinic",
    "wof:placetype":"venue"
},
  "geometry": {"coordinates":[-1.6419299841,54.97397995],"type":"Point"}
}