{
  "type": "Feature",
  "properties": {
    "addr:full":"52 Whalley Road Accrington Lancashire BB5 1AD",
    "addr:housenumber":"52",
    "addr:postcode":"bb5 1ad",
    "addr:street":"Whalley Road",
    "iso:country":"GB",
    "sg:address":"52 Whalley Road",
    "sg:city":"Accrington",
    "sg:classifiers":[
        {
            "category":"Personal",
            "subcategory":"Beauty Salon",
            "type":"Services"
        }
    ],
    "sg:postcode":"BB5 1AD",
    "sg:province":"Lancashire",
    "sg:tags":[
        "unisex",
        "hairdresser"
    ],
    "wof:name":"Headline",
    "wof:placetype":"venue"
},
  "geometry": {"coordinates":[-2.3642120361,53.75548172],"type":"Point"}
}