{
  "type": "Feature",
  "properties": {
    "addr:full":"50 London Road Bromley Kent BR1 3RA",
    "addr:housenumber":"50",
    "addr:postcode":"br1 3ra",
    "addr:street":"London Road",
    "iso:country":"GB",
    "sg:address":"50 London Road",
    "sg:city":"Bromley",
    "sg:classifiers":[
        {
            "category":"Manufacturing",
            "subcategory":"Petroleum Products",
            "type":"Manufacturing & Wholesale Goods"
        }
    ],
    "sg:postcode":"BR1 3RA",
    "sg:province":"Kent",
    "sg:tags":[
        "double",
        "glazing"
    ],
    "wof:name":"Futura Ltd",
    "wof:placetype":"venue"
},
  "geometry": {"coordinates":[0.0103019997,51.4103851318],"type":"Point"}
}