{
  "type": "Feature",
  "properties": {
    "iso:country":"GB",
    "sg:address":"53 Ealing Bdwy Centre, The Bdwy",
    "sg:city":"London",
    "sg:classifiers":[
        {
            "category":"Shopping",
            "subcategory":"Clothing, Apparel, & Fashions",
            "type":"Retail Goods"
        }
    ],
    "sg:phone":"+44 20 8840 4290",
    "sg:postcode":"W5 5JY",
    "sg:province":"Greater London",
    "sg:tags":[
        "menswear"
    ],
    "wof:name":"Suits You Youngs",
    "wof:placetype":"venue"
},
  "geometry": {"coordinates":[-0.3055199981,51.5106468201],"type":"Point"}
}