{
  "type": "Feature",
  "properties": {
    "iso:country":"GB",
    "sg:address":"101 Victoria Road",
    "sg:city":"Aberdeen",
    "sg:classifiers":[
        {
            "category":"Health Services",
            "subcategory":"Dentist",
            "type":"Services"
        }
    ],
    "sg:phone":"+44 1224 874588",
    "sg:postcode":"AB11 9LX",
    "sg:province":"Aberdeen City",
    "wof:name":"P Murray-Miller",
    "wof:placetype":"venue"
},
  "geometry": {"coordinates":[-2.087184,57.137394],"type":"Point"}
}