{
  "type": "Feature",
  "properties": {
    "addr:full":"Jacobs House, High Street Stockbridge Hampshire SO20 6HF",
    "addr:postcode":"so20 6hf",
    "addr:street":"High Street",
    "iso:country":"GB",
    "sg:address":"Jacobs House, High Street",
    "sg:city":"Stockbridge",
    "sg:classifiers":[
        {
            "category":"Shopping",
            "subcategory":"Antiques",
            "type":"Retail Goods"
        }
    ],
    "sg:postcode":"SO20 6HF",
    "sg:province":"Hampshire",
    "wof:name":"Viney Eliz",
    "wof:placetype":"venue"
},
  "geometry": {"coordinates":[-1.501394,51.115238],"type":"Point"}
}