{
  "type": "Feature",
  "properties": {
    "iso:country":"GB",
    "sg:address":"13 Canyon Rd, Netherton Indstl Est",
    "sg:city":"Wishaw",
    "sg:classifiers":[
        {
            "category":"Professional",
            "subcategory":"Engineering",
            "type":"Services"
        }
    ],
    "sg:postcode":"ML2 0DS",
    "sg:province":"North Lanarkshire",
    "wof:name":"Dewramet J M E Ltd",
    "wof:placetype":"venue"
},
  "geometry": {"coordinates":[-3.951162,55.770973],"type":"Point"}
}