{
  "type": "Feature",
  "properties": {
    "iso:country":"GB",
    "sg:address":"Unit 10 Enterprise Court, Lakes Road",
    "sg:city":"Braintree",
    "sg:classifiers":[
        {
            "category":"Retail",
            "subcategory":"Auto Repair",
            "type":"Services"
        }
    ],
    "sg:postcode":"CM7 3QS",
    "sg:province":"Essex",
    "sg:tags":[
        "engine",
        "car",
        "specialist"
    ],
    "wof:name":"Peter Watkinson Motor Repairs",
    "wof:placetype":"venue"
},
  "geometry": {"coordinates":[0.566165,51.875984],"type":"Point"}
}