{
  "type": "Feature",
  "properties": {
    "iso:country":"GB",
    "sg:address":"Higher Blackpool Farm, Nadder Lane",
    "sg:city":"South Molton",
    "sg:classifiers":[
        {
            "category":"Farming",
            "subcategory":"Livestock Farm",
            "type":"Manufacturing & Wholesale Goods"
        }
    ],
    "sg:phone":"+44 1769 572276",
    "sg:postcode":"EX36 4HR",
    "sg:province":"Devon",
    "sg:tags":[
        "others"
    ],
    "wof:name":"George W Jones",
    "wof:placetype":"venue"
},
  "geometry": {"coordinates":[-3.831824,51.017647],"type":"Point"}
}