{
  "type": "Feature",
  "properties": {
    "addr:full":"6 Chartwell Avenue, Readington Nottingham Nottinghamshire NG11 6DJ",
    "addr:housenumber":"6",
    "addr:postcode":"ng11 6dj",
    "addr:street":"Chartwell Avenue",
    "iso:country":"GB",
    "sg:address":"6 Chartwell Avenue, Readington",
    "sg:city":"Nottingham",
    "sg:classifiers":[
        {
            "category":"Wholesale",
            "subcategory":"Medical Equipment & Supplies",
            "type":"Manufacturing & Wholesale Goods"
        }
    ],
    "sg:phone":"+44 115 921 3833",
    "sg:postcode":"NG11 6DJ",
    "sg:province":"Nottinghamshire",
    "sg:tags":[
        "hospital"
    ],
    "wof:name":"Mercury Safety Products Ltd.",
    "wof:placetype":"venue"
},
  "geometry": {"coordinates":[-1.1559920311,52.8943557739],"type":"Point"}
}