{
  "type": "Feature",
  "properties": {
    "iso:country":"GB",
    "sg:address":"9 Great Queen Street",
    "sg:city":"Dartford",
    "sg:classifiers":[
        {
            "category":"Utilities",
            "subcategory":"Refuse",
            "type":"Services"
        },
        {
            "category":"Utilities",
            "subcategory":"Telephone",
            "type":"Services"
        }
    ],
    "sg:phone":"+44 1322 221388",
    "sg:postcode":"DA1 1TJ",
    "sg:province":"Kent",
    "sg:tags":[
        "disposal",
        "waste",
        "telecommunication",
        "network"
    ],
    "wof:name":"A WINCHESTER & SONS",
    "wof:placetype":"venue"
},
  "geometry": {"coordinates":[0.2252199948,51.4438285828],"type":"Point"}
}