{
  "type": "Feature",
  "properties": {
    "addr:full":"Link House, Knightrider Street Maidstone Kent ME15 6LY",
    "addr:postcode":"me15 6ly",
    "addr:street":"Knightrider Street",
    "iso:country":"GB",
    "sg:address":"Link House, Knightrider Street",
    "sg:city":"Maidstone",
    "sg:classifiers":[
        {
            "category":"Insurance",
            "subcategory":"Insurance Agent",
            "type":"Services"
        }
    ],
    "sg:phone":"+44 1622 683621",
    "sg:postcode":"ME15 6LY",
    "sg:province":"Kent",
    "wof:name":"Link Insurance",
    "wof:placetype":"venue"
},
  "geometry": {"coordinates":[0.524905026,51.2704086304],"type":"Point"}
}