{
  "type": "Feature",
  "properties": {
    "addr:full":"Britannic House, 20 Dunstable Road Luton Bedfordshire LU1 1DY",
    "addr:housenumber":"20",
    "addr:postcode":"lu1 1dy",
    "addr:street":"Dunstable Road",
    "iso:country":"GB",
    "sg:address":"Britannic House, 20 Dunstable Road",
    "sg:city":"Luton",
    "sg:classifiers":[
        {
            "category":"Professional",
            "subcategory":"Lawyer & Legal Services",
            "type":"Services"
        }
    ],
    "sg:phone":"+44 1582 410041",
    "sg:postcode":"LU1 1DY",
    "sg:province":"Bedfordshire",
    "sg:tags":[
        "solicitor"
    ],
    "wof:name":"Giffen Couch & Archer",
    "wof:placetype":"venue"
},
  "geometry": {"coordinates":[-0.4226790071,51.880645752],"type":"Point"}
}