{
  "type": "Feature",
  "properties": {
    "addr:full":"Alderney Works, Ringwood Rd Poole Dorset BH12 4ND",
    "addr:postcode":"bh12 4nd",
    "addr:street":"Ringwood Rd",
    "iso:country":"GB",
    "sg:address":"Alderney Works, Ringwood Rd",
    "sg:city":"Poole",
    "sg:classifiers":[
        {
            "category":"Manufacturing",
            "subcategory":"Building Materials",
            "type":"Manufacturing & Wholesale Goods"
        }
    ],
    "sg:phone":"+44 1202 715253",
    "sg:postcode":"BH12 4ND",
    "sg:province":"Dorset",
    "sg:tags":[
        "tarmac",
        "asphalt"
    ],
    "wof:name":"Tarmac Quarry Products Ltd",
    "wof:placetype":"venue"
},
  "geometry": {"coordinates":[-1.9378839731,50.7489204407],"type":"Point"}
}