{
  "type": "Feature",
  "properties": {
    "addr:full":"185a Moss Lane, Bramhall Stockport Cheshire SK7 1BA",
    "addr:housenumber":"185a",
    "addr:postcode":"sk7 1ba",
    "addr:street":"Moss Lane",
    "iso:country":"GB",
    "sg:address":"185a Moss Lane, Bramhall",
    "sg:city":"Stockport",
    "sg:classifiers":[
        {
            "category":"Conference Center",
            "type":"Public Place"
        }
    ],
    "sg:phone":"+44 161 440 0082",
    "sg:postcode":"SK7 1BA",
    "sg:province":"Cheshire",
    "wof:name":"Spring Innovations Ltd.",
    "wof:placetype":"venue"
},
  "geometry": {"coordinates":[-2.168257,53.357128],"type":"Point"}
}