{
  "type": "Feature",
  "properties": {
    "iso:country":"GB",
    "sg:address":"94 Baillieston Road, Mount Vernon",
    "sg:city":"Glasgow",
    "sg:classifiers":[
        {
            "category":"Autos & Motor Vehicles",
            "subcategory":"Auto Supplies",
            "type":"Retail Goods"
        }
    ],
    "sg:phone":"+44 141 778 1777",
    "sg:postcode":"G32 0TH",
    "sg:province":"Glasgow City",
    "sg:tags":[
        "exhaust",
        "absorber",
        "shock"
    ],
    "wof:name":"Kwik-Fit",
    "wof:placetype":"venue"
},
  "geometry": {"coordinates":[-4.1358098984,55.8501205444],"type":"Point"}
}