{
  "type": "Feature",
  "properties": {
    "iso:country":"GB",
    "sg:address":"Wilburton Farm, Ermington",
    "sg:city":"Ivybridge",
    "sg:classifiers":[
        {
            "category":"Banks & Credit Unions",
            "subcategory":"Investment Brokerage",
            "type":"Services"
        }
    ],
    "sg:phone":"+44 1752 880416",
    "sg:postcode":"PL21 9LB",
    "sg:province":"Devon",
    "sg:tags":[
        "contractor"
    ],
    "wof:name":"E G & Son Hingston",
    "wof:placetype":"venue"
},
  "geometry": {"coordinates":[-3.929039,50.387264],"type":"Point"}
}