{
  "type": "Feature",
  "properties": {
    "iso:country":"GB",
    "sg:address":"Bahama Close, Haydock Industrial Estate, Haydock",
    "sg:city":"St Helens",
    "sg:classifiers":[
        {
            "category":"Retail",
            "subcategory":"Storage",
            "type":"Services"
        }
    ],
    "sg:phone":"+44 1942 271111",
    "sg:postcode":"WA11 9XN",
    "sg:province":"Lancashire",
    "sg:tags":[
        "household",
        "removal"
    ],
    "wof:name":"Bullens Ltd.",
    "wof:placetype":"venue"
},
  "geometry": {"coordinates":[-2.6653439999,53.4742736816],"type":"Point"}
}