{
  "type": "Feature",
  "properties": {
    "iso:country":"GB",
    "sg:address":"5 Alice Howe, Kendal Road",
    "sg:city":"Windermere",
    "sg:classifiers":[
        {
            "category":"Military Area",
            "subcategory":"Army Base",
            "type":"Public Place"
        },
        {
            "category":"Shopping",
            "subcategory":"Crafts & Fabrics",
            "type":"Retail Goods"
        }
    ],
    "sg:phone":"+44 15394 48623",
    "sg:postcode":"LA23 1JG",
    "sg:province":"Cumbria",
    "sg:tags":[
        "supplier",
        "joinery",
        "centre"
    ],
    "wof:name":"D A Joinery",
    "wof:placetype":"venue"
},
  "geometry": {"coordinates":[-2.906404,54.379665],"type":"Point"}
}