{
  "type": "Feature",
  "properties": {
    "iso:country":"GB",
    "sg:address":"43 Parcel Terrace",
    "sg:city":"Derby",
    "sg:classifiers":[
        {
            "category":"Retail",
            "subcategory":"Auto Repair",
            "type":"Services"
        }
    ],
    "sg:phone":"+44 1332 380881",
    "sg:postcode":"DE1 1LY",
    "sg:province":"Derbyshire",
    "sg:tags":[
        "modification",
        "garage"
    ],
    "wof:name":"Technicar",
    "wof:placetype":"venue"
},
  "geometry": {"coordinates":[-1.496864,52.920719],"type":"Point"}
}