{
  "type": "Feature",
  "properties": {
    "addr:full":"5 Dumpdon View, Monkton Honiton Devon EX14 9QJ",
    "addr:housenumber":"5",
    "addr:postcode":"ex14 9qj",
    "addr:street":"Dumpdon View",
    "iso:country":"GB",
    "sg:address":"5 Dumpdon View, Monkton",
    "sg:city":"Honiton",
    "sg:classifiers":[
        {
            "category":"Retail",
            "subcategory":"Auto Repair",
            "type":"Services"
        }
    ],
    "sg:postcode":"EX14 9QJ",
    "sg:province":"Devon",
    "sg:tags":[
        "body",
        "car"
    ],
    "wof:name":"Retrieve Body Repairs",
    "wof:placetype":"venue"
},
  "geometry": {"coordinates":[-3.152688,50.823734],"type":"Point"}
}