{
  "type": "Feature",
  "properties": {
    "addr:full":"7 Osbornes Court, Victoria Place Colchester Essex CO7 0EB",
    "addr:housenumber":"7",
    "addr:postcode":"co7 0eb",
    "addr:street":"Osbornes Court Victoria Place",
    "iso:country":"GB",
    "sg:address":"7 Osbornes Court, Victoria Place",
    "sg:city":"Colchester",
    "sg:classifiers":[
        {
            "category":"Personal",
            "subcategory":"Beauty Salon",
            "type":"Services"
        },
        {
            "category":"Sports & Exercise",
            "subcategory":"Gym",
            "type":"Entertainment"
        }
    ],
    "sg:postcode":"CO7 0EB",
    "sg:province":"Essex",
    "sg:tags":[
        "unisex",
        "hairdresser",
        "health",
        "fitness",
        "centre"
    ],
    "wof:name":"Minims",
    "wof:placetype":"venue"
},
  "geometry": {"coordinates":[1.0251499414,51.8106918335],"type":"Point"}
}