{
  "type": "Feature",
  "properties": {
    "addr:full":"47, Old Market Street Thetford Norfolk IP24 2EQ",
    "addr:housenumber":"47",
    "addr:postcode":"ip24 2eq",
    "addr:street":"Old Market Street",
    "iso:country":"GB",
    "sg:address":"47, Old Market Street",
    "sg:city":"Thetford",
    "sg:classifiers":[
        {
            "category":"Professional",
            "subcategory":"Engineering",
            "type":"Services"
        }
    ],
    "sg:postcode":"IP24 2EQ",
    "sg:province":"Norfolk",
    "sg:tags":[
        "engineer"
    ],
    "wof:name":"Sabco Engineering Ltd",
    "wof:placetype":"venue"
},
  "geometry": {"coordinates":[0.7538260221,52.4104385376],"type":"Point"}
}