{
  "type": "Feature",
  "properties": {
    "addr:full":"13 King Harry Lane St Albans Hertfordshire AL3 4AS",
    "addr:housenumber":"13",
    "addr:postcode":"al3 4as",
    "addr:street":"King Harry Lane",
    "iso:country":"GB",
    "sg:address":"13 King Harry Lane",
    "sg:city":"St Albans",
    "sg:classifiers":[
        {
            "category":"Professional",
            "subcategory":"Management & Consulting",
            "type":"Services"
        }
    ],
    "sg:phone":"+44 1727 843424",
    "sg:postcode":"AL3 4AS",
    "sg:province":"Hertfordshire",
    "sg:tags":[
        "consultant",
        "business"
    ],
    "wof:name":"Mayo Learning International Ltd.",
    "wof:placetype":"venue"
},
  "geometry": {"coordinates":[-0.35135,51.742439],"type":"Point"}
}