{
  "type": "Feature",
  "properties": {
    "addr:full":"Forty Acre Rd Peterborough Cambridgeshire PE1 5PS",
    "addr:postcode":"pe1 5ps",
    "addr:street":"Forty Acre Rd",
    "iso:country":"GB",
    "sg:address":"Forty Acre Rd",
    "sg:city":"Peterborough",
    "sg:classifiers":[
        {
            "category":"Home & Garden",
            "subcategory":"Building Materials",
            "type":"Retail Goods"
        }
    ],
    "sg:phone":"+44 1733 345556",
    "sg:postcode":"PE1 5PS",
    "sg:province":"Cambridgeshire",
    "sg:tags":[
        "ready",
        "mixed",
        "concrete"
    ],
    "wof:name":"RMC Readymix Readicrete",
    "wof:placetype":"venue"
},
  "geometry": {"coordinates":[-0.217164,52.572796],"type":"Point"}
}