{
  "type": "Feature",
  "properties": {
    "iso:country":"GB",
    "sg:address":"Earsham Hall",
    "sg:city":"Bungay",
    "sg:classifiers":[
        {
            "category":"Home & Garden",
            "subcategory":"Furniture",
            "type":"Retail Goods"
        }
    ],
    "sg:postcode":"NR35 2AN",
    "sg:province":"Norfolk",
    "wof:name":"Earsham Hall Pine",
    "wof:placetype":"venue"
},
  "geometry": {"coordinates":[1.416795,52.452564],"type":"Point"}
}