{
  "type": "Feature",
  "properties": {
    "addr:full":"Unit 1 Pacemanor Business Centre, Brookside Uckfield East Sussex TN22 1YA",
    "addr:housenumber":"unit 1",
    "addr:postcode":"tn22 1ya",
    "addr:street":"Pacemanor Business Centre",
    "iso:country":"GB",
    "sg:address":"Unit 1 Pacemanor Business Centre, Brookside",
    "sg:city":"Uckfield",
    "sg:classifiers":[
        {
            "category":"Wholesale",
            "subcategory":"Sporting Goods",
            "type":"Manufacturing & Wholesale Goods"
        }
    ],
    "sg:phone":"+44 1825 762400",
    "sg:postcode":"TN22 1YA",
    "sg:province":"East Sussex",
    "sg:tags":[
        "wholesaler",
        "mnfrs",
        "cycle"
    ],
    "wof:name":"Jim Walker & Co. Ltd.",
    "wof:placetype":"venue"
},
  "geometry": {"coordinates":[0.09665,50.971813],"type":"Point"}
}