{
  "type": "Feature",
  "properties": {
    "addr:full":"The Yard, High Street,indus Est St Austell Cornwall PL26 7SU",
    "addr:postcode":"pl26 7su",
    "addr:street":"High Street;Est",
    "iso:country":"GB",
    "sg:address":"The Yard, High Street,indus Est",
    "sg:city":"St Austell",
    "sg:classifiers":[
        {
            "category":"Wholesale",
            "subcategory":"Scrap",
            "type":"Manufacturing & Wholesale Goods"
        }
    ],
    "sg:phone":"+44 1726 824666",
    "sg:postcode":"PL26 7SU",
    "sg:province":"Cornwall",
    "sg:tags":[
        "breaker",
        "dismantlers"
    ],
    "wof:name":"Nippy Cars",
    "wof:placetype":"venue"
},
  "geometry": {"coordinates":[-4.8586940765,50.343624115],"type":"Point"}
}