{
  "type": "Feature",
  "properties": {
    "addr:full":"45 Windsor Rd Sunbury-on-thames Surrey TW16 7QY",
    "addr:housenumber":"45",
    "addr:postcode":"tw16 7qy",
    "addr:street":"Windsor Rd",
    "iso:country":"GB",
    "sg:address":"45 Windsor Rd",
    "sg:city":"Sunbury-on-thames",
    "sg:classifiers":[
        {
            "category":"Professional",
            "subcategory":"Business Services",
            "type":"Services"
        }
    ],
    "sg:postcode":"TW16 7QY",
    "sg:province":"Surrey",
    "sg:tags":[
        "import",
        "export",
        "agent"
    ],
    "wof:name":"Mountash",
    "wof:placetype":"venue"
},
  "geometry": {"coordinates":[-0.416176,51.422707],"type":"Point"}
}