{
  "type": "Feature",
  "properties": {
    "addr:full":"The Play House, Rands Lane Doncaster South Yorkshire DN3 3DY",
    "addr:postcode":"dn3 3dy",
    "addr:street":"Rands Lane",
    "iso:country":"GB",
    "sg:address":"The Play House, Rands Lane",
    "sg:city":"Doncaster",
    "sg:classifiers":[
        {
            "category":"Wholesale",
            "subcategory":"Books, Periodicals, & Newspapers",
            "type":"Manufacturing & Wholesale Goods"
        }
    ],
    "sg:phone":"+44 1302 830930",
    "sg:postcode":"DN3 3DY",
    "sg:province":"South Yorkshire",
    "sg:tags":[
        "publishing"
    ],
    "wof:name":"The Antiques Advertiser",
    "wof:placetype":"venue"
},
  "geometry": {"coordinates":[-1.0426889658,53.5405845642],"type":"Point"}
}