{
  "type": "Feature",
  "properties": {
    "addr:full":"45 Oxford Street Weston-super-mare Somerset BS23 1TN",
    "addr:housenumber":"45",
    "addr:postcode":"bs23 1tn",
    "addr:street":"Oxford Street",
    "iso:country":"GB",
    "sg:address":"45 Oxford Street",
    "sg:city":"Weston-super-mare",
    "sg:classifiers":[
        {
            "category":"Health Services",
            "subcategory":"Clinic",
            "type":"Services"
        },
        {
            "category":"Professional",
            "subcategory":"Lawyer & Legal Services",
            "type":"Services"
        }
    ],
    "sg:phone":"+44 1934 415711",
    "sg:postcode":"BS23 1TN",
    "sg:province":"Somerset",
    "sg:tags":[
        "advice",
        "abuse",
        "drug",
        "counselling"
    ],
    "wof:name":"Western Counselling Services Ltd.",
    "wof:placetype":"venue"
},
  "geometry": {"coordinates":[-2.977442,51.346313],"type":"Point"}
}