{
  "type": "Feature",
  "properties": {
    "iso:country":"GB",
    "sg:address":"10-16 Lower Church Road",
    "sg:city":"Weston-super-mare",
    "sg:classifiers":[
        {
            "category":"Travel",
            "subcategory":"Hotels & Motels",
            "type":"Entertainment"
        }
    ],
    "sg:phone":"+44 1934 419523",
    "sg:postcode":"BS23 2AG",
    "sg:province":"Somerset",
    "wof:name":"Arosfa Hotel",
    "wof:placetype":"venue"
},
  "geometry": {"coordinates":[-2.980807066,51.3509979248],"type":"Point"}
}