{
  "type": "Feature",
  "properties": {
    "iso:country":"GB",
    "sg:address":"708 Oldham Road, Failsworth",
    "sg:city":"Manchester",
    "sg:classifiers":[
        {
            "category":"Bars & Pubs",
            "type":"Food & Drink"
        },
        {
            "category":"Community Center",
            "subcategory":"Social",
            "type":"Public Place"
        }
    ],
    "sg:phone":"+44 161 681 2784",
    "sg:postcode":"M35 9FD",
    "sg:province":"Lancashire",
    "sg:tags":[
        "pubs",
        "house",
        "inn",
        "activity"
    ],
    "wof:name":"Houghton Arms",
    "wof:placetype":"venue"
},
  "geometry": {"coordinates":[-2.1488220692,53.5160636902],"type":"Point"}
}