{
  "type": "Feature",
  "properties": {
    "iso:country":"GB",
    "sg:address":"29a Herne Street",
    "sg:city":"Herne Bay",
    "sg:classifiers":[
        {
            "category":"Food & Beverages",
            "subcategory":"Liquor & Beverages",
            "type":"Retail Goods"
        },
        {
            "category":"Shopping",
            "subcategory":"Florist",
            "type":"Retail Goods"
        }
    ],
    "sg:postcode":"CT6 7HL",
    "sg:province":"Kent",
    "sg:tags":[
        "beer",
        "spirit",
        "wines"
    ],
    "wof:name":"Canterbury Beer Shop",
    "wof:placetype":"venue"
},
  "geometry": {"coordinates":[1.133345,51.350231],"type":"Point"}
}