{
  "type": "Feature",
  "properties": {
    "addr:full":"28 Wash Road, Hutton Industrial Estate Brentwood Essex CM13 1TB",
    "addr:housenumber":"28",
    "addr:postcode":"cm13 1tb",
    "addr:street":"Wash Road;Industrial Estate",
    "iso:country":"GB",
    "sg:address":"28 Wash Road, Hutton Industrial Estate",
    "sg:city":"Brentwood",
    "sg:classifiers":[
        {
            "category":"Professional",
            "subcategory":"Engineering",
            "type":"Services"
        }
    ],
    "sg:postcode":"CM13 1TB",
    "sg:province":"Essex",
    "wof:name":"Falcon Engineering Ltd.",
    "wof:placetype":"venue"
},
  "geometry": {"coordinates":[0.35697,51.636951],"type":"Point"}
}