{
  "type": "Feature",
  "properties": {
    "addr:full":"11 Bardolph Clo Hereford Herefordshire HR2 7QA",
    "addr:housenumber":"11",
    "addr:postcode":"hr2 7qa",
    "addr:street":"Bardolph Clo",
    "iso:country":"GB",
    "sg:address":"11 Bardolph Clo",
    "sg:city":"Hereford",
    "sg:classifiers":[
        {
            "category":"Building & Trades",
            "subcategory":"Construction",
            "type":"Services"
        }
    ],
    "sg:phone":"+44 1432 356232",
    "sg:postcode":"HR2 7QA",
    "sg:province":"Herefordshire",
    "sg:tags":[
        "builder"
    ],
    "wof:name":"C J A Mayers",
    "wof:placetype":"venue"
},
  "geometry": {"coordinates":[-2.7254230976,52.036441803],"type":"Point"}
}