{
  "type": "Feature",
  "properties": {
    "addr:full":"Estate Office, Main Street, Carnwath Lanark South Lanarkshire ML11 8JY",
    "addr:postcode":"ml11 8jy",
    "addr:street":"Main Street",
    "iso:country":"GB",
    "sg:address":"Estate Office, Main Street, Carnwath",
    "sg:city":"Lanark",
    "sg:classifiers":[
        {
            "category":"Real Estate",
            "subcategory":"Real Estate Agent",
            "type":"Services"
        }
    ],
    "sg:postcode":"ML11 8JY",
    "sg:province":"South Lanarkshire",
    "wof:name":"Lee & Carnwath Estates",
    "wof:placetype":"venue"
},
  "geometry": {"coordinates":[-3.624613,55.700565],"type":"Point"}
}