{
  "type": "Feature",
  "properties": {
    "addr:full":"149 Wincombe Lee Hull East Riding of Yorkshire HU2 0HA",
    "addr:housenumber":"149",
    "addr:postcode":"hu2 0ha",
    "addr:street":"Wincombe Lee",
    "iso:country":"GB",
    "sg:address":"149 Wincombe Lee",
    "sg:city":"Hull",
    "sg:classifiers":[
        {
            "category":"Wholesale",
            "subcategory":"Scrap",
            "type":"Manufacturing & Wholesale Goods"
        }
    ],
    "sg:phone":"+44 1482 322100",
    "sg:postcode":"HU2 0HA",
    "sg:province":"East Riding of Yorkshire",
    "sg:tags":[
        "breaker",
        "dismantlers"
    ],
    "wof:name":"A & B Auto Salvage",
    "wof:placetype":"venue"
},
  "geometry": {"coordinates":[-0.333021,53.752522],"type":"Point"}
}