{
  "type": "Feature",
  "properties": {
    "addr:full":"Ash Lane, Etwall Derby Derbyshire DE65 6HT",
    "addr:postcode":"de65 6ht",
    "addr:street":"Ash Lane",
    "iso:country":"GB",
    "sg:address":"Ash Lane, Etwall",
    "sg:city":"Derby",
    "sg:classifiers":[
        {
            "category":"Shopping",
            "subcategory":"Bicycles & Sporting Goods",
            "type":"Retail Goods"
        }
    ],
    "sg:phone":"+44 1283 730166",
    "sg:postcode":"DE65 6HT",
    "sg:province":"Derbyshire",
    "sg:tags":[
        "riding",
        "saddlery",
        "wear"
    ],
    "wof:name":"Barleyfields Saddlery",
    "wof:placetype":"venue"
},
  "geometry": {"coordinates":[-1.6020699739,52.883266449],"type":"Point"}
}