{
  "type": "Feature",
  "properties": {
    "iso:country":"GB",
    "sg:address":"Unit 1, Plot 17",
    "sg:city":"Huntingdon",
    "sg:classifiers":[
        {
            "category":"Home & Garden",
            "subcategory":"Household Appliances",
            "type":"Retail Goods"
        }
    ],
    "sg:phone":"+44 1480 471296",
    "sg:postcode":"PE19 3JH",
    "sg:province":"Bedfordshire",
    "sg:tags":[
        "refrigeration",
        "air conditioning"
    ],
    "wof:name":"J & E Hall Ltd.",
    "wof:placetype":"venue"
},
  "geometry": {"coordinates":[-0.27204,52.246269],"type":"Point"}
}