{
  "type": "Feature",
  "properties": {
    "iso:country":"GB",
    "sg:address":"4 High Street, Long Sutton",
    "sg:city":"Spalding",
    "sg:classifiers":[
        {
            "category":"Organizations",
            "subcategory":"Non-profit Organization",
            "type":"Services"
        }
    ],
    "sg:phone":"+44 1406 365407",
    "sg:postcode":"PE12 9DB",
    "sg:province":"Cambridgeshire",
    "sg:tags":[
        "charitable",
        "organisation",
        "voluntary",
        "charity"
    ],
    "wof:name":"The British Polio Fellowship",
    "wof:placetype":"venue"
},
  "geometry": {"coordinates":[0.122379,52.785172],"type":"Point"}
}