{
  "type": "Feature",
  "properties": {
    "iso:country":"GB",
    "sg:address":"254 Cromwell Road",
    "sg:city":"Newport",
    "sg:classifiers":[
        {
            "category":"Retail",
            "subcategory":"Emissions Testing",
            "type":"Services"
        },
        {
            "category":"Professional",
            "subcategory":"Testing Lab",
            "type":"Services"
        }
    ],
    "sg:phone":"+44 1633 281888",
    "sg:postcode":"NP19 0HT",
    "sg:province":"Newport",
    "sg:tags":[
        "mot"
    ],
    "wof:name":"Somerton Park Garage",
    "wof:placetype":"venue"
},
  "geometry": {"coordinates":[-2.9645950794,51.5826568604],"type":"Point"}
}