{
  "type": "Feature",
  "properties": {
    "iso:country":"GB",
    "sg:address":"81-83 Russell Way, Metrocentre",
    "sg:city":"Gateshead",
    "sg:classifiers":[
        {
            "category":"Shopping",
            "subcategory":"Optician",
            "type":"Retail Goods"
        }
    ],
    "sg:phone":"+44 191 460 0644",
    "sg:postcode":"NE11 9XX",
    "sg:province":"Tyne and Wear",
    "sg:tags":[
        "dispensing"
    ],
    "wof:name":"Vision Express (UK) Ltd",
    "wof:placetype":"venue"
},
  "geometry": {"coordinates":[-1.66854,54.957661],"type":"Point"}
}