{
  "type": "Feature",
  "properties": {
    "iso:country":"GB",
    "sg:address":"160 Bdwy",
    "sg:city":"London",
    "sg:classifiers":[
        {
            "category":"Professional",
            "subcategory":"Printing & Photocopies",
            "type":"Services"
        }
    ],
    "sg:phone":"+44 20 8567 8727",
    "sg:postcode":"W13 0TL",
    "sg:province":"Greater London",
    "sg:tags":[
        "printer"
    ],
    "wof:name":"Express Print Ltd.",
    "wof:placetype":"venue"
},
  "geometry": {"coordinates":[-0.32793,51.509811],"type":"Point"}
}