{
  "type": "Feature",
  "properties": {
    "addr:full":"6 Fore St Bridgwater Somerset TA6 3NF",
    "addr:housenumber":"6",
    "addr:postcode":"ta6 3nf",
    "addr:street":"Fore St",
    "iso:country":"GB",
    "sg:address":"6 Fore St",
    "sg:city":"Bridgwater",
    "sg:classifiers":[
        {
            "category":"Travel",
            "subcategory":"Travel Agent",
            "type":"Entertainment"
        }
    ],
    "sg:phone":"+44 1278 428528",
    "sg:postcode":"TA6 3NF",
    "sg:province":"Somerset",
    "wof:name":"Worldchoice Carlson",
    "wof:placetype":"venue"
},
  "geometry": {"coordinates":[-3.0016930103,51.1289291382],"type":"Point"}
}