{
  "type": "Feature",
  "properties": {
    "iso:country":"GB",
    "sg:address":"The Granary, Park Lane, Finchampstead",
    "sg:city":"Wokingham",
    "sg:classifiers":[
        {
            "category":"Professional",
            "type":"Services"
        }
    ],
    "sg:postcode":"RG40 4QL",
    "sg:province":"Berkshire",
    "sg:tags":[
        "entertainer"
    ],
    "wof:name":"Frank P Reid",
    "wof:placetype":"venue"
},
  "geometry": {"coordinates":[-0.8345940113,51.4108009338],"type":"Point"}
}