{
  "type": "Feature",
  "properties": {
    "addr:full":"14 Woodstock Road Watford Hertfordshire WD23 1PH",
    "addr:housenumber":"14",
    "addr:postcode":"wd23 1ph",
    "addr:street":"Woodstock Road",
    "iso:country":"GB",
    "sg:address":"14 Woodstock Road",
    "sg:city":"Watford",
    "sg:classifiers":[
        {
            "category":"Building & Trades",
            "subcategory":"Construction",
            "type":"Services"
        }
    ],
    "sg:postcode":"WD23 1PH",
    "sg:province":"Hertfordshire",
    "sg:tags":[
        "decorator",
        "painter"
    ],
    "wof:name":"Alan Dryer Decorators",
    "wof:placetype":"venue"
},
  "geometry": {"coordinates":[-0.3455190063,51.6364898682],"type":"Point"}
}