{
  "type": "Feature",
  "properties": {
    "addr:full":"33 Queens Rd Aberdeen Aberdeen City AB15 4ZN",
    "addr:housenumber":"33",
    "addr:postcode":"ab15 4zn",
    "addr:street":"Queens Rd",
    "iso:country":"GB",
    "sg:address":"33 Queens Rd",
    "sg:city":"Aberdeen",
    "sg:classifiers":[
        {
            "category":"Professional",
            "subcategory":"Lawyer & Legal Services",
            "type":"Services"
        }
    ],
    "sg:phone":"+44 1224 209967",
    "sg:postcode":"AB15 4ZN",
    "sg:province":"Aberdeen City",
    "sg:tags":[
        "advice",
        "counselling"
    ],
    "wof:name":"Aberdeen Counselling Centre",
    "wof:placetype":"venue"
},
  "geometry": {"coordinates":[-2.134281,57.141415],"type":"Point"}
}