{
  "type": "Feature",
  "properties": {
    "iso:country":"GB",
    "sg:address":"Brook Cotts, Burnthorne Lane, Dunley",
    "sg:city":"Stourport-on-severn",
    "sg:classifiers":[
        {
            "category":"Food & Beverages",
            "subcategory":"Farmers Market",
            "type":"Retail Goods"
        }
    ],
    "sg:phone":"+44 1299 823198",
    "sg:postcode":"DY13 0TN",
    "sg:province":"Worcestershire",
    "sg:tags":[
        "gardener"
    ],
    "wof:name":"B E Collins",
    "wof:placetype":"venue"
},
  "geometry": {"coordinates":[-2.310629,52.320797],"type":"Point"}
}