{
  "type": "Feature",
  "properties": {
    "addr:full":"1 Shafford Cottage, Lower Road Hemel Hempstead Hertfordshire HP3 8RT",
    "addr:housenumber":"1",
    "addr:postcode":"hp3 8rt",
    "addr:street":"Lower Road",
    "iso:country":"GB",
    "sg:address":"1 Shafford Cottage, Lower Road",
    "sg:city":"Hemel Hempstead",
    "sg:classifiers":[
        {
            "category":"Building & Trades",
            "subcategory":"Construction",
            "type":"Services"
        }
    ],
    "sg:phone":"+44 1923 264029",
    "sg:postcode":"HP3 8RT",
    "sg:province":"Hertfordshire",
    "sg:tags":[
        "joiner",
        "carpenter"
    ],
    "wof:name":"Woodmill Farm Ltd.",
    "wof:placetype":"venue"
},
  "geometry": {"coordinates":[-0.4479799867,51.7258987427],"type":"Point"}
}