{
  "type": "Feature",
  "properties": {
    "addr:full":", Kippford Dalbeattie Dumfries and Galloway DG5 4LL",
    "addr:postcode":"dg5 4ll",
    "iso:country":"GB",
    "sg:address":", Kippford",
    "sg:city":"Dalbeattie",
    "sg:classifiers":[
        {
            "category":"Arena",
            "subcategory":"Sports Club",
            "type":"Entertainment"
        }
    ],
    "sg:phone":"+44 1556 620312",
    "sg:postcode":"DG5 4LL",
    "sg:province":"Dumfries and Galloway",
    "wof:name":"The Solway Yacht Club",
    "wof:placetype":"venue"
},
  "geometry": {"coordinates":[-3.823039,54.933456],"type":"Point"}
}