{
  "type": "Feature",
  "properties": {
    "addr:full":"Banbury Road, North Newington Banbury Oxfordshire OX15 6AB",
    "addr:postcode":"ox15 6ab",
    "addr:street":"Banbury Road North",
    "iso:country":"GB",
    "sg:address":"Banbury Road, North Newington",
    "sg:city":"Banbury",
    "sg:classifiers":[
        {
            "category":"Bars & Pubs",
            "type":"Food & Drink"
        },
        {
            "category":"Community Center",
            "subcategory":"Social",
            "type":"Public Place"
        }
    ],
    "sg:postcode":"OX15 6AB",
    "sg:province":"Oxfordshire",
    "sg:tags":[
        "pubs",
        "house",
        "inn",
        "activity"
    ],
    "wof:name":"GRAHAM NEWTON",
    "wof:placetype":"venue"
},
  "geometry": {"coordinates":[-1.379701972,52.0501976013],"type":"Point"}
}