{
  "type": "Feature",
  "properties": {
    "addr:full":"Unit 1 Modular Court, Enterprise Drive Four Ashes Wolverhampton Staffordshire WV10 7DF",
    "addr:housenumber":"unit 1",
    "addr:postcode":"ashes;wv10 7df",
    "addr:street":"Modular Court Enterprise Drive",
    "iso:country":"GB",
    "sg:address":"Unit 1 Modular Court, Enterprise Drive Four Ashes",
    "sg:city":"Wolverhampton",
    "sg:classifiers":[
        {
            "category":"Building & Trades",
            "subcategory":"Landscaping Services",
            "type":"Services"
        }
    ],
    "sg:phone":"+44 1902 790046",
    "sg:postcode":"WV10 7DF",
    "sg:province":"Staffordshire",
    "sg:tags":[
        "steel"
    ],
    "wof:name":"Modular Buildings (U K) Ltd.",
    "wof:placetype":"venue"
},
  "geometry": {"coordinates":[-2.1175460815,52.6737251282],"type":"Point"}
}