{
  "type": "Feature",
  "properties": {
    "iso:country":"GB",
    "sg:address":"29 Gildredge Road",
    "sg:city":"Eastbourne",
    "sg:classifiers":[
        {
            "category":"Professional",
            "subcategory":"Computer Services",
            "type":"Services"
        }
    ],
    "sg:phone":"+44 1323 411130",
    "sg:postcode":"BN21 4RU",
    "sg:province":"East Sussex",
    "sg:tags":[
        "system",
        "software"
    ],
    "wof:name":"First Independent Computer Services",
    "wof:placetype":"venue"
},
  "geometry": {"coordinates":[0.28142,50.767529],"type":"Point"}
}