{
  "type": "Feature",
  "properties": {
    "addr:full":"14 Snape Drive Lowestoft Suffolk NR32 4SF",
    "addr:housenumber":"14",
    "addr:postcode":"nr32 4sf",
    "addr:street":"Snape Drive",
    "iso:country":"GB",
    "sg:address":"14 Snape Drive",
    "sg:city":"Lowestoft",
    "sg:classifiers":[
        {
            "category":"Fast Food",
            "type":"Food & Drink"
        }
    ],
    "sg:phone":"+44 1502 585800",
    "sg:postcode":"NR32 4SF",
    "sg:province":"Suffolk",
    "sg:tags":[
        "away",
        "meal",
        "outlet",
        "take"
    ],
    "wof:name":"Evergreen Chinese Take Away Ltd",
    "wof:placetype":"venue"
},
  "geometry": {"coordinates":[1.724888,52.490723],"type":"Point"}
}