{
  "type": "Feature",
  "properties": {
    "iso:country":"GB",
    "sg:address":"1 Grasscroft Rd",
    "sg:city":"Wigan",
    "sg:classifiers":[
        {
            "category":"Building & Trades",
            "subcategory":"Equipment Rental",
            "type":"Services"
        }
    ],
    "sg:phone":"+44 1942 258271",
    "sg:postcode":"WN2 4QN",
    "sg:province":"Lancashire",
    "sg:tags":[
        "plant",
        "machinery"
    ],
    "wof:name":"Plantel Hire",
    "wof:placetype":"venue"
},
  "geometry": {"coordinates":[-2.556108,53.530079],"type":"Point"}
}