{
  "type": "Feature",
  "properties": {
    "addr:full":"5 Belgrave Drive Middlesbrough North Yorkshire TS6 0SQ",
    "addr:housenumber":"5",
    "addr:postcode":"ts6 0sq",
    "addr:street":"Belgrave Drive",
    "iso:country":"GB",
    "sg:address":"5 Belgrave Drive",
    "sg:city":"Middlesbrough",
    "sg:classifiers":[
        {
            "category":"Manufacturing",
            "subcategory":"Signs",
            "type":"Manufacturing & Wholesale Goods"
        }
    ],
    "sg:postcode":"TS6 0SQ",
    "sg:province":"North Yorkshire",
    "sg:tags":[
        "writer"
    ],
    "wof:name":"Fast Graphics & Signs",
    "wof:placetype":"venue"
},
  "geometry": {"coordinates":[-1.1608560085,54.5479240417],"type":"Point"}
}