{
  "type": "Feature",
  "properties": {
    "addr:full":"32 Regal Drive, Soham Ely Cambridgeshire CB7 5BE",
    "addr:housenumber":"32",
    "addr:postcode":"cb7 5be",
    "addr:street":"Regal Drive",
    "iso:country":"GB",
    "sg:address":"32 Regal Drive, Soham",
    "sg:city":"Ely",
    "sg:classifiers":[
        {
            "category":"Home & Garden",
            "subcategory":"Building Materials",
            "type":"Retail Goods"
        },
        {
            "category":"Bars & Pubs",
            "subcategory":"Oxygen Bar",
            "type":"Food & Drink"
        }
    ],
    "sg:phone":"+44 1353 624126",
    "sg:postcode":"CB7 5BE",
    "sg:province":"Cambridgeshire",
    "sg:tags":[
        "ventilator",
        "ventilation",
        "system"
    ],
    "wof:name":"E Chambers Mechanical Engineering Ltd",
    "wof:placetype":"venue"
},
  "geometry": {"coordinates":[0.350772,52.326443],"type":"Point"}
}