{
  "type": "Feature",
  "properties": {
    "addr:full":"5 Seymour Lane, North Baddesley Southampton Hampshire SO52 9FN",
    "addr:housenumber":"5",
    "addr:postcode":"so52 9fn",
    "addr:street":"Seymour Lane",
    "iso:country":"GB",
    "sg:address":"5 Seymour Lane, North Baddesley",
    "sg:city":"Southampton",
    "sg:classifiers":[
        {
            "category":"Food & Beverages",
            "subcategory":"Fruits & Vegetables",
            "type":"Retail Goods"
        }
    ],
    "sg:postcode":"SO52 9FN",
    "sg:province":"Hampshire",
    "sg:tags":[
        "greengrocer"
    ],
    "wof:name":"The Salad Bowl",
    "wof:placetype":"venue"
},
  "geometry": {"coordinates":[-1.4489990473,50.9760932922],"type":"Point"}
}