{
  "type": "Feature",
  "properties": {
    "iso:country":"GB",
    "sg:address":"8 Top O Th Meadows, Waterhead",
    "sg:city":"Oldham",
    "sg:classifiers":[
        {
            "category":"Professional",
            "subcategory":"Art Services",
            "type":"Services"
        }
    ],
    "sg:phone":"+44 161 785 0022",
    "sg:postcode":"OL4 3SF",
    "sg:province":"Lancashire",
    "sg:tags":[
        "graphic",
        "designer"
    ],
    "wof:name":"Baxter-Cox Design",
    "wof:placetype":"venue"
},
  "geometry": {"coordinates":[-2.0600509644,53.5529022217],"type":"Point"}
}