{
  "type": "Feature",
  "properties": {
    "addr:full":"Knowehead Dollar Clackmannanshire FK14 7NE",
    "addr:postcode":"fk14 7ne",
    "iso:country":"GB",
    "sg:address":"Knowehead",
    "sg:city":"Dollar",
    "sg:classifiers":[
        {
            "category":"Farming",
            "subcategory":"Farm",
            "type":"Manufacturing & Wholesale Goods"
        }
    ],
    "sg:postcode":"FK14 7NE",
    "sg:province":"Clackmannanshire",
    "sg:tags":[
        "mixed",
        "crop"
    ],
    "wof:name":"D & J Croy",
    "wof:placetype":"venue"
},
  "geometry": {"coordinates":[-3.6740090847,56.1627616882],"type":"Point"}
}