{
  "type": "Feature",
  "properties": {
    "addr:full":"25 Market Place Holt Norfolk NR25 6BE",
    "addr:housenumber":"25",
    "addr:postcode":"nr25 6be",
    "addr:street":"Market Place Holt",
    "iso:country":"GB",
    "sg:address":"25 Market Place",
    "sg:city":"Holt",
    "sg:classifiers":[
        {
            "category":"Fast Food",
            "type":"Food & Drink"
        }
    ],
    "sg:phone":"+44 1263 713939",
    "sg:postcode":"NR25 6BE",
    "sg:province":"Norfolk",
    "sg:tags":[
        "away",
        "meal",
        "outlet",
        "take"
    ],
    "wof:name":"Kebab Delight",
    "wof:placetype":"venue"
},
  "geometry": {"coordinates":[1.0900150537,52.9060134888],"type":"Point"}
}