{
  "type": "Feature",
  "properties": {
    "iso:country":"GB",
    "sg:address":"Enfield Lock",
    "sg:city":"Enfield",
    "sg:classifiers":[
        {
            "category":"Retail",
            "subcategory":"Event Space",
            "type":"Services"
        },
        {
            "category":"Community Center",
            "subcategory":"Social",
            "type":"Public Place"
        }
    ],
    "sg:phone":"+44 1992 761191",
    "sg:postcode":"EN3 6JQ",
    "sg:province":"Greater London",
    "sg:tags":[
        "house",
        "banqueting",
        "room",
        "activity"
    ],
    "wof:name":"Rifles",
    "wof:placetype":"venue"
},
  "geometry": {"coordinates":[-0.01801,51.667122],"type":"Point"}
}