{
  "type": "Feature",
  "properties": {
    "iso:country":"GB",
    "sg:address":"Milton Avenue",
    "sg:city":"Sevenoaks",
    "sg:classifiers":[
        {
            "category":"Home & Garden",
            "subcategory":"Building Materials",
            "type":"Retail Goods"
        }
    ],
    "sg:phone":"+44 1959 534229",
    "sg:postcode":"TN14 7AJ",
    "sg:province":"Kent",
    "sg:tags":[
        "furnishers",
        "bathroom",
        "planner"
    ],
    "wof:name":"Classic Bathrooms",
    "wof:placetype":"venue"
},
  "geometry": {"coordinates":[0.1479199976,51.3391036987],"type":"Point"}
}