{
  "type": "Feature",
  "properties": {
    "iso:country":"GB",
    "sg:address":"Garden House, Whitmuir",
    "sg:city":"Selkirk",
    "sg:classifiers":[
        {
            "category":"Banks & Credit Unions",
            "subcategory":"Investment Brokerage",
            "type":"Services"
        }
    ],
    "sg:postcode":"TD7 4PZ",
    "sg:province":"Scottish Borders",
    "sg:tags":[
        "contractor"
    ],
    "wof:name":"Robert S Dunlop",
    "wof:placetype":"venue"
},
  "geometry": {"coordinates":[-2.8414289951,55.547328949],"type":"Point"}
}