{
  "type": "Feature",
  "properties": {
    "addr:full":"28c Heath Road, Bedworth Nuneaton Warwickshire CV12 0AR",
    "addr:housenumber":"28c",
    "addr:postcode":"cv12 0ar",
    "addr:street":"Heath Road",
    "iso:country":"GB",
    "sg:address":"28c Heath Road, Bedworth",
    "sg:city":"Nuneaton",
    "sg:classifiers":[
        {
            "category":"Professional",
            "subcategory":"Engineering",
            "type":"Services"
        }
    ],
    "sg:postcode":"CV12 0AR",
    "sg:province":"Warwickshire",
    "sg:tags":[
        "civil",
        "engineer"
    ],
    "wof:name":"I C R Services",
    "wof:placetype":"venue"
},
  "geometry": {"coordinates":[-1.491755,52.477093],"type":"Point"}
}