{
  "type": "Feature",
  "properties": {
    "addr:full":", Old Romney Romney Marsh Kent TN29 9SG",
    "addr:postcode":"tn29 9sg",
    "addr:street":"Old Romney Romney",
    "iso:country":"GB",
    "sg:address":", Old Romney",
    "sg:city":"Romney Marsh",
    "sg:classifiers":[
        {
            "category":"Cafe",
            "type":"Food & Drink"
        }
    ],
    "sg:phone":"+44 1797 367979",
    "sg:postcode":"TN29 9SG",
    "sg:province":"Kent",
    "sg:tags":[
        "tea",
        "room"
    ],
    "wof:name":"The New Oasis Cafe",
    "wof:placetype":"venue"
},
  "geometry": {"coordinates":[0.9205009937,50.9791793823],"type":"Point"}
}