{
  "type": "Feature",
  "properties": {
    "addr:full":"Unit 8, Lawn Farm Buss Ctr Aylesbury Buckinghamshire HP18 0QX",
    "addr:housenumber":"unit 8",
    "addr:postcode":"hp18 0qx",
    "addr:street":"Lawn;Buss Ctr",
    "iso:country":"GB",
    "sg:address":"Unit 8, Lawn Farm Buss Ctr",
    "sg:city":"Aylesbury",
    "sg:classifiers":[
        {
            "category":"Communications",
            "type":"Services"
        }
    ],
    "sg:phone":"+44 1296 770088",
    "sg:postcode":"HP18 0QX",
    "sg:province":"Buckinghamshire",
    "sg:tags":[
        "telecommunication"
    ],
    "wof:name":"3c Test Ltd.",
    "wof:placetype":"venue"
},
  "geometry": {"coordinates":[-1.009288,51.899403],"type":"Point"}
}