{
  "type": "Feature",
  "properties": {
    "iso:country":"GB",
    "sg:address":"105 Spon End",
    "sg:city":"Coventry",
    "sg:classifiers":[
        {
            "category":"Food & Beverages",
            "subcategory":"Meat & Fish",
            "type":"Retail Goods"
        },
        {
            "category":"Food & Beverages",
            "subcategory":"Groceries & Convenience Stores",
            "type":"Retail Goods"
        }
    ],
    "sg:phone":"+44 24 7663 1573",
    "sg:postcode":"CV1 3HF",
    "sg:province":"West Midlands",
    "sg:tags":[
        "shop",
        "chip"
    ],
    "wof:name":"Maria & Peter Corey",
    "wof:placetype":"venue"
},
  "geometry": {"coordinates":[-1.526172,52.408264],"type":"Point"}
}