{
  "type": "Feature",
  "properties": {
    "addr:full":"26 High Street Blaenau Ffestiniog Gwynedd LL41 3AA",
    "addr:housenumber":"26",
    "addr:postcode":"ll41 3aa",
    "addr:street":"High Street",
    "iso:country":"GB",
    "sg:address":"26 High Street",
    "sg:city":"Blaenau Ffestiniog",
    "sg:classifiers":[
        {
            "category":"Shopping",
            "subcategory":"Pharmacy",
            "type":"Retail Goods"
        }
    ],
    "sg:phone":"+44 1766 830298",
    "sg:postcode":"LL41 3AA",
    "sg:province":"Gwynedd",
    "sg:tags":[
        "pharmacist",
        "chemist"
    ],
    "wof:name":"D Powys Davies",
    "wof:placetype":"venue"
},
  "geometry": {"coordinates":[-3.9323289394,52.9941291809],"type":"Point"}
}