{
  "type": "Feature",
  "properties": {
    "iso:country":"GB",
    "sg:address":"Knott Lanes",
    "sg:city":"Oldham",
    "sg:classifiers":[
        {
            "category":"Sports & Exercise",
            "subcategory":"Golf",
            "type":"Entertainment"
        }
    ],
    "sg:phone":"+44 161 627 2463",
    "sg:postcode":"OL8 3JD",
    "sg:province":"Lancashire",
    "sg:tags":[
        "club",
        "course"
    ],
    "wof:name":"Bardsley Park Golf Centre",
    "wof:placetype":"venue"
},
  "geometry": {"coordinates":[-2.108613,53.51215],"type":"Point"}
}