{
  "type": "Feature",
  "properties": {
    "addr:full":"16 Grate House Farm Road, Layer De Lane Haye Colchester Essex CO2 0LP",
    "addr:housenumber":"16;house",
    "addr:postcode":"co2 0lp",
    "addr:street":"Farm Road;De Lane;Colchester",
    "iso:country":"GB",
    "sg:address":"16 Grate House Farm Road, Layer De Lane Haye",
    "sg:city":"Colchester",
    "sg:classifiers":[
        {
            "category":"Building & Trades",
            "subcategory":"Construction",
            "type":"Services"
        }
    ],
    "sg:postcode":"CO2 0LP",
    "sg:province":"Essex",
    "sg:tags":[
        "builder"
    ],
    "wof:name":"Layer Products",
    "wof:placetype":"venue"
},
  "geometry": {"coordinates":[0.86203,51.845371],"type":"Point"}
}