{
  "type": "Feature",
  "properties": {
    "iso:country":"GB",
    "sg:address":"13 Headley Gro",
    "sg:city":"Tadworth",
    "sg:classifiers":[
        {
            "category":"Retail",
            "subcategory":"Repair Shop",
            "type":"Services"
        }
    ],
    "sg:postcode":"KT20 5JH",
    "sg:province":"Surrey",
    "sg:tags":[
        "radio",
        "television",
        "video"
    ],
    "wof:name":"Keith Apps",
    "wof:placetype":"venue"
},
  "geometry": {"coordinates":[-0.236185,51.30267],"type":"Point"}
}