{
  "type": "Feature",
  "properties": {
    "addr:full":"17 Station St Mansfield Derbyshire NG19 8AD",
    "addr:housenumber":"17",
    "addr:postcode":"ng19 8ad",
    "addr:street":"Station St",
    "iso:country":"GB",
    "sg:address":"17 Station St",
    "sg:city":"Mansfield",
    "sg:classifiers":[
        {
            "category":"Professional",
            "subcategory":"Art Services",
            "type":"Services"
        }
    ],
    "sg:phone":"+44 1623 634442",
    "sg:postcode":"NG19 8AD",
    "sg:province":"Derbyshire",
    "sg:tags":[
        "framing"
    ],
    "wof:name":"Tom Morgan",
    "wof:placetype":"venue"
},
  "geometry": {"coordinates":[-1.1958090067,53.1641540527],"type":"Point"}
}