{
  "type": "Feature",
  "properties": {
    "addr:full":"The Roofing Shop, 33 London Road, Southborough Tunbridge Wells Kent TN4 0PB",
    "addr:housenumber":"33",
    "addr:postcode":"tn4 0pb",
    "addr:street":"London Road",
    "iso:country":"GB",
    "sg:address":"The Roofing Shop, 33 London Road, Southborough",
    "sg:city":"Tunbridge Wells",
    "sg:classifiers":[
        {
            "category":"Building & Trades",
            "subcategory":"Construction",
            "type":"Services"
        }
    ],
    "sg:phone":"+44 1892 535572",
    "sg:postcode":"TN4 0PB",
    "sg:province":"Kent",
    "sg:tags":[
        "roofing"
    ],
    "wof:name":"Roofmaster & Co",
    "wof:placetype":"venue"
},
  "geometry": {"coordinates":[0.259949,51.155891],"type":"Point"}
}