{
  "type": "Feature",
  "properties": {
    "addr:full":"40 Blackburn St, Radcliffe Manchester Greater Manchester M26 1NQ",
    "addr:housenumber":"40",
    "addr:postcode":"m26 1nq",
    "addr:street":"Blackburn St",
    "iso:country":"GB",
    "sg:address":"40 Blackburn St, Radcliffe",
    "sg:city":"Manchester",
    "sg:classifiers":[
        {
            "category":"Shopping",
            "subcategory":"Used Merchandise",
            "type":"Retail Goods"
        }
    ],
    "sg:postcode":"M26 1NQ",
    "sg:province":"Greater Manchester",
    "sg:tags":[
        "shop",
        "second-hand"
    ],
    "wof:name":"McNeill,Andrew,",
    "wof:placetype":"venue"
},
  "geometry": {"coordinates":[-2.3260929585,53.560005188],"type":"Point"}
}