{
  "type": "Feature",
  "properties": {
    "iso:country":"GB",
    "sg:address":"46a Syon La, Osterley",
    "sg:city":"Isleworth",
    "sg:classifiers":[
        {
            "category":"Real Estate",
            "subcategory":"Real Estate Agent",
            "type":"Services"
        }
    ],
    "sg:postcode":"TW7 5NQ",
    "sg:province":"Greater London",
    "wof:name":"Falcon Realty Ltd",
    "wof:placetype":"venue"
},
  "geometry": {"coordinates":[-0.328363,51.483597],"type":"Point"}
}