{
  "type": "Feature",
  "properties": {
    "addr:full":"288 Old Durham Road Gateshead Tyne and Wear NE8 4BP",
    "addr:housenumber":"288",
    "addr:postcode":"ne8 4bp",
    "addr:street":"Old Durham Road",
    "iso:country":"GB",
    "sg:address":"288 Old Durham Road",
    "sg:city":"Gateshead",
    "sg:classifiers":[
        {
            "category":"Food & Beverages",
            "subcategory":"Meat & Fish",
            "type":"Retail Goods"
        }
    ],
    "sg:postcode":"NE8 4BP",
    "sg:province":"Tyne and Wear",
    "sg:tags":[
        "butcher"
    ],
    "wof:name":"Browns Family Butchers",
    "wof:placetype":"venue"
},
  "geometry": {"coordinates":[-1.595859,54.951721],"type":"Point"}
}