{
  "type": "Feature",
  "properties": {
    "addr:full":"Unit 3 Westwood Court, Clayhill Industrial Park Wirral Cheshire CH64 3UJ",
    "addr:housenumber":"unit 3",
    "addr:postcode":"ch64 3uj",
    "addr:street":"Westwood Court",
    "iso:country":"GB",
    "sg:address":"Unit 3 Westwood Court, Clayhill Industrial Park",
    "sg:city":"Wirral",
    "sg:classifiers":[
        {
            "category":"Professional",
            "type":"Services"
        }
    ],
    "sg:phone":"+44 151 353 1993",
    "sg:postcode":"CH64 3UJ",
    "sg:province":"Cheshire",
    "sg:tags":[
        "shopfitters"
    ],
    "wof:name":"Todhunter Davies Ltd.",
    "wof:placetype":"venue"
},
  "geometry": {"coordinates":[-3.06109,53.299721],"type":"Point"}
}