{
  "type": "Feature",
  "properties": {
    "iso:country":"GB",
    "sg:address":"Suite 106c Kent Ho, Station Rd",
    "sg:city":"Ashford",
    "sg:classifiers":[
        {
            "category":"Professional",
            "subcategory":"Accounting & Tax Preparation",
            "type":"Services"
        }
    ],
    "sg:phone":"+44 1233 645225",
    "sg:postcode":"TN23 1PJ",
    "sg:province":"Kent",
    "sg:tags":[
        "consultant"
    ],
    "wof:name":"Tax Team The",
    "wof:placetype":"venue"
},
  "geometry": {"coordinates":[0.87531,51.146858],"type":"Point"}
}