{
  "type": "Feature",
  "properties": {
    "iso:country":"GB",
    "sg:address":"125a Hughenden Road",
    "sg:city":"High Wycombe",
    "sg:classifiers":[
        {
            "category":"Food & Beverages",
            "subcategory":"Groceries & Convenience Stores",
            "type":"Retail Goods"
        }
    ],
    "sg:phone":"+44 1494 533007",
    "sg:postcode":"HP13 5HT",
    "sg:province":"Buckinghamshire",
    "wof:name":"T & B Minimarket",
    "wof:placetype":"venue"
},
  "geometry": {"coordinates":[-0.750791,51.638416],"type":"Point"}
}