{
  "type": "Feature",
  "properties": {
    "addr:full":"80 Gilmore Place Edinburgh City of Edinburgh EH3 9NX",
    "addr:housenumber":"80",
    "addr:postcode":"eh3 9nx",
    "addr:street":"Gilmore Place Edinburgh",
    "iso:country":"GB",
    "sg:address":"80 Gilmore Place",
    "sg:city":"Edinburgh",
    "sg:classifiers":[
        {
            "category":"Food & Beverages",
            "subcategory":"Supermarket",
            "type":"Retail Goods"
        }
    ],
    "sg:phone":"+44 131 228 8835",
    "sg:postcode":"EH3 9NX",
    "sg:province":"City of Edinburgh",
    "wof:name":"Lemington Mini Market",
    "wof:placetype":"venue"
},
  "geometry": {"coordinates":[-3.2099881172,55.9408035278],"type":"Point"}
}