{
  "type": "Feature",
  "properties": {
    "addr:full":"Dover Farm Close, Stonydelth Tamworth Staffordshire B77 4AP",
    "addr:postcode":"b77 4ap",
    "addr:street":"Farm Close",
    "iso:country":"GB",
    "sg:address":"Dover Farm Close, Stonydelth",
    "sg:city":"Tamworth",
    "sg:classifiers":[
        {
            "category":"Social Services",
            "subcategory":"Retirement Home",
            "type":"Services"
        }
    ],
    "sg:phone":"+44 1827 331116",
    "sg:postcode":"B77 4AP",
    "sg:province":"Staffordshire",
    "sg:tags":[
        "rest"
    ],
    "wof:name":"Dover Cottage Rest Home",
    "wof:placetype":"venue"
},
  "geometry": {"coordinates":[-1.649124,52.614834],"type":"Point"}
}