{
  "type": "Feature",
  "properties": {
    "iso:country":"GB",
    "sg:address":"12 Old Burlington St",
    "sg:city":"London",
    "sg:classifiers":[
        {
            "category":"Organizations",
            "subcategory":"Community Association",
            "type":"Services"
        }
    ],
    "sg:phone":"+44 20 7494 0303",
    "sg:postcode":"W1S 3AQ",
    "sg:province":"Greater London",
    "sg:tags":[
        "relation",
        "public"
    ],
    "wof:name":"P R Redwood & Marketing",
    "wof:placetype":"venue"
},
  "geometry": {"coordinates":[-0.140949,51.510948],"type":"Point"}
}