{
  "type": "Feature",
  "properties": {
    "iso:country":"GB",
    "sg:address":"Wyatts Lane",
    "sg:city":"London",
    "sg:classifiers":[
        {
            "category":"Building & Trades",
            "subcategory":"Construction",
            "type":"Services"
        }
    ],
    "sg:phone":"+44 20 8520 6491",
    "sg:postcode":"E17 3JD",
    "sg:province":"Greater London",
    "sg:tags":[
        "glazier"
    ],
    "wof:name":"Smiles & Sons Ltd",
    "wof:placetype":"venue"
},
  "geometry": {"coordinates":[-0.004795,51.590115],"type":"Point"}
}