{
  "type": "Feature",
  "properties": {
    "addr:full":"Unit 3 Clocktower Works, 4 Shearling Way London Greater London N7 9TH",
    "addr:housenumber":"unit 3;4",
    "addr:postcode":"n7 9th",
    "addr:street":"Clocktower Works;Shearling Way",
    "iso:country":"GB",
    "sg:address":"Unit 3 Clocktower Works, 4 Shearling Way",
    "sg:city":"London",
    "sg:classifiers":[
        {
            "category":"Shopping",
            "subcategory":"Computers & Home Electronics",
            "type":"Retail Goods"
        }
    ],
    "sg:postcode":"N7 9TH",
    "sg:province":"Greater London",
    "wof:name":"Micro Interface Ltd.",
    "wof:placetype":"venue"
},
  "geometry": {"coordinates":[-0.1220199987,51.5480918884],"type":"Point"}
}