{
  "type": "Feature",
  "properties": {
    "iso:country":"GB",
    "sg:address":"212 High Road",
    "sg:city":"Wood Green",
    "sg:classifiers":[
        {
            "category":"Shopping",
            "subcategory":"Thrift Store",
            "type":"Retail Goods"
        }
    ],
    "sg:phone":"+44 20 8365 8622",
    "sg:postcode":"N22 4HH",
    "sg:province":"Greater London",
    "sg:tags":[
        "shop",
        "charity"
    ],
    "wof:name":"North London Hospice",
    "wof:placetype":"venue"
},
  "geometry": {"coordinates":[-0.110248,51.597923],"type":"Point"}
}