{
  "type": "Feature",
  "properties": {
    "iso:country":"GB",
    "sg:address":"Alberton House, 30 St Mary's Parsonage",
    "sg:city":"Manchester",
    "sg:classifiers":[
        {
            "category":"Professional",
            "subcategory":"Management & Consulting",
            "type":"Services"
        },
        {
            "category":"Education",
            "subcategory":"Special Training",
            "type":"Public Place"
        }
    ],
    "sg:phone":"+44 161 817 6251",
    "sg:postcode":"M3 2WJ",
    "sg:province":"Greater Manchester",
    "sg:tags":[
        "consultant",
        "product",
        "business",
        "centre"
    ],
    "wof:name":"Scott-Grant (Training Services) Ltd.",
    "wof:placetype":"venue"
},
  "geometry": {"coordinates":[-2.224,53.434017],"type":"Point"}
}