{
  "type": "Feature",
  "properties": {
    "iso:country":"GB",
    "sg:address":"25-26 Indoor Market, Grosvenor Centre",
    "sg:city":"Macclesfield",
    "sg:classifiers":[
        {
            "category":"Sports & Exercise",
            "subcategory":"Athletic Track",
            "type":"Entertainment"
        }
    ],
    "sg:phone":"+44 1625 611795",
    "sg:postcode":"SK11 6AX",
    "sg:province":"Cheshire",
    "sg:tags":[
        "bags",
        "accessory",
        "belt"
    ],
    "wof:name":"Nota Bene Accessories Ltd.",
    "wof:placetype":"venue"
},
  "geometry": {"coordinates":[-2.125756,53.255669],"type":"Point"}
}