{
  "type": "Feature",
  "properties": {
    "iso:country":"GB",
    "sg:address":"26 St Ives Close, Digswell",
    "sg:city":"Welwyn",
    "sg:classifiers":[
        {
            "category":"Professional",
            "subcategory":"Management & Consulting",
            "type":"Services"
        }
    ],
    "sg:phone":"+44 1438 715173",
    "sg:postcode":"AL6 0BB",
    "sg:province":"Hertfordshire",
    "sg:tags":[
        "consultant",
        "business"
    ],
    "wof:name":"Castelmere Consulting Ltd.",
    "wof:placetype":"venue"
},
  "geometry": {"coordinates":[-0.192442,51.820351],"type":"Point"}
}