{
  "type": "Feature",
  "properties": {
    "iso:country":"GB",
    "sg:address":"44 Heathfields Clo",
    "sg:city":"Chester",
    "sg:classifiers":[
        {
            "category":"Building & Trades",
            "subcategory":"Construction",
            "type":"Services"
        }
    ],
    "sg:postcode":"CH2 2AT",
    "sg:province":"Cheshire",
    "sg:tags":[
        "builder"
    ],
    "wof:name":"Main,Maichael,",
    "wof:placetype":"venue"
},
  "geometry": {"coordinates":[-2.89152,53.200928],"type":"Point"}
}