{
  "type": "Feature",
  "properties": {
    "iso:country":"GB",
    "sg:address":"Freebournes Road",
    "sg:city":"Witham",
    "sg:classifiers":[
        {
            "category":"Professional",
            "subcategory":"Printing & Photocopies",
            "type":"Services"
        }
    ],
    "sg:phone":"+44 1376 534500",
    "sg:postcode":"CM8 3UH",
    "sg:province":"Essex",
    "sg:tags":[
        "printer"
    ],
    "wof:name":"Europress Holdings Ltd",
    "wof:placetype":"venue"
},
  "geometry": {"coordinates":[0.652185,51.805767],"type":"Point"}
}