{
  "type": "Feature",
  "properties": {
    "addr:full":"45 High Street Crieff Perth and Kinross PH7 3AB",
    "addr:housenumber":"45",
    "addr:postcode":"ph7 3ab",
    "addr:street":"High Street",
    "iso:country":"GB",
    "sg:address":"45 High Street",
    "sg:city":"Crieff",
    "sg:classifiers":[
        {
            "category":"Government",
            "subcategory":"Post Office",
            "type":"Public Place"
        }
    ],
    "sg:phone":"+44 1764 652400",
    "sg:postcode":"PH7 3AB",
    "sg:province":"Perth and Kinross",
    "wof:name":"Crieff Sub Post Office",
    "wof:placetype":"venue"
},
  "geometry": {"coordinates":[-3.837139,56.3727],"type":"Point"}
}