{
  "type": "Feature",
  "properties": {
    "iso:country":"GB",
    "sg:address":"28 Fore Street",
    "sg:city":"St Ives",
    "sg:classifiers":[
        {
            "category":"Shopping",
            "subcategory":"Shoes",
            "type":"Retail Goods"
        }
    ],
    "sg:postcode":"TR26 1HE",
    "sg:province":"Cornwall",
    "sg:tags":[
        "shop"
    ],
    "wof:name":"Peter Briggs",
    "wof:placetype":"venue"
},
  "geometry": {"coordinates":[-5.480605,50.213642],"type":"Point"}
}