{
  "type": "Feature",
  "properties": {
    "addr:full":"9 Muslin Street Glasgow Glasgow City G40 4AZ",
    "addr:housenumber":"9",
    "addr:postcode":"g40 4az",
    "addr:street":"Muslin Street",
    "iso:country":"GB",
    "sg:address":"9 Muslin Street",
    "sg:city":"Glasgow",
    "sg:classifiers":[
        {
            "category":"Social Services",
            "type":"Services"
        },
        {
            "category":"Professional",
            "subcategory":"Employment Agencies",
            "type":"Services"
        }
    ],
    "sg:phone":"+44 141 551 3000",
    "sg:postcode":"G40 4AZ",
    "sg:province":"Glasgow City",
    "sg:tags":[
        "consultant",
        "benefit",
        "recruitment"
    ],
    "wof:name":"Benefits Agency",
    "wof:placetype":"venue"
},
  "geometry": {"coordinates":[-4.225275,55.847031],"type":"Point"}
}