{
  "type": "Feature",
  "properties": {
    "addr:full":"Sotherby Rd Middlesbrough North Yorkshire TS3 8BT",
    "addr:postcode":"ts3 8bt",
    "addr:street":"Sotherby Rd",
    "iso:country":"GB",
    "sg:address":"Sotherby Rd",
    "sg:city":"Middlesbrough",
    "sg:classifiers":[
        {
            "category":"Building & Trades",
            "subcategory":"Equipment Rental",
            "type":"Services"
        }
    ],
    "sg:phone":"+44 1642 217000",
    "sg:postcode":"TS3 8BT",
    "sg:province":"North Yorkshire",
    "sg:tags":[
        "plant",
        "machinery"
    ],
    "wof:name":"Anderson Plant Ltd",
    "wof:placetype":"venue"
},
  "geometry": {"coordinates":[-1.1871019602,54.5727157593],"type":"Point"}
}