{
  "type": "Feature",
  "properties": {
    "iso:country":"GB",
    "sg:address":"Unit 1 60 Crail Street",
    "sg:city":"Glasgow",
    "sg:classifiers":[
        {
            "category":"Farming",
            "subcategory":"Nursery",
            "type":"Manufacturing & Wholesale Goods"
        },
        {
            "category":"Social Services",
            "subcategory":"Child Care",
            "type":"Services"
        }
    ],
    "sg:phone":"+44 141 554 0440",
    "sg:postcode":"G31 5AL",
    "sg:province":"Glasgow City",
    "sg:tags":[
        "creche"
    ],
    "wof:name":"Parkhead Community Nursery",
    "wof:placetype":"venue"
},
  "geometry": {"coordinates":[-4.1910691261,55.8509216309],"type":"Point"}
}