{
  "type": "Feature",
  "properties": {
    "addr:full":"11-13 Weavers Ct Halstead Essex CO9 2JN",
    "addr:housenumber":"11-13",
    "addr:postcode":"co9 2jn",
    "addr:street":"Weavers Ct",
    "iso:country":"GB",
    "sg:address":"11-13 Weavers Ct",
    "sg:city":"Halstead",
    "sg:classifiers":[
        {
            "category":"Bars & Pubs",
            "type":"Food & Drink"
        },
        {
            "category":"Bars & Pubs",
            "subcategory":"Wine Bar",
            "type":"Food & Drink"
        }
    ],
    "sg:postcode":"CO9 2JN",
    "sg:province":"Essex",
    "sg:tags":[
        "pubs",
        "inn"
    ],
    "wof:name":"Smith,Mark,",
    "wof:placetype":"venue"
},
  "geometry": {"coordinates":[0.6420840025,51.9428443909],"type":"Point"}
}