{
  "type": "Feature",
  "properties": {
    "addr:full":"20b/20d Blackmore Road, Ebblake Industrial Estate, Verwood Wimborne Dorset BH21 6AX",
    "addr:housenumber":"20b / 20d",
    "addr:postcode":"bh21 6ax",
    "addr:street":"Blackmore Road Ebblake Industrial Estate",
    "iso:country":"GB",
    "sg:address":"20b/20d Blackmore Road, Ebblake Industrial Estate, Verwood",
    "sg:city":"Wimborne",
    "sg:classifiers":[
        {
            "category":"Manufacturing",
            "subcategory":"Rubber & Plastics",
            "type":"Manufacturing & Wholesale Goods"
        }
    ],
    "sg:phone":"+44 1202 822982",
    "sg:postcode":"BH21 6AX",
    "sg:province":"Dorset",
    "sg:tags":[
        "forming",
        "vacuum"
    ],
    "wof:name":"M & R Heathcote",
    "wof:placetype":"venue"
},
  "geometry": {"coordinates":[-1.88164,50.85017],"type":"Point"}
}