{
  "type": "Feature",
  "properties": {
    "iso:country":"GB",
    "sg:address":"Rhiwfelin Fach, Llantrisant",
    "sg:city":"Pontyclun",
    "sg:classifiers":[
        {
            "category":"Farming",
            "subcategory":"Livestock Farm",
            "type":"Manufacturing & Wholesale Goods"
        }
    ],
    "sg:phone":"+44 1443 224241",
    "sg:postcode":"CF72 8LQ",
    "sg:province":"Bridgend",
    "sg:tags":[
        "others"
    ],
    "wof:name":"Richard Jones",
    "wof:placetype":"venue"
},
  "geometry": {"coordinates":[-3.374301,51.540771],"type":"Point"}
}