{
  "type": "Feature",
  "properties": {
    "iso:country":"GB",
    "sg:address":"40 Stockwell Street, Greenwich",
    "sg:city":"London",
    "sg:classifiers":[
        {
            "category":"Real Estate",
            "subcategory":"Developer",
            "type":"Services"
        }
    ],
    "sg:phone":"+44 20 8858 0808",
    "sg:postcode":"SE10 9EY",
    "sg:province":"Greater London",
    "sg:tags":[
        "property"
    ],
    "wof:name":"Greenwich House Properties Ltd.",
    "wof:placetype":"venue"
},
  "geometry": {"coordinates":[-0.008491,51.479473],"type":"Point"}
}