{
  "type": "Feature",
  "properties": {
    "addr:full":"Itv Regional Sales, Anglia Television., 16, Park Street, Luton Bedfordshire LU1 3EP",
    "addr:housenumber":"16",
    "addr:postcode":"lu1 3ep",
    "addr:street":"Park Street",
    "iso:country":"GB",
    "sg:address":"Itv Regional Sales, Anglia Television., 16, Park Street,",
    "sg:city":"Luton",
    "sg:classifiers":[
        {
            "category":"Communications",
            "type":"Services"
        }
    ],
    "sg:phone":"+44 1582 413618",
    "sg:postcode":"LU1 3EP",
    "sg:province":"Bedfordshire",
    "sg:tags":[
        "broadcasting"
    ],
    "wof:name":"Granada Enterprises (Anglia TV)",
    "wof:placetype":"venue"
},
  "geometry": {"coordinates":[-0.4156149924,51.8813362122],"type":"Point"}
}