{
  "type": "Feature",
  "properties": {
    "addr:full":"Ellbridge Equitation Centre, Lower South Wraxall Bradford-on-avon Wiltshire BA15 2RR",
    "addr:postcode":"ba15 2rr",
    "addr:street":"Lower South",
    "iso:country":"GB",
    "sg:address":"Ellbridge Equitation Centre, Lower South Wraxall",
    "sg:city":"Bradford-on-avon",
    "sg:classifiers":[
        {
            "category":"Farming",
            "subcategory":"Livestock Farm",
            "type":"Manufacturing & Wholesale Goods"
        }
    ],
    "sg:phone":"+44 1225 864664",
    "sg:postcode":"BA15 2RR",
    "sg:province":"Wiltshire",
    "sg:tags":[
        "breeder"
    ],
    "wof:name":"Ellbridge Equitation Centre",
    "wof:placetype":"venue"
},
  "geometry": {"coordinates":[-2.243919,51.381351],"type":"Point"}
}