{
  "type": "Feature",
  "properties": {
    "addr:full":"24 Kingsend Ruislip Greater London HA4 7DA",
    "addr:housenumber":"24",
    "addr:postcode":"ha4 7da",
    "addr:street":"Kingsend Ruislip",
    "iso:country":"GB",
    "sg:address":"24 Kingsend",
    "sg:city":"Ruislip",
    "sg:classifiers":[
        {
            "category":"Professional",
            "subcategory":"Management & Consulting",
            "type":"Services"
        }
    ],
    "sg:postcode":"HA4 7DA",
    "sg:province":"Greater London",
    "sg:tags":[
        "consultant"
    ],
    "wof:name":"Network Solutions",
    "wof:placetype":"venue"
},
  "geometry": {"coordinates":[-0.426562,51.572369],"type":"Point"}
}