{
  "type": "Feature",
  "properties": {
    "iso:country":"GB",
    "sg:address":"18 Dan-y-bryn",
    "sg:city":"Abergavenny",
    "sg:classifiers":[
        {
            "category":"Building & Trades",
            "subcategory":"Construction",
            "type":"Services"
        }
    ],
    "sg:phone":"+44 1873 831646",
    "sg:postcode":"NP7 0BL",
    "sg:province":"Herefordshire",
    "sg:tags":[
        "contractor",
        "paving",
        "driveway"
    ],
    "wof:name":"Glamorgan Paving",
    "wof:placetype":"venue"
},
  "geometry": {"coordinates":[-3.0905690193,51.8269958496],"type":"Point"}
}