{
  "type": "Feature",
  "properties": {
    "addr:full":"Mill Of Alvah, Alvah Banff Aberdeenshire AB45 3UT",
    "addr:postcode":"ab45 3ut",
    "iso:country":"GB",
    "sg:address":"Mill Of Alvah, Alvah",
    "sg:city":"Banff",
    "sg:classifiers":[
        {
            "category":"Farming",
            "subcategory":"Farm",
            "type":"Manufacturing & Wholesale Goods"
        }
    ],
    "sg:phone":"+44 1261 821609",
    "sg:postcode":"AB45 3UT",
    "sg:province":"Aberdeenshire",
    "sg:tags":[
        "mixed",
        "crop"
    ],
    "wof:name":"John C Davidson & Son",
    "wof:placetype":"venue"
},
  "geometry": {"coordinates":[-2.541113,57.630913],"type":"Point"}
}