{
  "type": "Feature",
  "properties": {
    "addr:full":"3 Ribble Place Farnborough Hampshire GU14 9LX",
    "addr:housenumber":"3",
    "addr:postcode":"gu14 9lx",
    "addr:street":"Ribble Place",
    "iso:country":"GB",
    "sg:address":"3 Ribble Place",
    "sg:city":"Farnborough",
    "sg:classifiers":[
        {
            "category":"Building & Trades",
            "subcategory":"Cleaning & Sanitation",
            "type":"Services"
        }
    ],
    "sg:phone":"+44 1252 409874",
    "sg:postcode":"GU14 9LX",
    "sg:province":"Hampshire",
    "sg:tags":[
        "cleaner",
        "window"
    ],
    "wof:name":"Fleet Area Window Cleaners",
    "wof:placetype":"venue"
},
  "geometry": {"coordinates":[-0.778932,51.306042],"type":"Point"}
}