{
  "type": "Feature",
  "properties": {
    "addr:full":"533 Tottington Rd, Tottington Bury Lancashire BL8 1UB",
    "addr:housenumber":"533",
    "addr:postcode":"bl8 1ub",
    "addr:street":"Tottington Rd",
    "iso:country":"GB",
    "sg:address":"533 Tottington Rd, Tottington",
    "sg:city":"Bury",
    "sg:classifiers":[
        {
            "category":"Manufacturing",
            "subcategory":"Petroleum Products",
            "type":"Manufacturing & Wholesale Goods"
        }
    ],
    "sg:postcode":"BL8 1UB",
    "sg:province":"Lancashire",
    "sg:tags":[
        "double",
        "glazing"
    ],
    "wof:name":"Booth,Gary,",
    "wof:placetype":"venue"
},
  "geometry": {"coordinates":[-2.326019,53.60564],"type":"Point"}
}