{
  "type": "Feature",
  "properties": {
    "addr:full":"95 Crown Road Twickenham Greater London TW1 3EX",
    "addr:housenumber":"95",
    "addr:postcode":"tw1 3ex",
    "addr:street":"Crown Road",
    "iso:country":"GB",
    "sg:address":"95 Crown Road",
    "sg:city":"Twickenham",
    "sg:classifiers":[
        {
            "category":"Shopping",
            "subcategory":"Jewelry",
            "type":"Retail Goods"
        },
        {
            "category":"Shopping",
            "subcategory":"Comic Books",
            "type":"Retail Goods"
        }
    ],
    "sg:phone":"+44 20 8891 4920",
    "sg:postcode":"TW1 3EX",
    "sg:province":"Greater London",
    "sg:tags":[
        "jeweller",
        "sale",
        "jewellery",
        "gold",
        "silversmith"
    ],
    "wof:name":"The Bead & Jewellery Shop",
    "wof:placetype":"venue"
},
  "geometry": {"coordinates":[-0.3185220063,51.4514961243],"type":"Point"}
}