{
  "type": "Feature",
  "properties": {
    "iso:country":"GB",
    "sg:address":"78 Fernside Road",
    "sg:city":"Poole",
    "sg:classifiers":[
        {
            "category":"Health Services",
            "subcategory":"Podiatrist",
            "type":"Services"
        }
    ],
    "sg:phone":"+44 1202 681457",
    "sg:postcode":"BH15 2JL",
    "sg:province":"Dorset",
    "sg:tags":[
        "podiatrists",
        "chiropodist"
    ],
    "wof:name":"Edward Oliver",
    "wof:placetype":"venue"
},
  "geometry": {"coordinates":[-1.9698129892,50.7268562317],"type":"Point"}
}