{
  "type": "Feature",
  "properties": {
    "addr:full":"Oak Cottage, 17 Pool Lane Lymm Cheshire WA13 9BN",
    "addr:housenumber":"17",
    "addr:postcode":"wa13 9bn",
    "addr:street":"Pool Lane",
    "iso:country":"GB",
    "sg:address":"Oak Cottage, 17 Pool Lane",
    "sg:city":"Lymm",
    "sg:classifiers":[
        {
            "category":"Industrial Area",
            "type":"Public Place"
        }
    ],
    "sg:postcode":"WA13 9BN",
    "sg:province":"Cheshire",
    "sg:tags":[
        "consultant"
    ],
    "wof:name":"Osborne Associates Ltd.",
    "wof:placetype":"venue"
},
  "geometry": {"coordinates":[-2.4875559807,53.379573822],"type":"Point"}
}