{
  "type": "Feature",
  "properties": {
    "iso:country":"GB",
    "sg:address":"30 Ash Gro, Keighley Road, Cross Hills",
    "sg:city":"Keighley",
    "sg:classifiers":[
        {
            "category":"Shopping",
            "subcategory":"News",
            "type":"Retail Goods"
        }
    ],
    "sg:postcode":"BD20 7RU",
    "sg:province":"North Yorkshire",
    "sg:tags":[
        "newsagent"
    ],
    "wof:name":"Bailey,Jg & A,",
    "wof:placetype":"venue"
},
  "geometry": {"coordinates":[-1.9841799736,53.9012794495],"type":"Point"}
}