{
  "type": "Feature",
  "properties": {
    "addr:full":"22 Bullock Wood Close Colchester Essex CO4 0HX",
    "addr:housenumber":"22",
    "addr:postcode":"co4 0hx",
    "addr:street":"Bullock Wood Close",
    "iso:country":"GB",
    "sg:address":"22 Bullock Wood Close",
    "sg:city":"Colchester",
    "sg:classifiers":[
        {
            "category":"Building & Trades",
            "subcategory":"Plumbing",
            "type":"Services"
        }
    ],
    "sg:postcode":"CO4 0HX",
    "sg:province":"Essex",
    "sg:tags":[
        "heating"
    ],
    "wof:name":"S J Smith Plumbing & Heating Engineers",
    "wof:placetype":"venue"
},
  "geometry": {"coordinates":[0.930708,51.913654],"type":"Point"}
}