{
  "type": "Feature",
  "properties": {
    "addr:full":"Rowan House, Sheepen Road Colchester Essex CO3 3WG",
    "addr:postcode":"co3 3wg",
    "addr:street":"Sheepen Road Colchester",
    "iso:country":"GB",
    "sg:address":"Rowan House, Sheepen Road",
    "sg:city":"Colchester",
    "sg:classifiers":[
        {
            "category":"Travel",
            "subcategory":"Travel Agent",
            "type":"Entertainment"
        }
    ],
    "sg:phone":"+44 870 242 2422",
    "sg:postcode":"CO3 3WG",
    "sg:province":"Essex",
    "wof:name":"Gray Dawes Travel Ltd.",
    "wof:placetype":"venue"
},
  "geometry": {"coordinates":[0.887447,51.894913],"type":"Point"}
}