{
  "type": "Feature",
  "properties": {
    "addr:full":"195 Albion Street Glasgow Glasgow City G1 1QP",
    "addr:housenumber":"195",
    "addr:postcode":"g1 1qp",
    "addr:street":"Albion Street",
    "iso:country":"GB",
    "sg:address":"195 Albion Street",
    "sg:city":"Glasgow",
    "sg:classifiers":[
        {
            "category":"Communications",
            "subcategory":"Newspaper",
            "type":"Services"
        }
    ],
    "sg:phone":"+44 141 553 3340",
    "sg:postcode":"G1 1QP",
    "sg:province":"Glasgow City",
    "sg:tags":[
        "magazine"
    ],
    "wof:name":"Voice Internet Access & Publishing",
    "wof:placetype":"venue"
},
  "geometry": {"coordinates":[-4.243897,55.860451],"type":"Point"}
}