{
  "type": "Feature",
  "properties": {
    "iso:country":"GB",
    "sg:address":"Day Care Centre, Beaufort Avenue",
    "sg:city":"Blackpool",
    "sg:classifiers":[
        {
            "category":"Place Of Worship",
            "type":"Public Place"
        }
    ],
    "sg:phone":"+44 1253 594207",
    "sg:postcode":"FY2 9HQ",
    "sg:province":"Lancashire",
    "wof:name":"Bispham Methodist Church",
    "wof:placetype":"venue"
},
  "geometry": {"coordinates":[-3.0515298843,53.8502502441],"type":"Point"}
}