{
  "type": "Feature",
  "properties": {
    "iso:country":"GB",
    "sg:address":"5 Main Ridge",
    "sg:city":"Boston",
    "sg:classifiers":[
        {
            "category":"Professional",
            "subcategory":"Lawyer & Legal Services",
            "type":"Services"
        }
    ],
    "sg:postcode":"PE21 6QL",
    "sg:province":"Lincolnshire",
    "sg:tags":[
        "solicitor"
    ],
    "wof:name":"Jebb & Tunnard",
    "wof:placetype":"venue"
},
  "geometry": {"coordinates":[-0.018354,52.978394],"type":"Point"}
}