{
  "type": "Feature",
  "properties": {
    "addr:full":"Fulmar Way, Donibristle Technology Park Dunfermline Fife KY11 9FP",
    "addr:postcode":"ky11 9fp",
    "addr:street":"Fulmar Way;Technology Park Dunfermline",
    "iso:country":"GB",
    "sg:address":"Fulmar Way, Donibristle Technology Park",
    "sg:city":"Dunfermline",
    "sg:classifiers":[
        {
            "category":"Manufacturing",
            "subcategory":"Electronics",
            "type":"Manufacturing & Wholesale Goods"
        }
    ],
    "sg:phone":"+44 1383 824642",
    "sg:postcode":"KY11 9FP",
    "sg:province":"Fife",
    "sg:tags":[
        "mnfr",
        "component",
        "electronic"
    ],
    "wof:name":"Broadline Electronics",
    "wof:placetype":"venue"
},
  "geometry": {"coordinates":[-3.3563389778,56.0409889221],"type":"Point"}
}