{
  "type": "Feature",
  "properties": {
    "iso:country":"GB",
    "sg:address":"Farm Road, Glenboig",
    "sg:city":"Coatbridge",
    "sg:classifiers":[
        {
            "category":"Autos & Motor Vehicles",
            "subcategory":"Auto Supplies",
            "type":"Retail Goods"
        }
    ],
    "sg:phone":"+44 1236 875697",
    "sg:postcode":"ML5 2ST",
    "sg:province":"North Lanarkshire",
    "sg:tags":[
        "tyre"
    ],
    "wof:name":"Glenboig Tyres & Exhausts Ltd.",
    "wof:placetype":"venue"
},
  "geometry": {"coordinates":[-4.0438570976,55.8931617737],"type":"Point"}
}