{
  "type": "Feature",
  "properties": {
    "iso:country":"GB",
    "sg:address":"58 Lower Dock St",
    "sg:city":"Newport",
    "sg:classifiers":[
        {
            "category":"Sports & Exercise",
            "subcategory":"Gym",
            "type":"Entertainment"
        }
    ],
    "sg:phone":"+44 1633 660400",
    "sg:postcode":"NP20 1EF",
    "sg:province":"Newport",
    "sg:tags":[
        "fitness",
        "health",
        "centre"
    ],
    "wof:name":"Powergym",
    "wof:placetype":"venue"
},
  "geometry": {"coordinates":[-2.9911580086,51.5841522217],"type":"Point"}
}