{
  "type": "Feature",
  "properties": {
    "iso:country":"GB",
    "sg:address":"Rudford Estate, Ford Aerodrome",
    "sg:city":"Arundel",
    "sg:classifiers":[
        {
            "category":"Professional",
            "subcategory":"Management & Consulting",
            "type":"Services"
        }
    ],
    "sg:phone":"+44 1903 721531",
    "sg:postcode":"BN18 0BE",
    "sg:province":"West Sussex",
    "sg:tags":[
        "fire",
        "consultant",
        "protection"
    ],
    "wof:name":"Photain Controls Plc",
    "wof:placetype":"venue"
},
  "geometry": {"coordinates":[-0.580514,50.823326],"type":"Point"}
}