{
  "type": "Feature",
  "properties": {
    "addr:full":"15 Church Street Brechin Aberdeenshire DD9 6HB",
    "addr:housenumber":"15",
    "addr:postcode":"dd9 6hb",
    "addr:street":"Church Street",
    "iso:country":"GB",
    "sg:address":"15 Church Street",
    "sg:city":"Brechin",
    "sg:classifiers":[
        {
            "category":"Shopping",
            "subcategory":"Department Store",
            "type":"Retail Goods"
        },
        {
            "category":"Recreation",
            "subcategory":"Fishing",
            "type":"Entertainment"
        }
    ],
    "sg:phone":"+44 1356 625700",
    "sg:postcode":"DD9 6HB",
    "sg:province":"Aberdeenshire",
    "sg:tags":[
        "angling"
    ],
    "wof:name":"Graham Carroll Fishing Tackle",
    "wof:placetype":"venue"
},
  "geometry": {"coordinates":[-2.6604189873,56.7313308716],"type":"Point"}
}