{
  "type": "Feature",
  "properties": {
    "iso:country":"GB",
    "sg:address":"5 Russell Parade, Golders Green Road",
    "sg:city":"London",
    "sg:classifiers":[
        {
            "category":"Home & Garden",
            "subcategory":"Hardware",
            "type":"Retail Goods"
        }
    ],
    "sg:postcode":"NW11 9NN",
    "sg:province":"Greater London",
    "sg:tags":[
        "retailer",
        "diy"
    ],
    "wof:name":"Golders Green D I Y",
    "wof:placetype":"venue"
},
  "geometry": {"coordinates":[-0.206684,51.577908],"type":"Point"}
}