{
  "type": "Feature",
  "properties": {
    "addr:full":"95 Fore Street, Topsham Exeter Devon EX3 0HQ",
    "addr:housenumber":"95",
    "addr:postcode":"ex3 0hq",
    "addr:street":"Fore Street",
    "iso:country":"GB",
    "sg:address":"95 Fore Street, Topsham",
    "sg:city":"Exeter",
    "sg:classifiers":[
        {
            "category":"Communications",
            "subcategory":"Film & Video Production",
            "type":"Services"
        }
    ],
    "sg:phone":"+44 1392 873964",
    "sg:postcode":"EX3 0HQ",
    "sg:province":"Devon",
    "sg:tags":[
        "tv",
        "studio"
    ],
    "wof:name":"Havills",
    "wof:placetype":"venue"
},
  "geometry": {"coordinates":[-3.4668660164,50.6847610474],"type":"Point"}
}