{
  "type": "Feature",
  "properties": {
    "iso:country":"GB",
    "sg:address":"Flint House, Boyneswood Road, Medstead",
    "sg:city":"Alton",
    "sg:classifiers":[
        {
            "category":"Building & Trades",
            "subcategory":"Landscaping Services",
            "type":"Services"
        }
    ],
    "sg:phone":"+44 1420 562020",
    "sg:postcode":"GU34 5EA",
    "sg:province":"Hampshire",
    "sg:tags":[
        "forestry",
        "tree"
    ],
    "wof:name":"Powell Forestry",
    "wof:placetype":"venue"
},
  "geometry": {"coordinates":[-1.041568,51.119335],"type":"Point"}
}