{
  "type": "Feature",
  "properties": {
    "addr:full":"20-22 Anyards Road Cobham Surrey KT11 2JZ",
    "addr:housenumber":"20-22",
    "addr:postcode":"kt11 2jz",
    "addr:street":"Anyards Road",
    "iso:country":"GB",
    "sg:address":"20-22 Anyards Road",
    "sg:city":"Cobham",
    "sg:classifiers":[
        {
            "category":"Autos & Motor Vehicles",
            "subcategory":"Automobile Sales",
            "type":"Retail Goods"
        }
    ],
    "sg:phone":"+44 1932 867888",
    "sg:postcode":"KT11 2JZ",
    "sg:province":"Surrey",
    "sg:tags":[
        "car"
    ],
    "wof:name":"Weybridge Automobiles Jeep Sales",
    "wof:placetype":"venue"
},
  "geometry": {"coordinates":[-0.410675,51.329838],"type":"Point"}
}