{
  "type": "Feature",
  "properties": {
    "iso:country":"GB",
    "sg:address":"Sadlers Lane Farm, Eccleston",
    "sg:city":"St Helens",
    "sg:classifiers":[
        {
            "category":"Freight",
            "type":"Transportation"
        }
    ],
    "sg:postcode":"WA11 7HT",
    "sg:province":"Lancashire",
    "sg:tags":[
        "haulage",
        "road"
    ],
    "wof:name":"Raymond S Charnock",
    "wof:placetype":"venue"
},
  "geometry": {"coordinates":[-2.793364048,53.4700088501],"type":"Point"}
}