{
  "type": "Feature",
  "properties": {
    "addr:full":"3 The Avenue Leeds North Yorkshire LS17 7BD",
    "addr:housenumber":"3",
    "addr:postcode":"ls17 7bd",
    "addr:street":"The Avenue",
    "iso:country":"GB",
    "sg:address":"3 The Avenue",
    "sg:city":"Leeds",
    "sg:classifiers":[
        {
            "category":"Food & Beverages",
            "subcategory":"Meat & Fish",
            "type":"Retail Goods"
        }
    ],
    "sg:phone":"+44 113 267 5511",
    "sg:postcode":"LS17 7BD",
    "sg:province":"North Yorkshire",
    "sg:tags":[
        "butcher"
    ],
    "wof:name":"G Walker",
    "wof:placetype":"venue"
},
  "geometry": {"coordinates":[-1.56255,53.856907],"type":"Point"}
}