{
  "type": "Feature",
  "properties": {
    "addr:full":"Fernwood House, Ash Hill Crescent Doncaster South Yorkshire DN7 6HZ",
    "addr:postcode":"dn7 6hz",
    "addr:street":"Ash Hill Crescent",
    "iso:country":"GB",
    "sg:address":"Fernwood House, Ash Hill Crescent",
    "sg:city":"Doncaster",
    "sg:classifiers":[
        {
            "category":"Fast Food",
            "type":"Food & Drink"
        }
    ],
    "sg:phone":"+44 1302 843364",
    "sg:postcode":"DN7 6HZ",
    "sg:province":"South Yorkshire",
    "sg:tags":[
        "away",
        "take"
    ],
    "wof:name":"Casanova Pizzeria",
    "wof:placetype":"venue"
},
  "geometry": {"coordinates":[-1.0077890158,53.5801696777],"type":"Point"}
}