{
  "type": "Feature",
  "properties": {
    "addr:full":"78 Manor Rd Wallington Surrey SM6 8RZ",
    "addr:housenumber":"78",
    "addr:postcode":"sm6 8rz",
    "addr:street":"Manor Rd",
    "iso:country":"GB",
    "sg:address":"78 Manor Rd",
    "sg:city":"Wallington",
    "sg:classifiers":[
        {
            "category":"Professional",
            "subcategory":"Lawyer & Legal Services",
            "type":"Services"
        }
    ],
    "sg:phone":"+44 20 8647 3666",
    "sg:postcode":"SM6 8RZ",
    "sg:province":"Surrey",
    "wof:name":"Cromwell House Expert Support Service",
    "wof:placetype":"venue"
},
  "geometry": {"coordinates":[-0.151789,51.364193],"type":"Point"}
}