{
  "type": "Feature",
  "properties": {
    "iso:country":"GB",
    "sg:address":"Devonshire Road, Broadheath",
    "sg:city":"Altrincham",
    "sg:classifiers":[
        {
            "category":"Sports & Exercise",
            "subcategory":"Ice Rink",
            "type":"Entertainment"
        }
    ],
    "sg:phone":"+44 161 928 1360",
    "sg:postcode":"WA14 4EZ",
    "sg:province":"Cheshire",
    "sg:tags":[
        "skating"
    ],
    "wof:name":"Altrincham Ice Rink",
    "wof:placetype":"venue"
},
  "geometry": {"coordinates":[-2.352774,53.396446],"type":"Point"}
}