{
  "type": "Feature",
  "properties": {
    "iso:country":"GB",
    "sg:address":"Wern Farm, Wern, Weston Rhyn",
    "sg:city":"Oswestry",
    "sg:classifiers":[
        {
            "category":"Farming",
            "subcategory":"Livestock Farm",
            "type":"Manufacturing & Wholesale Goods"
        }
    ],
    "sg:phone":"+44 1691 659770",
    "sg:postcode":"SY10 7LH",
    "sg:province":"Shropshire",
    "sg:tags":[
        "others"
    ],
    "wof:name":"Tudor M Evans",
    "wof:placetype":"venue"
},
  "geometry": {"coordinates":[-3.054109,52.917259],"type":"Point"}
}