{
  "type": "Feature",
  "properties": {
    "iso:country":"GB",
    "sg:address":"Sac Doig Scott Building, Craibstone Estate, Bucksburn",
    "sg:city":"Aberdeen",
    "sg:classifiers":[
        {
            "category":"Shopping",
            "type":"Retail Goods"
        }
    ],
    "sg:phone":"+44 1224 711122",
    "sg:postcode":"AB21 9TQ",
    "sg:province":"Aberdeen City",
    "sg:tags":[
        "scientific",
        "apparatus"
    ],
    "wof:name":"McQuilkin & Co",
    "wof:placetype":"venue"
},
  "geometry": {"coordinates":[-2.18166,57.178139],"type":"Point"}
}