{
  "type": "Feature",
  "properties": {
    "addr:full":"2 Bronte Close, Gomersal Cleckheaton West Yorkshire BD19 4PU",
    "addr:housenumber":"2",
    "addr:postcode":"bd19 4pu",
    "addr:street":"Bronte Close;West",
    "iso:country":"GB",
    "sg:address":"2 Bronte Close, Gomersal",
    "sg:city":"Cleckheaton",
    "sg:classifiers":[
        {
            "category":"Building & Trades",
            "subcategory":"Landscaping Services",
            "type":"Services"
        }
    ],
    "sg:phone":"+44 1274 862035",
    "sg:postcode":"BD19 4PU",
    "sg:province":"West Yorkshire",
    "sg:tags":[
        "landscape",
        "contractor"
    ],
    "wof:name":"Lakeland Landscapes",
    "wof:placetype":"venue"
},
  "geometry": {"coordinates":[-1.683844,53.730164],"type":"Point"}
}