{
  "type": "Feature",
  "properties": {
    "addr:full":"91-93 Farringdon Rd Clerkenwell Greater London EC1M 3LL",
    "addr:housenumber":"91-93",
    "addr:postcode":"ec1m 3ll",
    "addr:street":"Farringdon Rd",
    "iso:country":"GB",
    "sg:address":"91-93 Farringdon Rd",
    "sg:city":"Clerkenwell",
    "sg:classifiers":[
        {
            "category":"Wholesale",
            "subcategory":"Books, Periodicals, & Newspapers",
            "type":"Manufacturing & Wholesale Goods"
        }
    ],
    "sg:phone":"+44 20 7404 2322",
    "sg:postcode":"EC1M 3LL",
    "sg:province":"Greater London",
    "sg:tags":[
        "publishing"
    ],
    "wof:name":"Beaumont Corporation The",
    "wof:placetype":"venue"
},
  "geometry": {"coordinates":[-0.10706,51.521969],"type":"Point"}
}