{
  "type": "Feature",
  "properties": {
    "addr:full":"Old Wrexham Road, Gresford Wrexham Wrexham LL12 8TY",
    "addr:postcode":"ll12 8ty",
    "addr:street":"Old Wrexham Road",
    "iso:country":"GB",
    "sg:address":"Old Wrexham Road, Gresford",
    "sg:city":"Wrexham",
    "sg:classifiers":[
        {
            "category":"Farming",
            "subcategory":"Nursery",
            "type":"Manufacturing & Wholesale Goods"
        }
    ],
    "sg:phone":"+44 1978 853946",
    "sg:postcode":"LL12 8TY",
    "sg:province":"Wrexham",
    "sg:tags":[
        "creche"
    ],
    "wof:name":"The Homestead Day Nursey",
    "wof:placetype":"venue"
},
  "geometry": {"coordinates":[-2.9654140472,53.08801651],"type":"Point"}
}