{
  "type": "Feature",
  "properties": {
    "iso:country":"GB",
    "sg:address":"14 Coatham Gro",
    "sg:city":"Billingham",
    "sg:classifiers":[
        {
            "category":"Utilities",
            "type":"Services"
        }
    ],
    "sg:postcode":"TS23 3QF",
    "sg:province":"Durham",
    "sg:tags":[
        "internet"
    ],
    "wof:name":"Avocet Consulting",
    "wof:placetype":"venue"
},
  "geometry": {"coordinates":[-1.2814830542,54.6208763123],"type":"Point"}
}