{
  "type": "Feature",
  "properties": {
    "iso:country":"GB",
    "sg:address":"9 Tudor Parade, High Road",
    "sg:city":"Romford",
    "sg:classifiers":[
        {
            "category":"Shopping",
            "subcategory":"Florist",
            "type":"Retail Goods"
        }
    ],
    "sg:postcode":"RM6 6PS",
    "sg:province":"Essex",
    "wof:name":"Chadwells",
    "wof:placetype":"venue"
},
  "geometry": {"coordinates":[0.1327600032,51.5709495544],"type":"Point"}
}