{
  "type": "Feature",
  "properties": {
    "addr:full":"99 North Street Abergavenny Herefordshire NP7 7EB",
    "addr:housenumber":"99",
    "addr:postcode":"np7 7eb",
    "addr:street":"North Street",
    "iso:country":"GB",
    "sg:address":"99 North Street",
    "sg:city":"Abergavenny",
    "sg:classifiers":[
        {
            "category":"Building & Trades",
            "subcategory":"Construction",
            "type":"Services"
        }
    ],
    "sg:phone":"+44 1873 857059",
    "sg:postcode":"NP7 7EB",
    "sg:province":"Herefordshire",
    "sg:tags":[
        "roofing",
        "contracting"
    ],
    "wof:name":"B K Building Services Ltd.",
    "wof:placetype":"venue"
},
  "geometry": {"coordinates":[-3.0306520462,51.8284187317],"type":"Point"}
}