{
  "type": "Feature",
  "properties": {
    "addr:full":"Bards Hall Farm Mashbury Road, Mashbury Chelmsford Essex CM1 4TL",
    "addr:postcode":"cm1 4tl",
    "addr:street":"Mashbury Road",
    "iso:country":"GB",
    "sg:address":"Bards Hall Farm Mashbury Road, Mashbury",
    "sg:city":"Chelmsford",
    "sg:classifiers":[
        {
            "category":"Building & Trades",
            "subcategory":"Landscaping Services",
            "type":"Services"
        }
    ],
    "sg:phone":"+44 1245 362988",
    "sg:postcode":"CM1 4TL",
    "sg:province":"Essex",
    "sg:tags":[
        "forestry",
        "tree"
    ],
    "wof:name":"Pleshey Tree Services Ltd.",
    "wof:placetype":"venue"
},
  "geometry": {"coordinates":[0.3953419924,51.7834205627],"type":"Point"}
}