{
  "type": "Feature",
  "properties": {
    "iso:country":"GB",
    "sg:address":"8 Green Street, Hazlemere",
    "sg:city":"High Wycombe",
    "sg:classifiers":[
        {
            "category":"Wholesale",
            "subcategory":"Scrap",
            "type":"Manufacturing & Wholesale Goods"
        },
        {
            "category":"Retail",
            "subcategory":"Auto Repair",
            "type":"Services"
        }
    ],
    "sg:postcode":"HP15 7RB",
    "sg:province":"Buckinghamshire",
    "sg:tags":[
        "modification",
        "garage",
        "breaker",
        "dismantlers"
    ],
    "wof:name":"Howard Autos",
    "wof:placetype":"venue"
},
  "geometry": {"coordinates":[-0.714368,51.6516],"type":"Point"}
}