{
  "type": "Feature",
  "properties": {
    "iso:country":"GB",
    "sg:address":"West Street, Steeple Claydon",
    "sg:city":"Buckingham",
    "sg:classifiers":[
        {
            "category":"Bars & Pubs",
            "type":"Food & Drink"
        }
    ],
    "sg:phone":"+44 1296 730286",
    "sg:postcode":"MK18 2NT",
    "sg:province":"Buckinghamshire",
    "sg:tags":[
        "pubs",
        "inn"
    ],
    "wof:name":"The Fountain Inn",
    "wof:placetype":"venue"
},
  "geometry": {"coordinates":[-0.980986,51.936157],"type":"Point"}
}