{
  "type": "Feature",
  "properties": {
    "addr:full":"6a Wantage Road Hungerford Berkshire RG17 7BY",
    "addr:housenumber":"6a",
    "addr:postcode":"rg17 7by",
    "addr:street":"Wantage Road",
    "iso:country":"GB",
    "sg:address":"6a Wantage Road",
    "sg:city":"Hungerford",
    "sg:classifiers":[
        {
            "category":"Brewery",
            "type":"Food & Drink"
        }
    ],
    "sg:phone":"+44 1488 648133",
    "sg:postcode":"RG17 7BY",
    "sg:province":"Berkshire",
    "sg:tags":[
        "brewer"
    ],
    "wof:name":"Butts Brewery Ltd.",
    "wof:placetype":"venue"
},
  "geometry": {"coordinates":[-1.434376955,51.4921722412],"type":"Point"}
}