{
  "type": "Feature",
  "properties": {
    "addr:full":"Main Road, Gilwern Abergavenny Herefordshire NP7 0AU",
    "addr:postcode":"np7 0au",
    "addr:street":"Main Road",
    "iso:country":"GB",
    "sg:address":"Main Road, Gilwern",
    "sg:city":"Abergavenny",
    "sg:classifiers":[
        {
            "category":"Shopping",
            "subcategory":"Pharmacy",
            "type":"Retail Goods"
        }
    ],
    "sg:phone":"+44 1873 830647",
    "sg:postcode":"NP7 0AU",
    "sg:province":"Herefordshire",
    "sg:tags":[
        "pharmacist",
        "chemist"
    ],
    "wof:name":"T H Pritchard & Son Ltd.",
    "wof:placetype":"venue"
},
  "geometry": {"coordinates":[-3.091039,51.825275],"type":"Point"}
}