{
  "type": "Feature",
  "properties": {
    "addr:full":"71b Westoe Road South Shields Tyne and Wear NE33 4LU",
    "addr:housenumber":"71b",
    "addr:postcode":"ne33 4lu",
    "addr:street":"Westoe Road",
    "iso:country":"GB",
    "sg:address":"71b Westoe Road",
    "sg:city":"South Shields",
    "sg:classifiers":[
        {
            "category":"Personal",
            "subcategory":"Beauty Salon",
            "type":"Services"
        }
    ],
    "sg:phone":"+44 191 454 0365",
    "sg:postcode":"NE33 4LU",
    "sg:province":"Tyne and Wear",
    "sg:tags":[
        "unisex",
        "hairdresser"
    ],
    "wof:name":"Karens Hair Studio",
    "wof:placetype":"venue"
},
  "geometry": {"coordinates":[-1.428303,54.992523],"type":"Point"}
}