{
  "type": "Feature",
  "properties": {
    "iso:country":"GB",
    "sg:address":"54 Poplar Road",
    "sg:city":"Solihull",
    "sg:classifiers":[
        {
            "category":"Personal",
            "subcategory":"Barber",
            "type":"Services"
        }
    ],
    "sg:phone":"+44 121 705 1117",
    "sg:postcode":"B91 3AB",
    "sg:province":"West Midlands",
    "sg:tags":[
        "men's",
        "hairdresser"
    ],
    "wof:name":"Kents Hairdressers",
    "wof:placetype":"venue"
},
  "geometry": {"coordinates":[-1.7793649435,52.4140739441],"type":"Point"}
}