{
  "type": "Feature",
  "properties": {
    "addr:full":"The Old Exchange, Upper Parade Sq Manchester Greater Manchester M27 4EN",
    "addr:postcode":"m27 4en",
    "addr:street":"Upper Parade Sq",
    "iso:country":"GB",
    "sg:address":"The Old Exchange, Upper Parade Sq",
    "sg:city":"Manchester",
    "sg:classifiers":[
        {
            "category":"Professional",
            "subcategory":"Business Services",
            "type":"Services"
        }
    ],
    "sg:phone":"+44 161 728 1000",
    "sg:postcode":"M27 4EN",
    "sg:province":"Greater Manchester",
    "sg:tags":[
        "holding"
    ],
    "wof:name":"Core Corporation",
    "wof:placetype":"venue"
},
  "geometry": {"coordinates":[-2.2441840172,53.4823188782],"type":"Point"}
}