{
  "type": "Feature",
  "properties": {
    "iso:country":"GB",
    "sg:address":"271 Western Road, Crookes",
    "sg:city":"Sheffield",
    "sg:classifiers":[
        {
            "category":"Retail",
            "subcategory":"Funeral Services",
            "type":"Services"
        }
    ],
    "sg:phone":"+44 114 272 1671",
    "sg:postcode":"S10 1LE",
    "sg:province":"South Yorkshire",
    "wof:name":"Swift & Goodinson Ltd.",
    "wof:placetype":"venue"
},
  "geometry": {"coordinates":[-1.50572,53.387501],"type":"Point"}
}