{
  "type": "Feature",
  "properties": {
    "addr:full":"21 Alexandria Drive Lytham St Annes Lancashire FY8 1JF",
    "addr:housenumber":"21",
    "addr:postcode":"fy8 1jf",
    "addr:street":"Alexandria Drive",
    "iso:country":"GB",
    "sg:address":"21 Alexandria Drive",
    "sg:city":"Lytham St Annes",
    "sg:classifiers":[
        {
            "category":"Wholesale",
            "subcategory":"Fruits & Vegetables",
            "type":"Manufacturing & Wholesale Goods"
        }
    ],
    "sg:phone":"+44 1253 789203",
    "sg:postcode":"FY8 1JF",
    "sg:province":"Lancashire",
    "wof:name":"Garden of Eden",
    "wof:placetype":"venue"
},
  "geometry": {"coordinates":[-3.022454,53.745056],"type":"Point"}
}