{
  "type": "Feature",
  "properties": {
    "addr:full":"4 Bordeaux Clo Dudley West Midlands DY1 2UY",
    "addr:housenumber":"4",
    "addr:postcode":"dy1 2uy",
    "addr:street":"Bordeaux Clo",
    "iso:country":"GB",
    "sg:address":"4 Bordeaux Clo",
    "sg:city":"Dudley",
    "sg:classifiers":[
        {
            "category":"Shopping",
            "subcategory":"Stationery & Office Supplies",
            "type":"Retail Goods"
        }
    ],
    "sg:phone":"+44 1384 458184",
    "sg:postcode":"DY1 2UY",
    "sg:province":"West Midlands",
    "sg:tags":[
        "printers'"
    ],
    "wof:name":"P A Edgar",
    "wof:placetype":"venue"
},
  "geometry": {"coordinates":[-2.1141829491,52.5173683167],"type":"Point"}
}