{
  "type": "Feature",
  "properties": {
    "addr:full":"1 St Aldate St Gloucester Gloucestershire GL1 1RP",
    "addr:housenumber":"1",
    "addr:postcode":"gl1 1rp",
    "addr:street":"St Aldate St",
    "iso:country":"GB",
    "sg:address":"1 St Aldate St",
    "sg:city":"Gloucester",
    "sg:classifiers":[
        {
            "category":"Recreation",
            "subcategory":"Amusement Park",
            "type":"Entertainment"
        }
    ],
    "sg:phone":"+44 1452 529336",
    "sg:postcode":"GL1 1RP",
    "sg:province":"Gloucestershire",
    "sg:tags":[
        "arcade",
        "activity"
    ],
    "wof:name":"Raffles Entertainments",
    "wof:placetype":"venue"
},
  "geometry": {"coordinates":[-2.2439479828,51.8665084839],"type":"Point"}
}