{
  "type": "Feature",
  "properties": {
    "addr:full":"306 Hob Moor Road, Small Heath Birmingham West Midlands B10 9HH",
    "addr:housenumber":"306",
    "addr:postcode":"b10 9hh",
    "addr:street":"Hob Moor Road",
    "iso:country":"GB",
    "sg:address":"306 Hob Moor Road, Small Heath",
    "sg:city":"Birmingham",
    "sg:classifiers":[
        {
            "category":"Personal",
            "subcategory":"Beauty Salon",
            "type":"Services"
        },
        {
            "category":"Personal",
            "subcategory":"Barber",
            "type":"Services"
        }
    ],
    "sg:phone":"+44 121 789 9464",
    "sg:postcode":"B10 9HH",
    "sg:province":"West Midlands",
    "sg:tags":[
        "unisex",
        "hairdresser"
    ],
    "wof:name":"Cutting Crew",
    "wof:placetype":"venue"
},
  "geometry": {"coordinates":[-1.829625,52.470848],"type":"Point"}
}