{
  "type": "Feature",
  "properties": {
    "addr:full":"Portland Villas, Off North Road East Plymouth Devon PL4 6DX",
    "addr:postcode":"pl4 6dx",
    "addr:street":"North Road East",
    "iso:country":"GB",
    "sg:address":"Portland Villas, Off North Road East",
    "sg:city":"Plymouth",
    "sg:classifiers":[
        {
            "category":"Place Of Worship",
            "type":"Public Place"
        }
    ],
    "sg:phone":"+44 1752 225293",
    "sg:postcode":"PL4 6DX",
    "sg:province":"Devon",
    "wof:name":"Christadelphians",
    "wof:placetype":"venue"
},
  "geometry": {"coordinates":[-4.136894,50.375805],"type":"Point"}
}