{
  "type": "Feature",
  "properties": {
    "addr:full":"105a Euston Street London Greater London NW1 2EW",
    "addr:housenumber":"105a",
    "addr:postcode":"nw1 2ew",
    "addr:street":"Euston Street",
    "iso:country":"GB",
    "sg:address":"105a Euston Street",
    "sg:city":"London",
    "sg:classifiers":[
        {
            "category":"Professional",
            "subcategory":"Printing & Photocopies",
            "type":"Services"
        }
    ],
    "sg:phone":"+44 20 7383 2212",
    "sg:postcode":"NW1 2EW",
    "sg:province":"Greater London",
    "sg:tags":[
        "printer"
    ],
    "wof:name":"Page Bros",
    "wof:placetype":"venue"
},
  "geometry": {"coordinates":[-0.135704,51.526752],"type":"Point"}
}