{
  "type": "Feature",
  "properties": {
    "iso:country":"GB",
    "sg:address":"20 Summer Road, Acocks Green",
    "sg:city":"Birmingham",
    "sg:classifiers":[
        {
            "category":"Health Services",
            "subcategory":"Dentist",
            "type":"Services"
        }
    ],
    "sg:phone":"+44 121 708 2994",
    "sg:postcode":"B27 7UT",
    "sg:province":"West Midlands",
    "wof:name":"G J B Cottam",
    "wof:placetype":"venue"
},
  "geometry": {"coordinates":[-1.8333799839,52.4449691772],"type":"Point"}
}