{
  "type": "Feature",
  "properties": {
    "addr:full":"1 Sunshine Caravan Pk, Hogmoor Rd  Whitehill Bordon Hampshire GU35 9HW",
    "addr:housenumber":"1",
    "addr:postcode":"gu35 9hw",
    "addr:street":"Caravan Pk Hogmoor Rd",
    "iso:country":"GB",
    "sg:address":"1 Sunshine Caravan Pk, Hogmoor Rd  Whitehill",
    "sg:city":"Bordon",
    "sg:classifiers":[
        {
            "category":"Building & Trades",
            "subcategory":"Landscaping Services",
            "type":"Services"
        }
    ],
    "sg:postcode":"GU35 9HW",
    "sg:province":"Hampshire",
    "sg:tags":[
        "landscape",
        "contractor"
    ],
    "wof:name":"Oakhanger Landscapes",
    "wof:placetype":"venue"
},
  "geometry": {"coordinates":[-0.865114,51.108856],"type":"Point"}
}