{
  "type": "Feature",
  "properties": {
    "addr:full":"93 Croydon Road Beckenham Kent BR3 4AQ",
    "addr:housenumber":"93",
    "addr:postcode":"br3 4aq",
    "addr:street":"Croydon Road",
    "iso:country":"GB",
    "sg:address":"93 Croydon Road",
    "sg:city":"Beckenham",
    "sg:classifiers":[
        {
            "category":"Retail",
            "subcategory":"Auto Repair",
            "type":"Services"
        }
    ],
    "sg:postcode":"BR3 4AQ",
    "sg:province":"Kent",
    "sg:tags":[
        "electrician"
    ],
    "wof:name":"Metrolec Engineering Services",
    "wof:placetype":"venue"
},
  "geometry": {"coordinates":[-0.0451549999,51.3985214233],"type":"Point"}
}