{
  "type": "Feature",
  "properties": {
    "iso:country":"GB",
    "sg:address":"19 Eign Gate",
    "sg:city":"Hereford",
    "sg:classifiers":[
        {
            "category":"Shopping",
            "subcategory":"Clothing, Apparel, & Fashions",
            "type":"Retail Goods"
        }
    ],
    "sg:phone":"+44 1432 265084",
    "sg:postcode":"HR4 0AB",
    "sg:province":"Herefordshire",
    "sg:tags":[
        "shop"
    ],
    "wof:name":"Be-Wise Ltd",
    "wof:placetype":"venue"
},
  "geometry": {"coordinates":[-2.720629,52.05669],"type":"Point"}
}