{
  "type": "Feature",
  "properties": {
    "addr:full":"36 Haslemere Road High Wycombe Buckinghamshire HP10 8AD",
    "addr:housenumber":"36",
    "addr:postcode":"hp10 8ad",
    "addr:street":"Haslemere Road",
    "iso:country":"GB",
    "sg:address":"36 Haslemere Road",
    "sg:city":"High Wycombe",
    "sg:classifiers":[
        {
            "category":"Retail",
            "subcategory":"Auto Repair",
            "type":"Services"
        }
    ],
    "sg:phone":"+44 1494 816525",
    "sg:postcode":"HP10 8AD",
    "sg:province":"Buckinghamshire",
    "sg:tags":[
        "modification",
        "garage"
    ],
    "wof:name":"Sonalex Garage Ltd.",
    "wof:placetype":"venue"
},
  "geometry": {"coordinates":[-0.694642,51.642181],"type":"Point"}
}