{
  "type": "Feature",
  "properties": {
    "addr:full":"Aurelia Barn, Heath Road, Ixworth Bury St Edmunds Suffolk IP31 2JP",
    "addr:postcode":"ip31 2jp",
    "addr:street":"Aurelia;Heath Road",
    "iso:country":"GB",
    "sg:address":"Aurelia Barn, Heath Road, Ixworth",
    "sg:city":"Bury St Edmunds",
    "sg:classifiers":[
        {
            "category":"Education",
            "subcategory":"Special Training",
            "type":"Public Place"
        }
    ],
    "sg:phone":"+44 1359 268826",
    "sg:postcode":"IP31 2JP",
    "sg:province":"Suffolk",
    "sg:tags":[
        "product",
        "centre"
    ],
    "wof:name":"Aurelia Ltd.",
    "wof:placetype":"venue"
},
  "geometry": {"coordinates":[0.8396499753,52.2942047119],"type":"Point"}
}