{
  "type": "Feature",
  "properties": {
    "addr:full":"Unit 4 Smithfield Enterprise Estate, Whitworth St East Manchester Greater Manchester M11 2NQ",
    "addr:housenumber":"unit 4",
    "addr:postcode":"m11 2nq",
    "addr:street":"Smithfield Enterprise Estate;St",
    "iso:country":"GB",
    "sg:address":"Unit 4 Smithfield Enterprise Estate, Whitworth St East",
    "sg:city":"Manchester",
    "sg:classifiers":[
        {
            "category":"Shopping",
            "subcategory":"Florist",
            "type":"Retail Goods"
        }
    ],
    "sg:phone":"+44 161 223 2326",
    "sg:postcode":"M11 2NQ",
    "sg:province":"Greater Manchester",
    "wof:name":"Grain Sort",
    "wof:placetype":"venue"
},
  "geometry": {"coordinates":[-2.1746499538,53.4729003906],"type":"Point"}
}