{
  "type": "Feature",
  "properties": {
    "addr:full":"Apton Road Bishops Stortford Essex CM23 3SN",
    "addr:postcode":"cm23 3sn",
    "addr:street":"Apton Road",
    "iso:country":"GB",
    "sg:address":"Apton Road",
    "sg:city":"Bishops Stortford",
    "sg:classifiers":[
        {
            "category":"Education",
            "subcategory":"School",
            "type":"Public Place"
        }
    ],
    "sg:postcode":"CM23 3SN",
    "sg:province":"Essex",
    "sg:tags":[
        "local",
        "authority"
    ],
    "wof:name":"St Michael's C of E Primary School",
    "wof:placetype":"venue"
},
  "geometry": {"coordinates":[0.157843,51.869343],"type":"Point"}
}