{
  "type": "Feature",
  "properties": {
    "addr:full":"Windy Ridge, Selside Kendal Cumbria LA8 9LE",
    "addr:postcode":"la8 9le",
    "iso:country":"GB",
    "sg:address":"Windy Ridge, Selside",
    "sg:city":"Kendal",
    "sg:classifiers":[
        {
            "category":"Building & Trades",
            "subcategory":"Landscaping Services",
            "type":"Services"
        },
        {
            "category":"Manufacturing",
            "subcategory":"Musical Instruments",
            "type":"Manufacturing & Wholesale Goods"
        }
    ],
    "sg:phone":"+44 1539 823310",
    "sg:postcode":"LA8 9LE",
    "sg:province":"Cumbria",
    "sg:tags":[
        "horticultural",
        "consultant",
        "agent",
        "manufacturer"
    ],
    "wof:name":"R J Brown",
    "wof:placetype":"venue"
},
  "geometry": {"coordinates":[-2.7167870998,54.3852310181],"type":"Point"}
}