{
  "type": "Feature",
  "properties": {
    "iso:country":"GB",
    "sg:address":"10 Buchanan Units, Stephenson Road",
    "sg:city":"Clacton-on-sea",
    "sg:classifiers":[
        {
            "category":"Shopping",
            "subcategory":"Florist",
            "type":"Retail Goods"
        }
    ],
    "sg:phone":"+44 1255 422666",
    "sg:postcode":"CO15 4XA",
    "sg:province":"Essex",
    "sg:tags":[
        "wholesale"
    ],
    "wof:name":"Impulse Flowers",
    "wof:placetype":"venue"
},
  "geometry": {"coordinates":[1.1532700062,51.8018264771],"type":"Point"}
}