{
  "type": "Feature",
  "properties": {
    "addr:full":"84 Chilwell Rd, Beeston Nottingham Nottinghamshire NG9 1ES",
    "addr:housenumber":"84",
    "addr:postcode":"ng9 1es",
    "addr:street":"Chilwell Rd",
    "iso:country":"GB",
    "sg:address":"84 Chilwell Rd, Beeston",
    "sg:city":"Nottingham",
    "sg:classifiers":[
        {
            "category":"Food & Beverages",
            "subcategory":"Meat & Fish",
            "type":"Retail Goods"
        }
    ],
    "sg:postcode":"NG9 1ES",
    "sg:province":"Nottinghamshire",
    "sg:tags":[
        "chip"
    ],
    "wof:name":"Pepaous,P,",
    "wof:placetype":"venue"
},
  "geometry": {"coordinates":[-1.2193889618,52.9235191345],"type":"Point"}
}