{
  "type": "Feature",
  "properties": {
    "addr:full":"15a South Elstow Storage Depot, Ampthill Rd, Kemston Hardwicke Bedford Bedfordshire MK45 3JE",
    "addr:housenumber":"15a",
    "addr:postcode":"mk45 3je",
    "addr:street":"South;Ampthill Rd",
    "iso:country":"GB",
    "sg:address":"15a South Elstow Storage Depot, Ampthill Rd, Kemston Hardwicke",
    "sg:city":"Bedford",
    "sg:classifiers":[
        {
            "category":"Autos & Motor Vehicles",
            "subcategory":"Automobile Sales",
            "type":"Retail Goods"
        }
    ],
    "sg:postcode":"MK45 3JE",
    "sg:province":"Bedfordshire",
    "sg:tags":[
        "car"
    ],
    "wof:name":"Conrad,Leif,",
    "wof:placetype":"venue"
},
  "geometry": {"coordinates":[-0.48477,52.09692],"type":"Point"}
}