{
  "type": "Feature",
  "properties": {
    "iso:country":"GB",
    "sg:address":"68 Rose Ave",
    "sg:city":"Leeds",
    "sg:classifiers":[
        {
            "category":"Professional",
            "subcategory":"Detective & Security Services",
            "type":"Services"
        }
    ],
    "sg:phone":"+44 113 258 1263",
    "sg:postcode":"LS18 4QH",
    "sg:province":"West Yorkshire",
    "sg:tags":[
        "alarm",
        "burglar",
        "system"
    ],
    "wof:name":"Laser Protection",
    "wof:placetype":"venue"
},
  "geometry": {"coordinates":[-1.64416,53.833534],"type":"Point"}
}