{
  "type": "Feature",
  "properties": {
    "addr:full":"9 Hinksey Business Centre, North Hinksey Lane Oxford Oxfordshire OX2 0NR",
    "addr:housenumber":"9",
    "addr:postcode":"ox2 0nr",
    "addr:street":"Hinksey Business Centre North Hinksey Lane",
    "iso:country":"GB",
    "sg:address":"9 Hinksey Business Centre, North Hinksey Lane",
    "sg:city":"Oxford",
    "sg:classifiers":[
        {
            "category":"Professional",
            "subcategory":"Computer Services",
            "type":"Services"
        }
    ],
    "sg:phone":"+44 1865 791452",
    "sg:postcode":"OX2 0NR",
    "sg:province":"Oxfordshire",
    "sg:tags":[
        "system",
        "software"
    ],
    "wof:name":"3 T H Ltd.",
    "wof:placetype":"venue"
},
  "geometry": {"coordinates":[-1.2943999767,51.7521896362],"type":"Point"}
}