{
  "type": "Feature",
  "properties": {
    "iso:country":"GB",
    "sg:address":"64 St Barnabas Road",
    "sg:city":"Middlesbrough",
    "sg:classifiers":[
        {
            "category":"Recreation",
            "subcategory":"Dog Park",
            "type":"Entertainment"
        }
    ],
    "sg:phone":"+44 1642 812903",
    "sg:postcode":"TS5 6JT",
    "sg:province":"North Yorkshire",
    "wof:name":"The Dog House",
    "wof:placetype":"venue"
},
  "geometry": {"coordinates":[-1.2452780008,54.5623321533],"type":"Point"}
}