{
  "type": "Feature",
  "properties": {
    "addr:full":"13 Bridgepark Ardrossan North Ayrshire KA22 8BQ",
    "addr:housenumber":"13",
    "addr:postcode":"ka22 8bq",
    "addr:street":"Bridgepark Ardrossan",
    "iso:country":"GB",
    "sg:address":"13 Bridgepark",
    "sg:city":"Ardrossan",
    "sg:classifiers":[
        {
            "category":"Professional",
            "subcategory":"Engineering",
            "type":"Services"
        }
    ],
    "sg:phone":"+44 1294 601150",
    "sg:postcode":"KA22 8BQ",
    "sg:province":"North Ayrshire",
    "sg:tags":[
        "contractor",
        "electrical",
        "engineer"
    ],
    "wof:name":"Andrew Gilmour Electrical Contactor",
    "wof:placetype":"venue"
},
  "geometry": {"coordinates":[-4.8020119667,55.6442756653],"type":"Point"}
}