{
  "type": "Feature",
  "properties": {
    "addr:full":"15 Gossamer Lane Bognor Regis West Sussex PO21 3AT",
    "addr:housenumber":"15",
    "addr:postcode":"po21 3at",
    "addr:street":"Gossamer Lane",
    "iso:country":"GB",
    "sg:address":"15 Gossamer Lane",
    "sg:city":"Bognor Regis",
    "sg:classifiers":[
        {
            "category":"Manufacturing",
            "subcategory":"Buildings",
            "type":"Manufacturing & Wholesale Goods"
        }
    ],
    "sg:postcode":"PO21 3AT",
    "sg:province":"West Sussex",
    "sg:tags":[
        "mobile",
        "home"
    ],
    "wof:name":"Martin Moth Caravans",
    "wof:placetype":"venue"
},
  "geometry": {"coordinates":[-0.712049,50.783821],"type":"Point"}
}