{
  "type": "Feature",
  "properties": {
    "addr:full":"126 Watling Street East Towcester Buckinghamshire NN12 6BT",
    "addr:housenumber":"126",
    "addr:postcode":"nn12 6bt",
    "addr:street":"Watling Street East",
    "iso:country":"GB",
    "sg:address":"126 Watling Street East",
    "sg:city":"Towcester",
    "sg:classifiers":[
        {
            "category":"Personal",
            "subcategory":"Beauty Salon",
            "type":"Services"
        }
    ],
    "sg:phone":"+44 1327 359131",
    "sg:postcode":"NN12 6BT",
    "sg:province":"Buckinghamshire",
    "sg:tags":[
        "unisex",
        "hairdresser"
    ],
    "wof:name":"Zig Zag Hair & Beauty Studio",
    "wof:placetype":"venue"
},
  "geometry": {"coordinates":[-0.987009,52.130508],"type":"Point"}
}