{
  "type": "Feature",
  "properties": {
    "addr:full":"Corverton Road, Roundthorn Industrial Estate, Wythenshawe Manchester Cheshire M23 9YD",
    "addr:postcode":"m23 9yd",
    "addr:street":"Corverton Road Roundthorn Industrial Estate",
    "iso:country":"GB",
    "sg:address":"Corverton Road, Roundthorn Industrial Estate, Wythenshawe",
    "sg:city":"Manchester",
    "sg:classifiers":[
        {
            "category":"Freight",
            "type":"Transportation"
        }
    ],
    "sg:phone":"+44 161 998 5223",
    "sg:postcode":"M23 9YD",
    "sg:province":"Cheshire",
    "sg:tags":[
        "forwarders"
    ],
    "wof:name":"Uniserve (Europe) Ltd.",
    "wof:placetype":"venue"
},
  "geometry": {"coordinates":[-2.29648,53.389225],"type":"Point"}
}