{
  "type": "Feature",
  "properties": {
    "addr:full":"17 Glencairn Road, Cumbernauld Glasgow Falkirk G67 2EN",
    "addr:housenumber":"17",
    "addr:postcode":"g67 2en",
    "addr:street":"Glencairn Road",
    "iso:country":"GB",
    "sg:address":"17 Glencairn Road, Cumbernauld",
    "sg:city":"Glasgow",
    "sg:classifiers":[
        {
            "category":"Wholesale",
            "subcategory":"Office Equipment",
            "type":"Manufacturing & Wholesale Goods"
        },
        {
            "category":"Shopping",
            "subcategory":"Computers & Home Electronics",
            "type":"Retail Goods"
        }
    ],
    "sg:phone":"+44 1236 735180",
    "sg:postcode":"G67 2EN",
    "sg:province":"Falkirk",
    "sg:tags":[
        "supplier",
        "furniture"
    ],
    "wof:name":"CALEDONIAN FURNITURE COMPANY LTD",
    "wof:placetype":"venue"
},
  "geometry": {"coordinates":[-3.9690380096,55.9512252808],"type":"Point"}
}