{
  "type": "Feature",
  "properties": {
    "iso:country":"GB",
    "sg:address":"Unit 1 Kingsley Business Park, New Road, Kibworth",
    "sg:city":"Leicester",
    "sg:classifiers":[
        {
            "category":"Manufacturing",
            "subcategory":"Furniture",
            "type":"Manufacturing & Wholesale Goods"
        }
    ],
    "sg:phone":"+44 116 279 6601",
    "sg:postcode":"LE8 0LE",
    "sg:province":"Leicestershire",
    "sg:tags":[
        "design"
    ],
    "wof:name":"Ash Design",
    "wof:placetype":"venue"
},
  "geometry": {"coordinates":[-0.991872,52.542065],"type":"Point"}
}