{
  "type": "Feature",
  "properties": {
    "iso:country":"GB",
    "sg:address":"2 & 3 Henrietta Street",
    "sg:city":"Cheltenham",
    "sg:classifiers":[
        {
            "category":"Professional",
            "subcategory":"Business Services",
            "type":"Services"
        },
        {
            "category":"Shopping",
            "type":"Retail Goods"
        }
    ],
    "sg:phone":"+44 1242 513490",
    "sg:postcode":"GL50 4AA",
    "sg:province":"Gloucestershire",
    "sg:tags":[
        "shop",
        "agent",
        "new age",
        "export",
        "import"
    ],
    "wof:name":"Scarramouch",
    "wof:placetype":"venue"
},
  "geometry": {"coordinates":[-2.077437,51.903061],"type":"Point"}
}