{
  "type": "Feature",
  "properties": {
    "iso:country":"GB",
    "sg:address":"6-7 Bridge St",
    "sg:city":"Cambridge",
    "sg:classifiers":[
        {
            "category":"Travel",
            "subcategory":"Travel Agent",
            "type":"Entertainment"
        }
    ],
    "sg:phone":"+44 1223 360201",
    "sg:postcode":"CB2 1UA",
    "sg:province":"Cambridgeshire",
    "wof:name":"Campus Travel",
    "wof:placetype":"venue"
},
  "geometry": {"coordinates":[0.118561,52.208416],"type":"Point"}
}