{
  "type": "Feature",
  "properties": {
    "addr:full":"2 Buttershaw La Bradford West Yorkshire BD6 2DD",
    "addr:housenumber":"2",
    "addr:postcode":"bd6 2dd",
    "addr:street":"Buttershaw La Bradford West",
    "iso:country":"GB",
    "sg:address":"2 Buttershaw La",
    "sg:city":"Bradford",
    "sg:classifiers":[
        {
            "category":"Shopping",
            "subcategory":"News",
            "type":"Retail Goods"
        }
    ],
    "sg:phone":"+44 1274 673619",
    "sg:postcode":"BD6 2DD",
    "sg:province":"West Yorkshire",
    "sg:tags":[
        "newsagent"
    ],
    "wof:name":"Buttershaw News",
    "wof:placetype":"venue"
},
  "geometry": {"coordinates":[-1.7807190418,53.7602500916],"type":"Point"}
}