{
  "type": "Feature",
  "properties": {
    "addr:full":"Sunnymeads Lake Horton Rd, Datchet Slough Berkshire SL3 9HY",
    "addr:postcode":"sl3 9hy",
    "addr:street":"Horton Rd",
    "iso:country":"GB",
    "sg:address":"Sunnymeads Lake Horton Rd, Datchet",
    "sg:city":"Slough",
    "sg:classifiers":[
        {
            "category":"Recreation",
            "subcategory":"Water Park",
            "type":"Entertainment"
        }
    ],
    "sg:phone":"+44 1753 582040",
    "sg:postcode":"SL3 9HY",
    "sg:province":"Berkshire",
    "sg:tags":[
        "sport"
    ],
    "wof:name":"H2O Sports Ltd",
    "wof:placetype":"venue"
},
  "geometry": {"coordinates":[-0.580488,51.484074],"type":"Point"}
}