{
  "type": "Feature",
  "properties": {
    "iso:country":"GB",
    "sg:address":"12 Church Lane, Culcheth",
    "sg:city":"Warrington",
    "sg:classifiers":[
        {
            "category":"Personal",
            "subcategory":"Beauty Salon",
            "type":"Services"
        }
    ],
    "sg:phone":"+44 1925 767200",
    "sg:postcode":"WA3 5DJ",
    "sg:province":"Cheshire",
    "sg:tags":[
        "unisex",
        "hairdresser"
    ],
    "wof:name":"Big Scissor Co.The",
    "wof:placetype":"venue"
},
  "geometry": {"coordinates":[-2.518659,53.451836],"type":"Point"}
}