{
  "type": "Feature",
  "properties": {
    "iso:country":"GB",
    "sg:address":"14 Pen Street",
    "sg:city":"Boston",
    "sg:classifiers":[
        {
            "category":"Shopping",
            "subcategory":"Crafts & Fabrics",
            "type":"Retail Goods"
        }
    ],
    "sg:phone":"+44 1205 356681",
    "sg:postcode":"PE21 6TJ",
    "sg:province":"Lincolnshire",
    "sg:tags":[
        "shop",
        "needlecraft",
        "wool"
    ],
    "wof:name":"Wool & Crafts",
    "wof:placetype":"venue"
},
  "geometry": {"coordinates":[-0.019375,52.979687],"type":"Point"}
}