{
  "type": "Feature",
  "properties": {
    "iso:country":"GB",
    "sg:address":"Unit 1 Hambledon Road",
    "sg:city":"Waterlooville",
    "sg:classifiers":[
        {
            "category":"Home & Garden",
            "subcategory":"Hardware",
            "type":"Retail Goods"
        }
    ],
    "sg:phone":"+44 23 9224 0480",
    "sg:postcode":"PO7 7UL",
    "sg:province":"Hampshire",
    "sg:tags":[
        "shop",
        "retailer",
        "diy"
    ],
    "sg:website":"http://www.focusdoitall.co.uk",
    "wof:name":"Focus Do It All Ltd.",
    "wof:placetype":"venue"
},
  "geometry": {"coordinates":[-1.038485,50.885666],"type":"Point"}
}