{
  "type": "Feature",
  "properties": {
    "iso:country":"GB",
    "sg:address":"Gaer Rd",
    "sg:city":"Newport",
    "sg:classifiers":[
        {
            "category":"Community Center",
            "type":"Public Place"
        }
    ],
    "sg:phone":"+44 1633 259122",
    "sg:postcode":"NP9 3GY",
    "sg:province":"East Riding of Yorkshire",
    "sg:tags":[
        "centre"
    ],
    "wof:name":"Gaer Youth & Community Centre",
    "wof:placetype":"venue"
},
  "geometry": {"coordinates":[-3.0135641098,51.5751075745],"type":"Point"}
}