{
  "type": "Feature",
  "properties": {
    "iso:country":"GB",
    "sg:address":"162 High Street, Rainham",
    "sg:city":"Gillingham",
    "sg:classifiers":[
        {
            "category":"Parking",
            "type":"Transportation"
        }
    ],
    "sg:phone":"+44 1634 377803",
    "sg:postcode":"ME8 8AT",
    "sg:province":"Kent",
    "sg:tags":[
        "car",
        "valet"
    ],
    "wof:name":"R Day Car Body Repairers",
    "wof:placetype":"venue"
},
  "geometry": {"coordinates":[0.613428,51.36211],"type":"Point"}
}