{
  "type": "Feature",
  "properties": {
    "iso:country":"GB",
    "sg:address":"Wincham Wharf, 220 Manchester Road",
    "sg:city":"Northwich",
    "sg:classifiers":[
        {
            "category":"Autos & Motor Vehicles",
            "subcategory":"Boat Sales",
            "type":"Retail Goods"
        }
    ],
    "sg:phone":"+44 1606 47078",
    "sg:postcode":"CW9 7NT",
    "sg:province":"Cheshire",
    "sg:tags":[
        "repair",
        "builder"
    ],
    "wof:name":"Ruth Harrel",
    "wof:placetype":"venue"
},
  "geometry": {"coordinates":[-2.5119988918,53.260471344],"type":"Point"}
}