{
  "type": "Feature",
  "properties": {
    "iso:country":"GB",
    "sg:address":"Ballinkinrain Smithy",
    "sg:city":"Glasgow",
    "sg:classifiers":[
        {
            "category":"Real Estate",
            "subcategory":"Architect",
            "type":"Services"
        }
    ],
    "sg:phone":"+44 1360 440012",
    "sg:postcode":"G63 0LL",
    "sg:province":"Argyll and Bute",
    "wof:name":"Architectural Images",
    "wof:placetype":"venue"
},
  "geometry": {"coordinates":[-4.3747692108,56.0735282898],"type":"Point"}
}