{
  "type": "Feature",
  "properties": {
    "iso:country":"GB",
    "sg:address":"46 Holliers Hill",
    "sg:city":"Bexhill-on-sea",
    "sg:classifiers":[
        {
            "category":"Health Services",
            "subcategory":"Podiatrist",
            "type":"Services"
        }
    ],
    "sg:postcode":"TN40 2DD",
    "sg:province":"East Sussex",
    "sg:tags":[
        "podiatrists",
        "chiropodist"
    ],
    "wof:name":"H & D Winfield",
    "wof:placetype":"venue"
},
  "geometry": {"coordinates":[0.475395,50.853695],"type":"Point"}
}