{
  "type": "Feature",
  "properties": {
    "iso:country":"GB",
    "sg:address":"Orion House, Castle Heather",
    "sg:city":"Inverness",
    "sg:classifiers":[
        {
            "category":"Professional",
            "subcategory":"Employment Agencies",
            "type":"Services"
        }
    ],
    "sg:postcode":"IV2 6AA",
    "sg:province":"Highland",
    "sg:tags":[
        "consultant"
    ],
    "wof:name":"Bordax Ltd.",
    "wof:placetype":"venue"
},
  "geometry": {"coordinates":[-4.2083640099,57.4567260742],"type":"Point"}
}