{
  "type": "Feature",
  "properties": {
    "iso:country":"GB",
    "sg:address":"26 Cossington Road",
    "sg:city":"Loughborough",
    "sg:classifiers":[
        {
            "category":"Organizations",
            "subcategory":"Political Organization",
            "type":"Services"
        }
    ],
    "sg:phone":"+44 1509 812210",
    "sg:postcode":"LE12 7RF",
    "sg:province":"Leicestershire",
    "sg:tags":[
        "party"
    ],
    "wof:name":"The Sileby & District Constitutional Club Ltd.",
    "wof:placetype":"venue"
},
  "geometry": {"coordinates":[-1.110142,52.725918],"type":"Point"}
}