{
  "type": "Feature",
  "properties": {
    "addr:full":"26 Theobald Street Borehamwood Hertfordshire WD6 4SF",
    "addr:housenumber":"26",
    "addr:postcode":"wd6 4sf",
    "addr:street":"Theobald Street",
    "iso:country":"GB",
    "sg:address":"26 Theobald Street",
    "sg:city":"Borehamwood",
    "sg:classifiers":[
        {
            "category":"Professional",
            "subcategory":"Engineering",
            "type":"Services"
        }
    ],
    "sg:phone":"+44 20 8953 3348",
    "sg:postcode":"WD6 4SF",
    "sg:province":"Hertfordshire",
    "sg:tags":[
        "precision",
        "engineer"
    ],
    "wof:name":"Elstree Precision Co. Ltd.",
    "wof:placetype":"venue"
},
  "geometry": {"coordinates":[-0.280265,51.655106],"type":"Point"}
}