{
  "type": "Feature",
  "properties": {
    "addr:full":"4 Castle Rise, Spittal Haverfordwest Pembrokeshire SA62 5QW",
    "addr:housenumber":"4",
    "addr:postcode":"sa62 5qw",
    "addr:street":"Castle Rise",
    "iso:country":"GB",
    "sg:address":"4 Castle Rise, Spittal",
    "sg:city":"Haverfordwest",
    "sg:classifiers":[
        {
            "category":"Professional",
            "subcategory":"Management & Consulting",
            "type":"Services"
        }
    ],
    "sg:phone":"+44 1437 741706",
    "sg:postcode":"SA62 5QW",
    "sg:province":"Pembrokeshire",
    "sg:tags":[
        "consultant",
        "business"
    ],
    "wof:name":"Nicholas Jones & Taylor Associates",
    "wof:placetype":"venue"
},
  "geometry": {"coordinates":[-4.9393730164,51.8684043884],"type":"Point"}
}