{
  "type": "Feature",
  "properties": {
    "addr:full":"72 St Johns Lane, Bedminster Bristol City of Bristol BS3 5AF",
    "addr:housenumber":"72",
    "addr:postcode":"bs3 5af",
    "addr:street":"St Johns Lane",
    "iso:country":"GB",
    "sg:address":"72 St Johns Lane, Bedminster",
    "sg:city":"Bristol",
    "sg:classifiers":[
        {
            "category":"Professional",
            "subcategory":"Engineering",
            "type":"Services"
        }
    ],
    "sg:phone":"+44 1275 853853",
    "sg:postcode":"BS3 5AF",
    "sg:province":"City of Bristol",
    "sg:tags":[
        "contractor",
        "electrical",
        "engineer"
    ],
    "wof:name":"Gould Auto Plates & Sign Ltd.",
    "wof:placetype":"venue"
},
  "geometry": {"coordinates":[-2.5828299522,51.4383354187],"type":"Point"}
}