{
  "type": "Feature",
  "properties": {
    "iso:country":"GB",
    "sg:address":"4 Bushy Combe Gdn(s), Bovetown",
    "sg:city":"Glastonbury",
    "sg:classifiers":[
        {
            "category":"Building & Trades",
            "subcategory":"Construction",
            "type":"Services"
        }
    ],
    "sg:phone":"+44 1458 833703",
    "sg:postcode":"BA6 8JT",
    "sg:province":"Somerset",
    "sg:tags":[
        "decorator",
        "painter"
    ],
    "wof:name":"John Rankin Painter & Decorator",
    "wof:placetype":"venue"
},
  "geometry": {"coordinates":[-2.70805,51.148357],"type":"Point"}
}