{
  "type": "Feature",
  "properties": {
    "addr:full":"140 New Bond Street London Greater London W1S 2TN",
    "addr:housenumber":"140",
    "addr:postcode":"w1s 2tn",
    "addr:street":"New Bond Street",
    "iso:country":"GB",
    "sg:address":"140 New Bond Street",
    "sg:city":"London",
    "sg:classifiers":[
        {
            "category":"Shopping",
            "subcategory":"Clothing, Apparel, & Fashions",
            "type":"Retail Goods"
        }
    ],
    "sg:phone":"+44 20 7499 3510",
    "sg:postcode":"W1S 2TN",
    "sg:province":"Greater London",
    "sg:tags":[
        "menswear"
    ],
    "wof:name":"Alan Stuart Ltd.",
    "wof:placetype":"venue"
},
  "geometry": {"coordinates":[-0.144075,51.511677],"type":"Point"}
}