{
  "type": "Feature",
  "properties": {
    "addr:full":"Bridge Farm Shop, Pylle Shepton Mallet Somerset BA4 6TA",
    "addr:postcode":"ba4 6ta",
    "addr:street":"Bridge",
    "iso:country":"GB",
    "sg:address":"Bridge Farm Shop, Pylle",
    "sg:city":"Shepton Mallet",
    "sg:classifiers":[
        {
            "category":"Food & Beverages",
            "subcategory":"Farmers Market",
            "type":"Retail Goods"
        },
        {
            "category":"Food & Beverages",
            "subcategory":"Meat & Fish",
            "type":"Retail Goods"
        }
    ],
    "sg:phone":"+44 1749 830138",
    "sg:postcode":"BA4 6TA",
    "sg:province":"Somerset",
    "sg:tags":[
        "farm",
        "shop",
        "butcher"
    ],
    "wof:name":"Jon Thorners",
    "wof:placetype":"venue"
},
  "geometry": {"coordinates":[-2.547688,51.144215],"type":"Point"}
}