{
  "type": "Feature",
  "properties": {
    "addr:full":"39-41 Westgate North Berwick East Lothian EH39 4AG",
    "addr:housenumber":"39-41",
    "addr:postcode":"eh39 4ag",
    "addr:street":"Westgate North Berwick",
    "iso:country":"GB",
    "sg:address":"39-41 Westgate",
    "sg:city":"North Berwick",
    "sg:classifiers":[
        {
            "category":"Arts & Performance",
            "subcategory":"Art Gallery",
            "type":"Entertainment"
        }
    ],
    "sg:phone":"+44 1620 894976",
    "sg:postcode":"EH39 4AG",
    "sg:province":"East Lothian",
    "wof:name":"Westgate Gallery",
    "wof:placetype":"venue"
},
  "geometry": {"coordinates":[-2.72618,56.058037],"type":"Point"}
}