{
  "type": "Feature",
  "properties": {
    "iso:country":"GB",
    "sg:address":"39 Priory Close",
    "sg:city":"Uxbridge",
    "sg:classifiers":[
        {
            "category":"Freight",
            "type":"Transportation"
        }
    ],
    "sg:phone":"+44 1895 237291",
    "sg:postcode":"UB9 5AU",
    "sg:province":"Buckinghamshire",
    "sg:tags":[
        "haulage",
        "road"
    ],
    "wof:name":"A Wightman (Haulage)",
    "wof:placetype":"venue"
},
  "geometry": {"coordinates":[-0.49364,51.564392],"type":"Point"}
}