{
  "type": "Feature",
  "properties": {
    "iso:country":"GB",
    "sg:address":"17 Middleton Rd, Lawrence Weston",
    "sg:city":"Bristol",
    "sg:classifiers":[
        {
            "category":"Building & Trades",
            "subcategory":"Construction",
            "type":"Services"
        }
    ],
    "sg:phone":"+44 117 914 0154",
    "sg:postcode":"BS11 0JW",
    "sg:province":"City of Bristol",
    "sg:tags":[
        "bricklaying"
    ],
    "wof:name":"Ian O'Grady Brickwork",
    "wof:placetype":"venue"
},
  "geometry": {"coordinates":[-2.6692481041,51.4955635071],"type":"Point"}
}