{
  "type": "Feature",
  "properties": {
    "addr:full":"1d Laburnam Terrace Ashington Northumberland NE63 0XX",
    "addr:housenumber":"1d",
    "addr:postcode":"ne63 0xx",
    "addr:street":"Laburnam Terrace;Northumberland",
    "iso:country":"GB",
    "sg:address":"1d Laburnam Terrace",
    "sg:city":"Ashington",
    "sg:classifiers":[
        {
            "category":"Shopping",
            "subcategory":"Clothing, Apparel, & Fashions",
            "type":"Retail Goods"
        }
    ],
    "sg:phone":"+44 1670 520195",
    "sg:postcode":"NE63 0XX",
    "sg:province":"Northumberland",
    "sg:tags":[
        "ladieswear"
    ],
    "wof:name":"Quality Seconds",
    "wof:placetype":"venue"
},
  "geometry": {"coordinates":[-1.5678089857,55.1789283752],"type":"Point"}
}