{
  "type": "Feature",
  "properties": {
    "addr:full":"19a West Street Boston Lincolnshire PE21 8QE",
    "addr:housenumber":"19a",
    "addr:postcode":"pe21 8qe",
    "addr:street":"West Street",
    "iso:country":"GB",
    "sg:address":"19a West Street",
    "sg:city":"Boston",
    "sg:classifiers":[
        {
            "category":"Home & Garden",
            "subcategory":"Carpets & Floor Coverings",
            "type":"Retail Goods"
        }
    ],
    "sg:phone":"+44 1205 364405",
    "sg:postcode":"PE21 8QE",
    "sg:province":"Lincolnshire",
    "sg:tags":[
        "carpets",
        "retailer",
        "rug",
        "matting"
    ],
    "wof:name":"H ASHTON DISCOUNT CARPETS",
    "wof:placetype":"venue"
},
  "geometry": {"coordinates":[-0.0263749994,52.9763832092],"type":"Point"}
}