{
  "type": "Feature",
  "properties": {
    "addr:full":"The Court House Pimlico Ilkeston Derbyshire DE7 5HZ",
    "addr:postcode":"de7 5hz",
    "addr:street":"Pimlico",
    "iso:country":"GB",
    "sg:address":"The Court House Pimlico",
    "sg:city":"Ilkeston",
    "sg:classifiers":[
        {
            "category":"Government",
            "subcategory":"Court House",
            "type":"Public Place"
        }
    ],
    "sg:phone":"+44 115 932 0286",
    "sg:postcode":"DE7 5HZ",
    "sg:province":"Derbyshire",
    "wof:name":"East Derbyshire Magistrates Court",
    "wof:placetype":"venue"
},
  "geometry": {"coordinates":[-1.312253952,52.9712753296],"type":"Point"}
}