{
  "type": "Feature",
  "properties": {
    "addr:full":"22 Hillview Crescent, Baldwins Gate Newcastle Staffordshire ST5 5DE",
    "addr:housenumber":"22",
    "addr:postcode":"st5 5de",
    "addr:street":"Hillview Crescent Baldwins Gate",
    "iso:country":"GB",
    "sg:address":"22 Hillview Crescent, Baldwins Gate",
    "sg:city":"Newcastle",
    "sg:classifiers":[
        {
            "category":"Home & Garden",
            "subcategory":"Household Appliances",
            "type":"Retail Goods"
        }
    ],
    "sg:postcode":"ST5 5DE",
    "sg:province":"Staffordshire",
    "sg:tags":[
        "electrical"
    ],
    "wof:name":"B & C Refrigeration Service",
    "wof:placetype":"venue"
},
  "geometry": {"coordinates":[-2.307558,52.9608],"type":"Point"}
}