{
  "type": "Feature",
  "properties": {
    "addr:full":"189-193 South Liberty Lane, Ashton Vale Bristol City of Bristol BS3 2TX",
    "addr:housenumber":"189-193",
    "addr:postcode":"bs3 2tx",
    "addr:street":"South Liberty Lane",
    "iso:country":"GB",
    "sg:address":"189-193 South Liberty Lane, Ashton Vale",
    "sg:city":"Bristol",
    "sg:classifiers":[
        {
            "category":"Professional",
            "subcategory":"Printing & Photocopies",
            "type":"Services"
        }
    ],
    "sg:postcode":"BS3 2TX",
    "sg:province":"City of Bristol",
    "sg:tags":[
        "printer"
    ],
    "wof:name":"Bart Fifty Nine Ltd.",
    "wof:placetype":"venue"
},
  "geometry": {"coordinates":[-2.629420042,51.4282531738],"type":"Point"}
}