{
  "type": "Feature",
  "properties": {
    "iso:country":"GB",
    "sg:address":"Wilby Hall Farm, Highfield Rd, Mears Ashby",
    "sg:city":"Northampton",
    "sg:classifiers":[
        {
            "category":"Farming",
            "subcategory":"Livestock Farm",
            "type":"Manufacturing & Wholesale Goods"
        }
    ],
    "sg:postcode":"NN6 0EA",
    "sg:province":"Northamptonshire",
    "sg:tags":[
        "others"
    ],
    "wof:name":"Colyer,David Paul,",
    "wof:placetype":"venue"
},
  "geometry": {"coordinates":[-0.772307992,52.2901153564],"type":"Point"}
}