{
  "type": "Feature",
  "properties": {
    "addr:full":"39 Wood Road Camberley Berkshire GU15 2RN",
    "addr:housenumber":"39",
    "addr:postcode":"gu15 2rn",
    "addr:street":"Wood Road",
    "iso:country":"GB",
    "sg:address":"39 Wood Road",
    "sg:city":"Camberley",
    "sg:classifiers":[
        {
            "category":"Professional",
            "subcategory":"Art Services",
            "type":"Services"
        }
    ],
    "sg:postcode":"GU15 2RN",
    "sg:province":"Berkshire",
    "sg:tags":[
        "photographer"
    ],
    "wof:name":"Colin Barton Photography",
    "wof:placetype":"venue"
},
  "geometry": {"coordinates":[-0.755565,51.318016],"type":"Point"}
}