{
  "type": "Feature",
  "properties": {
    "addr:full":"Suite 3a 2nd Floor, Gilbros Business Centre, 4/18 Crafton St Leicester Leicestershire LE1 2DE",
    "addr:housenumber":"suite 3a 2nd floor gilbros business;4 / 18",
    "addr:postcode":"le1 2de",
    "addr:street":"Crafton St",
    "iso:country":"GB",
    "sg:address":"Suite 3a 2nd Floor, Gilbros Business Centre, 4/18 Crafton St",
    "sg:city":"Leicester",
    "sg:classifiers":[
        {
            "category":"Manufacturing",
            "subcategory":"Apparel",
            "type":"Manufacturing & Wholesale Goods"
        }
    ],
    "sg:postcode":"LE1 2DE",
    "sg:province":"Leicestershire",
    "sg:tags":[
        "shirt",
        "maker"
    ],
    "wof:name":"Beyond Fashions Ltd",
    "wof:placetype":"venue"
},
  "geometry": {"coordinates":[-1.1403650045,52.6378860474],"type":"Point"}
}