{
  "type": "Feature",
  "properties": {
    "iso:country":"GB",
    "sg:address":"Bosanketh Farm, St Buryan",
    "sg:city":"Penzance",
    "sg:classifiers":[
        {
            "category":"Farming",
            "subcategory":"Dairy Farm",
            "type":"Manufacturing & Wholesale Goods"
        }
    ],
    "sg:phone":"+44 1736 810314",
    "sg:postcode":"TR19 6HF",
    "sg:province":"Cornwall",
    "wof:name":"C Olds & Sons",
    "wof:placetype":"venue"
},
  "geometry": {"coordinates":[-5.65697,50.07774],"type":"Point"}
}