{
  "type": "Feature",
  "properties": {
    "iso:country":"GB",
    "sg:address":"15 Exchange Arcade",
    "sg:city":"Nottingham",
    "sg:classifiers":[
        {
            "category":"Shopping",
            "subcategory":"Clothing, Apparel, & Fashions",
            "type":"Retail Goods"
        }
    ],
    "sg:phone":"+44 115 947 2898",
    "sg:postcode":"NG1 2DD",
    "sg:province":"Nottinghamshire",
    "sg:tags":[
        "ladieswear"
    ],
    "wof:name":"Karen Millen Ltd.",
    "wof:placetype":"venue"
},
  "geometry": {"coordinates":[-1.149402976,52.9529647827],"type":"Point"}
}