{
  "type": "Feature",
  "properties": {
    "addr:full":"Braddon, Ashwater Beaworthy Devon EX21 5EP",
    "addr:housenumber":"beaworthy",
    "addr:postcode":"ex21 5ep",
    "addr:street":"Devon",
    "iso:country":"GB",
    "sg:address":"Braddon, Ashwater",
    "sg:city":"Beaworthy",
    "sg:classifiers":[
        {
            "category":"Travel",
            "subcategory":"Hotels & Motels",
            "type":"Entertainment"
        },
        {
            "category":"Bars & Pubs",
            "subcategory":"Hookah Bar",
            "type":"Food & Drink"
        }
    ],
    "sg:phone":"+44 1409 211350",
    "sg:postcode":"EX21 5EP",
    "sg:province":"Devon",
    "sg:tags":[
        "self",
        "holiday",
        "catering"
    ],
    "wof:name":"Braddon Holiday Cottages",
    "wof:placetype":"venue"
},
  "geometry": {"coordinates":[-4.1833848953,50.7753067017],"type":"Point"}
}