{
  "type": "Feature",
  "properties": {
    "iso:country":"GB",
    "sg:address":"20 Digbeth",
    "sg:city":"Walsall",
    "sg:classifiers":[
        {
            "category":"Shopping",
            "subcategory":"Department Store",
            "type":"Retail Goods"
        }
    ],
    "sg:phone":"+44 1922 610606",
    "sg:postcode":"WS1 1QU",
    "sg:province":"West Midlands",
    "wof:name":"Joyce's",
    "wof:placetype":"venue"
},
  "geometry": {"coordinates":[-1.982136,52.583855],"type":"Point"}
}