{
  "type": "Feature",
  "properties": {
    "addr:full":"13 King Street Thetford Norfolk IP24 2AN",
    "addr:housenumber":"13",
    "addr:postcode":"ip24 2an",
    "addr:street":"King Street",
    "iso:country":"GB",
    "sg:address":"13 King Street",
    "sg:city":"Thetford",
    "sg:classifiers":[
        {
            "category":"Shopping",
            "subcategory":"Shoes",
            "type":"Retail Goods"
        }
    ],
    "sg:phone":"+44 1842 820353",
    "sg:postcode":"IP24 2AN",
    "sg:province":"Norfolk",
    "sg:tags":[
        "shop"
    ],
    "wof:name":"Shoefayre Ltd.",
    "wof:placetype":"venue"
},
  "geometry": {"coordinates":[0.7495869994,52.4137039185],"type":"Point"}
}