{
  "type": "Feature",
  "properties": {
    "iso:country":"GB",
    "sg:address":"Unit, 1, Barnham",
    "sg:city":"Bognor Regis",
    "sg:classifiers":[
        {
            "category":"Conference Center",
            "type":"Public Place"
        }
    ],
    "sg:phone":"+44 1243 555222",
    "sg:postcode":"PO22 0AL",
    "sg:province":"West Sussex",
    "sg:tags":[
        "business",
        "centre"
    ],
    "wof:name":"Sussex Business Village Co",
    "wof:placetype":"venue"
},
  "geometry": {"coordinates":[-0.6354150176,50.8352241516],"type":"Point"}
}