{
  "type": "Feature",
  "properties": {
    "iso:country":"GB",
    "sg:address":"Lyons, East St",
    "sg:city":"Tonbridge",
    "sg:classifiers":[
        {
            "category":"Professional",
            "subcategory":"Lawyer & Legal Services",
            "type":"Services"
        }
    ],
    "sg:phone":"+44 1732 771411",
    "sg:postcode":"TN9 1HL",
    "sg:province":"Kent",
    "sg:tags":[
        "solicitor"
    ],
    "wof:name":"Thomson Snell & Passmore",
    "wof:placetype":"venue"
},
  "geometry": {"coordinates":[0.27634,51.199829],"type":"Point"}
}