{
  "type": "Feature",
  "properties": {
    "iso:country":"GB",
    "sg:address":"339 Row Heath Road, Cottridge",
    "sg:city":"Birmingham",
    "sg:classifiers":[
        {
            "category":"Personal",
            "subcategory":"Beauty Salon",
            "type":"Services"
        }
    ],
    "sg:phone":"+44 121 458 7455",
    "sg:postcode":"B30 2EP",
    "sg:province":"West Midlands",
    "wof:name":"Beauty First",
    "wof:placetype":"venue"
},
  "geometry": {"coordinates":[-1.928689,52.418072],"type":"Point"}
}