{
  "type": "Feature",
  "properties": {
    "addr:full":"36 Bank Street Galashiels Scottish Borders TD1 1ER",
    "addr:housenumber":"36",
    "addr:postcode":"td1 1er",
    "addr:street":"Bank Street",
    "iso:country":"GB",
    "sg:address":"36 Bank Street",
    "sg:city":"Galashiels",
    "sg:classifiers":[
        {
            "category":"Professional",
            "subcategory":"Lawyer & Legal Services",
            "type":"Services"
        }
    ],
    "sg:postcode":"TD1 1ER",
    "sg:province":"Scottish Borders",
    "sg:tags":[
        "solicitor"
    ],
    "wof:name":"Pike & Chapman",
    "wof:placetype":"venue"
},
  "geometry": {"coordinates":[-2.80745,55.615589],"type":"Point"}
}