{
  "type": "Feature",
  "properties": {
    "addr:full":"21 Lower Bridge Street Chester Cheshire CH1 1RS",
    "addr:housenumber":"21",
    "addr:postcode":"ch1 1rs",
    "addr:street":"Lower Bridge Street",
    "iso:country":"GB",
    "sg:address":"21 Lower Bridge Street",
    "sg:city":"Chester",
    "sg:classifiers":[
        {
            "category":"Fast Food",
            "type":"Food & Drink"
        }
    ],
    "sg:phone":"+44 1244 326472",
    "sg:postcode":"CH1 1RS",
    "sg:province":"Cheshire",
    "sg:tags":[
        "away",
        "take"
    ],
    "wof:name":"Davies's Fish & Chip Shop",
    "wof:placetype":"venue"
},
  "geometry": {"coordinates":[-2.8904809952,53.1881523132],"type":"Point"}
}