{
  "type": "Feature",
  "properties": {
    "iso:country":"GB",
    "sg:address":"13 Ulundi Street, Radcliffe",
    "sg:city":"Manchester",
    "sg:classifiers":[
        {
            "category":"Freight",
            "type":"Transportation"
        }
    ],
    "sg:phone":"+44 161 723 1622",
    "sg:postcode":"M26 3AN",
    "sg:province":"Greater Manchester",
    "sg:tags":[
        "haulage",
        "transport",
        "road"
    ],
    "wof:name":"J B Ashworth",
    "wof:placetype":"venue"
},
  "geometry": {"coordinates":[-2.330991,53.559834],"type":"Point"}
}