{
  "type": "Feature",
  "properties": {
    "iso:country":"GB",
    "sg:address":"20 Newport Road, Woburn",
    "sg:city":"Milton Keynes",
    "sg:classifiers":[
        {
            "category":"Restaurant",
            "type":"Food & Drink"
        }
    ],
    "sg:phone":"+44 1525 290295",
    "sg:postcode":"MK17 9HX",
    "sg:province":"Bedfordshire",
    "wof:name":"The Birch",
    "wof:placetype":"venue"
},
  "geometry": {"coordinates":[-0.6209290028,51.9913749695],"type":"Point"}
}