{
  "type": "Feature",
  "properties": {
    "iso:country":"GB",
    "sg:address":"2e High Street",
    "sg:city":"Eastleigh",
    "sg:classifiers":[
        {
            "category":"Retail",
            "subcategory":"Repair Shop",
            "type":"Services"
        }
    ],
    "sg:phone":"+44 23 8062 0285",
    "sg:postcode":"SO50 5LA",
    "sg:province":"Hampshire",
    "sg:tags":[
        "radio",
        "television",
        "video"
    ],
    "wof:name":"Direct Repair Ltd.",
    "wof:placetype":"venue"
},
  "geometry": {"coordinates":[-1.35314,50.969128],"type":"Point"}
}