{
  "type": "Feature",
  "properties": {
    "addr:full":"The Business Centre, 10 Tay Square Dundee Dundee City DD1 1PB",
    "addr:housenumber":"10",
    "addr:postcode":"dd1 1pb",
    "addr:street":"Tay Square",
    "iso:country":"GB",
    "sg:address":"The Business Centre, 10 Tay Square",
    "sg:city":"Dundee",
    "sg:classifiers":[
        {
            "category":"Bars & Pubs",
            "type":"Food & Drink"
        }
    ],
    "sg:phone":"+44 1382 522578",
    "sg:postcode":"DD1 1PB",
    "sg:province":"Dundee City",
    "sg:tags":[
        "pubs",
        "inn"
    ],
    "wof:name":"The Nelson Bar Ltd",
    "wof:placetype":"venue"
},
  "geometry": {"coordinates":[-2.97629,56.457722],"type":"Point"}
}