{
  "type": "Feature",
  "properties": {
    "addr:full":"24 Ashton Road Bristol City of Bristol BS3 2EA",
    "addr:housenumber":"24",
    "addr:postcode":"bs3 2ea",
    "addr:street":"Ashton Road",
    "iso:country":"GB",
    "sg:address":"24 Ashton Road",
    "sg:city":"Bristol",
    "sg:classifiers":[
        {
            "category":"Food & Beverages",
            "subcategory":"Meat & Fish",
            "type":"Retail Goods"
        }
    ],
    "sg:postcode":"BS3 2EA",
    "sg:province":"City of Bristol",
    "sg:tags":[
        "chip"
    ],
    "wof:name":"Parkway Chippy",
    "wof:placetype":"venue"
},
  "geometry": {"coordinates":[-2.6184329987,51.4420547485],"type":"Point"}
}