{
  "type": "Feature",
  "properties": {
    "addr:full":"251b East India Dock Road London Greater London E14 0EG",
    "addr:housenumber":"251b",
    "addr:postcode":"e14 0eg",
    "addr:street":"East India Dock Road",
    "iso:country":"GB",
    "sg:address":"251b East India Dock Road",
    "sg:city":"London",
    "sg:classifiers":[
        {
            "category":"Food & Beverages",
            "subcategory":"Supermarket",
            "type":"Retail Goods"
        }
    ],
    "sg:phone":"+44 20 7538 9950",
    "sg:postcode":"E14 0EG",
    "sg:province":"Greater London",
    "wof:name":"Woodcock Halal Meat",
    "wof:placetype":"venue"
},
  "geometry": {"coordinates":[-0.0097850002,51.5115242004],"type":"Point"}
}