{
  "type": "Feature",
  "properties": {
    "addr:full":"903 Millbrook Road West Southampton Hampshire SO15 0HW",
    "addr:housenumber":"903",
    "addr:postcode":"so15 0hw",
    "addr:street":"Millbrook Road West",
    "iso:country":"GB",
    "sg:address":"903 Millbrook Road West",
    "sg:city":"Southampton",
    "sg:classifiers":[
        {
            "category":"Health Services",
            "subcategory":"Dentist",
            "type":"Services"
        }
    ],
    "sg:phone":"+44 23 8034 3355",
    "sg:postcode":"SO15 0HW",
    "sg:province":"Hampshire",
    "wof:name":"J A T Dental Services",
    "wof:placetype":"venue"
},
  "geometry": {"coordinates":[-1.4519389868,50.9147415161],"type":"Point"}
}