{
  "type": "Feature",
  "properties": {
    "iso:country":"GB",
    "sg:address":"Cornwall Ho, Falkland Clo, Charter Avenue Industrial Est",
    "sg:city":"Coventry",
    "sg:classifiers":[
        {
            "category":"Government",
            "subcategory":"Post Office",
            "type":"Public Place"
        }
    ],
    "sg:phone":"+44 24 7642 1111",
    "sg:postcode":"CV4 8AU",
    "sg:province":"Warwickshire",
    "sg:tags":[
        "messenger",
        "courier"
    ],
    "wof:name":"J M Freight Ltd",
    "wof:placetype":"venue"
},
  "geometry": {"coordinates":[-1.59454,52.3942489624],"type":"Point"}
}