{
  "type": "Feature",
  "properties": {
    "iso:country":"GB",
    "sg:address":"Eyles Close",
    "sg:city":"Horsham",
    "sg:classifiers":[
        {
            "category":"Social Services",
            "subcategory":"Adult Care",
            "type":"Services"
        },
        {
            "category":"Government",
            "subcategory":"Office",
            "type":"Public Place"
        }
    ],
    "sg:phone":"+44 1403 262252",
    "sg:postcode":"RH12 2HT",
    "sg:province":"West Sussex",
    "sg:tags":[
        "housing",
        "local",
        "sheltered"
    ],
    "wof:name":"Eyles Close Sheltered Housing",
    "wof:placetype":"venue"
},
  "geometry": {"coordinates":[-0.334689,51.075397],"type":"Point"}
}