{
  "type": "Feature",
  "properties": {
    "iso:country":"GB",
    "sg:address":"31 White Rose Centre, Dewsbury Road",
    "sg:city":"Leeds",
    "sg:classifiers":[
        {
            "category":"Sports & Exercise",
            "subcategory":"Sports Center",
            "type":"Entertainment"
        }
    ],
    "sg:phone":"+44 113 271 4747",
    "sg:postcode":"LS11 8LL",
    "sg:province":"West Yorkshire",
    "sg:tags":[
        "shop",
        "good"
    ],
    "wof:name":"Sports Division Ltd.",
    "wof:placetype":"venue"
},
  "geometry": {"coordinates":[-1.546587,53.794495],"type":"Point"}
}