{
  "type": "Feature",
  "properties": {
    "addr:full":"The Old Bake House, 1242 Evesham Road Redditch Warwickshire B96 6AA",
    "addr:housenumber":"1242",
    "addr:postcode":"b96 6aa",
    "addr:street":"Evesham Road",
    "iso:country":"GB",
    "sg:address":"The Old Bake House, 1242 Evesham Road",
    "sg:city":"Redditch",
    "sg:classifiers":[
        {
            "category":"Manufacturing",
            "subcategory":"Buildings",
            "type":"Manufacturing & Wholesale Goods"
        }
    ],
    "sg:postcode":"B96 6AA",
    "sg:province":"Warwickshire",
    "sg:tags":[
        "system",
        "air conditioning"
    ],
    "wof:name":"Portable Air Conditioning Equipment",
    "wof:placetype":"venue"
},
  "geometry": {"coordinates":[-1.9374970198,52.2579727173],"type":"Point"}
}