{
  "type": "Feature",
  "properties": {
    "addr:full":"Upper Wick Lane, Rushwick Worcester Worcestershire WR2 5SU",
    "addr:postcode":"wr2 5su",
    "addr:street":"Upper Wick Lane",
    "iso:country":"GB",
    "sg:address":"Upper Wick Lane, Rushwick",
    "sg:city":"Worcester",
    "sg:classifiers":[
        {
            "category":"Education",
            "subcategory":"School",
            "type":"Public Place"
        }
    ],
    "sg:phone":"+44 1905 422502",
    "sg:postcode":"WR2 5SU",
    "sg:province":"Worcestershire",
    "sg:tags":[
        "local",
        "authority"
    ],
    "wof:name":"Rushwick C of E Primary School",
    "wof:placetype":"venue"
},
  "geometry": {"coordinates":[-2.2649,52.181557],"type":"Point"}
}