{
  "type": "Feature",
  "properties": {
    "iso:country":"GB",
    "sg:address":"42 Bank Street",
    "sg:city":"Rossendale",
    "sg:classifiers":[
        {
            "category":"Personal",
            "subcategory":"Beauty Salon",
            "type":"Services"
        }
    ],
    "sg:phone":"+44 1706 222444",
    "sg:postcode":"BB4 8DY",
    "sg:province":"Lancashire",
    "sg:tags":[
        "unisex",
        "hairdresser"
    ],
    "wof:name":"Pelo",
    "wof:placetype":"venue"
},
  "geometry": {"coordinates":[-2.2851159573,53.7025871277],"type":"Point"}
}