{
  "type": "Feature",
  "properties": {
    "iso:country":"GB",
    "sg:address":"St Nicholas House, Church Stoke",
    "sg:city":"Montgomery",
    "sg:classifiers":[
        {
            "category":"Social Services",
            "subcategory":"Retirement Home",
            "type":"Services"
        }
    ],
    "sg:phone":"+44 1588 620613",
    "sg:postcode":"SY15 6AF",
    "sg:province":"Shropshire",
    "sg:tags":[
        "residential",
        "care"
    ],
    "wof:name":"St.Nicholas House Residential Home Ltd.",
    "wof:placetype":"venue"
},
  "geometry": {"coordinates":[-3.146479,52.563564],"type":"Point"}
}