{
  "type": "Feature",
  "properties": {
    "iso:country":"GB",
    "sg:address":"Coniston Drive",
    "sg:city":"Farnham",
    "sg:classifiers":[
        {
            "category":"Education",
            "subcategory":"School",
            "type":"Public Place"
        }
    ],
    "sg:phone":"+44 1252 716121",
    "sg:postcode":"GU9 0DB",
    "sg:province":"Surrey",
    "sg:tags":[
        "local",
        "authority"
    ],
    "wof:name":"Surrey County Council",
    "wof:placetype":"venue"
},
  "geometry": {"coordinates":[-0.806339,51.2314],"type":"Point"}
}