{
  "type": "Feature",
  "properties": {
    "iso:country":"GB",
    "sg:address":"24 Canterbury Road",
    "sg:city":"Sudbury",
    "sg:classifiers":[
        {
            "category":"Manufacturing",
            "subcategory":"Lumber",
            "type":"Manufacturing & Wholesale Goods"
        }
    ],
    "sg:phone":"+44 1787 374585",
    "sg:postcode":"CO10 1LJ",
    "sg:province":"Essex",
    "sg:tags":[
        "importer",
        "merchants",
        "agent",
        "timber"
    ],
    "wof:name":"Roger Lloyd Partnership",
    "wof:placetype":"venue"
},
  "geometry": {"coordinates":[0.718529,52.05238],"type":"Point"}
}