{
  "type": "Feature",
  "properties": {
    "iso:country":"GB",
    "sg:address":"Park Avenue",
    "sg:city":"Aberystwyth",
    "sg:classifiers":[
        {
            "category":"Autos & Motor Vehicles",
            "subcategory":"Automobile Sales",
            "type":"Retail Goods"
        },
        {
            "category":"Autos & Motor Vehicles",
            "subcategory":"Auto Supplies",
            "type":"Retail Goods"
        }
    ],
    "sg:phone":"+44 1970 624841",
    "sg:postcode":"SY23 1PG",
    "sg:province":"Ceredigion",
    "sg:tags":[
        "component",
        "commercial"
    ],
    "wof:name":"Cambrian Garages Ltd.",
    "wof:placetype":"venue"
},
  "geometry": {"coordinates":[-4.0824561119,52.4131393433],"type":"Point"}
}