{
  "type": "Feature",
  "properties": {
    "addr:full":"Newcomen Way Colchester Essex CO4 4TG",
    "addr:postcode":"co4 4tg",
    "addr:street":"Newcomen Way",
    "iso:country":"GB",
    "sg:address":"Newcomen Way",
    "sg:city":"Colchester",
    "sg:classifiers":[
        {
            "category":"Manufacturing",
            "subcategory":"Printing",
            "type":"Manufacturing & Wholesale Goods"
        }
    ],
    "sg:phone":"+44 1206 751914",
    "sg:postcode":"CO4 4TG",
    "sg:province":"Essex",
    "sg:tags":[
        "bookbinder"
    ],
    "wof:name":"BPC Magazines (East Anglia) Ltd",
    "wof:placetype":"venue"
},
  "geometry": {"coordinates":[0.928265,51.922096],"type":"Point"}
}