{
  "type": "Feature",
  "properties": {
    "iso:country":"GB",
    "sg:address":"Second Floor, Lloyds Avenue House, 6 Lloyds Avenue",
    "sg:city":"Monument",
    "sg:classifiers":[
        {
            "category":"Professional",
            "subcategory":"Computer Services",
            "type":"Services"
        }
    ],
    "sg:phone":"+44 20 7481 4151",
    "sg:postcode":"EC3N 3AX",
    "sg:province":"Greater London",
    "sg:tags":[
        "consultant"
    ],
    "wof:name":"Cathox Ltd",
    "wof:placetype":"venue"
},
  "geometry": {"coordinates":[-0.078279,51.512058],"type":"Point"}
}