{
  "type": "Feature",
  "properties": {
    "iso:country":"GB",
    "sg:address":"Guild Hall, Walkden, Worsley",
    "sg:city":"Manchester",
    "sg:classifiers":[
        {
            "category":"Community Center",
            "type":"Public Place"
        }
    ],
    "sg:phone":"+44 161 703 8633",
    "sg:postcode":"M28 5AS",
    "sg:province":"Greater Manchester",
    "sg:tags":[
        "centre"
    ],
    "wof:name":"Guild Hall Community Centre",
    "wof:placetype":"venue"
},
  "geometry": {"coordinates":[-2.39868,53.523689],"type":"Point"}
}