{
  "type": "Feature",
  "properties": {
    "iso:country":"GB",
    "sg:address":"High Street, Burton Bradstock",
    "sg:city":"Bridport",
    "sg:classifiers":[
        {
            "category":"Personal",
            "subcategory":"Beauty Salon",
            "type":"Services"
        }
    ],
    "sg:phone":"+44 1308 897309",
    "sg:postcode":"DT6 4PY",
    "sg:province":"Dorset",
    "sg:tags":[
        "lady",
        "hairdresser"
    ],
    "wof:name":"Jayne",
    "wof:placetype":"venue"
},
  "geometry": {"coordinates":[-2.727519,50.702831],"type":"Point"}
}