{
  "type": "Feature",
  "properties": {
    "addr:full":"45 Holloway Lane, Harmondsworth West Drayton Greater London UB7 0AE",
    "addr:housenumber":"45",
    "addr:postcode":"ub7 0ae",
    "addr:street":"Holloway Lane",
    "iso:country":"GB",
    "sg:address":"45 Holloway Lane, Harmondsworth",
    "sg:city":"West Drayton",
    "sg:classifiers":[
        {
            "category":"Professional",
            "subcategory":"Advertising",
            "type":"Services"
        }
    ],
    "sg:phone":"+44 20 8564 8727",
    "sg:postcode":"UB7 0AE",
    "sg:province":"Greater London",
    "wof:name":"Cays Properties Ltd.",
    "wof:placetype":"venue"
},
  "geometry": {"coordinates":[-0.4697700143,51.4923248291],"type":"Point"}
}