{
  "type": "Feature",
  "properties": {
    "addr:full":"291 Acklam Road Middlesbrough North Yorkshire TS5 7EL",
    "addr:housenumber":"291",
    "addr:postcode":"ts5 7el",
    "addr:street":"Acklam Road",
    "iso:country":"GB",
    "sg:address":"291 Acklam Road",
    "sg:city":"Middlesbrough",
    "sg:classifiers":[
        {
            "category":"Bars & Pubs",
            "type":"Food & Drink"
        },
        {
            "category":"Community Center",
            "subcategory":"Social",
            "type":"Public Place"
        }
    ],
    "sg:phone":"+44 1642 819429",
    "sg:postcode":"TS5 7EL",
    "sg:province":"North Yorkshire",
    "sg:tags":[
        "pubs",
        "house",
        "inn",
        "activity"
    ],
    "wof:name":"The Master Cooper",
    "wof:placetype":"venue"
},
  "geometry": {"coordinates":[-1.2582299709,54.5452003479],"type":"Point"}
}