{
  "type": "Feature",
  "properties": {
    "addr:full":"8 Market Street Crewe Cheshire CW1 2EG",
    "addr:housenumber":"8",
    "addr:postcode":"cw1 2eg",
    "addr:street":"Market Street",
    "iso:country":"GB",
    "sg:address":"8 Market Street",
    "sg:city":"Crewe",
    "sg:classifiers":[
        {
            "category":"Shopping",
            "subcategory":"Crafts & Fabrics",
            "type":"Retail Goods"
        }
    ],
    "sg:phone":"+44 1270 500743",
    "sg:postcode":"CW1 2EG",
    "sg:province":"Cheshire",
    "sg:tags":[
        "shop",
        "linen"
    ],
    "wof:name":"Nightlines",
    "wof:placetype":"venue"
},
  "geometry": {"coordinates":[-2.441248,53.09647],"type":"Point"}
}