{
  "type": "Feature",
  "properties": {
    "addr:full":"38 Main Street Wishaw North Lanarkshire ML2 7AF",
    "addr:housenumber":"38",
    "addr:postcode":"ml2 7af",
    "addr:street":"Main Street",
    "iso:country":"GB",
    "sg:address":"38 Main Street",
    "sg:city":"Wishaw",
    "sg:classifiers":[
        {
            "category":"Health Services",
            "subcategory":"Optometrist",
            "type":"Services"
        },
        {
            "category":"Shopping",
            "subcategory":"Optician",
            "type":"Retail Goods"
        }
    ],
    "sg:phone":"+44 1698 375547",
    "sg:postcode":"ML2 7AF",
    "sg:province":"North Lanarkshire",
    "sg:tags":[
        "ophthalmic"
    ],
    "wof:name":"Insight",
    "wof:placetype":"venue"
},
  "geometry": {"coordinates":[-3.9212119579,55.7746925354],"type":"Point"}
}