{
  "type": "Feature",
  "properties": {
    "addr:full":"Riverside House, Dicker Mill Hertford Hertfordshire SG13 7AE",
    "addr:postcode":"sg13 7ae",
    "addr:street":"Dicker Mill Hertford",
    "iso:country":"GB",
    "sg:address":"Riverside House, Dicker Mill",
    "sg:city":"Hertford",
    "sg:classifiers":[
        {
            "category":"Professional",
            "subcategory":"Printing & Photocopies",
            "type":"Services"
        }
    ],
    "sg:phone":"+44 1992 587373",
    "sg:postcode":"SG13 7AE",
    "sg:province":"Hertfordshire",
    "sg:tags":[
        "printer"
    ],
    "wof:name":"Quadrant Offset Ltd.",
    "wof:placetype":"venue"
},
  "geometry": {"coordinates":[-0.071156,51.802025],"type":"Point"}
}