{
  "type": "Feature",
  "properties": {
    "addr:full":"Chetwynd Road, Chilwell, Beeston Nottingham Nottinghamshire NG9 5GE",
    "addr:postcode":"ng9 5ge",
    "addr:street":"Chetwynd Road",
    "iso:country":"GB",
    "sg:address":"Chetwynd Road, Chilwell, Beeston",
    "sg:city":"Nottingham",
    "sg:classifiers":[
        {
            "category":"Autos & Motor Vehicles",
            "subcategory":"Auto Supplies",
            "type":"Retail Goods"
        }
    ],
    "sg:phone":"+44 115 925 2549",
    "sg:postcode":"NG9 5GE",
    "sg:province":"Nottinghamshire",
    "sg:tags":[
        "box",
        "gearbox",
        "gear",
        "vehciles"
    ],
    "wof:name":"Automatic Transmission Services",
    "wof:placetype":"venue"
},
  "geometry": {"coordinates":[-1.238449,52.913361],"type":"Point"}
}