{
  "type": "Feature",
  "properties": {
    "addr:full":"Penfold House Rochester Kent ME1 1PT",
    "addr:postcode":"me1 1pt",
    "iso:country":"GB",
    "sg:address":"Penfold House",
    "sg:city":"Rochester",
    "sg:classifiers":[
        {
            "category":"Bars & Pubs",
            "type":"Food & Drink"
        }
    ],
    "sg:postcode":"ME1 1PT",
    "sg:province":"Kent",
    "sg:tags":[
        "pubs",
        "inn"
    ],
    "wof:name":"Veena Leisure Ltd.",
    "wof:placetype":"venue"
},
  "geometry": {"coordinates":[0.5025299788,51.3909111023],"type":"Point"}
}