{
  "type": "Feature",
  "properties": {
    "iso:country":"GB",
    "sg:address":"The Florence Roa Dsurgery, 26 Florence Rd",
    "sg:city":"Ealing",
    "sg:classifiers":[
        {
            "category":"Health Services",
            "subcategory":"Doctor",
            "type":"Services"
        }
    ],
    "sg:phone":"+44 20 8567 2111",
    "sg:postcode":"W5 3TU",
    "sg:province":"Greater London",
    "sg:tags":[
        "practitioners"
    ],
    "wof:name":"Evans, D C",
    "wof:placetype":"venue"
},
  "geometry": {"coordinates":[-0.299931,51.514023],"type":"Point"}
}