{
  "type": "Feature",
  "properties": {
    "addr:full":"Sheriff Hutton Road, Strensall York North Yorkshire YO32 5XH",
    "addr:postcode":"yo32 5xh",
    "addr:street":"Sheriff Hutton Road",
    "iso:country":"GB",
    "sg:address":"Sheriff Hutton Road, Strensall",
    "sg:city":"York",
    "sg:classifiers":[
        {
            "category":"Wholesale",
            "subcategory":"Scrap",
            "type":"Manufacturing & Wholesale Goods"
        },
        {
            "category":"Wholesale",
            "subcategory":"Auto Parts",
            "type":"Manufacturing & Wholesale Goods"
        }
    ],
    "sg:phone":"+44 1904 490978",
    "sg:postcode":"YO32 5XH",
    "sg:province":"North Yorkshire",
    "sg:tags":[
        "car",
        "breaker",
        "dismantlers"
    ],
    "wof:name":"Pigott's Auto Parts",
    "wof:placetype":"venue"
},
  "geometry": {"coordinates":[-1.038452,54.035957],"type":"Point"}
}