{
  "type": "Feature",
  "properties": {
    "addr:full":"Park House, Dunvegan Isle Of Skye Highland IV55 8GU",
    "addr:postcode":"iv55 8gu",
    "iso:country":"GB",
    "sg:address":"Park House, Dunvegan",
    "sg:city":"Isle Of Skye",
    "sg:classifiers":[
        {
            "category":"Building & Trades",
            "subcategory":"Construction",
            "type":"Services"
        }
    ],
    "sg:phone":"+44 1470 521434",
    "sg:postcode":"IV55 8GU",
    "sg:province":"Highland",
    "sg:tags":[
        "builder"
    ],
    "wof:name":"McKenzie Donald Heating & Building Contractors",
    "wof:placetype":"venue"
},
  "geometry": {"coordinates":[-6.539203167,57.4203567505],"type":"Point"}
}