{
  "type": "Feature",
  "properties": {
    "iso:country":"GB",
    "sg:address":"78 Bollo Bridge Road, Acton",
    "sg:city":"London",
    "sg:classifiers":[
        {
            "category":"Personal",
            "subcategory":"Tanning Parlor",
            "type":"Services"
        },
        {
            "category":"Retail",
            "subcategory":"Event Space",
            "type":"Services"
        }
    ],
    "sg:phone":"+44 20 8992 0268",
    "sg:postcode":"W3 8AU",
    "sg:province":"Greater London",
    "sg:tags":[
        "laser",
        "product",
        "electrical",
        "sales"
    ],
    "wof:name":"Scientifica-Cook Ltd",
    "wof:placetype":"venue"
},
  "geometry": {"coordinates":[-0.268767,51.502327],"type":"Point"}
}