{
  "type": "Feature",
  "properties": {
    "addr:full":"24 Llantrisant Road Cardiff Cardiff CF5 2PX",
    "addr:housenumber":"24",
    "addr:postcode":"cf5 2px",
    "addr:street":"Llantrisant Road",
    "iso:country":"GB",
    "sg:address":"24 Llantrisant Road",
    "sg:city":"Cardiff",
    "sg:classifiers":[
        {
            "category":"Community Center",
            "subcategory":"Youth",
            "type":"Public Place"
        },
        {
            "category":"Organizations",
            "subcategory":"Non-profit Organization",
            "type":"Services"
        }
    ],
    "sg:phone":"+44 29 2055 2083",
    "sg:postcode":"CF5 2PX",
    "sg:province":"Cardiff",
    "sg:tags":[
        "organisation",
        "charity",
        "voluntary",
        "centre"
    ],
    "wof:name":"Amnesty International Ltd.",
    "wof:placetype":"venue"
},
  "geometry": {"coordinates":[-3.229944,51.497791],"type":"Point"}
}