{
  "type": "Feature",
  "properties": {
    "addr:full":"8 Culduthel Road Inverness Highland IV2 4AB",
    "addr:housenumber":"8",
    "addr:postcode":"iv2 4ab",
    "addr:street":"Culduthel Road",
    "iso:country":"GB",
    "sg:address":"8 Culduthel Road",
    "sg:city":"Inverness",
    "sg:classifiers":[
        {
            "category":"Travel",
            "subcategory":"Hostel",
            "type":"Entertainment"
        }
    ],
    "sg:phone":"+44 1463 236556",
    "sg:postcode":"IV2 4AB",
    "sg:province":"Highland",
    "sg:tags":[
        "youth"
    ],
    "wof:name":"Inverness Student Hotel",
    "wof:placetype":"venue"
},
  "geometry": {"coordinates":[-4.2252187729,57.4749145508],"type":"Point"}
}