{
  "type": "Feature",
  "properties": {
    "iso:country":"GB",
    "sg:address":"Woodacres, Woodacre Crescent, Bardsey",
    "sg:city":"Leeds",
    "sg:classifiers":[
        {
            "category":"Building & Trades",
            "subcategory":"Construction",
            "type":"Services"
        }
    ],
    "sg:phone":"+44 1937 574278",
    "sg:postcode":"LS17 9DQ",
    "sg:province":"North Yorkshire",
    "sg:tags":[
        "contractor",
        "pool",
        "swimming"
    ],
    "wof:name":"Stuart White",
    "wof:placetype":"venue"
},
  "geometry": {"coordinates":[-1.446305,53.885593],"type":"Point"}
}