{
  "type": "Feature",
  "properties": {
    "iso:country":"GB",
    "sg:address":"South Place 1 Meeting House Lane",
    "sg:city":"Lancaster",
    "sg:classifiers":[
        {
            "category":"Community Center",
            "subcategory":"Youth",
            "type":"Public Place"
        }
    ],
    "sg:postcode":"LA1 1TQ",
    "sg:province":"Lancashire",
    "sg:tags":[
        "organisation",
        "centre"
    ],
    "wof:name":"The Lancashire Association of Clubs for Young People",
    "wof:placetype":"venue"
},
  "geometry": {"coordinates":[-2.7990291119,54.0445365906],"type":"Point"}
}