{
  "type": "Feature",
  "properties": {
    "addr:full":"35 Adam & Eve Mews Kensington Greater London W8 6UG",
    "addr:housenumber":"35",
    "addr:postcode":"w8 6ug",
    "addr:street":"Adam & Eve Mews",
    "iso:country":"GB",
    "sg:address":"35 Adam & Eve Mews",
    "sg:city":"Kensington",
    "sg:classifiers":[
        {
            "category":"Professional",
            "subcategory":"Management & Consulting",
            "type":"Services"
        }
    ],
    "sg:phone":"+44 20 7376 2777",
    "sg:postcode":"W8 6UG",
    "sg:province":"Greater London",
    "sg:tags":[
        "marketing",
        "consultant"
    ],
    "wof:name":"Smith Thompson White Ltd",
    "wof:placetype":"venue"
},
  "geometry": {"coordinates":[-0.1943800002,51.4995613098],"type":"Point"}
}