{
  "type": "Feature",
  "properties": {
    "addr:full":"33 Rosewood, Westhoughton Bolton Lancashire BL5 2RX",
    "addr:housenumber":"33",
    "addr:postcode":"bl5 2rx",
    "addr:street":"Rosewood Westhoughton",
    "iso:country":"GB",
    "sg:address":"33 Rosewood, Westhoughton",
    "sg:city":"Bolton",
    "sg:classifiers":[
        {
            "category":"Professional",
            "subcategory":"Engineering",
            "type":"Services"
        },
        {
            "category":"Real Estate",
            "subcategory":"Architect",
            "type":"Services"
        }
    ],
    "sg:phone":"+44 1942 819984",
    "sg:postcode":"BL5 2RX",
    "sg:province":"Lancashire",
    "sg:tags":[
        "consultant",
        "structural"
    ],
    "wof:name":"Barraclough Design Ltd",
    "wof:placetype":"venue"
},
  "geometry": {"coordinates":[-2.5369749069,53.5392684937],"type":"Point"}
}