{
  "type": "Feature",
  "properties": {
    "iso:country":"GB",
    "sg:address":"113 Showell Green Lane",
    "sg:city":"Birmingham",
    "sg:classifiers":[
        {
            "category":"Travel",
            "subcategory":"Hotels & Motels",
            "type":"Entertainment"
        }
    ],
    "sg:phone":"+44 121 449 3593",
    "sg:postcode":"B11 4JD",
    "sg:province":"West Midlands",
    "sg:tags":[
        "house",
        "guest"
    ],
    "wof:name":"Lovesey's Guest House",
    "wof:placetype":"venue"
},
  "geometry": {"coordinates":[-1.868374,52.448776],"type":"Point"}
}