{
  "type": "Feature",
  "properties": {
    "iso:country":"GB",
    "sg:address":"Help Of Christians Church Hall, Lady Margaret Road",
    "sg:city":"London",
    "sg:classifiers":[
        {
            "category":"Farming",
            "subcategory":"Nursery",
            "type":"Manufacturing & Wholesale Goods"
        }
    ],
    "sg:postcode":"NW5 2NE",
    "sg:province":"Greater London",
    "sg:tags":[
        "creche"
    ],
    "wof:name":"Bluebells Nursery",
    "wof:placetype":"venue"
},
  "geometry": {"coordinates":[-0.138139993,51.550868988],"type":"Point"}
}