{
  "type": "Feature",
  "properties": {
    "addr:full":"Wheatsheaf Farm, Yeaveley Ashbourne Derbyshire DE6 2DT",
    "addr:housenumber":"yeaveley",
    "addr:postcode":"de6 2dt",
    "addr:street":"Ashbourne",
    "iso:country":"GB",
    "sg:address":"Wheatsheaf Farm, Yeaveley",
    "sg:city":"Ashbourne",
    "sg:classifiers":[
        {
            "category":"Farming",
            "subcategory":"Livestock Farm",
            "type":"Manufacturing & Wholesale Goods"
        }
    ],
    "sg:phone":"+44 1335 330376",
    "sg:postcode":"DE6 2DT",
    "sg:province":"Derbyshire",
    "sg:tags":[
        "others"
    ],
    "wof:name":"R W Potter",
    "wof:placetype":"venue"
},
  "geometry": {"coordinates":[-1.723439,52.959812],"type":"Point"}
}