{
  "type": "Feature",
  "properties": {
    "addr:full":"Greenviews Caravan Fields, Broad Oak Heathfield East Sussex TN21 8RT",
    "addr:postcode":"tn21 8rt",
    "iso:country":"GB",
    "sg:address":"Greenviews Caravan Fields, Broad Oak",
    "sg:city":"Heathfield",
    "sg:classifiers":[
        {
            "category":"Recreation",
            "subcategory":"Campground",
            "type":"Entertainment"
        }
    ],
    "sg:phone":"+44 1435 863531",
    "sg:postcode":"TN21 8RT",
    "sg:province":"East Sussex",
    "sg:tags":[
        "holiday",
        "camp",
        "park",
        "centre"
    ],
    "wof:name":"Greenviews Caravan Park",
    "wof:placetype":"venue"
},
  "geometry": {"coordinates":[0.282781,50.978706],"type":"Point"}
}