{
  "type": "Feature",
  "properties": {
    "iso:country":"GB",
    "sg:address":"73 Ninian Road, Roath Park",
    "sg:city":"Cardiff",
    "sg:classifiers":[
        {
            "category":"Travel",
            "subcategory":"Hotels & Motels",
            "type":"Entertainment"
        }
    ],
    "sg:phone":"+44 29 4209 1803",
    "sg:postcode":"CF23 5EN",
    "sg:province":"Cardiff",
    "wof:name":"Beeches Hotel",
    "wof:placetype":"venue"
},
  "geometry": {"coordinates":[-3.171853,51.499447],"type":"Point"}
}