{
  "type": "Feature",
  "properties": {
    "addr:full":"1 St Paul's Road Bradford West Yorkshire BD8 7LU",
    "addr:housenumber":"1",
    "addr:postcode":"bd8 7lu",
    "addr:street":"St Paul'S Road",
    "iso:country":"GB",
    "sg:address":"1 St Paul's Road",
    "sg:city":"Bradford",
    "sg:classifiers":[
        {
            "category":"Social Services",
            "subcategory":"Retirement Home",
            "type":"Services"
        }
    ],
    "sg:postcode":"BD8 7LU",
    "sg:province":"West Yorkshire",
    "sg:tags":[
        "rest"
    ],
    "wof:name":"The Heathers",
    "wof:placetype":"venue"
},
  "geometry": {"coordinates":[-1.9010490179,53.8237457275],"type":"Point"}
}