{
  "type": "Feature",
  "properties": {
    "iso:country":"GB",
    "sg:address":"46a Market Street, Whittlesey",
    "sg:city":"Peterborough",
    "sg:classifiers":[
        {
            "category":"Cinema",
            "subcategory":"Movie Rental",
            "type":"Entertainment"
        }
    ],
    "sg:phone":"+44 1733 205040",
    "sg:postcode":"PE7 1BD",
    "sg:province":"Cambridgeshire",
    "sg:tags":[
        "video",
        "library"
    ],
    "wof:name":"Video Zone",
    "wof:placetype":"venue"
},
  "geometry": {"coordinates":[-0.1300889999,52.5566940308],"type":"Point"}
}