{
  "type": "Feature",
  "properties": {
    "iso:country":"GB",
    "sg:address":"Kerswell Cross, Chudleigh",
    "sg:city":"Newton Abbot",
    "sg:classifiers":[
        {
            "category":"Health Services",
            "subcategory":"Health Practitioner",
            "type":"Services"
        }
    ],
    "sg:postcode":"TQ13 0DN",
    "sg:province":"Devon",
    "sg:tags":[
        "homoeopathic"
    ],
    "wof:name":"N S Soffe",
    "wof:placetype":"venue"
},
  "geometry": {"coordinates":[-3.6016008854,50.6042289734],"type":"Point"}
}