{
  "type": "Feature",
  "properties": {
    "iso:country":"GB",
    "sg:address":"2/4 Vauxhall Road",
    "sg:city":"Wigan",
    "sg:classifiers":[
        {
            "category":"Bars & Pubs",
            "type":"Food & Drink"
        }
    ],
    "sg:postcode":"WN1 3LU",
    "sg:province":"Lancashire",
    "sg:tags":[
        "pubs",
        "inn"
    ],
    "wof:name":"Scholes Tavern",
    "wof:placetype":"venue"
},
  "geometry": {"coordinates":[-2.622119,53.546993],"type":"Point"}
}