{
  "type": "Feature",
  "properties": {
    "iso:country":"GB",
    "sg:address":"The Dale, Walcot Lees",
    "sg:city":"Telford",
    "sg:classifiers":[
        {
            "category":"Farming",
            "subcategory":"Livestock Farm",
            "type":"Manufacturing & Wholesale Goods"
        }
    ],
    "sg:postcode":"TF6 6NQ",
    "sg:province":"Shropshire",
    "sg:tags":[
        "others"
    ],
    "wof:name":"R F Lewis",
    "wof:placetype":"venue"
},
  "geometry": {"coordinates":[-2.517419,52.743271],"type":"Point"}
}