{
  "type": "Feature",
  "properties": {
    "addr:full":"Kenilworth Library, 11 Smalley Place Kenilworth Warwickshire CV8 1QG",
    "addr:housenumber":"11",
    "addr:postcode":"cv8 1qg",
    "addr:street":"Smalley Place",
    "iso:country":"GB",
    "sg:address":"Kenilworth Library, 11 Smalley Place",
    "sg:city":"Kenilworth",
    "sg:classifiers":[
        {
            "category":"Education",
            "subcategory":"Library",
            "type":"Public Place"
        },
        {
            "category":"Landmark",
            "subcategory":"Tourist Information",
            "type":"Public Place"
        }
    ],
    "sg:phone":"+44 1926 748900",
    "sg:postcode":"CV8 1QG",
    "sg:province":"Warwickshire",
    "wof:name":"Tourist Information Centre & Library",
    "wof:placetype":"venue"
},
  "geometry": {"coordinates":[-1.579441,52.342937],"type":"Point"}
}