{
  "type": "Feature",
  "properties": {
    "iso:country":"GB",
    "sg:address":"625 Southleigh Rd",
    "sg:city":"Emsworth",
    "sg:classifiers":[
        {
            "category":"Building & Trades",
            "subcategory":"Construction",
            "type":"Services"
        }
    ],
    "sg:phone":"+44 1243 379230",
    "sg:postcode":"PO10 7TE",
    "sg:province":"Hampshire",
    "sg:tags":[
        "builder"
    ],
    "wof:name":"Aaron Builders",
    "wof:placetype":"venue"
},
  "geometry": {"coordinates":[-0.935642,50.861385],"type":"Point"}
}