{
  "type": "Feature",
  "properties": {
    "iso:country":"GB",
    "sg:address":"571 Cable Street",
    "sg:city":"London",
    "sg:classifiers":[
        {
            "category":"Shopping",
            "type":"Retail Goods"
        }
    ],
    "sg:phone":"+44 20 7790 0364",
    "sg:postcode":"E1 9EP",
    "sg:province":"Greater London",
    "sg:tags":[
        "part",
        "accessory"
    ],
    "wof:name":"Kaymore Commercial Spares Ltd.",
    "wof:placetype":"venue"
},
  "geometry": {"coordinates":[-0.042362,51.51178],"type":"Point"}
}