{
  "type": "Feature",
  "properties": {
    "addr:full":"73 Chantry Ave, Blakenhall Walsall Staffordshire WS3 3EZ",
    "addr:housenumber":"73",
    "addr:postcode":"ws3 3ez",
    "addr:street":"Chantry Ave",
    "iso:country":"GB",
    "sg:address":"73 Chantry Ave, Blakenhall",
    "sg:city":"Walsall",
    "sg:classifiers":[
        {
            "category":"Building & Trades",
            "subcategory":"Construction",
            "type":"Services"
        }
    ],
    "sg:postcode":"WS3 3EZ",
    "sg:province":"Staffordshire",
    "sg:tags":[
        "roofing"
    ],
    "wof:name":"Mallin,David,",
    "wof:placetype":"venue"
},
  "geometry": {"coordinates":[-1.9936439991,52.612663269],"type":"Point"}
}