{
  "type": "Feature",
  "properties": {
    "iso:country":"GB",
    "sg:address":"67 Duckworth Lane",
    "sg:city":"Bradford",
    "sg:classifiers":[
        {
            "category":"Real Estate",
            "subcategory":"Real Estate Agent",
            "type":"Services"
        }
    ],
    "sg:phone":"+44 1274 549619",
    "sg:postcode":"BD9 5EU",
    "sg:province":"West Yorkshire",
    "wof:name":"S & K PROPERTIES LTD",
    "wof:placetype":"venue"
},
  "geometry": {"coordinates":[-1.790982,53.805542],"type":"Point"}
}