{
  "type": "Feature",
  "properties": {
    "iso:country":"GB",
    "sg:address":"50 Gordon Road",
    "sg:city":"Fareham",
    "sg:classifiers":[
        {
            "category":"Shopping",
            "subcategory":"News",
            "type":"Retail Goods"
        }
    ],
    "sg:phone":"+44 1329 310741",
    "sg:postcode":"PO16 7SP",
    "sg:province":"Hampshire",
    "sg:tags":[
        "newsagent"
    ],
    "wof:name":"The Top Shop",
    "wof:placetype":"venue"
},
  "geometry": {"coordinates":[-1.186537981,50.8545188904],"type":"Point"}
}