{
  "type": "Feature",
  "properties": {
    "addr:full":"32 Chester Street Wrexham Wrexham LL13 8TG",
    "addr:housenumber":"32",
    "addr:postcode":"ll13 8tg",
    "addr:street":"Chester Street",
    "iso:country":"GB",
    "sg:address":"32 Chester Street",
    "sg:city":"Wrexham",
    "sg:classifiers":[
        {
            "category":"Professional",
            "subcategory":"Employment Agencies",
            "type":"Services"
        }
    ],
    "sg:phone":"+44 1978 266626",
    "sg:postcode":"LL13 8TG",
    "sg:province":"Wrexham",
    "sg:tags":[
        "consultant"
    ],
    "wof:name":"A B C Contract Services Ltd.",
    "wof:placetype":"venue"
},
  "geometry": {"coordinates":[-2.9917740822,53.0494346619],"type":"Point"}
}