{
  "type": "Feature",
  "properties": {
    "addr:full":"Lake Road Ambleside Cumbria LA22 0AD",
    "addr:postcode":"la22 0ad",
    "addr:street":"Lake Road",
    "iso:country":"GB",
    "sg:address":"Lake Road",
    "sg:city":"Ambleside",
    "sg:classifiers":[
        {
            "category":"Travel",
            "subcategory":"Hotels & Motels",
            "type":"Entertainment"
        }
    ],
    "sg:phone":"+44 15394 33279",
    "sg:postcode":"LA22 0AD",
    "sg:province":"Cumbria",
    "sg:tags":[
        "house",
        "guest"
    ],
    "sg:website":"http://www.kent-house.com",
    "wof:name":"Kent House",
    "wof:placetype":"venue"
},
  "geometry": {"coordinates":[-2.962364,54.429115],"type":"Point"}
}