{
  "type": "Feature",
  "properties": {
    "iso:country":"GB",
    "sg:address":"396 Summer Lane",
    "sg:city":"Birmingham",
    "sg:classifiers":[
        {
            "category":"Banks & Credit Unions",
            "subcategory":"Bureau De Change",
            "type":"Services"
        }
    ],
    "sg:phone":"+44 121 248 4228",
    "sg:postcode":"B19 3PL",
    "sg:province":"West Midlands",
    "wof:name":"Currency Direct",
    "wof:placetype":"venue"
},
  "geometry": {"coordinates":[-1.8992489576,52.4887084961],"type":"Point"}
}