{
  "type": "Feature",
  "properties": {
    "addr:full":"49 Chalmers Street, Ardrishaig Lochgilphead Argyll and Bute PA30 8EY",
    "addr:housenumber":"49",
    "addr:postcode":"pa30 8ey",
    "addr:street":"Chalmers Street;Lochgilphead",
    "iso:country":"GB",
    "sg:address":"49 Chalmers Street, Ardrishaig",
    "sg:city":"Lochgilphead",
    "sg:classifiers":[
        {
            "category":"Government",
            "subcategory":"Post Office",
            "type":"Public Place"
        }
    ],
    "sg:phone":"+44 1546 603201",
    "sg:postcode":"PA30 8EY",
    "sg:province":"Argyll and Bute",
    "wof:name":"Ardrishaig Post Office",
    "wof:placetype":"venue"
},
  "geometry": {"coordinates":[-5.4482522011,56.0158233643],"type":"Point"}
}