{
  "type": "Feature",
  "properties": {
    "iso:country":"GB",
    "sg:address":"32 Tower Road West",
    "sg:city":"St Leonards-on-sea",
    "sg:classifiers":[
        {
            "category":"Communications",
            "subcategory":"News Services",
            "type":"Services"
        }
    ],
    "sg:postcode":"TN38 0RG",
    "sg:province":"East Sussex",
    "sg:tags":[
        "journalist"
    ],
    "wof:name":"John Shotton",
    "wof:placetype":"venue"
},
  "geometry": {"coordinates":[0.555355,50.861206],"type":"Point"}
}