{
  "type": "Feature",
  "properties": {
    "addr:full":"26 Leeway Court, Leeway Industrial Estate Newport Newport NP19 4SJ",
    "addr:housenumber":"26",
    "addr:postcode":"np19 4sj",
    "addr:street":"Leeway Court;Industrial Estate",
    "iso:country":"GB",
    "sg:address":"26 Leeway Court, Leeway Industrial Estate",
    "sg:city":"Newport",
    "sg:classifiers":[
        {
            "category":"Shopping",
            "subcategory":"Stationery & Office Supplies",
            "type":"Retail Goods"
        },
        {
            "category":"Manufacturing",
            "subcategory":"Wood Products",
            "type":"Manufacturing & Wholesale Goods"
        }
    ],
    "sg:phone":"+44 1633 278007",
    "sg:postcode":"NP19 4SJ",
    "sg:province":"Newport",
    "sg:tags":[
        "packaging",
        "equipment",
        "crate",
        "pallets"
    ],
    "wof:name":"Donald & Hugh Jenkins",
    "wof:placetype":"venue"
},
  "geometry": {"coordinates":[-2.946829,51.572769],"type":"Point"}
}