{
  "type": "Feature",
  "properties": {
    "iso:country":"GB",
    "sg:address":"10b Suffolk Road",
    "sg:city":"Lowestoft",
    "sg:classifiers":[
        {
            "category":"Wholesale",
            "subcategory":"Vending Machines",
            "type":"Manufacturing & Wholesale Goods"
        }
    ],
    "sg:postcode":"NR32 1DZ",
    "sg:province":"Suffolk",
    "sg:tags":[
        "sale"
    ],
    "wof:name":"Norfolk & Suffolk Vending",
    "wof:placetype":"venue"
},
  "geometry": {"coordinates":[1.7520469427,52.4742164612],"type":"Point"}
}