{
  "type": "Feature",
  "properties": {
    "iso:country":"GB",
    "sg:address":"Winnington Hill",
    "sg:city":"Northwich",
    "sg:classifiers":[
        {
            "category":"Health Services",
            "subcategory":"Hospital",
            "type":"Services"
        }
    ],
    "sg:phone":"+44 1606 564000",
    "sg:postcode":"CW8 1AW",
    "sg:province":"Cheshire",
    "wof:name":"Northwich Victoria Infirmary",
    "wof:placetype":"venue"
},
  "geometry": {"coordinates":[-2.519184,53.262482],"type":"Point"}
}