{
  "type": "Feature",
  "properties": {
    "addr:full":"94 Chaldon Rd Caterham Surrey CR3 5PH",
    "addr:housenumber":"94",
    "addr:postcode":"cr3 5ph",
    "addr:street":"Chaldon Rd",
    "iso:country":"GB",
    "sg:address":"94 Chaldon Rd",
    "sg:city":"Caterham",
    "sg:classifiers":[
        {
            "category":"Building & Trades",
            "subcategory":"Landscaping Services",
            "type":"Services"
        }
    ],
    "sg:phone":"+44 1883 344150",
    "sg:postcode":"CR3 5PH",
    "sg:province":"Surrey",
    "sg:tags":[
        "gardening"
    ],
    "wof:name":"BORDER MAINTENANCE",
    "wof:placetype":"venue"
},
  "geometry": {"coordinates":[-0.095351,51.285316],"type":"Point"}
}