{
  "type": "Feature",
  "properties": {
    "addr:full":"Brookside Farm, Woodhatch Redhill Surrey RH1 5JJ",
    "addr:postcode":"rh1 5jj",
    "iso:country":"GB",
    "sg:address":"Brookside Farm, Woodhatch",
    "sg:city":"Redhill",
    "sg:classifiers":[
        {
            "category":"Organizations",
            "subcategory":"Membership Organization",
            "type":"Services"
        }
    ],
    "sg:postcode":"RH1 5JJ",
    "sg:province":"Surrey",
    "sg:tags":[
        "club"
    ],
    "wof:name":"Viking Management Ltd",
    "wof:placetype":"venue"
},
  "geometry": {"coordinates":[-0.167755,51.211941],"type":"Point"}
}