{
  "type": "Feature",
  "properties": {
    "addr:full":"9 Wood Crescent Kilwinning East Ayrshire KA13 7BJ",
    "addr:housenumber":"9",
    "addr:postcode":"ka13 7bj",
    "addr:street":"Wood Crescent",
    "iso:country":"GB",
    "sg:address":"9 Wood Crescent",
    "sg:city":"Kilwinning",
    "sg:classifiers":[
        {
            "category":"Building & Trades",
            "subcategory":"Landscaping Services",
            "type":"Services"
        }
    ],
    "sg:postcode":"KA13 7BJ",
    "sg:province":"East Ayrshire",
    "sg:tags":[
        "landscape",
        "contractor"
    ],
    "wof:name":"S Quale",
    "wof:placetype":"venue"
},
  "geometry": {"coordinates":[-4.6968579292,55.657661438],"type":"Point"}
}