{
  "type": "Feature",
  "properties": {
    "addr:full":"Park Street Sutton-in-ashfield Nottinghamshire NG17 4BB",
    "addr:postcode":"ng17 4bb",
    "addr:street":"Park Street",
    "iso:country":"GB",
    "sg:address":"Park Street",
    "sg:city":"Sutton-in-ashfield",
    "sg:classifiers":[
        {
            "category":"Education",
            "subcategory":"School",
            "type":"Public Place"
        }
    ],
    "sg:phone":"+44 1623 465705",
    "sg:postcode":"NG17 4BB",
    "sg:province":"Nottinghamshire",
    "sg:tags":[
        "local",
        "authority"
    ],
    "wof:name":"Priestsic Primary School",
    "wof:placetype":"venue"
},
  "geometry": {"coordinates":[-1.25819,53.127991],"type":"Point"}
}