{
  "type": "Feature",
  "properties": {
    "addr:full":"77 Plumstead Road East Norwich Norfolk NR13 5AJ",
    "addr:housenumber":"77",
    "addr:postcode":"nr13 5aj",
    "addr:street":"Plumstead Road East Norwich",
    "iso:country":"GB",
    "sg:address":"77 Plumstead Road East",
    "sg:city":"Norwich",
    "sg:classifiers":[
        {
            "category":"Autos & Motor Vehicles",
            "subcategory":"Automobile Sales",
            "type":"Retail Goods"
        }
    ],
    "sg:phone":"+44 1603 439964",
    "sg:postcode":"NR13 5AJ",
    "sg:province":"Norfolk",
    "sg:tags":[
        "car"
    ],
    "wof:name":"Thorpend Motor Co",
    "wof:placetype":"venue"
},
  "geometry": {"coordinates":[1.370435,52.650303],"type":"Point"}
}