{
  "type": "Feature",
  "properties": {
    "addr:full":"41a Warwick Way London Greater London SW1V 1QS",
    "addr:housenumber":"41a",
    "addr:postcode":"sw1v 1qs",
    "addr:street":"Warwick Way",
    "iso:country":"GB",
    "sg:address":"41a Warwick Way",
    "sg:city":"London",
    "sg:classifiers":[
        {
            "category":"Cafe",
            "type":"Food & Drink"
        }
    ],
    "sg:phone":"+44 20 7233 8271",
    "sg:postcode":"SW1V 1QS",
    "sg:province":"Greater London",
    "sg:tags":[
        "tea",
        "room"
    ],
    "wof:name":"Cafe Mignon",
    "wof:placetype":"venue"
},
  "geometry": {"coordinates":[-0.140479,51.49221],"type":"Point"}
}