{
  "type": "Feature",
  "properties": {
    "iso:country":"GB",
    "sg:address":"35 Ware Road",
    "sg:city":"Hertford",
    "sg:classifiers":[
        {
            "category":"Professional",
            "subcategory":"Art Services",
            "type":"Services"
        }
    ],
    "sg:phone":"+44 1992 583584",
    "sg:postcode":"SG13 7EB",
    "sg:province":"Hertfordshire",
    "sg:tags":[
        "graphic",
        "designer"
    ],
    "wof:name":"Beaver Design",
    "wof:placetype":"venue"
},
  "geometry": {"coordinates":[-0.068412,51.798309],"type":"Point"}
}