{
  "type": "Feature",
  "properties": {
    "addr:full":"48 Pilleys Lane Boston Lincolnshire PE21 9RB",
    "addr:housenumber":"48",
    "addr:postcode":"pe21 9rb",
    "addr:street":"Pilleys Lane",
    "iso:country":"GB",
    "sg:address":"48 Pilleys Lane",
    "sg:city":"Boston",
    "sg:classifiers":[
        {
            "category":"Real Estate",
            "subcategory":"Architect",
            "type":"Services"
        }
    ],
    "sg:postcode":"PE21 9RB",
    "sg:province":"Lincolnshire",
    "sg:tags":[
        "architectural"
    ],
    "wof:name":"Terry Sykes Design & Build",
    "wof:placetype":"venue"
},
  "geometry": {"coordinates":[-0.0130770002,52.9990234375],"type":"Point"}
}