{
  "type": "Feature",
  "properties": {
    "addr:full":"170 Copenhagen St London Greater London N1 0ST",
    "addr:housenumber":"170",
    "addr:postcode":"n1 0st",
    "addr:street":"Copenhagen St",
    "iso:country":"GB",
    "sg:address":"170 Copenhagen St",
    "sg:city":"London",
    "sg:classifiers":[
        {
            "category":"Professional",
            "subcategory":"Printing & Photocopies",
            "type":"Services"
        }
    ],
    "sg:postcode":"N1 0ST",
    "sg:province":"Greater London",
    "sg:tags":[
        "engraving"
    ],
    "wof:name":"Excel Engraving Co",
    "wof:placetype":"venue"
},
  "geometry": {"coordinates":[-0.119129,51.537029],"type":"Point"}
}