{
  "type": "Feature",
  "properties": {
    "addr:full":"49 Rowms Lane, Swinton Mexborough South Yorkshire S64 8AA",
    "addr:housenumber":"49",
    "addr:postcode":"s64 8aa",
    "addr:street":"Rowms Lane",
    "iso:country":"GB",
    "sg:address":"49 Rowms Lane, Swinton",
    "sg:city":"Mexborough",
    "sg:classifiers":[
        {
            "category":"Home & Garden",
            "subcategory":"Household Appliances",
            "type":"Retail Goods"
        },
        {
            "category":"Retail",
            "subcategory":"Auto Repair",
            "type":"Services"
        }
    ],
    "sg:phone":"+44 1709 578188",
    "sg:postcode":"S64 8AA",
    "sg:province":"South Yorkshire",
    "sg:tags":[
        "garage",
        "electrical",
        "related"
    ],
    "wof:name":"D & C Appliances",
    "wof:placetype":"venue"
},
  "geometry": {"coordinates":[-1.2985800505,53.4901847839],"type":"Point"}
}