{
  "type": "Feature",
  "properties": {
    "addr:full":"Hilton Chambers, 15 Hilton St Manchester Greater Manchester M1 1JL",
    "addr:housenumber":"15",
    "addr:postcode":"m1 1jl",
    "addr:street":"Hilton St",
    "iso:country":"GB",
    "sg:address":"Hilton Chambers, 15 Hilton St",
    "sg:city":"Manchester",
    "sg:classifiers":[
        {
            "category":"Banks & Credit Unions",
            "subcategory":"Financial Services",
            "type":"Services"
        }
    ],
    "sg:postcode":"M1 1JL",
    "sg:province":"Greater Manchester",
    "sg:tags":[
        "consultant"
    ],
    "wof:name":"Mattinson Ginty & Partners (Financial Se",
    "wof:placetype":"venue"
},
  "geometry": {"coordinates":[-2.23451,53.483101],"type":"Point"}
}