{
  "type": "Feature",
  "properties": {
    "addr:full":"19 Market Sq Bristol City of Bristol BS16 4JS",
    "addr:housenumber":"19",
    "addr:postcode":"bs16 4js",
    "addr:street":"Market Sq",
    "iso:country":"GB",
    "sg:address":"19 Market Sq",
    "sg:city":"Bristol",
    "sg:classifiers":[
        {
            "category":"Building & Trades",
            "subcategory":"Construction",
            "type":"Services"
        }
    ],
    "sg:postcode":"BS16 4JS",
    "sg:province":"City of Bristol",
    "sg:tags":[
        "joiner",
        "carpenter"
    ],
    "wof:name":"Brooks,Mark,",
    "wof:placetype":"venue"
},
  "geometry": {"coordinates":[-2.514111,51.473934],"type":"Point"}
}