{
  "type": "Feature",
  "properties": {
    "addr:full":"Dec House Reading Berkshire RG1 8JF",
    "addr:postcode":"rg1 8jf",
    "iso:country":"GB",
    "sg:address":"Dec House",
    "sg:city":"Reading",
    "sg:classifiers":[
        {
            "category":"Manufacturing",
            "subcategory":"Rubber & Plastics",
            "type":"Manufacturing & Wholesale Goods"
        }
    ],
    "sg:phone":"+44 118 957 2188",
    "sg:postcode":"RG1 8JF",
    "sg:province":"Berkshire",
    "sg:tags":[
        "injection",
        "moulding"
    ],
    "wof:name":"G M D Mouldings Ltd.",
    "wof:placetype":"venue"
},
  "geometry": {"coordinates":[-0.963009,51.453522],"type":"Point"}
}