{
  "type": "Feature",
  "properties": {
    "addr:full":"810 High Street, Kingswinford Brierley Hill Staffordshire DY6 8AA",
    "addr:housenumber":"810",
    "addr:postcode":"dy6 8aa",
    "addr:street":"High Street",
    "iso:country":"GB",
    "sg:address":"810 High Street, Kingswinford",
    "sg:city":"Brierley Hill",
    "sg:classifiers":[
        {
            "category":"Personal",
            "subcategory":"Beauty Salon",
            "type":"Services"
        }
    ],
    "sg:phone":"+44 1384 402220",
    "sg:postcode":"DY6 8AA",
    "sg:province":"Staffordshire",
    "sg:tags":[
        "unisex",
        "hairdresser"
    ],
    "wof:name":"Duos",
    "wof:placetype":"venue"
},
  "geometry": {"coordinates":[-2.1682350636,52.4975967407],"type":"Point"}
}