{
  "type": "Feature",
  "properties": {
    "addr:full":"Brundall Library, 90 The Street, Brundall Norwich Norfolk NR13 5LH",
    "addr:housenumber":"90",
    "addr:postcode":"nr13 5lh",
    "addr:street":"The Street;Norwich",
    "iso:country":"GB",
    "sg:address":"Brundall Library, 90 The Street, Brundall",
    "sg:city":"Norwich",
    "sg:classifiers":[
        {
            "category":"Education",
            "subcategory":"Library",
            "type":"Public Place"
        },
        {
            "category":"Government",
            "subcategory":"Office",
            "type":"Public Place"
        }
    ],
    "sg:phone":"+44 1603 714576",
    "sg:postcode":"NR13 5LH",
    "sg:province":"Norfolk",
    "sg:tags":[
        "book",
        "local"
    ],
    "wof:name":"NORFOLK COUNTY COUNCIL",
    "wof:placetype":"venue"
},
  "geometry": {"coordinates":[1.430913,52.624752],"type":"Point"}
}