{
  "type": "Feature",
  "properties": {
    "addr:full":"142 Minories London Greater London EC3N 1LB",
    "addr:housenumber":"142",
    "addr:postcode":"ec3n 1lb",
    "addr:street":"Minories",
    "iso:country":"GB",
    "sg:address":"142 Minories",
    "sg:city":"London",
    "sg:classifiers":[
        {
            "category":"Organizations",
            "subcategory":"Non-profit Organization",
            "type":"Services"
        }
    ],
    "sg:phone":"+44 20 7480 7788",
    "sg:postcode":"EC3N 1LB",
    "sg:province":"Greater London",
    "sg:tags":[
        "organisation",
        "voluntary",
        "charity"
    ],
    "wof:name":"Princess Royal Trust",
    "wof:placetype":"venue"
},
  "geometry": {"coordinates":[-0.0756900012,51.5127487183],"type":"Point"}
}