{
  "type": "Feature",
  "properties": {
    "addr:full":"66 Dolphin Square Plymouth Devon PL9 8RW",
    "addr:housenumber":"66",
    "addr:postcode":"pl9 8rw",
    "addr:street":"Dolphin Square",
    "iso:country":"GB",
    "sg:address":"66 Dolphin Square",
    "sg:city":"Plymouth",
    "sg:classifiers":[
        {
            "category":"Retail",
            "subcategory":"Driving School",
            "type":"Services"
        }
    ],
    "sg:phone":"+44 1752 491387",
    "sg:postcode":"PL9 8RW",
    "sg:province":"Devon",
    "wof:name":"The Sweeney School of Motoring",
    "wof:placetype":"venue"
},
  "geometry": {"coordinates":[-4.08167696,50.3585472107],"type":"Point"}
}