{
  "type": "Feature",
  "properties": {
    "addr:full":"Northway Dental Practice, Northway Centre, Northway La Tewkesbury Gloucestershire GL20 8UB",
    "addr:postcode":"gl20 8ub",
    "addr:street":"Northway;Northway La Tewkesbury",
    "iso:country":"GB",
    "sg:address":"Northway Dental Practice, Northway Centre, Northway La",
    "sg:city":"Tewkesbury",
    "sg:classifiers":[
        {
            "category":"Health Services",
            "subcategory":"Dentist",
            "type":"Services"
        }
    ],
    "sg:phone":"+44 1684 295867",
    "sg:postcode":"GL20 8UB",
    "sg:province":"Gloucestershire",
    "wof:name":"C Ross",
    "wof:placetype":"venue"
},
  "geometry": {"coordinates":[-2.149463,51.992958],"type":"Point"}
}