{
  "type": "Feature",
  "properties": {
    "iso:country":"GB",
    "sg:address":"132 Heathfield Road",
    "sg:city":"Keston",
    "sg:classifiers":[
        {
            "category":"Communications",
            "subcategory":"Film & Video Production",
            "type":"Services"
        },
        {
            "category":"Retail",
            "subcategory":"Event Space",
            "type":"Services"
        }
    ],
    "sg:phone":"+44 1737 645111",
    "sg:postcode":"BR2 6BA",
    "sg:province":"Kent",
    "sg:tags":[
        "pr",
        "exhibition",
        "telemarketing",
        "organiser"
    ],
    "wof:name":"E M D Telemarketing",
    "wof:placetype":"venue"
},
  "geometry": {"coordinates":[0.032679,51.354637],"type":"Point"}
}