{
  "type": "Feature",
  "properties": {
    "addr:full":"24 Cresswell Crescent Walsall Staffordshire WS3 2UW",
    "addr:housenumber":"24",
    "addr:postcode":"ws3 2uw",
    "addr:street":"Cresswell Crescent",
    "iso:country":"GB",
    "sg:address":"24 Cresswell Crescent",
    "sg:city":"Walsall",
    "sg:classifiers":[
        {
            "category":"Fast Food",
            "type":"Food & Drink"
        }
    ],
    "sg:phone":"+44 1922 712939",
    "sg:postcode":"WS3 2UW",
    "sg:province":"Staffordshire",
    "sg:tags":[
        "away",
        "take"
    ],
    "wof:name":"Mossley Fish Bar",
    "wof:placetype":"venue"
},
  "geometry": {"coordinates":[-2.021056,52.620613],"type":"Point"}
}