{
  "type": "Feature",
  "properties": {
    "addr:full":"101 Park Street La St Albans Hertfordshire AL2 2JA",
    "addr:housenumber":"101",
    "addr:postcode":"al2 2ja",
    "addr:street":"Park Street La",
    "iso:country":"GB",
    "sg:address":"101 Park Street La",
    "sg:city":"St Albans",
    "sg:classifiers":[
        {
            "category":"Personal",
            "type":"Services"
        }
    ],
    "sg:postcode":"AL2 2JA",
    "sg:province":"Hertfordshire",
    "sg:tags":[
        "wedding"
    ],
    "wof:name":"Newman,Lisa,",
    "wof:placetype":"venue"
},
  "geometry": {"coordinates":[-0.337955,51.721676],"type":"Point"}
}