{
  "type": "Feature",
  "properties": {
    "addr:full":"32 Church Street, Norton Malton North Yorkshire YO17 9HS",
    "addr:housenumber":"32",
    "addr:postcode":"yo17 9hs",
    "addr:street":"Church Street",
    "iso:country":"GB",
    "sg:address":"32 Church Street, Norton",
    "sg:city":"Malton",
    "sg:classifiers":[
        {
            "category":"Wholesale",
            "subcategory":"Office Equipment",
            "type":"Manufacturing & Wholesale Goods"
        },
        {
            "category":"Social Services",
            "subcategory":"Job Training",
            "type":"Services"
        }
    ],
    "sg:phone":"+44 1653 600153",
    "sg:postcode":"YO17 9HS",
    "sg:province":"North Yorkshire",
    "sg:tags":[
        "epos",
        "register",
        "cash",
        "accessory"
    ],
    "wof:name":"Ryedale Cash Registers",
    "wof:placetype":"venue"
},
  "geometry": {"coordinates":[-0.787994,54.132038],"type":"Point"}
}