{
  "type": "Feature",
  "properties": {
    "addr:full":"20a Northgate Peebles Scottish Borders EH45 8RS",
    "addr:housenumber":"20a",
    "addr:postcode":"eh45 8rs",
    "addr:street":"Northgate",
    "iso:country":"GB",
    "sg:address":"20a Northgate",
    "sg:city":"Peebles",
    "sg:classifiers":[
        {
            "category":"Personal",
            "subcategory":"Beauty Salon",
            "type":"Services"
        }
    ],
    "sg:postcode":"EH45 8RS",
    "sg:province":"Scottish Borders",
    "sg:tags":[
        "unisex",
        "hairdresser"
    ],
    "wof:name":"Clouds Hairdressing",
    "wof:placetype":"venue"
},
  "geometry": {"coordinates":[-3.188781023,55.6528892517],"type":"Point"}
}