{
  "type": "Feature",
  "properties": {
    "addr:full":", Veryan Truro Cornwall TR2 5UW",
    "addr:postcode":"tr2 5uw",
    "iso:country":"GB",
    "sg:address":", Veryan",
    "sg:city":"Truro",
    "sg:classifiers":[
        {
            "category":"Arena",
            "subcategory":"Sports Club",
            "type":"Entertainment"
        }
    ],
    "sg:phone":"+44 1872 501733",
    "sg:postcode":"TR2 5UW",
    "sg:province":"Cornwall",
    "wof:name":"Veryan Sports & Social Club",
    "wof:placetype":"venue"
},
  "geometry": {"coordinates":[-4.9240641594,50.2185554504],"type":"Point"}
}