{
  "type": "Feature",
  "properties": {
    "iso:country":"GB",
    "sg:address":"2, The Old Sawmill, Pickwell Lane, Ansty",
    "sg:city":"Haywards Heath",
    "sg:classifiers":[
        {
            "category":"Home & Garden",
            "subcategory":"Building Materials",
            "type":"Retail Goods"
        },
        {
            "category":"Manufacturing",
            "subcategory":"Building Materials",
            "type":"Manufacturing & Wholesale Goods"
        }
    ],
    "sg:phone":"+44 1444 414172",
    "sg:postcode":"RH17 5AP",
    "sg:province":"East Sussex",
    "sg:tags":[
        "fencing",
        "manufacturer",
        "door",
        "barrier",
        "gate"
    ],
    "sg:website":"http://www.beaconfencing.com",
    "wof:name":"Beacon Fencing Ltd",
    "wof:placetype":"venue"
},
  "geometry": {"coordinates":[-0.177126,50.996029],"type":"Point"}
}