{
  "type": "Feature",
  "properties": {
    "addr:full":"181 Tarring Rd, Tarring Worthing West Sussex BN11 4HL",
    "addr:housenumber":"181",
    "addr:postcode":"bn11 4hl",
    "addr:street":"Tarring Rd",
    "iso:country":"GB",
    "sg:address":"181 Tarring Rd, Tarring",
    "sg:city":"Worthing",
    "sg:classifiers":[
        {
            "category":"Insurance",
            "subcategory":"Insurance Agent",
            "type":"Services"
        }
    ],
    "sg:postcode":"BN11 4HL",
    "sg:province":"West Sussex",
    "wof:name":"Independent Direct Insurance Services Lt",
    "wof:placetype":"venue"
},
  "geometry": {"coordinates":[-0.3887459934,50.8181838989],"type":"Point"}
}