{
  "type": "Feature",
  "properties": {
    "iso:country":"GB",
    "sg:address":"Holme Lacy Road, Rotherwas",
    "sg:city":"Hereford",
    "sg:classifiers":[
        {
            "category":"Professional",
            "subcategory":"Employment Agencies",
            "type":"Services"
        }
    ],
    "sg:phone":"+44 1432 264264",
    "sg:postcode":"HR2 6LA",
    "sg:province":"Herefordshire",
    "sg:tags":[
        "agricultural",
        "advice"
    ],
    "wof:name":"L U K (Hereford) Ltd.",
    "wof:placetype":"venue"
},
  "geometry": {"coordinates":[-2.649543047,52.0177459717],"type":"Point"}
}