{
  "type": "Feature",
  "properties": {
    "addr:full":"Mamhead House, Mamhead Exeter Devon EX6 8HD",
    "addr:postcode":"ex6 8hd",
    "addr:street":"Mamhead",
    "iso:country":"GB",
    "sg:address":"Mamhead House, Mamhead",
    "sg:city":"Exeter",
    "sg:classifiers":[
        {
            "category":"Real Estate",
            "subcategory":"Developer",
            "type":"Services"
        }
    ],
    "sg:phone":"+44 1626 890999",
    "sg:postcode":"EX6 8HD",
    "sg:province":"Devon",
    "sg:tags":[
        "property"
    ],
    "wof:name":"Eagle One Securities Ltd.",
    "wof:placetype":"venue"
},
  "geometry": {"coordinates":[-3.47508,50.638779],"type":"Point"}
}