{
  "type": "Feature",
  "properties": {
    "addr:full":"Care Of Roundhouse Furnishings, Lodge Av Dagenham Essex RM8 2HF",
    "addr:postcode":"rm8 2hf",
    "addr:street":"Av Dagenham",
    "iso:country":"GB",
    "sg:address":"Care Of Roundhouse Furnishings, Lodge Av",
    "sg:city":"Dagenham",
    "sg:classifiers":[
        {
            "category":"Home & Garden",
            "subcategory":"Carpets & Floor Coverings",
            "type":"Retail Goods"
        }
    ],
    "sg:phone":"+44 20 8517 2727",
    "sg:postcode":"RM8 2HF",
    "sg:province":"Essex",
    "sg:tags":[
        "carpets",
        "rug",
        "matting"
    ],
    "wof:name":"Carpet Gallery",
    "wof:placetype":"venue"
},
  "geometry": {"coordinates":[0.11278,51.54187],"type":"Point"}
}