{
  "type": "Feature",
  "properties": {
    "iso:country":"GB",
    "sg:address":"Fenton Street",
    "sg:city":"Smethwick",
    "sg:classifiers":[
        {
            "category":"Organizations",
            "subcategory":"Non-profit Organization",
            "type":"Services"
        }
    ],
    "sg:phone":"+44 121 558 2198",
    "sg:postcode":"B66 1HR",
    "sg:province":"West Midlands",
    "sg:tags":[
        "charitable",
        "organisation",
        "voluntary",
        "charity"
    ],
    "wof:name":"SANDWELL ASIAN FAMILY SUPPORT SERVICE",
    "wof:placetype":"venue"
},
  "geometry": {"coordinates":[-1.9795440435,52.4998092651],"type":"Point"}
}