{
  "type": "Feature",
  "properties": {
    "iso:country":"GB",
    "sg:address":"Care Of Harveys",
    "sg:city":"Aylesford",
    "sg:classifiers":[
        {
            "category":"Manufacturing",
            "subcategory":"Wood Products",
            "type":"Manufacturing & Wholesale Goods"
        },
        {
            "category":"Home & Garden",
            "subcategory":"Kitchen Supply",
            "type":"Retail Goods"
        }
    ],
    "sg:postcode":"ME20 7TP",
    "sg:province":"Kent",
    "sg:tags":[
        "ware",
        "maker",
        "cabinet"
    ],
    "wof:name":"Simply Kitchen Studios Ltd.",
    "wof:placetype":"venue"
},
  "geometry": {"coordinates":[0.48037,51.303631],"type":"Point"}
}