{
  "type": "Feature",
  "properties": {
    "addr:full":"43 Melstock Avenue Upminster Essex RM14 3UR",
    "addr:housenumber":"43",
    "addr:postcode":"rm14 3ur",
    "addr:street":"Melstock Avenue",
    "iso:country":"GB",
    "sg:address":"43 Melstock Avenue",
    "sg:city":"Upminster",
    "sg:classifiers":[
        {
            "category":"Organizations",
            "subcategory":"Membership Organization",
            "type":"Services"
        }
    ],
    "sg:phone":"+44 1708 222808",
    "sg:postcode":"RM14 3UR",
    "sg:province":"Essex",
    "sg:tags":[
        "club"
    ],
    "wof:name":"Romford Scottish Association",
    "wof:placetype":"venue"
},
  "geometry": {"coordinates":[0.249016,51.547703],"type":"Point"}
}