{
  "type": "Feature",
  "properties": {
    "addr:full":"The Timberies, Church Lane, East Finchley London Greater London N2 8DZ",
    "addr:postcode":"n2 8dz",
    "addr:street":"Church Lane",
    "iso:country":"GB",
    "sg:address":"The Timberies, Church Lane, East Finchley",
    "sg:city":"London",
    "sg:classifiers":[
        {
            "category":"Manufacturing",
            "subcategory":"Lumber",
            "type":"Manufacturing & Wholesale Goods"
        }
    ],
    "sg:phone":"+44 20 8883 1610",
    "sg:postcode":"N2 8DZ",
    "sg:province":"Greater London",
    "sg:tags":[
        "importer",
        "merchants",
        "agent",
        "timber"
    ],
    "wof:name":"P O Joyce Ltd.",
    "wof:placetype":"venue"
},
  "geometry": {"coordinates":[-0.1711400002,51.5946388245],"type":"Point"}
}