{
  "type": "Feature",
  "properties": {
    "addr:full":"54 Rectory Road Ipswich Suffolk IP2 8EQ",
    "addr:housenumber":"54",
    "addr:postcode":"ip2 8eq",
    "addr:street":"Rectory Road",
    "iso:country":"GB",
    "sg:address":"54 Rectory Road",
    "sg:city":"Ipswich",
    "sg:classifiers":[
        {
            "category":"Building & Trades",
            "subcategory":"Plumbing",
            "type":"Services"
        }
    ],
    "sg:phone":"+44 1473 689184",
    "sg:postcode":"IP2 8EQ",
    "sg:province":"Suffolk",
    "sg:tags":[
        "heating"
    ],
    "wof:name":"A M D Ventilation Ltd.",
    "wof:placetype":"venue"
},
  "geometry": {"coordinates":[1.151648,52.048435],"type":"Point"}
}