{
  "type": "Feature",
  "properties": {
    "iso:country":"GB",
    "sg:address":"119 Shirland Road",
    "sg:city":"London",
    "sg:classifiers":[
        {
            "category":"Real Estate",
            "subcategory":"Real Estate Agent",
            "type":"Services"
        }
    ],
    "sg:phone":"+44 20 8930 4646",
    "sg:postcode":"W9 2EW",
    "sg:province":"Greater London",
    "wof:name":"Connect Asia (Uk) Ltd.",
    "wof:placetype":"venue"
},
  "geometry": {"coordinates":[-0.1936970055,51.5264663696],"type":"Point"}
}