{
  "type": "Feature",
  "properties": {
    "addr:full":"Roch Haverfordwest Pembrokeshire SA62 6AF",
    "addr:postcode":"sa62 6af",
    "addr:street":"Roch;Pembrokeshire",
    "iso:country":"GB",
    "sg:address":"Roch",
    "sg:city":"Haverfordwest",
    "sg:classifiers":[
        {
            "category":"Travel",
            "subcategory":"Hotels & Motels",
            "type":"Entertainment"
        }
    ],
    "sg:phone":"+44 1437 710435",
    "sg:postcode":"SA62 6AF",
    "sg:province":"Pembrokeshire",
    "wof:name":"Rochgate Motel",
    "wof:placetype":"venue"
},
  "geometry": {"coordinates":[-5.08327,51.841228],"type":"Point"}
}