{
  "type": "Feature",
  "properties": {
    "addr:full":"6 The Thatchers, Off Poplar Gro, Allington Maidstone Kent ME16 0XA",
    "addr:housenumber":"6",
    "addr:postcode":"me16 0xa",
    "addr:street":"The;Off",
    "iso:country":"GB",
    "sg:address":"6 The Thatchers, Off Poplar Gro, Allington",
    "sg:city":"Maidstone",
    "sg:classifiers":[
        {
            "category":"Professional",
            "subcategory":"Engineering",
            "type":"Services"
        },
        {
            "category":"Professional",
            "subcategory":"Management & Consulting",
            "type":"Services"
        }
    ],
    "sg:phone":"+44 1622 686918",
    "sg:postcode":"ME16 0XA",
    "sg:province":"Kent",
    "sg:tags":[
        "engineer",
        "specialist",
        "contractor",
        "electrical",
        "consultant"
    ],
    "wof:name":"Sugaring by Terri",
    "wof:placetype":"venue"
},
  "geometry": {"coordinates":[0.491233,51.277004],"type":"Point"}
}