{
  "type": "Feature",
  "properties": {
    "iso:country":"GB",
    "sg:address":"3 The Micro Centre, Gillette Way",
    "sg:city":"Reading",
    "sg:classifiers":[
        {
            "category":"Manufacturing",
            "subcategory":"Building Materials",
            "type":"Manufacturing & Wholesale Goods"
        }
    ],
    "sg:phone":"+44 118 987 4000",
    "sg:postcode":"RG2 0LR",
    "sg:province":"Berkshire",
    "sg:tags":[
        "shutter",
        "supp",
        "door"
    ],
    "wof:name":"Dynasty Doors",
    "wof:placetype":"venue"
},
  "geometry": {"coordinates":[-0.9715,51.435261],"type":"Point"}
}