{
  "type": "Feature",
  "properties": {
    "iso:country":"GB",
    "sg:address":"63 Redhill Road",
    "sg:city":"Stockton-on-tees",
    "sg:classifiers":[
        {
            "category":"Food & Beverages",
            "subcategory":"Supermarket",
            "type":"Retail Goods"
        }
    ],
    "sg:phone":"+44 1642 615572",
    "sg:postcode":"TS19 9BX",
    "sg:province":"Durham",
    "wof:name":"North Eastern & Cumbrian Co-Op Food Stores",
    "wof:placetype":"venue"
},
  "geometry": {"coordinates":[-1.341154,54.588203],"type":"Point"}
}