{
  "type": "Feature",
  "properties": {
    "addr:full":"67 Bradford Road Brighouse West Yorkshire HD6 1ST",
    "addr:housenumber":"67",
    "addr:postcode":"hd6 1st",
    "addr:street":"Bradford Road",
    "iso:country":"GB",
    "sg:address":"67 Bradford Road",
    "sg:city":"Brighouse",
    "sg:classifiers":[
        {
            "category":"Manufacturing",
            "subcategory":"Textiles",
            "type":"Manufacturing & Wholesale Goods"
        }
    ],
    "sg:phone":"+44 1484 714033",
    "sg:postcode":"HD6 1ST",
    "sg:province":"West Yorkshire",
    "sg:tags":[
        "merchant",
        "agent"
    ],
    "wof:name":"Ullmann & Bamforth Ltd.",
    "wof:placetype":"venue"
},
  "geometry": {"coordinates":[-1.778957,53.704041],"type":"Point"}
}