{
  "type": "Feature",
  "properties": {
    "iso:country":"GB",
    "sg:address":"1-4 Upper Gardner Street",
    "sg:city":"Brighton",
    "sg:classifiers":[
        {
            "category":"Shopping",
            "subcategory":"Antiques",
            "type":"Retail Goods"
        }
    ],
    "sg:postcode":"BN1 4AN",
    "sg:province":"East Sussex",
    "wof:name":"Christopher Douglas Restorations",
    "wof:placetype":"venue"
},
  "geometry": {"coordinates":[-0.1392080039,50.8258285522],"type":"Point"}
}