{
  "type": "Feature",
  "properties": {
    "addr:full":"12 Thorpe Lane Banbury Oxfordshire OX16 4UT",
    "addr:housenumber":"12",
    "addr:postcode":"ox16 4ut",
    "addr:street":"Thorpe Lane",
    "iso:country":"GB",
    "sg:address":"12 Thorpe Lane",
    "sg:city":"Banbury",
    "sg:classifiers":[
        {
            "category":"Retail",
            "subcategory":"Auto Repair",
            "type":"Services"
        }
    ],
    "sg:phone":"+44 1295 273945",
    "sg:postcode":"OX16 4UT",
    "sg:province":"Oxfordshire",
    "sg:tags":[
        "car",
        "body"
    ],
    "wof:name":"CAR BODY (BANBURY) LTD",
    "wof:placetype":"venue"
},
  "geometry": {"coordinates":[-1.3181430101,52.0624313354],"type":"Point"}
}