{
  "type": "Feature",
  "properties": {
    "iso:country":"GB",
    "sg:address":"58 High Street, Bovingdon",
    "sg:city":"Hemel Hempstead",
    "sg:classifiers":[
        {
            "category":"Professional",
            "subcategory":"Lawyer & Legal Services",
            "type":"Services"
        }
    ],
    "sg:phone":"+44 1442 834344",
    "sg:postcode":"HP3 0HJ",
    "sg:province":"Hertfordshire",
    "sg:tags":[
        "solicitor"
    ],
    "wof:name":"Batemans",
    "wof:placetype":"venue"
},
  "geometry": {"coordinates":[-0.5318880081,51.7226371765],"type":"Point"}
}