{
  "type": "Feature",
  "properties": {
    "addr:full":"Greenock Road Port Glasgow Inverclyde PA14 6TR",
    "addr:postcode":"pa14 6tr",
    "addr:street":"Greenock Road",
    "iso:country":"GB",
    "sg:address":"Greenock Road",
    "sg:city":"Port Glasgow",
    "sg:classifiers":[
        {
            "category":"Building & Trades",
            "subcategory":"Landscaping Services",
            "type":"Services"
        }
    ],
    "sg:phone":"+44 1475 743602",
    "sg:postcode":"PA14 6TR",
    "sg:province":"Inverclyde",
    "sg:tags":[
        "contractor",
        "sport",
        "ground"
    ],
    "wof:name":"Parklee Playing Fields",
    "wof:placetype":"venue"
},
  "geometry": {"coordinates":[-4.6263837814,55.9304237366],"type":"Point"}
}