{
  "type": "Feature",
  "properties": {
    "addr:full":"5 Station Avenue Caterham Surrey CR3 6LB",
    "addr:housenumber":"5",
    "addr:postcode":"cr3 6lb",
    "addr:street":"Station Avenue",
    "iso:country":"GB",
    "sg:address":"5 Station Avenue",
    "sg:city":"Caterham",
    "sg:classifiers":[
        {
            "category":"Travel",
            "subcategory":"Travel Agent",
            "type":"Entertainment"
        }
    ],
    "sg:phone":"+44 1883 346628",
    "sg:postcode":"CR3 6LB",
    "sg:province":"Surrey",
    "wof:name":"Lunn Poly Ltd.",
    "wof:placetype":"venue"
},
  "geometry": {"coordinates":[-0.0775189996,51.2820281982],"type":"Point"}
}