{
  "type": "Feature",
  "properties": {
    "iso:country":"GB",
    "sg:address":"16 Choir Grn, Knaphill",
    "sg:city":"Woking",
    "sg:classifiers":[
        {
            "category":"Retail",
            "subcategory":"Laundry & Dry Cleaning",
            "type":"Services"
        }
    ],
    "sg:postcode":"GU21 2NQ",
    "sg:province":"Surrey",
    "sg:tags":[
        "home",
        "ironing"
    ],
    "wof:name":"Full Steam Ahead",
    "wof:placetype":"venue"
},
  "geometry": {"coordinates":[-0.607294023,51.320602417],"type":"Point"}
}