{
  "type": "Feature",
  "properties": {
    "addr:full":"103 The Grove Isleworth Greater London TW7 4JE",
    "addr:housenumber":"103",
    "addr:postcode":"tw7 4je",
    "addr:street":"The Grove",
    "iso:country":"GB",
    "sg:address":"103 The Grove",
    "sg:city":"Isleworth",
    "sg:classifiers":[
        {
            "category":"Health Services",
            "subcategory":"Doctor",
            "type":"Services"
        },
        {
            "category":"Health Services",
            "subcategory":"Clinic",
            "type":"Services"
        }
    ],
    "sg:phone":"+44 20 8630 1700",
    "sg:postcode":"TW7 4JE",
    "sg:province":"Greater London",
    "sg:tags":[
        "nh",
        "practitioners"
    ],
    "wof:name":"The Grove Medical Centre",
    "wof:placetype":"venue"
},
  "geometry": {"coordinates":[-0.340101,51.475868],"type":"Point"}
}