{
  "type": "Feature",
  "properties": {
    "iso:country":"GB",
    "sg:address":"Two Trees, Chapel Lane, Great Bromley",
    "sg:city":"Colchester",
    "sg:classifiers":[
        {
            "category":"Professional",
            "subcategory":"Engineering",
            "type":"Services"
        }
    ],
    "sg:postcode":"CO7 0LE",
    "sg:province":"Essex",
    "sg:tags":[
        "civil",
        "engineer"
    ],
    "wof:name":"Fieldview Contracts",
    "wof:placetype":"venue"
},
  "geometry": {"coordinates":[1.01718,51.812309],"type":"Point"}
}