{
  "type": "Feature",
  "properties": {
    "addr:full":"3 Alexander Terrace Stocksfield Northumberland NE43 7LA",
    "addr:housenumber":"3",
    "addr:postcode":"ne43 7la",
    "addr:street":"Alexander Terrace",
    "iso:country":"GB",
    "sg:address":"3 Alexander Terrace",
    "sg:city":"Stocksfield",
    "sg:classifiers":[
        {
            "category":"Personal",
            "subcategory":"Beauty Salon",
            "type":"Services"
        }
    ],
    "sg:phone":"+44 1661 844096",
    "sg:postcode":"NE43 7LA",
    "sg:province":"Northumberland",
    "sg:tags":[
        "unisex",
        "hairdresser"
    ],
    "wof:name":"Oaks Hair Studio",
    "wof:placetype":"venue"
},
  "geometry": {"coordinates":[-1.9163589478,54.9457092285],"type":"Point"}
}