{
  "type": "Feature",
  "properties": {
    "iso:country":"GB",
    "sg:address":"17 Abbey Terrace",
    "sg:city":"Whitby",
    "sg:classifiers":[
        {
            "category":"Travel",
            "subcategory":"Hotels & Motels",
            "type":"Entertainment"
        }
    ],
    "sg:phone":"+44 1947 603868",
    "sg:postcode":"YO21 3HQ",
    "sg:province":"North Yorkshire",
    "wof:name":"Kirklands Private Hotel",
    "wof:placetype":"venue"
},
  "geometry": {"coordinates":[-0.6199889779,54.4889183044],"type":"Point"}
}