{
  "type": "Feature",
  "properties": {
    "addr:full":"37 Sprucedale Gardens Wallington Surrey SM6 9LB",
    "addr:housenumber":"37",
    "addr:postcode":"sm6 9lb",
    "addr:street":"Sprucedale Gardens",
    "iso:country":"GB",
    "sg:address":"37 Sprucedale Gardens",
    "sg:city":"Wallington",
    "sg:classifiers":[
        {
            "category":"Building & Trades",
            "subcategory":"Construction",
            "type":"Services"
        }
    ],
    "sg:phone":"+44 20 8773 9285",
    "sg:postcode":"SM6 9LB",
    "sg:province":"Surrey",
    "sg:tags":[
        "heating",
        "contractor"
    ],
    "wof:name":"Instant Heating",
    "wof:placetype":"venue"
},
  "geometry": {"coordinates":[-0.1343329996,51.34790802],"type":"Point"}
}