{
  "type": "Feature",
  "properties": {
    "addr:full":"Priory Walk Birmingham West Midlands B4 7LJ",
    "addr:postcode":"b4 7lj",
    "addr:street":"Priory Walk",
    "iso:country":"GB",
    "sg:address":"Priory Walk",
    "sg:city":"Birmingham",
    "sg:classifiers":[
        {
            "category":"Food & Beverages",
            "subcategory":"Fruits & Vegetables",
            "type":"Retail Goods"
        }
    ],
    "sg:phone":"+44 121 236 3161",
    "sg:postcode":"B4 7LJ",
    "sg:province":"West Midlands",
    "sg:tags":[
        "greengrocer"
    ],
    "wof:name":"Crisp & Juicy",
    "wof:placetype":"venue"
},
  "geometry": {"coordinates":[-1.8944580555,52.4814224243],"type":"Point"}
}