{
  "type": "Feature",
  "properties": {
    "iso:country":"GB",
    "sg:address":"3 New Street",
    "sg:city":"Huddersfield",
    "sg:classifiers":[
        {
            "category":"Personal",
            "subcategory":"Beauty Salon",
            "type":"Services"
        }
    ],
    "sg:phone":"+44 1484 517344",
    "sg:postcode":"HD1 2AX",
    "sg:province":"West Yorkshire",
    "sg:tags":[
        "unisex",
        "hairdresser"
    ],
    "wof:name":"Saks",
    "wof:placetype":"venue"
},
  "geometry": {"coordinates":[-1.782572,53.645748],"type":"Point"}
}