{
  "type": "Feature",
  "properties": {
    "addr:full":"Unit J Higham Business Park, Bury Close Rushden Bedfordshire NN10 8HQ",
    "addr:postcode":"nn10 8hq",
    "addr:street":"Higham Business Park Bury Close",
    "iso:country":"GB",
    "sg:address":"Unit J Higham Business Park, Bury Close",
    "sg:city":"Rushden",
    "sg:classifiers":[
        {
            "category":"Building & Trades",
            "subcategory":"Electrical",
            "type":"Services"
        }
    ],
    "sg:phone":"+44 1933 410111",
    "sg:postcode":"NN10 8HQ",
    "sg:province":"Bedfordshire",
    "sg:tags":[
        "lighting"
    ],
    "wof:name":"Stanwick Engineering Ltd.",
    "wof:placetype":"venue"
},
  "geometry": {"coordinates":[-0.5980240107,52.2876243591],"type":"Point"}
}