{
  "type": "Feature",
  "properties": {
    "iso:country":"GB",
    "sg:address":"30 Marmora Road",
    "sg:city":"London",
    "sg:classifiers":[
        {
            "category":"Education",
            "subcategory":"Dance Studio",
            "type":"Public Place"
        }
    ],
    "sg:postcode":"SE22 0RX",
    "sg:province":"Greater London",
    "sg:tags":[
        "school",
        "dancing"
    ],
    "wof:name":"Julie Pierre",
    "wof:placetype":"venue"
},
  "geometry": {"coordinates":[-0.0567060001,51.4516105652],"type":"Point"}
}