{
  "type": "Feature",
  "properties": {
    "addr:full":"30 Marmora Road London Greater London SE22 0RX",
    "addr:housenumber":"30",
    "addr:postcode":"se22 0rx",
    "addr:street":"Marmora Road",
    "iso:country":"GB",
    "sg:address":"30 Marmora Road",
    "sg:city":"London",
    "sg:classifiers":[
        {
            "category":"Education",
            "subcategory":"Dance Studio",
            "type":"Public Place"
        }
    ],
    "sg:postcode":"SE22 0RX",
    "sg:province":"Greater London",
    "sg:tags":[
        "school",
        "dancing"
    ],
    "wof:name":"Julie Pierre",
    "wof:placetype":"venue"
},
  "geometry": {"coordinates":[-0.0567060001,51.4516105652],"type":"Point"}
}