{
  "type": "Feature",
  "properties": {
    "addr:full":"Normanton Park Rd Oakham Leicestershire LE15 8QH",
    "addr:postcode":"le15 8qh",
    "addr:street":"Normanton Park Rd",
    "iso:country":"GB",
    "sg:address":"Normanton Park Rd",
    "sg:city":"Oakham",
    "sg:classifiers":[
        {
            "category":"Cafe",
            "type":"Food & Drink"
        }
    ],
    "sg:phone":"+44 1780 722118",
    "sg:postcode":"LE15 8QH",
    "sg:province":"Leicestershire",
    "sg:tags":[
        "tea",
        "room"
    ],
    "wof:name":"Tickled Trout The",
    "wof:placetype":"venue"
},
  "geometry": {"coordinates":[-0.59111,52.659077],"type":"Point"}
}