{
  "type": "Feature",
  "properties": {
    "addr:full":"209 Blackstock Road London Greater London N5 2LL",
    "addr:housenumber":"209",
    "addr:postcode":"n5 2ll",
    "addr:street":"Blackstock Road",
    "iso:country":"GB",
    "sg:address":"209 Blackstock Road",
    "sg:city":"London",
    "sg:classifiers":[
        {
            "category":"Food & Beverages",
            "subcategory":"Groceries & Convenience Stores",
            "type":"Retail Goods"
        }
    ],
    "sg:phone":"+44 20 7226 9744",
    "sg:postcode":"N5 2LL",
    "sg:province":"Greater London",
    "wof:name":"Blackstock Mini Market",
    "wof:placetype":"venue"
},
  "geometry": {"coordinates":[-0.0985149965,51.5598373413],"type":"Point"}
}