{
  "type": "Feature",
  "properties": {
    "addr:full":"103 Bancroft Hitchin Bedfordshire SG5 1NB",
    "addr:housenumber":"103",
    "addr:postcode":"sg5 1nb",
    "addr:street":"Bancroft",
    "iso:country":"GB",
    "sg:address":"103 Bancroft",
    "sg:city":"Hitchin",
    "sg:classifiers":[
        {
            "category":"Restaurant",
            "type":"Food & Drink"
        }
    ],
    "sg:postcode":"SG5 1NB",
    "sg:province":"Bedfordshire",
    "wof:name":"Stevens,C,",
    "wof:placetype":"venue"
},
  "geometry": {"coordinates":[-0.2765800059,51.9503555298],"type":"Point"}
}