{
  "type": "Feature",
  "properties": {
    "iso:country":"GB",
    "sg:address":"37-39 Coventry Road, Sharnford",
    "sg:city":"Hinckley",
    "sg:classifiers":[
        {
            "category":"Sports & Exercise",
            "subcategory":"Golf",
            "type":"Entertainment"
        }
    ],
    "sg:phone":"+44 1455 272231",
    "sg:postcode":"LE10 3PG",
    "sg:province":"Leicestershire",
    "sg:tags":[
        "equipment"
    ],
    "wof:name":"Jeffrey Kibble",
    "wof:placetype":"venue"
},
  "geometry": {"coordinates":[-1.2956269979,52.5204086304],"type":"Point"}
}