{
  "type": "Feature",
  "properties": {
    "addr:full":"680 Green Lane Ilford Essex IG3 9RX",
    "addr:housenumber":"680",
    "addr:postcode":"ig3 9rx",
    "addr:street":"Green Lane",
    "iso:country":"GB",
    "sg:address":"680 Green Lane",
    "sg:city":"Ilford",
    "sg:classifiers":[
        {
            "category":"Autos & Motor Vehicles",
            "subcategory":"Auto Supplies",
            "type":"Retail Goods"
        },
        {
            "category":"Professional",
            "subcategory":"Detective & Security Services",
            "type":"Services"
        }
    ],
    "sg:phone":"+44 20 8599 9002",
    "sg:postcode":"IG3 9RX",
    "sg:province":"Essex",
    "sg:tags":[
        "car",
        "part",
        "accessory"
    ],
    "wof:name":"Benak's",
    "wof:placetype":"venue"
},
  "geometry": {"coordinates":[0.1166400015,51.5629730225],"type":"Point"}
}