{
  "type": "Feature",
  "properties": {
    "addr:full":"9 High Street, Pittenweem Anstruther Fife KY10 2LA",
    "addr:housenumber":"9",
    "addr:postcode":"ky10 2la",
    "addr:street":"High Street",
    "iso:country":"GB",
    "sg:address":"9 High Street, Pittenweem",
    "sg:city":"Anstruther",
    "sg:classifiers":[
        {
            "category":"Shopping",
            "subcategory":"Department Store",
            "type":"Retail Goods"
        }
    ],
    "sg:phone":"+44 1333 311495",
    "sg:postcode":"KY10 2LA",
    "sg:province":"Fife",
    "wof:name":"Gingerbread Horse",
    "wof:placetype":"venue"
},
  "geometry": {"coordinates":[-2.729234,56.213783],"type":"Point"}
}