{
  "type": "Feature",
  "properties": {
    "addr:full":"Kings Aveune House, Kings Avenue New Malden Surrey KT3 4DY",
    "addr:postcode":"kt3 4dy",
    "addr:street":"Kings;Kings Avenue",
    "iso:country":"GB",
    "sg:address":"Kings Aveune House, Kings Avenue",
    "sg:city":"New Malden",
    "sg:classifiers":[
        {
            "category":"Professional",
            "subcategory":"Accounting & Tax Preparation",
            "type":"Services"
        }
    ],
    "sg:phone":"+44 20 8949 1657",
    "sg:postcode":"KT3 4DY",
    "sg:province":"Surrey",
    "sg:tags":[
        "accountant"
    ],
    "wof:name":"Mantle Evans",
    "wof:placetype":"venue"
},
  "geometry": {"coordinates":[-0.2523739934,51.4020118713],"type":"Point"}
}