{
  "type": "Feature",
  "properties": {
    "addr:full":"829 Manchester Road, Castleton Rochdale Lancashire OL11 3AH",
    "addr:housenumber":"829",
    "addr:postcode":"ol11 3ah",
    "addr:street":"Manchester Road",
    "iso:country":"GB",
    "sg:address":"829 Manchester Road, Castleton",
    "sg:city":"Rochdale",
    "sg:classifiers":[
        {
            "category":"Fast Food",
            "type":"Food & Drink"
        }
    ],
    "sg:postcode":"OL11 3AH",
    "sg:province":"Lancashire",
    "sg:tags":[
        "away",
        "take"
    ],
    "wof:name":"Tung Hing",
    "wof:placetype":"venue"
},
  "geometry": {"coordinates":[-2.1790540218,53.5921707153],"type":"Point"}
}