{
  "type": "Feature",
  "properties": {
    "iso:country":"GB",
    "sg:address":"East Anglia Regional Office, Blickling",
    "sg:city":"Norwich",
    "sg:classifiers":[
        {
            "category":"Landmark",
            "subcategory":"Tourist Attraction",
            "type":"Public Place"
        }
    ],
    "sg:phone":"+44 1263 733471",
    "sg:postcode":"NR11 6NF",
    "sg:province":"Norfolk",
    "sg:tags":[
        "interest"
    ],
    "wof:name":"The National Trust",
    "wof:placetype":"venue"
},
  "geometry": {"coordinates":[1.2291400433,52.8101997375],"type":"Point"}
}