{
  "type": "Feature",
  "properties": {
    "iso:country":"GB",
    "sg:address":"32 Heathwood Rd",
    "sg:city":"Weymouth",
    "sg:classifiers":[
        {
            "category":"Retail",
            "subcategory":"Auto Repair",
            "type":"Services"
        }
    ],
    "sg:phone":"+44 1305 767335",
    "sg:postcode":"DT4 0PQ",
    "sg:province":"Dorset",
    "sg:tags":[
        "modification",
        "garage"
    ],
    "wof:name":"Computa Tune",
    "wof:placetype":"venue"
},
  "geometry": {"coordinates":[-2.467919,50.61615],"type":"Point"}
}