{
  "type": "Feature",
  "properties": {
    "addr:full":"75 Rayne Road Braintree Essex CM7 2QD",
    "addr:housenumber":"75",
    "addr:postcode":"cm7 2qd",
    "addr:street":"Rayne Road",
    "iso:country":"GB",
    "sg:address":"75 Rayne Road",
    "sg:city":"Braintree",
    "sg:classifiers":[
        {
            "category":"Building & Trades",
            "subcategory":"Plumbing",
            "type":"Services"
        }
    ],
    "sg:phone":"+44 1376 342589",
    "sg:postcode":"CM7 2QD",
    "sg:province":"Essex",
    "sg:tags":[
        "central",
        "heating"
    ],
    "wof:name":"Agimec (Mechanical Services) Ltd.",
    "wof:placetype":"venue"
},
  "geometry": {"coordinates":[0.54644,51.87896],"type":"Point"}
}