{
  "type": "Feature",
  "properties": {
    "iso:country":"GB",
    "sg:address":"342 Harrow Road",
    "sg:city":"London",
    "sg:classifiers":[
        {
            "category":"Real Estate",
            "subcategory":"Real Estate Operator",
            "type":"Services"
        }
    ],
    "sg:phone":"+44 20 8952 7200",
    "sg:postcode":"W9 2HP",
    "sg:province":"Greater London",
    "sg:tags":[
        "letting",
        "agent"
    ],
    "wof:name":"Douglas Philips",
    "wof:placetype":"venue"
},
  "geometry": {"coordinates":[-0.194609,51.522949],"type":"Point"}
}