{
  "type": "Feature",
  "properties": {
    "addr:full":", Haresfield Stonehouse Stonehouse Gloucestershire GL10 3EF",
    "addr:housenumber":"haresfield",
    "addr:postcode":"gl10 3ef",
    "addr:street":"Stonehouse",
    "iso:country":"GB",
    "sg:address":", Haresfield Stonehouse",
    "sg:city":"Stonehouse",
    "sg:classifiers":[
        {
            "category":"Education",
            "subcategory":"School",
            "type":"Public Place"
        }
    ],
    "sg:phone":"+44 1452 720303",
    "sg:postcode":"GL10 3EF",
    "sg:province":"Gloucestershire",
    "sg:tags":[
        "local",
        "authority"
    ],
    "wof:name":"Haresfield C Of E Primary School",
    "wof:placetype":"venue"
},
  "geometry": {"coordinates":[-2.27043,51.791252],"type":"Point"}
}