{
  "type": "Feature",
  "properties": {
    "addr:full":"63 Avon Crescent Stratford-upon-avon Warwickshire CV37 7EZ",
    "addr:housenumber":"63",
    "addr:postcode":"cv37 7ez",
    "addr:street":"Avon Crescent",
    "iso:country":"GB",
    "sg:address":"63 Avon Crescent",
    "sg:city":"Stratford-upon-avon",
    "sg:classifiers":[
        {
            "category":"Shopping",
            "subcategory":"Clothing, Apparel, & Fashions",
            "type":"Retail Goods"
        },
        {
            "category":"Shopping",
            "subcategory":"Baby Store",
            "type":"Retail Goods"
        }
    ],
    "sg:phone":"+44 1789 267991",
    "sg:postcode":"CV37 7EZ",
    "sg:province":"Warwickshire",
    "sg:tags":[
        "child",
        "childrens",
        "babywear"
    ],
    "wof:name":"Lilliput",
    "wof:placetype":"venue"
},
  "geometry": {"coordinates":[-1.6028490067,52.135219574],"type":"Point"}
}