{
  "type": "Feature",
  "properties": {
    "addr:full":"Auew House, 51 Furnival Gate Sheffield South Yorkshire S1 4QQ",
    "addr:housenumber":"51",
    "addr:postcode":"s1 4qq",
    "addr:street":"Furnival Gate",
    "iso:country":"GB",
    "sg:address":"Auew House, 51 Furnival Gate",
    "sg:city":"Sheffield",
    "sg:classifiers":[
        {
            "category":"Banks & Credit Unions",
            "subcategory":"Financial Services",
            "type":"Services"
        }
    ],
    "sg:phone":"+44 114 276 6800",
    "sg:postcode":"S1 4QQ",
    "sg:province":"South Yorkshire",
    "sg:tags":[
        "consultant"
    ],
    "wof:name":"The Associates",
    "wof:placetype":"venue"
},
  "geometry": {"coordinates":[-1.470379,53.377636],"type":"Point"}
}