{
  "type": "Feature",
  "properties": {
    "addr:full":"302 High St North London Greater London E12 6SA",
    "addr:housenumber":"302",
    "addr:postcode":"e12 6sa",
    "addr:street":"High St North",
    "iso:country":"GB",
    "sg:address":"302 High St North",
    "sg:city":"London",
    "sg:classifiers":[
        {
            "category":"Shopping",
            "subcategory":"Department Store",
            "type":"Retail Goods"
        }
    ],
    "sg:postcode":"E12 6SA",
    "sg:province":"Greater London",
    "wof:name":"Singh,Inderjhi,",
    "wof:placetype":"venue"
},
  "geometry": {"coordinates":[0.0502879992,51.5427513123],"type":"Point"}
}