{
  "type": "Feature",
  "properties": {
    "iso:country":"GB",
    "sg:address":"School Farm, Rowberrow",
    "sg:city":"Winscombe",
    "sg:classifiers":[
        {
            "category":"Freight",
            "type":"Transportation"
        }
    ],
    "sg:postcode":"BS25 1QP",
    "sg:province":"Somerset",
    "sg:tags":[
        "haulage",
        "road"
    ],
    "wof:name":"P C Lyons & Son",
    "wof:placetype":"venue"
},
  "geometry": {"coordinates":[-2.831329,51.313171],"type":"Point"}
}