{
  "type": "Feature",
  "properties": {
    "addr:full":"Bells Farm, Bells Farm Clo Birmingham West Midlands B14 5QP",
    "addr:postcode":"b14 5qp",
    "iso:country":"GB",
    "sg:address":"Bells Farm, Bells Farm Clo",
    "sg:city":"Birmingham",
    "sg:classifiers":[
        {
            "category":"Organizations",
            "subcategory":"Non-profit Organization",
            "type":"Services"
        }
    ],
    "sg:phone":"+44 121 451 2992",
    "sg:postcode":"B14 5QP",
    "sg:province":"West Midlands",
    "sg:tags":[
        "organisation",
        "voluntary",
        "charity"
    ],
    "wof:name":"Dyspraxia Foundation West Midlands Group",
    "wof:placetype":"venue"
},
  "geometry": {"coordinates":[-1.9078960419,52.4064407349],"type":"Point"}
}