{
  "type": "Feature",
  "properties": {
    "iso:country":"GB",
    "sg:address":"72 Stockport Rd",
    "sg:city":"Cheadle",
    "sg:classifiers":[
        {
            "category":"Professional",
            "subcategory":"Art Services",
            "type":"Services"
        }
    ],
    "sg:phone":"+44 161 428 8205",
    "sg:postcode":"SK8 2AF",
    "sg:province":"Cheshire",
    "sg:tags":[
        "photographer"
    ],
    "wof:name":"Cheadle Photo Service",
    "wof:placetype":"venue"
},
  "geometry": {"coordinates":[-2.208313,53.395145],"type":"Point"}
}