{
  "type": "Feature",
  "properties": {
    "addr:full":"51 Carnanton Road, Upper Walthamstow London Greater London E17 4DB",
    "addr:housenumber":"51",
    "addr:postcode":"e17 4db",
    "addr:street":"Carnanton Road",
    "iso:country":"GB",
    "sg:address":"51 Carnanton Road, Upper Walthamstow",
    "sg:city":"London",
    "sg:classifiers":[
        {
            "category":"Professional",
            "subcategory":"Computer Services",
            "type":"Services"
        }
    ],
    "sg:postcode":"E17 4DB",
    "sg:province":"Greater London",
    "sg:tags":[
        "system",
        "software"
    ],
    "wof:name":"Gabriel Computer Services Ltd",
    "wof:placetype":"venue"
},
  "geometry": {"coordinates":[0.002371,51.596058],"type":"Point"}
}