{
  "type": "Feature",
  "properties": {
    "addr:full":"Middlebrook Gardens, Brayton Selby East Riding of Yorkshire YO8 9SY",
    "addr:postcode":"yo8 9sy",
    "addr:street":"Middlebrook Gardens",
    "iso:country":"GB",
    "sg:address":"Middlebrook Gardens, Brayton",
    "sg:city":"Selby",
    "sg:classifiers":[
        {
            "category":"Military Area",
            "subcategory":"Air Force Base",
            "type":"Public Place"
        }
    ],
    "sg:phone":"+44 7973 828017",
    "sg:postcode":"YO8 9SY",
    "sg:province":"East Riding of Yorkshire",
    "sg:tags":[
        "taxi",
        "hire",
        "private"
    ],
    "wof:name":"Toad Stool Cabs",
    "wof:placetype":"venue"
},
  "geometry": {"coordinates":[-1.0892560482,53.7682876587],"type":"Point"}
}