{
  "type": "Feature",
  "properties": {
    "iso:country":"GB",
    "sg:address":"Church End Barley",
    "sg:city":"Royston",
    "sg:classifiers":[
        {
            "category":"Social Services",
            "subcategory":"Retirement Home",
            "type":"Services"
        }
    ],
    "sg:postcode":"SG8 8JS",
    "sg:province":"Bedfordshire",
    "sg:tags":[
        "residential",
        "care"
    ],
    "wof:name":"Margaret House",
    "wof:placetype":"venue"
},
  "geometry": {"coordinates":[0.0377800018,52.0260543823],"type":"Point"}
}