{
  "type": "Feature",
  "properties": {
    "addr:full":"284 High Street Felixstowe Suffolk IP11 9EB",
    "addr:housenumber":"284",
    "addr:postcode":"ip11 9eb",
    "addr:street":"High Street",
    "iso:country":"GB",
    "sg:address":"284 High Street",
    "sg:city":"Felixstowe",
    "sg:classifiers":[
        {
            "category":"Shopping",
            "subcategory":"Bicycles & Sporting Goods",
            "type":"Retail Goods"
        }
    ],
    "sg:postcode":"IP11 9EB",
    "sg:province":"Suffolk",
    "sg:tags":[
        "cycle",
        "accessory"
    ],
    "wof:name":"Stephen Hudson-Smith",
    "wof:placetype":"venue"
},
  "geometry": {"coordinates":[1.3422,51.97073],"type":"Point"}
}