{
  "type": "Feature",
  "properties": {
    "iso:country":"GB",
    "sg:address":"St Johns Centre, Hedge End",
    "sg:city":"Southampton",
    "sg:classifiers":[
        {
            "category":"Banks & Credit Unions",
            "subcategory":"Financial Services",
            "type":"Services"
        }
    ],
    "sg:phone":"+44 1489 785574",
    "sg:postcode":"SO304QU",
    "sg:province":"Hampshire",
    "sg:tags":[
        "building",
        "society"
    ],
    "wof:name":"Portman Building Society",
    "wof:placetype":"venue"
},
  "geometry": {"coordinates":[-1.30366,50.913216],"type":"Point"}
}