{
  "type": "Feature",
  "properties": {
    "addr:full":"Po Box 15 Wellingborough Northamptonshire NN8 1LH",
    "addr:housenumber":"po box 15",
    "addr:postcode":"nn8 1lh",
    "iso:country":"GB",
    "sg:address":"Po Box 15",
    "sg:city":"Wellingborough",
    "sg:classifiers":[
        {
            "category":"Food & Beverages",
            "subcategory":"Supermarket",
            "type":"Retail Goods"
        }
    ],
    "sg:phone":"+44 1933 221700",
    "sg:postcode":"NN8 1LH",
    "sg:province":"Northamptonshire",
    "sg:tags":[
        "frozen"
    ],
    "wof:name":"Saxby Bros Ltd.",
    "wof:placetype":"venue"
},
  "geometry": {"coordinates":[-0.696296,52.302422],"type":"Point"}
}