{
  "type": "Feature",
  "properties": {
    "addr:full":"99 Bankfield Lane, Churchtown Southport Lancashire PR9 7NT",
    "addr:housenumber":"99",
    "addr:postcode":"pr9 7nt",
    "addr:street":"Bankfield Lane",
    "iso:country":"GB",
    "sg:address":"99 Bankfield Lane, Churchtown",
    "sg:city":"Southport",
    "sg:classifiers":[
        {
            "category":"Building & Trades",
            "subcategory":"Landscaping Services",
            "type":"Services"
        },
        {
            "category":"Home & Garden",
            "subcategory":"Garden Supply",
            "type":"Retail Goods"
        }
    ],
    "sg:phone":"+44 1704 228235",
    "sg:postcode":"PR9 7NT",
    "sg:province":"Lancashire",
    "sg:tags":[
        "planting",
        "nurseryman",
        "tree",
        "shrub"
    ],
    "wof:name":"J A Jones & Sons (Churchtown) Ltd.",
    "wof:placetype":"venue"
},
  "geometry": {"coordinates":[-2.9541599751,53.6640739441],"type":"Point"}
}