{
  "type": "Feature",
  "properties": {
    "addr:full":"10-12 Queens Square Crawley Surrey RH10 1DY",
    "addr:housenumber":"10-12",
    "addr:postcode":"rh10 1dy",
    "addr:street":"Queens Square",
    "iso:country":"GB",
    "sg:address":"10-12 Queens Square",
    "sg:city":"Crawley",
    "sg:classifiers":[
        {
            "category":"Shopping",
            "subcategory":"Clothing, Apparel, & Fashions",
            "type":"Retail Goods"
        }
    ],
    "sg:phone":"+44 1293 619874",
    "sg:postcode":"RH10 1DY",
    "sg:province":"Surrey",
    "sg:tags":[
        "shop"
    ],
    "wof:name":"Bewise",
    "wof:placetype":"venue"
},
  "geometry": {"coordinates":[-0.1872970015,51.1156654358],"type":"Point"}
}