{
  "type": "Feature",
  "properties": {
    "addr:full":"6 Nell Gap Avenue, Middlestown Wakefield West Yorkshire WF4 4PJ",
    "addr:housenumber":"6",
    "addr:postcode":"wf4 4pj",
    "addr:street":"Nell Gap Avenue;West",
    "iso:country":"GB",
    "sg:address":"6 Nell Gap Avenue, Middlestown",
    "sg:city":"Wakefield",
    "sg:classifiers":[
        {
            "category":"Home & Garden",
            "subcategory":"Home Furnishings",
            "type":"Retail Goods"
        }
    ],
    "sg:postcode":"WF4 4PJ",
    "sg:province":"West Yorkshire",
    "sg:tags":[
        "awning",
        "canopy",
        "blinds"
    ],
    "wof:name":"S & J Quality Blinds",
    "wof:placetype":"venue"
},
  "geometry": {"coordinates":[-1.599125,53.651833],"type":"Point"}
}