{
  "type": "Feature",
  "properties": {
    "addr:full":"138 Dewsbury Rd Ossett West Yorkshire WF5 9PE",
    "addr:housenumber":"138",
    "addr:postcode":"wf5 9pe",
    "addr:street":"Dewsbury Rd",
    "iso:country":"GB",
    "sg:address":"138 Dewsbury Rd",
    "sg:city":"Ossett",
    "sg:classifiers":[
        {
            "category":"Home & Garden",
            "subcategory":"Household Appliances",
            "type":"Retail Goods"
        }
    ],
    "sg:phone":"+44 1924 280327",
    "sg:postcode":"WF5 9PE",
    "sg:province":"West Yorkshire",
    "sg:tags":[
        "cleaner",
        "domestic",
        "vacuum"
    ],
    "wof:name":"Ossett Vacuum Service Centre",
    "wof:placetype":"venue"
},
  "geometry": {"coordinates":[-1.585567,53.689987],"type":"Point"}
}