{
  "type": "Feature",
  "properties": {
    "addr:full":"Anderson Avenue Rugby Warwickshire CV22 5PE",
    "addr:postcode":"cv22 5pe",
    "addr:street":"Anderson Avenue",
    "iso:country":"GB",
    "sg:address":"Anderson Avenue",
    "sg:city":"Rugby",
    "sg:classifiers":[
        {
            "category":"Education",
            "subcategory":"School",
            "type":"Public Place"
        }
    ],
    "sg:phone":"+44 1788 812449",
    "sg:postcode":"CV22 5PE",
    "sg:province":"Warwickshire",
    "sg:tags":[
        "local",
        "authority"
    ],
    "wof:name":"Rokeby Infant School",
    "wof:placetype":"venue"
},
  "geometry": {"coordinates":[-1.264969945,52.3607177734],"type":"Point"}
}