{
  "type": "Feature",
  "properties": {
    "addr:full":"Unit 4 Kimpton Trade & Business Centre, Minden Rd Sutton Surrey SM3 9QP",
    "addr:housenumber":"unit 4 kimpton",
    "addr:postcode":"sm3 9qp",
    "addr:street":"Minden Rd",
    "iso:country":"GB",
    "sg:address":"Unit 4 Kimpton Trade & Business Centre, Minden Rd",
    "sg:city":"Sutton",
    "sg:classifiers":[
        {
            "category":"Building & Trades",
            "subcategory":"Construction",
            "type":"Services"
        }
    ],
    "sg:phone":"+44 20 8641 0066",
    "sg:postcode":"SM3 9QP",
    "sg:province":"Surrey",
    "sg:tags":[
        "window",
        "replacement"
    ],
    "wof:name":"B A C Windows",
    "wof:placetype":"venue"
},
  "geometry": {"coordinates":[-0.208220005,51.37474823],"type":"Point"}
}