{
  "type": "Feature",
  "properties": {
    "iso:country":"GB",
    "sg:address":"Hartlepool Dock Offices, Cleveland Road",
    "sg:city":"Hartlepool",
    "sg:classifiers":[
        {
            "category":"Freight",
            "type":"Transportation"
        }
    ],
    "sg:phone":"+44 1429 860966",
    "sg:postcode":"TS24 0SY",
    "sg:province":"Durham",
    "sg:tags":[
        "shipping"
    ],
    "wof:name":"G B Agencies Ltd.",
    "wof:placetype":"venue"
},
  "geometry": {"coordinates":[-1.2141189575,54.6854057312],"type":"Point"}
}