{
  "type": "Feature",
  "properties": {
    "addr:full":"C/o Jayden Consultant Ltd, North Park Lodge Lewes East Sussex BN8 6DS",
    "addr:housenumber":"/ o;north",
    "addr:postcode":"bn8 6ds",
    "addr:street":"C;Park Lodge",
    "iso:country":"GB",
    "sg:address":"C/o Jayden Consultant Ltd, North Park Lodge",
    "sg:city":"Lewes",
    "sg:classifiers":[
        {
            "category":"Building & Trades",
            "subcategory":"Cleaning & Sanitation",
            "type":"Services"
        }
    ],
    "sg:phone":"+44 1342 825300",
    "sg:postcode":"BN8 6DS",
    "sg:province":"East Sussex",
    "sg:tags":[
        "polishing",
        "floor"
    ],
    "wof:name":"Lurrell Industries Ltd.",
    "wof:placetype":"venue"
},
  "geometry": {"coordinates":[0.16159,50.924061],"type":"Point"}
}