{
  "type": "Feature",
  "properties": {
    "iso:country":"GB",
    "sg:address":"The Mansion, Kidbrooke Park",
    "sg:city":"Forest Row",
    "sg:classifiers":[
        {
            "category":"Organizations",
            "subcategory":"Non-profit Organization",
            "type":"Services"
        }
    ],
    "sg:phone":"+44 1342 826104",
    "sg:postcode":"RH18 5JA",
    "sg:province":"East Sussex",
    "sg:tags":[
        "organisation",
        "voluntary",
        "charity"
    ],
    "wof:name":"Hermes Trust",
    "wof:placetype":"venue"
},
  "geometry": {"coordinates":[0.033261,51.098259],"type":"Point"}
}