{
  "type": "Feature",
  "properties": {
    "addr:full":"91 Mayflower Road, Park Street St Albans Hertfordshire AL2 2QN",
    "addr:housenumber":"91",
    "addr:postcode":"al2 2qn",
    "addr:street":"Mayflower Road Park Street",
    "iso:country":"GB",
    "sg:address":"91 Mayflower Road, Park Street",
    "sg:city":"St Albans",
    "sg:classifiers":[
        {
            "category":"Professional",
            "subcategory":"Engineering",
            "type":"Services"
        }
    ],
    "sg:phone":"+44 1727 874158",
    "sg:postcode":"AL2 2QN",
    "sg:province":"Hertfordshire",
    "sg:tags":[
        "contractor",
        "electrical",
        "engineer"
    ],
    "wof:name":"T & S Electrical Services Ltd.",
    "wof:placetype":"venue"
},
  "geometry": {"coordinates":[-0.356639,51.722019],"type":"Point"}
}