{
  "type": "Feature",
  "properties": {
    "addr:full":"141 Thomas La Liverpool Merseyside L14 5NT",
    "addr:housenumber":"141",
    "addr:postcode":"l14 5nt",
    "addr:street":"Thomas La",
    "iso:country":"GB",
    "sg:address":"141 Thomas La",
    "sg:city":"Liverpool",
    "sg:classifiers":[
        {
            "category":"Shopping",
            "subcategory":"Gifts & Souvenirs",
            "type":"Retail Goods"
        }
    ],
    "sg:phone":"+44 151 228 3931",
    "sg:postcode":"L14 5NT",
    "sg:province":"Merseyside",
    "sg:tags":[
        "shop"
    ],
    "wof:name":"Gifts From Around The Globe",
    "wof:placetype":"venue"
},
  "geometry": {"coordinates":[-2.892305,53.41156],"type":"Point"}
}