{
  "type": "Feature",
  "properties": {
    "addr:full":"37 Anchorsholme Lane East Thornton-cleveleys Lancashire FY5 3QH",
    "addr:housenumber":"37",
    "addr:postcode":"fy5 3qh",
    "addr:street":"Anchorsholme Lane East Thornton-Cleveleys",
    "iso:country":"GB",
    "sg:address":"37 Anchorsholme Lane East",
    "sg:city":"Thornton-cleveleys",
    "sg:classifiers":[
        {
            "category":"Professional",
            "subcategory":"Engineering",
            "type":"Services"
        },
        {
            "category":"Building & Trades",
            "subcategory":"Electrical",
            "type":"Services"
        }
    ],
    "sg:phone":"+44 1253 821596",
    "sg:postcode":"FY5 3QH",
    "sg:province":"Lancashire",
    "sg:tags":[
        "engineer",
        "electrician",
        "contractor"
    ],
    "wof:name":"Parkers Electrical",
    "wof:placetype":"venue"
},
  "geometry": {"coordinates":[-3.039345026,53.8726348877],"type":"Point"}
}