{
  "type": "Feature",
  "properties": {
    "iso:country":"GB",
    "sg:address":"P O Box 58",
    "sg:city":"Godalming",
    "sg:classifiers":[
        {
            "category":"Travel",
            "subcategory":"Travel Agent",
            "type":"Entertainment"
        }
    ],
    "sg:phone":"+44 1483 425448",
    "sg:postcode":"GU7 2SE",
    "sg:province":"Surrey",
    "wof:name":"Photo Travellers Ltd.",
    "wof:placetype":"venue"
},
  "geometry": {"coordinates":[-0.634334,51.201195],"type":"Point"}
}