{
  "type": "Feature",
  "properties": {
    "addr:full":"93 Harlow Crescent Harrogate North Yorkshire HG2 0AL",
    "addr:housenumber":"93",
    "addr:postcode":"hg2 0al",
    "addr:street":"Harlow Crescent",
    "iso:country":"GB",
    "sg:address":"93 Harlow Crescent",
    "sg:city":"Harrogate",
    "sg:classifiers":[
        {
            "category":"Education",
            "subcategory":"School",
            "type":"Public Place"
        },
        {
            "category":"Education",
            "subcategory":"University",
            "type":"Public Place"
        }
    ],
    "sg:phone":"+44 1423 506708",
    "sg:postcode":"HG2 0AL",
    "sg:province":"North Yorkshire",
    "sg:tags":[
        "private",
        "tuition"
    ],
    "wof:name":"GEOFFREY D A WILSON",
    "wof:placetype":"venue"
},
  "geometry": {"coordinates":[-1.5542279482,53.9791145325],"type":"Point"}
}