{
  "type": "Feature",
  "properties": {
    "addr:full":"Orchard Cottage, Brighton Road Lewes East Sussex BN7 3JJ",
    "addr:postcode":"bn7 3jj",
    "addr:street":"Brighton Road",
    "iso:country":"GB",
    "sg:address":"Orchard Cottage, Brighton Road",
    "sg:city":"Lewes",
    "sg:classifiers":[
        {
            "category":"Health Services",
            "subcategory":"Hospital",
            "type":"Services"
        }
    ],
    "sg:phone":"+44 1273 554000",
    "sg:postcode":"BN7 3JJ",
    "sg:province":"East Sussex",
    "sg:tags":[
        "ambulance"
    ],
    "wof:name":"In-Pulse Medical Services",
    "wof:placetype":"venue"
},
  "geometry": {"coordinates":[0.0106199998,50.8732032776],"type":"Point"}
}