{
  "type": "Feature",
  "properties": {
    "addr:full":"94 Southover Street Brighton East Sussex BN2 9UD",
    "addr:postcode":"bn2 9ud",
    "addr:street":"Southover Street",
    "iso:country":"GB",
    "sg:address":"94 Southover Street",
    "sg:city":"Brighton",
    "sg:classifiers":[
        {
            "category":"Bars & Pubs",
            "type":"Food & Drink"
        }
    ],
    "sg:postcode":"BN2 9UD",
    "sg:province":"East Sussex",
    "sg:tags":[
        "pubs",
        "inn"
    ],
    "wof:name":"The Burlington",
    "wof:placetype":"venue"
},
  "geometry": {"coordinates":[-0.129448995,50.8285980225],"type":"Point"}
}