{
  "type": "Feature",
  "properties": {
    "addr:full":"106 High Street Barnstaple Devon EX31 1HP",
    "addr:housenumber":"106",
    "addr:postcode":"ex31 1hp",
    "addr:street":"High Street",
    "iso:country":"GB",
    "sg:address":"106 High Street",
    "sg:city":"Barnstaple",
    "sg:classifiers":[
        {
            "category":"Shopping",
            "subcategory":"Jewelry",
            "type":"Retail Goods"
        },
        {
            "category":"Shopping",
            "subcategory":"Comic Books",
            "type":"Retail Goods"
        }
    ],
    "sg:phone":"+44 1271 374504",
    "sg:postcode":"EX31 1HP",
    "sg:province":"Devon",
    "sg:tags":[
        "jeweller",
        "sale",
        "jewellery"
    ],
    "wof:name":"Mark Parkhouse",
    "wof:placetype":"venue"
},
  "geometry": {"coordinates":[-4.0589442253,51.0788574219],"type":"Point"}
}