{
  "type": "Feature",
  "properties": {
    "iso:country":"GB",
    "sg:address":"12b Venture Court, Ackworth Road",
    "sg:city":"Portsmouth",
    "sg:classifiers":[
        {
            "category":"Retail",
            "subcategory":"Auto Repair",
            "type":"Services"
        }
    ],
    "sg:phone":"+44 23 9266 4987",
    "sg:postcode":"PO3 5RY",
    "sg:province":"Hampshire",
    "sg:tags":[
        "body",
        "car"
    ],
    "wof:name":"S G Car Repairs",
    "wof:placetype":"venue"
},
  "geometry": {"coordinates":[-1.06153,50.832378],"type":"Point"}
}