{
  "type": "Feature",
  "properties": {
    "addr:full":"King George V Playing Field, Congresbury Bristol Somerset BS49 5DN",
    "addr:postcode":"bs49 5dn",
    "addr:street":"Playing Field",
    "iso:country":"GB",
    "sg:address":"King George V Playing Field, Congresbury",
    "sg:city":"Bristol",
    "sg:classifiers":[
        {
            "category":"Arena",
            "subcategory":"Sports Club",
            "type":"Entertainment"
        }
    ],
    "sg:phone":"+44 1934 832150",
    "sg:postcode":"BS49 5DN",
    "sg:province":"Somerset",
    "wof:name":"Congresbury Recreation Club",
    "wof:placetype":"venue"
},
  "geometry": {"coordinates":[-2.8069140911,51.3664665222],"type":"Point"}
}