{
  "type": "Feature",
  "properties": {
    "iso:country":"GB",
    "sg:address":"19 The Wyncies, Bishopstone",
    "sg:city":"Swindon",
    "sg:classifiers":[
        {
            "category":"Professional",
            "subcategory":"Accounting & Tax Preparation",
            "type":"Services"
        }
    ],
    "sg:postcode":"SN6 8PJ",
    "sg:province":"Gloucestershire",
    "sg:tags":[
        "accountant"
    ],
    "wof:name":"Oakleaf Book-Keeping & Business Services",
    "wof:placetype":"venue"
},
  "geometry": {"coordinates":[-1.6545590162,51.5992584229],"type":"Point"}
}