{
  "type": "Feature",
  "properties": {
    "addr:full":"17 Stramongate Kendal Cumbria LA9 4BN",
    "addr:housenumber":"17",
    "addr:postcode":"la9 4bn",
    "addr:street":"Stramongate Kendal",
    "iso:country":"GB",
    "sg:address":"17 Stramongate",
    "sg:city":"Kendal",
    "sg:classifiers":[
        {
            "category":"Home & Garden",
            "subcategory":"Furniture",
            "type":"Retail Goods"
        }
    ],
    "sg:phone":"+44 1539 735814",
    "sg:postcode":"LA9 4BN",
    "sg:province":"Cumbria",
    "wof:name":"Lancashire Pine Furniture Co.",
    "wof:placetype":"venue"
},
  "geometry": {"coordinates":[-2.7444870472,54.328250885],"type":"Point"}
}