{
  "type": "Feature",
  "properties": {
    "addr:full":"Wisteria Cottage, Aldworth Reading Berkshire RG8 9SB",
    "addr:postcode":"rg8 9sb",
    "iso:country":"GB",
    "sg:address":"Wisteria Cottage, Aldworth",
    "sg:city":"Reading",
    "sg:classifiers":[
        {
            "category":"Shopping",
            "subcategory":"Department Store",
            "type":"Retail Goods"
        }
    ],
    "sg:phone":"+44 1635 578254",
    "sg:postcode":"RG8 9SB",
    "sg:province":"Berkshire",
    "wof:name":"The Post Office Stores",
    "wof:placetype":"venue"
},
  "geometry": {"coordinates":[-1.2012,51.50959],"type":"Point"}
}