{
  "type": "Feature",
  "properties": {
    "addr:full":"Little Dean Yard, Old London Road Stockbridge Hampshire SO20 6EL",
    "addr:postcode":"so20 6el",
    "addr:street":"Old London Road",
    "iso:country":"GB",
    "sg:address":"Little Dean Yard, Old London Road",
    "sg:city":"Stockbridge",
    "sg:classifiers":[
        {
            "category":"Retail",
            "subcategory":"Auto Repair",
            "type":"Services"
        }
    ],
    "sg:phone":"+44 1264 810080",
    "sg:postcode":"SO20 6EL",
    "sg:province":"Hampshire",
    "sg:tags":[
        "car",
        "upholsterer"
    ],
    "wof:name":"Southbound Motor Trimmers",
    "wof:placetype":"venue"
},
  "geometry": {"coordinates":[-1.48442,51.117062],"type":"Point"}
}