{
  "type": "Feature",
  "properties": {
    "addr:full":"2 Hook Road Surbiton Surrey KT6 5BH",
    "addr:housenumber":"2",
    "addr:postcode":"kt6 5bh",
    "addr:street":"Hook Road",
    "iso:country":"GB",
    "sg:address":"2 Hook Road",
    "sg:city":"Surbiton",
    "sg:classifiers":[
        {
            "category":"Bars & Pubs",
            "type":"Food & Drink"
        }
    ],
    "sg:phone":"+44 20 8399 2906",
    "sg:postcode":"KT6 5BH",
    "sg:province":"Surrey",
    "sg:tags":[
        "pubs",
        "inn"
    ],
    "wof:name":"The Maypole",
    "wof:placetype":"venue"
},
  "geometry": {"coordinates":[-0.300907,51.382694],"type":"Point"}
}