{
  "type": "Feature",
  "properties": {
    "addr:full":"Unit 13 Canterbury Industrial Park, 297 Ilderton Road London Greater London SE15 1NP",
    "addr:housenumber":"unit 13;297",
    "addr:postcode":"se15 1np",
    "addr:street":"Canterbury Industrial Park;Ilderton Road",
    "iso:country":"GB",
    "sg:address":"Unit 13 Canterbury Industrial Park, 297 Ilderton Road",
    "sg:city":"London",
    "sg:classifiers":[
        {
            "category":"Retail",
            "subcategory":"Repair Shop",
            "type":"Services"
        }
    ],
    "sg:postcode":"SE15 1NP",
    "sg:province":"Greater London",
    "sg:tags":[
        "upholsterer"
    ],
    "wof:name":"William Munnoch Ltd.",
    "wof:placetype":"venue"
},
  "geometry": {"coordinates":[-0.05349,51.481377],"type":"Point"}
}