{
  "type": "Feature",
  "properties": {
    "iso:country":"GB",
    "sg:address":"102 Crown St",
    "sg:city":"Aberdeen",
    "sg:classifiers":[
        {
            "category":"Professional",
            "subcategory":"Business Services",
            "type":"Services"
        }
    ],
    "sg:phone":"+44 1224 571847",
    "sg:postcode":"AB11 6HJ",
    "sg:province":"Aberdeen City",
    "sg:tags":[
        "trade"
    ],
    "wof:name":"Royal College of Nursing of the United K",
    "wof:placetype":"venue"
},
  "geometry": {"coordinates":[-2.102175,57.142948],"type":"Point"}
}