{
  "type": "Feature",
  "properties": {
    "addr:full":"Glebelands, Middle Road Shoreham-by-sea West Sussex BN43 6GA",
    "addr:postcode":"bn43 6ga",
    "addr:street":"Middle Road",
    "iso:country":"GB",
    "sg:address":"Glebelands, Middle Road",
    "sg:city":"Shoreham-by-sea",
    "sg:classifiers":[
        {
            "category":"Social Services",
            "type":"Services"
        }
    ],
    "sg:phone":"+44 1273 463551",
    "sg:postcode":"BN43 6GA",
    "sg:province":"West Sussex",
    "wof:name":"Shoreham Social Services",
    "wof:placetype":"venue"
},
  "geometry": {"coordinates":[-0.260089,50.836979],"type":"Point"}
}