{
  "type": "Feature",
  "properties": {
    "addr:full":"Unit 1 Station Indstl Est, Skipton Rd, Earby Barnoldswick Lancashire BB18 6PX",
    "addr:housenumber":"unit 1",
    "addr:postcode":"bb18 6px",
    "addr:street":"Indstl Est Skipton Rd",
    "iso:country":"GB",
    "sg:address":"Unit 1 Station Indstl Est, Skipton Rd, Earby",
    "sg:city":"Barnoldswick",
    "sg:classifiers":[
        {
            "category":"Shopping",
            "subcategory":"Clothing, Apparel, & Fashions",
            "type":"Retail Goods"
        }
    ],
    "sg:postcode":"BB18 6PX",
    "sg:province":"Lancashire",
    "sg:tags":[
        "clothing"
    ],
    "wof:name":"Red Stripe Jean Co Ltd",
    "wof:placetype":"venue"
},
  "geometry": {"coordinates":[-2.146198988,53.9144859314],"type":"Point"}
}