{
  "type": "Feature",
  "properties": {
    "addr:full":"The Glen House, Crossways Road, Grayshott Hindhead Hampshire GU26 6HG",
    "addr:postcode":"gu26 6hg",
    "addr:street":"Crossways Road",
    "iso:country":"GB",
    "sg:address":"The Glen House, Crossways Road, Grayshott",
    "sg:city":"Hindhead",
    "sg:classifiers":[
        {
            "category":"Professional",
            "subcategory":"Printing & Photocopies",
            "type":"Services"
        }
    ],
    "sg:phone":"+44 1428 606789",
    "sg:postcode":"GU26 6HG",
    "sg:province":"Hampshire",
    "sg:tags":[
        "duplicating",
        "copying"
    ],
    "wof:name":"Business Connections",
    "wof:placetype":"venue"
},
  "geometry": {"coordinates":[-0.7531679869,51.1218795776],"type":"Point"}
}