{
  "type": "Feature",
  "properties": {
    "iso:country":"GB",
    "sg:address":"37 Hill Lane, Barnham",
    "sg:city":"Bognor Regis",
    "sg:classifiers":[
        {
            "category":"Shopping",
            "subcategory":"Florist",
            "type":"Retail Goods"
        }
    ],
    "sg:postcode":"PO22 0BL",
    "sg:province":"West Sussex",
    "wof:name":"Country Fresh Flowers & Plants Ltd.",
    "wof:placetype":"venue"
},
  "geometry": {"coordinates":[-0.6387060285,50.8251533508],"type":"Point"}
}