{
  "type": "Feature",
  "properties": {
    "addr:full":"Victoria Street Goole East Riding of Yorkshire DN14 5DZ",
    "addr:postcode":"dn14 5dz",
    "addr:street":"Victoria Street",
    "iso:country":"GB",
    "sg:address":"Victoria Street",
    "sg:city":"Goole",
    "sg:classifiers":[
        {
            "category":"Organizations",
            "subcategory":"Membership Organization",
            "type":"Services"
        }
    ],
    "sg:phone":"+44 1405 763947",
    "sg:postcode":"DN14 5DZ",
    "sg:province":"East Riding of Yorkshire",
    "sg:tags":[
        "club"
    ],
    "wof:name":"Goole Working Mens Club",
    "wof:placetype":"venue"
},
  "geometry": {"coordinates":[-0.869393,53.703568],"type":"Point"}
}