{
  "type": "Feature",
  "properties": {
    "iso:country":"GB",
    "sg:address":"Hamble Court, Hamble Lane, Hamble",
    "sg:city":"Southampton",
    "sg:classifiers":[
        {
            "category":"Professional",
            "type":"Services"
        }
    ],
    "sg:phone":"+44 23 8045 4184",
    "sg:postcode":"SO31 4HX",
    "sg:province":"Hampshire",
    "sg:tags":[
        "marine"
    ],
    "wof:name":"Viking Life-Saving Equipment Ltd.",
    "wof:placetype":"venue"
},
  "geometry": {"coordinates":[-1.328794,50.863125],"type":"Point"}
}