{
  "type": "Feature",
  "properties": {
    "iso:country":"GB",
    "sg:address":"45 Alexandra Road",
    "sg:city":"Epsom",
    "sg:classifiers":[
        {
            "category":"Travel",
            "subcategory":"Hotels & Motels",
            "type":"Entertainment"
        }
    ],
    "sg:phone":"+44 1372 728308",
    "sg:postcode":"KT17 4DB",
    "sg:province":"Surrey",
    "sg:tags":[
        "house",
        "guest"
    ],
    "wof:name":"Swallowfield Guest House",
    "wof:placetype":"venue"
},
  "geometry": {"coordinates":[-0.2499540001,51.3304748535],"type":"Point"}
}