{
  "type": "Feature",
  "properties": {
    "addr:full":"1-4 The High Pde, Streatham High Rd Streatham Greater London SW16 1EX",
    "addr:housenumber":"1-4",
    "addr:postcode":"sw16 1ex",
    "addr:street":"The High Pde;High Rd",
    "iso:country":"GB",
    "sg:address":"1-4 The High Pde, Streatham High Rd",
    "sg:city":"Streatham",
    "sg:classifiers":[
        {
            "category":"Health Services",
            "subcategory":"Doctor",
            "type":"Services"
        }
    ],
    "sg:phone":"+44 20 8677 9282",
    "sg:postcode":"SW16 1EX",
    "sg:province":"Greater London",
    "sg:tags":[
        "practitioners"
    ],
    "wof:name":"Ashby, P M",
    "wof:placetype":"venue"
},
  "geometry": {"coordinates":[-0.1282500029,51.4342498779],"type":"Point"}
}