{
  "type": "Feature",
  "properties": {
    "iso:country":"GB",
    "sg:address":"28 Bowness Road",
    "sg:city":"Barrow-in-furness",
    "sg:classifiers":[
        {
            "category":"Professional",
            "subcategory":"Engineering",
            "type":"Services"
        }
    ],
    "sg:phone":"+44 1229 831897",
    "sg:postcode":"LA14 5PW",
    "sg:province":"Cumbria",
    "sg:tags":[
        "contractor",
        "electrical",
        "engineer"
    ],
    "wof:name":"Alan Quinn",
    "wof:placetype":"venue"
},
  "geometry": {"coordinates":[-3.2155709267,54.1283226013],"type":"Point"}
}