{
  "type": "Feature",
  "properties": {
    "iso:country":"GB",
    "sg:address":"17 Shotts Street",
    "sg:city":"Glasgow",
    "sg:classifiers":[
        {
            "category":"Home & Garden",
            "subcategory":"Kitchen Supply",
            "type":"Retail Goods"
        }
    ],
    "sg:phone":"+44 141 774 3456",
    "sg:postcode":"G33 4JB",
    "sg:province":"Glasgow City",
    "sg:tags":[
        "equipment",
        "catering"
    ],
    "wof:name":"The Hobart Manufacturing Co.",
    "wof:placetype":"venue"
},
  "geometry": {"coordinates":[-4.146821022,55.8645515442],"type":"Point"}
}