{
  "type": "Feature",
  "properties": {
    "addr:full":"61 Charles Street, Cheadle Stoke-on-trent Staffordshire ST10 1EE",
    "addr:housenumber":"61",
    "addr:postcode":"st10 1ee",
    "addr:street":"Charles Street Cheadle",
    "iso:country":"GB",
    "sg:address":"61 Charles Street, Cheadle",
    "sg:city":"Stoke-on-trent",
    "sg:classifiers":[
        {
            "category":"Social Services",
            "subcategory":"Adult Care",
            "type":"Services"
        }
    ],
    "sg:phone":"+44 1538 757158",
    "sg:postcode":"ST10 1EE",
    "sg:province":"Staffordshire",
    "sg:tags":[
        "day",
        "centre"
    ],
    "wof:name":"Cheadle Day Centre",
    "wof:placetype":"venue"
},
  "geometry": {"coordinates":[-1.9872339964,52.9883117676],"type":"Point"}
}