{
  "type": "Feature",
  "properties": {
    "addr:full":"271a Lytham Rd Blackpool Lancashire FY4 1DP",
    "addr:housenumber":"271a",
    "addr:postcode":"fy4 1dp",
    "addr:street":"Lytham Rd",
    "iso:country":"GB",
    "sg:address":"271a Lytham Rd",
    "sg:city":"Blackpool",
    "sg:classifiers":[
        {
            "category":"Health Services",
            "subcategory":"Dentist",
            "type":"Services"
        }
    ],
    "sg:phone":"+44 1253 407085",
    "sg:postcode":"FY4 1DP",
    "sg:province":"Lancashire",
    "sg:tags":[
        "technician",
        "dental"
    ],
    "wof:name":"Colin Taylor",
    "wof:placetype":"venue"
},
  "geometry": {"coordinates":[-3.050770998,53.7985877991],"type":"Point"}
}