{
  "type": "Feature",
  "properties": {
    "addr:full":"181 Ashburnham Road Richmond Greater London TW10 7NR",
    "addr:housenumber":"181",
    "addr:postcode":"tw10 7nr",
    "addr:street":"Ashburnham Road",
    "iso:country":"GB",
    "sg:address":"181 Ashburnham Road",
    "sg:city":"Richmond",
    "sg:classifiers":[
        {
            "category":"Food & Beverages",
            "subcategory":"Meat & Fish",
            "type":"Retail Goods"
        }
    ],
    "sg:postcode":"TW10 7NR",
    "sg:province":"Greater London",
    "sg:tags":[
        "butcher"
    ],
    "wof:name":"Johns Butchers",
    "wof:placetype":"venue"
},
  "geometry": {"coordinates":[-0.320044,51.436733],"type":"Point"}
}