{
  "type": "Feature",
  "properties": {
    "addr:full":"1 St Thomas Street London Greater London SE1 9RY",
    "addr:housenumber":"1",
    "addr:postcode":"se1 9ry",
    "addr:street":"St Thomas Street",
    "iso:country":"GB",
    "sg:address":"1 St Thomas Street",
    "sg:city":"London",
    "sg:classifiers":[
        {
            "category":"Professional",
            "subcategory":"Computer Services",
            "type":"Services"
        }
    ],
    "sg:phone":"+44 20 7234 3000",
    "sg:postcode":"SE1 9RY",
    "sg:province":"Greater London",
    "sg:tags":[
        "system",
        "software"
    ],
    "wof:name":"Copitrak Systems U K Ltd.",
    "wof:placetype":"venue"
},
  "geometry": {"coordinates":[-0.089167,51.505245],"type":"Point"}
}