{
  "type": "Feature",
  "properties": {
    "iso:country":"GB",
    "sg:address":"The Vines, Southsea Avenue, Minster On Sea",
    "sg:city":"Sheerness",
    "sg:classifiers":[
        {
            "category":"Shopping",
            "subcategory":"Discount & Variety Stores",
            "type":"Retail Goods"
        }
    ],
    "sg:postcode":"ME12 2NH",
    "sg:province":"Kent",
    "sg:tags":[
        "cleaning",
        "supply"
    ],
    "wof:name":"Ha-Ra Daniels U K  Ltd.",
    "wof:placetype":"venue"
},
  "geometry": {"coordinates":[0.764665,51.43885],"type":"Point"}
}