{
  "type": "Feature",
  "properties": {
    "addr:full":"59b Grove Road, Strood Rochester Kent ME2 4BY",
    "addr:housenumber":"59b",
    "addr:postcode":"me2 4by",
    "addr:street":"Grove Road",
    "iso:country":"GB",
    "sg:address":"59b Grove Road, Strood",
    "sg:city":"Rochester",
    "sg:classifiers":[
        {
            "category":"Manufacturing",
            "subcategory":"Building Materials",
            "type":"Manufacturing & Wholesale Goods"
        }
    ],
    "sg:phone":"+44 1634 713001",
    "sg:postcode":"ME2 4BY",
    "sg:province":"Kent",
    "sg:tags":[
        "merchant",
        "builder"
    ],
    "wof:name":"Pattendens Ltd",
    "wof:placetype":"venue"
},
  "geometry": {"coordinates":[0.49955,51.39764],"type":"Point"}
}