{
  "type": "Feature",
  "properties": {
    "addr:full":"Chudleigh Woods, Chudleigh Newton Abbot Devon TQ13 0NE",
    "addr:postcode":"tq13 0ne",
    "addr:street":"Chudleigh Woods Chudleigh",
    "iso:country":"GB",
    "sg:address":"Chudleigh Woods, Chudleigh",
    "sg:city":"Newton Abbot",
    "sg:classifiers":[
        {
            "category":"Farming",
            "subcategory":"Livestock Farm",
            "type":"Manufacturing & Wholesale Goods"
        }
    ],
    "sg:phone":"+44 1626 852169",
    "sg:postcode":"TQ13 0NE",
    "sg:province":"Devon",
    "sg:tags":[
        "others"
    ],
    "wof:name":"C W & H M Stanyon",
    "wof:placetype":"venue"
},
  "geometry": {"coordinates":[-3.601601,50.604229],"type":"Point"}
}