{
  "type": "Feature",
  "properties": {
    "iso:country":"GB",
    "sg:address":"Lyons Lane Mills",
    "sg:city":"Chorley",
    "sg:classifiers":[
        {
            "category":"Shopping",
            "subcategory":"Crafts & Fabrics",
            "type":"Retail Goods"
        }
    ],
    "sg:phone":"+44 1257 262294",
    "sg:postcode":"PR6 0PJ",
    "sg:province":"Lancashire",
    "sg:tags":[
        "yarn",
        "supply"
    ],
    "wof:name":"W M Lawrence & Sons Ltd.",
    "wof:placetype":"venue"
},
  "geometry": {"coordinates":[-2.618282,53.65237],"type":"Point"}
}