{
  "type": "Feature",
  "properties": {
    "addr:full":"24 Brewery Street Dumfries Dumfries and Galloway DG1 2RP",
    "addr:housenumber":"24",
    "addr:postcode":"dg1 2rp",
    "addr:street":"Brewery Street",
    "iso:country":"GB",
    "sg:address":"24 Brewery Street",
    "sg:city":"Dumfries",
    "sg:classifiers":[
        {
            "category":"Cafe",
            "type":"Food & Drink"
        }
    ],
    "sg:phone":"+44 1387 268203",
    "sg:postcode":"DG1 2RP",
    "sg:province":"Dumfries and Galloway",
    "sg:tags":[
        "tea",
        "room"
    ],
    "wof:name":"Puffins Cafe",
    "wof:placetype":"venue"
},
  "geometry": {"coordinates":[-3.6152129173,55.0688667297],"type":"Point"}
}