{
  "type": "Feature",
  "properties": {
    "addr:full":"Unit 2a Palmerston Road Barry The Vale of Glamorgan CF63 2NR",
    "addr:housenumber":"unit 2a",
    "addr:postcode":"cf63 2nr",
    "addr:street":"Palmerston Road;Vale",
    "iso:country":"GB",
    "sg:address":"Unit 2a Palmerston Road",
    "sg:city":"Barry",
    "sg:classifiers":[
        {
            "category":"Professional",
            "type":"Services"
        }
    ],
    "sg:phone":"+44 1446 733288",
    "sg:postcode":"CF63 2NR",
    "sg:province":"The Vale of Glamorgan",
    "sg:tags":[
        "services",
        "belt",
        "conveyor"
    ],
    "wof:name":"Ace Conveyor Equipment Ltd.",
    "wof:placetype":"venue"
},
  "geometry": {"coordinates":[-3.241604,51.412125],"type":"Point"}
}