{
  "type": "Feature",
  "properties": {
    "iso:country":"GB",
    "sg:address":"Unit 1, Penallta Industrial Estate",
    "sg:city":"Hengoed",
    "sg:classifiers":[
        {
            "category":"Home & Garden",
            "subcategory":"Hardware",
            "type":"Retail Goods"
        }
    ],
    "sg:phone":"+44 1443 815313",
    "sg:postcode":"CF82 7QZ",
    "sg:province":"Caerphilly",
    "sg:tags":[
        "device",
        "fixing",
        "fastener"
    ],
    "wof:name":"Talbot-Owen Tool & Fastener",
    "wof:placetype":"venue"
},
  "geometry": {"coordinates":[-3.240043,51.648979],"type":"Point"}
}