{
  "type": "Feature",
  "properties": {
    "iso:country":"GB",
    "sg:address":"1 Ladyburn Street",
    "sg:city":"Paisley",
    "sg:classifiers":[
        {
            "category":"Shopping",
            "subcategory":"News",
            "type":"Retail Goods"
        }
    ],
    "sg:postcode":"PA1 1PH",
    "sg:province":"Renfrewshire",
    "sg:tags":[
        "newsagent"
    ],
    "wof:name":"D C Faulds & Son",
    "wof:placetype":"venue"
},
  "geometry": {"coordinates":[-4.411792,55.844135],"type":"Point"}
}