{
  "type": "Feature",
  "properties": {
    "addr:full":"Social Services Emergency Out Of Hours, Woodborough Rd Nottingham Nottinghamshire NG3 5GX",
    "addr:postcode":"ng3 5gx",
    "addr:street":"Woodborough Rd",
    "iso:country":"GB",
    "sg:address":"Social Services Emergency Out Of Hours, Woodborough Rd",
    "sg:city":"Nottingham",
    "sg:classifiers":[
        {
            "category":"Government",
            "subcategory":"Office",
            "type":"Public Place"
        }
    ],
    "sg:phone":"+44 115 962 2226",
    "sg:postcode":"NG3 5GX",
    "sg:province":"Nottinghamshire",
    "sg:tags":[
        "local"
    ],
    "wof:name":"Nottinghamshire County Council",
    "wof:placetype":"venue"
},
  "geometry": {"coordinates":[-1.1382199526,52.9742698669],"type":"Point"}
}