{
  "type": "Feature",
  "properties": {
    "addr:full":"Ferdre Fawr Farm Llandovery Carmarthenshire SA20 0RU",
    "addr:housenumber":"llandovery",
    "addr:postcode":"sa20 0ru",
    "addr:street":"Carmarthenshire",
    "iso:country":"GB",
    "sg:address":"Ferdre Fawr Farm",
    "sg:city":"Llandovery",
    "sg:classifiers":[
        {
            "category":"Farming",
            "subcategory":"Livestock Farm",
            "type":"Manufacturing & Wholesale Goods"
        }
    ],
    "sg:postcode":"SA20 0RU",
    "sg:province":"Carmarthenshire",
    "sg:tags":[
        "others"
    ],
    "wof:name":"I Morgan",
    "wof:placetype":"venue"
},
  "geometry": {"coordinates":[-3.800155,51.994087],"type":"Point"}
}