{
  "type": "Feature",
  "properties": {
    "addr:full":"66 Moss Lane, Churchtown Southport Lancashire PR9 7QS",
    "addr:housenumber":"66",
    "addr:postcode":"pr9 7qs",
    "addr:street":"Moss Lane",
    "iso:country":"GB",
    "sg:address":"66 Moss Lane, Churchtown",
    "sg:city":"Southport",
    "sg:classifiers":[
        {
            "category":"Building & Trades",
            "subcategory":"Construction",
            "type":"Services"
        }
    ],
    "sg:phone":"+44 1704 229456",
    "sg:postcode":"PR9 7QS",
    "sg:province":"Lancashire",
    "sg:tags":[
        "builder"
    ],
    "wof:name":"Gus Miller & Son",
    "wof:placetype":"venue"
},
  "geometry": {"coordinates":[-2.953736,53.652973],"type":"Point"}
}