{
  "type": "Feature",
  "properties": {
    "addr:full":"32 Poulton Road Blackpool Lancashire FY3 7DT",
    "addr:housenumber":"32",
    "addr:postcode":"fy3 7dt",
    "addr:street":"Poulton Road",
    "iso:country":"GB",
    "sg:address":"32 Poulton Road",
    "sg:city":"Blackpool",
    "sg:classifiers":[
        {
            "category":"Professional",
            "subcategory":"Business Services",
            "type":"Services"
        }
    ],
    "sg:phone":"+44 1253 301201",
    "sg:postcode":"FY3 7DT",
    "sg:province":"Lancashire",
    "sg:tags":[
        "import",
        "export",
        "agent"
    ],
    "wof:name":"Eurocar Direct (U K) Ltd.",
    "wof:placetype":"venue"
},
  "geometry": {"coordinates":[-3.028225,53.832954],"type":"Point"}
}