{
  "type": "Feature",
  "properties": {
    "iso:country":"GB",
    "sg:address":"Sigma House, 51 Peach Street",
    "sg:city":"Wokingham",
    "sg:classifiers":[
        {
            "category":"Professional",
            "subcategory":"Employment Agencies",
            "type":"Services"
        }
    ],
    "sg:postcode":"RG40 1XP",
    "sg:province":"Berkshire",
    "sg:tags":[
        "career",
        "guidance"
    ],
    "wof:name":"Stephen Marshall",
    "wof:placetype":"venue"
},
  "geometry": {"coordinates":[-0.830369,51.411037],"type":"Point"}
}