{
  "type": "Feature",
  "properties": {
    "addr:full":"Prospect Works, Clive Road Redditch Warwickshire B97 4BX",
    "addr:postcode":"b97 4bx",
    "addr:street":"Clive Road",
    "iso:country":"GB",
    "sg:address":"Prospect Works, Clive Road",
    "sg:city":"Redditch",
    "sg:classifiers":[
        {
            "category":"Wholesale",
            "subcategory":"Construction Materials",
            "type":"Manufacturing & Wholesale Goods"
        }
    ],
    "sg:postcode":"B97 4BX",
    "sg:province":"Warwickshire",
    "sg:tags":[
        "distributor",
        "spring"
    ],
    "wof:name":"Prospect Redditch Ltd.",
    "wof:placetype":"venue"
},
  "geometry": {"coordinates":[-1.941267,52.30727],"type":"Point"}
}