{
  "type": "Feature",
  "properties": {
    "addr:full":"21 The Hedgerow, Grove Grn Maidstone Kent ME14 5TG",
    "addr:housenumber":"21",
    "addr:postcode":"me14 5tg",
    "addr:street":"The Hedgerow Grove Grn",
    "iso:country":"GB",
    "sg:address":"21 The Hedgerow, Grove Grn",
    "sg:city":"Maidstone",
    "sg:classifiers":[
        {
            "category":"Building & Trades",
            "subcategory":"Plumbing",
            "type":"Services"
        }
    ],
    "sg:phone":"+44 1622 734018",
    "sg:postcode":"ME14 5TG",
    "sg:province":"Kent",
    "sg:tags":[
        "heating"
    ],
    "wof:name":"Paul Roberts Plumbing & Heating",
    "wof:placetype":"venue"
},
  "geometry": {"coordinates":[0.5572460294,51.278175354],"type":"Point"}
}