{
  "type": "Feature",
  "properties": {
    "addr:full":"H.q.s Wellington, Temple Stairs London Greater London WC2R 2PN",
    "addr:postcode":"wc2r 2pn",
    "addr:street":"Stairs",
    "iso:country":"GB",
    "sg:address":"H.q.s Wellington, Temple Stairs",
    "sg:city":"London",
    "sg:classifiers":[
        {
            "category":"Professional",
            "type":"Services"
        }
    ],
    "sg:postcode":"WC2R 2PN",
    "sg:province":"Greater London",
    "sg:tags":[
        "marine"
    ],
    "wof:name":"Specifications & Surveys Ltd",
    "wof:placetype":"venue"
},
  "geometry": {"coordinates":[-0.1119,51.510761],"type":"Point"}
}