{
  "type": "Feature",
  "properties": {
    "iso:country":"GB",
    "sg:address":"30 York Street",
    "sg:city":"Blackpool",
    "sg:classifiers":[
        {
            "category":"Travel",
            "subcategory":"Hotels & Motels",
            "type":"Entertainment"
        }
    ],
    "sg:phone":"+44 1253 620421",
    "sg:postcode":"FY1 5AQ",
    "sg:province":"Lancashire",
    "sg:tags":[
        "house",
        "guest"
    ],
    "wof:name":"Aysgarth House",
    "wof:placetype":"venue"
},
  "geometry": {"coordinates":[-3.052575,53.810848],"type":"Point"}
}