{
  "type": "Feature",
  "properties": {
    "iso:country":"GB",
    "sg:address":"An Aird",
    "sg:city":"Fort William",
    "sg:classifiers":[
        {
            "category":"Building & Trades",
            "subcategory":"Construction",
            "type":"Services"
        }
    ],
    "sg:postcode":"PH33 6AN",
    "sg:province":"Highland",
    "sg:tags":[
        "builder"
    ],
    "wof:name":"Morrison Construction Ltd",
    "wof:placetype":"venue"
},
  "geometry": {"coordinates":[-5.1084589958,56.8184318542],"type":"Point"}
}