{
  "type": "Feature",
  "properties": {
    "addr:full":"59 Prospect Avenue, Strood Rochester Kent ME2 3BZ",
    "addr:housenumber":"59",
    "addr:postcode":"me2 3bz",
    "addr:street":"Prospect Avenue",
    "iso:country":"GB",
    "sg:address":"59 Prospect Avenue, Strood",
    "sg:city":"Rochester",
    "sg:classifiers":[
        {
            "category":"Building & Trades",
            "subcategory":"Construction",
            "type":"Services"
        }
    ],
    "sg:phone":"+44 1634 715954",
    "sg:postcode":"ME2 3BZ",
    "sg:province":"Kent",
    "sg:tags":[
        "platform",
        "work",
        "scaffolding"
    ],
    "wof:name":"T.J Franks",
    "wof:placetype":"venue"
},
  "geometry": {"coordinates":[0.4991999865,51.4023513794],"type":"Point"}
}