{
  "type": "Feature",
  "properties": {
    "iso:country":"GB",
    "sg:address":"856 Woodborough Road, Mapperley",
    "sg:city":"Nottingham",
    "sg:classifiers":[
        {
            "category":"Health Services",
            "subcategory":"Health Practitioner",
            "type":"Services"
        }
    ],
    "sg:phone":"+44 115 960 6408",
    "sg:postcode":"NG3 5QQ",
    "sg:province":"Nottinghamshire",
    "sg:tags":[
        "physiotherapist"
    ],
    "wof:name":"Plains Physiotherapy Clinic",
    "wof:placetype":"venue"
},
  "geometry": {"coordinates":[-1.124245,52.98233],"type":"Point"}
}