{
  "type": "Feature",
  "properties": {
    "iso:country":"GB",
    "sg:address":"Paterson Rd, Finedon Road Indust Est",
    "sg:city":"Wellingborough",
    "sg:classifiers":[
        {
            "category":"Utilities",
            "subcategory":"Refuse",
            "type":"Services"
        }
    ],
    "sg:phone":"+44 1933 277833",
    "sg:postcode":"NN8 4BZ",
    "sg:province":"Northamptonshire",
    "sg:tags":[
        "skip",
        "hire"
    ],
    "wof:name":"Turners",
    "wof:placetype":"venue"
},
  "geometry": {"coordinates":[-0.682044,52.32196],"type":"Point"}
}