{
  "type": "Feature",
  "properties": {
    "addr:full":"23 Rectory Rd Nottingham Nottinghamshire NG2 6BE",
    "addr:housenumber":"23",
    "addr:postcode":"ng2 6be",
    "addr:street":"Rectory Rd",
    "iso:country":"GB",
    "sg:address":"23 Rectory Rd",
    "sg:city":"Nottingham",
    "sg:classifiers":[
        {
            "category":"Shopping",
            "subcategory":"Hobbies, Toys, & Games",
            "type":"Retail Goods"
        }
    ],
    "sg:phone":"+44 115 982 6152",
    "sg:postcode":"NG2 6BE",
    "sg:province":"Nottinghamshire",
    "sg:tags":[
        "stamp"
    ],
    "wof:name":"Robinhood Stamp Co",
    "wof:placetype":"venue"
},
  "geometry": {"coordinates":[-1.1295950413,52.9300346375],"type":"Point"}
}