{
  "type": "Feature",
  "properties": {
    "iso:country":"GB",
    "sg:address":"12 Dundas Street",
    "sg:city":"Saltburn-by-the-sea",
    "sg:classifiers":[
        {
            "category":"Shopping",
            "subcategory":"Clothing, Apparel, & Fashions",
            "type":"Retail Goods"
        }
    ],
    "sg:phone":"+44 1287 623754",
    "sg:postcode":"TS12 1AH",
    "sg:province":"North Yorkshire",
    "sg:tags":[
        "menswear"
    ],
    "wof:name":"David V Townend",
    "wof:placetype":"venue"
},
  "geometry": {"coordinates":[-0.974189,54.582371],"type":"Point"}
}