{
  "type": "Feature",
  "properties": {
    "addr:full":"The Hertford Chiropractic Clinic, 5 Port Hill Hertford Hertfordshire SG14 1PJ",
    "addr:housenumber":"5",
    "addr:postcode":"sg14 1pj",
    "iso:country":"GB",
    "sg:address":"The Hertford Chiropractic Clinic, 5 Port Hill",
    "sg:city":"Hertford",
    "sg:classifiers":[
        {
            "category":"Health Services",
            "subcategory":"Chiropractor",
            "type":"Services"
        }
    ],
    "sg:phone":"+44 1992 501659",
    "sg:postcode":"SG14 1PJ",
    "sg:province":"Hertfordshire",
    "wof:name":"Atherton Ann Louise",
    "wof:placetype":"venue"
},
  "geometry": {"coordinates":[-0.082699,51.796341],"type":"Point"}
}