{
  "type": "Feature",
  "properties": {
    "addr:full":"92 Botanic Road Southport Lancashire PR9 7NE",
    "addr:housenumber":"92",
    "addr:postcode":"pr9 7ne",
    "addr:street":"Botanic Road",
    "iso:country":"GB",
    "sg:address":"92 Botanic Road",
    "sg:city":"Southport",
    "sg:classifiers":[
        {
            "category":"Shopping",
            "subcategory":"News",
            "type":"Retail Goods"
        }
    ],
    "sg:phone":"+44 1704 226807",
    "sg:postcode":"PR9 7NE",
    "sg:province":"Lancashire",
    "sg:tags":[
        "newsagent"
    ],
    "wof:name":"The Village Newsagent",
    "wof:placetype":"venue"
},
  "geometry": {"coordinates":[-2.962487936,53.659576416],"type":"Point"}
}