{
  "type": "Feature",
  "properties": {
    "iso:country":"GB",
    "sg:address":"10 Hillway",
    "sg:city":"Highgate",
    "sg:classifiers":[
        {
            "category":"Professional",
            "type":"Services"
        },
        {
            "category":"Professional",
            "subcategory":"Business Services",
            "type":"Services"
        }
    ],
    "sg:phone":"+44 20 8348 7370",
    "sg:postcode":"N6 6QA",
    "sg:province":"Greater London",
    "sg:tags":[
        "interior",
        "furnishers",
        "designer",
        "refurbishment"
    ],
    "wof:name":"Anne Jordan",
    "wof:placetype":"venue"
},
  "geometry": {"coordinates":[-0.1489039958,51.5630226135],"type":"Point"}
}