{
  "type": "Feature",
  "properties": {
    "iso:country":"GB",
    "sg:address":"50 Newton St",
    "sg:city":"Manchester",
    "sg:classifiers":[
        {
            "category":"Utilities",
            "subcategory":"Water",
            "type":"Services"
        }
    ],
    "sg:phone":"+44 161 439 0111",
    "sg:postcode":"M1 2EA",
    "sg:province":"Greater Manchester",
    "wof:name":"K M A Uk Ltd",
    "wof:placetype":"venue"
},
  "geometry": {"coordinates":[-2.232693,53.481827],"type":"Point"}
}