{
  "type": "Feature",
  "properties": {
    "addr:full":"2 Stamford Street Bradford West Yorkshire BD4 8SD",
    "addr:housenumber":"2",
    "addr:postcode":"bd4 8sd",
    "addr:street":"Stamford Street",
    "iso:country":"GB",
    "sg:address":"2 Stamford Street",
    "sg:city":"Bradford",
    "sg:classifiers":[
        {
            "category":"Fast Food",
            "type":"Food & Drink"
        },
        {
            "category":"Cafe",
            "type":"Food & Drink"
        }
    ],
    "sg:postcode":"BD4 8SD",
    "sg:province":"West Yorkshire",
    "sg:tags":[
        "room",
        "tea",
        "away",
        "outlet",
        "meal",
        "take"
    ],
    "wof:name":"Scoffers Paradise",
    "wof:placetype":"venue"
},
  "geometry": {"coordinates":[-1.7353049517,53.786857605],"type":"Point"}
}