{
  "type": "Feature",
  "properties": {
    "iso:country":"GB",
    "sg:address":"9 Bridge Terrace, Shiremoor",
    "sg:city":"Newcastle-upon-tyne",
    "sg:classifiers":[
        {
            "category":"Farming",
            "subcategory":"Nursery",
            "type":"Manufacturing & Wholesale Goods"
        },
        {
            "category":"Social Services",
            "subcategory":"Child Care",
            "type":"Services"
        }
    ],
    "sg:phone":"+44 191 200 7905",
    "sg:postcode":"NE27 0TA",
    "sg:province":"Northumberland",
    "sg:tags":[
        "creche"
    ],
    "wof:name":"Childcare Shiremoor",
    "wof:placetype":"venue"
},
  "geometry": {"coordinates":[-1.5049120188,55.0377159119],"type":"Point"}
}