{
  "type": "Feature",
  "properties": {
    "iso:country":"GB",
    "sg:address":"5-9 Dalmarnock Road, Rutherglen",
    "sg:city":"Glasgow",
    "sg:classifiers":[
        {
            "category":"Shopping",
            "subcategory":"Pharmacy",
            "type":"Retail Goods"
        }
    ],
    "sg:phone":"+44 141 647 2244",
    "sg:postcode":"G73 1NY",
    "sg:province":"Glasgow City",
    "sg:tags":[
        "toiletry"
    ],
    "wof:name":"Sanmex Holdings Plc",
    "wof:placetype":"venue"
},
  "geometry": {"coordinates":[-4.208809,55.835873],"type":"Point"}
}