{
  "type": "Feature",
  "properties": {
    "iso:country":"GB",
    "sg:address":"51 The Bdwy",
    "sg:city":"Loughton",
    "sg:classifiers":[
        {
            "category":"Shopping",
            "subcategory":"Florist",
            "type":"Retail Goods"
        }
    ],
    "sg:phone":"+44 20 8508 3107",
    "sg:postcode":"IG10 1SX",
    "sg:province":"Essex",
    "wof:name":"Flower Elegance",
    "wof:placetype":"venue"
},
  "geometry": {"coordinates":[0.06853,51.651131],"type":"Point"}
}