{
  "type": "Feature",
  "properties": {
    "iso:country":"GB",
    "sg:address":"12 Enterprise Court, Crow Hall Road, Nelson Industrial Estate",
    "sg:city":"Cramlington",
    "sg:classifiers":[
        {
            "category":"Professional",
            "subcategory":"Detective & Security Services",
            "type":"Services"
        }
    ],
    "sg:postcode":"NE23 1LZ",
    "sg:province":"Northumberland",
    "sg:tags":[
        "equipment"
    ],
    "wof:name":"Computerlink Control Systems Ltd.",
    "wof:placetype":"venue"
},
  "geometry": {"coordinates":[-1.599559,55.100014],"type":"Point"}
}