{
  "type": "Feature",
  "properties": {
    "addr:full":"Crompton Cottage, Park Avenue, Higher Kinnerton Chester Cheshire CH4 9AS",
    "addr:postcode":"ch4 9as",
    "addr:street":"Park Avenue",
    "iso:country":"GB",
    "sg:address":"Crompton Cottage, Park Avenue, Higher Kinnerton",
    "sg:city":"Chester",
    "sg:classifiers":[
        {
            "category":"Shopping",
            "subcategory":"Beauty & Cosmetics",
            "type":"Retail Goods"
        }
    ],
    "sg:postcode":"CH4 9AS",
    "sg:province":"Cheshire",
    "sg:tags":[
        "equipment",
        "supply",
        "hairdressing"
    ],
    "wof:name":"Deeside Hair",
    "wof:placetype":"venue"
},
  "geometry": {"coordinates":[-3.0055689812,53.1450614929],"type":"Point"}
}