{
  "type": "Feature",
  "properties": {
    "iso:country":"GB",
    "sg:address":"25 Honeysuckle Lane, Creekmoor",
    "sg:city":"Poole",
    "sg:classifiers":[
        {
            "category":"Building & Trades",
            "subcategory":"Construction",
            "type":"Services"
        }
    ],
    "sg:postcode":"BH17 7YY",
    "sg:province":"Dorset",
    "sg:tags":[
        "joiner",
        "carpenter"
    ],
    "wof:name":"J V McBain Ltd.",
    "wof:placetype":"venue"
},
  "geometry": {"coordinates":[-2.005294,50.746803],"type":"Point"}
}