{
  "type": "Feature",
  "properties": {
    "addr:full":"15 The Gardens Newtown Powys SY16 4NX",
    "addr:housenumber":"15",
    "addr:postcode":"sy16 4nx",
    "addr:street":"The Gardens",
    "iso:country":"GB",
    "sg:address":"15 The Gardens",
    "sg:city":"Newtown",
    "sg:classifiers":[
        {
            "category":"Home & Garden",
            "subcategory":"Carpets & Floor Coverings",
            "type":"Retail Goods"
        }
    ],
    "sg:postcode":"SY16 4NX",
    "sg:province":"Powys",
    "sg:tags":[
        "carpets",
        "rug",
        "matting"
    ],
    "wof:name":"Sit 'N' Choose",
    "wof:placetype":"venue"
},
  "geometry": {"coordinates":[-3.3146119118,52.5127754211],"type":"Point"}
}