{
  "type": "Feature",
  "properties": {
    "iso:country":"GB",
    "sg:address":"10 White Hart Arcade, Madford Lane",
    "sg:city":"Launceston",
    "sg:classifiers":[
        {
            "category":"Cafe",
            "type":"Food & Drink"
        }
    ],
    "sg:phone":"+44 1566 776195",
    "sg:postcode":"PL15 9EB",
    "sg:province":"Cornwall",
    "sg:tags":[
        "tea",
        "room"
    ],
    "wof:name":"The Coffee Pot",
    "wof:placetype":"venue"
},
  "geometry": {"coordinates":[-4.363344,50.636707],"type":"Point"}
}