{
  "type": "Feature",
  "properties": {
    "addr:full":"The White House, Sewardstone Road, Chingford London Greater London E4 7RE",
    "addr:postcode":"e4 7re",
    "addr:street":"Sewardstone Road",
    "iso:country":"GB",
    "sg:address":"The White House, Sewardstone Road, Chingford",
    "sg:city":"London",
    "sg:classifiers":[
        {
            "category":"Professional",
            "subcategory":"Engineering",
            "type":"Services"
        }
    ],
    "sg:postcode":"E4 7RE",
    "sg:province":"Greater London",
    "sg:tags":[
        "pneumatic",
        "engineer"
    ],
    "wof:name":"R C Dickerson Pneumatic Engineers",
    "wof:placetype":"venue"
},
  "geometry": {"coordinates":[-0.011434,51.641052],"type":"Point"}
}