{
  "type": "Feature",
  "properties": {
    "addr:full":"Jail Lane, Biggin Hill Westerham Kent TN16 3AX",
    "addr:postcode":"tn16 3ax",
    "addr:street":"Jail Lane",
    "iso:country":"GB",
    "sg:address":"Jail Lane, Biggin Hill",
    "sg:city":"Westerham",
    "sg:classifiers":[
        {
            "category":"Bars & Pubs",
            "type":"Food & Drink"
        }
    ],
    "sg:phone":"+44 1959 572979",
    "sg:postcode":"TN16 3AX",
    "sg:province":"Kent",
    "sg:tags":[
        "pubs",
        "inn"
    ],
    "wof:name":"The Old Jail",
    "wof:placetype":"venue"
},
  "geometry": {"coordinates":[0.054715,51.314774],"type":"Point"}
}