{
  "type": "Feature",
  "properties": {
    "iso:country":"GB",
    "sg:address":"65-67 Drayton Park, Highbury",
    "sg:city":"London",
    "sg:classifiers":[
        {
            "category":"Autos & Motor Vehicles",
            "subcategory":"Auto Supplies",
            "type":"Retail Goods"
        }
    ],
    "sg:postcode":"N5 1NT",
    "sg:province":"Greater London",
    "sg:tags":[
        "tyre"
    ],
    "wof:name":"Drayton Park Tyres",
    "wof:placetype":"venue"
},
  "geometry": {"coordinates":[-0.1060120016,51.5518875122],"type":"Point"}
}