{
  "type": "Feature",
  "properties": {
    "addr:full":"38 Oakwood Gro Warwick Warwickshire CV34 5TD",
    "addr:housenumber":"38",
    "addr:postcode":"cv34 5td",
    "addr:street":"Oakwood Gro",
    "iso:country":"GB",
    "sg:address":"38 Oakwood Gro",
    "sg:city":"Warwick",
    "sg:classifiers":[
        {
            "category":"Organizations",
            "subcategory":"Non-profit Organization",
            "type":"Services"
        }
    ],
    "sg:phone":"+44 1926 497793",
    "sg:postcode":"CV34 5TD",
    "sg:province":"Warwickshire",
    "sg:tags":[
        "organisation",
        "voluntary",
        "charity"
    ],
    "wof:name":"Mid Warwickshire Mencap",
    "wof:placetype":"venue"
},
  "geometry": {"coordinates":[-1.5708010197,52.2941741943],"type":"Point"}
}