{
  "type": "Feature",
  "properties": {
    "addr:full":"17 Deansgate Blackpool Lancashire FY1 1BN",
    "addr:housenumber":"17",
    "addr:postcode":"fy1 1bn",
    "addr:street":"Deansgate",
    "iso:country":"GB",
    "sg:address":"17 Deansgate",
    "sg:city":"Blackpool",
    "sg:classifiers":[
        {
            "category":"Fast Food",
            "type":"Food & Drink"
        }
    ],
    "sg:phone":"+44 1253 291909",
    "sg:postcode":"FY1 1BN",
    "sg:province":"Lancashire",
    "sg:tags":[
        "away",
        "take"
    ],
    "wof:name":"Gilly's Take Away",
    "wof:placetype":"venue"
},
  "geometry": {"coordinates":[-3.0515239239,53.8195648193],"type":"Point"}
}