{
  "type": "Feature",
  "properties": {
    "addr:full":"Bartons Farm, Moss Lane, Burscough Ormskirk Lancashire L40 4AL",
    "addr:postcode":"l40 4al",
    "addr:street":"Moss Lane",
    "iso:country":"GB",
    "sg:address":"Bartons Farm, Moss Lane, Burscough",
    "sg:city":"Ormskirk",
    "sg:classifiers":[
        {
            "category":"Home & Garden",
            "subcategory":"Furniture",
            "type":"Retail Goods"
        }
    ],
    "sg:phone":"+44 1704 893789",
    "sg:postcode":"L40 4AL",
    "sg:province":"Lancashire",
    "wof:name":"Grovesnor Furnishings",
    "wof:placetype":"venue"
},
  "geometry": {"coordinates":[-2.83958,53.606411],"type":"Point"}
}