{
  "type": "Feature",
  "properties": {
    "addr:full":"26 Oxford Road Yeovil Somerset BA21 5HR",
    "addr:housenumber":"26",
    "addr:postcode":"ba21 5hr",
    "addr:street":"Oxford Road",
    "iso:country":"GB",
    "sg:address":"26 Oxford Road",
    "sg:city":"Yeovil",
    "sg:classifiers":[
        {
            "category":"Autos & Motor Vehicles",
            "subcategory":"Motorcycle Sales",
            "type":"Retail Goods"
        }
    ],
    "sg:postcode":"BA21 5HR",
    "sg:province":"Somerset",
    "wof:name":"Riders (Yeovil) Ltd.",
    "wof:placetype":"venue"
},
  "geometry": {"coordinates":[-2.6053819656,50.9520530701],"type":"Point"}
}