{
  "type": "Feature",
  "properties": {
    "iso:country":"GB",
    "sg:address":"Main Street, Peasmarsh",
    "sg:city":"Rye",
    "sg:classifiers":[
        {
            "category":"Cafe",
            "type":"Food & Drink"
        }
    ],
    "sg:phone":"+44 1797 230287",
    "sg:postcode":"TN31 6SP",
    "sg:province":"East Sussex",
    "sg:tags":[
        "tea",
        "room"
    ],
    "wof:name":"Mr K & Mrs B Clements",
    "wof:placetype":"venue"
},
  "geometry": {"coordinates":[0.691108,50.971294],"type":"Point"}
}