{
  "type": "Feature",
  "properties": {
    "addr:full":"C/o Roehampton Club, Roehampton Lane London Greater London SW15 5LR",
    "addr:postcode":"sw15 5lr",
    "addr:street":"C;Roehampton Lane",
    "iso:country":"GB",
    "sg:address":"C/o Roehampton Club, Roehampton Lane",
    "sg:city":"London",
    "sg:classifiers":[
        {
            "category":"Health Services",
            "subcategory":"Hospital",
            "type":"Services"
        }
    ],
    "sg:postcode":"SW15 5LR",
    "sg:province":"Greater London",
    "wof:name":"The Tulloch Clinic",
    "wof:placetype":"venue"
},
  "geometry": {"coordinates":[-0.243099,51.455521],"type":"Point"}
}