{
  "type": "Feature",
  "properties": {
    "addr:full":"Unit B2, Acre Business Park, Acre Rd Reading Berkshire RG2 0SA",
    "addr:housenumber":"b2",
    "addr:postcode":"rg2 0sa",
    "addr:street":"Acre Business Park Acre Rd",
    "iso:country":"GB",
    "sg:address":"Unit B2, Acre Business Park, Acre Rd",
    "sg:city":"Reading",
    "sg:classifiers":[
        {
            "category":"Building & Trades",
            "subcategory":"Pest Control",
            "type":"Services"
        }
    ],
    "sg:phone":"+44 118 975 0326",
    "sg:postcode":"RG2 0SA",
    "sg:province":"Berkshire",
    "sg:tags":[
        "panel"
    ],
    "wof:name":"JRP Control & Automation",
    "wof:placetype":"venue"
},
  "geometry": {"coordinates":[-0.9724400043,51.4239311218],"type":"Point"}
}