{
  "type": "Feature",
  "properties": {
    "addr:full":"2 Fore Street Holsworthy Cornwall EX22 6EB",
    "addr:housenumber":"2",
    "addr:postcode":"ex22 6eb",
    "addr:street":"Fore Street",
    "iso:country":"GB",
    "sg:address":"2 Fore Street",
    "sg:city":"Holsworthy",
    "sg:classifiers":[
        {
            "category":"Fast Food",
            "type":"Food & Drink"
        }
    ],
    "sg:phone":"+44 1409 253969",
    "sg:postcode":"EX22 6EB",
    "sg:province":"Cornwall",
    "sg:tags":[
        "away",
        "take"
    ],
    "wof:name":"Town Fryer",
    "wof:placetype":"venue"
},
  "geometry": {"coordinates":[-4.352971077,50.8104743958],"type":"Point"}
}