{
  "type": "Feature",
  "properties": {
    "iso:country":"GB",
    "sg:address":"34 Barleyknowe Terrace",
    "sg:city":"Gorebridge",
    "sg:classifiers":[
        {
            "category":"Bus Charters",
            "type":"Transportation"
        }
    ],
    "sg:phone":"+44 1875 823151",
    "sg:postcode":"EH23 4EQ",
    "sg:province":"Midlothian",
    "sg:tags":[
        "hire",
        "coach"
    ],
    "wof:name":"Charlotte Travel",
    "wof:placetype":"venue"
},
  "geometry": {"coordinates":[-3.0479450226,55.83644104],"type":"Point"}
}