{
  "type": "Feature",
  "properties": {
    "addr:full":"154 St Neots Road, Eaton Ford Huntingdon Bedfordshire PE19 3AD",
    "addr:housenumber":"154",
    "addr:postcode":"pe19 3ad",
    "addr:street":"St Neots Road",
    "iso:country":"GB",
    "sg:address":"154 St Neots Road, Eaton Ford",
    "sg:city":"Huntingdon",
    "sg:classifiers":[
        {
            "category":"Home & Garden",
            "subcategory":"Furniture",
            "type":"Retail Goods"
        }
    ],
    "sg:phone":"+44 1480 218890",
    "sg:postcode":"PE19 3AD",
    "sg:province":"Bedfordshire",
    "wof:name":"M Ware",
    "wof:placetype":"venue"
},
  "geometry": {"coordinates":[-0.28242,52.227951],"type":"Point"}
}