{
  "type": "Feature",
  "properties": {
    "iso:country":"GB",
    "sg:address":"42 Buttermere Avenue",
    "sg:city":"Middlesbrough",
    "sg:classifiers":[
        {
            "category":"Retail",
            "subcategory":"Driving School",
            "type":"Services"
        }
    ],
    "sg:phone":"+44 1642 812109",
    "sg:postcode":"TS5 7BA",
    "sg:province":"North Yorkshire",
    "wof:name":"Eric Parry School of Motoring",
    "wof:placetype":"venue"
},
  "geometry": {"coordinates":[-1.256549,54.549095],"type":"Point"}
}