{
  "type": "Feature",
  "properties": {
    "addr:full":"14 Cranham Clo Redditch Warwickshire B97 5AY",
    "addr:housenumber":"14",
    "addr:postcode":"b97 5ay",
    "addr:street":"Cranham Clo",
    "iso:country":"GB",
    "sg:address":"14 Cranham Clo",
    "sg:city":"Redditch",
    "sg:classifiers":[
        {
            "category":"Home & Garden",
            "subcategory":"Home Furnishings",
            "type":"Retail Goods"
        }
    ],
    "sg:phone":"+44 1527 545732",
    "sg:postcode":"B97 5AY",
    "sg:province":"Warwickshire",
    "sg:tags":[
        "mantelpiece",
        "fireplace"
    ],
    "wof:name":"Fireplaces By Fairways",
    "wof:placetype":"venue"
},
  "geometry": {"coordinates":[-1.95865798,52.2926292419],"type":"Point"}
}