{
  "type": "Feature",
  "properties": {
    "addr:full":"6-7 Market Place Mansfield Nottinghamshire NG18 1HU",
    "addr:housenumber":"6-7",
    "addr:postcode":"ng18 1hu",
    "addr:street":"Market Place",
    "iso:country":"GB",
    "sg:address":"6-7 Market Place",
    "sg:city":"Mansfield",
    "sg:classifiers":[
        {
            "category":"Professional",
            "subcategory":"Employment Agencies",
            "type":"Services"
        }
    ],
    "sg:phone":"+44 1623 422755",
    "sg:postcode":"NG18 1HU",
    "sg:province":"Nottinghamshire",
    "sg:tags":[
        "consultant"
    ],
    "wof:name":"Hays Accountancy Personnel",
    "wof:placetype":"venue"
},
  "geometry": {"coordinates":[-1.196189,53.144562],"type":"Point"}
}