{
  "type": "Feature",
  "properties": {
    "iso:country":"GB",
    "sg:address":"Church Gate",
    "sg:city":"Thatcham",
    "sg:classifiers":[
        {
            "category":"Education",
            "subcategory":"Preschool",
            "type":"Public Place"
        }
    ],
    "sg:phone":"+44 1635 872339",
    "sg:postcode":"RG19 3PJ",
    "sg:province":"Berkshire",
    "sg:tags":[
        "pre-school",
        "playgroups"
    ],
    "wof:name":"Busy Bees Pre School",
    "wof:placetype":"venue"
},
  "geometry": {"coordinates":[-1.2594250441,51.4012985229],"type":"Point"}
}