{
  "type": "Feature",
  "properties": {
    "addr:full":"13 Alandale Crescent, Garforth Leeds North Yorkshire LS25 1DH",
    "addr:housenumber":"13",
    "addr:postcode":"ls25 1dh",
    "addr:street":"Alandale Crescent",
    "iso:country":"GB",
    "sg:address":"13 Alandale Crescent, Garforth",
    "sg:city":"Leeds",
    "sg:classifiers":[
        {
            "category":"Utilities",
            "subcategory":"Natural Gas",
            "type":"Services"
        }
    ],
    "sg:postcode":"LS25 1DH",
    "sg:province":"North Yorkshire",
    "sg:tags":[
        "welding"
    ],
    "wof:name":"J M G Plastic Fabrications",
    "wof:placetype":"venue"
},
  "geometry": {"coordinates":[-1.4003000259,53.7914733887],"type":"Point"}
}