{
  "type": "Feature",
  "properties": {
    "iso:country":"GB",
    "sg:address":"Workshop, Myrtle Cottages, Burgh Rd",
    "sg:city":"Cowdenbeath",
    "sg:classifiers":[
        {
            "category":"Retail",
            "subcategory":"Auto Repair",
            "type":"Services"
        }
    ],
    "sg:phone":"+44 1383 515551",
    "sg:postcode":"KY4 9QD",
    "sg:province":"Fife",
    "sg:tags":[
        "modification",
        "garage"
    ],
    "wof:name":"Burgh Road Garage",
    "wof:placetype":"venue"
},
  "geometry": {"coordinates":[-3.344159,56.112125],"type":"Point"}
}