{
  "type": "Feature",
  "properties": {
    "addr:full":"57 Cornwall Road, Bishopston Bristol City of Bristol BS7 8LJ",
    "addr:housenumber":"57",
    "addr:postcode":"bs7 8lj",
    "addr:street":"Cornwall Road",
    "iso:country":"GB",
    "sg:address":"57 Cornwall Road, Bishopston",
    "sg:city":"Bristol",
    "sg:classifiers":[
        {
            "category":"Shopping",
            "subcategory":"Musical Instruments",
            "type":"Retail Goods"
        }
    ],
    "sg:phone":"+44 117 975 9751",
    "sg:postcode":"BS7 8LJ",
    "sg:province":"City of Bristol",
    "wof:name":"Gary J Whiteland",
    "wof:placetype":"venue"
},
  "geometry": {"coordinates":[-2.597745,51.478973],"type":"Point"}
}