{
  "type": "Feature",
  "properties": {
    "addr:full":"42 Parker St Barnsley South Yorkshire S70 6EG",
    "addr:housenumber":"42",
    "addr:postcode":"s70 6eg",
    "addr:street":"Parker St;Yorkshire",
    "iso:country":"GB",
    "sg:address":"42 Parker St",
    "sg:city":"Barnsley",
    "sg:classifiers":[
        {
            "category":"Professional",
            "type":"Services"
        }
    ],
    "sg:postcode":"S70 6EG",
    "sg:province":"South Yorkshire",
    "sg:tags":[
        "caterer"
    ],
    "wof:name":"South Yorkshire Catering",
    "wof:placetype":"venue"
},
  "geometry": {"coordinates":[-1.4912539721,53.5505485535],"type":"Point"}
}