{
  "type": "Feature",
  "properties": {
    "addr:full":"33 Queens Way Romney Marsh Kent TN29 0NB",
    "addr:housenumber":"33",
    "addr:postcode":"tn29 0nb",
    "addr:street":"Queens Way",
    "iso:country":"GB",
    "sg:address":"33 Queens Way",
    "sg:city":"Romney Marsh",
    "sg:classifiers":[
        {
            "category":"Wholesale",
            "subcategory":"Electrical",
            "type":"Manufacturing & Wholesale Goods"
        }
    ],
    "sg:phone":"+44 1303 875000",
    "sg:postcode":"TN29 0NB",
    "sg:province":"Kent",
    "sg:tags":[
        "equipment",
        "refrigeration"
    ],
    "wof:name":"Safe Ltd",
    "wof:placetype":"venue"
},
  "geometry": {"coordinates":[1.0093150139,51.0362586975],"type":"Point"}
}