{
  "type": "Feature",
  "properties": {
    "addr:full":"Pyramid House, Lowman Way, Tiverton Business Park Tiverton Devon EX16 6SR",
    "addr:postcode":"ex16 6sr",
    "addr:street":"Lowman Way Tiverton Business Park",
    "iso:country":"GB",
    "sg:address":"Pyramid House, Lowman Way, Tiverton Business Park",
    "sg:city":"Tiverton",
    "sg:classifiers":[
        {
            "category":"Building & Trades",
            "subcategory":"Construction",
            "type":"Services"
        }
    ],
    "sg:phone":"+44 1884 254584",
    "sg:postcode":"EX16 6SR",
    "sg:province":"Devon",
    "sg:tags":[
        "builder"
    ],
    "wof:name":"Devonshire Homes Ltd.",
    "wof:placetype":"venue"
},
  "geometry": {"coordinates":[-3.464324,50.911671],"type":"Point"}
}