{
  "type": "Feature",
  "properties": {
    "addr:full":"1 Park Hill, Swallownest Sheffield Derbyshire S31 0TF",
    "addr:housenumber":"1",
    "addr:postcode":"s31 0tf",
    "addr:street":"Park Hill Swallownest",
    "iso:country":"GB",
    "sg:address":"1 Park Hill, Swallownest",
    "sg:city":"Sheffield",
    "sg:classifiers":[
        {
            "category":"Real Estate",
            "subcategory":"Surveying",
            "type":"Services"
        }
    ],
    "sg:phone":"+44 114 269 4111",
    "sg:postcode":"S31 0TF",
    "sg:province":"Derbyshire",
    "sg:tags":[
        "surveyor",
        "land"
    ],
    "wof:name":"Initial Land Surveys",
    "wof:placetype":"venue"
},
  "geometry": {"coordinates":[-1.3289500475,53.3585090637],"type":"Point"}
}