{
  "type": "Feature",
  "properties": {
    "addr:full":"Heath Road, Bradfield Manningtree Essex CO11 2XH",
    "addr:postcode":"co11 2xh",
    "addr:street":"Heath Road",
    "iso:country":"GB",
    "sg:address":"Heath Road, Bradfield",
    "sg:city":"Manningtree",
    "sg:classifiers":[
        {
            "category":"Autos & Motor Vehicles",
            "subcategory":"Automobile Sales",
            "type":"Retail Goods"
        },
        {
            "category":"Retail",
            "subcategory":"Auto Repair",
            "type":"Services"
        }
    ],
    "sg:phone":"+44 1255 870184",
    "sg:postcode":"CO11 2XH",
    "sg:province":"Essex",
    "sg:tags":[
        "modification",
        "car",
        "related",
        "garage"
    ],
    "wof:name":"T R Autos",
    "wof:placetype":"venue"
},
  "geometry": {"coordinates":[1.1103949547,51.9264945984],"type":"Point"}
}