{
  "type": "Feature",
  "properties": {
    "addr:full":"34-38 Whalley Banks, King Street Blackburn Lancashire BB2 1NU",
    "addr:housenumber":"34-38",
    "addr:postcode":"bb2 1nu",
    "addr:street":"Whalley Banks King Street",
    "iso:country":"GB",
    "sg:address":"34-38 Whalley Banks, King Street",
    "sg:city":"Blackburn",
    "sg:classifiers":[
        {
            "category":"Communications",
            "type":"Services"
        },
        {
            "category":"Shopping",
            "subcategory":"Used Merchandise",
            "type":"Retail Goods"
        }
    ],
    "sg:postcode":"BB2 1NU",
    "sg:province":"Lancashire",
    "sg:tags":[
        "shop",
        "tv",
        "video",
        "second-hand",
        "radio"
    ],
    "wof:name":"Jogee Secondhand Shop",
    "wof:placetype":"venue"
},
  "geometry": {"coordinates":[-2.491702,53.744251],"type":"Point"}
}