{
  "type": "Feature",
  "properties": {
    "iso:country":"GB",
    "sg:address":"Bank Ho, Little Reedness",
    "sg:city":"Goole",
    "sg:classifiers":[
        {
            "category":"Transit Center",
            "subcategory":"Passenger",
            "type":"Transportation"
        }
    ],
    "sg:postcode":"DN14 8HQ",
    "sg:province":"East Riding of Yorkshire",
    "sg:tags":[
        "boarding",
        "kennel",
        "catteries"
    ],
    "wof:name":"Lockwood,Barbara,",
    "wof:placetype":"venue"
},
  "geometry": {"coordinates":[-0.792099,53.697861],"type":"Point"}
}