{
  "type": "Feature",
  "properties": {
    "addr:full":"Unit 8, 4 Whistleberry Industrial Park Hamilton South Lanarkshire ML3 0ED",
    "addr:housenumber":"unit;4",
    "addr:postcode":"ml3 0ed",
    "addr:street":"Whistleberry Industrial Park",
    "iso:country":"GB",
    "sg:address":"Unit 8, 4 Whistleberry Industrial Park",
    "sg:city":"Hamilton",
    "sg:classifiers":[
        {
            "category":"Building & Trades",
            "subcategory":"Construction",
            "type":"Services"
        }
    ],
    "sg:phone":"+44 1698 712122",
    "sg:postcode":"ML3 0ED",
    "sg:province":"South Lanarkshire",
    "sg:tags":[
        "welder",
        "welding"
    ],
    "wof:name":"Allweld Fabrication Services",
    "wof:placetype":"venue"
},
  "geometry": {"coordinates":[-4.064059,55.790253],"type":"Point"}
}