{
  "type": "Feature",
  "properties": {
    "addr:full":"87 Allestree Lane Derby Derbyshire DE22 2HS",
    "addr:housenumber":"87",
    "addr:postcode":"de22 2hs",
    "addr:street":"Allestree Lane",
    "iso:country":"GB",
    "sg:address":"87 Allestree Lane",
    "sg:city":"Derby",
    "sg:classifiers":[
        {
            "category":"Building & Trades",
            "subcategory":"Plumbing",
            "type":"Services"
        }
    ],
    "sg:phone":"+44 1332 552775",
    "sg:postcode":"DE22 2HS",
    "sg:province":"Derbyshire",
    "sg:tags":[
        "heating"
    ],
    "wof:name":"Robert Alan Eason",
    "wof:placetype":"venue"
},
  "geometry": {"coordinates":[-1.495808959,52.9495811462],"type":"Point"}
}