{
  "type": "Feature",
  "properties": {
    "addr:full":"The Estates Office, Westacre King's Lynn Norfolk PE32 1UB",
    "addr:postcode":"pe32 1ub",
    "addr:street":"Lynn",
    "iso:country":"GB",
    "sg:address":"The Estates Office, Westacre",
    "sg:city":"King's Lynn",
    "sg:classifiers":[
        {
            "category":"Farming",
            "subcategory":"Livestock Farm",
            "type":"Manufacturing & Wholesale Goods"
        },
        {
            "category":"Real Estate",
            "subcategory":"Real Estate Agent",
            "type":"Services"
        }
    ],
    "sg:phone":"+44 1760 755254",
    "sg:postcode":"PE32 1UB",
    "sg:province":"Norfolk",
    "sg:tags":[
        "others"
    ],
    "wof:name":"Westacre Farms",
    "wof:placetype":"venue"
},
  "geometry": {"coordinates":[0.6317600012,52.7053604126],"type":"Point"}
}