{
  "type": "Feature",
  "properties": {
    "iso:country":"GB",
    "sg:address":"All Well House, Cowley Road",
    "sg:city":"Cambridge",
    "sg:classifiers":[
        {
            "category":"Shopping",
            "subcategory":"News",
            "type":"Retail Goods"
        }
    ],
    "sg:postcode":"CB4 0WY",
    "sg:province":"Cambridgeshire",
    "sg:tags":[
        "newsagent"
    ],
    "wof:name":"Officepoint East Anglia",
    "wof:placetype":"venue"
},
  "geometry": {"coordinates":[0.15388,52.229324],"type":"Point"}
}