{
  "type": "Feature",
  "properties": {
    "addr:full":"Coombe Ho, Church St, Pensford Bristol Somerset BS39 4AQ",
    "addr:postcode":"bs39 4aq",
    "addr:street":"St",
    "iso:country":"GB",
    "sg:address":"Coombe Ho, Church St, Pensford",
    "sg:city":"Bristol",
    "sg:classifiers":[
        {
            "category":"Retail",
            "subcategory":"Funeral Services",
            "type":"Services"
        }
    ],
    "sg:phone":"+44 1761 490312",
    "sg:postcode":"BS39 4AQ",
    "sg:province":"Somerset",
    "wof:name":"Albert Batten & Sons Ltd",
    "wof:placetype":"venue"
},
  "geometry": {"coordinates":[-2.5473659039,51.3699607849],"type":"Point"}
}