{
  "type": "Feature",
  "properties": {
    "addr:full":"Crown Industrial Estate Burton-on-trent Derbyshire DE14 3PA",
    "addr:postcode":"de14 3pa",
    "iso:country":"GB",
    "sg:address":"Crown Industrial Estate",
    "sg:city":"Burton-on-trent",
    "sg:classifiers":[
        {
            "category":"Utilities",
            "subcategory":"Sewage",
            "type":"Services"
        }
    ],
    "sg:postcode":"DE14 3PA",
    "sg:province":"Derbyshire",
    "sg:tags":[
        "acoustic",
        "consultant"
    ],
    "wof:name":"Ecomax Acoustics Ltd.",
    "wof:placetype":"venue"
},
  "geometry": {"coordinates":[-1.646604,52.800049],"type":"Point"}
}