{
  "type": "Feature",
  "properties": {
    "iso:country":"GB",
    "sg:address":"88 Eastcourt Lane",
    "sg:city":"Gillingham",
    "sg:classifiers":[
        {
            "category":"Building & Trades",
            "subcategory":"Plumbing",
            "type":"Services"
        }
    ],
    "sg:phone":"+44 1634 375257",
    "sg:postcode":"ME8 6HG",
    "sg:province":"Kent",
    "sg:tags":[
        "plumber",
        "heating"
    ],
    "wof:name":"D W G Smith",
    "wof:placetype":"venue"
},
  "geometry": {"coordinates":[0.57877,51.373749],"type":"Point"}
}