{
  "type": "Feature",
  "properties": {
    "addr:full":"2 Brickle Cotts, Brickle Road, Stoke Holy Cross Norwich Norfolk NR14 8NQ",
    "addr:housenumber":"2;cotts",
    "addr:postcode":"nr14 8nq",
    "addr:street":"Brickle;Brickle Road",
    "iso:country":"GB",
    "sg:address":"2 Brickle Cotts, Brickle Road, Stoke Holy Cross",
    "sg:city":"Norwich",
    "sg:classifiers":[
        {
            "category":"Building & Trades",
            "subcategory":"Construction",
            "type":"Services"
        }
    ],
    "sg:postcode":"NR14 8NQ",
    "sg:province":"Norfolk",
    "sg:tags":[
        "decorator",
        "painter"
    ],
    "wof:name":"R A Bezant",
    "wof:placetype":"venue"
},
  "geometry": {"coordinates":[1.2950110435,52.5686759949],"type":"Point"}
}