{
  "type": "Feature",
  "properties": {
    "addr:full":"Flat 4 The Stables, Valingers Road King's Lynn Norfolk PE30 5HD",
    "addr:housenumber":"the",
    "addr:postcode":"pe30 5hd",
    "addr:street":"Valingers Road",
    "iso:country":"GB",
    "sg:address":"Flat 4 The Stables, Valingers Road",
    "sg:city":"King's Lynn",
    "sg:classifiers":[
        {
            "category":"Building & Trades",
            "subcategory":"Construction",
            "type":"Services"
        }
    ],
    "sg:phone":"+44 1553 769618",
    "sg:postcode":"PE30 5HD",
    "sg:province":"Norfolk",
    "sg:tags":[
        "contractor",
        "paving",
        "driveway"
    ],
    "wof:name":"M S H Paving",
    "wof:placetype":"venue"
},
  "geometry": {"coordinates":[0.4007000029,52.7485389709],"type":"Point"}
}