{
  "type": "Feature",
  "properties": {
    "addr:full":"The Studio, Regency House, 67 Long Acre Nottingham Leicestershire NG13 8BU",
    "addr:housenumber":"67",
    "addr:postcode":"ng13 8bu",
    "addr:street":"Long Acre",
    "iso:country":"GB",
    "sg:address":"The Studio, Regency House, 67 Long Acre",
    "sg:city":"Nottingham",
    "sg:classifiers":[
        {
            "category":"Professional",
            "subcategory":"Art Services",
            "type":"Services"
        }
    ],
    "sg:phone":"+44 1949 839367",
    "sg:postcode":"NG13 8BU",
    "sg:province":"Leicestershire",
    "sg:tags":[
        "photographer"
    ],
    "wof:name":"Ray Rockley",
    "wof:placetype":"venue"
},
  "geometry": {"coordinates":[-0.949499011,52.9510192871],"type":"Point"}
}