{
  "type": "Feature",
  "properties": {
    "addr:full":"Centurian Ho, Centurian Way Preston Lancashire PR5 1TZ",
    "addr:postcode":"pr5 1tz",
    "addr:street":"Centurian Way",
    "iso:country":"GB",
    "sg:address":"Centurian Ho, Centurian Way",
    "sg:city":"Preston",
    "sg:classifiers":[
        {
            "category":"Health Services",
            "subcategory":"Health Practitioner",
            "type":"Services"
        }
    ],
    "sg:phone":"+44 1772 454454",
    "sg:postcode":"PR5 1TZ",
    "sg:province":"Lancashire",
    "sg:tags":[
        "acupuncture"
    ],
    "wof:name":"Primary House Promotion Services",
    "wof:placetype":"venue"
},
  "geometry": {"coordinates":[-2.6308400631,53.7457618713],"type":"Point"}
}