{
  "type": "Feature",
  "properties": {
    "addr:full":"1-5 Garlands Road Redhill Surrey RH1 6NX",
    "addr:housenumber":"1-5",
    "addr:postcode":"rh1 6nx",
    "addr:street":"Garlands Road",
    "iso:country":"GB",
    "sg:address":"1-5 Garlands Road",
    "sg:city":"Redhill",
    "sg:classifiers":[
        {
            "category":"Manufacturing",
            "subcategory":"Jewelry",
            "type":"Manufacturing & Wholesale Goods"
        }
    ],
    "sg:phone":"+44 1737 767363",
    "sg:postcode":"RH1 6NX",
    "sg:province":"Surrey",
    "sg:tags":[
        "precious",
        "stone"
    ],
    "wof:name":"Baines Orr (London) Ltd.",
    "wof:placetype":"venue"
},
  "geometry": {"coordinates":[-0.170534,51.236671],"type":"Point"}
}