{
  "type": "Feature",
  "properties": {
    "addr:full":"Windrush The Ridgeway Enfield Greater London EN2 8AN",
    "addr:postcode":"en2 8an",
    "addr:street":"The Ridgeway",
    "iso:country":"GB",
    "sg:address":"Windrush The Ridgeway",
    "sg:city":"Enfield",
    "sg:classifiers":[
        {
            "category":"Professional",
            "subcategory":"Management & Consulting",
            "type":"Services"
        }
    ],
    "sg:phone":"+44 20 8366 4443",
    "sg:postcode":"EN2 8AN",
    "sg:province":"Greater London",
    "sg:tags":[
        "consultant",
        "business"
    ],
    "wof:name":"Heather Newham Associates",
    "wof:placetype":"venue"
},
  "geometry": {"coordinates":[-0.1117089987,51.6681785583],"type":"Point"}
}