{
  "type": "Feature",
  "properties": {
    "addr:full":"85 High Street Montrose Aberdeenshire DD10 8QY",
    "addr:housenumber":"85",
    "addr:postcode":"dd10 8qy",
    "addr:street":"High Street",
    "iso:country":"GB",
    "sg:address":"85 High Street",
    "sg:city":"Montrose",
    "sg:classifiers":[
        {
            "category":"Community Center",
            "subcategory":"Social",
            "type":"Public Place"
        }
    ],
    "sg:phone":"+44 1674 675940",
    "sg:postcode":"DD10 8QY",
    "sg:province":"Aberdeenshire",
    "sg:tags":[
        "frozen",
        "food",
        "freezer",
        "centre"
    ],
    "wof:name":"Farm Foods",
    "wof:placetype":"venue"
},
  "geometry": {"coordinates":[-2.467924118,56.711730957],"type":"Point"}
}