{
  "type": "Feature",
  "properties": {
    "addr:full":"Sandy Hey Farm, London Road, Adlington Macclesfield Cheshire SK10 4NG",
    "addr:postcode":"sk10 4ng",
    "addr:street":"Sandy Hey Farm London Road",
    "iso:country":"GB",
    "sg:address":"Sandy Hey Farm, London Road, Adlington",
    "sg:city":"Macclesfield",
    "sg:classifiers":[
        {
            "category":"Sports & Exercise",
            "subcategory":"Golf",
            "type":"Entertainment"
        }
    ],
    "sg:phone":"+44 1625 850660",
    "sg:postcode":"SK10 4NG",
    "sg:province":"Cheshire",
    "sg:tags":[
        "club",
        "course",
        "range",
        "practice"
    ],
    "wof:name":"Adlington Golf Centre",
    "wof:placetype":"venue"
},
  "geometry": {"coordinates":[-2.1349608898,53.3202590942],"type":"Point"}
}