{
  "type": "Feature",
  "properties": {
    "iso:country":"GB",
    "sg:address":"Point Industrial Estate, Point Road",
    "sg:city":"Canvey Island",
    "sg:classifiers":[
        {
            "category":"Sports & Exercise",
            "subcategory":"Gym",
            "type":"Entertainment"
        }
    ],
    "sg:postcode":"SS8 7RT",
    "sg:province":"Essex",
    "sg:tags":[
        "fitness",
        "health",
        "centre"
    ],
    "wof:name":"The Fitness Factory",
    "wof:placetype":"venue"
},
  "geometry": {"coordinates":[0.62237,51.518959],"type":"Point"}
}