{
  "type": "Feature",
  "properties": {
    "addr:full":"157 Stratford Road, Shirley Solihull West Midlands B90 3AX",
    "addr:housenumber":"157",
    "addr:postcode":"b90 3ax",
    "addr:street":"Stratford Road",
    "iso:country":"GB",
    "sg:address":"157 Stratford Road, Shirley",
    "sg:city":"Solihull",
    "sg:classifiers":[
        {
            "category":"Organizations",
            "subcategory":"Non-profit Organization",
            "type":"Services"
        }
    ],
    "sg:phone":"+44 121 733 2370",
    "sg:postcode":"B90 3AX",
    "sg:province":"West Midlands",
    "sg:tags":[
        "organisation",
        "voluntary",
        "charity"
    ],
    "wof:name":"Barnardo S Shops",
    "wof:placetype":"venue"
},
  "geometry": {"coordinates":[-1.8281129599,52.4144363403],"type":"Point"}
}