{
  "type": "Feature",
  "properties": {
    "addr:full":"82 Park Street Camberley Berkshire GU15 3PT",
    "addr:housenumber":"82",
    "addr:postcode":"gu15 3pt",
    "addr:street":"Park Street",
    "iso:country":"GB",
    "sg:address":"82 Park Street",
    "sg:city":"Camberley",
    "sg:classifiers":[
        {
            "category":"Professional",
            "subcategory":"Management & Consulting",
            "type":"Services"
        }
    ],
    "sg:phone":"+44 1276 686327",
    "sg:postcode":"GU15 3PT",
    "sg:province":"Berkshire",
    "sg:tags":[
        "consultant",
        "business"
    ],
    "wof:name":"M M I Consulting Group",
    "wof:placetype":"venue"
},
  "geometry": {"coordinates":[-0.747608006,51.3359107971],"type":"Point"}
}