{
  "type": "Feature",
  "properties": {
    "addr:full":"Youth Hall, Bruton Road, Maiden Bradley Warminster Somerset BA12 7JE",
    "addr:postcode":"ba12 7je",
    "addr:street":"Bruton Road",
    "iso:country":"GB",
    "sg:address":"Youth Hall, Bruton Road, Maiden Bradley",
    "sg:city":"Warminster",
    "sg:classifiers":[
        {
            "category":"Government",
            "subcategory":"Office",
            "type":"Public Place"
        }
    ],
    "sg:phone":"+44 1985 844085",
    "sg:postcode":"BA12 7JE",
    "sg:province":"Somerset",
    "sg:tags":[
        "education",
        "agency",
        "authority"
    ],
    "wof:name":"Whole World Day Nursery",
    "wof:placetype":"venue"
},
  "geometry": {"coordinates":[-2.2852790356,51.1486434937],"type":"Point"}
}