{
  "type": "Feature",
  "properties": {
    "addr:full":"11 Market Walk Chorley Lancashire PR7 1DE",
    "addr:housenumber":"11",
    "addr:postcode":"pr7 1de",
    "addr:street":"Market Walk",
    "iso:country":"GB",
    "sg:address":"11 Market Walk",
    "sg:city":"Chorley",
    "sg:classifiers":[
        {
            "category":"Sports & Exercise",
            "subcategory":"Sports Center",
            "type":"Entertainment"
        }
    ],
    "sg:phone":"+44 1257 262110",
    "sg:postcode":"PR7 1DE",
    "sg:province":"Lancashire",
    "sg:tags":[
        "shop",
        "good"
    ],
    "wof:name":"Streetwise Sports",
    "wof:placetype":"venue"
},
  "geometry": {"coordinates":[-2.6326630116,53.6538238525],"type":"Point"}
}