{
  "type": "Feature",
  "properties": {
    "addr:full":"The Office, Apple Tree Court Salford Greater Manchester M5 4AY",
    "addr:postcode":"m5 4ay",
    "addr:street":"Tree Court",
    "iso:country":"GB",
    "sg:address":"The Office, Apple Tree Court",
    "sg:city":"Salford",
    "sg:classifiers":[
        {
            "category":"Organizations",
            "subcategory":"Community Association",
            "type":"Services"
        }
    ],
    "sg:phone":"+44 161 743 9233",
    "sg:postcode":"M5 4AY",
    "sg:province":"Greater Manchester",
    "sg:tags":[
        "co-operatives",
        "society",
        "housing",
        "trust"
    ],
    "wof:name":"Apple Tree Court Tenant Management Co Ltd",
    "wof:placetype":"venue"
},
  "geometry": {"coordinates":[-2.2842900753,53.4839782715],"type":"Point"}
}