{
  "type": "Feature",
  "properties": {
    "addr:full":"325 Cowbridge Road East Cardiff Cardiff CF5 1JD",
    "addr:housenumber":"325",
    "addr:postcode":"cf5 1jd",
    "addr:street":"Cowbridge Road East",
    "iso:country":"GB",
    "sg:address":"325 Cowbridge Road East",
    "sg:city":"Cardiff",
    "sg:classifiers":[
        {
            "category":"Restaurant",
            "type":"Food & Drink"
        }
    ],
    "sg:phone":"+44 29 2038 3101",
    "sg:postcode":"CF5 1JD",
    "sg:province":"Cardiff",
    "sg:tags":[
        "indian"
    ],
    "wof:name":"Jonota Palace",
    "wof:placetype":"venue"
},
  "geometry": {"coordinates":[-3.2048969269,51.4817695618],"type":"Point"}
}