{
  "type": "Feature",
  "properties": {
    "iso:country":"GB",
    "sg:address":"Fieldgate, Coltstaple Lane",
    "sg:city":"Horsham",
    "sg:classifiers":[
        {
            "category":"Social Services",
            "subcategory":"Job Training",
            "type":"Services"
        }
    ],
    "sg:phone":"+44 1403 734550",
    "sg:postcode":"RH13 9BB",
    "sg:province":"West Sussex",
    "sg:tags":[
        "translator",
        "interpreter"
    ],
    "wof:name":"C T T Languages",
    "wof:placetype":"venue"
},
  "geometry": {"coordinates":[-0.334266,51.038273],"type":"Point"}
}