{
  "type": "Feature",
  "properties": {
    "addr:full":"Manor Farm, Radclive Valley Buckingham Buckinghamshire MK18 4AB",
    "addr:postcode":"mk18 4ab",
    "addr:street":"Manor;Radclive Valley",
    "iso:country":"GB",
    "sg:address":"Manor Farm, Radclive Valley",
    "sg:city":"Buckingham",
    "sg:classifiers":[
        {
            "category":"Farming",
            "subcategory":"Livestock Farm",
            "type":"Manufacturing & Wholesale Goods"
        }
    ],
    "sg:phone":"+44 1280 812638",
    "sg:postcode":"MK18 4AB",
    "sg:province":"Buckinghamshire",
    "sg:tags":[
        "others"
    ],
    "wof:name":"A F S  Lester",
    "wof:placetype":"venue"
},
  "geometry": {"coordinates":[-1.0156879425,52.0005836487],"type":"Point"}
}