{
  "type": "Feature",
  "properties": {
    "iso:country":"GB",
    "sg:address":"Unit 5 The Tower Centre, Alvescot Rd",
    "sg:city":"Carterton",
    "sg:classifiers":[
        {
            "category":"Shopping",
            "subcategory":"Clothing, Apparel, & Fashions",
            "type":"Retail Goods"
        }
    ],
    "sg:phone":"+44 1993 846141",
    "sg:postcode":"OX18 3JG",
    "sg:province":"Gloucestershire",
    "sg:tags":[
        "shop"
    ],
    "wof:name":"Emerald",
    "wof:placetype":"venue"
},
  "geometry": {"coordinates":[-1.5903840065,51.7606239319],"type":"Point"}
}