{
  "type": "Feature",
  "properties": {
    "addr:full":"58 The Village, Hambleden Henley-on-thames Berkshire RG9 6RT",
    "addr:housenumber":"58",
    "addr:postcode":"rg9 6rt",
    "addr:street":"The Village",
    "iso:country":"GB",
    "sg:address":"58 The Village, Hambleden",
    "sg:city":"Henley-on-thames",
    "sg:classifiers":[
        {
            "category":"Government",
            "subcategory":"Post Office",
            "type":"Public Place"
        }
    ],
    "sg:phone":"+44 1491 571201",
    "sg:postcode":"RG9 6RT",
    "sg:province":"Berkshire",
    "wof:name":"HAMBLEDEN STORES",
    "wof:placetype":"venue"
},
  "geometry": {"coordinates":[-0.903189,51.535297],"type":"Point"}
}