{
  "type": "Feature",
  "properties": {
    "addr:full":"118 Marine Crescent Stourbridge Staffordshire DY8 4XR",
    "addr:housenumber":"118",
    "addr:postcode":"dy8 4xr",
    "addr:street":"Marine Crescent",
    "iso:country":"GB",
    "sg:address":"118 Marine Crescent",
    "sg:city":"Stourbridge",
    "sg:classifiers":[
        {
            "category":"Professional",
            "subcategory":"Engineering",
            "type":"Services"
        },
        {
            "category":"Retail",
            "subcategory":"Auto Repair",
            "type":"Services"
        }
    ],
    "sg:phone":"+44 1384 74772",
    "sg:postcode":"DY8 4XR",
    "sg:province":"Staffordshire",
    "sg:tags":[
        "electrical",
        "engineer",
        "electrician",
        "contractor"
    ],
    "wof:name":"A & S Vehicle Electrical Specialists",
    "wof:placetype":"venue"
},
  "geometry": {"coordinates":[-2.1587269306,52.4731864929],"type":"Point"}
}