{
  "type": "Feature",
  "properties": {
    "iso:country":"GB",
    "sg:address":"Unit 200, Willoughby La, Tottenham",
    "sg:city":"London",
    "sg:classifiers":[
        {
            "category":"Home & Garden",
            "subcategory":"Building Materials",
            "type":"Retail Goods"
        }
    ],
    "sg:phone":"+44 20 8884 2442",
    "sg:postcode":"N17 0SQ",
    "sg:province":"Greater London",
    "sg:tags":[
        "roofing"
    ],
    "wof:name":"Metal Roofing Products Ltd",
    "wof:placetype":"venue"
},
  "geometry": {"coordinates":[-0.054394,51.607697],"type":"Point"}
}