{
  "type": "Feature",
  "properties": {
    "iso:country":"GB",
    "sg:address":"2 Astons Close",
    "sg:city":"Brierley Hill",
    "sg:classifiers":[
        {
            "category":"Building & Trades",
            "subcategory":"Landscaping Services",
            "type":"Services"
        }
    ],
    "sg:phone":"+44 1384 423150",
    "sg:postcode":"DY5 2QT",
    "sg:province":"West Midlands",
    "sg:tags":[
        "irrigation",
        "system"
    ],
    "wof:name":"Sprinkler Irrigation Systems",
    "wof:placetype":"venue"
},
  "geometry": {"coordinates":[-2.124270916,52.4643554688],"type":"Point"}
}