{
  "type": "Feature",
  "properties": {
    "iso:country":"GB",
    "sg:address":"25 Dovecot Street",
    "sg:city":"Stockton-on-tees",
    "sg:classifiers":[
        {
            "category":"Shopping",
            "subcategory":"Hobbies, Toys, & Games",
            "type":"Retail Goods"
        }
    ],
    "sg:postcode":"TS18 1LH",
    "sg:province":"Durham",
    "sg:tags":[
        "computer"
    ],
    "wof:name":"Dovecot Games Centre",
    "wof:placetype":"venue"
},
  "geometry": {"coordinates":[-1.3145279884,54.5642662048],"type":"Point"}
}