{
  "type": "Feature",
  "properties": {
    "addr:full":"Holden Road, Salterbeck Workington Cumbria CA14 5LN",
    "addr:postcode":"ca14 5ln",
    "addr:street":"Holden Road Salterbeck",
    "iso:country":"GB",
    "sg:address":"Holden Road, Salterbeck",
    "sg:city":"Workington",
    "sg:classifiers":[
        {
            "category":"Education",
            "subcategory":"School",
            "type":"Public Place"
        }
    ],
    "sg:phone":"+44 1946 830430",
    "sg:postcode":"CA14 5LN",
    "sg:province":"Cumbria",
    "sg:tags":[
        "local",
        "authority"
    ],
    "wof:name":"St.Marys Catholic Primary School Harrington",
    "wof:placetype":"venue"
},
  "geometry": {"coordinates":[-3.5662589073,54.620716095],"type":"Point"}
}