{
  "type": "Feature",
  "properties": {
    "addr:full":"Sunset Cottage, Wapping Lane York North Yorkshire YO62 6PD",
    "addr:postcode":"yo62 6pd",
    "addr:street":"Wapping Lane",
    "iso:country":"GB",
    "sg:address":"Sunset Cottage, Wapping Lane",
    "sg:city":"York",
    "sg:classifiers":[
        {
            "category":"Home & Garden",
            "subcategory":"Building Materials",
            "type":"Retail Goods"
        }
    ],
    "sg:phone":"+44 1751 431460",
    "sg:postcode":"YO62 6PD",
    "sg:province":"North Yorkshire",
    "sg:tags":[
        "fencing"
    ],
    "wof:name":"A Smith",
    "wof:placetype":"venue"
},
  "geometry": {"coordinates":[-0.91685,54.24757],"type":"Point"}
}