{
  "type": "Feature",
  "properties": {
    "iso:country":"GB",
    "sg:address":"14 Chester Rd",
    "sg:city":"Northwich",
    "sg:classifiers":[
        {
            "category":"Social Services",
            "subcategory":"Retirement Home",
            "type":"Services"
        }
    ],
    "sg:phone":"+44 1606 77771",
    "sg:postcode":"CW8 1JB",
    "sg:province":"Cheshire",
    "sg:tags":[
        "care"
    ],
    "wof:name":"G P Homecare Services",
    "wof:placetype":"venue"
},
  "geometry": {"coordinates":[-2.5217430592,53.2570724487],"type":"Point"}
}