{
  "type": "Feature",
  "properties": {
    "addr:full":"7 St Clair Close, Clayhall Ilford Essex IG5 0PA",
    "addr:housenumber":"7",
    "addr:postcode":"ig5 0pa",
    "addr:street":"St Clair Close",
    "iso:country":"GB",
    "sg:address":"7 St Clair Close, Clayhall",
    "sg:city":"Ilford",
    "sg:classifiers":[
        {
            "category":"Building & Trades",
            "subcategory":"Construction",
            "type":"Services"
        }
    ],
    "sg:phone":"+44 20 8550 5216",
    "sg:postcode":"IG5 0PA",
    "sg:province":"Essex",
    "sg:tags":[
        "builder"
    ],
    "wof:name":"D D C Builders Ltd",
    "wof:placetype":"venue"
},
  "geometry": {"coordinates":[0.058863,51.59277],"type":"Point"}
}