{
  "type": "Feature",
  "properties": {
    "addr:full":"Trefwrdan Isaf, Nevern Newport Pembrokeshire SA42 0PA",
    "addr:postcode":"sa42 0pa",
    "iso:country":"GB",
    "sg:address":"Trefwrdan Isaf, Nevern",
    "sg:city":"Newport",
    "sg:classifiers":[
        {
            "category":"Farming",
            "subcategory":"Dairy Farm",
            "type":"Manufacturing & Wholesale Goods"
        }
    ],
    "sg:phone":"+44 1239 881226",
    "sg:postcode":"SA42 0PA",
    "sg:province":"Pembrokeshire",
    "wof:name":"D W & M J Owens",
    "wof:placetype":"venue"
},
  "geometry": {"coordinates":[-4.8339772224,52.0160331726],"type":"Point"}
}