{
  "type": "Feature",
  "properties": {
    "iso:country":"GB",
    "sg:address":"2 Water Lane",
    "sg:city":"London",
    "sg:classifiers":[
        {
            "category":"Shopping",
            "subcategory":"Stationery & Office Supplies",
            "type":"Retail Goods"
        },
        {
            "category":"Fast Food",
            "type":"Food & Drink"
        }
    ],
    "sg:phone":"+44 20 8534 6673",
    "sg:postcode":"E15 4NH",
    "sg:province":"Greater London",
    "sg:tags":[
        "mobile",
        "away",
        "catering",
        "take",
        "meal",
        "outlet"
    ],
    "wof:name":"Cater Trailer",
    "wof:placetype":"venue"
},
  "geometry": {"coordinates":[0.00838,51.54459],"type":"Point"}
}