{
  "type": "Feature",
  "properties": {
    "addr:full":"86 Arundel Avenue, Ewell Epsom Surrey KT17 2RL",
    "addr:housenumber":"86",
    "addr:postcode":"kt17 2rl",
    "addr:street":"Arundel Avenue",
    "iso:country":"GB",
    "sg:address":"86 Arundel Avenue, Ewell",
    "sg:city":"Epsom",
    "sg:classifiers":[
        {
            "category":"Professional",
            "subcategory":"Computer Services",
            "type":"Services"
        }
    ],
    "sg:phone":"+44 20 8394 2891",
    "sg:postcode":"KT17 2RL",
    "sg:province":"Surrey",
    "sg:tags":[
        "system",
        "software"
    ],
    "wof:name":"Jupecoll Ltd.",
    "wof:placetype":"venue"
},
  "geometry": {"coordinates":[-0.2344699949,51.3489761353],"type":"Point"}
}