{
  "type": "Feature",
  "properties": {
    "iso:country":"GB",
    "sg:address":"Newburgh, Coxwold",
    "sg:city":"York",
    "sg:classifiers":[
        {
            "category":"Farming",
            "subcategory":"Farm",
            "type":"Manufacturing & Wholesale Goods"
        }
    ],
    "sg:phone":"+44 1347 868488",
    "sg:postcode":"YO61 4AS",
    "sg:province":"North Yorkshire",
    "sg:tags":[
        "mixed",
        "crop"
    ],
    "wof:name":"Newburgh Home Farms",
    "wof:placetype":"venue"
},
  "geometry": {"coordinates":[-1.1858830452,54.1882553101],"type":"Point"}
}