{
  "type": "Feature",
  "properties": {
    "iso:country":"GB",
    "sg:address":"Middle Row",
    "sg:city":"Maidstone",
    "sg:classifiers":[
        {
            "category":"Bars & Pubs",
            "type":"Food & Drink"
        }
    ],
    "sg:phone":"+44 1622 606941",
    "sg:postcode":"ME14 1TG",
    "sg:province":"Kent",
    "sg:tags":[
        "pubs",
        "inn"
    ],
    "wof:name":"Bar Coast",
    "wof:placetype":"venue"
},
  "geometry": {"coordinates":[0.5250849724,51.2737998962],"type":"Point"}
}