{
  "type": "Feature",
  "properties": {
    "iso:country":"GB",
    "sg:address":"Tubwell Row",
    "sg:city":"Darlington",
    "sg:classifiers":[
        {
            "category":"Museum",
            "subcategory":"Art Museum",
            "type":"Entertainment"
        }
    ],
    "sg:phone":"+44 1325 463795",
    "sg:postcode":"DL1 1PD",
    "sg:province":"Durham",
    "sg:tags":[
        "gallery"
    ],
    "wof:name":"Darlington Museum & Art Gallery",
    "wof:placetype":"venue"
},
  "geometry": {"coordinates":[-1.553325,54.524952],"type":"Point"}
}