{
  "type": "Feature",
  "properties": {
    "iso:country":"GB",
    "sg:address":"24 West Clyde Street",
    "sg:city":"Helensburgh",
    "sg:classifiers":[
        {
            "category":"Shopping",
            "subcategory":"Gifts & Souvenirs",
            "type":"Retail Goods"
        }
    ],
    "sg:postcode":"G84 8SQ",
    "sg:province":"Argyll and Bute",
    "sg:tags":[
        "shop"
    ],
    "wof:name":"M Cant",
    "wof:placetype":"venue"
},
  "geometry": {"coordinates":[-4.735717,56.003387],"type":"Point"}
}