{
  "type": "Feature",
  "properties": {
    "iso:country":"GB",
    "sg:address":"8 Pages Court, Yatton",
    "sg:city":"Bristol",
    "sg:classifiers":[
        {
            "category":"Shopping",
            "subcategory":"Pharmacy",
            "type":"Retail Goods"
        }
    ],
    "sg:phone":"+44 1934 832236",
    "sg:postcode":"BS49 4EG",
    "sg:province":"Somerset",
    "sg:tags":[
        "pharmacist",
        "chemist"
    ],
    "wof:name":"Lloyds Chemist",
    "wof:placetype":"venue"
},
  "geometry": {"coordinates":[-2.823439,51.38858],"type":"Point"}
}