{
  "type": "Feature",
  "properties": {
    "addr:full":"1 Cavalier Way East Grinstead East Sussex RH19 4SE",
    "addr:housenumber":"1",
    "addr:postcode":"rh19 4se",
    "addr:street":"Cavalier Way",
    "iso:country":"GB",
    "sg:address":"1 Cavalier Way",
    "sg:city":"East Grinstead",
    "sg:classifiers":[
        {
            "category":"Food & Beverages",
            "subcategory":"Specialty",
            "type":"Retail Goods"
        }
    ],
    "sg:postcode":"RH19 4SE",
    "sg:province":"East Sussex",
    "sg:tags":[
        "product",
        "health"
    ],
    "wof:name":"West Nutrition",
    "wof:placetype":"venue"
},
  "geometry": {"coordinates":[-0.005263,51.119034],"type":"Point"}
}