{
  "type": "Feature",
  "properties": {
    "addr:full":"12 Tithebarn St Bury Lancashire BL9 0JR",
    "addr:housenumber":"12",
    "addr:postcode":"bl9 0jr",
    "addr:street":"Tithebarn St",
    "iso:country":"GB",
    "sg:address":"12 Tithebarn St",
    "sg:city":"Bury",
    "sg:classifiers":[
        {
            "category":"Professional",
            "subcategory":"Lawyer & Legal Services",
            "type":"Services"
        }
    ],
    "sg:phone":"+44 161 797 4326",
    "sg:postcode":"BL9 0JR",
    "sg:province":"Lancashire",
    "sg:tags":[
        "advice",
        "counselling"
    ],
    "wof:name":"Bury Unemployed Workers Centre",
    "wof:placetype":"venue"
},
  "geometry": {"coordinates":[-2.295175,53.594563],"type":"Point"}
}