{
  "type": "Feature",
  "properties": {
    "iso:country":"GB",
    "sg:address":"37 Westwood Avenue",
    "sg:city":"Ipswich",
    "sg:classifiers":[
        {
            "category":"Insurance",
            "subcategory":"Insurance Agent",
            "type":"Services"
        },
        {
            "category":"Real Estate",
            "subcategory":"Developer",
            "type":"Services"
        },
        {
            "category":"Banks & Credit Unions",
            "subcategory":"Financial Services",
            "type":"Services"
        }
    ],
    "sg:phone":"+44 1473 231373",
    "sg:postcode":"IP1 4EQ",
    "sg:province":"Suffolk",
    "sg:tags":[
        "consultant",
        "property"
    ],
    "wof:name":"Oliver T Properties Ltd.",
    "wof:placetype":"venue"
},
  "geometry": {"coordinates":[1.1419420242,52.0676002502],"type":"Point"}
}