{
  "type": "Feature",
  "properties": {
    "addr:full":"Welbury Farm, Hempstead Lane Hailsham East Sussex BN27 3AE",
    "addr:housenumber":"welbury",
    "addr:postcode":"bn27 3ae",
    "addr:street":"Hempstead Lane",
    "iso:country":"GB",
    "sg:address":"Welbury Farm, Hempstead Lane",
    "sg:city":"Hailsham",
    "sg:classifiers":[
        {
            "category":"Farming",
            "subcategory":"Livestock Farm",
            "type":"Manufacturing & Wholesale Goods"
        }
    ],
    "sg:phone":"+44 1323 841024",
    "sg:postcode":"BN27 3AE",
    "sg:province":"East Sussex",
    "sg:tags":[
        "others"
    ],
    "wof:name":"John E Gutsell",
    "wof:placetype":"venue"
},
  "geometry": {"coordinates":[0.25652,50.865383],"type":"Point"}
}