{
  "type": "Feature",
  "properties": {
    "iso:country":"GB",
    "sg:address":"73 Milton Street, Palfrey",
    "sg:city":"Walsall",
    "sg:classifiers":[
        {
            "category":"Food & Beverages",
            "subcategory":"Supermarket",
            "type":"Retail Goods"
        }
    ],
    "sg:phone":"+44 1922 449368",
    "sg:postcode":"WS1 4JT",
    "sg:province":"West Midlands",
    "wof:name":"Fine Price Supermarket",
    "wof:placetype":"venue"
},
  "geometry": {"coordinates":[-1.987931,52.574211],"type":"Point"}
}