{
  "type": "Feature",
  "properties": {
    "addr:full":"Ebor House, Ebor Street Selby East Riding of Yorkshire YO8 4AH",
    "addr:postcode":"yo8 4ah",
    "addr:street":"Ebor Street",
    "iso:country":"GB",
    "sg:address":"Ebor House, Ebor Street",
    "sg:city":"Selby",
    "sg:classifiers":[
        {
            "category":"Personal",
            "subcategory":"Beauty Salon",
            "type":"Services"
        }
    ],
    "sg:phone":"+44 1757 707359",
    "sg:postcode":"YO8 4AH",
    "sg:province":"East Riding of Yorkshire",
    "sg:tags":[
        "unisex",
        "hairdresser"
    ],
    "wof:name":"Uppercut",
    "wof:placetype":"venue"
},
  "geometry": {"coordinates":[-1.0734540224,53.7824249268],"type":"Point"}
}