{
  "type": "Feature",
  "properties": {
    "addr:full":"52 Longdale Lane, Ravenshead Nottingham Nottinghamshire NG15 9AD",
    "addr:housenumber":"52",
    "addr:postcode":"ng15 9ad",
    "addr:street":"Longdale Lane",
    "iso:country":"GB",
    "sg:address":"52 Longdale Lane, Ravenshead",
    "sg:city":"Nottingham",
    "sg:classifiers":[
        {
            "category":"Banks & Credit Unions",
            "subcategory":"Bank",
            "type":"Services"
        }
    ],
    "sg:phone":"+44 1623 491661",
    "sg:postcode":"NG15 9AD",
    "sg:province":"Nottinghamshire",
    "sg:tags":[
        "broker",
        "mortgage"
    ],
    "wof:name":"Mansfield Finance & Mortgage",
    "wof:placetype":"venue"
},
  "geometry": {"coordinates":[-1.1640779972,53.0803413391],"type":"Point"}
}