{
  "type": "Feature",
  "properties": {
    "addr:full":"48 North View, Halifax Road Todmorden Lancashire OL14 5QG",
    "addr:housenumber":"48",
    "addr:postcode":"ol14 5qg",
    "addr:street":"North View Halifax Road",
    "iso:country":"GB",
    "sg:address":"48 North View, Halifax Road",
    "sg:city":"Todmorden",
    "sg:classifiers":[
        {
            "category":"Autos & Motor Vehicles",
            "subcategory":"Auto Supplies",
            "type":"Retail Goods"
        },
        {
            "category":"Retail",
            "subcategory":"Auto Repair",
            "type":"Services"
        }
    ],
    "sg:phone":"+44 1706 813649",
    "sg:postcode":"OL14 5QG",
    "sg:province":"Lancashire",
    "sg:tags":[
        "car",
        "part",
        "electrician",
        "accessory"
    ],
    "wof:name":"R Ford Motor Spares",
    "wof:placetype":"venue"
},
  "geometry": {"coordinates":[-2.097308,53.71431],"type":"Point"}
}