{
  "type": "Feature",
  "properties": {
    "iso:country":"GB",
    "sg:address":"Unit 5 107-111 Peascod Street",
    "sg:city":"Windsor",
    "sg:classifiers":[
        {
            "category":"Shopping",
            "subcategory":"News",
            "type":"Retail Goods"
        },
        {
            "category":"Food & Beverages",
            "subcategory":"Groceries & Convenience Stores",
            "type":"Retail Goods"
        }
    ],
    "sg:phone":"+44 1753 840548",
    "sg:postcode":"SL4 1DN",
    "sg:province":"Berkshire",
    "sg:tags":[
        "newsagent"
    ],
    "wof:name":"Forbuoys",
    "wof:placetype":"venue"
},
  "geometry": {"coordinates":[-0.610336,51.481552],"type":"Point"}
}