{
  "type": "Feature",
  "properties": {
    "iso:country":"GB",
    "sg:address":"36 Peffermill Road",
    "sg:city":"Edinburgh",
    "sg:classifiers":[
        {
            "category":"Autos & Motor Vehicles",
            "subcategory":"Motorcycle Sales",
            "type":"Retail Goods"
        }
    ],
    "sg:phone":"+44 131 667 7305",
    "sg:postcode":"EH16 5LL",
    "sg:province":"City of Edinburgh",
    "sg:tags":[
        "scooter",
        "cycle"
    ],
    "wof:name":"Two Wheels",
    "wof:placetype":"venue"
},
  "geometry": {"coordinates":[-3.158072,55.930489],"type":"Point"}
}