{
  "type": "Feature",
  "properties": {
    "addr:full":"15 Charter Street Leicester Leicestershire LE1 3UD",
    "addr:housenumber":"15",
    "addr:postcode":"le1 3ud",
    "addr:street":"Charter Street",
    "iso:country":"GB",
    "sg:address":"15 Charter Street",
    "sg:city":"Leicester",
    "sg:classifiers":[
        {
            "category":"Retail",
            "subcategory":"Auto Repair",
            "type":"Services"
        }
    ],
    "sg:phone":"+44 116 262 6715",
    "sg:postcode":"LE1 3UD",
    "sg:province":"Leicestershire",
    "sg:tags":[
        "modification",
        "garage"
    ],
    "wof:name":"Ansa Motor Works",
    "wof:placetype":"venue"
},
  "geometry": {"coordinates":[-1.131555,52.643284],"type":"Point"}
}