{
  "type": "Feature",
  "properties": {
    "addr:full":"51 Broad Street, Parkgate Rotherham South Yorkshire S62 6DU",
    "addr:housenumber":"51",
    "addr:postcode":"s62 6du",
    "addr:street":"Broad Street Parkgate",
    "iso:country":"GB",
    "sg:address":"51 Broad Street, Parkgate",
    "sg:city":"Rotherham",
    "sg:classifiers":[
        {
            "category":"Personal",
            "subcategory":"Beauty Salon",
            "type":"Services"
        },
        {
            "category":"Personal",
            "subcategory":"Barber",
            "type":"Services"
        }
    ],
    "sg:phone":"+44 1709 526607",
    "sg:postcode":"S62 6DU",
    "sg:province":"South Yorkshire",
    "sg:tags":[
        "unisex",
        "hairdresser"
    ],
    "wof:name":"Take Five",
    "wof:placetype":"venue"
},
  "geometry": {"coordinates":[-1.343632,53.452377],"type":"Point"}
}