{
  "type": "Feature",
  "properties": {
    "addr:full":"Hillend House, Biggar Road Edinburgh City of Edinburgh EH10 7DX",
    "addr:postcode":"eh10 7dx",
    "addr:street":"Biggar Road",
    "iso:country":"GB",
    "sg:address":"Hillend House, Biggar Road",
    "sg:city":"Edinburgh",
    "sg:classifiers":[
        {
            "category":"Professional",
            "type":"Services"
        }
    ],
    "sg:phone":"+44 131 445 5885",
    "sg:postcode":"EH10 7DX",
    "sg:province":"City of Edinburgh",
    "sg:tags":[
        "writer"
    ],
    "wof:name":"Maclean Dubois",
    "wof:placetype":"venue"
},
  "geometry": {"coordinates":[-3.202737093,55.8950195312],"type":"Point"}
}