{
  "type": "Feature",
  "properties": {
    "iso:country":"GB",
    "sg:address":"31 Elmstead Gardens",
    "sg:city":"Worcester Park",
    "sg:classifiers":[
        {
            "category":"Manufacturing",
            "subcategory":"Buildings",
            "type":"Manufacturing & Wholesale Goods"
        }
    ],
    "sg:phone":"+44 20 8330 1403",
    "sg:postcode":"KT4 7BD",
    "sg:province":"Surrey",
    "sg:tags":[
        "system",
        "air conditioning"
    ],
    "wof:name":"Cristopia",
    "wof:placetype":"venue"
},
  "geometry": {"coordinates":[-0.247306,51.373951],"type":"Point"}
}