{
  "type": "Feature",
  "properties": {
    "iso:country":"GB",
    "sg:address":"Egham Hill",
    "sg:city":"Egham",
    "sg:classifiers":[
        {
            "category":"Shopping",
            "subcategory":"Books",
            "type":"Retail Goods"
        }
    ],
    "sg:phone":"+44 1784 471272",
    "sg:postcode":"TW20 0EX",
    "sg:province":"Surrey",
    "sg:tags":[
        "bookseller"
    ],
    "wof:name":"Dillons The Bookstore",
    "wof:placetype":"venue"
},
  "geometry": {"coordinates":[-0.555013001,51.4313316345],"type":"Point"}
}