{
  "type": "Feature",
  "properties": {
    "addr:full":"19 Oxford St Woodstock Oxfordshire OX20 1TH",
    "addr:housenumber":"19",
    "addr:postcode":"ox20 1th",
    "addr:street":"Oxford St",
    "iso:country":"GB",
    "sg:address":"19 Oxford St",
    "sg:city":"Woodstock",
    "sg:classifiers":[
        {
            "category":"Shopping",
            "subcategory":"Antiques",
            "type":"Retail Goods"
        }
    ],
    "sg:postcode":"OX20 1TH",
    "sg:province":"Oxfordshire",
    "wof:name":"Peedell,David,",
    "wof:placetype":"venue"
},
  "geometry": {"coordinates":[-1.3539539576,51.8472290039],"type":"Point"}
}