{
  "type": "Feature",
  "properties": {
    "addr:full":"Unit 1 Stewart House, Kingsway East Dundee Dundee City DD4 7RE",
    "addr:housenumber":"unit 1 stewart house",
    "addr:postcode":"dd4 7re",
    "addr:street":"Kingsway",
    "iso:country":"GB",
    "sg:address":"Unit 1 Stewart House, Kingsway East",
    "sg:city":"Dundee",
    "sg:classifiers":[
        {
            "category":"Home & Garden",
            "subcategory":"Home Furnishings",
            "type":"Retail Goods"
        }
    ],
    "sg:phone":"+44 1382 453572",
    "sg:postcode":"DD4 7RE",
    "sg:province":"Dundee City",
    "sg:tags":[
        "furnishers",
        "planner",
        "kitchen"
    ],
    "wof:name":"Space Kitchens & Bedrooms",
    "wof:placetype":"venue"
},
  "geometry": {"coordinates":[-2.955955,56.480495],"type":"Point"}
}