{
  "type": "Feature",
  "properties": {
    "addr:full":"Suite D, Drapers Way Stevenage Hertfordshire SG1 3DT",
    "addr:housenumber":"suite",
    "addr:postcode":"sg1 3dt",
    "addr:street":"Drapers Way",
    "iso:country":"GB",
    "sg:address":"Suite D, Drapers Way",
    "sg:city":"Stevenage",
    "sg:classifiers":[
        {
            "category":"Real Estate",
            "subcategory":"Developer",
            "type":"Services"
        }
    ],
    "sg:phone":"+44 1438 747016",
    "sg:postcode":"SG1 3DT",
    "sg:province":"Hertfordshire",
    "sg:tags":[
        "property"
    ],
    "wof:name":"Broadwater Properties",
    "wof:placetype":"venue"
},
  "geometry": {"coordinates":[-0.2084890008,51.9108963013],"type":"Point"}
}