{
  "type": "Feature",
  "properties": {
    "addr:full":"5-9 Cross Street Oswestry Shropshire SY11 2NF",
    "addr:housenumber":"5-9",
    "addr:postcode":"sy11 2nf",
    "addr:street":"Cross Street",
    "iso:country":"GB",
    "sg:address":"5-9 Cross Street",
    "sg:city":"Oswestry",
    "sg:classifiers":[
        {
            "category":"Shopping",
            "subcategory":"Shoes",
            "type":"Retail Goods"
        }
    ],
    "sg:phone":"+44 1691 670654",
    "sg:postcode":"SY11 2NF",
    "sg:province":"Shropshire",
    "sg:tags":[
        "shop"
    ],
    "wof:name":"Stylo Barratt Shoes Ltd.",
    "wof:placetype":"venue"
},
  "geometry": {"coordinates":[-3.054959,52.859451],"type":"Point"}
}