{
  "type": "Feature",
  "properties": {
    "addr:full":"Unit 7 Shireoaks Business Centre, Shireoaks Road Worksop Nottinghamshire S81 8ND",
    "addr:housenumber":"unit 7 shireoaks business centre",
    "addr:postcode":"s81 8nd",
    "addr:street":"Shireoaks Road",
    "iso:country":"GB",
    "sg:address":"Unit 7 Shireoaks Business Centre, Shireoaks Road",
    "sg:city":"Worksop",
    "sg:classifiers":[
        {
            "category":"Sports & Exercise",
            "subcategory":"Tennis Court",
            "type":"Entertainment"
        }
    ],
    "sg:phone":"+44 1909 531999",
    "sg:postcode":"S81 8ND",
    "sg:province":"Nottinghamshire",
    "sg:tags":[
        "breakdown",
        "recovery"
    ],
    "wof:name":"Accident Breakdown Centre",
    "wof:placetype":"venue"
},
  "geometry": {"coordinates":[-1.1656479836,53.3201408386],"type":"Point"}
}