{
  "type": "Feature",
  "properties": {
    "addr:full":"Liverpool Rd Liverpool Merseyside L36 3RN",
    "addr:postcode":"l36 3rn",
    "addr:street":"Liverpool Rd",
    "iso:country":"GB",
    "sg:address":"Liverpool Rd",
    "sg:city":"Liverpool",
    "sg:classifiers":[
        {
            "category":"Autos & Motor Vehicles",
            "subcategory":"Fuel & Gas Station",
            "type":"Retail Goods"
        }
    ],
    "sg:phone":"+44 151 443 6920",
    "sg:postcode":"L36 3RN",
    "sg:province":"Merseyside",
    "sg:tags":[
        "hr",
        "petrol"
    ],
    "wof:name":"Shell Crescent",
    "wof:placetype":"venue"
},
  "geometry": {"coordinates":[-2.860654,53.421764],"type":"Point"}
}