{
  "type": "Feature",
  "properties": {
    "iso:country":"GB",
    "sg:address":"Unit 37, Bowen Ind Est, Aberbargoed",
    "sg:city":"Bargoed",
    "sg:classifiers":[
        {
            "category":"Shopping",
            "subcategory":"Party Supplies",
            "type":"Retail Goods"
        }
    ],
    "sg:phone":"+44 1443 822790",
    "sg:postcode":"CF81 9EP",
    "sg:province":"Caerphilly",
    "sg:tags":[
        "plan",
        "agent"
    ],
    "wof:name":"Reflections Giftware Parties",
    "wof:placetype":"venue"
},
  "geometry": {"coordinates":[-3.215136,51.683956],"type":"Point"}
}