{
  "type": "Feature",
  "properties": {
    "addr:full":"8 Sandhurst Dr Nottingham Nottinghamshire NG11 6HY",
    "addr:housenumber":"8",
    "addr:postcode":"ng11 6hy",
    "addr:street":"Sandhurst Dr",
    "iso:country":"GB",
    "sg:address":"8 Sandhurst Dr",
    "sg:city":"Nottingham",
    "sg:classifiers":[
        {
            "category":"Insurance",
            "subcategory":"Health Insurance",
            "type":"Services"
        }
    ],
    "sg:phone":"+44 115 984 4130",
    "sg:postcode":"NG11 6HY",
    "sg:province":"Nottinghamshire",
    "sg:tags":[
        "indemnity"
    ],
    "wof:name":"Trade Indemnity Heller Commercial Finance Ltd",
    "wof:placetype":"venue"
},
  "geometry": {"coordinates":[-1.1543550491,52.889755249],"type":"Point"}
}