{
  "type": "Feature",
  "properties": {
    "addr:full":"Greenhill Sherborne Dorset DT9 4EP",
    "addr:postcode":"dt9 4ep",
    "addr:street":"Greenhill",
    "iso:country":"GB",
    "sg:address":"Greenhill",
    "sg:city":"Sherborne",
    "sg:classifiers":[
        {
            "category":"Restaurant",
            "type":"Food & Drink"
        }
    ],
    "sg:phone":"+44 1935 813969",
    "sg:postcode":"DT9 4EP",
    "sg:province":"Dorset",
    "wof:name":"THE GREENHILL RESTAURANT",
    "wof:placetype":"venue"
},
  "geometry": {"coordinates":[-2.5193378925,50.9502944946],"type":"Point"}
}