{
  "type": "Feature",
  "properties": {
    "addr:full":"19 St James Street Okehampton Devon EX20 1DH",
    "addr:housenumber":"19",
    "addr:postcode":"ex20 1dh",
    "addr:street":"St James Street",
    "iso:country":"GB",
    "sg:address":"19 St James Street",
    "sg:city":"Okehampton",
    "sg:classifiers":[
        {
            "category":"Professional",
            "subcategory":"Computer Services",
            "type":"Services"
        }
    ],
    "sg:postcode":"EX20 1DH",
    "sg:province":"Devon",
    "sg:tags":[
        "information"
    ],
    "wof:name":"Okehampton O K Ltd.",
    "wof:placetype":"venue"
},
  "geometry": {"coordinates":[-4.0019030571,50.7385253906],"type":"Point"}
}