{
  "type": "Feature",
  "properties": {
    "addr:full":"48 The Grove, St Margarets Road Twickenham Greater London TW1 1RB",
    "addr:housenumber":"48",
    "addr:postcode":"tw1 1rb",
    "addr:street":"The Grove St Margarets Road",
    "iso:country":"GB",
    "sg:address":"48 The Grove, St Margarets Road",
    "sg:city":"Twickenham",
    "sg:classifiers":[
        {
            "category":"Health Services",
            "subcategory":"Health Practitioner",
            "type":"Services"
        },
        {
            "category":"Health Services",
            "subcategory":"Podiatrist",
            "type":"Services"
        }
    ],
    "sg:phone":"+44 20 8744 1694",
    "sg:postcode":"TW1 1RB",
    "sg:province":"Greater London",
    "sg:tags":[
        "podiatrists",
        "hypnotherapists",
        "chiropodist"
    ],
    "wof:name":"Susan Ratcliffe",
    "wof:placetype":"venue"
},
  "geometry": {"coordinates":[-0.3215740025,51.4566040039],"type":"Point"}
}