{
  "type": "Feature",
  "properties": {
    "addr:full":"Studio Ho, 19a Livingstone Rd Newbury Berkshire RG14 7PD",
    "addr:housenumber":"19a",
    "addr:postcode":"rg14 7pd",
    "addr:street":"Livingstone Rd",
    "iso:country":"GB",
    "sg:address":"Studio Ho, 19a Livingstone Rd",
    "sg:city":"Newbury",
    "sg:classifiers":[
        {
            "category":"Communications",
            "type":"Services"
        }
    ],
    "sg:postcode":"RG14 7PD",
    "sg:province":"Berkshire",
    "sg:tags":[
        "audio-visual"
    ],
    "wof:name":"Payne,Tim,",
    "wof:placetype":"venue"
},
  "geometry": {"coordinates":[-1.325872,51.405872],"type":"Point"}
}