{
  "type": "Feature",
  "properties": {
    "addr:full":"60 High St Whitchurch Cheshire SY13 1BB",
    "addr:housenumber":"60",
    "addr:postcode":"sy13 1bb",
    "addr:street":"High St",
    "iso:country":"GB",
    "sg:address":"60 High St",
    "sg:city":"Whitchurch",
    "sg:classifiers":[
        {
            "category":"Restaurant",
            "type":"Food & Drink"
        }
    ],
    "sg:phone":"+44 1948 662248",
    "sg:postcode":"SY13 1BB",
    "sg:province":"Cheshire",
    "sg:tags":[
        "italian"
    ],
    "wof:name":"Tolchards",
    "wof:placetype":"venue"
},
  "geometry": {"coordinates":[-2.685114,52.970211],"type":"Point"}
}