{
  "type": "Feature",
  "properties": {
    "addr:full":"The Ridgewood Centre, 1 Ridgewood Drive, Frimley Camberley Hampshire GU16 9QE",
    "addr:housenumber":"1",
    "addr:postcode":"gu16 9qe",
    "addr:street":"Ridgewood Drive",
    "iso:country":"GB",
    "sg:address":"The Ridgewood Centre, 1 Ridgewood Drive, Frimley",
    "sg:city":"Camberley",
    "sg:classifiers":[
        {
            "category":"Professional",
            "subcategory":"Lawyer & Legal Services",
            "type":"Services"
        }
    ],
    "sg:phone":"+44 1276 676048",
    "sg:postcode":"GU16 9QE",
    "sg:province":"Hampshire",
    "sg:tags":[
        "advice",
        "counselling"
    ],
    "wof:name":"Youth Counselling Service",
    "wof:placetype":"venue"
},
  "geometry": {"coordinates":[-0.70383,51.323479],"type":"Point"}
}