{
  "type": "Feature",
  "properties": {
    "iso:country":"GB",
    "sg:address":"Ellingham",
    "sg:city":"Chathill",
    "sg:classifiers":[
        {
            "category":"Farming",
            "subcategory":"Livestock Farm",
            "type":"Manufacturing & Wholesale Goods"
        }
    ],
    "sg:postcode":"NE67 5EZ",
    "sg:province":"Northumberland",
    "sg:tags":[
        "others"
    ],
    "wof:name":"Ellingham Home Farm",
    "wof:placetype":"venue"
},
  "geometry": {"coordinates":[-1.705524,55.536743],"type":"Point"}
}