{
  "type": "Feature",
  "properties": {
    "iso:country":"GB",
    "sg:address":"120 High Street",
    "sg:city":"Newmarket",
    "sg:classifiers":[
        {
            "category":"Professional",
            "subcategory":"Art Services",
            "type":"Services"
        }
    ],
    "sg:phone":"+44 1638 600960",
    "sg:postcode":"CB8 8JP",
    "sg:province":"Cambridgeshire",
    "sg:tags":[
        "photographer"
    ],
    "wof:name":"The Newmarket Phto Co.",
    "wof:placetype":"venue"
},
  "geometry": {"coordinates":[0.4042260051,52.2433280945],"type":"Point"}
}