{
  "type": "Feature",
  "properties": {
    "addr:full":"Waltham Cross Service Station, Crossbrook Street Waltham Cross Essex EN8 8LR",
    "addr:postcode":"en8 8lr",
    "addr:street":"Crossbrook Street",
    "iso:country":"GB",
    "sg:address":"Waltham Cross Service Station, Crossbrook Street",
    "sg:city":"Waltham Cross",
    "sg:classifiers":[
        {
            "category":"Retail",
            "subcategory":"Auto Repair",
            "type":"Services"
        }
    ],
    "sg:phone":"+44 1992 632625",
    "sg:postcode":"EN8 8LR",
    "sg:province":"Essex",
    "sg:tags":[
        "modification",
        "garage"
    ],
    "wof:name":"Waltham Cross Service Station",
    "wof:placetype":"venue"
},
  "geometry": {"coordinates":[-0.033814,51.69051],"type":"Point"}
}