{
  "type": "Feature",
  "properties": {
    "iso:country":"GB",
    "sg:address":"Seudar, Barcaldine",
    "sg:city":"Oban",
    "sg:classifiers":[
        {
            "category":"Professional",
            "subcategory":"Advertising",
            "type":"Services"
        }
    ],
    "sg:postcode":"PA37 1SG",
    "sg:province":"Argyll and Bute",
    "sg:tags":[
        "agency"
    ],
    "wof:name":"Smith,Robert Francis,",
    "wof:placetype":"venue"
},
  "geometry": {"coordinates":[-5.317561,56.521923],"type":"Point"}
}