{
  "type": "Feature",
  "properties": {
    "iso:country":"GB",
    "sg:address":"26-28 Sceptre St",
    "sg:city":"Newcastle Upon Tyne",
    "sg:classifiers":[
        {
            "category":"Place Of Worship",
            "type":"Public Place"
        }
    ],
    "sg:phone":"+44 191 272 4505",
    "sg:postcode":"NE4 6PQ",
    "sg:province":"Tyne and Wear",
    "wof:name":"Shah Jalal Mosque & Islamic Centre",
    "wof:placetype":"venue"
},
  "geometry": {"coordinates":[-1.6384030581,54.9713554382],"type":"Point"}
}