{
  "type": "Feature",
  "properties": {
    "addr:full":"181 Copnor Rd Portsmouth Hampshire PO3 5BT",
    "addr:housenumber":"181",
    "addr:postcode":"hampshire po3 5bt",
    "addr:street":"Copnor Rd",
    "iso:country":"GB",
    "sg:address":"181 Copnor Rd",
    "sg:city":"Portsmouth",
    "sg:classifiers":[
        {
            "category":"Food & Beverages",
            "subcategory":"Meat & Fish",
            "type":"Retail Goods"
        }
    ],
    "sg:phone":"+44 23 9266 4185",
    "sg:postcode":"PO3 5BT",
    "sg:province":"Hampshire",
    "sg:tags":[
        "chip"
    ],
    "wof:name":"The Tall Ship",
    "wof:placetype":"venue"
},
  "geometry": {"coordinates":[-1.064764,50.81601],"type":"Point"}
}