{
  "type": "Feature",
  "properties": {
    "iso:country":"GB",
    "sg:address":"13/19 Fort Pendlestone, Telford Road",
    "sg:city":"Bridgnorth",
    "sg:classifiers":[
        {
            "category":"Home & Garden",
            "subcategory":"Carpets & Floor Coverings",
            "type":"Retail Goods"
        }
    ],
    "sg:phone":"+44 1746 764118",
    "sg:postcode":"WV15 5NG",
    "sg:province":"Shropshire",
    "sg:tags":[
        "cleaner",
        "upholstery"
    ],
    "wof:name":"Servicemaster Shropshire/Cambrian",
    "wof:placetype":"venue"
},
  "geometry": {"coordinates":[-2.40978,52.541981],"type":"Point"}
}