{
  "type": "Feature",
  "properties": {
    "addr:full":"Cevantes House, 5-9 Headstone Road Harrow Greater London HA1 1PD",
    "addr:housenumber":"5-9",
    "addr:postcode":"ha1 1pd",
    "addr:street":"Headstone Road",
    "iso:country":"GB",
    "sg:address":"Cevantes House, 5-9 Headstone Road",
    "sg:city":"Harrow",
    "sg:classifiers":[
        {
            "category":"Manufacturing",
            "subcategory":"Tools & Machinery",
            "type":"Manufacturing & Wholesale Goods"
        },
        {
            "category":"Insurance",
            "subcategory":"Insurance Agent",
            "type":"Services"
        }
    ],
    "sg:phone":"+44 20 8424 7777",
    "sg:postcode":"HA1 1PD",
    "sg:province":"Greater London",
    "sg:tags":[
        "society",
        "broker",
        "friendly"
    ],
    "wof:name":"The Travel Protection Group Plc",
    "wof:placetype":"venue"
},
  "geometry": {"coordinates":[-0.340198,51.580246],"type":"Point"}
}