{
  "type": "Feature",
  "properties": {
    "addr:full":"Longbow House, 14-20 Chiswell Street London Greater London EC1Y 4TD",
    "addr:housenumber":"14-20",
    "addr:postcode":"ec1y 4td",
    "addr:street":"Chiswell Street",
    "iso:country":"GB",
    "sg:address":"Longbow House, 14-20 Chiswell Street",
    "sg:city":"London",
    "sg:classifiers":[
        {
            "category":"Banks & Credit Unions",
            "subcategory":"Bank",
            "type":"Services"
        }
    ],
    "sg:phone":"+44 20 7588 2738",
    "sg:postcode":"EC1Y 4TD",
    "sg:province":"Greater London",
    "wof:name":"Banco de la Nacion Argentina",
    "wof:placetype":"venue"
},
  "geometry": {"coordinates":[-0.0887909979,51.5207023621],"type":"Point"}
}