{
  "type": "Feature",
  "properties": {
    "addr:full":"6 Arundel Pl Brighton East Sussex BN2 1GD",
    "addr:housenumber":"6",
    "addr:postcode":"bn2 1gd",
    "addr:street":"Arundel Pl",
    "iso:country":"GB",
    "sg:address":"6 Arundel Pl",
    "sg:city":"Brighton",
    "sg:classifiers":[
        {
            "category":"Autos & Motor Vehicles",
            "subcategory":"Automobile Sales",
            "type":"Retail Goods"
        }
    ],
    "sg:postcode":"BN2 1GD",
    "sg:province":"East Sussex",
    "sg:tags":[
        "car"
    ],
    "wof:name":"Rotberg,D,",
    "wof:placetype":"venue"
},
  "geometry": {"coordinates":[-0.10849,50.815311],"type":"Point"}
}