{
  "type": "Feature",
  "properties": {
    "addr:full":"Bram Cragg Farm Keswick Cumbria CA12 4TS",
    "addr:postcode":"ca12 4ts",
    "addr:street":"Bram Cragg Farm",
    "iso:country":"GB",
    "sg:address":"Bram Cragg Farm",
    "sg:city":"Keswick",
    "sg:classifiers":[
        {
            "category":"Building & Trades",
            "subcategory":"Construction",
            "type":"Services"
        }
    ],
    "sg:postcode":"CA12 4TS",
    "sg:province":"Cumbria",
    "sg:tags":[
        "builder"
    ],
    "wof:name":"D Stuart",
    "wof:placetype":"venue"
},
  "geometry": {"coordinates":[-3.1235089302,54.6044616699],"type":"Point"}
}