{
  "type": "Feature",
  "properties": {
    "addr:full":"Clinton Street, Arnold Nottingham Nottinghamshire NG5 6GR",
    "addr:postcode":"ng5 6gr",
    "addr:street":"Clinton Street",
    "iso:country":"GB",
    "sg:address":"Clinton Street, Arnold",
    "sg:city":"Nottingham",
    "sg:classifiers":[
        {
            "category":"Organizations",
            "subcategory":"Membership Organization",
            "type":"Services"
        }
    ],
    "sg:phone":"+44 115 955 5501",
    "sg:postcode":"NG5 6GR",
    "sg:province":"Nottinghamshire",
    "sg:tags":[
        "club"
    ],
    "wof:name":"Arnold & District Ex Service Club Ltd.",
    "wof:placetype":"venue"
},
  "geometry": {"coordinates":[-1.1346390247,53.0027008057],"type":"Point"}
}