{
  "type": "Feature",
  "properties": {
    "addr:full":"1 Cumberland Avenue Blackpool Lancashire FY1 5QL",
    "addr:housenumber":"1",
    "addr:postcode":"fy1 5ql",
    "addr:street":"Cumberland Avenue",
    "iso:country":"GB",
    "sg:address":"1 Cumberland Avenue",
    "sg:city":"Blackpool",
    "sg:classifiers":[
        {
            "category":"Health Services",
            "subcategory":"Clinic",
            "type":"Services"
        }
    ],
    "sg:phone":"+44 1253 699444",
    "sg:postcode":"FY1 5QL",
    "sg:province":"Lancashire",
    "sg:tags":[
        "private"
    ],
    "wof:name":"Cumberland Medical Services Ltd.",
    "wof:placetype":"venue"
},
  "geometry": {"coordinates":[-3.0351910591,53.8121147156],"type":"Point"}
}