{
  "type": "Feature",
  "properties": {
    "addr:full":"4 Muskoka Bewdley Shropshire DY12 2BJ",
    "addr:housenumber":"4",
    "addr:postcode":"dy12 2bj",
    "addr:street":"Muskoka Bewdley",
    "iso:country":"GB",
    "sg:address":"4 Muskoka",
    "sg:city":"Bewdley",
    "sg:classifiers":[
        {
            "category":"Retail",
            "subcategory":"Driving School",
            "type":"Services"
        }
    ],
    "sg:phone":"+44 1299 403500",
    "sg:postcode":"DY12 2BJ",
    "sg:province":"Shropshire",
    "wof:name":"Bewdley Motoring School",
    "wof:placetype":"venue"
},
  "geometry": {"coordinates":[-2.3253750801,52.3758354187],"type":"Point"}
}