{
  "type": "Feature",
  "properties": {
    "addr:full":"Unit 7/8, The Vale Industrial Centre, Southern Road Aylesbury Buckinghamshire HP19 9EP",
    "addr:housenumber":"unit 7 / 8",
    "addr:postcode":"hp19 9ep",
    "addr:street":"The Vale Industrial Centre Southern Road",
    "iso:country":"GB",
    "sg:address":"Unit 7/8, The Vale Industrial Centre, Southern Road",
    "sg:city":"Aylesbury",
    "sg:classifiers":[
        {
            "category":"Wholesale",
            "subcategory":"Sporting Goods",
            "type":"Manufacturing & Wholesale Goods"
        }
    ],
    "sg:phone":"+44 1296 394980",
    "sg:postcode":"HP19 9EP",
    "sg:province":"Buckinghamshire",
    "sg:tags":[
        "linen"
    ],
    "wof:name":"The French Linen Co. Ltd.",
    "wof:placetype":"venue"
},
  "geometry": {"coordinates":[-0.82753,51.825932],"type":"Point"}
}