{
  "type": "Feature",
  "properties": {
    "iso:country":"GB",
    "sg:address":"Datchet Road, Horton",
    "sg:city":"Slough",
    "sg:classifiers":[
        {
            "category":"Autos & Motor Vehicles",
            "subcategory":"Automobile Sales",
            "type":"Retail Goods"
        }
    ],
    "sg:phone":"+44 1753 680860",
    "sg:postcode":"SL3 9PS",
    "sg:province":"Berkshire",
    "sg:tags":[
        "car"
    ],
    "wof:name":"Horton Car Sales",
    "wof:placetype":"venue"
},
  "geometry": {"coordinates":[-0.580488,51.484074],"type":"Point"}
}