{
  "type": "Feature",
  "properties": {
    "addr:full":"Cambridge Road Portsmouth Hampshire PO1 2EN",
    "addr:postcode":"hampshire po1 2en",
    "addr:street":"Cambridge Road",
    "iso:country":"GB",
    "sg:address":"Cambridge Road",
    "sg:city":"Portsmouth",
    "sg:classifiers":[
        {
            "category":"Social Services",
            "subcategory":"Job Training",
            "type":"Services"
        },
        {
            "category":"Professional",
            "subcategory":"Employment Agencies",
            "type":"Services"
        }
    ],
    "sg:phone":"+44 23 9282 3744",
    "sg:postcode":"PO1 2EN",
    "sg:province":"Hampshire",
    "sg:tags":[
        "career",
        "information",
        "guidance"
    ],
    "sg:website":"http://www.armyjob.mod.uk",
    "wof:name":"Armed Forces Careers Office",
    "wof:placetype":"venue"
},
  "geometry": {"coordinates":[-1.096204,50.794865],"type":"Point"}
}