{
  "type": "Feature",
  "properties": {
    "iso:country":"GB",
    "sg:address":"1070 Shield Road",
    "sg:city":"Newcastle-upon-tyne",
    "sg:classifiers":[
        {
            "category":"Health Services",
            "subcategory":"Dentist",
            "type":"Services"
        }
    ],
    "sg:phone":"+44 191 262 8027",
    "sg:postcode":"NE6 4SR",
    "sg:province":"Tyne and Wear",
    "wof:name":"Norgrove Dental Surgery",
    "wof:placetype":"venue"
},
  "geometry": {"coordinates":[-1.545495,54.989101],"type":"Point"}
}