{
  "type": "Feature",
  "properties": {
    "iso:country":"GB",
    "sg:address":"27b Dreadnought Trading Est",
    "sg:city":"Bridport",
    "sg:classifiers":[
        {
            "category":"Manufacturing",
            "subcategory":"Food",
            "type":"Manufacturing & Wholesale Goods"
        }
    ],
    "sg:postcode":"DT6 5BU",
    "sg:province":"Dorset",
    "sg:tags":[
        "technologist"
    ],
    "wof:name":"Cornick Fine Foods",
    "wof:placetype":"venue"
},
  "geometry": {"coordinates":[-2.766064,50.73259],"type":"Point"}
}