{
  "type": "Feature",
  "properties": {
    "addr:full":"124 Heath Lane Warrington Cheshire WA3 7DS",
    "addr:housenumber":"124",
    "addr:postcode":"wa3 7ds",
    "addr:street":"Heath Lane",
    "iso:country":"GB",
    "sg:address":"124 Heath Lane",
    "sg:city":"Warrington",
    "sg:classifiers":[
        {
            "category":"Professional",
            "subcategory":"Computer Services",
            "type":"Services"
        }
    ],
    "sg:phone":"+44 1925 764999",
    "sg:postcode":"WA3 7DS",
    "sg:province":"Cheshire",
    "sg:tags":[
        "system",
        "software"
    ],
    "wof:name":"Newprice Ltd.",
    "wof:placetype":"venue"
},
  "geometry": {"coordinates":[-2.5581688881,53.4487190247],"type":"Point"}
}