{
  "type": "Feature",
  "properties": {
    "addr:full":"Stevenson Court, Bent Street, Kearsley Bolton Lancashire BL4 8BA",
    "addr:postcode":"bl4 8ba",
    "addr:street":"Stevenson Court Bent Street",
    "iso:country":"GB",
    "sg:address":"Stevenson Court, Bent Street, Kearsley",
    "sg:city":"Bolton",
    "sg:classifiers":[
        {
            "category":"Organizations",
            "subcategory":"Community Association",
            "type":"Services"
        }
    ],
    "sg:phone":"+44 1204 793293",
    "sg:postcode":"BL4 8BA",
    "sg:province":"Lancashire",
    "sg:tags":[
        "society",
        "housing"
    ],
    "wof:name":"Anchor Trust",
    "wof:placetype":"venue"
},
  "geometry": {"coordinates":[-2.3753089905,53.5398216248],"type":"Point"}
}