{
  "type": "Feature",
  "properties": {
    "iso:country":"GB",
    "sg:address":"25 Institute Road",
    "sg:city":"Swanage",
    "sg:classifiers":[
        {
            "category":"Fast Food",
            "type":"Food & Drink"
        },
        {
            "category":"Restaurant",
            "type":"Food & Drink"
        }
    ],
    "sg:phone":"+44 1929 422706",
    "sg:postcode":"BH19 1BT",
    "sg:province":"Dorset",
    "sg:tags":[
        "away",
        "take"
    ],
    "wof:name":"Alexandra's Restaurant",
    "wof:placetype":"venue"
},
  "geometry": {"coordinates":[-1.9565559626,50.6084671021],"type":"Point"}
}