{
  "type": "Feature",
  "properties": {
    "iso:country":"GB",
    "sg:address":"67-69 High Street, Ewell Village",
    "sg:city":"Epsom",
    "sg:classifiers":[
        {
            "category":"Restaurant",
            "type":"Food & Drink"
        }
    ],
    "sg:phone":"+44 20 8393 8810",
    "sg:postcode":"KT17 1RX",
    "sg:province":"Surrey",
    "sg:tags":[
        "-",
        "italian"
    ],
    "wof:name":"A Roma Restaurant",
    "wof:placetype":"venue"
},
  "geometry": {"coordinates":[-0.249153,51.34856],"type":"Point"}
}