{
  "type": "Feature",
  "properties": {
    "iso:country":"GB",
    "sg:address":"Scott House, 5 Whitsome Village",
    "sg:city":"Duns",
    "sg:classifiers":[
        {
            "category":"Professional",
            "subcategory":"Computer Services",
            "type":"Services"
        }
    ],
    "sg:phone":"+44 1890 870666",
    "sg:postcode":"TD11 3NB",
    "sg:province":"East Lothian",
    "sg:tags":[
        "system",
        "software"
    ],
    "wof:name":"Business Computer Systems",
    "wof:placetype":"venue"
},
  "geometry": {"coordinates":[-2.306005,55.786613],"type":"Point"}
}