{
  "type": "Feature",
  "properties": {
    "iso:country":"GB",
    "sg:address":"Westgate Business Park, Westgate Carr Road",
    "sg:city":"Pickering",
    "sg:classifiers":[
        {
            "category":"Food & Beverages",
            "subcategory":"Bakery",
            "type":"Retail Goods"
        }
    ],
    "sg:phone":"+44 1751 473483",
    "sg:postcode":"YO18 8LX",
    "sg:province":"North Yorkshire",
    "sg:tags":[
        "manufacture",
        "equipment",
        "supply"
    ],
    "wof:name":"Invicta Bakeware Ltd.",
    "wof:placetype":"venue"
},
  "geometry": {"coordinates":[-0.7793880105,54.245010376],"type":"Point"}
}