{
  "type": "Feature",
  "properties": {
    "iso:country":"GB",
    "sg:address":"Union Road",
    "sg:city":"Bolton",
    "sg:classifiers":[
        {
            "category":"Building & Trades",
            "subcategory":"Electrical",
            "type":"Services"
        }
    ],
    "sg:phone":"+44 1204 558960",
    "sg:postcode":"BL2 2HJ",
    "sg:province":"Lancashire",
    "sg:tags":[
        "lighting"
    ],
    "wof:name":"Francis Searchlights Ltd.",
    "wof:placetype":"venue"
},
  "geometry": {"coordinates":[-2.4171938896,53.5875663757],"type":"Point"}
}