{
  "type": "Feature",
  "properties": {
    "addr:full":"Lynora, Dickies Lane Blackpool Lancashire FY4 5LG",
    "addr:postcode":"fy4 5lg",
    "addr:street":"Dickies Lane",
    "iso:country":"GB",
    "sg:address":"Lynora, Dickies Lane",
    "sg:city":"Blackpool",
    "sg:classifiers":[
        {
            "category":"Freight",
            "type":"Transportation"
        },
        {
            "category":"Retail",
            "subcategory":"Storage",
            "type":"Services"
        }
    ],
    "sg:phone":"+44 1253 761807",
    "sg:postcode":"FY4 5LG",
    "sg:province":"Lancashire",
    "sg:tags":[
        "haulage",
        "household",
        "road",
        "removal"
    ],
    "wof:name":"T & M Marshall",
    "wof:placetype":"venue"
},
  "geometry": {"coordinates":[-3.0039839745,53.7906951904],"type":"Point"}
}