{
  "type": "Feature",
  "properties": {
    "addr:full":"33 Rose Street London Greater London WC2E 9EB",
    "addr:housenumber":"33",
    "addr:postcode":"wc2e 9eb",
    "addr:street":"Rose Street",
    "iso:country":"GB",
    "sg:address":"33 Rose Street",
    "sg:city":"London",
    "sg:classifiers":[
        {
            "category":"Bars & Pubs",
            "type":"Food & Drink"
        }
    ],
    "sg:postcode":"WC2E 9EB",
    "sg:province":"Greater London",
    "sg:tags":[
        "pubs",
        "inn"
    ],
    "wof:name":"Lamb & Flag",
    "wof:placetype":"venue"
},
  "geometry": {"coordinates":[-0.1256289929,51.5116615295],"type":"Point"}
}