{
  "type": "Feature",
  "properties": {
    "addr:full":"53-55 Weymouth Street London Greater London W1G 8NJ",
    "addr:housenumber":"53-55",
    "addr:postcode":"w1g 8nj",
    "addr:street":"Weymouth Street",
    "iso:country":"GB",
    "sg:address":"53-55 Weymouth Street",
    "sg:city":"London",
    "sg:classifiers":[
        {
            "category":"Real Estate",
            "subcategory":"Real Estate Agent",
            "type":"Services"
        }
    ],
    "sg:phone":"+44 20 7224 5544",
    "sg:postcode":"W1G 8NJ",
    "sg:province":"Greater London",
    "wof:name":"Harris Latner Ltd.",
    "wof:placetype":"venue"
},
  "geometry": {"coordinates":[-0.1503790021,51.5200080872],"type":"Point"}
}