{
  "type": "Feature",
  "properties": {
    "addr:full":"Unit 6 Rougham Industrial Estate, Rougham Bury St Edmunds Suffolk IP30 9ND",
    "addr:housenumber":"unit 6",
    "addr:postcode":"ip30 9nd",
    "addr:street":"Industrial Estate",
    "iso:country":"GB",
    "sg:address":"Unit 6 Rougham Industrial Estate, Rougham",
    "sg:city":"Bury St Edmunds",
    "sg:classifiers":[
        {
            "category":"Building & Trades",
            "subcategory":"Construction",
            "type":"Services"
        }
    ],
    "sg:phone":"+44 1359 270160",
    "sg:postcode":"IP30 9ND",
    "sg:province":"Suffolk",
    "sg:tags":[
        "dry",
        "lining",
        "plasterers",
        "screeders"
    ],
    "wof:name":"J F Cornell Interiors Ltd.",
    "wof:placetype":"venue"
},
  "geometry": {"coordinates":[0.798714,52.222191],"type":"Point"}
}