{
  "type": "Feature",
  "properties": {
    "iso:country":"GB",
    "sg:address":"20 Warren Rd",
    "sg:city":"Braintree",
    "sg:classifiers":[
        {
            "category":"Professional",
            "subcategory":"Accounting & Tax Preparation",
            "type":"Services"
        }
    ],
    "sg:phone":"+44 1376 551627",
    "sg:postcode":"CM7 3PB",
    "sg:province":"Essex",
    "sg:tags":[
        "accountant"
    ],
    "wof:name":"A J Hurrell",
    "wof:placetype":"venue"
},
  "geometry": {"coordinates":[0.57496,51.877022],"type":"Point"}
}