{
  "type": "Feature",
  "properties": {
    "addr:full":"Unit 4 Building 11, Stanmore Industrial Estate Bridgnorth Shropshire WV15 5HP",
    "addr:housenumber":"unit;11",
    "addr:postcode":"wv15 5hp",
    "addr:street":"Stanmore Industrial Estate",
    "iso:country":"GB",
    "sg:address":"Unit 4 Building 11, Stanmore Industrial Estate",
    "sg:city":"Bridgnorth",
    "sg:classifiers":[
        {
            "category":"Utilities",
            "subcategory":"Natural Gas",
            "type":"Services"
        }
    ],
    "sg:postcode":"WV15 5HP",
    "sg:province":"Shropshire",
    "sg:tags":[
        "welding"
    ],
    "wof:name":"M J Systems (Midlands) Ltd.",
    "wof:placetype":"venue"
},
  "geometry": {"coordinates":[-2.384303093,52.5323982239],"type":"Point"}
}