{
  "type": "Feature",
  "properties": {
    "addr:full":"4 Scarr End Lane, Moorend Dewsbury West Yorkshire WF13 4NT",
    "addr:housenumber":"4",
    "addr:postcode":"wf13 4nt",
    "addr:street":"Scarr End Lane",
    "iso:country":"GB",
    "sg:address":"4 Scarr End Lane, Moorend",
    "sg:city":"Dewsbury",
    "sg:classifiers":[
        {
            "category":"Education",
            "subcategory":"Music School",
            "type":"Public Place"
        }
    ],
    "sg:phone":"+44 1924 452081",
    "sg:postcode":"WF13 4NT",
    "sg:province":"West Yorkshire",
    "sg:tags":[
        "teacher"
    ],
    "wof:name":"P Sewell",
    "wof:placetype":"venue"
},
  "geometry": {"coordinates":[-1.655918,53.69899],"type":"Point"}
}