{
  "type": "Feature",
  "properties": {
    "iso:country":"GB",
    "sg:address":"14 Burnham St",
    "sg:city":"Nottingham",
    "sg:classifiers":[
        {
            "category":"Health Services",
            "subcategory":"Health Practitioner",
            "type":"Services"
        }
    ],
    "sg:phone":"+44 115 841 1385",
    "sg:postcode":"NG5 2FH",
    "sg:province":"Nottinghamshire",
    "sg:tags":[
        "acupuncture"
    ],
    "wof:name":"Cherry Chapman",
    "wof:placetype":"venue"
},
  "geometry": {"coordinates":[-1.148808,52.97958],"type":"Point"}
}