{
  "type": "Feature",
  "properties": {
    "addr:full":"Hall Of Residence, 30 Old Road London Greater London SE13 5SZ",
    "addr:housenumber":"30",
    "addr:postcode":"se13 5sz",
    "addr:street":"Old Road",
    "iso:country":"GB",
    "sg:address":"Hall Of Residence, 30 Old Road",
    "sg:city":"London",
    "sg:classifiers":[
        {
            "category":"Education",
            "subcategory":"University",
            "type":"Public Place"
        }
    ],
    "sg:phone":"+44 20 8852 9657",
    "sg:postcode":"SE13 5SZ",
    "sg:province":"Greater London",
    "sg:tags":[
        "medical",
        "school"
    ],
    "wof:name":"Pentland House",
    "wof:placetype":"venue"
},
  "geometry": {"coordinates":[0.00489,51.457779],"type":"Point"}
}