{
  "type": "Feature",
  "properties": {
    "iso:country":"GB",
    "sg:address":"Rectory Road, Little Oakley",
    "sg:city":"Harwich",
    "sg:classifiers":[
        {
            "category":"Education",
            "subcategory":"School",
            "type":"Public Place"
        }
    ],
    "sg:phone":"+44 1255 880330",
    "sg:postcode":"CO12 5JY",
    "sg:province":"Essex",
    "sg:tags":[
        "local",
        "authority"
    ],
    "wof:name":"Little Oakley Church of England Infant School",
    "wof:placetype":"venue"
},
  "geometry": {"coordinates":[1.223584,51.916195],"type":"Point"}
}