{
  "type": "Feature",
  "properties": {
    "addr:full":"40 Priory St Great Yarmouth Norfolk NR31 6NG",
    "addr:housenumber":"40",
    "addr:postcode":"nr31 6ng",
    "addr:street":"Priory St",
    "iso:country":"GB",
    "sg:address":"40 Priory St",
    "sg:city":"Great Yarmouth",
    "sg:classifiers":[
        {
            "category":"Building & Trades",
            "subcategory":"Construction",
            "type":"Services"
        }
    ],
    "sg:postcode":"NR31 6NG",
    "sg:province":"Norfolk",
    "sg:tags":[
        "builder"
    ],
    "wof:name":"Watsons Building Services",
    "wof:placetype":"venue"
},
  "geometry": {"coordinates":[1.727685,52.582165],"type":"Point"}
}