{
  "type": "Feature",
  "properties": {
    "addr:full":"24 Clegg St Oldham Lancashire OL1 1PL",
    "addr:housenumber":"24",
    "addr:postcode":"ol1 1pl",
    "addr:street":"Clegg St",
    "iso:country":"GB",
    "sg:address":"24 Clegg St",
    "sg:city":"Oldham",
    "sg:classifiers":[
        {
            "category":"Professional",
            "subcategory":"Lawyer & Legal Services",
            "type":"Services"
        }
    ],
    "sg:phone":"+44 161 633 4291",
    "sg:postcode":"OL1 1PL",
    "sg:province":"Lancashire",
    "sg:tags":[
        "advice",
        "counselling"
    ],
    "wof:name":"Citizens Advice Bureau",
    "wof:placetype":"venue"
},
  "geometry": {"coordinates":[-2.111629,53.541088],"type":"Point"}
}