{
  "type": "Feature",
  "properties": {
    "addr:full":"Cardinal House, 46 St Nicholas Street Ipswich Suffolk IP1 1TT",
    "addr:housenumber":"46",
    "addr:postcode":"ip1 1tt",
    "addr:street":"St Nicholas Street",
    "iso:country":"GB",
    "sg:address":"Cardinal House, 46 St Nicholas Street",
    "sg:city":"Ipswich",
    "sg:classifiers":[
        {
            "category":"Professional",
            "subcategory":"Computer Services",
            "type":"Services"
        }
    ],
    "sg:postcode":"IP1 1TT",
    "sg:province":"Suffolk",
    "sg:tags":[
        "system",
        "software"
    ],
    "wof:name":"Small Systems Engineering Ltd",
    "wof:placetype":"venue"
},
  "geometry": {"coordinates":[1.1526429653,52.0547714233],"type":"Point"}
}