{
  "type": "Feature",
  "properties": {
    "iso:country":"GB",
    "sg:address":"London House, Maengwyn St",
    "sg:city":"Tywyn",
    "sg:classifiers":[
        {
            "category":"Professional",
            "subcategory":"Business Services",
            "type":"Services"
        }
    ],
    "sg:phone":"+44 1654 712141",
    "sg:postcode":"LL36 9DW",
    "sg:province":"Gwynedd",
    "sg:tags":[
        "bookmaker"
    ],
    "wof:name":"Carole-annes",
    "wof:placetype":"venue"
},
  "geometry": {"coordinates":[-4.083637,52.587978],"type":"Point"}
}