{
  "type": "Feature",
  "properties": {
    "addr:full":"Design Studio, 124 City Rd Clerkenwell Greater London EC1V 2NJ",
    "addr:housenumber":"124",
    "addr:postcode":"ec1v 2nj",
    "addr:street":"City Rd",
    "iso:country":"GB",
    "sg:address":"Design Studio, 124 City Rd",
    "sg:city":"Clerkenwell",
    "sg:classifiers":[
        {
            "category":"Shopping",
            "subcategory":"Clothing, Apparel, & Fashions",
            "type":"Retail Goods"
        }
    ],
    "sg:phone":"+44 20 7251 1001",
    "sg:postcode":"EC1V 2NJ",
    "sg:province":"Greater London",
    "sg:tags":[
        "clothing"
    ],
    "wof:name":"Paul Costelloe International Ltd",
    "wof:placetype":"venue"
},
  "geometry": {"coordinates":[-0.0884099975,51.5265617371],"type":"Point"}
}