{
  "type": "Feature",
  "properties": {
    "iso:country":"GB",
    "sg:address":"Flat 1 Charter House, 1-4 Camden Crescent",
    "sg:city":"Dover",
    "sg:classifiers":[
        {
            "category":"Shopping",
            "subcategory":"Event Tickets",
            "type":"Retail Goods"
        }
    ],
    "sg:postcode":"CT16 1LE",
    "sg:province":"Kent",
    "sg:tags":[
        "agency"
    ],
    "wof:name":"Just Tickets & Motoring Ltd.",
    "wof:placetype":"venue"
},
  "geometry": {"coordinates":[1.328761,51.126846],"type":"Point"}
}