{
  "type": "Feature",
  "properties": {
    "addr:full":"Crown Hill, Upshire Waltham Abbey Essex EN9 3TF",
    "addr:postcode":"en9 3tf",
    "addr:street":"Abbey",
    "iso:country":"GB",
    "sg:address":"Crown Hill, Upshire",
    "sg:city":"Waltham Abbey",
    "sg:classifiers":[
        {
            "category":"Home & Garden",
            "subcategory":"Garden Supply",
            "type":"Retail Goods"
        }
    ],
    "sg:postcode":"EN9 3TF",
    "sg:province":"Essex",
    "sg:tags":[
        "nursery",
        "centre"
    ],
    "wof:name":"Crown Hill Nursery",
    "wof:placetype":"venue"
},
  "geometry": {"coordinates":[0.0624560006,51.685546875],"type":"Point"}
}