{
  "type": "Feature",
  "properties": {
    "iso:country":"GB",
    "sg:address":"24 Cheltenham Road",
    "sg:city":"Orpington",
    "sg:classifiers":[
        {
            "category":"Professional",
            "subcategory":"Engineering",
            "type":"Services"
        }
    ],
    "sg:phone":"+44 1689 831187",
    "sg:postcode":"BR6 9HJ",
    "sg:province":"Kent",
    "sg:tags":[
        "contractor",
        "electrical",
        "engineer"
    ],
    "wof:name":"I Payne",
    "wof:placetype":"venue"
},
  "geometry": {"coordinates":[0.097697,51.365753],"type":"Point"}
}