{
  "type": "Feature",
  "properties": {
    "iso:country":"GB",
    "sg:address":"The Pavilion, Whitchurch Downs, Whitchurch",
    "sg:city":"Tavistock",
    "sg:classifiers":[
        {
            "category":"Arena",
            "subcategory":"Sports Club",
            "type":"Entertainment"
        }
    ],
    "sg:phone":"+44 1822 614130",
    "sg:postcode":"PL19 9LD",
    "sg:province":"Devon",
    "wof:name":"Tavistock Cricket Club",
    "wof:placetype":"venue"
},
  "geometry": {"coordinates":[-4.1350288391,50.5359306335],"type":"Point"}
}