{
  "type": "Feature",
  "properties": {
    "addr:full":"166 Church Road, St George Bristol City of Bristol BS5 8AQ",
    "addr:housenumber":"166",
    "addr:postcode":"bs5 8aq",
    "addr:street":"Church Road",
    "iso:country":"GB",
    "sg:address":"166 Church Road, St George",
    "sg:city":"Bristol",
    "sg:classifiers":[
        {
            "category":"Military Area",
            "subcategory":"Air Force Base",
            "type":"Public Place"
        }
    ],
    "sg:phone":"+44 117 955 0555",
    "sg:postcode":"BS5 8AQ",
    "sg:province":"City of Bristol",
    "sg:tags":[
        "taxi",
        "hire",
        "private"
    ],
    "wof:name":"A 2 B Taxis",
    "wof:placetype":"venue"
},
  "geometry": {"coordinates":[-2.550909,51.45966],"type":"Point"}
}