{
  "type": "Feature",
  "properties": {
    "iso:country":"GB",
    "sg:address":"2 Elwes Street",
    "sg:city":"Brigg",
    "sg:classifiers":[
        {
            "category":"Personal",
            "subcategory":"Beauty Salon",
            "type":"Services"
        },
        {
            "category":"Personal",
            "subcategory":"Barber",
            "type":"Services"
        }
    ],
    "sg:phone":"+44 1652 655610",
    "sg:postcode":"DN20 8LB",
    "sg:province":"Lincolnshire",
    "sg:tags":[
        "unisex",
        "hairdresser"
    ],
    "wof:name":"Groomers",
    "wof:placetype":"venue"
},
  "geometry": {"coordinates":[-0.491689,53.551338],"type":"Point"}
}