{
  "type": "Feature",
  "properties": {
    "iso:country":"GB",
    "sg:address":"18 Ullswater Av",
    "sg:city":"Whitehaven",
    "sg:classifiers":[
        {
            "category":"Building & Trades",
            "subcategory":"Construction",
            "type":"Services"
        }
    ],
    "sg:phone":"+44 1946 66192",
    "sg:postcode":"CA28 8SE",
    "sg:province":"Cumbria",
    "sg:tags":[
        "guttering"
    ],
    "wof:name":"Newtec Fascias",
    "wof:placetype":"venue"
},
  "geometry": {"coordinates":[-3.559046,54.535393],"type":"Point"}
}