{
  "type": "Feature",
  "properties": {
    "iso:country":"GB",
    "sg:address":"58 Valley Prospect",
    "sg:city":"Newark",
    "sg:classifiers":[
        {
            "category":"Professional",
            "subcategory":"Accounting & Tax Preparation",
            "type":"Services"
        }
    ],
    "sg:postcode":"NG24 4QW",
    "sg:province":"Nottinghamshire",
    "sg:tags":[
        "accountant"
    ],
    "wof:name":"Beaumont,David,",
    "wof:placetype":"venue"
},
  "geometry": {"coordinates":[-0.82292,53.064869],"type":"Point"}
}