{
  "type": "Feature",
  "properties": {
    "addr:full":"32 Southfield Road Middlesbrough North Yorkshire TS1 3EX",
    "addr:housenumber":"32",
    "addr:postcode":"ts1 3ex",
    "addr:street":"Southfield Road",
    "iso:country":"GB",
    "sg:address":"32 Southfield Road",
    "sg:city":"Middlesbrough",
    "sg:classifiers":[
        {
            "category":"Military Area",
            "subcategory":"Air Force Base",
            "type":"Public Place"
        }
    ],
    "sg:phone":"+44 1642 222000",
    "sg:postcode":"TS1 3EX",
    "sg:province":"North Yorkshire",
    "sg:tags":[
        "taxi",
        "hire",
        "private"
    ],
    "wof:name":"Middlesbrough Borough Cars Ltd.",
    "wof:placetype":"venue"
},
  "geometry": {"coordinates":[-1.2301169634,54.5703277588],"type":"Point"}
}