{
  "type": "Feature",
  "properties": {
    "iso:country":"GB",
    "sg:address":"3 Stainburn Parade",
    "sg:city":"Leeds",
    "sg:classifiers":[
        {
            "category":"Shopping",
            "subcategory":"News",
            "type":"Retail Goods"
        }
    ],
    "sg:phone":"+44 113 268 5464",
    "sg:postcode":"LS17 6NA",
    "sg:province":"North Yorkshire",
    "sg:tags":[
        "newsagent"
    ],
    "wof:name":"Stainburn News",
    "wof:placetype":"venue"
},
  "geometry": {"coordinates":[-1.528135,53.84045],"type":"Point"}
}