{
  "type": "Feature",
  "properties": {
    "addr:full":"Old Road, Mottram Hyde Cheshire SK14 6LG",
    "addr:postcode":"sk14 6lg",
    "addr:street":"Old Road",
    "iso:country":"GB",
    "sg:address":"Old Road, Mottram",
    "sg:city":"Hyde",
    "sg:classifiers":[
        {
            "category":"Transit Center",
            "subcategory":"Passenger",
            "type":"Transportation"
        }
    ],
    "sg:phone":"+44 1457 766633",
    "sg:postcode":"SK14 6LG",
    "sg:province":"Cheshire",
    "sg:tags":[
        "taxidermist"
    ],
    "wof:name":"Pennine Taxidermist Studios",
    "wof:placetype":"venue"
},
  "geometry": {"coordinates":[-2.0129239559,53.4590950012],"type":"Point"}
}