{
  "type": "Feature",
  "properties": {
    "addr:full":"40 Mortimer Street London Greater London W1W 7RQ",
    "addr:housenumber":"40",
    "addr:postcode":"w1w 7rq",
    "addr:street":"Mortimer Street",
    "iso:country":"GB",
    "sg:address":"40 Mortimer Street",
    "sg:city":"London",
    "sg:classifiers":[
        {
            "category":"Real Estate",
            "subcategory":"Real Estate Operator",
            "type":"Services"
        }
    ],
    "sg:postcode":"W1W 7RQ",
    "sg:province":"Greater London",
    "sg:tags":[
        "letting",
        "agent"
    ],
    "wof:name":"Accommodation Finders Club",
    "wof:placetype":"venue"
},
  "geometry": {"coordinates":[-0.1401689947,51.5179481506],"type":"Point"}
}