{
  "type": "Feature",
  "properties": {
    "iso:country":"GB",
    "sg:address":"74 Tangmere Drive, Llandaf",
    "sg:city":"Cardiff",
    "sg:classifiers":[
        {
            "category":"Communications",
            "subcategory":"News Services",
            "type":"Services"
        }
    ],
    "sg:postcode":"CF5 2PQ",
    "sg:province":"Cardiff",
    "sg:tags":[
        "photo",
        "agency"
    ],
    "wof:name":"Christopher Wynne Davies",
    "wof:placetype":"venue"
},
  "geometry": {"coordinates":[-3.236857,51.499168],"type":"Point"}
}