{
  "type": "Feature",
  "properties": {
    "addr:full":"29 Main Street Seahouses Northumberland NE68 7RE",
    "addr:housenumber":"29",
    "addr:postcode":"ne68 7re",
    "addr:street":"Main Street",
    "iso:country":"GB",
    "sg:address":"29 Main Street",
    "sg:city":"Seahouses",
    "sg:classifiers":[
        {
            "category":"Shopping",
            "subcategory":"Gifts & Souvenirs",
            "type":"Retail Goods"
        }
    ],
    "sg:phone":"+44 1665 721157",
    "sg:postcode":"NE68 7RE",
    "sg:province":"Northumberland",
    "sg:tags":[
        "shop"
    ],
    "wof:name":"Polka Dot",
    "wof:placetype":"venue"
},
  "geometry": {"coordinates":[-1.6528470516,55.5818786621],"type":"Point"}
}