{
  "type": "Feature",
  "properties": {
    "iso:country":"GB",
    "sg:address":"43 Kingstown Road",
    "sg:city":"Carlisle",
    "sg:classifiers":[
        {
            "category":"Freight",
            "type":"Transportation"
        }
    ],
    "sg:phone":"+44 1228 539365",
    "sg:postcode":"CA3 0AB",
    "sg:province":"Cumbria",
    "sg:tags":[
        "haulage",
        "transport",
        "road"
    ],
    "wof:name":"H D & S BROWN",
    "wof:placetype":"venue"
},
  "geometry": {"coordinates":[-2.94133,54.913593],"type":"Point"}
}