{
  "type": "Feature",
  "properties": {
    "addr:full":"Top O'th Meadow Farm, Pot House La Rochdale Lancashire OL12 9PP",
    "addr:postcode":"ol12 9pp",
    "addr:street":"Meadow;Pot House La Rochdale",
    "iso:country":"GB",
    "sg:address":"Top O'th Meadow Farm, Pot House La",
    "sg:city":"Rochdale",
    "sg:classifiers":[
        {
            "category":"Building & Trades",
            "subcategory":"Construction",
            "type":"Services"
        }
    ],
    "sg:phone":"+44 1706 358669",
    "sg:postcode":"OL12 9PP",
    "sg:province":"Lancashire",
    "sg:tags":[
        "builder"
    ],
    "wof:name":"V Stringer & Co",
    "wof:placetype":"venue"
},
  "geometry": {"coordinates":[-2.1530799866,53.6437110901],"type":"Point"}
}