{
  "type": "Feature",
  "properties": {
    "iso:country":"GB",
    "sg:address":"58 Acorn Gro, Ditton",
    "sg:city":"Aylesford",
    "sg:classifiers":[
        {
            "category":"Professional",
            "subcategory":"Secretarial Services",
            "type":"Services"
        }
    ],
    "sg:postcode":"ME20 6EW",
    "sg:province":"Kent",
    "wof:name":"The Grey Rose Agency",
    "wof:placetype":"venue"
},
  "geometry": {"coordinates":[0.4605090022,51.2922592163],"type":"Point"}
}