{
  "type": "Feature",
  "properties": {
    "addr:full":"201 Citadel Road East Plymouth Devon PL1 2JF",
    "addr:housenumber":"201",
    "addr:postcode":"pl1 2jf",
    "addr:street":"Citadel Road East",
    "iso:country":"GB",
    "sg:address":"201 Citadel Road East",
    "sg:city":"Plymouth",
    "sg:classifiers":[
        {
            "category":"Travel",
            "subcategory":"Hotels & Motels",
            "type":"Entertainment"
        }
    ],
    "sg:phone":"+44 1752 265742",
    "sg:postcode":"PL1 2JF",
    "sg:province":"Devon",
    "sg:tags":[
        "house",
        "guest"
    ],
    "wof:name":"L R & G M Fletcher",
    "wof:placetype":"venue"
},
  "geometry": {"coordinates":[-4.143579,50.36673],"type":"Point"}
}