{
  "type": "Feature",
  "properties": {
    "iso:country":"GB",
    "sg:address":"Lincoln Rd",
    "sg:city":"Lincoln",
    "sg:classifiers":[
        {
            "category":"Health Services",
            "subcategory":"Doctor",
            "type":"Services"
        }
    ],
    "sg:phone":"+44 1522 730269",
    "sg:postcode":"LN1 2XF",
    "sg:province":"Lincolnshire",
    "sg:tags":[
        "practitioners"
    ],
    "wof:name":"Sultan, M M",
    "wof:placetype":"venue"
},
  "geometry": {"coordinates":[-0.5444589853,53.2966918945],"type":"Point"}
}