{
  "type": "Feature",
  "properties": {
    "iso:country":"GB",
    "sg:address":"14 Sheen Lane",
    "sg:city":"London",
    "sg:classifiers":[
        {
            "category":"Manufacturing",
            "subcategory":"Lumber",
            "type":"Manufacturing & Wholesale Goods"
        }
    ],
    "sg:postcode":"SW14 8LW",
    "sg:province":"Greater London",
    "sg:tags":[
        "importer",
        "merchants",
        "agent",
        "timber"
    ],
    "wof:name":"Alsford Timber Traders",
    "wof:placetype":"venue"
},
  "geometry": {"coordinates":[-0.266782999,51.4678344727],"type":"Point"}
}