{
  "type": "Feature",
  "properties": {
    "addr:full":"77 High Street Poole Dorset BH15 1AH",
    "addr:housenumber":"77",
    "addr:postcode":"bh15 1ah",
    "addr:street":"High Street",
    "iso:country":"GB",
    "sg:address":"77 High Street",
    "sg:city":"Poole",
    "sg:classifiers":[
        {
            "category":"Food & Beverages",
            "subcategory":"Fruits & Vegetables",
            "type":"Retail Goods"
        }
    ],
    "sg:phone":"+44 1202 380688",
    "sg:postcode":"BH15 1AH",
    "sg:province":"Dorset",
    "sg:tags":[
        "greengrocer"
    ],
    "wof:name":"M & D Fruit And Veg",
    "wof:placetype":"venue"
},
  "geometry": {"coordinates":[-1.986243,50.713936],"type":"Point"}
}