{
  "type": "Feature",
  "properties": {
    "addr:full":"26 Green Lane Bromsgrove Worcestershire B61 0LD",
    "addr:housenumber":"26",
    "addr:postcode":"b61 0ld",
    "addr:street":"Green Lane",
    "iso:country":"GB",
    "sg:address":"26 Green Lane",
    "sg:city":"Bromsgrove",
    "sg:classifiers":[
        {
            "category":"Building & Trades",
            "subcategory":"Construction",
            "type":"Services"
        }
    ],
    "sg:postcode":"B61 0LD",
    "sg:province":"Worcestershire",
    "sg:tags":[
        "roofing"
    ],
    "wof:name":"Leja Roofing",
    "wof:placetype":"venue"
},
  "geometry": {"coordinates":[-2.054822,52.364277],"type":"Point"}
}