{
  "type": "Feature",
  "properties": {
    "addr:full":"Parsonage Lane Sawbridgeworth Essex CM21 0ND",
    "addr:postcode":"cm21 0nd",
    "addr:street":"Parsonage Lane",
    "iso:country":"GB",
    "sg:address":"Parsonage Lane",
    "sg:city":"Sawbridgeworth",
    "sg:classifiers":[
        {
            "category":"Home & Garden",
            "subcategory":"Home Furnishings",
            "type":"Retail Goods"
        },
        {
            "category":"Building & Trades",
            "subcategory":"Construction",
            "type":"Services"
        }
    ],
    "sg:postcode":"CM21 0ND",
    "sg:province":"Essex",
    "sg:tags":[
        "blind",
        "thatching",
        "craft",
        "fitting",
        "conservation",
        "curtain"
    ],
    "wof:name":"Jennie Childs",
    "wof:placetype":"venue"
},
  "geometry": {"coordinates":[0.150354,51.824986],"type":"Point"}
}