{
  "type": "Feature",
  "properties": {
    "addr:full":"Lower Common Lane, Three Legged Cross Wimborne Dorset BH21 6RX",
    "addr:postcode":"bh21 6rx",
    "addr:street":"Lower Common Lane",
    "iso:country":"GB",
    "sg:address":"Lower Common Lane, Three Legged Cross",
    "sg:city":"Wimborne",
    "sg:classifiers":[
        {
            "category":"Professional",
            "subcategory":"Engineering",
            "type":"Services"
        }
    ],
    "sg:phone":"+44 1202 824453",
    "sg:postcode":"BH21 6RX",
    "sg:province":"Dorset",
    "sg:tags":[
        "civil",
        "engineer"
    ],
    "wof:name":"J.H Hammond",
    "wof:placetype":"venue"
},
  "geometry": {"coordinates":[-1.8842710257,50.8503456116],"type":"Point"}
}