{
  "type": "Feature",
  "properties": {
    "iso:country":"GB",
    "sg:address":"25 East Gate",
    "sg:city":"Harlow",
    "sg:classifiers":[
        {
            "category":"Banks & Credit Unions",
            "subcategory":"Bank",
            "type":"Services"
        }
    ],
    "sg:phone":"+44 845 303 0108",
    "sg:postcode":"CM20 1LD",
    "sg:province":"Essex",
    "sg:tags":[
        "financial",
        "institution"
    ],
    "sg:website":"http://www.lloydstsb.com",
    "wof:name":"Lloyds T S B Bank Plc",
    "wof:placetype":"venue"
},
  "geometry": {"coordinates":[0.09312,51.77076],"type":"Point"}
}