{
  "type": "Feature",
  "properties": {
    "addr:full":"62 Dale End Birmingham West Midlands B4 7LS",
    "addr:housenumber":"62",
    "addr:postcode":"b4 7ls",
    "addr:street":"Dale End",
    "iso:country":"GB",
    "sg:address":"62 Dale End",
    "sg:city":"Birmingham",
    "sg:classifiers":[
        {
            "category":"Restaurant",
            "type":"Food & Drink"
        }
    ],
    "sg:phone":"+44 121 233 1182",
    "sg:postcode":"B4 7LS",
    "sg:province":"West Midlands",
    "wof:name":"Wimpy Restaurant",
    "wof:placetype":"venue"
},
  "geometry": {"coordinates":[-1.8943740129,52.4805297852],"type":"Point"}
}