{
  "type": "Feature",
  "properties": {
    "addr:full":"Unit 11d, Angel Rd Upper Edmonton Greater London N18 3LD",
    "addr:housenumber":"11d",
    "addr:postcode":"n18 3ld",
    "addr:street":"Angel Rd",
    "iso:country":"GB",
    "sg:address":"Unit 11d, Angel Rd",
    "sg:city":"Upper Edmonton",
    "sg:classifiers":[
        {
            "category":"Wholesale",
            "subcategory":"Music Publishers",
            "type":"Manufacturing & Wholesale Goods"
        }
    ],
    "sg:phone":"+44 20 8803 7231",
    "sg:postcode":"N18 3LD",
    "sg:province":"Greater London",
    "sg:tags":[
        "record"
    ],
    "wof:name":"Buzy B Ltd",
    "wof:placetype":"venue"
},
  "geometry": {"coordinates":[-0.039383,51.612965],"type":"Point"}
}