{
  "type": "Feature",
  "properties": {
    "iso:country":"GB",
    "sg:address":"Council Office, High Street",
    "sg:city":"Elgin",
    "sg:classifiers":[
        {
            "category":"Government",
            "subcategory":"Post Office",
            "type":"Public Place"
        },
        {
            "category":"Government",
            "subcategory":"Office",
            "type":"Public Place"
        }
    ],
    "sg:phone":"+44 1343 543451",
    "sg:postcode":"IV30 1BX",
    "sg:province":"Moray",
    "sg:tags":[
        "local"
    ],
    "wof:name":"The Murray Council",
    "wof:placetype":"venue"
},
  "geometry": {"coordinates":[-3.313489,57.64893],"type":"Point"}
}