{
  "type": "Feature",
  "properties": {
    "addr:full":"7-8 Broad Street Banbury Oxfordshire OX16 5BN",
    "addr:housenumber":"7-8",
    "addr:postcode":"ox16 5bn",
    "addr:street":"Broad Street",
    "iso:country":"GB",
    "sg:address":"7-8 Broad Street",
    "sg:city":"Banbury",
    "sg:classifiers":[
        {
            "category":"Fast Food",
            "type":"Food & Drink"
        }
    ],
    "sg:phone":"+44 1295 263083",
    "sg:postcode":"OX16 5BN",
    "sg:province":"Oxfordshire",
    "sg:tags":[
        "away",
        "take"
    ],
    "wof:name":"Banbury Fish Bar",
    "wof:placetype":"venue"
},
  "geometry": {"coordinates":[-1.334614,52.061401],"type":"Point"}
}