{
  "type": "Feature",
  "properties": {
    "iso:country":"GB",
    "sg:address":"1a Grange Road, Erdington",
    "sg:city":"Birmingham",
    "sg:classifiers":[
        {
            "category":"Building & Trades",
            "subcategory":"Construction",
            "type":"Services"
        }
    ],
    "sg:phone":"+44 121 373 3925",
    "sg:postcode":"B24 0DG",
    "sg:province":"West Midlands",
    "sg:tags":[
        "builder"
    ],
    "wof:name":"Belhavel Construction Ltd.",
    "wof:placetype":"venue"
},
  "geometry": {"coordinates":[-1.8283729553,52.5263671875],"type":"Point"}
}