{
  "type": "Feature",
  "properties": {
    "addr:full":"Newcastle Rd Sunderland Tyne and Wear SR5 1HX",
    "addr:postcode":"sr5 1hx",
    "addr:street":"Newcastle Rd",
    "iso:country":"GB",
    "sg:address":"Newcastle Rd",
    "sg:city":"Sunderland",
    "sg:classifiers":[
        {
            "category":"Bars & Pubs",
            "subcategory":"Nightclub",
            "type":"Food & Drink"
        }
    ],
    "sg:phone":"+44 191 565 5551",
    "sg:postcode":"SR5 1HX",
    "sg:province":"Tyne and Wear",
    "sg:tags":[
        "club",
        "night"
    ],
    "wof:name":"Palace The (closed down)",
    "wof:placetype":"venue"
},
  "geometry": {"coordinates":[-1.38264,54.916939],"type":"Point"}
}