{
  "type": "Feature",
  "properties": {
    "addr:full":"37a Reading Road, Pangbourne Reading Berkshire RG8 7HY",
    "addr:housenumber":"37a",
    "addr:postcode":"rg8 7hy",
    "addr:street":"Reading Road",
    "iso:country":"GB",
    "sg:address":"37a Reading Road, Pangbourne",
    "sg:city":"Reading",
    "sg:classifiers":[
        {
            "category":"Banks & Credit Unions",
            "subcategory":"Bank",
            "type":"Services"
        }
    ],
    "sg:phone":"+44 118 984 4445",
    "sg:postcode":"RG8 7HY",
    "sg:province":"Berkshire",
    "sg:tags":[
        "broker",
        "mortgage"
    ],
    "wof:name":"Riverbank Financial Services",
    "wof:placetype":"venue"
},
  "geometry": {"coordinates":[-1.083554,51.483631],"type":"Point"}
}