{
  "type": "Feature",
  "properties": {
    "iso:country":"GB",
    "sg:address":"93 Bailiff St",
    "sg:city":"Northampton",
    "sg:classifiers":[
        {
            "category":"Retail",
            "subcategory":"Event Space",
            "type":"Services"
        }
    ],
    "sg:postcode":"NN1 3EA",
    "sg:province":"Northamptonshire",
    "sg:tags":[
        "exhibition",
        "organiser"
    ],
    "wof:name":"Gardner,Mick,",
    "wof:placetype":"venue"
},
  "geometry": {"coordinates":[-0.894032,52.244686],"type":"Point"}
}