{
  "type": "Feature",
  "properties": {
    "addr:full":"Hollies Farm, Uppertown, Bonsall Matlock Derbyshire DE4 2AW",
    "addr:postcode":"de4 2aw",
    "addr:street":"Uppertown",
    "iso:country":"GB",
    "sg:address":"Hollies Farm, Uppertown, Bonsall",
    "sg:city":"Matlock",
    "sg:classifiers":[
        {
            "category":"Building & Trades",
            "subcategory":"Landscaping Services",
            "type":"Services"
        },
        {
            "category":"Farming",
            "subcategory":"Nursery",
            "type":"Manufacturing & Wholesale Goods"
        },
        {
            "category":"Farming",
            "subcategory":"Livestock Farm",
            "type":"Manufacturing & Wholesale Goods"
        },
        {
            "category":"Farming",
            "subcategory":"Farm",
            "type":"Manufacturing & Wholesale Goods"
        }
    ],
    "sg:phone":"+44 1629 822734",
    "sg:postcode":"DE4 2AW",
    "sg:province":"Derbyshire",
    "sg:tags":[
        "mixed",
        "nurseryman",
        "crop",
        "others"
    ],
    "wof:name":"P C & L WELLS",
    "wof:placetype":"venue"
},
  "geometry": {"coordinates":[-1.5838060379,53.1204071045],"type":"Point"}
}