{
  "type": "Feature",
  "properties": {
    "addr:full":"11 Selby Avenue Leeds West Yorkshire LS9 0ES",
    "addr:housenumber":"11",
    "addr:postcode":"ls9 0es",
    "addr:street":"Selby Avenue",
    "iso:country":"GB",
    "sg:address":"11 Selby Avenue",
    "sg:city":"Leeds",
    "sg:classifiers":[
        {
            "category":"Building & Trades",
            "subcategory":"Landscaping Services",
            "type":"Services"
        }
    ],
    "sg:phone":"+44 113 249 5770",
    "sg:postcode":"LS9 0ES",
    "sg:province":"West Yorkshire",
    "sg:tags":[
        "forestry",
        "surgeon",
        "tree"
    ],
    "wof:name":"Tree Toppers",
    "wof:placetype":"venue"
},
  "geometry": {"coordinates":[-1.4841879606,53.7992095947],"type":"Point"}
}