{
  "type": "Feature",
  "properties": {
    "iso:country":"GB",
    "sg:address":"47 Commercial Street",
    "sg:city":"Tredegar",
    "sg:classifiers":[
        {
            "category":"Food & Beverages",
            "subcategory":"Fruits & Vegetables",
            "type":"Retail Goods"
        }
    ],
    "sg:phone":"+44 1685 384642",
    "sg:postcode":"NP22 3DJ",
    "sg:province":"Blaenau Gwent",
    "sg:tags":[
        "greengrocer"
    ],
    "wof:name":"Ivor Probert & Son",
    "wof:placetype":"venue"
},
  "geometry": {"coordinates":[-3.246365,51.775024],"type":"Point"}
}