{
  "type": "Feature",
  "properties": {
    "addr:full":"16 Carr Road Nelson Lancashire BB9 7JS",
    "addr:housenumber":"16",
    "addr:postcode":"bb9 7js",
    "addr:street":"Carr Road",
    "iso:country":"GB",
    "sg:address":"16 Carr Road",
    "sg:city":"Nelson",
    "sg:classifiers":[
        {
            "category":"Professional",
            "subcategory":"Lawyer & Legal Services",
            "type":"Services"
        }
    ],
    "sg:phone":"+44 1282 611234",
    "sg:postcode":"BB9 7JS",
    "sg:province":"Lancashire",
    "sg:tags":[
        "solicitor"
    ],
    "wof:name":"Bukhari & Co.",
    "wof:placetype":"venue"
},
  "geometry": {"coordinates":[-2.2168390751,53.836971283],"type":"Point"}
}