{
  "type": "Feature",
  "properties": {
    "iso:country":"GB",
    "sg:address":"12 Ebenezer St",
    "sg:city":"Islington",
    "sg:classifiers":[
        {
            "category":"Professional",
            "subcategory":"Art Services",
            "type":"Services"
        }
    ],
    "sg:phone":"+44 20 7251 4336",
    "sg:postcode":"N1 7NP",
    "sg:province":"Greater London",
    "sg:tags":[
        "graphic",
        "designer"
    ],
    "wof:name":"Notabene Design",
    "wof:placetype":"venue"
},
  "geometry": {"coordinates":[-0.090317,51.531212],"type":"Point"}
}