{
  "type": "Feature",
  "properties": {
    "addr:full":"Sandy La, West Thurrock Grays Essex RM20 4BH",
    "addr:postcode":"rm20 4bh",
    "addr:street":"West",
    "iso:country":"GB",
    "sg:address":"Sandy La, West Thurrock",
    "sg:city":"Grays",
    "sg:classifiers":[
        {
            "category":"Manufacturing",
            "subcategory":"Paper Products",
            "type":"Manufacturing & Wholesale Goods"
        }
    ],
    "sg:postcode":"RM20 4BH",
    "sg:province":"Essex",
    "sg:tags":[
        "merchant",
        "waste"
    ],
    "wof:name":"K Waste Paper Company Ltd",
    "wof:placetype":"venue"
},
  "geometry": {"coordinates":[0.28736,51.477551],"type":"Point"}
}