{
  "type": "Feature",
  "properties": {
    "addr:full":"29 Waterloo Road Shepton Mallet Somerset BA4 5HH",
    "addr:housenumber":"29",
    "addr:postcode":"ba4 5hh",
    "addr:street":"Waterloo Road",
    "iso:country":"GB",
    "sg:address":"29 Waterloo Road",
    "sg:city":"Shepton Mallet",
    "sg:classifiers":[
        {
            "category":"Restaurant",
            "type":"Food & Drink"
        }
    ],
    "sg:postcode":"BA4 5HH",
    "sg:province":"Somerset",
    "wof:name":"Blostins",
    "wof:placetype":"venue"
},
  "geometry": {"coordinates":[-2.5457699299,51.1946640015],"type":"Point"}
}