{
  "type": "Feature",
  "properties": {
    "iso:country":"GB",
    "sg:address":"220 Brompton Road",
    "sg:city":"London",
    "sg:classifiers":[
        {
            "category":"Home & Garden",
            "subcategory":"Home Furnishings",
            "type":"Retail Goods"
        }
    ],
    "sg:phone":"+44 20 7581 9989",
    "sg:postcode":"SW3 2BB",
    "sg:province":"Greater London",
    "sg:tags":[
        "furnishers",
        "planner",
        "kitchen"
    ],
    "wof:name":"Smallbone & Co. (Devizes) Ltd.",
    "wof:placetype":"venue"
},
  "geometry": {"coordinates":[-0.169182,51.496639],"type":"Point"}
}