{
  "type": "Feature",
  "properties": {
    "iso:country":"GB",
    "sg:address":"41 Highfield Park",
    "sg:city":"Rhyl",
    "sg:classifiers":[
        {
            "category":"Building & Trades",
            "subcategory":"Construction",
            "type":"Services"
        }
    ],
    "sg:phone":"+44 1745 336673",
    "sg:postcode":"LL18 3NL",
    "sg:province":"Conwy",
    "sg:tags":[
        "roofing",
        "contracting"
    ],
    "wof:name":"Brian Burt & Sons Roofing Contractors",
    "wof:placetype":"venue"
},
  "geometry": {"coordinates":[-3.479067,53.324135],"type":"Point"}
}