{
  "type": "Feature",
  "properties": {
    "addr:full":"13 Bury St Abingdon Oxfordshire OX14 3QX",
    "addr:housenumber":"13",
    "addr:postcode":"ox14 3qx",
    "addr:street":"Bury St",
    "iso:country":"GB",
    "sg:address":"13 Bury St",
    "sg:city":"Abingdon",
    "sg:classifiers":[
        {
            "category":"Home & Garden",
            "subcategory":"Household Appliances",
            "type":"Retail Goods"
        }
    ],
    "sg:phone":"+44 1235 520112",
    "sg:postcode":"OX14 3QX",
    "sg:province":"Oxfordshire",
    "sg:tags":[
        "electrical",
        "domestic"
    ],
    "wof:name":"Dixons Ltd",
    "wof:placetype":"venue"
},
  "geometry": {"coordinates":[-1.2825490236,51.6703796387],"type":"Point"}
}