{
  "type": "Feature",
  "properties": {
    "addr:full":"5 The Sanctuary, 23 Oak Hill Gro Surbiton Surrey KT6 6DU",
    "addr:housenumber":"5;23",
    "addr:postcode":"kt6 6du",
    "addr:street":"The Sanctuary;Hill Gro",
    "iso:country":"GB",
    "sg:address":"5 The Sanctuary, 23 Oak Hill Gro",
    "sg:city":"Surbiton",
    "sg:classifiers":[
        {
            "category":"Education",
            "subcategory":"School",
            "type":"Public Place"
        }
    ],
    "sg:phone":"+44 20 8390 8810",
    "sg:postcode":"KT6 6DU",
    "sg:province":"Surrey",
    "sg:tags":[
        "local",
        "authority"
    ],
    "wof:name":"Sutherland Education Ltd.",
    "wof:placetype":"venue"
},
  "geometry": {"coordinates":[-0.306949,51.392059],"type":"Point"}
}