{
  "type": "Feature",
  "properties": {
    "addr:full":"Hillside, Mill Road, Wistow Huntingdon Bedfordshire PE28 2QQ",
    "addr:postcode":"pe28 2qq",
    "addr:street":"Hillside Mill Road",
    "iso:country":"GB",
    "sg:address":"Hillside, Mill Road, Wistow",
    "sg:city":"Huntingdon",
    "sg:classifiers":[
        {
            "category":"Farming",
            "subcategory":"Livestock Farm",
            "type":"Manufacturing & Wholesale Goods"
        }
    ],
    "sg:phone":"+44 1487 822492",
    "sg:postcode":"PE28 2QQ",
    "sg:province":"Bedfordshire",
    "sg:tags":[
        "others"
    ],
    "wof:name":"P D & R P Burton",
    "wof:placetype":"venue"
},
  "geometry": {"coordinates":[-0.121829,52.412079],"type":"Point"}
}