{
  "type": "Feature",
  "properties": {
    "iso:country":"GB",
    "sg:address":"Church Terrace, Alton",
    "sg:city":"Stoke-on-trent",
    "sg:classifiers":[
        {
            "category":"Education",
            "subcategory":"School",
            "type":"Public Place"
        }
    ],
    "sg:phone":"+44 1538 702388",
    "sg:postcode":"ST10 4AH",
    "sg:province":"Staffordshire",
    "sg:tags":[
        "local",
        "authority"
    ],
    "wof:name":"St John's R C (A) Primary School",
    "wof:placetype":"venue"
},
  "geometry": {"coordinates":[-1.893792,52.972149],"type":"Point"}
}