{
  "type": "Feature",
  "properties": {
    "addr:full":"Unit 2 Wakefield Road, Ackworth Pontefract West Yorkshire WF7 7DE",
    "addr:housenumber":"unit 2",
    "addr:postcode":"wf7 7de",
    "addr:street":"Wakefield Road;Pontefract West",
    "iso:country":"GB",
    "sg:address":"Unit 2 Wakefield Road, Ackworth",
    "sg:city":"Pontefract",
    "sg:classifiers":[
        {
            "category":"Retail",
            "subcategory":"Auto Repair",
            "type":"Services"
        }
    ],
    "sg:phone":"+44 1977 617254",
    "sg:postcode":"WF7 7DE",
    "sg:province":"West Yorkshire",
    "sg:tags":[
        "modification",
        "garage",
        "related"
    ],
    "wof:name":"K B Auto Reliant",
    "wof:placetype":"venue"
},
  "geometry": {"coordinates":[-1.358319,53.642899],"type":"Point"}
}