{
  "type": "Feature",
  "properties": {
    "addr:full":"8a Arbuthnot Rd New Cross Greater London SE14 5NP",
    "addr:housenumber":"8a",
    "addr:postcode":"se14 5np",
    "addr:street":"Arbuthnot Rd New",
    "iso:country":"GB",
    "sg:address":"8a Arbuthnot Rd",
    "sg:city":"New Cross",
    "sg:classifiers":[
        {
            "category":"Professional",
            "subcategory":"Business Services",
            "type":"Services"
        }
    ],
    "sg:phone":"+44 20 7277 5114",
    "sg:postcode":"SE14 5NP",
    "sg:province":"Greater London",
    "sg:tags":[
        "import",
        "export",
        "agent"
    ],
    "wof:name":"Ingel Services",
    "wof:placetype":"venue"
},
  "geometry": {"coordinates":[-0.043635,51.470436],"type":"Point"}
}