{
  "type": "Feature",
  "properties": {
    "addr:full":"Pond Farm Cullompton Devon EX15 1NF",
    "addr:housenumber":"cullompton",
    "addr:postcode":"ex15 1nf",
    "addr:street":"Devon",
    "iso:country":"GB",
    "sg:address":"Pond Farm",
    "sg:city":"Cullompton",
    "sg:classifiers":[
        {
            "category":"Farming",
            "subcategory":"Livestock Farm",
            "type":"Manufacturing & Wholesale Goods"
        }
    ],
    "sg:phone":"+44 1884 33203",
    "sg:postcode":"EX15 1NF",
    "sg:province":"Devon",
    "sg:tags":[
        "others"
    ],
    "wof:name":"D C Emmett",
    "wof:placetype":"venue"
},
  "geometry": {"coordinates":[-3.3954589367,50.8536300659],"type":"Point"}
}