{
  "type": "Feature",
  "properties": {
    "addr:full":"Mill Road, Theddlethorpe Mablethorpe Lincolnshire LN12 1PB",
    "addr:postcode":"ln12 1pb",
    "addr:street":"Mill Road",
    "iso:country":"GB",
    "sg:address":"Mill Road, Theddlethorpe",
    "sg:city":"Mablethorpe",
    "sg:classifiers":[
        {
            "category":"Bars & Pubs",
            "type":"Food & Drink"
        }
    ],
    "sg:phone":"+44 1507 339990",
    "sg:postcode":"LN12 1PB",
    "sg:province":"Lincolnshire",
    "sg:tags":[
        "pubs",
        "inn"
    ],
    "wof:name":"The Kings Head Inn",
    "wof:placetype":"venue"
},
  "geometry": {"coordinates":[0.2363130003,53.3353004456],"type":"Point"}
}