{
  "type": "Feature",
  "properties": {
    "addr:full":"Unit 2, Low Valley Ind Est, Wombwell Barnsley South Yorkshire S73 8AG",
    "addr:housenumber":"unit 2",
    "addr:postcode":"s73 8ag",
    "addr:street":"Low Valley;Yorkshire",
    "iso:country":"GB",
    "sg:address":"Unit 2, Low Valley Ind Est, Wombwell",
    "sg:city":"Barnsley",
    "sg:classifiers":[
        {
            "category":"Freight",
            "type":"Transportation"
        }
    ],
    "sg:phone":"+44 1226 754944",
    "sg:postcode":"S73 8AG",
    "sg:province":"South Yorkshire",
    "sg:tags":[
        "haulage",
        "road"
    ],
    "wof:name":"R F Transport Services",
    "wof:placetype":"venue"
},
  "geometry": {"coordinates":[-1.41062,53.530636],"type":"Point"}
}