{
  "type": "Feature",
  "properties": {
    "addr:full":"5 Lloyd Street Llandudno Conwy LL30 2UP",
    "addr:housenumber":"5",
    "addr:postcode":"ll30 2up",
    "addr:street":"Lloyd Street",
    "iso:country":"GB",
    "sg:address":"5 Lloyd Street",
    "sg:city":"Llandudno",
    "sg:classifiers":[
        {
            "category":"Shopping",
            "subcategory":"Discount & Variety Stores",
            "type":"Retail Goods"
        }
    ],
    "sg:phone":"+44 1492 860139",
    "sg:postcode":"LL30 2UP",
    "sg:province":"Conwy",
    "sg:tags":[
        "centre"
    ],
    "wof:name":"A & A Cash & Carry",
    "wof:placetype":"venue"
},
  "geometry": {"coordinates":[-3.8302540779,53.3240509033],"type":"Point"}
}