{
  "type": "Feature",
  "properties": {
    "addr:full":"136 Derby Street Bolton Lancashire BL3 6JR",
    "addr:housenumber":"136",
    "addr:postcode":"bl3 6jr",
    "addr:street":"Derby Street",
    "iso:country":"GB",
    "sg:address":"136 Derby Street",
    "sg:city":"Bolton",
    "sg:classifiers":[
        {
            "category":"Cafe",
            "type":"Food & Drink"
        }
    ],
    "sg:phone":"+44 1204 531347",
    "sg:postcode":"BL3 6JR",
    "sg:province":"Lancashire",
    "sg:tags":[
        "tea",
        "room"
    ],
    "wof:name":"Derby Diner",
    "wof:placetype":"venue"
},
  "geometry": {"coordinates":[-2.437649,53.571217],"type":"Point"}
}