{
  "type": "Feature",
  "properties": {
    "addr:full":"40 Courtfield Road, Skegby Sutton-in-ashfield Nottinghamshire NG17 3AT",
    "addr:housenumber":"40",
    "addr:postcode":"ng17 3at",
    "addr:street":"Courtfield Road",
    "iso:country":"GB",
    "sg:address":"40 Courtfield Road, Skegby",
    "sg:city":"Sutton-in-ashfield",
    "sg:classifiers":[
        {
            "category":"Professional",
            "subcategory":"Art Services",
            "type":"Services"
        }
    ],
    "sg:phone":"+44 1623 550760",
    "sg:postcode":"NG17 3AT",
    "sg:province":"Nottinghamshire",
    "sg:tags":[
        "photographer"
    ],
    "wof:name":"J A H Photographics",
    "wof:placetype":"venue"
},
  "geometry": {"coordinates":[-1.2490570545,53.1415977478],"type":"Point"}
}