{
  "type": "Feature",
  "properties": {
    "addr:full":"2a Kingswood Road, Penge London Greater London SE20 7BN",
    "addr:housenumber":"2a",
    "addr:postcode":"se20 7bn",
    "addr:street":"Kingswood Road",
    "iso:country":"GB",
    "sg:address":"2a Kingswood Road, Penge",
    "sg:city":"London",
    "sg:classifiers":[
        {
            "category":"Retail",
            "subcategory":"Repair Shop",
            "type":"Services"
        }
    ],
    "sg:phone":"+44 20 8249 0088",
    "sg:postcode":"SE20 7BN",
    "sg:province":"Greater London",
    "sg:tags":[
        "plant",
        "machinery"
    ],
    "wof:name":"Musselbrook Machine Maintenance",
    "wof:placetype":"venue"
},
  "geometry": {"coordinates":[-0.05789,51.417488],"type":"Point"}
}