{
  "type": "Feature",
  "properties": {
    "iso:country":"GB",
    "sg:address":"1 Balfour Way",
    "sg:city":"Aylesbury",
    "sg:classifiers":[
        {
            "category":"Building & Trades",
            "subcategory":"Cleaning & Sanitation",
            "type":"Services"
        }
    ],
    "sg:phone":"+44 1296 434755",
    "sg:postcode":"HP20 1HG",
    "sg:province":"Buckinghamshire",
    "sg:tags":[
        "sweep",
        "chimney"
    ],
    "wof:name":"Joes Sweep Service",
    "wof:placetype":"venue"
},
  "geometry": {"coordinates":[-0.8051720262,51.824508667],"type":"Point"}
}