{
  "type": "Feature",
  "properties": {
    "addr:full":"Milner Cop Wirral Merseyside CH60 5RJ",
    "addr:postcode":"ch60 5rj",
    "addr:street":"Cop",
    "iso:country":"GB",
    "sg:address":"Milner Cop",
    "sg:city":"Wirral",
    "sg:classifiers":[
        {
            "category":"Building & Trades",
            "subcategory":"Equipment Rental",
            "type":"Services"
        }
    ],
    "sg:phone":"+44 151 342 4136",
    "sg:postcode":"CH60 5RJ",
    "sg:province":"Merseyside",
    "sg:tags":[
        "supply"
    ],
    "wof:name":"Milan Accessories",
    "wof:placetype":"venue"
},
  "geometry": {"coordinates":[-3.0948851109,53.3280563354],"type":"Point"}
}