{
  "type": "Feature",
  "properties": {
    "addr:full":"66 Kingston Road Leatherhead Surrey KT22 7BW",
    "addr:housenumber":"66",
    "addr:postcode":"kt22 7bw",
    "addr:street":"Kingston Road",
    "iso:country":"GB",
    "sg:address":"66 Kingston Road",
    "sg:city":"Leatherhead",
    "sg:classifiers":[
        {
            "category":"Food & Beverages",
            "subcategory":"Meat & Fish",
            "type":"Retail Goods"
        },
        {
            "category":"Food & Beverages",
            "subcategory":"Groceries & Convenience Stores",
            "type":"Retail Goods"
        }
    ],
    "sg:phone":"+44 1372 372210",
    "sg:postcode":"KT22 7BW",
    "sg:province":"Surrey",
    "sg:tags":[
        "shop",
        "chip"
    ],
    "wof:name":"Golden Plaice",
    "wof:placetype":"venue"
},
  "geometry": {"coordinates":[-0.330043,51.300831],"type":"Point"}
}