{
  "type": "Feature",
  "properties": {
    "addr:full":"86 Hereford Road London Greater London W2 5AL",
    "addr:housenumber":"86",
    "addr:postcode":"w2 5al",
    "addr:street":"Hereford Road",
    "iso:country":"GB",
    "sg:address":"86 Hereford Road",
    "sg:city":"London",
    "sg:classifiers":[
        {
            "category":"Travel",
            "subcategory":"Hotels & Motels",
            "type":"Entertainment"
        }
    ],
    "sg:phone":"+44 20 7229 7683",
    "sg:postcode":"W2 5AL",
    "sg:province":"Greater London",
    "sg:tags":[
        "house",
        "self",
        "guest",
        "catering"
    ],
    "wof:name":"Stanbridge House",
    "wof:placetype":"venue"
},
  "geometry": {"coordinates":[-0.1943009943,51.5170059204],"type":"Point"}
}