{
  "type": "Feature",
  "properties": {
    "addr:full":"66 Lynwood Gro Orpington Kent BR6 0BH",
    "addr:housenumber":"66",
    "addr:postcode":"br6 0bh",
    "addr:street":"Lynwood Gro Orpington",
    "iso:country":"GB",
    "sg:address":"66 Lynwood Gro",
    "sg:city":"Orpington",
    "sg:classifiers":[
        {
            "category":"Professional",
            "subcategory":"Accounting & Tax Preparation",
            "type":"Services"
        }
    ],
    "sg:postcode":"BR6 0BH",
    "sg:province":"Kent",
    "sg:tags":[
        "accountant"
    ],
    "wof:name":"Geoffrey J Griggs",
    "wof:placetype":"venue"
},
  "geometry": {"coordinates":[0.087935,51.379845],"type":"Point"}
}