{
  "type": "Feature",
  "properties": {
    "addr:full":"Unit 3 Vernon Building, Westbourne Street High Wycombe Buckinghamshire HP11 2PX",
    "addr:housenumber":"unit 3",
    "addr:postcode":"hp11 2px",
    "addr:street":"Westbourne Street",
    "iso:country":"GB",
    "sg:address":"Unit 3 Vernon Building, Westbourne Street",
    "sg:city":"High Wycombe",
    "sg:classifiers":[
        {
            "category":"Manufacturing",
            "subcategory":"Metals",
            "type":"Manufacturing & Wholesale Goods"
        },
        {
            "category":"Wholesale",
            "subcategory":"Metals & Minerals",
            "type":"Manufacturing & Wholesale Goods"
        }
    ],
    "sg:phone":"+44 1494 532421",
    "sg:postcode":"HP11 2PX",
    "sg:province":"Buckinghamshire",
    "sg:tags":[
        "fabricator",
        "work",
        "sheet"
    ],
    "wof:name":"H J Morgan Smith",
    "wof:placetype":"venue"
},
  "geometry": {"coordinates":[-0.7591300011,51.6316795349],"type":"Point"}
}