{
  "type": "Feature",
  "properties": {
    "iso:country":"GB",
    "sg:address":"11-13 Charterhouse Bldgs",
    "sg:city":"London",
    "sg:classifiers":[
        {
            "category":"Shopping",
            "subcategory":"Books",
            "type":"Retail Goods"
        }
    ],
    "sg:postcode":"EC1M 7AN",
    "sg:province":"Greater London",
    "wof:name":"C I S Information Publishing Ltd",
    "wof:placetype":"venue"
},
  "geometry": {"coordinates":[-0.0984290019,51.5230522156],"type":"Point"}
}