{
  "type": "Feature",
  "properties": {
    "iso:country":"GB",
    "sg:address":"68 North Promenade",
    "sg:city":"Lytham St. Annes",
    "sg:classifiers":[
        {
            "category":"Food & Beverages",
            "subcategory":"Supermarket",
            "type":"Retail Goods"
        }
    ],
    "sg:phone":"+44 1253 723535",
    "sg:postcode":"FY8 2NH",
    "sg:province":"Lancashire",
    "sg:tags":[
        "frozen"
    ],
    "wof:name":"Race River",
    "wof:placetype":"venue"
},
  "geometry": {"coordinates":[-3.040983,53.75573],"type":"Point"}
}