{
  "type": "Feature",
  "properties": {
    "addr:full":"Apeton Hall Farm, Apeton Stafford Staffordshire ST20 0AE",
    "addr:postcode":"st20 0ae",
    "addr:street":"Apeton",
    "iso:country":"GB",
    "sg:address":"Apeton Hall Farm, Apeton",
    "sg:city":"Stafford",
    "sg:classifiers":[
        {
            "category":"Farming",
            "subcategory":"Dairy Farm",
            "type":"Manufacturing & Wholesale Goods"
        }
    ],
    "sg:phone":"+44 1785 823092",
    "sg:postcode":"ST20 0AE",
    "sg:province":"Staffordshire",
    "wof:name":"Colin R J Hitchens",
    "wof:placetype":"venue"
},
  "geometry": {"coordinates":[-2.22141,52.761311],"type":"Point"}
}