{
  "type": "Feature",
  "properties": {
    "iso:country":"GB",
    "sg:address":"78 Queens Road",
    "sg:city":"Aberdeen",
    "sg:classifiers":[
        {
            "category":"Utilities",
            "subcategory":"Fuel Oil & Lpg",
            "type":"Services"
        }
    ],
    "sg:phone":"+44 1224 208800",
    "sg:postcode":"AB15 4YE",
    "sg:province":"Aberdeen City",
    "sg:tags":[
        "gas"
    ],
    "wof:name":"Wellmasters Ltd",
    "wof:placetype":"venue"
},
  "geometry": {"coordinates":[-2.138476,57.140827],"type":"Point"}
}