{
  "type": "Feature",
  "properties": {
    "addr:full":"67a Bexley High Street Bexley Kent DA5 1AA",
    "addr:housenumber":"67a",
    "addr:postcode":"da5 1aa",
    "addr:street":"Bexley High Street",
    "iso:country":"GB",
    "sg:address":"67a Bexley High Street",
    "sg:city":"Bexley",
    "sg:classifiers":[
        {
            "category":"Wholesale",
            "subcategory":"Medical Equipment & Supplies",
            "type":"Manufacturing & Wholesale Goods"
        }
    ],
    "sg:postcode":"DA5 1AA",
    "sg:province":"Kent",
    "sg:tags":[
        "aid",
        "hearing"
    ],
    "wof:name":"G Williams Hearing Aid Services Ltd.",
    "wof:placetype":"venue"
},
  "geometry": {"coordinates":[0.1496179998,51.4417686462],"type":"Point"}
}