{
  "type": "Feature",
  "properties": {
    "iso:country":"GB",
    "sg:address":"19 Union Street",
    "sg:city":"Newport Pagnell",
    "sg:classifiers":[
        {
            "category":"Professional",
            "subcategory":"Engineering",
            "type":"Services"
        }
    ],
    "sg:phone":"+44 1908 611170",
    "sg:postcode":"MK16 8ET",
    "sg:province":"Buckinghamshire",
    "sg:tags":[
        "contractor",
        "electrical",
        "engineer"
    ],
    "wof:name":"Michael E Tole",
    "wof:placetype":"venue"
},
  "geometry": {"coordinates":[-0.721791,52.087872],"type":"Point"}
}