{
  "type": "Feature",
  "properties": {
    "iso:country":"GB",
    "sg:address":"Glosaid Offices, Chequers Bridge Centre, Painswick Road",
    "sg:city":"Gloucester",
    "sg:classifiers":[
        {
            "category":"Organizations",
            "subcategory":"Non-profit Organization",
            "type":"Services"
        }
    ],
    "sg:phone":"+44 1452 304227",
    "sg:postcode":"GL4 6PR",
    "sg:province":"Gloucestershire",
    "sg:tags":[
        "organisation",
        "voluntary",
        "charity"
    ],
    "wof:name":"Glosaid Youth Action",
    "wof:placetype":"venue"
},
  "geometry": {"coordinates":[-2.22763,51.853802],"type":"Point"}
}