{
  "type": "Feature",
  "properties": {
    "addr:full":"286 Church Road, St George Bristol City of Bristol BS5 8AH",
    "addr:housenumber":"286",
    "addr:postcode":"bs5 8ah",
    "addr:street":"Church Road",
    "iso:country":"GB",
    "sg:address":"286 Church Road, St George",
    "sg:city":"Bristol",
    "sg:classifiers":[
        {
            "category":"Manufacturing",
            "subcategory":"Paper Products",
            "type":"Manufacturing & Wholesale Goods"
        }
    ],
    "sg:phone":"+44 117 955 2919",
    "sg:postcode":"BS5 8AH",
    "sg:province":"City of Bristol",
    "sg:tags":[
        "cardboard"
    ],
    "wof:name":"Brooklyn's",
    "wof:placetype":"venue"
},
  "geometry": {"coordinates":[-2.54652,51.459743],"type":"Point"}
}