{
  "type": "Feature",
  "properties": {
    "iso:country":"GB",
    "sg:address":"Holly House 73, Sankey Street",
    "sg:city":"Warrington",
    "sg:classifiers":[
        {
            "category":"Professional",
            "subcategory":"Detective & Security Services",
            "type":"Services"
        }
    ],
    "sg:phone":"+44 1925 245335",
    "sg:postcode":"WA1 1SL",
    "sg:province":"Cheshire",
    "sg:tags":[
        "equipment"
    ],
    "wof:name":"Group 4 Total Security Ltd.",
    "wof:placetype":"venue"
},
  "geometry": {"coordinates":[-2.5978689194,53.3886985779],"type":"Point"}
}