{
  "type": "Feature",
  "properties": {
    "addr:full":"17 High St Cambridge Cambridgeshire CB5 9JU",
    "addr:housenumber":"17",
    "addr:postcode":"cb5 9ju",
    "addr:street":"High St",
    "iso:country":"GB",
    "sg:address":"17 High St",
    "sg:city":"Cambridge",
    "sg:classifiers":[
        {
            "category":"Food & Beverages",
            "subcategory":"Bakery",
            "type":"Retail Goods"
        }
    ],
    "sg:phone":"+44 1223 860916",
    "sg:postcode":"CB5 9JU",
    "sg:province":"Cambridgeshire",
    "sg:tags":[
        "baker"
    ],
    "wof:name":"Waterbeach Bakery",
    "wof:placetype":"venue"
},
  "geometry": {"coordinates":[0.244538,52.240833],"type":"Point"}
}