{
  "type": "Feature",
  "properties": {
    "iso:country":"GB",
    "sg:address":"43 Friends Road",
    "sg:city":"Croydon",
    "sg:classifiers":[
        {
            "category":"Professional",
            "subcategory":"Lawyer & Legal Services",
            "type":"Services"
        }
    ],
    "sg:phone":"+44 20 8681 0123",
    "sg:postcode":"CR0 1ED",
    "sg:province":"Surrey",
    "sg:tags":[
        "conveyancing"
    ],
    "wof:name":"Aistons Solicitors",
    "wof:placetype":"venue"
},
  "geometry": {"coordinates":[-0.095666,51.371128],"type":"Point"}
}