{
  "type": "Feature",
  "properties": {
    "addr:full":"186 High Road Leytonstone Wanstead Greater London E11 3HU",
    "addr:housenumber":"186",
    "addr:postcode":"e11 3hu",
    "addr:street":"High Road",
    "iso:country":"GB",
    "sg:address":"186 High Road Leytonstone",
    "sg:city":"Wanstead",
    "sg:classifiers":[
        {
            "category":"Shopping",
            "subcategory":"Used Merchandise",
            "type":"Retail Goods"
        }
    ],
    "sg:phone":"+44 20 8536 1855",
    "sg:postcode":"E11 3HU",
    "sg:province":"Greater London",
    "sg:tags":[
        "shop",
        "second-hand"
    ],
    "wof:name":"Second Hand City",
    "wof:placetype":"venue"
},
  "geometry": {"coordinates":[0.0054919999,51.5532722473],"type":"Point"}
}