{
  "type": "Feature",
  "properties": {
    "addr:full":"483-485 New Cross Rd New Cross Greater London SE14 6TQ",
    "addr:housenumber":"483-485",
    "addr:postcode":"se14 6tq",
    "addr:street":"New Cross Rd New",
    "iso:country":"GB",
    "sg:address":"483-485 New Cross Rd",
    "sg:city":"New Cross",
    "sg:classifiers":[
        {
            "category":"Retail",
            "subcategory":"Auto Repair",
            "type":"Services"
        }
    ],
    "sg:phone":"+44 20 8469 3200",
    "sg:postcode":"SE14 6TQ",
    "sg:province":"Greater London",
    "sg:tags":[
        "modification",
        "garage"
    ],
    "wof:name":"Walsh Cylinder Head Services",
    "wof:placetype":"venue"
},
  "geometry": {"coordinates":[-0.027954,51.475288],"type":"Point"}
}