{
  "type": "Feature",
  "properties": {
    "iso:country":"GB",
    "sg:address":"Kings Road",
    "sg:city":"Bradford",
    "sg:classifiers":[
        {
            "category":"Autos & Motor Vehicles",
            "subcategory":"Automobile Sales",
            "type":"Retail Goods"
        }
    ],
    "sg:phone":"+44 1274 230300",
    "sg:postcode":"BD2 1EY",
    "sg:province":"West Yorkshire",
    "sg:tags":[
        "car"
    ],
    "wof:name":"Warfedale Audi",
    "wof:placetype":"venue"
},
  "geometry": {"coordinates":[-1.743336,53.826187],"type":"Point"}
}