{
  "type": "Feature",
  "properties": {
    "addr:full":"21 Kirkley Cliff Rd Lowestoft Suffolk NR33 0DB",
    "addr:housenumber":"21",
    "addr:postcode":"nr33 0db",
    "addr:street":"Kirkley Cliff Rd",
    "iso:country":"GB",
    "sg:address":"21 Kirkley Cliff Rd",
    "sg:city":"Lowestoft",
    "sg:classifiers":[
        {
            "category":"Health Services",
            "subcategory":"Dentist",
            "type":"Services"
        }
    ],
    "sg:phone":"+44 1502 573950",
    "sg:postcode":"NR33 0DB",
    "sg:province":"Suffolk",
    "wof:name":"D R Curtis",
    "wof:placetype":"venue"
},
  "geometry": {"coordinates":[1.742828,52.46431],"type":"Point"}
}