{
  "type": "Feature",
  "properties": {
    "addr:full":"Seven Brethren Estate Barnstaple Devon EX31 2AS",
    "addr:postcode":"ex31 2as",
    "iso:country":"GB",
    "sg:address":"Seven Brethren Estate",
    "sg:city":"Barnstaple",
    "sg:classifiers":[
        {
            "category":"Utilities",
            "subcategory":"Fuel Oil & Lpg",
            "type":"Services"
        },
        {
            "category":"Wholesale",
            "subcategory":"Petroleum",
            "type":"Manufacturing & Wholesale Goods"
        }
    ],
    "sg:phone":"+44 1271 345977",
    "sg:postcode":"EX31 2AS",
    "sg:province":"Devon",
    "sg:tags":[
        "distributor"
    ],
    "wof:name":"Total Butler Ltd",
    "wof:placetype":"venue"
},
  "geometry": {"coordinates":[-4.05969,51.073261],"type":"Point"}
}