{
  "type": "Feature",
  "properties": {
    "iso:country":"GB",
    "sg:address":"Newstead Industrial Trading Estate",
    "sg:city":"Stoke-on-trent",
    "sg:classifiers":[
        {
            "category":"Manufacturing",
            "subcategory":"Petroleum Products",
            "type":"Manufacturing & Wholesale Goods"
        }
    ],
    "sg:phone":"+44 1782 659831",
    "sg:postcode":"ST4 8HX",
    "sg:province":"Staffordshire",
    "sg:tags":[
        "double",
        "glazing"
    ],
    "wof:name":"P J's Window Factory",
    "wof:placetype":"venue"
},
  "geometry": {"coordinates":[-2.1638889313,52.9682998657],"type":"Point"}
}