{
  "type": "Feature",
  "properties": {
    "addr:full":"8 Malvern Close, Bishops Waltham Southampton Hampshire SO32 1AY",
    "addr:housenumber":"8",
    "addr:postcode":"so32 1ay",
    "addr:street":"Malvern Close",
    "iso:country":"GB",
    "sg:address":"8 Malvern Close, Bishops Waltham",
    "sg:city":"Southampton",
    "sg:classifiers":[
        {
            "category":"Building & Trades",
            "subcategory":"Construction",
            "type":"Services"
        }
    ],
    "sg:postcode":"SO32 1AY",
    "sg:province":"Hampshire",
    "sg:tags":[
        "equipment"
    ],
    "wof:name":"Meon Valley Crane Hire",
    "wof:placetype":"venue"
},
  "geometry": {"coordinates":[-1.2103149891,50.9535446167],"type":"Point"}
}