{
  "type": "Feature",
  "properties": {
    "iso:country":"GB",
    "sg:address":"Higher Kennaland Farm, Brandis Corner",
    "sg:city":"Holsworthy",
    "sg:classifiers":[
        {
            "category":"Farming",
            "subcategory":"Livestock Farm",
            "type":"Manufacturing & Wholesale Goods"
        }
    ],
    "sg:phone":"+44 1409 281303",
    "sg:postcode":"EX22 7YD",
    "sg:province":"Cornwall",
    "sg:tags":[
        "others"
    ],
    "wof:name":"G T Griffiths",
    "wof:placetype":"venue"
},
  "geometry": {"coordinates":[-4.334923,50.849064],"type":"Point"}
}