{
  "type": "Feature",
  "properties": {
    "addr:full":"32 Moravian Road, Kingswood Bristol City of Bristol BS15 8LZ",
    "addr:housenumber":"32",
    "addr:postcode":"bs15 8lz",
    "addr:street":"Moravian Road",
    "iso:country":"GB",
    "sg:address":"32 Moravian Road, Kingswood",
    "sg:city":"Bristol",
    "sg:classifiers":[
        {
            "category":"Building & Trades",
            "subcategory":"Plumbing",
            "type":"Services"
        }
    ],
    "sg:phone":"+44 117 960 1017",
    "sg:postcode":"BS15 8LZ",
    "sg:province":"City of Bristol",
    "sg:tags":[
        "drain",
        "clearance",
        "sewer"
    ],
    "wof:name":"M R Drains",
    "wof:placetype":"venue"
},
  "geometry": {"coordinates":[-2.50781703,51.4612693787],"type":"Point"}
}