{
  "type": "Feature",
  "properties": {
    "iso:country":"GB",
    "sg:address":"18 Highview Road, Fulford",
    "sg:city":"Stoke-on-trent",
    "sg:classifiers":[
        {
            "category":"Building & Trades",
            "subcategory":"Landscaping Services",
            "type":"Services"
        }
    ],
    "sg:phone":"+44 1782 392794",
    "sg:postcode":"ST11 9QQ",
    "sg:province":"Staffordshire",
    "sg:tags":[
        "gardening"
    ],
    "wof:name":"Michael's Garden Services",
    "wof:placetype":"venue"
},
  "geometry": {"coordinates":[-2.072954,52.937485],"type":"Point"}
}