{
  "type": "Feature",
  "properties": {
    "addr:full":"106 Byron Road Chelmsford Essex CM2 6HJ",
    "addr:housenumber":"106",
    "addr:postcode":"cm2 6hj",
    "addr:street":"Byron Road",
    "iso:country":"GB",
    "sg:address":"106 Byron Road",
    "sg:city":"Chelmsford",
    "sg:classifiers":[
        {
            "category":"Shopping",
            "subcategory":"News",
            "type":"Retail Goods"
        }
    ],
    "sg:phone":"+44 1245 495612",
    "sg:postcode":"CM2 6HJ",
    "sg:province":"Essex",
    "sg:tags":[
        "newsagent"
    ],
    "wof:name":"Byron News",
    "wof:placetype":"venue"
},
  "geometry": {"coordinates":[0.4858019948,51.7315368652],"type":"Point"}
}