{
  "type": "Feature",
  "properties": {
    "iso:country":"GB",
    "sg:address":"40 Challoner St",
    "sg:city":"Cockermouth",
    "sg:classifiers":[
        {
            "category":"Shopping",
            "subcategory":"Department Store",
            "type":"Retail Goods"
        }
    ],
    "sg:postcode":"CA13 9QU",
    "sg:province":"Cumbria",
    "wof:name":"Taylor,Colin,",
    "wof:placetype":"venue"
},
  "geometry": {"coordinates":[-3.363495,54.663677],"type":"Point"}
}