{
  "type": "Feature",
  "properties": {
    "addr:full":"Museum Library & Art Gallery, John Frost Square, John Frost Square Newport Newport NP20 4UR",
    "addr:postcode":"np20 4ur",
    "addr:street":"John Frost Square John Frost Square",
    "iso:country":"GB",
    "sg:address":"Museum Library & Art Gallery, John Frost Square, John Frost Square",
    "sg:city":"Newport",
    "sg:classifiers":[
        {
            "category":"Landmark",
            "subcategory":"Tourist Information",
            "type":"Public Place"
        },
        {
            "category":"Government",
            "subcategory":"Office",
            "type":"Public Place"
        }
    ],
    "sg:phone":"+44 1633 842962",
    "sg:postcode":"NP20 4UR",
    "sg:province":"Newport",
    "sg:tags":[
        "local"
    ],
    "wof:name":"Tourist Information Centre",
    "wof:placetype":"venue"
},
  "geometry": {"coordinates":[-3.00585,51.588612],"type":"Point"}
}