{
  "type": "Feature",
  "properties": {
    "addr:full":"48 Bateman Street Cambridge Cambridgeshire CB2 1LR",
    "addr:housenumber":"48",
    "addr:postcode":"cb2 1lr",
    "addr:street":"Bateman Street",
    "iso:country":"GB",
    "sg:address":"48 Bateman Street",
    "sg:city":"Cambridge",
    "sg:classifiers":[
        {
            "category":"Professional",
            "subcategory":"Accounting & Tax Preparation",
            "type":"Services"
        }
    ],
    "sg:postcode":"CB2 1LR",
    "sg:province":"Cambridgeshire",
    "sg:tags":[
        "accountant"
    ],
    "wof:name":"Stafford & Co",
    "wof:placetype":"venue"
},
  "geometry": {"coordinates":[0.127005,52.195229],"type":"Point"}
}