{
  "type": "Feature",
  "properties": {
    "iso:country":"GB",
    "sg:address":"Unit D3 Brymau One Trading Estate, River Lane, Saltney",
    "sg:city":"Chester",
    "sg:classifiers":[
        {
            "category":"Shopping",
            "subcategory":"Computers & Home Electronics",
            "type":"Retail Goods"
        }
    ],
    "sg:phone":"+44 1244 675779",
    "sg:postcode":"CH4 8RG",
    "sg:province":"Cheshire",
    "sg:tags":[
        "electrical"
    ],
    "wof:name":"T N Robinson",
    "wof:placetype":"venue"
},
  "geometry": {"coordinates":[-2.92297,53.180752],"type":"Point"}
}