{
  "type": "Feature",
  "properties": {
    "iso:country":"GB",
    "sg:address":"Zeals House, 39 Church Street, Wye",
    "sg:city":"Ashford",
    "sg:classifiers":[
        {
            "category":"Banks & Credit Unions",
            "subcategory":"Bank",
            "type":"Services"
        }
    ],
    "sg:phone":"+44 1233 813333",
    "sg:postcode":"TN25 5BN",
    "sg:province":"Kent",
    "sg:tags":[
        "broker",
        "mortgage"
    ],
    "wof:name":"Hellier Independant Financial Services",
    "wof:placetype":"venue"
},
  "geometry": {"coordinates":[0.93736,51.183472],"type":"Point"}
}