{
  "type": "Feature",
  "properties": {
    "addr:full":"Beacon Oak Rd Tenterden Kent TN30 6RY",
    "addr:postcode":"tn30 6ry",
    "addr:street":"Beacon Oak Rd",
    "iso:country":"GB",
    "sg:address":"Beacon Oak Rd",
    "sg:city":"Tenterden",
    "sg:classifiers":[
        {
            "category":"Bus Charters",
            "type":"Transportation"
        }
    ],
    "sg:phone":"+44 1580 763887",
    "sg:postcode":"TN30 6RY",
    "sg:province":"Kent",
    "sg:tags":[
        "hire",
        "coach"
    ],
    "wof:name":"Warrens Coaches Ltd",
    "wof:placetype":"venue"
},
  "geometry": {"coordinates":[0.6943899989,51.0739936829],"type":"Point"}
}