{
  "type": "Feature",
  "properties": {
    "addr:full":"266 Daws Heath Road Benfleet Essex SS7 2TP",
    "addr:housenumber":"266",
    "addr:postcode":"ss7 2tp",
    "addr:street":"Daws Heath Road",
    "iso:country":"GB",
    "sg:address":"266 Daws Heath Road",
    "sg:city":"Benfleet",
    "sg:classifiers":[
        {
            "category":"Shopping",
            "subcategory":"Department Store",
            "type":"Retail Goods"
        }
    ],
    "sg:phone":"+44 1702 557644",
    "sg:postcode":"SS7 2TP",
    "sg:province":"Essex",
    "wof:name":"Mini Market",
    "wof:placetype":"venue"
},
  "geometry": {"coordinates":[0.6114789844,51.5692520142],"type":"Point"}
}