{
  "type": "Feature",
  "properties": {
    "addr:full":"16 Skylines Village, Limeharbour London Greater London E14 9XT",
    "addr:housenumber":"16",
    "addr:postcode":"e14 9xt",
    "addr:street":"Skylines Village Limeharbour",
    "iso:country":"GB",
    "sg:address":"16 Skylines Village, Limeharbour",
    "sg:city":"London",
    "sg:classifiers":[
        {
            "category":"Professional",
            "subcategory":"Art Services",
            "type":"Services"
        }
    ],
    "sg:postcode":"E14 9XT",
    "sg:province":"Greater London",
    "sg:tags":[
        "graphic",
        "designer"
    ],
    "wof:name":"Global Media Imaging Ltd.",
    "wof:placetype":"venue"
},
  "geometry": {"coordinates":[-0.0132200001,51.4991989136],"type":"Point"}
}