{
  "type": "Feature",
  "properties": {
    "addr:full":"Kings Arms Yard Bromyard Herefordshire HR7 4EE",
    "addr:postcode":"hr7 4ee",
    "addr:street":"Yard",
    "iso:country":"GB",
    "sg:address":"Kings Arms Yard",
    "sg:city":"Bromyard",
    "sg:classifiers":[
        {
            "category":"Personal",
            "subcategory":"Beauty Salon",
            "type":"Services"
        }
    ],
    "sg:phone":"+44 1885 483547",
    "sg:postcode":"HR7 4EE",
    "sg:province":"Herefordshire",
    "sg:tags":[
        "unisex",
        "hairdresser"
    ],
    "wof:name":"Short Cutz",
    "wof:placetype":"venue"
},
  "geometry": {"coordinates":[-2.5103991032,52.1890983582],"type":"Point"}
}