{
  "type": "Feature",
  "properties": {
    "iso:country":"GB",
    "sg:address":"8 Bell Meadow",
    "sg:city":"Maidstone",
    "sg:classifiers":[
        {
            "category":"Organizations",
            "subcategory":"Non-profit Organization",
            "type":"Services"
        }
    ],
    "sg:phone":"+44 1622 757967",
    "sg:postcode":"ME15 9NB",
    "sg:province":"Kent",
    "sg:tags":[
        "organisation",
        "voluntary",
        "charity"
    ],
    "wof:name":"I A",
    "wof:placetype":"venue"
},
  "geometry": {"coordinates":[0.552778,51.243786],"type":"Point"}
}