{
  "type": "Feature",
  "properties": {
    "iso:country":"GB",
    "sg:address":"51 Worcester Rd",
    "sg:city":"Bromsgrove",
    "sg:classifiers":[
        {
            "category":"Professional",
            "subcategory":"Lawyer & Legal Services",
            "type":"Services"
        }
    ],
    "sg:phone":"+44 1527 570490",
    "sg:postcode":"B61 7DN",
    "sg:province":"Worcestershire",
    "sg:tags":[
        "advice",
        "counselling"
    ],
    "wof:name":"Age Concern Information Centre",
    "wof:placetype":"venue"
},
  "geometry": {"coordinates":[-2.063435,52.332443],"type":"Point"}
}