{
  "type": "Feature",
  "properties": {
    "addr:full":"149-152 Waterloo Street Burton-on-trent Derbyshire DE14 2NG",
    "addr:housenumber":"149-152",
    "addr:postcode":"de14 2ng",
    "addr:street":"Waterloo Street",
    "iso:country":"GB",
    "sg:address":"149-152 Waterloo Street",
    "sg:city":"Burton-on-trent",
    "sg:classifiers":[
        {
            "category":"Shopping",
            "subcategory":"Baby Store",
            "type":"Retail Goods"
        }
    ],
    "sg:phone":"+44 1283 568870",
    "sg:postcode":"DE14 2NG",
    "sg:province":"Derbyshire",
    "sg:tags":[
        "nursery",
        "accessory"
    ],
    "wof:name":"Hewitts",
    "wof:placetype":"venue"
},
  "geometry": {"coordinates":[-1.6430530548,52.8132286072],"type":"Point"}
}