{
  "type": "Feature",
  "properties": {
    "iso:country":"GB",
    "sg:address":"Market St",
    "sg:city":"Coalville",
    "sg:classifiers":[
        {
            "category":"Shopping",
            "subcategory":"Shoes",
            "type":"Retail Goods"
        }
    ],
    "sg:phone":"+44 1530 811452",
    "sg:postcode":"LE67 3DX",
    "sg:province":"Leicestershire",
    "sg:tags":[
        "shop"
    ],
    "wof:name":"Gillivers Shoes Ltd",
    "wof:placetype":"venue"
},
  "geometry": {"coordinates":[-1.3760989904,52.7264709473],"type":"Point"}
}