{
  "type": "Feature",
  "properties": {
    "addr:full":"The Dovecote, High Street, Kislingbury Northampton Buckinghamshire NN7 4AG",
    "addr:postcode":"nn7 4ag",
    "addr:street":"High Street",
    "iso:country":"GB",
    "sg:address":"The Dovecote, High Street, Kislingbury",
    "sg:city":"Northampton",
    "sg:classifiers":[
        {
            "category":"Professional",
            "subcategory":"Management & Consulting",
            "type":"Services"
        },
        {
            "category":"Professional",
            "subcategory":"Employment Agencies",
            "type":"Services"
        }
    ],
    "sg:phone":"+44 1604 831122",
    "sg:postcode":"NN7 4AG",
    "sg:province":"Buckinghamshire",
    "sg:tags":[
        "consultant",
        "business"
    ],
    "wof:name":"Radcliffe Gower Ltd.",
    "wof:placetype":"venue"
},
  "geometry": {"coordinates":[-0.9789040089,52.2289886475],"type":"Point"}
}