{
  "type": "Feature",
  "properties": {
    "addr:full":"6 Ralston Way, South Oxhey Watford Hertfordshire WD19 7BH",
    "addr:housenumber":"6",
    "addr:postcode":"wd19 7bh",
    "addr:street":"Ralston Way South",
    "iso:country":"GB",
    "sg:address":"6 Ralston Way, South Oxhey",
    "sg:city":"Watford",
    "sg:classifiers":[
        {
            "category":"Building & Trades",
            "subcategory":"Construction",
            "type":"Services"
        }
    ],
    "sg:postcode":"WD19 7BH",
    "sg:province":"Hertfordshire",
    "sg:tags":[
        "roofing"
    ],
    "wof:name":"J P Roofing Services",
    "wof:placetype":"venue"
},
  "geometry": {"coordinates":[-0.3896389902,51.6298294067],"type":"Point"}
}