{
  "type": "Feature",
  "properties": {
    "addr:full":"4-5 Market Place, Aylesham Canterbury Kent CT3 3EY",
    "addr:housenumber":"4-5",
    "addr:postcode":"ct3 3ey",
    "addr:street":"Market Place",
    "iso:country":"GB",
    "sg:address":"4-5 Market Place, Aylesham",
    "sg:city":"Canterbury",
    "sg:classifiers":[
        {
            "category":"Shopping",
            "subcategory":"News",
            "type":"Retail Goods"
        }
    ],
    "sg:phone":"+44 1304 840249",
    "sg:postcode":"CT3 3EY",
    "sg:province":"Kent",
    "sg:tags":[
        "newsagent"
    ],
    "wof:name":"Aylesham Newsagency",
    "wof:placetype":"venue"
},
  "geometry": {"coordinates":[1.202621,51.225338],"type":"Point"}
}