{
  "type": "Feature",
  "properties": {
    "iso:country":"GB",
    "sg:address":"15 Tasmania Rd, Brockley Whins Estate",
    "sg:city":"South Shields",
    "sg:classifiers":[
        {
            "category":"Shopping",
            "subcategory":"Computers & Home Electronics",
            "type":"Retail Goods"
        }
    ],
    "sg:phone":"+44 191 424 0233",
    "sg:postcode":"NE34 9DX",
    "sg:province":"Tyne and Wear",
    "wof:name":"Q.C.C Products",
    "wof:placetype":"venue"
},
  "geometry": {"coordinates":[-1.4595630169,54.963886261],"type":"Point"}
}