{
  "type": "Feature",
  "properties": {
    "addr:full":"Wickens, Milton Rough, Acton Bridge Northwich Cheshire CW8 2RF",
    "addr:postcode":"cw8 2rf",
    "addr:street":"Wickens;Rough Acton Bridge",
    "iso:country":"GB",
    "sg:address":"Wickens, Milton Rough, Acton Bridge",
    "sg:city":"Northwich",
    "sg:classifiers":[
        {
            "category":"Organizations",
            "subcategory":"Community Association",
            "type":"Services"
        }
    ],
    "sg:phone":"+44 1606 853535",
    "sg:postcode":"CW8 2RF",
    "sg:province":"Cheshire",
    "sg:tags":[
        "relation",
        "public"
    ],
    "wof:name":"M K L Publicity Consultancy",
    "wof:placetype":"venue"
},
  "geometry": {"coordinates":[-2.6067,53.265862],"type":"Point"}
}