{
  "type": "Feature",
  "properties": {
    "addr:full":"Whitehouse Farm, Knowle La Chard Devon TA20 3BZ",
    "addr:postcode":"ta20 3bz",
    "addr:street":"Knowle",
    "iso:country":"GB",
    "sg:address":"Whitehouse Farm, Knowle La",
    "sg:city":"Chard",
    "sg:classifiers":[
        {
            "category":"Farming",
            "subcategory":"Livestock Farm",
            "type":"Manufacturing & Wholesale Goods"
        }
    ],
    "sg:phone":"+44 1460 62289",
    "sg:postcode":"TA20 3BZ",
    "sg:province":"Devon",
    "sg:tags":[
        "others"
    ],
    "wof:name":"E G Trott",
    "wof:placetype":"venue"
},
  "geometry": {"coordinates":[-2.960474,50.873524],"type":"Point"}
}