{
  "type": "Feature",
  "properties": {
    "addr:full":"47 Wittonwood Rd Frinton On Sea Essex CO13 9JZ",
    "addr:housenumber":"47",
    "addr:postcode":"co13 9jz",
    "addr:street":"Wittonwood Rd",
    "iso:country":"GB",
    "sg:address":"47 Wittonwood Rd",
    "sg:city":"Frinton On Sea",
    "sg:classifiers":[
        {
            "category":"Education",
            "subcategory":"Special Training",
            "type":"Public Place"
        }
    ],
    "sg:phone":"+44 1255 850180",
    "sg:postcode":"CO13 9JZ",
    "sg:province":"Essex",
    "sg:tags":[
        "product",
        "centre"
    ],
    "wof:name":"National First",
    "wof:placetype":"venue"
},
  "geometry": {"coordinates":[1.2419400215,51.8373718262],"type":"Point"}
}