{
  "type": "Feature",
  "properties": {
    "addr:full":"12 Galmington Drive Taunton Somerset TA1 5AD",
    "addr:housenumber":"12",
    "addr:postcode":"ta1 5ad",
    "addr:street":"Galmington Drive",
    "iso:country":"GB",
    "sg:address":"12 Galmington Drive",
    "sg:city":"Taunton",
    "sg:classifiers":[
        {
            "category":"Professional",
            "type":"Services"
        }
    ],
    "sg:phone":"+44 1823 277551",
    "sg:postcode":"TA1 5AD",
    "sg:province":"Somerset",
    "sg:tags":[
        "caterer"
    ],
    "wof:name":"Blue Ribbon Bar Services",
    "wof:placetype":"venue"
},
  "geometry": {"coordinates":[-3.124368,51.007771],"type":"Point"}
}