{
  "type": "Feature",
  "properties": {
    "addr:full":"101 Corbiehall Bo'ness Falkirk EH51 0AU",
    "addr:housenumber":"101",
    "addr:postcode":"eh51 0au",
    "addr:street":"Corbiehall",
    "iso:country":"GB",
    "sg:address":"101 Corbiehall",
    "sg:city":"Bo'ness",
    "sg:classifiers":[
        {
            "category":"Shopping",
            "subcategory":"Computers & Home Electronics",
            "type":"Retail Goods"
        }
    ],
    "sg:phone":"+44 1506 517037",
    "sg:postcode":"EH51 0AU",
    "sg:province":"Falkirk",
    "wof:name":"Meridion Computer Technologies",
    "wof:placetype":"venue"
},
  "geometry": {"coordinates":[-3.6151490211,56.0146598816],"type":"Point"}
}