{
  "type": "Feature",
  "properties": {
    "iso:country":"GB",
    "sg:address":"163 County Rd",
    "sg:city":"Liverpool",
    "sg:classifiers":[
        {
            "category":"Home & Garden",
            "subcategory":"Home Furnishings",
            "type":"Retail Goods"
        }
    ],
    "sg:postcode":"L4 5PB",
    "sg:province":"Merseyside",
    "sg:tags":[
        "blind",
        "curtain",
        "fitting"
    ],
    "wof:name":"County Curtains",
    "wof:placetype":"venue"
},
  "geometry": {"coordinates":[-2.970126,53.443859],"type":"Point"}
}