{
  "type": "Feature",
  "properties": {
    "iso:country":"GB",
    "sg:address":"21 St Helens Street",
    "sg:city":"Ipswich",
    "sg:classifiers":[
        {
            "category":"Personal",
            "subcategory":"Beauty Salon",
            "type":"Services"
        }
    ],
    "sg:phone":"+44 1473 251453",
    "sg:postcode":"IP4 1HE",
    "sg:province":"Suffolk",
    "wof:name":"Perfections Health & Beauty Salon",
    "wof:placetype":"venue"
},
  "geometry": {"coordinates":[1.161271,52.057049],"type":"Point"}
}