{
  "type": "Feature",
  "properties": {
    "addr:full":"17m Roseview, 122 Marsala Road London Greater London SE13 7AF",
    "addr:housenumber":"17m;122",
    "addr:postcode":"se13 7af",
    "addr:street":"Roseview;Marsala Road",
    "iso:country":"GB",
    "sg:address":"17m Roseview, 122 Marsala Road",
    "sg:city":"London",
    "sg:classifiers":[
        {
            "category":"Government",
            "subcategory":"Office",
            "type":"Public Place"
        }
    ],
    "sg:phone":"+44 20 8690 8675",
    "sg:postcode":"SE13 7AF",
    "sg:province":"Greater London",
    "sg:tags":[
        "local"
    ],
    "wof:name":"Social Services",
    "wof:placetype":"venue"
},
  "geometry": {"coordinates":[-0.0189699996,51.4582901001],"type":"Point"}
}