{
  "type": "Feature",
  "properties": {
    "iso:country":"GB",
    "sg:address":"Ketches La, Sheffield Pk",
    "sg:city":"Uckfield",
    "sg:classifiers":[
        {
            "category":"Building & Trades",
            "subcategory":"Construction",
            "type":"Services"
        }
    ],
    "sg:postcode":"TN22 3RY",
    "sg:province":"East Sussex",
    "sg:tags":[
        "excavation",
        "groundwork",
        "contractor"
    ],
    "wof:name":"Lakes & Greens Ltd",
    "wof:placetype":"venue"
},
  "geometry": {"coordinates":[-0.010976,51.010536],"type":"Point"}
}