{
  "type": "Feature",
  "properties": {
    "iso:country":"GB",
    "sg:address":"46 Stirling Street",
    "sg:city":"Denny",
    "sg:classifiers":[
        {
            "category":"Fast Food",
            "type":"Food & Drink"
        }
    ],
    "sg:phone":"+44 1324 826757",
    "sg:postcode":"FK6 6DJ",
    "sg:province":"Falkirk",
    "sg:tags":[
        "away",
        "meal",
        "outlet",
        "take"
    ],
    "wof:name":"Tasty Bite Kebab House",
    "wof:placetype":"venue"
},
  "geometry": {"coordinates":[-3.907896,56.023884],"type":"Point"}
}