{
  "type": "Feature",
  "properties": {
    "iso:country":"GB",
    "sg:address":"Unit 12d, Adlington Park",
    "sg:city":"Macclesfield",
    "sg:classifiers":[
        {
            "category":"Professional",
            "subcategory":"Computer Services",
            "type":"Services"
        }
    ],
    "sg:phone":"+44 870 740 8090",
    "sg:postcode":"SK10 4PZ",
    "sg:province":"Cheshire",
    "sg:tags":[
        "consultant"
    ],
    "wof:name":"Getonline Ltd.",
    "wof:placetype":"venue"
},
  "geometry": {"coordinates":[-2.132956,53.335804],"type":"Point"}
}