{
  "type": "Feature",
  "properties": {
    "iso:country":"GB",
    "sg:address":"Marton House, Low Road",
    "sg:city":"Bungay",
    "sg:classifiers":[
        {
            "category":"Building & Trades",
            "subcategory":"Construction",
            "type":"Services"
        }
    ],
    "sg:phone":"+44 1986 893464",
    "sg:postcode":"NR35 1TS",
    "sg:province":"Norfolk",
    "sg:tags":[
        "builder"
    ],
    "wof:name":"Sprake & Tyrrell",
    "wof:placetype":"venue"
},
  "geometry": {"coordinates":[1.4675379992,52.4611968994],"type":"Point"}
}