{
  "type": "Feature",
  "properties": {
    "addr:full":"20 Somerset Street, Kingsdown Bristol City of Bristol BS2 8LZ",
    "addr:housenumber":"20",
    "addr:postcode":"bs2 8lz",
    "addr:street":"Somerset Street",
    "iso:country":"GB",
    "sg:address":"20 Somerset Street, Kingsdown",
    "sg:city":"Bristol",
    "sg:classifiers":[
        {
            "category":"Professional",
            "type":"Services"
        }
    ],
    "sg:postcode":"BS2 8LZ",
    "sg:province":"City of Bristol",
    "sg:tags":[
        "entertainer"
    ],
    "wof:name":"Brog Puppets",
    "wof:placetype":"venue"
},
  "geometry": {"coordinates":[-2.5938849449,51.4626655579],"type":"Point"}
}