{
  "type": "Feature",
  "properties": {
    "iso:country":"GB",
    "sg:address":"Auchengate Farm",
    "sg:city":"Irvine",
    "sg:classifiers":[
        {
            "category":"Building & Trades",
            "subcategory":"Construction",
            "type":"Services"
        }
    ],
    "sg:phone":"+44 1294 277955",
    "sg:postcode":"KA11 5BQ",
    "sg:province":"East Ayrshire",
    "sg:tags":[
        "welder"
    ],
    "wof:name":"Kayes Mobile Welding",
    "wof:placetype":"venue"
},
  "geometry": {"coordinates":[-4.638259,55.598297],"type":"Point"}
}