{
  "type": "Feature",
  "properties": {
    "addr:full":"Chapel House Suite 4, Out Westgate Bury St Edmunds Suffolk IP33 3NZ",
    "addr:housenumber":"suite 4",
    "addr:postcode":"ip33 3nz",
    "addr:street":"Westgate",
    "iso:country":"GB",
    "sg:address":"Chapel House Suite 4, Out Westgate",
    "sg:city":"Bury St Edmunds",
    "sg:classifiers":[
        {
            "category":"Health Services",
            "subcategory":"Nursing And Care Facility",
            "type":"Services"
        }
    ],
    "sg:phone":"+44 1284 769922",
    "sg:postcode":"IP33 3NZ",
    "sg:province":"Suffolk",
    "sg:tags":[
        "home"
    ],
    "wof:name":"Pinford End Ltd.",
    "wof:placetype":"venue"
},
  "geometry": {"coordinates":[0.7103840113,52.2405395508],"type":"Point"}
}