{
  "type": "Feature",
  "properties": {
    "iso:country":"GB",
    "sg:address":"North Road, Dipton",
    "sg:city":"Stanley",
    "sg:classifiers":[
        {
            "category":"Place Of Worship",
            "type":"Public Place"
        }
    ],
    "sg:postcode":"DH9 9BB",
    "sg:province":"Durham",
    "wof:name":"St.Patricks R C Church",
    "wof:placetype":"venue"
},
  "geometry": {"coordinates":[-1.761599,54.876953],"type":"Point"}
}