{
  "type": "Feature",
  "properties": {
    "addr:full":"14 Windsor Gdns, Hatchwarren Basingstoke Hampshire RG22 4XW",
    "addr:housenumber":"14",
    "addr:postcode":"rg22 4xw",
    "addr:street":"Windsor Gdns Hatchwarren",
    "iso:country":"GB",
    "sg:address":"14 Windsor Gdns, Hatchwarren",
    "sg:city":"Basingstoke",
    "sg:classifiers":[
        {
            "category":"Personal",
            "type":"Services"
        }
    ],
    "sg:phone":"+44 1256 334335",
    "sg:postcode":"RG22 4XW",
    "sg:province":"Hampshire",
    "sg:tags":[
        "consultant",
        "fitness"
    ],
    "wof:name":"Unique Fitness",
    "wof:placetype":"venue"
},
  "geometry": {"coordinates":[-1.1378350258,51.2369232178],"type":"Point"}
}