{
  "type": "Feature",
  "properties": {
    "addr:full":"Oxford St Daventry Northamptonshire NN11 4AD",
    "addr:postcode":"nn11 4ad",
    "addr:street":"Oxford St",
    "iso:country":"GB",
    "sg:address":"Oxford St",
    "sg:city":"Daventry",
    "sg:classifiers":[
        {
            "category":"Professional",
            "subcategory":"Printing & Photocopies",
            "type":"Services"
        }
    ],
    "sg:phone":"+44 1327 311305",
    "sg:postcode":"NN11 4AD",
    "sg:province":"Northamptonshire",
    "sg:tags":[
        "printer"
    ],
    "wof:name":"Print-X-Press Copy Shop",
    "wof:placetype":"venue"
},
  "geometry": {"coordinates":[-1.163308,52.255875],"type":"Point"}
}