{
  "type": "Feature",
  "properties": {
    "addr:full":"Fore St Ivybridge Devon PL21 9AB",
    "addr:postcode":"pl21 9ab",
    "addr:street":"Fore St",
    "iso:country":"GB",
    "sg:address":"Fore St",
    "sg:city":"Ivybridge",
    "sg:classifiers":[
        {
            "category":"Military Area",
            "subcategory":"Air Force Base",
            "type":"Public Place"
        }
    ],
    "sg:phone":"+44 1752 896759",
    "sg:postcode":"PL21 9AB",
    "sg:province":"Devon",
    "sg:tags":[
        "taxi",
        "hire",
        "private"
    ],
    "wof:name":"Ivybridge Taxis",
    "wof:placetype":"venue"
},
  "geometry": {"coordinates":[-3.9207038879,50.3894805908],"type":"Point"}
}