{
  "type": "Feature",
  "properties": {
    "addr:full":"Tower Park, Mannings Heath Poole Dorset BH12 4NY",
    "addr:postcode":"bh12 4ny",
    "addr:street":"Tower Park",
    "iso:country":"GB",
    "sg:address":"Tower Park, Mannings Heath",
    "sg:city":"Poole",
    "sg:classifiers":[
        {
            "category":"Organizations",
            "subcategory":"Membership Organization",
            "type":"Services"
        }
    ],
    "sg:phone":"+44 1202 739989",
    "sg:postcode":"BH12 4NY",
    "sg:province":"Dorset",
    "sg:tags":[
        "club"
    ],
    "wof:name":"Gala Clubs",
    "wof:placetype":"venue"
},
  "geometry": {"coordinates":[-1.951744,50.747795],"type":"Point"}
}