{
  "type": "Feature",
  "properties": {
    "iso:country":"GB",
    "sg:address":"Lime Tree Road",
    "sg:city":"Matlock",
    "sg:classifiers":[
        {
            "category":"Shopping",
            "subcategory":"Department Store",
            "type":"Retail Goods"
        },
        {
            "category":"Food & Beverages",
            "subcategory":"Groceries & Convenience Stores",
            "type":"Retail Goods"
        }
    ],
    "sg:phone":"+44 1629 55975",
    "sg:postcode":"DE4 3EJ",
    "sg:province":"Derbyshire",
    "wof:name":"Lime Tree Stores Ltd",
    "wof:placetype":"venue"
},
  "geometry": {"coordinates":[-1.548106,53.138687],"type":"Point"}
}