{
  "type": "Feature",
  "properties": {
    "iso:country":"GB",
    "sg:address":"57-60 Haymarket",
    "sg:city":"London",
    "sg:classifiers":[
        {
            "category":"Restaurant",
            "type":"Food & Drink"
        }
    ],
    "sg:phone":"+44 20 7930 9970",
    "sg:postcode":"SW1Y 4QX",
    "sg:province":"Greater London",
    "wof:name":"Punch Inns (U K) Ltd",
    "wof:placetype":"venue"
},
  "geometry": {"coordinates":[-0.132536,51.509254],"type":"Point"}
}