{
  "type": "Feature",
  "properties": {
    "addr:full":"136 Campbell St, Farnworth Bolton Lancashire BL4 7HW",
    "addr:housenumber":"136",
    "addr:postcode":"bl4 7hw",
    "addr:street":"Campbell St",
    "iso:country":"GB",
    "sg:address":"136 Campbell St, Farnworth",
    "sg:city":"Bolton",
    "sg:classifiers":[
        {
            "category":"Shopping",
            "subcategory":"News",
            "type":"Retail Goods"
        }
    ],
    "sg:postcode":"BL4 7HW",
    "sg:province":"Lancashire",
    "sg:tags":[
        "newsagent"
    ],
    "wof:name":"Ahmed,Mohammed,",
    "wof:placetype":"venue"
},
  "geometry": {"coordinates":[-2.413623,53.554634],"type":"Point"}
}