{
  "type": "Feature",
  "properties": {
    "addr:full":"220 Martin Way Morden Surrey SM4 4AW",
    "addr:housenumber":"220",
    "addr:postcode":"sm4 4aw",
    "addr:street":"Martin Way",
    "iso:country":"GB",
    "sg:address":"220 Martin Way",
    "sg:city":"Morden",
    "sg:classifiers":[
        {
            "category":"Professional",
            "subcategory":"Engineering",
            "type":"Services"
        },
        {
            "category":"Building & Trades",
            "subcategory":"Electrical",
            "type":"Services"
        }
    ],
    "sg:phone":"+44 20 8540 9879",
    "sg:postcode":"SM4 4AW",
    "sg:province":"Surrey",
    "sg:tags":[
        "engineer",
        "electrician",
        "contractor"
    ],
    "wof:name":"Sparks",
    "wof:placetype":"venue"
},
  "geometry": {"coordinates":[-0.2112420052,51.4029197693],"type":"Point"}
}