{
  "type": "Feature",
  "properties": {
    "addr:full":"Pitcow Farm, Whiterashes Aberbeen Aberdeen Aberdeen City AB21 0QW",
    "addr:postcode":"ab21 0qw",
    "iso:country":"GB",
    "sg:address":"Pitcow Farm, Whiterashes Aberbeen",
    "sg:city":"Aberdeen",
    "sg:classifiers":[
        {
            "category":"Train Station",
            "subcategory":"Rail",
            "type":"Transportation"
        }
    ],
    "sg:phone":"+44 1651 882202",
    "sg:postcode":"AB21 0QW",
    "sg:province":"Aberdeen City",
    "sg:tags":[
        "caravan"
    ],
    "wof:name":"Pitcow Self-tow",
    "wof:placetype":"venue"
},
  "geometry": {"coordinates":[-2.2443740368,57.3027992249],"type":"Point"}
}