{
  "type": "Feature",
  "properties": {
    "addr:full":"5 Mead Industrial Park, Riverway Harlow Essex CM20 2SE",
    "addr:housenumber":"5",
    "addr:postcode":"cm20 2se",
    "addr:street":"Mead Industrial Park Riverway",
    "iso:country":"GB",
    "sg:address":"5 Mead Industrial Park, Riverway",
    "sg:city":"Harlow",
    "sg:classifiers":[
        {
            "category":"Shopping",
            "subcategory":"Discount & Variety Stores",
            "type":"Retail Goods"
        }
    ],
    "sg:phone":"+44 1279 454007",
    "sg:postcode":"CM20 2SE",
    "sg:province":"Essex",
    "sg:tags":[
        "cleaning",
        "supply"
    ],
    "wof:name":"Jasan Supplies Ltd.",
    "wof:placetype":"venue"
},
  "geometry": {"coordinates":[0.1117,51.787769],"type":"Point"}
}