{
  "type": "Feature",
  "properties": {
    "iso:country":"GB",
    "sg:address":"Unit 2 The Forge, Nepcote Lane",
    "sg:city":"Worthing",
    "sg:classifiers":[
        {
            "category":"Autos & Motor Vehicles",
            "subcategory":"Motorcycle Sales",
            "type":"Retail Goods"
        }
    ],
    "sg:phone":"+44 1903 877517",
    "sg:postcode":"BN14 0SE",
    "sg:province":"West Sussex",
    "sg:tags":[
        "component"
    ],
    "wof:name":"C L Promotions",
    "wof:placetype":"venue"
},
  "geometry": {"coordinates":[-0.4064800143,50.8673782349],"type":"Point"}
}