{
  "type": "Feature",
  "properties": {
    "addr:full":"34 Philips Av Bolton Lancashire BL4 9BJ",
    "addr:housenumber":"34",
    "addr:postcode":"bl4 9bj",
    "addr:street":"Philips Av Bolton",
    "iso:country":"GB",
    "sg:address":"34 Philips Av",
    "sg:city":"Bolton",
    "sg:classifiers":[
        {
            "category":"Manufacturing",
            "subcategory":"Petroleum Products",
            "type":"Manufacturing & Wholesale Goods"
        }
    ],
    "sg:phone":"+44 1204 571632",
    "sg:postcode":"BL4 9BJ",
    "sg:province":"Lancashire",
    "sg:tags":[
        "double",
        "glazing"
    ],
    "wof:name":"T Travers",
    "wof:placetype":"venue"
},
  "geometry": {"coordinates":[-2.394985,53.544994],"type":"Point"}
}