{
  "type": "Feature",
  "properties": {
    "addr:full":"45 Dowbridge, Kirkham Preston Lancashire PR4 2YJ",
    "addr:housenumber":"45",
    "addr:postcode":"pr4 2yj",
    "addr:street":"Dowbridge Kirkham",
    "iso:country":"GB",
    "sg:address":"45 Dowbridge, Kirkham",
    "sg:city":"Preston",
    "sg:classifiers":[
        {
            "category":"Building & Trades",
            "subcategory":"Construction",
            "type":"Services"
        }
    ],
    "sg:postcode":"PR4 2YJ",
    "sg:province":"Lancashire",
    "sg:tags":[
        "joiner",
        "carpenter"
    ],
    "wof:name":"Kevin Dodd",
    "wof:placetype":"venue"
},
  "geometry": {"coordinates":[-2.860853,53.779545],"type":"Point"}
}