{
  "type": "Feature",
  "properties": {
    "addr:full":"42 Charles Street Cardiff Cardiff CF10 2GE",
    "addr:housenumber":"42",
    "addr:postcode":"cf10 2ge",
    "addr:street":"Charles Street",
    "iso:country":"GB",
    "sg:address":"42 Charles Street",
    "sg:city":"Cardiff",
    "sg:classifiers":[
        {
            "category":"Bars & Pubs",
            "type":"Food & Drink"
        }
    ],
    "sg:phone":"+44 29 2023 3128",
    "sg:postcode":"CF10 2GE",
    "sg:province":"Cardiff",
    "sg:tags":[
        "pubs",
        "inn"
    ],
    "wof:name":"Minsky Ltd.",
    "wof:placetype":"venue"
},
  "geometry": {"coordinates":[-3.174589,51.482109],"type":"Point"}
}