{
  "type": "Feature",
  "properties": {
    "addr:full":"1 Novar Drive Glasgow Glasgow City G12 9PX",
    "addr:housenumber":"1",
    "addr:postcode":"g12 9px",
    "addr:street":"Novar Drive",
    "iso:country":"GB",
    "sg:address":"1 Novar Drive",
    "sg:city":"Glasgow",
    "sg:classifiers":[
        {
            "category":"Professional",
            "subcategory":"Employment Agencies",
            "type":"Services"
        }
    ],
    "sg:postcode":"G12 9PX",
    "sg:province":"Glasgow City",
    "sg:tags":[
        "pair",
        "consultant",
        "au"
    ],
    "wof:name":"Scandinavian Au Pair Agency",
    "wof:placetype":"venue"
},
  "geometry": {"coordinates":[-4.306457,55.879662],"type":"Point"}
}