{
  "type": "Feature",
  "properties": {
    "iso:country":"GB",
    "sg:address":"19 Granville Road",
    "sg:city":"Broadstairs",
    "sg:classifiers":[
        {
            "category":"Travel",
            "subcategory":"Hotels & Motels",
            "type":"Entertainment"
        }
    ],
    "sg:postcode":"CT10 1QB",
    "sg:province":"Kent",
    "sg:tags":[
        "house",
        "guest"
    ],
    "wof:name":"ST AUGUSTINES HOTEL",
    "wof:placetype":"venue"
},
  "geometry": {"coordinates":[1.4407000542,51.3557739258],"type":"Point"}
}