{
  "type": "Feature",
  "properties": {
    "iso:country":"GB",
    "sg:address":"Pelham Road",
    "sg:city":"Immingham",
    "sg:classifiers":[
        {
            "category":"Education",
            "subcategory":"School",
            "type":"Public Place"
        },
        {
            "category":"Government",
            "subcategory":"Office",
            "type":"Public Place"
        }
    ],
    "sg:phone":"+44 1469 572424",
    "sg:postcode":"DN40 1JR",
    "sg:province":"Lincolnshire",
    "sg:tags":[
        "local",
        "authority"
    ],
    "wof:name":"Canon Peter Hall Cv Church of England Primary Scho",
    "wof:placetype":"venue"
},
  "geometry": {"coordinates":[-0.2007849962,53.6200218201],"type":"Point"}
}