{
  "type": "Feature",
  "properties": {
    "addr:full":"30 Great Portland St West End Hampshire W1N 5AD",
    "addr:housenumber":"30",
    "addr:postcode":"w1n 5ad",
    "addr:street":"Great Portland St",
    "iso:country":"GB",
    "sg:address":"30 Great Portland St",
    "sg:city":"West End",
    "sg:classifiers":[
        {
            "category":"Manufacturing",
            "subcategory":"Textiles",
            "type":"Manufacturing & Wholesale Goods"
        }
    ],
    "sg:phone":"+44 20 7637 4840",
    "sg:postcode":"W1N 5AD",
    "sg:province":"Hampshire",
    "sg:tags":[
        "knitwear"
    ],
    "wof:name":"Michael Grimwood",
    "wof:placetype":"venue"
},
  "geometry": {"coordinates":[-0.1410659999,51.5168952942],"type":"Point"}
}