{
  "type": "Feature",
  "properties": {
    "iso:country":"GB",
    "sg:address":"Charis 31 Mile End Road",
    "sg:city":"London",
    "sg:classifiers":[
        {
            "category":"Organizations",
            "subcategory":"Non-profit Organization",
            "type":"Services"
        }
    ],
    "sg:phone":"+44 20 7790 3040",
    "sg:postcode":"E1 4TP",
    "sg:province":"Greater London",
    "sg:tags":[
        "organisation",
        "voluntary",
        "charity"
    ],
    "wof:name":"The Tower Hamlets Mission",
    "wof:placetype":"venue"
},
  "geometry": {"coordinates":[-0.053989999,51.5205612183],"type":"Point"}
}