{
  "type": "Feature",
  "properties": {
    "iso:country":"GB",
    "sg:address":"32 Park Square",
    "sg:city":"Leeds",
    "sg:classifiers":[
        {
            "category":"Professional",
            "subcategory":"Lawyer & Legal Services",
            "type":"Services"
        }
    ],
    "sg:phone":"+44 113 247 1477",
    "sg:postcode":"LS1 2PF",
    "sg:province":"West Yorkshire",
    "sg:tags":[
        "solicitor"
    ],
    "wof:name":"O'Garra Smith Gold",
    "wof:placetype":"venue"
},
  "geometry": {"coordinates":[-1.552609,53.797596],"type":"Point"}
}