{
  "type": "Feature",
  "properties": {
    "addr:full":"The Street, Sheering Bishops Stortford Essex CM22 7LZ",
    "addr:postcode":"cm22 7lz",
    "addr:street":"The Street",
    "iso:country":"GB",
    "sg:address":"The Street, Sheering",
    "sg:city":"Bishops Stortford",
    "sg:classifiers":[
        {
            "category":"Bars & Pubs",
            "type":"Food & Drink"
        }
    ],
    "sg:phone":"+44 1279 734203",
    "sg:postcode":"CM22 7LZ",
    "sg:province":"Essex",
    "sg:tags":[
        "pubs",
        "inn"
    ],
    "wof:name":"The Crown Inn",
    "wof:placetype":"venue"
},
  "geometry": {"coordinates":[0.213116,51.855583],"type":"Point"}
}