{
  "type": "Feature",
  "properties": {
    "iso:country":"GB",
    "sg:address":"Mill Court",
    "sg:city":"Stafford",
    "sg:classifiers":[
        {
            "category":"Shopping",
            "subcategory":"Optician",
            "type":"Retail Goods"
        }
    ],
    "sg:phone":"+44 1785 215077",
    "sg:postcode":"ST16 2AX",
    "sg:province":"Staffordshire",
    "wof:name":"Visionex 2000 Ltd.",
    "wof:placetype":"venue"
},
  "geometry": {"coordinates":[-2.121768,52.803959],"type":"Point"}
}