{
  "type": "Feature",
  "properties": {
    "addr:full":"240 Mansfield Road, Redhill Nottingham Nottinghamshire NG5 8JY",
    "addr:housenumber":"240",
    "addr:postcode":"ng5 8jy",
    "addr:street":"Mansfield Road",
    "iso:country":"GB",
    "sg:address":"240 Mansfield Road, Redhill",
    "sg:city":"Nottingham",
    "sg:classifiers":[
        {
            "category":"Retail",
            "subcategory":"Auto Repair",
            "type":"Services"
        }
    ],
    "sg:postcode":"NG5 8JY",
    "sg:province":"Nottinghamshire",
    "sg:tags":[
        "electrician"
    ],
    "wof:name":"Arnold Auto Electrical",
    "wof:placetype":"venue"
},
  "geometry": {"coordinates":[-1.1333559752,53.0121612549],"type":"Point"}
}