{
  "type": "Feature",
  "properties": {
    "addr:full":"2-4 Wharfdale Road London Greater London N1 9RY",
    "addr:housenumber":"2-4",
    "addr:postcode":"n1 9ry",
    "addr:street":"Wharfdale Road",
    "iso:country":"GB",
    "sg:address":"2-4 Wharfdale Road",
    "sg:city":"London",
    "sg:classifiers":[
        {
            "category":"Bars & Pubs",
            "type":"Food & Drink"
        }
    ],
    "sg:phone":"+44 20 7278 8827",
    "sg:postcode":"N1 9RY",
    "sg:province":"Greater London",
    "sg:tags":[
        "pubs",
        "inn"
    ],
    "wof:name":"General Picton",
    "wof:placetype":"venue"
},
  "geometry": {"coordinates":[-0.119051002,51.5336303711],"type":"Point"}
}