{
  "type": "Feature",
  "properties": {
    "iso:country":"GB",
    "sg:address":"55 Beatrice Road",
    "sg:city":"Leicester",
    "sg:classifiers":[
        {
            "category":"Organizations",
            "subcategory":"Membership Organization",
            "type":"Services"
        }
    ],
    "sg:phone":"+44 116 262 7230",
    "sg:postcode":"LE3 9FJ",
    "sg:province":"Leicestershire",
    "sg:tags":[
        "club"
    ],
    "wof:name":"Newfoundpool Working Mens Non-Political",
    "wof:placetype":"venue"
},
  "geometry": {"coordinates":[-1.154485,52.641209],"type":"Point"}
}