{
  "type": "Feature",
  "properties": {
    "addr:full":"149 Clenchwarton Rd King's Lynn Lincolnshire PE34 3LH",
    "addr:housenumber":"149",
    "addr:postcode":"pe34 3lh",
    "addr:street":"Clenchwarton Rd",
    "iso:country":"GB",
    "sg:address":"149 Clenchwarton Rd",
    "sg:city":"King's Lynn",
    "sg:classifiers":[
        {
            "category":"Autos & Motor Vehicles",
            "subcategory":"Automobile Sales",
            "type":"Retail Goods"
        }
    ],
    "sg:postcode":"PE34 3LH",
    "sg:province":"Lincolnshire",
    "sg:tags":[
        "car"
    ],
    "wof:name":"Moore,Steve,",
    "wof:placetype":"venue"
},
  "geometry": {"coordinates":[0.38042,52.75106],"type":"Point"}
}