{
  "type": "Feature",
  "properties": {
    "addr:full":"9 Gurney Way Aycliffe Industrial Estate Newton Aycliffe Durham DL5 6UJ",
    "addr:housenumber":"9",
    "addr:postcode":"dl5 6uj",
    "addr:street":"Gurney Way;Industrial Estate;Aycliffe",
    "iso:country":"GB",
    "sg:address":"9 Gurney Way Aycliffe Industrial Estate",
    "sg:city":"Newton Aycliffe",
    "sg:classifiers":[
        {
            "category":"Home & Garden",
            "subcategory":"Hardware",
            "type":"Retail Goods"
        }
    ],
    "sg:phone":"+44 1325 317478",
    "sg:postcode":"DL5 6UJ",
    "sg:province":"Durham",
    "sg:tags":[
        "fixing",
        "nuts",
        "bolt"
    ],
    "wof:name":"Thomas Potter (Aycliffe) Branch",
    "wof:placetype":"venue"
},
  "geometry": {"coordinates":[-1.563024,54.596272],"type":"Point"}
}