{
  "type": "Feature",
  "properties": {
    "iso:country":"GB",
    "sg:address":"Woodstock Bower Farm, Marchington Woodlands, Marchington",
    "sg:city":"Uttoxeter",
    "sg:classifiers":[
        {
            "category":"Transit Center",
            "subcategory":"Passenger",
            "type":"Transportation"
        }
    ],
    "sg:postcode":"ST14 8PD",
    "sg:province":"Derbyshire",
    "sg:tags":[
        "boarding",
        "kennel",
        "catteries"
    ],
    "wof:name":"Woodstock Bower Boarding & Breeding Kennels",
    "wof:placetype":"venue"
},
  "geometry": {"coordinates":[-1.807716012,52.8694610596],"type":"Point"}
}