{
  "type": "Feature",
  "properties": {
    "addr:full":"Bells Orchard, Regent Street, Talgarth Brecon Powys LD3 0DD",
    "addr:postcode":"ld3 0dd",
    "addr:street":"Regent Street",
    "iso:country":"GB",
    "sg:address":"Bells Orchard, Regent Street, Talgarth",
    "sg:city":"Brecon",
    "sg:classifiers":[
        {
            "category":"Bus Charters",
            "type":"Transportation"
        }
    ],
    "sg:postcode":"LD3 0DD",
    "sg:province":"Powys",
    "sg:tags":[
        "coach"
    ],
    "wof:name":"Talgarth Travel",
    "wof:placetype":"venue"
},
  "geometry": {"coordinates":[-3.2325880527,51.995349884],"type":"Point"}
}