{
  "type": "Feature",
  "properties": {
    "iso:country":"GB",
    "sg:address":"547 Main Rd",
    "sg:city":"Harwich",
    "sg:classifiers":[
        {
            "category":"Building & Trades",
            "subcategory":"Construction",
            "type":"Services"
        }
    ],
    "sg:phone":"+44 1255 502386",
    "sg:postcode":"CO12 4NH",
    "sg:province":"Essex",
    "sg:tags":[
        "builder"
    ],
    "wof:name":"Heritage Builders",
    "wof:placetype":"venue"
},
  "geometry": {"coordinates":[1.253214,51.932159],"type":"Point"}
}