{
  "type": "Feature",
  "properties": {
    "iso:country":"GB",
    "sg:address":"277 Globe Road",
    "sg:city":"London",
    "sg:classifiers":[
        {
            "category":"Bars & Pubs",
            "type":"Food & Drink"
        },
        {
            "category":"Community Center",
            "subcategory":"Social",
            "type":"Public Place"
        }
    ],
    "sg:phone":"+44 20 8983 9888",
    "sg:postcode":"E2 0JD",
    "sg:province":"Greater London",
    "sg:tags":[
        "pubs",
        "house",
        "inn",
        "activity"
    ],
    "wof:name":"The Camel",
    "wof:placetype":"venue"
},
  "geometry": {"coordinates":[-0.051899,51.528744],"type":"Point"}
}