{
  "type": "Feature",
  "properties": {
    "addr:full":"87 Hockenhull Lane, Tarvin Chester Cheshire CH3 8LD",
    "addr:housenumber":"87",
    "addr:postcode":"ch3 8ld",
    "addr:street":"Hockenhull Lane",
    "iso:country":"GB",
    "sg:address":"87 Hockenhull Lane, Tarvin",
    "sg:city":"Chester",
    "sg:classifiers":[
        {
            "category":"Home & Garden",
            "subcategory":"Carpets & Floor Coverings",
            "type":"Retail Goods"
        }
    ],
    "sg:postcode":"CH3 8LD",
    "sg:province":"Cheshire",
    "sg:tags":[
        "cleaner",
        "upholstery"
    ],
    "wof:name":"Mr Kleen",
    "wof:placetype":"venue"
},
  "geometry": {"coordinates":[-2.7696809769,53.1914863586],"type":"Point"}
}