{
  "type": "Feature",
  "properties": {
    "addr:full":"Castle Hill Axminster Devon EX13 5PY",
    "addr:postcode":"ex13 5py",
    "addr:street":"Castle Hill",
    "iso:country":"GB",
    "sg:address":"Castle Hill",
    "sg:city":"Axminster",
    "sg:classifiers":[
        {
            "category":"Shopping",
            "subcategory":"Clothing, Apparel, & Fashions",
            "type":"Retail Goods"
        }
    ],
    "sg:phone":"+44 1297 33408",
    "sg:postcode":"EX13 5PY",
    "sg:province":"Devon",
    "sg:tags":[
        "accessory"
    ],
    "wof:name":"Jaffe Feather Products",
    "wof:placetype":"venue"
},
  "geometry": {"coordinates":[-2.9994409084,50.7833786011],"type":"Point"}
}