{
  "type": "Feature",
  "properties": {
    "iso:country":"GB",
    "sg:address":"227 Sauchiehall Street",
    "sg:city":"Glasgow",
    "sg:classifiers":[
        {
            "category":"Recreation",
            "subcategory":"Gun Range",
            "type":"Entertainment"
        }
    ],
    "sg:phone":"+44 141 353 0699",
    "sg:postcode":"G2 3EX",
    "sg:province":"Glasgow City",
    "sg:tags":[
        "operator",
        "tour"
    ],
    "wof:name":"The Globespan Group Plc",
    "wof:placetype":"venue"
},
  "geometry": {"coordinates":[-4.2614450455,55.8650360107],"type":"Point"}
}