{
  "type": "Feature",
  "properties": {
    "addr:full":"77a Plaistow Lane Bromley Kent BR1 3JF",
    "addr:housenumber":"77a",
    "addr:postcode":"br1 3jf",
    "addr:street":"Plaistow Lane",
    "iso:country":"GB",
    "sg:address":"77a Plaistow Lane",
    "sg:city":"Bromley",
    "sg:classifiers":[
        {
            "category":"Arena",
            "subcategory":"Sports Club",
            "type":"Entertainment"
        }
    ],
    "sg:phone":"+44 20 8460 1368",
    "sg:postcode":"BR1 3JF",
    "sg:province":"Kent",
    "wof:name":"The Bromley Bowling Club Ltd.",
    "wof:placetype":"venue"
},
  "geometry": {"coordinates":[0.025373,51.412708],"type":"Point"}
}