{
  "type": "Feature",
  "properties": {
    "addr:full":"29 Flower Street, Castle Northwich Cheshire CW8 1BZ",
    "addr:housenumber":"29",
    "addr:postcode":"cw8 1bz",
    "addr:street":"Flower Street",
    "iso:country":"GB",
    "sg:address":"29 Flower Street, Castle",
    "sg:city":"Northwich",
    "sg:classifiers":[
        {
            "category":"Home & Garden",
            "subcategory":"Building Materials",
            "type":"Retail Goods"
        },
        {
            "category":"Building & Trades",
            "subcategory":"Construction",
            "type":"Services"
        }
    ],
    "sg:phone":"+44 1606 74780",
    "sg:postcode":"CW8 1BZ",
    "sg:province":"Cheshire",
    "sg:tags":[
        "dry",
        "plasterers",
        "installers",
        "lining",
        "insulation",
        "screeders"
    ],
    "wof:name":"K Birtles & Son",
    "wof:placetype":"venue"
},
  "geometry": {"coordinates":[-2.524654,53.254265],"type":"Point"}
}