{
  "type": "Feature",
  "properties": {
    "addr:full":"39 Cantley Lane Norwich Norfolk NR4 6TA",
    "addr:housenumber":"39",
    "addr:postcode":"nr4 6ta",
    "addr:street":"Cantley Lane",
    "iso:country":"GB",
    "sg:address":"39 Cantley Lane",
    "sg:city":"Norwich",
    "sg:classifiers":[
        {
            "category":"Home & Garden",
            "subcategory":"Home Furnishings",
            "type":"Retail Goods"
        },
        {
            "category":"Professional",
            "subcategory":"Art Services",
            "type":"Services"
        }
    ],
    "sg:phone":"+44 1603 507152",
    "sg:postcode":"NR4 6TA",
    "sg:province":"Norfolk",
    "sg:tags":[
        "furnishers",
        "model",
        "planner",
        "maker",
        "kitchen"
    ],
    "wof:name":"Paragon Designs",
    "wof:placetype":"venue"
},
  "geometry": {"coordinates":[1.23452,52.601967],"type":"Point"}
}