{
  "type": "Feature",
  "properties": {
    "iso:country":"GB",
    "sg:address":"Edgebold Farm, Sarnau",
    "sg:city":"Llanymynech",
    "sg:classifiers":[
        {
            "category":"Farming",
            "subcategory":"Dairy Farm",
            "type":"Manufacturing & Wholesale Goods"
        }
    ],
    "sg:phone":"+44 1938 590277",
    "sg:postcode":"SY22 6QJ",
    "sg:province":"Shropshire",
    "wof:name":"Thomas J R & Son",
    "wof:placetype":"venue"
},
  "geometry": {"coordinates":[-3.089354,52.780853],"type":"Point"}
}