{
  "type": "Feature",
  "properties": {
    "iso:country":"GB",
    "sg:address":"Suite 2h, Central Bldgs, 11 Peter St",
    "sg:city":"Manchester",
    "sg:classifiers":[
        {
            "category":"Social Services",
            "subcategory":"Job Training",
            "type":"Services"
        }
    ],
    "sg:phone":"+44 161 839 3813",
    "sg:postcode":"M2 5QR",
    "sg:province":"Greater Manchester",
    "sg:tags":[
        "translator",
        "interpreter"
    ],
    "wof:name":"Eiger Translations Ltd",
    "wof:placetype":"venue"
},
  "geometry": {"coordinates":[-2.2487499714,53.4782485962],"type":"Point"}
}