{
  "type": "Feature",
  "properties": {
    "iso:country":"GB",
    "sg:address":"Bridge Farm, Edstaston, Wem",
    "sg:city":"Shrewsbury",
    "sg:classifiers":[
        {
            "category":"Farming",
            "subcategory":"Dairy Farm",
            "type":"Manufacturing & Wholesale Goods"
        }
    ],
    "sg:postcode":"SY4 5RG",
    "sg:province":"Shropshire",
    "wof:name":"R J T Sadler",
    "wof:placetype":"venue"
},
  "geometry": {"coordinates":[-2.71177,52.886299],"type":"Point"}
}