{
  "type": "Feature",
  "properties": {
    "addr:full":"Station Road, Barrow Hill Chesterfield Derbyshire S43 2PG",
    "addr:postcode":"s43 2pg",
    "addr:street":"Station Road",
    "iso:country":"GB",
    "sg:address":"Station Road, Barrow Hill",
    "sg:city":"Chesterfield",
    "sg:classifiers":[
        {
            "category":"Health Services",
            "subcategory":"Doctor",
            "type":"Services"
        }
    ],
    "sg:phone":"+44 1246 280185",
    "sg:postcode":"S43 2PG",
    "sg:province":"Derbyshire",
    "sg:tags":[
        "practitioners"
    ],
    "wof:name":"Barrow Hill Surgery",
    "wof:placetype":"venue"
},
  "geometry": {"coordinates":[-1.370964,53.276363],"type":"Point"}
}