{
  "type": "Feature",
  "properties": {
    "addr:full":"Main Street, Watford Northampton Northamptonshire NN6 7UY",
    "addr:postcode":"nn6 7uy",
    "addr:street":"Main Street",
    "iso:country":"GB",
    "sg:address":"Main Street, Watford",
    "sg:city":"Northampton",
    "sg:classifiers":[
        {
            "category":"Government",
            "subcategory":"Post Office",
            "type":"Public Place"
        }
    ],
    "sg:phone":"+44 1327 842241",
    "sg:postcode":"NN6 7UY",
    "sg:province":"Northamptonshire",
    "wof:name":"Watford Post Office",
    "wof:placetype":"venue"
},
  "geometry": {"coordinates":[-1.1136440039,52.3143043518],"type":"Point"}
}