{
  "type": "Feature",
  "properties": {
    "addr:full":"Unit 7 Cannon Park Road Middlesbrough North Yorkshire TS1 5JP",
    "addr:housenumber":"unit 7",
    "addr:postcode":"ts1 5jp",
    "addr:street":"Cannon Park Road",
    "iso:country":"GB",
    "sg:address":"Unit 7 Cannon Park Road",
    "sg:city":"Middlesbrough",
    "sg:classifiers":[
        {
            "category":"Building & Trades",
            "subcategory":"Equipment Rental",
            "type":"Services"
        }
    ],
    "sg:phone":"+44 1642 230101",
    "sg:postcode":"TS1 5JP",
    "sg:province":"North Yorkshire",
    "sg:tags":[
        "hire",
        "centre"
    ],
    "wof:name":"Lord Hire Centres",
    "wof:placetype":"venue"
},
  "geometry": {"coordinates":[-1.247794,54.574894],"type":"Point"}
}