{
  "type": "Feature",
  "properties": {
    "iso:country":"GB",
    "sg:address":"39-41 The Green",
    "sg:city":"Sunderland",
    "sg:classifiers":[
        {
            "category":"Food & Beverages",
            "subcategory":"Supermarket",
            "type":"Retail Goods"
        }
    ],
    "sg:phone":"+44 191 549 2666",
    "sg:postcode":"SR5 2HJ",
    "sg:province":"Tyne and Wear",
    "wof:name":"Food Giant",
    "wof:placetype":"venue"
},
  "geometry": {"coordinates":[-1.402997,54.919624],"type":"Point"}
}