{
  "type": "Feature",
  "properties": {
    "addr:full":"50 Brangwyn Gro, Lockleaze Bristol City of Bristol BS7 9UB",
    "addr:housenumber":"50",
    "addr:postcode":"bs7 9ub",
    "addr:street":"Brangwyn Gro",
    "iso:country":"GB",
    "sg:address":"50 Brangwyn Gro, Lockleaze",
    "sg:city":"Bristol",
    "sg:classifiers":[
        {
            "category":"Professional",
            "subcategory":"Accounting & Tax Preparation",
            "type":"Services"
        }
    ],
    "sg:postcode":"BS7 9UB",
    "sg:province":"City of Bristol",
    "sg:tags":[
        "accountant"
    ],
    "wof:name":"R Roseway Accounting Services",
    "wof:placetype":"venue"
},
  "geometry": {"coordinates":[-2.5672559738,51.4870147705],"type":"Point"}
}