{
  "type": "Feature",
  "properties": {
    "addr:full":"Bowmead Residential Care, 75 Hollway Road Bristol City of Bristol BS14 8PG",
    "addr:housenumber":"75",
    "addr:postcode":"bs14 8pg",
    "addr:street":"Hollway Road",
    "iso:country":"GB",
    "sg:address":"Bowmead Residential Care, 75 Hollway Road",
    "sg:city":"Bristol",
    "sg:classifiers":[
        {
            "category":"Government",
            "subcategory":"Office",
            "type":"Public Place"
        }
    ],
    "sg:phone":"+44 1275 833998",
    "sg:postcode":"BS14 8PG",
    "sg:province":"City of Bristol",
    "sg:tags":[
        "local"
    ],
    "wof:name":"Bristol City Council",
    "wof:placetype":"venue"
},
  "geometry": {"coordinates":[-2.5914289951,51.453666687],"type":"Point"}
}