{
  "type": "Feature",
  "properties": {
    "addr:full":"124 Queens Road Brighton East Sussex BN1 3WB",
    "addr:housenumber":"124",
    "addr:postcode":"bn1 3wb",
    "addr:street":"Queens Road",
    "iso:country":"GB",
    "sg:address":"124 Queens Road",
    "sg:city":"Brighton",
    "sg:classifiers":[
        {
            "category":"Shopping",
            "subcategory":"Books",
            "type":"Retail Goods"
        }
    ],
    "sg:phone":"+44 1273 323105",
    "sg:postcode":"BN1 3WB",
    "sg:province":"East Sussex",
    "sg:tags":[
        "second-hand"
    ],
    "wof:name":"Ivyclad Ltd.",
    "wof:placetype":"venue"
},
  "geometry": {"coordinates":[-0.1427939981,50.8246459961],"type":"Point"}
}