{
  "type": "Feature",
  "properties": {
    "addr:full":"21 Lucks Way Tonbridge Kent TN12 9QW",
    "addr:housenumber":"21",
    "addr:postcode":"tn12 9qw",
    "addr:street":"Lucks Way",
    "iso:country":"GB",
    "sg:address":"21 Lucks Way",
    "sg:city":"Tonbridge",
    "sg:classifiers":[
        {
            "category":"Building & Trades",
            "subcategory":"Construction",
            "type":"Services"
        }
    ],
    "sg:phone":"+44 1622 831413",
    "sg:postcode":"TN12 9QW",
    "sg:province":"Kent",
    "sg:tags":[
        "contractor",
        "paving",
        "driveway"
    ],
    "wof:name":"Regency Driveways",
    "wof:placetype":"venue"
},
  "geometry": {"coordinates":[0.4874480069,51.1745223999],"type":"Point"}
}