{
  "type": "Feature",
  "properties": {
    "iso:country":"GB",
    "sg:address":"Unit 1 + 2, Orchard Trading Estate",
    "sg:city":"Cheltenham",
    "sg:classifiers":[
        {
            "category":"Travel",
            "subcategory":"Hotels & Motels",
            "type":"Entertainment"
        }
    ],
    "sg:postcode":"GL54 5EP",
    "sg:province":"Gloucestershire",
    "wof:name":"Advanced Fluid Stripping Ltd.",
    "wof:placetype":"venue"
},
  "geometry": {"coordinates":[-1.970714,51.956203],"type":"Point"}
}