{
  "type": "Feature",
  "properties": {
    "addr:full":"Belsize Close Cannock Staffordshire WS11 3TQ",
    "addr:postcode":"ws11 3tq",
    "addr:street":"Belsize Close",
    "iso:country":"GB",
    "sg:address":"Belsize Close",
    "sg:city":"Cannock",
    "sg:classifiers":[
        {
            "category":"Retail",
            "subcategory":"Storage",
            "type":"Services"
        }
    ],
    "sg:phone":"+44 1543 274565",
    "sg:postcode":"WS11 3TQ",
    "sg:province":"Staffordshire",
    "sg:tags":[
        "cold"
    ],
    "wof:name":"Novacold",
    "wof:placetype":"venue"
},
  "geometry": {"coordinates":[-1.972714,52.670429],"type":"Point"}
}