{
  "type": "Feature",
  "properties": {
    "addr:full":"Bakers Farm Park Homes, Upper Horsebridge Hailsham East Sussex BN27 3BE",
    "addr:postcode":"bn27 3be",
    "addr:street":"Park Homes Upper Horsebridge Hailsham",
    "iso:country":"GB",
    "sg:address":"Bakers Farm Park Homes, Upper Horsebridge",
    "sg:city":"Hailsham",
    "sg:classifiers":[
        {
            "category":"Manufacturing",
            "subcategory":"Buildings",
            "type":"Manufacturing & Wholesale Goods"
        }
    ],
    "sg:phone":"+44 1323 844495",
    "sg:postcode":"BN27 3BE",
    "sg:province":"East Sussex",
    "sg:tags":[
        "mobile",
        "home"
    ],
    "wof:name":"Bakersfarm Park Homes",
    "wof:placetype":"venue"
},
  "geometry": {"coordinates":[0.25652,50.865383],"type":"Point"}
}