{
  "type": "Feature",
  "properties": {
    "addr:full":"Main Street, Hilton Derby Derbyshire DE65 5GG",
    "addr:postcode":"de65 5gg",
    "addr:street":"Main Street",
    "iso:country":"GB",
    "sg:address":"Main Street, Hilton",
    "sg:city":"Derby",
    "sg:classifiers":[
        {
            "category":"Retail",
            "subcategory":"Auto Repair",
            "type":"Services"
        }
    ],
    "sg:phone":"+44 1283 732527",
    "sg:postcode":"DE65 5GG",
    "sg:province":"Derbyshire",
    "sg:tags":[
        "modification",
        "garage"
    ],
    "wof:name":"Hilton Garage",
    "wof:placetype":"venue"
},
  "geometry": {"coordinates":[-1.640199,52.872623],"type":"Point"}
}