{
  "type": "Feature",
  "properties": {
    "iso:country":"GB",
    "sg:address":"Rose Villa Court, Potton Road",
    "sg:city":"Biggleswade",
    "sg:classifiers":[
        {
            "category":"Food & Beverages",
            "subcategory":"Liquor & Beverages",
            "type":"Retail Goods"
        }
    ],
    "sg:postcode":"SG18 0EP",
    "sg:province":"Bedfordshire",
    "sg:tags":[
        "beer",
        "spirit",
        "wines"
    ],
    "wof:name":"Continental Wines Ltd.",
    "wof:placetype":"venue"
},
  "geometry": {"coordinates":[-0.251599,52.095551],"type":"Point"}
}