{
  "type": "Feature",
  "properties": {
    "addr:full":"79 Bush Street Pembroke Dock Pembrokeshire SA72 6DH",
    "addr:housenumber":"79",
    "addr:postcode":"sa72 6dh",
    "addr:street":"Bush Street",
    "iso:country":"GB",
    "sg:address":"79 Bush Street",
    "sg:city":"Pembroke Dock",
    "sg:classifiers":[
        {
            "category":"Building & Trades",
            "subcategory":"Construction",
            "type":"Services"
        }
    ],
    "sg:phone":"+44 1646 685468",
    "sg:postcode":"SA72 6DH",
    "sg:province":"Pembrokeshire",
    "sg:tags":[
        "joinery",
        "joiner",
        "carpenter",
        "carpentry"
    ],
    "wof:name":"Derek J Hillier",
    "wof:placetype":"venue"
},
  "geometry": {"coordinates":[-4.9399318695,51.6917495728],"type":"Point"}
}