{
  "type": "Feature",
  "properties": {
    "iso:country":"GB",
    "sg:address":"1c Portland Place, Regent Street",
    "sg:city":"London",
    "sg:classifiers":[
        {
            "category":"Travel",
            "subcategory":"Hotels & Motels",
            "type":"Entertainment"
        }
    ],
    "sg:phone":"+44 20 7636 1000",
    "sg:postcode":"W1B 1JA",
    "sg:province":"Greater London",
    "wof:name":"Great Eagle Hotels (U K) Ltd.",
    "wof:placetype":"venue"
},
  "geometry": {"coordinates":[-0.144385,51.518364],"type":"Point"}
}