{
  "type": "Feature",
  "properties": {
    "addr:full":"5 Bristol Road, Keynsham Bristol City of Bristol BS31 2BA",
    "addr:housenumber":"5",
    "addr:postcode":"bs31 2ba",
    "addr:street":"Bristol Road",
    "iso:country":"GB",
    "sg:address":"5 Bristol Road, Keynsham",
    "sg:city":"Bristol",
    "sg:classifiers":[
        {
            "category":"Travel",
            "subcategory":"Hotels & Motels",
            "type":"Entertainment"
        },
        {
            "category":"Restaurant",
            "type":"Food & Drink"
        }
    ],
    "sg:phone":"+44 117 986 3107",
    "sg:postcode":"BS31 2BA",
    "sg:province":"City of Bristol",
    "wof:name":"Old Manor House Hotel",
    "wof:placetype":"venue"
},
  "geometry": {"coordinates":[-2.5013289452,51.4178886414],"type":"Point"}
}