{
  "type": "Feature",
  "properties": {
    "addr:full":"18 Guilford St, Brierfield Nelson Lancashire BB9 5LH",
    "addr:housenumber":"18",
    "addr:postcode":"bb9 5lh",
    "addr:street":"Guilford St",
    "iso:country":"GB",
    "sg:address":"18 Guilford St, Brierfield",
    "sg:city":"Nelson",
    "sg:classifiers":[
        {
            "category":"Shopping",
            "subcategory":"Comic Books",
            "type":"Retail Goods"
        }
    ],
    "sg:phone":"+44 1282 696762",
    "sg:postcode":"BB9 5LH",
    "sg:province":"Lancashire",
    "sg:tags":[
        "jeweller"
    ],
    "wof:name":"Momena Jeweller",
    "wof:placetype":"venue"
},
  "geometry": {"coordinates":[-2.23562,53.822247],"type":"Point"}
}