{
  "type": "Feature",
  "properties": {
    "iso:country":"GB",
    "sg:address":"20 Manor Way, Belasis Hall Technology Pk",
    "sg:city":"Billingham",
    "sg:classifiers":[
        {
            "category":"Government",
            "subcategory":"Office",
            "type":"Public Place"
        }
    ],
    "sg:phone":"+44 1642 330100",
    "sg:postcode":"TS23 4HN",
    "sg:province":"Durham",
    "sg:tags":[
        "development",
        "agency"
    ],
    "wof:name":"Northern Development Co",
    "wof:placetype":"venue"
},
  "geometry": {"coordinates":[-1.2630800009,54.6004829407],"type":"Point"}
}