{
  "type": "Feature",
  "properties": {
    "addr:full":"Unit 1b Romford Rd, Aston Fields Indstl Est Stafford Staffordshire ST16 3DZ",
    "addr:housenumber":"unit 1b",
    "addr:postcode":"st16 3dz",
    "addr:street":"Romford Rd Aston Fields Indstl Est",
    "iso:country":"GB",
    "sg:address":"Unit 1b Romford Rd, Aston Fields Indstl Est",
    "sg:city":"Stafford",
    "sg:classifiers":[
        {
            "category":"Retail",
            "subcategory":"Repair Shop",
            "type":"Services"
        }
    ],
    "sg:postcode":"ST16 3DZ",
    "sg:province":"Staffordshire",
    "sg:tags":[
        "sharpening",
        "tool"
    ],
    "wof:name":"Midland Saw Service",
    "wof:placetype":"venue"
},
  "geometry": {"coordinates":[-2.1145870686,52.8201713562],"type":"Point"}
}