{
  "type": "Feature",
  "properties": {
    "addr:full":"Bayhead Farm Munlochy Highland IV8 8NP",
    "addr:postcode":"iv8 8np",
    "addr:street":"Munlochy",
    "iso:country":"GB",
    "sg:address":"Bayhead Farm",
    "sg:city":"Munlochy",
    "sg:classifiers":[
        {
            "category":"Home & Garden",
            "subcategory":"Garden Supply",
            "type":"Retail Goods"
        }
    ],
    "sg:phone":"+44 1463 811288",
    "sg:postcode":"IV8 8NP",
    "sg:province":"Highland",
    "sg:tags":[
        "bulb",
        "grower"
    ],
    "wof:name":"P D Dalgetty",
    "wof:placetype":"venue"
},
  "geometry": {"coordinates":[-4.2610611916,57.5495796204],"type":"Point"}
}