{
  "type": "Feature",
  "properties": {
    "addr:full":"Gillibrands Farm, Turner Street, Westhoughton Bolton Lancashire BL5 2DZ",
    "addr:postcode":"bl5 2dz",
    "addr:street":"Turner Street",
    "iso:country":"GB",
    "sg:address":"Gillibrands Farm, Turner Street, Westhoughton",
    "sg:city":"Bolton",
    "sg:classifiers":[
        {
            "category":"Farming",
            "subcategory":"Farm",
            "type":"Manufacturing & Wholesale Goods"
        }
    ],
    "sg:phone":"+44 1942 813922",
    "sg:postcode":"BL5 2DZ",
    "sg:province":"Lancashire",
    "sg:tags":[
        "mixed",
        "crop"
    ],
    "wof:name":"J & K Heyes",
    "wof:placetype":"venue"
},
  "geometry": {"coordinates":[-2.5255300999,53.5322990417],"type":"Point"}
}