{
  "type": "Feature",
  "properties": {
    "addr:full":"9 High Street, Broughton Brigg Lincolnshire DN20 0JA",
    "addr:housenumber":"9",
    "addr:postcode":"dn20 0ja",
    "addr:street":"High Street;Brigg",
    "iso:country":"GB",
    "sg:address":"9 High Street, Broughton",
    "sg:city":"Brigg",
    "sg:classifiers":[
        {
            "category":"Bars & Pubs",
            "type":"Food & Drink"
        }
    ],
    "sg:phone":"+44 1652 655565",
    "sg:postcode":"DN20 0JA",
    "sg:province":"Lincolnshire",
    "sg:tags":[
        "pubs",
        "inn"
    ],
    "wof:name":"The Thatch Inn",
    "wof:placetype":"venue"
},
  "geometry": {"coordinates":[-0.5446959734,53.5677223206],"type":"Point"}
}