{
  "type": "Feature",
  "properties": {
    "iso:country":"GB",
    "sg:address":"350 Holderness Road",
    "sg:city":"Hull",
    "sg:classifiers":[
        {
            "category":"Travel",
            "subcategory":"Travel Agent",
            "type":"Entertainment"
        }
    ],
    "sg:phone":"+44 1482 226338",
    "sg:postcode":"HU9 3DQ",
    "sg:province":"East Riding of Yorkshire",
    "wof:name":"Pandora Travel",
    "wof:placetype":"venue"
},
  "geometry": {"coordinates":[-0.308059,53.757332],"type":"Point"}
}