{
  "type": "Feature",
  "properties": {
    "addr:full":"Mauldeth House, Mauldeth Road West Manchester Cheshire M21 7RX",
    "addr:postcode":"m21 7rx",
    "addr:street":"Mauldeth Road West",
    "iso:country":"GB",
    "sg:address":"Mauldeth House, Mauldeth Road West",
    "sg:city":"Manchester",
    "sg:classifiers":[
        {
            "category":"Communications",
            "type":"Services"
        }
    ],
    "sg:phone":"+44 161 374 5566",
    "sg:postcode":"M21 7RX",
    "sg:province":"Cheshire",
    "sg:tags":[
        "broadcasting"
    ],
    "wof:name":"Multi-Media Arts (M M A) Ltd.",
    "wof:placetype":"venue"
},
  "geometry": {"coordinates":[-2.246599,53.439842],"type":"Point"}
}