{
  "type": "Feature",
  "properties": {
    "iso:country":"GB",
    "sg:address":"Brook Clo",
    "sg:city":"Saltash",
    "sg:classifiers":[
        {
            "category":"Community Center",
            "subcategory":"Youth",
            "type":"Public Place"
        }
    ],
    "sg:phone":"+44 1752 843570",
    "sg:postcode":"PL12 4EN",
    "sg:province":"Cornwall",
    "sg:tags":[
        "organisation",
        "centre"
    ],
    "wof:name":"Saltash Boys Club",
    "wof:placetype":"venue"
},
  "geometry": {"coordinates":[-4.207056,50.407028],"type":"Point"}
}