{
  "type": "Feature",
  "properties": {
    "addr:full":"1 Venture Park, Stirling Way, Bretton Peterborough Cambridgeshire PE3 8YD",
    "addr:housenumber":"1",
    "addr:postcode":"pe3 8yd",
    "addr:street":"Venture Park Stirling Way",
    "iso:country":"GB",
    "sg:address":"1 Venture Park, Stirling Way, Bretton",
    "sg:city":"Peterborough",
    "sg:classifiers":[
        {
            "category":"Wholesale",
            "subcategory":"Medical Equipment & Supplies",
            "type":"Manufacturing & Wholesale Goods"
        }
    ],
    "sg:phone":"+44 1733 333100",
    "sg:postcode":"PE3 8YD",
    "sg:province":"Cambridgeshire",
    "sg:tags":[
        "hospital"
    ],
    "wof:name":"Surgipath Europe Ltd.",
    "wof:placetype":"venue"
},
  "geometry": {"coordinates":[-0.288839,52.6008],"type":"Point"}
}