{
  "type": "Feature",
  "properties": {
    "addr:full":"216c Siemens Road London Greater London SE18 5TT",
    "addr:housenumber":"216c",
    "addr:postcode":"se18 5tt",
    "addr:street":"Siemens Road",
    "iso:country":"GB",
    "sg:address":"216c Siemens Road",
    "sg:city":"London",
    "sg:classifiers":[
        {
            "category":"Communications",
            "subcategory":"Film & Video Production",
            "type":"Services"
        },
        {
            "category":"Conference Center",
            "type":"Public Place"
        }
    ],
    "sg:postcode":"SE18 5TT",
    "sg:province":"Greater London",
    "sg:tags":[
        "tv",
        "studio"
    ],
    "wof:name":"Set Two",
    "wof:placetype":"venue"
},
  "geometry": {"coordinates":[0.04206,51.493179],"type":"Point"}
}