{
  "type": "Feature",
  "properties": {
    "addr:full":"Sibleys Green, Sibleys Lane, Thaxted Dunmow Essex CM6 2NU",
    "addr:postcode":"cm6 2nu",
    "addr:street":"Sibleys Green Sibleys Lane",
    "iso:country":"GB",
    "sg:address":"Sibleys Green, Sibleys Lane, Thaxted",
    "sg:city":"Dunmow",
    "sg:classifiers":[
        {
            "category":"Manufacturing",
            "subcategory":"Tobacco Products",
            "type":"Manufacturing & Wholesale Goods"
        },
        {
            "category":"Shopping",
            "subcategory":"Computers & Home Electronics",
            "type":"Retail Goods"
        },
        {
            "category":"Organizations",
            "subcategory":"Membership Organization",
            "type":"Services"
        }
    ],
    "sg:phone":"+44 1371 830326",
    "sg:postcode":"CM6 2NU",
    "sg:province":"Essex",
    "sg:tags":[
        "manufacture",
        "mnfr",
        "intercom",
        "component",
        "system",
        "distribution",
        "electronic"
    ],
    "wof:name":"Complus Teltronic Ltd",
    "wof:placetype":"venue"
},
  "geometry": {"coordinates":[0.3447650075,51.953163147],"type":"Point"}
}