{
  "type": "Feature",
  "properties": {
    "iso:country":"GB",
    "sg:address":"Turney Street, Ovenden",
    "sg:city":"Halifax",
    "sg:classifiers":[
        {
            "category":"Professional",
            "subcategory":"Engineering",
            "type":"Services"
        }
    ],
    "sg:phone":"+44 1422 330263",
    "sg:postcode":"HX3 5PP",
    "sg:province":"West Yorkshire",
    "wof:name":"Greening & Crowther Engineering Co. Ltd.",
    "wof:placetype":"venue"
},
  "geometry": {"coordinates":[-1.875485,53.739098],"type":"Point"}
}