{
  "type": "Feature",
  "properties": {
    "iso:country":"GB",
    "sg:address":"11 Cedar Drive, Parklands",
    "sg:city":"Chichester",
    "sg:classifiers":[
        {
            "category":"Building & Trades",
            "subcategory":"Construction",
            "type":"Services"
        }
    ],
    "sg:postcode":"PO19 3EH",
    "sg:province":"West Sussex",
    "sg:tags":[
        "builder"
    ],
    "wof:name":"A K Bryars",
    "wof:placetype":"venue"
},
  "geometry": {"coordinates":[-0.7861419916,50.8424530029],"type":"Point"}
}