{
  "type": "Feature",
  "properties": {
    "addr:full":"20 Berkeley Square London Greater London W1J 6LJ",
    "addr:housenumber":"20",
    "addr:postcode":"w1j 6lj",
    "addr:street":"Berkeley Square",
    "iso:country":"GB",
    "sg:address":"20 Berkeley Square",
    "sg:city":"London",
    "sg:classifiers":[
        {
            "category":"Real Estate",
            "subcategory":"Surveying",
            "type":"Services"
        }
    ],
    "sg:phone":"+44 20 7499 3162",
    "sg:postcode":"W1J 6LJ",
    "sg:province":"Greater London",
    "sg:tags":[
        "surveyor",
        "valuer"
    ],
    "wof:name":"Oliver Liggins Ltd.",
    "wof:placetype":"venue"
},
  "geometry": {"coordinates":[-0.1445569992,51.5089912415],"type":"Point"}
}