{
  "type": "Feature",
  "properties": {
    "iso:country":"GB",
    "sg:address":"103 Broad Street",
    "sg:city":"Denny",
    "sg:classifiers":[
        {
            "category":"Professional",
            "subcategory":"Engineering",
            "type":"Services"
        }
    ],
    "sg:phone":"+44 1324 824309",
    "sg:postcode":"FK6 6DX",
    "sg:province":"Falkirk",
    "sg:tags":[
        "engineer"
    ],
    "wof:name":"Machan Engineering Ltd.",
    "wof:placetype":"venue"
},
  "geometry": {"coordinates":[-3.905322,56.022915],"type":"Point"}
}