{
  "type": "Feature",
  "properties": {
    "addr:full":"9 West St Sheffield South Yorkshire S20 1EN",
    "addr:housenumber":"9",
    "addr:postcode":"s20 1en",
    "addr:street":"West St",
    "iso:country":"GB",
    "sg:address":"9 West St",
    "sg:city":"Sheffield",
    "sg:classifiers":[
        {
            "category":"Professional",
            "type":"Services"
        }
    ],
    "sg:phone":"+44 114 248 9360",
    "sg:postcode":"S20 1EN",
    "sg:province":"South Yorkshire",
    "sg:tags":[
        "repair",
        "tech",
        "maintenance"
    ],
    "wof:name":"Image Services",
    "wof:placetype":"venue"
},
  "geometry": {"coordinates":[-1.3388949633,53.3425598145],"type":"Point"}
}