{
  "type": "Feature",
  "properties": {
    "iso:country":"GB",
    "sg:address":"Unit 3 Station Road",
    "sg:city":"Bakewell",
    "sg:classifiers":[
        {
            "category":"Wholesale",
            "subcategory":"Machinery & Supplies",
            "type":"Manufacturing & Wholesale Goods"
        }
    ],
    "sg:postcode":"DE45 1GA",
    "sg:province":"Derbyshire",
    "sg:tags":[
        "industrial",
        "commercial"
    ],
    "wof:name":"East Midlands Equipment Co. Ltd.",
    "wof:placetype":"venue"
},
  "geometry": {"coordinates":[-1.6678980589,53.2170829773],"type":"Point"}
}