{
  "type": "Feature",
  "properties": {
    "iso:country":"GB",
    "sg:address":"Station Road",
    "sg:city":"Cardigan",
    "sg:classifiers":[
        {
            "category":"Wholesale",
            "subcategory":"Machinery & Supplies",
            "type":"Manufacturing & Wholesale Goods"
        }
    ],
    "sg:postcode":"SA43 3AD",
    "sg:province":"Ceredigion",
    "wof:name":"Corbett Williams & Son Ltd.",
    "wof:placetype":"venue"
},
  "geometry": {"coordinates":[-4.658431,52.080132],"type":"Point"}
}