{
  "type": "Feature",
  "properties": {
    "addr:full":"Unit 10 Wisbech Cambridgeshire PE13 3PQ",
    "addr:housenumber":"unit 10",
    "addr:postcode":"pe13 3pq",
    "iso:country":"GB",
    "sg:address":"Unit 10",
    "sg:city":"Wisbech",
    "sg:classifiers":[
        {
            "category":"Retail",
            "subcategory":"Auto Repair",
            "type":"Services"
        }
    ],
    "sg:phone":"+44 1945 474282",
    "sg:postcode":"PE13 3PQ",
    "sg:province":"Cambridgeshire",
    "sg:tags":[
        "modification",
        "garage"
    ],
    "wof:name":"Plough House Transmission",
    "wof:placetype":"venue"
},
  "geometry": {"coordinates":[0.187232,52.670956],"type":"Point"}
}