{
  "type": "Feature",
  "properties": {
    "addr:full":"28 Ely Place London Greater London EC1N 6RL",
    "addr:housenumber":"28",
    "addr:postcode":"ec1n 6rl",
    "addr:street":"Ely Place",
    "iso:country":"GB",
    "sg:address":"28 Ely Place",
    "sg:city":"London",
    "sg:classifiers":[
        {
            "category":"Organizations",
            "subcategory":"Membership Organization",
            "type":"Services"
        }
    ],
    "sg:postcode":"EC1N 6RL",
    "sg:province":"Greater London",
    "sg:tags":[
        "club"
    ],
    "wof:name":"Longshot Bridge Ltd",
    "wof:placetype":"venue"
},
  "geometry": {"coordinates":[-0.107009,51.5187],"type":"Point"}
}