{
  "type": "Feature",
  "properties": {
    "iso:country":"GB",
    "sg:address":"First Floor, 22 Church Street",
    "sg:city":"Peterborough",
    "sg:classifiers":[
        {
            "category":"Professional",
            "subcategory":"Employment Agencies",
            "type":"Services"
        }
    ],
    "sg:phone":"+44 1733 310855",
    "sg:postcode":"PE1 1XF",
    "sg:province":"Cambridgeshire",
    "sg:tags":[
        "consultant"
    ],
    "wof:name":"Brook Street",
    "wof:placetype":"venue"
},
  "geometry": {"coordinates":[-0.2445210069,52.5726470947],"type":"Point"}
}