{
  "type": "Feature",
  "properties": {
    "addr:full":"322 Hook Rise North Surbiton Surrey KT6 7LN",
    "addr:housenumber":"322",
    "addr:postcode":"kt6 7ln",
    "addr:street":"Hook Rise North",
    "iso:country":"GB",
    "sg:address":"322 Hook Rise North",
    "sg:city":"Surbiton",
    "sg:classifiers":[
        {
            "category":"Autos & Motor Vehicles",
            "subcategory":"Automobile Sales",
            "type":"Retail Goods"
        },
        {
            "category":"Retail",
            "subcategory":"Auto Repair",
            "type":"Services"
        }
    ],
    "sg:phone":"+44 20 8391 1004",
    "sg:postcode":"KT6 7LN",
    "sg:province":"Surrey",
    "sg:tags":[
        "truck",
        "electrician",
        "car"
    ],
    "wof:name":"Jay Electrics",
    "wof:placetype":"venue"
},
  "geometry": {"coordinates":[-0.297742,51.374237],"type":"Point"}
}