{
  "type": "Feature",
  "properties": {
    "addr:full":"Gyle Centre, South Gyle Bdwy Edinburgh City of Edinburgh EH12 9JT",
    "addr:postcode":"eh12 9jt",
    "addr:street":"Centre;Bdwy",
    "iso:country":"GB",
    "sg:address":"Gyle Centre, South Gyle Bdwy",
    "sg:city":"Edinburgh",
    "sg:classifiers":[
        {
            "category":"Sports & Exercise",
            "subcategory":"Sports Center",
            "type":"Entertainment"
        }
    ],
    "sg:phone":"+44 131 538 8222",
    "sg:postcode":"EH12 9JT",
    "sg:province":"City of Edinburgh",
    "sg:tags":[
        "shop",
        "good"
    ],
    "wof:name":"J J B Sports Plc",
    "wof:placetype":"venue"
},
  "geometry": {"coordinates":[-3.3001840115,55.9358253479],"type":"Point"}
}