{
  "type": "Feature",
  "properties": {
    "addr:full":"Studio 6treglisson Rural Wksps, Wheal Alfred Road Hayle Cornwall TR27 5JT",
    "addr:postcode":"tr27 5jt",
    "addr:street":"Wheal Alfred Road",
    "iso:country":"GB",
    "sg:address":"Studio 6treglisson Rural Wksps, Wheal Alfred Road",
    "sg:city":"Hayle",
    "sg:classifiers":[
        {
            "category":"Professional",
            "subcategory":"Art Services",
            "type":"Services"
        }
    ],
    "sg:postcode":"TR27 5JT",
    "sg:province":"Cornwall",
    "sg:tags":[
        "photographer"
    ],
    "wof:name":"J S Ailes",
    "wof:placetype":"venue"
},
  "geometry": {"coordinates":[-5.4076089859,50.192035675],"type":"Point"}
}