{
  "type": "Feature",
  "properties": {
    "iso:country":"GB",
    "sg:address":"Tamar Medical Centre, Severn Drive",
    "sg:city":"Wolverhampton",
    "sg:classifiers":[
        {
            "category":"Health Services",
            "subcategory":"Doctor",
            "type":"Services"
        }
    ],
    "sg:phone":"+44 1902 755053",
    "sg:postcode":"WV6 7QL",
    "sg:province":"Shropshire",
    "sg:tags":[
        "practitioners"
    ],
    "wof:name":"H S Dhingra",
    "wof:placetype":"venue"
},
  "geometry": {"coordinates":[-2.20508,52.59317],"type":"Point"}
}