{
  "type": "Feature",
  "properties": {
    "addr:full":"25 Mallard Drive, Cippenham Slough Berkshire SL1 5BW",
    "addr:housenumber":"25",
    "addr:postcode":"sl1 5bw",
    "addr:street":"Mallard Drive",
    "iso:country":"GB",
    "sg:address":"25 Mallard Drive, Cippenham",
    "sg:city":"Slough",
    "sg:classifiers":[
        {
            "category":"Building & Trades",
            "subcategory":"Landscaping Services",
            "type":"Services"
        }
    ],
    "sg:phone":"+44 1753 527358",
    "sg:postcode":"SL1 5BW",
    "sg:province":"Berkshire",
    "sg:tags":[
        "forestry",
        "surgeon",
        "tree"
    ],
    "wof:name":"iGreenwood Tree Surgeons",
    "wof:placetype":"venue"
},
  "geometry": {"coordinates":[-0.6357939839,51.5175247192],"type":"Point"}
}