{
  "type": "Feature",
  "properties": {
    "addr:full":"Unit 42, Battersea Business Centre, 103-109 Lavender Hill London Greater London SW11 5QL",
    "addr:housenumber":"unit 42;103-109",
    "addr:postcode":"sw11 5ql",
    "addr:street":"Battersea Business Centre;Hill",
    "iso:country":"GB",
    "sg:address":"Unit 42, Battersea Business Centre, 103-109 Lavender Hill",
    "sg:city":"London",
    "sg:classifiers":[
        {
            "category":"Manufacturing",
            "subcategory":"Apparel",
            "type":"Manufacturing & Wholesale Goods"
        }
    ],
    "sg:postcode":"SW11 5QL",
    "sg:province":"Greater London",
    "sg:tags":[
        "garment",
        "designer"
    ],
    "wof:name":"Gail P Hoppen",
    "wof:placetype":"venue"
},
  "geometry": {"coordinates":[-0.1559469998,51.4654045105],"type":"Point"}
}