{
  "type": "Feature",
  "properties": {
    "iso:country":"GB",
    "sg:address":"Orchard Lane, Off Stafford Road",
    "sg:city":"Newport",
    "sg:classifiers":[
        {
            "category":"Community Center",
            "type":"Public Place"
        }
    ],
    "sg:phone":"+44 1633 265818",
    "sg:postcode":"NP19 7DW",
    "sg:province":"Newport",
    "sg:tags":[
        "centre"
    ],
    "wof:name":"ST JULIANS SENIOR CITIZENS CLUB",
    "wof:placetype":"venue"
},
  "geometry": {"coordinates":[-2.9817318916,51.6000671387],"type":"Point"}
}