{
  "type": "Feature",
  "properties": {
    "addr:full":"29-31 Sea Road Bexhill-on-sea East Sussex TN40 1EE",
    "addr:housenumber":"29-31",
    "addr:postcode":"tn40 1ee",
    "addr:street":"Sea Road",
    "iso:country":"GB",
    "sg:address":"29-31 Sea Road",
    "sg:city":"Bexhill-on-sea",
    "sg:classifiers":[
        {
            "category":"Shopping",
            "subcategory":"Antiques",
            "type":"Retail Goods"
        }
    ],
    "sg:phone":"+44 1424 731224",
    "sg:postcode":"TN40 1EE",
    "sg:province":"East Sussex",
    "wof:name":"Bexhill Antique & Craft Centre",
    "wof:placetype":"venue"
},
  "geometry": {"coordinates":[0.4773080051,50.8399162292],"type":"Point"}
}