{
  "type": "Feature",
  "properties": {
    "iso:country":"GB",
    "sg:address":"41 Northfield Street",
    "sg:city":"Worcester",
    "sg:classifiers":[
        {
            "category":"Shopping",
            "subcategory":"News",
            "type":"Retail Goods"
        }
    ],
    "sg:phone":"+44 1905 25695",
    "sg:postcode":"WR1 1NS",
    "sg:province":"Worcestershire",
    "sg:tags":[
        "newsagent"
    ],
    "wof:name":"Virk's Newsagents",
    "wof:placetype":"venue"
},
  "geometry": {"coordinates":[-2.218031,52.198849],"type":"Point"}
}