{
  "type": "Feature",
  "properties": {
    "addr:full":"Eastgate House    40 Dukes Place London Greater London EC3A 7NH",
    "addr:housenumber":"40",
    "addr:postcode":"ec3a 7nh",
    "addr:street":"Eastgate;Dukes Place",
    "iso:country":"GB",
    "sg:address":"Eastgate House    40 Dukes Place",
    "sg:city":"London",
    "sg:classifiers":[
        {
            "category":"Professional",
            "subcategory":"Business Services",
            "type":"Services"
        }
    ],
    "sg:postcode":"EC3A 7NH",
    "sg:province":"Greater London",
    "sg:tags":[
        "holding"
    ],
    "wof:name":"Oast Holdings Ltd",
    "wof:placetype":"venue"
},
  "geometry": {"coordinates":[-0.077563,51.514313],"type":"Point"}
}