{
  "type": "Feature",
  "properties": {
    "iso:country":"GB",
    "sg:address":"3 Mountleigh Close, Euroway Industrial Estate",
    "sg:city":"Bradford",
    "sg:classifiers":[
        {
            "category":"Home & Garden",
            "subcategory":"Hardware",
            "type":"Retail Goods"
        }
    ],
    "sg:phone":"+44 1274 688327",
    "sg:postcode":"BD4 6SP",
    "sg:province":"West Yorkshire",
    "sg:tags":[
        "retailer",
        "diy"
    ],
    "wof:name":"B & Q Supercentre",
    "wof:placetype":"venue"
},
  "geometry": {"coordinates":[-1.7394340038,53.7571754456],"type":"Point"}
}