{
  "type": "Feature",
  "properties": {
    "iso:country":"GB",
    "sg:address":"Station House, Murton",
    "sg:city":"Seaham",
    "sg:classifiers":[
        {
            "category":"Government",
            "subcategory":"Post Office",
            "type":"Public Place"
        }
    ],
    "sg:phone":"+44 191 517 0148",
    "sg:postcode":"SR7 9SS",
    "sg:province":"Durham",
    "sg:tags":[
        "messenger",
        "courier"
    ],
    "wof:name":"Station Courier Services",
    "wof:placetype":"venue"
},
  "geometry": {"coordinates":[-1.387859,54.817039],"type":"Point"}
}