{
  "type": "Feature",
  "properties": {
    "iso:country":"GB",
    "sg:address":"Went Vale Works, Pontefract Road, Featherstone",
    "sg:city":"Pontefract",
    "sg:classifiers":[
        {
            "category":"Autos & Motor Vehicles",
            "subcategory":"Boat Sales",
            "type":"Retail Goods"
        },
        {
            "category":"Retail",
            "subcategory":"Auto Repair",
            "type":"Services"
        }
    ],
    "sg:phone":"+44 1977 703619",
    "sg:postcode":"WF7 5HG",
    "sg:province":"West Yorkshire",
    "sg:tags":[
        "engine",
        "car",
        "rebuilders",
        "specialist"
    ],
    "wof:name":"B & S Engineers",
    "wof:placetype":"venue"
},
  "geometry": {"coordinates":[-1.337244,53.679283],"type":"Point"}
}