{
  "type": "Feature",
  "properties": {
    "iso:country":"GB",
    "sg:address":"Unit 10, Lawn Farm Business Centre, Grendon Underwood",
    "sg:city":"Aylesbury",
    "sg:classifiers":[
        {
            "category":"Autos & Motor Vehicles",
            "subcategory":"Fuel & Gas Station",
            "type":"Retail Goods"
        }
    ],
    "sg:phone":"+44 1296 770138",
    "sg:postcode":"HP18 0QX",
    "sg:province":"Buckinghamshire",
    "sg:tags":[
        "aga",
        "cooker"
    ],
    "wof:name":"B T L Cookers Ltd.",
    "wof:placetype":"venue"
},
  "geometry": {"coordinates":[-1.011735,51.881187],"type":"Point"}
}