{
  "type": "Feature",
  "properties": {
    "addr:full":"Pomprensych, Pant Y Dwr Rhayader Powys LD6 5LL",
    "addr:postcode":"ld6 5ll",
    "addr:street":"Pant Y Dwr",
    "iso:country":"GB",
    "sg:address":"Pomprensych, Pant Y Dwr",
    "sg:city":"Rhayader",
    "sg:classifiers":[
        {
            "category":"Building & Trades",
            "subcategory":"Construction",
            "type":"Services"
        },
        {
            "category":"Government",
            "subcategory":"Post Office",
            "type":"Public Place"
        }
    ],
    "sg:phone":"+44 1597 870600",
    "sg:postcode":"LD6 5LL",
    "sg:province":"Powys",
    "sg:tags":[
        "builder"
    ],
    "wof:name":"Pantydwr Post Office",
    "wof:placetype":"venue"
},
  "geometry": {"coordinates":[-3.51158,52.302761],"type":"Point"}
}