{
  "type": "Feature",
  "properties": {
    "iso:country":"GB",
    "sg:address":"Redhouse Service Station, London Road",
    "sg:city":"Ware",
    "sg:classifiers":[
        {
            "category":"Shopping",
            "type":"Retail Goods"
        }
    ],
    "sg:phone":"+44 1920 460800",
    "sg:postcode":"SG12 9LY",
    "sg:province":"Hertfordshire",
    "sg:tags":[
        "part",
        "accessory"
    ],
    "wof:name":"R P M Motorsport Ltd.",
    "wof:placetype":"venue"
},
  "geometry": {"coordinates":[-0.035126999,51.8163375854],"type":"Point"}
}