{
  "type": "Feature",
  "properties": {
    "addr:full":"706 Wimborne Road, Winton Bournemouth Dorset BH9 2EG",
    "addr:housenumber":"706",
    "addr:postcode":"bh9 2eg",
    "addr:street":"Wimborne Road",
    "iso:country":"GB",
    "sg:address":"706 Wimborne Road, Winton",
    "sg:city":"Bournemouth",
    "sg:classifiers":[
        {
            "category":"Real Estate",
            "subcategory":"Real Estate Agent",
            "type":"Services"
        }
    ],
    "sg:phone":"+44 1202 525411",
    "sg:postcode":"BH9 2EG",
    "sg:province":"Dorset",
    "wof:name":"Connell Estate Agents",
    "wof:placetype":"venue"
},
  "geometry": {"coordinates":[-1.877687,50.748962],"type":"Point"}
}