{
  "type": "Feature",
  "properties": {
    "iso:country":"GB",
    "sg:address":"1 Anstable Road",
    "sg:city":"Morecambe",
    "sg:classifiers":[
        {
            "category":"Government",
            "subcategory":"Post Office",
            "type":"Public Place"
        }
    ],
    "sg:phone":"+44 1524 410586",
    "sg:postcode":"LA4 6TG",
    "sg:province":"Lancashire",
    "wof:name":"BEAUFORT ROAD POST OFFICE",
    "wof:placetype":"venue"
},
  "geometry": {"coordinates":[-2.843277,54.071838],"type":"Point"}
}