{
  "type": "Feature",
  "properties": {
    "iso:country":"GB",
    "sg:address":"Unit 4 Baston Fen, Baston",
    "sg:city":"Peterborough",
    "sg:classifiers":[
        {
            "category":"Building & Trades",
            "subcategory":"Cleaning & Sanitation",
            "type":"Services"
        }
    ],
    "sg:phone":"+44 1778 561111",
    "sg:postcode":"PE6 9PT",
    "sg:province":"Cambridgeshire",
    "sg:tags":[
        "blast"
    ],
    "wof:name":"S P Blastings",
    "wof:placetype":"venue"
},
  "geometry": {"coordinates":[-0.356869,52.710545],"type":"Point"}
}