{
  "type": "Feature",
  "properties": {
    "addr:full":"Unit 28, 14-20 George Street, Balsall Heath Birmingham West Midlands B12 9RG",
    "addr:housenumber":"unit 28 14-20",
    "addr:postcode":"b12 9rg",
    "addr:street":"George Street",
    "iso:country":"GB",
    "sg:address":"Unit 28, 14-20 George Street, Balsall Heath",
    "sg:city":"Birmingham",
    "sg:classifiers":[
        {
            "category":"Building & Trades",
            "subcategory":"Electrical",
            "type":"Services"
        }
    ],
    "sg:phone":"+44 121 440 7477",
    "sg:postcode":"B12 9RG",
    "sg:province":"West Midlands",
    "sg:tags":[
        "lighting"
    ],
    "wof:name":"Hughes Light",
    "wof:placetype":"venue"
},
  "geometry": {"coordinates":[-1.8908269405,52.4564781189],"type":"Point"}
}