{
  "type": "Feature",
  "properties": {
    "iso:country":"GB",
    "sg:address":"Grayston Plain, Grayston Plain Lane, Hampsthwaite",
    "sg:city":"Harrogate",
    "sg:classifiers":[
        {
            "category":"Retail",
            "subcategory":"Auto Repair",
            "type":"Services"
        }
    ],
    "sg:phone":"+44 1423 770779",
    "sg:postcode":"HG3 2LY",
    "sg:province":"North Yorkshire",
    "sg:tags":[
        "modification",
        "garage"
    ],
    "wof:name":"Simon Graeme Auto Service Centre",
    "wof:placetype":"venue"
},
  "geometry": {"coordinates":[-1.604429,54.026176],"type":"Point"}
}