{
  "type": "Feature",
  "properties": {
    "addr:full":"75 New Road Rugeley Staffordshire WS15 4BH",
    "addr:housenumber":"75",
    "addr:postcode":"ws15 4bh",
    "addr:street":"New Road",
    "iso:country":"GB",
    "sg:address":"75 New Road",
    "sg:city":"Rugeley",
    "sg:classifiers":[
        {
            "category":"Shopping",
            "subcategory":"News",
            "type":"Retail Goods"
        }
    ],
    "sg:phone":"+44 1543 490338",
    "sg:postcode":"WS15 4BH",
    "sg:province":"Staffordshire",
    "sg:tags":[
        "newsagent"
    ],
    "wof:name":"C & S Lela",
    "wof:placetype":"venue"
},
  "geometry": {"coordinates":[-1.874973,52.741859],"type":"Point"}
}