{
  "type": "Feature",
  "properties": {
    "addr:full":"44 High Street Uttoxeter Derbyshire ST14 7HT",
    "addr:housenumber":"44",
    "addr:postcode":"st14 7ht",
    "addr:street":"High Street",
    "iso:country":"GB",
    "sg:address":"44 High Street",
    "sg:city":"Uttoxeter",
    "sg:classifiers":[
        {
            "category":"Food & Beverages",
            "subcategory":"Meat & Fish",
            "type":"Retail Goods"
        }
    ],
    "sg:phone":"+44 1889 564282",
    "sg:postcode":"ST14 7HT",
    "sg:province":"Derbyshire",
    "sg:tags":[
        "chip"
    ],
    "wof:name":"Cods Corners",
    "wof:placetype":"venue"
},
  "geometry": {"coordinates":[-1.865711,52.899902],"type":"Point"}
}