{
  "type": "Feature",
  "properties": {
    "addr:full":"7 Highfield Parade Waterlooville Hampshire PO7 7QH",
    "addr:housenumber":"7",
    "addr:postcode":"po7 7qh",
    "addr:street":"Highfield Parade",
    "iso:country":"GB",
    "sg:address":"7 Highfield Parade",
    "sg:city":"Waterlooville",
    "sg:classifiers":[
        {
            "category":"Personal",
            "subcategory":"Beauty Salon",
            "type":"Services"
        },
        {
            "category":"Personal",
            "subcategory":"Barber",
            "type":"Services"
        }
    ],
    "sg:phone":"+44 23 9224 1243",
    "sg:postcode":"PO7 7QH",
    "sg:province":"Hampshire",
    "sg:tags":[
        "unisex",
        "hairdresser"
    ],
    "wof:name":"Fringe",
    "wof:placetype":"venue"
},
  "geometry": {"coordinates":[-1.0251020193,50.8868675232],"type":"Point"}
}