{
  "type": "Feature",
  "properties": {
    "iso:country":"GB",
    "sg:address":"Gauze Place",
    "sg:city":"Bo'ness",
    "sg:classifiers":[
        {
            "category":"Shopping",
            "subcategory":"Department Store",
            "type":"Retail Goods"
        }
    ],
    "sg:phone":"+44 1506 517030",
    "sg:postcode":"EH51 9JQ",
    "sg:province":"Falkirk",
    "wof:name":"Hays Family Store",
    "wof:placetype":"venue"
},
  "geometry": {"coordinates":[-3.6013200283,56.0077285767],"type":"Point"}
}