{
  "type": "Feature",
  "properties": {
    "addr:full":"3 Kinwarton Workshops, Kinwarton Farm Road Alcester Warwickshire B49 6EH",
    "addr:housenumber":"3",
    "addr:postcode":"b49 6eh",
    "addr:street":"Kinwarton Workshops Kinwarton Farm Road",
    "iso:country":"GB",
    "sg:address":"3 Kinwarton Workshops, Kinwarton Farm Road",
    "sg:city":"Alcester",
    "sg:classifiers":[
        {
            "category":"Professional",
            "subcategory":"Art Services",
            "type":"Services"
        }
    ],
    "sg:phone":"+44 1789 400366",
    "sg:postcode":"B49 6EH",
    "sg:province":"Warwickshire",
    "sg:tags":[
        "graphic",
        "designer"
    ],
    "wof:name":"Intelligent Design Solutions Ltd.",
    "wof:placetype":"venue"
},
  "geometry": {"coordinates":[-1.860992,52.221798],"type":"Point"}
}