{
  "type": "Feature",
  "properties": {
    "addr:full":"15a Hay Lane London Greater London NW9 0NH",
    "addr:housenumber":"15a",
    "addr:postcode":"nw9 0nh",
    "addr:street":"Hay Lane",
    "iso:country":"GB",
    "sg:address":"15a Hay Lane",
    "sg:city":"London",
    "sg:classifiers":[
        {
            "category":"Cinema",
            "subcategory":"Movie Rental",
            "type":"Entertainment"
        }
    ],
    "sg:phone":"+44 20 8204 9952",
    "sg:postcode":"NW9 0NH",
    "sg:province":"Greater London",
    "sg:tags":[
        "video",
        "library"
    ],
    "wof:name":"Savanis",
    "wof:placetype":"venue"
},
  "geometry": {"coordinates":[-0.2630020082,51.5882911682],"type":"Point"}
}