{
  "type": "Feature",
  "properties": {
    "addr:full":"55 Main St West Kilbride North Ayrshire KA23 9AW",
    "addr:housenumber":"55",
    "addr:postcode":"ka23 9aw",
    "addr:street":"Main St",
    "iso:country":"GB",
    "sg:address":"55 Main St",
    "sg:city":"West Kilbride",
    "sg:classifiers":[
        {
            "category":"Shopping",
            "subcategory":"News",
            "type":"Retail Goods"
        }
    ],
    "sg:phone":"+44 1294 823646",
    "sg:postcode":"KA23 9AW",
    "sg:province":"North Ayrshire",
    "sg:tags":[
        "newsagent"
    ],
    "wof:name":"Village News",
    "wof:placetype":"venue"
},
  "geometry": {"coordinates":[-4.855373,55.69582],"type":"Point"}
}