{
  "type": "Feature",
  "properties": {
    "addr:full":"17 Wakley Street London Greater London EC1V 7RQ",
    "addr:housenumber":"17",
    "addr:postcode":"ec1v 7rq",
    "addr:street":"Wakley Street",
    "iso:country":"GB",
    "sg:address":"17 Wakley Street",
    "sg:city":"London",
    "sg:classifiers":[
        {
            "category":"Organizations",
            "subcategory":"Non-profit Organization",
            "type":"Services"
        }
    ],
    "sg:phone":"+44 20 7837 0006",
    "sg:postcode":"EC1V 7RQ",
    "sg:province":"Greater London",
    "sg:tags":[
        "organisation",
        "animal",
        "welfare"
    ],
    "wof:name":"National Canine Defence League Rescue Centre",
    "wof:placetype":"venue"
},
  "geometry": {"coordinates":[-0.1023110002,51.5300712585],"type":"Point"}
}