{
  "type": "Feature",
  "properties": {
    "addr:full":"Meadows Surgery, Temple Gro Burgess Hill East Sussex RH15 9XN",
    "addr:postcode":"rh15 9xn",
    "addr:street":"Gro",
    "iso:country":"GB",
    "sg:address":"Meadows Surgery, Temple Gro",
    "sg:city":"Burgess Hill",
    "sg:classifiers":[
        {
            "category":"Health Services",
            "subcategory":"Doctor",
            "type":"Services"
        }
    ],
    "sg:phone":"+44 1444 258357",
    "sg:postcode":"RH15 9XN",
    "sg:province":"East Sussex",
    "sg:tags":[
        "practitioners"
    ],
    "wof:name":"J MacGuire & Parterns",
    "wof:placetype":"venue"
},
  "geometry": {"coordinates":[-0.139174,50.95533],"type":"Point"}
}