{
  "type": "Feature",
  "properties": {
    "iso:country":"GB",
    "sg:address":"83 Baysham St",
    "sg:city":"Hereford",
    "sg:classifiers":[
        {
            "category":"Farming",
            "subcategory":"Dairy Farm",
            "type":"Manufacturing & Wholesale Goods"
        }
    ],
    "sg:phone":"+44 1432 268740",
    "sg:postcode":"HR4 0ET",
    "sg:province":"Herefordshire",
    "wof:name":"E.P Thomas",
    "wof:placetype":"venue"
},
  "geometry": {"coordinates":[-2.729245,52.057659],"type":"Point"}
}