{
  "type": "Feature",
  "properties": {
    "iso:country":"GB",
    "sg:address":"40 Aston Road",
    "sg:city":"Waterlooville",
    "sg:classifiers":[
        {
            "category":"Manufacturing",
            "subcategory":"Metals",
            "type":"Manufacturing & Wholesale Goods"
        }
    ],
    "sg:phone":"+44 23 9226 7614",
    "sg:postcode":"PO7 7XF",
    "sg:province":"Hampshire",
    "sg:tags":[
        "steel",
        "fabricator",
        "erectors"
    ],
    "wof:name":"Caroway Fabrications Ltd.",
    "wof:placetype":"venue"
},
  "geometry": {"coordinates":[-1.035354,50.885651],"type":"Point"}
}