{
  "type": "Feature",
  "properties": {
    "addr:full":"144 Hampton La Southampton Hampshire SO45 1WE",
    "addr:housenumber":"144",
    "addr:postcode":"so45 1we",
    "addr:street":"Hampton La Southampton",
    "iso:country":"GB",
    "sg:address":"144 Hampton La",
    "sg:city":"Southampton",
    "sg:classifiers":[
        {
            "category":"Shopping",
            "subcategory":"Department Store",
            "type":"Retail Goods"
        }
    ],
    "sg:phone":"+44 23 8089 2376",
    "sg:postcode":"SO45 1WE",
    "sg:province":"Hampshire",
    "wof:name":"Country Store",
    "wof:placetype":"venue"
},
  "geometry": {"coordinates":[-1.371803,50.817547],"type":"Point"}
}