{
  "type": "Feature",
  "properties": {
    "addr:full":"45 East Street, Fritwell Bicester Buckinghamshire OX27 7PX",
    "addr:housenumber":"45",
    "addr:postcode":"ox27 7px",
    "addr:street":"East Street",
    "iso:country":"GB",
    "sg:address":"45 East Street, Fritwell",
    "sg:city":"Bicester",
    "sg:classifiers":[
        {
            "category":"Food & Beverages",
            "subcategory":"Meat & Fish",
            "type":"Retail Goods"
        }
    ],
    "sg:phone":"+44 1869 345229",
    "sg:postcode":"OX27 7PX",
    "sg:province":"Buckinghamshire",
    "sg:tags":[
        "butcher"
    ],
    "wof:name":"G B Wrighton & Son",
    "wof:placetype":"venue"
},
  "geometry": {"coordinates":[-1.233433,51.958244],"type":"Point"}
}