{
  "type": "Feature",
  "properties": {
    "addr:full":"26 Eastfield Road Dagenham Essex RM10 8PU",
    "addr:housenumber":"26",
    "addr:postcode":"rm10 8pu",
    "addr:street":"Eastfield Road",
    "iso:country":"GB",
    "sg:address":"26 Eastfield Road",
    "sg:city":"Dagenham",
    "sg:classifiers":[
        {
            "category":"Building & Trades",
            "subcategory":"Construction",
            "type":"Services"
        }
    ],
    "sg:phone":"+44 20 8262 3179",
    "sg:postcode":"RM10 8PU",
    "sg:province":"Essex",
    "sg:tags":[
        "decorator",
        "painter"
    ],
    "wof:name":"Lady Decorators",
    "wof:placetype":"venue"
},
  "geometry": {"coordinates":[0.149118,51.549526],"type":"Point"}
}