{
  "type": "Feature",
  "properties": {
    "iso:country":"GB",
    "sg:address":"Gapton Hall Road, Harfreys Industrial Estate, Harfreys Industrial Estate",
    "sg:city":"Great Yarmouth",
    "sg:classifiers":[
        {
            "category":"Home & Garden",
            "subcategory":"Carpets & Floor Coverings",
            "type":"Retail Goods"
        }
    ],
    "sg:phone":"+44 1493 446080",
    "sg:postcode":"NR31 0NL",
    "sg:province":"Norfolk",
    "sg:tags":[
        "carpets",
        "rug",
        "matting"
    ],
    "wof:name":"Allied Carpets",
    "wof:placetype":"venue"
},
  "geometry": {"coordinates":[1.71314,52.598476],"type":"Point"}
}