{
  "type": "Feature",
  "properties": {
    "iso:country":"GB",
    "sg:address":"Administration Building, Erskine Bridge",
    "sg:city":"Bishopton",
    "sg:classifiers":[
        {
            "category":"Parking",
            "type":"Transportation"
        }
    ],
    "sg:phone":"+44 141 812 7022",
    "sg:postcode":"PA7 5QD",
    "sg:province":"Renfrewshire",
    "sg:tags":[
        "car",
        "park"
    ],
    "wof:name":"Acoa Parking (Uk)",
    "wof:placetype":"venue"
},
  "geometry": {"coordinates":[-4.5131192207,55.911190033],"type":"Point"}
}