{
  "type": "Feature",
  "properties": {
    "addr:full":"Weatherwise Building, Well Road East Cowes Isle of Wight PO32 6SP",
    "addr:postcode":"po32 6sp",
    "addr:street":"Well Road",
    "iso:country":"GB",
    "sg:address":"Weatherwise Building, Well Road",
    "sg:city":"East Cowes",
    "sg:classifiers":[
        {
            "category":"Shopping",
            "subcategory":"Clothing, Apparel, & Fashions",
            "type":"Retail Goods"
        }
    ],
    "sg:phone":"+44 1983 883491",
    "sg:postcode":"PO32 6SP",
    "sg:province":"Isle of Wight",
    "sg:tags":[
        "t-shirt"
    ],
    "wof:name":"Weatherwise",
    "wof:placetype":"venue"
},
  "geometry": {"coordinates":[-1.2840679884,50.7557792664],"type":"Point"}
}