{
  "type": "Feature",
  "properties": {
    "addr:full":"2 Castle House, 2 Castle Boulevard Nottingham Nottinghamshire NG7 1FB",
    "addr:housenumber":"2;2",
    "addr:postcode":"ng7 1fb",
    "addr:street":"Castle;Castle Boulevard",
    "iso:country":"GB",
    "sg:address":"2 Castle House, 2 Castle Boulevard",
    "sg:city":"Nottingham",
    "sg:classifiers":[
        {
            "category":"Professional",
            "subcategory":"Art Services",
            "type":"Services"
        }
    ],
    "sg:phone":"+44 115 941 0647",
    "sg:postcode":"NG7 1FB",
    "sg:province":"Nottinghamshire",
    "sg:tags":[
        "photographer"
    ],
    "wof:name":"Garie Hind Photography",
    "wof:placetype":"venue"
},
  "geometry": {"coordinates":[-1.15083,52.948879],"type":"Point"}
}