{
  "type": "Feature",
  "properties": {
    "addr:full":"30 Brock Street Bath Bath and North East Somerset BA1 2LN",
    "addr:housenumber":"30",
    "addr:postcode":"ba1 2ln",
    "addr:street":"Brock Street",
    "iso:country":"GB",
    "sg:address":"30 Brock Street",
    "sg:city":"Bath",
    "sg:classifiers":[
        {
            "category":"Building & Trades",
            "subcategory":"Landscaping Services",
            "type":"Services"
        },
        {
            "category":"Professional",
            "subcategory":"Management & Consulting",
            "type":"Services"
        }
    ],
    "sg:phone":"+44 1225 445548",
    "sg:postcode":"BA1 2LN",
    "sg:province":"Bath and North East Somerset",
    "sg:tags":[
        "consultant",
        "designer",
        "architect",
        "landscape",
        "environmental"
    ],
    "wof:name":"Nicholas Pearson Associates Ltd.",
    "wof:placetype":"venue"
},
  "geometry": {"coordinates":[-2.3652141094,51.3862838745],"type":"Point"}
}