{
  "type": "Feature",
  "properties": {
    "addr:full":"25 Eastgate Street Chester Cheshire CH1 1LG",
    "addr:housenumber":"25",
    "addr:postcode":"ch1 1lg",
    "addr:street":"Eastgate Street",
    "iso:country":"GB",
    "sg:address":"25 Eastgate Street",
    "sg:city":"Chester",
    "sg:classifiers":[
        {
            "category":"Shopping",
            "subcategory":"Gifts & Souvenirs",
            "type":"Retail Goods"
        }
    ],
    "sg:phone":"+44 1244 310682",
    "sg:postcode":"CH1 1LG",
    "sg:province":"Cheshire",
    "sg:tags":[
        "shop",
        "poster",
        "card"
    ],
    "wof:name":"CLINTON CARDS PLC",
    "wof:placetype":"venue"
},
  "geometry": {"coordinates":[-2.890618,53.190651],"type":"Point"}
}