{
  "type": "Feature",
  "properties": {
    "addr:full":"14 Riverdale Road Twickenham Greater London TW1 2BS",
    "addr:housenumber":"14",
    "addr:postcode":"tw1 2bs",
    "addr:street":"Riverdale Road",
    "iso:country":"GB",
    "sg:address":"14 Riverdale Road",
    "sg:city":"Twickenham",
    "sg:classifiers":[
        {
            "category":"Organizations",
            "subcategory":"Membership Organization",
            "type":"Services"
        }
    ],
    "sg:postcode":"TW1 2BS",
    "sg:province":"Greater London",
    "sg:tags":[
        "club"
    ],
    "wof:name":"14 RIVERDALE ROAD RESIDENTS' ASSOCIATION LTD",
    "wof:placetype":"venue"
},
  "geometry": {"coordinates":[-0.3131799996,51.4563064575],"type":"Point"}
}