{
  "type": "Feature",
  "properties": {
    "iso:country":"GB",
    "sg:address":"Old Courts Road",
    "sg:city":"Brigg",
    "sg:classifiers":[
        {
            "category":"Professional",
            "subcategory":"Business Services",
            "type":"Services"
        }
    ],
    "sg:postcode":"DN20 8JD",
    "sg:province":"Lincolnshire",
    "sg:tags":[
        "bookmaker"
    ],
    "wof:name":"John Margrave Bookmakers",
    "wof:placetype":"venue"
},
  "geometry": {"coordinates":[-0.4906390011,53.5529136658],"type":"Point"}
}