{
  "type": "Feature",
  "properties": {
    "iso:country":"GB",
    "sg:address":"83 Rushey Green, Catford",
    "sg:city":"Catford",
    "sg:classifiers":[
        {
            "category":"Sports & Exercise",
            "subcategory":"Sports Center",
            "type":"Entertainment"
        }
    ],
    "sg:phone":"+44 20 8697 7733",
    "sg:postcode":"SE6 4AF",
    "sg:province":"Greater London",
    "sg:tags":[
        "shop",
        "good"
    ],
    "wof:name":"XS Muscle Store",
    "wof:placetype":"venue"
},
  "geometry": {"coordinates":[-0.017659,51.447906],"type":"Point"}
}