{
  "type": "Feature",
  "properties": {
    "iso:country":"GB",
    "sg:address":"34 Longcrofte Rd",
    "sg:city":"Edgware",
    "sg:classifiers":[
        {
            "category":"Professional",
            "subcategory":"Accounting & Tax Preparation",
            "type":"Services"
        }
    ],
    "sg:phone":"+44 20 8952 8791",
    "sg:postcode":"HA8 6RR",
    "sg:province":"Greater London",
    "sg:tags":[
        "accountant"
    ],
    "wof:name":"C H J Chartered Certified Accountants",
    "wof:placetype":"venue"
},
  "geometry": {"coordinates":[-0.299624,51.609436],"type":"Point"}
}