{
  "type": "Feature",
  "properties": {
    "addr:full":"Devonshire House, 28 Devon Square Newton Abbot Devon TQ12 2HH",
    "addr:housenumber":"28",
    "addr:postcode":"tq12 2hh",
    "addr:street":"Devon Square",
    "iso:country":"GB",
    "sg:address":"Devonshire House, 28 Devon Square",
    "sg:city":"Newton Abbot",
    "sg:classifiers":[
        {
            "category":"Real Estate",
            "subcategory":"Surveying",
            "type":"Services"
        }
    ],
    "sg:phone":"+44 1626 201020",
    "sg:postcode":"TQ12 2HH",
    "sg:province":"Devon",
    "sg:tags":[
        "surveyor",
        "quantity"
    ],
    "wof:name":"Randall & Simmonds",
    "wof:placetype":"venue"
},
  "geometry": {"coordinates":[-3.604938,50.529404],"type":"Point"}
}