{
  "type": "Feature",
  "properties": {
    "addr:full":"93 Eversley Road, Sketty Swansea Swansea SA2 9DE",
    "addr:housenumber":"93",
    "addr:postcode":"sa2 9de",
    "addr:street":"Eversley Road",
    "iso:country":"GB",
    "sg:address":"93 Eversley Road, Sketty",
    "sg:city":"Swansea",
    "sg:classifiers":[
        {
            "category":"Food & Beverages",
            "subcategory":"Meat & Fish",
            "type":"Retail Goods"
        }
    ],
    "sg:phone":"+44 1792 419619",
    "sg:postcode":"SA2 9DE",
    "sg:province":"Swansea",
    "sg:tags":[
        "chip"
    ],
    "wof:name":"The Range Fish & Chip Shop",
    "wof:placetype":"venue"
},
  "geometry": {"coordinates":[-3.9842329025,51.6183547974],"type":"Point"}
}