{
  "type": "Feature",
  "properties": {
    "iso:country":"GB",
    "sg:address":"Rose Cottage Farm, Trevellas",
    "sg:city":"St Agnes",
    "sg:classifiers":[
        {
            "category":"Retail",
            "subcategory":"Veterinary Services",
            "type":"Services"
        }
    ],
    "sg:phone":"+44 1872 552837",
    "sg:postcode":"TR5 0WX",
    "sg:province":"Cornwall",
    "sg:tags":[
        "surgeon"
    ],
    "wof:name":"G M Doody",
    "wof:placetype":"venue"
},
  "geometry": {"coordinates":[-5.199199,50.312099],"type":"Point"}
}