{
  "type": "Feature",
  "properties": {
    "addr:full":"9 Manningtree St Whitechapel Greater London E1 1LG",
    "addr:housenumber":"9",
    "addr:postcode":"e1 1lg",
    "addr:street":"Manningtree St",
    "iso:country":"GB",
    "sg:address":"9 Manningtree St",
    "sg:city":"Whitechapel",
    "sg:classifiers":[
        {
            "category":"Shopping",
            "subcategory":"Clothing, Apparel, & Fashions",
            "type":"Retail Goods"
        }
    ],
    "sg:phone":"+44 20 7247 3056",
    "sg:postcode":"E1 1LG",
    "sg:province":"Greater London",
    "sg:tags":[
        "clothing"
    ],
    "wof:name":"Amora Wear",
    "wof:placetype":"venue"
},
  "geometry": {"coordinates":[-0.069352001,51.5152740479],"type":"Point"}
}