{
  "type": "Feature",
  "properties": {
    "addr:full":"Unit 2 Knightsridge Indstl Est Livingston West Lothian EH54 8RA",
    "addr:housenumber":"unit 2",
    "addr:postcode":"eh54 8ra",
    "addr:street":"Knightsridge Indstl Est",
    "iso:country":"GB",
    "sg:address":"Unit 2 Knightsridge Indstl Est",
    "sg:city":"Livingston",
    "sg:classifiers":[
        {
            "category":"Autos & Motor Vehicles",
            "subcategory":"Auto Supplies",
            "type":"Retail Goods"
        }
    ],
    "sg:postcode":"EH54 8RA",
    "sg:province":"West Lothian",
    "sg:tags":[
        "tyre"
    ],
    "wof:name":"A1 Bandag Ltd",
    "wof:placetype":"venue"
},
  "geometry": {"coordinates":[-3.5310239792,55.9052238464],"type":"Point"}
}