{
  "type": "Feature",
  "properties": {
    "addr:full":"47 Cann Bridge Street, Higher Walton Preston Lancashire PR5 4DJ",
    "addr:housenumber":"47",
    "addr:postcode":"pr5 4dj",
    "addr:street":"Cann Bridge Street",
    "iso:country":"GB",
    "sg:address":"47 Cann Bridge Street, Higher Walton",
    "sg:city":"Preston",
    "sg:classifiers":[
        {
            "category":"Professional",
            "type":"Services"
        }
    ],
    "sg:phone":"+44 1772 334802",
    "sg:postcode":"PR5 4DJ",
    "sg:province":"Lancashire",
    "sg:tags":[
        "caterer"
    ],
    "wof:name":"Bon Appetit",
    "wof:placetype":"venue"
},
  "geometry": {"coordinates":[-2.643446,53.742695],"type":"Point"}
}