{
  "type": "Feature",
  "properties": {
    "iso:country":"GB",
    "sg:address":"88 Westcliffe",
    "sg:city":"Dumbarton",
    "sg:classifiers":[
        {
            "category":"Home & Garden",
            "subcategory":"Household Appliances",
            "type":"Retail Goods"
        }
    ],
    "sg:phone":"+44 1389 762324",
    "sg:postcode":"G82 5DL",
    "sg:province":"Argyll and Bute",
    "sg:tags":[
        "electrical"
    ],
    "wof:name":"A Robinson",
    "wof:placetype":"venue"
},
  "geometry": {"coordinates":[-4.6033492088,55.9485702515],"type":"Point"}
}