{
  "type": "Feature",
  "properties": {
    "addr:full":"Olmar Street London Greater London SE1 5AY",
    "addr:postcode":"se1 5ay",
    "addr:street":"Olmar Street",
    "iso:country":"GB",
    "sg:address":"Olmar Street",
    "sg:city":"London",
    "sg:classifiers":[
        {
            "category":"Communications",
            "subcategory":"Film & Video Production",
            "type":"Services"
        },
        {
            "category":"Communications",
            "type":"Services"
        }
    ],
    "sg:phone":"+44 20 7237 5332",
    "sg:postcode":"SE1 5AY",
    "sg:province":"Greater London",
    "sg:tags":[
        "tv",
        "studio",
        "audio-visual"
    ],
    "wof:name":"James Electrical Group",
    "wof:placetype":"venue"
},
  "geometry": {"coordinates":[-0.0699390024,51.4839477539],"type":"Point"}
}