{
  "type": "Feature",
  "properties": {
    "addr:full":"Rossa Bach, Prion Denbigh Conwy LL16 4RP",
    "addr:postcode":"ll16 4rp",
    "addr:street":"Denbigh",
    "iso:country":"GB",
    "sg:address":"Rossa Bach, Prion",
    "sg:city":"Denbigh",
    "sg:classifiers":[
        {
            "category":"Farming",
            "subcategory":"Livestock Farm",
            "type":"Manufacturing & Wholesale Goods"
        }
    ],
    "sg:phone":"+44 1745 812397",
    "sg:postcode":"LL16 4RP",
    "sg:province":"Conwy",
    "sg:tags":[
        "others"
    ],
    "wof:name":"G M Roberts & Sons",
    "wof:placetype":"venue"
},
  "geometry": {"coordinates":[-3.4203400612,53.1485748291],"type":"Point"}
}