{
  "type": "Feature",
  "properties": {
    "iso:country":"GB",
    "sg:address":"Miletree Road, Heath And Reach",
    "sg:city":"Leighton Buzzard",
    "sg:classifiers":[
        {
            "category":"Transit Center",
            "subcategory":"Passenger",
            "type":"Transportation"
        }
    ],
    "sg:phone":"+44 1525 237563",
    "sg:postcode":"LU7 9LA",
    "sg:province":"Bedfordshire",
    "sg:tags":[
        "boarding",
        "kennel",
        "catteries"
    ],
    "wof:name":"Miletree Catotel",
    "wof:placetype":"venue"
},
  "geometry": {"coordinates":[-0.630372,51.940285],"type":"Point"}
}