{
  "type": "Feature",
  "properties": {
    "iso:country":"GB",
    "sg:address":"Colwick Indust Est",
    "sg:city":"Nottingham",
    "sg:classifiers":[
        {
            "category":"Home & Garden",
            "subcategory":"Home Furnishings",
            "type":"Retail Goods"
        }
    ],
    "sg:phone":"+44 115 961 8234",
    "sg:postcode":"NG4 2JR",
    "sg:province":"Nottinghamshire",
    "sg:tags":[
        "awning",
        "canopy",
        "blinds"
    ],
    "wof:name":"Hillarys Blinds Ltd",
    "wof:placetype":"venue"
},
  "geometry": {"coordinates":[-1.089914,52.955173],"type":"Point"}
}