{
  "type": "Feature",
  "properties": {
    "addr:full":"Fiveways, Thornley Gate Hexham Northumberland NE47 9NH",
    "addr:postcode":"ne47 9nh",
    "addr:street":"Gate",
    "iso:country":"GB",
    "sg:address":"Fiveways, Thornley Gate",
    "sg:city":"Hexham",
    "sg:classifiers":[
        {
            "category":"Autos & Motor Vehicles",
            "subcategory":"Fuel & Gas Station",
            "type":"Retail Goods"
        }
    ],
    "sg:phone":"+44 1434 683756",
    "sg:postcode":"NE47 9NH",
    "sg:province":"Northumberland",
    "sg:tags":[
        "petrol",
        "filling"
    ],
    "wof:name":"H L Coulson",
    "wof:placetype":"venue"
},
  "geometry": {"coordinates":[-2.2649888992,54.900932312],"type":"Point"}
}