{
  "type": "Feature",
  "properties": {
    "addr:full":"90 Stirling St Alva Clackmannanshire FK12 5EA",
    "addr:housenumber":"90",
    "addr:postcode":"fk12 5ea",
    "addr:street":"Stirling St",
    "iso:country":"GB",
    "sg:address":"90 Stirling St",
    "sg:city":"Alva",
    "sg:classifiers":[
        {
            "category":"Banks & Credit Unions",
            "subcategory":"Bank",
            "type":"Services"
        }
    ],
    "sg:phone":"+44 1259 769267",
    "sg:postcode":"FK12 5EA",
    "sg:province":"Clackmannanshire",
    "sg:tags":[
        "broker",
        "mortgage"
    ],
    "wof:name":"Mortgage Desk The",
    "wof:placetype":"venue"
},
  "geometry": {"coordinates":[-3.800260067,56.1531639099],"type":"Point"}
}