{
  "type": "Feature",
  "properties": {
    "iso:country":"GB",
    "sg:address":"4 Drinnishadder",
    "sg:city":"Harris",
    "sg:classifiers":[
        {
            "category":"Government",
            "subcategory":"Post Office",
            "type":"Public Place"
        }
    ],
    "sg:phone":"+44 1859 511200",
    "sg:postcode":"HS3 3DX",
    "sg:province":"Eilean Siar",
    "wof:name":"Drinnishader Post Office",
    "wof:placetype":"venue"
},
  "geometry": {"coordinates":[-6.7710161209,57.8579483032],"type":"Point"}
}