{
  "type": "Feature",
  "properties": {
    "iso:country":"GB",
    "sg:address":"21 Redstart Close",
    "sg:city":"London",
    "sg:classifiers":[
        {
            "category":"Building & Trades",
            "subcategory":"Cleaning & Sanitation",
            "type":"Services"
        }
    ],
    "sg:postcode":"E6 5XB",
    "sg:province":"Greater London",
    "sg:tags":[
        "repair",
        "lift",
        "-"
    ],
    "wof:name":"Direct Lift Services Ltd.",
    "wof:placetype":"venue"
},
  "geometry": {"coordinates":[0.0488459989,51.5168838501],"type":"Point"}
}