{
  "type": "Feature",
  "properties": {
    "addr:full":"65-67 Provost Rd Dundee Dundee City DD3 8AG",
    "addr:housenumber":"65-67",
    "addr:postcode":"dd3 8ag",
    "addr:street":"Provost Rd",
    "iso:country":"GB",
    "sg:address":"65-67 Provost Rd",
    "sg:city":"Dundee",
    "sg:classifiers":[
        {
            "category":"Food & Beverages",
            "subcategory":"Fruits & Vegetables",
            "type":"Retail Goods"
        }
    ],
    "sg:phone":"+44 1382 812618",
    "sg:postcode":"DD3 8AG",
    "sg:province":"Dundee City",
    "sg:tags":[
        "greengrocer"
    ],
    "wof:name":"Z & F Butt",
    "wof:placetype":"venue"
},
  "geometry": {"coordinates":[-2.975517,56.47757],"type":"Point"}
}