{
  "type": "Feature",
  "properties": {
    "iso:country":"GB",
    "sg:address":"1 Bewell Square",
    "sg:city":"Hereford",
    "sg:classifiers":[
        {
            "category":"Deli",
            "type":"Food & Drink"
        }
    ],
    "sg:phone":"+44 1432 353423",
    "sg:postcode":"HR4 0BB",
    "sg:province":"Herefordshire",
    "sg:tags":[
        "delicatessen"
    ],
    "wof:name":"The Mouse Trap Cheese Shop",
    "wof:placetype":"venue"
},
  "geometry": {"coordinates":[-2.720389,52.056679],"type":"Point"}
}