{
  "type": "Feature",
  "properties": {
    "addr:full":"19 Croft Rd Godalming Surrey GU7 1DB",
    "addr:housenumber":"19",
    "addr:postcode":"gu7 1db",
    "addr:street":"Croft Rd",
    "iso:country":"GB",
    "sg:address":"19 Croft Rd",
    "sg:city":"Godalming",
    "sg:classifiers":[
        {
            "category":"Place Of Worship",
            "type":"Public Place"
        }
    ],
    "sg:phone":"+44 1483 416880",
    "sg:postcode":"GU7 1DB",
    "sg:province":"Surrey",
    "wof:name":"St Edmund King & Martyr",
    "wof:placetype":"venue"
},
  "geometry": {"coordinates":[-0.6152070165,51.1837692261],"type":"Point"}
}