{
  "type": "Feature",
  "properties": {
    "addr:full":"47 Mayfield Road Chester Cheshire CH1 5HY",
    "addr:housenumber":"47",
    "addr:postcode":"ch1 5hy",
    "addr:street":"Mayfield Road",
    "iso:country":"GB",
    "sg:address":"47 Mayfield Road",
    "sg:city":"Chester",
    "sg:classifiers":[
        {
            "category":"Retail",
            "subcategory":"Auto Repair",
            "type":"Services"
        }
    ],
    "sg:phone":"+44 1244 371200",
    "sg:postcode":"CH1 5HY",
    "sg:province":"Cheshire",
    "sg:tags":[
        "car",
        "upholsterer"
    ],
    "wof:name":"Chester Autotrim",
    "wof:placetype":"venue"
},
  "geometry": {"coordinates":[-2.93469,53.208363],"type":"Point"}
}