{
  "type": "Feature",
  "properties": {
    "iso:country":"GB",
    "sg:address":"The Galleries, Washington Centre",
    "sg:city":"Washington",
    "sg:classifiers":[
        {
            "category":"Bars & Pubs",
            "type":"Food & Drink"
        }
    ],
    "sg:phone":"+44 191 419 5901",
    "sg:postcode":"NE38 7SA",
    "sg:province":"Durham",
    "sg:tags":[
        "pubs",
        "inn"
    ],
    "wof:name":"The Oasis",
    "wof:placetype":"venue"
},
  "geometry": {"coordinates":[-1.531789,54.898144],"type":"Point"}
}