{
  "type": "Feature",
  "properties": {
    "iso:country":"GB",
    "sg:address":"64 Derby Road",
    "sg:city":"Ilkeston",
    "sg:classifiers":[
        {
            "category":"Taxi",
            "type":"Transportation"
        },
        {
            "category":"Military Area",
            "subcategory":"Air Force Base",
            "type":"Public Place"
        }
    ],
    "sg:phone":"+44 115 932 1642",
    "sg:postcode":"DE7 5EZ",
    "sg:province":"Derbyshire",
    "sg:tags":[
        "hire",
        "private"
    ],
    "wof:name":"Avenger Taxis",
    "wof:placetype":"venue"
},
  "geometry": {"coordinates":[-1.311441,52.967514],"type":"Point"}
}