{
  "type": "Feature",
  "properties": {
    "iso:country":"GB",
    "sg:address":"208 Marlborough Road",
    "sg:city":"Romford",
    "sg:classifiers":[
        {
            "category":"Building & Trades",
            "subcategory":"Construction",
            "type":"Services"
        }
    ],
    "sg:phone":"+44 1708 728726",
    "sg:postcode":"RM7 8AS",
    "sg:province":"Essex",
    "sg:tags":[
        "roofing"
    ],
    "wof:name":"F & H Roofing Specialists",
    "wof:placetype":"venue"
},
  "geometry": {"coordinates":[0.1546330005,51.583568573],"type":"Point"}
}