{
  "type": "Feature",
  "properties": {
    "iso:country":"GB",
    "sg:address":"250 Church Lane",
    "sg:city":"London",
    "sg:classifiers":[
        {
            "category":"Cinema",
            "subcategory":"Movie Rental",
            "type":"Entertainment"
        }
    ],
    "sg:phone":"+44 20 8200 9836",
    "sg:postcode":"NW9 8SL",
    "sg:province":"Greater London",
    "sg:tags":[
        "video",
        "library"
    ],
    "wof:name":"Hit Video",
    "wof:placetype":"venue"
},
  "geometry": {"coordinates":[-0.2620199919,51.574180603],"type":"Point"}
}