{
  "type": "Feature",
  "properties": {
    "iso:country":"GB",
    "sg:address":"8 Wrotham Road",
    "sg:city":"Gravesend",
    "sg:classifiers":[
        {
            "category":"Health Services",
            "subcategory":"Podiatrist",
            "type":"Services"
        }
    ],
    "sg:phone":"+44 1474 355400",
    "sg:postcode":"DA11 0PA",
    "sg:province":"Kent",
    "sg:tags":[
        "podiatrists",
        "chiropodist"
    ],
    "wof:name":"J R Mason",
    "wof:placetype":"venue"
},
  "geometry": {"coordinates":[0.368054,51.440273],"type":"Point"}
}