{
  "type": "Feature",
  "properties": {
    "addr:full":"Alliance House, 20 Fawcett Street Sunderland Tyne and Wear SR1 1RZ",
    "addr:housenumber":"20",
    "addr:postcode":"sr1 1rz",
    "addr:street":"Fawcett Street",
    "iso:country":"GB",
    "sg:address":"Alliance House, 20 Fawcett Street",
    "sg:city":"Sunderland",
    "sg:classifiers":[
        {
            "category":"Professional",
            "subcategory":"Lawyer & Legal Services",
            "type":"Services"
        }
    ],
    "sg:phone":"+44 191 567 0101",
    "sg:postcode":"SR1 1RZ",
    "sg:province":"Tyne and Wear",
    "sg:tags":[
        "conveyancing"
    ],
    "wof:name":"Hedleys & Co.",
    "wof:placetype":"venue"
},
  "geometry": {"coordinates":[-1.3815870285,54.9055137634],"type":"Point"}
}