{
  "type": "Feature",
  "properties": {
    "iso:country":"GB",
    "sg:address":"301 Stockport Road, Marple",
    "sg:city":"Stockport",
    "sg:classifiers":[
        {
            "category":"Health Services",
            "subcategory":"Dentist",
            "type":"Services"
        }
    ],
    "sg:phone":"+44 161 427 2255",
    "sg:postcode":"SK6 6ES",
    "sg:province":"Cheshire",
    "wof:name":"Rosehill Dental Practice",
    "wof:placetype":"venue"
},
  "geometry": {"coordinates":[-2.083203,53.396271],"type":"Point"}
}