{
  "type": "Feature",
  "properties": {
    "addr:full":"2 Sheridan Road London Greater London SW19 3HR",
    "addr:housenumber":"2",
    "addr:postcode":"sw19 3hr",
    "addr:street":"Sheridan Road",
    "iso:country":"GB",
    "sg:address":"2 Sheridan Road",
    "sg:city":"London",
    "sg:classifiers":[
        {
            "category":"Professional",
            "subcategory":"Accounting & Tax Preparation",
            "type":"Services"
        }
    ],
    "sg:postcode":"SW19 3HR",
    "sg:province":"Greater London",
    "sg:tags":[
        "accountant"
    ],
    "wof:name":"George Bate & Co.",
    "wof:placetype":"venue"
},
  "geometry": {"coordinates":[-0.2034880072,51.4118003845],"type":"Point"}
}