{
  "type": "Feature",
  "properties": {
    "iso:country":"GB",
    "sg:address":"4-6 Riverside, Milngavie",
    "sg:city":"Glasgow",
    "sg:classifiers":[
        {
            "category":"Autos & Motor Vehicles",
            "subcategory":"Auto Supplies",
            "type":"Retail Goods"
        }
    ],
    "sg:phone":"+44 141 956 3055",
    "sg:postcode":"G62 6PQ",
    "sg:province":"East Dunbartonshire",
    "sg:tags":[
        "towing",
        "eqpt",
        "trailer"
    ],
    "wof:name":"Indespension Ltd.",
    "wof:placetype":"venue"
},
  "geometry": {"coordinates":[-4.318714,55.942081],"type":"Point"}
}