{
  "type": "Feature",
  "properties": {
    "addr:full":"19 Oxford Street Kidderminster Staffordshire DY10 1AU",
    "addr:housenumber":"19",
    "addr:postcode":"dy10 1au",
    "addr:street":"Oxford Street",
    "iso:country":"GB",
    "sg:address":"19 Oxford Street",
    "sg:city":"Kidderminster",
    "sg:classifiers":[
        {
            "category":"Real Estate",
            "subcategory":"Real Estate Agent",
            "type":"Services"
        }
    ],
    "sg:phone":"+44 1562 742442",
    "sg:postcode":"DY10 1AU",
    "sg:province":"Staffordshire",
    "sg:website":"http://www.dixons.co.uk",
    "wof:name":"Dixons Estate Agents Ltd",
    "wof:placetype":"venue"
},
  "geometry": {"coordinates":[-2.244786,52.385666],"type":"Point"}
}