{
  "type": "Feature",
  "properties": {
    "iso:country":"GB",
    "sg:address":"49 Dundalk Lane",
    "sg:city":"Walsall",
    "sg:classifiers":[
        {
            "category":"Professional",
            "subcategory":"Accounting & Tax Preparation",
            "type":"Services"
        }
    ],
    "sg:phone":"+44 1922 413552",
    "sg:postcode":"WS6 7AZ",
    "sg:province":"Staffordshire",
    "sg:tags":[
        "accountant"
    ],
    "wof:name":"Hayward & Co",
    "wof:placetype":"venue"
},
  "geometry": {"coordinates":[-2.0370299816,52.656791687],"type":"Point"}
}