{
  "type": "Feature",
  "properties": {
    "iso:country":"GB",
    "sg:address":"Nymet Barton, Nymet Rowland",
    "sg:city":"Crediton",
    "sg:classifiers":[
        {
            "category":"Farming",
            "subcategory":"Farm",
            "type":"Manufacturing & Wholesale Goods"
        }
    ],
    "sg:phone":"+44 1363 83255",
    "sg:postcode":"EX17 6AP",
    "sg:province":"Devon",
    "sg:tags":[
        "mixed",
        "crop"
    ],
    "wof:name":"Dennis J Gough",
    "wof:placetype":"venue"
},
  "geometry": {"coordinates":[-3.830454,50.859653],"type":"Point"}
}