{
  "type": "Feature",
  "properties": {
    "addr:full":"205 Wandsworth High Street London Greater London SW18 4JE",
    "addr:housenumber":"205",
    "addr:postcode":"sw18 4je",
    "addr:street":"Wandsworth High Street",
    "iso:country":"GB",
    "sg:address":"205 Wandsworth High Street",
    "sg:city":"London",
    "sg:classifiers":[
        {
            "category":"Arena",
            "subcategory":"Sports Club",
            "type":"Entertainment"
        }
    ],
    "sg:phone":"+44 20 8874 1274",
    "sg:postcode":"SW18 4JE",
    "sg:province":"Greater London",
    "wof:name":"Fighting Fit Personal Training & Classes",
    "wof:placetype":"venue"
},
  "geometry": {"coordinates":[-0.197373,51.456978],"type":"Point"}
}