{
  "type": "Feature",
  "properties": {
    "iso:country":"GB",
    "sg:address":"228 Blackness Rd",
    "sg:city":"Dundee",
    "sg:classifiers":[
        {
            "category":"Building & Trades",
            "subcategory":"Construction",
            "type":"Services"
        }
    ],
    "sg:phone":"+44 1382 600300",
    "sg:postcode":"DD2 1RG",
    "sg:province":"Dundee City",
    "sg:tags":[
        "glazier"
    ],
    "wof:name":"City Glass",
    "wof:placetype":"venue"
},
  "geometry": {"coordinates":[-2.995685,56.460472],"type":"Point"}
}