{
  "type": "Feature",
  "properties": {
    "iso:country":"GB",
    "sg:address":"7a Long Rock Industrial Estate",
    "sg:city":"Penzance",
    "sg:classifiers":[
        {
            "category":"Retail",
            "subcategory":"Laundry & Dry Cleaning",
            "type":"Services"
        }
    ],
    "sg:postcode":"TR20 8HX",
    "sg:province":"Cornwall",
    "sg:tags":[
        "launderette"
    ],
    "wof:name":"N J & D I Dowrick",
    "wof:placetype":"venue"
},
  "geometry": {"coordinates":[-5.505128,50.12923],"type":"Point"}
}