{
  "type": "Feature",
  "properties": {
    "iso:country":"GB",
    "sg:address":"16 Hawkwood",
    "sg:city":"Maidstone",
    "sg:classifiers":[
        {
            "category":"Organizations",
            "subcategory":"Religious Organization",
            "type":"Services"
        }
    ],
    "sg:phone":"+44 1622 686351",
    "sg:postcode":"ME16 0JQ",
    "sg:province":"Kent",
    "sg:tags":[
        "organisation"
    ],
    "wof:name":"United Church Of God",
    "wof:placetype":"venue"
},
  "geometry": {"coordinates":[0.490964,51.278553],"type":"Point"}
}