{
  "type": "Feature",
  "properties": {
    "addr:full":"80 Oldbury Orchard Gloucester Gloucestershire GL3 2NY",
    "addr:housenumber":"80",
    "addr:postcode":"gl3 2ny",
    "addr:street":"Oldbury Orchard",
    "iso:country":"GB",
    "sg:address":"80 Oldbury Orchard",
    "sg:city":"Gloucester",
    "sg:classifiers":[
        {
            "category":"Manufacturing",
            "subcategory":"Petroleum Products",
            "type":"Manufacturing & Wholesale Goods"
        }
    ],
    "sg:phone":"+44 1452 856555",
    "sg:postcode":"GL3 2NY",
    "sg:province":"Gloucestershire",
    "sg:tags":[
        "double",
        "glazing"
    ],
    "wof:name":"Churchdown Conservatories",
    "wof:placetype":"venue"
},
  "geometry": {"coordinates":[-2.1647360325,51.874961853],"type":"Point"}
}