{
  "type": "Feature",
  "properties": {
    "addr:full":"32 St Peters Avenue Arlesey Bedfordshire SG15 6UR",
    "addr:housenumber":"32",
    "addr:postcode":"sg15 6ur",
    "addr:street":"St Peters Avenue",
    "iso:country":"GB",
    "sg:address":"32 St Peters Avenue",
    "sg:city":"Arlesey",
    "sg:classifiers":[
        {
            "category":"Sports & Exercise",
            "subcategory":"Sports Center",
            "type":"Entertainment"
        }
    ],
    "sg:postcode":"SG15 6UR",
    "sg:province":"Bedfordshire",
    "sg:tags":[
        "game",
        "combat"
    ],
    "wof:name":"The Big Red One Ltd.",
    "wof:placetype":"venue"
},
  "geometry": {"coordinates":[-0.2608999908,52.0224647522],"type":"Point"}
}