{
  "type": "Feature",
  "properties": {
    "iso:country":"GB",
    "sg:address":"36-38 Arundel Street",
    "sg:city":"Portsmouth",
    "sg:classifiers":[
        {
            "category":"Banks & Credit Unions",
            "subcategory":"Bank",
            "type":"Services"
        },
        {
            "category":"Banks & Credit Unions",
            "subcategory":"Financial Services",
            "type":"Services"
        }
    ],
    "sg:phone":"+44 23 9275 2924",
    "sg:postcode":"PO1 1RT",
    "sg:province":"Hampshire",
    "sg:tags":[
        "building",
        "society",
        "institution"
    ],
    "wof:name":"Bristol & West Plc",
    "wof:placetype":"venue"
},
  "geometry": {"coordinates":[-1.088875,50.799717],"type":"Point"}
}