{
  "type": "Feature",
  "properties": {
    "addr:full":"11a Fulton St (off Sunbridge Rd) Bradford West Yorkshire BD1 2LZ",
    "addr:housenumber":"11a",
    "addr:postcode":"bd1 2lz",
    "addr:street":"Fulton St Off Sunbridge Rd",
    "iso:country":"GB",
    "sg:address":"11a Fulton St (off Sunbridge Rd)",
    "sg:city":"Bradford",
    "sg:classifiers":[
        {
            "category":"Shopping",
            "subcategory":"Computers & Home Electronics",
            "type":"Retail Goods"
        }
    ],
    "sg:postcode":"BD1 2LZ",
    "sg:province":"West Yorkshire",
    "sg:tags":[
        "sound",
        "equipment"
    ],
    "wof:name":"Sound Reinforcement Society",
    "wof:placetype":"venue"
},
  "geometry": {"coordinates":[-1.75868,53.794487],"type":"Point"}
}