{
  "type": "Feature",
  "properties": {
    "iso:country":"GB",
    "sg:address":"136 Blackburn Road",
    "sg:city":"Bolton",
    "sg:classifiers":[
        {
            "category":"Autos & Motor Vehicles",
            "subcategory":"Motorcycle Sales",
            "type":"Retail Goods"
        },
        {
            "category":"Retail",
            "subcategory":"Auto Repair",
            "type":"Services"
        }
    ],
    "sg:phone":"+44 1204 532183",
    "sg:postcode":"BL1 8DW",
    "sg:province":"Lancashire",
    "sg:tags":[
        "modification",
        "garage",
        "scooter",
        "cycle"
    ],
    "wof:name":"Valley Scooters",
    "wof:placetype":"venue"
},
  "geometry": {"coordinates":[-2.430592,53.590187],"type":"Point"}
}