{
  "type": "Feature",
  "properties": {
    "addr:full":"Currock Road Carlisle Cumbria CA2 4AS",
    "addr:postcode":"ca2 4as",
    "addr:street":"Currock Road",
    "iso:country":"GB",
    "sg:address":"Currock Road",
    "sg:city":"Carlisle",
    "sg:classifiers":[
        {
            "category":"Retail",
            "subcategory":"Auto Repair",
            "type":"Services"
        }
    ],
    "sg:phone":"+44 1228 542158",
    "sg:postcode":"CA2 4AS",
    "sg:province":"Cumbria",
    "sg:tags":[
        "modification",
        "garage",
        "related"
    ],
    "wof:name":"Bryan Fell",
    "wof:placetype":"venue"
},
  "geometry": {"coordinates":[-2.9315340519,54.8830299377],"type":"Point"}
}