{
  "type": "Feature",
  "properties": {
    "addr:full":"5 Egerton Crescent, Withington Manchester Greater Manchester M20 4PN",
    "addr:housenumber":"5",
    "addr:postcode":"m20 4pn",
    "addr:street":"Egerton Crescent",
    "iso:country":"GB",
    "sg:address":"5 Egerton Crescent, Withington",
    "sg:city":"Manchester",
    "sg:classifiers":[
        {
            "category":"Professional",
            "subcategory":"Management & Consulting",
            "type":"Services"
        }
    ],
    "sg:postcode":"M20 4PN",
    "sg:province":"Greater Manchester",
    "sg:tags":[
        "consultant",
        "business"
    ],
    "wof:name":"Caduceus Consultancy Services Ltd",
    "wof:placetype":"venue"
},
  "geometry": {"coordinates":[-2.228006,53.434093],"type":"Point"}
}