{
  "type": "Feature",
  "properties": {
    "addr:full":"8 Stryt Isa Wrexham Wrexham LL14 2NP",
    "addr:housenumber":"8",
    "addr:postcode":"ll14 2np",
    "addr:street":"Stryt Isa",
    "iso:country":"GB",
    "sg:address":"8 Stryt Isa",
    "sg:city":"Wrexham",
    "sg:classifiers":[
        {
            "category":"Food & Beverages",
            "subcategory":"Groceries & Convenience Stores",
            "type":"Retail Goods"
        }
    ],
    "sg:phone":"+44 1978 840169",
    "sg:postcode":"LL14 2NP",
    "sg:province":"Wrexham",
    "wof:name":"Siop-y-Pentre",
    "wof:placetype":"venue"
},
  "geometry": {"coordinates":[-3.058349,53.00824],"type":"Point"}
}