{
  "type": "Feature",
  "properties": {
    "addr:full":"Dandys Farm, Shustoke Birmingham Warwickshire B46 2RX",
    "addr:postcode":"b46 2rx",
    "iso:country":"GB",
    "sg:address":"Dandys Farm, Shustoke",
    "sg:city":"Birmingham",
    "sg:classifiers":[
        {
            "category":"Banks & Credit Unions",
            "subcategory":"Investment Brokerage",
            "type":"Services"
        }
    ],
    "sg:postcode":"B46 2RX",
    "sg:province":"Warwickshire",
    "sg:tags":[
        "contractor"
    ],
    "wof:name":"A & J Nightingale",
    "wof:placetype":"venue"
},
  "geometry": {"coordinates":[-1.665871,52.51527],"type":"Point"}
}