{
  "type": "Feature",
  "properties": {
    "addr:full":"35 Oakey Field Road, Thurston Bury St Edmunds Suffolk IP31 3RX",
    "addr:housenumber":"35",
    "addr:postcode":"ip31 3rx",
    "addr:street":"Oakey Field Road",
    "iso:country":"GB",
    "sg:address":"35 Oakey Field Road, Thurston",
    "sg:city":"Bury St Edmunds",
    "sg:classifiers":[
        {
            "category":"Building & Trades",
            "subcategory":"Construction",
            "type":"Services"
        }
    ],
    "sg:postcode":"IP31 3RX",
    "sg:province":"Suffolk",
    "sg:tags":[
        "roofing"
    ],
    "wof:name":"M W Browne Flat Roofing",
    "wof:placetype":"venue"
},
  "geometry": {"coordinates":[0.818973,52.251183],"type":"Point"}
}