{
  "type": "Feature",
  "properties": {
    "addr:full":"Rear Of Shop High Wycombe Buckinghamshire HP12 3JQ",
    "addr:postcode":"hp12 3jq",
    "addr:street":"High",
    "iso:country":"GB",
    "sg:address":"Rear Of Shop",
    "sg:city":"High Wycombe",
    "sg:classifiers":[
        {
            "category":"Military Area",
            "subcategory":"Air Force Base",
            "type":"Public Place"
        }
    ],
    "sg:phone":"+44 1494 461111",
    "sg:postcode":"HP12 3JQ",
    "sg:province":"Buckinghamshire",
    "sg:tags":[
        "taxi",
        "hire",
        "private"
    ],
    "wof:name":"Tiger Taxis",
    "wof:placetype":"venue"
},
  "geometry": {"coordinates":[-0.7796800137,51.6287498474],"type":"Point"}
}