{
  "type": "Feature",
  "properties": {
    "addr:full":"40 Oxford Rd High Wycombe Buckinghamshire HP11 2EE",
    "addr:housenumber":"40",
    "addr:postcode":"hp11 2ee",
    "addr:street":"Oxford Rd",
    "iso:country":"GB",
    "sg:address":"40 Oxford Rd",
    "sg:city":"High Wycombe",
    "sg:classifiers":[
        {
            "category":"Professional",
            "subcategory":"Computer Services",
            "type":"Services"
        }
    ],
    "sg:phone":"+44 1494 538200",
    "sg:postcode":"HP11 2EE",
    "sg:province":"Buckinghamshire",
    "sg:tags":[
        "consultant"
    ],
    "wof:name":"Pontis Consulting",
    "wof:placetype":"venue"
},
  "geometry": {"coordinates":[-0.7563319802,51.6320915222],"type":"Point"}
}