{
  "type": "Feature",
  "properties": {
    "addr:full":"Ellis Road Mitcham Greater London CR4 4HX",
    "addr:postcode":"cr4 4hx",
    "addr:street":"Ellis Road",
    "iso:country":"GB",
    "sg:address":"Ellis Road",
    "sg:city":"Mitcham",
    "sg:classifiers":[
        {
            "category":"Building & Trades",
            "subcategory":"Equipment Rental",
            "type":"Services"
        }
    ],
    "sg:postcode":"CR4 4HX",
    "sg:province":"Greater London",
    "sg:tags":[
        "plant",
        "machinery"
    ],
    "wof:name":"Wates P F I Investments (Q E D) Ltd.",
    "wof:placetype":"venue"
},
  "geometry": {"coordinates":[-0.161454007,51.388584137],"type":"Point"}
}