{
  "type": "Feature",
  "properties": {
    "addr:full":"18 Western Road, Churchill Square Brighton East Sussex BN1 2EA",
    "addr:housenumber":"18",
    "addr:postcode":"bn1 2ea",
    "addr:street":"Western Road",
    "iso:country":"GB",
    "sg:address":"18 Western Road, Churchill Square",
    "sg:city":"Brighton",
    "sg:classifiers":[
        {
            "category":"Shopping",
            "subcategory":"Clothing, Apparel, & Fashions",
            "type":"Retail Goods"
        }
    ],
    "sg:phone":"+44 1273 738898",
    "sg:postcode":"BN1 2EA",
    "sg:province":"East Sussex",
    "sg:tags":[
        "ladieswear"
    ],
    "wof:name":"Jeffrey Rogers Ltd.",
    "wof:placetype":"venue"
},
  "geometry": {"coordinates":[-0.144918,50.823662],"type":"Point"}
}