{
  "type": "Feature",
  "properties": {
    "addr:full":"1 Exeter Street Norwich Norfolk NR2 4QB",
    "addr:housenumber":"1",
    "addr:postcode":"nr2 4qb",
    "addr:street":"Exeter Street",
    "iso:country":"GB",
    "sg:address":"1 Exeter Street",
    "sg:city":"Norwich",
    "sg:classifiers":[
        {
            "category":"Conference Center",
            "type":"Public Place"
        }
    ],
    "sg:phone":"+44 1603 764000",
    "sg:postcode":"NR2 4QB",
    "sg:province":"Norfolk",
    "sg:tags":[
        "business",
        "centre"
    ],
    "wof:name":"Ferndale Business Centre",
    "wof:placetype":"venue"
},
  "geometry": {"coordinates":[1.2806249857,52.6335716248],"type":"Point"}
}