{
  "type": "Feature",
  "properties": {
    "addr:full":"38 Ashwood Drive, Gildersome Leeds West Yorkshire LS27 7AG",
    "addr:housenumber":"38",
    "addr:postcode":"ls27 7ag",
    "addr:street":"Ashwood Drive",
    "iso:country":"GB",
    "sg:address":"38 Ashwood Drive, Gildersome",
    "sg:city":"Leeds",
    "sg:classifiers":[
        {
            "category":"Building & Trades",
            "subcategory":"Construction",
            "type":"Services"
        }
    ],
    "sg:phone":"+44 113 252 2153",
    "sg:postcode":"LS27 7AG",
    "sg:province":"West Yorkshire",
    "sg:tags":[
        "builder"
    ],
    "wof:name":"B & D Construction",
    "wof:placetype":"venue"
},
  "geometry": {"coordinates":[-1.6382659674,53.759727478],"type":"Point"}
}