{
  "type": "Feature",
  "properties": {
    "iso:country":"GB",
    "sg:address":"Alcester House, 2-4 Gas House Lane",
    "sg:city":"Alcester",
    "sg:classifiers":[
        {
            "category":"Shopping",
            "subcategory":"Stationery & Office Supplies",
            "type":"Retail Goods"
        }
    ],
    "sg:phone":"+44 1789 762266",
    "sg:postcode":"B49 5QP",
    "sg:province":"Warwickshire",
    "sg:tags":[
        "equipment",
        "furniture"
    ],
    "wof:name":"Abc Solutions (U K) Ltd.",
    "wof:placetype":"venue"
},
  "geometry": {"coordinates":[-1.8697500229,52.2138557434],"type":"Point"}
}