{
  "type": "Feature",
  "properties": {
    "addr:full":"11 Holton Hill Brighton East Sussex BN2 6RQ",
    "addr:housenumber":"11",
    "addr:postcode":"bn2 6rq",
    "addr:street":"Holton Hill",
    "iso:country":"GB",
    "sg:address":"11 Holton Hill",
    "sg:city":"Brighton",
    "sg:classifiers":[
        {
            "category":"Building & Trades",
            "subcategory":"Plumbing",
            "type":"Services"
        }
    ],
    "sg:postcode":"BN2 6RQ",
    "sg:province":"East Sussex",
    "sg:tags":[
        "heating"
    ],
    "wof:name":"Geoffrey C Wells",
    "wof:placetype":"venue"
},
  "geometry": {"coordinates":[-0.067143999,50.8303413391],"type":"Point"}
}