{
  "type": "Feature",
  "properties": {
    "addr:full":"17 Pudding Lane Maidstone Kent ME14 1PA",
    "addr:housenumber":"17",
    "addr:postcode":"me14 1pa",
    "addr:street":"Pudding Lane",
    "iso:country":"GB",
    "sg:address":"17 Pudding Lane",
    "sg:city":"Maidstone",
    "sg:classifiers":[
        {
            "category":"Professional",
            "subcategory":"Employment Agencies",
            "type":"Services"
        }
    ],
    "sg:phone":"+44 1622 755002",
    "sg:postcode":"ME14 1PA",
    "sg:province":"Kent",
    "sg:tags":[
        "consultant"
    ],
    "wof:name":"New Appointments Group",
    "wof:placetype":"venue"
},
  "geometry": {"coordinates":[0.5203859806,51.273891449],"type":"Point"}
}