{
  "type": "Feature",
  "properties": {
    "addr:full":"Temperance House Kineton Road, Radway Warwick Warwickshire CV35 0UQ",
    "addr:postcode":"cv35 0uq",
    "addr:street":"Kineton Road Radway",
    "iso:country":"GB",
    "sg:address":"Temperance House Kineton Road, Radway",
    "sg:city":"Warwick",
    "sg:classifiers":[
        {
            "category":"Professional",
            "subcategory":"Accounting & Tax Preparation",
            "type":"Services"
        },
        {
            "category":"Professional",
            "subcategory":"Computer Services",
            "type":"Services"
        }
    ],
    "sg:phone":"+44 1295 670770",
    "sg:postcode":"CV35 0UQ",
    "sg:province":"Warwickshire",
    "sg:tags":[
        "accountant",
        "system",
        "software"
    ],
    "wof:name":"Userwyse Ltd.",
    "wof:placetype":"venue"
},
  "geometry": {"coordinates":[-1.470109,52.183529],"type":"Point"}
}