{
  "type": "Feature",
  "properties": {
    "iso:country":"GB",
    "sg:address":"1-2 Portview Road",
    "sg:city":"Bristol",
    "sg:classifiers":[
        {
            "category":"Professional",
            "type":"Services"
        }
    ],
    "sg:phone":"+44 1454 203680",
    "sg:postcode":"BS11 9LQ",
    "sg:province":"City of Bristol",
    "sg:tags":[
        "shopfitters"
    ],
    "wof:name":"V H Leadbetter Ltd.",
    "wof:placetype":"venue"
},
  "geometry": {"coordinates":[-2.692321,51.494617],"type":"Point"}
}