{
  "type": "Feature",
  "properties": {
    "iso:country":"GB",
    "sg:address":"14 Eldon Way Industrial Estate",
    "sg:city":"Hockley",
    "sg:classifiers":[
        {
            "category":"Shopping",
            "subcategory":"Computers & Home Electronics",
            "type":"Retail Goods"
        }
    ],
    "sg:phone":"+44 1702 207854",
    "sg:postcode":"SS5 4AD",
    "sg:province":"Essex",
    "wof:name":"Manderine Furniture Ltd.",
    "wof:placetype":"venue"
},
  "geometry": {"coordinates":[0.65642,51.60281],"type":"Point"}
}