{
  "type": "Feature",
  "properties": {
    "iso:country":"GB",
    "sg:address":"Terminal 4, Air Side",
    "sg:city":"Hounslow",
    "sg:classifiers":[
        {
            "category":"Shopping",
            "subcategory":"Music",
            "type":"Retail Goods"
        }
    ],
    "sg:phone":"+44 20 8745 0692",
    "sg:postcode":"TW6 3XA",
    "sg:province":"Greater London",
    "sg:tags":[
        "record",
        "tape",
        "cd"
    ],
    "wof:name":"H M V",
    "wof:placetype":"venue"
},
  "geometry": {"coordinates":[-0.44772,51.459728],"type":"Point"}
}