{
  "type": "Feature",
  "properties": {
    "addr:full":"49a High St Watford Hertfordshire WD2 1BD",
    "addr:housenumber":"49a",
    "addr:postcode":"wd2 1bd",
    "addr:street":"High St",
    "iso:country":"GB",
    "sg:address":"49a High St",
    "sg:city":"Watford",
    "sg:classifiers":[
        {
            "category":"Professional",
            "subcategory":"Engineering",
            "type":"Services"
        }
    ],
    "sg:phone":"+44 20 8421 8670",
    "sg:postcode":"WD2 1BD",
    "sg:province":"Hertfordshire",
    "sg:tags":[
        "engineer",
        "structural"
    ],
    "wof:name":"Riley Larkin Partnership The",
    "wof:placetype":"venue"
},
  "geometry": {"coordinates":[-0.397047,51.656288],"type":"Point"}
}