{
  "type": "Feature",
  "properties": {
    "addr:full":"Hunts Hill, Normandy Guildford Surrey GU3 2AH",
    "addr:postcode":"gu3 2ah",
    "addr:street":"Hunts Hill Normandy",
    "iso:country":"GB",
    "sg:address":"Hunts Hill, Normandy",
    "sg:city":"Guildford",
    "sg:classifiers":[
        {
            "category":"Arena",
            "subcategory":"Sports Club",
            "type":"Entertainment"
        }
    ],
    "sg:phone":"+44 1483 811519",
    "sg:postcode":"GU3 2AH",
    "sg:province":"Surrey",
    "wof:name":"Normandy Cricket Club",
    "wof:placetype":"venue"
},
  "geometry": {"coordinates":[-0.6669890285,51.2567558289],"type":"Point"}
}