{
  "type": "Feature",
  "properties": {
    "addr:full":"171b Railway Arches, Midland Rd London Greater London E10 6JT",
    "addr:housenumber":"171b",
    "addr:postcode":"e10 6jt",
    "addr:street":"Railway Arches Midland Rd",
    "iso:country":"GB",
    "sg:address":"171b Railway Arches, Midland Rd",
    "sg:city":"London",
    "sg:classifiers":[
        {
            "category":"Retail",
            "subcategory":"Auto Repair",
            "type":"Services"
        }
    ],
    "sg:postcode":"E10 6JT",
    "sg:province":"Greater London",
    "sg:tags":[
        "modification",
        "garage"
    ],
    "wof:name":"Singh,Bobby,",
    "wof:placetype":"venue"
},
  "geometry": {"coordinates":[-0.00727,51.56958],"type":"Point"}
}