{
  "type": "Feature",
  "properties": {
    "iso:country":"GB",
    "sg:address":"Joanville, The Common",
    "sg:city":"West Drayton",
    "sg:classifiers":[
        {
            "category":"Travel",
            "subcategory":"Travel Agent",
            "type":"Entertainment"
        }
    ],
    "sg:phone":"+44 1895 446169",
    "sg:postcode":"UB7 7HQ",
    "sg:province":"Greater London",
    "wof:name":"Future Travel",
    "wof:placetype":"venue"
},
  "geometry": {"coordinates":[-0.47399,51.509117],"type":"Point"}
}