{
  "type": "Feature",
  "properties": {
    "iso:country":"GB",
    "sg:address":"Unit 2a, Saxon Business Park, Hanbury Road",
    "sg:city":"Bromsgrove",
    "sg:classifiers":[
        {
            "category":"Shopping",
            "subcategory":"Crafts & Fabrics",
            "type":"Retail Goods"
        },
        {
            "category":"Manufacturing",
            "subcategory":"Retail Goods",
            "type":"Manufacturing & Wholesale Goods"
        }
    ],
    "sg:phone":"+44 1527 837001",
    "sg:postcode":"B60 4AD",
    "sg:province":"Worcestershire",
    "sg:tags":[
        "brush",
        "manufacturer"
    ],
    "wof:name":"Bee Gee Brushes Ltd",
    "wof:placetype":"venue"
},
  "geometry": {"coordinates":[-2.055703,52.2729],"type":"Point"}
}