{
  "type": "Feature",
  "properties": {
    "addr:full":"Maple Estate, Wentworth Road Barnsley South Yorkshire S75 6DT",
    "addr:postcode":"s75 6dt",
    "addr:street":"Maple;Wentworth Road;Yorkshire",
    "iso:country":"GB",
    "sg:address":"Maple Estate, Wentworth Road",
    "sg:city":"Barnsley",
    "sg:classifiers":[
        {
            "category":"Building & Trades",
            "subcategory":"Construction",
            "type":"Services"
        }
    ],
    "sg:phone":"+44 1226 383460",
    "sg:postcode":"S75 6DT",
    "sg:province":"South Yorkshire",
    "sg:tags":[
        "roofing"
    ],
    "wof:name":"D J Allen Roofing Ltd.",
    "wof:placetype":"venue"
},
  "geometry": {"coordinates":[-1.510823,53.588493],"type":"Point"}
}