{
  "type": "Feature",
  "properties": {
    "addr:full":"1a Ravenscourt Square Hammersmith Greater London W6 0TW",
    "addr:housenumber":"1a",
    "addr:postcode":"w6 0tw",
    "addr:street":"Ravenscourt Square",
    "iso:country":"GB",
    "sg:address":"1a Ravenscourt Square",
    "sg:city":"Hammersmith",
    "sg:classifiers":[
        {
            "category":"Retail",
            "subcategory":"Auto Repair",
            "type":"Services"
        }
    ],
    "sg:phone":"+44 20 8748 3344",
    "sg:postcode":"W6 0TW",
    "sg:province":"Greater London",
    "sg:tags":[
        "body",
        "car"
    ],
    "wof:name":"Aird Body Craft",
    "wof:placetype":"venue"
},
  "geometry": {"coordinates":[-0.239402,51.493526],"type":"Point"}
}