{
  "type": "Feature",
  "properties": {
    "addr:full":"150 Heyes Street, Anfield Liverpool Merseyside L5 6SQ",
    "addr:housenumber":"150",
    "addr:postcode":"l5 6sq",
    "addr:street":"Heyes Street",
    "iso:country":"GB",
    "sg:address":"150 Heyes Street, Anfield",
    "sg:city":"Liverpool",
    "sg:classifiers":[
        {
            "category":"Manufacturing",
            "subcategory":"Building Materials",
            "type":"Manufacturing & Wholesale Goods"
        }
    ],
    "sg:postcode":"L5 6SQ",
    "sg:province":"Merseyside",
    "sg:tags":[
        "merchant",
        "builder"
    ],
    "wof:name":"Liverpool Brick & Block",
    "wof:placetype":"venue"
},
  "geometry": {"coordinates":[-2.960149,53.425739],"type":"Point"}
}