{
  "type": "Feature",
  "properties": {
    "addr:full":"19 Blackhouse Pl Ayr South Ayrshire KA8 0HP",
    "addr:housenumber":"19",
    "addr:postcode":"ka8 0hp",
    "addr:street":"Blackhouse Pl",
    "iso:country":"GB",
    "sg:address":"19 Blackhouse Pl",
    "sg:city":"Ayr",
    "sg:classifiers":[
        {
            "category":"Health Services",
            "subcategory":"Health Practitioner",
            "type":"Services"
        }
    ],
    "sg:phone":"+44 1292 264960",
    "sg:postcode":"KA8 0HP",
    "sg:province":"South Ayrshire",
    "sg:tags":[
        "hypnotherapists"
    ],
    "wof:name":"Ian Hodge C.H.P. F.A.S.C. A.M.I.H. N.H.R.P .",
    "wof:placetype":"venue"
},
  "geometry": {"coordinates":[-4.60631,55.461369],"type":"Point"}
}