{
  "type": "Feature",
  "properties": {
    "addr:full":"R M C House, Whitehall Road Colchester Essex CO2 8HD",
    "addr:postcode":"co2 8hd",
    "addr:street":"M;Whitehall Road Colchester",
    "iso:country":"GB",
    "sg:address":"R M C House, Whitehall Road",
    "sg:city":"Colchester",
    "sg:classifiers":[
        {
            "category":"Home & Garden",
            "subcategory":"Building Materials",
            "type":"Retail Goods"
        }
    ],
    "sg:phone":"+44 1206 862222",
    "sg:postcode":"CO2 8HD",
    "sg:province":"Essex",
    "sg:tags":[
        "ready",
        "mixed",
        "concrete"
    ],
    "wof:name":"R M C Readymix East Anglia Ltd.",
    "wof:placetype":"venue"
},
  "geometry": {"coordinates":[0.931351,51.876659],"type":"Point"}
}