{
  "type": "Feature",
  "properties": {
    "iso:country":"GB",
    "sg:address":"23 Calder Rd",
    "sg:city":"Lincoln",
    "sg:classifiers":[
        {
            "category":"Professional",
            "subcategory":"Detective & Security Services",
            "type":"Services"
        }
    ],
    "sg:phone":"+44 1522 820687",
    "sg:postcode":"LN5 8SA",
    "sg:province":"Lincolnshire",
    "sg:tags":[
        "agency"
    ],
    "wof:name":"The Espy Bureau",
    "wof:placetype":"venue"
},
  "geometry": {"coordinates":[-0.5543889999,53.1964111328],"type":"Point"}
}