{
  "type": "Feature",
  "properties": {
    "addr:full":"25 New Rd Kidderminster Staffordshire DY10 1AF",
    "addr:housenumber":"25",
    "addr:postcode":"dy10 1af",
    "addr:street":"New Rd",
    "iso:country":"GB",
    "sg:address":"25 New Rd",
    "sg:city":"Kidderminster",
    "sg:classifiers":[
        {
            "category":"Shopping",
            "subcategory":"Department Store",
            "type":"Retail Goods"
        }
    ],
    "sg:postcode":"DY10 1AF",
    "sg:province":"Staffordshire",
    "wof:name":"Grove,Brian,",
    "wof:placetype":"venue"
},
  "geometry": {"coordinates":[-2.2478089333,52.3845176697],"type":"Point"}
}