{
  "type": "Feature",
  "properties": {
    "iso:country":"GB",
    "sg:address":"38a Station Road, Myrtle Lane",
    "sg:city":"Billingshurst",
    "sg:classifiers":[
        {
            "category":"Personal",
            "subcategory":"Beauty Salon",
            "type":"Services"
        }
    ],
    "sg:postcode":"RH14 9SE",
    "sg:province":"West Sussex",
    "wof:name":"Chrisessence@ the Skin Care Centre",
    "wof:placetype":"venue"
},
  "geometry": {"coordinates":[-0.450549,51.015903],"type":"Point"}
}