{
  "type": "Feature",
  "properties": {
    "iso:country":"GB",
    "sg:address":"Barritshayes Farm",
    "sg:city":"Colyton",
    "sg:classifiers":[
        {
            "category":"Travel",
            "subcategory":"Hotels & Motels",
            "type":"Entertainment"
        }
    ],
    "sg:postcode":"EX24 6DU",
    "sg:province":"Devon",
    "wof:name":"Barritshayes Farm",
    "wof:placetype":"venue"
},
  "geometry": {"coordinates":[-3.070244,50.740337],"type":"Point"}
}