{
  "type": "Feature",
  "properties": {
    "addr:full":"7 St Stephens Street Bristol City of Bristol BS1 1EE",
    "addr:housenumber":"7",
    "addr:postcode":"bs1 1ee",
    "addr:street":"St Stephens Street",
    "iso:country":"GB",
    "sg:address":"7 St Stephens Street",
    "sg:city":"Bristol",
    "sg:classifiers":[
        {
            "category":"Farming",
            "subcategory":"Poultry Farm",
            "type":"Manufacturing & Wholesale Goods"
        }
    ],
    "sg:phone":"+44 117 922 0755",
    "sg:postcode":"BS1 1EE",
    "sg:province":"City of Bristol",
    "sg:tags":[
        "related"
    ],
    "wof:name":"Triple F (U K) Ltd.",
    "wof:placetype":"venue"
},
  "geometry": {"coordinates":[-2.595545,51.454617],"type":"Point"}
}