{
  "type": "Feature",
  "properties": {
    "iso:country":"GB",
    "sg:address":"Empire Business Centre, Shay Lane",
    "sg:city":"Halifax",
    "sg:classifiers":[
        {
            "category":"Professional",
            "subcategory":"Employment Agencies",
            "type":"Services"
        }
    ],
    "sg:phone":"+44 1422 886608",
    "sg:postcode":"HX3 6SG",
    "sg:province":"West Yorkshire",
    "sg:tags":[
        "introduction"
    ],
    "wof:name":"White Rose Singles Directory",
    "wof:placetype":"venue"
},
  "geometry": {"coordinates":[-1.8778500557,53.7486381531],"type":"Point"}
}