{
  "type": "Feature",
  "properties": {
    "addr:full":"41 Easton Sq Portland Dorset DT5 1BY",
    "addr:housenumber":"41",
    "addr:postcode":"dt5 1by",
    "addr:street":"Easton Sq",
    "iso:country":"GB",
    "sg:address":"41 Easton Sq",
    "sg:city":"Portland",
    "sg:classifiers":[
        {
            "category":"Recreation",
            "subcategory":"Dog Park",
            "type":"Entertainment"
        }
    ],
    "sg:phone":"+44 1305 820546",
    "sg:postcode":"DT5 1BY",
    "sg:province":"Dorset",
    "wof:name":"Easton Pet Shop",
    "wof:placetype":"venue"
},
  "geometry": {"coordinates":[-2.435736,50.545273],"type":"Point"}
}