{
  "type": "Feature",
  "properties": {
    "iso:country":"GB",
    "sg:address":"68 Queen Street, Morley",
    "sg:city":"Leeds",
    "sg:classifiers":[
        {
            "category":"Shopping",
            "subcategory":"Pharmacy",
            "type":"Retail Goods"
        }
    ],
    "sg:phone":"+44 113 253 3143",
    "sg:postcode":"LS27 9BP",
    "sg:province":"West Yorkshire",
    "sg:tags":[
        "pharmacist",
        "dispensing",
        "chemist"
    ],
    "wof:name":"Crimonsea Ltd.",
    "wof:placetype":"venue"
},
  "geometry": {"coordinates":[-1.604728,53.743805],"type":"Point"}
}