{
  "type": "Feature",
  "properties": {
    "addr:full":"98 Greengate Lane, High Grn Sheffield South Yorkshire S35 3GS",
    "addr:housenumber":"98",
    "addr:postcode":"s35 3gs",
    "addr:street":"Greengate Lane High Grn",
    "iso:country":"GB",
    "sg:address":"98 Greengate Lane, High Grn",
    "sg:city":"Sheffield",
    "sg:classifiers":[
        {
            "category":"Bars & Pubs",
            "type":"Food & Drink"
        }
    ],
    "sg:phone":"+44 114 284 5093",
    "sg:postcode":"S35 3GS",
    "sg:province":"South Yorkshire",
    "sg:tags":[
        "pubs",
        "inn"
    ],
    "wof:name":"Pheonix Public House",
    "wof:placetype":"venue"
},
  "geometry": {"coordinates":[-1.4885179996,53.468082428],"type":"Point"}
}