{
  "type": "Feature",
  "properties": {
    "addr:full":"Diplomat Ho, Oakfield St Blandford Forum Dorset DT11 7EX",
    "addr:postcode":"dt11 7ex",
    "addr:street":"Oakfield St",
    "iso:country":"GB",
    "sg:address":"Diplomat Ho, Oakfield St",
    "sg:city":"Blandford Forum",
    "sg:classifiers":[
        {
            "category":"Health Services",
            "subcategory":"Dentist",
            "type":"Services"
        }
    ],
    "sg:phone":"+44 1258 456901",
    "sg:postcode":"DT11 7EX",
    "sg:province":"Dorset",
    "wof:name":"C D Barley",
    "wof:placetype":"venue"
},
  "geometry": {"coordinates":[-2.1588189602,50.8626441956],"type":"Point"}
}