{
  "type": "Feature",
  "properties": {
    "addr:full":"Goodnestone Road, Wingham Canterbury Kent CT3 1AR",
    "addr:postcode":"ct3 1ar",
    "addr:street":"Goodnestone Road",
    "iso:country":"GB",
    "sg:address":"Goodnestone Road, Wingham",
    "sg:city":"Canterbury",
    "sg:classifiers":[
        {
            "category":"Manufacturing",
            "subcategory":"Metals",
            "type":"Manufacturing & Wholesale Goods"
        }
    ],
    "sg:phone":"+44 1227 720886",
    "sg:postcode":"CT3 1AR",
    "sg:province":"Kent",
    "sg:tags":[
        "steel",
        "fabricator",
        "erectors"
    ],
    "wof:name":"S J L Fabrications",
    "wof:placetype":"venue"
},
  "geometry": {"coordinates":[1.227733016,51.2564086914],"type":"Point"}
}