{
  "type": "Feature",
  "properties": {
    "iso:country":"GB",
    "sg:address":"7 Holmdene Ave, Mill Hill",
    "sg:city":"London",
    "sg:classifiers":[
        {
            "category":"Organizations",
            "subcategory":"Membership Organization",
            "type":"Services"
        }
    ],
    "sg:postcode":"NW7 2LY",
    "sg:province":"Greater London",
    "sg:tags":[
        "club"
    ],
    "wof:name":"M & D (Sylvan Avenue) Management Co Ltd",
    "wof:placetype":"venue"
},
  "geometry": {"coordinates":[-0.236153,51.610516],"type":"Point"}
}