{
  "type": "Feature",
  "properties": {
    "iso:country":"GB",
    "sg:address":"93 London Road",
    "sg:city":"Morden",
    "sg:classifiers":[
        {
            "category":"Fast Food",
            "type":"Food & Drink"
        }
    ],
    "sg:phone":"+44 20 8648 3048",
    "sg:postcode":"SM4 5HP",
    "sg:province":"Surrey",
    "sg:tags":[
        "away",
        "meal",
        "outlet",
        "take"
    ],
    "wof:name":"Chopsticks & Bowl",
    "wof:placetype":"venue"
},
  "geometry": {"coordinates":[-0.1956370026,51.4008369446],"type":"Point"}
}