{
  "type": "Feature",
  "properties": {
    "addr:full":"C/o Bhanot Partnership, 1st Floor 126-128 Uxbridge Road London Greater London W13 8QS",
    "addr:housenumber":"1st floor 126-128",
    "addr:postcode":"w13 8qs",
    "addr:street":"C;Uxbridge Road",
    "iso:country":"GB",
    "sg:address":"C/o Bhanot Partnership, 1st Floor 126-128 Uxbridge Road",
    "sg:city":"London",
    "sg:classifiers":[
        {
            "category":"Building & Trades",
            "subcategory":"Construction",
            "type":"Services"
        }
    ],
    "sg:postcode":"W13 8QS",
    "sg:province":"Greater London",
    "sg:tags":[
        "builder"
    ],
    "wof:name":"Pyramid Building Co Ltd",
    "wof:placetype":"venue"
},
  "geometry": {"coordinates":[-0.3167400062,51.5112304688],"type":"Point"}
}