{
  "type": "Feature",
  "properties": {
    "iso:country":"GB",
    "sg:address":"16 Stockton Lane, Weeping Cross",
    "sg:city":"Stafford",
    "sg:classifiers":[
        {
            "category":"Health Services",
            "subcategory":"Dentist",
            "type":"Services"
        }
    ],
    "sg:postcode":"ST17 0JT",
    "sg:province":"Staffordshire",
    "sg:tags":[
        "technician",
        "dental"
    ],
    "wof:name":"Stafford Dental Laboratory",
    "wof:placetype":"venue"
},
  "geometry": {"coordinates":[-2.070771,52.789688],"type":"Point"}
}