{
  "type": "Feature",
  "properties": {
    "iso:country":"GB",
    "sg:address":"Orchard House, Leys Hill, Walford",
    "sg:city":"Ross-on-wye",
    "sg:classifiers":[
        {
            "category":"Home & Garden",
            "subcategory":"Garden Supply",
            "type":"Retail Goods"
        }
    ],
    "sg:phone":"+44 1600 890491",
    "sg:postcode":"HR9 5QU",
    "sg:province":"Gloucestershire",
    "sg:tags":[
        "bulb",
        "grower"
    ],
    "wof:name":"E J & T R Sainsbury",
    "wof:placetype":"venue"
},
  "geometry": {"coordinates":[-2.6013429165,51.8767280579],"type":"Point"}
}