{
  "type": "Feature",
  "properties": {
    "iso:country":"GB",
    "sg:address":"99 West Street, Portchester",
    "sg:city":"Fareham",
    "sg:classifiers":[
        {
            "category":"Shopping",
            "subcategory":"Stationery & Office Supplies",
            "type":"Retail Goods"
        }
    ],
    "sg:phone":"+44 23 9220 1566",
    "sg:postcode":"PO16 9UF",
    "sg:province":"Hampshire",
    "wof:name":"Hillcroft Enterprises",
    "wof:placetype":"venue"
},
  "geometry": {"coordinates":[-1.130037,50.846188],"type":"Point"}
}