{
  "type": "Feature",
  "properties": {
    "addr:full":"10 Grandison Avenue, Bishopsteignton Teignmouth Devon TQ14 9SP",
    "addr:housenumber":"10",
    "addr:postcode":"tq14 9sp",
    "addr:street":"Grandison Avenue",
    "iso:country":"GB",
    "sg:address":"10 Grandison Avenue, Bishopsteignton",
    "sg:city":"Teignmouth",
    "sg:classifiers":[
        {
            "category":"Building & Trades",
            "subcategory":"Construction",
            "type":"Services"
        }
    ],
    "sg:postcode":"TQ14 9SP",
    "sg:province":"Devon",
    "sg:tags":[
        "builder"
    ],
    "wof:name":"D  Coburn (Building Services) Ltd.",
    "wof:placetype":"venue"
},
  "geometry": {"coordinates":[-3.500104,50.548344],"type":"Point"}
}