{
  "type": "Feature",
  "properties": {
    "addr:full":"54 Hamilton Street Carluke South Lanarkshire ML8 4HA",
    "addr:housenumber":"54",
    "addr:postcode":"ml8 4ha",
    "addr:street":"Hamilton Street",
    "iso:country":"GB",
    "sg:address":"54 Hamilton Street",
    "sg:city":"Carluke",
    "sg:classifiers":[
        {
            "category":"Retail",
            "subcategory":"Veterinary Services",
            "type":"Services"
        }
    ],
    "sg:phone":"+44 1555 751560",
    "sg:postcode":"ML8 4HA",
    "sg:province":"South Lanarkshire",
    "sg:tags":[
        "surgeon"
    ],
    "wof:name":"W A Robb",
    "wof:placetype":"venue"
},
  "geometry": {"coordinates":[-3.8386409283,55.7323265076],"type":"Point"}
}