{
  "type": "Feature",
  "properties": {
    "iso:country":"GB",
    "sg:address":"95 Bar End Road",
    "sg:city":"Winchester",
    "sg:classifiers":[
        {
            "category":"Government",
            "subcategory":"Office",
            "type":"Public Place"
        }
    ],
    "sg:phone":"+44 1962 870099",
    "sg:postcode":"SO23 9NP",
    "sg:province":"Hampshire",
    "sg:tags":[
        "local"
    ],
    "wof:name":"Hampshire Printing Services",
    "wof:placetype":"venue"
},
  "geometry": {"coordinates":[-1.3056390285,51.0539512634],"type":"Point"}
}