{
  "type": "Feature",
  "properties": {
    "iso:country":"GB",
    "sg:address":"7 Oak Road, Ealing Broadway Shopping Centre",
    "sg:city":"London",
    "sg:classifiers":[
        {
            "category":"Professional",
            "type":"Services"
        },
        {
            "category":"Food & Beverages",
            "subcategory":"Bakery",
            "type":"Retail Goods"
        }
    ],
    "sg:phone":"+44 20 8840 5656",
    "sg:postcode":"W5 3SS",
    "sg:province":"Greater London",
    "sg:tags":[
        "shop",
        "baker",
        "caterer"
    ],
    "wof:name":"Bonne Bouche Catering Ltd",
    "wof:placetype":"venue"
},
  "geometry": {"coordinates":[-0.3017719984,51.5134963989],"type":"Point"}
}