{
  "type": "Feature",
  "properties": {
    "iso:country":"GB",
    "sg:address":"323 High St",
    "sg:city":"Chatham",
    "sg:classifiers":[
        {
            "category":"Retail",
            "subcategory":"Driving School",
            "type":"Services"
        }
    ],
    "sg:phone":"+44 1634 843573",
    "sg:postcode":"ME4 4BN",
    "sg:province":"Kent",
    "wof:name":"B S M (Anglia) Ltd",
    "wof:placetype":"venue"
},
  "geometry": {"coordinates":[0.5297,51.380505],"type":"Point"}
}