{
  "type": "Feature",
  "properties": {
    "iso:country":"GB",
    "sg:address":"Back Valley Drive",
    "sg:city":"Harrogate",
    "sg:classifiers":[
        {
            "category":"Wholesale",
            "subcategory":"Construction Materials",
            "type":"Manufacturing & Wholesale Goods"
        }
    ],
    "sg:phone":"+44 1423 562930",
    "sg:postcode":"HG2 0JU",
    "sg:province":"North Yorkshire",
    "sg:tags":[
        "merchant",
        "glass"
    ],
    "wof:name":"Harrogate Glass Co",
    "wof:placetype":"venue"
},
  "geometry": {"coordinates":[-1.550884,53.989063],"type":"Point"}
}