{
  "type": "Feature",
  "properties": {
    "addr:full":"3 Wadlands Drive, Farsley Pudsey West Yorkshire LS28 5JS",
    "addr:housenumber":"3",
    "addr:postcode":"ls28 5js",
    "addr:street":"Wadlands Drive;West",
    "iso:country":"GB",
    "sg:address":"3 Wadlands Drive, Farsley",
    "sg:city":"Pudsey",
    "sg:classifiers":[
        {
            "category":"Building & Trades",
            "subcategory":"Equipment Rental",
            "type":"Services"
        },
        {
            "category":"Shopping",
            "subcategory":"Pharmacy",
            "type":"Retail Goods"
        }
    ],
    "sg:phone":"+44 113 236 3852",
    "sg:postcode":"LS28 5JS",
    "sg:province":"West Yorkshire",
    "sg:tags":[
        "safety",
        "marking",
        "health",
        "product",
        "id"
    ],
    "wof:name":"C Mark",
    "wof:placetype":"venue"
},
  "geometry": {"coordinates":[-1.676718,53.815704],"type":"Point"}
}