{
  "type": "Feature",
  "properties": {
    "iso:country":"GB",
    "sg:address":"197-199 Mare Street, Hackney",
    "sg:city":"London",
    "sg:classifiers":[
        {
            "category":"Shopping",
            "subcategory":"Bicycles & Sporting Goods",
            "type":"Retail Goods"
        }
    ],
    "sg:phone":"+44 20 8985 0752",
    "sg:postcode":"E8 3QF",
    "sg:province":"Greater London",
    "sg:tags":[
        "equipment",
        "leisure"
    ],
    "wof:name":"Collins & Chambers Ltd.",
    "wof:placetype":"venue"
},
  "geometry": {"coordinates":[-0.055468,51.541256],"type":"Point"}
}