{
  "type": "Feature",
  "properties": {
    "addr:full":"Cadland Road, Hardley, Hythe Southampton Hampshire SO45 3YY",
    "addr:postcode":"so45 3yy",
    "addr:street":"Cadland Road",
    "iso:country":"GB",
    "sg:address":"Cadland Road, Hardley, Hythe",
    "sg:city":"Southampton",
    "sg:classifiers":[
        {
            "category":"Freight",
            "type":"Transportation"
        }
    ],
    "sg:phone":"+44 23 8089 0888",
    "sg:postcode":"SO45 3YY",
    "sg:province":"Hampshire",
    "sg:tags":[
        "haulage",
        "road"
    ],
    "wof:name":"Meachers",
    "wof:placetype":"venue"
},
  "geometry": {"coordinates":[-1.3922740221,50.8427734375],"type":"Point"}
}