{
  "type": "Feature",
  "properties": {
    "addr:full":"17 Gurney Close Bradford West Yorkshire BD5 9QR",
    "addr:housenumber":"17",
    "addr:postcode":"bd5 9qr",
    "addr:street":"Gurney Close",
    "iso:country":"GB",
    "sg:address":"17 Gurney Close",
    "sg:city":"Bradford",
    "sg:classifiers":[
        {
            "category":"Retail",
            "subcategory":"Driving School",
            "type":"Services"
        }
    ],
    "sg:phone":"+44 1274 503219",
    "sg:postcode":"BD5 9QR",
    "sg:province":"West Yorkshire",
    "wof:name":"Chahal School Of Motoring",
    "wof:placetype":"venue"
},
  "geometry": {"coordinates":[-1.764539,53.777042],"type":"Point"}
}