{
  "type": "Feature",
  "properties": {
    "iso:country":"GB",
    "sg:address":"117 Highland Rd",
    "sg:city":"Southsea",
    "sg:classifiers":[
        {
            "category":"Utilities",
            "subcategory":"Natural Gas",
            "type":"Services"
        }
    ],
    "sg:phone":"+44 23 9275 0700",
    "sg:postcode":"PO4 9DD",
    "sg:province":"Hampshire",
    "sg:tags":[
        "supplier"
    ],
    "wof:name":"M & B Gases",
    "wof:placetype":"venue"
},
  "geometry": {"coordinates":[-1.065197,50.786999],"type":"Point"}
}