{
  "type": "Feature",
  "properties": {
    "addr:full":"Swallow Lane, Golcar Huddersfield West Yorkshire HD7 4NB",
    "addr:postcode":"hd7 4nb",
    "addr:street":"Swallow Lane;West",
    "iso:country":"GB",
    "sg:address":"Swallow Lane, Golcar",
    "sg:city":"Huddersfield",
    "sg:classifiers":[
        {
            "category":"Home & Garden",
            "subcategory":"Kitchen Supply",
            "type":"Retail Goods"
        }
    ],
    "sg:postcode":"HD7 4NB",
    "sg:province":"West Yorkshire",
    "sg:tags":[
        "equipment",
        "brewer"
    ],
    "wof:name":"Barfit",
    "wof:placetype":"venue"
},
  "geometry": {"coordinates":[-1.8399139643,53.6400985718],"type":"Point"}
}