{
  "type": "Feature",
  "properties": {
    "iso:country":"GB",
    "sg:address":"5 Martins Drive",
    "sg:city":"Atherstone",
    "sg:classifiers":[
        {
            "category":"Manufacturing",
            "subcategory":"Metals",
            "type":"Manufacturing & Wholesale Goods"
        }
    ],
    "sg:postcode":"CV9 3AU",
    "sg:province":"Leicestershire",
    "sg:tags":[
        "product",
        "fabricated"
    ],
    "wof:name":"Aluminium Supply Aerospace",
    "wof:placetype":"venue"
},
  "geometry": {"coordinates":[-1.543467,52.585438],"type":"Point"}
}