{
  "type": "Feature",
  "properties": {
    "addr:full":"12 Barley Mow Passage London Greater London W4 4PH",
    "addr:housenumber":"12;mow",
    "addr:postcode":"w4 4ph",
    "addr:street":"Barley;Passage",
    "iso:country":"GB",
    "sg:address":"12 Barley Mow Passage",
    "sg:city":"London",
    "sg:classifiers":[
        {
            "category":"Organizations",
            "subcategory":"Community Association",
            "type":"Services"
        }
    ],
    "sg:phone":"+44 20 8987 0123",
    "sg:postcode":"W4 4PH",
    "sg:province":"Greater London",
    "sg:tags":[
        "relation",
        "public"
    ],
    "wof:name":"Coalition Management Ltd.",
    "wof:placetype":"venue"
},
  "geometry": {"coordinates":[-0.2618820071,51.4918441772],"type":"Point"}
}