{
  "type": "Feature",
  "properties": {
    "iso:country":"GB",
    "sg:address":"107 Wyndham Road, Blacon",
    "sg:city":"Chester",
    "sg:classifiers":[
        {
            "category":"Building & Trades",
            "subcategory":"Construction",
            "type":"Services"
        }
    ],
    "sg:postcode":"CH1 5SF",
    "sg:province":"Cheshire",
    "sg:tags":[
        "roofing"
    ],
    "wof:name":"Abbey Roofing Services",
    "wof:placetype":"venue"
},
  "geometry": {"coordinates":[-2.939171,53.202801],"type":"Point"}
}