{
  "type": "Feature",
  "properties": {
    "addr:full":"Cissbury Dr Worthing West Sussex BN14 0DT",
    "addr:postcode":"bn14 0dt",
    "addr:street":"Cissbury Dr",
    "iso:country":"GB",
    "sg:address":"Cissbury Dr",
    "sg:city":"Worthing",
    "sg:classifiers":[
        {
            "category":"Government",
            "subcategory":"City Hall",
            "type":"Public Place"
        }
    ],
    "sg:phone":"+44 1903 873161",
    "sg:postcode":"BN14 0DT",
    "sg:province":"West Sussex",
    "wof:name":"All Saints Church Hall",
    "wof:placetype":"venue"
},
  "geometry": {"coordinates":[-0.3959690034,50.8514022827],"type":"Point"}
}