{
  "type": "Feature",
  "properties": {
    "iso:country":"GB",
    "sg:address":"1e Walm Lane",
    "sg:city":"London",
    "sg:classifiers":[
        {
            "category":"Fast Food",
            "type":"Food & Drink"
        }
    ],
    "sg:phone":"+44 20 8459 5777",
    "sg:postcode":"NW2 5SJ",
    "sg:province":"Greater London",
    "sg:tags":[
        "away",
        "meal",
        "outlet",
        "take"
    ],
    "wof:name":"Blue Orchid",
    "wof:placetype":"venue"
},
  "geometry": {"coordinates":[-0.224622,51.547531],"type":"Point"}
}