{
  "type": "Feature",
  "properties": {
    "iso:country":"GB",
    "sg:address":"Unit 2 Wymans Lane, Kingsditch",
    "sg:city":"Cheltenham",
    "sg:classifiers":[
        {
            "category":"Sports & Exercise",
            "subcategory":"Bowling",
            "type":"Entertainment"
        }
    ],
    "sg:phone":"+44 1242 226766",
    "sg:postcode":"GL51 9NA",
    "sg:province":"Gloucestershire",
    "wof:name":"Cotswold Tenpin Bowling Centre",
    "wof:placetype":"venue"
},
  "geometry": {"coordinates":[-2.091628,51.920399],"type":"Point"}
}