{
  "type": "Feature",
  "properties": {
    "iso:country":"GB",
    "sg:address":"11 Undercliff Road",
    "sg:city":"Bournemouth",
    "sg:classifiers":[
        {
            "category":"Real Estate",
            "subcategory":"Real Estate Agent",
            "type":"Services"
        }
    ],
    "sg:phone":"+44 1202 309317",
    "sg:postcode":"BH5 1BL",
    "sg:province":"Dorset",
    "wof:name":"Ivaville Co.",
    "wof:placetype":"venue"
},
  "geometry": {"coordinates":[-1.843729,50.720753],"type":"Point"}
}