{
  "type": "Feature",
  "properties": {
    "iso:country":"GB",
    "sg:address":"85 School Lane",
    "sg:city":"Manchester",
    "sg:classifiers":[
        {
            "category":"Shopping",
            "subcategory":"Antiques",
            "type":"Retail Goods"
        }
    ],
    "sg:postcode":"M20 6WN",
    "sg:province":"Greater Manchester",
    "wof:name":"Didsbury Antiques",
    "wof:placetype":"venue"
},
  "geometry": {"coordinates":[-2.225157,53.417004],"type":"Point"}
}