{
  "type": "Feature",
  "properties": {
    "addr:full":"Fforddlas Bach Farm Abergele Conwy LL22 9BB",
    "addr:postcode":"ll22 9bb",
    "iso:country":"GB",
    "sg:address":"Fforddlas Bach Farm",
    "sg:city":"Abergele",
    "sg:classifiers":[
        {
            "category":"Building & Trades",
            "subcategory":"Construction",
            "type":"Services"
        }
    ],
    "sg:phone":"+44 1745 824524",
    "sg:postcode":"LL22 9BB",
    "sg:province":"Conwy",
    "sg:tags":[
        "builder"
    ],
    "wof:name":"J & T Gizzi",
    "wof:placetype":"venue"
},
  "geometry": {"coordinates":[-3.581144,53.284355],"type":"Point"}
}