{
  "type": "Feature",
  "properties": {
    "addr:full":"Unit 1 Ber-mar House, Rumer Hill Business Estate, Rumner Hill Road Cannock Staffordshire WS11 3ET",
    "addr:housenumber":"unit 1 ber-mar house",
    "addr:postcode":"ws11 3et",
    "addr:street":"Rumer Hill Business Estate Rumner Hill Road",
    "iso:country":"GB",
    "sg:address":"Unit 1 Ber-mar House, Rumer Hill Business Estate, Rumner Hill Road",
    "sg:city":"Cannock",
    "sg:classifiers":[
        {
            "category":"Organizations",
            "subcategory":"Non-profit Organization",
            "type":"Services"
        }
    ],
    "sg:phone":"+44 1543 462386",
    "sg:postcode":"WS11 3ET",
    "sg:province":"Staffordshire",
    "sg:tags":[
        "organisation",
        "voluntary",
        "charity"
    ],
    "wof:name":"Mencap Homes Foundation",
    "wof:placetype":"venue"
},
  "geometry": {"coordinates":[-2.023437,52.682632],"type":"Point"}
}