{
  "type": "Feature",
  "properties": {
    "addr:full":"Hartfirled House, Poolhill Telford Shropshire TF4 3AS",
    "addr:postcode":"tf4 3as",
    "iso:country":"GB",
    "sg:address":"Hartfirled House, Poolhill",
    "sg:city":"Telford",
    "sg:classifiers":[
        {
            "category":"Shopping",
            "subcategory":"Bicycles & Sporting Goods",
            "type":"Retail Goods"
        }
    ],
    "sg:postcode":"TF4 3AS",
    "sg:province":"Shropshire",
    "sg:tags":[
        "riding",
        "saddlery",
        "wear"
    ],
    "wof:name":"The Horse Shop",
    "wof:placetype":"venue"
},
  "geometry": {"coordinates":[-2.477691,52.66148],"type":"Point"}
}