{
  "type": "Feature",
  "properties": {
    "addr:full":"67 Ermine St, Broughton Brigg Lincolnshire DN20 0AH",
    "addr:housenumber":"67",
    "addr:postcode":"dn20 0ah",
    "addr:street":"Ermine St;Brigg",
    "iso:country":"GB",
    "sg:address":"67 Ermine St, Broughton",
    "sg:city":"Brigg",
    "sg:classifiers":[
        {
            "category":"Professional",
            "subcategory":"Engineering",
            "type":"Services"
        }
    ],
    "sg:phone":"+44 1652 653524",
    "sg:postcode":"DN20 0AH",
    "sg:province":"Lincolnshire",
    "sg:tags":[
        "contractor",
        "electrical",
        "engineer"
    ],
    "wof:name":"Owen Bowness & Son",
    "wof:placetype":"venue"
},
  "geometry": {"coordinates":[-0.549236,53.565613],"type":"Point"}
}