{
  "type": "Feature",
  "properties": {
    "addr:full":"Carlisle Road Airdrie North Lanarkshire ML6 8AA",
    "addr:postcode":"ml6 8aa",
    "addr:street":"Carlisle Road",
    "iso:country":"GB",
    "sg:address":"Carlisle Road",
    "sg:city":"Airdrie",
    "sg:classifiers":[
        {
            "category":"Building & Trades",
            "subcategory":"Landscaping Services",
            "type":"Services"
        }
    ],
    "sg:postcode":"ML6 8AA",
    "sg:province":"North Lanarkshire",
    "sg:tags":[
        "horticultural",
        "consultant"
    ],
    "wof:name":"Dal Plant Sales Ltd.",
    "wof:placetype":"venue"
},
  "geometry": {"coordinates":[-3.964329,55.860821],"type":"Point"}
}