{
  "type": "Feature",
  "properties": {
    "addr:full":"2-6 Portsea Rd Tilbury Essex RM18 8AX",
    "addr:housenumber":"2-6",
    "addr:postcode":"rm18 8ax",
    "addr:street":"Portsea Rd",
    "iso:country":"GB",
    "sg:address":"2-6 Portsea Rd",
    "sg:city":"Tilbury",
    "sg:classifiers":[
        {
            "category":"Food & Beverages",
            "subcategory":"Groceries & Convenience Stores",
            "type":"Retail Goods"
        }
    ],
    "sg:phone":"+44 1375 844738",
    "sg:postcode":"RM18 8AX",
    "sg:province":"Essex",
    "wof:name":"Circle C",
    "wof:placetype":"venue"
},
  "geometry": {"coordinates":[0.376354,51.463478],"type":"Point"}
}