{
  "type": "Feature",
  "properties": {
    "iso:country":"GB",
    "sg:address":"Ormskirk Road",
    "sg:city":"Wigan",
    "sg:classifiers":[
        {
            "category":"Personal",
            "type":"Services"
        }
    ],
    "sg:postcode":"WN5 9DD",
    "sg:province":"Lancashire",
    "sg:tags":[
        "wedding"
    ],
    "wof:name":"At Your Service Prestige Cars",
    "wof:placetype":"venue"
},
  "geometry": {"coordinates":[-2.6528439522,53.5395507812],"type":"Point"}
}