{
  "type": "Feature",
  "properties": {
    "iso:country":"GB",
    "sg:address":"Rear Of 81-87 Collier Row Road",
    "sg:city":"Romford",
    "sg:classifiers":[
        {
            "category":"Sports & Exercise",
            "subcategory":"Tennis Court",
            "type":"Entertainment"
        }
    ],
    "sg:phone":"+44 1708 723005",
    "sg:postcode":"RM5 2AU",
    "sg:province":"Essex",
    "sg:tags":[
        "breakdown",
        "recovery"
    ],
    "wof:name":"Eastern General Recovery Service",
    "wof:placetype":"venue"
},
  "geometry": {"coordinates":[0.1584,51.598141],"type":"Point"}
}