{
  "type": "Feature",
  "properties": {
    "iso:country":"GB",
    "sg:address":"52 Sandbach Place, Plumstead",
    "sg:city":"London",
    "sg:classifiers":[
        {
            "category":"Social Services",
            "subcategory":"Retirement Home",
            "type":"Services"
        },
        {
            "category":"Government",
            "subcategory":"Office",
            "type":"Public Place"
        }
    ],
    "sg:phone":"+44 20 8854 9958",
    "sg:postcode":"SE18 7EX",
    "sg:province":"Greater London",
    "sg:tags":[
        "residential",
        "local",
        "care"
    ],
    "wof:name":"Sandbach Place Respite Care Home",
    "wof:placetype":"venue"
},
  "geometry": {"coordinates":[0.074929,51.486893],"type":"Point"}
}