{
  "type": "Feature",
  "properties": {
    "addr:full":"33 Melford Court, Hardwick Grange Warrington Cheshire WA1 4RZ",
    "addr:housenumber":"33",
    "addr:postcode":"wa1 4rz",
    "addr:street":"Melford Court",
    "iso:country":"GB",
    "sg:address":"33 Melford Court, Hardwick Grange",
    "sg:city":"Warrington",
    "sg:classifiers":[
        {
            "category":"Professional",
            "subcategory":"Engineering",
            "type":"Services"
        }
    ],
    "sg:phone":"+44 1925 810810",
    "sg:postcode":"WA1 4RZ",
    "sg:province":"Cheshire",
    "sg:tags":[
        "precision",
        "engineer"
    ],
    "wof:name":"Howley Engineering Ltd.",
    "wof:placetype":"venue"
},
  "geometry": {"coordinates":[-2.531199,53.403896],"type":"Point"}
}