{
  "type": "Feature",
  "properties": {
    "addr:full":"168 Silver Road Norwich Norfolk NR3 4TH",
    "addr:housenumber":"168",
    "addr:postcode":"nr3 4th",
    "addr:street":"Silver Road Norwich Norfolk",
    "iso:country":"GB",
    "sg:address":"168 Silver Road",
    "sg:city":"Norwich",
    "sg:classifiers":[
        {
            "category":"Retail",
            "subcategory":"Auto Repair",
            "type":"Services"
        }
    ],
    "sg:phone":"+44 1603 413134",
    "sg:postcode":"NR3 4TH",
    "sg:province":"Norfolk",
    "sg:tags":[
        "electrician"
    ],
    "wof:name":"A W Electrics",
    "wof:placetype":"venue"
},
  "geometry": {"coordinates":[1.302535,52.642063],"type":"Point"}
}