{
  "type": "Feature",
  "properties": {
    "addr:full":"Norwich Research Park, Colney Lane Norwich Norfolk NR4 7UQ",
    "addr:postcode":"nr4 7uq",
    "addr:street":"Colney Lane",
    "iso:country":"GB",
    "sg:address":"Norwich Research Park, Colney Lane",
    "sg:city":"Norwich",
    "sg:classifiers":[
        {
            "category":"Government",
            "subcategory":"Post Office",
            "type":"Public Place"
        }
    ],
    "sg:postcode":"NR4 7UQ",
    "sg:province":"Norfolk",
    "sg:tags":[
        "organisation",
        "soc",
        "research"
    ],
    "wof:name":"C S L Food Science Laboratory",
    "wof:placetype":"venue"
},
  "geometry": {"coordinates":[1.2292699814,52.6270561218],"type":"Point"}
}