{
  "type": "Feature",
  "properties": {
    "addr:full":"75 Tilford Rd Hindhead Hampshire GU26 6RH",
    "addr:housenumber":"75",
    "addr:postcode":"gu26 6rh",
    "addr:street":"Tilford Rd",
    "iso:country":"GB",
    "sg:address":"75 Tilford Rd",
    "sg:city":"Hindhead",
    "sg:classifiers":[
        {
            "category":"Fast Food",
            "type":"Food & Drink"
        }
    ],
    "sg:phone":"+44 1428 606946",
    "sg:postcode":"GU26 6RH",
    "sg:province":"Hampshire",
    "sg:tags":[
        "away",
        "take"
    ],
    "wof:name":"Piggy's",
    "wof:placetype":"venue"
},
  "geometry": {"coordinates":[-0.751469,51.131794],"type":"Point"}
}