{
  "type": "Feature",
  "properties": {
    "iso:country":"GB",
    "sg:address":"1 Hartdene House, Bridge Road",
    "sg:city":"Bagshot",
    "sg:classifiers":[
        {
            "category":"Professional",
            "subcategory":"Management & Consulting",
            "type":"Services"
        }
    ],
    "sg:phone":"+44 1344 426123",
    "sg:postcode":"GU19 5AT",
    "sg:province":"Berkshire",
    "sg:tags":[
        "consultant",
        "business"
    ],
    "wof:name":"E2e Customer Services Ltd.",
    "wof:placetype":"venue"
},
  "geometry": {"coordinates":[-0.6961200237,51.3587989807],"type":"Point"}
}