{
  "type": "Feature",
  "properties": {
    "addr:full":"G A T X Avonmouth Terminal, Royal Edward Dock Bristol City of Bristol BS11 9BT",
    "addr:postcode":"bs11 9bt",
    "addr:street":"G A T X",
    "iso:country":"GB",
    "sg:address":"G A T X Avonmouth Terminal, Royal Edward Dock",
    "sg:city":"Bristol",
    "sg:classifiers":[
        {
            "category":"Utilities",
            "subcategory":"Fuel Oil & Lpg",
            "type":"Services"
        }
    ],
    "sg:phone":"+44 117 923 5181",
    "sg:postcode":"BS11 9BT",
    "sg:province":"City of Bristol",
    "sg:tags":[
        "distributor"
    ],
    "wof:name":"Midwinter Oil Supplies Ltd.",
    "wof:placetype":"venue"
},
  "geometry": {"coordinates":[-2.694124,51.498917],"type":"Point"}
}