{
  "type": "Feature",
  "properties": {
    "addr:full":"43 High Town Crewe Cheshire CW1 3BZ",
    "addr:housenumber":"43",
    "addr:postcode":"cw1 3bz",
    "addr:street":"High Town",
    "iso:country":"GB",
    "sg:address":"43 High Town",
    "sg:city":"Crewe",
    "sg:classifiers":[
        {
            "category":"Manufacturing",
            "subcategory":"Textiles",
            "type":"Manufacturing & Wholesale Goods"
        }
    ],
    "sg:postcode":"CW1 3BZ",
    "sg:province":"Cheshire",
    "sg:tags":[
        "dyer"
    ],
    "wof:name":"Harding,Michael,",
    "wof:placetype":"venue"
},
  "geometry": {"coordinates":[-2.4479939938,53.1004753113],"type":"Point"}
}