{
  "type": "Feature",
  "properties": {
    "iso:country":"GB",
    "sg:address":"1a-3a Melbourne Avenue",
    "sg:city":"London",
    "sg:classifiers":[
        {
            "category":"Food & Beverages",
            "subcategory":"Meat & Fish",
            "type":"Retail Goods"
        }
    ],
    "sg:phone":"+44 20 8965 5044",
    "sg:postcode":"W13 9BS",
    "sg:province":"Greater London",
    "sg:tags":[
        "butcher"
    ],
    "wof:name":"A J Luckhurst & Sons Ltd.",
    "wof:placetype":"venue"
},
  "geometry": {"coordinates":[-0.3246690035,51.5091285706],"type":"Point"}
}