{
  "type": "Feature",
  "properties": {
    "iso:country":"GB",
    "sg:address":"11 Elmwood Close",
    "sg:city":"Retford",
    "sg:classifiers":[
        {
            "category":"Organizations",
            "subcategory":"Non-profit Organization",
            "type":"Services"
        }
    ],
    "sg:postcode":"DN22 6SL",
    "sg:province":"Nottinghamshire",
    "sg:tags":[
        "organisation",
        "voluntary",
        "charity"
    ],
    "wof:name":"The Cancer Research Campaign",
    "wof:placetype":"venue"
},
  "geometry": {"coordinates":[-0.93499,53.329929],"type":"Point"}
}