{
  "type": "Feature",
  "properties": {
    "addr:full":"47 Gardiner Street Market Harborough Leicestershire LE16 9QN",
    "addr:housenumber":"47",
    "addr:postcode":"le16 9qn",
    "addr:street":"Gardiner Street",
    "iso:country":"GB",
    "sg:address":"47 Gardiner Street",
    "sg:city":"Market Harborough",
    "sg:classifiers":[
        {
            "category":"Professional",
            "subcategory":"Engineering",
            "type":"Services"
        }
    ],
    "sg:phone":"+44 1858 431771",
    "sg:postcode":"LE16 9QN",
    "sg:province":"Leicestershire",
    "sg:tags":[
        "contractor",
        "electrical",
        "engineer"
    ],
    "wof:name":"S M Alden Electrical Contractor",
    "wof:placetype":"venue"
},
  "geometry": {"coordinates":[-0.935543,52.477863],"type":"Point"}
}