{
  "type": "Feature",
  "properties": {
    "iso:country":"GB",
    "sg:address":"Unit 39 Clarks Village, Farm Rd",
    "sg:city":"Street",
    "sg:classifiers":[
        {
            "category":"Home & Garden",
            "subcategory":"Kitchen Supply",
            "type":"Retail Goods"
        }
    ],
    "sg:phone":"+44 1458 840450",
    "sg:postcode":"BA16 0BB",
    "sg:province":"Somerset",
    "sg:tags":[
        "glassware",
        "china"
    ],
    "wof:name":"Waterford Wedgwood Factory Shop",
    "wof:placetype":"venue"
},
  "geometry": {"coordinates":[-2.74872,51.127872],"type":"Point"}
}