{
  "type": "Feature",
  "properties": {
    "iso:country":"GB",
    "sg:address":"Guithavon Valley",
    "sg:city":"Witham",
    "sg:classifiers":[
        {
            "category":"Retail",
            "subcategory":"Repair Shop",
            "type":"Services"
        }
    ],
    "sg:postcode":"CM8 1HF",
    "sg:province":"Essex",
    "sg:tags":[
        "radio",
        "television",
        "video"
    ],
    "wof:name":"Eastern Electronic Services",
    "wof:placetype":"venue"
},
  "geometry": {"coordinates":[0.637606,51.803535],"type":"Point"}
}