{
  "type": "Feature",
  "properties": {
    "iso:country":"GB",
    "sg:address":"Unit 4, Lyon Close",
    "sg:city":"Wigston",
    "sg:classifiers":[
        {
            "category":"Building & Trades",
            "subcategory":"Landscaping Services",
            "type":"Services"
        },
        {
            "category":"Wholesale",
            "subcategory":"Plants",
            "type":"Manufacturing & Wholesale Goods"
        }
    ],
    "sg:phone":"+44 116 288 6070",
    "sg:postcode":"LE18 2BJ",
    "sg:province":"Leicestershire",
    "sg:tags":[
        "horticultural",
        "consultant"
    ],
    "wof:name":"B W Machine Tools",
    "wof:placetype":"venue"
},
  "geometry": {"coordinates":[-1.1243530512,52.5917358398],"type":"Point"}
}