{
  "type": "Feature",
  "properties": {
    "addr:full":"274 Kirkdale London Greater London SE26 4RS",
    "addr:housenumber":"274",
    "addr:postcode":"se26 4rs",
    "iso:country":"GB",
    "sg:address":"274 Kirkdale",
    "sg:city":"London",
    "sg:classifiers":[
        {
            "category":"Home & Garden",
            "subcategory":"Hardware",
            "type":"Retail Goods"
        }
    ],
    "sg:phone":"+44 20 8776 7020",
    "sg:postcode":"SE26 4RS",
    "sg:province":"Greater London",
    "sg:tags":[
        "retailer",
        "diy"
    ],
    "wof:name":"Sydenham D I Y",
    "wof:placetype":"venue"
},
  "geometry": {"coordinates":[-0.056219,51.427147],"type":"Point"}
}