{
  "type": "Feature",
  "properties": {
    "addr:full":"Ryston End Downham Market Cambridgeshire PE38 9AY",
    "addr:postcode":"pe38 9ay",
    "addr:street":"Ryston;Market",
    "iso:country":"GB",
    "sg:address":"Ryston End",
    "sg:city":"Downham Market",
    "sg:classifiers":[
        {
            "category":"Professional",
            "subcategory":"Management & Consulting",
            "type":"Services"
        }
    ],
    "sg:phone":"+44 1366 383878",
    "sg:postcode":"PE38 9AY",
    "sg:province":"Cambridgeshire",
    "sg:tags":[
        "consultant",
        "training"
    ],
    "wof:name":"The Business Technology Centre",
    "wof:placetype":"venue"
},
  "geometry": {"coordinates":[0.38022,52.599293],"type":"Point"}
}