{
  "type": "Feature",
  "properties": {
    "iso:country":"GB",
    "sg:address":"304 Upper Richmond Road West",
    "sg:city":"London",
    "sg:classifiers":[
        {
            "category":"Shopping",
            "subcategory":"Comic Books",
            "type":"Retail Goods"
        }
    ],
    "sg:phone":"+44 20 8876 6895",
    "sg:postcode":"SW14 7JG",
    "sg:province":"Greater London",
    "sg:tags":[
        "jeweller"
    ],
    "wof:name":"East Sheen Jewellers",
    "wof:placetype":"venue"
},
  "geometry": {"coordinates":[-0.2693319917,51.4643096924],"type":"Point"}
}