{
  "type": "Feature",
  "properties": {
    "addr:full":"130b Felsham Road London Greater London SW15 1DP",
    "addr:housenumber":"130b",
    "addr:postcode":"sw15 1dp",
    "addr:street":"Felsham Road",
    "iso:country":"GB",
    "sg:address":"130b Felsham Road",
    "sg:city":"London",
    "sg:classifiers":[
        {
            "category":"Banks & Credit Unions",
            "subcategory":"Financial Services",
            "type":"Services"
        }
    ],
    "sg:postcode":"SW15 1DP",
    "sg:province":"Greater London",
    "sg:tags":[
        "consultant"
    ],
    "wof:name":"Unitemp Securities Ltd",
    "wof:placetype":"venue"
},
  "geometry": {"coordinates":[-0.221679,51.466534],"type":"Point"}
}