{
  "type": "Feature",
  "properties": {
    "iso:country":"GB",
    "sg:address":"Unit A Old School Industrial Estate, Moorland Road",
    "sg:city":"St Columb",
    "sg:classifiers":[
        {
            "category":"Communications",
            "type":"Services"
        },
        {
            "category":"Food & Beverages",
            "subcategory":"Meat & Fish",
            "type":"Retail Goods"
        }
    ],
    "sg:postcode":"TR9 6HF",
    "sg:province":"Cornwall",
    "sg:tags":[
        "merchant",
        "audio-visual"
    ],
    "wof:name":"Flying Fish",
    "wof:placetype":"venue"
},
  "geometry": {"coordinates":[-4.936884,50.43256],"type":"Point"}
}