{
  "type": "Feature",
  "properties": {
    "addr:full":"62a High Street Cowbridge The Vale of Glamorgan CF71 7AH",
    "addr:housenumber":"62a",
    "addr:postcode":"cf71 7ah",
    "addr:street":"High Street;Vale",
    "iso:country":"GB",
    "sg:address":"62a High Street",
    "sg:city":"Cowbridge",
    "sg:classifiers":[
        {
            "category":"Real Estate",
            "subcategory":"Architect",
            "type":"Services"
        }
    ],
    "sg:phone":"+44 1446 774493",
    "sg:postcode":"CF71 7AH",
    "sg:province":"The Vale of Glamorgan",
    "wof:name":"Quorum Associates Ltd.",
    "wof:placetype":"venue"
},
  "geometry": {"coordinates":[-3.4504630566,51.4622573853],"type":"Point"}
}