{
  "type": "Feature",
  "properties": {
    "iso:country":"GB",
    "sg:address":"623 Rainham Road South",
    "sg:city":"Dagenham",
    "sg:classifiers":[
        {
            "category":"Food & Beverages",
            "subcategory":"Liquor & Beverages",
            "type":"Retail Goods"
        }
    ],
    "sg:phone":"+44 20 8592 3630",
    "sg:postcode":"RM10 8AH",
    "sg:province":"Essex",
    "sg:tags":[
        "beer",
        "spirit",
        "wines"
    ],
    "wof:name":"Dagenham East Wines",
    "wof:placetype":"venue"
},
  "geometry": {"coordinates":[0.165651,51.542992],"type":"Point"}
}