{
  "type": "Feature",
  "properties": {
    "addr:full":"Duff Street Aberdeen Aberdeen City AB24 5LF",
    "addr:postcode":"ab24 5lf",
    "addr:street":"Duff Street",
    "iso:country":"GB",
    "sg:address":"Duff Street",
    "sg:city":"Aberdeen",
    "sg:classifiers":[
        {
            "category":"Wholesale",
            "subcategory":"Vending Machines",
            "type":"Manufacturing & Wholesale Goods"
        }
    ],
    "sg:phone":"+44 1224 647505",
    "sg:postcode":"AB24 5LF",
    "sg:province":"Aberdeen City",
    "sg:tags":[
        "sale"
    ],
    "wof:name":"Grampian Leisure Vending",
    "wof:placetype":"venue"
},
  "geometry": {"coordinates":[-2.089384079,57.1525192261],"type":"Point"}
}