{
  "type": "Feature",
  "properties": {
    "addr:full":"301 Titford Road Smethwick West Midlands B69 4QN",
    "addr:housenumber":"301",
    "addr:postcode":"b69 4qn",
    "addr:street":"Titford Road",
    "iso:country":"GB",
    "sg:address":"301 Titford Road",
    "sg:city":"Smethwick",
    "sg:classifiers":[
        {
            "category":"Wholesale",
            "subcategory":"Scrap",
            "type":"Manufacturing & Wholesale Goods"
        },
        {
            "category":"Retail",
            "subcategory":"Auto Repair",
            "type":"Services"
        }
    ],
    "sg:phone":"+44 121 552 1878",
    "sg:postcode":"B69 4QN",
    "sg:province":"West Midlands",
    "sg:tags":[
        "modification",
        "garage",
        "breaker",
        "dismantlers"
    ],
    "wof:name":"Mario Zarelli & Winston Sutherland",
    "wof:placetype":"venue"
},
  "geometry": {"coordinates":[-2.01979,52.48793],"type":"Point"}
}