{
  "type": "Feature",
  "properties": {
    "iso:country":"GB",
    "sg:address":"3 Cotswold Mews, Battersea Sq",
    "sg:city":"London",
    "sg:classifiers":[
        {
            "category":"Professional",
            "subcategory":"Art Services",
            "type":"Services"
        }
    ],
    "sg:postcode":"SW11 3RA",
    "sg:province":"Greater London",
    "sg:tags":[
        "graphic",
        "designer"
    ],
    "wof:name":"Unlimited",
    "wof:placetype":"venue"
},
  "geometry": {"coordinates":[-0.17496,51.47472],"type":"Point"}
}