{
  "type": "Feature",
  "properties": {
    "addr:full":"10 The Paddock, Yarnton Kidlington Buckinghamshire OX5 1TF",
    "addr:housenumber":"10",
    "addr:postcode":"ox5 1tf",
    "addr:street":"The Paddock;Kidlington",
    "iso:country":"GB",
    "sg:address":"10 The Paddock, Yarnton",
    "sg:city":"Kidlington",
    "sg:classifiers":[
        {
            "category":"Professional",
            "subcategory":"Detective & Security Services",
            "type":"Services"
        }
    ],
    "sg:postcode":"OX5 1TF",
    "sg:province":"Buckinghamshire",
    "sg:tags":[
        "alarm",
        "burglar",
        "system"
    ],
    "wof:name":"Witney Alarms",
    "wof:placetype":"venue"
},
  "geometry": {"coordinates":[-1.3085839748,51.8056411743],"type":"Point"}
}