{
  "type": "Feature",
  "properties": {
    "addr:full":"13-15 Countess Street Saltcoats North Ayrshire KA21 5HP",
    "addr:housenumber":"13-15",
    "addr:postcode":"ka21 5hp",
    "addr:street":"Countess Street",
    "iso:country":"GB",
    "sg:address":"13-15 Countess Street",
    "sg:city":"Saltcoats",
    "sg:classifiers":[
        {
            "category":"Home & Garden",
            "subcategory":"Hardware",
            "type":"Retail Goods"
        }
    ],
    "sg:phone":"+44 1294 470476",
    "sg:postcode":"KA21 5HP",
    "sg:province":"North Ayrshire",
    "sg:tags":[
        "merchant",
        "ironmonger"
    ],
    "wof:name":"V R Imports Direct Ltd.",
    "wof:placetype":"venue"
},
  "geometry": {"coordinates":[-4.784967,55.633038],"type":"Point"}
}