{
  "type": "Feature",
  "properties": {
    "iso:country":"GB",
    "sg:address":"16 Ruby Clo",
    "sg:city":"Wokingham",
    "sg:classifiers":[
        {
            "category":"Shopping",
            "subcategory":"Catalog Store",
            "type":"Retail Goods"
        }
    ],
    "sg:phone":"+44 118 978 8148",
    "sg:postcode":"RG41 3TX",
    "sg:province":"Berkshire",
    "sg:tags":[
        "mail",
        "order"
    ],
    "wof:name":"Hayley Green Models Ltd",
    "wof:placetype":"venue"
},
  "geometry": {"coordinates":[-0.864574,51.418736],"type":"Point"}
}