{
  "type": "Feature",
  "properties": {
    "addr:full":"Village Street, Adwick-le-street Doncaster North Yorkshire DN6 7AA",
    "addr:postcode":"dn6 7aa",
    "addr:street":"Village Street",
    "iso:country":"GB",
    "sg:address":"Village Street, Adwick-le-street",
    "sg:city":"Doncaster",
    "sg:classifiers":[
        {
            "category":"Education",
            "subcategory":"School",
            "type":"Public Place"
        },
        {
            "category":"Government",
            "subcategory":"Office",
            "type":"Public Place"
        }
    ],
    "sg:phone":"+44 1302 723571",
    "sg:postcode":"DN6 7AA",
    "sg:province":"North Yorkshire",
    "sg:tags":[
        "local",
        "authority"
    ],
    "wof:name":"Fernbank Special School",
    "wof:placetype":"venue"
},
  "geometry": {"coordinates":[-1.1839460135,53.5702133179],"type":"Point"}
}