{
  "type": "Feature",
  "properties": {
    "iso:country":"GB",
    "sg:address":"Park Lodge, Kings Park Community Hospital, Gloucester Rd",
    "sg:city":"Bournemouth",
    "sg:classifiers":[
        {
            "category":"Professional",
            "subcategory":"Lawyer & Legal Services",
            "type":"Services"
        }
    ],
    "sg:phone":"+44 1202 395768",
    "sg:postcode":"BH7 6JE",
    "sg:province":"Dorset",
    "sg:tags":[
        "advice",
        "counselling"
    ],
    "wof:name":"Needle Exchange",
    "wof:placetype":"venue"
},
  "geometry": {"coordinates":[-1.8341399431,50.7314910889],"type":"Point"}
}