{
  "type": "Feature",
  "properties": {
    "iso:country":"GB",
    "sg:address":"41 Atlantic Rd",
    "sg:city":"Brixton",
    "sg:classifiers":[
        {
            "category":"Food & Beverages",
            "subcategory":"Supermarket",
            "type":"Retail Goods"
        }
    ],
    "sg:phone":"+44 20 7737 0471",
    "sg:postcode":"SW9 8JL",
    "sg:province":"Greater London",
    "wof:name":"Atlantic",
    "wof:placetype":"venue"
},
  "geometry": {"coordinates":[-0.1122969985,51.4621429443],"type":"Point"}
}