{
  "type": "Feature",
  "properties": {
    "addr:full":"Unit 12, Lecturers Close Bolton Lancashire BL3 6DG",
    "addr:housenumber":"unit 12",
    "addr:postcode":"bl3 6dg",
    "addr:street":"Lecturers Close",
    "iso:country":"GB",
    "sg:address":"Unit 12, Lecturers Close",
    "sg:city":"Bolton",
    "sg:classifiers":[
        {
            "category":"Professional",
            "subcategory":"Printing & Photocopies",
            "type":"Services"
        }
    ],
    "sg:postcode":"BL3 6DG",
    "sg:province":"Lancashire",
    "sg:tags":[
        "engraving"
    ],
    "wof:name":"Eric Whitley & Peter Morrison",
    "wof:placetype":"venue"
},
  "geometry": {"coordinates":[-2.431101,53.571941],"type":"Point"}
}