{
  "type": "Feature",
  "properties": {
    "addr:full":"7 Elm Tree Road West Lowestoft Suffolk NR33 9EP",
    "addr:housenumber":"7",
    "addr:postcode":"nr33 9ep",
    "addr:street":"Elm Tree Road West",
    "iso:country":"GB",
    "sg:address":"7 Elm Tree Road West",
    "sg:city":"Lowestoft",
    "sg:classifiers":[
        {
            "category":"Professional",
            "type":"Services"
        }
    ],
    "sg:phone":"+44 1502 565189",
    "sg:postcode":"NR33 9EP",
    "sg:province":"Suffolk",
    "sg:tags":[
        "entertainer"
    ],
    "wof:name":"Haraldo & Julie",
    "wof:placetype":"venue"
},
  "geometry": {"coordinates":[1.7099319696,52.4619941711],"type":"Point"}
}