{
  "type": "Feature",
  "properties": {
    "addr:full":"59 Budleigh Cres Welling Kent DA16 1DX",
    "addr:housenumber":"59",
    "addr:postcode":"da16 1dx",
    "addr:street":"Budleigh Cres Welling",
    "iso:country":"GB",
    "sg:address":"59 Budleigh Cres",
    "sg:city":"Welling",
    "sg:classifiers":[
        {
            "category":"Building & Trades",
            "subcategory":"Construction",
            "type":"Services"
        }
    ],
    "sg:phone":"+44 20 8301 4665",
    "sg:postcode":"DA16 1DX",
    "sg:province":"Kent",
    "sg:tags":[
        "builder"
    ],
    "wof:name":"Carriages Building",
    "wof:placetype":"venue"
},
  "geometry": {"coordinates":[0.118098,51.47282],"type":"Point"}
}