{
  "type": "Feature",
  "properties": {
    "iso:country":"GB",
    "sg:address":"Moorbridge Road Est, Moorbridge Rd",
    "sg:city":"Nottingham",
    "sg:classifiers":[
        {
            "category":"Professional",
            "subcategory":"Printing & Photocopies",
            "type":"Services"
        }
    ],
    "sg:phone":"+44 1949 831030",
    "sg:postcode":"NG13 8GG",
    "sg:province":"Leicestershire",
    "sg:tags":[
        "computer",
        "tag",
        "label"
    ],
    "wof:name":"Brian Pulfrey Ltd",
    "wof:placetype":"venue"
},
  "geometry": {"coordinates":[-0.955581,52.956718],"type":"Point"}
}