{
  "type": "Feature",
  "properties": {
    "addr:full":"Godson St Oldham Lancashire OL1 2LS",
    "addr:postcode":"ol1 2ls",
    "addr:street":"Godson St",
    "iso:country":"GB",
    "sg:address":"Godson St",
    "sg:city":"Oldham",
    "sg:classifiers":[
        {
            "category":"Place Of Worship",
            "type":"Public Place"
        }
    ],
    "sg:phone":"+44 161 627 1640",
    "sg:postcode":"OL1 2LS",
    "sg:province":"Lancashire",
    "wof:name":"Holy Trinity Church",
    "wof:placetype":"venue"
},
  "geometry": {"coordinates":[-2.1189498901,53.5529136658],"type":"Point"}
}