{
  "type": "Feature",
  "properties": {
    "iso:country":"GB",
    "sg:address":"13 Queensmead",
    "sg:city":"Farnborough",
    "sg:classifiers":[
        {
            "category":"Professional",
            "subcategory":"Computer Services",
            "type":"Services"
        }
    ],
    "sg:phone":"+44 1252 542221",
    "sg:postcode":"GU14 7RG",
    "sg:province":"Hampshire",
    "sg:tags":[
        "system",
        "software"
    ],
    "wof:name":"The Technology Centre",
    "wof:placetype":"venue"
},
  "geometry": {"coordinates":[-0.755969,51.293301],"type":"Point"}
}