{
  "type": "Feature",
  "properties": {
    "addr:full":"Upland Road, Thornwood Epping Essex CM16 6NL",
    "addr:postcode":"cm16 6nl",
    "addr:street":"Upland Road",
    "iso:country":"GB",
    "sg:address":"Upland Road, Thornwood",
    "sg:city":"Epping",
    "sg:classifiers":[
        {
            "category":"Sports & Exercise",
            "subcategory":"Golf",
            "type":"Entertainment"
        }
    ],
    "sg:phone":"+44 1992 570707",
    "sg:postcode":"CM16 6NL",
    "sg:province":"Essex",
    "sg:tags":[
        "club",
        "range",
        "driving"
    ],
    "wof:name":"H & S LEISURE",
    "wof:placetype":"venue"
},
  "geometry": {"coordinates":[0.128565,51.721344],"type":"Point"}
}