{
  "type": "Feature",
  "properties": {
    "addr:full":"67 High St Hemel Hempstead Hertfordshire HP1 3AF",
    "addr:housenumber":"67",
    "addr:postcode":"hp1 3af",
    "addr:street":"High St",
    "iso:country":"GB",
    "sg:address":"67 High St",
    "sg:city":"Hemel Hempstead",
    "sg:classifiers":[
        {
            "category":"Professional",
            "subcategory":"Employment Agencies",
            "type":"Services"
        }
    ],
    "sg:phone":"+44 1442 219210",
    "sg:postcode":"HP1 3AF",
    "sg:province":"Hertfordshire",
    "sg:tags":[
        "consultant"
    ],
    "wof:name":"Firth & Associates",
    "wof:placetype":"venue"
},
  "geometry": {"coordinates":[-0.472351,51.759998],"type":"Point"}
}