{
  "type": "Feature",
  "properties": {
    "iso:country":"GB",
    "sg:address":"17 Verrington Rd",
    "sg:city":"Wincanton",
    "sg:classifiers":[
        {
            "category":"Taxi",
            "type":"Transportation"
        }
    ],
    "sg:phone":"+44 1963 824269",
    "sg:postcode":"BA9 9DA",
    "sg:province":"Somerset",
    "sg:tags":[
        "mini",
        "cab"
    ],
    "wof:name":"Wincanton Taxis",
    "wof:placetype":"venue"
},
  "geometry": {"coordinates":[-2.416808,51.057076],"type":"Point"}
}