{
  "type": "Feature",
  "properties": {
    "addr:full":"College Yard, Church Road, Wingfield Eye Norfolk IP21 5RA",
    "addr:postcode":"ip21 5ra",
    "addr:street":"College;Church Road",
    "iso:country":"GB",
    "sg:address":"College Yard, Church Road, Wingfield",
    "sg:city":"Eye",
    "sg:classifiers":[
        {
            "category":"Professional",
            "subcategory":"Business Services",
            "type":"Services"
        },
        {
            "category":"Community Center",
            "type":"Public Place"
        }
    ],
    "sg:phone":"+44 1379 384048",
    "sg:postcode":"IP21 5RA",
    "sg:province":"Norfolk",
    "sg:tags":[
        "entertainment",
        "centre",
        "trade"
    ],
    "wof:name":"Wingfield Arts & Music",
    "wof:placetype":"venue"
},
  "geometry": {"coordinates":[1.27072,52.347076],"type":"Point"}
}