{
  "type": "Feature",
  "properties": {
    "iso:country":"GB",
    "sg:address":"875 Shettleston Road",
    "sg:city":"Glasgow",
    "sg:classifiers":[
        {
            "category":"Bars & Pubs",
            "type":"Food & Drink"
        }
    ],
    "sg:phone":"+44 141 778 3859",
    "sg:postcode":"G32 7NR",
    "sg:province":"Glasgow City",
    "sg:tags":[
        "pubs",
        "inn"
    ],
    "wof:name":"The Cottage Bar",
    "wof:placetype":"venue"
},
  "geometry": {"coordinates":[-4.174767,55.852173],"type":"Point"}
}