{
  "type": "Feature",
  "properties": {
    "addr:full":"72 Ridgeway, Plymton Plymouth Devon PL7 2AL",
    "addr:housenumber":"72",
    "addr:postcode":"pl7 2al",
    "addr:street":"Ridgeway",
    "iso:country":"GB",
    "sg:address":"72 Ridgeway, Plymton",
    "sg:city":"Plymouth",
    "sg:classifiers":[
        {
            "category":"Personal",
            "subcategory":"Beauty Salon",
            "type":"Services"
        }
    ],
    "sg:phone":"+44 1752 336870",
    "sg:postcode":"PL7 2AL",
    "sg:province":"Devon",
    "sg:tags":[
        "lady",
        "hairdresser"
    ],
    "wof:name":"Angela's",
    "wof:placetype":"venue"
},
  "geometry": {"coordinates":[-4.051682,50.387596],"type":"Point"}
}