{
  "type": "Feature",
  "properties": {
    "iso:country":"GB",
    "sg:address":"Abbey Park",
    "sg:city":"Pershore",
    "sg:classifiers":[
        {
            "category":"Sports & Exercise",
            "subcategory":"Bowling",
            "type":"Entertainment"
        }
    ],
    "sg:phone":"+44 1386 561028",
    "sg:postcode":"WR10 1JP",
    "sg:province":"Worcestershire",
    "wof:name":"Pershore Bowling Club",
    "wof:placetype":"venue"
},
  "geometry": {"coordinates":[-2.079339,52.113766],"type":"Point"}
}