{
  "type": "Feature",
  "properties": {
    "addr:full":"Unit 4, St Stevens Business Centre Bristol Gloucestershire BS30 5JX",
    "addr:housenumber":"unit 4;business centre",
    "addr:postcode":"bs30 5jx",
    "addr:street":"St Stevens",
    "iso:country":"GB",
    "sg:address":"Unit 4, St Stevens Business Centre",
    "sg:city":"Bristol",
    "sg:classifiers":[
        {
            "category":"Shopping",
            "subcategory":"Stationery & Office Supplies",
            "type":"Retail Goods"
        }
    ],
    "sg:postcode":"BS30 5JX",
    "sg:province":"Gloucestershire",
    "sg:tags":[
        "printers'"
    ],
    "wof:name":"K B Graphic Reproductions Ltd.",
    "wof:placetype":"venue"
},
  "geometry": {"coordinates":[-2.4316449165,51.457950592],"type":"Point"}
}