{
  "type": "Feature",
  "properties": {
    "iso:country":"GB",
    "sg:address":"2 Station Lane, Featherstone",
    "sg:city":"Pontefract",
    "sg:classifiers":[
        {
            "category":"Shopping",
            "subcategory":"Pharmacy",
            "type":"Retail Goods"
        }
    ],
    "sg:phone":"+44 1977 791932",
    "sg:postcode":"WF7 5BE",
    "sg:province":"West Yorkshire",
    "sg:tags":[
        "pharmacist",
        "dispensing",
        "chemist"
    ],
    "wof:name":"Wright'S Chemists Ltd",
    "wof:placetype":"venue"
},
  "geometry": {"coordinates":[-1.358883,53.674866],"type":"Point"}
}