{
  "type": "Feature",
  "properties": {
    "addr:full":"The Warehouse, Checker Street King's Lynn Norfolk PE30 5AF",
    "addr:postcode":"pe30 5af",
    "addr:street":"Checker Street",
    "iso:country":"GB",
    "sg:address":"The Warehouse, Checker Street",
    "sg:city":"King's Lynn",
    "sg:classifiers":[
        {
            "category":"Shopping",
            "subcategory":"Clothing, Apparel, & Fashions",
            "type":"Retail Goods"
        }
    ],
    "sg:phone":"+44 1553 770014",
    "sg:postcode":"PE30 5AF",
    "sg:province":"Norfolk",
    "sg:tags":[
        "shop"
    ],
    "wof:name":"Yanks Ltd.",
    "wof:placetype":"venue"
},
  "geometry": {"coordinates":[0.39765,52.748859],"type":"Point"}
}