{
  "type": "Feature",
  "properties": {
    "iso:country":"GB",
    "sg:address":"47 Thorne Road, Thornton Lodge",
    "sg:city":"Huddersfield",
    "sg:classifiers":[
        {
            "category":"Building & Trades",
            "subcategory":"Cleaning & Sanitation",
            "type":"Services"
        }
    ],
    "sg:postcode":"HD1 3JJ",
    "sg:province":"West Yorkshire",
    "sg:tags":[
        "commercial"
    ],
    "wof:name":"Cotech (Uk) Ltd.",
    "wof:placetype":"venue"
},
  "geometry": {"coordinates":[-1.797964,53.637871],"type":"Point"}
}