{
  "type": "Feature",
  "properties": {
    "addr:full":"31 Green Street Ayr South Ayrshire KA8 8BQ",
    "addr:housenumber":"31",
    "addr:postcode":"ka8 8bq",
    "addr:street":"Green Street",
    "iso:country":"GB",
    "sg:address":"31 Green Street",
    "sg:city":"Ayr",
    "sg:classifiers":[
        {
            "category":"Bars & Pubs",
            "type":"Food & Drink"
        }
    ],
    "sg:phone":"+44 1292 267571",
    "sg:postcode":"KA8 8BQ",
    "sg:province":"South Ayrshire",
    "sg:tags":[
        "pubs",
        "inn"
    ],
    "wof:name":"The Wee Man's",
    "wof:placetype":"venue"
},
  "geometry": {"coordinates":[-4.6334061623,55.4685134888],"type":"Point"}
}