{
  "type": "Feature",
  "properties": {
    "addr:full":"21 Wyndham Street Bridgend Bridgend CF31 1ED",
    "addr:housenumber":"21",
    "addr:postcode":"cf31 1ed",
    "addr:street":"Wyndham Street",
    "iso:country":"GB",
    "sg:address":"21 Wyndham Street",
    "sg:city":"Bridgend",
    "sg:classifiers":[
        {
            "category":"Shopping",
            "subcategory":"Thrift Store",
            "type":"Retail Goods"
        }
    ],
    "sg:phone":"+44 1656 665298",
    "sg:postcode":"CF31 1ED",
    "sg:province":"Bridgend",
    "sg:tags":[
        "shop",
        "charity"
    ],
    "sg:website":"http://www.oxfam.org.uk",
    "wof:name":"Oxfam",
    "wof:placetype":"venue"
},
  "geometry": {"coordinates":[-3.578277,51.507504],"type":"Point"}
}