{
  "type": "Feature",
  "properties": {
    "addr:full":"20,broadhidley Drive, Bartley Green Birmingham West Midlands B32 3QN",
    "addr:housenumber":"20",
    "addr:postcode":"b32 3qn",
    "addr:street":"Broadhidley Drive",
    "iso:country":"GB",
    "sg:address":"20,broadhidley Drive, Bartley Green",
    "sg:city":"Birmingham",
    "sg:classifiers":[
        {
            "category":"Professional",
            "subcategory":"Computer Services",
            "type":"Services"
        }
    ],
    "sg:postcode":"B32 3QN",
    "sg:province":"West Midlands",
    "sg:tags":[
        "system",
        "software"
    ],
    "wof:name":"Plumpool Limited",
    "wof:placetype":"venue"
},
  "geometry": {"coordinates":[-2.0034620762,52.4392204285],"type":"Point"}
}