{
  "type": "Feature",
  "properties": {
    "addr:full":"2 The Pavilion Tonbridge Kent TN9 1TE",
    "addr:housenumber":"2",
    "addr:postcode":"tn9 1te",
    "addr:street":"The Pavilion",
    "iso:country":"GB",
    "sg:address":"2 The Pavilion",
    "sg:city":"Tonbridge",
    "sg:classifiers":[
        {
            "category":"Shopping",
            "subcategory":"Clothing, Apparel, & Fashions",
            "type":"Retail Goods"
        }
    ],
    "sg:phone":"+44 1732 362536",
    "sg:postcode":"TN9 1TE",
    "sg:province":"Kent",
    "sg:tags":[
        "menswear"
    ],
    "sg:website":"http://www.burton.co.uk",
    "wof:name":"Burton Menswear Ltd",
    "wof:placetype":"venue"
},
  "geometry": {"coordinates":[0.2731750011,51.1922531128],"type":"Point"}
}