{
  "type": "Feature",
  "properties": {
    "addr:full":"Buxton Road, Frettenham Norwich Norfolk NR12 7NH",
    "addr:postcode":"nr12 7nh",
    "addr:street":"Buxton Road",
    "iso:country":"GB",
    "sg:address":"Buxton Road, Frettenham",
    "sg:city":"Norwich",
    "sg:classifiers":[
        {
            "category":"Real Estate",
            "subcategory":"Developer",
            "type":"Services"
        }
    ],
    "sg:phone":"+44 1603 898252",
    "sg:postcode":"NR12 7NH",
    "sg:province":"Norfolk",
    "sg:tags":[
        "property"
    ],
    "wof:name":"NOVARA DEVELOPMENTS LTD",
    "wof:placetype":"venue"
},
  "geometry": {"coordinates":[1.314265,52.710522],"type":"Point"}
}