{
  "type": "Feature",
  "properties": {
    "addr:full":"Rustwood, Newchapel Road Lingfield Surrey RH7 6BJ",
    "addr:postcode":"rh7 6bj",
    "addr:street":"Newchapel Road",
    "iso:country":"GB",
    "sg:address":"Rustwood, Newchapel Road",
    "sg:city":"Lingfield",
    "sg:classifiers":[
        {
            "category":"Banks & Credit Unions",
            "subcategory":"Bank",
            "type":"Services"
        }
    ],
    "sg:phone":"+44 1342 836465",
    "sg:postcode":"RH7 6BJ",
    "sg:province":"Surrey",
    "sg:tags":[
        "broker",
        "mortgage"
    ],
    "wof:name":"Rustwood Independent Financial Services Ltd.",
    "wof:placetype":"venue"
},
  "geometry": {"coordinates":[-0.0196860004,51.1748199463],"type":"Point"}
}