{
  "type": "Feature",
  "properties": {
    "addr:full":"21 Cheam Road Sutton Surrey SM1 1SN",
    "addr:housenumber":"21",
    "addr:postcode":"sm1 1sn",
    "addr:street":"Cheam Road",
    "iso:country":"GB",
    "sg:address":"21 Cheam Road",
    "sg:city":"Sutton",
    "sg:classifiers":[
        {
            "category":"Place Of Worship",
            "type":"Public Place"
        }
    ],
    "sg:phone":"+44 20 8642 7390",
    "sg:postcode":"SM1 1SN",
    "sg:province":"Surrey",
    "wof:name":"Sutton Baptist Church",
    "wof:placetype":"venue"
},
  "geometry": {"coordinates":[-0.194184,51.361256],"type":"Point"}
}