{
  "type": "Feature",
  "properties": {
    "addr:full":"6a St Cross Road Winchester Hampshire SO23 9HX",
    "addr:housenumber":"6a",
    "addr:postcode":"so23 9hx",
    "addr:street":"St Cross Road",
    "iso:country":"GB",
    "sg:address":"6a St Cross Road",
    "sg:city":"Winchester",
    "sg:classifiers":[
        {
            "category":"Fast Food",
            "type":"Food & Drink"
        }
    ],
    "sg:phone":"+44 1962 877797",
    "sg:postcode":"SO23 9HX",
    "sg:province":"Hampshire",
    "sg:tags":[
        "away",
        "take"
    ],
    "wof:name":"West Sessex Tandori",
    "wof:placetype":"venue"
},
  "geometry": {"coordinates":[-1.318666,51.060047],"type":"Point"}
}