{
  "type": "Feature",
  "properties": {
    "iso:country":"GB",
    "sg:address":"21 West, Princes Street",
    "sg:city":"Helensburgh",
    "sg:classifiers":[
        {
            "category":"Food & Beverages",
            "subcategory":"Meat & Fish",
            "type":"Retail Goods"
        }
    ],
    "sg:postcode":"G84 8TF",
    "sg:province":"Argyll and Bute",
    "sg:tags":[
        "butcher"
    ],
    "wof:name":"Alex Sommerville",
    "wof:placetype":"venue"
},
  "geometry": {"coordinates":[-4.7344489098,56.0040512085],"type":"Point"}
}