{
  "type": "Feature",
  "properties": {
    "addr:full":"Bottlesford Pewsey Wiltshire SN9 6LW",
    "addr:postcode":"sn9 6lw",
    "addr:street":"Pewsey",
    "iso:country":"GB",
    "sg:address":"Bottlesford",
    "sg:city":"Pewsey",
    "sg:classifiers":[
        {
            "category":"Retail",
            "subcategory":"Auto Repair",
            "type":"Services"
        }
    ],
    "sg:postcode":"SN9 6LW",
    "sg:province":"Wiltshire",
    "sg:tags":[
        "body",
        "car"
    ],
    "wof:name":"Turner,Paul,",
    "wof:placetype":"venue"
},
  "geometry": {"coordinates":[-1.8330550194,51.3342056274],"type":"Point"}
}