{
  "type": "Feature",
  "properties": {
    "addr:full":"51 Woodhouse Road Whitehaven Cumbria CA28 9LL",
    "addr:housenumber":"51",
    "addr:postcode":"ca28 9ll",
    "addr:street":"Woodhouse Road",
    "iso:country":"GB",
    "sg:address":"51 Woodhouse Road",
    "sg:city":"Whitehaven",
    "sg:classifiers":[
        {
            "category":"Food & Beverages",
            "subcategory":"Meat & Fish",
            "type":"Retail Goods"
        }
    ],
    "sg:phone":"+44 1946 590040",
    "sg:postcode":"CA28 9LL",
    "sg:province":"Cumbria",
    "sg:tags":[
        "chip"
    ],
    "wof:name":"Edna's Plaice",
    "wof:placetype":"venue"
},
  "geometry": {"coordinates":[-3.5898270607,54.5304336548],"type":"Point"}
}