{
  "type": "Feature",
  "properties": {
    "iso:country":"GB",
    "sg:address":"Clifton Comprehensive School, Cranworth Road",
    "sg:city":"Rotherham",
    "sg:classifiers":[
        {
            "category":"Community Center",
            "subcategory":"Youth",
            "type":"Public Place"
        }
    ],
    "sg:phone":"+44 1709 828542",
    "sg:postcode":"S65 1LN",
    "sg:province":"South Yorkshire",
    "sg:tags":[
        "organisation",
        "centre"
    ],
    "wof:name":"Eastwood Youth & Community Centre",
    "wof:placetype":"venue"
},
  "geometry": {"coordinates":[-1.340879,53.437889],"type":"Point"}
}