{
  "type": "Feature",
  "properties": {
    "addr:full":"116 Galston Road, Hurlford Kilmarnock East Ayrshire KA1 5JB",
    "addr:housenumber":"116",
    "addr:postcode":"ka1 5jb",
    "addr:street":"Galston Road",
    "iso:country":"GB",
    "sg:address":"116 Galston Road, Hurlford",
    "sg:city":"Kilmarnock",
    "sg:classifiers":[
        {
            "category":"Autos & Motor Vehicles",
            "subcategory":"Automobile Sales",
            "type":"Retail Goods"
        }
    ],
    "sg:phone":"+44 1563 523688",
    "sg:postcode":"KA1 5JB",
    "sg:province":"East Ayrshire",
    "sg:tags":[
        "commercial"
    ],
    "wof:name":"Hurlford Van Sales",
    "wof:placetype":"venue"
},
  "geometry": {"coordinates":[-4.4448242188,55.60131073],"type":"Point"}
}