{
  "type": "Feature",
  "properties": {
    "iso:country":"GB",
    "sg:address":"10 Richardson Rd",
    "sg:city":"Hove",
    "sg:classifiers":[
        {
            "category":"Retail",
            "subcategory":"Repair Shop",
            "type":"Services"
        }
    ],
    "sg:phone":"+44 1273 735921",
    "sg:postcode":"BN3 5RB",
    "sg:province":"East Sussex",
    "sg:tags":[
        "clocks",
        "watch"
    ],
    "wof:name":"K.J West",
    "wof:placetype":"venue"
},
  "geometry": {"coordinates":[-0.1886,50.830669],"type":"Point"}
}