{
  "type": "Feature",
  "properties": {
    "iso:country":"GB",
    "sg:address":"Church View, Gisburn",
    "sg:city":"Clitheroe",
    "sg:classifiers":[
        {
            "category":"Travel",
            "subcategory":"Hotels & Motels",
            "type":"Entertainment"
        }
    ],
    "sg:phone":"+44 1200 445269",
    "sg:postcode":"BB7 4HG",
    "sg:province":"Lancashire",
    "sg:tags":[
        "house",
        "guest"
    ],
    "wof:name":"Park House Guest House",
    "wof:placetype":"venue"
},
  "geometry": {"coordinates":[-2.260546,53.935184],"type":"Point"}
}