{
  "type": "Feature",
  "properties": {
    "iso:country":"GB",
    "sg:address":"1 South Hawksworth Street",
    "sg:city":"Ilkley",
    "sg:classifiers":[
        {
            "category":"Education",
            "subcategory":"Dance Studio",
            "type":"Public Place"
        }
    ],
    "sg:phone":"+44 1943 602211",
    "sg:postcode":"LS29 9DX",
    "sg:province":"North Yorkshire",
    "sg:tags":[
        "school",
        "dancing"
    ],
    "wof:name":"Maureen Williams School of Dancing",
    "wof:placetype":"venue"
},
  "geometry": {"coordinates":[-1.8257329464,53.9259719849],"type":"Point"}
}