{
  "type": "Feature",
  "properties": {
    "iso:country":"GB",
    "sg:address":"Unit 4 Mariner, Litchfield Rd Indstl Est",
    "sg:city":"Tamworth",
    "sg:classifiers":[
        {
            "category":"Fast Food",
            "type":"Food & Drink"
        }
    ],
    "sg:postcode":"B79 7UL",
    "sg:province":"Staffordshire",
    "sg:tags":[
        "away",
        "take"
    ],
    "wof:name":"Davies,Roger,",
    "wof:placetype":"venue"
},
  "geometry": {"coordinates":[-1.71093,52.639458],"type":"Point"}
}