{
  "type": "Feature",
  "properties": {
    "addr:full":"Elmbrook House, 28 Willow La Estate, Mitcham Surrey Clerkenwell Greater London EC1M 4BE",
    "addr:housenumber":"28",
    "addr:postcode":"ec1m 4be",
    "addr:street":"Willow La Estate",
    "iso:country":"GB",
    "sg:address":"Elmbrook House, 28 Willow La Estate, Mitcham Surrey",
    "sg:city":"Clerkenwell",
    "sg:classifiers":[
        {
            "category":"Home & Garden",
            "subcategory":"Building Materials",
            "type":"Retail Goods"
        }
    ],
    "sg:phone":"+44 20 7253 6921",
    "sg:postcode":"EC1M 4BE",
    "sg:province":"Greater London",
    "sg:tags":[
        "furnishers",
        "bathroom",
        "planner"
    ],
    "wof:name":"Farmilowe & Farmilowe (WBS) Ltd",
    "wof:placetype":"venue"
},
  "geometry": {"coordinates":[-0.1022799984,51.5211296082],"type":"Point"}
}