{
  "type": "Feature",
  "properties": {
    "iso:country":"GB",
    "sg:address":"51 All Saints Green",
    "sg:city":"Norwich",
    "sg:classifiers":[
        {
            "category":"Real Estate",
            "subcategory":"Surveying",
            "type":"Services"
        },
        {
            "category":"Real Estate",
            "subcategory":"Architect",
            "type":"Services"
        }
    ],
    "sg:postcode":"NR1 3LY",
    "sg:province":"Norfolk",
    "sg:tags":[
        "surveyor",
        "valuer"
    ],
    "wof:name":"David Barrett & Co",
    "wof:placetype":"venue"
},
  "geometry": {"coordinates":[1.295015,52.624065],"type":"Point"}
}