{
  "type": "Feature",
  "properties": {
    "addr:full":"55 Sloane Street London Greater London SW1X 9SR",
    "addr:housenumber":"55",
    "addr:postcode":"sw1x 9sr",
    "addr:street":"Sloane Street",
    "iso:country":"GB",
    "sg:address":"55 Sloane Street",
    "sg:city":"London",
    "sg:classifiers":[
        {
            "category":"Building & Trades",
            "subcategory":"Pest Control",
            "type":"Services"
        }
    ],
    "sg:postcode":"SW1X 9SR",
    "sg:province":"Greater London",
    "sg:tags":[
        "-",
        "direct",
        "mortgage"
    ],
    "wof:name":"Reallcredit Danmark",
    "wof:placetype":"venue"
},
  "geometry": {"coordinates":[-0.1593270004,51.497795105],"type":"Point"}
}