{
  "type": "Feature",
  "properties": {
    "iso:country":"GB",
    "sg:address":"51 Station Road",
    "sg:city":"Burgess Hill",
    "sg:classifiers":[
        {
            "category":"Professional",
            "subcategory":"Computer Services",
            "type":"Services"
        }
    ],
    "sg:phone":"+44 1444 245290",
    "sg:postcode":"RH16 9DE",
    "sg:province":"East Sussex",
    "sg:tags":[
        "system",
        "software"
    ],
    "wof:name":"Johnson Technologies Ltd.",
    "wof:placetype":"venue"
},
  "geometry": {"coordinates":[-0.129722,50.954224],"type":"Point"}
}