{
  "type": "Feature",
  "properties": {
    "addr:full":"80 Leys Park Road Dunfermline Fife KY12 0AB",
    "addr:housenumber":"80",
    "addr:postcode":"ky12 0ab",
    "addr:street":"Leys Park Road",
    "iso:country":"GB",
    "sg:address":"80 Leys Park Road",
    "sg:city":"Dunfermline",
    "sg:classifiers":[
        {
            "category":"Health Services",
            "subcategory":"Nursing And Care Facility",
            "type":"Services"
        }
    ],
    "sg:phone":"+44 1383 723790",
    "sg:postcode":"KY12 0AB",
    "sg:province":"Fife",
    "sg:tags":[
        "home"
    ],
    "wof:name":"Leys Park Nursing Home",
    "wof:placetype":"venue"
},
  "geometry": {"coordinates":[-3.4448990822,56.0759811401],"type":"Point"}
}