{
  "type": "Feature",
  "properties": {
    "addr:full":"2 Verdant La London Greater London SE6 1LF",
    "addr:housenumber":"2",
    "addr:postcode":"se6 1lf",
    "addr:street":"Verdant La",
    "iso:country":"GB",
    "sg:address":"2 Verdant La",
    "sg:city":"London",
    "sg:classifiers":[
        {
            "category":"Travel",
            "subcategory":"Hostel",
            "type":"Entertainment"
        }
    ],
    "sg:phone":"+44 20 8695 5176",
    "sg:postcode":"SE6 1LF",
    "sg:province":"Greater London",
    "wof:name":"C C O Ltd",
    "wof:placetype":"venue"
},
  "geometry": {"coordinates":[0.0044880002,51.4445228577],"type":"Point"}
}