{
  "type": "Feature",
  "properties": {
    "iso:country":"GB",
    "sg:address":"10 Commercial Street",
    "sg:city":"Edinburgh",
    "sg:classifiers":[
        {
            "category":"Real Estate",
            "subcategory":"Architect",
            "type":"Services"
        }
    ],
    "sg:phone":"+44 131 553 2111",
    "sg:postcode":"EH6 6JA",
    "sg:province":"City of Edinburgh",
    "wof:name":"Holmes Partnership",
    "wof:placetype":"venue"
},
  "geometry": {"coordinates":[-3.17733,55.977688],"type":"Point"}
}