{
  "type": "Feature",
  "properties": {
    "iso:country":"GB",
    "sg:address":"Unit 12 City Business Centre, 6 Brighton Rd",
    "sg:city":"Horsham",
    "sg:classifiers":[
        {
            "category":"Education",
            "subcategory":"Special Training",
            "type":"Public Place"
        }
    ],
    "sg:phone":"+44 1403 276034",
    "sg:postcode":"RH13 5BA",
    "sg:province":"West Sussex",
    "sg:tags":[
        "product",
        "centre"
    ],
    "wof:name":"S D G International",
    "wof:placetype":"venue"
},
  "geometry": {"coordinates":[-0.3208900094,51.0599594116],"type":"Point"}
}