{
  "type": "Feature",
  "properties": {
    "addr:full":"44 Newman Street London Greater London W1T 1QD",
    "addr:housenumber":"44",
    "addr:postcode":"w1t 1qd",
    "addr:street":"Newman Street",
    "iso:country":"GB",
    "sg:address":"44 Newman Street",
    "sg:city":"London",
    "sg:classifiers":[
        {
            "category":"Real Estate",
            "subcategory":"Architect",
            "type":"Services"
        }
    ],
    "sg:phone":"+44 20 7255 1564",
    "sg:postcode":"W1T 1QD",
    "sg:province":"Greater London",
    "wof:name":"Sergison Bates",
    "wof:placetype":"venue"
},
  "geometry": {"coordinates":[-0.1365890056,51.5188560486],"type":"Point"}
}