{
  "type": "Feature",
  "properties": {
    "addr:full":"Hagley Mall, The Precinct Halesowen West Midlands B63 4AJ",
    "addr:postcode":"b63 4aj",
    "iso:country":"GB",
    "sg:address":"Hagley Mall, The Precinct",
    "sg:city":"Halesowen",
    "sg:classifiers":[
        {
            "category":"Food & Beverages",
            "subcategory":"Bakery",
            "type":"Retail Goods"
        }
    ],
    "sg:phone":"+44 121 550 4674",
    "sg:postcode":"B63 4AJ",
    "sg:province":"West Midlands",
    "sg:tags":[
        "baker"
    ],
    "wof:name":"Three Cooks Ltd.",
    "wof:placetype":"venue"
},
  "geometry": {"coordinates":[-2.0506989956,52.4504508972],"type":"Point"}
}