{
  "type": "Feature",
  "properties": {
    "iso:country":"GB",
    "sg:address":"Derby Road",
    "sg:city":"Croydon",
    "sg:classifiers":[
        {
            "category":"Place Of Worship",
            "type":"Public Place"
        }
    ],
    "sg:phone":"+44 20 8688 6094",
    "sg:postcode":"CR0 3SE",
    "sg:province":"Surrey",
    "wof:name":"Church of God 7th Day",
    "wof:placetype":"venue"
},
  "geometry": {"coordinates":[-0.103511,51.378048],"type":"Point"}
}