{
  "type": "Feature",
  "properties": {
    "addr:full":"The Goat House, Bristol Road, Brent Knoll Highbridge Somerset TA9 4HJ",
    "addr:postcode":"ta9 4hj",
    "addr:street":"Bristol Road",
    "iso:country":"GB",
    "sg:address":"The Goat House, Bristol Road, Brent Knoll",
    "sg:city":"Highbridge",
    "sg:classifiers":[
        {
            "category":"Retail",
            "subcategory":"Storage",
            "type":"Services"
        }
    ],
    "sg:postcode":"TA9 4HJ",
    "sg:province":"Somerset",
    "sg:tags":[
        "household",
        "removal"
    ],
    "wof:name":"A & D Direct",
    "wof:placetype":"venue"
},
  "geometry": {"coordinates":[-2.951374054,51.2381668091],"type":"Point"}
}