{
  "type": "Feature",
  "properties": {
    "addr:full":"Fog Close Farm, Kirkoswald Penrith Cumbria CA10 1JG",
    "addr:postcode":"ca10 1jg",
    "addr:street":"Fog Close",
    "iso:country":"GB",
    "sg:address":"Fog Close Farm, Kirkoswald",
    "sg:city":"Penrith",
    "sg:classifiers":[
        {
            "category":"Farming",
            "subcategory":"Livestock Farm",
            "type":"Manufacturing & Wholesale Goods"
        },
        {
            "category":"Farming",
            "subcategory":"Farm",
            "type":"Manufacturing & Wholesale Goods"
        }
    ],
    "sg:phone":"+44 1768 898345",
    "sg:postcode":"CA10 1JG",
    "sg:province":"Cumbria",
    "sg:tags":[
        "mixed",
        "crop"
    ],
    "wof:name":"R W S RAINE",
    "wof:placetype":"venue"
},
  "geometry": {"coordinates":[-2.693748951,54.7646484375],"type":"Point"}
}