{
  "type": "Feature",
  "properties": {
    "iso:country":"GB",
    "sg:address":"28 Goldhawk Rd",
    "sg:city":"London",
    "sg:classifiers":[
        {
            "category":"Shopping",
            "subcategory":"Clothing, Apparel, & Fashions",
            "type":"Retail Goods"
        }
    ],
    "sg:postcode":"W12 8DH",
    "sg:province":"Greater London",
    "sg:tags":[
        "shop",
        "hat"
    ],
    "wof:name":"Floral Hats & Designs",
    "wof:placetype":"venue"
},
  "geometry": {"coordinates":[-0.225366,51.502754],"type":"Point"}
}