{
  "type": "Feature",
  "properties": {
    "addr:full":"28 Baldorran Cres Glasgow East Dunbartonshire G68 9BL",
    "addr:housenumber":"28",
    "addr:postcode":"g68 9bl",
    "addr:street":"Baldorran Cres",
    "iso:country":"GB",
    "sg:address":"28 Baldorran Cres",
    "sg:city":"Glasgow",
    "sg:classifiers":[
        {
            "category":"Building & Trades",
            "subcategory":"Plumbing",
            "type":"Services"
        }
    ],
    "sg:postcode":"G68 9BL",
    "sg:province":"East Dunbartonshire",
    "sg:tags":[
        "heating"
    ],
    "wof:name":"McGinley,James,",
    "wof:placetype":"venue"
},
  "geometry": {"coordinates":[-4.0212302208,55.9531402588],"type":"Point"}
}