{
  "type": "Feature",
  "properties": {
    "iso:country":"GB",
    "sg:address":"91 Midland Road",
    "sg:city":"Peterborough",
    "sg:classifiers":[
        {
            "category":"Home & Garden",
            "subcategory":"Household Appliances",
            "type":"Retail Goods"
        }
    ],
    "sg:phone":"+44 1733 310008",
    "sg:postcode":"PE3 6DW",
    "sg:province":"Cambridgeshire",
    "sg:tags":[
        "electrical"
    ],
    "wof:name":"Domestic Repair Service",
    "wof:placetype":"venue"
},
  "geometry": {"coordinates":[-0.2549999952,52.5770797729],"type":"Point"}
}