{
  "type": "Feature",
  "properties": {
    "addr:full":"Bencombe Farm, Marlow Bottom Marlow Berkshire SL7 3LT",
    "addr:postcode":"sl7 3lt",
    "addr:street":"Bottom",
    "iso:country":"GB",
    "sg:address":"Bencombe Farm, Marlow Bottom",
    "sg:city":"Marlow",
    "sg:classifiers":[
        {
            "category":"Brewery",
            "type":"Food & Drink"
        }
    ],
    "sg:phone":"+44 1628 476594",
    "sg:postcode":"SL7 3LT",
    "sg:province":"Berkshire",
    "sg:tags":[
        "brewer"
    ],
    "wof:name":"Rebellion Beer Co Ltd",
    "wof:placetype":"venue"
},
  "geometry": {"coordinates":[-0.7833840251,51.5993499756],"type":"Point"}
}