{
  "type": "Feature",
  "properties": {
    "addr:full":"Mill Bank Farm, Chester Road, Hazel Gro Stockport Cheshire SK7 6EN",
    "addr:postcode":"sk7 6en",
    "addr:street":"Mill;Chester Road",
    "iso:country":"GB",
    "sg:address":"Mill Bank Farm, Chester Road, Hazel Gro",
    "sg:city":"Stockport",
    "sg:classifiers":[
        {
            "category":"Transit Center",
            "subcategory":"Passenger",
            "type":"Transportation"
        }
    ],
    "sg:postcode":"SK7 6EN",
    "sg:province":"Cheshire",
    "sg:tags":[
        "boarding",
        "kennel",
        "catteries"
    ],
    "wof:name":"Kozy Kennels",
    "wof:placetype":"venue"
},
  "geometry": {"coordinates":[-2.112734,53.367615],"type":"Point"}
}