{
  "type": "Feature",
  "properties": {
    "addr:full":"Chesham House, Chesham Close Romford Essex RM7 7PJ",
    "addr:postcode":"rm7 7pj",
    "addr:street":"Chesham Close",
    "iso:country":"GB",
    "sg:address":"Chesham House, Chesham Close",
    "sg:city":"Romford",
    "sg:classifiers":[
        {
            "category":"Taxi",
            "type":"Transportation"
        }
    ],
    "sg:phone":"+44 1708 737372",
    "sg:postcode":"RM7 7PJ",
    "sg:province":"Essex",
    "sg:tags":[
        "mini",
        "cab"
    ],
    "wof:name":"H & H Mini Cabs",
    "wof:placetype":"venue"
},
  "geometry": {"coordinates":[0.1726559997,51.5834922791],"type":"Point"}
}