{
  "type": "Feature",
  "properties": {
    "addr:full":"1472 Leeds Rd Bradford West Yorkshire BD3 7AA",
    "addr:housenumber":"1472",
    "addr:postcode":"bd3 7aa",
    "addr:street":"Leeds Rd",
    "iso:country":"GB",
    "sg:address":"1472 Leeds Rd",
    "sg:city":"Bradford",
    "sg:classifiers":[
        {
            "category":"Communications",
            "type":"Services"
        }
    ],
    "sg:phone":"+44 1274 786100",
    "sg:postcode":"BD3 7AA",
    "sg:province":"West Yorkshire",
    "sg:tags":[
        "telecommunication"
    ],
    "wof:name":"Mobile Phone Shop",
    "wof:placetype":"venue"
},
  "geometry": {"coordinates":[-1.708195,53.800674],"type":"Point"}
}