{
  "type": "Feature",
  "properties": {
    "iso:country":"GB",
    "sg:address":"Canterbury Business Centre, 37 Old Dover Rd",
    "sg:city":"Canterbury",
    "sg:classifiers":[
        {
            "category":"Banks & Credit Unions",
            "subcategory":"Bank",
            "type":"Services"
        }
    ],
    "sg:phone":"+44 1227 783939",
    "sg:postcode":"CT1 3JB",
    "sg:province":"Kent",
    "wof:name":"NatWest",
    "wof:placetype":"venue"
},
  "geometry": {"coordinates":[1.07561,51.27597],"type":"Point"}
}