{
  "type": "Feature",
  "properties": {
    "iso:country":"GB",
    "sg:address":"Ivydene, Listoft, Hogsthorpe",
    "sg:city":"Skegness",
    "sg:classifiers":[
        {
            "category":"Farming",
            "subcategory":"Livestock Farm",
            "type":"Manufacturing & Wholesale Goods"
        }
    ],
    "sg:postcode":"PE24 5PF",
    "sg:province":"Lincolnshire",
    "sg:tags":[
        "others"
    ],
    "wof:name":"F B & G Coxhead",
    "wof:placetype":"venue"
},
  "geometry": {"coordinates":[0.30132,53.22419],"type":"Point"}
}