{
  "type": "Feature",
  "properties": {
    "iso:country":"GB",
    "sg:address":"Unit 3 Osbourne House, Station Road",
    "sg:city":"New Milton",
    "sg:classifiers":[
        {
            "category":"Shopping",
            "subcategory":"Clothing, Apparel, & Fashions",
            "type":"Retail Goods"
        }
    ],
    "sg:postcode":"BH25 6HL",
    "sg:province":"Hampshire",
    "sg:tags":[
        "shop"
    ],
    "wof:name":"Catalogue Returns",
    "wof:placetype":"venue"
},
  "geometry": {"coordinates":[-1.6566040516,50.7559814453],"type":"Point"}
}