{
  "type": "Feature",
  "properties": {
    "addr:full":"Dallas Rd Chippenham Wiltshire SN15 1LE",
    "addr:postcode":"sn15 1le",
    "addr:street":"Dallas Rd",
    "iso:country":"GB",
    "sg:address":"Dallas Rd",
    "sg:city":"Chippenham",
    "sg:classifiers":[
        {
            "category":"Government",
            "subcategory":"Fire Station",
            "type":"Public Place"
        }
    ],
    "sg:phone":"+44 1249 651624",
    "sg:postcode":"SN15 1LE",
    "sg:province":"Wiltshire",
    "wof:name":"Dallas Road Fire Station",
    "wof:placetype":"venue"
},
  "geometry": {"coordinates":[-2.120739,51.461544],"type":"Point"}
}