{
  "type": "Feature",
  "properties": {
    "addr:full":"172 Bournemouth Road Poole Dorset BH14 9HY",
    "addr:housenumber":"172",
    "addr:postcode":"bh14 9hy",
    "addr:street":"Bournemouth Road",
    "iso:country":"GB",
    "sg:address":"172 Bournemouth Road",
    "sg:city":"Poole",
    "sg:classifiers":[
        {
            "category":"Freight",
            "type":"Transportation"
        }
    ],
    "sg:phone":"+44 1202 740522",
    "sg:postcode":"BH14 9HY",
    "sg:province":"Dorset",
    "sg:tags":[
        "haulage",
        "transport",
        "road"
    ],
    "wof:name":"M G M TRANSPORT SERVICES",
    "wof:placetype":"venue"
},
  "geometry": {"coordinates":[-1.9339410067,50.724395752],"type":"Point"}
}