{
  "type": "Feature",
  "properties": {
    "iso:country":"GB",
    "sg:address":"54 High Street",
    "sg:city":"Glastonbury",
    "sg:classifiers":[
        {
            "category":"Food & Beverages",
            "subcategory":"Fruits & Vegetables",
            "type":"Retail Goods"
        }
    ],
    "sg:postcode":"BA6 9DY",
    "sg:province":"Somerset",
    "sg:tags":[
        "greengrocer"
    ],
    "wof:name":"Top of the Crops",
    "wof:placetype":"venue"
},
  "geometry": {"coordinates":[-2.714717,51.147778],"type":"Point"}
}