{
  "type": "Feature",
  "properties": {
    "iso:country":"GB",
    "sg:address":"Fron Deg Park Road",
    "sg:city":"Ruthin",
    "sg:classifiers":[
        {
            "category":"Communications",
            "subcategory":"Film & Video Production",
            "type":"Services"
        }
    ],
    "sg:phone":"+44 1824 704223",
    "sg:postcode":"LL15 1NB",
    "sg:province":"Denbighshire",
    "sg:tags":[
        "illustrator",
        "artist"
    ],
    "wof:name":"Derek Roberts",
    "wof:placetype":"venue"
},
  "geometry": {"coordinates":[-3.304522,53.114017],"type":"Point"}
}