{
  "type": "Feature",
  "properties": {
    "iso:country":"GB",
    "sg:address":"Unit 17 Thornleigh Trading Estate",
    "sg:city":"Dudley",
    "sg:classifiers":[
        {
            "category":"Professional",
            "subcategory":"Printing & Photocopies",
            "type":"Services"
        }
    ],
    "sg:phone":"+44 1384 253048",
    "sg:postcode":"DY2 8UB",
    "sg:province":"West Midlands",
    "sg:tags":[
        "plate",
        "lithographic",
        "maker"
    ],
    "wof:name":"F O S Midlands",
    "wof:placetype":"venue"
},
  "geometry": {"coordinates":[-2.093204,52.500546],"type":"Point"}
}