{
  "type": "Feature",
  "properties": {
    "iso:country":"GB",
    "sg:address":"Brookwall Farm, Wirksworth",
    "sg:city":"Matlock",
    "sg:classifiers":[
        {
            "category":"Building & Trades",
            "subcategory":"Construction",
            "type":"Services"
        }
    ],
    "sg:postcode":"DE4 4AF",
    "sg:province":"Derbyshire",
    "sg:tags":[
        "joiner",
        "carpenter"
    ],
    "wof:name":"Hilda Wood",
    "wof:placetype":"venue"
},
  "geometry": {"coordinates":[-1.574056,53.082214],"type":"Point"}
}