{
  "type": "Feature",
  "properties": {
    "addr:full":"40 Meadowmead Avenue Southampton Hampshire SO15 4LX",
    "addr:housenumber":"40",
    "addr:postcode":"so15 4lx",
    "addr:street":"Meadowmead Avenue",
    "iso:country":"GB",
    "sg:address":"40 Meadowmead Avenue",
    "sg:city":"Southampton",
    "sg:classifiers":[
        {
            "category":"Building & Trades",
            "subcategory":"Construction",
            "type":"Services"
        }
    ],
    "sg:phone":"+44 23 8077 4417",
    "sg:postcode":"SO15 4LX",
    "sg:province":"Hampshire",
    "sg:tags":[
        "builder"
    ],
    "wof:name":"C A N Maunders",
    "wof:placetype":"venue"
},
  "geometry": {"coordinates":[-1.443934,50.919106],"type":"Point"}
}