{
  "type": "Feature",
  "properties": {
    "iso:country":"GB",
    "sg:address":"25 Nursery Park, Delamere Road, Norley",
    "sg:city":"Warrington",
    "sg:classifiers":[
        {
            "category":"Health Services",
            "subcategory":"Health Practitioner",
            "type":"Services"
        }
    ],
    "sg:postcode":"WA6 6LX",
    "sg:province":"Cheshire",
    "sg:tags":[
        "osteopath"
    ],
    "wof:name":"Willams Osteopathic Clinic",
    "wof:placetype":"venue"
},
  "geometry": {"coordinates":[-2.67897,53.254238],"type":"Point"}
}