{
  "type": "Feature",
  "properties": {
    "addr:full":"14 Bond Road Mitcham Greater London CR4 3HE",
    "addr:housenumber":"14",
    "addr:postcode":"cr4 3he",
    "addr:street":"Bond Road",
    "iso:country":"GB",
    "sg:address":"14 Bond Road",
    "sg:city":"Mitcham",
    "sg:classifiers":[
        {
            "category":"Professional",
            "subcategory":"Printing & Photocopies",
            "type":"Services"
        }
    ],
    "sg:phone":"+44 20 8648 0577",
    "sg:postcode":"CR4 3HE",
    "sg:province":"Greater London",
    "sg:tags":[
        "printer"
    ],
    "wof:name":"Carlvenas Ltd.",
    "wof:placetype":"venue"
},
  "geometry": {"coordinates":[-0.1629299968,51.4099121094],"type":"Point"}
}