{
  "type": "Feature",
  "properties": {
    "addr:full":"Leigh Court, Leigh Street High Wycombe Buckinghamshire HP11 2RH",
    "addr:postcode":"hp11 2rh",
    "addr:street":"Leigh Court Leigh Street",
    "iso:country":"GB",
    "sg:address":"Leigh Court, Leigh Street",
    "sg:city":"High Wycombe",
    "sg:classifiers":[
        {
            "category":"Home & Garden",
            "subcategory":"Building Materials",
            "type":"Retail Goods"
        }
    ],
    "sg:phone":"+44 1494 447477",
    "sg:postcode":"HP11 2RH",
    "sg:province":"Buckinghamshire",
    "sg:tags":[
        "veneer"
    ],
    "wof:name":"John Wilde Ltd.",
    "wof:placetype":"venue"
},
  "geometry": {"coordinates":[-0.7643790245,51.6316108704],"type":"Point"}
}