{
  "type": "Feature",
  "properties": {
    "iso:country":"GB",
    "sg:address":"589 London Road",
    "sg:city":"Westcliff-on-sea",
    "sg:classifiers":[
        {
            "category":"Professional",
            "subcategory":"Accounting & Tax Preparation",
            "type":"Services"
        }
    ],
    "sg:phone":"+44 1702 339963",
    "sg:postcode":"SS0 9PQ",
    "sg:province":"Essex",
    "sg:tags":[
        "accountant"
    ],
    "wof:name":"Bookcomp Ltd.",
    "wof:placetype":"venue"
},
  "geometry": {"coordinates":[0.6862490177,51.5454521179],"type":"Point"}
}