{
  "type": "Feature",
  "properties": {
    "addr:full":"81 Bowerham Road Lancaster Lancashire LA1 4AQ",
    "addr:housenumber":"81",
    "addr:postcode":"la1 4aq",
    "addr:street":"Bowerham Road",
    "iso:country":"GB",
    "sg:address":"81 Bowerham Road",
    "sg:city":"Lancaster",
    "sg:classifiers":[
        {
            "category":"Personal",
            "subcategory":"Beauty Salon",
            "type":"Services"
        },
        {
            "category":"Personal",
            "subcategory":"Barber",
            "type":"Services"
        }
    ],
    "sg:phone":"+44 1524 63045",
    "sg:postcode":"LA1 4AQ",
    "sg:province":"Lancashire",
    "sg:tags":[
        "unisex",
        "hairdresser"
    ],
    "wof:name":"Hair Care",
    "wof:placetype":"venue"
},
  "geometry": {"coordinates":[-2.7893950939,54.0376548767],"type":"Point"}
}