{
  "type": "Feature",
  "properties": {
    "iso:country":"GB",
    "sg:address":"55 Packsaddle Way",
    "sg:city":"Frome",
    "sg:classifiers":[
        {
            "category":"Freight",
            "type":"Transportation"
        }
    ],
    "sg:phone":"+44 7860 349888",
    "sg:postcode":"BA11 2RW",
    "sg:province":"Somerset",
    "sg:tags":[
        "haulage",
        "transport",
        "road"
    ],
    "wof:name":"G C H TRANSPORT",
    "wof:placetype":"venue"
},
  "geometry": {"coordinates":[-2.3233940601,51.2416763306],"type":"Point"}
}