{
  "type": "Feature",
  "properties": {
    "addr:full":"31 Leslie Street Blairgowrie Perth and Kinross PH10 6AH",
    "addr:housenumber":"31",
    "addr:postcode":"ph10 6ah",
    "addr:street":"Leslie Street",
    "iso:country":"GB",
    "sg:address":"31 Leslie Street",
    "sg:city":"Blairgowrie",
    "sg:classifiers":[
        {
            "category":"Organizations",
            "subcategory":"Community Association",
            "type":"Services"
        }
    ],
    "sg:phone":"+44 1250 874478",
    "sg:postcode":"PH10 6AH",
    "sg:province":"Perth and Kinross",
    "sg:tags":[
        "society",
        "housing"
    ],
    "wof:name":"Perthshire Housing Association",
    "wof:placetype":"venue"
},
  "geometry": {"coordinates":[-3.33852,56.59174],"type":"Point"}
}