{
  "type": "Feature",
  "properties": {
    "addr:full":"Unit 2d Nupen Business Centre, Old Nebworth Hertford Hertfordshire SG3 6QJ",
    "addr:housenumber":"unit;nupen business centre",
    "addr:postcode":"sg3 6qj",
    "addr:street":"Old Nebworth Hertford",
    "iso:country":"GB",
    "sg:address":"Unit 2d Nupen Business Centre, Old Nebworth",
    "sg:city":"Hertford",
    "sg:classifiers":[
        {
            "category":"Building & Trades",
            "subcategory":"Construction",
            "type":"Services"
        }
    ],
    "sg:phone":"+44 1438 821778",
    "sg:postcode":"SG3 6QJ",
    "sg:province":"Hertfordshire",
    "sg:tags":[
        "builder"
    ],
    "wof:name":"Trinity Developments",
    "wof:placetype":"venue"
},
  "geometry": {"coordinates":[-0.2213200033,51.8633804321],"type":"Point"}
}