{
  "type": "Feature",
  "properties": {
    "iso:country":"GB",
    "sg:address":"134 Dundee Street",
    "sg:city":"Carnoustie",
    "sg:classifiers":[
        {
            "category":"Cinema",
            "subcategory":"Movie Rental",
            "type":"Entertainment"
        }
    ],
    "sg:phone":"+44 1241 855886",
    "sg:postcode":"DD7 7PP",
    "sg:province":"Angus",
    "sg:tags":[
        "video",
        "library"
    ],
    "wof:name":"Visions (Scotland) Ltd.",
    "wof:placetype":"venue"
},
  "geometry": {"coordinates":[-2.722059,56.500912],"type":"Point"}
}