{
  "type": "Feature",
  "properties": {
    "iso:country":"GB",
    "sg:address":"Hope Cove",
    "sg:city":"Kingsbridge",
    "sg:classifiers":[
        {
            "category":"Travel",
            "subcategory":"Hotels & Motels",
            "type":"Entertainment"
        }
    ],
    "sg:phone":"+44 1548 561673",
    "sg:postcode":"TQ7 3HF",
    "sg:province":"Devon",
    "wof:name":"Sand Pebbles Hotel",
    "wof:placetype":"venue"
},
  "geometry": {"coordinates":[-3.859208,50.242207],"type":"Point"}
}