{
  "type": "Feature",
  "properties": {
    "addr:full":"Ross House, Ross Way Folkestone Kent CT20 3UJ",
    "addr:postcode":"ct20 3uj",
    "addr:street":"Ross Way",
    "iso:country":"GB",
    "sg:address":"Ross House, Ross Way",
    "sg:city":"Folkestone",
    "sg:classifiers":[
        {
            "category":"Utilities",
            "subcategory":"Refuse",
            "type":"Services"
        }
    ],
    "sg:phone":"+44 1303 240711",
    "sg:postcode":"CT20 3UJ",
    "sg:province":"Kent",
    "sg:tags":[
        "disposal",
        "waste"
    ],
    "wof:name":"South Herts Waste Management",
    "wof:placetype":"venue"
},
  "geometry": {"coordinates":[1.1412,51.081291],"type":"Point"}
}