{
  "type": "Feature",
  "properties": {
    "addr:full":"77 Regent St Cambridge Cambridgeshire CB2 1AW",
    "addr:housenumber":"77",
    "addr:postcode":"cb2 1aw",
    "addr:street":"Regent St",
    "iso:country":"GB",
    "sg:address":"77 Regent St",
    "sg:city":"Cambridge",
    "sg:classifiers":[
        {
            "category":"Cafe",
            "type":"Food & Drink"
        }
    ],
    "sg:phone":"+44 1223 508013",
    "sg:postcode":"CB2 1AW",
    "sg:province":"Cambridgeshire",
    "sg:tags":[
        "tea",
        "room"
    ],
    "wof:name":"The Bun Shop",
    "wof:placetype":"venue"
},
  "geometry": {"coordinates":[0.126577,52.200413],"type":"Point"}
}