{
  "type": "Feature",
  "properties": {
    "addr:full":"Wesley Rd Leeds West Yorkshire LS12 1SR",
    "addr:postcode":"ls12 1sr",
    "addr:street":"Wesley Rd",
    "iso:country":"GB",
    "sg:address":"Wesley Rd",
    "sg:city":"Leeds",
    "sg:classifiers":[
        {
            "category":"Building & Trades",
            "subcategory":"Construction",
            "type":"Services"
        }
    ],
    "sg:phone":"+44 113 263 1116",
    "sg:postcode":"LS12 1SR",
    "sg:province":"West Yorkshire",
    "sg:tags":[
        "joiner",
        "carpenter"
    ],
    "wof:name":"M C Joiners",
    "wof:placetype":"venue"
},
  "geometry": {"coordinates":[-1.588534,53.797047],"type":"Point"}
}