{
  "type": "Feature",
  "properties": {
    "iso:country":"GB",
    "sg:address":"3a Drybriggs Balgarvie Rd",
    "sg:city":"Cupar",
    "sg:classifiers":[
        {
            "category":"Landmark",
            "subcategory":"Tourist Information",
            "type":"Public Place"
        }
    ],
    "sg:phone":"+44 1334 655057",
    "sg:postcode":"KY15 4AJ",
    "sg:province":"Fife",
    "sg:tags":[
        "tour",
        "guide",
        "sightseeing"
    ],
    "wof:name":"The Original St. Andrews Witches Tour",
    "wof:placetype":"venue"
},
  "geometry": {"coordinates":[-3.023852,56.319145],"type":"Point"}
}