{
  "type": "Feature",
  "properties": {
    "addr:full":"2 Cross La Newport Newport NP20 1ES",
    "addr:housenumber":"2",
    "addr:postcode":"np20 1es",
    "addr:street":"Cross La Newport",
    "iso:country":"GB",
    "sg:address":"2 Cross La",
    "sg:city":"Newport",
    "sg:classifiers":[
        {
            "category":"Manufacturing",
            "subcategory":"Pottery",
            "type":"Manufacturing & Wholesale Goods"
        }
    ],
    "sg:postcode":"NP20 1ES",
    "sg:province":"Newport",
    "wof:name":"Goldcrest Ceramics",
    "wof:placetype":"venue"
},
  "geometry": {"coordinates":[-2.991492033,51.5845451355],"type":"Point"}
}