{
  "type": "Feature",
  "properties": {
    "addr:full":"69 Sinclair Street Helensburgh Argyll and Bute G84 8TG",
    "addr:housenumber":"69",
    "addr:postcode":"g84 8tg",
    "addr:street":"Sinclair Street",
    "iso:country":"GB",
    "sg:address":"69 Sinclair Street",
    "sg:city":"Helensburgh",
    "sg:classifiers":[
        {
            "category":"Social Services",
            "subcategory":"Adult Care",
            "type":"Services"
        }
    ],
    "sg:phone":"+44 1436 671389",
    "sg:postcode":"G84 8TG",
    "sg:province":"Argyll and Bute",
    "sg:tags":[
        "home",
        "help",
        "private"
    ],
    "wof:name":"Carers Direct Agency",
    "wof:placetype":"venue"
},
  "geometry": {"coordinates":[-4.7333650589,56.0047073364],"type":"Point"}
}