{
  "type": "Feature",
  "properties": {
    "addr:full":"303 Chase Road, Southgate London Greater London N14 6JB",
    "addr:housenumber":"303",
    "addr:postcode":"n14 6jb",
    "addr:street":"Chase Road",
    "iso:country":"GB",
    "sg:address":"303 Chase Road, Southgate",
    "sg:city":"London",
    "sg:classifiers":[
        {
            "category":"Shopping",
            "subcategory":"Pharmacy",
            "type":"Retail Goods"
        }
    ],
    "sg:phone":"+44 870 873 4900",
    "sg:postcode":"N14 6JB",
    "sg:province":"Greater London",
    "sg:tags":[
        "medical"
    ],
    "wof:name":"Southern Syringe Services Ltd.",
    "wof:placetype":"venue"
},
  "geometry": {"coordinates":[-0.12753,51.633743],"type":"Point"}
}