{
  "type": "Feature",
  "properties": {
    "iso:country":"GB",
    "sg:address":"395 Edgware Road, Colindale",
    "sg:city":"London",
    "sg:classifiers":[
        {
            "category":"Manufacturing",
            "subcategory":"Tools & Machinery",
            "type":"Manufacturing & Wholesale Goods"
        }
    ],
    "sg:phone":"+44 20 8200 0996",
    "sg:postcode":"NW9 6NJ",
    "sg:province":"Greater London",
    "sg:tags":[
        "society",
        "friendly"
    ],
    "wof:name":"Alpine Insurance Services Ltd.",
    "wof:placetype":"venue"
},
  "geometry": {"coordinates":[-0.256124,51.591095],"type":"Point"}
}