{
  "type": "Feature",
  "properties": {
    "addr:full":"32-34 Main Street, Busby Glasgow East Renfrewshire G76 8DX",
    "addr:housenumber":"32-34",
    "addr:postcode":"g76 8dx",
    "addr:street":"Main Street",
    "iso:country":"GB",
    "sg:address":"32-34 Main Street, Busby",
    "sg:city":"Glasgow",
    "sg:classifiers":[
        {
            "category":"Professional",
            "type":"Services"
        },
        {
            "category":"Professional",
            "subcategory":"Art Services",
            "type":"Services"
        }
    ],
    "sg:phone":"+44 141 644 3521",
    "sg:postcode":"G76 8DX",
    "sg:province":"East Renfrewshire",
    "sg:tags":[
        "interior",
        "furnishers",
        "designer"
    ],
    "wof:name":"Busby Interiors Ltd.",
    "wof:placetype":"venue"
},
  "geometry": {"coordinates":[-4.267274,55.781857],"type":"Point"}
}