{
  "type": "Feature",
  "properties": {
    "iso:country":"GB",
    "sg:address":"256a Ongar Road",
    "sg:city":"Brentwood",
    "sg:classifiers":[
        {
            "category":"Health Services",
            "subcategory":"Nursing And Care Facility",
            "type":"Services"
        }
    ],
    "sg:phone":"+44 1277 202270",
    "sg:postcode":"CM15 9DX",
    "sg:province":"Essex",
    "sg:tags":[
        "home"
    ],
    "wof:name":"The Hedgerows Nursing Home",
    "wof:placetype":"venue"
},
  "geometry": {"coordinates":[0.296143,51.627567],"type":"Point"}
}