{
  "type": "Feature",
  "properties": {
    "addr:full":"Monument Hill Weybridge Surrey KT13 8RJ",
    "addr:postcode":"kt13 8rj",
    "addr:street":"Monument Hill Weybridge",
    "iso:country":"GB",
    "sg:address":"Monument Hill",
    "sg:city":"Weybridge",
    "sg:classifiers":[
        {
            "category":"Bars & Pubs",
            "type":"Food & Drink"
        }
    ],
    "sg:phone":"+44 1932 842480",
    "sg:postcode":"KT13 8RJ",
    "sg:province":"Surrey",
    "sg:tags":[
        "pubs",
        "inn"
    ],
    "wof:name":"E Brookfield",
    "wof:placetype":"venue"
},
  "geometry": {"coordinates":[-0.4553540051,51.3736114502],"type":"Point"}
}