{
  "type": "Feature",
  "properties": {
    "addr:full":"66 First Avenue Chelmsford Essex CM1 1RU",
    "addr:housenumber":"66",
    "addr:postcode":"cm1 1ru",
    "addr:street":"First Avenue",
    "iso:country":"GB",
    "sg:address":"66 First Avenue",
    "sg:city":"Chelmsford",
    "sg:classifiers":[
        {
            "category":"Retail",
            "subcategory":"Driving School",
            "type":"Services"
        }
    ],
    "sg:phone":"+44 1245 269883",
    "sg:postcode":"CM1 1RU",
    "sg:province":"Essex",
    "wof:name":"Lawrence Driving School",
    "wof:placetype":"venue"
},
  "geometry": {"coordinates":[0.4712879956,51.74634552],"type":"Point"}
}