{
  "type": "Feature",
  "properties": {
    "addr:full":"P O Box 168 Doncaster South Yorkshire DN4 7EY",
    "addr:housenumber":"168",
    "addr:postcode":"dn4 7ey",
    "addr:street":"P O Box",
    "iso:country":"GB",
    "sg:address":"P O Box 168",
    "sg:city":"Doncaster",
    "sg:classifiers":[
        {
            "category":"Professional",
            "subcategory":"Engineering",
            "type":"Services"
        }
    ],
    "sg:phone":"+44 1302 533598",
    "sg:postcode":"DN4 7EY",
    "sg:province":"South Yorkshire",
    "sg:tags":[
        "contractor",
        "electrical",
        "engineer"
    ],
    "wof:name":"A W Gibbs",
    "wof:placetype":"venue"
},
  "geometry": {"coordinates":[-1.0873800516,53.5012817383],"type":"Point"}
}