{
  "type": "Feature",
  "properties": {
    "addr:full":"Salesbrook Farm, Aston Nantwich Cheshire CW5 8DS",
    "addr:postcode":"cw5 8ds",
    "iso:country":"GB",
    "sg:address":"Salesbrook Farm, Aston",
    "sg:city":"Nantwich",
    "sg:classifiers":[
        {
            "category":"Farming",
            "subcategory":"Livestock Farm",
            "type":"Manufacturing & Wholesale Goods"
        }
    ],
    "sg:phone":"+44 1270 780223",
    "sg:postcode":"CW5 8DS",
    "sg:province":"Cheshire",
    "sg:tags":[
        "others"
    ],
    "wof:name":"David Shore",
    "wof:placetype":"venue"
},
  "geometry": {"coordinates":[-2.5789740086,53.0152626038],"type":"Point"}
}