{
  "type": "Feature",
  "properties": {
    "iso:country":"GB",
    "sg:address":"Bradd Ho, Manchester Rd",
    "sg:city":"Bradford",
    "sg:classifiers":[
        {
            "category":"Wholesale",
            "subcategory":"Music Publishers",
            "type":"Manufacturing & Wholesale Goods"
        }
    ],
    "sg:phone":"+44 1274 400710",
    "sg:postcode":"BD5 7AG",
    "sg:province":"West Yorkshire",
    "sg:tags":[
        "record"
    ],
    "wof:name":"1st Music Shop",
    "wof:placetype":"venue"
},
  "geometry": {"coordinates":[-1.7598839998,53.7806091309],"type":"Point"}
}