{
  "type": "Feature",
  "properties": {
    "iso:country":"GB",
    "sg:address":"Weirview 7 St. Lukes Rd, Dukestown",
    "sg:city":"Tredegar",
    "sg:classifiers":[
        {
            "category":"Shopping",
            "subcategory":"Musical Instruments",
            "type":"Retail Goods"
        }
    ],
    "sg:phone":"+44 1495 717866",
    "sg:postcode":"NP22 4EW",
    "sg:province":"Blaenau Gwent",
    "wof:name":"Presto Brass",
    "wof:placetype":"venue"
},
  "geometry": {"coordinates":[-3.2505021095,51.7873268127],"type":"Point"}
}