{
  "type": "Feature",
  "properties": {
    "addr:full":"175 South Ealing Rd Ealing Greater London W5 4QP",
    "addr:housenumber":"175",
    "addr:postcode":"w5 4qp",
    "addr:street":"South Ealing Rd",
    "iso:country":"GB",
    "sg:address":"175 South Ealing Rd",
    "sg:city":"Ealing",
    "sg:classifiers":[
        {
            "category":"Deli",
            "type":"Food & Drink"
        }
    ],
    "sg:phone":"+44 20 8847 1740",
    "sg:postcode":"W5 4QP",
    "sg:province":"Greater London",
    "sg:tags":[
        "delivery",
        "sandwich"
    ],
    "wof:name":"As You Like It",
    "wof:placetype":"venue"
},
  "geometry": {"coordinates":[-0.3056550026,51.4978179932],"type":"Point"}
}