{
  "type": "Feature",
  "properties": {
    "iso:country":"GB",
    "sg:address":"274 Archway Road",
    "sg:city":"London",
    "sg:classifiers":[
        {
            "category":"Autos & Motor Vehicles",
            "subcategory":"Auto Supplies",
            "type":"Retail Goods"
        }
    ],
    "sg:phone":"+44 20 8348 4000",
    "sg:postcode":"N6 5AU",
    "sg:province":"Greater London",
    "sg:tags":[
        "tyre"
    ],
    "wof:name":"Archway Exhaust & Tyres",
    "wof:placetype":"venue"
},
  "geometry": {"coordinates":[-0.142631,51.575375],"type":"Point"}
}