{
  "type": "Feature",
  "properties": {
    "addr:full":"35 Devonshire Drive, North Anston Sheffield South Yorkshire S25 4AN",
    "addr:housenumber":"35",
    "addr:postcode":"s25 4an",
    "addr:street":"Devonshire Drive North Anston",
    "iso:country":"GB",
    "sg:address":"35 Devonshire Drive, North Anston",
    "sg:city":"Sheffield",
    "sg:classifiers":[
        {
            "category":"Professional",
            "subcategory":"Secretarial Services",
            "type":"Services"
        }
    ],
    "sg:postcode":"S25 4AN",
    "sg:province":"South Yorkshire",
    "wof:name":"J W Business Services",
    "wof:placetype":"venue"
},
  "geometry": {"coordinates":[-1.2182489634,53.3632240295],"type":"Point"}
}