{
  "type": "Feature",
  "properties": {
    "iso:country":"GB",
    "sg:address":"58 Thames Road",
    "sg:city":"London",
    "sg:classifiers":[
        {
            "category":"Food & Beverages",
            "subcategory":"Meat & Fish",
            "type":"Retail Goods"
        }
    ],
    "sg:phone":"+44 20 8994 1105",
    "sg:postcode":"W4 3RE",
    "sg:province":"Greater London",
    "sg:tags":[
        "butcher"
    ],
    "wof:name":"K Hammond Butchers",
    "wof:placetype":"venue"
},
  "geometry": {"coordinates":[-0.280606,51.486557],"type":"Point"}
}