{
  "type": "Feature",
  "properties": {
    "iso:country":"GB",
    "sg:address":"61 Riverleys",
    "sg:city":"Cheltenham",
    "sg:classifiers":[
        {
            "category":"Building & Trades",
            "subcategory":"Plumbing",
            "type":"Services"
        }
    ],
    "sg:postcode":"GL51 9SA",
    "sg:province":"Gloucestershire",
    "sg:tags":[
        "central",
        "heating"
    ],
    "wof:name":"K Steel & Son",
    "wof:placetype":"venue"
},
  "geometry": {"coordinates":[-2.106439,51.916374],"type":"Point"}
}