{
  "type": "Feature",
  "properties": {
    "addr:full":"Housing Department, Agency Office, Ingrave Rd Brentwood Essex CM15 8AT",
    "addr:postcode":"cm15 8at",
    "addr:street":"Ingrave Rd",
    "iso:country":"GB",
    "sg:address":"Housing Department, Agency Office, Ingrave Rd",
    "sg:city":"Brentwood",
    "sg:classifiers":[
        {
            "category":"Government",
            "subcategory":"Office",
            "type":"Public Place"
        }
    ],
    "sg:phone":"+44 1277 261111",
    "sg:postcode":"CM15 8AT",
    "sg:province":"Essex",
    "sg:tags":[
        "local"
    ],
    "wof:name":"Essex County Council",
    "wof:placetype":"venue"
},
  "geometry": {"coordinates":[0.30573,51.620708],"type":"Point"}
}