{
  "type": "Feature",
  "properties": {
    "addr:full":"31 Lower Cathedral Road Cardiff Cardiff CF11 6LU",
    "addr:housenumber":"31",
    "addr:postcode":"cf11 6lu",
    "addr:street":"Lower Cathedral Road",
    "iso:country":"GB",
    "sg:address":"31 Lower Cathedral Road",
    "sg:city":"Cardiff",
    "sg:classifiers":[
        {
            "category":"Bakery",
            "type":"Food & Drink"
        },
        {
            "category":"Home & Garden",
            "subcategory":"Kitchen Supply",
            "type":"Retail Goods"
        }
    ],
    "sg:phone":"+44 29 2037 2161",
    "sg:postcode":"CF11 6LU",
    "sg:province":"Cardiff",
    "sg:tags":[
        "cake",
        "equipment",
        "decorating",
        "maker"
    ],
    "wof:name":"Confectionery Supplies",
    "wof:placetype":"venue"
},
  "geometry": {"coordinates":[-3.1887090206,51.4804191589],"type":"Point"}
}