{
  "type": "Feature",
  "properties": {
    "addr:full":"36 Hazel Gro Livingston West Lothian EH54 5JW",
    "addr:housenumber":"36",
    "addr:postcode":"eh54 5jw",
    "addr:street":"Hazel Gro",
    "iso:country":"GB",
    "sg:address":"36 Hazel Gro",
    "sg:city":"Livingston",
    "sg:classifiers":[
        {
            "category":"Building & Trades",
            "subcategory":"Cleaning & Sanitation",
            "type":"Services"
        }
    ],
    "sg:phone":"+44 131 557 5090",
    "sg:postcode":"EH54 5JW",
    "sg:province":"West Lothian",
    "sg:tags":[
        "commercial"
    ],
    "wof:name":"Alpro Services",
    "wof:placetype":"venue"
},
  "geometry": {"coordinates":[-3.492024,55.901218],"type":"Point"}
}