{
  "type": "Feature",
  "properties": {
    "addr:full":"1 Putney Bridge Approach London Greater London SW6 3JD",
    "addr:housenumber":"1",
    "addr:postcode":"sw6 3jd",
    "addr:street":"Putney Bridge Approach",
    "iso:country":"GB",
    "sg:address":"1 Putney Bridge Approach",
    "sg:city":"London",
    "sg:classifiers":[
        {
            "category":"Professional",
            "subcategory":"Computer Services",
            "type":"Services"
        }
    ],
    "sg:phone":"+44 20 7741 5347",
    "sg:postcode":"SW6 3JD",
    "sg:province":"Greater London",
    "sg:tags":[
        "system",
        "software"
    ],
    "wof:name":"Cross Atlantic Software Ltd",
    "wof:placetype":"venue"
},
  "geometry": {"coordinates":[-0.211826,51.468132],"type":"Point"}
}