{
  "type": "Feature",
  "properties": {
    "addr:full":"Orchard Court 3 Binley Business, Park, Harry Weston Road Binley Coventry Warwickshire CV3 2TQ",
    "addr:housenumber":"3;business",
    "addr:postcode":"cv3 2tq",
    "addr:street":"Orchard Court;Park Harry Weston Road",
    "iso:country":"GB",
    "sg:address":"Orchard Court 3 Binley Business, Park, Harry Weston Road Binley",
    "sg:city":"Coventry",
    "sg:classifiers":[
        {
            "category":"Professional",
            "type":"Services"
        }
    ],
    "sg:phone":"+44 24 7644 4433",
    "sg:postcode":"CV3 2TQ",
    "sg:province":"Warwickshire",
    "sg:tags":[
        "control",
        "system"
    ],
    "wof:name":"Dickinson Integrated Solutions Ltd.",
    "wof:placetype":"venue"
},
  "geometry": {"coordinates":[-1.439694047,52.3997268677],"type":"Point"}
}