{
  "type": "Feature",
  "properties": {
    "addr:full":"Unit 23, Market Hall Burnley Lancashire BB11 1AZ",
    "addr:housenumber":"unit 23",
    "addr:postcode":"bb11 1az",
    "addr:street":"Market Hall",
    "iso:country":"GB",
    "sg:address":"Unit 23, Market Hall",
    "sg:city":"Burnley",
    "sg:classifiers":[
        {
            "category":"Manufacturing",
            "subcategory":"Textiles",
            "type":"Manufacturing & Wholesale Goods"
        }
    ],
    "sg:phone":"+44 1282 411622",
    "sg:postcode":"BB11 1AZ",
    "sg:province":"Lancashire",
    "sg:tags":[
        "made-up"
    ],
    "wof:name":"Drape It Right",
    "wof:placetype":"venue"
},
  "geometry": {"coordinates":[-2.248718977,53.7898788452],"type":"Point"}
}