{
  "type": "Feature",
  "properties": {
    "addr:full":"62 High Brooms Road Tunbridge Wells Kent TN4 9DB",
    "addr:housenumber":"62",
    "addr:postcode":"tn4 9db",
    "addr:street":"High Brooms Road",
    "iso:country":"GB",
    "sg:address":"62 High Brooms Road",
    "sg:city":"Tunbridge Wells",
    "sg:classifiers":[
        {
            "category":"Fast Food",
            "type":"Food & Drink"
        },
        {
            "category":"Food & Beverages",
            "subcategory":"Meat & Fish",
            "type":"Retail Goods"
        }
    ],
    "sg:phone":"+44 1892 520284",
    "sg:postcode":"TN4 9DB",
    "sg:province":"Kent",
    "sg:tags":[
        "shop",
        "chip"
    ],
    "wof:name":"G E Marino Fish Bar",
    "wof:placetype":"venue"
},
  "geometry": {"coordinates":[0.2736499906,51.1514778137],"type":"Point"}
}