{
  "type": "Feature",
  "properties": {
    "addr:full":"141 Uxbridge Road London Greater London W13 9AU",
    "addr:housenumber":"141",
    "addr:postcode":"w13 9au",
    "addr:street":"Uxbridge Road",
    "iso:country":"GB",
    "sg:address":"141 Uxbridge Road",
    "sg:city":"London",
    "sg:classifiers":[
        {
            "category":"Manufacturing",
            "subcategory":"Tools & Machinery",
            "type":"Manufacturing & Wholesale Goods"
        }
    ],
    "sg:phone":"+44 20 8567 7555",
    "sg:postcode":"W13 9AU",
    "sg:province":"Greater London",
    "sg:tags":[
        "society",
        "friendly"
    ],
    "wof:name":"Asset Insurance Services",
    "wof:placetype":"venue"
},
  "geometry": {"coordinates":[-0.316989,51.51128],"type":"Point"}
}