{
  "type": "Feature",
  "properties": {
    "addr:full":"6 Old Mill Road Torquay Devon TQ2 6AU",
    "addr:housenumber":"6",
    "addr:postcode":"tq2 6au",
    "addr:street":"Old Mill Road",
    "iso:country":"GB",
    "sg:address":"6 Old Mill Road",
    "sg:city":"Torquay",
    "sg:classifiers":[
        {
            "category":"Food & Beverages",
            "subcategory":"Supermarket",
            "type":"Retail Goods"
        }
    ],
    "sg:phone":"+44 1803 690479",
    "sg:postcode":"TQ2 6AU",
    "sg:province":"Devon",
    "wof:name":"Spar",
    "wof:placetype":"venue"
},
  "geometry": {"coordinates":[-3.5461330414,50.4665794373],"type":"Point"}
}