{
  "type": "Feature",
  "properties": {
    "addr:full":"Crossfield Industrial Estate, Crossfield Road Lichfield Staffordshire WS13 6RJ",
    "addr:housenumber":"estate",
    "addr:postcode":"ws13 6rj",
    "addr:street":"Crossfield Road",
    "iso:country":"GB",
    "sg:address":"Crossfield Industrial Estate, Crossfield Road",
    "sg:city":"Lichfield",
    "sg:classifiers":[
        {
            "category":"Retail",
            "subcategory":"Auto Repair",
            "type":"Services"
        }
    ],
    "sg:phone":"+44 1543 418896",
    "sg:postcode":"WS13 6RJ",
    "sg:province":"Staffordshire",
    "sg:tags":[
        "modification",
        "garage"
    ],
    "wof:name":"T Turner Autos",
    "wof:placetype":"venue"
},
  "geometry": {"coordinates":[-1.81966,52.684029],"type":"Point"}
}