{
  "type": "Feature",
  "properties": {
    "addr:full":"637 City Road Sheffield South Yorkshire S2 1GP",
    "addr:housenumber":"637",
    "addr:postcode":"s2 1gp",
    "addr:street":"City Road",
    "iso:country":"GB",
    "sg:address":"637 City Road",
    "sg:city":"Sheffield",
    "sg:classifiers":[
        {
            "category":"Building & Trades",
            "subcategory":"Construction",
            "type":"Services"
        }
    ],
    "sg:postcode":"S2 1GP",
    "sg:province":"South Yorkshire",
    "sg:tags":[
        "roofing"
    ],
    "wof:name":"City Roofing",
    "wof:placetype":"venue"
},
  "geometry": {"coordinates":[-1.4327150583,53.3635253906],"type":"Point"}
}