{
  "type": "Feature",
  "properties": {
    "iso:country":"GB",
    "sg:address":"15 Ashwell Road, Bygrave",
    "sg:city":"Baldock",
    "sg:classifiers":[
        {
            "category":"Professional",
            "subcategory":"Management & Consulting",
            "type":"Services"
        }
    ],
    "sg:postcode":"SG7 5DT",
    "sg:province":"Bedfordshire",
    "sg:tags":[
        "marketing",
        "consultant"
    ],
    "wof:name":"Taylor Bennett Partnership",
    "wof:placetype":"venue"
},
  "geometry": {"coordinates":[-0.1653559953,52.0005340576],"type":"Point"}
}