{
  "type": "Feature",
  "properties": {
    "iso:country":"GB",
    "sg:address":"10a Cowgate",
    "sg:city":"Peterborough",
    "sg:classifiers":[
        {
            "category":"Insurance",
            "subcategory":"Insurance Agent",
            "type":"Services"
        }
    ],
    "sg:phone":"+44 1733 564100",
    "sg:postcode":"PE1 1NA",
    "sg:province":"Cambridgeshire",
    "wof:name":"Sterling Consultants",
    "wof:placetype":"venue"
},
  "geometry": {"coordinates":[-0.2457720041,52.5726699829],"type":"Point"}
}