{
  "type": "Feature",
  "properties": {
    "addr:full":"1a Grove St Mansfield Nottinghamshire NG18 1EL",
    "addr:housenumber":"1a",
    "addr:postcode":"ng18 1el",
    "addr:street":"Grove St",
    "iso:country":"GB",
    "sg:address":"1a Grove St",
    "sg:city":"Mansfield",
    "sg:classifiers":[
        {
            "category":"Professional",
            "subcategory":"Lawyer & Legal Services",
            "type":"Services"
        }
    ],
    "sg:phone":"+44 1623 422224",
    "sg:postcode":"NG18 1EL",
    "sg:province":"Nottinghamshire",
    "sg:tags":[
        "advice",
        "counselling"
    ],
    "wof:name":"Samaritans The",
    "wof:placetype":"venue"
},
  "geometry": {"coordinates":[-1.1967339516,53.1403465271],"type":"Point"}
}