{
  "type": "Feature",
  "properties": {
    "addr:full":"Church Road Windlesham Surrey GU20 6BN",
    "addr:postcode":"gu20 6bn",
    "addr:street":"Church Road",
    "iso:country":"GB",
    "sg:address":"Church Road",
    "sg:city":"Windlesham",
    "sg:classifiers":[
        {
            "category":"Bars & Pubs",
            "type":"Food & Drink"
        }
    ],
    "sg:postcode":"GU20 6BN",
    "sg:province":"Surrey",
    "sg:tags":[
        "pubs",
        "inn"
    ],
    "wof:name":"The Half Moon",
    "wof:placetype":"venue"
},
  "geometry": {"coordinates":[-0.668159008,51.3662452698],"type":"Point"}
}