{
  "type": "Feature",
  "properties": {
    "addr:full":"157a Havant Rd, Drayton Portsmouth Hampshire PO6 2AA",
    "addr:housenumber":"157a",
    "addr:postcode":"hampshire po6 2aa",
    "addr:street":"Havant Rd",
    "iso:country":"GB",
    "sg:address":"157a Havant Rd, Drayton",
    "sg:city":"Portsmouth",
    "sg:classifiers":[
        {
            "category":"Shopping",
            "subcategory":"Books",
            "type":"Retail Goods"
        }
    ],
    "sg:postcode":"PO6 2AA",
    "sg:province":"Hampshire",
    "wof:name":"T & A Publishing",
    "wof:placetype":"venue"
},
  "geometry": {"coordinates":[-1.0541490316,50.8462600708],"type":"Point"}
}