{
  "type": "Feature",
  "properties": {
    "addr:full":"34 High Street, Buckdon St Neots Bedfordshire PE19 5XA",
    "addr:housenumber":"34",
    "addr:postcode":"pe19 5xa",
    "addr:street":"High Street Buckdon",
    "iso:country":"GB",
    "sg:address":"34 High Street, Buckdon",
    "sg:city":"St Neots",
    "sg:classifiers":[
        {
            "category":"Shopping",
            "subcategory":"Shoes",
            "type":"Retail Goods"
        }
    ],
    "sg:phone":"+44 1480 812441",
    "sg:postcode":"PE19 5XA",
    "sg:province":"Bedfordshire",
    "sg:tags":[
        "shop",
        "retailer",
        "footwear"
    ],
    "wof:name":"Susan Peters",
    "wof:placetype":"venue"
},
  "geometry": {"coordinates":[-0.2543619871,52.2932243347],"type":"Point"}
}