{
  "type": "Feature",
  "properties": {
    "addr:full":"3 Johnstone Avenue, Werrington Stoke-on-trent Staffordshire ST9 0DY",
    "addr:housenumber":"3",
    "addr:postcode":"staffordshire st9 0dy",
    "addr:street":"Johnstone Avenue",
    "iso:country":"GB",
    "sg:address":"3 Johnstone Avenue, Werrington",
    "sg:city":"Stoke-on-trent",
    "sg:classifiers":[
        {
            "category":"Shopping",
            "subcategory":"News",
            "type":"Retail Goods"
        }
    ],
    "sg:phone":"+44 1782 302785",
    "sg:postcode":"ST9 0DY",
    "sg:province":"Staffordshire",
    "sg:tags":[
        "newsagent"
    ],
    "wof:name":"Sangha News",
    "wof:placetype":"venue"
},
  "geometry": {"coordinates":[-2.0874459743,53.0247383118],"type":"Point"}
}