{
  "type": "Feature",
  "properties": {
    "iso:country":"GB",
    "sg:address":"175 Bordesley Green East, Bordesley Green",
    "sg:city":"Birmingham",
    "sg:classifiers":[
        {
            "category":"Professional",
            "subcategory":"Business Services",
            "type":"Services"
        }
    ],
    "sg:postcode":"B9 5SR",
    "sg:province":"West Midlands",
    "sg:tags":[
        "tile",
        "stockist"
    ],
    "wof:name":"A T Overton Discount Tiles",
    "wof:placetype":"venue"
},
  "geometry": {"coordinates":[-1.824628,52.479813],"type":"Point"}
}