{
  "type": "Feature",
  "properties": {
    "iso:country":"GB",
    "sg:address":"13 London Road, Hackbridge",
    "sg:city":"Wallington",
    "sg:classifiers":[
        {
            "category":"Wholesale",
            "subcategory":"Construction Materials",
            "type":"Manufacturing & Wholesale Goods"
        },
        {
            "category":"Professional",
            "subcategory":"Business Services",
            "type":"Services"
        }
    ],
    "sg:phone":"+44 20 8647 4576",
    "sg:postcode":"SM6 7HW",
    "sg:province":"Surrey",
    "sg:tags":[
        "tile",
        "wholesaler",
        "supplier",
        "stockist"
    ],
    "wof:name":"All Tile Ceramics Ltd",
    "wof:placetype":"venue"
},
  "geometry": {"coordinates":[-0.153234,51.376743],"type":"Point"}
}