{
  "type": "Feature",
  "properties": {
    "iso:country":"GB",
    "sg:address":"Unit F Bradley Mill Bradley Lane",
    "sg:city":"Newton Abbot",
    "sg:classifiers":[
        {
            "category":"Manufacturing",
            "subcategory":"Building Materials",
            "type":"Manufacturing & Wholesale Goods"
        }
    ],
    "sg:phone":"+44 1626 331699",
    "sg:postcode":"TQ12 1LZ",
    "sg:province":"Devon",
    "sg:tags":[
        "mnfr",
        "marble",
        "specialist"
    ],
    "wof:name":"Grants Marble Manufactory Ltd.",
    "wof:placetype":"venue"
},
  "geometry": {"coordinates":[-3.607659,50.52887],"type":"Point"}
}