{
  "type": "Feature",
  "properties": {
    "addr:full":"Unit 8 The Singleton Centre, Singleton Ashford Kent TN23 5GR",
    "addr:housenumber":"unit 8",
    "addr:postcode":"tn23 5gr",
    "addr:street":"The;Singleton",
    "iso:country":"GB",
    "sg:address":"Unit 8 The Singleton Centre, Singleton",
    "sg:city":"Ashford",
    "sg:classifiers":[
        {
            "category":"Food & Beverages",
            "subcategory":"Liquor & Beverages",
            "type":"Retail Goods"
        }
    ],
    "sg:phone":"+44 1233 621999",
    "sg:postcode":"TN23 5GR",
    "sg:province":"Kent",
    "sg:tags":[
        "beer",
        "spirit",
        "wines"
    ],
    "wof:name":"Unwins Wine Merchants",
    "wof:placetype":"venue"
},
  "geometry": {"coordinates":[0.8390030265,51.1407012939],"type":"Point"}
}