{
  "type": "Feature",
  "properties": {
    "addr:full":"Lee Court, Moonshill Road, Stoke St Michael Bath Somerset BA3 5LG",
    "addr:postcode":"ba3 5lg",
    "addr:street":"Lee;Moonshill Road",
    "iso:country":"GB",
    "sg:address":"Lee Court, Moonshill Road, Stoke St Michael",
    "sg:city":"Bath",
    "sg:classifiers":[
        {
            "category":"Home & Garden",
            "subcategory":"Building Materials",
            "type":"Retail Goods"
        },
        {
            "category":"Building & Trades",
            "subcategory":"Construction",
            "type":"Services"
        }
    ],
    "sg:phone":"+44 1749 840150",
    "sg:postcode":"BA3 5LG",
    "sg:province":"Somerset",
    "sg:tags":[
        "dry",
        "plastering",
        "plasterers",
        "lining",
        "related",
        "installers",
        "insulation",
        "screeders"
    ],
    "wof:name":"EDWARD ILOTT",
    "wof:placetype":"venue"
},
  "geometry": {"coordinates":[-2.4822239876,51.2229232788],"type":"Point"}
}