{
  "type": "Feature",
  "properties": {
    "addr:full":"47 Kitchener Road Thornton Heath Surrey CR7 8QN",
    "addr:housenumber":"47",
    "addr:postcode":"cr7 8qn",
    "addr:street":"Kitchener Road",
    "iso:country":"GB",
    "sg:address":"47 Kitchener Road",
    "sg:city":"Thornton Heath",
    "sg:classifiers":[
        {
            "category":"Home & Garden",
            "subcategory":"Carpets & Floor Coverings",
            "type":"Retail Goods"
        }
    ],
    "sg:phone":"+44 20 8771 4364",
    "sg:postcode":"CR7 8QN",
    "sg:province":"Surrey",
    "sg:tags":[
        "carpets",
        "rug",
        "matting"
    ],
    "wof:name":"G D Carpets",
    "wof:placetype":"venue"
},
  "geometry": {"coordinates":[-0.093532,51.403969],"type":"Point"}
}