{
  "type": "Feature",
  "properties": {
    "iso:country":"GB",
    "sg:address":"Dixies Yard, High St, Ashwell",
    "sg:city":"Baldock",
    "sg:classifiers":[
        {
            "category":"Professional",
            "subcategory":"Management & Consulting",
            "type":"Services"
        }
    ],
    "sg:phone":"+44 1462 742214",
    "sg:postcode":"SG7 5NT",
    "sg:province":"Bedfordshire",
    "sg:tags":[
        "marketing",
        "consultant"
    ],
    "wof:name":"The Fig Group",
    "wof:placetype":"venue"
},
  "geometry": {"coordinates":[-0.155537,52.038834],"type":"Point"}
}