{
  "type": "Feature",
  "properties": {
    "addr:full":"Wessex Way Maidenhead Berkshire SL6 3DN",
    "addr:postcode":"sl6 3dn",
    "addr:street":"Wessex Way",
    "iso:country":"GB",
    "sg:address":"Wessex Way",
    "sg:city":"Maidenhead",
    "sg:classifiers":[
        {
            "category":"Education",
            "subcategory":"Library",
            "type":"Public Place"
        }
    ],
    "sg:phone":"+44 1628 673942",
    "sg:postcode":"SL6 3DN",
    "sg:province":"Berkshire",
    "sg:tags":[
        "book"
    ],
    "wof:name":"Coxgreen Library",
    "wof:placetype":"venue"
},
  "geometry": {"coordinates":[-0.7515339851,51.5094299316],"type":"Point"}
}