{
  "type": "Feature",
  "properties": {
    "addr:full":"9 The Crescent, Station Rd Caterham Surrey CR3 7DB",
    "addr:housenumber":"9",
    "addr:postcode":"cr3 7db",
    "addr:street":"The Crescent Station Rd",
    "iso:country":"GB",
    "sg:address":"9 The Crescent, Station Rd",
    "sg:city":"Caterham",
    "sg:classifiers":[
        {
            "category":"Shopping",
            "subcategory":"Crafts & Fabrics",
            "type":"Retail Goods"
        }
    ],
    "sg:phone":"+44 1883 652508",
    "sg:postcode":"CR3 7DB",
    "sg:province":"Surrey",
    "sg:tags":[
        "material",
        "art"
    ],
    "wof:name":"Rembrants",
    "wof:placetype":"venue"
},
  "geometry": {"coordinates":[-0.0363349989,51.2849464417],"type":"Point"}
}