{
  "type": "Feature",
  "properties": {
    "iso:country":"GB",
    "sg:address":"24 Lemon St",
    "sg:city":"Truro",
    "sg:classifiers":[
        {
            "category":"Bus Charters",
            "type":"Transportation"
        }
    ],
    "sg:phone":"+44 1326 572440",
    "sg:postcode":"TR1 2LS",
    "sg:province":"Cornwall",
    "sg:tags":[
        "hire",
        "coach"
    ],
    "wof:name":"Flora Coaches",
    "wof:placetype":"venue"
},
  "geometry": {"coordinates":[-5.051953,50.261684],"type":"Point"}
}