{
  "type": "Feature",
  "properties": {
    "addr:full":"55 Chase Rd Willesden Greater London NW10 6LU",
    "addr:housenumber":"55",
    "addr:postcode":"nw10 6lu",
    "addr:street":"Chase Rd",
    "iso:country":"GB",
    "sg:address":"55 Chase Rd",
    "sg:city":"Willesden",
    "sg:classifiers":[
        {
            "category":"Professional",
            "subcategory":"Detective & Security Services",
            "type":"Services"
        }
    ],
    "sg:phone":"+44 20 8838 5200",
    "sg:postcode":"NW10 6LU",
    "sg:province":"Greater London",
    "sg:tags":[
        "activity"
    ],
    "wof:name":"Global Protection London Ltd",
    "wof:placetype":"venue"
},
  "geometry": {"coordinates":[-0.25998,51.525406],"type":"Point"}
}