{
  "type": "Feature",
  "properties": {
    "addr:full":"Kingston House, 3 Jamaica St Greenock Inverclyde PA15 1XX",
    "addr:housenumber":"3",
    "addr:postcode":"pa15 1xx",
    "addr:street":"Jamaica St Greenock",
    "iso:country":"GB",
    "sg:address":"Kingston House, 3 Jamaica St",
    "sg:city":"Greenock",
    "sg:classifiers":[
        {
            "category":"Professional",
            "subcategory":"Management & Consulting",
            "type":"Services"
        }
    ],
    "sg:phone":"+44 1475 724676",
    "sg:postcode":"PA15 1XX",
    "sg:province":"Inverclyde",
    "sg:tags":[
        "sport"
    ],
    "wof:name":"Scottish Womens Bowling Association",
    "wof:placetype":"venue"
},
  "geometry": {"coordinates":[-4.7628560066,55.951461792],"type":"Point"}
}