{
  "type": "Feature",
  "properties": {
    "iso:country":"GB",
    "sg:address":"28a Victoria Street",
    "sg:city":"Newton Stewart",
    "sg:classifiers":[
        {
            "category":"Government",
            "subcategory":"Customs House",
            "type":"Public Place"
        }
    ],
    "sg:postcode":"DG8 6BT",
    "sg:province":"Dumfries and Galloway",
    "sg:tags":[
        "clearance"
    ],
    "wof:name":"Newton Stewart Indoor Market",
    "wof:placetype":"venue"
},
  "geometry": {"coordinates":[-4.482958,54.957806],"type":"Point"}
}