{
  "type": "Feature",
  "properties": {
    "addr:full":"91b West Savile Terr Edinburgh City of Edinburgh EH9 3DP",
    "addr:housenumber":"91b",
    "addr:postcode":"eh9 3dp",
    "addr:street":"West Savile Terr",
    "iso:country":"GB",
    "sg:address":"91b West Savile Terr",
    "sg:city":"Edinburgh",
    "sg:classifiers":[
        {
            "category":"Building & Trades",
            "subcategory":"Construction",
            "type":"Services"
        }
    ],
    "sg:phone":"+44 131 667 8044",
    "sg:postcode":"EH9 3DP",
    "sg:province":"City of Edinburgh",
    "sg:tags":[
        "contractor",
        "paving",
        "driveway"
    ],
    "wof:name":"Town & Country Paving (Scotland) Ltd",
    "wof:placetype":"venue"
},
  "geometry": {"coordinates":[-3.183137,55.927544],"type":"Point"}
}