{
  "type": "Feature",
  "properties": {
    "iso:country":"GB",
    "sg:address":"57 Kenilworth Drive, Oadby",
    "sg:city":"Leicester",
    "sg:classifiers":[
        {
            "category":"Professional",
            "subcategory":"Engineering",
            "type":"Services"
        }
    ],
    "sg:phone":"+44 116 271 4099",
    "sg:postcode":"LE2 5LT",
    "sg:province":"Leicestershire",
    "sg:tags":[
        "design",
        "engineer"
    ],
    "wof:name":"Mettleshop Ltd.",
    "wof:placetype":"venue"
},
  "geometry": {"coordinates":[-1.0911979675,52.5972290039],"type":"Point"}
}