{
  "type": "Feature",
  "properties": {
    "addr:full":"8 Shannon St Glasgow Glasgow City G20 9RA",
    "addr:housenumber":"8",
    "addr:postcode":"g20 9ra",
    "addr:street":"Shannon St",
    "iso:country":"GB",
    "sg:address":"8 Shannon St",
    "sg:city":"Glasgow",
    "sg:classifiers":[
        {
            "category":"Retail",
            "subcategory":"Laundry & Dry Cleaning",
            "type":"Services"
        }
    ],
    "sg:postcode":"G20 9RA",
    "sg:province":"Glasgow City",
    "sg:tags":[
        "launderette"
    ],
    "wof:name":"P K Marwaha",
    "wof:placetype":"venue"
},
  "geometry": {"coordinates":[-4.275206,55.88739],"type":"Point"}
}