{
  "type": "Feature",
  "properties": {
    "addr:full":"4 Crescent Road, East Ham London Greater London E6 1ED",
    "addr:housenumber":"4",
    "addr:postcode":"e6 1ed",
    "addr:street":"Crescent Road",
    "iso:country":"GB",
    "sg:address":"4 Crescent Road, East Ham",
    "sg:city":"London",
    "sg:classifiers":[
        {
            "category":"Manufacturing",
            "subcategory":"Metals",
            "type":"Manufacturing & Wholesale Goods"
        }
    ],
    "sg:postcode":"E6 1ED",
    "sg:province":"Greater London",
    "sg:tags":[
        "steel",
        "stockholder"
    ],
    "wof:name":"Andrews & Ingram",
    "wof:placetype":"venue"
},
  "geometry": {"coordinates":[0.0356040001,51.5358963013],"type":"Point"}
}