{
  "type": "Feature",
  "properties": {
    "addr:full":"Sweetmans Industrial Estate Hereford Herefordshire HR4 0EE",
    "addr:housenumber":"estate",
    "addr:postcode":"hr4 0ee",
    "addr:street":"Hereford Herefordshire",
    "iso:country":"GB",
    "sg:address":"Sweetmans Industrial Estate",
    "sg:city":"Hereford",
    "sg:classifiers":[
        {
            "category":"Building & Trades",
            "subcategory":"Construction",
            "type":"Services"
        }
    ],
    "sg:phone":"+44 1432 279103",
    "sg:postcode":"HR4 0EE",
    "sg:province":"Herefordshire",
    "sg:tags":[
        "builder"
    ],
    "wof:name":"Hereford Sectional Buildings Ltd.",
    "wof:placetype":"venue"
},
  "geometry": {"coordinates":[-2.731761,52.059204],"type":"Point"}
}