{
  "type": "Feature",
  "properties": {
    "iso:country":"GB",
    "sg:address":"3 Beils Brae, Urquhart",
    "sg:city":"Elgin",
    "sg:classifiers":[
        {
            "category":"Building & Trades",
            "subcategory":"Construction",
            "type":"Services"
        }
    ],
    "sg:phone":"+44 1343 843971",
    "sg:postcode":"IV30 8XQ",
    "sg:province":"Moray",
    "sg:tags":[
        "joiner",
        "carpenter"
    ],
    "wof:name":"Morrison Joiners",
    "wof:placetype":"venue"
},
  "geometry": {"coordinates":[-3.196882,57.65007],"type":"Point"}
}