{
  "type": "Feature",
  "properties": {
    "iso:country":"GB",
    "sg:address":"1a High Street",
    "sg:city":"Eastleigh",
    "sg:classifiers":[
        {
            "category":"Cafe",
            "type":"Food & Drink"
        }
    ],
    "sg:postcode":"SO50 5LB",
    "sg:province":"Hampshire",
    "sg:tags":[
        "tea",
        "room"
    ],
    "wof:name":"Brian Smith",
    "wof:placetype":"venue"
},
  "geometry": {"coordinates":[-1.353561,50.969173],"type":"Point"}
}