{
  "type": "Feature",
  "properties": {
    "addr:full":"Castle Works, Station Rd Poulton Le Fylde Lancashire FY6 7HZ",
    "addr:postcode":"fy6 7hz",
    "addr:street":"Station Rd",
    "iso:country":"GB",
    "sg:address":"Castle Works, Station Rd",
    "sg:city":"Poulton Le Fylde",
    "sg:classifiers":[
        {
            "category":"Parking",
            "type":"Transportation"
        }
    ],
    "sg:phone":"+44 1253 891200",
    "sg:postcode":"FY6 7HZ",
    "sg:province":"Lancashire",
    "sg:tags":[
        "car",
        "valet"
    ],
    "wof:name":"Carclean",
    "wof:placetype":"venue"
},
  "geometry": {"coordinates":[-2.994659,53.84808],"type":"Point"}
}