{
  "type": "Feature",
  "properties": {
    "iso:country":"GB",
    "sg:address":"241 Garratt Lane",
    "sg:city":"London",
    "sg:classifiers":[
        {
            "category":"Shopping",
            "subcategory":"News",
            "type":"Retail Goods"
        }
    ],
    "sg:phone":"+44 20 8870 3946",
    "sg:postcode":"SW18 4DU",
    "sg:province":"Greater London",
    "sg:tags":[
        "newsagent"
    ],
    "wof:name":"Brocklebank Newsagents",
    "wof:placetype":"venue"
},
  "geometry": {"coordinates":[-0.189359,51.448563],"type":"Point"}
}