{
  "type": "Feature",
  "properties": {
    "addr:full":"44 Pointer Clo, Thamesmead London Greater London SE28 8PW",
    "addr:housenumber":"44",
    "addr:postcode":"se28 8pw",
    "addr:street":"Pointer Clo Thamesmead",
    "iso:country":"GB",
    "sg:address":"44 Pointer Clo, Thamesmead",
    "sg:city":"London",
    "sg:classifiers":[
        {
            "category":"Shopping",
            "subcategory":"Computers & Home Electronics",
            "type":"Retail Goods"
        }
    ],
    "sg:phone":"+44 1709 562233",
    "sg:postcode":"SE28 8PW",
    "sg:province":"Greater London",
    "wof:name":"Supplies Wise Ltd",
    "wof:placetype":"venue"
},
  "geometry": {"coordinates":[0.1250959933,51.5098495483],"type":"Point"}
}