{
  "type": "Feature",
  "properties": {
    "iso:country":"GB",
    "sg:address":"21 Azalea Drive",
    "sg:city":"Trowbridge",
    "sg:classifiers":[
        {
            "category":"Building & Trades",
            "subcategory":"Construction",
            "type":"Services"
        }
    ],
    "sg:postcode":"BA14 9GG",
    "sg:province":"Wiltshire",
    "sg:tags":[
        "builder"
    ],
    "wof:name":"Johnsons (1989) Ltd.",
    "wof:placetype":"venue"
},
  "geometry": {"coordinates":[-2.2296218872,51.3135986328],"type":"Point"}
}