{
  "type": "Feature",
  "properties": {
    "addr:full":"38 Lawrence Avenue, Stanstead Abbotts Ware Hertfordshire SG12 8JL",
    "addr:housenumber":"38",
    "addr:postcode":"sg12 8jl",
    "addr:street":"Lawrence Avenue",
    "iso:country":"GB",
    "sg:address":"38 Lawrence Avenue, Stanstead Abbotts",
    "sg:city":"Ware",
    "sg:classifiers":[
        {
            "category":"Home & Garden",
            "subcategory":"Household Appliances",
            "type":"Retail Goods"
        }
    ],
    "sg:phone":"+44 1920 877568",
    "sg:postcode":"SG12 8JL",
    "sg:province":"Hertfordshire",
    "sg:tags":[
        "electrical"
    ],
    "wof:name":"Express Refrigeration",
    "wof:placetype":"venue"
},
  "geometry": {"coordinates":[0.0036180001,51.7841796875],"type":"Point"}
}