{
  "type": "Feature",
  "properties": {
    "addr:full":"150 Babylon La Chorley Lancashire PR6 9ES",
    "addr:housenumber":"150",
    "addr:postcode":"pr6 9es",
    "addr:street":"Babylon La Chorley",
    "iso:country":"GB",
    "sg:address":"150 Babylon La",
    "sg:city":"Chorley",
    "sg:classifiers":[
        {
            "category":"Building & Trades",
            "subcategory":"Construction",
            "type":"Services"
        }
    ],
    "sg:phone":"+44 1257 482232",
    "sg:postcode":"PR6 9ES",
    "sg:province":"Lancashire",
    "sg:tags":[
        "builder"
    ],
    "wof:name":"Spirit Services Ltd",
    "wof:placetype":"venue"
},
  "geometry": {"coordinates":[-2.5914230347,53.62241745],"type":"Point"}
}