{
  "type": "Feature",
  "properties": {
    "iso:country":"GB",
    "sg:address":"West Gate House, Hills Lane",
    "sg:city":"Shrewsbury",
    "sg:classifiers":[
        {
            "category":"Communications",
            "subcategory":"Film & Video Production",
            "type":"Services"
        }
    ],
    "sg:phone":"+44 1743 245447",
    "sg:postcode":"SY1 1QU",
    "sg:province":"Shropshire",
    "sg:tags":[
        "illustrator",
        "artist"
    ],
    "wof:name":"Jeremy Pyke Illustrators",
    "wof:placetype":"venue"
},
  "geometry": {"coordinates":[-2.757724,52.70932],"type":"Point"}
}