{
  "type": "Feature",
  "properties": {
    "addr:full":"35 The Broadway, Stoneleigh Epsom Surrey KT17 2JE",
    "addr:housenumber":"35",
    "addr:postcode":"kt17 2je",
    "addr:street":"The Broadway",
    "iso:country":"GB",
    "sg:address":"35 The Broadway, Stoneleigh",
    "sg:city":"Epsom",
    "sg:classifiers":[
        {
            "category":"Professional",
            "subcategory":"Art Services",
            "type":"Services"
        }
    ],
    "sg:phone":"+44 20 8393 1101",
    "sg:postcode":"KT17 2JE",
    "sg:province":"Surrey",
    "sg:tags":[
        "photographer"
    ],
    "wof:name":"Dawson Strange Photography Ltd.",
    "wof:placetype":"venue"
},
  "geometry": {"coordinates":[-0.2420130074,51.3610649109],"type":"Point"}
}