{
  "type": "Feature",
  "properties": {
    "addr:full":"Unit C Olmar Wharf, Olmar Street London Greater London SE1 5AY",
    "addr:housenumber":"unit c",
    "addr:postcode":"se1 5ay",
    "addr:street":"Olmar Wharf Olmar Street",
    "iso:country":"GB",
    "sg:address":"Unit C Olmar Wharf, Olmar Street",
    "sg:city":"London",
    "sg:classifiers":[
        {
            "category":"Shopping",
            "subcategory":"Computers & Home Electronics",
            "type":"Retail Goods"
        }
    ],
    "sg:postcode":"SE1 5AY",
    "sg:province":"Greater London",
    "wof:name":"Merchants",
    "wof:placetype":"venue"
},
  "geometry": {"coordinates":[-0.069310002,51.4837989807],"type":"Point"}
}