{
  "type": "Feature",
  "properties": {
    "iso:country":"GB",
    "sg:address":"78 Nottingham Hill Gate",
    "sg:city":"London",
    "sg:classifiers":[
        {
            "category":"Banks & Credit Unions",
            "subcategory":"Bank",
            "type":"Services"
        }
    ],
    "sg:phone":"+44 20 7221 2360",
    "sg:postcode":"W11 3HS",
    "sg:province":"Greater London",
    "wof:name":"The Royal Bank of Scotland Plc",
    "wof:placetype":"venue"
},
  "geometry": {"coordinates":[-0.197109,51.508968],"type":"Point"}
}