{
  "type": "Feature",
  "properties": {
    "addr:full":"13 Allens Avenue Norwich Norfolk NR7 8EP",
    "addr:housenumber":"13",
    "addr:postcode":"nr7 8ep",
    "addr:street":"Allens Avenue Norwich Norfolk",
    "iso:country":"GB",
    "sg:address":"13 Allens Avenue",
    "sg:city":"Norwich",
    "sg:classifiers":[
        {
            "category":"Home & Garden",
            "subcategory":"Home Furnishings",
            "type":"Retail Goods"
        },
        {
            "category":"Home & Garden",
            "subcategory":"Building Materials",
            "type":"Retail Goods"
        }
    ],
    "sg:phone":"+44 1603 400657",
    "sg:postcode":"NR7 8EP",
    "sg:province":"Norfolk",
    "sg:tags":[
        "installers",
        "planner",
        "kitchen",
        "furnishers"
    ],
    "wof:name":"Prestige Home Improvements",
    "wof:placetype":"venue"
},
  "geometry": {"coordinates":[1.315949,52.655315],"type":"Point"}
}