{
  "type": "Feature",
  "properties": {
    "iso:country":"GB",
    "sg:address":"6-8 Broadway",
    "sg:city":"Manchester",
    "sg:classifiers":[
        {
            "category":"Shopping",
            "subcategory":"News",
            "type":"Retail Goods"
        }
    ],
    "sg:phone":"+44 161 681 1384",
    "sg:postcode":"M40 3LN",
    "sg:province":"Greater Manchester",
    "sg:tags":[
        "newsagent"
    ],
    "wof:name":"Reed's News",
    "wof:placetype":"venue"
},
  "geometry": {"coordinates":[-2.16667,53.52095],"type":"Point"}
}