{
  "type": "Feature",
  "properties": {
    "addr:full":"Unit 3, 38 Crown Street Ayr South Ayrshire KA8 8BY",
    "addr:housenumber":"unit;38",
    "addr:postcode":"ka8 8by",
    "addr:street":"Crown Street",
    "iso:country":"GB",
    "sg:address":"Unit 3, 38 Crown Street",
    "sg:city":"Ayr",
    "sg:classifiers":[
        {
            "category":"Shopping",
            "type":"Retail Goods"
        }
    ],
    "sg:phone":"+44 1292 618200",
    "sg:postcode":"KA8 8BY",
    "sg:province":"South Ayrshire",
    "sg:tags":[
        "part",
        "accessory"
    ],
    "wof:name":"Irvine Autostores Ltd.",
    "wof:placetype":"venue"
},
  "geometry": {"coordinates":[-4.6325488091,55.4682312012],"type":"Point"}
}