{
  "type": "Feature",
  "properties": {
    "addr:full":"Cauldon Road Stoke-on-trent Staffordshire ST4 2DZ",
    "addr:postcode":"st4 2dz",
    "addr:street":"Cauldon Road",
    "iso:country":"GB",
    "sg:address":"Cauldon Road",
    "sg:city":"Stoke-on-trent",
    "sg:classifiers":[
        {
            "category":"Education",
            "subcategory":"School",
            "type":"Public Place"
        }
    ],
    "sg:phone":"+44 1782 235711",
    "sg:postcode":"ST4 2DZ",
    "sg:province":"Staffordshire",
    "sg:tags":[
        "local",
        "authority"
    ],
    "wof:name":"Cauldon Primary School",
    "wof:placetype":"venue"
},
  "geometry": {"coordinates":[-2.1817440987,53.0124511719],"type":"Point"}
}