{
  "type": "Feature",
  "properties": {
    "addr:full":"7 Tickle Avenue, Parr St Helens Cheshire WA9 1RZ",
    "addr:housenumber":"7",
    "addr:postcode":"wa9 1rz",
    "addr:street":"Tickle Avenue Parr",
    "iso:country":"GB",
    "sg:address":"7 Tickle Avenue, Parr",
    "sg:city":"St Helens",
    "sg:classifiers":[
        {
            "category":"Government",
            "subcategory":"Office",
            "type":"Public Place"
        }
    ],
    "sg:phone":"+44 1744 451505",
    "sg:postcode":"WA9 1RZ",
    "sg:province":"Cheshire",
    "sg:tags":[
        "local"
    ],
    "wof:name":"St. Helens Personal Services Department",
    "wof:placetype":"venue"
},
  "geometry": {"coordinates":[-2.7140889168,53.4508552551],"type":"Point"}
}