{
  "type": "Feature",
  "properties": {
    "iso:country":"GB",
    "sg:address":"522 Portway",
    "sg:city":"Bristol",
    "sg:classifiers":[
        {
            "category":"Education",
            "subcategory":"Special Training",
            "type":"Public Place"
        }
    ],
    "sg:phone":"+44 117 904 8239",
    "sg:postcode":"BS11 9QQ",
    "sg:province":"City of Bristol",
    "sg:tags":[
        "product",
        "centre"
    ],
    "wof:name":"Routemaster Training",
    "wof:placetype":"venue"
},
  "geometry": {"coordinates":[-2.68367,51.486954],"type":"Point"}
}