{
  "type": "Feature",
  "properties": {
    "iso:country":"GB",
    "sg:address":"293-295 Wakefield Road, Heyrod",
    "sg:city":"Stalybridge",
    "sg:classifiers":[
        {
            "category":"Travel",
            "subcategory":"Hotels & Motels",
            "type":"Entertainment"
        }
    ],
    "sg:postcode":"SK15 3BY",
    "sg:province":"Greater Manchester",
    "sg:tags":[
        "house",
        "guest"
    ],
    "wof:name":"Flushing Meadow",
    "wof:placetype":"venue"
},
  "geometry": {"coordinates":[-2.046084,53.493771],"type":"Point"}
}