{
  "type": "Feature",
  "properties": {
    "iso:country":"GB",
    "sg:address":"Cranbrook Road, Frittenden",
    "sg:city":"Cranbrook",
    "sg:classifiers":[
        {
            "category":"Bars & Pubs",
            "type":"Food & Drink"
        }
    ],
    "sg:phone":"+44 1580 891298",
    "sg:postcode":"TN17 2BT",
    "sg:province":"Kent",
    "sg:tags":[
        "pubs",
        "inn"
    ],
    "wof:name":"Knoxbridge Inn",
    "wof:placetype":"venue"
},
  "geometry": {"coordinates":[0.593937,51.142101],"type":"Point"}
}