{
  "type": "Feature",
  "properties": {
    "addr:full":"Suite 874 Lloyds Building, 1 Lime Street London Greater London EC3M 7DQ",
    "addr:housenumber":"suite 874",
    "addr:postcode":"ec3m 7dq",
    "addr:street":"Lime Street",
    "iso:country":"GB",
    "sg:address":"Suite 874 Lloyds Building, 1 Lime Street",
    "sg:city":"London",
    "sg:classifiers":[
        {
            "category":"Manufacturing",
            "subcategory":"Tools & Machinery",
            "type":"Manufacturing & Wholesale Goods"
        }
    ],
    "sg:phone":"+44 20 7204 4300",
    "sg:postcode":"EC3M 7DQ",
    "sg:province":"Greater London",
    "sg:tags":[
        "society",
        "friendly"
    ],
    "wof:name":"Harvey Bowring",
    "wof:placetype":"venue"
},
  "geometry": {"coordinates":[-0.0827400014,51.5122909546],"type":"Point"}
}