{
  "type": "Feature",
  "properties": {
    "addr:full":"20 Canning St Brighton East Sussex BN2 0EF",
    "addr:housenumber":"20",
    "addr:postcode":"bn2 0ef",
    "addr:street":"Canning St",
    "iso:country":"GB",
    "sg:address":"20 Canning St",
    "sg:city":"Brighton",
    "sg:classifiers":[
        {
            "category":"Government",
            "subcategory":"Office",
            "type":"Public Place"
        }
    ],
    "sg:postcode":"BN2 0EF",
    "sg:province":"East Sussex",
    "sg:tags":[
        "education",
        "agency",
        "authority"
    ],
    "wof:name":"Arched",
    "wof:placetype":"venue"
},
  "geometry": {"coordinates":[-0.1198130026,50.8231391907],"type":"Point"}
}