{
  "type": "Feature",
  "properties": {
    "addr:full":"16 Noel Gate, Aughton Ormskirk Lancashire L39 5EG",
    "addr:housenumber":"16",
    "addr:postcode":"l39 5eg",
    "addr:street":"Noel Gate",
    "iso:country":"GB",
    "sg:address":"16 Noel Gate, Aughton",
    "sg:city":"Ormskirk",
    "sg:classifiers":[
        {
            "category":"Building & Trades",
            "subcategory":"Construction",
            "type":"Services"
        }
    ],
    "sg:phone":"+44 1695 423206",
    "sg:postcode":"L39 5EG",
    "sg:province":"Lancashire",
    "sg:tags":[
        "roofing"
    ],
    "wof:name":"Aughton Roofing",
    "wof:placetype":"venue"
},
  "geometry": {"coordinates":[-2.910042,53.552452],"type":"Point"}
}