{
  "type": "Feature",
  "properties": {
    "addr:full":"Lancashire House Preston Lancashire PR1 3JJ",
    "addr:postcode":"pr1 3jj",
    "iso:country":"GB",
    "sg:address":"Lancashire House",
    "sg:city":"Preston",
    "sg:classifiers":[
        {
            "category":"Organizations",
            "subcategory":"Community Association",
            "type":"Services"
        }
    ],
    "sg:postcode":"PR1 3JJ",
    "sg:province":"Lancashire",
    "sg:tags":[
        "relation",
        "public"
    ],
    "wof:name":"Enterprise Properties Ltd.",
    "wof:placetype":"venue"
},
  "geometry": {"coordinates":[-2.705729,53.757961],"type":"Point"}
}