{
  "type": "Feature",
  "properties": {
    "addr:full":"High Holborn Rd, Codnor Indstl Est Ripley Derbyshire DE5 3NW",
    "addr:postcode":"de5 3nw",
    "addr:street":"High Holborn Rd;Indstl Est",
    "iso:country":"GB",
    "sg:address":"High Holborn Rd, Codnor Indstl Est",
    "sg:city":"Ripley",
    "sg:classifiers":[
        {
            "category":"Home & Garden",
            "subcategory":"Hardware",
            "type":"Retail Goods"
        }
    ],
    "sg:postcode":"DE5 3NW",
    "sg:province":"Derbyshire",
    "sg:tags":[
        "device",
        "fixing",
        "fastener"
    ],
    "wof:name":"Sharow Fasteners Ltd",
    "wof:placetype":"venue"
},
  "geometry": {"coordinates":[-1.378227,53.048954],"type":"Point"}
}