{
  "type": "Feature",
  "properties": {
    "addr:full":"Princess Avenue Clitheroe Lancashire BB7 2AL",
    "addr:postcode":"bb7 2al",
    "addr:street":"Princess Avenue",
    "iso:country":"GB",
    "sg:address":"Princess Avenue",
    "sg:city":"Clitheroe",
    "sg:classifiers":[
        {
            "category":"Retail",
            "subcategory":"Veterinary Services",
            "type":"Services"
        }
    ],
    "sg:phone":"+44 1200 423256",
    "sg:postcode":"BB7 2AL",
    "sg:province":"Lancashire",
    "sg:tags":[
        "surgeon",
        "activity"
    ],
    "sg:website":"http://www.myvets.co.uk",
    "wof:name":"Myerscough Veterinary Group",
    "wof:placetype":"venue"
},
  "geometry": {"coordinates":[-2.386699,53.87616],"type":"Point"}
}