{
  "type": "Feature",
  "properties": {
    "addr:full":"Byron Street Macclesfield Cheshire SK11 7QA",
    "addr:postcode":"sk11 7qa",
    "addr:street":"Byron Street",
    "iso:country":"GB",
    "sg:address":"Byron Street",
    "sg:city":"Macclesfield",
    "sg:classifiers":[
        {
            "category":"Organizations",
            "subcategory":"Non-profit Organization",
            "type":"Services"
        }
    ],
    "sg:phone":"+44 1625 433257",
    "sg:postcode":"SK11 7QA",
    "sg:province":"Cheshire",
    "sg:tags":[
        "organisation",
        "voluntary",
        "charity"
    ],
    "wof:name":"Mayo Centre",
    "wof:placetype":"venue"
},
  "geometry": {"coordinates":[-2.1207540035,53.2505302429],"type":"Point"}
}