{
  "type": "Feature",
  "properties": {
    "iso:country":"GB",
    "sg:address":"207 Heath Way",
    "sg:city":"Birmingham",
    "sg:classifiers":[
        {
            "category":"Shopping",
            "subcategory":"Pharmacy",
            "type":"Retail Goods"
        }
    ],
    "sg:phone":"+44 121 747 2133",
    "sg:postcode":"B34 6QU",
    "sg:province":"West Midlands",
    "sg:tags":[
        "pharmacist",
        "chemist"
    ],
    "wof:name":"Heath Way Pharmacy",
    "wof:placetype":"venue"
},
  "geometry": {"coordinates":[-1.790366,52.498631],"type":"Point"}
}