{
  "type": "Feature",
  "properties": {
    "iso:country":"GB",
    "sg:address":"Stone House Farm, Prince Of Wales Road, Outwood",
    "sg:city":"Redhill",
    "sg:classifiers":[
        {
            "category":"Banks & Credit Unions",
            "subcategory":"Investment Brokerage",
            "type":"Services"
        }
    ],
    "sg:postcode":"RH1 5QU",
    "sg:province":"Surrey",
    "sg:tags":[
        "contractor"
    ],
    "wof:name":"George Frank Layberry",
    "wof:placetype":"venue"
},
  "geometry": {"coordinates":[-0.121865,51.2048],"type":"Point"}
}