{
  "type": "Feature",
  "properties": {
    "iso:country":"GB",
    "sg:address":"Hafod, Dwrbach",
    "sg:city":"Fishguard",
    "sg:classifiers":[
        {
            "category":"Farming",
            "subcategory":"Farm",
            "type":"Manufacturing & Wholesale Goods"
        }
    ],
    "sg:phone":"+44 1348 873296",
    "sg:postcode":"SA65 9RP",
    "sg:province":"Pembrokeshire",
    "sg:tags":[
        "mixed",
        "crop"
    ],
    "wof:name":"John George Davies",
    "wof:placetype":"venue"
},
  "geometry": {"coordinates":[-4.977396965,51.9943733215],"type":"Point"}
}