{
  "type": "Feature",
  "properties": {
    "addr:full":"12 Burghley Road London Greater London N8 0QE",
    "addr:housenumber":"12",
    "addr:postcode":"n8 0qe",
    "addr:street":"Burghley Road",
    "iso:country":"GB",
    "sg:address":"12 Burghley Road",
    "sg:city":"London",
    "sg:classifiers":[
        {
            "category":"Real Estate",
            "subcategory":"Real Estate Services",
            "type":"Services"
        },
        {
            "category":"Real Estate",
            "subcategory":"Real Estate Agent",
            "type":"Services"
        }
    ],
    "sg:phone":"+44 20 8888 3956",
    "sg:postcode":"N8 0QE",
    "sg:province":"Greater London",
    "sg:tags":[
        "management"
    ],
    "wof:name":"Link Properties",
    "wof:placetype":"venue"
},
  "geometry": {"coordinates":[-0.106735,51.590099],"type":"Point"}
}