{
  "type": "Feature",
  "properties": {
    "addr:full":"Church Works, 29a Offord Road London Greater London N1 1EA",
    "addr:housenumber":"29a",
    "addr:postcode":"n1 1ea",
    "addr:street":"Offord Road",
    "iso:country":"GB",
    "sg:address":"Church Works, 29a Offord Road",
    "sg:city":"London",
    "sg:classifiers":[
        {
            "category":"Home & Garden",
            "subcategory":"Home Furnishings",
            "type":"Retail Goods"
        },
        {
            "category":"Social Services",
            "subcategory":"Adult Care",
            "type":"Services"
        }
    ],
    "sg:phone":"+44 20 7609 1164",
    "sg:postcode":"N1 1EA",
    "sg:province":"Greater London",
    "sg:tags":[
        "merchant",
        "decorator",
        "diy",
        "decorators'"
    ],
    "wof:name":"The Colour Centre",
    "wof:placetype":"venue"
},
  "geometry": {"coordinates":[-0.1156909987,51.5426216125],"type":"Point"}
}