{
  "type": "Feature",
  "properties": {
    "iso:country":"GB",
    "sg:address":"28 Olive Gro",
    "sg:city":"Harrogate",
    "sg:classifiers":[
        {
            "category":"Building & Trades",
            "subcategory":"Construction",
            "type":"Services"
        }
    ],
    "sg:phone":"+44 1423 889052",
    "sg:postcode":"HG1 4RQ",
    "sg:province":"North Yorkshire",
    "sg:tags":[
        "decorator",
        "painter"
    ],
    "wof:name":"S J B Painting & Decorating",
    "wof:placetype":"venue"
},
  "geometry": {"coordinates":[-1.5060549974,54.0000648499],"type":"Point"}
}