{
  "type": "Feature",
  "properties": {
    "addr:full":"14 Branwen Close Cardiff Cardiff CF5 4NE",
    "addr:housenumber":"14",
    "addr:postcode":"cf5 4ne",
    "addr:street":"Branwen Close",
    "iso:country":"GB",
    "sg:address":"14 Branwen Close",
    "sg:city":"Cardiff",
    "sg:classifiers":[
        {
            "category":"Professional",
            "subcategory":"Lawyer & Legal Services",
            "type":"Services"
        }
    ],
    "sg:phone":"+44 29 2059 9077",
    "sg:postcode":"CF5 4NE",
    "sg:province":"Cardiff",
    "sg:tags":[
        "solicitor"
    ],
    "wof:name":"Claims Direct",
    "wof:placetype":"venue"
},
  "geometry": {"coordinates":[-3.2620511055,51.4668312073],"type":"Point"}
}