{
  "type": "Feature",
  "properties": {
    "iso:country":"GB",
    "sg:address":"Meadow View, Fernhill Lane",
    "sg:city":"Oswestry",
    "sg:classifiers":[
        {
            "category":"Military Area",
            "subcategory":"Air Force Base",
            "type":"Public Place"
        }
    ],
    "sg:postcode":"SY11 3PP",
    "sg:province":"Shropshire",
    "sg:tags":[
        "taxi",
        "hire",
        "private"
    ],
    "wof:name":"Berwyn Cars of Gobowen",
    "wof:placetype":"venue"
},
  "geometry": {"coordinates":[-3.035410881,52.893283844],"type":"Point"}
}