{
  "type": "Feature",
  "properties": {
    "addr:full":"Unit 13,boden St Glasgow Glasgow City G40 3PU",
    "addr:housenumber":"unit 13",
    "addr:postcode":"g40 3pu",
    "addr:street":"Boden St",
    "iso:country":"GB",
    "sg:address":"Unit 13,boden St",
    "sg:city":"Glasgow",
    "sg:classifiers":[
        {
            "category":"Professional",
            "type":"Services"
        }
    ],
    "sg:postcode":"G40 3PU",
    "sg:province":"Glasgow City",
    "sg:tags":[
        "caterer"
    ],
    "wof:name":"Spence,James,",
    "wof:placetype":"venue"
},
  "geometry": {"coordinates":[-4.214344,55.848351],"type":"Point"}
}