{
  "type": "Feature",
  "properties": {
    "iso:country":"GB",
    "sg:address":"Bridge End, Love Industrial Estate",
    "sg:city":"Cirencester",
    "sg:classifiers":[
        {
            "category":"Professional",
            "subcategory":"Engineering",
            "type":"Services"
        }
    ],
    "sg:phone":"+44 1285 655220",
    "sg:postcode":"GL7 1NQ",
    "sg:province":"Gloucestershire",
    "sg:tags":[
        "precision",
        "engineer"
    ],
    "wof:name":"Batten & Allen International Ltd.",
    "wof:placetype":"venue"
},
  "geometry": {"coordinates":[-1.962039,51.708061],"type":"Point"}
}