{
  "type": "Feature",
  "properties": {
    "addr:full":"Unit 4 Alexandra Trading Estate, Alexandra Road, Alexandra Road Denton Manchester Greater Manchester M34 3DX",
    "addr:housenumber":"unit 4",
    "addr:postcode":"m34 3dx",
    "addr:street":"Alexandra Trading Estate Alexandra Road Alexandra Road",
    "iso:country":"GB",
    "sg:address":"Unit 4 Alexandra Trading Estate, Alexandra Road, Alexandra Road Denton",
    "sg:city":"Manchester",
    "sg:classifiers":[
        {
            "category":"Home & Garden",
            "subcategory":"Home Furnishings",
            "type":"Retail Goods"
        },
        {
            "category":"Manufacturing",
            "subcategory":"Furniture",
            "type":"Manufacturing & Wholesale Goods"
        }
    ],
    "sg:phone":"+44 161 320 7644",
    "sg:postcode":"M34 3DX",
    "sg:province":"Greater Manchester",
    "sg:tags":[
        "soft",
        "manufacturer"
    ],
    "wof:name":"Ottoman Textiles Ltd.",
    "wof:placetype":"venue"
},
  "geometry": {"coordinates":[-2.102876,53.458637],"type":"Point"}
}