{
  "type": "Feature",
  "properties": {
    "addr:full":"Bryniau, Dyserth Rhyl Conwy LL18 6BY",
    "addr:postcode":"ll18 6by",
    "iso:country":"GB",
    "sg:address":"Bryniau, Dyserth",
    "sg:city":"Rhyl",
    "sg:classifiers":[
        {
            "category":"Travel",
            "subcategory":"Hotels & Motels",
            "type":"Entertainment"
        }
    ],
    "sg:postcode":"LL18 6BY",
    "sg:province":"Conwy",
    "wof:name":"Bron-y-Bryn Hotel",
    "wof:placetype":"venue"
},
  "geometry": {"coordinates":[-3.4159560204,53.2998580933],"type":"Point"}
}