{
  "type": "Feature",
  "properties": {
    "addr:full":"29 Balham High Road London Greater London SW12 9AL",
    "addr:housenumber":"29",
    "addr:postcode":"sw12 9al",
    "addr:street":"Balham High Road",
    "iso:country":"GB",
    "sg:address":"29 Balham High Road",
    "sg:city":"London",
    "sg:classifiers":[
        {
            "category":"Building & Trades",
            "subcategory":"Equipment Rental",
            "type":"Services"
        }
    ],
    "sg:phone":"+44 20 8673 2224",
    "sg:postcode":"SW12 9AL",
    "sg:province":"Greater London",
    "sg:tags":[
        "hire",
        "centre"
    ],
    "wof:name":"H S S Hire Shops",
    "wof:placetype":"venue"
},
  "geometry": {"coordinates":[-0.1490779966,51.4468421936],"type":"Point"}
}