{
  "type": "Feature",
  "properties": {
    "iso:country":"GB",
    "sg:address":"1 North Town Moor",
    "sg:city":"Maidenhead",
    "sg:classifiers":[
        {
            "category":"Professional",
            "subcategory":"Detective & Security Services",
            "type":"Services"
        },
        {
            "category":"Building & Trades",
            "subcategory":"Electrical",
            "type":"Services"
        }
    ],
    "sg:phone":"+44 1628 635227",
    "sg:postcode":"SL6 7JR",
    "sg:province":"Berkshire",
    "sg:tags":[
        "burglar",
        "alarm",
        "electrician",
        "system",
        "contractor"
    ],
    "wof:name":"L M LESTER",
    "wof:placetype":"venue"
},
  "geometry": {"coordinates":[-0.7193379998,51.5330314636],"type":"Point"}
}