{
  "type": "Feature",
  "properties": {
    "iso:country":"GB",
    "sg:address":"Main Street",
    "sg:city":"Bellshill",
    "sg:classifiers":[
        {
            "category":"Education",
            "subcategory":"School",
            "type":"Public Place"
        },
        {
            "category":"Government",
            "subcategory":"Office",
            "type":"Public Place"
        }
    ],
    "sg:phone":"+44 1698 747593",
    "sg:postcode":"ML4 3DW",
    "sg:province":"North Lanarkshire",
    "sg:tags":[
        "local",
        "authority"
    ],
    "wof:name":"Cardinal Newman High School",
    "wof:placetype":"venue"
},
  "geometry": {"coordinates":[-4.030189,55.819065],"type":"Point"}
}