{
  "type": "Feature",
  "properties": {
    "iso:country":"GB",
    "sg:address":"Ffordd Corwen, Treuddyn",
    "sg:city":"Mold",
    "sg:classifiers":[
        {
            "category":"Retail",
            "subcategory":"Auto Repair",
            "type":"Services"
        }
    ],
    "sg:phone":"+44 1352 770286",
    "sg:postcode":"CH7 4LE",
    "sg:province":"Denbighshire",
    "sg:tags":[
        "modification",
        "garage"
    ],
    "wof:name":"Corner Garage",
    "wof:placetype":"venue"
},
  "geometry": {"coordinates":[-3.113699,53.113255],"type":"Point"}
}