{
  "type": "Feature",
  "properties": {
    "iso:country":"GB",
    "sg:address":"12 Page Moss Parade",
    "sg:city":"Liverpool",
    "sg:classifiers":[
        {
            "category":"Manufacturing",
            "subcategory":"Wood Products",
            "type":"Manufacturing & Wholesale Goods"
        },
        {
            "category":"Building & Trades",
            "subcategory":"Construction",
            "type":"Services"
        }
    ],
    "sg:phone":"+44 151 489 3935",
    "sg:postcode":"L36 2PA",
    "sg:province":"Merseyside",
    "sg:tags":[
        "joinery",
        "manufacturer"
    ],
    "wof:name":"Thingwall Joinery",
    "wof:placetype":"venue"
},
  "geometry": {"coordinates":[-2.862647,53.420498],"type":"Point"}
}