{
  "type": "Feature",
  "properties": {
    "addr:full":"Mid Borland Farm, Eaglesham Glasgow East Renfrewshire G76 0PP",
    "addr:postcode":"g76 0pp",
    "addr:street":"Eaglesham",
    "iso:country":"GB",
    "sg:address":"Mid Borland Farm, Eaglesham",
    "sg:city":"Glasgow",
    "sg:classifiers":[
        {
            "category":"Farming",
            "subcategory":"Dairy Farm",
            "type":"Manufacturing & Wholesale Goods"
        },
        {
            "category":"Farming",
            "subcategory":"Farm",
            "type":"Manufacturing & Wholesale Goods"
        }
    ],
    "sg:phone":"+44 1355 303253",
    "sg:postcode":"G76 0PP",
    "sg:province":"East Renfrewshire",
    "sg:tags":[
        "mixed",
        "crop",
        "farmer"
    ],
    "wof:name":"Robert Carswell & Son",
    "wof:placetype":"venue"
},
  "geometry": {"coordinates":[-4.2763271332,55.7429466248],"type":"Point"}
}