{
  "type": "Feature",
  "properties": {
    "addr:full":"2-3 Moorcroft Mews, Saltney Chester Cheshire CH4 8SH",
    "addr:housenumber":"2-3",
    "addr:postcode":"ch4 8sh",
    "addr:street":"Moorcroft Mews Saltney",
    "iso:country":"GB",
    "sg:address":"2-3 Moorcroft Mews, Saltney",
    "sg:city":"Chester",
    "sg:classifiers":[
        {
            "category":"Home & Garden",
            "subcategory":"Carpets & Floor Coverings",
            "type":"Retail Goods"
        }
    ],
    "sg:postcode":"CH4 8SH",
    "sg:province":"Cheshire",
    "sg:tags":[
        "carpets",
        "rug",
        "matting"
    ],
    "wof:name":"Discount Carpet Warehouse",
    "wof:placetype":"venue"
},
  "geometry": {"coordinates":[-2.9311261177,53.1769256592],"type":"Point"}
}