{
  "type": "Feature",
  "properties": {
    "addr:full":"Unit 1 Middleton Business Park, Middleton Road, Heysham Morecambe Lancashire LA3 3PW",
    "addr:housenumber":"unit 1",
    "addr:postcode":"la3 3pw",
    "addr:street":"Middleton Business Park Middleton Road",
    "iso:country":"GB",
    "sg:address":"Unit 1 Middleton Business Park, Middleton Road, Heysham",
    "sg:city":"Morecambe",
    "sg:classifiers":[
        {
            "category":"Professional",
            "subcategory":"Engineering",
            "type":"Services"
        }
    ],
    "sg:phone":"+44 1524 852883",
    "sg:postcode":"LA3 3PW",
    "sg:province":"Lancashire",
    "sg:tags":[
        "engineer"
    ],
    "sg:website":"http://www.aspinall.co.uk",
    "wof:name":"T P Aspinall & Sons Ltd",
    "wof:placetype":"venue"
},
  "geometry": {"coordinates":[-2.8818941116,54.0211143494],"type":"Point"}
}