{
  "type": "Feature",
  "properties": {
    "addr:full":"23 Rakersfield Road Wallasey Merseyside CH45 1NW",
    "addr:housenumber":"23",
    "addr:postcode":"ch45 1nw",
    "addr:street":"Rakersfield Road",
    "iso:country":"GB",
    "sg:address":"23 Rakersfield Road",
    "sg:city":"Wallasey",
    "sg:classifiers":[
        {
            "category":"Professional",
            "subcategory":"Detective & Security Services",
            "type":"Services"
        }
    ],
    "sg:phone":"+44 151 630 3562",
    "sg:postcode":"CH45 1NW",
    "sg:province":"Merseyside",
    "sg:tags":[
        "agency"
    ],
    "wof:name":"Enigma Investigations",
    "wof:placetype":"venue"
},
  "geometry": {"coordinates":[-3.0382061005,53.4358711243],"type":"Point"}
}