{
  "type": "Feature",
  "properties": {
    "addr:full":"17 Broadlands Drive Malvern Herefordshire WR14 1PW",
    "addr:housenumber":"17",
    "addr:postcode":"wr14 1pw",
    "addr:street":"Broadlands Drive;Herefordshire",
    "iso:country":"GB",
    "sg:address":"17 Broadlands Drive",
    "sg:city":"Malvern",
    "sg:classifiers":[
        {
            "category":"Building & Trades",
            "subcategory":"Construction",
            "type":"Services"
        }
    ],
    "sg:phone":"+44 1684 575498",
    "sg:postcode":"WR14 1PW",
    "sg:province":"Herefordshire",
    "sg:tags":[
        "builder"
    ],
    "wof:name":"J P Homes",
    "wof:placetype":"venue"
},
  "geometry": {"coordinates":[-2.3379631042,52.126991272],"type":"Point"}
}