{
  "type": "Feature",
  "properties": {
    "addr:full":"432 Ecclesall Road Sheffield Derbyshire S11 8PX",
    "addr:housenumber":"432",
    "addr:postcode":"s11 8px",
    "addr:street":"Ecclesall Road",
    "iso:country":"GB",
    "sg:address":"432 Ecclesall Road",
    "sg:city":"Sheffield",
    "sg:classifiers":[
        {
            "category":"Deli",
            "type":"Food & Drink"
        }
    ],
    "sg:phone":"+44 114 266 1666",
    "sg:postcode":"S11 8PX",
    "sg:province":"Derbyshire",
    "sg:tags":[
        "delivery",
        "sandwich"
    ],
    "wof:name":"Spoilt for Choice",
    "wof:placetype":"venue"
},
  "geometry": {"coordinates":[-1.493848,53.369789],"type":"Point"}
}