{
  "type": "Feature",
  "properties": {
    "addr:full":"Unit 76, Sandford Lane, Kennington Oxford Oxfordshire OX1 5RP",
    "addr:housenumber":"unit 76",
    "addr:postcode":"ox1 5rp",
    "addr:street":"Sandford Lane",
    "iso:country":"GB",
    "sg:address":"Unit 76, Sandford Lane, Kennington",
    "sg:city":"Oxford",
    "sg:classifiers":[
        {
            "category":"Manufacturing",
            "subcategory":"Wood Products",
            "type":"Manufacturing & Wholesale Goods"
        },
        {
            "category":"Building & Trades",
            "subcategory":"Construction",
            "type":"Services"
        }
    ],
    "sg:phone":"+44 1865 739297",
    "sg:postcode":"OX1 5RP",
    "sg:province":"Oxfordshire",
    "sg:tags":[
        "joinery",
        "manufacturer"
    ],
    "wof:name":"Rosewood Joinery",
    "wof:placetype":"venue"
},
  "geometry": {"coordinates":[-1.236072,51.706306],"type":"Point"}
}