{
  "type": "Feature",
  "properties": {
    "iso:country":"GB",
    "sg:address":"10-12 Medway St",
    "sg:city":"Chatham",
    "sg:classifiers":[
        {
            "category":"Home & Garden",
            "subcategory":"Furniture",
            "type":"Retail Goods"
        }
    ],
    "sg:phone":"+44 1634 400897",
    "sg:postcode":"ME4 4HA",
    "sg:province":"Kent",
    "wof:name":"County Suites",
    "wof:placetype":"venue"
},
  "geometry": {"coordinates":[0.5219359994,51.384262085],"type":"Point"}
}