{
  "type": "Feature",
  "properties": {
    "iso:country":"GB",
    "sg:address":"Unit 40 Townmead Business Centre, William Morris Way",
    "sg:city":"Fulham",
    "sg:classifiers":[
        {
            "category":"Real Estate",
            "subcategory":"Architect",
            "type":"Services"
        }
    ],
    "sg:phone":"+44 20 7736 7770",
    "sg:postcode":"SW6 2SZ",
    "sg:province":"Greater London",
    "wof:name":"Absolute Design Consultants",
    "wof:placetype":"venue"
},
  "geometry": {"coordinates":[-0.185514,51.468601],"type":"Point"}
}