{
  "type": "Feature",
  "properties": {
    "addr:full":"12 Delme Court, Maytree Rd Fareham Hampshire PO16 0HX",
    "addr:housenumber":"12",
    "addr:postcode":"po16 0hx",
    "addr:street":"Delme Court Maytree Rd",
    "iso:country":"GB",
    "sg:address":"12 Delme Court, Maytree Rd",
    "sg:city":"Fareham",
    "sg:classifiers":[
        {
            "category":"Professional",
            "subcategory":"Employment Agencies",
            "type":"Services"
        }
    ],
    "sg:phone":"+44 1329 284460",
    "sg:postcode":"PO16 0HX",
    "sg:province":"Hampshire",
    "sg:tags":[
        "consultant"
    ],
    "wof:name":"Online Railway Recuruitment Ltd",
    "wof:placetype":"venue"
},
  "geometry": {"coordinates":[-1.174099,50.852734],"type":"Point"}
}