{
  "type": "Feature",
  "properties": {
    "iso:country":"GB",
    "sg:address":"Unit 45- 46 Queens Court Trading Estate, Unit 46, Queens Court Trading Estate, Greets Green Road",
    "sg:city":"West Bromwich",
    "sg:classifiers":[
        {
            "category":"Professional",
            "subcategory":"Engineering",
            "type":"Services"
        }
    ],
    "sg:phone":"+44 121 557 3837",
    "sg:postcode":"B70 9EQ",
    "sg:province":"West Midlands",
    "sg:tags":[
        "electrical",
        "electronic",
        "engineer"
    ],
    "wof:name":"Gotronic Ltd",
    "wof:placetype":"venue"
},
  "geometry": {"coordinates":[-1.9902240038,52.5186233521],"type":"Point"}
}