{
  "type": "Feature",
  "properties": {
    "iso:country":"GB",
    "sg:address":"Public Hall, 27 Clifton St",
    "sg:city":"Lytham St. Annes",
    "sg:classifiers":[
        {
            "category":"Government",
            "subcategory":"City Hall",
            "type":"Public Place"
        }
    ],
    "sg:phone":"+44 1253 738359",
    "sg:postcode":"FY8 5EP",
    "sg:province":"Lancashire",
    "wof:name":"Hewitt Lecture Room",
    "wof:placetype":"venue"
},
  "geometry": {"coordinates":[-2.961519,53.737171],"type":"Point"}
}