{
  "type": "Feature",
  "properties": {
    "addr:full":"37 Arundel Street Liverpool Merseyside L4 3RS",
    "addr:housenumber":"37",
    "addr:postcode":"l4 3rs",
    "addr:street":"Arundel Street",
    "iso:country":"GB",
    "sg:address":"37 Arundel Street",
    "sg:city":"Liverpool",
    "sg:classifiers":[
        {
            "category":"Home & Garden",
            "subcategory":"Building Materials",
            "type":"Retail Goods"
        }
    ],
    "sg:phone":"+44 151 525 8097",
    "sg:postcode":"L4 3RS",
    "sg:province":"Merseyside",
    "sg:tags":[
        "insulation",
        "installers"
    ],
    "wof:name":"Harry J Moore",
    "wof:placetype":"venue"
},
  "geometry": {"coordinates":[-2.9725179672,53.4410896301],"type":"Point"}
}