{
  "type": "Feature",
  "properties": {
    "iso:country":"GB",
    "sg:address":"Galena House, 30 Galena Road, Hammersmith",
    "sg:city":"London",
    "sg:classifiers":[
        {
            "category":"Professional",
            "subcategory":"Engineering",
            "type":"Services"
        }
    ],
    "sg:phone":"+44 20 8748 8611",
    "sg:postcode":"W6 0LT",
    "sg:province":"Greater London",
    "sg:tags":[
        "civil",
        "consultant",
        "structural",
        "engineer"
    ],
    "sg:website":"http://www.cnmlondon.com",
    "wof:name":"Clarke Nicholls & Marcel",
    "wof:placetype":"venue"
},
  "geometry": {"coordinates":[-0.232796,51.49337],"type":"Point"}
}