{
  "type": "Feature",
  "properties": {
    "iso:country":"GB",
    "sg:address":"Bishopgate St",
    "sg:city":"Leeds",
    "sg:classifiers":[
        {
            "category":"Bars & Pubs",
            "type":"Food & Drink"
        }
    ],
    "sg:phone":"+44 113 243 4590",
    "sg:postcode":"LS1 5DY",
    "sg:province":"West Yorkshire",
    "sg:tags":[
        "pubs",
        "inn"
    ],
    "wof:name":"Punch Retail Ltd",
    "wof:placetype":"venue"
},
  "geometry": {"coordinates":[-1.5462930202,53.7952041626],"type":"Point"}
}