{
  "type": "Feature",
  "properties": {
    "addr:full":"555 Castlehill Edinburgh City of Edinburgh EH1 2ND",
    "addr:housenumber":"555",
    "addr:postcode":"eh1 2nd",
    "addr:street":"Castlehill Edinburgh",
    "iso:country":"GB",
    "sg:address":"555 Castlehill",
    "sg:city":"Edinburgh",
    "sg:classifiers":[
        {
            "category":"Retail",
            "subcategory":"Photofinishing",
            "type":"Services"
        }
    ],
    "sg:phone":"+44 131 226 4171",
    "sg:postcode":"EH1 2ND",
    "sg:province":"City of Edinburgh",
    "sg:tags":[
        "photographic",
        "processor"
    ],
    "wof:name":"G & L Attractions",
    "wof:placetype":"venue"
},
  "geometry": {"coordinates":[-3.1957790852,55.9488716125],"type":"Point"}
}