{
  "type": "Feature",
  "properties": {
    "addr:full":"19a Main Street, Willerby Hull East Riding of Yorkshire HU10 6BP",
    "addr:housenumber":"19a",
    "addr:postcode":"hu10 6bp",
    "addr:street":"Main Street",
    "iso:country":"GB",
    "sg:address":"19a Main Street, Willerby",
    "sg:city":"Hull",
    "sg:classifiers":[
        {
            "category":"Retail",
            "subcategory":"Auto Repair",
            "type":"Services"
        }
    ],
    "sg:phone":"+44 1482 653785",
    "sg:postcode":"HU10 6BP",
    "sg:province":"East Riding of Yorkshire",
    "sg:tags":[
        "modification",
        "garage"
    ],
    "wof:name":"Crescent Garage (Humberside) Ltd.",
    "wof:placetype":"venue"
},
  "geometry": {"coordinates":[-0.447065,53.758369],"type":"Point"}
}