{
  "type": "Feature",
  "properties": {
    "iso:country":"GB",
    "sg:address":"32 Kenneth St",
    "sg:city":"Inverness",
    "sg:classifiers":[
        {
            "category":"Shopping",
            "subcategory":"Department Store",
            "type":"Retail Goods"
        }
    ],
    "sg:postcode":"IV3 5DP",
    "sg:province":"Highland",
    "wof:name":"Courtney,Marie-Lou,",
    "wof:placetype":"venue"
},
  "geometry": {"coordinates":[-4.2310009003,57.4764556885],"type":"Point"}
}