{
  "type": "Feature",
  "properties": {
    "addr:full":"52 Stanley Street Southport Lancashire PR9 0BS",
    "addr:housenumber":"52",
    "addr:postcode":"pr9 0bs",
    "addr:street":"Stanley Street",
    "iso:country":"GB",
    "sg:address":"52 Stanley Street",
    "sg:city":"Southport",
    "sg:classifiers":[
        {
            "category":"Restaurant",
            "type":"Food & Drink"
        }
    ],
    "sg:phone":"+44 1704 530720",
    "sg:postcode":"PR9 0BS",
    "sg:province":"Lancashire",
    "sg:tags":[
        "seafood",
        "-"
    ],
    "wof:name":"The Swan Restaurant",
    "wof:placetype":"venue"
},
  "geometry": {"coordinates":[-3.00161,53.651276],"type":"Point"}
}