{
  "type": "Feature",
  "properties": {
    "addr:full":"79 Fareham Road Gosport Hampshire PO13 0XN",
    "addr:housenumber":"79",
    "addr:postcode":"po13 0xn",
    "addr:street":"Fareham Road",
    "iso:country":"GB",
    "sg:address":"79 Fareham Road",
    "sg:city":"Gosport",
    "sg:classifiers":[
        {
            "category":"Building & Trades",
            "subcategory":"Construction",
            "type":"Services"
        }
    ],
    "sg:phone":"+44 1329 235776",
    "sg:postcode":"PO13 0XN",
    "sg:province":"Hampshire",
    "sg:tags":[
        "builder"
    ],
    "wof:name":"S J Daniels",
    "wof:placetype":"venue"
},
  "geometry": {"coordinates":[-1.165282011,50.8253326416],"type":"Point"}
}