{
  "type": "Feature",
  "properties": {
    "iso:country":"GB",
    "sg:address":"38 Alexandra Road",
    "sg:city":"Grimsby",
    "sg:classifiers":[
        {
            "category":"Personal",
            "subcategory":"Beauty Salon",
            "type":"Services"
        }
    ],
    "sg:postcode":"DN31 1RW",
    "sg:province":"Lincolnshire",
    "sg:tags":[
        "unisex",
        "hairdresser"
    ],
    "wof:name":"Cepelli Hair Design",
    "wof:placetype":"venue"
},
  "geometry": {"coordinates":[-0.086824,53.568562],"type":"Point"}
}