{
  "type": "Feature",
  "properties": {
    "addr:full":"Little Barrington Burford Gloucestershire OX18 4TN",
    "addr:postcode":"ox18 4tn",
    "iso:country":"GB",
    "sg:address":"Little Barrington",
    "sg:city":"Burford",
    "sg:classifiers":[
        {
            "category":"Autos & Motor Vehicles",
            "subcategory":"Fuel & Gas Station",
            "type":"Retail Goods"
        }
    ],
    "sg:phone":"+44 1451 844309",
    "sg:postcode":"OX18 4TN",
    "sg:province":"Gloucestershire",
    "sg:tags":[
        "petrol",
        "filling"
    ],
    "wof:name":"Barrington Filling Station",
    "wof:placetype":"venue"
},
  "geometry": {"coordinates":[-1.6350229979,51.8023376465],"type":"Point"}
}