{
  "type": "Feature",
  "properties": {
    "iso:country":"GB",
    "sg:address":"12 Peldon Pavement",
    "sg:city":"Basildon",
    "sg:classifiers":[
        {
            "category":"Professional",
            "type":"Services"
        }
    ],
    "sg:phone":"+44 1268 527887",
    "sg:postcode":"SS14 2TA",
    "sg:province":"Essex",
    "sg:tags":[
        "entertainer"
    ],
    "wof:name":"Crazy Faces & Magical Mayhem",
    "wof:placetype":"venue"
},
  "geometry": {"coordinates":[0.480133,51.579971],"type":"Point"}
}