{
  "type": "Feature",
  "properties": {
    "addr:full":"Kincarrathie, Pitcullen Crescent Perth Perth and Kinross PH2 7HX",
    "addr:postcode":"ph2 7hx",
    "addr:street":"Pitcullen Crescent",
    "iso:country":"GB",
    "sg:address":"Kincarrathie, Pitcullen Crescent",
    "sg:city":"Perth",
    "sg:classifiers":[
        {
            "category":"Organizations",
            "subcategory":"Non-profit Organization",
            "type":"Services"
        }
    ],
    "sg:phone":"+44 1738 620653",
    "sg:postcode":"PH2 7HX",
    "sg:province":"Perth and Kinross",
    "sg:tags":[
        "charitable",
        "organisation",
        "voluntary",
        "charity"
    ],
    "wof:name":"The Gannochy Trust",
    "wof:placetype":"venue"
},
  "geometry": {"coordinates":[-3.423393,56.404449],"type":"Point"}
}