{
  "type": "Feature",
  "properties": {
    "addr:full":"Myrtle House, High Street Sidmouth Devon EX10 8EG",
    "addr:postcode":"ex10 8eg",
    "addr:street":"High Street",
    "iso:country":"GB",
    "sg:address":"Myrtle House, High Street",
    "sg:city":"Sidmouth",
    "sg:classifiers":[
        {
            "category":"Professional",
            "subcategory":"Accounting & Tax Preparation",
            "type":"Services"
        }
    ],
    "sg:phone":"+44 1395 514403",
    "sg:postcode":"EX10 8EG",
    "sg:province":"Devon",
    "sg:tags":[
        "accountant",
        "activity"
    ],
    "wof:name":"Sleight Tosh & Co",
    "wof:placetype":"venue"
},
  "geometry": {"coordinates":[-3.2381229401,50.6817893982],"type":"Point"}
}