{
  "type": "Feature",
  "properties": {
    "addr:full":"6-8 Silver Street Leicester Leicestershire LE1 5ET",
    "addr:housenumber":"6-8",
    "addr:postcode":"le1 5et",
    "addr:street":"Silver Street",
    "iso:country":"GB",
    "sg:address":"6-8 Silver Street",
    "sg:city":"Leicester",
    "sg:classifiers":[
        {
            "category":"Recreation",
            "subcategory":"Amusement Park",
            "type":"Entertainment"
        }
    ],
    "sg:phone":"+44 116 233 7337",
    "sg:postcode":"LE1 5ET",
    "sg:province":"Leicestershire",
    "sg:tags":[
        "arcade",
        "activity"
    ],
    "wof:name":"Thomas's Entertainments (Leicester) Ltd.",
    "wof:placetype":"venue"
},
  "geometry": {"coordinates":[-1.1342799664,52.6355667114],"type":"Point"}
}