{
  "type": "Feature",
  "properties": {
    "addr:full":"335 Ballards Lane, North Finchley North Finchley Greater London N12 8LT",
    "addr:housenumber":"335",
    "addr:postcode":"n12 8lt",
    "addr:street":"Ballards Lane",
    "iso:country":"GB",
    "sg:address":"335 Ballards Lane, North Finchley",
    "sg:city":"North Finchley",
    "sg:classifiers":[
        {
            "category":"Banks & Credit Unions",
            "subcategory":"Financial Services",
            "type":"Services"
        }
    ],
    "sg:phone":"+44 20 8446 6378",
    "sg:postcode":"N12 8LT",
    "sg:province":"Greater London",
    "sg:tags":[
        "adviser"
    ],
    "wof:name":"Team Agencies plc",
    "wof:placetype":"venue"
},
  "geometry": {"coordinates":[-0.1767240018,51.6149787903],"type":"Point"}
}