{
  "type": "Feature",
  "properties": {
    "iso:country":"GB",
    "sg:address":"124 Crossgates Road",
    "sg:city":"Leeds",
    "sg:classifiers":[
        {
            "category":"Recreation",
            "subcategory":"Fishing",
            "type":"Entertainment"
        }
    ],
    "sg:phone":"+44 113 230 8800",
    "sg:postcode":"LS15 7NG",
    "sg:province":"West Yorkshire",
    "sg:tags":[
        "angling"
    ],
    "wof:name":"Coe's Fisheries (Crossgates) Ltd.",
    "wof:placetype":"venue"
},
  "geometry": {"coordinates":[-1.454354,53.808128],"type":"Point"}
}