{
  "type": "Feature",
  "properties": {
    "addr:full":"Swedebank House, 42 New Broad St Moorgate Greater London EC2M 1LT",
    "addr:housenumber":"42",
    "addr:postcode":"ec2m 1lt",
    "addr:street":"New Broad St Moorgate",
    "iso:country":"GB",
    "sg:address":"Swedebank House, 42 New Broad St",
    "sg:city":"Moorgate",
    "sg:classifiers":[
        {
            "category":"Banks & Credit Unions",
            "subcategory":"Investment Brokerage",
            "type":"Services"
        }
    ],
    "sg:phone":"+44 171 825 7300",
    "sg:postcode":"EC2M 1LT",
    "sg:province":"Greater London",
    "wof:name":"Chiyoda Life Europe",
    "wof:placetype":"venue"
},
  "geometry": {"coordinates":[-0.083657,51.516968],"type":"Point"}
}