{
  "type": "Feature",
  "properties": {
    "iso:country":"GB",
    "sg:address":"31 High Street, Wraysbury",
    "sg:city":"Staines",
    "sg:classifiers":[
        {
            "category":"Government",
            "subcategory":"Post Office",
            "type":"Public Place"
        }
    ],
    "sg:phone":"+44 1784 482477",
    "sg:postcode":"TW19 5DA",
    "sg:province":"Berkshire",
    "wof:name":"Wraysbury Post Office",
    "wof:placetype":"venue"
},
  "geometry": {"coordinates":[-0.554474,51.456879],"type":"Point"}
}