{
  "type": "Feature",
  "properties": {
    "iso:country":"GB",
    "sg:address":"Unit 3, Swan Barn Business Centre",
    "sg:city":"Hailsham",
    "sg:classifiers":[
        {
            "category":"Professional",
            "subcategory":"Engineering",
            "type":"Services"
        }
    ],
    "sg:phone":"+44 1323 842500",
    "sg:postcode":"BN27 2BY",
    "sg:province":"East Sussex",
    "sg:tags":[
        "precision",
        "engineer"
    ],
    "wof:name":"Amber Tooling Ltd.",
    "wof:placetype":"venue"
},
  "geometry": {"coordinates":[0.268403,50.858059],"type":"Point"}
}