{
  "type": "Feature",
  "properties": {
    "iso:country":"GB",
    "sg:address":"Brixeys Farm House, Sandford",
    "sg:city":"Ringwood",
    "sg:classifiers":[
        {
            "category":"Professional",
            "subcategory":"Management & Consulting",
            "type":"Services"
        }
    ],
    "sg:phone":"+44 1425 480064",
    "sg:postcode":"BH24 3BU",
    "sg:province":"Dorset",
    "sg:tags":[
        "marketing",
        "consultant"
    ],
    "wof:name":"Hallam Mills & Associates",
    "wof:placetype":"venue"
},
  "geometry": {"coordinates":[-1.7635040283,50.8252258301],"type":"Point"}
}