{
  "type": "Feature",
  "properties": {
    "addr:full":"119 Willowbrae Road Edinburgh City of Edinburgh EH8 7HN",
    "addr:housenumber":"119",
    "addr:postcode":"eh8 7hn",
    "addr:street":"Willowbrae Road",
    "iso:country":"GB",
    "sg:address":"119 Willowbrae Road",
    "sg:city":"Edinburgh",
    "sg:classifiers":[
        {
            "category":"Travel",
            "subcategory":"Hotels & Motels",
            "type":"Entertainment"
        }
    ],
    "sg:phone":"+44 131 661 0170",
    "sg:postcode":"EH8 7HN",
    "sg:province":"City of Edinburgh",
    "sg:tags":[
        "house",
        "guest"
    ],
    "wof:name":"The Brae Guest House",
    "wof:placetype":"venue"
},
  "geometry": {"coordinates":[-3.1453509331,55.9527778625],"type":"Point"}
}