{
  "type": "Feature",
  "properties": {
    "addr:full":"Elstree Way, Haydon Wick Swindon Wiltshire SN25 4YX",
    "addr:postcode":"sn25 4yx",
    "addr:street":"Elstree Way",
    "iso:country":"GB",
    "sg:address":"Elstree Way, Haydon Wick",
    "sg:city":"Swindon",
    "sg:classifiers":[
        {
            "category":"Government",
            "subcategory":"Post Office",
            "type":"Public Place"
        }
    ],
    "sg:phone":"+44 1793 704182",
    "sg:postcode":"SN25 4YX",
    "sg:province":"Wiltshire",
    "wof:name":"Abbeymeads P.O",
    "wof:placetype":"venue"
},
  "geometry": {"coordinates":[-1.79511,51.5994],"type":"Point"}
}