{
  "type": "Feature",
  "properties": {
    "iso:country":"GB",
    "sg:address":"First Floor",
    "sg:city":"Tetbury",
    "sg:classifiers":[
        {
            "category":"Shopping",
            "subcategory":"Stationery & Office Supplies",
            "type":"Retail Goods"
        }
    ],
    "sg:phone":"+44 1666 504899",
    "sg:postcode":"GL8 8AA",
    "sg:province":"Gloucestershire",
    "sg:tags":[
        "item",
        "promotional"
    ],
    "wof:name":"Promotional Business Answers Ltd.",
    "wof:placetype":"venue"
},
  "geometry": {"coordinates":[-2.160976,51.637859],"type":"Point"}
}