{
  "type": "Feature",
  "properties": {
    "addr:full":"7 Picton Place London Greater London W1U 1BH",
    "addr:housenumber":"7",
    "addr:postcode":"w1u 1bh",
    "addr:street":"Picton Place",
    "iso:country":"GB",
    "sg:address":"7 Picton Place",
    "sg:city":"London",
    "sg:classifiers":[
        {
            "category":"Fast Food",
            "type":"Food & Drink"
        }
    ],
    "sg:phone":"+44 20 7935 6647",
    "sg:postcode":"W1U 1BH",
    "sg:province":"Greater London",
    "sg:tags":[
        "away",
        "take"
    ],
    "wof:name":"Renzo Bragoli",
    "wof:placetype":"venue"
},
  "geometry": {"coordinates":[-0.151738,51.515327],"type":"Point"}
}