{
  "type": "Feature",
  "properties": {
    "iso:country":"GB",
    "sg:address":"88a High Street, Milton Regis",
    "sg:city":"Sittingbourne",
    "sg:classifiers":[
        {
            "category":"Food & Beverages",
            "subcategory":"Bakery",
            "type":"Retail Goods"
        }
    ],
    "sg:phone":"+44 1795 435770",
    "sg:postcode":"ME10 2AN",
    "sg:province":"Kent",
    "sg:tags":[
        "baker"
    ],
    "wof:name":"Amy's Bakery",
    "wof:placetype":"venue"
},
  "geometry": {"coordinates":[0.732564,51.349407],"type":"Point"}
}