{
  "type": "Feature",
  "properties": {
    "iso:country":"GB",
    "sg:address":"99a High Street, Staple Hill",
    "sg:city":"Bristol",
    "sg:classifiers":[
        {
            "category":"Recreation",
            "type":"Entertainment"
        }
    ],
    "sg:phone":"+44 117 957 0637",
    "sg:postcode":"BS16 5HF",
    "sg:province":"City of Bristol",
    "sg:tags":[
        "snooker",
        "billiards",
        "pool"
    ],
    "wof:name":"D Kemp Snooker Services",
    "wof:placetype":"venue"
},
  "geometry": {"coordinates":[-2.515334,51.481468],"type":"Point"}
}