{
  "type": "Feature",
  "properties": {
    "iso:country":"GB",
    "sg:address":"Avanti House, 71 Kingsway North, Team Valley Trading Estate",
    "sg:city":"Gateshead",
    "sg:classifiers":[
        {
            "category":"Shopping",
            "subcategory":"Bicycles & Sporting Goods",
            "type":"Retail Goods"
        }
    ],
    "sg:postcode":"NE11 0JH",
    "sg:province":"Tyne and Wear",
    "sg:tags":[
        "equipment",
        "gym",
        "sport"
    ],
    "wof:name":"Avanti Fitness Ltd.",
    "wof:placetype":"venue"
},
  "geometry": {"coordinates":[-1.620399,54.933113],"type":"Point"}
}