{
  "type": "Feature",
  "properties": {
    "addr:full":"72 Shott Lane Letchworth Hertfordshire SG6 1SE",
    "addr:housenumber":"72",
    "addr:postcode":"sg6 1se",
    "addr:street":"Shott Lane",
    "iso:country":"GB",
    "sg:address":"72 Shott Lane",
    "sg:city":"Letchworth",
    "sg:classifiers":[
        {
            "category":"Health Services",
            "subcategory":"Clinic",
            "type":"Services"
        }
    ],
    "sg:postcode":"SG6 1SE",
    "sg:province":"Hertfordshire",
    "sg:tags":[
        "aromatherapy"
    ],
    "wof:name":"Karen Hilton",
    "wof:placetype":"venue"
},
  "geometry": {"coordinates":[-0.220114,51.976006],"type":"Point"}
}