{
  "type": "Feature",
  "properties": {
    "addr:full":"50 High Street, Horbury Wakefield West Yorkshire WF4 5LE",
    "addr:housenumber":"50",
    "addr:postcode":"wf4 5le",
    "addr:street":"High Street;West",
    "iso:country":"GB",
    "sg:address":"50 High Street, Horbury",
    "sg:city":"Wakefield",
    "sg:classifiers":[
        {
            "category":"Retail",
            "subcategory":"Veterinary Services",
            "type":"Services"
        }
    ],
    "sg:phone":"+44 1924 465592",
    "sg:postcode":"WF4 5LE",
    "sg:province":"West Yorkshire",
    "sg:tags":[
        "surgeon",
        "activity"
    ],
    "wof:name":"Calder Veterinary Group",
    "wof:placetype":"venue"
},
  "geometry": {"coordinates":[-1.55716,53.660118],"type":"Point"}
}