{
  "type": "Feature",
  "properties": {
    "addr:full":"68 Heath Street London Greater London NW3 1DN",
    "addr:housenumber":"68",
    "addr:postcode":"nw3 1dn",
    "addr:street":"Heath Street",
    "iso:country":"GB",
    "sg:address":"68 Heath Street",
    "sg:city":"London",
    "sg:classifiers":[
        {
            "category":"Bars & Pubs",
            "type":"Food & Drink"
        }
    ],
    "sg:phone":"+44 20 7435 3140",
    "sg:postcode":"NW3 1DN",
    "sg:province":"Greater London",
    "sg:tags":[
        "pubs",
        "inn"
    ],
    "wof:name":"Horse & Groom",
    "wof:placetype":"venue"
},
  "geometry": {"coordinates":[-0.178136,51.557533],"type":"Point"}
}