{
  "type": "Feature",
  "properties": {
    "iso:country":"GB",
    "sg:address":"Ward Street",
    "sg:city":"Prescot",
    "sg:classifiers":[
        {
            "category":"Education",
            "subcategory":"School",
            "type":"Public Place"
        }
    ],
    "sg:phone":"+44 151 426 5005",
    "sg:postcode":"L34 6JJ",
    "sg:province":"Merseyside",
    "sg:tags":[
        "local",
        "authority"
    ],
    "wof:name":"Our Lady's R C Primary School",
    "wof:placetype":"venue"
},
  "geometry": {"coordinates":[-2.801469,53.432186],"type":"Point"}
}