{
  "type": "Feature",
  "properties": {
    "addr:full":"14 Shipley Lane Bexhill-on-sea East Sussex TN39 3SR",
    "addr:housenumber":"14",
    "addr:postcode":"tn39 3sr",
    "addr:street":"Shipley Lane",
    "iso:country":"GB",
    "sg:address":"14 Shipley Lane",
    "sg:city":"Bexhill-on-sea",
    "sg:classifiers":[
        {
            "category":"Manufacturing",
            "subcategory":"Petroleum Products",
            "type":"Manufacturing & Wholesale Goods"
        }
    ],
    "sg:postcode":"TN39 3SR",
    "sg:province":"East Sussex",
    "sg:tags":[
        "double",
        "glazing"
    ],
    "wof:name":"Sunbrite Home Improvements",
    "wof:placetype":"venue"
},
  "geometry": {"coordinates":[0.43953,50.837788],"type":"Point"}
}