{
  "type": "Feature",
  "properties": {
    "addr:full":"Newbank Farm, Beattock Moffat Dumfries and Galloway DG10 9PZ",
    "addr:postcode":"dg10 9pz",
    "addr:street":"Beattock",
    "iso:country":"GB",
    "sg:address":"Newbank Farm, Beattock",
    "sg:city":"Moffat",
    "sg:classifiers":[
        {
            "category":"Farming",
            "subcategory":"Livestock Farm",
            "type":"Manufacturing & Wholesale Goods"
        }
    ],
    "sg:phone":"+44 1683 300371",
    "sg:postcode":"DG10 9PZ",
    "sg:province":"Dumfries and Galloway",
    "sg:tags":[
        "others"
    ],
    "wof:name":"M & S Wilson & Sons",
    "wof:placetype":"venue"
},
  "geometry": {"coordinates":[-3.4455990791,55.335193634],"type":"Point"}
}