{
  "type": "Feature",
  "properties": {
    "iso:country":"GB",
    "sg:address":"P O Box 936",
    "sg:city":"Manningtree",
    "sg:classifiers":[
        {
            "category":"Banks & Credit Unions",
            "subcategory":"Financial Services",
            "type":"Services"
        }
    ],
    "sg:phone":"+44 1206 395162",
    "sg:postcode":"CO11 2LW",
    "sg:province":"Essex",
    "sg:tags":[
        "consultant"
    ],
    "wof:name":"Stour Valley Credit & Finance",
    "wof:placetype":"venue"
},
  "geometry": {"coordinates":[1.1167149544,51.935344696],"type":"Point"}
}