{
  "type": "Feature",
  "properties": {
    "iso:country":"GB",
    "sg:address":"37 Church Street",
    "sg:city":"Gainsborough",
    "sg:classifiers":[
        {
            "category":"Bars & Pubs",
            "type":"Food & Drink"
        }
    ],
    "sg:phone":"+44 1427 613696",
    "sg:postcode":"DN21 2JR",
    "sg:province":"Lincolnshire",
    "sg:tags":[
        "pubs",
        "inn"
    ],
    "wof:name":"D J Roofe",
    "wof:placetype":"venue"
},
  "geometry": {"coordinates":[-0.776075,53.401501],"type":"Point"}
}