{
  "type": "Feature",
  "properties": {
    "iso:country":"GB",
    "sg:address":"Claremont Hall, Claremont Road",
    "sg:city":"Surbiton",
    "sg:classifiers":[
        {
            "category":"Education",
            "subcategory":"Dance Studio",
            "type":"Public Place"
        }
    ],
    "sg:phone":"+44 20 8390 1953",
    "sg:postcode":"KT6 4RL",
    "sg:province":"Surrey",
    "sg:tags":[
        "school",
        "dancing"
    ],
    "wof:name":"Margaret Barnes School of Dancing",
    "wof:placetype":"venue"
},
  "geometry": {"coordinates":[-0.306949,51.392059],"type":"Point"}
}