{
  "type": "Feature",
  "properties": {
    "addr:full":"42 Sandon Road Stourbridge West Midlands DY9 8XY",
    "addr:housenumber":"42",
    "addr:postcode":"dy9 8xy",
    "addr:street":"Sandon Road",
    "iso:country":"GB",
    "sg:address":"42 Sandon Road",
    "sg:city":"Stourbridge",
    "sg:classifiers":[
        {
            "category":"Home & Garden",
            "subcategory":"Garden Supply",
            "type":"Retail Goods"
        }
    ],
    "sg:phone":"+44 1384 895247",
    "sg:postcode":"DY9 8XY",
    "sg:province":"West Midlands",
    "sg:tags":[
        "turfing"
    ],
    "wof:name":"Graham Norgrove",
    "wof:placetype":"venue"
},
  "geometry": {"coordinates":[-2.1066520214,52.4520111084],"type":"Point"}
}