{
  "type": "Feature",
  "properties": {
    "addr:full":"87 Belstead Road Ipswich Suffolk IP2 9AT",
    "addr:housenumber":"87",
    "addr:postcode":"ip2 9at",
    "addr:street":"Belstead Road",
    "iso:country":"GB",
    "sg:address":"87 Belstead Road",
    "sg:city":"Ipswich",
    "sg:classifiers":[
        {
            "category":"Building & Trades",
            "subcategory":"Plumbing",
            "type":"Services"
        },
        {
            "category":"Building & Trades",
            "subcategory":"Construction",
            "type":"Services"
        }
    ],
    "sg:phone":"+44 1473 602264",
    "sg:postcode":"IP2 9AT",
    "sg:province":"Suffolk",
    "sg:tags":[
        "plumber",
        "builder"
    ],
    "wof:name":"B F Smart",
    "wof:placetype":"venue"
},
  "geometry": {"coordinates":[1.1439319849,52.0470314026],"type":"Point"}
}