{
  "type": "Feature",
  "properties": {
    "iso:country":"GB",
    "sg:address":"94 Defoe Road",
    "sg:city":"Ipswich",
    "sg:classifiers":[
        {
            "category":"Building & Trades",
            "subcategory":"Plumbing",
            "type":"Services"
        }
    ],
    "sg:phone":"+44 1473 748387",
    "sg:postcode":"IP1 6SD",
    "sg:province":"Suffolk",
    "sg:tags":[
        "central",
        "heating"
    ],
    "wof:name":"A C Butler Heating & Plumbing",
    "wof:placetype":"venue"
},
  "geometry": {"coordinates":[1.140561,52.084602],"type":"Point"}
}