{
  "type": "Feature",
  "properties": {
    "addr:full":"Shotton Steel Works Deeside Flintshire CH5 2NH",
    "addr:postcode":"ch5 2nh",
    "iso:country":"GB",
    "sg:address":"Shotton Steel Works",
    "sg:city":"Deeside",
    "sg:classifiers":[
        {
            "category":"Freight",
            "type":"Transportation"
        }
    ],
    "sg:phone":"+44 1244 812310",
    "sg:postcode":"CH5 2NH",
    "sg:province":"Flintshire",
    "sg:tags":[
        "haulage",
        "road"
    ],
    "wof:name":"Multiserv Logistics Ltd.",
    "wof:placetype":"venue"
},
  "geometry": {"coordinates":[-3.024987936,53.2024803162],"type":"Point"}
}