{
  "type": "Feature",
  "properties": {
    "addr:full":"Brynawelon, Cilan Pwllheli Gwynedd LL53 7DB",
    "addr:postcode":"ll53 7db",
    "iso:country":"GB",
    "sg:address":"Brynawelon, Cilan",
    "sg:city":"Pwllheli",
    "sg:classifiers":[
        {
            "category":"Building & Trades",
            "subcategory":"Construction",
            "type":"Services"
        }
    ],
    "sg:postcode":"LL53 7DB",
    "sg:province":"Gwynedd",
    "sg:tags":[
        "decorator",
        "painter"
    ],
    "wof:name":"D R Turner Decorating Services",
    "wof:placetype":"venue"
},
  "geometry": {"coordinates":[-4.525919,52.785976],"type":"Point"}
}