{
  "type": "Feature",
  "properties": {
    "addr:full":"6 Whitmore Road London Greater London N1 5PY",
    "addr:housenumber":"6",
    "addr:postcode":"n1 5py",
    "addr:street":"Whitmore Road",
    "iso:country":"GB",
    "sg:address":"6 Whitmore Road",
    "sg:city":"London",
    "sg:classifiers":[
        {
            "category":"Shopping",
            "subcategory":"News",
            "type":"Retail Goods"
        }
    ],
    "sg:phone":"+44 20 7684 1446",
    "sg:postcode":"N1 5PY",
    "sg:province":"Greater London",
    "sg:tags":[
        "newsagent"
    ],
    "wof:name":"Kingsley Roberts Ltd.",
    "wof:placetype":"venue"
},
  "geometry": {"coordinates":[-0.082107,51.535637],"type":"Point"}
}