{
  "type": "Feature",
  "properties": {
    "addr:full":"Old Court Ho, St. Peters Church Yd Derby Derbyshire DE1 1NN",
    "addr:postcode":"de1 1nn",
    "addr:street":"Yd",
    "iso:country":"GB",
    "sg:address":"Old Court Ho, St. Peters Church Yd",
    "sg:city":"Derby",
    "sg:classifiers":[
        {
            "category":"Professional",
            "subcategory":"Credit Reporting & Collection",
            "type":"Services"
        }
    ],
    "sg:postcode":"DE1 1NN",
    "sg:province":"Derbyshire",
    "sg:tags":[
        "collecting",
        "agency"
    ],
    "wof:name":"James Grace Ltd",
    "wof:placetype":"venue"
},
  "geometry": {"coordinates":[-1.483684,52.925171],"type":"Point"}
}