{
  "type": "Feature",
  "properties": {
    "iso:country":"GB",
    "sg:address":"33 Carolgate",
    "sg:city":"Retford",
    "sg:classifiers":[
        {
            "category":"Retail",
            "subcategory":"Photofinishing",
            "type":"Services"
        }
    ],
    "sg:phone":"+44 1777 710756",
    "sg:postcode":"DN22 6BZ",
    "sg:province":"Nottinghamshire",
    "sg:tags":[
        "photographic",
        "processor"
    ],
    "wof:name":"Klick Photopoint",
    "wof:placetype":"venue"
},
  "geometry": {"coordinates":[-0.9418439865,53.3211975098],"type":"Point"}
}