{
  "type": "Feature",
  "properties": {
    "iso:country":"GB",
    "sg:address":"Hampshire Way",
    "sg:city":"South Shields",
    "sg:classifiers":[
        {
            "category":"Health Services",
            "subcategory":"Nursing And Care Facility",
            "type":"Services"
        }
    ],
    "sg:phone":"+44 191 455 5298",
    "sg:postcode":"NE34 7HR",
    "sg:province":"Tyne and Wear",
    "sg:tags":[
        "home",
        "agency"
    ],
    "wof:name":"MARSDEN ROCK HOUSE",
    "wof:placetype":"venue"
},
  "geometry": {"coordinates":[-1.388989,54.97979],"type":"Point"}
}