{
  "type": "Feature",
  "properties": {
    "addr:full":"C2 Cornwall Road Wigston Leicestershire LE18 4XH",
    "addr:housenumber":"c2",
    "addr:postcode":"le18 4xh",
    "addr:street":"Cornwall Road",
    "iso:country":"GB",
    "sg:address":"C2 Cornwall Road",
    "sg:city":"Wigston",
    "sg:classifiers":[
        {
            "category":"Manufacturing",
            "subcategory":"Textiles",
            "type":"Manufacturing & Wholesale Goods"
        }
    ],
    "sg:phone":"+44 116 278 4333",
    "sg:postcode":"LE18 4XH",
    "sg:province":"Leicestershire",
    "sg:tags":[
        "knitwear"
    ],
    "wof:name":"Glentex (U K) Ltd.",
    "wof:placetype":"venue"
},
  "geometry": {"coordinates":[-1.114289,52.582981],"type":"Point"}
}