{
  "type": "Feature",
  "properties": {
    "iso:country":"GB",
    "sg:address":"15 Station Rd",
    "sg:city":"Peterborough",
    "sg:classifiers":[
        {
            "category":"Freight",
            "type":"Transportation"
        }
    ],
    "sg:phone":"+44 1780 782853",
    "sg:postcode":"PE8 6QB",
    "sg:province":"Cambridgeshire",
    "sg:tags":[
        "haulage",
        "road"
    ],
    "wof:name":"N R Adams Haulage",
    "wof:placetype":"venue"
},
  "geometry": {"coordinates":[-0.426747,52.554115],"type":"Point"}
}