{
  "type": "Feature",
  "properties": {
    "iso:country":"GB",
    "sg:address":"22 Feckenham Road, Headless Cross",
    "sg:city":"Redditch",
    "sg:classifiers":[
        {
            "category":"Social Services",
            "subcategory":"Retirement Home",
            "type":"Services"
        }
    ],
    "sg:phone":"+44 1527 544592",
    "sg:postcode":"B97 5AR",
    "sg:province":"Warwickshire",
    "sg:tags":[
        "rest"
    ],
    "wof:name":"St Martins Home",
    "wof:placetype":"venue"
},
  "geometry": {"coordinates":[-1.9529360533,52.2942123413],"type":"Point"}
}