{
  "type": "Feature",
  "properties": {
    "iso:country":"GB",
    "sg:address":"Park Farm, Town Green St, Rothley",
    "sg:city":"Leicester",
    "sg:classifiers":[
        {
            "category":"Farming",
            "subcategory":"Livestock Farm",
            "type":"Manufacturing & Wholesale Goods"
        }
    ],
    "sg:phone":"+44 116 230 2067",
    "sg:postcode":"LE7 7NW",
    "sg:province":"Leicestershire",
    "sg:tags":[
        "others"
    ],
    "wof:name":"W.H Cooper",
    "wof:placetype":"venue"
},
  "geometry": {"coordinates":[-1.137163043,52.708366394],"type":"Point"}
}