{
  "type": "Feature",
  "properties": {
    "iso:country":"GB",
    "sg:address":"The Garage, Alvah",
    "sg:city":"Banff",
    "sg:classifiers":[
        {
            "category":"Retail",
            "subcategory":"Auto Repair",
            "type":"Services"
        }
    ],
    "sg:phone":"+44 1261 821605",
    "sg:postcode":"AB45 3US",
    "sg:province":"Aberdeenshire",
    "sg:tags":[
        "modification",
        "garage"
    ],
    "wof:name":"A W & M Stevenson",
    "wof:placetype":"venue"
},
  "geometry": {"coordinates":[-2.5411128998,57.6309127808],"type":"Point"}
}