{
  "type": "Feature",
  "properties": {
    "iso:country":"GB",
    "sg:address":"Parsonage Farm, Longdon Marsh",
    "sg:city":"Tewkesbury",
    "sg:classifiers":[
        {
            "category":"Building & Trades",
            "subcategory":"Landscaping Services",
            "type":"Services"
        }
    ],
    "sg:postcode":"GL20 6BD",
    "sg:province":"Gloucestershire",
    "sg:tags":[
        "forestry",
        "tree"
    ],
    "wof:name":"B J Unwin Forestry Consultancy",
    "wof:placetype":"venue"
},
  "geometry": {"coordinates":[-2.23796,52.024349],"type":"Point"}
}