{
  "type": "Feature",
  "properties": {
    "addr:full":"187 Worcester Rd Malvern Herefordshire WR14 1EX",
    "addr:housenumber":"187",
    "addr:postcode":"wr14 1ex",
    "addr:street":"Worcester Rd;Herefordshire",
    "iso:country":"GB",
    "sg:address":"187 Worcester Rd",
    "sg:city":"Malvern",
    "sg:classifiers":[
        {
            "category":"Social Services",
            "subcategory":"Adult Care",
            "type":"Services"
        }
    ],
    "sg:phone":"+44 1684 564121",
    "sg:postcode":"WR14 1EX",
    "sg:province":"Herefordshire",
    "sg:tags":[
        "day",
        "centre"
    ],
    "wof:name":"Headway Day Centre",
    "wof:placetype":"venue"
},
  "geometry": {"coordinates":[-2.3146591187,52.128112793],"type":"Point"}
}