{
  "type": "Feature",
  "properties": {
    "addr:full":"325 London Road Westcliff-on-sea Essex SS0 7BX",
    "addr:housenumber":"325",
    "addr:postcode":"ss0 7bx",
    "addr:street":"London Road",
    "iso:country":"GB",
    "sg:address":"325 London Road",
    "sg:city":"Westcliff-on-sea",
    "sg:classifiers":[
        {
            "category":"Home & Garden",
            "subcategory":"Kitchen Supply",
            "type":"Retail Goods"
        }
    ],
    "sg:postcode":"SS0 7BX",
    "sg:province":"Essex",
    "sg:tags":[
        "ware"
    ],
    "wof:name":"Plusmail Ltd.",
    "wof:placetype":"venue"
},
  "geometry": {"coordinates":[0.6968250275,51.5417976379],"type":"Point"}
}