{
  "type": "Feature",
  "properties": {
    "iso:country":"GB",
    "sg:address":"11 Upper Millergate",
    "sg:city":"Bradford",
    "sg:classifiers":[
        {
            "category":"Shopping",
            "subcategory":"Clothing, Apparel, & Fashions",
            "type":"Retail Goods"
        }
    ],
    "sg:phone":"+44 1274 733163",
    "sg:postcode":"BD1 1SX",
    "sg:province":"West Yorkshire",
    "sg:tags":[
        "menswear"
    ],
    "wof:name":"An-x",
    "wof:placetype":"venue"
},
  "geometry": {"coordinates":[-1.755514,53.793991],"type":"Point"}
}