{
  "type": "Feature",
  "properties": {
    "iso:country":"GB",
    "sg:address":"11 Memory Close, Freckleton",
    "sg:city":"Preston",
    "sg:classifiers":[
        {
            "category":"Arts & Performance",
            "subcategory":"Music",
            "type":"Entertainment"
        }
    ],
    "sg:phone":"+44 1772 635901",
    "sg:postcode":"PR4 1YS",
    "sg:province":"Lancashire",
    "sg:tags":[
        "mobile",
        "disco"
    ],
    "wof:name":"T.J's Entertainments",
    "wof:placetype":"venue"
},
  "geometry": {"coordinates":[-2.8683350086,53.7546653748],"type":"Point"}
}