{
  "type": "Feature",
  "properties": {
    "iso:country":"GB",
    "sg:address":"59 Whitby Avenue, Ingol",
    "sg:city":"Preston",
    "sg:classifiers":[
        {
            "category":"Education",
            "subcategory":"School",
            "type":"Public Place"
        }
    ],
    "sg:phone":"+44 1772 727471",
    "sg:postcode":"PR2 3YP",
    "sg:province":"Lancashire",
    "sg:tags":[
        "local",
        "authority"
    ],
    "wof:name":"Holy Family Catholic Primary School",
    "wof:placetype":"venue"
},
  "geometry": {"coordinates":[-2.745766,53.780888],"type":"Point"}
}