{
  "type": "Feature",
  "properties": {
    "addr:full":"Alder Hey Hospital, Eaton Road, West Derby Liverpool Merseyside L12 2AP",
    "addr:postcode":"l12 2ap",
    "addr:street":"Alder;Eaton Road West Derby",
    "iso:country":"GB",
    "sg:address":"Alder Hey Hospital, Eaton Road, West Derby",
    "sg:city":"Liverpool",
    "sg:classifiers":[
        {
            "category":"Health Services",
            "subcategory":"Hospital",
            "type":"Services"
        },
        {
            "category":"Organizations",
            "subcategory":"Non-profit Organization",
            "type":"Services"
        }
    ],
    "sg:phone":"+44 151 228 4811",
    "sg:postcode":"L12 2AP",
    "sg:province":"Merseyside",
    "sg:tags":[
        "charitable",
        "organisation",
        "charity"
    ],
    "wof:name":"ROYAL LIVERPOOL CHILDREN'S N H S TRUST",
    "wof:placetype":"venue"
},
  "geometry": {"coordinates":[-2.9002389908,53.4212188721],"type":"Point"}
}