{
  "type": "Feature",
  "properties": {
    "iso:country":"GB",
    "sg:address":"62 Grosvenor Road",
    "sg:city":"Tunbridge Wells",
    "sg:classifiers":[
        {
            "category":"Home & Garden",
            "subcategory":"Hardware",
            "type":"Retail Goods"
        }
    ],
    "sg:phone":"+44 1892 543483",
    "sg:postcode":"TN1 2AS",
    "sg:province":"Kent",
    "wof:name":"Hardware Goods Tunbridge Wells",
    "wof:placetype":"venue"
},
  "geometry": {"coordinates":[0.262486,51.136559],"type":"Point"}
}