{
  "type": "Feature",
  "properties": {
    "addr:full":"2 South Mall London Greater London N9 0TN",
    "addr:housenumber":"2",
    "addr:postcode":"n9 0tn",
    "addr:street":"South Mall",
    "iso:country":"GB",
    "sg:address":"2 South Mall",
    "sg:city":"London",
    "sg:classifiers":[
        {
            "category":"Shopping",
            "subcategory":"News",
            "type":"Retail Goods"
        }
    ],
    "sg:phone":"+44 20 8803 0931",
    "sg:postcode":"N9 0TN",
    "sg:province":"Greater London",
    "sg:tags":[
        "newsagent"
    ],
    "wof:name":"Dodhia Newsagents",
    "wof:placetype":"venue"
},
  "geometry": {"coordinates":[-0.05846,51.62344],"type":"Point"}
}