{
  "type": "Feature",
  "properties": {
    "iso:country":"GB",
    "sg:address":"2 Rye Close",
    "sg:city":"Bexley",
    "sg:classifiers":[
        {
            "category":"Building & Trades",
            "subcategory":"Cleaning & Sanitation",
            "type":"Services"
        }
    ],
    "sg:phone":"+44 1322 551416",
    "sg:postcode":"DA5 1PX",
    "sg:province":"Kent",
    "sg:tags":[
        "commercial"
    ],
    "wof:name":"Sevens Cleaning Co",
    "wof:placetype":"venue"
},
  "geometry": {"coordinates":[0.143484,51.445023],"type":"Point"}
}