{
  "type": "Feature",
  "properties": {
    "iso:country":"GB",
    "sg:address":"19 Goodwood Square, Teesside Retail Park, Thornaby",
    "sg:city":"Stockton-on-tees",
    "sg:classifiers":[
        {
            "category":"Professional",
            "subcategory":"Computer Services",
            "type":"Services"
        }
    ],
    "sg:phone":"+44 1642 602100",
    "sg:postcode":"TS17 7BW",
    "sg:province":"Durham",
    "sg:tags":[
        "system",
        "software"
    ],
    "wof:name":"Time Computers",
    "wof:placetype":"venue"
},
  "geometry": {"coordinates":[-1.275138,54.556126],"type":"Point"}
}