{
  "type": "Feature",
  "properties": {
    "iso:country":"GB",
    "sg:address":"2 Provision Market",
    "sg:city":"Norwich",
    "sg:classifiers":[
        {
            "category":"Farming",
            "subcategory":"Fish & Marine Products",
            "type":"Manufacturing & Wholesale Goods"
        }
    ],
    "sg:postcode":"NR2 1ND",
    "sg:province":"Norfolk",
    "sg:tags":[
        "fishmonger"
    ],
    "wof:name":"Claude R Rose",
    "wof:placetype":"venue"
},
  "geometry": {"coordinates":[1.293,52.628502],"type":"Point"}
}