{
  "type": "Feature",
  "properties": {
    "addr:full":"18 Ashley Centre Epsom Surrey KT18 5DA",
    "addr:housenumber":"18;centre",
    "addr:postcode":"kt18 5da",
    "addr:street":"Ashley",
    "iso:country":"GB",
    "sg:address":"18 Ashley Centre",
    "sg:city":"Epsom",
    "sg:classifiers":[
        {
            "category":"Shopping",
            "subcategory":"Books",
            "type":"Retail Goods"
        }
    ],
    "sg:phone":"+44 1372 742533",
    "sg:postcode":"KT18 5DA",
    "sg:province":"Surrey",
    "sg:tags":[
        "bookseller"
    ],
    "wof:name":"Hammicks Bookshop",
    "wof:placetype":"venue"
},
  "geometry": {"coordinates":[-0.266913,51.331646],"type":"Point"}
}