{
  "type": "Feature",
  "properties": {
    "iso:country":"GB",
    "sg:address":"22 Eastville Close, Eastern Avenue",
    "sg:city":"Gloucester",
    "sg:classifiers":[
        {
            "category":"Personal",
            "type":"Services"
        }
    ],
    "sg:phone":"+44 1452 504110",
    "sg:postcode":"GL4 7SJ",
    "sg:province":"Gloucestershire",
    "sg:tags":[
        "delivery"
    ],
    "wof:name":"A N C (Cheltenham) Ltd.",
    "wof:placetype":"venue"
},
  "geometry": {"coordinates":[-2.0954,51.828678],"type":"Point"}
}