{
  "type": "Feature",
  "properties": {
    "iso:country":"GB",
    "sg:address":"Churchill Wood Farm, Alcester Road, Churchill",
    "sg:city":"Worcester",
    "sg:classifiers":[
        {
            "category":"Farming",
            "subcategory":"Livestock Farm",
            "type":"Manufacturing & Wholesale Goods"
        }
    ],
    "sg:phone":"+44 1905 345232",
    "sg:postcode":"WR7 4QD",
    "sg:province":"Worcestershire",
    "sg:tags":[
        "others"
    ],
    "wof:name":"J R Lane",
    "wof:placetype":"venue"
},
  "geometry": {"coordinates":[-2.1143250465,52.1858215332],"type":"Point"}
}