{
  "type": "Feature",
  "properties": {
    "iso:country":"GB",
    "sg:address":"6 Middles Av",
    "sg:city":"Worcester",
    "sg:classifiers":[
        {
            "category":"Professional",
            "subcategory":"Printing & Photocopies",
            "type":"Services"
        }
    ],
    "sg:phone":"+44 1905 724227",
    "sg:postcode":"WR4 0HE",
    "sg:province":"Worcestershire",
    "sg:tags":[
        "duplicating",
        "copying"
    ],
    "wof:name":"On Line Office",
    "wof:placetype":"venue"
},
  "geometry": {"coordinates":[-2.1814460754,52.2015686035],"type":"Point"}
}