{
  "type": "Feature",
  "properties": {
    "iso:country":"GB",
    "sg:address":"40 Averill Street, Fulham",
    "sg:city":"London",
    "sg:classifiers":[
        {
            "category":"Professional",
            "subcategory":"Computer Services",
            "type":"Services"
        }
    ],
    "sg:postcode":"W6 8EB",
    "sg:province":"Greater London",
    "sg:tags":[
        "system",
        "software"
    ],
    "wof:name":"Euriskei Ltd",
    "wof:placetype":"venue"
},
  "geometry": {"coordinates":[-0.218096,51.484535],"type":"Point"}
}