{
  "type": "Feature",
  "properties": {
    "addr:full":"Constituency Of Chesham And Amersham, House Of Commons Westminster Greater London SW1A 2PW",
    "addr:postcode":"sw1a 2pw",
    "iso:country":"GB",
    "sg:address":"Constituency Of Chesham And Amersham, House Of Commons",
    "sg:city":"Westminster",
    "sg:classifiers":[
        {
            "category":"Government",
            "subcategory":"Office",
            "type":"Public Place"
        }
    ],
    "sg:phone":"+44 20 7219 3000",
    "sg:postcode":"SW1A 2PW",
    "sg:province":"Greater London",
    "sg:tags":[
        "mp",
        "meps"
    ],
    "wof:name":"Cheryl Gillan MP (Con)",
    "wof:placetype":"venue"
},
  "geometry": {"coordinates":[-0.1246400028,51.4997901917],"type":"Point"}
}