{
  "type": "Feature",
  "properties": {
    "addr:full":"Carr Farm, Cadney Brigg Lincolnshire DN20 9HP",
    "addr:postcode":"dn20 9hp",
    "addr:street":"Carr;Brigg",
    "iso:country":"GB",
    "sg:address":"Carr Farm, Cadney",
    "sg:city":"Brigg",
    "sg:classifiers":[
        {
            "category":"Building & Trades",
            "subcategory":"Landscaping Services",
            "type":"Services"
        }
    ],
    "sg:phone":"+44 1652 651341",
    "sg:postcode":"DN20 9HP",
    "sg:province":"Lincolnshire",
    "sg:tags":[
        "design",
        "designer",
        "architect",
        "garden",
        "landscape"
    ],
    "wof:name":"CAPABILITY DESIGN & LANDSCAPES LTD",
    "wof:placetype":"venue"
},
  "geometry": {"coordinates":[-0.4705089927,53.5182762146],"type":"Point"}
}