{
  "type": "Feature",
  "properties": {
    "addr:full":"52 Kings Walk Gloucester Gloucestershire GL1 1RX",
    "addr:housenumber":"52",
    "addr:postcode":"gl1 1rx",
    "addr:street":"Kings Walk",
    "iso:country":"GB",
    "sg:address":"52 Kings Walk",
    "sg:city":"Gloucester",
    "sg:classifiers":[
        {
            "category":"Professional",
            "subcategory":"Art Services",
            "type":"Services"
        }
    ],
    "sg:phone":"+44 1452 414461",
    "sg:postcode":"GL1 1RX",
    "sg:province":"Gloucestershire",
    "sg:tags":[
        "photographer"
    ],
    "wof:name":"Kodak Express",
    "wof:placetype":"venue"
},
  "geometry": {"coordinates":[-2.2420198917,51.8652458191],"type":"Point"}
}