{
  "type": "Feature",
  "properties": {
    "addr:full":"Heritage House, Lodge Lane Derby Derbyshire DE1 3HE",
    "addr:postcode":"de1 3he",
    "addr:street":"Lodge Lane",
    "iso:country":"GB",
    "sg:address":"Heritage House, Lodge Lane",
    "sg:city":"Derby",
    "sg:classifiers":[
        {
            "category":"Communications",
            "subcategory":"Newspaper",
            "type":"Services"
        }
    ],
    "sg:phone":"+44 1332 347087",
    "sg:postcode":"DE1 3HE",
    "sg:province":"Derbyshire",
    "sg:tags":[
        "magazine"
    ],
    "wof:name":"Derbyshire Countryside Ltd.",
    "wof:placetype":"venue"
},
  "geometry": {"coordinates":[-1.482519,52.927639],"type":"Point"}
}