{
  "type": "Feature",
  "properties": {
    "iso:country":"GB",
    "sg:address":"9 Alington Gro",
    "sg:city":"Wallington",
    "sg:classifiers":[
        {
            "category":"Retail",
            "subcategory":"Driving School",
            "type":"Services"
        }
    ],
    "sg:phone":"+44 20 8647 5684",
    "sg:postcode":"SM6 9NH",
    "sg:province":"Surrey",
    "wof:name":"J D S",
    "wof:placetype":"venue"
},
  "geometry": {"coordinates":[-0.1396149993,51.3501739502],"type":"Point"}
}