{
  "type": "Feature",
  "properties": {
    "iso:country":"GB",
    "sg:address":"25a Prospect St",
    "sg:city":"Bridlington",
    "sg:classifiers":[
        {
            "category":"Social Services",
            "subcategory":"Retirement Home",
            "type":"Services"
        }
    ],
    "sg:phone":"+44 1262 672566",
    "sg:postcode":"YO15 2AE",
    "sg:province":"East Riding of Yorkshire",
    "sg:tags":[
        "furrier"
    ],
    "wof:name":"Rodgers Of Bridlington Ltd",
    "wof:placetype":"venue"
},
  "geometry": {"coordinates":[-0.187399,54.08749],"type":"Point"}
}