{
  "type": "Feature",
  "properties": {
    "addr:full":"Trussley Works, Trussley Road London Greater London W6 7PR",
    "addr:postcode":"w6 7pr",
    "addr:street":"Trussley Road",
    "iso:country":"GB",
    "sg:address":"Trussley Works, Trussley Road",
    "sg:city":"London",
    "sg:classifiers":[
        {
            "category":"Building & Trades",
            "subcategory":"Construction",
            "type":"Services"
        }
    ],
    "sg:phone":"+44 20 8748 3011",
    "sg:postcode":"W6 7PR",
    "sg:province":"Greater London",
    "sg:tags":[
        "platform",
        "work",
        "scaffolding"
    ],
    "wof:name":"Kwikform (Uk)",
    "wof:placetype":"venue"
},
  "geometry": {"coordinates":[-0.225704,51.498783],"type":"Point"}
}