{
  "type": "Feature",
  "properties": {
    "iso:country":"GB",
    "sg:address":"220-224 Chatham Hill",
    "sg:city":"Chatham",
    "sg:classifiers":[
        {
            "category":"Manufacturing",
            "subcategory":"Furniture",
            "type":"Manufacturing & Wholesale Goods"
        }
    ],
    "sg:phone":"+44 1634 570111",
    "sg:postcode":"ME5 7BA",
    "sg:province":"Kent",
    "sg:tags":[
        "polishing",
        "french"
    ],
    "wof:name":"A C Polishers",
    "wof:placetype":"venue"
},
  "geometry": {"coordinates":[0.5397,51.377102],"type":"Point"}
}