{
  "type": "Feature",
  "properties": {
    "iso:country":"GB",
    "sg:address":"19 Bridge Street",
    "sg:city":"Witney",
    "sg:classifiers":[
        {
            "category":"Shopping",
            "subcategory":"Jewelry",
            "type":"Retail Goods"
        }
    ],
    "sg:phone":"+44 1993 775399",
    "sg:postcode":"OX28 1DA",
    "sg:province":"Oxfordshire",
    "sg:tags":[
        "gold",
        "silversmith"
    ],
    "wof:name":"We Three Kings",
    "wof:placetype":"venue"
},
  "geometry": {"coordinates":[-1.4821460247,51.7899284363],"type":"Point"}
}