{
  "type": "Feature",
  "properties": {
    "addr:full":"Toldunie, Glenfender, Blair Atholl Pitlochry Perth and Kinross PH18 5TU",
    "addr:postcode":"ph18 5tu",
    "addr:street":"Blair;Pitlochry",
    "iso:country":"GB",
    "sg:address":"Toldunie, Glenfender, Blair Atholl",
    "sg:city":"Pitlochry",
    "sg:classifiers":[
        {
            "category":"Building & Trades",
            "subcategory":"Construction",
            "type":"Services"
        }
    ],
    "sg:postcode":"PH18 5TU",
    "sg:province":"Perth and Kinross",
    "sg:tags":[
        "joiner",
        "carpenter"
    ],
    "wof:name":"Kyle Grant Construction",
    "wof:placetype":"venue"
},
  "geometry": {"coordinates":[-3.847939,56.765846],"type":"Point"}
}