{
  "type": "Feature",
  "properties": {
    "iso:country":"GB",
    "sg:address":"68 Mottram Rd",
    "sg:city":"Hyde",
    "sg:classifiers":[
        {
            "category":"Professional",
            "subcategory":"Management & Consulting",
            "type":"Services"
        }
    ],
    "sg:phone":"+44 1457 766755",
    "sg:postcode":"SK14 6BB",
    "sg:province":"Cheshire",
    "sg:tags":[
        "consultant",
        "safety"
    ],
    "wof:name":"Risk Dynamics",
    "wof:placetype":"venue"
},
  "geometry": {"coordinates":[-2.019914,53.442574],"type":"Point"}
}