{
  "type": "Feature",
  "properties": {
    "addr:full":"95 Vale Crescent London Greater London SW15 3RL",
    "addr:housenumber":"95",
    "addr:postcode":"sw15 3rl",
    "addr:street":"Vale Crescent",
    "iso:country":"GB",
    "sg:address":"95 Vale Crescent",
    "sg:city":"London",
    "sg:classifiers":[
        {
            "category":"Personal",
            "subcategory":"Hair Removal",
            "type":"Services"
        }
    ],
    "sg:phone":"+44 20 8549 6586",
    "sg:postcode":"SW15 3RL",
    "sg:province":"Greater London",
    "sg:tags":[
        "electrolysis"
    ],
    "wof:name":"Michael Kelly",
    "wof:placetype":"venue"
},
  "geometry": {"coordinates":[-0.2554430068,51.4331130981],"type":"Point"}
}