{
  "type": "Feature",
  "properties": {
    "iso:country":"GB",
    "sg:address":"3 Ravensbourne Road",
    "sg:city":"Bromley",
    "sg:classifiers":[
        {
            "category":"Personal",
            "subcategory":"Beauty Salon",
            "type":"Services"
        }
    ],
    "sg:phone":"+44 20 8464 0511",
    "sg:postcode":"BR1 1HN",
    "sg:province":"Kent",
    "sg:tags":[
        "unisex",
        "hairdresser"
    ],
    "wof:name":"Shears",
    "wof:placetype":"venue"
},
  "geometry": {"coordinates":[0.016258,51.400635],"type":"Point"}
}