{
  "type": "Feature",
  "properties": {
    "addr:full":"Ladygreen Lane, Ince Blundell Liverpool Merseyside L38 1QD",
    "addr:postcode":"l38 1qd",
    "addr:street":"Ladygreen Lane",
    "iso:country":"GB",
    "sg:address":"Ladygreen Lane, Ince Blundell",
    "sg:city":"Liverpool",
    "sg:classifiers":[
        {
            "category":"Home & Garden",
            "subcategory":"Garden Supply",
            "type":"Retail Goods"
        }
    ],
    "sg:phone":"+44 151 929 3635",
    "sg:postcode":"L38 1QD",
    "sg:province":"Merseyside",
    "sg:tags":[
        "nursery",
        "centre"
    ],
    "wof:name":"Ladygreen Nurseries",
    "wof:placetype":"venue"
},
  "geometry": {"coordinates":[-3.0313119888,53.5262680054],"type":"Point"}
}