{
  "type": "Feature",
  "properties": {
    "iso:country":"GB",
    "sg:address":"52 Shelley Rd",
    "sg:city":"Cheltenham",
    "sg:classifiers":[
        {
            "category":"Building & Trades",
            "subcategory":"Construction",
            "type":"Services"
        }
    ],
    "sg:phone":"+44 1242 584858",
    "sg:postcode":"GL51 7DR",
    "sg:province":"Gloucestershire",
    "sg:tags":[
        "decorator",
        "painter"
    ],
    "wof:name":"P F Lucey",
    "wof:placetype":"venue"
},
  "geometry": {"coordinates":[-2.117059,51.900154],"type":"Point"}
}