{
  "type": "Feature",
  "properties": {
    "addr:full":"Hollybush Cottage Pentrepiod Lane, Pentrepiod Pontypool Monmouthshire NP4 6TR",
    "addr:postcode":"np4 6tr",
    "addr:street":"Pentrepiod Lane",
    "iso:country":"GB",
    "sg:address":"Hollybush Cottage Pentrepiod Lane, Pentrepiod",
    "sg:city":"Pontypool",
    "sg:classifiers":[
        {
            "category":"Building & Trades",
            "subcategory":"Equipment Rental",
            "type":"Services"
        }
    ],
    "sg:phone":"+44 1495 769541",
    "sg:postcode":"NP4 6TR",
    "sg:province":"Monmouthshire",
    "sg:tags":[
        "plant",
        "machinery"
    ],
    "wof:name":"Williams B C D Plant Hire & Landfill Services",
    "wof:placetype":"venue"
},
  "geometry": {"coordinates":[-3.04319,51.703087],"type":"Point"}
}