{
  "type": "Feature",
  "properties": {
    "iso:country":"GB",
    "sg:address":"Kings Hall, St Ives Business Park, Parsons Green",
    "sg:city":"Huntingdon",
    "sg:classifiers":[
        {
            "category":"Professional",
            "subcategory":"Computer Services",
            "type":"Services"
        }
    ],
    "sg:phone":"+44 1480 494330",
    "sg:postcode":"PE17 4WY",
    "sg:province":"Cambridgeshire",
    "sg:tags":[
        "system",
        "software"
    ],
    "wof:name":"Pro-Iv Systems Ltd",
    "wof:placetype":"venue"
},
  "geometry": {"coordinates":[-0.1893000007,52.3351402283],"type":"Point"}
}