{
  "type": "Feature",
  "properties": {
    "iso:country":"GB",
    "sg:address":"9 Bouchier Avenue, Kings Park Village",
    "sg:city":"Braintree",
    "sg:classifiers":[
        {
            "category":"Retail",
            "subcategory":"Driving School",
            "type":"Services"
        }
    ],
    "sg:phone":"+44 1376 324448",
    "sg:postcode":"CM7 9FQ",
    "sg:province":"Essex",
    "wof:name":"K A Mutlow School Of Motoring",
    "wof:placetype":"venue"
},
  "geometry": {"coordinates":[0.582604,51.887245],"type":"Point"}
}