{
  "type": "Feature",
  "properties": {
    "addr:full":"4 Dundas Street Bonnyrigg Midlothian EH19 3AS",
    "addr:housenumber":"4",
    "addr:postcode":"eh19 3as",
    "addr:street":"Dundas Street",
    "iso:country":"GB",
    "sg:address":"4 Dundas Street",
    "sg:city":"Bonnyrigg",
    "sg:classifiers":[
        {
            "category":"Communications",
            "type":"Services"
        }
    ],
    "sg:postcode":"EH19 3AS",
    "sg:province":"Midlothian",
    "sg:tags":[
        "tv",
        "video",
        "radio"
    ],
    "wof:name":"W Watson",
    "wof:placetype":"venue"
},
  "geometry": {"coordinates":[-3.105451,55.874935],"type":"Point"}
}