{
  "type": "Feature",
  "properties": {
    "addr:full":"Staffords Farm, Garstang Road, Pilling Preston Lancashire PR3 6AR",
    "addr:postcode":"pr3 6ar",
    "addr:street":"Garstang Road",
    "iso:country":"GB",
    "sg:address":"Staffords Farm, Garstang Road, Pilling",
    "sg:city":"Preston",
    "sg:classifiers":[
        {
            "category":"Farming",
            "subcategory":"Livestock Farm",
            "type":"Manufacturing & Wholesale Goods"
        }
    ],
    "sg:phone":"+44 1253 790425",
    "sg:postcode":"PR3 6AR",
    "sg:province":"Lancashire",
    "sg:tags":[
        "others"
    ],
    "wof:name":"J & J Walmsley",
    "wof:placetype":"venue"
},
  "geometry": {"coordinates":[-2.9101560116,53.9309768677],"type":"Point"}
}