{
  "type": "Feature",
  "properties": {
    "addr:full":"1 Paternoster Row London Greater London EC4M 7DH",
    "addr:housenumber":"1",
    "addr:postcode":"ec4m 7dh",
    "addr:street":"Paternoster Row",
    "iso:country":"GB",
    "sg:address":"1 Paternoster Row",
    "sg:city":"London",
    "sg:classifiers":[
        {
            "category":"Banks & Credit Unions",
            "subcategory":"Bank",
            "type":"Services"
        }
    ],
    "sg:phone":"+44 20 7213 9900",
    "sg:postcode":"EC4M 7DH",
    "sg:province":"Greater London",
    "wof:name":"Credit Commercial De France",
    "wof:placetype":"venue"
},
  "geometry": {"coordinates":[-0.097534,51.514576],"type":"Point"}
}