{
  "type": "Feature",
  "properties": {
    "addr:full":"Fields Farm, Sutton On The Hill Ashbourne Derbyshire DE6 5JA",
    "addr:housenumber":"sutton",
    "addr:postcode":"de6 5ja",
    "addr:street":"Fields",
    "iso:country":"GB",
    "sg:address":"Fields Farm, Sutton On The Hill",
    "sg:city":"Ashbourne",
    "sg:classifiers":[
        {
            "category":"Farming",
            "subcategory":"Farm",
            "type":"Manufacturing & Wholesale Goods"
        }
    ],
    "sg:postcode":"DE6 5JA",
    "sg:province":"Derbyshire",
    "sg:tags":[
        "mixed",
        "crop"
    ],
    "wof:name":"R Etches",
    "wof:placetype":"venue"
},
  "geometry": {"coordinates":[-1.6531250477,52.8997802734],"type":"Point"}
}