{
  "type": "Feature",
  "properties": {
    "addr:full":"Barmston Rd, Swinemoor La Beverley East Riding of Yorkshire HU17 0LA",
    "addr:postcode":"hu17 0la",
    "addr:street":"Barmston Rd;La Beverley",
    "iso:country":"GB",
    "sg:address":"Barmston Rd, Swinemoor La",
    "sg:city":"Beverley",
    "sg:classifiers":[
        {
            "category":"Building & Trades",
            "subcategory":"Construction",
            "type":"Services"
        }
    ],
    "sg:phone":"+44 1482 862727",
    "sg:postcode":"HU17 0LA",
    "sg:province":"East Riding of Yorkshire",
    "sg:tags":[
        "equipment"
    ],
    "wof:name":"Willhire",
    "wof:placetype":"venue"
},
  "geometry": {"coordinates":[-0.4064149857,53.846118927],"type":"Point"}
}