{
  "type": "Feature",
  "properties": {
    "iso:country":"GB",
    "sg:address":"Lochearnhead Road",
    "sg:city":"Lochearnhead",
    "sg:classifiers":[
        {
            "category":"Travel",
            "subcategory":"Hotels & Motels",
            "type":"Entertainment"
        }
    ],
    "sg:postcode":"FK19 8NS",
    "sg:province":"Stirling",
    "wof:name":"Mansewood Country House",
    "wof:placetype":"venue"
},
  "geometry": {"coordinates":[-4.287324,56.385239],"type":"Point"}
}