{
  "type": "Feature",
  "properties": {
    "addr:full":"80 West Street, Bedminster Bristol City of Bristol BS3 3LL",
    "addr:housenumber":"80",
    "addr:postcode":"bs3 3ll",
    "addr:street":"West Street",
    "iso:country":"GB",
    "sg:address":"80 West Street, Bedminster",
    "sg:city":"Bristol",
    "sg:classifiers":[
        {
            "category":"Farming",
            "subcategory":"Aquatic Farm",
            "type":"Manufacturing & Wholesale Goods"
        }
    ],
    "sg:postcode":"BS3 3LL",
    "sg:province":"City of Bristol",
    "sg:tags":[
        "hydroponics"
    ],
    "wof:name":"Hydro Grow",
    "wof:placetype":"venue"
},
  "geometry": {"coordinates":[-2.603847,51.437962],"type":"Point"}
}