{
  "type": "Feature",
  "properties": {
    "iso:country":"GB",
    "sg:address":"104 Conway Road",
    "sg:city":"Colwyn Bay",
    "sg:classifiers":[
        {
            "category":"Health Services",
            "subcategory":"Dentist",
            "type":"Services"
        }
    ],
    "sg:phone":"+44 1492 532168",
    "sg:postcode":"LL29 7LL",
    "sg:province":"Conwy",
    "wof:name":"The West End Dental Clinic",
    "wof:placetype":"venue"
},
  "geometry": {"coordinates":[-3.735852,53.298496],"type":"Point"}
}