{
  "type": "Feature",
  "properties": {
    "addr:full":"18 Repton Drive Romford Essex RM2 5LP",
    "addr:housenumber":"18",
    "addr:postcode":"rm2 5lp",
    "addr:street":"Repton Drive",
    "iso:country":"GB",
    "sg:address":"18 Repton Drive",
    "sg:city":"Romford",
    "sg:classifiers":[
        {
            "category":"Travel",
            "subcategory":"Hotels & Motels",
            "type":"Entertainment"
        }
    ],
    "sg:phone":"+44 1708 745253",
    "sg:postcode":"RM2 5LP",
    "sg:province":"Essex",
    "wof:name":"Repton Private Hotel",
    "wof:placetype":"venue"
},
  "geometry": {"coordinates":[0.1964419931,51.5833816528],"type":"Point"}
}