{
  "type": "Feature",
  "properties": {
    "iso:country":"GB",
    "sg:address":"Hamdilla, Tregolls",
    "sg:city":"Truro",
    "sg:classifiers":[
        {
            "category":"Professional",
            "subcategory":"Secretarial Services",
            "type":"Services"
        }
    ],
    "sg:phone":"+44 1209 861345",
    "sg:postcode":"TR3 7BX",
    "sg:province":"Cornwall",
    "wof:name":"Business Matters",
    "wof:placetype":"venue"
},
  "geometry": {"coordinates":[-5.17976,50.179649],"type":"Point"}
}