{
  "type": "Feature",
  "properties": {
    "iso:country":"GB",
    "sg:address":"Segensworth Road, Titchfield",
    "sg:city":"Fareham",
    "sg:classifiers":[
        {
            "category":"Professional",
            "subcategory":"Computer Services",
            "type":"Services"
        }
    ],
    "sg:phone":"+44 1329 842511",
    "sg:postcode":"PO15 5RR",
    "sg:province":"Hampshire",
    "sg:tags":[
        "information"
    ],
    "wof:name":"Office for National Statistics",
    "wof:placetype":"venue"
},
  "geometry": {"coordinates":[-1.2477190495,50.8644981384],"type":"Point"}
}