{
  "type": "Feature",
  "properties": {
    "iso:country":"GB",
    "sg:address":"10a Victoria Street, Denton",
    "sg:city":"Manchester",
    "sg:classifiers":[
        {
            "category":"Shopping",
            "subcategory":"Clothing, Apparel, & Fashions",
            "type":"Retail Goods"
        }
    ],
    "sg:phone":"+44 161 335 9110",
    "sg:postcode":"M34 3JQ",
    "sg:province":"Greater Manchester",
    "sg:tags":[
        "sportswear"
    ],
    "wof:name":"Kingdom Sports Ltd.",
    "wof:placetype":"venue"
},
  "geometry": {"coordinates":[-2.1142590046,53.4558334351],"type":"Point"}
}