{
  "type": "Feature",
  "properties": {
    "addr:full":"Pinkneys Green Youth & Community Centre, Blenheim Rd Maidenhead Berkshire SL6 5HE",
    "addr:postcode":"sl6 5he",
    "addr:street":"Pinkneys;Blenheim Rd",
    "iso:country":"GB",
    "sg:address":"Pinkneys Green Youth & Community Centre, Blenheim Rd",
    "sg:city":"Maidenhead",
    "sg:classifiers":[
        {
            "category":"Government",
            "subcategory":"Office",
            "type":"Public Place"
        }
    ],
    "sg:phone":"+44 1628 628785",
    "sg:postcode":"SL6 5HE",
    "sg:province":"Berkshire",
    "sg:tags":[
        "local"
    ],
    "wof:name":"Windsor & Maidenhead Royal Borough Of",
    "wof:placetype":"venue"
},
  "geometry": {"coordinates":[-0.7496200204,51.5282897949],"type":"Point"}
}