{
  "type": "Feature",
  "properties": {
    "addr:full":"6 Old Red Lion Court, Bridge Street Stratford-upon-avon Warwickshire CV37 6AB",
    "addr:housenumber":"6",
    "addr:postcode":"cv37 6ab",
    "addr:street":"Old Red;Bridge Street",
    "iso:country":"GB",
    "sg:address":"6 Old Red Lion Court, Bridge Street",
    "sg:city":"Stratford-upon-avon",
    "sg:classifiers":[
        {
            "category":"Shopping",
            "subcategory":"Clothing, Apparel, & Fashions",
            "type":"Retail Goods"
        }
    ],
    "sg:postcode":"CV37 6AB",
    "sg:province":"Warwickshire",
    "sg:tags":[
        "menswear"
    ],
    "wof:name":"Classic Casuals",
    "wof:placetype":"venue"
},
  "geometry": {"coordinates":[-1.7072689533,52.1941337585],"type":"Point"}
}