{
  "type": "Feature",
  "properties": {
    "addr:full":"7 Kings Road Sutton Coldfield West Midlands B73 5AB",
    "addr:housenumber":"7",
    "addr:postcode":"b73 5ab",
    "addr:street":"Kings Road",
    "iso:country":"GB",
    "sg:address":"7 Kings Road",
    "sg:city":"Sutton Coldfield",
    "sg:classifiers":[
        {
            "category":"Food & Beverages",
            "subcategory":"Meat & Fish",
            "type":"Retail Goods"
        }
    ],
    "sg:phone":"+44 121 354 9546",
    "sg:postcode":"B73 5AB",
    "sg:province":"West Midlands",
    "sg:tags":[
        "butcher"
    ],
    "wof:name":"Lay Bros",
    "wof:placetype":"venue"
},
  "geometry": {"coordinates":[-1.859989,52.548351],"type":"Point"}
}