{
  "type": "Feature",
  "properties": {
    "iso:country":"GB",
    "sg:address":"135-137 Station Rd",
    "sg:city":"Chingford",
    "sg:classifiers":[
        {
            "category":"Professional",
            "subcategory":"Accounting & Tax Preparation",
            "type":"Services"
        }
    ],
    "sg:phone":"+44 20 8524 0119",
    "sg:postcode":"E4 6AG",
    "sg:province":"Greater London",
    "sg:tags":[
        "accountant",
        "chartered",
        "activity"
    ],
    "wof:name":"Findlay Wetherfield Scott & Co",
    "wof:placetype":"venue"
},
  "geometry": {"coordinates":[0.008031,51.632694],"type":"Point"}
}