{
  "type": "Feature",
  "properties": {
    "addr:full":"Barrowby Gate Swindon Wiltshire SN3 4UH",
    "addr:postcode":"sn3 4uh",
    "addr:street":"Barrowby Gate",
    "iso:country":"GB",
    "sg:address":"Barrowby Gate",
    "sg:city":"Swindon",
    "sg:classifiers":[
        {
            "category":"Manufacturing",
            "subcategory":"Building Materials",
            "type":"Manufacturing & Wholesale Goods"
        }
    ],
    "sg:phone":"+44 1793 829785",
    "sg:postcode":"SN3 4UH",
    "sg:province":"Wiltshire",
    "sg:tags":[
        "merchant",
        "builder"
    ],
    "wof:name":"Bauen Ltd",
    "wof:placetype":"venue"
},
  "geometry": {"coordinates":[-1.751305,51.588303],"type":"Point"}
}