{
  "type": "Feature",
  "properties": {
    "iso:country":"GB",
    "sg:address":"13 Milton Road, Hersham",
    "sg:city":"Walton-on-thames",
    "sg:classifiers":[
        {
            "category":"Professional",
            "subcategory":"Engineering",
            "type":"Services"
        },
        {
            "category":"Building & Trades",
            "subcategory":"Electrical",
            "type":"Services"
        }
    ],
    "sg:phone":"+44 1932 882223",
    "sg:postcode":"KT12 3HB",
    "sg:province":"Surrey",
    "sg:tags":[
        "engineer",
        "electrician",
        "contractor"
    ],
    "wof:name":"Qualified Electrician",
    "wof:placetype":"venue"
},
  "geometry": {"coordinates":[-0.394004,51.376385],"type":"Point"}
}