{
  "type": "Feature",
  "properties": {
    "addr:full":"Owls Barn, 28 Foxton Rd Cambridge Cambridgeshire CB2 5RN",
    "addr:housenumber":"28",
    "addr:postcode":"cb2 5rn",
    "addr:street":"Foxton Rd",
    "iso:country":"GB",
    "sg:address":"Owls Barn, 28 Foxton Rd",
    "sg:city":"Cambridge",
    "sg:classifiers":[
        {
            "category":"Building & Trades",
            "subcategory":"Construction",
            "type":"Services"
        }
    ],
    "sg:phone":"+44 1223 872422",
    "sg:postcode":"CB2 5RN",
    "sg:province":"Cambridgeshire",
    "sg:tags":[
        "heating",
        "contractor"
    ],
    "wof:name":"Peter Hollidge",
    "wof:placetype":"venue"
},
  "geometry": {"coordinates":[0.04291,52.127201],"type":"Point"}
}