{
  "type": "Feature",
  "properties": {
    "addr:full":"Unit 9 Bentley Business Park, Bentley La Walsall West Midlands WS2 8TL",
    "addr:housenumber":"unit 9",
    "addr:postcode":"ws2 8tl",
    "addr:street":"Bentley Business Park",
    "iso:country":"GB",
    "sg:address":"Unit 9 Bentley Business Park, Bentley La",
    "sg:city":"Walsall",
    "sg:classifiers":[
        {
            "category":"Wholesale",
            "subcategory":"Construction Materials",
            "type":"Manufacturing & Wholesale Goods"
        }
    ],
    "sg:phone":"+44 1922 610980",
    "sg:postcode":"WS2 8TL",
    "sg:province":"West Midlands",
    "sg:tags":[
        "merchant",
        "glass"
    ],
    "wof:name":"Ws28tl",
    "wof:placetype":"venue"
},
  "geometry": {"coordinates":[-2.003949,52.590225],"type":"Point"}
}