{
  "type": "Feature",
  "properties": {
    "iso:country":"GB",
    "sg:address":"Far Cromwell Road",
    "sg:city":"Stockport",
    "sg:classifiers":[
        {
            "category":"Building & Trades",
            "subcategory":"Equipment Rental",
            "type":"Services"
        }
    ],
    "sg:phone":"+44 161 430 4324",
    "sg:postcode":"SK6 2RP",
    "sg:province":"Cheshire",
    "sg:tags":[
        "plant",
        "machinery"
    ],
    "wof:name":"Cox Hire Centres",
    "wof:placetype":"venue"
},
  "geometry": {"coordinates":[-2.125394,53.433765],"type":"Point"}
}