{
  "type": "Feature",
  "properties": {
    "iso:country":"GB",
    "sg:address":"12 West End, Holbeach",
    "sg:city":"Spalding",
    "sg:classifiers":[
        {
            "category":"Health Services",
            "subcategory":"Optometrist",
            "type":"Services"
        },
        {
            "category":"Shopping",
            "subcategory":"Optician",
            "type":"Retail Goods"
        }
    ],
    "sg:phone":"+44 1406 423239",
    "sg:postcode":"PE12 7LW",
    "sg:province":"Cambridgeshire",
    "sg:tags":[
        "ophthalmic"
    ],
    "wof:name":"K Stradling Opticians",
    "wof:placetype":"venue"
},
  "geometry": {"coordinates":[0.0126550002,52.8040847778],"type":"Point"}
}