{
  "type": "Feature",
  "properties": {
    "addr:full":"Westfield Garage, Exeter Road Tiverton Devon EX16 5NZ",
    "addr:postcode":"ex16 5nz",
    "addr:street":"Exeter Road",
    "iso:country":"GB",
    "sg:address":"Westfield Garage, Exeter Road",
    "sg:city":"Tiverton",
    "sg:classifiers":[
        {
            "category":"Bus Charters",
            "type":"Transportation"
        }
    ],
    "sg:postcode":"EX16 5NZ",
    "sg:province":"Devon",
    "sg:tags":[
        "hire",
        "coach"
    ],
    "wof:name":"Kingdoms Coaches",
    "wof:placetype":"venue"
},
  "geometry": {"coordinates":[-3.493149,50.905025],"type":"Point"}
}