{
  "type": "Feature",
  "properties": {
    "addr:full":"Blaentir, Llangain Carmarthen Carmarthenshire SA33 5AY",
    "addr:postcode":"sa33 5ay",
    "addr:street":"Llangain;Carmarthenshire",
    "iso:country":"GB",
    "sg:address":"Blaentir, Llangain",
    "sg:city":"Carmarthen",
    "sg:classifiers":[
        {
            "category":"Home & Garden",
            "subcategory":"Garden Supply",
            "type":"Retail Goods"
        },
        {
            "category":"Community Center",
            "type":"Public Place"
        }
    ],
    "sg:phone":"+44 1267 241361",
    "sg:postcode":"SA33 5AY",
    "sg:province":"Carmarthenshire",
    "sg:tags":[
        "nursery",
        "ornament",
        "centre"
    ],
    "wof:name":"Graphbest Ltd.",
    "wof:placetype":"venue"
},
  "geometry": {"coordinates":[-4.347984,51.818481],"type":"Point"}
}