{
  "type": "Feature",
  "properties": {
    "addr:full":"Unit 3 Station Lane Industrial Estate, Station Lane, Old Whittington Chesterfield Derbyshire S41 9QX",
    "addr:housenumber":"unit 3;estate",
    "addr:postcode":"s41 9qx",
    "addr:street":"Station Lane Industrial;Station Lane",
    "iso:country":"GB",
    "sg:address":"Unit 3 Station Lane Industrial Estate, Station Lane, Old Whittington",
    "sg:city":"Chesterfield",
    "sg:classifiers":[
        {
            "category":"Retail",
            "subcategory":"Auto Repair",
            "type":"Services"
        }
    ],
    "sg:phone":"+44 1246 455540",
    "sg:postcode":"S41 9QX",
    "sg:province":"Derbyshire",
    "sg:tags":[
        "body",
        "car"
    ],
    "wof:name":"Roy Maskrey",
    "wof:placetype":"venue"
},
  "geometry": {"coordinates":[-1.4254390001,53.2690200806],"type":"Point"}
}