{
  "type": "Feature",
  "properties": {
    "iso:country":"GB",
    "sg:address":"6 Cooper Street, Off South Street",
    "sg:city":"Chichester",
    "sg:classifiers":[
        {
            "category":"Professional",
            "subcategory":"Management & Consulting",
            "type":"Services"
        }
    ],
    "sg:phone":"+44 1243 778825",
    "sg:postcode":"PO19 1EB",
    "sg:province":"West Sussex",
    "sg:tags":[
        "consultant",
        "specialist"
    ],
    "wof:name":"The Lazer Clinic",
    "wof:placetype":"venue"
},
  "geometry": {"coordinates":[-0.778803,50.835804],"type":"Point"}
}