{
  "type": "Feature",
  "properties": {
    "iso:country":"GB",
    "sg:address":"Butt Lane, Haworth",
    "sg:city":"Keighley",
    "sg:classifiers":[
        {
            "category":"Government",
            "subcategory":"Office",
            "type":"Public Place"
        }
    ],
    "sg:phone":"+44 1535 643608",
    "sg:postcode":"BD22 8QJ",
    "sg:province":"North Yorkshire",
    "sg:tags":[
        "local"
    ],
    "wof:name":"Haworth Youth & Community Centre",
    "wof:placetype":"venue"
},
  "geometry": {"coordinates":[-1.950252,53.830444],"type":"Point"}
}