{
  "type": "Feature",
  "properties": {
    "addr:full":"Wern Rd, Sebastopol Pontypool Monmouthshire NP4 5DR",
    "addr:postcode":"np4 5dr",
    "addr:street":"Wern Rd",
    "iso:country":"GB",
    "sg:address":"Wern Rd, Sebastopol",
    "sg:city":"Pontypool",
    "sg:classifiers":[
        {
            "category":"Bars & Pubs",
            "type":"Food & Drink"
        }
    ],
    "sg:phone":"+44 1495 763752",
    "sg:postcode":"NP4 5DR",
    "sg:province":"Monmouthshire",
    "sg:tags":[
        "pubs",
        "inn"
    ],
    "wof:name":"Open Hearth Inn",
    "wof:placetype":"venue"
},
  "geometry": {"coordinates":[-3.022395,51.680553],"type":"Point"}
}