{
  "type": "Feature",
  "properties": {
    "addr:full":"115 Montagu Street Kettering Northamptonshire NN16 8XJ",
    "addr:housenumber":"115",
    "addr:postcode":"nn16 8xj",
    "addr:street":"Montagu Street",
    "iso:country":"GB",
    "sg:address":"115 Montagu Street",
    "sg:city":"Kettering",
    "sg:classifiers":[
        {
            "category":"Fast Food",
            "type":"Food & Drink"
        }
    ],
    "sg:phone":"+44 1536 517827",
    "sg:postcode":"NN16 8XJ",
    "sg:province":"Northamptonshire",
    "sg:tags":[
        "away",
        "meal",
        "outlet",
        "take"
    ],
    "wof:name":"Master Chef",
    "wof:placetype":"venue"
},
  "geometry": {"coordinates":[-0.7193400264,52.4023323059],"type":"Point"}
}