{
  "type": "Feature",
  "properties": {
    "addr:full":"Newtown Hungerford Berkshire RG17 0PX",
    "addr:postcode":"rg17 0px",
    "iso:country":"GB",
    "sg:address":"Newtown",
    "sg:city":"Hungerford",
    "sg:classifiers":[
        {
            "category":"Home & Garden",
            "subcategory":"Home Furnishings",
            "type":"Retail Goods"
        }
    ],
    "sg:postcode":"RG17 0PX",
    "sg:province":"Berkshire",
    "sg:tags":[
        "mantelpiece",
        "fireplace"
    ],
    "wof:name":"Catchsmoke Firehoods",
    "wof:placetype":"venue"
},
  "geometry": {"coordinates":[-1.516156,51.413197],"type":"Point"}
}