{
  "type": "Feature",
  "properties": {
    "iso:country":"GB",
    "sg:address":"Seamer Grange Farm, Seamer",
    "sg:city":"Middlesbrough",
    "sg:classifiers":[
        {
            "category":"Farming",
            "subcategory":"Livestock Farm",
            "type":"Manufacturing & Wholesale Goods"
        }
    ],
    "sg:phone":"+44 1642 590079",
    "sg:postcode":"TS9 5LY",
    "sg:province":"North Yorkshire",
    "sg:tags":[
        "others"
    ],
    "wof:name":"T & C Bainbridge",
    "wof:placetype":"venue"
},
  "geometry": {"coordinates":[-1.230557,54.484856],"type":"Point"}
}