{
  "type": "Feature",
  "properties": {
    "addr:full":"578 Hertford Rd Enfield Greater London EN3 5SU",
    "addr:housenumber":"578",
    "addr:postcode":"en3 5su",
    "addr:street":"Hertford Rd",
    "iso:country":"GB",
    "sg:address":"578 Hertford Rd",
    "sg:city":"Enfield",
    "sg:classifiers":[
        {
            "category":"Professional",
            "subcategory":"Printing & Photocopies",
            "type":"Services"
        }
    ],
    "sg:phone":"+44 20 8443 3789",
    "sg:postcode":"EN3 5SU",
    "sg:province":"Greater London",
    "sg:tags":[
        "plate",
        "printer",
        "lithographic",
        "maker"
    ],
    "wof:name":"Minuteman Press",
    "wof:placetype":"venue"
},
  "geometry": {"coordinates":[-0.041557,51.668941],"type":"Point"}
}