{
  "type": "Feature",
  "properties": {
    "addr:full":"19/20 Garlick Hill London Greater London EC4V 2AL",
    "addr:housenumber":"19 / 20",
    "addr:postcode":"ec4v 2al",
    "addr:street":"Garlick Hill",
    "iso:country":"GB",
    "sg:address":"19/20 Garlick Hill",
    "sg:city":"London",
    "sg:classifiers":[
        {
            "category":"Professional",
            "subcategory":"Management & Consulting",
            "type":"Services"
        }
    ],
    "sg:postcode":"EC4V 2AL",
    "sg:province":"Greater London",
    "sg:tags":[
        "consultant",
        "business"
    ],
    "wof:name":"Font Framework Limited",
    "wof:placetype":"venue"
},
  "geometry": {"coordinates":[-0.0938989967,51.5112686157],"type":"Point"}
}