{
  "type": "Feature",
  "properties": {
    "addr:full":", Penmachno Betws Y Coed Conwy LL24 0UR",
    "addr:postcode":"ll24 0ur",
    "iso:country":"GB",
    "sg:address":", Penmachno",
    "sg:city":"Betws Y Coed",
    "sg:classifiers":[
        {
            "category":"Education",
            "subcategory":"School",
            "type":"Public Place"
        }
    ],
    "sg:phone":"+44 1690 760394",
    "sg:postcode":"LL24 0UR",
    "sg:province":"Conwy",
    "sg:tags":[
        "local",
        "authority"
    ],
    "wof:name":"Penmachno Primary School",
    "wof:placetype":"venue"
},
  "geometry": {"coordinates":[-3.802329,53.09182],"type":"Point"}
}