{
  "type": "Feature",
  "properties": {
    "addr:full":"16-18 Market Place Bury Lancashire BL0 9HT",
    "addr:housenumber":"16-18",
    "addr:postcode":"bl0 9ht",
    "addr:street":"Market Place",
    "iso:country":"GB",
    "sg:address":"16-18 Market Place",
    "sg:city":"Bury",
    "sg:classifiers":[
        {
            "category":"Restaurant",
            "type":"Food & Drink"
        }
    ],
    "sg:phone":"+44 1706 825070",
    "sg:postcode":"BL0 9HT",
    "sg:province":"Lancashire",
    "wof:name":"The Village Restaurant",
    "wof:placetype":"venue"
},
  "geometry": {"coordinates":[-2.2934319973,53.5926055908],"type":"Point"}
}