{
  "type": "Feature",
  "properties": {
    "iso:country":"GB",
    "sg:address":"6 The Mall",
    "sg:city":"Surbiton",
    "sg:classifiers":[
        {
            "category":"Organizations",
            "subcategory":"Religious Organization",
            "type":"Services"
        }
    ],
    "sg:phone":"+44 20 8390 4886",
    "sg:postcode":"KT6 4EQ",
    "sg:province":"Surrey",
    "sg:tags":[
        "organisation",
        "place",
        "worship"
    ],
    "wof:name":"Baha'i Faith",
    "wof:placetype":"venue"
},
  "geometry": {"coordinates":[-0.309882,51.39381],"type":"Point"}
}