{
  "type": "Feature",
  "properties": {
    "addr:full":"519 Slade Road Birmingham West Midlands B23 7JG",
    "addr:housenumber":"519",
    "addr:postcode":"b23 7jg",
    "addr:street":"Slade Road",
    "iso:country":"GB",
    "sg:address":"519 Slade Road",
    "sg:city":"Birmingham",
    "sg:classifiers":[
        {
            "category":"Food & Beverages",
            "subcategory":"Meat & Fish",
            "type":"Retail Goods"
        }
    ],
    "sg:phone":"+44 121 382 5212",
    "sg:postcode":"B23 7JG",
    "sg:province":"West Midlands",
    "sg:tags":[
        "butcher"
    ],
    "wof:name":"Brain Sillery Butchers",
    "wof:placetype":"venue"
},
  "geometry": {"coordinates":[-1.8588110209,52.5233039856],"type":"Point"}
}