{
  "type": "Feature",
  "properties": {
    "iso:country":"GB",
    "sg:address":"17 Willow Rd, Poyle Ind Est, Colnbrook",
    "sg:city":"Slough",
    "sg:classifiers":[
        {
            "category":"Home & Garden",
            "subcategory":"Kitchen Supply",
            "type":"Retail Goods"
        }
    ],
    "sg:phone":"+44 1753 685560",
    "sg:postcode":"SL3 0BS",
    "sg:province":"Berkshire",
    "sg:tags":[
        "equipment",
        "catering"
    ],
    "wof:name":"C.P Rose Ham Cookers",
    "wof:placetype":"venue"
},
  "geometry": {"coordinates":[-0.512429,51.475216],"type":"Point"}
}