{
  "type": "Feature",
  "properties": {
    "iso:country":"GB",
    "sg:address":"4 Churchhill Gdn(s)",
    "sg:city":"Newcastle-upon-tyne",
    "sg:classifiers":[
        {
            "category":"Shopping",
            "subcategory":"Antiques",
            "type":"Retail Goods"
        }
    ],
    "sg:phone":"+44 191 212 1500",
    "sg:postcode":"NE2 1HB",
    "sg:province":"Tyne and Wear",
    "wof:name":"Cradlewell Antiques",
    "wof:placetype":"venue"
},
  "geometry": {"coordinates":[-1.593289,54.988194],"type":"Point"}
}