{
  "type": "Feature",
  "properties": {
    "addr:full":"3 Duke Rd, Gorleston Great Yarmouth Norfolk NR31 6LL",
    "addr:housenumber":"3",
    "addr:postcode":"nr31 6ll",
    "addr:street":"Duke Rd Gorleston Great Yarmouth",
    "iso:country":"GB",
    "sg:address":"3 Duke Rd, Gorleston",
    "sg:city":"Great Yarmouth",
    "sg:classifiers":[
        {
            "category":"Personal",
            "subcategory":"Barber",
            "type":"Services"
        }
    ],
    "sg:phone":"+44 1493 661615",
    "sg:postcode":"NR31 6LL",
    "sg:province":"Norfolk",
    "sg:tags":[
        "men's",
        "hairdresser"
    ],
    "wof:name":"J Sargeant",
    "wof:placetype":"venue"
},
  "geometry": {"coordinates":[1.726191,52.580822],"type":"Point"}
}