{
  "type": "Feature",
  "properties": {
    "addr:full":"71 Bell St Reigate Surrey RH2 7AN",
    "addr:housenumber":"71",
    "addr:postcode":"rh2 7an",
    "addr:street":"Bell St",
    "iso:country":"GB",
    "sg:address":"71 Bell St",
    "sg:city":"Reigate",
    "sg:classifiers":[
        {
            "category":"Restaurant",
            "type":"Food & Drink"
        }
    ],
    "sg:phone":"+44 1737 241966",
    "sg:postcode":"RH2 7AN",
    "sg:province":"Surrey",
    "wof:name":"La Barbe",
    "wof:placetype":"venue"
},
  "geometry": {"coordinates":[-0.204483,51.235516],"type":"Point"}
}