{
  "type": "Feature",
  "properties": {
    "addr:full":"76 Adelaide Road Southampton Hampshire SO17 2HW",
    "addr:housenumber":"76",
    "addr:postcode":"so17 2hw",
    "addr:street":"Adelaide Road",
    "iso:country":"GB",
    "sg:address":"76 Adelaide Road",
    "sg:city":"Southampton",
    "sg:classifiers":[
        {
            "category":"Real Estate",
            "subcategory":"Real Estate Agent",
            "type":"Services"
        }
    ],
    "sg:phone":"+44 23 8039 9710",
    "sg:postcode":"SO17 2HW",
    "sg:province":"Hampshire",
    "wof:name":"Gillie & Co.",
    "wof:placetype":"venue"
},
  "geometry": {"coordinates":[-1.387066,50.922604],"type":"Point"}
}