{
  "type": "Feature",
  "properties": {
    "iso:country":"GB",
    "sg:address":"17 Church Street",
    "sg:city":"Tewkesbury",
    "sg:classifiers":[
        {
            "category":"Professional",
            "subcategory":"Computer Services",
            "type":"Services"
        }
    ],
    "sg:phone":"+44 1684 296585",
    "sg:postcode":"GL20 5PD",
    "sg:province":"Gloucestershire",
    "sg:tags":[
        "provider",
        "bureau",
        "facility"
    ],
    "sg:website":"http://www.atlas.co.uk",
    "wof:name":"Tewkesbury Data Services Ltd",
    "wof:placetype":"venue"
},
  "geometry": {"coordinates":[-2.1583180428,51.9918556213],"type":"Point"}
}