{
  "type": "Feature",
  "properties": {
    "addr:full":"Grover House, Grover Walk, Corringham Stanford Le Hope Essex SS17 7LS",
    "addr:postcode":"ss17 7ls",
    "addr:street":"Grover Walk",
    "iso:country":"GB",
    "sg:address":"Grover House, Grover Walk, Corringham",
    "sg:city":"Stanford Le Hope",
    "sg:classifiers":[
        {
            "category":"Shopping",
            "subcategory":"Department Store",
            "type":"Retail Goods"
        }
    ],
    "sg:postcode":"SS17 7LS",
    "sg:province":"Essex",
    "wof:name":"Rags Ltd",
    "wof:placetype":"venue"
},
  "geometry": {"coordinates":[0.446591,51.524548],"type":"Point"}
}