{
  "type": "Feature",
  "properties": {
    "iso:country":"GB",
    "sg:address":"Holmers Farm, Holmer Lane",
    "sg:city":"High Wycombe",
    "sg:classifiers":[
        {
            "category":"Health Services",
            "subcategory":"Health Practitioner",
            "type":"Services"
        }
    ],
    "sg:phone":"+44 1494 473414",
    "sg:postcode":"HP12 4QA",
    "sg:province":"Buckinghamshire",
    "sg:tags":[
        "homoeopathic"
    ],
    "wof:name":"Helen Jane Johnson",
    "wof:placetype":"venue"
},
  "geometry": {"coordinates":[-0.791679,51.613831],"type":"Point"}
}