{
  "type": "Feature",
  "properties": {
    "iso:country":"GB",
    "sg:address":"18 Morgan Arcade",
    "sg:city":"Cardiff",
    "sg:classifiers":[
        {
            "category":"Shopping",
            "subcategory":"Clothing, Apparel, & Fashions",
            "type":"Retail Goods"
        }
    ],
    "sg:phone":"+44 7813 758676",
    "sg:postcode":"CF10 1AF",
    "sg:province":"Cardiff",
    "sg:tags":[
        "clothing",
        "maternity",
        "wear"
    ],
    "sg:website":"http://www.swells.co.uk",
    "wof:name":"Swells Maternity Wear",
    "wof:placetype":"venue"
},
  "geometry": {"coordinates":[-3.177089,51.47879],"type":"Point"}
}