{
  "type": "Feature",
  "properties": {
    "iso:country":"GB",
    "sg:address":"P O Box 76",
    "sg:city":"Malvern",
    "sg:classifiers":[
        {
            "category":"Shopping",
            "subcategory":"Books",
            "type":"Retail Goods"
        }
    ],
    "sg:phone":"+44 1684 577433",
    "sg:postcode":"WR14 3LY",
    "sg:province":"Herefordshire",
    "wof:name":"Malvern Language Guides",
    "wof:placetype":"venue"
},
  "geometry": {"coordinates":[-2.31136,52.10833],"type":"Point"}
}