{
  "type": "Feature",
  "properties": {
    "addr:full":"2 York Road Paignton Devon TQ4 5NW",
    "addr:housenumber":"2",
    "addr:postcode":"tq4 5nw",
    "addr:street":"York Road",
    "iso:country":"GB",
    "sg:address":"2 York Road",
    "sg:city":"Paignton",
    "sg:classifiers":[
        {
            "category":"Manufacturing",
            "subcategory":"Glass & Minerals",
            "type":"Manufacturing & Wholesale Goods"
        }
    ],
    "sg:phone":"+44 1803 520254",
    "sg:postcode":"TQ4 5NW",
    "sg:province":"Devon",
    "sg:tags":[
        "fibre",
        "moulding"
    ],
    "wof:name":"Laminated Coatings Ltd.",
    "wof:placetype":"venue"
},
  "geometry": {"coordinates":[-3.5700850487,50.4302139282],"type":"Point"}
}