{
  "type": "Feature",
  "properties": {
    "iso:country":"GB",
    "sg:address":"River Farm",
    "sg:city":"Norwich",
    "sg:classifiers":[
        {
            "category":"Transit Center",
            "subcategory":"Passenger",
            "type":"Transportation"
        }
    ],
    "sg:phone":"+44 1362 820065",
    "sg:postcode":"NR9 4PJ",
    "sg:province":"Norfolk",
    "sg:tags":[
        "boarding",
        "kennel",
        "catteries"
    ],
    "wof:name":"Tugwells Boarding Kennels",
    "wof:placetype":"venue"
},
  "geometry": {"coordinates":[1.0221899748,52.6008415222],"type":"Point"}
}