{
  "type": "Feature",
  "properties": {
    "iso:country":"GB",
    "sg:address":"23 Sandyhill Road",
    "sg:city":"St Andrews",
    "sg:classifiers":[
        {
            "category":"Professional",
            "subcategory":"Engineering",
            "type":"Services"
        },
        {
            "category":"Building & Trades",
            "subcategory":"Electrical",
            "type":"Services"
        }
    ],
    "sg:phone":"+44 1334 476529",
    "sg:postcode":"KY16 8EG",
    "sg:province":"Fife",
    "sg:tags":[
        "engineer",
        "electrician",
        "contractor"
    ],
    "wof:name":"Richardson Electrical",
    "wof:placetype":"venue"
},
  "geometry": {"coordinates":[-2.794627,56.331825],"type":"Point"}
}