{
  "type": "Feature",
  "properties": {
    "iso:country":"GB",
    "sg:address":"14 Dalewood Walk, Stokesley",
    "sg:city":"Middlesbrough",
    "sg:classifiers":[
        {
            "category":"Building & Trades",
            "subcategory":"Construction",
            "type":"Services"
        }
    ],
    "sg:phone":"+44 1642 710809",
    "sg:postcode":"TS9 5JB",
    "sg:province":"North Yorkshire",
    "sg:tags":[
        "roofing"
    ],
    "wof:name":"Trinasco Roofing & Flooring",
    "wof:placetype":"venue"
},
  "geometry": {"coordinates":[-1.186591,54.477875],"type":"Point"}
}