{
  "type": "Feature",
  "properties": {
    "iso:country":"GB",
    "sg:address":"Bodowen Surgery, Halkyn Rd",
    "sg:city":"Holywell",
    "sg:classifiers":[
        {
            "category":"Health Services",
            "subcategory":"Doctor",
            "type":"Services"
        }
    ],
    "sg:phone":"+44 1352 710529",
    "sg:postcode":"CH8 7GA",
    "sg:province":"Denbighshire",
    "sg:tags":[
        "practitioners"
    ],
    "wof:name":"Lloyd, S M",
    "wof:placetype":"venue"
},
  "geometry": {"coordinates":[-3.225195,53.274548],"type":"Point"}
}