{
  "type": "Feature",
  "properties": {
    "iso:country":"GB",
    "sg:address":"109 Holme Lane",
    "sg:city":"Sheffield",
    "sg:classifiers":[
        {
            "category":"Freight",
            "type":"Transportation"
        }
    ],
    "sg:phone":"+44 114 233 3698",
    "sg:postcode":"S6 4JR",
    "sg:province":"South Yorkshire",
    "sg:tags":[
        "haulage",
        "road"
    ],
    "wof:name":"G Lake & Son Ltd.",
    "wof:placetype":"venue"
},
  "geometry": {"coordinates":[-1.5043450594,53.4014930725],"type":"Point"}
}