{
  "type": "Feature",
  "properties": {
    "iso:country":"GB",
    "sg:address":"Denbury Green, Denbury",
    "sg:city":"Newton Abbot",
    "sg:classifiers":[
        {
            "category":"Bars & Pubs",
            "type":"Food & Drink"
        }
    ],
    "sg:phone":"+44 1803 812595",
    "sg:postcode":"TQ12 6DQ",
    "sg:province":"Devon",
    "sg:tags":[
        "pubs",
        "inn"
    ],
    "wof:name":"The Union Inn",
    "wof:placetype":"venue"
},
  "geometry": {"coordinates":[-3.659479,50.505638],"type":"Point"}
}