{
  "type": "Feature",
  "properties": {
    "iso:country":"GB",
    "sg:address":"Padnell Road, Cowplain",
    "sg:city":"Waterlooville",
    "sg:classifiers":[
        {
            "category":"Arena",
            "subcategory":"Sports Club",
            "type":"Entertainment"
        }
    ],
    "sg:postcode":"PO8 8DZ",
    "sg:province":"Hampshire",
    "wof:name":"Cowplain Activity Centre Association",
    "wof:placetype":"venue"
},
  "geometry": {"coordinates":[-1.008779,50.896255],"type":"Point"}
}