{
  "type": "Feature",
  "properties": {
    "addr:full":"Bootle 1 Inland Revenue Office, The Triad, Stanley Rd Liverpool Merseyside L69 9HB",
    "addr:housenumber":"1;the",
    "addr:postcode":"l69 9hb",
    "addr:street":"Bootle;Stanley Rd",
    "iso:country":"GB",
    "sg:address":"Bootle 1 Inland Revenue Office, The Triad, Stanley Rd",
    "sg:city":"Liverpool",
    "sg:classifiers":[
        {
            "category":"Government",
            "subcategory":"Office",
            "type":"Public Place"
        }
    ],
    "sg:phone":"+44 151 300 5000",
    "sg:postcode":"L69 9HB",
    "sg:province":"Merseyside",
    "sg:tags":[
        "inland",
        "revenue"
    ],
    "wof:name":"Inland Revenue",
    "wof:placetype":"venue"
},
  "geometry": {"coordinates":[-2.98847,53.447899],"type":"Point"}
}