{
  "type": "Feature",
  "properties": {
    "addr:full":"12 Ashdene, Denecroft Cinderford Gloucestershire GL14 2LL",
    "addr:housenumber":"12",
    "addr:postcode":"gl14 2ll",
    "addr:street":"Ashdene Denecroft",
    "iso:country":"GB",
    "sg:address":"12 Ashdene, Denecroft",
    "sg:city":"Cinderford",
    "sg:classifiers":[
        {
            "category":"Freight",
            "type":"Transportation"
        }
    ],
    "sg:phone":"+44 1594 824113",
    "sg:postcode":"GL14 2LL",
    "sg:province":"Gloucestershire",
    "sg:tags":[
        "haulage",
        "transport",
        "road"
    ],
    "wof:name":"ROGER J TUDOR",
    "wof:placetype":"venue"
},
  "geometry": {"coordinates":[-2.5007989407,51.8200187683],"type":"Point"}
}