{
  "type": "Feature",
  "properties": {
    "addr:full":"12 Church Street Stranraer Dumfries and Galloway DG9 7JG",
    "addr:housenumber":"12",
    "addr:postcode":"dg9 7jg",
    "addr:street":"Church Street",
    "iso:country":"GB",
    "sg:address":"12 Church Street",
    "sg:city":"Stranraer",
    "sg:classifiers":[
        {
            "category":"Organizations",
            "subcategory":"Non-profit Organization",
            "type":"Services"
        }
    ],
    "sg:phone":"+44 1776 704415",
    "sg:postcode":"DG9 7JG",
    "sg:province":"Dumfries and Galloway",
    "sg:tags":[
        "charitable",
        "organisation",
        "voluntary",
        "charity"
    ],
    "wof:name":"DUMFRIES & GALLOWAY MENTAL HEALTH ASSOCIATION",
    "wof:placetype":"venue"
},
  "geometry": {"coordinates":[-5.0282320976,54.9041404724],"type":"Point"}
}