{
  "type": "Feature",
  "properties": {
    "addr:full":"180a Lifford Lane, Kings Norton Birmingham West Midlands B30 3DY",
    "addr:housenumber":"180a",
    "addr:postcode":"b30 3dy",
    "addr:street":"Lifford Lane",
    "iso:country":"GB",
    "sg:address":"180a Lifford Lane, Kings Norton",
    "sg:city":"Birmingham",
    "sg:classifiers":[
        {
            "category":"Sports & Exercise",
            "subcategory":"Gym",
            "type":"Entertainment"
        }
    ],
    "sg:phone":"+44 121 433 5472",
    "sg:postcode":"B30 3DY",
    "sg:province":"West Midlands",
    "sg:tags":[
        "fitness",
        "health",
        "centre"
    ],
    "wof:name":"Lakeside Fitness Centre",
    "wof:placetype":"venue"
},
  "geometry": {"coordinates":[-1.920699,52.419552],"type":"Point"}
}