{
  "type": "Feature",
  "properties": {
    "iso:country":"GB",
    "sg:address":"Garner Street",
    "sg:city":"Stoke-on-trent",
    "sg:classifiers":[
        {
            "category":"Utilities",
            "subcategory":"Fuel Oil & Lpg",
            "type":"Services"
        }
    ],
    "sg:phone":"+44 1782 745678",
    "sg:postcode":"ST4 7DE",
    "sg:province":"Staffordshire",
    "sg:tags":[
        "distributor"
    ],
    "wof:name":"Thames Lubricants Ltd.",
    "wof:placetype":"venue"
},
  "geometry": {"coordinates":[-2.2007329464,53.0160560608],"type":"Point"}
}