{
  "type": "Feature",
  "properties": {
    "addr:full":"125-126 Dunraven Street Tonypandy Rhondda, Cynon, Taff CF40 1QD",
    "addr:housenumber":"125-126",
    "addr:postcode":"cf40 1qd",
    "addr:street":"Dunraven Street;Cynon Taff",
    "iso:country":"GB",
    "sg:address":"125-126 Dunraven Street",
    "sg:city":"Tonypandy",
    "sg:classifiers":[
        {
            "category":"Shopping",
            "subcategory":"Department Store",
            "type":"Retail Goods"
        }
    ],
    "sg:phone":"+44 1443 434999",
    "sg:postcode":"CF40 1QD",
    "sg:province":"Rhondda, Cynon, Taff",
    "wof:name":"Sheila Williams",
    "wof:placetype":"venue"
},
  "geometry": {"coordinates":[-3.4553079605,51.6224594116],"type":"Point"}
}