{
  "type": "Feature",
  "properties": {
    "iso:country":"GB",
    "sg:address":"36 Straight Road, Boxted",
    "sg:city":"Colchester",
    "sg:classifiers":[
        {
            "category":"Personal",
            "type":"Services"
        }
    ],
    "sg:postcode":"CO4 5HN",
    "sg:province":"Essex",
    "sg:tags":[
        "wedding"
    ],
    "wof:name":"Anglia Regal Cars",
    "wof:placetype":"venue"
},
  "geometry": {"coordinates":[0.901373,51.935562],"type":"Point"}
}