{
  "type": "Feature",
  "properties": {
    "iso:country":"GB",
    "sg:address":"60 Main Street, Dundonald",
    "sg:city":"Kilmarnock",
    "sg:classifiers":[
        {
            "category":"Government",
            "subcategory":"City Hall",
            "type":"Public Place"
        },
        {
            "category":"Retail",
            "subcategory":"Event Space",
            "type":"Services"
        },
        {
            "category":"Government",
            "subcategory":"Office",
            "type":"Public Place"
        }
    ],
    "sg:phone":"+44 1563 851454",
    "sg:postcode":"KA2 9HE",
    "sg:province":"East Ayrshire",
    "sg:tags":[
        "function",
        "hire",
        "local",
        "room"
    ],
    "wof:name":"SOUTH AYRSHIRE COUNCIL",
    "wof:placetype":"venue"
},
  "geometry": {"coordinates":[-4.592688,55.574574],"type":"Point"}
}