{
  "type": "Feature",
  "properties": {
    "iso:country":"GB",
    "sg:address":"249 School Rd",
    "sg:city":"Birmingham",
    "sg:classifiers":[
        {
            "category":"Bars & Pubs",
            "type":"Food & Drink"
        }
    ],
    "sg:phone":"+44 121 430 4021",
    "sg:postcode":"B14 4ER",
    "sg:province":"West Midlands",
    "sg:tags":[
        "pubs",
        "inn"
    ],
    "wof:name":"Old Cottage The",
    "wof:placetype":"venue"
},
  "geometry": {"coordinates":[-1.864545,52.414272],"type":"Point"}
}