{
  "type": "Feature",
  "properties": {
    "addr:full":"Wesley House, 52/54 High Street Stoke-on-trent Cheshire ST7 4JT",
    "addr:housenumber":"52 / 54",
    "addr:postcode":"st7 4jt",
    "addr:street":"High Street",
    "iso:country":"GB",
    "sg:address":"Wesley House, 52/54 High Street",
    "sg:city":"Stoke-on-trent",
    "sg:classifiers":[
        {
            "category":"Real Estate",
            "subcategory":"Real Estate Agent",
            "type":"Services"
        }
    ],
    "sg:phone":"+44 1782 522117",
    "sg:postcode":"ST7 4JT",
    "sg:province":"Cheshire",
    "wof:name":"N J P Designs Ltd.",
    "wof:placetype":"venue"
},
  "geometry": {"coordinates":[-2.2079730034,53.1011390686],"type":"Point"}
}