{
  "type": "Feature",
  "properties": {
    "iso:country":"GB",
    "sg:address":"Chester Road",
    "sg:city":"Buckley",
    "sg:classifiers":[
        {
            "category":"Retail",
            "subcategory":"Auto Repair",
            "type":"Services"
        }
    ],
    "sg:phone":"+44 1244 549488",
    "sg:postcode":"CH7 3AJ",
    "sg:province":"Denbighshire",
    "sg:tags":[
        "body",
        "car"
    ],
    "wof:name":"Vincent Accident Repairs Biggs",
    "wof:placetype":"venue"
},
  "geometry": {"coordinates":[-3.066631,53.166538],"type":"Point"}
}