{
  "type": "Feature",
  "properties": {
    "addr:full":"5 Harwick Shopping Precinct, Home Farm Lane Bury St Edmunds Suffolk IP33 2RH",
    "addr:housenumber":"5",
    "addr:postcode":"ip33 2rh",
    "addr:street":"Harwick;Home Farm Lane",
    "iso:country":"GB",
    "sg:address":"5 Harwick Shopping Precinct, Home Farm Lane",
    "sg:city":"Bury St Edmunds",
    "sg:classifiers":[
        {
            "category":"Food & Beverages",
            "subcategory":"Liquor & Beverages",
            "type":"Retail Goods"
        }
    ],
    "sg:phone":"+44 1284 703601",
    "sg:postcode":"IP33 2RH",
    "sg:province":"Suffolk",
    "sg:tags":[
        "beer",
        "spirit",
        "wines"
    ],
    "wof:name":"Unwins Wine Merchants",
    "wof:placetype":"venue"
},
  "geometry": {"coordinates":[0.7093200088,52.2499046326],"type":"Point"}
}