{
  "type": "Feature",
  "properties": {
    "iso:country":"GB",
    "sg:address":"Exeter Livestock Centre, Matford Business Park",
    "sg:city":"Exeter",
    "sg:classifiers":[
        {
            "category":"Restaurant",
            "type":"Food & Drink"
        }
    ],
    "sg:phone":"+44 1392 203286",
    "sg:postcode":"EX2 8FD",
    "sg:province":"Devon",
    "wof:name":"Stockmans",
    "wof:placetype":"venue"
},
  "geometry": {"coordinates":[-3.522329,50.691917],"type":"Point"}
}