{
  "type": "Feature",
  "properties": {
    "iso:country":"GB",
    "sg:address":"Middle Slade, Buckingham Industrial Estate",
    "sg:city":"Buckingham",
    "sg:classifiers":[
        {
            "category":"Food & Beverages",
            "subcategory":"Bakery",
            "type":"Retail Goods"
        },
        {
            "category":"Home & Garden",
            "subcategory":"Kitchen Supply",
            "type":"Retail Goods"
        }
    ],
    "sg:phone":"+44 1280 822860",
    "sg:postcode":"MK18 1XT",
    "sg:province":"Buckinghamshire",
    "sg:tags":[
        "confectioner",
        "baker",
        "confectionery"
    ],
    "sg:website":"http://www.puratos.com",
    "wof:name":"Puratos Ltd.",
    "wof:placetype":"venue"
},
  "geometry": {"coordinates":[-0.9864789844,52.0007514954],"type":"Point"}
}