{
  "type": "Feature",
  "properties": {
    "addr:full":"1 Cramond Terrace Glasgow Glasgow City G32 0PE",
    "addr:housenumber":"1",
    "addr:postcode":"g32 0pe",
    "addr:street":"Cramond Terrace",
    "iso:country":"GB",
    "sg:address":"1 Cramond Terrace",
    "sg:city":"Glasgow",
    "sg:classifiers":[
        {
            "category":"Food & Beverages",
            "subcategory":"Meat & Fish",
            "type":"Retail Goods"
        }
    ],
    "sg:phone":"+44 141 774 5400",
    "sg:postcode":"G32 0PE",
    "sg:province":"Glasgow City",
    "sg:tags":[
        "chip"
    ],
    "wof:name":"Pauls Fish & Chip Takeaway",
    "wof:placetype":"venue"
},
  "geometry": {"coordinates":[-4.1591691971,55.8546791077],"type":"Point"}
}