{
  "type": "Feature",
  "properties": {
    "iso:country":"GB",
    "sg:address":"1 Needle St",
    "sg:city":"Sanquhar",
    "sg:classifiers":[
        {
            "category":"Community Center",
            "type":"Public Place"
        }
    ],
    "sg:phone":"+44 1659 66407",
    "sg:postcode":"DG4 6ND",
    "sg:province":"Dumfries and Galloway",
    "sg:tags":[
        "centre"
    ],
    "wof:name":"Miners Memorial Centre",
    "wof:placetype":"venue"
},
  "geometry": {"coordinates":[-4.0055408478,55.3874397278],"type":"Point"}
}