{
  "type": "Feature",
  "properties": {
    "iso:country":"GB",
    "sg:address":"Charles Ho, Bridge Rd",
    "sg:city":"Southall",
    "sg:classifiers":[
        {
            "category":"Manufacturing",
            "subcategory":"Signs",
            "type":"Manufacturing & Wholesale Goods"
        },
        {
            "category":"Professional",
            "subcategory":"Printing & Photocopies",
            "type":"Services"
        }
    ],
    "sg:postcode":"UB2 4BD",
    "sg:province":"Greater London",
    "sg:tags":[
        "plate",
        "writer",
        "lithographic",
        "maker"
    ],
    "wof:name":"Harlequin Graphics",
    "wof:placetype":"venue"
},
  "geometry": {"coordinates":[-0.353494,51.508785],"type":"Point"}
}