{
  "type": "Feature",
  "properties": {
    "iso:country":"GB",
    "sg:address":"39 Alfreton Road",
    "sg:city":"Nottingham",
    "sg:classifiers":[
        {
            "category":"Professional",
            "subcategory":"Art Services",
            "type":"Services"
        }
    ],
    "sg:postcode":"NG7 3JE",
    "sg:province":"Nottinghamshire",
    "sg:tags":[
        "graphic",
        "designer"
    ],
    "wof:name":"Charles Allison Associates",
    "wof:placetype":"venue"
},
  "geometry": {"coordinates":[-1.16365695,52.9568977356],"type":"Point"}
}