{
  "type": "Feature",
  "properties": {
    "addr:full":"5 Grange Park Road Manchester Greater Manchester M9 7AF",
    "addr:housenumber":"5",
    "addr:postcode":"m9 7af",
    "addr:street":"Grange Park Road",
    "iso:country":"GB",
    "sg:address":"5 Grange Park Road",
    "sg:city":"Manchester",
    "sg:classifiers":[
        {
            "category":"Fast Food",
            "type":"Food & Drink"
        }
    ],
    "sg:postcode":"M9 7AF",
    "sg:province":"Greater Manchester",
    "sg:tags":[
        "away",
        "take"
    ],
    "wof:name":"Hing Lung",
    "wof:placetype":"venue"
},
  "geometry": {"coordinates":[-2.193099,53.527023],"type":"Point"}
}