{
  "type": "Feature",
  "properties": {
    "iso:country":"GB",
    "sg:address":"Suite 1a Pc House, Hythe",
    "sg:city":"Southampton",
    "sg:classifiers":[
        {
            "category":"Professional",
            "subcategory":"Engineering",
            "type":"Services"
        }
    ],
    "sg:postcode":"SO45 6EB",
    "sg:province":"Hampshire",
    "sg:tags":[
        "merchant",
        "engineers'"
    ],
    "wof:name":"Engineering Supplies Ltd",
    "wof:placetype":"venue"
},
  "geometry": {"coordinates":[-1.45441401,50.886756897],"type":"Point"}
}