{
  "type": "Feature",
  "properties": {
    "iso:country":"GB",
    "sg:address":"91 Hockliffe Road",
    "sg:city":"Leighton Buzzard",
    "sg:classifiers":[
        {
            "category":"Insurance",
            "subcategory":"Insurance Agent",
            "type":"Services"
        }
    ],
    "sg:phone":"+44 1525 375940",
    "sg:postcode":"LU7 3FL",
    "sg:province":"Bedfordshire",
    "sg:tags":[
        "broker"
    ],
    "wof:name":"Fleetway Insurance Consultants",
    "wof:placetype":"venue"
},
  "geometry": {"coordinates":[-0.650469,51.918472],"type":"Point"}
}