{
  "type": "Feature",
  "properties": {
    "iso:country":"GB",
    "sg:address":"The E-tech Centre, Boundary Road, Harfreys Industrial Estate",
    "sg:city":"Great Yarmouth",
    "sg:classifiers":[
        {
            "category":"Professional",
            "subcategory":"Engineering",
            "type":"Services"
        }
    ],
    "sg:phone":"+44 1493 602020",
    "sg:postcode":"NR31 0LY",
    "sg:province":"Norfolk",
    "sg:tags":[
        "contractor",
        "electrical",
        "engineer"
    ],
    "wof:name":"Peto Services Ltd",
    "wof:placetype":"venue"
},
  "geometry": {"coordinates":[1.71553,52.593891],"type":"Point"}
}