{
  "type": "Feature",
  "properties": {
    "addr:full":"Gravel Walk Cullompton Devon EX15 1DA",
    "addr:postcode":"ex15 1da",
    "addr:street":"Gravel Walk",
    "iso:country":"GB",
    "sg:address":"Gravel Walk",
    "sg:city":"Cullompton",
    "sg:classifiers":[
        {
            "category":"Health Services",
            "subcategory":"Nursing And Care Facility",
            "type":"Services"
        }
    ],
    "sg:phone":"+44 1884 33142",
    "sg:postcode":"EX15 1DA",
    "sg:province":"Devon",
    "sg:tags":[
        "home"
    ],
    "wof:name":"Old Vicarage Nursing Home",
    "wof:placetype":"venue"
},
  "geometry": {"coordinates":[-3.390921,50.855461],"type":"Point"}
}