{
  "type": "Feature",
  "properties": {
    "addr:full":"14 Hildreth St London Greater London SW12 9RQ",
    "addr:housenumber":"14",
    "addr:postcode":"sw12 9rq",
    "addr:street":"Hildreth St",
    "iso:country":"GB",
    "sg:address":"14 Hildreth St",
    "sg:city":"London",
    "sg:classifiers":[
        {
            "category":"Shopping",
            "subcategory":"Beauty & Cosmetics",
            "type":"Retail Goods"
        }
    ],
    "sg:phone":"+44 20 8673 3609",
    "sg:postcode":"SW12 9RQ",
    "sg:province":"Greater London",
    "sg:tags":[
        "product"
    ],
    "wof:name":"Classic Cosmetic & Beauty Supplies",
    "wof:placetype":"venue"
},
  "geometry": {"coordinates":[-0.151344,51.444382],"type":"Point"}
}