{
  "type": "Feature",
  "properties": {
    "addr:full":"3 Fore Street South Brent Devon TQ10 9BQ",
    "addr:housenumber":"3",
    "addr:postcode":"tq10 9bq",
    "addr:street":"Fore Street",
    "iso:country":"GB",
    "sg:address":"3 Fore Street",
    "sg:city":"South Brent",
    "sg:classifiers":[
        {
            "category":"Food & Beverages",
            "subcategory":"Fruits & Vegetables",
            "type":"Retail Goods"
        }
    ],
    "sg:phone":"+44 1364 73545",
    "sg:postcode":"TQ10 9BQ",
    "sg:province":"Devon",
    "sg:tags":[
        "greengrocer"
    ],
    "wof:name":"Minimarket",
    "wof:placetype":"venue"
},
  "geometry": {"coordinates":[-3.834389,50.426338],"type":"Point"}
}