{
  "type": "Feature",
  "properties": {
    "addr:full":"Skelton Grange Road Leeds West Yorkshire LS10 1RZ",
    "addr:postcode":"ls10 1rz",
    "addr:street":"Grange Road",
    "iso:country":"GB",
    "sg:address":"Skelton Grange Road",
    "sg:city":"Leeds",
    "sg:classifiers":[
        {
            "category":"Wholesale",
            "subcategory":"Non-durable Goods",
            "type":"Manufacturing & Wholesale Goods"
        }
    ],
    "sg:phone":"+44 113 277 1313",
    "sg:postcode":"LS10 1RZ",
    "sg:province":"West Yorkshire",
    "sg:tags":[
        "carry",
        "cash"
    ],
    "wof:name":"Batleys Plc",
    "wof:placetype":"venue"
},
  "geometry": {"coordinates":[-1.5014569759,53.7741622925],"type":"Point"}
}