{
  "type": "Feature",
  "properties": {
    "iso:country":"GB",
    "sg:address":"Inchmartine House, Inchture",
    "sg:city":"Perth",
    "sg:classifiers":[
        {
            "category":"Shopping",
            "subcategory":"Antiques",
            "type":"Retail Goods"
        }
    ],
    "sg:postcode":"PH14 9QQ",
    "sg:province":"Perth and Kinross",
    "wof:name":"Inchmartine Fine Art",
    "wof:placetype":"venue"
},
  "geometry": {"coordinates":[-3.168468,56.446461],"type":"Point"}
}