{
  "type": "Feature",
  "properties": {
    "iso:country":"GB",
    "sg:address":"Winslow, Benacre Rd",
    "sg:city":"Whitstable",
    "sg:classifiers":[
        {
            "category":"Building & Trades",
            "subcategory":"Construction",
            "type":"Services"
        }
    ],
    "sg:phone":"+44 1227 772298",
    "sg:postcode":"CT5 4NY",
    "sg:province":"Kent",
    "sg:tags":[
        "builder"
    ],
    "wof:name":"Kent Building Services",
    "wof:placetype":"venue"
},
  "geometry": {"coordinates":[1.022855,51.344238],"type":"Point"}
}