{
  "type": "Feature",
  "properties": {
    "addr:full":"46 Common La Sheringham Norfolk NR26 8PW",
    "addr:housenumber":"46",
    "addr:postcode":"nr26 8pw",
    "addr:street":"Common La Sheringham",
    "iso:country":"GB",
    "sg:address":"46 Common La",
    "sg:city":"Sheringham",
    "sg:classifiers":[
        {
            "category":"Professional",
            "subcategory":"Management & Consulting",
            "type":"Services"
        }
    ],
    "sg:postcode":"NR26 8PW",
    "sg:province":"Norfolk",
    "sg:tags":[
        "consultant",
        "business"
    ],
    "wof:name":"Wood,David,",
    "wof:placetype":"venue"
},
  "geometry": {"coordinates":[1.2168409824,52.9359588623],"type":"Point"}
}