{
  "type": "Feature",
  "properties": {
    "iso:country":"GB",
    "sg:address":"8 Irving Street",
    "sg:city":"Southport",
    "sg:classifiers":[
        {
            "category":"Travel",
            "subcategory":"Hotels & Motels",
            "type":"Entertainment"
        }
    ],
    "sg:phone":"+44 1704 530924",
    "sg:postcode":"PR9 0HD",
    "sg:province":"Lancashire",
    "sg:tags":[
        "house",
        "guest"
    ],
    "wof:name":"Nirvana",
    "wof:placetype":"venue"
},
  "geometry": {"coordinates":[-3.000412,53.654888],"type":"Point"}
}