{
  "type": "Feature",
  "properties": {
    "iso:country":"GB",
    "sg:address":"C/o Kwik Save, 287-361 Caernarfon Road",
    "sg:city":"Bangor",
    "sg:classifiers":[
        {
            "category":"Food & Beverages",
            "subcategory":"Bakery",
            "type":"Retail Goods"
        }
    ],
    "sg:phone":"+44 1248 351512",
    "sg:postcode":"LL57 4SG",
    "sg:province":"Gwynedd",
    "sg:tags":[
        "baker"
    ],
    "wof:name":"Gibsons Hot Bread Kitchens",
    "wof:placetype":"venue"
},
  "geometry": {"coordinates":[-4.126064,53.229595],"type":"Point"}
}