{
  "type": "Feature",
  "properties": {
    "addr:full":"21 Atkyns Road Oxford Oxfordshire OX3 8RA",
    "addr:housenumber":"21",
    "addr:postcode":"ox3 8ra",
    "addr:street":"Atkyns Road",
    "iso:country":"GB",
    "sg:address":"21 Atkyns Road",
    "sg:city":"Oxford",
    "sg:classifiers":[
        {
            "category":"Food & Beverages",
            "subcategory":"Bakery",
            "type":"Retail Goods"
        }
    ],
    "sg:phone":"+44 1865 750053",
    "sg:postcode":"OX3 8RA",
    "sg:province":"Oxfordshire",
    "sg:tags":[
        "baker"
    ],
    "wof:name":"Wood Farm Bakery",
    "wof:placetype":"venue"
},
  "geometry": {"coordinates":[-1.201307,51.749359],"type":"Point"}
}