{
  "type": "Feature",
  "properties": {
    "addr:full":"County House, Castle Meadow Road Nottingham Nottinghamshire NG2 1AG",
    "addr:postcode":"ng2 1ag",
    "addr:street":"Castle Meadow Road",
    "iso:country":"GB",
    "sg:address":"County House, Castle Meadow Road",
    "sg:city":"Nottingham",
    "sg:classifiers":[
        {
            "category":"Education",
            "subcategory":"Library",
            "type":"Public Place"
        }
    ],
    "sg:phone":"+44 115 958 1634",
    "sg:postcode":"NG2 1AG",
    "sg:province":"Nottinghamshire",
    "sg:tags":[
        "book"
    ],
    "wof:name":"Nottinghamshire Archives",
    "wof:placetype":"venue"
},
  "geometry": {"coordinates":[-1.1521140337,52.9475898743],"type":"Point"}
}