{
  "type": "Feature",
  "properties": {
    "addr:full":"Mercian House, 15 Gleneagles, Amington Tamworth Staffordshire B77 4NS",
    "addr:housenumber":"15",
    "addr:postcode":"b77 4ns",
    "addr:street":"Gleneagles Amington",
    "iso:country":"GB",
    "sg:address":"Mercian House, 15 Gleneagles, Amington",
    "sg:city":"Tamworth",
    "sg:classifiers":[
        {
            "category":"Home & Garden",
            "subcategory":"Building Materials",
            "type":"Retail Goods"
        }
    ],
    "sg:phone":"+44 1827 54729",
    "sg:postcode":"B77 4NS",
    "sg:province":"Staffordshire",
    "sg:tags":[
        "gate",
        "door",
        "barrier"
    ],
    "wof:name":"Mercian Security Fencing Ltd",
    "wof:placetype":"venue"
},
  "geometry": {"coordinates":[-1.6483,52.634769],"type":"Point"}
}