{
  "type": "Feature",
  "properties": {
    "addr:full":"49-51 Front Street Stanley Durham DH9 0ST",
    "addr:housenumber":"49-51",
    "addr:postcode":"dh9 0st",
    "addr:street":"Front Street",
    "iso:country":"GB",
    "sg:address":"49-51 Front Street",
    "sg:city":"Stanley",
    "sg:classifiers":[
        {
            "category":"Shopping",
            "subcategory":"Discount & Variety Stores",
            "type":"Retail Goods"
        }
    ],
    "sg:phone":"+44 1207 280647",
    "sg:postcode":"DH9 0ST",
    "sg:province":"Durham",
    "sg:tags":[
        "centre"
    ],
    "wof:name":"Your More Store Ltd.",
    "wof:placetype":"venue"
},
  "geometry": {"coordinates":[-1.696629,54.872181],"type":"Point"}
}