{
  "type": "Feature",
  "properties": {
    "addr:full":"Unit B4 Lowfields Close, Lowfields Business Park Elland West Yorkshire HX5 9DX",
    "addr:postcode":"hx5 9dx",
    "addr:street":"Lowfields Close Lowfields Business Park Elland West",
    "iso:country":"GB",
    "sg:address":"Unit B4 Lowfields Close, Lowfields Business Park",
    "sg:city":"Elland",
    "sg:classifiers":[
        {
            "category":"Professional",
            "subcategory":"Computer Services",
            "type":"Services"
        }
    ],
    "sg:phone":"+44 1422 327000",
    "sg:postcode":"HX5 9DX",
    "sg:province":"West Yorkshire",
    "sg:tags":[
        "system",
        "software"
    ],
    "wof:name":"Result Group Ltd.",
    "wof:placetype":"venue"
},
  "geometry": {"coordinates":[-1.829345,53.691116],"type":"Point"}
}