{
  "type": "Feature",
  "properties": {
    "addr:full":"11 Lambeth Close Craven Arms Herefordshire SY7 9PD",
    "addr:housenumber":"11",
    "addr:postcode":"sy7 9pd",
    "addr:street":"Lambeth Close",
    "iso:country":"GB",
    "sg:address":"11 Lambeth Close",
    "sg:city":"Craven Arms",
    "sg:classifiers":[
        {
            "category":"Real Estate",
            "subcategory":"Real Estate Agent",
            "type":"Services"
        }
    ],
    "sg:phone":"+44 1588 672373",
    "sg:postcode":"SY7 9PD",
    "sg:province":"Herefordshire",
    "wof:name":"M J Cotham",
    "wof:placetype":"venue"
},
  "geometry": {"coordinates":[-2.833548069,52.4379806519],"type":"Point"}
}