{
  "type": "Feature",
  "properties": {
    "addr:full":"147 Town St Leeds West Yorkshire LS12 3HG",
    "addr:housenumber":"147",
    "addr:postcode":"ls12 3hg",
    "addr:street":"Town St",
    "iso:country":"GB",
    "sg:address":"147 Town St",
    "sg:city":"Leeds",
    "sg:classifiers":[
        {
            "category":"Restaurant",
            "type":"Food & Drink"
        }
    ],
    "sg:phone":"+44 113 279 4978",
    "sg:postcode":"LS12 3HG",
    "sg:province":"West Yorkshire",
    "sg:tags":[
        "indian"
    ],
    "wof:name":"Naseeb Restaurant & Take Away",
    "wof:placetype":"venue"
},
  "geometry": {"coordinates":[-1.5968799591,53.7970428467],"type":"Point"}
}