{
  "type": "Feature",
  "properties": {
    "iso:country":"GB",
    "sg:address":"13 Cross Street",
    "sg:city":"Wakefield",
    "sg:classifiers":[
        {
            "category":"Professional",
            "subcategory":"Detective & Security Services",
            "type":"Services"
        }
    ],
    "sg:phone":"+44 1924 377158",
    "sg:postcode":"WF1 3BW",
    "sg:province":"West Yorkshire",
    "sg:tags":[
        "alarm",
        "burglar",
        "system"
    ],
    "wof:name":"West Riding Home Securities",
    "wof:placetype":"venue"
},
  "geometry": {"coordinates":[-1.499691,53.683838],"type":"Point"}
}