{
  "type": "Feature",
  "properties": {
    "addr:full":"Anchor Service Station, Blackburn Rd Darwen Lancashire BB3 0AB",
    "addr:postcode":"bb3 0ab",
    "addr:street":"Blackburn Rd",
    "iso:country":"GB",
    "sg:address":"Anchor Service Station, Blackburn Rd",
    "sg:city":"Darwen",
    "sg:classifiers":[
        {
            "category":"Autos & Motor Vehicles",
            "subcategory":"Automobile Sales",
            "type":"Retail Goods"
        }
    ],
    "sg:phone":"+44 1254 701601",
    "sg:postcode":"BB3 0AB",
    "sg:province":"Lancashire",
    "sg:tags":[
        "commercial"
    ],
    "wof:name":"Cardinal Cars",
    "wof:placetype":"venue"
},
  "geometry": {"coordinates":[-2.4711899757,53.7228622437],"type":"Point"}
}