{
  "type": "Feature",
  "properties": {
    "iso:country":"GB",
    "sg:address":"2 Cheltenham Dr",
    "sg:city":"Chippenham",
    "sg:classifiers":[
        {
            "category":"Professional",
            "subcategory":"Art Services",
            "type":"Services"
        }
    ],
    "sg:phone":"+44 1249 460205",
    "sg:postcode":"SN14 0SE",
    "sg:province":"Gloucestershire",
    "sg:tags":[
        "photographer"
    ],
    "wof:name":"Sunset Studios",
    "wof:placetype":"venue"
},
  "geometry": {"coordinates":[-2.1429998875,51.4491233826],"type":"Point"}
}