{
  "type": "Feature",
  "properties": {
    "addr:full":"Marlow, Cardigan Road, Crundale Haverfordwest Pembrokeshire SA62 4DG",
    "addr:postcode":"sa62 4dg",
    "addr:street":"Marlow Cardigan Road",
    "iso:country":"GB",
    "sg:address":"Marlow, Cardigan Road, Crundale",
    "sg:city":"Haverfordwest",
    "sg:classifiers":[
        {
            "category":"Building & Trades",
            "subcategory":"Construction",
            "type":"Services"
        }
    ],
    "sg:phone":"+44 1437 764121",
    "sg:postcode":"SA62 4DG",
    "sg:province":"Pembrokeshire",
    "sg:tags":[
        "joiner",
        "carpenter"
    ],
    "wof:name":"Gwynn B Thomas",
    "wof:placetype":"venue"
},
  "geometry": {"coordinates":[-4.9482188225,51.8243293762],"type":"Point"}
}