{
  "type": "Feature",
  "properties": {
    "addr:full":"33 Bull Street Holt Norfolk NR25 6HP",
    "addr:housenumber":"33",
    "addr:postcode":"nr25 6hp",
    "addr:street":"Bull Street",
    "iso:country":"GB",
    "sg:address":"33 Bull Street",
    "sg:city":"Holt",
    "sg:classifiers":[
        {
            "category":"Shopping",
            "subcategory":"Antiques",
            "type":"Retail Goods"
        }
    ],
    "sg:phone":"+44 1263 714040",
    "sg:postcode":"NR25 6HP",
    "sg:province":"Norfolk",
    "wof:name":"Langhams",
    "wof:placetype":"venue"
},
  "geometry": {"coordinates":[1.0900609493,52.9065933228],"type":"Point"}
}