{
  "type": "Feature",
  "properties": {
    "addr:full":"9 Norwich Business Park, Whiting Rd Norwich Norfolk NR4 6DJ",
    "addr:housenumber":"9",
    "addr:postcode":"nr4 6dj",
    "addr:street":"Norwich Business Park Whiting Rd",
    "iso:country":"GB",
    "sg:address":"9 Norwich Business Park, Whiting Rd",
    "sg:city":"Norwich",
    "sg:classifiers":[
        {
            "category":"Insurance",
            "subcategory":"Insurance Agent",
            "type":"Services"
        }
    ],
    "sg:phone":"+44 1603 761377",
    "sg:postcode":"NR4 6DJ",
    "sg:province":"Norfolk",
    "wof:name":"Norwich Union Financial Services",
    "wof:placetype":"venue"
},
  "geometry": {"coordinates":[1.29205,52.608002],"type":"Point"}
}