{
  "type": "Feature",
  "properties": {
    "addr:full":"181 Becontree Avenue Dagenham Essex RM8 2UR",
    "addr:housenumber":"181",
    "addr:postcode":"rm8 2ur",
    "addr:street":"Becontree Avenue",
    "iso:country":"GB",
    "sg:address":"181 Becontree Avenue",
    "sg:city":"Dagenham",
    "sg:classifiers":[
        {
            "category":"Manufacturing",
            "subcategory":"Petroleum Products",
            "type":"Manufacturing & Wholesale Goods"
        }
    ],
    "sg:phone":"+44 20 8983 8183",
    "sg:postcode":"RM8 2UR",
    "sg:province":"Essex",
    "sg:tags":[
        "double",
        "glazing"
    ],
    "wof:name":"Essex Glazing Ltd.",
    "wof:placetype":"venue"
},
  "geometry": {"coordinates":[0.1191890016,51.5559577942],"type":"Point"}
}