{
  "type": "Feature",
  "properties": {
    "iso:country":"GB",
    "sg:address":"20 Bank Street",
    "sg:city":"Galashiels",
    "sg:classifiers":[
        {
            "category":"Retail",
            "subcategory":"Laundry & Dry Cleaning",
            "type":"Services"
        }
    ],
    "sg:phone":"+44 1896 751443",
    "sg:postcode":"TD1 1EN",
    "sg:province":"Scottish Borders",
    "sg:tags":[
        "alteration"
    ],
    "wof:name":"Nu-Look",
    "wof:placetype":"venue"
},
  "geometry": {"coordinates":[-2.807764,55.615761],"type":"Point"}
}