{
  "type": "Feature",
  "properties": {
    "addr:full":"182 Rainham Road Chatham Kent ME5 7EN",
    "addr:housenumber":"182",
    "addr:postcode":"me5 7en",
    "addr:street":"Rainham Road",
    "iso:country":"GB",
    "sg:address":"182 Rainham Road",
    "sg:city":"Chatham",
    "sg:classifiers":[
        {
            "category":"Home & Garden",
            "subcategory":"Building Materials",
            "type":"Retail Goods"
        },
        {
            "category":"Home & Garden",
            "subcategory":"Hardware",
            "type":"Retail Goods"
        }
    ],
    "sg:phone":"+44 1634 572162",
    "sg:postcode":"ME5 7EN",
    "sg:province":"Kent",
    "sg:tags":[
        "bathroom",
        "central",
        "fixture",
        "heating",
        "equipment",
        "fitting"
    ],
    "wof:name":"Oasis Plumbing & Bathrooms Ltd",
    "wof:placetype":"venue"
},
  "geometry": {"coordinates":[0.543843,51.37516],"type":"Point"}
}