{
  "type": "Feature",
  "properties": {
    "iso:country":"GB",
    "sg:address":"Rookery Road, Wombourne",
    "sg:city":"Wolverhampton",
    "sg:classifiers":[
        {
            "category":"Retail",
            "subcategory":"Repair Shop",
            "type":"Services"
        }
    ],
    "sg:phone":"+44 1902 895316",
    "sg:postcode":"WV5 0JG",
    "sg:province":"Shropshire",
    "sg:tags":[
        "plant",
        "machinery"
    ],
    "wof:name":"Dart Service Engineering",
    "wof:placetype":"venue"
},
  "geometry": {"coordinates":[-2.179478,52.535278],"type":"Point"}
}