{
  "type": "Feature",
  "properties": {
    "iso:country":"GB",
    "sg:address":"126-144 Lockhurst Lane",
    "sg:city":"Coventry",
    "sg:classifiers":[
        {
            "category":"Autos & Motor Vehicles",
            "subcategory":"Automobile Sales",
            "type":"Retail Goods"
        }
    ],
    "sg:phone":"+44 24 7668 6699",
    "sg:postcode":"CV6 5NY",
    "sg:province":"Warwickshire",
    "sg:tags":[
        "car"
    ],
    "sg:website":"http://www.prestige-garage.co.uk",
    "wof:name":"Prestige Garage Ltd",
    "wof:placetype":"venue"
},
  "geometry": {"coordinates":[-1.504749,52.432663],"type":"Point"}
}