{
  "type": "Feature",
  "properties": {
    "addr:full":"15 Progress Way Leicester Leicestershire LE4 9LQ",
    "addr:housenumber":"15",
    "addr:postcode":"le4 9lq",
    "addr:street":"Progress Way",
    "iso:country":"GB",
    "sg:address":"15 Progress Way",
    "sg:city":"Leicester",
    "sg:classifiers":[
        {
            "category":"Banks & Credit Unions",
            "subcategory":"Investment Brokerage",
            "type":"Services"
        },
        {
            "category":"Wholesale",
            "subcategory":"Chemicals & Plastics",
            "type":"Manufacturing & Wholesale Goods"
        }
    ],
    "sg:phone":"+44 116 274 2100",
    "sg:postcode":"LE4 9LQ",
    "sg:province":"Leicestershire",
    "sg:tags":[
        "supplier",
        "w'sale",
        "product"
    ],
    "wof:name":"Eurocell Building Plastics Ltd",
    "wof:placetype":"venue"
},
  "geometry": {"coordinates":[-1.0835319757,52.6586227417],"type":"Point"}
}