{
  "type": "Feature",
  "properties": {
    "iso:country":"GB",
    "sg:address":"54 Whyke Lane",
    "sg:city":"Chichester",
    "sg:classifiers":[
        {
            "category":"Shopping",
            "subcategory":"Department Store",
            "type":"Retail Goods"
        },
        {
            "category":"Food & Beverages",
            "subcategory":"Groceries & Convenience Stores",
            "type":"Retail Goods"
        }
    ],
    "sg:phone":"+44 1243 784080",
    "sg:postcode":"PO19 7PD",
    "sg:province":"West Sussex",
    "wof:name":"Lindwhyke Stores",
    "wof:placetype":"venue"
},
  "geometry": {"coordinates":[-0.769667,50.832619],"type":"Point"}
}