{
  "type": "Feature",
  "properties": {
    "addr:full":"Oakham Medical Centre, Cold Overton Road Oakham Leicestershire LE15 6NT",
    "addr:postcode":"le15 6nt",
    "addr:street":"Cold Overton Road",
    "iso:country":"GB",
    "sg:address":"Oakham Medical Centre, Cold Overton Road",
    "sg:city":"Oakham",
    "sg:classifiers":[
        {
            "category":"Health Services",
            "subcategory":"Health Practitioner",
            "type":"Services"
        }
    ],
    "sg:phone":"+44 116 257 1234",
    "sg:postcode":"LE15 6NT",
    "sg:province":"Leicestershire",
    "sg:tags":[
        "osteopath"
    ],
    "wof:name":"Oakham Osteopathic Clinic",
    "wof:placetype":"venue"
},
  "geometry": {"coordinates":[-0.730749011,52.6699790955],"type":"Point"}
}