{
  "type": "Feature",
  "properties": {
    "addr:full":"1 Culver St West Colchester Essex CO1 1JG",
    "addr:housenumber":"1",
    "addr:postcode":"co1 1jg",
    "addr:street":"Culver St West Colchester",
    "iso:country":"GB",
    "sg:address":"1 Culver St West",
    "sg:city":"Colchester",
    "sg:classifiers":[
        {
            "category":"Banks & Credit Unions",
            "subcategory":"Bank",
            "type":"Services"
        }
    ],
    "sg:phone":"+44 1206 577557",
    "sg:postcode":"CO1 1JG",
    "sg:province":"Essex",
    "sg:tags":[
        "broker",
        "mortgage"
    ],
    "wof:name":"H.P.S Financial Services",
    "wof:placetype":"venue"
},
  "geometry": {"coordinates":[0.8966339827,51.8892364502],"type":"Point"}
}