{
  "type": "Feature",
  "properties": {
    "iso:country":"GB",
    "sg:address":"Souterhead Road, Altens Industrial Estate",
    "sg:city":"Aberdeen",
    "sg:classifiers":[
        {
            "category":"Government",
            "subcategory":"Post Office",
            "type":"Public Place"
        }
    ],
    "sg:phone":"+44 1224 890999",
    "sg:postcode":"AB12 3LF",
    "sg:province":"Aberdeen City",
    "sg:tags":[
        "messenger",
        "courier"
    ],
    "wof:name":"Pegasus Express Ltd.",
    "wof:placetype":"venue"
},
  "geometry": {"coordinates":[-2.085233,57.110611],"type":"Point"}
}