{
  "type": "Feature",
  "properties": {
    "addr:full":"17 Kings Park Dereham Norfolk NR19 2AH",
    "addr:housenumber":"17",
    "addr:postcode":"nr19 2ah",
    "iso:country":"GB",
    "sg:address":"17 Kings Park",
    "sg:city":"Dereham",
    "sg:classifiers":[
        {
            "category":"Manufacturing",
            "subcategory":"Tools & Machinery",
            "type":"Manufacturing & Wholesale Goods"
        }
    ],
    "sg:phone":"+44 1362 696833",
    "sg:postcode":"NR19 2AH",
    "sg:province":"Norfolk",
    "sg:tags":[
        "cleaning"
    ],
    "wof:name":"Electromode Anglia",
    "wof:placetype":"venue"
},
  "geometry": {"coordinates":[0.9470729828,52.6832046509],"type":"Point"}
}