{
  "type": "Feature",
  "properties": {
    "iso:country":"GB",
    "sg:address":"14 Mountain Rd",
    "sg:city":"Caerphilly",
    "sg:classifiers":[
        {
            "category":"Shopping",
            "subcategory":"Computers & Home Electronics",
            "type":"Retail Goods"
        }
    ],
    "sg:phone":"+44 29 2088 2119",
    "sg:postcode":"CF83 1HJ",
    "sg:province":"Caerphilly",
    "wof:name":"M & A Pc Repairs Caerphilly",
    "wof:placetype":"venue"
},
  "geometry": {"coordinates":[-3.217893,51.569191],"type":"Point"}
}