{
  "type": "Feature",
  "properties": {
    "addr:full":"3 Lisle Road High Wycombe Buckinghamshire HP13 5SG",
    "addr:housenumber":"3",
    "addr:postcode":"hp13 5sg",
    "addr:street":"Lisle Road",
    "iso:country":"GB",
    "sg:address":"3 Lisle Road",
    "sg:city":"High Wycombe",
    "sg:classifiers":[
        {
            "category":"Communications",
            "type":"Services"
        },
        {
            "category":"Professional",
            "subcategory":"Computer Services",
            "type":"Services"
        }
    ],
    "sg:phone":"+44 1494 444036",
    "sg:postcode":"HP13 5SG",
    "sg:province":"Buckinghamshire",
    "sg:tags":[
        "consultant",
        "data",
        "network"
    ],
    "wof:name":"Cablelink (U K) Ltd.",
    "wof:placetype":"venue"
},
  "geometry": {"coordinates":[-0.755738,51.639214],"type":"Point"}
}