{
  "type": "Feature",
  "properties": {
    "addr:full":"Millfield Industrial Estate, Arksey Lane, Bentley Doncaster South Yorkshire DN5 0SJ",
    "addr:housenumber":"estate",
    "addr:postcode":"dn5 0sj",
    "addr:street":"Millfield Industrial;Arksey Lane",
    "iso:country":"GB",
    "sg:address":"Millfield Industrial Estate, Arksey Lane, Bentley",
    "sg:city":"Doncaster",
    "sg:classifiers":[
        {
            "category":"Home & Garden",
            "subcategory":"Garden Supply",
            "type":"Retail Goods"
        },
        {
            "category":"Manufacturing",
            "subcategory":"Building Materials",
            "type":"Manufacturing & Wholesale Goods"
        }
    ],
    "sg:phone":"+44 1302 820323",
    "sg:postcode":"DN5 0SJ",
    "sg:province":"South Yorkshire",
    "sg:tags":[
        "merchant",
        "sand",
        "gravel",
        "builder"
    ],
    "wof:name":"B M B Doncaster",
    "wof:placetype":"venue"
},
  "geometry": {"coordinates":[-1.1257719994,53.5556221008],"type":"Point"}
}