{
  "type": "Feature",
  "properties": {
    "iso:country":"GB",
    "sg:address":"14 Marsh Green Road",
    "sg:city":"Exeter",
    "sg:classifiers":[
        {
            "category":"Shopping",
            "subcategory":"Computers & Home Electronics",
            "type":"Retail Goods"
        }
    ],
    "sg:phone":"+44 1392 434551",
    "sg:postcode":"EX2 8PX",
    "sg:province":"Devon",
    "sg:tags":[
        "electrical"
    ],
    "wof:name":"Walsall Electrical Distributors",
    "wof:placetype":"venue"
},
  "geometry": {"coordinates":[-3.526976,50.707195],"type":"Point"}
}