{
  "type": "Feature",
  "properties": {
    "iso:country":"GB",
    "sg:address":"Drummond Road, Aston Fields Industrial Estate",
    "sg:city":"Stafford",
    "sg:classifiers":[
        {
            "category":"Wholesale",
            "subcategory":"Construction Materials",
            "type":"Manufacturing & Wholesale Goods"
        }
    ],
    "sg:phone":"+44 1785 223166",
    "sg:postcode":"ST16 3EL",
    "sg:province":"Staffordshire",
    "sg:tags":[
        "merchant",
        "glass"
    ],
    "wof:name":"Schott U K Ltd.",
    "wof:placetype":"venue"
},
  "geometry": {"coordinates":[-2.1142230034,52.8214836121],"type":"Point"}
}