{
  "type": "Feature",
  "properties": {
    "iso:country":"GB",
    "sg:address":"4 Medway Walk",
    "sg:city":"Manchester",
    "sg:classifiers":[
        {
            "category":"Food & Beverages",
            "subcategory":"Meat & Fish",
            "type":"Retail Goods"
        }
    ],
    "sg:postcode":"M40 7HS",
    "sg:province":"Greater Manchester",
    "sg:tags":[
        "butcher"
    ],
    "wof:name":"Tomlin Bros",
    "wof:placetype":"venue"
},
  "geometry": {"coordinates":[-2.218879,53.490665],"type":"Point"}
}