{
  "type": "Feature",
  "properties": {
    "addr:full":"52 Dalrymple Street Stranraer Dumfries and Galloway DG9 7EU",
    "addr:housenumber":"52",
    "addr:postcode":"dg9 7eu",
    "addr:street":"Dalrymple Street",
    "iso:country":"GB",
    "sg:address":"52 Dalrymple Street",
    "sg:city":"Stranraer",
    "sg:classifiers":[
        {
            "category":"Farming",
            "subcategory":"Dairy Farm",
            "type":"Manufacturing & Wholesale Goods"
        }
    ],
    "sg:postcode":"DG9 7EU",
    "sg:province":"Dumfries and Galloway",
    "wof:name":"Douglas Dairy Supply",
    "wof:placetype":"venue"
},
  "geometry": {"coordinates":[-5.0234479904,54.9010620117],"type":"Point"}
}