{
  "type": "Feature",
  "properties": {
    "iso:country":"GB",
    "sg:address":"40 Lowtown",
    "sg:city":"Pudsey",
    "sg:classifiers":[
        {
            "category":"Fast Food",
            "type":"Food & Drink"
        }
    ],
    "sg:phone":"+44 113 255 6103",
    "sg:postcode":"LS28 7AA",
    "sg:province":"West Yorkshire",
    "sg:tags":[
        "away",
        "meal",
        "outlet",
        "take"
    ],
    "wof:name":"Red Fort Take Away",
    "wof:placetype":"venue"
},
  "geometry": {"coordinates":[-1.6608599424,53.7973632812],"type":"Point"}
}