{
  "type": "Feature",
  "properties": {
    "iso:country":"GB",
    "sg:address":"26a Bancroft",
    "sg:city":"Hitchin",
    "sg:classifiers":[
        {
            "category":"Professional",
            "subcategory":"Accounting & Tax Preparation",
            "type":"Services"
        }
    ],
    "sg:phone":"+44 1462 441999",
    "sg:postcode":"SG5 1JW",
    "sg:province":"Bedfordshire",
    "sg:tags":[
        "accountant"
    ],
    "wof:name":"PTS Associates",
    "wof:placetype":"venue"
},
  "geometry": {"coordinates":[-0.276997,51.9504356384],"type":"Point"}
}