{
  "type": "Feature",
  "properties": {
    "iso:country":"GB",
    "sg:address":"16 The Broadway",
    "sg:city":"Woking",
    "sg:classifiers":[
        {
            "category":"Shopping",
            "subcategory":"Music",
            "type":"Retail Goods"
        }
    ],
    "sg:phone":"+44 1483 750040",
    "sg:postcode":"GU21 5AP",
    "sg:province":"Surrey",
    "sg:tags":[
        "record",
        "tape",
        "cd"
    ],
    "wof:name":"Collectors Record Centre",
    "wof:placetype":"venue"
},
  "geometry": {"coordinates":[-0.555641,51.319504],"type":"Point"}
}