{
  "type": "Feature",
  "properties": {
    "iso:country":"GB",
    "sg:address":"Graylaw Ho, 21 Goldington Rd",
    "sg:city":"Bedford",
    "sg:classifiers":[
        {
            "category":"Professional",
            "subcategory":"Management & Consulting",
            "type":"Services"
        }
    ],
    "sg:phone":"+44 1234 272407",
    "sg:postcode":"MK40 3JY",
    "sg:province":"Bedfordshire",
    "sg:tags":[
        "consultant",
        "geophysical",
        "geological"
    ],
    "wof:name":"Nopec GeoVentures International Ltd",
    "wof:placetype":"venue"
},
  "geometry": {"coordinates":[-0.464958,52.138973],"type":"Point"}
}