{
  "type": "Feature",
  "properties": {
    "iso:country":"GB",
    "sg:address":"The Goods Yard, Federal Road, Perivale",
    "sg:city":"Greenford",
    "sg:classifiers":[
        {
            "category":"Utilities",
            "subcategory":"Refuse",
            "type":"Services"
        }
    ],
    "sg:phone":"+44 20 8903 4714",
    "sg:postcode":"UB6 7AP",
    "sg:province":"Greater London",
    "sg:tags":[
        "skip",
        "hire"
    ],
    "wof:name":"Dunning Skip Hire",
    "wof:placetype":"venue"
},
  "geometry": {"coordinates":[-0.3101,51.53653],"type":"Point"}
}