{
  "type": "Feature",
  "properties": {
    "addr:full":"344 Elm Low Rd, Elm Wisbech Cambridgeshire PE14 0DA",
    "addr:housenumber":"344",
    "addr:postcode":"pe14 0da",
    "addr:street":"Elm Low Rd",
    "iso:country":"GB",
    "sg:address":"344 Elm Low Rd, Elm",
    "sg:city":"Wisbech",
    "sg:classifiers":[
        {
            "category":"Shopping",
            "subcategory":"Photographic Equipment",
            "type":"Retail Goods"
        }
    ],
    "sg:phone":"+44 1945 583744",
    "sg:postcode":"PE14 0DA",
    "sg:province":"Cambridgeshire",
    "wof:name":"Nene Studios",
    "wof:placetype":"venue"
},
  "geometry": {"coordinates":[0.17238,52.647961],"type":"Point"}
}