{
  "type": "Feature",
  "properties": {
    "addr:full":"Aquarius House, Archway Corner London Greater London N19 3TD",
    "addr:postcode":"n19 3td",
    "addr:street":"Archway Corner",
    "iso:country":"GB",
    "sg:address":"Aquarius House, Archway Corner",
    "sg:city":"London",
    "sg:classifiers":[
        {
            "category":"Professional",
            "subcategory":"Employment Agencies",
            "type":"Services"
        }
    ],
    "sg:phone":"+44 20 7272 6252",
    "sg:postcode":"N19 3TD",
    "sg:province":"Greater London",
    "sg:tags":[
        "consultant",
        "recruitment"
    ],
    "wof:name":"AQUARIUS EMPLOYMENT BUREAU (LONDON) LTD",
    "wof:placetype":"venue"
},
  "geometry": {"coordinates":[-0.1345700026,51.5660514832],"type":"Point"}
}