{
  "type": "Feature",
  "properties": {
    "iso:country":"GB",
    "sg:address":"Blackaton Farm",
    "sg:city":"Torrington",
    "sg:classifiers":[
        {
            "category":"Farming",
            "subcategory":"Livestock Farm",
            "type":"Manufacturing & Wholesale Goods"
        }
    ],
    "sg:phone":"+44 1805 622379",
    "sg:postcode":"EX38 7ET",
    "sg:province":"Devon",
    "sg:tags":[
        "others"
    ],
    "wof:name":"B W Allin",
    "wof:placetype":"venue"
},
  "geometry": {"coordinates":[-4.1422548294,50.9531517029],"type":"Point"}
}