{
  "type": "Feature",
  "properties": {
    "addr:full":"8 English St Carlisle Cumbria CA3 8HX",
    "addr:housenumber":"8",
    "addr:postcode":"ca3 8hx",
    "addr:street":"English St",
    "iso:country":"GB",
    "sg:address":"8 English St",
    "sg:city":"Carlisle",
    "sg:classifiers":[
        {
            "category":"Travel",
            "subcategory":"Travel Agent",
            "type":"Entertainment"
        }
    ],
    "sg:phone":"+44 1228 527531",
    "sg:postcode":"CA3 8HX",
    "sg:province":"Cumbria",
    "wof:name":"Worldchoice Carlson",
    "wof:placetype":"venue"
},
  "geometry": {"coordinates":[-2.935041,54.893639],"type":"Point"}
}