{
  "type": "Feature",
  "properties": {
    "iso:country":"GB",
    "sg:address":"56 Gavelly Hill, Erdington",
    "sg:city":"Birmingham",
    "sg:classifiers":[
        {
            "category":"Professional",
            "subcategory":"Management & Consulting",
            "type":"Services"
        }
    ],
    "sg:postcode":"B23 7TF",
    "sg:province":"West Midlands",
    "sg:tags":[
        "consultant",
        "specialist"
    ],
    "wof:name":"Patricia Walsh",
    "wof:placetype":"venue"
},
  "geometry": {"coordinates":[-1.854779,52.511051],"type":"Point"}
}