{
  "type": "Feature",
  "properties": {
    "addr:full":"76 Conference Road, Armley Leeds West Yorkshire LS12 3DX",
    "addr:housenumber":"76",
    "addr:postcode":"ls12 3dx",
    "addr:street":"Conference Road",
    "iso:country":"GB",
    "sg:address":"76 Conference Road, Armley",
    "sg:city":"Leeds",
    "sg:classifiers":[
        {
            "category":"Recreation",
            "subcategory":"Amusement Park",
            "type":"Entertainment"
        }
    ],
    "sg:postcode":"LS12 3DX",
    "sg:province":"West Yorkshire",
    "sg:tags":[
        "arcade"
    ],
    "wof:name":"M R Pickard",
    "wof:placetype":"venue"
},
  "geometry": {"coordinates":[-1.605011,53.795616],"type":"Point"}
}