{
  "type": "Feature",
  "properties": {
    "iso:country":"GB",
    "sg:address":"185 High Street, Cefn Coed",
    "sg:city":"Merthyr Tydfil",
    "sg:classifiers":[
        {
            "category":"Shopping",
            "subcategory":"Bicycles & Sporting Goods",
            "type":"Retail Goods"
        },
        {
            "category":"Recreation",
            "subcategory":"Fishing",
            "type":"Entertainment"
        }
    ],
    "sg:phone":"+44 1685 379809",
    "sg:postcode":"CF48 2PG",
    "sg:province":"Caerphilly",
    "sg:tags":[
        "equipment",
        "angling"
    ],
    "wof:name":"Merthyr Angling Centre",
    "wof:placetype":"venue"
},
  "geometry": {"coordinates":[-3.398250103,51.7600440979],"type":"Point"}
}