{
  "type": "Feature",
  "properties": {
    "addr:full":"36 Cascades Portsmouth Hampshire PO1 4RP",
    "addr:housenumber":"36",
    "addr:postcode":"hampshire po1 4rp",
    "addr:street":"Cascades",
    "iso:country":"GB",
    "sg:address":"36 Cascades",
    "sg:city":"Portsmouth",
    "sg:classifiers":[
        {
            "category":"Retail",
            "subcategory":"Photofinishing",
            "type":"Services"
        }
    ],
    "sg:phone":"+44 23 9283 8886",
    "sg:postcode":"PO1 4RP",
    "sg:province":"Hampshire",
    "sg:tags":[
        "photographic",
        "processor"
    ],
    "wof:name":"Warren James (Jewellers) Ltd.",
    "wof:placetype":"venue"
},
  "geometry": {"coordinates":[-1.09051,50.802822],"type":"Point"}
}