{
  "type": "Feature",
  "properties": {
    "addr:full":"Rochdale Road Oldham Lancashire OL1 2JH",
    "addr:postcode":"ol1 2jh",
    "addr:street":"Rochdale Road",
    "iso:country":"GB",
    "sg:address":"Rochdale Road",
    "sg:city":"Oldham",
    "sg:classifiers":[
        {
            "category":"Health Services",
            "subcategory":"Hospital",
            "type":"Services"
        }
    ],
    "sg:phone":"+44 161 627 8787",
    "sg:postcode":"OL1 2JH",
    "sg:province":"Lancashire",
    "sg:tags":[
        "ambulance"
    ],
    "wof:name":"Greater Manchester Ambulance Service N H S Trust",
    "wof:placetype":"venue"
},
  "geometry": {"coordinates":[-2.1204440594,53.5544433594],"type":"Point"}
}