{
  "type": "Feature",
  "properties": {
    "addr:full":"First Floor Newport Pagnell Buckinghamshire MK16 0AG",
    "addr:postcode":"mk16 0ag",
    "iso:country":"GB",
    "sg:address":"First Floor",
    "sg:city":"Newport Pagnell",
    "sg:classifiers":[
        {
            "category":"Professional",
            "subcategory":"Accounting & Tax Preparation",
            "type":"Services"
        }
    ],
    "sg:phone":"+44 1908 615225",
    "sg:postcode":"MK16 0AG",
    "sg:province":"Buckinghamshire",
    "sg:tags":[
        "accountant"
    ],
    "wof:name":"Clark Pritchard",
    "wof:placetype":"venue"
},
  "geometry": {"coordinates":[-0.6821290255,52.0458641052],"type":"Point"}
}