{
  "type": "Feature",
  "properties": {
    "iso:country":"GB",
    "sg:address":"2 Valmont Road, Sherwood",
    "sg:city":"Nottingham",
    "sg:classifiers":[
        {
            "category":"Community Center",
            "subcategory":"Youth",
            "type":"Public Place"
        }
    ],
    "sg:phone":"+44 115 952 3617",
    "sg:postcode":"NG5 1GA",
    "sg:province":"Nottinghamshire",
    "sg:tags":[
        "organisation",
        "centre"
    ],
    "wof:name":"Scout Association (Nottinghamshire County)",
    "wof:placetype":"venue"
},
  "geometry": {"coordinates":[-1.159797,52.986225],"type":"Point"}
}