{
  "type": "Feature",
  "properties": {
    "addr:full":"20 Wareham Road, Owermoigne Dorchester Dorset DT2 8HN",
    "addr:housenumber":"20",
    "addr:postcode":"dt2 8hn",
    "addr:street":"Wareham Road",
    "iso:country":"GB",
    "sg:address":"20 Wareham Road, Owermoigne",
    "sg:city":"Dorchester",
    "sg:classifiers":[
        {
            "category":"Home & Garden",
            "subcategory":"Garden Supply",
            "type":"Retail Goods"
        },
        {
            "category":"Home & Garden",
            "subcategory":"Building Materials",
            "type":"Retail Goods"
        }
    ],
    "sg:phone":"+44 1305 852483",
    "sg:postcode":"DT2 8HN",
    "sg:province":"Dorset",
    "sg:tags":[
        "plant",
        "centre",
        "equipment",
        "nursery",
        "servicing",
        "horticultural"
    ],
    "wof:name":"Owermoigne Nurseries",
    "wof:placetype":"venue"
},
  "geometry": {"coordinates":[-2.317449,50.663479],"type":"Point"}
}