{
  "type": "Feature",
  "properties": {
    "iso:country":"GB",
    "sg:address":"161 Lincoln Road",
    "sg:city":"Peterborough",
    "sg:classifiers":[
        {
            "category":"Travel",
            "subcategory":"Hotels & Motels",
            "type":"Entertainment"
        }
    ],
    "sg:phone":"+44 1733 568631",
    "sg:postcode":"PE1 2PW",
    "sg:province":"Cambridgeshire",
    "wof:name":"Brandon Hotel",
    "wof:placetype":"venue"
},
  "geometry": {"coordinates":[-0.244318,52.582737],"type":"Point"}
}