{
  "type": "Feature",
  "properties": {
    "iso:country":"GB",
    "sg:address":"Hilltop Cotts, Budworth Heath Lane, Aston-by-budworth",
    "sg:city":"Northwich",
    "sg:classifiers":[
        {
            "category":"Farming",
            "subcategory":"Aquatic Farm",
            "type":"Manufacturing & Wholesale Goods"
        }
    ],
    "sg:phone":"+44 1606 892083",
    "sg:postcode":"CW9 6NG",
    "sg:province":"Cheshire",
    "sg:tags":[
        "installers",
        "draughtproofing"
    ],
    "wof:name":"Draughtproofing Technology",
    "wof:placetype":"venue"
},
  "geometry": {"coordinates":[-2.5009739399,53.3022232056],"type":"Point"}
}