{
  "type": "Feature",
  "properties": {
    "iso:country":"GB",
    "sg:address":"St David's Park",
    "sg:city":"Deeside",
    "sg:classifiers":[
        {
            "category":"Travel",
            "subcategory":"Hotels & Motels",
            "type":"Entertainment"
        }
    ],
    "sg:phone":"+44 1244 520800",
    "sg:postcode":"CH5 3YB",
    "sg:province":"Flintshire",
    "wof:name":"VERE ST DAVID'S PARK HOTEL",
    "wof:placetype":"venue"
},
  "geometry": {"coordinates":[-3.0527899265,53.1903495789],"type":"Point"}
}