{
  "type": "Feature",
  "properties": {
    "iso:country":"GB",
    "sg:address":"5 Parrett Mead",
    "sg:city":"Taunton",
    "sg:classifiers":[
        {
            "category":"Utilities",
            "subcategory":"Natural Gas",
            "type":"Services"
        }
    ],
    "sg:phone":"+44 1823 322224",
    "sg:postcode":"TA1 2RZ",
    "sg:province":"Somerset",
    "sg:tags":[
        "control",
        "energy",
        "management",
        "system"
    ],
    "wof:name":"M S Services",
    "wof:placetype":"venue"
},
  "geometry": {"coordinates":[-3.0728309155,51.0121574402],"type":"Point"}
}