{
  "type": "Feature",
  "properties": {
    "addr:full":"32 Station Road Liphook Hampshire GU30 7DR",
    "addr:housenumber":"32",
    "addr:postcode":"gu30 7dr",
    "addr:street":"Station Road",
    "iso:country":"GB",
    "sg:address":"32 Station Road",
    "sg:city":"Liphook",
    "sg:classifiers":[
        {
            "category":"Home & Garden",
            "subcategory":"Carpets & Floor Coverings",
            "type":"Retail Goods"
        }
    ],
    "sg:phone":"+44 1428 724449",
    "sg:postcode":"GU30 7DR",
    "sg:province":"Hampshire",
    "sg:tags":[
        "carpets",
        "rug",
        "matting"
    ],
    "wof:name":"Carpetbaggers",
    "wof:placetype":"venue"
},
  "geometry": {"coordinates":[-0.8016530275,51.071269989],"type":"Point"}
}