{
  "type": "Feature",
  "properties": {
    "addr:full":"Raigmore Hospital Inverness Highland IV2 3UJ",
    "addr:postcode":"iv2 3uj",
    "iso:country":"GB",
    "sg:address":"Raigmore Hospital",
    "sg:city":"Inverness",
    "sg:classifiers":[
        {
            "category":"Banks & Credit Unions",
            "subcategory":"Bank",
            "type":"Services"
        }
    ],
    "sg:phone":"+44 1463 239167",
    "sg:postcode":"IV2 3UJ",
    "sg:province":"Highland",
    "wof:name":"Clydesdale Bank Plc",
    "wof:placetype":"venue"
},
  "geometry": {"coordinates":[-4.195579,57.480446],"type":"Point"}
}