{
  "type": "Feature",
  "properties": {
    "iso:country":"GB",
    "sg:address":"146 Portland Road",
    "sg:city":"London",
    "sg:classifiers":[
        {
            "category":"Food & Beverages",
            "subcategory":"Bakery",
            "type":"Retail Goods"
        }
    ],
    "sg:phone":"+44 20 8655 2983",
    "sg:postcode":"SE25 4PT",
    "sg:province":"Greater London",
    "sg:tags":[
        "baker"
    ],
    "wof:name":"Katie's Bakery",
    "wof:placetype":"venue"
},
  "geometry": {"coordinates":[-0.0673260018,51.3942222595],"type":"Point"}
}