{
  "type": "Feature",
  "properties": {
    "addr:full":"48 Lower Forster Street Walsall West Midlands WS1 1XB",
    "addr:housenumber":"48",
    "addr:postcode":"ws1 1xb",
    "addr:street":"Lower Forster Street",
    "iso:country":"GB",
    "sg:address":"48 Lower Forster Street",
    "sg:city":"Walsall",
    "sg:classifiers":[
        {
            "category":"Shopping",
            "subcategory":"Bicycles & Sporting Goods",
            "type":"Retail Goods"
        }
    ],
    "sg:phone":"+44 1922 623407",
    "sg:postcode":"WS1 1XB",
    "sg:province":"West Midlands",
    "sg:tags":[
        "riding",
        "saddlery",
        "wear"
    ],
    "wof:name":"Beebee & Beebee Ltd.",
    "wof:placetype":"venue"
},
  "geometry": {"coordinates":[-1.9775090218,52.5889091492],"type":"Point"}
}