{
  "type": "Feature",
  "properties": {
    "addr:full":"Duir House Dunfermline Fife KY11 8PY",
    "addr:postcode":"ky11 8py",
    "addr:street":"Dunfermline",
    "iso:country":"GB",
    "sg:address":"Duir House",
    "sg:city":"Dunfermline",
    "sg:classifiers":[
        {
            "category":"Shopping",
            "subcategory":"Stationery & Office Supplies",
            "type":"Retail Goods"
        }
    ],
    "sg:phone":"+44 1383 840800",
    "sg:postcode":"KY11 8PY",
    "sg:province":"Fife",
    "sg:tags":[
        "equipment"
    ],
    "wof:name":"The Copier & Computer Co",
    "wof:placetype":"venue"
},
  "geometry": {"coordinates":[-3.4021599293,56.0811271667],"type":"Point"}
}