{
  "type": "Feature",
  "properties": {
    "addr:full":"109 Radford Road Nottingham Nottinghamshire NG7 5DU",
    "addr:housenumber":"109",
    "addr:postcode":"ng7 5du",
    "addr:street":"Radford Road",
    "iso:country":"GB",
    "sg:address":"109 Radford Road",
    "sg:city":"Nottingham",
    "sg:classifiers":[
        {
            "category":"Manufacturing",
            "subcategory":"Textiles",
            "type":"Manufacturing & Wholesale Goods"
        }
    ],
    "sg:postcode":"NG7 5DU",
    "sg:province":"Nottinghamshire",
    "sg:tags":[
        "made-up"
    ],
    "wof:name":"Manchester Direct",
    "wof:placetype":"venue"
},
  "geometry": {"coordinates":[-1.1709740162,52.9661598206],"type":"Point"}
}