{
  "type": "Feature",
  "properties": {
    "addr:full":"38 Green Lane, West Ewell Epsom Surrey KT19 9UJ",
    "addr:housenumber":"38",
    "addr:postcode":"kt19 9uj",
    "addr:street":"Green Lane West",
    "iso:country":"GB",
    "sg:address":"38 Green Lane, West Ewell",
    "sg:city":"Epsom",
    "sg:classifiers":[
        {
            "category":"Retail",
            "subcategory":"Storage",
            "type":"Services"
        }
    ],
    "sg:postcode":"KT19 9UJ",
    "sg:province":"Surrey",
    "sg:tags":[
        "household",
        "removal"
    ],
    "wof:name":"Hope Transport & Light Removals Service",
    "wof:placetype":"venue"
},
  "geometry": {"coordinates":[-0.260317,51.351383],"type":"Point"}
}