{
  "type": "Feature",
  "properties": {
    "iso:country":"GB",
    "sg:address":"16 Park Road",
    "sg:city":"Swanage",
    "sg:classifiers":[
        {
            "category":"Travel",
            "subcategory":"Hotels & Motels",
            "type":"Entertainment"
        }
    ],
    "sg:postcode":"BH19 2AD",
    "sg:province":"Dorset",
    "sg:tags":[
        "house",
        "guest"
    ],
    "wof:name":"INGLESIDE GUEST HOUSE",
    "wof:placetype":"venue"
},
  "geometry": {"coordinates":[-1.955945,50.606857],"type":"Point"}
}