{
  "type": "Feature",
  "properties": {
    "iso:country":"GB",
    "sg:address":"39 Bridle Road, Shirley",
    "sg:city":"Croydon",
    "sg:classifiers":[
        {
            "category":"Professional",
            "subcategory":"Computer Services",
            "type":"Services"
        }
    ],
    "sg:postcode":"CR0 8HN",
    "sg:province":"Surrey",
    "sg:tags":[
        "system",
        "software"
    ],
    "wof:name":"D T P Services",
    "wof:placetype":"venue"
},
  "geometry": {"coordinates":[-0.030391,51.375443],"type":"Point"}
}