{
  "type": "Feature",
  "properties": {
    "addr:full":"151 Shaftesbury Avenue Holborn Greater London WC2H 8AL",
    "addr:housenumber":"151",
    "addr:postcode":"wc2h 8al",
    "addr:street":"Shaftesbury Avenue",
    "iso:country":"GB",
    "sg:address":"151 Shaftesbury Avenue",
    "sg:city":"Holborn",
    "sg:classifiers":[
        {
            "category":"Communications",
            "type":"Services"
        }
    ],
    "sg:phone":"+44 20 7769 8000",
    "sg:postcode":"WC2H 8AL",
    "sg:province":"Greater London",
    "sg:tags":[
        "telecommunication"
    ],
    "wof:name":"G T S Uk Ltd",
    "wof:placetype":"venue"
},
  "geometry": {"coordinates":[-0.12782,51.514442],"type":"Point"}
}