{
  "type": "Feature",
  "properties": {
    "addr:full":"4 Holmlea Road, Battlefield Glasgow East Renfrewshire G44 4AH",
    "addr:housenumber":"4",
    "addr:postcode":"g44 4ah",
    "addr:street":"Holmlea Road",
    "iso:country":"GB",
    "sg:address":"4 Holmlea Road, Battlefield",
    "sg:city":"Glasgow",
    "sg:classifiers":[
        {
            "category":"Taxi",
            "type":"Transportation"
        },
        {
            "category":"Military Area",
            "subcategory":"Air Force Base",
            "type":"Public Place"
        }
    ],
    "sg:phone":"+44 141 649 3333",
    "sg:postcode":"G44 4AH",
    "sg:province":"East Renfrewshire",
    "sg:tags":[
        "mini",
        "hire",
        "private",
        "cab"
    ],
    "wof:name":"Radio Cars Glasgow",
    "wof:placetype":"venue"
},
  "geometry": {"coordinates":[-4.2616991997,55.8246383667],"type":"Point"}
}