{
  "type": "Feature",
  "properties": {
    "iso:country":"GB",
    "sg:address":"199 Blackshots La",
    "sg:city":"Grays",
    "sg:classifiers":[
        {
            "category":"Retail",
            "subcategory":"Auto Rental",
            "type":"Services"
        }
    ],
    "sg:phone":"+44 1375 375527",
    "sg:postcode":"RM16 2LL",
    "sg:province":"Essex",
    "sg:tags":[
        "truck",
        "hire",
        "van"
    ],
    "wof:name":"A.J. Self Drive Van Hire",
    "wof:placetype":"venue"
},
  "geometry": {"coordinates":[0.337089,51.50087],"type":"Point"}
}