{
  "type": "Feature",
  "properties": {
    "iso:country":"GB",
    "sg:address":"86 Southampton Row",
    "sg:city":"London",
    "sg:classifiers":[
        {
            "category":"Shopping",
            "subcategory":"Stationery & Office Supplies",
            "type":"Retail Goods"
        }
    ],
    "sg:phone":"+44 20 7404 3948",
    "sg:postcode":"WC1B 4BB",
    "sg:province":"Greater London",
    "wof:name":"Ryman Stationers",
    "wof:placetype":"venue"
},
  "geometry": {"coordinates":[-0.1218649969,51.5198402405],"type":"Point"}
}