{
  "type": "Feature",
  "properties": {
    "iso:country":"GB",
    "sg:address":"79 Heathwood Road, Heath",
    "sg:city":"Cardiff",
    "sg:classifiers":[
        {
            "category":"Shopping",
            "subcategory":"Antiques",
            "type":"Retail Goods"
        }
    ],
    "sg:phone":"+44 29 2062 0520",
    "sg:postcode":"CF14 4JN",
    "sg:province":"Cardiff",
    "wof:name":"David Robinson Fairs",
    "wof:placetype":"venue"
},
  "geometry": {"coordinates":[-3.194522,51.513702],"type":"Point"}
}