{
  "type": "Feature",
  "properties": {
    "addr:full":"87-89 Forncett St Sheffield South Yorkshire S4 7QG",
    "addr:housenumber":"87-89",
    "addr:postcode":"s4 7qg",
    "addr:street":"Forncett St",
    "iso:country":"GB",
    "sg:address":"87-89 Forncett St",
    "sg:city":"Sheffield",
    "sg:classifiers":[
        {
            "category":"Bars & Pubs",
            "type":"Food & Drink"
        }
    ],
    "sg:phone":"+44 114 272 2140",
    "sg:postcode":"S4 7QG",
    "sg:province":"South Yorkshire",
    "sg:tags":[
        "pubs",
        "inn"
    ],
    "wof:name":"Crown Inn The",
    "wof:placetype":"venue"
},
  "geometry": {"coordinates":[-1.450077,53.395504],"type":"Point"}
}