{
  "type": "Feature",
  "properties": {
    "addr:full":"203 Coldharbour Lane Brixton Greater London SW9 8RZ",
    "addr:housenumber":"203",
    "addr:postcode":"sw9 8rz",
    "addr:street":"Coldharbour Lane",
    "iso:country":"GB",
    "sg:address":"203 Coldharbour Lane",
    "sg:city":"Brixton",
    "sg:classifiers":[
        {
            "category":"Fast Food",
            "type":"Food & Drink"
        }
    ],
    "sg:phone":"+44 20 7274 4110",
    "sg:postcode":"SW9 8RZ",
    "sg:province":"Greater London",
    "sg:tags":[
        "away",
        "take"
    ],
    "wof:name":"Fishermans Takeaway",
    "wof:placetype":"venue"
},
  "geometry": {"coordinates":[-0.101629,51.466179],"type":"Point"}
}