{
  "type": "Feature",
  "properties": {
    "addr:full":"13-15 North Road St Helens Merseyside WA10 2TN",
    "addr:housenumber":"13-15",
    "addr:postcode":"wa10 2tn",
    "addr:street":"North Road",
    "iso:country":"GB",
    "sg:address":"13-15 North Road",
    "sg:city":"St Helens",
    "sg:classifiers":[
        {
            "category":"Shopping",
            "subcategory":"Bicycles & Sporting Goods",
            "type":"Retail Goods"
        }
    ],
    "sg:phone":"+44 1744 25015",
    "sg:postcode":"WA10 2TN",
    "sg:province":"Merseyside",
    "sg:tags":[
        "cycle",
        "accessory"
    ],
    "wof:name":"Eric Bramilow's Cycle Shop",
    "wof:placetype":"venue"
},
  "geometry": {"coordinates":[-2.739047,53.456448],"type":"Point"}
}