{
  "type": "Feature",
  "properties": {
    "addr:full":"Unit B13 Poplar Business Park, Prestons Rd Poplar Greater London E14 9RL",
    "addr:housenumber":"b13",
    "addr:postcode":"e14 9rl",
    "addr:street":"Poplar Business Park Prestons Rd",
    "iso:country":"GB",
    "sg:address":"Unit B13 Poplar Business Park, Prestons Rd",
    "sg:city":"Poplar",
    "sg:classifiers":[
        {
            "category":"Manufacturing",
            "subcategory":"Signs",
            "type":"Manufacturing & Wholesale Goods"
        }
    ],
    "sg:phone":"+44 20 7515 0212",
    "sg:postcode":"E14 9RL",
    "sg:province":"Greater London",
    "sg:tags":[
        "nameplate"
    ],
    "wof:name":"A & S Signs",
    "wof:placetype":"venue"
},
  "geometry": {"coordinates":[-0.01043,51.507999],"type":"Point"}
}