{
  "type": "Feature",
  "properties": {
    "iso:country":"GB",
    "sg:address":"2 Ingleborough View, Main Street",
    "sg:city":"Carnforth",
    "sg:classifiers":[
        {
            "category":"Travel",
            "subcategory":"Hotels & Motels",
            "type":"Entertainment"
        }
    ],
    "sg:phone":"+44 15242 41523",
    "sg:postcode":"LA6 3HH",
    "sg:province":"Cumbria",
    "sg:tags":[
        "house",
        "guest"
    ],
    "wof:name":"Ingleborough View Guest House",
    "wof:placetype":"venue"
},
  "geometry": {"coordinates":[-2.460995,54.152115],"type":"Point"}
}