{
  "type": "Feature",
  "properties": {
    "iso:country":"GB",
    "sg:address":"15 Darlington Street",
    "sg:city":"Wigan",
    "sg:classifiers":[
        {
            "category":"Autos & Motor Vehicles",
            "subcategory":"Motorcycle Sales",
            "type":"Retail Goods"
        }
    ],
    "sg:phone":"+44 1942 497602",
    "sg:postcode":"WN1 1DL",
    "sg:province":"Lancashire",
    "wof:name":"Lamoto Motor Cycles",
    "wof:placetype":"venue"
},
  "geometry": {"coordinates":[-2.6280360222,53.5430603027],"type":"Point"}
}