{
  "type": "Feature",
  "properties": {
    "iso:country":"GB",
    "sg:address":"24 Regents Park Close, West Bridgford",
    "sg:city":"Nottingham",
    "sg:classifiers":[
        {
            "category":"Professional",
            "subcategory":"Accounting & Tax Preparation",
            "type":"Services"
        }
    ],
    "sg:postcode":"NG2 7ES",
    "sg:province":"Nottinghamshire",
    "sg:tags":[
        "accountant"
    ],
    "wof:name":"West Bridgford Tax And Accountancy Services Ltd",
    "wof:placetype":"venue"
},
  "geometry": {"coordinates":[-1.147497,52.919952],"type":"Point"}
}