{
  "type": "Feature",
  "properties": {
    "iso:country":"GB",
    "sg:address":"1 Claughton Street",
    "sg:city":"St Helens",
    "sg:classifiers":[
        {
            "category":"Home & Garden",
            "subcategory":"Carpets & Floor Coverings",
            "type":"Retail Goods"
        }
    ],
    "sg:phone":"+44 1744 735333",
    "sg:postcode":"WA10 1RR",
    "sg:province":"Merseyside",
    "sg:tags":[
        "carpets",
        "rug",
        "matting"
    ],
    "wof:name":"Do A Deal Ltd.",
    "wof:placetype":"venue"
},
  "geometry": {"coordinates":[-2.735765,53.453201],"type":"Point"}
}