{
  "type": "Feature",
  "properties": {
    "addr:full":"5 Kirkdale Gardens, Long Eaton Nottingham Derbyshire NG10 3JA",
    "addr:housenumber":"5",
    "addr:postcode":"ng10 3ja",
    "addr:street":"Kirkdale Gardens",
    "iso:country":"GB",
    "sg:address":"5 Kirkdale Gardens, Long Eaton",
    "sg:city":"Nottingham",
    "sg:classifiers":[
        {
            "category":"Retail",
            "subcategory":"Driving School",
            "type":"Services"
        }
    ],
    "sg:phone":"+44 115 972 7976",
    "sg:postcode":"NG10 3JA",
    "sg:province":"Derbyshire",
    "wof:name":"Douglas Driving School",
    "wof:placetype":"venue"
},
  "geometry": {"coordinates":[-1.2929370403,52.8879508972],"type":"Point"}
}