{
  "type": "Feature",
  "properties": {
    "addr:full":"The Old School, Wiston Haverfordwest Pembrokeshire SA62 4PS",
    "addr:postcode":"sa62 4ps",
    "addr:street":"Wiston;Pembrokeshire",
    "iso:country":"GB",
    "sg:address":"The Old School, Wiston",
    "sg:city":"Haverfordwest",
    "sg:classifiers":[
        {
            "category":"Education",
            "subcategory":"University",
            "type":"Public Place"
        }
    ],
    "sg:postcode":"SA62 4PS",
    "sg:province":"Pembrokeshire",
    "sg:tags":[
        "adult"
    ],
    "wof:name":"Wiston Project School",
    "wof:placetype":"venue"
},
  "geometry": {"coordinates":[-4.873139,51.82618],"type":"Point"}
}