{
  "type": "Feature",
  "properties": {
    "addr:full":"84 Trelowarren Street Camborne Cornwall TR14 8AN",
    "addr:housenumber":"84",
    "addr:postcode":"tr14 8an",
    "addr:street":"Trelowarren Street",
    "iso:country":"GB",
    "sg:address":"84 Trelowarren Street",
    "sg:city":"Camborne",
    "sg:classifiers":[
        {
            "category":"Shopping",
            "subcategory":"Florist",
            "type":"Retail Goods"
        }
    ],
    "sg:phone":"+44 1209 713146",
    "sg:postcode":"TR14 8AN",
    "sg:province":"Cornwall",
    "wof:name":"Brides & Flowers",
    "wof:placetype":"venue"
},
  "geometry": {"coordinates":[-5.294798,50.214428],"type":"Point"}
}