{
  "type": "Feature",
  "properties": {
    "iso:country":"GB",
    "sg:address":"13 Broadoak Drive, Lanchester",
    "sg:city":"Durham",
    "sg:classifiers":[
        {
            "category":"Professional",
            "subcategory":"Engineering",
            "type":"Services"
        }
    ],
    "sg:postcode":"DH7 0PN",
    "sg:province":"Durham",
    "sg:tags":[
        "contractor",
        "electrical",
        "engineer"
    ],
    "wof:name":"Raine Derick Electrical and Mechanical Services",
    "wof:placetype":"venue"
},
  "geometry": {"coordinates":[-1.7502260208,54.8214073181],"type":"Point"}
}