{
  "type": "Feature",
  "properties": {
    "iso:country":"GB",
    "sg:address":"The Glen, Wenffrwd",
    "sg:city":"Llangollen",
    "sg:classifiers":[
        {
            "category":"Professional",
            "subcategory":"Engineering",
            "type":"Services"
        }
    ],
    "sg:phone":"+44 1978 860706",
    "sg:postcode":"LL20 7UH",
    "sg:province":"Denbighshire",
    "sg:tags":[
        "engineer",
        "mechanical"
    ],
    "wof:name":"Robert C Hicks (Engineering Services) Ltd.",
    "wof:placetype":"venue"
},
  "geometry": {"coordinates":[-3.0959889889,52.9748420715],"type":"Point"}
}