{
  "type": "Feature",
  "properties": {
    "addr:full":"13 Tulketh Avenue, Ashton On Ribble Preston Lancashire PR2 1DR",
    "addr:housenumber":"13",
    "addr:postcode":"pr2 1dr",
    "addr:street":"Tulketh Avenue",
    "iso:country":"GB",
    "sg:address":"13 Tulketh Avenue, Ashton On Ribble",
    "sg:city":"Preston",
    "sg:classifiers":[
        {
            "category":"Building & Trades",
            "subcategory":"Plumbing",
            "type":"Services"
        }
    ],
    "sg:postcode":"PR2 1DR",
    "sg:province":"Lancashire",
    "sg:tags":[
        "heating"
    ],
    "wof:name":"J Flynn",
    "wof:placetype":"venue"
},
  "geometry": {"coordinates":[-2.7305800915,53.7670135498],"type":"Point"}
}