{
  "type": "Feature",
  "properties": {
    "addr:full":"371 Blackfen Rd Sidcup Kent DA15 9NJ",
    "addr:housenumber":"371",
    "addr:postcode":"da15 9nj",
    "addr:street":"Blackfen Rd",
    "iso:country":"GB",
    "sg:address":"371 Blackfen Rd",
    "sg:city":"Sidcup",
    "sg:classifiers":[
        {
            "category":"Professional",
            "subcategory":"Detective & Security Services",
            "type":"Services"
        }
    ],
    "sg:phone":"+44 20 8301 5156",
    "sg:postcode":"DA15 9NJ",
    "sg:province":"Kent",
    "wof:name":"Mylyn Security",
    "wof:placetype":"venue"
},
  "geometry": {"coordinates":[0.1092040017,51.4498634338],"type":"Point"}
}