{
  "type": "Feature",
  "properties": {
    "addr:full":"55-57 Church Street Bilston West Midlands WV14 0AX",
    "addr:housenumber":"55-57",
    "addr:postcode":"wv14 0ax",
    "addr:street":"Church Street",
    "iso:country":"GB",
    "sg:address":"55-57 Church Street",
    "sg:city":"Bilston",
    "sg:classifiers":[
        {
            "category":"Shopping",
            "subcategory":"Catalog Store",
            "type":"Retail Goods"
        }
    ],
    "sg:phone":"+44 1902 490408",
    "sg:postcode":"WV14 0AX",
    "sg:province":"West Midlands",
    "sg:tags":[
        "catalogue",
        "showroom"
    ],
    "wof:name":"Argos Call & Collect",
    "wof:placetype":"venue"
},
  "geometry": {"coordinates":[-2.0762879848,52.5657501221],"type":"Point"}
}