{
  "type": "Feature",
  "properties": {
    "iso:country":"GB",
    "sg:address":"Unit 1 Meadow Rd",
    "sg:city":"Glasgow",
    "sg:classifiers":[
        {
            "category":"Professional",
            "subcategory":"Printing & Photocopies",
            "type":"Services"
        }
    ],
    "sg:postcode":"G11 6HX",
    "sg:province":"Glasgow City",
    "sg:tags":[
        "plate",
        "lithographic",
        "maker"
    ],
    "wof:name":"D G C Graphics Ltd",
    "wof:placetype":"venue"
},
  "geometry": {"coordinates":[-4.316229,55.869461],"type":"Point"}
}