{
  "type": "Feature",
  "properties": {
    "addr:full":"16 Church Street, Bocking Braintree Essex CM7 5JS",
    "addr:housenumber":"16",
    "addr:postcode":"cm7 5js",
    "addr:street":"Church Street",
    "iso:country":"GB",
    "sg:address":"16 Church Street, Bocking",
    "sg:city":"Braintree",
    "sg:classifiers":[
        {
            "category":"Building & Trades",
            "subcategory":"Plumbing",
            "type":"Services"
        }
    ],
    "sg:phone":"+44 1376 344011",
    "sg:postcode":"CM7 5JS",
    "sg:province":"Essex",
    "sg:tags":[
        "central",
        "heating"
    ],
    "wof:name":"S T B Services",
    "wof:placetype":"venue"
},
  "geometry": {"coordinates":[0.5540329814,51.9009208679],"type":"Point"}
}