{
  "type": "Feature",
  "properties": {
    "iso:country":"GB",
    "sg:address":"Wodside Farm, Stratford Road",
    "sg:city":"Sandy",
    "sg:classifiers":[
        {
            "category":"Farming",
            "subcategory":"Livestock Farm",
            "type":"Manufacturing & Wholesale Goods"
        }
    ],
    "sg:phone":"+44 1767 681177",
    "sg:postcode":"SG19 2AB",
    "sg:province":"Bedfordshire",
    "sg:tags":[
        "others"
    ],
    "wof:name":"Robert Glenn",
    "wof:placetype":"venue"
},
  "geometry": {"coordinates":[-0.291109,52.12928],"type":"Point"}
}