{
  "type": "Feature",
  "properties": {
    "iso:country":"GB",
    "sg:address":"25a Watermouth Road",
    "sg:city":"Ilfracombe",
    "sg:classifiers":[
        {
            "category":"Shopping",
            "subcategory":"Department Store",
            "type":"Retail Goods"
        }
    ],
    "sg:phone":"+44 1271 865080",
    "sg:postcode":"EX34 9QY",
    "sg:province":"Devon",
    "wof:name":"A C Electrical Services",
    "wof:placetype":"venue"
},
  "geometry": {"coordinates":[-4.098879,51.20892],"type":"Point"}
}