{
  "type": "Feature",
  "properties": {
    "iso:country":"GB",
    "sg:address":"Matlock Road, Wessington",
    "sg:city":"Alfreton",
    "sg:classifiers":[
        {
            "category":"Home & Garden",
            "subcategory":"Garden Supply",
            "type":"Retail Goods"
        }
    ],
    "sg:phone":"+44 1773 832517",
    "sg:postcode":"DE55 6DS",
    "sg:province":"Derbyshire",
    "sg:tags":[
        "nursery",
        "centre"
    ],
    "wof:name":"Wessington Garden Centre",
    "wof:placetype":"venue"
},
  "geometry": {"coordinates":[-1.469856,53.125381],"type":"Point"}
}