{
  "type": "Feature",
  "properties": {
    "iso:country":"GB",
    "sg:address":"249 London Rd",
    "sg:city":"Portsmouth",
    "sg:classifiers":[
        {
            "category":"Communications",
            "type":"Services"
        }
    ],
    "sg:phone":"+44 23 9279 9787",
    "sg:postcode":"PO2 9HA",
    "sg:province":"Hampshire",
    "sg:tags":[
        "telecommunication"
    ],
    "wof:name":"BT Homecare Ltd",
    "wof:placetype":"venue"
},
  "geometry": {"coordinates":[-1.076196,50.821377],"type":"Point"}
}