{
  "type": "Feature",
  "properties": {
    "addr:full":"Unit 13 Pembroke Business Centre, Gardiners La South Basildon Essex SS14 3HX",
    "addr:housenumber":"unit 13",
    "addr:postcode":"ss14 3hx",
    "addr:street":"Pembroke Business Centre Gardiners La South",
    "iso:country":"GB",
    "sg:address":"Unit 13 Pembroke Business Centre, Gardiners La South",
    "sg:city":"Basildon",
    "sg:classifiers":[
        {
            "category":"Professional",
            "subcategory":"Engineering",
            "type":"Services"
        }
    ],
    "sg:phone":"+44 1268 524090",
    "sg:postcode":"SS14 3HX",
    "sg:province":"Essex",
    "sg:tags":[
        "contractor",
        "electrical",
        "engineer"
    ],
    "wof:name":"Sutton,John,Electrical Services Ltd",
    "wof:placetype":"venue"
},
  "geometry": {"coordinates":[0.4840799868,51.5897789001],"type":"Point"}
}