{
  "type": "Feature",
  "properties": {
    "addr:full":"5 The Lea Stoke-on-trent Staffordshire ST4 8DY",
    "addr:housenumber":"5",
    "addr:postcode":"st4 8dy",
    "addr:street":"The Lea",
    "iso:country":"GB",
    "sg:address":"5 The Lea",
    "sg:city":"Stoke-on-trent",
    "sg:classifiers":[
        {
            "category":"Home & Garden",
            "subcategory":"Hardware",
            "type":"Retail Goods"
        }
    ],
    "sg:phone":"+44 1782 643312",
    "sg:postcode":"ST4 8DY",
    "sg:province":"Staffordshire",
    "sg:tags":[
        "retailer",
        "diy"
    ],
    "wof:name":"McNicols D I Y",
    "wof:placetype":"venue"
},
  "geometry": {"coordinates":[-2.188245,52.967827],"type":"Point"}
}