{
  "type": "Feature",
  "properties": {
    "iso:country":"GB",
    "sg:address":"394-395 The Kingsway",
    "sg:city":"Swansea",
    "sg:classifiers":[
        {
            "category":"Health Services",
            "subcategory":"Optometrist",
            "type":"Services"
        }
    ],
    "sg:phone":"+44 1792 474426",
    "sg:postcode":"SA1 5LQ",
    "sg:province":"Neath Port Talbot",
    "sg:tags":[
        "optician"
    ],
    "wof:name":"Specsavers Optical Group Ltd.",
    "wof:placetype":"venue"
},
  "geometry": {"coordinates":[-3.946669,51.620441],"type":"Point"}
}