{
  "type": "Feature",
  "properties": {
    "addr:full":"750 London Road, Larkfield Aylesford Kent ME20 6BG",
    "addr:housenumber":"750",
    "addr:postcode":"me20 6bg",
    "addr:street":"London Road",
    "iso:country":"GB",
    "sg:address":"750 London Road, Larkfield",
    "sg:city":"Aylesford",
    "sg:classifiers":[
        {
            "category":"Personal",
            "subcategory":"Beauty Salon",
            "type":"Services"
        }
    ],
    "sg:phone":"+44 1732 842426",
    "sg:postcode":"ME20 6BG",
    "sg:province":"Kent",
    "sg:tags":[
        "lady",
        "hairdresser"
    ],
    "wof:name":"Noelle",
    "wof:placetype":"venue"
},
  "geometry": {"coordinates":[0.4420590103,51.2986831665],"type":"Point"}
}