{
  "type": "Feature",
  "properties": {
    "addr:full":"11-13 Holmes Rd Reading Berkshire RG6 7BH",
    "addr:housenumber":"11-13",
    "addr:postcode":"rg6 7bh",
    "addr:street":"Holmes Rd",
    "iso:country":"GB",
    "sg:address":"11-13 Holmes Rd",
    "sg:city":"Reading",
    "sg:classifiers":[
        {
            "category":"Professional",
            "subcategory":"Engineering",
            "type":"Services"
        }
    ],
    "sg:phone":"+44 118 926 9369",
    "sg:postcode":"RG6 7BH",
    "sg:province":"Berkshire",
    "sg:tags":[
        "hydraulic",
        "engineer"
    ],
    "wof:name":"Hose Fit Ltd",
    "wof:placetype":"venue"
},
  "geometry": {"coordinates":[-0.9332330227,51.4422607422],"type":"Point"}
}