{
  "type": "Feature",
  "properties": {
    "iso:country":"GB",
    "sg:address":"Eagle Court, 224 London Road",
    "sg:city":"Mitcham",
    "sg:classifiers":[
        {
            "category":"Professional",
            "subcategory":"Lawyer & Legal Services",
            "type":"Services"
        }
    ],
    "sg:phone":"+44 20 8646 0646",
    "sg:postcode":"CR4 3HD",
    "sg:province":"Greater London",
    "sg:tags":[
        "advice",
        "counselling"
    ],
    "wof:name":"Aids Care & Education Project",
    "wof:placetype":"venue"
},
  "geometry": {"coordinates":[-0.1645990014,51.4047012329],"type":"Point"}
}