{
  "type": "Feature",
  "properties": {
    "addr:full":"The Pharmacy High Street Moreton-in-marsh Gloucestershire GL56 0AL",
    "addr:postcode":"gl56 0al",
    "addr:street":"High Street",
    "iso:country":"GB",
    "sg:address":"The Pharmacy High Street",
    "sg:city":"Moreton-in-marsh",
    "sg:classifiers":[
        {
            "category":"Shopping",
            "subcategory":"Pharmacy",
            "type":"Retail Goods"
        }
    ],
    "sg:phone":"+44 1608 650306",
    "sg:postcode":"GL56 0AL",
    "sg:province":"Gloucestershire",
    "sg:tags":[
        "pharmacist",
        "chemist"
    ],
    "wof:name":"Andrew D Byers",
    "wof:placetype":"venue"
},
  "geometry": {"coordinates":[-1.703281045,51.9897270203],"type":"Point"}
}