{
  "type": "Feature",
  "properties": {
    "addr:full":"Henfryn Farm Llandysul Carmarthenshire SA44 5BB",
    "addr:housenumber":"llandysul",
    "addr:postcode":"sa44 5bb",
    "addr:street":"Carmarthenshire",
    "iso:country":"GB",
    "sg:address":"Henfryn Farm",
    "sg:city":"Llandysul",
    "sg:classifiers":[
        {
            "category":"Farming",
            "subcategory":"Livestock Farm",
            "type":"Manufacturing & Wholesale Goods"
        }
    ],
    "sg:phone":"+44 1559 362211",
    "sg:postcode":"SA44 5BB",
    "sg:province":"Carmarthenshire",
    "sg:tags":[
        "others"
    ],
    "wof:name":"E G Davies",
    "wof:placetype":"venue"
},
  "geometry": {"coordinates":[-4.307817,52.044479],"type":"Point"}
}