{
  "type": "Feature",
  "properties": {
    "addr:full":"94 Longden Road Shrewsbury Shropshire SY3 7HS",
    "addr:housenumber":"94",
    "addr:postcode":"sy3 7hs",
    "addr:street":"Longden Road",
    "iso:country":"GB",
    "sg:address":"94 Longden Road",
    "sg:city":"Shrewsbury",
    "sg:classifiers":[
        {
            "category":"Building & Trades",
            "subcategory":"Construction",
            "type":"Services"
        }
    ],
    "sg:phone":"+44 1743 233686",
    "sg:postcode":"SY3 7HS",
    "sg:province":"Shropshire",
    "sg:tags":[
        "monumental",
        "mason"
    ],
    "wof:name":"The Sabrina Monumental Works Ltd.",
    "wof:placetype":"venue"
},
  "geometry": {"coordinates":[-2.7592890263,52.6981391907],"type":"Point"}
}