{
  "type": "Feature",
  "properties": {
    "addr:full":"5 Woodlands Av Corby Northamptonshire NN17 1JH",
    "addr:housenumber":"5",
    "addr:postcode":"nn17 1jh",
    "addr:street":"Woodlands Av",
    "iso:country":"GB",
    "sg:address":"5 Woodlands Av",
    "sg:city":"Corby",
    "sg:classifiers":[
        {
            "category":"Autos & Motor Vehicles",
            "subcategory":"Automobile Sales",
            "type":"Retail Goods"
        }
    ],
    "sg:phone":"+44 1536 408209",
    "sg:postcode":"NN17 1JH",
    "sg:province":"Northamptonshire",
    "sg:tags":[
        "car"
    ],
    "wof:name":"Local Motor Centre",
    "wof:placetype":"venue"
},
  "geometry": {"coordinates":[-0.6942549944,52.5015220642],"type":"Point"}
}