{
  "type": "Feature",
  "properties": {
    "addr:full":"School Lane, Donington Spalding Lincolnshire PE11 4TF",
    "addr:postcode":"pe11 4tf",
    "addr:street":"School Lane",
    "iso:country":"GB",
    "sg:address":"School Lane, Donington",
    "sg:city":"Spalding",
    "sg:classifiers":[
        {
            "category":"Education",
            "subcategory":"School",
            "type":"Public Place"
        },
        {
            "category":"Government",
            "subcategory":"Office",
            "type":"Public Place"
        }
    ],
    "sg:phone":"+44 1775 820254",
    "sg:postcode":"PE11 4TF",
    "sg:province":"Lincolnshire",
    "sg:tags":[
        "local",
        "authority"
    ],
    "wof:name":"The Thomas Cowley High School",
    "wof:placetype":"venue"
},
  "geometry": {"coordinates":[-0.198247999,52.9040336609],"type":"Point"}
}