{
  "type": "Feature",
  "properties": {
    "addr:full":"Unit 5 Mercury Units, Tir Llwyd Enterprise Park Rhyl Conwy LL18 5JZ",
    "addr:housenumber":"unit 5;units",
    "addr:postcode":"ll18 5jz",
    "addr:street":"Mercury",
    "iso:country":"GB",
    "sg:address":"Unit 5 Mercury Units, Tir Llwyd Enterprise Park",
    "sg:city":"Rhyl",
    "sg:classifiers":[
        {
            "category":"Organizations",
            "subcategory":"Non-profit Organization",
            "type":"Services"
        }
    ],
    "sg:postcode":"LL18 5JZ",
    "sg:province":"Conwy",
    "sg:tags":[
        "organisation",
        "voluntary",
        "charity"
    ],
    "wof:name":"Mobility Equipment Repair Service",
    "wof:placetype":"venue"
},
  "geometry": {"coordinates":[-3.5161790848,53.2976417542],"type":"Point"}
}