{
  "type": "Feature",
  "properties": {
    "addr:full":"2 Larches Way, Crawley Down Crawley Surrey RH10 4UH",
    "addr:housenumber":"2",
    "addr:postcode":"rh10 4uh",
    "addr:street":"Larches Way",
    "iso:country":"GB",
    "sg:address":"2 Larches Way, Crawley Down",
    "sg:city":"Crawley",
    "sg:classifiers":[
        {
            "category":"Freight",
            "type":"Transportation"
        }
    ],
    "sg:postcode":"RH10 4UH",
    "sg:province":"Surrey",
    "sg:tags":[
        "haulage",
        "road"
    ],
    "wof:name":"Watkins,Brian, Light Haulage",
    "wof:placetype":"venue"
},
  "geometry": {"coordinates":[-0.086029,51.122921],"type":"Point"}
}