{
  "type": "Feature",
  "properties": {
    "addr:full":"Whessoe Road Darlington Durham DL3 0QW",
    "addr:postcode":"dl3 0qw",
    "addr:street":"Whessoe Road",
    "iso:country":"GB",
    "sg:address":"Whessoe Road",
    "sg:city":"Darlington",
    "sg:classifiers":[
        {
            "category":"Home & Garden",
            "subcategory":"Hardware",
            "type":"Retail Goods"
        }
    ],
    "sg:phone":"+44 1325 480812",
    "sg:postcode":"DL3 0QW",
    "sg:province":"Durham",
    "sg:tags":[
        "retailer",
        "diy"
    ],
    "wof:name":"B & Q Supercentre",
    "wof:placetype":"venue"
},
  "geometry": {"coordinates":[-1.5600830317,54.5461578369],"type":"Point"}
}