{
  "type": "Feature",
  "properties": {
    "iso:country":"GB",
    "sg:address":"7 Dunleary Rd, Town Moor",
    "sg:city":"Doncaster",
    "sg:classifiers":[
        {
            "category":"Building & Trades",
            "subcategory":"Construction",
            "type":"Services"
        }
    ],
    "sg:postcode":"DN2 5EX",
    "sg:province":"South Yorkshire",
    "sg:tags":[
        "builder"
    ],
    "wof:name":"P D Building & Roofing",
    "wof:placetype":"venue"
},
  "geometry": {"coordinates":[-1.1093930006,53.5269927979],"type":"Point"}
}