{
  "type": "Feature",
  "properties": {
    "addr:full":"81a Rochester Row London Greater London SW1P 1LJ",
    "addr:housenumber":"81a",
    "addr:postcode":"sw1p 1lj",
    "addr:street":"Rochester Row",
    "iso:country":"GB",
    "sg:address":"81a Rochester Row",
    "sg:city":"London",
    "sg:classifiers":[
        {
            "category":"Retail",
            "subcategory":"Repair Shop",
            "type":"Services"
        }
    ],
    "sg:phone":"+44 20 7834 4305",
    "sg:postcode":"SW1P 1LJ",
    "sg:province":"Greater London",
    "sg:tags":[
        "clocks",
        "watch"
    ],
    "wof:name":"William J Jenkins",
    "wof:placetype":"venue"
},
  "geometry": {"coordinates":[-0.137487,51.493267],"type":"Point"}
}