{
  "type": "Feature",
  "properties": {
    "addr:full":"168 Felinfoel Road Llanelli Carmarthenshire SA15 3JT",
    "addr:housenumber":"168",
    "addr:postcode":"sa15 3jt",
    "addr:street":"Felinfoel Road",
    "iso:country":"GB",
    "sg:address":"168 Felinfoel Road",
    "sg:city":"Llanelli",
    "sg:classifiers":[
        {
            "category":"Shopping",
            "subcategory":"Department Store",
            "type":"Retail Goods"
        },
        {
            "category":"Food & Beverages",
            "subcategory":"Groceries & Convenience Stores",
            "type":"Retail Goods"
        }
    ],
    "sg:postcode":"SA15 3JT",
    "sg:province":"Carmarthenshire",
    "wof:name":"The Corner Shop",
    "wof:placetype":"venue"
},
  "geometry": {"coordinates":[-4.1555109024,51.6923332214],"type":"Point"}
}