{
  "type": "Feature",
  "properties": {
    "iso:country":"GB",
    "sg:address":"Churchfield House, Tunstall",
    "sg:city":"Carnforth",
    "sg:classifiers":[
        {
            "category":"Farming",
            "subcategory":"Dairy Farm",
            "type":"Manufacturing & Wholesale Goods"
        }
    ],
    "sg:phone":"+44 15242 74233",
    "sg:postcode":"LA6 2RH",
    "sg:province":"Cumbria",
    "wof:name":"W.H Taylor & Son",
    "wof:placetype":"venue"
},
  "geometry": {"coordinates":[-2.6009819508,54.1564445496],"type":"Point"}
}