{
  "type": "Feature",
  "properties": {
    "addr:full":"Machine House, Gilwern Abergavenny Herefordshire NP7 0EP",
    "addr:postcode":"np7 0ep",
    "addr:street":"Gilwern",
    "iso:country":"GB",
    "sg:address":"Machine House, Gilwern",
    "sg:city":"Abergavenny",
    "sg:classifiers":[
        {
            "category":"Home & Garden",
            "subcategory":"Building Materials",
            "type":"Retail Goods"
        }
    ],
    "sg:postcode":"NP7 0EP",
    "sg:province":"Herefordshire",
    "sg:tags":[
        "ventilator",
        "ventilation",
        "system"
    ],
    "wof:name":"Scott Heat Recovery Co.",
    "wof:placetype":"venue"
},
  "geometry": {"coordinates":[-3.091039,51.825275],"type":"Point"}
}