{
  "type": "Feature",
  "properties": {
    "addr:full":"178 Mill Road, Romsey Town Cambridge Cambridgeshire CB1 3LP",
    "addr:housenumber":"178",
    "addr:postcode":"cb1 3lp",
    "addr:street":"Mill Road",
    "iso:country":"GB",
    "sg:address":"178 Mill Road, Romsey Town",
    "sg:city":"Cambridge",
    "sg:classifiers":[
        {
            "category":"Place Of Worship",
            "type":"Public Place"
        }
    ],
    "sg:phone":"+44 1223 242376",
    "sg:postcode":"CB1 3LP",
    "sg:province":"Cambridgeshire",
    "wof:name":"Mill Road baptist Church",
    "wof:placetype":"venue"
},
  "geometry": {"coordinates":[0.143209,52.197914],"type":"Point"}
}