{
  "type": "Feature",
  "properties": {
    "iso:country":"GB",
    "sg:address":"98 Balfour Road",
    "sg:city":"Brighton",
    "sg:classifiers":[
        {
            "category":"Health Services",
            "subcategory":"Health Practitioner",
            "type":"Services"
        }
    ],
    "sg:postcode":"BN1 6ND",
    "sg:province":"East Sussex",
    "sg:tags":[
        "physiotherapist"
    ],
    "wof:name":"R Grimshaw",
    "wof:placetype":"venue"
},
  "geometry": {"coordinates":[-0.140319,50.84634],"type":"Point"}
}