{
  "type": "Feature",
  "properties": {
    "addr:full":"Ennerdale Road, Astley Manchester Greater Manchester M29 7PY",
    "addr:postcode":"m29 7py",
    "addr:street":"Ennerdale Road",
    "iso:country":"GB",
    "sg:address":"Ennerdale Road, Astley",
    "sg:city":"Manchester",
    "sg:classifiers":[
        {
            "category":"Education",
            "subcategory":"School",
            "type":"Public Place"
        }
    ],
    "sg:phone":"+44 1942 882870",
    "sg:postcode":"M29 7PY",
    "sg:province":"Greater Manchester",
    "sg:tags":[
        "local",
        "authority"
    ],
    "wof:name":"Tyldesley Junior & Infant School",
    "wof:placetype":"venue"
},
  "geometry": {"coordinates":[-2.4596159458,53.5073776245],"type":"Point"}
}