{
  "type": "Feature",
  "properties": {
    "addr:full":"55/59 London Road, Southborough Tunbridge Wells Kent TN4 0PB",
    "addr:housenumber":"55 / 59",
    "addr:postcode":"tn4 0pb",
    "addr:street":"London Road",
    "iso:country":"GB",
    "sg:address":"55/59 London Road, Southborough",
    "sg:city":"Tunbridge Wells",
    "sg:classifiers":[
        {
            "category":"Home & Garden",
            "subcategory":"Furniture",
            "type":"Retail Goods"
        }
    ],
    "sg:phone":"+44 1892 527863",
    "sg:postcode":"TN4 0PB",
    "sg:province":"Kent",
    "wof:name":"Newsdouble Ltd.",
    "wof:placetype":"venue"
},
  "geometry": {"coordinates":[0.257232,51.160778],"type":"Point"}
}