{
  "type": "Feature",
  "properties": {
    "iso:country":"GB",
    "sg:address":"21 Mansfield Road",
    "sg:city":"Ilford",
    "sg:classifiers":[
        {
            "category":"Travel",
            "subcategory":"Hotels & Motels",
            "type":"Entertainment"
        }
    ],
    "sg:phone":"+44 20 8478 8459",
    "sg:postcode":"IG1 3BA",
    "sg:province":"Essex",
    "sg:tags":[
        "house",
        "guest"
    ],
    "wof:name":"Mansfield Guest House",
    "wof:placetype":"venue"
},
  "geometry": {"coordinates":[0.0675569996,51.5610160828],"type":"Point"}
}