{
  "type": "Feature",
  "properties": {
    "addr:full":"5-9 Norfolk Square London Greater London W2 1RU",
    "addr:housenumber":"5-9",
    "addr:postcode":"w2 1ru",
    "addr:street":"Norfolk Square",
    "iso:country":"GB",
    "sg:address":"5-9 Norfolk Square",
    "sg:city":"London",
    "sg:classifiers":[
        {
            "category":"Travel",
            "subcategory":"Hotels & Motels",
            "type":"Entertainment"
        }
    ],
    "sg:phone":"+44 20 7723 4500",
    "sg:postcode":"W2 1RU",
    "sg:province":"Greater London",
    "wof:name":"The Cardiff Hotel",
    "wof:placetype":"venue"
},
  "geometry": {"coordinates":[-0.173585,51.515453],"type":"Point"}
}