{
  "type": "Feature",
  "properties": {
    "iso:country":"GB",
    "sg:address":"15 Applewood Gro",
    "sg:city":"Waterlooville",
    "sg:classifiers":[
        {
            "category":"Building & Trades",
            "subcategory":"Construction",
            "type":"Services"
        }
    ],
    "sg:phone":"+44 23 9235 6438",
    "sg:postcode":"PO7 5DL",
    "sg:province":"Hampshire",
    "sg:tags":[
        "builder"
    ],
    "wof:name":"S G Hellyer",
    "wof:placetype":"venue"
},
  "geometry": {"coordinates":[-1.0476449728,50.858959198],"type":"Point"}
}