{
  "type": "Feature",
  "properties": {
    "addr:full":"Phoenix House, Rushton Avenue, Thornbury Bradford West Yorkshire BD3 7BH",
    "addr:postcode":"bd3 7bh",
    "addr:street":"Rushton Avenue;Bradford West",
    "iso:country":"GB",
    "sg:address":"Phoenix House, Rushton Avenue, Thornbury",
    "sg:city":"Bradford",
    "sg:classifiers":[
        {
            "category":"Home & Garden",
            "subcategory":"Kitchen Supply",
            "type":"Retail Goods"
        }
    ],
    "sg:phone":"+44 1274 661880",
    "sg:postcode":"BD3 7BH",
    "sg:province":"West Yorkshire",
    "sg:tags":[
        "equipment",
        "catering"
    ],
    "wof:name":"Mollett Catering Equipment",
    "wof:placetype":"venue"
},
  "geometry": {"coordinates":[-1.720529,53.79879],"type":"Point"}
}