{
  "type": "Feature",
  "properties": {
    "addr:full":"6 Northern Buildings Portsmouth Hampshire PO6 3DL",
    "addr:housenumber":"6",
    "addr:postcode":"hampshire po6 3dl",
    "addr:street":"Northern Buildings",
    "iso:country":"GB",
    "sg:address":"6 Northern Buildings",
    "sg:city":"Portsmouth",
    "sg:classifiers":[
        {
            "category":"Restaurant",
            "type":"Food & Drink"
        }
    ],
    "sg:phone":"+44 23 9237 6163",
    "sg:postcode":"PO6 3DL",
    "sg:province":"Hampshire",
    "sg:tags":[
        "mexican"
    ],
    "wof:name":"El Meson Restaurant",
    "wof:placetype":"venue"
},
  "geometry": {"coordinates":[-1.0685590506,50.8468513489],"type":"Point"}
}