{
  "type": "Feature",
  "properties": {
    "addr:full":"1 St. Johns Rd Bath Somerset BA3 1HR",
    "addr:housenumber":"1",
    "addr:postcode":"ba3 1hr",
    "addr:street":"St. Johns Rd",
    "iso:country":"GB",
    "sg:address":"1 St. Johns Rd",
    "sg:city":"Bath",
    "sg:classifiers":[
        {
            "category":"Social Services",
            "subcategory":"Adult Care",
            "type":"Services"
        }
    ],
    "sg:phone":"+44 1761 470061",
    "sg:postcode":"BA3 1HR",
    "sg:province":"Somerset",
    "sg:tags":[
        "housing",
        "sheltered"
    ],
    "wof:name":"Greenvale Drive Sheltered Housing",
    "wof:placetype":"venue"
},
  "geometry": {"coordinates":[-2.38316,51.384823],"type":"Point"}
}