{
  "type": "Feature",
  "properties": {
    "addr:full":"58a High Street, Old Town Hastings East Sussex TN34 3EN",
    "addr:housenumber":"58a",
    "addr:postcode":"tn34 3en",
    "addr:street":"High Street",
    "iso:country":"GB",
    "sg:address":"58a High Street, Old Town",
    "sg:city":"Hastings",
    "sg:classifiers":[
        {
            "category":"Home & Garden",
            "subcategory":"Garden Supply",
            "type":"Retail Goods"
        },
        {
            "category":"Museum",
            "subcategory":"Art Museum",
            "type":"Entertainment"
        }
    ],
    "sg:phone":"+44 1424 427793",
    "sg:postcode":"TN34 3EN",
    "sg:province":"East Sussex",
    "sg:tags":[
        "flower",
        "gallery",
        "shrub"
    ],
    "wof:name":"Shirley Leaf & Petal Co",
    "wof:placetype":"venue"
},
  "geometry": {"coordinates":[0.590708,50.85648],"type":"Point"}
}