{
  "type": "Feature",
  "properties": {
    "addr:full":"54 Newton Rd Swansea Swansea SA3 4BQ",
    "addr:housenumber":"54",
    "addr:postcode":"sa3 4bq",
    "addr:street":"Newton Rd",
    "iso:country":"GB",
    "sg:address":"54 Newton Rd",
    "sg:city":"Swansea",
    "sg:classifiers":[
        {
            "category":"Shopping",
            "subcategory":"Clothing, Apparel, & Fashions",
            "type":"Retail Goods"
        }
    ],
    "sg:phone":"+44 1792 368001",
    "sg:postcode":"SA3 4BQ",
    "sg:province":"Swansea",
    "sg:tags":[
        "shop"
    ],
    "wof:name":"Antams",
    "wof:placetype":"venue"
},
  "geometry": {"coordinates":[-4.0026931763,51.5755615234],"type":"Point"}
}