{
  "type": "Feature",
  "properties": {
    "addr:full":"The Concourse Colindale Greater London NW9 5UP",
    "addr:postcode":"nw9 5up",
    "iso:country":"GB",
    "sg:address":"The Concourse",
    "sg:city":"Colindale",
    "sg:classifiers":[
        {
            "category":"Shopping",
            "subcategory":"Department Store",
            "type":"Retail Goods"
        }
    ],
    "sg:phone":"+44 20 8205 9016",
    "sg:postcode":"NW9 5UP",
    "sg:province":"Greater London",
    "wof:name":"Woodley",
    "wof:placetype":"venue"
},
  "geometry": {"coordinates":[-0.24484,51.602982],"type":"Point"}
}