{
  "type": "Feature",
  "properties": {
    "addr:full":"64 Castle Street Woodbridge Suffolk IP12 1HL",
    "addr:housenumber":"64",
    "addr:postcode":"ip12 1hl",
    "addr:street":"Castle Street",
    "iso:country":"GB",
    "sg:address":"64 Castle Street",
    "sg:city":"Woodbridge",
    "sg:classifiers":[
        {
            "category":"Fast Food",
            "type":"Food & Drink"
        },
        {
            "category":"Food & Beverages",
            "subcategory":"Meat & Fish",
            "type":"Retail Goods"
        }
    ],
    "sg:phone":"+44 1394 386809",
    "sg:postcode":"IP12 1HL",
    "sg:province":"Suffolk",
    "sg:tags":[
        "outlet",
        "chip",
        "meal",
        "away",
        "take"
    ],
    "wof:name":"Castle Kitchen",
    "wof:placetype":"venue"
},
  "geometry": {"coordinates":[1.316064,52.095749],"type":"Point"}
}