{
  "type": "Feature",
  "properties": {
    "addr:full":"Polperro, The Ridings, Stonesfield Witney Oxfordshire OX29 8EA",
    "addr:postcode":"ox29 8ea",
    "addr:street":"Ridings",
    "iso:country":"GB",
    "sg:address":"Polperro, The Ridings, Stonesfield",
    "sg:city":"Witney",
    "sg:classifiers":[
        {
            "category":"Building & Trades",
            "subcategory":"Plumbing",
            "type":"Services"
        }
    ],
    "sg:phone":"+44 1993 891314",
    "sg:postcode":"OX29 8EA",
    "sg:province":"Oxfordshire",
    "sg:tags":[
        "central",
        "heating"
    ],
    "wof:name":"Douglas J R Miles",
    "wof:placetype":"venue"
},
  "geometry": {"coordinates":[-1.430052,51.855747],"type":"Point"}
}