{
  "type": "Feature",
  "properties": {
    "iso:country":"GB",
    "sg:address":"Equine Clinic Southampton Rd, Clarendon",
    "sg:city":"Salisbury",
    "sg:classifiers":[
        {
            "category":"Organizations",
            "subcategory":"Non-profit Organization",
            "type":"Services"
        }
    ],
    "sg:phone":"+44 1722 710046",
    "sg:postcode":"SP5 3DG",
    "sg:province":"Dorset",
    "sg:tags":[
        "organisation",
        "animal",
        "welfare"
    ],
    "wof:name":"Endell Veterinary Group",
    "wof:placetype":"venue"
},
  "geometry": {"coordinates":[-1.75765,51.055462],"type":"Point"}
}