{
  "type": "Feature",
  "properties": {
    "iso:country":"GB",
    "sg:address":"Devonshire Avenue",
    "sg:city":"Southsea",
    "sg:classifiers":[
        {
            "category":"Place Of Worship",
            "type":"Public Place"
        }
    ],
    "sg:phone":"+44 23 9258 3629",
    "sg:postcode":"PO4 9ED",
    "sg:province":"Hampshire",
    "wof:name":"Devonshire Avenue Baptist Church",
    "wof:placetype":"venue"
},
  "geometry": {"coordinates":[-1.0663239956,50.7912712097],"type":"Point"}
}