{
  "type": "Feature",
  "properties": {
    "addr:full":"Unit 15, Stock Rd Southend On Sea Essex SS2 5QL",
    "addr:housenumber":"unit 15",
    "addr:postcode":"ss2 5ql",
    "addr:street":"Stock Rd",
    "iso:country":"GB",
    "sg:address":"Unit 15, Stock Rd",
    "sg:city":"Southend On Sea",
    "sg:classifiers":[
        {
            "category":"Home & Garden",
            "subcategory":"Furniture",
            "type":"Retail Goods"
        }
    ],
    "sg:phone":"+44 1702 601566",
    "sg:postcode":"SS2 5QL",
    "sg:province":"Essex",
    "sg:tags":[
        "built-in",
        "fitted"
    ],
    "wof:name":"C.P.S Associates",
    "wof:placetype":"venue"
},
  "geometry": {"coordinates":[0.709359,51.55814],"type":"Point"}
}