{
  "type": "Feature",
  "properties": {
    "iso:country":"GB",
    "sg:address":"Unit 9",
    "sg:city":"Cambridge",
    "sg:classifiers":[
        {
            "category":"Food & Beverages",
            "subcategory":"Meat & Fish",
            "type":"Retail Goods"
        }
    ],
    "sg:postcode":"CB3 8DZ",
    "sg:province":"Cambridgeshire",
    "sg:tags":[
        "chip"
    ],
    "wof:name":"J W Fisheries",
    "wof:placetype":"venue"
},
  "geometry": {"coordinates":[-0.048879,52.250359],"type":"Point"}
}