{
  "type": "Feature",
  "properties": {
    "iso:country":"GB",
    "sg:address":"Kimberworth Park Medical Centre, Langdon Rd",
    "sg:city":"Rotherham",
    "sg:classifiers":[
        {
            "category":"Health Services",
            "subcategory":"Doctor",
            "type":"Services"
        }
    ],
    "sg:phone":"+44 1709 555135",
    "sg:postcode":"S61 3QH",
    "sg:province":"South Yorkshire",
    "sg:tags":[
        "practitioners"
    ],
    "wof:name":"Chandra, U",
    "wof:placetype":"venue"
},
  "geometry": {"coordinates":[-1.401219,53.446754],"type":"Point"}
}