{
  "type": "Feature",
  "properties": {
    "iso:country":"GB",
    "sg:address":"234-238 Norwood Road",
    "sg:city":"London",
    "sg:classifiers":[
        {
            "category":"Retail",
            "subcategory":"Auto Repair",
            "type":"Services"
        }
    ],
    "sg:phone":"+44 20 8766 8899",
    "sg:postcode":"SE27 9AW",
    "sg:province":"Greater London",
    "sg:tags":[
        "modification",
        "garage"
    ],
    "wof:name":"Capital Crashworks Ltd.",
    "wof:placetype":"venue"
},
  "geometry": {"coordinates":[-0.1060110033,51.4382171631],"type":"Point"}
}