{
  "type": "Feature",
  "properties": {
    "iso:country":"GB",
    "sg:address":"Ramada Hotel Heathrow Bath Rd, Heathrow",
    "sg:city":"Hounslow",
    "sg:classifiers":[
        {
            "category":"Government",
            "subcategory":"Office",
            "type":"Public Place"
        }
    ],
    "sg:postcode":"TW6 2AQ",
    "sg:province":"Greater London",
    "sg:tags":[
        "central"
    ],
    "wof:name":"Department of the Environment Transport",
    "wof:placetype":"venue"
},
  "geometry": {"coordinates":[-0.4455,51.48045],"type":"Point"}
}