{
  "type": "Feature",
  "properties": {
    "addr:full":"70b Hough Lane Preston Lancashire PR5 2WB",
    "addr:housenumber":"70b",
    "addr:postcode":"pr5 2wb",
    "addr:street":"Hough Lane",
    "iso:country":"GB",
    "sg:address":"70b Hough Lane",
    "sg:city":"Preston",
    "sg:classifiers":[
        {
            "category":"Professional",
            "subcategory":"Employment Agencies",
            "type":"Services"
        }
    ],
    "sg:phone":"+44 1772 621687",
    "sg:postcode":"PR5 2WB",
    "sg:province":"Lancashire",
    "sg:tags":[
        "consultant"
    ],
    "wof:name":"First Call Lancashire",
    "wof:placetype":"venue"
},
  "geometry": {"coordinates":[-2.63084,53.745762],"type":"Point"}
}