{
  "type": "Feature",
  "properties": {
    "iso:country":"GB",
    "sg:address":"High Street, Lolworth",
    "sg:city":"Cambridge",
    "sg:classifiers":[
        {
            "category":"Personal",
            "subcategory":"Adult",
            "type":"Services"
        }
    ],
    "sg:phone":"+44 1954 780159",
    "sg:postcode":"CB3 8HG",
    "sg:province":"Cambridgeshire",
    "sg:tags":[
        "equestrian"
    ],
    "wof:name":"Broadway Farm Stables",
    "wof:placetype":"venue"
},
  "geometry": {"coordinates":[0.00126,52.258190155],"type":"Point"}
}