{
  "type": "Feature",
  "properties": {
    "addr:full":"28 Pullman Lane Godalming Surrey GU7 1XY",
    "addr:housenumber":"28",
    "addr:postcode":"gu7 1xy",
    "addr:street":"Pullman Lane",
    "iso:country":"GB",
    "sg:address":"28 Pullman Lane",
    "sg:city":"Godalming",
    "sg:classifiers":[
        {
            "category":"Professional",
            "subcategory":"Business Services",
            "type":"Services"
        }
    ],
    "sg:phone":"+44 1483 426904",
    "sg:postcode":"GU7 1XY",
    "sg:province":"Surrey",
    "sg:tags":[
        "transfer",
        "agent"
    ],
    "wof:name":"Bishops Business Transfer Ltd",
    "wof:placetype":"venue"
},
  "geometry": {"coordinates":[-0.621999979,51.1772041321],"type":"Point"}
}