{
  "type": "Feature",
  "properties": {
    "addr:full":"Stone Farm, Brayford Barnstaple Devon EX32 7PJ",
    "addr:postcode":"ex32 7pj",
    "iso:country":"GB",
    "sg:address":"Stone Farm, Brayford",
    "sg:city":"Barnstaple",
    "sg:classifiers":[
        {
            "category":"Farming",
            "subcategory":"Livestock Farm",
            "type":"Manufacturing & Wholesale Goods"
        }
    ],
    "sg:postcode":"EX32 7PJ",
    "sg:province":"Devon",
    "sg:tags":[
        "others"
    ],
    "wof:name":"David Joslin",
    "wof:placetype":"venue"
},
  "geometry": {"coordinates":[-3.875933,51.096909],"type":"Point"}
}