{
  "type": "Feature",
  "properties": {
    "iso:country":"GB",
    "sg:address":"Fosters Farm, Henley-in-arden",
    "sg:city":"Solihull",
    "sg:classifiers":[
        {
            "category":"Farming",
            "subcategory":"Livestock Farm",
            "type":"Manufacturing & Wholesale Goods"
        }
    ],
    "sg:phone":"+44 1564 795885",
    "sg:postcode":"B95 5NE",
    "sg:province":"Warwickshire",
    "sg:tags":[
        "others"
    ],
    "wof:name":"Longmead Developments Ltd",
    "wof:placetype":"venue"
},
  "geometry": {"coordinates":[-1.780079,52.291359],"type":"Point"}
}