{
  "type": "Feature",
  "properties": {
    "iso:country":"GB",
    "sg:address":"7 Grosvenor Gdns",
    "sg:city":"London",
    "sg:classifiers":[
        {
            "category":"Shopping",
            "subcategory":"Hobbies, Toys, & Games",
            "type":"Retail Goods"
        }
    ],
    "sg:postcode":"SW1W 0BH",
    "sg:province":"Greater London",
    "sg:tags":[
        "coin",
        "medal"
    ],
    "wof:name":"Royal Mint (The)",
    "wof:placetype":"venue"
},
  "geometry": {"coordinates":[-0.144975,51.498123],"type":"Point"}
}