{
  "type": "Feature",
  "properties": {
    "addr:full":"8 Thirlestane Court, Tilford Rd Hindhead Hampshire GU26 6SH",
    "addr:housenumber":"8",
    "addr:postcode":"gu26 6sh",
    "addr:street":"Thirlestane Court Tilford Rd",
    "iso:country":"GB",
    "sg:address":"8 Thirlestane Court, Tilford Rd",
    "sg:city":"Hindhead",
    "sg:classifiers":[
        {
            "category":"Organizations",
            "subcategory":"Political Organization",
            "type":"Services"
        }
    ],
    "sg:phone":"+44 1428 609074",
    "sg:postcode":"GU26 6SH",
    "sg:province":"Hampshire",
    "sg:tags":[
        "mediation"
    ],
    "wof:name":"Afirm",
    "wof:placetype":"venue"
},
  "geometry": {"coordinates":[-0.7531679869,51.1218795776],"type":"Point"}
}