{
  "type": "Feature",
  "properties": {
    "iso:country":"GB",
    "sg:address":"District Nurses & Health Visitor, The Surgery, Sainfoin La",
    "sg:city":"Basingstoke",
    "sg:classifiers":[
        {
            "category":"Health Services",
            "subcategory":"Clinic",
            "type":"Services"
        }
    ],
    "sg:phone":"+44 1256 782225",
    "sg:postcode":"RG23 7HZ",
    "sg:province":"Hampshire",
    "sg:tags":[
        "nh"
    ],
    "wof:name":"Lodden Trust Community Staff",
    "wof:placetype":"venue"
},
  "geometry": {"coordinates":[-1.17232,51.24231],"type":"Point"}
}