{
  "type": "Feature",
  "properties": {
    "addr:full":"93-99 Upper Richmond Road London Greater London SW15 2TG",
    "addr:housenumber":"93-99",
    "addr:postcode":"sw15 2tg",
    "addr:street":"Upper Richmond Road",
    "iso:country":"GB",
    "sg:address":"93-99 Upper Richmond Road",
    "sg:city":"London",
    "sg:classifiers":[
        {
            "category":"Home & Garden",
            "subcategory":"Kitchen Supply",
            "type":"Retail Goods"
        }
    ],
    "sg:phone":"+44 20 8246 4300",
    "sg:postcode":"SW15 2TG",
    "sg:province":"Greater London",
    "sg:tags":[
        "table"
    ],
    "wof:name":"Cucina Direct Ltd.",
    "wof:placetype":"venue"
},
  "geometry": {"coordinates":[-0.2127809972,51.4598121643],"type":"Point"}
}