{
  "type": "Feature",
  "properties": {
    "iso:country":"GB",
    "sg:address":"Unit 43 Progress Business Park, Garden Street, Kirkham",
    "sg:city":"Preston",
    "sg:classifiers":[
        {
            "category":"Home & Garden",
            "subcategory":"Home Furnishings",
            "type":"Retail Goods"
        },
        {
            "category":"Building & Trades",
            "subcategory":"Construction",
            "type":"Services"
        }
    ],
    "sg:phone":"+44 1772 684991",
    "sg:postcode":"PR4 2TU",
    "sg:province":"Lancashire",
    "sg:tags":[
        "installers",
        "planner",
        "kitchen",
        "furnishers"
    ],
    "wof:name":"Penthouse Furniture Ltd",
    "wof:placetype":"venue"
},
  "geometry": {"coordinates":[-2.877711,53.779903],"type":"Point"}
}