{
  "type": "Feature",
  "properties": {
    "addr:full":"19 Temple Fortune Parade London Greater London NW11 0QS",
    "addr:housenumber":"19",
    "addr:postcode":"nw11 0qs",
    "addr:street":"Temple Fortune Parade",
    "iso:country":"GB",
    "sg:address":"19 Temple Fortune Parade",
    "sg:city":"London",
    "sg:classifiers":[
        {
            "category":"Food & Beverages",
            "subcategory":"Bakery",
            "type":"Retail Goods"
        }
    ],
    "sg:postcode":"NW11 0QS",
    "sg:province":"Greater London",
    "sg:tags":[
        "baker"
    ],
    "wof:name":"Sherrards Patisserie",
    "wof:placetype":"venue"
},
  "geometry": {"coordinates":[-0.194933,51.5826],"type":"Point"}
}