{
  "type": "Feature",
  "properties": {
    "iso:country":"GB",
    "sg:address":"Post Office No 32",
    "sg:city":"Newcastle-upon-tyne",
    "sg:classifiers":[
        {
            "category":"Professional",
            "subcategory":"Lawyer & Legal Services",
            "type":"Services"
        }
    ],
    "sg:phone":"+44 191 265 1848",
    "sg:postcode":"NE6 1HZ",
    "sg:province":"Tyne and Wear",
    "sg:tags":[
        "advice",
        "counselling"
    ],
    "wof:name":"Womens Aid",
    "wof:placetype":"venue"
},
  "geometry": {"coordinates":[-1.581099987,54.9735717773],"type":"Point"}
}