{
  "type": "Feature",
  "properties": {
    "iso:country":"GB",
    "sg:address":"Independent Ho, Chapel St, Tyldesley",
    "sg:city":"Manchester",
    "sg:classifiers":[
        {
            "category":"Professional",
            "subcategory":"Accounting & Tax Preparation",
            "type":"Services"
        }
    ],
    "sg:postcode":"M29 8FZ",
    "sg:province":"Greater Manchester",
    "sg:tags":[
        "accountant"
    ],
    "wof:name":"Horton & Mascord",
    "wof:placetype":"venue"
},
  "geometry": {"coordinates":[-2.467259,53.51376],"type":"Point"}
}