{
  "type": "Feature",
  "properties": {
    "addr:full":"Bryn Myfanwy Stryd-y-fron Bala Gwynedd LL23 7YD",
    "addr:postcode":"ll23 7yd",
    "addr:street":"Bala",
    "iso:country":"GB",
    "sg:address":"Bryn Myfanwy Stryd-y-fron",
    "sg:city":"Bala",
    "sg:classifiers":[
        {
            "category":"Professional",
            "subcategory":"Management & Consulting",
            "type":"Services"
        }
    ],
    "sg:phone":"+44 1678 521000",
    "sg:postcode":"LL23 7YD",
    "sg:province":"Gwynedd",
    "sg:tags":[
        "consultant",
        "business"
    ],
    "wof:name":"Professional Personnel Consultants",
    "wof:placetype":"venue"
},
  "geometry": {"coordinates":[-3.5954670906,52.912147522],"type":"Point"}
}