{
  "type": "Feature",
  "properties": {
    "iso:country":"GB",
    "sg:address":"48 Portland Road",
    "sg:city":"Hove",
    "sg:classifiers":[
        {
            "category":"Professional",
            "subcategory":"Detective & Security Services",
            "type":"Services"
        }
    ],
    "sg:postcode":"BN3 5DL",
    "sg:province":"East Sussex",
    "sg:tags":[
        "alarm",
        "burglar",
        "system"
    ],
    "wof:name":"Knightguard Security",
    "wof:placetype":"venue"
},
  "geometry": {"coordinates":[-0.179783,50.832489],"type":"Point"}
}