{
  "type": "Feature",
  "properties": {
    "addr:full":"18 Hadley Highstone Barnet Hertfordshire EN5 4PU",
    "addr:housenumber":"18",
    "addr:postcode":"en5 4pu",
    "addr:street":"Hadley Highstone",
    "iso:country":"GB",
    "sg:address":"18 Hadley Highstone",
    "sg:city":"Barnet",
    "sg:classifiers":[
        {
            "category":"Bars & Pubs",
            "type":"Food & Drink"
        }
    ],
    "sg:postcode":"EN5 4PU",
    "sg:province":"Hertfordshire",
    "sg:tags":[
        "pubs",
        "inn"
    ],
    "wof:name":"King William Iv",
    "wof:placetype":"venue"
},
  "geometry": {"coordinates":[-0.199009,51.66383],"type":"Point"}
}