{
  "type": "Feature",
  "properties": {
    "addr:full":"37 St. Marys Rd, Oatlands Village Weybridge Surrey KT13 9PT",
    "addr:housenumber":"37",
    "addr:postcode":"kt13 9pt",
    "addr:street":"St. Marys Rd",
    "iso:country":"GB",
    "sg:address":"37 St. Marys Rd, Oatlands Village",
    "sg:city":"Weybridge",
    "sg:classifiers":[
        {
            "category":"Shopping",
            "subcategory":"Antiques",
            "type":"Retail Goods"
        }
    ],
    "sg:postcode":"KT13 9PT",
    "sg:province":"Surrey",
    "wof:name":"Porter,Ian,",
    "wof:placetype":"venue"
},
  "geometry": {"coordinates":[-0.4391970038,51.3721961975],"type":"Point"}
}