{
  "type": "Feature",
  "properties": {
    "addr:full":"1 St. Johns Grn, Writtle Chelmsford Essex CM1 3DZ",
    "addr:housenumber":"1",
    "addr:postcode":"cm1 3dz",
    "addr:street":"St. Johns Grn Writtle",
    "iso:country":"GB",
    "sg:address":"1 St. Johns Grn, Writtle",
    "sg:city":"Chelmsford",
    "sg:classifiers":[
        {
            "category":"Real Estate",
            "subcategory":"Real Estate Agent",
            "type":"Services"
        }
    ],
    "sg:postcode":"CM1 3DZ",
    "sg:province":"Essex",
    "wof:name":"Reader,Malcolm,",
    "wof:placetype":"venue"
},
  "geometry": {"coordinates":[0.4301530123,51.7303848267],"type":"Point"}
}