{
  "type": "Feature",
  "properties": {
    "addr:full":"49 Scotts Rd Paisley East Renfrewshire PA2 7AN",
    "addr:housenumber":"49",
    "addr:postcode":"pa2 7an",
    "addr:street":"Scotts Rd",
    "iso:country":"GB",
    "sg:address":"49 Scotts Rd",
    "sg:city":"Paisley",
    "sg:classifiers":[
        {
            "category":"Retail",
            "subcategory":"Auto Repair",
            "type":"Services"
        }
    ],
    "sg:phone":"+44 141 889 2126",
    "sg:postcode":"PA2 7AN",
    "sg:province":"East Renfrewshire",
    "sg:tags":[
        "modification",
        "garage"
    ],
    "wof:name":"Lochfield Garage",
    "wof:placetype":"venue"
},
  "geometry": {"coordinates":[-4.3709588051,55.8408088684],"type":"Point"}
}