{
  "type": "Feature",
  "properties": {
    "iso:country":"GB",
    "sg:address":"Little Fleece Bookshop, Bisley St",
    "sg:city":"Stroud",
    "sg:classifiers":[
        {
            "category":"Shopping",
            "subcategory":"Books",
            "type":"Retail Goods"
        },
        {
            "category":"Landmark",
            "subcategory":"Tourist Attraction",
            "type":"Public Place"
        }
    ],
    "sg:phone":"+44 1452 812103",
    "sg:postcode":"GL6 6QQ",
    "sg:province":"Gloucestershire",
    "sg:tags":[
        "bookseller",
        "interest"
    ],
    "wof:name":"National Trust The",
    "wof:placetype":"venue"
},
  "geometry": {"coordinates":[-2.19296,51.786461],"type":"Point"}
}