{
  "type": "Feature",
  "properties": {
    "iso:country":"GB",
    "sg:address":"17 Holmoaks, Rainham",
    "sg:city":"Gillingham",
    "sg:classifiers":[
        {
            "category":"Professional",
            "subcategory":"Engineering",
            "type":"Services"
        }
    ],
    "sg:postcode":"ME8 7DE",
    "sg:province":"Kent",
    "sg:tags":[
        "contractor",
        "electrical",
        "engineer"
    ],
    "wof:name":"Scott Electrical Services",
    "wof:placetype":"venue"
},
  "geometry": {"coordinates":[0.603968,51.368263],"type":"Point"}
}