{
  "type": "Feature",
  "properties": {
    "addr:full":"39 Fairfax Rd, Swiss Cottage Kilburn Greater London NW6 4EL",
    "addr:housenumber":"39",
    "addr:postcode":"nw6 4el",
    "addr:street":"Fairfax Rd",
    "iso:country":"GB",
    "sg:address":"39 Fairfax Rd, Swiss Cottage",
    "sg:city":"Kilburn",
    "sg:classifiers":[
        {
            "category":"Home & Garden",
            "subcategory":"Home Furnishings",
            "type":"Retail Goods"
        }
    ],
    "sg:phone":"+44 20 7328 5462",
    "sg:postcode":"NW6 4EL",
    "sg:province":"Greater London",
    "sg:tags":[
        "homefurnishings"
    ],
    "wof:name":"Personal Touch",
    "wof:placetype":"venue"
},
  "geometry": {"coordinates":[-0.1795639992,51.5435066223],"type":"Point"}
}