{
  "type": "Feature",
  "properties": {
    "iso:country":"GB",
    "sg:address":"23 Croft Road",
    "sg:city":"Swindon",
    "sg:classifiers":[
        {
            "category":"Travel",
            "subcategory":"Hostel",
            "type":"Entertainment"
        }
    ],
    "sg:phone":"+44 1793 521324",
    "sg:postcode":"SN1 4DG",
    "sg:province":"Wiltshire",
    "wof:name":"Bridge Services",
    "wof:placetype":"venue"
},
  "geometry": {"coordinates":[-1.777294,51.547878],"type":"Point"}
}