{
  "type": "Feature",
  "properties": {
    "iso:country":"GB",
    "sg:address":"Everill Gate Lane, Broomhill, Wombwell",
    "sg:city":"Barnsley",
    "sg:classifiers":[
        {
            "category":"Community Center",
            "type":"Public Place"
        }
    ],
    "sg:phone":"+44 1226 754024",
    "sg:postcode":"S73 0YH",
    "sg:province":"South Yorkshire",
    "sg:tags":[
        "recreation",
        "leisure",
        "centre"
    ],
    "wof:name":"Unique Leisure",
    "wof:placetype":"venue"
},
  "geometry": {"coordinates":[-1.3746949434,53.5200119019],"type":"Point"}
}