{
  "type": "Feature",
  "properties": {
    "addr:full":"33 Academy Street Inverness Highland IV1 1JN",
    "addr:housenumber":"33",
    "addr:postcode":"iv1 1jn",
    "addr:street":"Academy Street",
    "iso:country":"GB",
    "sg:address":"33 Academy Street",
    "sg:city":"Inverness",
    "sg:classifiers":[
        {
            "category":"Personal",
            "subcategory":"Beauty Salon",
            "type":"Services"
        }
    ],
    "sg:phone":"+44 1463 231123",
    "sg:postcode":"IV1 1JN",
    "sg:province":"Highland",
    "sg:tags":[
        "unisex",
        "hairdresser"
    ],
    "wof:name":"Fornari",
    "wof:placetype":"venue"
},
  "geometry": {"coordinates":[-4.2254018784,57.4795265198],"type":"Point"}
}