{
  "type": "Feature",
  "properties": {
    "iso:country":"GB",
    "sg:address":"Unit 17 Autumn Park, Dysart Road",
    "sg:city":"Grantham",
    "sg:classifiers":[
        {
            "category":"Retail",
            "subcategory":"Auto Repair",
            "type":"Services"
        }
    ],
    "sg:phone":"+44 1476 590229",
    "sg:postcode":"NG31 7DD",
    "sg:province":"Lincolnshire",
    "sg:tags":[
        "modification",
        "garage",
        "related"
    ],
    "wof:name":"STUART W WATTS",
    "wof:placetype":"venue"
},
  "geometry": {"coordinates":[-0.642859,52.913197],"type":"Point"}
}