{
  "type": "Feature",
  "properties": {
    "addr:full":"Shakespeare Rd Exeter Devon EX2 6BU",
    "addr:postcode":"ex2 6bu",
    "addr:street":"Shakespeare Rd",
    "iso:country":"GB",
    "sg:address":"Shakespeare Rd",
    "sg:city":"Exeter",
    "sg:classifiers":[
        {
            "category":"Health Services",
            "subcategory":"Clinic",
            "type":"Services"
        }
    ],
    "sg:phone":"+44 1392 274983",
    "sg:postcode":"EX2 6BU",
    "sg:province":"Devon",
    "sg:tags":[
        "private"
    ],
    "wof:name":"Burnthouse Lane Clinic",
    "wof:placetype":"venue"
},
  "geometry": {"coordinates":[-3.507745,50.711784],"type":"Point"}
}