{
  "type": "Feature",
  "properties": {
    "iso:country":"GB",
    "sg:address":"35 Ghyllside Drive",
    "sg:city":"Hastings",
    "sg:classifiers":[
        {
            "category":"Food & Beverages",
            "subcategory":"Meat & Fish",
            "type":"Retail Goods"
        }
    ],
    "sg:phone":"+44 1424 441664",
    "sg:postcode":"TN34 2NA",
    "sg:province":"East Sussex",
    "sg:tags":[
        "merchant"
    ],
    "wof:name":"Don Creed",
    "wof:placetype":"venue"
},
  "geometry": {"coordinates":[0.5644770265,50.8754310608],"type":"Point"}
}