{
  "type": "Feature",
  "properties": {
    "iso:country":"GB",
    "sg:address":"247 Westleigh Lane",
    "sg:city":"Leigh",
    "sg:classifiers":[
        {
            "category":"Utilities",
            "subcategory":"Fuel Oil & Lpg",
            "type":"Services"
        }
    ],
    "sg:phone":"+44 1942 884210",
    "sg:postcode":"WN7 5PN",
    "sg:province":"Lancashire",
    "sg:tags":[
        "coal",
        "smokeless"
    ],
    "wof:name":"F Wardle",
    "wof:placetype":"venue"
},
  "geometry": {"coordinates":[-2.530327,53.517769],"type":"Point"}
}