{
  "type": "Feature",
  "properties": {
    "iso:country":"GB",
    "sg:address":"6 Porchfield Square, Deansgate",
    "sg:city":"Manchester",
    "sg:classifiers":[
        {
            "category":"Professional",
            "subcategory":"Printing & Photocopies",
            "type":"Services"
        }
    ],
    "sg:phone":"+44 161 839 5983",
    "sg:postcode":"M3 4FG",
    "sg:province":"Greater Manchester",
    "sg:tags":[
        "rubber",
        "stamp"
    ],
    "wof:name":"Fleetwood Agencies Ltd.",
    "wof:placetype":"venue"
},
  "geometry": {"coordinates":[-2.252371,53.477169],"type":"Point"}
}