{
  "type": "Feature",
  "properties": {
    "iso:country":"GB",
    "sg:address":"22 Westward Road, Hedge End",
    "sg:city":"Southampton",
    "sg:classifiers":[
        {
            "category":"Shopping",
            "subcategory":"Mobile Phones",
            "type":"Retail Goods"
        }
    ],
    "sg:postcode":"SO30 4NQ",
    "sg:province":"Hampshire",
    "wof:name":"Response Communications",
    "wof:placetype":"venue"
},
  "geometry": {"coordinates":[-1.303392,50.921715],"type":"Point"}
}