{
  "type": "Feature",
  "properties": {
    "iso:country":"GB",
    "sg:address":"Millans Park",
    "sg:city":"Ambleside",
    "sg:classifiers":[
        {
            "category":"Place Of Worship",
            "type":"Public Place"
        }
    ],
    "sg:phone":"+44 15394 33205",
    "sg:postcode":"LA22 9AD",
    "sg:province":"Cumbria",
    "wof:name":"St.Marys Church",
    "wof:placetype":"venue"
},
  "geometry": {"coordinates":[-2.9644539356,54.4333305359],"type":"Point"}
}