{
  "type": "Feature",
  "properties": {
    "iso:country":"GB",
    "sg:address":"28 Queens Dr",
    "sg:city":"Waltham Cross",
    "sg:classifiers":[
        {
            "category":"Social Services",
            "subcategory":"Child Care",
            "type":"Services"
        }
    ],
    "sg:postcode":"EN8 7PP",
    "sg:province":"Essex",
    "sg:tags":[
        "childminders"
    ],
    "wof:name":"Kunning,S,",
    "wof:placetype":"venue"
},
  "geometry": {"coordinates":[-0.01838,51.684811],"type":"Point"}
}