{
  "type": "Feature",
  "properties": {
    "iso:country":"GB",
    "sg:address":"74 Oak Lane",
    "sg:city":"West Bromwich",
    "sg:classifiers":[
        {
            "category":"Food & Beverages",
            "subcategory":"Liquor & Beverages",
            "type":"Retail Goods"
        }
    ],
    "sg:phone":"+44 121 525 3352",
    "sg:postcode":"B70 8PN",
    "sg:province":"West Midlands",
    "sg:tags":[
        "beer",
        "spirit",
        "wines"
    ],
    "wof:name":"Oak Halal Lodge",
    "wof:placetype":"venue"
},
  "geometry": {"coordinates":[-2.0038490295,52.5180854797],"type":"Point"}
}