{
  "type": "Feature",
  "properties": {
    "addr:full":"Warren Road, Hopton Great Yarmouth Norfolk NR31 9BN",
    "addr:postcode":"nr31 9bn",
    "addr:street":"Warren Road;Yarmouth",
    "iso:country":"GB",
    "sg:address":"Warren Road, Hopton",
    "sg:city":"Great Yarmouth",
    "sg:classifiers":[
        {
            "category":"Health Services",
            "subcategory":"Nursing And Care Facility",
            "type":"Services"
        }
    ],
    "sg:phone":"+44 1502 731786",
    "sg:postcode":"NR31 9BN",
    "sg:province":"Norfolk",
    "sg:tags":[
        "home",
        "residential"
    ],
    "wof:name":"Estateband Ltd.",
    "wof:placetype":"venue"
},
  "geometry": {"coordinates":[1.7259199619,52.5393486023],"type":"Point"}
}