{
  "type": "Feature",
  "properties": {
    "iso:country":"GB",
    "sg:address":"22 Royston Drive",
    "sg:city":"Belper",
    "sg:classifiers":[
        {
            "category":"Building & Trades",
            "subcategory":"Cleaning & Sanitation",
            "type":"Services"
        },
        {
            "category":"Retail",
            "subcategory":"Storage",
            "type":"Services"
        }
    ],
    "sg:postcode":"DE56 0EL",
    "sg:province":"Derbyshire",
    "sg:tags":[
        "industrial",
        "business",
        "household",
        "domestic",
        "removal",
        "activity"
    ],
    "wof:name":"Brewer & Turnbull",
    "wof:placetype":"venue"
},
  "geometry": {"coordinates":[-1.44974,53.029434],"type":"Point"}
}