{
  "type": "Feature",
  "properties": {
    "iso:country":"GB",
    "sg:address":"57 Brudenell Gro, Near Hyde Pk",
    "sg:city":"Leeds",
    "sg:classifiers":[
        {
            "category":"Shopping",
            "subcategory":"Comic Books",
            "type":"Retail Goods"
        }
    ],
    "sg:postcode":"LS6 1HR",
    "sg:province":"West Yorkshire",
    "sg:tags":[
        "jeweller"
    ],
    "wof:name":"Punjab Jewellers",
    "wof:placetype":"venue"
},
  "geometry": {"coordinates":[-1.56762,53.811752],"type":"Point"}
}