{
  "type": "Feature",
  "properties": {
    "iso:country":"GB",
    "sg:address":"390 Cathcart Road",
    "sg:city":"Glasgow",
    "sg:classifiers":[
        {
            "category":"Wholesale",
            "subcategory":"Office Equipment",
            "type":"Manufacturing & Wholesale Goods"
        },
        {
            "category":"Banks & Credit Unions",
            "subcategory":"Bureau De Change",
            "type":"Services"
        }
    ],
    "sg:phone":"+44 141 423 9999",
    "sg:postcode":"G42 7DF",
    "sg:province":"Glasgow City",
    "sg:tags":[
        "manufacture",
        "register",
        "cash",
        "accessory",
        "supply"
    ],
    "wof:name":"Cash Control Equipment Ltd.",
    "wof:placetype":"venue"
},
  "geometry": {"coordinates":[-4.256925,55.839378],"type":"Point"}
}