{
  "type": "Feature",
  "properties": {
    "addr:full":"30 Hetton Road Leeds West Yorkshire LS8 2RT",
    "addr:postcode":"ls8 2rt",
    "addr:street":"Hetton Road",
    "iso:country":"GB",
    "sg:address":"30 Hetton Road",
    "sg:city":"Leeds",
    "sg:classifiers":[
        {
            "category":"Professional",
            "type":"Services"
        },
        {
            "category":"Social Services",
            "subcategory":"Job Training",
            "type":"Services"
        }
    ],
    "sg:phone":"+44 113 294 5773",
    "sg:postcode":"LS8 2RT",
    "sg:province":"West Yorkshire",
    "sg:tags":[
        "translator",
        "interpreter",
        "translation",
        "activity"
    ],
    "wof:name":"Arabic Language Services",
    "wof:placetype":"venue"
},
  "geometry": {"coordinates":[-1.503217,53.821999],"type":"Point"}
}