{
  "type": "Feature",
  "properties": {
    "addr:full":"Unit 7b, Drum Industrial Estate Chester-le-street Durham DH2 1AG",
    "addr:housenumber":"unit 7b",
    "addr:postcode":"dh2 1ag",
    "addr:street":"Drum Industrial",
    "iso:country":"GB",
    "sg:address":"Unit 7b, Drum Industrial Estate",
    "sg:city":"Chester-le-street",
    "sg:classifiers":[
        {
            "category":"Wholesale",
            "subcategory":"Medical Equipment & Supplies",
            "type":"Manufacturing & Wholesale Goods"
        }
    ],
    "sg:phone":"+44 191 492 0777",
    "sg:postcode":"DH2 1AG",
    "sg:province":"Durham",
    "sg:tags":[
        "hospital"
    ],
    "wof:name":"Wescott Medical Ltd.",
    "wof:placetype":"venue"
},
  "geometry": {"coordinates":[-1.6236989498,54.8671417236],"type":"Point"}
}