{
  "type": "Feature",
  "properties": {
    "addr:full":"Unit 1 Birch Coppice Colliery, Dordon Tamworth Staffordshire B78 1SZ",
    "addr:housenumber":"unit 1",
    "addr:postcode":"b78 1sz",
    "addr:street":"Birch Coppice",
    "iso:country":"GB",
    "sg:address":"Unit 1 Birch Coppice Colliery, Dordon",
    "sg:city":"Tamworth",
    "sg:classifiers":[
        {
            "category":"Utilities",
            "subcategory":"Refuse",
            "type":"Services"
        }
    ],
    "sg:phone":"+44 1827 897799",
    "sg:postcode":"B78 1SZ",
    "sg:province":"Staffordshire",
    "sg:tags":[
        "skip",
        "hire"
    ],
    "wof:name":"Douglas Non Ferrous Metals & Skip Hire Ltd.",
    "wof:placetype":"venue"
},
  "geometry": {"coordinates":[-1.6335790157,52.6100883484],"type":"Point"}
}