{
  "type": "Feature",
  "properties": {
    "addr:full":"Field House Lodge, Malton Rd Filey North Yorkshire YO14 0PG",
    "addr:postcode":"yo14 0pg",
    "addr:street":"Malton Rd",
    "iso:country":"GB",
    "sg:address":"Field House Lodge, Malton Rd",
    "sg:city":"Filey",
    "sg:classifiers":[
        {
            "category":"Banks & Credit Unions",
            "subcategory":"Investment Brokerage",
            "type":"Services"
        }
    ],
    "sg:phone":"+44 1723 891572",
    "sg:postcode":"YO14 0PG",
    "sg:province":"North Yorkshire",
    "sg:tags":[
        "contractor"
    ],
    "wof:name":"D & M Sleightholme",
    "wof:placetype":"venue"
},
  "geometry": {"coordinates":[-0.32674,54.182056],"type":"Point"}
}