{
  "type": "Feature",
  "properties": {
    "iso:country":"GB",
    "sg:address":"72 St Margarets Avenue",
    "sg:city":"Sutton",
    "sg:classifiers":[
        {
            "category":"Building & Trades",
            "subcategory":"Construction",
            "type":"Services"
        }
    ],
    "sg:phone":"+44 20 8715 4764",
    "sg:postcode":"SM3 9TT",
    "sg:province":"Surrey",
    "sg:tags":[
        "builder"
    ],
    "wof:name":"J & D Smith Builders & Decorators",
    "wof:placetype":"venue"
},
  "geometry": {"coordinates":[-0.215964,51.372395],"type":"Point"}
}