{
  "type": "Feature",
  "properties": {
    "addr:full":"Unit 5a Gallamore Lane Market Rasen Lincolnshire LN8 3HZ",
    "addr:housenumber":"unit 5a",
    "addr:postcode":"ln8 3hz",
    "addr:street":"Gallamore Lane",
    "iso:country":"GB",
    "sg:address":"Unit 5a Gallamore Lane",
    "sg:city":"Market Rasen",
    "sg:classifiers":[
        {
            "category":"Professional",
            "subcategory":"Employment Agencies",
            "type":"Services"
        }
    ],
    "sg:postcode":"LN8 3HZ",
    "sg:province":"Lincolnshire",
    "sg:tags":[
        "agricultural",
        "advice"
    ],
    "wof:name":"G C Industrial Electronic",
    "wof:placetype":"venue"
},
  "geometry": {"coordinates":[-0.3466030061,53.391960144],"type":"Point"}
}