{
  "type": "Feature",
  "properties": {
    "addr:full":"70 Hutton Gro London Greater London N12 8DR",
    "addr:housenumber":"70",
    "addr:postcode":"n12 8dr",
    "addr:street":"Hutton Gro",
    "iso:country":"GB",
    "sg:address":"70 Hutton Gro",
    "sg:city":"London",
    "sg:classifiers":[
        {
            "category":"Building & Trades",
            "subcategory":"Landscaping Services",
            "type":"Services"
        }
    ],
    "sg:postcode":"N12 8DR",
    "sg:province":"Greater London",
    "sg:tags":[
        "gardening"
    ],
    "wof:name":"Mark Fairchild Landscapes",
    "wof:placetype":"venue"
},
  "geometry": {"coordinates":[-0.182794,51.61359],"type":"Point"}
}