{
  "type": "Feature",
  "properties": {
    "addr:full":"8 Crossway Bracknell Berkshire RG12 1AF",
    "addr:housenumber":"8",
    "addr:postcode":"rg12 1af",
    "addr:street":"Crossway",
    "iso:country":"GB",
    "sg:address":"8 Crossway",
    "sg:city":"Bracknell",
    "sg:classifiers":[
        {
            "category":"Fast Food",
            "type":"Food & Drink"
        }
    ],
    "sg:phone":"+44 1344 300900",
    "sg:postcode":"RG12 1AF",
    "sg:province":"Berkshire",
    "sg:tags":[
        "away",
        "meal",
        "outlet",
        "take"
    ],
    "sg:website":"http://www.dominos.co.uk",
    "wof:name":"Domino's Pizza",
    "wof:placetype":"venue"
},
  "geometry": {"coordinates":[-0.7487699986,51.4169387817],"type":"Point"}
}