{
  "type": "Feature",
  "properties": {
    "iso:country":"GB",
    "sg:address":"128 Middlefield Lane",
    "sg:city":"Hinckley",
    "sg:classifiers":[
        {
            "category":"Professional",
            "subcategory":"Engineering",
            "type":"Services"
        }
    ],
    "sg:phone":"+44 1455 618731",
    "sg:postcode":"LE10 0RA",
    "sg:province":"Leicestershire",
    "sg:tags":[
        "civil",
        "engineer"
    ],
    "wof:name":"Premier Paviours",
    "wof:placetype":"venue"
},
  "geometry": {"coordinates":[-1.3734760284,52.5544700623],"type":"Point"}
}