{
  "type": "Feature",
  "properties": {
    "addr:full":"31-35 New Road, Whittlesey Peterborough Cambridgeshire PE7 1ST",
    "addr:housenumber":"31-35",
    "addr:postcode":"pe7 1st",
    "addr:street":"New Road",
    "iso:country":"GB",
    "sg:address":"31-35 New Road, Whittlesey",
    "sg:city":"Peterborough",
    "sg:classifiers":[
        {
            "category":"Professional",
            "subcategory":"Art Services",
            "type":"Services"
        }
    ],
    "sg:phone":"+44 1733 202109",
    "sg:postcode":"PE7 1ST",
    "sg:province":"Cambridgeshire",
    "sg:tags":[
        "graphic",
        "designer"
    ],
    "wof:name":"Wenham Arts",
    "wof:placetype":"venue"
},
  "geometry": {"coordinates":[-0.123027,52.554504],"type":"Point"}
}