{
  "type": "Feature",
  "properties": {
    "iso:country":"GB",
    "sg:address":"6 Amanda Road, Rainhill",
    "sg:city":"Prescot",
    "sg:classifiers":[
        {
            "category":"Communications",
            "type":"Services"
        }
    ],
    "sg:postcode":"L35 8PP",
    "sg:province":"Cheshire",
    "sg:tags":[
        "audio-visual"
    ],
    "wof:name":"A B C",
    "wof:placetype":"venue"
},
  "geometry": {"coordinates":[-2.7750101089,53.4231338501],"type":"Point"}
}