{
  "type": "Feature",
  "properties": {
    "iso:country":"GB",
    "sg:address":"4 Stand Park, Sheffield Road",
    "sg:city":"Chesterfield",
    "sg:classifiers":[
        {
            "category":"Professional",
            "subcategory":"Art Services",
            "type":"Services"
        }
    ],
    "sg:phone":"+44 1246 234263",
    "sg:postcode":"S41 8JT",
    "sg:province":"Derbyshire",
    "sg:tags":[
        "decorating",
        "painting"
    ],
    "wof:name":"Yorkshire Decorative Materials Co. Ltd.",
    "wof:placetype":"venue"
},
  "geometry": {"coordinates":[-1.428263,53.256145],"type":"Point"}
}