{
  "type": "Feature",
  "properties": {
    "iso:country":"GB",
    "sg:address":"62 High St",
    "sg:city":"Sandhurst",
    "sg:classifiers":[
        {
            "category":"Home & Garden",
            "subcategory":"Building Materials",
            "type":"Retail Goods"
        }
    ],
    "sg:phone":"+44 1252 876876",
    "sg:postcode":"GU47 8DY",
    "sg:province":"Berkshire",
    "sg:tags":[
        "brick"
    ],
    "wof:name":"Exclusive Fireplaces",
    "wof:placetype":"venue"
},
  "geometry": {"coordinates":[-0.806397,51.346684],"type":"Point"}
}