{
  "type": "Feature",
  "properties": {
    "iso:country":"GB",
    "sg:address":"29 Out Risbygate",
    "sg:city":"Bury St Edmunds",
    "sg:classifiers":[
        {
            "category":"Health Services",
            "subcategory":"Nursing And Care Facility",
            "type":"Services"
        }
    ],
    "sg:postcode":"IP33 3RJ",
    "sg:province":"Suffolk",
    "sg:tags":[
        "home"
    ],
    "wof:name":"St.Peters Cottage",
    "wof:placetype":"venue"
},
  "geometry": {"coordinates":[0.700116992,52.2475624084],"type":"Point"}
}