{
  "type": "Feature",
  "properties": {
    "addr:full":"39 Market Street Bridgwater Somerset TA6 3BL",
    "addr:housenumber":"39",
    "addr:postcode":"ta6 3bl",
    "addr:street":"Market Street",
    "iso:country":"GB",
    "sg:address":"39 Market Street",
    "sg:city":"Bridgwater",
    "sg:classifiers":[
        {
            "category":"Professional",
            "type":"Services"
        }
    ],
    "sg:postcode":"TA6 3BL",
    "sg:province":"Somerset",
    "sg:tags":[
        "auctioneer"
    ],
    "wof:name":"Sedgemoor Auction Rooms",
    "wof:placetype":"venue"
},
  "geometry": {"coordinates":[-3.0073950291,51.128074646],"type":"Point"}
}