{
  "type": "Feature",
  "properties": {
    "iso:country":"GB",
    "sg:address":"121 Churchill Drive",
    "sg:city":"Glasgow",
    "sg:classifiers":[
        {
            "category":"Autos & Motor Vehicles",
            "subcategory":"Automobile Sales",
            "type":"Retail Goods"
        }
    ],
    "sg:postcode":"G11 7EY",
    "sg:province":"Glasgow City",
    "sg:tags":[
        "car"
    ],
    "wof:name":"F Macritchie",
    "wof:placetype":"venue"
},
  "geometry": {"coordinates":[-4.3157978058,55.8795089722],"type":"Point"}
}