{
  "type": "Feature",
  "properties": {
    "addr:full":"82 Priory Rd Kilburn Greater London NW6 3NT",
    "addr:housenumber":"82",
    "addr:postcode":"nw6 3nt",
    "addr:street":"Priory Rd",
    "iso:country":"GB",
    "sg:address":"82 Priory Rd",
    "sg:city":"Kilburn",
    "sg:classifiers":[
        {
            "category":"Communications",
            "type":"Services"
        }
    ],
    "sg:phone":"+44 20 7624 7870",
    "sg:postcode":"NW6 3NT",
    "sg:province":"Greater London",
    "sg:tags":[
        "audio-visual"
    ],
    "wof:name":"Creation Video",
    "wof:placetype":"venue"
},
  "geometry": {"coordinates":[-0.1887589991,51.5437850952],"type":"Point"}
}