{
  "type": "Feature",
  "properties": {
    "addr:full":"Midthorn Ind Est, Laurieston Rd Grangemouth Falkirk FK3 8XX",
    "addr:postcode":"fk3 8xx",
    "addr:street":"Laurieston Rd",
    "iso:country":"GB",
    "sg:address":"Midthorn Ind Est, Laurieston Rd",
    "sg:city":"Grangemouth",
    "sg:classifiers":[
        {
            "category":"Autos & Motor Vehicles",
            "subcategory":"Automobile Sales",
            "type":"Retail Goods"
        }
    ],
    "sg:phone":"+44 1324 472897",
    "sg:postcode":"FK3 8XX",
    "sg:province":"Falkirk",
    "sg:tags":[
        "commercial"
    ],
    "wof:name":"Smith Trucks Ltd",
    "wof:placetype":"venue"
},
  "geometry": {"coordinates":[-3.727298975,56.0127296448],"type":"Point"}
}