{
  "type": "Feature",
  "properties": {
    "addr:full":"3 Loughton Rd Milton Keynes Buckinghamshire MK13 9AB",
    "addr:housenumber":"3",
    "addr:postcode":"mk13 9ab",
    "addr:street":"Loughton Rd",
    "iso:country":"GB",
    "sg:address":"3 Loughton Rd",
    "sg:city":"Milton Keynes",
    "sg:classifiers":[
        {
            "category":"Building & Trades",
            "subcategory":"Construction",
            "type":"Services"
        }
    ],
    "sg:phone":"+44 1908 315410",
    "sg:postcode":"MK13 9AB",
    "sg:province":"Buckinghamshire",
    "sg:tags":[
        "welder"
    ],
    "wof:name":"Ken Baitey",
    "wof:placetype":"venue"
},
  "geometry": {"coordinates":[-0.7864720225,52.0512390137],"type":"Point"}
}