{
  "type": "Feature",
  "properties": {
    "addr:full":"Hyde End Road, Shinfield Reading Berkshire RG2 9ER",
    "addr:postcode":"rg2 9er",
    "addr:street":"Hyde End Road",
    "iso:country":"GB",
    "sg:address":"Hyde End Road, Shinfield",
    "sg:city":"Reading",
    "sg:classifiers":[
        {
            "category":"Home & Garden",
            "subcategory":"Garden Supply",
            "type":"Retail Goods"
        }
    ],
    "sg:phone":"+44 118 988 4822",
    "sg:postcode":"RG2 9ER",
    "sg:province":"Berkshire",
    "sg:tags":[
        "nursery",
        "centre"
    ],
    "wof:name":"Grovelands Garden Centre Ltd.",
    "wof:placetype":"venue"
},
  "geometry": {"coordinates":[-0.948345,51.401489],"type":"Point"}
}