{
  "type": "Feature",
  "properties": {
    "iso:country":"GB",
    "sg:address":"54 Bristol Road, Portishead",
    "sg:city":"Bristol",
    "sg:classifiers":[
        {
            "category":"Professional",
            "subcategory":"Engineering",
            "type":"Services"
        },
        {
            "category":"Home & Garden",
            "subcategory":"Household Appliances",
            "type":"Retail Goods"
        }
    ],
    "sg:phone":"+44 1275 848983",
    "sg:postcode":"BS20 6QB",
    "sg:province":"Somerset",
    "sg:tags":[
        "contractor",
        "electrical",
        "engineer"
    ],
    "wof:name":"A P Electrical",
    "wof:placetype":"venue"
},
  "geometry": {"coordinates":[-2.763494,51.476093],"type":"Point"}
}