{
  "type": "Feature",
  "properties": {
    "addr:full":"Whitehouse Farm, Skipton Rd, Farnhill Keighley North Yorkshire BD20 9BT",
    "addr:postcode":"bd20 9bt",
    "addr:street":"Skipton Rd",
    "iso:country":"GB",
    "sg:address":"Whitehouse Farm, Skipton Rd, Farnhill",
    "sg:city":"Keighley",
    "sg:classifiers":[
        {
            "category":"Shopping",
            "subcategory":"Shoes",
            "type":"Retail Goods"
        }
    ],
    "sg:postcode":"BD20 9BT",
    "sg:province":"North Yorkshire",
    "sg:tags":[
        "shop"
    ],
    "wof:name":"Touch of Class",
    "wof:placetype":"venue"
},
  "geometry": {"coordinates":[-1.9962240458,53.9153442383],"type":"Point"}
}