{
  "type": "Feature",
  "properties": {
    "addr:full":"36a New Park Street Devizes Wiltshire SN10 1DZ",
    "addr:housenumber":"36a",
    "addr:postcode":"sn10 1dz",
    "addr:street":"New Park Street",
    "iso:country":"GB",
    "sg:address":"36a New Park Street",
    "sg:city":"Devizes",
    "sg:classifiers":[
        {
            "category":"Personal",
            "subcategory":"Beauty Salon",
            "type":"Services"
        }
    ],
    "sg:postcode":"SN10 1DZ",
    "sg:province":"Wiltshire",
    "sg:tags":[
        "unisex",
        "hairdresser"
    ],
    "wof:name":"Salon Louis",
    "wof:placetype":"venue"
},
  "geometry": {"coordinates":[-1.995362,51.354172],"type":"Point"}
}