{
  "type": "Feature",
  "properties": {
    "iso:country":"GB",
    "sg:address":"Playing Fields, Axwell View",
    "sg:city":"Blaydon-on-tyne",
    "sg:classifiers":[
        {
            "category":"Arena",
            "subcategory":"Sports Club",
            "type":"Entertainment"
        }
    ],
    "sg:phone":"+44 191 414 2502",
    "sg:postcode":"NE21 6NF",
    "sg:province":"Tyne and Wear",
    "wof:name":"Winlaton Vulcans Rugby Football Club",
    "wof:placetype":"venue"
},
  "geometry": {"coordinates":[-1.707943,54.963013],"type":"Point"}
}