{
  "type": "Feature",
  "properties": {
    "addr:full":"39 Winnipeg Rd Doncaster South Yorkshire DN5 0ED",
    "addr:housenumber":"39",
    "addr:postcode":"dn5 0ed",
    "addr:street":"Winnipeg Rd",
    "iso:country":"GB",
    "sg:address":"39 Winnipeg Rd",
    "sg:city":"Doncaster",
    "sg:classifiers":[
        {
            "category":"Social Services",
            "subcategory":"Adult Care",
            "type":"Services"
        }
    ],
    "sg:phone":"+44 1302 876023",
    "sg:postcode":"DN5 0ED",
    "sg:province":"South Yorkshire",
    "sg:tags":[
        "housing",
        "sheltered"
    ],
    "wof:name":"J Woodward",
    "wof:placetype":"venue"
},
  "geometry": {"coordinates":[-1.1447739601,53.5499038696],"type":"Point"}
}