{
  "type": "Feature",
  "properties": {
    "addr:full":"Flood Lane Bridport Dorset DT6 3QG",
    "addr:postcode":"dt6 3qg",
    "addr:street":"Flood Lane",
    "iso:country":"GB",
    "sg:address":"Flood Lane",
    "sg:city":"Bridport",
    "sg:classifiers":[
        {
            "category":"Education",
            "subcategory":"Special Training",
            "type":"Public Place"
        },
        {
            "category":"Education",
            "subcategory":"School",
            "type":"Public Place"
        }
    ],
    "sg:phone":"+44 1308 422250",
    "sg:postcode":"DT6 3QG",
    "sg:province":"Dorset",
    "wof:name":"Mountjoy School",
    "wof:placetype":"venue"
},
  "geometry": {"coordinates":[-2.7569670677,50.7248420715],"type":"Point"}
}