{
  "type": "Feature",
  "properties": {
    "iso:country":"GB",
    "sg:address":"Greenacres, Broad Oak",
    "sg:city":"Sturminster Newton",
    "sg:classifiers":[
        {
            "category":"Building & Trades",
            "subcategory":"Construction",
            "type":"Services"
        }
    ],
    "sg:phone":"+44 1258 472198",
    "sg:postcode":"DT10 2HG",
    "sg:province":"Dorset",
    "sg:tags":[
        "builder",
        "contractor"
    ],
    "wof:name":"John Starkey Builders",
    "wof:placetype":"venue"
},
  "geometry": {"coordinates":[-2.312842,50.919811],"type":"Point"}
}