{
  "type": "Feature",
  "properties": {
    "iso:country":"GB",
    "sg:address":"211 Downs Road",
    "sg:city":"Folkestone",
    "sg:classifiers":[
        {
            "category":"Building & Trades",
            "subcategory":"Construction",
            "type":"Services"
        }
    ],
    "sg:phone":"+44 1303 255382",
    "sg:postcode":"CT19 5PX",
    "sg:province":"Kent",
    "sg:tags":[
        "decorator",
        "painter"
    ],
    "wof:name":"David E Arnold",
    "wof:placetype":"venue"
},
  "geometry": {"coordinates":[1.175598979,51.0948638916],"type":"Point"}
}