{
  "type": "Feature",
  "properties": {
    "addr:full":"56 Truro Road Gravesend Kent DA12 5RF",
    "addr:housenumber":"56",
    "addr:postcode":"da12 5rf",
    "addr:street":"Truro Road",
    "iso:country":"GB",
    "sg:address":"56 Truro Road",
    "sg:city":"Gravesend",
    "sg:classifiers":[
        {
            "category":"Professional",
            "subcategory":"Computer Services",
            "type":"Services"
        }
    ],
    "sg:phone":"+44 1474 325628",
    "sg:postcode":"DA12 5RF",
    "sg:province":"Kent",
    "sg:tags":[
        "development",
        "system",
        "software"
    ],
    "wof:name":"R N B Systems",
    "wof:placetype":"venue"
},
  "geometry": {"coordinates":[0.381362,51.424118],"type":"Point"}
}