{
  "type": "Feature",
  "properties": {
    "addr:full":"Unit 20 The Oaks, Framfield Uckfield East Sussex TN22 5PN",
    "addr:housenumber":"unit 20",
    "addr:postcode":"tn22 5pn",
    "addr:street":"The Oaks",
    "iso:country":"GB",
    "sg:address":"Unit 20 The Oaks, Framfield",
    "sg:city":"Uckfield",
    "sg:classifiers":[
        {
            "category":"Shopping",
            "subcategory":"Stationery & Office Supplies",
            "type":"Retail Goods"
        },
        {
            "category":"Professional",
            "type":"Services"
        },
        {
            "category":"Professional",
            "subcategory":"Printing & Photocopies",
            "type":"Services"
        }
    ],
    "sg:phone":"+44 1825 890082",
    "sg:postcode":"TN22 5PN",
    "sg:province":"East Sussex",
    "sg:tags":[
        "directory",
        "finishing",
        "printer",
        "pub",
        "label"
    ],
    "sg:website":"http://www.tagitltd.com",
    "wof:name":"Tagit Ltd",
    "wof:placetype":"venue"
},
  "geometry": {"coordinates":[0.128748998,50.9636611938],"type":"Point"}
}