{
  "type": "Feature",
  "properties": {
    "iso:country":"GB",
    "sg:address":"Keynsham Road, Willsbridge",
    "sg:city":"Bristol",
    "sg:classifiers":[
        {
            "category":"Communications",
            "subcategory":"Film & Video Production",
            "type":"Services"
        }
    ],
    "sg:phone":"+44 117 932 2046",
    "sg:postcode":"BS30 6EL",
    "sg:province":"Gloucestershire",
    "sg:tags":[
        "tv",
        "studio"
    ],
    "wof:name":"Bristol Television & Film Service",
    "wof:placetype":"venue"
},
  "geometry": {"coordinates":[-2.4798591137,51.4310417175],"type":"Point"}
}