{
  "type": "Feature",
  "properties": {
    "addr:full":"Unit 3, Goldicote Business Park, Banbury Road Stratford-upon-avon Warwickshire CV37 7NL",
    "addr:housenumber":"unit 3",
    "addr:postcode":"cv37 7nl",
    "addr:street":"Goldicote Business Park Banbury Road",
    "iso:country":"GB",
    "sg:address":"Unit 3, Goldicote Business Park, Banbury Road",
    "sg:city":"Stratford-upon-avon",
    "sg:classifiers":[
        {
            "category":"Manufacturing",
            "subcategory":"Rubber & Plastics",
            "type":"Manufacturing & Wholesale Goods"
        }
    ],
    "sg:phone":"+44 808 118 1224",
    "sg:postcode":"CV37 7NL",
    "sg:province":"Warwickshire",
    "sg:tags":[
        "product"
    ],
    "wof:name":"Mid Pack",
    "wof:placetype":"venue"
},
  "geometry": {"coordinates":[-1.638469,52.155056],"type":"Point"}
}