{
  "type": "Feature",
  "properties": {
    "addr:full":"Market Square, Pembridge Leominster Herefordshire HR6 9DZ",
    "addr:postcode":"hr6 9dz",
    "addr:street":"Market Square Pembridge",
    "iso:country":"GB",
    "sg:address":"Market Square, Pembridge",
    "sg:city":"Leominster",
    "sg:classifiers":[
        {
            "category":"Bars & Pubs",
            "type":"Food & Drink"
        }
    ],
    "sg:phone":"+44 1544 388427",
    "sg:postcode":"HR6 9DZ",
    "sg:province":"Herefordshire",
    "sg:tags":[
        "pubs",
        "house",
        "inn",
        "public",
        "activity"
    ],
    "wof:name":"New Inn",
    "wof:placetype":"venue"
},
  "geometry": {"coordinates":[-2.894509,52.217983],"type":"Point"}
}