{
  "type": "Feature",
  "properties": {
    "addr:full":"Pool Hill Caernarfon Gwynedd LL55 1NP",
    "addr:postcode":"ll55 1np",
    "addr:street":"Pool Hill",
    "iso:country":"GB",
    "sg:address":"Pool Hill",
    "sg:city":"Caernarfon",
    "sg:classifiers":[
        {
            "category":"Personal",
            "subcategory":"Beauty Salon",
            "type":"Services"
        }
    ],
    "sg:phone":"+44 1286 672999",
    "sg:postcode":"LL55 1NP",
    "sg:province":"Gwynedd",
    "sg:tags":[
        "unisex",
        "hairdresser"
    ],
    "wof:name":"G & G's Studio",
    "wof:placetype":"venue"
},
  "geometry": {"coordinates":[-4.2736940384,53.1398849487],"type":"Point"}
}