{
  "type": "Feature",
  "properties": {
    "addr:full":"110 St Georges Rd Brighton East Sussex BN2 1EA",
    "addr:housenumber":"110",
    "addr:postcode":"bn2 1ea",
    "addr:street":"St Georges Rd",
    "iso:country":"GB",
    "sg:address":"110 St Georges Rd",
    "sg:city":"Brighton",
    "sg:classifiers":[
        {
            "category":"Community Center",
            "type":"Public Place"
        }
    ],
    "sg:phone":"+44 1273 697493",
    "sg:postcode":"BN2 1EA",
    "sg:province":"East Sussex",
    "sg:tags":[
        "centre"
    ],
    "wof:name":"St Anne's Institute",
    "wof:placetype":"venue"
},
  "geometry": {"coordinates":[-0.12407,50.819271],"type":"Point"}
}