{
  "type": "Feature",
  "properties": {
    "iso:country":"GB",
    "sg:address":"188 Chapel Lane, New Longton",
    "sg:city":"Preston",
    "sg:classifiers":[
        {
            "category":"Manufacturing",
            "subcategory":"Metals",
            "type":"Manufacturing & Wholesale Goods"
        },
        {
            "category":"Building & Trades",
            "subcategory":"Construction",
            "type":"Services"
        }
    ],
    "sg:phone":"+44 1772 613540",
    "sg:postcode":"PR4 4AE",
    "sg:province":"Lancashire",
    "sg:tags":[
        "steel",
        "fabricator",
        "builder",
        "erectors"
    ],
    "wof:name":"D R Fabrications",
    "wof:placetype":"venue"
},
  "geometry": {"coordinates":[-2.762441,53.724571],"type":"Point"}
}