{
  "type": "Feature",
  "properties": {
    "addr:full":"Co-operative House, Lindsey Centre, Market Place Gainsborough Lincolnshire DN21 2BT",
    "addr:postcode":"dn21 2bt",
    "addr:street":"Market Place Gainsborough",
    "iso:country":"GB",
    "sg:address":"Co-operative House, Lindsey Centre, Market Place",
    "sg:city":"Gainsborough",
    "sg:classifiers":[
        {
            "category":"Travel",
            "subcategory":"Travel Agent",
            "type":"Entertainment"
        }
    ],
    "sg:phone":"+44 1427 615648",
    "sg:postcode":"DN21 2BT",
    "sg:province":"Lincolnshire",
    "wof:name":"Cooperative Travel",
    "wof:placetype":"venue"
},
  "geometry": {"coordinates":[-0.7727680206,53.3956947327],"type":"Point"}
}