{
  "type": "Feature",
  "properties": {
    "iso:country":"GB",
    "sg:address":"Dental Surgery, 118-120 High St",
    "sg:city":"Birmingham",
    "sg:classifiers":[
        {
            "category":"Health Services",
            "subcategory":"Dentist",
            "type":"Services"
        }
    ],
    "sg:phone":"+44 1675 463305",
    "sg:postcode":"B46 3BJ",
    "sg:province":"Warwickshire",
    "wof:name":"P S Hill",
    "wof:placetype":"venue"
},
  "geometry": {"coordinates":[-1.70599,52.49765],"type":"Point"}
}