{
  "type": "Feature",
  "properties": {
    "addr:full":"60 Kingston Drive Plymouth Devon PL7 2UZ",
    "addr:housenumber":"60",
    "addr:postcode":"pl7 2uz",
    "addr:street":"Kingston Drive",
    "iso:country":"GB",
    "sg:address":"60 Kingston Drive",
    "sg:city":"Plymouth",
    "sg:classifiers":[
        {
            "category":"Arts & Performance",
            "subcategory":"Music",
            "type":"Entertainment"
        }
    ],
    "sg:postcode":"PL7 2UZ",
    "sg:province":"Devon",
    "sg:tags":[
        "mobile",
        "disco"
    ],
    "wof:name":"Martini Roadshow",
    "wof:placetype":"venue"
},
  "geometry": {"coordinates":[-4.035895,50.3913],"type":"Point"}
}