{
  "type": "Feature",
  "properties": {
    "iso:country":"GB",
    "sg:address":"32 Midland Rd",
    "sg:city":"Bedford",
    "sg:classifiers":[
        {
            "category":"Shopping",
            "subcategory":"Clothing, Apparel, & Fashions",
            "type":"Retail Goods"
        }
    ],
    "sg:phone":"+44 1234 360641",
    "sg:postcode":"MK40 1RH",
    "sg:province":"Bedfordshire",
    "sg:tags":[
        "shop"
    ],
    "wof:name":"C & A",
    "wof:placetype":"venue"
},
  "geometry": {"coordinates":[-0.471348,52.136051],"type":"Point"}
}