{
  "type": "Feature",
  "properties": {
    "addr:full":"107 Woodville Road Cardiff Cardiff CF24 4DY",
    "addr:housenumber":"107",
    "addr:postcode":"cf24 4dy",
    "addr:street":"Woodville Road",
    "iso:country":"GB",
    "sg:address":"107 Woodville Road",
    "sg:city":"Cardiff",
    "sg:classifiers":[
        {
            "category":"Fast Food",
            "type":"Food & Drink"
        }
    ],
    "sg:phone":"+44 29 2023 1871",
    "sg:postcode":"CF24 4DY",
    "sg:province":"Cardiff",
    "sg:tags":[
        "away",
        "meal",
        "outlet",
        "take"
    ],
    "wof:name":"Ali's Tandoori",
    "wof:placetype":"venue"
},
  "geometry": {"coordinates":[-3.177432,51.493671],"type":"Point"}
}