{
  "type": "Feature",
  "properties": {
    "addr:full":"10 Corney Road, Chiswick London Greater London W4 2RA",
    "addr:housenumber":"10",
    "addr:postcode":"w4 2ra",
    "addr:street":"Corney Road",
    "iso:country":"GB",
    "sg:address":"10 Corney Road, Chiswick",
    "sg:city":"London",
    "sg:classifiers":[
        {
            "category":"Real Estate",
            "subcategory":"Architect",
            "type":"Services"
        }
    ],
    "sg:postcode":"W4 2RA",
    "sg:province":"Greater London",
    "wof:name":"Robin Rockel Associates",
    "wof:placetype":"venue"
},
  "geometry": {"coordinates":[-0.254776,51.483707],"type":"Point"}
}