{
  "type": "Feature",
  "properties": {
    "addr:full":"Parish Room, Lords Lane, Bradwell Great Yarmouth Norfolk NR31 8NY",
    "addr:postcode":"nr31 8ny",
    "addr:street":"Lords Lane;Yarmouth",
    "iso:country":"GB",
    "sg:address":"Parish Room, Lords Lane, Bradwell",
    "sg:city":"Great Yarmouth",
    "sg:classifiers":[
        {
            "category":"Education",
            "subcategory":"Library",
            "type":"Public Place"
        },
        {
            "category":"Government",
            "subcategory":"Office",
            "type":"Public Place"
        }
    ],
    "sg:phone":"+44 1493 667953",
    "sg:postcode":"NR31 8NY",
    "sg:province":"Norfolk",
    "sg:tags":[
        "book",
        "local"
    ],
    "wof:name":"Norfolk County Council",
    "wof:placetype":"venue"
},
  "geometry": {"coordinates":[1.69363,52.57642],"type":"Point"}
}