{
  "type": "Feature",
  "properties": {
    "addr:full":"84 Chester Road Macclesfield Cheshire SK11 8DL",
    "addr:housenumber":"84",
    "addr:postcode":"sk11 8dl",
    "addr:street":"Chester Road",
    "iso:country":"GB",
    "sg:address":"84 Chester Road",
    "sg:city":"Macclesfield",
    "sg:classifiers":[
        {
            "category":"Government",
            "subcategory":"Customs House",
            "type":"Public Place"
        }
    ],
    "sg:postcode":"SK11 8DL",
    "sg:province":"Cheshire",
    "sg:tags":[
        "clearance"
    ],
    "wof:name":"Macclesfield Antiques",
    "wof:placetype":"venue"
},
  "geometry": {"coordinates":[-2.1363689899,53.2600822449],"type":"Point"}
}