{
  "type": "Feature",
  "properties": {
    "addr:full":"542 Millbrook Road West Southampton Hampshire SO15 0LN",
    "addr:housenumber":"542",
    "addr:postcode":"so15 0ln",
    "addr:street":"Millbrook Road West",
    "iso:country":"GB",
    "sg:address":"542 Millbrook Road West",
    "sg:city":"Southampton",
    "sg:classifiers":[
        {
            "category":"Building & Trades",
            "subcategory":"Plumbing",
            "type":"Services"
        }
    ],
    "sg:phone":"+44 23 8077 4499",
    "sg:postcode":"SO15 0LN",
    "sg:province":"Hampshire",
    "sg:tags":[
        "merchant",
        "plumbers'"
    ],
    "wof:name":"Plumbase",
    "wof:placetype":"venue"
},
  "geometry": {"coordinates":[-1.451939,50.914742],"type":"Point"}
}