{
  "type": "Feature",
  "properties": {
    "addr:full":"Park House Works, Bacon Lane Sheffield South Yorkshire S9 3NH",
    "addr:postcode":"s9 3nh",
    "addr:street":"Bacon Lane",
    "iso:country":"GB",
    "sg:address":"Park House Works, Bacon Lane",
    "sg:city":"Sheffield",
    "sg:classifiers":[
        {
            "category":"Manufacturing",
            "subcategory":"Metals",
            "type":"Manufacturing & Wholesale Goods"
        },
        {
            "category":"Real Estate",
            "subcategory":"Real Estate Operator",
            "type":"Services"
        }
    ],
    "sg:phone":"+44 114 275 5199",
    "sg:postcode":"S9 3NH",
    "sg:province":"South Yorkshire",
    "sg:tags":[
        "steel",
        "stainless",
        "stockholder"
    ],
    "sg:website":"http://www.nationwidegroup.co.uk",
    "wof:name":"Nationwide Stainless Ltd",
    "wof:placetype":"venue"
},
  "geometry": {"coordinates":[-1.4299889803,53.3953285217],"type":"Point"}
}