{
  "type": "Feature",
  "properties": {
    "addr:full":"Microtech Ho, Old Wareham Rd Poole Dorset BH12 4QR",
    "addr:postcode":"bh12 4qr",
    "addr:street":"Old Wareham Rd",
    "iso:country":"GB",
    "sg:address":"Microtech Ho, Old Wareham Rd",
    "sg:city":"Poole",
    "sg:classifiers":[
        {
            "category":"Professional",
            "subcategory":"Computer Services",
            "type":"Services"
        }
    ],
    "sg:phone":"+44 1202 383383",
    "sg:postcode":"BH12 4QR",
    "sg:province":"Dorset",
    "sg:tags":[
        "system",
        "software"
    ],
    "wof:name":"Small Business Computer Systems",
    "wof:placetype":"venue"
},
  "geometry": {"coordinates":[-1.948139,50.742634],"type":"Point"}
}