{
  "type": "Feature",
  "properties": {
    "iso:country":"GB",
    "sg:address":"War Memorial Ground",
    "sg:city":"Winscombe",
    "sg:classifiers":[
        {
            "category":"Arena",
            "subcategory":"Sports Club",
            "type":"Entertainment"
        }
    ],
    "sg:phone":"+44 1934 842720",
    "sg:postcode":"BS25 1AP",
    "sg:province":"Somerset",
    "wof:name":"Winscombe Cricket Club",
    "wof:placetype":"venue"
},
  "geometry": {"coordinates":[-2.831329,51.313171],"type":"Point"}
}