{
  "type": "Feature",
  "properties": {
    "iso:country":"GB",
    "sg:address":"Magee St",
    "sg:city":"Northampton",
    "sg:classifiers":[
        {
            "category":"Professional",
            "subcategory":"Engineering",
            "type":"Services"
        }
    ],
    "sg:phone":"+44 1604 635485",
    "sg:postcode":"NN1 4JT",
    "sg:province":"Northamptonshire",
    "sg:tags":[
        "engineer"
    ],
    "wof:name":"Fs Day Ltd",
    "wof:placetype":"venue"
},
  "geometry": {"coordinates":[-0.880369,52.246014],"type":"Point"}
}