{
  "type": "Feature",
  "properties": {
    "iso:country":"GB",
    "sg:address":"114 Tudor Walk, North Watford",
    "sg:city":"Watford",
    "sg:classifiers":[
        {
            "category":"Professional",
            "subcategory":"Engineering",
            "type":"Services"
        }
    ],
    "sg:postcode":"WD24 7PA",
    "sg:province":"Hertfordshire",
    "sg:tags":[
        "contractor",
        "electrical",
        "engineer"
    ],
    "wof:name":"J A D Electrical Services",
    "wof:placetype":"venue"
},
  "geometry": {"coordinates":[-0.3831450045,51.6778526306],"type":"Point"}
}