{
  "type": "Feature",
  "properties": {
    "addr:full":"20 The Street, Hulavington Chippenham Gloucestershire SN14 6DU",
    "addr:housenumber":"20",
    "addr:postcode":"sn14 6du",
    "addr:street":"The Street Hulavington",
    "iso:country":"GB",
    "sg:address":"20 The Street, Hulavington",
    "sg:city":"Chippenham",
    "sg:classifiers":[
        {
            "category":"Professional",
            "type":"Services"
        }
    ],
    "sg:phone":"+44 1666 838111",
    "sg:postcode":"SN14 6DU",
    "sg:province":"Gloucestershire",
    "sg:tags":[
        "control",
        "system"
    ],
    "wof:name":"Dundas Systems Ltd.",
    "wof:placetype":"venue"
},
  "geometry": {"coordinates":[-2.152326,51.537682],"type":"Point"}
}