{
  "type": "Feature",
  "properties": {
    "addr:full":"156 Eilsa Rd Coatbridge North Lanarkshire ML5 5HZ",
    "addr:housenumber":"156",
    "addr:postcode":"ml5 5hz",
    "addr:street":"Eilsa Rd",
    "iso:country":"GB",
    "sg:address":"156 Eilsa Rd",
    "sg:city":"Coatbridge",
    "sg:classifiers":[
        {
            "category":"Health Services",
            "subcategory":"Nursing And Care Facility",
            "type":"Services"
        }
    ],
    "sg:phone":"+44 1236 440270",
    "sg:postcode":"ML5 5HZ",
    "sg:province":"North Lanarkshire",
    "sg:tags":[
        "home"
    ],
    "wof:name":"Ferrden Care",
    "wof:placetype":"venue"
},
  "geometry": {"coordinates":[-4.0320501328,55.8494796753],"type":"Point"}
}