{
  "type": "Feature",
  "properties": {
    "iso:country":"GB",
    "sg:address":"Spital Rd, Bromborough",
    "sg:city":"Wirral",
    "sg:classifiers":[
        {
            "category":"Community Center",
            "type":"Public Place"
        }
    ],
    "sg:phone":"+44 151 334 9851",
    "sg:postcode":"CH62 2BJ",
    "sg:province":"Cheshire",
    "sg:tags":[
        "nursery",
        "centre"
    ],
    "wof:name":"Dibbinsdale Nature Reserve",
    "wof:placetype":"venue"
},
  "geometry": {"coordinates":[-2.978035,53.334751],"type":"Point"}
}