{
  "type": "Feature",
  "properties": {
    "iso:country":"GB",
    "sg:address":"11 Rother Court, Parkgate",
    "sg:city":"Rotherham",
    "sg:classifiers":[
        {
            "category":"Wholesale",
            "subcategory":"Electrical",
            "type":"Manufacturing & Wholesale Goods"
        },
        {
            "category":"Shopping",
            "subcategory":"Computers & Home Electronics",
            "type":"Retail Goods"
        }
    ],
    "sg:phone":"+44 1709 710777",
    "sg:postcode":"S62 6DR",
    "sg:province":"South Yorkshire",
    "sg:tags":[
        "wholesaler"
    ],
    "wof:name":"Edmundson Electrical Ltd.",
    "wof:placetype":"venue"
},
  "geometry": {"coordinates":[-1.348035,53.449711],"type":"Point"}
}