{
  "type": "Feature",
  "properties": {
    "addr:full":"St Josephs Place Devizes Wiltshire SN10 1DD",
    "addr:postcode":"sn10 1dd",
    "addr:street":"Josephs Place",
    "iso:country":"GB",
    "sg:address":"St Josephs Place",
    "sg:city":"Devizes",
    "sg:classifiers":[
        {
            "category":"Education",
            "subcategory":"Special Training",
            "type":"Public Place"
        }
    ],
    "sg:phone":"+44 1380 726366",
    "sg:postcode":"SN10 1DD",
    "sg:province":"Wiltshire",
    "sg:tags":[
        "product",
        "centre"
    ],
    "wof:name":"Wiltshire Early Years Assessment Centre Ltd.",
    "wof:placetype":"venue"
},
  "geometry": {"coordinates":[-2.001953,51.353737],"type":"Point"}
}