{
  "type": "Feature",
  "properties": {
    "iso:country":"GB",
    "sg:address":"6 Essex Street",
    "sg:city":"Bradford",
    "sg:classifiers":[
        {
            "category":"Shopping",
            "type":"Retail Goods"
        }
    ],
    "sg:phone":"+44 1274 200008",
    "sg:postcode":"BD4 7PG",
    "sg:province":"West Yorkshire",
    "sg:tags":[
        "part",
        "accessory"
    ],
    "wof:name":"Carnation Salvage",
    "wof:placetype":"venue"
},
  "geometry": {"coordinates":[-1.740056,53.787968],"type":"Point"}
}