{
  "type": "Feature",
  "properties": {
    "addr:full":"13 Lloyd Drive, Greasby Wirral Merseyside CH49 1RG",
    "addr:housenumber":"13",
    "addr:postcode":"ch49 1rg",
    "addr:street":"Lloyd Drive",
    "iso:country":"GB",
    "sg:address":"13 Lloyd Drive, Greasby",
    "sg:city":"Wirral",
    "sg:classifiers":[
        {
            "category":"Professional",
            "subcategory":"Detective & Security Services",
            "type":"Services"
        }
    ],
    "sg:postcode":"CH49 1RG",
    "sg:province":"Merseyside",
    "wof:name":"Owen,Paul,",
    "wof:placetype":"venue"
},
  "geometry": {"coordinates":[-3.116193,53.375687],"type":"Point"}
}