{
  "type": "Feature",
  "properties": {
    "iso:country":"GB",
    "sg:address":"100 Montagu St",
    "sg:city":"Kettering",
    "sg:classifiers":[
        {
            "category":"Autos & Motor Vehicles",
            "subcategory":"Automobile Sales",
            "type":"Retail Goods"
        }
    ],
    "sg:phone":"+44 1536 482890",
    "sg:postcode":"NN16 8RZ",
    "sg:province":"Northamptonshire",
    "sg:tags":[
        "car",
        "specialist",
        "sales",
        "classic"
    ],
    "wof:name":"Seagrave",
    "wof:placetype":"venue"
},
  "geometry": {"coordinates":[-0.7198470235,52.4022064209],"type":"Point"}
}