{
  "type": "Feature",
  "properties": {
    "addr:full":"Unit F2, Cross Lane, Hornsey Hornsey Greater London N8 7SA",
    "addr:housenumber":"f2",
    "addr:postcode":"n8 7sa",
    "addr:street":"Cross Lane",
    "iso:country":"GB",
    "sg:address":"Unit F2, Cross Lane, Hornsey",
    "sg:city":"Hornsey",
    "sg:classifiers":[
        {
            "category":"Manufacturing",
            "subcategory":"Building Materials",
            "type":"Manufacturing & Wholesale Goods"
        }
    ],
    "sg:phone":"+44 20 8340 1857",
    "sg:postcode":"N8 7SA",
    "sg:province":"Greater London",
    "sg:tags":[
        "mnfr",
        "maker",
        "cabinet"
    ],
    "wof:name":"Joe Clarke",
    "wof:placetype":"venue"
},
  "geometry": {"coordinates":[-0.1159690022,51.5878334045],"type":"Point"}
}