{
  "type": "Feature",
  "properties": {
    "iso:country":"GB",
    "sg:address":"129 Pitmore Road",
    "sg:city":"Eastleigh",
    "sg:classifiers":[
        {
            "category":"Building & Trades",
            "subcategory":"Plumbing",
            "type":"Services"
        }
    ],
    "sg:postcode":"SO50 4LS",
    "sg:province":"Hampshire",
    "sg:tags":[
        "heating"
    ],
    "wof:name":"Barry D'Arcy-Burt",
    "wof:placetype":"venue"
},
  "geometry": {"coordinates":[-1.350131,50.993382],"type":"Point"}
}