{
  "type": "Feature",
  "properties": {
    "addr:full":"Lisle Avenue Kidderminster Staffordshire DY11 7DE",
    "addr:postcode":"dy11 7de",
    "addr:street":"Lisle Avenue",
    "iso:country":"GB",
    "sg:address":"Lisle Avenue",
    "sg:city":"Kidderminster",
    "sg:classifiers":[
        {
            "category":"Wholesale",
            "subcategory":"Scrap",
            "type":"Manufacturing & Wholesale Goods"
        }
    ],
    "sg:phone":"+44 1562 755929",
    "sg:postcode":"DY11 7DE",
    "sg:province":"Staffordshire",
    "sg:tags":[
        "breaker",
        "dismantlers"
    ],
    "wof:name":"Kidderminster Car Dismantlers",
    "wof:placetype":"venue"
},
  "geometry": {"coordinates":[-2.254882,52.37307],"type":"Point"}
}