{
  "type": "Feature",
  "properties": {
    "addr:full":"14 The Green Rowland's Castle Hampshire PO9 6BN",
    "addr:housenumber":"14",
    "addr:postcode":"po9 6bn",
    "addr:street":"The Green Rowland'S",
    "iso:country":"GB",
    "sg:address":"14 The Green",
    "sg:city":"Rowland's Castle",
    "sg:classifiers":[
        {
            "category":"Cafe",
            "type":"Food & Drink"
        }
    ],
    "sg:postcode":"PO9 6BN",
    "sg:province":"Hampshire",
    "sg:tags":[
        "tea",
        "room"
    ],
    "wof:name":"The Coffee Pot",
    "wof:placetype":"venue"
},
  "geometry": {"coordinates":[-0.966633,50.888451],"type":"Point"}
}