{
  "type": "Feature",
  "properties": {
    "iso:country":"GB",
    "sg:address":"19 Wallmans Lane, Swavesey",
    "sg:city":"Cambridge",
    "sg:classifiers":[
        {
            "category":"Building & Trades",
            "subcategory":"Pest Control",
            "type":"Services"
        }
    ],
    "sg:phone":"+44 1954 230708",
    "sg:postcode":"CB4 5QY",
    "sg:province":"Cambridgeshire",
    "sg:tags":[
        "vermin"
    ],
    "wof:name":"D R E Pest Control",
    "wof:placetype":"venue"
},
  "geometry": {"coordinates":[-0.003137,52.300983],"type":"Point"}
}