{
  "type": "Feature",
  "properties": {
    "addr:full":"26 Wesley Street Southport Lancashire PR8 1BN",
    "addr:housenumber":"26",
    "addr:postcode":"pr8 1bn",
    "addr:street":"Wesley Street",
    "iso:country":"GB",
    "sg:address":"26 Wesley Street",
    "sg:city":"Southport",
    "sg:classifiers":[
        {
            "category":"Shopping",
            "subcategory":"Clothing, Apparel, & Fashions",
            "type":"Retail Goods"
        }
    ],
    "sg:phone":"+44 1704 531950",
    "sg:postcode":"PR8 1BN",
    "sg:province":"Lancashire",
    "sg:tags":[
        "shop"
    ],
    "wof:name":"Grade 1 Seconds",
    "wof:placetype":"venue"
},
  "geometry": {"coordinates":[-3.003399,53.645721],"type":"Point"}
}