{
  "type": "Feature",
  "properties": {
    "iso:country":"GB",
    "sg:address":"74-78 Katesgrove Lane",
    "sg:city":"Reading",
    "sg:classifiers":[
        {
            "category":"Communications",
            "subcategory":"Film & Video Production",
            "type":"Services"
        }
    ],
    "sg:phone":"+44 118 958 8889",
    "sg:postcode":"RG1 2ND",
    "sg:province":"Berkshire",
    "sg:tags":[
        "recording",
        "studio"
    ],
    "wof:name":"Alleycat Club Ltd.",
    "wof:placetype":"venue"
},
  "geometry": {"coordinates":[-0.973565,51.450527],"type":"Point"}
}