{
  "type": "Feature",
  "properties": {
    "iso:country":"GB",
    "sg:address":"87 Maple Road",
    "sg:city":"Surbiton",
    "sg:classifiers":[
        {
            "category":"Bars & Pubs",
            "type":"Food & Drink"
        },
        {
            "category":"Community Center",
            "subcategory":"Social",
            "type":"Public Place"
        }
    ],
    "sg:phone":"+44 20 8399 5029",
    "sg:postcode":"KT6 4AW",
    "sg:province":"Surrey",
    "sg:tags":[
        "pubs",
        "house",
        "inn",
        "activity"
    ],
    "wof:name":"The Antelope",
    "wof:placetype":"venue"
},
  "geometry": {"coordinates":[-0.307736,51.395145],"type":"Point"}
}