{
  "type": "Feature",
  "properties": {
    "addr:full":"11 Embleford Crescent, Moretonhampstead Newton Abbot Devon TQ13 8LW",
    "addr:housenumber":"11",
    "addr:postcode":"tq13 8lw",
    "addr:street":"Embleford Crescent",
    "iso:country":"GB",
    "sg:address":"11 Embleford Crescent, Moretonhampstead",
    "sg:city":"Newton Abbot",
    "sg:classifiers":[
        {
            "category":"Retail",
            "subcategory":"Auto Repair",
            "type":"Services"
        }
    ],
    "sg:phone":"+44 1647 252344",
    "sg:postcode":"TQ13 8LW",
    "sg:province":"Devon",
    "sg:tags":[
        "car",
        "specialist",
        "customizing"
    ],
    "wof:name":"Mobile Tyre Service",
    "wof:placetype":"venue"
},
  "geometry": {"coordinates":[-3.7668049335,50.6634063721],"type":"Point"}
}