{
  "type": "Feature",
  "properties": {
    "addr:full":"186 Ravenswood Road, Arnold Nottingham Nottinghamshire NG5 7FR",
    "addr:housenumber":"186",
    "addr:postcode":"ng5 7fr",
    "addr:street":"Ravenswood Road",
    "iso:country":"GB",
    "sg:address":"186 Ravenswood Road, Arnold",
    "sg:city":"Nottingham",
    "sg:classifiers":[
        {
            "category":"Home & Garden",
            "subcategory":"Household Appliances",
            "type":"Retail Goods"
        }
    ],
    "sg:postcode":"NG5 7FR",
    "sg:province":"Nottinghamshire",
    "sg:tags":[
        "electrical"
    ],
    "wof:name":"John Love",
    "wof:placetype":"venue"
},
  "geometry": {"coordinates":[-1.1206170321,53.0057868958],"type":"Point"}
}