{
  "type": "Feature",
  "properties": {
    "addr:full":"25 Orchard Link, West Orchard Shopping Centre Coventry West Midlands CV1 1QS",
    "addr:housenumber":"25",
    "addr:postcode":"cv1 1qs",
    "addr:street":"Orchard Link West Orchard Shopping Centre",
    "iso:country":"GB",
    "sg:address":"25 Orchard Link, West Orchard Shopping Centre",
    "sg:city":"Coventry",
    "sg:classifiers":[
        {
            "category":"Shopping",
            "subcategory":"Clothing, Apparel, & Fashions",
            "type":"Retail Goods"
        }
    ],
    "sg:phone":"+44 24 7663 4260",
    "sg:postcode":"CV1 1QS",
    "sg:province":"West Midlands",
    "sg:tags":[
        "ladieswear"
    ],
    "wof:name":"Select",
    "wof:placetype":"venue"
},
  "geometry": {"coordinates":[-1.5121599436,52.4092102051],"type":"Point"}
}