{
  "type": "Feature",
  "properties": {
    "iso:country":"GB",
    "sg:address":"16 North Terrace, Mildenhall",
    "sg:city":"Bury St Edmunds",
    "sg:classifiers":[
        {
            "category":"Retail",
            "subcategory":"Funeral Services",
            "type":"Services"
        }
    ],
    "sg:phone":"+44 1638 713201",
    "sg:postcode":"IP28 7AA",
    "sg:province":"Cambridgeshire",
    "sg:tags":[
        "director"
    ],
    "wof:name":"G R Peachey & Sons",
    "wof:placetype":"venue"
},
  "geometry": {"coordinates":[0.511084,52.345863],"type":"Point"}
}