{
  "type": "Feature",
  "properties": {
    "iso:country":"GB",
    "sg:address":"Mountbatten House, Stonehouse Green",
    "sg:city":"Congleton",
    "sg:classifiers":[
        {
            "category":"Retail",
            "subcategory":"Funeral Services",
            "type":"Services"
        }
    ],
    "sg:phone":"+44 1260 298829",
    "sg:postcode":"CW12 1DF",
    "sg:province":"Cheshire",
    "sg:tags":[
        "director"
    ],
    "wof:name":"John Garside & Son",
    "wof:placetype":"venue"
},
  "geometry": {"coordinates":[-2.211919,53.164673],"type":"Point"}
}