{
  "type": "Feature",
  "properties": {
    "addr:full":"Stanley Road, Skewen Neath Neath Port Talbot SA10 6LP",
    "addr:postcode":"sa10 6lp",
    "addr:street":"Stanley Road",
    "iso:country":"GB",
    "sg:address":"Stanley Road, Skewen",
    "sg:city":"Neath",
    "sg:classifiers":[
        {
            "category":"Education",
            "subcategory":"School",
            "type":"Public Place"
        }
    ],
    "sg:phone":"+44 1792 813508",
    "sg:postcode":"SA10 6LP",
    "sg:province":"Neath Port Talbot",
    "sg:tags":[
        "local",
        "authority"
    ],
    "wof:name":"Neath & Port Talbot Borough Council",
    "wof:placetype":"venue"
},
  "geometry": {"coordinates":[-3.844704,51.660599],"type":"Point"}
}