{
  "type": "Feature",
  "properties": {
    "addr:full":"302 Regent Street London Greater London W1B 3AS",
    "addr:housenumber":"302",
    "addr:postcode":"w1b 3as",
    "addr:street":"Regent Street",
    "iso:country":"GB",
    "sg:address":"302 Regent Street",
    "sg:city":"London",
    "sg:classifiers":[
        {
            "category":"Shopping",
            "subcategory":"Pharmacy",
            "type":"Retail Goods"
        }
    ],
    "sg:phone":"+44 20 7637 9418",
    "sg:postcode":"W1B 3AS",
    "sg:province":"Greater London",
    "sg:tags":[
        "pharmacist",
        "chemist"
    ],
    "wof:name":"Boots the Chemist",
    "wof:placetype":"venue"
},
  "geometry": {"coordinates":[-0.142385,51.516544],"type":"Point"}
}