{
  "type": "Feature",
  "properties": {
    "addr:full":"13b Victoria Rd, Taverham Norwich Norfolk NR8 6NU",
    "addr:housenumber":"13b",
    "addr:postcode":"nr8 6nu",
    "addr:street":"Victoria Rd;Norwich Norfolk",
    "iso:country":"GB",
    "sg:address":"13b Victoria Rd, Taverham",
    "sg:city":"Norwich",
    "sg:classifiers":[
        {
            "category":"Shopping",
            "subcategory":"Baby Store",
            "type":"Retail Goods"
        }
    ],
    "sg:postcode":"NR8 6NU",
    "sg:province":"Norfolk",
    "sg:tags":[
        "babywear",
        "childrens"
    ],
    "wof:name":"Thompson,D,",
    "wof:placetype":"venue"
},
  "geometry": {"coordinates":[1.2013269663,52.6806221008],"type":"Point"}
}