{
  "type": "Feature",
  "properties": {
    "addr:full":"Ladywell Close Burton-on-trent Derbyshire DE13 0FS",
    "addr:postcode":"de13 0fs",
    "addr:street":"Ladywell Close",
    "iso:country":"GB",
    "sg:address":"Ladywell Close",
    "sg:city":"Burton-on-trent",
    "sg:classifiers":[
        {
            "category":"Health Services",
            "subcategory":"Doctor",
            "type":"Services"
        }
    ],
    "sg:phone":"+44 1283 537450",
    "sg:postcode":"DE13 0FS",
    "sg:province":"Derbyshire",
    "sg:tags":[
        "practitioners"
    ],
    "wof:name":"Stretton Medical Centre",
    "wof:placetype":"venue"
},
  "geometry": {"coordinates":[-1.6298810244,52.8316268921],"type":"Point"}
}