{
  "type": "Feature",
  "properties": {
    "addr:full":"23 Waudby Garth Rd, Keyingham Hull East Riding of Yorkshire HU12 9TN",
    "addr:housenumber":"23",
    "addr:postcode":"hu12 9tn",
    "addr:street":"Waudby Garth Rd",
    "iso:country":"GB",
    "sg:address":"23 Waudby Garth Rd, Keyingham",
    "sg:city":"Hull",
    "sg:classifiers":[
        {
            "category":"Utilities",
            "subcategory":"Natural Gas",
            "type":"Services"
        }
    ],
    "sg:phone":"+44 1964 622506",
    "sg:postcode":"HU12 9TN",
    "sg:province":"East Riding of Yorkshire",
    "sg:tags":[
        "control",
        "energy",
        "management",
        "system"
    ],
    "wof:name":"Brian Sykes",
    "wof:placetype":"venue"
},
  "geometry": {"coordinates":[-0.108603999,53.7114105225],"type":"Point"}
}