{
  "type": "Feature",
  "properties": {
    "iso:country":"GB",
    "sg:address":"Tresevern Farm, Tresevern",
    "sg:city":"Truro",
    "sg:classifiers":[
        {
            "category":"Farming",
            "subcategory":"Livestock Farm",
            "type":"Manufacturing & Wholesale Goods"
        }
    ],
    "sg:postcode":"TR3 7AT",
    "sg:province":"Cornwall",
    "sg:tags":[
        "others"
    ],
    "wof:name":"P J Williams",
    "wof:placetype":"venue"
},
  "geometry": {"coordinates":[-5.2045722008,50.1918144226],"type":"Point"}
}