{
  "type": "Feature",
  "properties": {
    "iso:country":"GB",
    "sg:address":"8 Carnsew Close, Mabe Burnthouse",
    "sg:city":"Penryn",
    "sg:classifiers":[
        {
            "category":"Building & Trades",
            "subcategory":"Construction",
            "type":"Services"
        }
    ],
    "sg:postcode":"TR10 9HE",
    "sg:province":"Cornwall",
    "sg:tags":[
        "roofing"
    ],
    "wof:name":"Stephen Gary Uphill",
    "wof:placetype":"venue"
},
  "geometry": {"coordinates":[-5.133042,50.166534],"type":"Point"}
}