{
  "type": "Feature",
  "properties": {
    "addr:full":"15 The Grn, Lund Driffield East Riding of Yorkshire YO25 9TE",
    "addr:housenumber":"15",
    "addr:postcode":"yo25 9te",
    "addr:street":"The Grn",
    "iso:country":"GB",
    "sg:address":"15 The Grn, Lund",
    "sg:city":"Driffield",
    "sg:classifiers":[
        {
            "category":"Farming",
            "subcategory":"Farm",
            "type":"Manufacturing & Wholesale Goods"
        }
    ],
    "sg:phone":"+44 1377 217240",
    "sg:postcode":"YO25 9TE",
    "sg:province":"East Riding of Yorkshire",
    "sg:tags":[
        "mixed",
        "crop"
    ],
    "wof:name":"Robert S Hall",
    "wof:placetype":"venue"
},
  "geometry": {"coordinates":[-0.5294589996,53.9193000793],"type":"Point"}
}