{
  "type": "Feature",
  "properties": {
    "addr:full":"66 Aynsley Gardens Church, Langley Harlow Essex CM17 9PD",
    "addr:housenumber":"66",
    "addr:postcode":"cm17 9pd",
    "addr:street":"Aynsley Gardens",
    "iso:country":"GB",
    "sg:address":"66 Aynsley Gardens Church, Langley",
    "sg:city":"Harlow",
    "sg:classifiers":[
        {
            "category":"Home & Garden",
            "subcategory":"Household Appliances",
            "type":"Retail Goods"
        }
    ],
    "sg:postcode":"CM17 9PD",
    "sg:province":"Essex",
    "sg:tags":[
        "electrical"
    ],
    "wof:name":"Wash 'N' Tumble",
    "wof:placetype":"venue"
},
  "geometry": {"coordinates":[0.1357550025,51.7666816711],"type":"Point"}
}