{
  "type": "Feature",
  "properties": {
    "addr:full":"31 Inhedge House, Wolverhampton Street Dudley West Midlands DY1 1DB",
    "addr:housenumber":"31;house",
    "addr:postcode":"dy1 1db",
    "addr:street":"Wolverhampton Street",
    "iso:country":"GB",
    "sg:address":"31 Inhedge House, Wolverhampton Street",
    "sg:city":"Dudley",
    "sg:classifiers":[
        {
            "category":"Professional",
            "subcategory":"Lawyer & Legal Services",
            "type":"Services"
        }
    ],
    "sg:phone":"+44 1384 342100",
    "sg:postcode":"DY1 1DB",
    "sg:province":"West Midlands",
    "sg:tags":[
        "solicitor"
    ],
    "wof:name":"Higgs & Sons",
    "wof:placetype":"venue"
},
  "geometry": {"coordinates":[-2.0880000591,52.5107383728],"type":"Point"}
}