{
  "type": "Feature",
  "properties": {
    "addr:full":"Parkhouse East Indstl Est, Chesterton Newcastle Staffordshire ST5 7RB",
    "addr:postcode":"st5 7rb",
    "addr:street":"Indstl Est",
    "iso:country":"GB",
    "sg:address":"Parkhouse East Indstl Est, Chesterton",
    "sg:city":"Newcastle",
    "sg:classifiers":[
        {
            "category":"Personal",
            "type":"Services"
        }
    ],
    "sg:phone":"+44 1782 563322",
    "sg:postcode":"ST5 7RB",
    "sg:province":"Staffordshire",
    "sg:tags":[
        "delivery"
    ],
    "wof:name":"A N C Ltd",
    "wof:placetype":"venue"
},
  "geometry": {"coordinates":[-2.250059,53.041046],"type":"Point"}
}