{
  "type": "Feature",
  "properties": {
    "addr:full":"Castle Boulevard Nottingham Nottinghamshire NG7 1FP",
    "addr:postcode":"ng7 1fp",
    "addr:street":"Castle Boulevard",
    "iso:country":"GB",
    "sg:address":"Castle Boulevard",
    "sg:city":"Nottingham",
    "sg:classifiers":[
        {
            "category":"Retail",
            "subcategory":"Car Wash",
            "type":"Services"
        }
    ],
    "sg:phone":"+44 115 950 9307",
    "sg:postcode":"NG7 1FP",
    "sg:province":"Nottinghamshire",
    "sg:tags":[
        "polishing",
        "washing"
    ],
    "wof:name":"I.M.O Car Wash",
    "wof:placetype":"venue"
},
  "geometry": {"coordinates":[-1.1553839445,52.9482002258],"type":"Point"}
}