{
  "type": "Feature",
  "properties": {
    "addr:full":"64 Harpur Street Bedford Bedfordshire MK40 2ST",
    "addr:housenumber":"64",
    "addr:postcode":"mk40 2st",
    "addr:street":"Harpur Street",
    "iso:country":"GB",
    "sg:address":"64 Harpur Street",
    "sg:city":"Bedford",
    "sg:classifiers":[
        {
            "category":"Shopping",
            "subcategory":"Computers & Home Electronics",
            "type":"Retail Goods"
        },
        {
            "category":"Professional",
            "subcategory":"Computer Services",
            "type":"Services"
        }
    ],
    "sg:postcode":"MK40 2ST",
    "sg:province":"Bedfordshire",
    "sg:tags":[
        "equipment",
        "video",
        "cctv",
        "system",
        "software"
    ],
    "wof:name":"Omnis Solutions Ltd",
    "wof:placetype":"venue"
},
  "geometry": {"coordinates":[-0.4688729942,52.1398468018],"type":"Point"}
}