{
  "type": "Feature",
  "properties": {
    "iso:country":"GB",
    "sg:address":"Heston Park House, New Heston Road",
    "sg:city":"Hounslow",
    "sg:classifiers":[
        {
            "category":"Organizations",
            "subcategory":"Non-profit Organization",
            "type":"Services"
        }
    ],
    "sg:phone":"+44 20 8814 2929",
    "sg:postcode":"TW5 0LJ",
    "sg:province":"Greater London",
    "sg:tags":[
        "alarm",
        "system"
    ],
    "wof:name":"Protection One (U K) Plc",
    "wof:placetype":"venue"
},
  "geometry": {"coordinates":[-0.374689,51.48547],"type":"Point"}
}