{
  "type": "Feature",
  "properties": {
    "iso:country":"GB",
    "sg:address":"248-250 Bacup Road, Cloughfold",
    "sg:city":"Rossendale",
    "sg:classifiers":[
        {
            "category":"Manufacturing",
            "subcategory":"Textiles",
            "type":"Manufacturing & Wholesale Goods"
        }
    ],
    "sg:phone":"+44 1706 228208",
    "sg:postcode":"BB4 7LG",
    "sg:province":"Lancashire",
    "sg:tags":[
        "knitwear"
    ],
    "wof:name":"B Booth Textiles",
    "wof:placetype":"venue"
},
  "geometry": {"coordinates":[-2.2697820663,53.6990585327],"type":"Point"}
}