{
  "type": "Feature",
  "properties": {
    "addr:full":"2 Chatsworth St Preston Lancashire PR1 4XY",
    "addr:housenumber":"2",
    "addr:postcode":"pr1 4xy",
    "addr:street":"Chatsworth St",
    "iso:country":"GB",
    "sg:address":"2 Chatsworth St",
    "sg:city":"Preston",
    "sg:classifiers":[
        {
            "category":"Taxi",
            "type":"Transportation"
        }
    ],
    "sg:phone":"+44 1772 491800",
    "sg:postcode":"PR1 4XY",
    "sg:province":"Lancashire",
    "sg:tags":[
        "mini",
        "cab"
    ],
    "wof:name":"Millennium Private Hire",
    "wof:placetype":"venue"
},
  "geometry": {"coordinates":[-2.6771349907,53.7628211975],"type":"Point"}
}