{
  "type": "Feature",
  "properties": {
    "addr:full":"51 Wordsworth Rd Hampton Greater London TW12 1EW",
    "addr:housenumber":"51",
    "addr:postcode":"tw12 1ew",
    "addr:street":"Wordsworth Rd",
    "iso:country":"GB",
    "sg:address":"51 Wordsworth Rd",
    "sg:city":"Hampton",
    "sg:classifiers":[
        {
            "category":"Social Services",
            "subcategory":"Job Training",
            "type":"Services"
        }
    ],
    "sg:phone":"+44 20 8783 1334",
    "sg:postcode":"TW12 1EW",
    "sg:province":"Greater London",
    "sg:tags":[
        "translator",
        "interpreter"
    ],
    "wof:name":"A-z Languages",
    "wof:placetype":"venue"
},
  "geometry": {"coordinates":[-0.3769209981,51.4330329895],"type":"Point"}
}