{
  "type": "Feature",
  "properties": {
    "addr:full":"104 Warrington Road Leigh Lancashire WN7 3EA",
    "addr:housenumber":"104",
    "addr:postcode":"wn7 3ea",
    "addr:street":"Warrington Road Leigh",
    "iso:country":"GB",
    "sg:address":"104 Warrington Road",
    "sg:city":"Leigh",
    "sg:classifiers":[
        {
            "category":"Personal",
            "subcategory":"Beauty Salon",
            "type":"Services"
        }
    ],
    "sg:phone":"+44 1942 601021",
    "sg:postcode":"WN7 3EA",
    "sg:province":"Lancashire",
    "sg:tags":[
        "unisex",
        "hairdresser"
    ],
    "wof:name":"Jan's Hair Design",
    "wof:placetype":"venue"
},
  "geometry": {"coordinates":[-2.499567,53.489388],"type":"Point"}
}