{
  "type": "Feature",
  "properties": {
    "iso:country":"GB",
    "sg:address":"19 Broadwalk",
    "sg:city":"Crawley",
    "sg:classifiers":[
        {
            "category":"Professional",
            "subcategory":"Employment Agencies",
            "type":"Services"
        }
    ],
    "sg:phone":"+44 1293 547762",
    "sg:postcode":"RH10 1HJ",
    "sg:province":"Surrey",
    "sg:tags":[
        "consultant"
    ],
    "wof:name":"Reed Accountancy",
    "wof:placetype":"venue"
},
  "geometry": {"coordinates":[-0.1847530007,51.1184577942],"type":"Point"}
}