{
  "type": "Feature",
  "properties": {
    "addr:full":"1 Dell Close, Newton Flotman Norwich Norfolk NR15 1RG",
    "addr:housenumber":"1",
    "addr:postcode":"nr15 1rg",
    "addr:street":"Dell Close;Norwich",
    "iso:country":"GB",
    "sg:address":"1 Dell Close, Newton Flotman",
    "sg:city":"Norwich",
    "sg:classifiers":[
        {
            "category":"Wholesale",
            "subcategory":"Office Equipment",
            "type":"Manufacturing & Wholesale Goods"
        }
    ],
    "sg:phone":"+44 1508 471164",
    "sg:postcode":"NR15 1RG",
    "sg:province":"Norfolk",
    "sg:tags":[
        "register",
        "cash",
        "accessory"
    ],
    "wof:name":"Retail Systems Services",
    "wof:placetype":"venue"
},
  "geometry": {"coordinates":[1.2566889524,52.5346603394],"type":"Point"}
}