{
  "type": "Feature",
  "properties": {
    "addr:full":"4/5 Oaktree Gardens Dumbarton Argyll and Bute G82 1EU",
    "addr:housenumber":"4 / 5",
    "addr:postcode":"g82 1eu",
    "addr:street":"Oaktree Gardens",
    "iso:country":"GB",
    "sg:address":"4/5 Oaktree Gardens",
    "sg:city":"Dumbarton",
    "sg:classifiers":[
        {
            "category":"Manufacturing",
            "subcategory":"Petroleum Products",
            "type":"Manufacturing & Wholesale Goods"
        },
        {
            "category":"Building & Trades",
            "subcategory":"Construction",
            "type":"Services"
        }
    ],
    "sg:phone":"+44 1389 734108",
    "sg:postcode":"G82 1EU",
    "sg:province":"Argyll and Bute",
    "sg:tags":[
        "double",
        "glazing",
        "installers"
    ],
    "wof:name":"Premier Double Glazing",
    "wof:placetype":"venue"
},
  "geometry": {"coordinates":[-4.540897,55.938175],"type":"Point"}
}