{
  "type": "Feature",
  "properties": {
    "addr:full":"12 Grange Terrace Edinburgh City of Edinburgh EH9 2LD",
    "addr:housenumber":"12",
    "addr:postcode":"eh9 2ld",
    "addr:street":"Grange Terrace",
    "iso:country":"GB",
    "sg:address":"12 Grange Terrace",
    "sg:city":"Edinburgh",
    "sg:classifiers":[
        {
            "category":"Professional",
            "subcategory":"Business Services",
            "type":"Services"
        }
    ],
    "sg:postcode":"EH9 2LD",
    "sg:province":"City of Edinburgh",
    "sg:tags":[
        "assessment",
        "quality"
    ],
    "wof:name":"Peat Marion Quality Consultant",
    "wof:placetype":"venue"
},
  "geometry": {"coordinates":[-3.188002,55.930229],"type":"Point"}
}