{
  "type": "Feature",
  "properties": {
    "addr:full":"Telford Road, Churchfileds Estate Salisbury Wiltshire SP2 7PH",
    "addr:postcode":"sp2 7ph",
    "addr:street":"Telford Road Churchfileds Estate",
    "iso:country":"GB",
    "sg:address":"Telford Road, Churchfileds Estate",
    "sg:city":"Salisbury",
    "sg:classifiers":[
        {
            "category":"Retail",
            "subcategory":"Auto Rental",
            "type":"Services"
        }
    ],
    "sg:phone":"+44 1722 338644",
    "sg:postcode":"SP2 7PH",
    "sg:province":"Wiltshire",
    "sg:tags":[
        "truck",
        "hire",
        "van"
    ],
    "wof:name":"A V H Truck Rental (South West) Ltd.",
    "wof:placetype":"venue"
},
  "geometry": {"coordinates":[-1.814246,51.068008],"type":"Point"}
}