{
  "type": "Feature",
  "properties": {
    "addr:full":"1 Weston Road Olney Buckinghamshire MK46 5BD",
    "addr:housenumber":"1",
    "addr:postcode":"mk46 5bd",
    "addr:street":"Weston Road",
    "iso:country":"GB",
    "sg:address":"1 Weston Road",
    "sg:city":"Olney",
    "sg:classifiers":[
        {
            "category":"Cinema",
            "subcategory":"Movie Rental",
            "type":"Entertainment"
        }
    ],
    "sg:phone":"+44 1234 711158",
    "sg:postcode":"MK46 5BD",
    "sg:province":"Buckinghamshire",
    "sg:tags":[
        "video",
        "library"
    ],
    "wof:name":"The Only Video Shop",
    "wof:placetype":"venue"
},
  "geometry": {"coordinates":[-0.7034839988,52.1520881653],"type":"Point"}
}