{
  "type": "Feature",
  "properties": {
    "addr:full":"141 Lillie Road London Greater London SW6 7SX",
    "addr:housenumber":"141",
    "addr:postcode":"sw6 7sx",
    "addr:street":"Lillie Road",
    "iso:country":"GB",
    "sg:address":"141 Lillie Road",
    "sg:city":"London",
    "sg:classifiers":[
        {
            "category":"Food & Beverages",
            "subcategory":"Liquor & Beverages",
            "type":"Retail Goods"
        }
    ],
    "sg:phone":"+44 20 7381 3003",
    "sg:postcode":"SW6 7SX",
    "sg:province":"Greater London",
    "sg:tags":[
        "beer",
        "spirit",
        "wines"
    ],
    "wof:name":"A-Z Winemart",
    "wof:placetype":"venue"
},
  "geometry": {"coordinates":[-0.204854995,51.4844017029],"type":"Point"}
}