{
  "type": "Feature",
  "properties": {
    "addr:full":"Evesham Road, Greet Cheltenham Gloucestershire GL54 5BX",
    "addr:postcode":"gl54 5bx",
    "addr:street":"Evesham Road",
    "iso:country":"GB",
    "sg:address":"Evesham Road, Greet",
    "sg:city":"Cheltenham",
    "sg:classifiers":[
        {
            "category":"Home & Garden",
            "subcategory":"Home Furnishings",
            "type":"Retail Goods"
        }
    ],
    "sg:phone":"+44 1242 621177",
    "sg:postcode":"GL54 5BX",
    "sg:province":"Gloucestershire",
    "sg:tags":[
        "furnishers",
        "planner",
        "kitchen"
    ],
    "wof:name":"Redbrook Kitchens",
    "wof:placetype":"venue"
},
  "geometry": {"coordinates":[-1.966341,51.969093],"type":"Point"}
}