{
  "type": "Feature",
  "properties": {
    "addr:full":"2a Trumpington Street Cambridge Cambridgeshire CB2 1QA",
    "addr:housenumber":"2a",
    "addr:postcode":"cb2 1qa",
    "addr:street":"Trumpington Street",
    "iso:country":"GB",
    "sg:address":"2a Trumpington Street",
    "sg:city":"Cambridge",
    "sg:classifiers":[
        {
            "category":"Shopping",
            "subcategory":"Department Store",
            "type":"Retail Goods"
        },
        {
            "category":"Government",
            "subcategory":"Post Office",
            "type":"Public Place"
        }
    ],
    "sg:phone":"+44 1223 359596",
    "sg:postcode":"CB2 1QA",
    "sg:province":"Cambridgeshire",
    "wof:name":"D & J Barot",
    "wof:placetype":"venue"
},
  "geometry": {"coordinates":[0.122014,52.198341],"type":"Point"}
}