{
  "type": "Feature",
  "properties": {
    "addr:full":"16 White Lion Road Amersham Buckinghamshire HP7 9JD",
    "addr:housenumber":"16",
    "addr:postcode":"hp7 9jd",
    "addr:street":"White Lion Road",
    "iso:country":"GB",
    "sg:address":"16 White Lion Road",
    "sg:city":"Amersham",
    "sg:classifiers":[
        {
            "category":"Personal",
            "subcategory":"Beauty Salon",
            "type":"Services"
        },
        {
            "category":"Personal",
            "subcategory":"Barber",
            "type":"Services"
        }
    ],
    "sg:phone":"+44 1494 765948",
    "sg:postcode":"HP7 9JD",
    "sg:province":"Buckinghamshire",
    "sg:tags":[
        "unisex",
        "hairdresser"
    ],
    "wof:name":"Oasis Hair Studio",
    "wof:placetype":"venue"
},
  "geometry": {"coordinates":[-0.587421,51.672146],"type":"Point"}
}