{
  "type": "Feature",
  "properties": {
    "iso:country":"GB",
    "sg:address":"Stoke Fields Farm, Stoke Road",
    "sg:city":"Hinckley",
    "sg:classifiers":[
        {
            "category":"Farming",
            "subcategory":"Livestock Farm",
            "type":"Manufacturing & Wholesale Goods"
        }
    ],
    "sg:postcode":"LE10 3EA",
    "sg:province":"Leicestershire",
    "sg:tags":[
        "others"
    ],
    "wof:name":"L G Upton",
    "wof:placetype":"venue"
},
  "geometry": {"coordinates":[-1.400317,52.556419],"type":"Point"}
}