{
  "type": "Feature",
  "properties": {
    "iso:country":"GB",
    "sg:address":"187 Hewlett Rd",
    "sg:city":"Cheltenham",
    "sg:classifiers":[
        {
            "category":"Shopping",
            "subcategory":"Books",
            "type":"Retail Goods"
        }
    ],
    "sg:phone":"+44 1242 575943",
    "sg:postcode":"GL52 6UF",
    "sg:province":"Gloucestershire",
    "wof:name":"Goldeneye Maps",
    "wof:placetype":"venue"
},
  "geometry": {"coordinates":[-2.0588009357,51.9014472961],"type":"Point"}
}