{
  "type": "Feature",
  "properties": {
    "addr:full":"29 Mentone Avenue, Aspley Guise Milton Keynes Bedfordshire MK17 8EQ",
    "addr:housenumber":"29",
    "addr:postcode":"mk17 8eq",
    "addr:street":"Mentone Avenue;Guise",
    "iso:country":"GB",
    "sg:address":"29 Mentone Avenue, Aspley Guise",
    "sg:city":"Milton Keynes",
    "sg:classifiers":[
        {
            "category":"Real Estate",
            "subcategory":"Architect",
            "type":"Services"
        }
    ],
    "sg:phone":"+44 1908 587132",
    "sg:postcode":"MK17 8EQ",
    "sg:province":"Bedfordshire",
    "wof:name":"R Hollowood Ltd.",
    "wof:placetype":"venue"
},
  "geometry": {"coordinates":[-0.6352360249,52.0105934143],"type":"Point"}
}