{
  "type": "Feature",
  "properties": {
    "addr:full":"6 Parkfield Neath Neath Port Talbot SA11 3JN",
    "addr:housenumber":"6",
    "addr:postcode":"sa11 3jn",
    "addr:street":"Parkfield",
    "iso:country":"GB",
    "sg:address":"6 Parkfield",
    "sg:city":"Neath",
    "sg:classifiers":[
        {
            "category":"Building & Trades",
            "subcategory":"Construction",
            "type":"Services"
        }
    ],
    "sg:postcode":"SA11 3JN",
    "sg:province":"Neath Port Talbot",
    "sg:tags":[
        "builder"
    ],
    "wof:name":"David Evans & Sons",
    "wof:placetype":"venue"
},
  "geometry": {"coordinates":[-3.780289,51.667301],"type":"Point"}
}