{
  "type": "Feature",
  "properties": {
    "addr:full":"63 Congreve Rd Worthing West Sussex BN14 8EL",
    "addr:housenumber":"63",
    "addr:postcode":"bn14 8el",
    "addr:street":"Congreve Rd",
    "iso:country":"GB",
    "sg:address":"63 Congreve Rd",
    "sg:city":"Worthing",
    "sg:classifiers":[
        {
            "category":"Professional",
            "subcategory":"Printing & Photocopies",
            "type":"Services"
        }
    ],
    "sg:postcode":"BN14 8EL",
    "sg:province":"West Sussex",
    "sg:tags":[
        "plate",
        "printer",
        "lithographic",
        "maker"
    ],
    "wof:name":"Hanley,Margaret,",
    "wof:placetype":"venue"
},
  "geometry": {"coordinates":[-0.365557,50.822968],"type":"Point"}
}