{
  "type": "Feature",
  "properties": {
    "iso:country":"GB",
    "sg:address":"52 Pillory Street",
    "sg:city":"Nantwich",
    "sg:classifiers":[
        {
            "category":"Shopping",
            "subcategory":"Clothing, Apparel, & Fashions",
            "type":"Retail Goods"
        }
    ],
    "sg:phone":"+44 1270 625455",
    "sg:postcode":"CW5 5BG",
    "sg:province":"Cheshire",
    "sg:tags":[
        "ladieswear"
    ],
    "wof:name":"Morton Marjorie",
    "wof:placetype":"venue"
},
  "geometry": {"coordinates":[-2.5209329128,53.0653419495],"type":"Point"}
}