{
  "type": "Feature",
  "properties": {
    "iso:country":"GB",
    "sg:address":"Bennington House, Long Bennington",
    "sg:city":"Newark",
    "sg:classifiers":[
        {
            "category":"Professional",
            "subcategory":"Lawyer & Legal Services",
            "type":"Services"
        }
    ],
    "sg:phone":"+44 1400 281677",
    "sg:postcode":"NG23 5EH",
    "sg:province":"Lincolnshire",
    "sg:tags":[
        "solicitor"
    ],
    "wof:name":"Jay Bishop & Co.",
    "wof:placetype":"venue"
},
  "geometry": {"coordinates":[-0.758644,52.994484],"type":"Point"}
}