{
  "type": "Feature",
  "properties": {
    "iso:country":"GB",
    "sg:address":"2 Windsor Corner",
    "sg:city":"Peterlee",
    "sg:classifiers":[
        {
            "category":"Military Area",
            "subcategory":"Air Force Base",
            "type":"Public Place"
        }
    ],
    "sg:phone":"+44 191 586 0555",
    "sg:postcode":"SR8 4HR",
    "sg:province":"Durham",
    "sg:tags":[
        "taxi",
        "hire",
        "private"
    ],
    "wof:name":"Chevron Taxis",
    "wof:placetype":"venue"
},
  "geometry": {"coordinates":[-1.308562994,54.7611732483],"type":"Point"}
}