{
  "type": "Feature",
  "properties": {
    "addr:full":"170 Meadow Rise, Brynna Pontyclun Bridgend CF72 9TJ",
    "addr:housenumber":"170",
    "addr:postcode":"cf72 9tj",
    "addr:street":"Meadow Rise Brynna Pontyclun",
    "iso:country":"GB",
    "sg:address":"170 Meadow Rise, Brynna",
    "sg:city":"Pontyclun",
    "sg:classifiers":[
        {
            "category":"Building & Trades",
            "subcategory":"Cleaning & Sanitation",
            "type":"Services"
        }
    ],
    "sg:postcode":"CF72 9TJ",
    "sg:province":"Bridgend",
    "sg:tags":[
        "cleaner",
        "window"
    ],
    "wof:name":"A Cadreman",
    "wof:placetype":"venue"
},
  "geometry": {"coordinates":[-3.450161,51.542034],"type":"Point"}
}