{
  "type": "Feature",
  "properties": {
    "addr:full":"Kirkenel Farm, Ashford Carbonel Ludlow Herefordshire SY8 4DF",
    "addr:housenumber":"ashford carbonel",
    "addr:postcode":"sy8 4df",
    "iso:country":"GB",
    "sg:address":"Kirkenel Farm, Ashford Carbonel",
    "sg:city":"Ludlow",
    "sg:classifiers":[
        {
            "category":"Farming",
            "subcategory":"Livestock Farm",
            "type":"Manufacturing & Wholesale Goods"
        }
    ],
    "sg:postcode":"SY8 4DF",
    "sg:province":"Herefordshire",
    "sg:tags":[
        "others"
    ],
    "wof:name":"J P & G & P Whittal",
    "wof:placetype":"venue"
},
  "geometry": {"coordinates":[-2.700164,52.33448],"type":"Point"}
}