{
  "type": "Feature",
  "properties": {
    "addr:full":"27 Muller Road, Lambeth Central London Greater London SW4 8BZ",
    "addr:housenumber":"27",
    "addr:postcode":"sw4 8bz",
    "addr:street":"Muller Road",
    "iso:country":"GB",
    "sg:address":"27 Muller Road, Lambeth Central",
    "sg:city":"London",
    "sg:classifiers":[
        {
            "category":"Shopping",
            "subcategory":"Stationery & Office Supplies",
            "type":"Retail Goods"
        }
    ],
    "sg:postcode":"SW4 8BZ",
    "sg:province":"Greater London",
    "sg:tags":[
        "printers'"
    ],
    "wof:name":"Adisa-Adesina International Ltd.",
    "wof:placetype":"venue"
},
  "geometry": {"coordinates":[-0.131329,51.4504776001],"type":"Point"}
}