{
  "type": "Feature",
  "properties": {
    "iso:country":"GB",
    "sg:address":"144 Redhill Dr",
    "sg:city":"Castleford",
    "sg:classifiers":[
        {
            "category":"Building & Trades",
            "subcategory":"Construction",
            "type":"Services"
        }
    ],
    "sg:phone":"+44 1977 517980",
    "sg:postcode":"WF10 3HQ",
    "sg:province":"West Yorkshire",
    "sg:tags":[
        "contractor",
        "paving",
        "driveway"
    ],
    "wof:name":"S & T Paving",
    "wof:placetype":"venue"
},
  "geometry": {"coordinates":[-1.3215810061,53.7179145813],"type":"Point"}
}