{
  "type": "Feature",
  "properties": {
    "iso:country":"GB",
    "sg:address":"46 Calverley Road",
    "sg:city":"Birmingham",
    "sg:classifiers":[
        {
            "category":"Building & Trades",
            "subcategory":"Construction",
            "type":"Services"
        }
    ],
    "sg:phone":"+44 121 459 3443",
    "sg:postcode":"B38 8PW",
    "sg:province":"West Midlands",
    "sg:tags":[
        "joinery",
        "joiner",
        "carpenter",
        "carpentry"
    ],
    "wof:name":"Dovetails",
    "wof:placetype":"venue"
},
  "geometry": {"coordinates":[-1.944771,52.399483],"type":"Point"}
}