{
  "type": "Feature",
  "properties": {
    "iso:country":"GB",
    "sg:address":"53a London Rd",
    "sg:city":"Dunstable",
    "sg:classifiers":[
        {
            "category":"Personal",
            "subcategory":"Beauty Salon",
            "type":"Services"
        }
    ],
    "sg:phone":"+44 1582 665444",
    "sg:postcode":"LU6 3DH",
    "sg:province":"Bedfordshire",
    "sg:tags":[
        "unisex",
        "hairdresser"
    ],
    "wof:name":"Stephanies Hair Boutique",
    "wof:placetype":"venue"
},
  "geometry": {"coordinates":[-0.50887,51.877972],"type":"Point"}
}