{
  "type": "Feature",
  "properties": {
    "iso:country":"GB",
    "sg:address":"Arden Ho, Masons Rd",
    "sg:city":"Stratford-upon-avon",
    "sg:classifiers":[
        {
            "category":"Building & Trades",
            "subcategory":"Construction",
            "type":"Services"
        }
    ],
    "sg:postcode":"CV37 9YW",
    "sg:province":"Warwickshire",
    "sg:tags":[
        "management"
    ],
    "wof:name":"A M E C Construction Ltd",
    "wof:placetype":"venue"
},
  "geometry": {"coordinates":[-1.7662190199,52.2209434509],"type":"Point"}
}