{
  "type": "Feature",
  "properties": {
    "addr:full":"2 Rectory La Huddersfield South Yorkshire HD8 9RR",
    "addr:housenumber":"2",
    "addr:postcode":"hd8 9rr",
    "addr:street":"Rectory La Huddersfield South",
    "iso:country":"GB",
    "sg:address":"2 Rectory La",
    "sg:city":"Huddersfield",
    "sg:classifiers":[
        {
            "category":"Retail",
            "subcategory":"Auto Repair",
            "type":"Services"
        }
    ],
    "sg:phone":"+44 1924 840410",
    "sg:postcode":"HD8 9RR",
    "sg:province":"South Yorkshire",
    "sg:tags":[
        "modification",
        "garage"
    ],
    "wof:name":"Beaver,J K,",
    "wof:placetype":"venue"
},
  "geometry": {"coordinates":[-1.628712,53.617523],"type":"Point"}
}