{
  "type": "Feature",
  "properties": {
    "iso:country":"GB",
    "sg:address":"14-16 Portland Pl, Huddersfield Rd",
    "sg:city":"Halifax",
    "sg:classifiers":[
        {
            "category":"Building & Trades",
            "subcategory":"Construction",
            "type":"Services"
        }
    ],
    "sg:phone":"+44 1422 252376",
    "sg:postcode":"HX1 2QN",
    "sg:province":"West Yorkshire",
    "sg:tags":[
        "decorator",
        "painter"
    ],
    "wof:name":"Primary Painting Co Ltd",
    "wof:placetype":"venue"
},
  "geometry": {"coordinates":[-1.8607130051,53.7196884155],"type":"Point"}
}