{
  "type": "Feature",
  "properties": {
    "addr:full":"Aegon House, Daresbury Park Warrington Cheshire WA4 4HS",
    "addr:postcode":"wa4 4hs",
    "addr:street":"Park",
    "iso:country":"GB",
    "sg:address":"Aegon House, Daresbury Park",
    "sg:city":"Warrington",
    "sg:classifiers":[
        {
            "category":"Banks & Credit Unions",
            "subcategory":"Financial Services",
            "type":"Services"
        }
    ],
    "sg:phone":"+44 1928 707900",
    "sg:postcode":"WA4 4HS",
    "sg:province":"Cheshire",
    "sg:tags":[
        "adviser"
    ],
    "wof:name":"H S Administrative Services Ltd.",
    "wof:placetype":"venue"
},
  "geometry": {"coordinates":[-2.632883,53.341518],"type":"Point"}
}