{
  "type": "Feature",
  "properties": {
    "addr:full":"Unit 2, Bridgewater Road, Hertburn Industrial Estate Washington Tyne and Wear NE37 2SG",
    "addr:housenumber":"unit 2",
    "addr:postcode":"ne37 2sg",
    "addr:street":"Bridgewater Road Hertburn Industrial Estate",
    "iso:country":"GB",
    "sg:address":"Unit 2, Bridgewater Road, Hertburn Industrial Estate",
    "sg:city":"Washington",
    "sg:classifiers":[
        {
            "category":"Professional",
            "subcategory":"Printing & Photocopies",
            "type":"Services"
        }
    ],
    "sg:phone":"+44 191 417 8001",
    "sg:postcode":"NE37 2SG",
    "sg:province":"Tyne and Wear",
    "sg:tags":[
        "printer"
    ],
    "wof:name":"Aztec Print North East Ltd.",
    "wof:placetype":"venue"
},
  "geometry": {"coordinates":[-1.514354,54.908428],"type":"Point"}
}