{
  "type": "Feature",
  "properties": {
    "addr:full":"4 Artillery Place, Methan Crescent Harrow Greater London HA3 6QJ",
    "addr:housenumber":"4",
    "addr:postcode":"ha3 6qj",
    "addr:street":"Artillery Place Methan Crescent",
    "iso:country":"GB",
    "sg:address":"4 Artillery Place, Methan Crescent",
    "sg:city":"Harrow",
    "sg:classifiers":[
        {
            "category":"Wholesale",
            "subcategory":"Sporting Goods",
            "type":"Manufacturing & Wholesale Goods"
        }
    ],
    "sg:phone":"+44 20 8421 5307",
    "sg:postcode":"HA3 6QJ",
    "sg:province":"Greater London",
    "sg:tags":[
        "mnfr",
        "sport",
        "equipment"
    ],
    "wof:name":"Dmcl Ltd.",
    "wof:placetype":"venue"
},
  "geometry": {"coordinates":[-0.3519299924,51.6095085144],"type":"Point"}
}