{
  "type": "Feature",
  "properties": {
    "iso:country":"GB",
    "sg:address":"26 St Johns Road",
    "sg:city":"Bungay",
    "sg:classifiers":[
        {
            "category":"Health Services",
            "subcategory":"Nursing And Care Facility",
            "type":"Services"
        }
    ],
    "sg:phone":"+44 1986 892643",
    "sg:postcode":"NR35 1DL",
    "sg:province":"Norfolk",
    "sg:tags":[
        "home"
    ],
    "wof:name":"Adele House Nursing Home",
    "wof:placetype":"venue"
},
  "geometry": {"coordinates":[1.44388,52.44944],"type":"Point"}
}