{
  "type": "Feature",
  "properties": {
    "addr:full":"Victoria St Cheltenham Gloucestershire GL54 2BU",
    "addr:postcode":"gl54 2bu",
    "addr:street":"Victoria St",
    "iso:country":"GB",
    "sg:address":"Victoria St",
    "sg:city":"Cheltenham",
    "sg:classifiers":[
        {
            "category":"Travel",
            "subcategory":"Hotels & Motels",
            "type":"Entertainment"
        }
    ],
    "sg:phone":"+44 1451 820286",
    "sg:postcode":"GL54 2BU",
    "sg:province":"Gloucestershire",
    "wof:name":"Chester House Hotel",
    "wof:placetype":"venue"
},
  "geometry": {"coordinates":[-1.757836,51.883789],"type":"Point"}
}