{
  "type": "Feature",
  "properties": {
    "addr:full":"Memorial Pavillion, Field Lane Tattenhall Chester Cheshire CH3 9QF",
    "addr:postcode":"ch3 9qf",
    "addr:street":"Field Lane",
    "iso:country":"GB",
    "sg:address":"Memorial Pavillion, Field Lane Tattenhall",
    "sg:city":"Chester",
    "sg:classifiers":[
        {
            "category":"Community Center",
            "type":"Public Place"
        }
    ],
    "sg:phone":"+44 1829 770150",
    "sg:postcode":"CH3 9QF",
    "sg:province":"Cheshire",
    "sg:tags":[
        "recreation",
        "leisure",
        "centre"
    ],
    "wof:name":"Tattenhall Recreation Club Ltd.",
    "wof:placetype":"venue"
},
  "geometry": {"coordinates":[-2.7728788853,53.1191558838],"type":"Point"}
}