{
  "type": "Feature",
  "properties": {
    "addr:full":"34 The Ridgeway Chatham Kent ME4 6PD",
    "addr:housenumber":"34",
    "addr:postcode":"me4 6pd",
    "addr:street":"The Ridgeway",
    "iso:country":"GB",
    "sg:address":"34 The Ridgeway",
    "sg:city":"Chatham",
    "sg:classifiers":[
        {
            "category":"Health Services",
            "subcategory":"Doctor",
            "type":"Services"
        }
    ],
    "sg:postcode":"ME4 6PD",
    "sg:province":"Kent",
    "sg:tags":[
        "practitioners"
    ],
    "wof:name":"D J Tooby",
    "wof:placetype":"venue"
},
  "geometry": {"coordinates":[0.518914,51.361099],"type":"Point"}
}