{
  "type": "Feature",
  "properties": {
    "addr:full":"25 Bridge Street Stourport-on-severn Worcestershire DY13 8UR",
    "addr:housenumber":"25",
    "addr:postcode":"dy13 8ur",
    "addr:street":"Bridge Street",
    "iso:country":"GB",
    "sg:address":"25 Bridge Street",
    "sg:city":"Stourport-on-severn",
    "sg:classifiers":[
        {
            "category":"Home & Garden",
            "subcategory":"Kitchen Supply",
            "type":"Retail Goods"
        }
    ],
    "sg:phone":"+44 1299 828321",
    "sg:postcode":"DY13 8UR",
    "sg:province":"Worcestershire",
    "sg:tags":[
        "glassware",
        "china"
    ],
    "wof:name":"Henry's China & Gift Ware",
    "wof:placetype":"venue"
},
  "geometry": {"coordinates":[-2.2811698914,52.339176178],"type":"Point"}
}