{
  "type": "Feature",
  "properties": {
    "addr:full":"The Chapel, Church Street Banwell Somerset BS29 6EA",
    "addr:postcode":"bs29 6ea",
    "addr:street":"Church Street",
    "iso:country":"GB",
    "sg:address":"The Chapel, Church Street",
    "sg:city":"Banwell",
    "sg:classifiers":[
        {
            "category":"Professional",
            "subcategory":"Engineering",
            "type":"Services"
        }
    ],
    "sg:phone":"+44 1934 822492",
    "sg:postcode":"BS29 6EA",
    "sg:province":"Somerset",
    "sg:tags":[
        "consulting",
        "engineer"
    ],
    "wof:name":"Fast Tec",
    "wof:placetype":"venue"
},
  "geometry": {"coordinates":[-2.864942,51.327827],"type":"Point"}
}