{
  "type": "Feature",
  "properties": {
    "iso:country":"GB",
    "sg:address":"P O Box 48, Stourvale Road, Lye",
    "sg:city":"Stourbridge",
    "sg:classifiers":[
        {
            "category":"Home & Garden",
            "subcategory":"Hardware",
            "type":"Retail Goods"
        }
    ],
    "sg:phone":"+44 1384 424767",
    "sg:postcode":"DY9 8QF",
    "sg:province":"West Midlands",
    "sg:tags":[
        "fixing",
        "nuts",
        "bolt"
    ],
    "wof:name":"Martyn Price (Quality Assured Fasteners) Ltd.",
    "wof:placetype":"venue"
},
  "geometry": {"coordinates":[-2.10656,52.460678],"type":"Point"}
}