{
  "type": "Feature",
  "properties": {
    "addr:full":"124 Cannock Road, Wednesfield Wolverhampton Staffordshire WV10 8PW",
    "addr:housenumber":"124",
    "addr:postcode":"wv10 8pw",
    "addr:street":"Cannock Road",
    "iso:country":"GB",
    "sg:address":"124 Cannock Road, Wednesfield",
    "sg:city":"Wolverhampton",
    "sg:classifiers":[
        {
            "category":"Shopping",
            "subcategory":"Pharmacy",
            "type":"Retail Goods"
        }
    ],
    "sg:phone":"+44 1902 731310",
    "sg:postcode":"WV10 8PW",
    "sg:province":"Staffordshire",
    "sg:tags":[
        "pharmacist",
        "chemist"
    ],
    "wof:name":"H N Pharmacy",
    "wof:placetype":"venue"
},
  "geometry": {"coordinates":[-2.099324,52.612579],"type":"Point"}
}