{
  "type": "Feature",
  "properties": {
    "addr:full":"Princess Avenue London Greater London NW9 9JL",
    "addr:postcode":"nw9 9jl",
    "addr:street":"Princess Avenue",
    "iso:country":"GB",
    "sg:address":"Princess Avenue",
    "sg:city":"London",
    "sg:classifiers":[
        {
            "category":"Education",
            "subcategory":"School",
            "type":"Public Place"
        }
    ],
    "sg:phone":"+44 20 8204 3531",
    "sg:postcode":"NW9 9JL",
    "sg:province":"Greater London",
    "sg:tags":[
        "local",
        "authority"
    ],
    "wof:name":"Roe Green Junior School",
    "wof:placetype":"venue"
},
  "geometry": {"coordinates":[-0.269284,51.591686],"type":"Point"}
}