{
  "type": "Feature",
  "properties": {
    "iso:country":"GB",
    "sg:address":"18 Queen Street",
    "sg:city":"Maidenhead",
    "sg:classifiers":[
        {
            "category":"Travel",
            "subcategory":"Travel Agent",
            "type":"Entertainment"
        }
    ],
    "sg:phone":"+44 1628 788330",
    "sg:postcode":"SL6 1HZ",
    "sg:province":"Berkshire",
    "wof:name":"Bell Promotions",
    "wof:placetype":"venue"
},
  "geometry": {"coordinates":[-0.7203239799,51.5217208862],"type":"Point"}
}