{
  "type": "Feature",
  "properties": {
    "iso:country":"GB",
    "sg:address":"21 Old Brompton Road",
    "sg:city":"London",
    "sg:classifiers":[
        {
            "category":"Travel",
            "subcategory":"Travel Agent",
            "type":"Entertainment"
        }
    ],
    "sg:phone":"+44 20 7823 9939",
    "sg:postcode":"SW7 3HZ",
    "sg:province":"Greater London",
    "wof:name":"Thomas Cook",
    "wof:placetype":"venue"
},
  "geometry": {"coordinates":[-0.174876,51.493565],"type":"Point"}
}