{
  "type": "Feature",
  "properties": {
    "addr:full":"Unit 7 Balderton Shopping Centre, London Road, Balderton Newark Nottinghamshire NG24 3JE",
    "addr:housenumber":"unit 7 balderton",
    "addr:postcode":"ng24 3je",
    "addr:street":"Shopping;London Road",
    "iso:country":"GB",
    "sg:address":"Unit 7 Balderton Shopping Centre, London Road, Balderton",
    "sg:city":"Newark",
    "sg:classifiers":[
        {
            "category":"Community Center",
            "subcategory":"Social",
            "type":"Public Place"
        }
    ],
    "sg:phone":"+44 1636 610858",
    "sg:postcode":"NG24 3JE",
    "sg:province":"Nottinghamshire",
    "sg:tags":[
        "frozen",
        "food",
        "freezer",
        "centre"
    ],
    "wof:name":"Farmfoods Freezer Centre",
    "wof:placetype":"venue"
},
  "geometry": {"coordinates":[-0.784139,53.05579],"type":"Point"}
}