{
  "type": "Feature",
  "properties": {
    "iso:country":"GB",
    "sg:address":"Clark Way",
    "sg:city":"Hyde",
    "sg:classifiers":[
        {
            "category":"Home & Garden",
            "subcategory":"Home Furnishings",
            "type":"Retail Goods"
        }
    ],
    "sg:phone":"+44 161 367 9013",
    "sg:postcode":"SK14 2AU",
    "sg:province":"Cheshire",
    "sg:tags":[
        "awning",
        "canopy",
        "blinds"
    ],
    "wof:name":"Better Blind Co",
    "wof:placetype":"venue"
},
  "geometry": {"coordinates":[-2.079725,53.45422],"type":"Point"}
}