{
  "type": "Feature",
  "properties": {
    "iso:country":"GB",
    "sg:address":"Ludgate Ho, 107-111 Fleet St",
    "sg:city":"London",
    "sg:classifiers":[
        {
            "category":"Professional",
            "subcategory":"Employment Agencies",
            "type":"Services"
        }
    ],
    "sg:phone":"+44 20 7936 9015",
    "sg:postcode":"EC4A 2AB",
    "sg:province":"Greater London",
    "sg:tags":[
        "consultant"
    ],
    "wof:name":"Telestaff Ltd",
    "wof:placetype":"venue"
},
  "geometry": {"coordinates":[-0.10893,51.51421],"type":"Point"}
}