{
  "type": "Feature",
  "properties": {
    "addr:full":"83a South Road Southall Greater London UB1 1SQ",
    "addr:housenumber":"83a",
    "addr:postcode":"ub1 1sq",
    "addr:street":"South Road",
    "iso:country":"GB",
    "sg:address":"83a South Road",
    "sg:city":"Southall",
    "sg:classifiers":[
        {
            "category":"Professional",
            "subcategory":"Lawyer & Legal Services",
            "type":"Services"
        }
    ],
    "sg:phone":"+44 20 8571 3535",
    "sg:postcode":"UB1 1SQ",
    "sg:province":"Greater London",
    "sg:tags":[
        "solicitor"
    ],
    "wof:name":"Shehan Pinidiya & Co",
    "wof:placetype":"venue"
},
  "geometry": {"coordinates":[-0.377859,51.507572],"type":"Point"}
}