{
  "type": "Feature",
  "properties": {
    "addr:full":"142 Beacon Road, Great Barr Birmingham West Midlands B43 7BN",
    "addr:housenumber":"142",
    "addr:postcode":"b43 7bn",
    "addr:street":"Beacon Road",
    "iso:country":"GB",
    "sg:address":"142 Beacon Road, Great Barr",
    "sg:city":"Birmingham",
    "sg:classifiers":[
        {
            "category":"Shopping",
            "subcategory":"Clothing, Apparel, & Fashions",
            "type":"Retail Goods"
        }
    ],
    "sg:phone":"+44 121 366 6895",
    "sg:postcode":"B43 7BN",
    "sg:province":"West Midlands",
    "sg:tags":[
        "shop",
        "dress",
        "outlet",
        "fancy"
    ],
    "wof:name":"Giggles & Gear",
    "wof:placetype":"venue"
},
  "geometry": {"coordinates":[-1.911469,52.55735],"type":"Point"}
}