{
  "type": "Feature",
  "properties": {
    "iso:country":"GB",
    "sg:address":"125 Convent Road",
    "sg:city":"Ashford",
    "sg:classifiers":[
        {
            "category":"Food & Beverages",
            "subcategory":"Supermarket",
            "type":"Retail Goods"
        },
        {
            "category":"Food & Beverages",
            "subcategory":"Groceries & Convenience Stores",
            "type":"Retail Goods"
        }
    ],
    "sg:phone":"+44 1784 252233",
    "sg:postcode":"TW15 2HW",
    "sg:province":"Greater London",
    "wof:name":"J F DOSANJH",
    "wof:placetype":"venue"
},
  "geometry": {"coordinates":[-0.4529489875,51.4289894104],"type":"Point"}
}