{
  "type": "Feature",
  "properties": {
    "addr:full":"16a Home Street Edinburgh City of Edinburgh EH3 9LY",
    "addr:housenumber":"16a",
    "addr:postcode":"eh3 9ly",
    "addr:street":"Home Street",
    "iso:country":"GB",
    "sg:address":"16a Home Street",
    "sg:city":"Edinburgh",
    "sg:classifiers":[
        {
            "category":"Personal",
            "subcategory":"Beauty Salon",
            "type":"Services"
        },
        {
            "category":"Personal",
            "subcategory":"Barber",
            "type":"Services"
        }
    ],
    "sg:phone":"+44 131 228 2848",
    "sg:postcode":"EH3 9LY",
    "sg:province":"City of Edinburgh",
    "sg:tags":[
        "unisex",
        "hairdresser"
    ],
    "wof:name":"Kiama",
    "wof:placetype":"venue"
},
  "geometry": {"coordinates":[-3.2039449215,55.9434089661],"type":"Point"}
}