{
  "type": "Feature",
  "properties": {
    "addr:full":"Lyebourne House London Greater London NW6 5UA",
    "addr:postcode":"nw6 5ua",
    "iso:country":"GB",
    "sg:address":"Lyebourne House",
    "sg:city":"London",
    "sg:classifiers":[
        {
            "category":"Autos & Motor Vehicles",
            "subcategory":"Motorcycle Sales",
            "type":"Retail Goods"
        }
    ],
    "sg:postcode":"NW6 5UA",
    "sg:province":"Greater London",
    "sg:tags":[
        "chauffeur",
        "driven",
        "car"
    ],
    "wof:name":"Burlington Cars",
    "wof:placetype":"venue"
},
  "geometry": {"coordinates":[-0.0879139975,51.5073699951],"type":"Point"}
}