{
  "type": "Feature",
  "properties": {
    "iso:country":"GB",
    "sg:address":"49 Somervell Drive",
    "sg:city":"Fareham",
    "sg:classifiers":[
        {
            "category":"Building & Trades",
            "subcategory":"Plumbing",
            "type":"Services"
        }
    ],
    "sg:postcode":"PO16 7QN",
    "sg:province":"Hampshire",
    "sg:tags":[
        "central",
        "heating"
    ],
    "wof:name":"March Heating Ltd.",
    "wof:placetype":"venue"
},
  "geometry": {"coordinates":[-1.1912750006,50.8602600098],"type":"Point"}
}