{
  "type": "Feature",
  "properties": {
    "addr:full":"15 Seagrave Road Beaconsfield Buckinghamshire HP9 1SU",
    "addr:housenumber":"15",
    "addr:postcode":"hp9 1su",
    "addr:street":"Seagrave Road",
    "iso:country":"GB",
    "sg:address":"15 Seagrave Road",
    "sg:city":"Beaconsfield",
    "sg:classifiers":[
        {
            "category":"Utilities",
            "type":"Services"
        }
    ],
    "sg:phone":"+44 1494 677045",
    "sg:postcode":"HP9 1SU",
    "sg:province":"Buckinghamshire",
    "sg:tags":[
        "internet"
    ],
    "wof:name":"A I I T Ltd.",
    "wof:placetype":"venue"
},
  "geometry": {"coordinates":[-0.652173996,51.6179008484],"type":"Point"}
}