{
  "type": "Feature",
  "properties": {
    "addr:full":"Suite 302-304 Caledonian Ho, 98 The Centre Feltham Greater London TW13 4BH",
    "addr:housenumber":"suite 302-304;98",
    "addr:postcode":"tw13 4bh",
    "addr:street":"Caledonian Ho;The Centre",
    "iso:country":"GB",
    "sg:address":"Suite 302-304 Caledonian Ho, 98 The Centre",
    "sg:city":"Feltham",
    "sg:classifiers":[
        {
            "category":"Professional",
            "subcategory":"Accounting & Tax Preparation",
            "type":"Services"
        }
    ],
    "sg:phone":"+44 20 8831 9298",
    "sg:postcode":"TW13 4BH",
    "sg:province":"Greater London",
    "sg:tags":[
        "accountant"
    ],
    "wof:name":"Colin Murrell Associates",
    "wof:placetype":"venue"
},
  "geometry": {"coordinates":[-0.4092040062,51.4470748901],"type":"Point"}
}