{
  "type": "Feature",
  "properties": {
    "addr:full":"Spring Lane Malvern Herefordshire WR14 1BX",
    "addr:postcode":"wr14 1bx",
    "addr:street":"Spring Lane;Herefordshire",
    "iso:country":"GB",
    "sg:address":"Spring Lane",
    "sg:city":"Malvern",
    "sg:classifiers":[
        {
            "category":"Manufacturing",
            "subcategory":"Metals",
            "type":"Manufacturing & Wholesale Goods"
        }
    ],
    "sg:phone":"+44 1684 562226",
    "sg:postcode":"WR14 1BX",
    "sg:province":"Herefordshire",
    "sg:tags":[
        "work",
        "sheet"
    ],
    "wof:name":"Evans Fabrications Ltd.",
    "wof:placetype":"venue"
},
  "geometry": {"coordinates":[-2.3078589439,52.1283187866],"type":"Point"}
}