{
  "type": "Feature",
  "properties": {
    "iso:country":"GB",
    "sg:address":"Long Acre, Long Lane",
    "sg:city":"Hemel Hempstead",
    "sg:classifiers":[
        {
            "category":"Retail",
            "subcategory":"Auto Repair",
            "type":"Services"
        }
    ],
    "sg:phone":"+44 1442 832682",
    "sg:postcode":"HP3 0NE",
    "sg:province":"Hertfordshire",
    "sg:tags":[
        "modification",
        "garage"
    ],
    "wof:name":"D Broome Autos",
    "wof:placetype":"venue"
},
  "geometry": {"coordinates":[-0.5376300216,51.7101593018],"type":"Point"}
}