{
  "type": "Feature",
  "properties": {
    "addr:full":"73 Front Street Newbiggin-by-the-sea Northumberland NE64 6AD",
    "addr:housenumber":"73",
    "addr:postcode":"ne64 6ad",
    "addr:street":"Front Street;Northumberland",
    "iso:country":"GB",
    "sg:address":"73 Front Street",
    "sg:city":"Newbiggin-by-the-sea",
    "sg:classifiers":[
        {
            "category":"Shopping",
            "subcategory":"News",
            "type":"Retail Goods"
        }
    ],
    "sg:phone":"+44 1670 818334",
    "sg:postcode":"NE64 6AD",
    "sg:province":"Northumberland",
    "sg:tags":[
        "newsagent"
    ],
    "wof:name":"United News Shops Ltd.",
    "wof:placetype":"venue"
},
  "geometry": {"coordinates":[-1.510211,55.185402],"type":"Point"}
}