{
  "type": "Feature",
  "properties": {
    "iso:country":"GB",
    "sg:address":"Woodend Industrial Estate",
    "sg:city":"Cowdenbeath",
    "sg:classifiers":[
        {
            "category":"Home & Garden",
            "subcategory":"Hardware",
            "type":"Retail Goods"
        }
    ],
    "sg:phone":"+44 1383 515999",
    "sg:postcode":"KY4 8HW",
    "sg:province":"Fife",
    "sg:tags":[
        "retailer",
        "diy"
    ],
    "wof:name":"Jamieson Joinery Supplies",
    "wof:placetype":"venue"
},
  "geometry": {"coordinates":[-3.356193,56.099125],"type":"Point"}
}