{
  "type": "Feature",
  "properties": {
    "addr:full":"23 High Street Ventnor Isle of Wight PO38 1RZ",
    "addr:housenumber":"23",
    "addr:postcode":"po38 1rz",
    "addr:street":"High Street",
    "iso:country":"GB",
    "sg:address":"23 High Street",
    "sg:city":"Ventnor",
    "sg:classifiers":[
        {
            "category":"Food & Beverages",
            "subcategory":"Meat & Fish",
            "type":"Retail Goods"
        }
    ],
    "sg:postcode":"PO38 1RZ",
    "sg:province":"Isle of Wight",
    "sg:tags":[
        "butcher"
    ],
    "wof:name":"Branson's",
    "wof:placetype":"venue"
},
  "geometry": {"coordinates":[-1.2049549818,50.5955505371],"type":"Point"}
}