{
  "type": "Feature",
  "properties": {
    "addr:full":"86 Bailgate Lincoln Lincolnshire LN1 3AR",
    "addr:housenumber":"86",
    "addr:postcode":"ln1 3ar",
    "addr:street":"Bailgate Lincoln",
    "iso:country":"GB",
    "sg:address":"86 Bailgate",
    "sg:city":"Lincoln",
    "sg:classifiers":[
        {
            "category":"Manufacturing",
            "subcategory":"Textiles",
            "type":"Manufacturing & Wholesale Goods"
        }
    ],
    "sg:postcode":"LN1 3AR",
    "sg:province":"Lincolnshire",
    "sg:tags":[
        "knitwear"
    ],
    "wof:name":"The Lincoln Knitwear Store",
    "wof:placetype":"venue"
},
  "geometry": {"coordinates":[-0.538475,53.235168],"type":"Point"}
}