{
  "type": "Feature",
  "properties": {
    "iso:country":"GB",
    "sg:address":"3 Tylers Farm, Gedney Drove End",
    "sg:city":"Spalding",
    "sg:classifiers":[
        {
            "category":"Farming",
            "subcategory":"Livestock Farm",
            "type":"Manufacturing & Wholesale Goods"
        }
    ],
    "sg:phone":"+44 1406 550200",
    "sg:postcode":"PE12 9PA",
    "sg:province":"Cambridgeshire",
    "sg:tags":[
        "others"
    ],
    "wof:name":"A A Edgley",
    "wof:placetype":"venue"
},
  "geometry": {"coordinates":[0.14158,52.836048],"type":"Point"}
}