{
  "type": "Feature",
  "properties": {
    "iso:country":"GB",
    "sg:address":"10-12 Carlisle Road",
    "sg:city":"Eastbourne",
    "sg:classifiers":[
        {
            "category":"Social Services",
            "subcategory":"Retirement Home",
            "type":"Services"
        }
    ],
    "sg:phone":"+44 1323 734009",
    "sg:postcode":"BN20 7EJ",
    "sg:province":"East Sussex",
    "sg:tags":[
        "residential",
        "care"
    ],
    "wof:name":"Ingham House",
    "wof:placetype":"venue"
},
  "geometry": {"coordinates":[0.276476,50.762016],"type":"Point"}
}