{
  "type": "Feature",
  "properties": {
    "addr:full":"14 Bridewell Close, North Leigh Witney Oxfordshire OX29 6TR",
    "addr:housenumber":"14",
    "addr:postcode":"ox29 6tr",
    "addr:street":"Bridewell Close North Leigh",
    "iso:country":"GB",
    "sg:address":"14 Bridewell Close, North Leigh",
    "sg:city":"Witney",
    "sg:classifiers":[
        {
            "category":"Organizations",
            "subcategory":"Non-profit Organization",
            "type":"Services"
        }
    ],
    "sg:postcode":"OX29 6TR",
    "sg:province":"Oxfordshire",
    "sg:tags":[
        "organisation",
        "voluntary",
        "charity"
    ],
    "wof:name":"Multiple Sclerosis Society West Oxfordshire Brank",
    "wof:placetype":"venue"
},
  "geometry": {"coordinates":[-1.4422609806,51.8160057068],"type":"Point"}
}