{
  "type": "Feature",
  "properties": {
    "iso:country":"GB",
    "sg:address":"Unit 1 Coopies Haugh Business Park, Coopers Lane",
    "sg:city":"Morpeth",
    "sg:classifiers":[
        {
            "category":"Restaurant",
            "type":"Food & Drink"
        }
    ],
    "sg:phone":"+44 1670 504143",
    "sg:postcode":"NE24 1JN",
    "sg:province":"Northumberland",
    "wof:name":"The Canteen",
    "wof:placetype":"venue"
},
  "geometry": {"coordinates":[-1.51718,55.13044],"type":"Point"}
}