{
  "type": "Feature",
  "properties": {
    "addr:full":"Weydown Road Haslemere Hampshire GU27 1BT",
    "addr:postcode":"gu27 1bt",
    "addr:street":"Weydown Road",
    "iso:country":"GB",
    "sg:address":"Weydown Road",
    "sg:city":"Haslemere",
    "sg:classifiers":[
        {
            "category":"Home & Garden",
            "subcategory":"Hardware",
            "type":"Retail Goods"
        }
    ],
    "sg:phone":"+44 1428 651246",
    "sg:postcode":"GU27 1BT",
    "sg:province":"Hampshire",
    "sg:tags":[
        "paint",
        "coating"
    ],
    "wof:name":"Paint Services Group Ltd.",
    "wof:placetype":"venue"
},
  "geometry": {"coordinates":[-0.7152690291,51.0964851379],"type":"Point"}
}