{
  "type": "Feature",
  "properties": {
    "addr:full":"33 Market St Crewe Cheshire CW1 2EW",
    "addr:housenumber":"33",
    "addr:postcode":"cw1 2ew",
    "addr:street":"Market St",
    "iso:country":"GB",
    "sg:address":"33 Market St",
    "sg:city":"Crewe",
    "sg:classifiers":[
        {
            "category":"Fast Food",
            "type":"Food & Drink"
        }
    ],
    "sg:phone":"+44 1270 212021",
    "sg:postcode":"CW1 2EW",
    "sg:province":"Cheshire",
    "sg:tags":[
        "away",
        "take"
    ],
    "wof:name":"HARVEYS",
    "wof:placetype":"venue"
},
  "geometry": {"coordinates":[-2.441569,53.097069],"type":"Point"}
}