{
  "type": "Feature",
  "properties": {
    "addr:full":"Atlas House, Bank Terrace, Barwell Leicester Leicestershire LE9 8GG",
    "addr:postcode":"le9 8gg",
    "addr:street":"Bank Terrace",
    "iso:country":"GB",
    "sg:address":"Atlas House, Bank Terrace, Barwell",
    "sg:city":"Leicester",
    "sg:classifiers":[
        {
            "category":"Professional",
            "type":"Services"
        }
    ],
    "sg:phone":"+44 1455 841119",
    "sg:postcode":"LE9 8GG",
    "sg:province":"Leicestershire",
    "sg:tags":[
        "shopfitters"
    ],
    "wof:name":"Astley Shopfitters Ltd.",
    "wof:placetype":"venue"
},
  "geometry": {"coordinates":[-1.3472739458,52.5683708191],"type":"Point"}
}