{
  "type": "Feature",
  "properties": {
    "addr:full":"Leconfield St Cleator Moor Cumbria CA25 5QQ",
    "addr:postcode":"ca25 5qq",
    "addr:street":"Leconfield St;Moor",
    "iso:country":"GB",
    "sg:address":"Leconfield St",
    "sg:city":"Cleator Moor",
    "sg:classifiers":[
        {
            "category":"Autos & Motor Vehicles",
            "subcategory":"Fuel & Gas Station",
            "type":"Retail Goods"
        }
    ],
    "sg:phone":"+44 1946 815526",
    "sg:postcode":"CA25 5QQ",
    "sg:province":"Cumbria",
    "sg:tags":[
        "petrol",
        "filling"
    ],
    "wof:name":"Crossfield Garage Services",
    "wof:placetype":"venue"
},
  "geometry": {"coordinates":[-3.525987,54.524933],"type":"Point"}
}