{
  "type": "Feature",
  "properties": {
    "addr:full":"Dartmouth Road, Churston Ferrers Brixham Devon TQ5 0LL",
    "addr:postcode":"tq5 0ll",
    "addr:street":"Dartmouth Road",
    "iso:country":"GB",
    "sg:address":"Dartmouth Road, Churston Ferrers",
    "sg:city":"Brixham",
    "sg:classifiers":[
        {
            "category":"Travel",
            "subcategory":"Hotels & Motels",
            "type":"Entertainment"
        },
        {
            "category":"Restaurant",
            "type":"Food & Drink"
        }
    ],
    "sg:phone":"+44 1803 842280",
    "sg:postcode":"TQ5 0LL",
    "sg:province":"Devon",
    "wof:name":"The Weary Ploughman",
    "wof:placetype":"venue"
},
  "geometry": {"coordinates":[-3.5463531017,50.3911018372],"type":"Point"}
}