{
  "type": "Feature",
  "properties": {
    "addr:full":"Brook Street, Blaenrhondda Treorchy Rhondda, Cynon, Taff CF42 5SB",
    "addr:postcode":"cf42 5sb",
    "addr:street":"Brook Street;Cynon Taff",
    "iso:country":"GB",
    "sg:address":"Brook Street, Blaenrhondda",
    "sg:city":"Treorchy",
    "sg:classifiers":[
        {
            "category":"Education",
            "subcategory":"School",
            "type":"Public Place"
        }
    ],
    "sg:phone":"+44 1443 771432",
    "sg:postcode":"CF42 5SB",
    "sg:province":"Rhondda, Cynon, Taff",
    "sg:tags":[
        "local",
        "authority"
    ],
    "wof:name":"Mid Glamorgan County Council",
    "wof:placetype":"venue"
},
  "geometry": {"coordinates":[-3.552266,51.681129],"type":"Point"}
}