{
  "type": "Feature",
  "properties": {
    "addr:full":"165 High St, Worle Weston-super-mare Somerset BS22 6JA",
    "addr:housenumber":"165",
    "addr:postcode":"bs22 6ja",
    "addr:street":"High St",
    "iso:country":"GB",
    "sg:address":"165 High St, Worle",
    "sg:city":"Weston-super-mare",
    "sg:classifiers":[
        {
            "category":"Autos & Motor Vehicles",
            "subcategory":"Automobile Sales",
            "type":"Retail Goods"
        }
    ],
    "sg:postcode":"BS22 6JA",
    "sg:province":"Somerset",
    "sg:tags":[
        "car"
    ],
    "wof:name":"Central Garage",
    "wof:placetype":"venue"
},
  "geometry": {"coordinates":[-2.927492,51.360451],"type":"Point"}
}