{
  "type": "Feature",
  "properties": {
    "iso:country":"GB",
    "sg:address":"The Mill, Parkwood Road",
    "sg:city":"Tavistock",
    "sg:classifiers":[
        {
            "category":"Home & Garden",
            "subcategory":"Hardware",
            "type":"Retail Goods"
        }
    ],
    "sg:phone":"+44 1822 610200",
    "sg:postcode":"PL19 9ET",
    "sg:province":"Devon",
    "wof:name":"Lawsons",
    "wof:placetype":"venue"
},
  "geometry": {"coordinates":[-4.144739,50.549934],"type":"Point"}
}