{
  "type": "Feature",
  "properties": {
    "addr:full":"4 Wellington Rd Bournemouth Dorset BH8 8JQ",
    "addr:housenumber":"4",
    "addr:postcode":"bh8 8jq",
    "addr:street":"Wellington Rd",
    "iso:country":"GB",
    "sg:address":"4 Wellington Rd",
    "sg:city":"Bournemouth",
    "sg:classifiers":[
        {
            "category":"Freight",
            "type":"Transportation"
        }
    ],
    "sg:phone":"+44 1202 638264",
    "sg:postcode":"BH8 8JQ",
    "sg:province":"Dorset",
    "sg:tags":[
        "haulage",
        "road"
    ],
    "wof:name":"Royal Mail",
    "wof:placetype":"venue"
},
  "geometry": {"coordinates":[-1.8624329567,50.7277107239],"type":"Point"}
}