{
  "type": "Feature",
  "properties": {
    "iso:country":"GB",
    "sg:address":"62 Gateford Road",
    "sg:city":"Worksop",
    "sg:classifiers":[
        {
            "category":"Manufacturing",
            "subcategory":"Petroleum Products",
            "type":"Manufacturing & Wholesale Goods"
        }
    ],
    "sg:phone":"+44 1909 474007",
    "sg:postcode":"S80 1TX",
    "sg:province":"Nottinghamshire",
    "sg:tags":[
        "double",
        "glazing"
    ],
    "wof:name":"Colourfast Ultra White Windows",
    "wof:placetype":"venue"
},
  "geometry": {"coordinates":[-1.1242649555,53.3099594116],"type":"Point"}
}