{
  "type": "Feature",
  "properties": {
    "iso:country":"GB",
    "sg:address":"1371 London Road",
    "sg:city":"London",
    "sg:classifiers":[
        {
            "category":"Shopping",
            "subcategory":"News",
            "type":"Retail Goods"
        }
    ],
    "sg:phone":"+44 20 8764 8163",
    "sg:postcode":"SW16 4BE",
    "sg:province":"Greater London",
    "sg:tags":[
        "newsagent"
    ],
    "wof:name":"Your Friendly Store",
    "wof:placetype":"venue"
},
  "geometry": {"coordinates":[-0.12162,51.40765],"type":"Point"}
}