{
  "type": "Feature",
  "properties": {
    "iso:country":"GB",
    "sg:address":"192a Rye Lane",
    "sg:city":"London",
    "sg:classifiers":[
        {
            "category":"Cafe",
            "type":"Food & Drink"
        }
    ],
    "sg:phone":"+44 20 7277 8093",
    "sg:postcode":"SE15 4NF",
    "sg:province":"Greater London",
    "sg:tags":[
        "tea",
        "room"
    ],
    "wof:name":"Ozzies Coffee Shop",
    "wof:placetype":"venue"
},
  "geometry": {"coordinates":[-0.067022,51.467533],"type":"Point"}
}