{
  "type": "Feature",
  "properties": {
    "iso:country":"GB",
    "sg:address":"21 Friary Walk",
    "sg:city":"Worcester",
    "sg:classifiers":[
        {
            "category":"Wholesale",
            "subcategory":"Meat",
            "type":"Manufacturing & Wholesale Goods"
        }
    ],
    "sg:phone":"+44 1905 726486",
    "sg:postcode":"WR1 3LE",
    "sg:province":"Worcestershire",
    "sg:tags":[
        "product"
    ],
    "wof:name":"Three Lions Meat Co.",
    "wof:placetype":"venue"
},
  "geometry": {"coordinates":[-2.2185339928,52.1897087097],"type":"Point"}
}