{
  "type": "Feature",
  "properties": {
    "iso:country":"GB",
    "sg:address":"33 Hemingway Garth",
    "sg:city":"Leeds",
    "sg:classifiers":[
        {
            "category":"Organizations",
            "subcategory":"Community Association",
            "type":"Services"
        }
    ],
    "sg:phone":"+44 113 271 0002",
    "sg:postcode":"LS10 2PG",
    "sg:province":"West Yorkshire",
    "sg:tags":[
        "associations",
        "housing",
        "co-operatives",
        "society",
        "trust",
        "societies"
    ],
    "wof:name":"Stonham Housing Association Ltd",
    "wof:placetype":"venue"
},
  "geometry": {"coordinates":[-1.526505,53.777832],"type":"Point"}
}