{
  "type": "Feature",
  "properties": {
    "iso:country":"GB",
    "sg:address":"Hayes Point, Sully",
    "sg:city":"Penarth",
    "sg:classifiers":[
        {
            "category":"Military Area",
            "subcategory":"Coast Guard Base",
            "type":"Public Place"
        },
        {
            "category":"Education",
            "subcategory":"Special Training",
            "type":"Public Place"
        }
    ],
    "sg:phone":"+44 1446 744044",
    "sg:postcode":"CF64 5XU",
    "sg:province":"The Vale of Glamorgan",
    "sg:tags":[
        "armed",
        "product",
        "force",
        "centre"
    ],
    "wof:name":"H M S Cambria",
    "wof:placetype":"venue"
},
  "geometry": {"coordinates":[-3.214549,51.405689],"type":"Point"}
}