{
  "type": "Feature",
  "properties": {
    "addr:full":"18 Milnrow Road Rochdale Lancashire OL16 1UD",
    "addr:housenumber":"18",
    "addr:postcode":"ol16 1ud",
    "addr:street":"Milnrow Road",
    "iso:country":"GB",
    "sg:address":"18 Milnrow Road",
    "sg:city":"Rochdale",
    "sg:classifiers":[
        {
            "category":"Personal",
            "subcategory":"Beauty Salon",
            "type":"Services"
        }
    ],
    "sg:postcode":"OL16 1UD",
    "sg:province":"Lancashire",
    "sg:tags":[
        "unisex",
        "hairdresser"
    ],
    "wof:name":"Charlie's Hair Salon",
    "wof:placetype":"venue"
},
  "geometry": {"coordinates":[-2.1520950794,53.6138648987],"type":"Point"}
}