{
  "type": "Feature",
  "properties": {
    "iso:country":"GB",
    "sg:address":"55 Caroline Street, Hockley",
    "sg:city":"Birmingham",
    "sg:classifiers":[
        {
            "category":"Professional",
            "type":"Services"
        }
    ],
    "sg:postcode":"B3 1UF",
    "sg:province":"West Midlands",
    "sg:tags":[
        "repair",
        "tech",
        "maintenance"
    ],
    "wof:name":"Solvtec",
    "wof:placetype":"venue"
},
  "geometry": {"coordinates":[-1.908386,52.486694],"type":"Point"}
}