{
  "type": "Feature",
  "properties": {
    "addr:full":"Wood Farm, Woodham Road, Battlesbridge Wickford Essex SS11 7QU",
    "addr:postcode":"ss11 7qu",
    "addr:street":"Woodham Road",
    "iso:country":"GB",
    "sg:address":"Wood Farm, Woodham Road, Battlesbridge",
    "sg:city":"Wickford",
    "sg:classifiers":[
        {
            "category":"Manufacturing",
            "subcategory":"Rubber & Plastics",
            "type":"Manufacturing & Wholesale Goods"
        }
    ],
    "sg:phone":"+44 1245 328801",
    "sg:postcode":"SS11 7QU",
    "sg:province":"Essex",
    "sg:tags":[
        "product"
    ],
    "wof:name":"B P H Plastics",
    "wof:placetype":"venue"
},
  "geometry": {"coordinates":[0.570253,51.622868],"type":"Point"}
}