{
  "type": "Feature",
  "properties": {
    "addr:full":"The Oast House, Crouch Lane Faversham Kent ME13 9PX",
    "addr:postcode":"me13 9px",
    "addr:street":"Crouch Lane",
    "iso:country":"GB",
    "sg:address":"The Oast House, Crouch Lane",
    "sg:city":"Faversham",
    "sg:classifiers":[
        {
            "category":"Professional",
            "subcategory":"Accounting & Tax Preparation",
            "type":"Services"
        }
    ],
    "sg:phone":"+44 1227 752540",
    "sg:postcode":"ME13 9PX",
    "sg:province":"Kent",
    "sg:tags":[
        "accountant"
    ],
    "wof:name":"Brian Kelsey & Co. Ltd.",
    "wof:placetype":"venue"
},
  "geometry": {"coordinates":[0.939163,51.284405],"type":"Point"}
}