{
  "type": "Feature",
  "properties": {
    "iso:country":"GB",
    "sg:address":"Care Of Auchenharbie Academy, Saltcoats Road",
    "sg:city":"Stevenston",
    "sg:classifiers":[
        {
            "category":"Farming",
            "subcategory":"Nursery",
            "type":"Manufacturing & Wholesale Goods"
        }
    ],
    "sg:phone":"+44 1294 469802",
    "sg:postcode":"KA20 3JW",
    "sg:province":"North Ayrshire",
    "sg:tags":[
        "creche"
    ],
    "wof:name":"Auchenharbie Community Nursery",
    "wof:placetype":"venue"
},
  "geometry": {"coordinates":[-4.7562508583,55.6429252625],"type":"Point"}
}