{
  "type": "Feature",
  "properties": {
    "iso:country":"GB",
    "sg:address":"10 Coldicotts Clo",
    "sg:city":"Evesham",
    "sg:classifiers":[
        {
            "category":"Building & Trades",
            "subcategory":"Construction",
            "type":"Services"
        }
    ],
    "sg:phone":"+44 1386 830374",
    "sg:postcode":"WR11 5HT",
    "sg:province":"Gloucestershire",
    "sg:tags":[
        "builder"
    ],
    "wof:name":"R Vernon",
    "wof:placetype":"venue"
},
  "geometry": {"coordinates":[-1.95163,52.084984],"type":"Point"}
}