{
  "type": "Feature",
  "properties": {
    "iso:country":"GB",
    "sg:address":"68-74 Lytham Road, Freckleton",
    "sg:city":"Preston",
    "sg:classifiers":[
        {
            "category":"Food & Beverages",
            "subcategory":"Bakery",
            "type":"Retail Goods"
        }
    ],
    "sg:phone":"+44 1772 631264",
    "sg:postcode":"PR4 1XA",
    "sg:province":"Lancashire",
    "sg:tags":[
        "pizza"
    ],
    "wof:name":"Pizza Primo Express",
    "wof:placetype":"venue"
},
  "geometry": {"coordinates":[-2.870173,53.753967],"type":"Point"}
}