{
  "type": "Feature",
  "properties": {
    "addr:full":"20 Bird St Lichfield Staffordshire WS13 6PR",
    "addr:housenumber":"20",
    "addr:postcode":"ws13 6pr",
    "addr:street":"Bird St",
    "iso:country":"GB",
    "sg:address":"20 Bird St",
    "sg:city":"Lichfield",
    "sg:classifiers":[
        {
            "category":"Bars & Pubs",
            "type":"Food & Drink"
        }
    ],
    "sg:postcode":"WS13 6PR",
    "sg:province":"Staffordshire",
    "sg:tags":[
        "pubs",
        "inn"
    ],
    "wof:name":"Sharkeys Bar",
    "wof:placetype":"venue"
},
  "geometry": {"coordinates":[-1.8305209875,52.6832733154],"type":"Point"}
}