{
  "type": "Feature",
  "properties": {
    "iso:country":"GB",
    "sg:address":"41 Leslie Park Road",
    "sg:city":"Croydon",
    "sg:classifiers":[
        {
            "category":"Communications",
            "subcategory":"Film & Video Production",
            "type":"Services"
        }
    ],
    "sg:phone":"+44 20 8654 1197",
    "sg:postcode":"CR0 6TP",
    "sg:province":"Surrey",
    "sg:tags":[
        "recording",
        "studio"
    ],
    "wof:name":"Moon Recording Studios",
    "wof:placetype":"venue"
},
  "geometry": {"coordinates":[-0.086331,51.379177],"type":"Point"}
}