{
  "type": "Feature",
  "properties": {
    "iso:country":"GB",
    "sg:address":"70 Furtherwick Road",
    "sg:city":"Canvey Island",
    "sg:classifiers":[
        {
            "category":"Food & Beverages",
            "subcategory":"Meat & Fish",
            "type":"Retail Goods"
        }
    ],
    "sg:phone":"+44 1268 690935",
    "sg:postcode":"SS8 7AJ",
    "sg:province":"Essex",
    "sg:tags":[
        "butcher"
    ],
    "wof:name":"Freddie Caring",
    "wof:placetype":"venue"
},
  "geometry": {"coordinates":[0.592396,51.5215],"type":"Point"}
}