{
  "type": "Feature",
  "properties": {
    "iso:country":"GB",
    "sg:address":"Millbrook House, George Street, Nailsworth",
    "sg:city":"Stroud",
    "sg:classifiers":[
        {
            "category":"Shopping",
            "subcategory":"Department Store",
            "type":"Retail Goods"
        }
    ],
    "sg:phone":"+44 1453 834704",
    "sg:postcode":"GL6 0AG",
    "sg:province":"Gloucestershire",
    "wof:name":"Diane Tigwell",
    "wof:placetype":"venue"
},
  "geometry": {"coordinates":[-2.2173750401,51.6964378357],"type":"Point"}
}