{
  "type": "Feature",
  "properties": {
    "addr:full":"The Training Ship, Bridge Street, Lower Town Fishguard Pembrokeshire SA65 9LX",
    "addr:postcode":"sa65 9lx",
    "addr:street":"Bridge Street",
    "iso:country":"GB",
    "sg:address":"The Training Ship, Bridge Street, Lower Town",
    "sg:city":"Fishguard",
    "sg:classifiers":[
        {
            "category":"Community Center",
            "subcategory":"Youth",
            "type":"Public Place"
        }
    ],
    "sg:phone":"+44 1348 875027",
    "sg:postcode":"SA65 9LX",
    "sg:province":"Pembrokeshire",
    "sg:tags":[
        "organisation",
        "centre"
    ],
    "wof:name":"Fishguard Sea Cadets",
    "wof:placetype":"venue"
},
  "geometry": {"coordinates":[-4.977396965,51.9943733215],"type":"Point"}
}