{
  "type": "Feature",
  "properties": {
    "iso:country":"GB",
    "sg:address":"5 South Street",
    "sg:city":"Exeter",
    "sg:classifiers":[
        {
            "category":"Professional",
            "subcategory":"Art Services",
            "type":"Services"
        }
    ],
    "sg:phone":"+44 1392 423734",
    "sg:postcode":"EX1 1DZ",
    "sg:province":"Devon",
    "sg:tags":[
        "framing"
    ],
    "wof:name":"Frameworld",
    "wof:placetype":"venue"
},
  "geometry": {"coordinates":[-3.531993,50.722263],"type":"Point"}
}