{
  "type": "Feature",
  "properties": {
    "iso:country":"GB",
    "sg:address":"39 Sutton Common Road",
    "sg:city":"Sutton",
    "sg:classifiers":[
        {
            "category":"Retail",
            "subcategory":"Storage",
            "type":"Services"
        }
    ],
    "sg:phone":"+44 20 8641 0126",
    "sg:postcode":"SM1 3HJ",
    "sg:province":"Surrey",
    "sg:tags":[
        "household",
        "activity",
        "domestic",
        "removal"
    ],
    "wof:name":"Osborne Light Removals",
    "wof:placetype":"venue"
},
  "geometry": {"coordinates":[-0.19562,51.374065],"type":"Point"}
}