{
  "type": "Feature",
  "properties": {
    "addr:full":"Boundry Elms, Burchetts Green Lane Maidenhead Berkshire SL6 3QW",
    "addr:postcode":"sl6 3qw",
    "addr:street":"Green Lane",
    "iso:country":"GB",
    "sg:address":"Boundry Elms, Burchetts Green Lane",
    "sg:city":"Maidenhead",
    "sg:classifiers":[
        {
            "category":"Shopping",
            "subcategory":"Discount & Variety Stores",
            "type":"Retail Goods"
        }
    ],
    "sg:phone":"+44 1628 822992",
    "sg:postcode":"SL6 3QW",
    "sg:province":"Berkshire",
    "sg:tags":[
        "shop",
        "model"
    ],
    "wof:name":"Model Store",
    "wof:placetype":"venue"
},
  "geometry": {"coordinates":[-0.7897869945,51.5206413269],"type":"Point"}
}