{
  "type": "Feature",
  "properties": {
    "addr:full":"33 Market Place Holt Norfolk NR25 6BE",
    "addr:housenumber":"33",
    "addr:postcode":"nr25 6be",
    "addr:street":"Market Place Holt",
    "iso:country":"GB",
    "sg:address":"33 Market Place",
    "sg:city":"Holt",
    "sg:classifiers":[
        {
            "category":"Shopping",
            "subcategory":"Clothing, Apparel, & Fashions",
            "type":"Retail Goods"
        }
    ],
    "sg:postcode":"NR25 6BE",
    "sg:province":"Norfolk",
    "sg:tags":[
        "dresswear"
    ],
    "wof:name":"Norfolk Frock Change",
    "wof:placetype":"venue"
},
  "geometry": {"coordinates":[1.090468049,52.9061012268],"type":"Point"}
}