{
  "type": "Feature",
  "properties": {
    "addr:full":"Unit 3 Blunts La Peterborough Cambridgeshire PE7 1AH",
    "addr:housenumber":"unit 3",
    "addr:postcode":"pe7 1ah",
    "addr:street":"Blunts La Peterborough",
    "iso:country":"GB",
    "sg:address":"Unit 3 Blunts La",
    "sg:city":"Peterborough",
    "sg:classifiers":[
        {
            "category":"Shopping",
            "subcategory":"Clothing, Apparel, & Fashions",
            "type":"Retail Goods"
        }
    ],
    "sg:postcode":"PE7 1AH",
    "sg:province":"Cambridgeshire",
    "sg:tags":[
        "shop"
    ],
    "wof:name":"Bali,N K,",
    "wof:placetype":"venue"
},
  "geometry": {"coordinates":[-0.1246839985,52.5571670532],"type":"Point"}
}