{
  "type": "Feature",
  "properties": {
    "iso:country":"GB",
    "sg:address":"26 Woolgreaves Garth, Sandal",
    "sg:city":"Wakefield",
    "sg:classifiers":[
        {
            "category":"Professional",
            "subcategory":"Business Services",
            "type":"Services"
        }
    ],
    "sg:phone":"+44 1924 257777",
    "sg:postcode":"WF2 6DY",
    "sg:province":"West Yorkshire",
    "sg:tags":[
        "agent",
        "manufacturers'"
    ],
    "wof:name":"Gap Management Ltd.",
    "wof:placetype":"venue"
},
  "geometry": {"coordinates":[-1.48971,53.646519],"type":"Point"}
}