{
  "type": "Feature",
  "properties": {
    "addr:full":"37-39 Church St St Helens Merseyside WA10 1AX",
    "addr:housenumber":"37-39",
    "addr:postcode":"wa10 1ax",
    "addr:street":"Church St",
    "iso:country":"GB",
    "sg:address":"37-39 Church St",
    "sg:city":"St Helens",
    "sg:classifiers":[
        {
            "category":"Shopping",
            "subcategory":"Catalog Store",
            "type":"Retail Goods"
        }
    ],
    "sg:phone":"+44 1744 454897",
    "sg:postcode":"WA10 1AX",
    "sg:province":"Merseyside",
    "sg:tags":[
        "catalogue",
        "showroom"
    ],
    "wof:name":"Index The Catalogue Shop",
    "wof:placetype":"venue"
},
  "geometry": {"coordinates":[-2.7358310223,53.4523086548],"type":"Point"}
}