{
  "type": "Feature",
  "properties": {
    "iso:country":"GB",
    "sg:address":"Campbell Street, Belper",
    "sg:city":"Derby",
    "sg:classifiers":[
        {
            "category":"Professional",
            "subcategory":"Business Services",
            "type":"Services"
        },
        {
            "category":"Shopping",
            "subcategory":"Pets & Pet Supplies",
            "type":"Retail Goods"
        }
    ],
    "sg:phone":"+44 1773 828944",
    "sg:postcode":"DE56 1AP",
    "sg:province":"Derbyshire",
    "sg:tags":[
        "shop",
        "import",
        "export",
        "agent"
    ],
    "wof:name":"J B Pet Supplies",
    "wof:placetype":"venue"
},
  "geometry": {"coordinates":[-1.483113,53.022316],"type":"Point"}
}