{
  "type": "Feature",
  "properties": {
    "addr:full":"Malthouse Trading Estate, Brighton Road Shoreham-by-sea West Sussex BN43 6RJ",
    "addr:postcode":"bn43 6rj",
    "addr:street":"Trading Estate Brighton Road",
    "iso:country":"GB",
    "sg:address":"Malthouse Trading Estate, Brighton Road",
    "sg:city":"Shoreham-by-sea",
    "sg:classifiers":[
        {
            "category":"Manufacturing",
            "subcategory":"Building Materials",
            "type":"Manufacturing & Wholesale Goods"
        }
    ],
    "sg:phone":"+44 1273 870000",
    "sg:postcode":"BN43 6RJ",
    "sg:province":"West Sussex",
    "sg:tags":[
        "merchant",
        "builder"
    ],
    "wof:name":"Travis Perkins Trading Co. Ltd.",
    "wof:placetype":"venue"
},
  "geometry": {"coordinates":[-0.2764689922,50.8319168091],"type":"Point"}
}