{
  "type": "Feature",
  "properties": {
    "addr:full":"Unit 4b Sovereign Park Indust Est Market Harborough Leicestershire LE16 9EG",
    "addr:housenumber":"unit 4b",
    "addr:postcode":"le16 9eg",
    "addr:street":"Sovereign Park Indust Est",
    "iso:country":"GB",
    "sg:address":"Unit 4b Sovereign Park Indust Est",
    "sg:city":"Market Harborough",
    "sg:classifiers":[
        {
            "category":"Professional",
            "subcategory":"Computer Services",
            "type":"Services"
        }
    ],
    "sg:phone":"+44 1858 468828",
    "sg:postcode":"LE16 9EG",
    "sg:province":"Leicestershire",
    "sg:tags":[
        "system",
        "software"
    ],
    "wof:name":"Connectus Open Systems",
    "wof:placetype":"venue"
},
  "geometry": {"coordinates":[-0.9225789905,52.4793968201],"type":"Point"}
}