{
  "type": "Feature",
  "properties": {
    "addr:full":"52 Earl Howe Road, Holmer Green High Wycombe Buckinghamshire HP15 6PX",
    "addr:housenumber":"52",
    "addr:postcode":"hp15 6px",
    "addr:street":"Earl Howe Road",
    "iso:country":"GB",
    "sg:address":"52 Earl Howe Road, Holmer Green",
    "sg:city":"High Wycombe",
    "sg:classifiers":[
        {
            "category":"Retail",
            "subcategory":"Driving School",
            "type":"Services"
        }
    ],
    "sg:phone":"+44 1494 714958",
    "sg:postcode":"HP15 6PX",
    "sg:province":"Buckinghamshire",
    "wof:name":"EILEEN TAPPING",
    "wof:placetype":"venue"
},
  "geometry": {"coordinates":[-0.691742003,51.6621818542],"type":"Point"}
}