{
  "type": "Feature",
  "properties": {
    "addr:full":"15 East Reach Taunton Somerset TA1 3EW",
    "addr:housenumber":"15",
    "addr:postcode":"ta1 3ew",
    "addr:street":"East Reach",
    "iso:country":"GB",
    "sg:address":"15 East Reach",
    "sg:city":"Taunton",
    "sg:classifiers":[
        {
            "category":"Shopping",
            "subcategory":"Used Merchandise",
            "type":"Retail Goods"
        }
    ],
    "sg:phone":"+44 1823 254411",
    "sg:postcode":"TA1 3EW",
    "sg:province":"Somerset",
    "sg:tags":[
        "shop",
        "second-hand"
    ],
    "wof:name":"Toad Hall",
    "wof:placetype":"venue"
},
  "geometry": {"coordinates":[-3.0951390266,51.0151824951],"type":"Point"}
}