{
  "type": "Feature",
  "properties": {
    "iso:country":"GB",
    "sg:address":"1 Cornhill",
    "sg:city":"Lincoln",
    "sg:classifiers":[
        {
            "category":"Fast Food",
            "type":"Food & Drink"
        },
        {
            "category":"Restaurant",
            "type":"Food & Drink"
        }
    ],
    "sg:phone":"+44 1522 542934",
    "sg:postcode":"LN5 7HE",
    "sg:province":"Lincolnshire",
    "sg:tags":[
        "away",
        "take"
    ],
    "sg:website":"http://www.mcdonalds.co.uk",
    "wof:name":"Mcdonald'S Restaurants Ltd",
    "wof:placetype":"venue"
},
  "geometry": {"coordinates":[-0.539387,53.22723],"type":"Point"}
}