{
  "type": "Feature",
  "properties": {
    "iso:country":"GB",
    "sg:address":"Unit W13, Long Lane",
    "sg:city":"Warrington",
    "sg:classifiers":[
        {
            "category":"Professional",
            "subcategory":"Computer Services",
            "type":"Services"
        }
    ],
    "sg:phone":"+44 1925 632243",
    "sg:postcode":"WA2 8TX",
    "sg:province":"Cheshire",
    "sg:tags":[
        "system",
        "software"
    ],
    "wof:name":"System Works",
    "wof:placetype":"venue"
},
  "geometry": {"coordinates":[-2.591621,53.408428],"type":"Point"}
}