{
  "type": "Feature",
  "properties": {
    "addr:full":"19 Campden Road, Tuffley Gloucester Gloucestershire GL4 0HX",
    "addr:housenumber":"19",
    "addr:postcode":"gl4 0hx",
    "addr:street":"Campden Road",
    "iso:country":"GB",
    "sg:address":"19 Campden Road, Tuffley",
    "sg:city":"Gloucester",
    "sg:classifiers":[
        {
            "category":"Personal",
            "subcategory":"Beauty Salon",
            "type":"Services"
        },
        {
            "category":"Personal",
            "subcategory":"Barber",
            "type":"Services"
        }
    ],
    "sg:phone":"+44 1452 411712",
    "sg:postcode":"GL4 0HX",
    "sg:province":"Gloucestershire",
    "sg:tags":[
        "unisex",
        "hairdresser"
    ],
    "wof:name":"Kims Unisex Hair Salon",
    "wof:placetype":"venue"
},
  "geometry": {"coordinates":[-2.2470729351,51.8349189758],"type":"Point"}
}