{
  "type": "Feature",
  "properties": {
    "iso:country":"GB",
    "sg:address":"33 Hyndland Road",
    "sg:city":"Glasgow",
    "sg:classifiers":[
        {
            "category":"Education",
            "subcategory":"School",
            "type":"Public Place"
        },
        {
            "category":"Arts & Performance",
            "subcategory":"Theater",
            "type":"Entertainment"
        }
    ],
    "sg:postcode":"G12 9UY",
    "sg:province":"Glasgow City",
    "sg:tags":[
        "drama",
        "theatre"
    ],
    "wof:name":"Spotlight Stage School",
    "wof:placetype":"venue"
},
  "geometry": {"coordinates":[-4.304118,55.881428],"type":"Point"}
}