{
  "type": "Feature",
  "properties": {
    "iso:country":"GB",
    "sg:address":"71a Great Bridge",
    "sg:city":"Tipton",
    "sg:classifiers":[
        {
            "category":"Health Services",
            "subcategory":"Optometrist",
            "type":"Services"
        },
        {
            "category":"Shopping",
            "subcategory":"Optician",
            "type":"Retail Goods"
        }
    ],
    "sg:phone":"+44 121 557 1523",
    "sg:postcode":"DY4 7HF",
    "sg:province":"West Midlands",
    "sg:tags":[
        "ophthalmic"
    ],
    "wof:name":"Peter Bainbridge",
    "wof:placetype":"venue"
},
  "geometry": {"coordinates":[-2.0324940681,52.5300292969],"type":"Point"}
}