{
  "type": "Feature",
  "properties": {
    "addr:full":"Fore St Sidmouth Devon EX10 8AH",
    "addr:postcode":"ex10 8ah",
    "addr:street":"Fore St",
    "iso:country":"GB",
    "sg:address":"Fore St",
    "sg:city":"Sidmouth",
    "sg:classifiers":[
        {
            "category":"Bars & Pubs",
            "type":"Food & Drink"
        }
    ],
    "sg:phone":"+44 1395 513445",
    "sg:postcode":"EX10 8AH",
    "sg:province":"Devon",
    "sg:tags":[
        "pubs",
        "inn"
    ],
    "wof:name":"Finns",
    "wof:placetype":"venue"
},
  "geometry": {"coordinates":[-3.237419,50.67971],"type":"Point"}
}