{
  "type": "Feature",
  "properties": {
    "iso:country":"GB",
    "sg:address":"Mildred Sylvester Way",
    "sg:city":"Pontefract",
    "sg:classifiers":[
        {
            "category":"Shopping",
            "type":"Retail Goods"
        }
    ],
    "sg:phone":"+44 1302 304035",
    "sg:postcode":"WF6 1TA",
    "sg:province":"West Yorkshire",
    "sg:tags":[
        "part",
        "accessory"
    ],
    "wof:name":"Imperial Motor Components Ltd.",
    "wof:placetype":"venue"
},
  "geometry": {"coordinates":[-1.39379,53.698872],"type":"Point"}
}