{
  "type": "Feature",
  "properties": {
    "addr:full":"58 Queens Road Nuneaton Leicestershire CV11 5JZ",
    "addr:housenumber":"58",
    "addr:postcode":"cv11 5jz",
    "addr:street":"Queens Road",
    "iso:country":"GB",
    "sg:address":"58 Queens Road",
    "sg:city":"Nuneaton",
    "sg:classifiers":[
        {
            "category":"Shopping",
            "subcategory":"Used Merchandise",
            "type":"Retail Goods"
        }
    ],
    "sg:phone":"+44 24 7635 3688",
    "sg:postcode":"CV11 5JZ",
    "sg:province":"Leicestershire",
    "sg:tags":[
        "shop",
        "second-hand"
    ],
    "wof:name":"Cash Converters",
    "wof:placetype":"venue"
},
  "geometry": {"coordinates":[-1.4732149839,52.5223350525],"type":"Point"}
}