{
  "type": "Feature",
  "properties": {
    "iso:country":"GB",
    "sg:address":"18 Humberstone Road",
    "sg:city":"Andover",
    "sg:classifiers":[
        {
            "category":"Home & Garden",
            "subcategory":"Building Materials",
            "type":"Retail Goods"
        }
    ],
    "sg:phone":"+44 1264 361577",
    "sg:postcode":"SP10 2EJ",
    "sg:province":"Hampshire",
    "sg:tags":[
        "wire",
        "cable"
    ],
    "wof:name":"Wilders Consultants",
    "wof:placetype":"venue"
},
  "geometry": {"coordinates":[-1.48075,51.201916],"type":"Point"}
}