{
  "type": "Feature",
  "properties": {
    "iso:country":"GB",
    "sg:address":"St Johns Street",
    "sg:city":"Whitland",
    "sg:classifiers":[
        {
            "category":"Cafe",
            "type":"Food & Drink"
        }
    ],
    "sg:phone":"+44 1994 240033",
    "sg:postcode":"SA34 0AW",
    "sg:province":"Carmarthenshire",
    "sg:tags":[
        "tea",
        "room"
    ],
    "wof:name":"The Kebabe Ho",
    "wof:placetype":"venue"
},
  "geometry": {"coordinates":[-4.61433,51.819157],"type":"Point"}
}