{
  "type": "Feature",
  "properties": {
    "iso:country":"GB",
    "sg:address":"7 Lower Street, Cleobury Mortimer",
    "sg:city":"Kidderminster",
    "sg:classifiers":[
        {
            "category":"Retail",
            "subcategory":"Auto Repair",
            "type":"Services"
        }
    ],
    "sg:phone":"+44 1299 270208",
    "sg:postcode":"DY14 8AA",
    "sg:province":"Shropshire",
    "sg:tags":[
        "modification",
        "garage",
        "related"
    ],
    "wof:name":"Lower Street Garage Ltd.",
    "wof:placetype":"venue"
},
  "geometry": {"coordinates":[-2.477869,52.380917],"type":"Point"}
}