{
  "type": "Feature",
  "properties": {
    "addr:full":"Hockley Industrial Centre, 12 Hooley La Redhill Surrey RH1 6ET",
    "addr:housenumber":"12",
    "addr:postcode":"rh1 6et",
    "addr:street":"Hockley;Hooley La Redhill",
    "iso:country":"GB",
    "sg:address":"Hockley Industrial Centre, 12 Hooley La",
    "sg:city":"Redhill",
    "sg:classifiers":[
        {
            "category":"Building & Trades",
            "subcategory":"Construction",
            "type":"Services"
        }
    ],
    "sg:phone":"+44 1737 766775",
    "sg:postcode":"RH1 6ET",
    "sg:province":"Surrey",
    "sg:tags":[
        "joinery"
    ],
    "wof:name":"Paul Owen",
    "wof:placetype":"venue"
},
  "geometry": {"coordinates":[-0.1688790023,51.2381782532],"type":"Point"}
}