{
  "type": "Feature",
  "properties": {
    "iso:country":"GB",
    "sg:address":"2 Shortbridge Street",
    "sg:city":"Newtown",
    "sg:classifiers":[
        {
            "category":"Travel",
            "subcategory":"Travel Agent",
            "type":"Entertainment"
        }
    ],
    "sg:phone":"+44 1686 626576",
    "sg:postcode":"SY16 2LW",
    "sg:province":"Powys",
    "wof:name":"Travel Master Holidays Ltd.",
    "wof:placetype":"venue"
},
  "geometry": {"coordinates":[-3.314734,52.514931],"type":"Point"}
}