{
  "type": "Feature",
  "properties": {
    "iso:country":"GB",
    "sg:address":"Dorton House, Dorton",
    "sg:city":"Aylesbury",
    "sg:classifiers":[
        {
            "category":"Education",
            "subcategory":"School",
            "type":"Public Place"
        }
    ],
    "sg:phone":"+44 1844 238237",
    "sg:postcode":"HP18 9NG",
    "sg:province":"Buckinghamshire",
    "sg:tags":[
        "independent",
        "preparatory"
    ],
    "wof:name":"Ashfold School Ltd",
    "wof:placetype":"venue"
},
  "geometry": {"coordinates":[-1.013319,51.822796],"type":"Point"}
}