{
  "type": "Feature",
  "properties": {
    "addr:full":"Phoenix Adventure Playground, Cockshutt La Wolverhampton West Midlands WV2 3NP",
    "addr:postcode":"wv2 3np",
    "addr:street":"Cockshutt La Wolverhampton",
    "iso:country":"GB",
    "sg:address":"Phoenix Adventure Playground, Cockshutt La",
    "sg:city":"Wolverhampton",
    "sg:classifiers":[
        {
            "category":"Government",
            "subcategory":"Office",
            "type":"Public Place"
        }
    ],
    "sg:phone":"+44 1902 343094",
    "sg:postcode":"WV2 3NP",
    "sg:province":"West Midlands",
    "sg:tags":[
        "local"
    ],
    "wof:name":"Wolverhampton Borough Council",
    "wof:placetype":"venue"
},
  "geometry": {"coordinates":[-2.1214299202,52.5718688965],"type":"Point"}
}