{
  "type": "Feature",
  "properties": {
    "iso:country":"GB",
    "sg:address":"Grange Farm, Hodgson Lane, Upper Poppleton",
    "sg:city":"York",
    "sg:classifiers":[
        {
            "category":"Farming",
            "subcategory":"Crops",
            "type":"Manufacturing & Wholesale Goods"
        },
        {
            "category":"Farming",
            "subcategory":"Livestock Farm",
            "type":"Manufacturing & Wholesale Goods"
        }
    ],
    "sg:phone":"+44 1904 795229",
    "sg:postcode":"YO26 6PP",
    "sg:province":"North Yorkshire",
    "sg:tags":[
        "arable",
        "others"
    ],
    "wof:name":"C & T Parker",
    "wof:placetype":"venue"
},
  "geometry": {"coordinates":[-1.1520240307,53.978843689],"type":"Point"}
}