{
  "type": "Feature",
  "properties": {
    "addr:full":"Reception Classes, Salisbury Rd, Burton Christchurch Dorset BH23 7JN",
    "addr:postcode":"bh23 7jn",
    "addr:street":"Salisbury Rd",
    "iso:country":"GB",
    "sg:address":"Reception Classes, Salisbury Rd, Burton",
    "sg:city":"Christchurch",
    "sg:classifiers":[
        {
            "category":"Education",
            "subcategory":"School",
            "type":"Public Place"
        }
    ],
    "sg:postcode":"BH23 7JN",
    "sg:province":"Dorset",
    "sg:tags":[
        "local",
        "authority"
    ],
    "wof:name":"Dorset County Council",
    "wof:placetype":"venue"
},
  "geometry": {"coordinates":[-1.776564,50.73407],"type":"Point"}
}