{
  "type": "Feature",
  "properties": {
    "addr:full":"20 Riding Dene, Mickley Stocksfield Northumberland NE43 7DL",
    "addr:housenumber":"20",
    "addr:postcode":"ne43 7dl",
    "addr:street":"Riding Dene",
    "iso:country":"GB",
    "sg:address":"20 Riding Dene, Mickley",
    "sg:city":"Stocksfield",
    "sg:classifiers":[
        {
            "category":"Building & Trades",
            "subcategory":"Landscaping Services",
            "type":"Services"
        }
    ],
    "sg:phone":"+44 1661 842090",
    "sg:postcode":"NE43 7DL",
    "sg:province":"Northumberland",
    "sg:tags":[
        "landscape",
        "contractor"
    ],
    "wof:name":"Calum David Tordoff",
    "wof:placetype":"venue"
},
  "geometry": {"coordinates":[-1.916359,54.945709],"type":"Point"}
}