{
  "type": "Feature",
  "properties": {
    "addr:full":"58-60 West Norwood High Street London Greater London SE27 9NR",
    "addr:housenumber":"58-60",
    "addr:postcode":"se27 9nr",
    "addr:street":"West;High Street",
    "iso:country":"GB",
    "sg:address":"58-60 West Norwood High Street",
    "sg:city":"London",
    "sg:classifiers":[
        {
            "category":"Professional",
            "subcategory":"Business Services",
            "type":"Services"
        }
    ],
    "sg:phone":"+44 20 8670 7373",
    "sg:postcode":"SE27 9NR",
    "sg:province":"Greater London",
    "sg:tags":[
        "bookmaker"
    ],
    "wof:name":"E Coomes",
    "wof:placetype":"venue"
},
  "geometry": {"coordinates":[-0.1021300033,51.4307098389],"type":"Point"}
}