{
  "type": "Feature",
  "properties": {
    "iso:country":"GB",
    "sg:address":"58-60 West Norwood High Street",
    "sg:city":"London",
    "sg:classifiers":[
        {
            "category":"Professional",
            "subcategory":"Business Services",
            "type":"Services"
        }
    ],
    "sg:phone":"+44 20 8670 7373",
    "sg:postcode":"SE27 9NR",
    "sg:province":"Greater London",
    "sg:tags":[
        "bookmaker"
    ],
    "wof:name":"E Coomes",
    "wof:placetype":"venue"
},
  "geometry": {"coordinates":[-0.1021300033,51.4307098389],"type":"Point"}
}