{
  "type": "Feature",
  "properties": {
    "addr:full":"O'cott Barn, O'cott Lane, Scammonden Huddersfield West Yorkshire HD3 3FW",
    "addr:postcode":"hd3 3fw",
    "addr:street":"O'Cott Lane;West",
    "iso:country":"GB",
    "sg:address":"O'cott Barn, O'cott Lane, Scammonden",
    "sg:city":"Huddersfield",
    "sg:classifiers":[
        {
            "category":"Utilities",
            "subcategory":"Refuse",
            "type":"Services"
        }
    ],
    "sg:phone":"+44 1484 845948",
    "sg:postcode":"HD3 3FW",
    "sg:province":"West Yorkshire",
    "sg:tags":[
        "skip",
        "hire"
    ],
    "wof:name":"Colne Valley Skip Hire",
    "wof:placetype":"venue"
},
  "geometry": {"coordinates":[-1.899960041,53.6397705078],"type":"Point"}
}