{
  "type": "Feature",
  "properties": {
    "addr:full":"Hempstead Valley Shopping Centre, Hempstead Gillingham Kent ME7 3PB",
    "addr:postcode":"me7 3pb",
    "addr:street":"Hempstead;Shopping Centre",
    "iso:country":"GB",
    "sg:address":"Hempstead Valley Shopping Centre, Hempstead",
    "sg:city":"Gillingham",
    "sg:classifiers":[
        {
            "category":"Fast Food",
            "type":"Food & Drink"
        }
    ],
    "sg:phone":"+44 1634 371536",
    "sg:postcode":"ME7 3PB",
    "sg:province":"Kent",
    "sg:tags":[
        "away",
        "take"
    ],
    "wof:name":"K F C",
    "wof:placetype":"venue"
},
  "geometry": {"coordinates":[0.56876,51.349747],"type":"Point"}
}