{
  "type": "Feature",
  "properties": {
    "iso:country":"GB",
    "sg:address":"Unit 19 Peacock Industrial Estate, 20-22 White Hart Lane",
    "sg:city":"London",
    "sg:classifiers":[
        {
            "category":"Building & Trades",
            "subcategory":"Construction",
            "type":"Services"
        }
    ],
    "sg:postcode":"N17 8DT",
    "sg:province":"Greater London",
    "sg:tags":[
        "joiner",
        "carpenter"
    ],
    "wof:name":"Ryan Joinery Ltd.",
    "wof:placetype":"venue"
},
  "geometry": {"coordinates":[-0.06585,51.603279],"type":"Point"}
}