{
  "type": "Feature",
  "properties": {
    "addr:full":"Pelham House, Bridge Street Brigg Lincolnshire DN20 8NQ",
    "addr:postcode":"dn20 8nq",
    "addr:street":"Bridge Street",
    "iso:country":"GB",
    "sg:address":"Pelham House, Bridge Street",
    "sg:city":"Brigg",
    "sg:classifiers":[
        {
            "category":"Professional",
            "subcategory":"Employment Agencies",
            "type":"Services"
        }
    ],
    "sg:phone":"+44 1482 223323",
    "sg:postcode":"DN20 8NQ",
    "sg:province":"Lincolnshire",
    "sg:tags":[
        "consultant",
        "recruitment"
    ],
    "wof:name":"Appollo 2000 Recruitment Services",
    "wof:placetype":"venue"
},
  "geometry": {"coordinates":[-0.4945990145,53.551700592],"type":"Point"}
}