{
  "type": "Feature",
  "properties": {
    "iso:country":"GB",
    "sg:address":"241 Rake Lane",
    "sg:city":"Wallasey",
    "sg:classifiers":[
        {
            "category":"Shopping",
            "subcategory":"Clothing, Apparel, & Fashions",
            "type":"Retail Goods"
        }
    ],
    "sg:phone":"+44 151 639 7382",
    "sg:postcode":"CH45 5DJ",
    "sg:province":"Merseyside",
    "sg:tags":[
        "shop",
        "workwear",
        "protective"
    ],
    "wof:name":"MERSEYSIDE INDUSTRIAL SUPPLIES",
    "wof:placetype":"venue"
},
  "geometry": {"coordinates":[-3.042089,53.42709],"type":"Point"}
}