{
  "type": "Feature",
  "properties": {
    "addr:full":"40 Mellerstain Road Kirkcaldy Fife KY2 6UA",
    "addr:housenumber":"40",
    "addr:postcode":"ky2 6ua",
    "addr:street":"Mellerstain Road",
    "iso:country":"GB",
    "sg:address":"40 Mellerstain Road",
    "sg:city":"Kirkcaldy",
    "sg:classifiers":[
        {
            "category":"Professional",
            "subcategory":"Engineering",
            "type":"Services"
        }
    ],
    "sg:phone":"+44 1592 200245",
    "sg:postcode":"KY2 6UA",
    "sg:province":"Fife",
    "sg:tags":[
        "civil",
        "engineer"
    ],
    "wof:name":"Sub-K Civil Engineering/Building Contractors Ltd",
    "wof:placetype":"venue"
},
  "geometry": {"coordinates":[-3.1987230778,56.1235656738],"type":"Point"}
}