{
  "type": "Feature",
  "properties": {
    "addr:full":"433 North End Road London Greater London SW6 1NY",
    "addr:housenumber":"433",
    "addr:postcode":"sw6 1ny",
    "addr:street":"North End Road",
    "iso:country":"GB",
    "sg:address":"433 North End Road",
    "sg:city":"London",
    "sg:classifiers":[
        {
            "category":"Shopping",
            "subcategory":"Clothing, Apparel, & Fashions",
            "type":"Retail Goods"
        }
    ],
    "sg:phone":"+44 20 7386 5030",
    "sg:postcode":"SW6 1NY",
    "sg:province":"Greater London",
    "sg:tags":[
        "shop"
    ],
    "wof:name":"Raj Enterprises",
    "wof:placetype":"venue"
},
  "geometry": {"coordinates":[-0.199508,51.48193],"type":"Point"}
}