{
  "type": "Feature",
  "properties": {
    "iso:country":"GB",
    "sg:address":"214-216 High Street",
    "sg:city":"Guildford",
    "sg:classifiers":[
        {
            "category":"Health Services",
            "subcategory":"Optometrist",
            "type":"Services"
        },
        {
            "category":"Shopping",
            "subcategory":"Optician",
            "type":"Retail Goods"
        }
    ],
    "sg:phone":"+44 1483 561256",
    "sg:postcode":"GU1 3JB",
    "sg:province":"Surrey",
    "sg:tags":[
        "ophthalmic"
    ],
    "wof:name":"Nicklins Opticians",
    "wof:placetype":"venue"
},
  "geometry": {"coordinates":[-0.569005,51.236622],"type":"Point"}
}