{
  "type": "Feature",
  "properties": {
    "iso:country":"GB",
    "sg:address":"193 Newborough Road, Hall Green",
    "sg:city":"Birmingham",
    "sg:classifiers":[
        {
            "category":"Home & Garden",
            "subcategory":"Building Materials",
            "type":"Retail Goods"
        }
    ],
    "sg:phone":"+44 121 745 3501",
    "sg:postcode":"B28 0UU",
    "sg:province":"West Midlands",
    "sg:tags":[
        "fencing"
    ],
    "wof:name":"Harold R Phillips",
    "wof:placetype":"venue"
},
  "geometry": {"coordinates":[-1.8428790569,52.4140586853],"type":"Point"}
}