{
  "type": "Feature",
  "properties": {
    "iso:country":"GB",
    "sg:address":"Music Hall Passage, St Werburgh Street",
    "sg:city":"Chester",
    "sg:classifiers":[
        {
            "category":"Bars & Pubs",
            "subcategory":"Wine Bar",
            "type":"Food & Drink"
        }
    ],
    "sg:phone":"+44 1244 354041",
    "sg:postcode":"CH1 2EU",
    "sg:province":"Cheshire",
    "wof:name":"Loaf",
    "wof:placetype":"venue"
},
  "geometry": {"coordinates":[-2.894369,53.188129],"type":"Point"}
}