{
  "type": "Feature",
  "properties": {
    "addr:full":"7 The Spires Shopping Centre, High Street Barnet Hertfordshire EN5 5XY",
    "addr:housenumber":"7",
    "addr:postcode":"en5 5xy",
    "addr:street":"The Spires;High Street",
    "iso:country":"GB",
    "sg:address":"7 The Spires Shopping Centre, High Street",
    "sg:city":"Barnet",
    "sg:classifiers":[
        {
            "category":"Shopping",
            "subcategory":"Clothing, Apparel, & Fashions",
            "type":"Retail Goods"
        }
    ],
    "sg:phone":"+44 20 8441 4833",
    "sg:postcode":"EN5 5XY",
    "sg:province":"Hertfordshire",
    "sg:tags":[
        "lingerie",
        "hosiery"
    ],
    "wof:name":"Contessa",
    "wof:placetype":"venue"
},
  "geometry": {"coordinates":[-0.1982599944,51.6521186829],"type":"Point"}
}