{
  "type": "Feature",
  "properties": {
    "iso:country":"GB",
    "sg:address":"Hawthorn Hill, Stainton",
    "sg:city":"Kendal",
    "sg:classifiers":[
        {
            "category":"Professional",
            "subcategory":"Management & Consulting",
            "type":"Services"
        },
        {
            "category":"Social Services",
            "subcategory":"Job Training",
            "type":"Services"
        }
    ],
    "sg:phone":"+44 15395 61311",
    "sg:postcode":"LA8 0LQ",
    "sg:province":"Cumbria",
    "sg:tags":[
        "consultant",
        "provider"
    ],
    "wof:name":"Rob Kelly & Associates",
    "wof:placetype":"venue"
},
  "geometry": {"coordinates":[-2.7314751148,54.2667274475],"type":"Point"}
}