{
  "type": "Feature",
  "properties": {
    "addr:full":"Crescent House, 51high Street Billericay Essex CM12 9AX",
    "addr:housenumber":"51high",
    "addr:postcode":"cm12 9ax",
    "addr:street":"Street",
    "iso:country":"GB",
    "sg:address":"Crescent House, 51high Street",
    "sg:city":"Billericay",
    "sg:classifiers":[
        {
            "category":"Professional",
            "subcategory":"Management & Consulting",
            "type":"Services"
        }
    ],
    "sg:phone":"+44 1277 623042",
    "sg:postcode":"CM12 9AX",
    "sg:province":"Essex",
    "sg:tags":[
        "marketing",
        "consultant"
    ],
    "wof:name":"Advertising & Promotion Management",
    "wof:placetype":"venue"
},
  "geometry": {"coordinates":[0.4100199938,51.617401123],"type":"Point"}
}