{
  "type": "Feature",
  "properties": {
    "addr:full":"48a Barton Hill Road Torquay Devon TQ2 8JD",
    "addr:housenumber":"48a",
    "addr:postcode":"tq2 8jd",
    "addr:street":"Barton Hill Road",
    "iso:country":"GB",
    "sg:address":"48a Barton Hill Road",
    "sg:city":"Torquay",
    "sg:classifiers":[
        {
            "category":"Health Services",
            "subcategory":"Chiropractor",
            "type":"Services"
        }
    ],
    "sg:postcode":"TQ2 8JD",
    "sg:province":"Devon",
    "wof:name":"Chiropractic Health Care Clinic",
    "wof:placetype":"venue"
},
  "geometry": {"coordinates":[-3.541621,50.487801],"type":"Point"}
}