{
  "type": "Feature",
  "properties": {
    "addr:full":"Within Clements 29 The Parade, High St Watford Hertfordshire WD1 1LX",
    "addr:housenumber":"29",
    "addr:postcode":"wd1 1lx",
    "addr:street":"The Parade High St",
    "iso:country":"GB",
    "sg:address":"Within Clements 29 The Parade, High St",
    "sg:city":"Watford",
    "sg:classifiers":[
        {
            "category":"Personal",
            "subcategory":"Beauty Salon",
            "type":"Services"
        }
    ],
    "sg:phone":"+44 1923 238043",
    "sg:postcode":"WD1 1LX",
    "sg:province":"Hertfordshire",
    "sg:tags":[
        "unisex",
        "hairdresser"
    ],
    "wof:name":"Essanelle Hair & Beauty Salon",
    "wof:placetype":"venue"
},
  "geometry": {"coordinates":[-0.39072,51.652119],"type":"Point"}
}