{
  "type": "Feature",
  "properties": {
    "addr:full":"Castle Industrail Estate, Chesterfield Road, Bolsover Chesterfield Derbyshire S44 6BH",
    "addr:postcode":"s44 6bh",
    "addr:street":"Industrail Estate Chesterfield Road",
    "iso:country":"GB",
    "sg:address":"Castle Industrail Estate, Chesterfield Road, Bolsover",
    "sg:city":"Chesterfield",
    "sg:classifiers":[
        {
            "category":"Manufacturing",
            "subcategory":"Metals",
            "type":"Manufacturing & Wholesale Goods"
        }
    ],
    "sg:phone":"+44 1246 826363",
    "sg:postcode":"S44 6BH",
    "sg:province":"Derbyshire",
    "sg:tags":[
        "work",
        "sheet"
    ],
    "wof:name":"M & J Products",
    "wof:placetype":"venue"
},
  "geometry": {"coordinates":[-1.2900710106,53.2290916443],"type":"Point"}
}