{
  "type": "Feature",
  "properties": {
    "iso:country":"GB",
    "sg:address":"Pasture Lane",
    "sg:city":"Nottingham",
    "sg:classifiers":[
        {
            "category":"Shopping",
            "subcategory":"Gifts & Souvenirs",
            "type":"Retail Goods"
        }
    ],
    "sg:phone":"+44 115 984 5679",
    "sg:postcode":"NG11 6AG",
    "sg:province":"Nottinghamshire",
    "sg:tags":[
        "diy"
    ],
    "wof:name":"Artex-Blue Hawk Ltd.",
    "wof:placetype":"venue"
},
  "geometry": {"coordinates":[-1.160732,52.895607],"type":"Point"}
}