{
  "type": "Feature",
  "properties": {
    "iso:country":"GB",
    "sg:address":"Osmonds Farm, Culmstock",
    "sg:city":"Cullompton",
    "sg:classifiers":[
        {
            "category":"Farming",
            "subcategory":"Livestock Farm",
            "type":"Manufacturing & Wholesale Goods"
        }
    ],
    "sg:postcode":"EX15 3JZ",
    "sg:province":"Devon",
    "sg:tags":[
        "others"
    ],
    "wof:name":"Timothy Charles Stuart Andrews",
    "wof:placetype":"venue"
},
  "geometry": {"coordinates":[-3.279414,50.914421],"type":"Point"}
}