{
  "type": "Feature",
  "properties": {
    "iso:country":"GB",
    "sg:address":"24-28 Addington Street",
    "sg:city":"Margate",
    "sg:classifiers":[
        {
            "category":"Home & Garden",
            "subcategory":"Building Materials",
            "type":"Retail Goods"
        },
        {
            "category":"Building & Trades",
            "subcategory":"Landfill",
            "type":"Services"
        }
    ],
    "sg:phone":"+44 1843 295217",
    "sg:postcode":"CT9 1PW",
    "sg:province":"Kent",
    "sg:tags":[
        "blind",
        "shutter",
        "canopy",
        "door"
    ],
    "wof:name":"Phillips Blinds",
    "wof:placetype":"venue"
},
  "geometry": {"coordinates":[1.385093,51.38707],"type":"Point"}
}