{
  "type": "Feature",
  "properties": {
    "iso:country":"GB",
    "sg:address":"187 Findon Road, Findon",
    "sg:city":"Worthing",
    "sg:classifiers":[
        {
            "category":"Retail",
            "subcategory":"Auto Repair",
            "type":"Services"
        }
    ],
    "sg:phone":"+44 1903 873022",
    "sg:postcode":"BN14 0EP",
    "sg:province":"West Sussex",
    "sg:tags":[
        "modification",
        "garage"
    ],
    "wof:name":"Anca Garage (Worthing) Ltd.",
    "wof:placetype":"venue"
},
  "geometry": {"coordinates":[-0.3991329968,50.8503723145],"type":"Point"}
}