{
  "type": "Feature",
  "properties": {
    "addr:full":"33 St Swithin Street Aberdeen Aberdeen City AB10 6XL",
    "addr:housenumber":"33",
    "addr:postcode":"ab10 6xl",
    "addr:street":"St Swithin Street",
    "iso:country":"GB",
    "sg:address":"33 St Swithin Street",
    "sg:city":"Aberdeen",
    "sg:classifiers":[
        {
            "category":"Building & Trades",
            "subcategory":"Construction",
            "type":"Services"
        }
    ],
    "sg:postcode":"AB10 6XL",
    "sg:province":"Aberdeen City",
    "sg:tags":[
        "builder"
    ],
    "wof:name":"Churchill Drilling Tools Ltd.",
    "wof:placetype":"venue"
},
  "geometry": {"coordinates":[-2.1252009869,57.1404571533],"type":"Point"}
}