{
  "type": "Feature",
  "properties": {
    "addr:full":"32 High Street, Brightlingsea Colchester Essex CO7 0AG",
    "addr:housenumber":"32",
    "addr:postcode":"co7 0ag",
    "addr:street":"High Street",
    "iso:country":"GB",
    "sg:address":"32 High Street, Brightlingsea",
    "sg:city":"Colchester",
    "sg:classifiers":[
        {
            "category":"Home & Garden",
            "subcategory":"Carpets & Floor Coverings",
            "type":"Retail Goods"
        }
    ],
    "sg:postcode":"CO7 0AG",
    "sg:province":"Essex",
    "sg:tags":[
        "carpets",
        "rug",
        "matting"
    ],
    "wof:name":"Carpet Station",
    "wof:placetype":"venue"
},
  "geometry": {"coordinates":[1.027563,51.810387],"type":"Point"}
}