{
  "type": "Feature",
  "properties": {
    "addr:full":"Aylestone Lane Wigston Leicestershire LE18 1AB",
    "addr:postcode":"le18 1ab",
    "addr:street":"Aylestone Lane",
    "iso:country":"GB",
    "sg:address":"Aylestone Lane",
    "sg:city":"Wigston",
    "sg:classifiers":[
        {
            "category":"Health Services",
            "subcategory":"Nursing And Care Facility",
            "type":"Services"
        },
        {
            "category":"Social Services",
            "subcategory":"Retirement Home",
            "type":"Services"
        }
    ],
    "sg:phone":"+44 116 288 7516",
    "sg:postcode":"LE18 1AB",
    "sg:province":"Leicestershire",
    "sg:tags":[
        "residential"
    ],
    "wof:name":"Curtis Weston House Residential Home",
    "wof:placetype":"venue"
},
  "geometry": {"coordinates":[-1.1247639656,52.5926094055],"type":"Point"}
}