{
  "type": "Feature",
  "properties": {
    "addr:full":"The Chequers, 28 White Horse Street Baldock Bedfordshire SG7 6QQ",
    "addr:housenumber":"28",
    "addr:postcode":"sg7 6qq",
    "addr:street":"White Horse Street",
    "iso:country":"GB",
    "sg:address":"The Chequers, 28 White Horse Street",
    "sg:city":"Baldock",
    "sg:classifiers":[
        {
            "category":"Professional",
            "subcategory":"Computer Services",
            "type":"Services"
        }
    ],
    "sg:phone":"+44 1462 895999",
    "sg:postcode":"SG7 6QQ",
    "sg:province":"Bedfordshire",
    "sg:tags":[
        "information"
    ],
    "wof:name":"New Media Services Ltd.",
    "wof:placetype":"venue"
},
  "geometry": {"coordinates":[-0.187854,51.98877],"type":"Point"}
}