{
  "type": "Feature",
  "properties": {
    "iso:country":"GB",
    "sg:address":"Acumen Place, Lonsdale Gardens",
    "sg:city":"Tunbridge Wells",
    "sg:classifiers":[
        {
            "category":"Utilities",
            "type":"Services"
        }
    ],
    "sg:postcode":"TN1 1NU",
    "sg:province":"Kent",
    "sg:tags":[
        "internet"
    ],
    "wof:name":"Multi-Faceted Ltd",
    "wof:placetype":"venue"
},
  "geometry": {"coordinates":[0.2635500133,51.1333732605],"type":"Point"}
}