{
  "type": "Feature",
  "properties": {
    "iso:country":"GB",
    "sg:address":"Whitehouse, Chirnside",
    "sg:city":"Duns",
    "sg:classifiers":[
        {
            "category":"Shopping",
            "type":"Retail Goods"
        }
    ],
    "sg:postcode":"TD11 3XL",
    "sg:province":"East Lothian",
    "sg:tags":[
        "merchant"
    ],
    "wof:name":"Farmery Seeds Lime & Fertilisers",
    "wof:placetype":"venue"
},
  "geometry": {"coordinates":[-2.3411068916,55.7757759094],"type":"Point"}
}