{
  "type": "Feature",
  "properties": {
    "addr:full":"44 Hill Rise Richmond Greater London TW10 6UF",
    "addr:housenumber":"44",
    "addr:postcode":"tw10 6uf",
    "addr:street":"Hill Rise",
    "iso:country":"GB",
    "sg:address":"44 Hill Rise",
    "sg:city":"Richmond",
    "sg:classifiers":[
        {
            "category":"Shopping",
            "subcategory":"Clothing, Apparel, & Fashions",
            "type":"Retail Goods"
        }
    ],
    "sg:phone":"+44 20 8948 0199",
    "sg:postcode":"TW10 6UF",
    "sg:province":"Greater London",
    "sg:tags":[
        "shop"
    ],
    "wof:name":"Anna",
    "wof:placetype":"venue"
},
  "geometry": {"coordinates":[-0.30427,51.457611],"type":"Point"}
}