{
  "type": "Feature",
  "properties": {
    "addr:full":"8 Northfield Rd Princes Risborough Buckinghamshire HP27 0HY",
    "addr:housenumber":"8",
    "addr:postcode":"hp27 0hy",
    "addr:street":"Northfield Rd",
    "iso:country":"GB",
    "sg:address":"8 Northfield Rd",
    "sg:city":"Princes Risborough",
    "sg:classifiers":[
        {
            "category":"Bus Charters",
            "type":"Transportation"
        }
    ],
    "sg:phone":"+44 1494 444551",
    "sg:postcode":"HP27 0HY",
    "sg:province":"Buckinghamshire",
    "sg:tags":[
        "hire",
        "coach"
    ],
    "wof:name":"Harlequin Travel",
    "wof:placetype":"venue"
},
  "geometry": {"coordinates":[-0.8218610287,51.7256660461],"type":"Point"}
}