{
  "type": "Feature",
  "properties": {
    "iso:country":"GB",
    "sg:address":"19 Boscobel Road North",
    "sg:city":"St Leonards-on-sea",
    "sg:classifiers":[
        {
            "category":"Building & Trades",
            "subcategory":"Landscaping Services",
            "type":"Services"
        }
    ],
    "sg:postcode":"TN38 0NY",
    "sg:province":"East Sussex",
    "sg:tags":[
        "designer",
        "architect",
        "landscape"
    ],
    "wof:name":"Albion Design",
    "wof:placetype":"venue"
},
  "geometry": {"coordinates":[0.5481470227,50.8558921814],"type":"Point"}
}