{
  "type": "Feature",
  "properties": {
    "addr:full":"Animal Quarantine Section, Beacon Rd Hounslow Greater London TW6 3JF",
    "addr:postcode":"tw6 3jf",
    "addr:street":"Beacon Rd",
    "iso:country":"GB",
    "sg:address":"Animal Quarantine Section, Beacon Rd",
    "sg:city":"Hounslow",
    "sg:classifiers":[
        {
            "category":"Government",
            "subcategory":"Office",
            "type":"Public Place"
        }
    ],
    "sg:phone":"+44 20 8745 7894",
    "sg:postcode":"TW6 3JF",
    "sg:province":"Greater London",
    "sg:tags":[
        "local"
    ],
    "wof:name":"Corporation of London",
    "wof:placetype":"venue"
},
  "geometry": {"coordinates":[-0.4559000134,51.4560317993],"type":"Point"}
}