{
  "type": "Feature",
  "properties": {
    "iso:country":"GB",
    "sg:address":"The Rectory",
    "sg:city":"Andover",
    "sg:classifiers":[
        {
            "category":"Place Of Worship",
            "type":"Public Place"
        }
    ],
    "sg:phone":"+44 1264 772414",
    "sg:postcode":"SP11 9HX",
    "sg:province":"Hampshire",
    "wof:name":"Fyfield C Of E Church",
    "wof:placetype":"venue"
},
  "geometry": {"coordinates":[-1.55898,51.236919],"type":"Point"}
}