{
  "type": "Feature",
  "properties": {
    "addr:full":"1st Floor Albion Court, 5 Albion Place Leeds West Yorkshire LS1 6JL",
    "addr:housenumber":"5",
    "addr:postcode":"ls1 6jl",
    "addr:street":"Albion Place",
    "iso:country":"GB",
    "sg:address":"1st Floor Albion Court, 5 Albion Place",
    "sg:city":"Leeds",
    "sg:classifiers":[
        {
            "category":"Personal",
            "subcategory":"Skin Care",
            "type":"Services"
        }
    ],
    "sg:phone":"+44 113 242 5020",
    "sg:postcode":"LS1 6JL",
    "sg:province":"West Yorkshire",
    "sg:tags":[
        "surgery",
        "cosmetic"
    ],
    "wof:name":"The Harley Medical Group",
    "wof:placetype":"venue"
},
  "geometry": {"coordinates":[-1.5438649654,53.7980728149],"type":"Point"}
}