{
  "type": "Feature",
  "properties": {
    "addr:full":"Watton Service Centre, Brandon Road, Watton Thetford Norfolk IP25 6AL",
    "addr:postcode":"ip25 6al",
    "addr:street":"Brandon Road",
    "iso:country":"GB",
    "sg:address":"Watton Service Centre, Brandon Road, Watton",
    "sg:city":"Thetford",
    "sg:classifiers":[
        {
            "category":"Retail",
            "subcategory":"Auto Repair",
            "type":"Services"
        }
    ],
    "sg:phone":"+44 1953 885783",
    "sg:postcode":"IP25 6AL",
    "sg:province":"Norfolk",
    "sg:tags":[
        "modification",
        "garage"
    ],
    "wof:name":"K & G Service and Repair Station",
    "wof:placetype":"venue"
},
  "geometry": {"coordinates":[0.8296499848,52.5707168579],"type":"Point"}
}