{
  "type": "Feature",
  "properties": {
    "addr:full":"9 Tower St Selkirk Scottish Borders TD7 4LR",
    "addr:housenumber":"9",
    "addr:postcode":"td7 4lr",
    "addr:street":"Tower St Selkirk",
    "iso:country":"GB",
    "sg:address":"9 Tower St",
    "sg:city":"Selkirk",
    "sg:classifiers":[
        {
            "category":"Professional",
            "subcategory":"Art Services",
            "type":"Services"
        }
    ],
    "sg:phone":"+44 1750 20521",
    "sg:postcode":"TD7 4LR",
    "sg:province":"Scottish Borders",
    "sg:tags":[
        "photographer"
    ],
    "wof:name":"Ron Ballantyne",
    "wof:placetype":"venue"
},
  "geometry": {"coordinates":[-2.827121,55.533382],"type":"Point"}
}