{
  "type": "Feature",
  "properties": {
    "addr:full":"Leigh Commerce Park, Greenfold Way Leigh Lancashire WN7 3XJ",
    "addr:postcode":"wn7 3xj",
    "addr:street":"Commerce Park Greenfold Way Leigh",
    "iso:country":"GB",
    "sg:address":"Leigh Commerce Park, Greenfold Way",
    "sg:city":"Leigh",
    "sg:classifiers":[
        {
            "category":"Shopping",
            "subcategory":"Computers & Home Electronics",
            "type":"Retail Goods"
        }
    ],
    "sg:phone":"+44 1942 685200",
    "sg:postcode":"WN7 3XJ",
    "sg:province":"Lancashire",
    "sg:tags":[
        "component",
        "electronic"
    ],
    "wof:name":"Pencon",
    "wof:placetype":"venue"
},
  "geometry": {"coordinates":[-2.5008990765,53.4833564758],"type":"Point"}
}