{
  "type": "Feature",
  "properties": {
    "iso:country":"GB",
    "sg:address":"Doncaster Road",
    "sg:city":"Wakefield",
    "sg:classifiers":[
        {
            "category":"Restaurant",
            "type":"Food & Drink"
        }
    ],
    "sg:phone":"+44 1924 862730",
    "sg:postcode":"WF4 1RR",
    "sg:province":"West Yorkshire",
    "wof:name":"Alvin  Worth",
    "wof:placetype":"venue"
},
  "geometry": {"coordinates":[-1.451605,53.665211],"type":"Point"}
}