{
  "type": "Feature",
  "properties": {
    "iso:country":"GB",
    "sg:address":"46 Shortmead Street",
    "sg:city":"Biggleswade",
    "sg:classifiers":[
        {
            "category":"Shopping",
            "subcategory":"Antiques",
            "type":"Retail Goods"
        }
    ],
    "sg:phone":"+44 1767 601780",
    "sg:postcode":"SG18 0AP",
    "sg:province":"Bedfordshire",
    "wof:name":"Shortmead Antiques",
    "wof:placetype":"venue"
},
  "geometry": {"coordinates":[-0.266804,52.088509],"type":"Point"}
}