{
  "type": "Feature",
  "properties": {
    "iso:country":"GB",
    "sg:address":"61 Junction Road",
    "sg:city":"London",
    "sg:classifiers":[
        {
            "category":"Restaurant",
            "type":"Food & Drink"
        },
        {
            "category":"Cafe",
            "type":"Food & Drink"
        }
    ],
    "sg:phone":"+44 20 7561 0991",
    "sg:postcode":"N19 5QU",
    "sg:province":"Greater London",
    "sg:tags":[
        "tea",
        "room"
    ],
    "wof:name":"H Erbil",
    "wof:placetype":"venue"
},
  "geometry": {"coordinates":[-0.135196,51.56385],"type":"Point"}
}