{
  "type": "Feature",
  "properties": {
    "iso:country":"GB",
    "sg:address":"P O Box 24",
    "sg:city":"Bolton",
    "sg:classifiers":[
        {
            "category":"Government",
            "subcategory":"Court House",
            "type":"Public Place"
        }
    ],
    "sg:phone":"+44 1204 522244",
    "sg:postcode":"BL1 1QX",
    "sg:province":"Lancashire",
    "wof:name":"Bolton Magistrates Court",
    "wof:placetype":"venue"
},
  "geometry": {"coordinates":[-2.4276790619,53.5801582336],"type":"Point"}
}