{
  "type": "Feature",
  "properties": {
    "addr:full":"7 Lon Ddwr, Talybont Bangor Gwynedd LL57 3UT",
    "addr:housenumber":"7",
    "addr:postcode":"ll57 3ut",
    "addr:street":"Lon Ddwr Talybont",
    "iso:country":"GB",
    "sg:address":"7 Lon Ddwr, Talybont",
    "sg:city":"Bangor",
    "sg:classifiers":[
        {
            "category":"Government",
            "subcategory":"Post Office",
            "type":"Public Place"
        }
    ],
    "sg:phone":"+44 1248 352950",
    "sg:postcode":"LL57 3UT",
    "sg:province":"Gwynedd",
    "wof:name":"R Hughes",
    "wof:placetype":"venue"
},
  "geometry": {"coordinates":[-4.058578968,53.182800293],"type":"Point"}
}