{
  "type": "Feature",
  "properties": {
    "iso:country":"GB",
    "sg:address":"174 Upper Tooting Road",
    "sg:city":"London",
    "sg:classifiers":[
        {
            "category":"Personal",
            "subcategory":"Beauty Salon",
            "type":"Services"
        }
    ],
    "sg:postcode":"SW17 7ER",
    "sg:province":"Greater London",
    "sg:tags":[
        "unisex",
        "hairdresser"
    ],
    "wof:name":"Hair Line Junction",
    "wof:placetype":"venue"
},
  "geometry": {"coordinates":[-0.1642629951,51.4319572449],"type":"Point"}
}