{
  "type": "Feature",
  "properties": {
    "addr:full":"166 Blackburn Road Bolton Lancashire BL1 8DR",
    "addr:housenumber":"166",
    "addr:postcode":"bl1 8dr",
    "addr:street":"Blackburn Road",
    "iso:country":"GB",
    "sg:address":"166 Blackburn Road",
    "sg:city":"Bolton",
    "sg:classifiers":[
        {
            "category":"Shopping",
            "subcategory":"Gifts & Souvenirs",
            "type":"Retail Goods"
        },
        {
            "category":"Government",
            "subcategory":"Post Office",
            "type":"Public Place"
        }
    ],
    "sg:phone":"+44 1204 527902",
    "sg:postcode":"BL1 8DR",
    "sg:province":"Lancashire",
    "sg:tags":[
        "poster",
        "card"
    ],
    "wof:name":"North End Post Office",
    "wof:placetype":"venue"
},
  "geometry": {"coordinates":[-2.4306960106,53.5911750793],"type":"Point"}
}