{
  "type": "Feature",
  "properties": {
    "iso:country":"GB",
    "sg:address":"9 New Church Rd",
    "sg:city":"Camberwell",
    "sg:classifiers":[
        {
            "category":"Personal",
            "subcategory":"Beauty Salon",
            "type":"Services"
        }
    ],
    "sg:phone":"+44 20 7657 2021",
    "sg:postcode":"SE5 7JH",
    "sg:province":"Greater London",
    "sg:tags":[
        "unisex",
        "hairdresser"
    ],
    "wof:name":"Look The",
    "wof:placetype":"venue"
},
  "geometry": {"coordinates":[-0.0936560035,51.4795722961],"type":"Point"}
}