{
  "type": "Feature",
  "properties": {
    "iso:country":"GB",
    "sg:address":"9du Trueway Drive, Shepshed",
    "sg:city":"Loughborough",
    "sg:classifiers":[
        {
            "category":"Professional",
            "subcategory":"Business Services",
            "type":"Services"
        }
    ],
    "sg:postcode":"LE12 9YT",
    "sg:province":"Leicestershire",
    "sg:tags":[
        "import",
        "export",
        "agent"
    ],
    "wof:name":"Nedtron Ltd.",
    "wof:placetype":"venue"
},
  "geometry": {"coordinates":[-1.2839570045,52.7670516968],"type":"Point"}
}