{
  "type": "Feature",
  "properties": {
    "iso:country":"GB",
    "sg:address":"Hill View Rd",
    "sg:city":"Romsey",
    "sg:classifiers":[
        {
            "category":"Shopping",
            "subcategory":"Department Store",
            "type":"Retail Goods"
        }
    ],
    "sg:phone":"+44 1794 368326",
    "sg:postcode":"SO51 0PP",
    "sg:province":"Hampshire",
    "wof:name":"Braishfield Post Office",
    "wof:placetype":"venue"
},
  "geometry": {"coordinates":[-1.467174,51.022186],"type":"Point"}
}