{
  "type": "Feature",
  "properties": {
    "addr:full":"Unit 5 Forge Industrial Park, North Roskear Camborne Cornwall TR14 0AW",
    "addr:housenumber":"unit 5",
    "addr:postcode":"tr14 0aw",
    "addr:street":"Forge Industrial Park North Roskear",
    "iso:country":"GB",
    "sg:address":"Unit 5 Forge Industrial Park, North Roskear",
    "sg:city":"Camborne",
    "sg:classifiers":[
        {
            "category":"Retail",
            "subcategory":"Auto Repair",
            "type":"Services"
        }
    ],
    "sg:phone":"+44 1209 612700",
    "sg:postcode":"TR14 0AW",
    "sg:province":"Cornwall",
    "sg:tags":[
        "electrician"
    ],
    "wof:name":"Steve's Auto Sparks",
    "wof:placetype":"venue"
},
  "geometry": {"coordinates":[-5.28997,50.223621],"type":"Point"}
}