{
  "type": "Feature",
  "properties": {
    "addr:full":"62a Garden Walk, Metrocentre Gateshead Tyne and Wear NE11 9XZ",
    "addr:housenumber":"62a",
    "addr:postcode":"ne11 9xz",
    "addr:street":"Garden Walk",
    "iso:country":"GB",
    "sg:address":"62a Garden Walk, Metrocentre",
    "sg:city":"Gateshead",
    "sg:classifiers":[
        {
            "category":"Shopping",
            "subcategory":"Mobile Phones",
            "type":"Retail Goods"
        }
    ],
    "sg:phone":"+44 191 461 1415",
    "sg:postcode":"NE11 9XZ",
    "sg:province":"Tyne and Wear",
    "wof:name":"Phonehouse",
    "wof:placetype":"venue"
},
  "geometry": {"coordinates":[-1.66854,54.957661],"type":"Point"}
}