{
  "type": "Feature",
  "properties": {
    "addr:full":"Unit 16, Bedford St, Shelton Stoke On Trent Staffordshire ST1 4PZ",
    "addr:housenumber":"unit 16",
    "addr:postcode":"st1 4pz",
    "addr:street":"Bedford St",
    "iso:country":"GB",
    "sg:address":"Unit 16, Bedford St, Shelton",
    "sg:city":"Stoke On Trent",
    "sg:classifiers":[
        {
            "category":"Arts & Performance",
            "subcategory":"Music",
            "type":"Entertainment"
        }
    ],
    "sg:phone":"+44 1782 206555",
    "sg:postcode":"ST1 4PZ",
    "sg:province":"Staffordshire",
    "sg:tags":[
        "mobile",
        "disco"
    ],
    "wof:name":"Dazzal & Blast",
    "wof:placetype":"venue"
},
  "geometry": {"coordinates":[-2.186353,53.017632],"type":"Point"}
}