{
  "type": "Feature",
  "properties": {
    "iso:country":"GB",
    "sg:address":"The Homestead, Prees Green",
    "sg:city":"Whitchurch",
    "sg:classifiers":[
        {
            "category":"Shopping",
            "subcategory":"Stationery & Office Supplies",
            "type":"Retail Goods"
        }
    ],
    "sg:phone":"+44 1948 841145",
    "sg:postcode":"SY13 2BN",
    "sg:province":"Cheshire",
    "sg:tags":[
        "item",
        "promotional"
    ],
    "wof:name":"Brand Mark",
    "wof:placetype":"venue"
},
  "geometry": {"coordinates":[-2.644243,52.881813],"type":"Point"}
}