{
  "type": "Feature",
  "properties": {
    "addr:full":"12 Madeira Place Brighton East Sussex BN2 1TN",
    "addr:housenumber":"12",
    "addr:postcode":"bn2 1tn",
    "addr:street":"Madeira Place",
    "iso:country":"GB",
    "sg:address":"12 Madeira Place",
    "sg:city":"Brighton",
    "sg:classifiers":[
        {
            "category":"Travel",
            "subcategory":"Hotels & Motels",
            "type":"Entertainment"
        }
    ],
    "sg:postcode":"BN2 1TN",
    "sg:province":"East Sussex",
    "sg:tags":[
        "house",
        "guest"
    ],
    "wof:name":"Pavilion Guest House",
    "wof:placetype":"venue"
},
  "geometry": {"coordinates":[-0.134325996,50.8205184937],"type":"Point"}
}