{
  "type": "Feature",
  "properties": {
    "addr:full":"Staunton Harrold Hall, Melborne Road Staunton Harrold Ashby-de-la-zouch Derbyshire LE65 1RT",
    "addr:postcode":"le65 1rt",
    "addr:street":"Melborne Road;Derbyshire",
    "iso:country":"GB",
    "sg:address":"Staunton Harrold Hall, Melborne Road Staunton Harrold",
    "sg:city":"Ashby-de-la-zouch",
    "sg:classifiers":[
        {
            "category":"Professional",
            "subcategory":"Computer Services",
            "type":"Services"
        }
    ],
    "sg:phone":"+44 1332 856390",
    "sg:postcode":"LE65 1RT",
    "sg:province":"Derbyshire",
    "sg:tags":[
        "system",
        "software"
    ],
    "wof:name":"Highgrove Computer Services Ltd.",
    "wof:placetype":"venue"
},
  "geometry": {"coordinates":[-1.4388400316,52.7844314575],"type":"Point"}
}