{
  "type": "Feature",
  "properties": {
    "iso:country":"GB",
    "sg:address":"10 Bangor Road",
    "sg:city":"Conwy",
    "sg:classifiers":[
        {
            "category":"Cinema",
            "subcategory":"Movie Rental",
            "type":"Entertainment"
        }
    ],
    "sg:phone":"+44 1492 583006",
    "sg:postcode":"LL32 8NH",
    "sg:province":"Conwy",
    "sg:tags":[
        "video",
        "library"
    ],
    "wof:name":"North Wales Video Services Conwy",
    "wof:placetype":"venue"
},
  "geometry": {"coordinates":[-3.8314750195,53.2812728882],"type":"Point"}
}