{
  "type": "Feature",
  "properties": {
    "iso:country":"GB",
    "sg:address":"21 Melville Street",
    "sg:city":"Edinburgh",
    "sg:classifiers":[
        {
            "category":"Professional",
            "subcategory":"Computer Services",
            "type":"Services"
        }
    ],
    "sg:phone":"+44 131 220 6700",
    "sg:postcode":"EH3 7PE",
    "sg:province":"City of Edinburgh",
    "sg:tags":[
        "consultant"
    ],
    "wof:name":"Coalescence Ltd.",
    "wof:placetype":"venue"
},
  "geometry": {"coordinates":[-3.212198,55.950691],"type":"Point"}
}