{
  "type": "Feature",
  "properties": {
    "addr:full":"221-223 High Road, South Woodford London Greater London E18 2PB",
    "addr:housenumber":"221-223",
    "addr:postcode":"e18 2pb",
    "addr:street":"High Road",
    "iso:country":"GB",
    "sg:address":"221-223 High Road, South Woodford",
    "sg:city":"London",
    "sg:classifiers":[
        {
            "category":"Professional",
            "subcategory":"Art Services",
            "type":"Services"
        }
    ],
    "sg:phone":"+44 20 8504 8463",
    "sg:postcode":"E18 2PB",
    "sg:province":"Greater London",
    "sg:tags":[
        "photographer"
    ],
    "wof:name":"Ken Bray Studios",
    "wof:placetype":"venue"
},
  "geometry": {"coordinates":[0.0204060003,51.5988197327],"type":"Point"}
}