{
  "type": "Feature",
  "properties": {
    "addr:full":"6 Hollywood Gardens Hayes Greater London UB4 0DX",
    "addr:housenumber":"6",
    "addr:postcode":"ub4 0dx",
    "addr:street":"Hollywood Gardens",
    "iso:country":"GB",
    "sg:address":"6 Hollywood Gardens",
    "sg:city":"Hayes",
    "sg:classifiers":[
        {
            "category":"Building & Trades",
            "subcategory":"Plumbing",
            "type":"Services"
        }
    ],
    "sg:phone":"+44 20 8561 7711",
    "sg:postcode":"UB4 0DX",
    "sg:province":"Greater London",
    "sg:tags":[
        "heating"
    ],
    "wof:name":"I D Garner",
    "wof:placetype":"venue"
},
  "geometry": {"coordinates":[-0.4067269862,51.5216026306],"type":"Point"}
}