{
  "type": "Feature",
  "properties": {
    "iso:country":"GB",
    "sg:address":"Western Hanga, Lawrence Road, Mount Batten",
    "sg:city":"Plymouth",
    "sg:classifiers":[
        {
            "category":"Social Services",
            "subcategory":"Job Training",
            "type":"Services"
        },
        {
            "category":"Shopping",
            "subcategory":"Bicycles & Sporting Goods",
            "type":"Retail Goods"
        },
        {
            "category":"Retail",
            "subcategory":"Auto Rental",
            "type":"Services"
        },
        {
            "category":"Professional",
            "type":"Services"
        }
    ],
    "sg:phone":"+44 1752 408804",
    "sg:postcode":"PL9 9SJ",
    "sg:province":"Devon",
    "sg:tags":[
        "equipment",
        "car",
        "engineering",
        "marine",
        "supply"
    ],
    "wof:name":"Western Marine Power Ltd.",
    "wof:placetype":"venue"
},
  "geometry": {"coordinates":[-4.1282100677,50.3590583801],"type":"Point"}
}