{
  "type": "Feature",
  "properties": {
    "iso:country":"GB",
    "sg:address":"11 Beeley Wood Road",
    "sg:city":"Sheffield",
    "sg:classifiers":[
        {
            "category":"Manufacturing",
            "subcategory":"Metals",
            "type":"Manufacturing & Wholesale Goods"
        }
    ],
    "sg:phone":"+44 114 234 3244",
    "sg:postcode":"S6 1NH",
    "sg:province":"South Yorkshire",
    "sg:tags":[
        "steel",
        "fabricator",
        "erectors"
    ],
    "wof:name":"Beeley Fabrications Ltd",
    "wof:placetype":"venue"
},
  "geometry": {"coordinates":[-1.501531,53.415882],"type":"Point"}
}